Workbook

Sheet Zomba
A1: SOUTHERN REGION WATER BOARD
A3: MONTHLY REPORTS - 2024/2025
A4: ZOMBA ZONE
A5: ZOMBA SCHEME
A7: PARAMETERS | C7: UNITS | D7: APRIL | E7: MAY | F7: JUNE | G7: JULY | H7: AUGUST | I7: SEPTEMBER | J7: OCTOBER | K7: NOVEMBER | L7: DECEMBER | M7: JANUARY | N7: FEBRUARY | O7: MARCH | P7: TOTALS
A8: PRODUCTION
A9: Volume Produced | C9: m3 | D9: 455725 | E9: 543720 | F9: 487019 | G9: 480949 | H9: 517415 | I9: 515483 | J9: 566721 | K9: 417636 | L9: 542479 | M9: 557661 | N9: 426923 | O9: 492032 | P9: =SUM(D9:O9) -> 6003763
A10: REVENUE WATER - POSTPAID
A11: Volume Billed Individuals | C11: m3 | D11: 162543 | E11: 158741 | F11: 154972 | G11: 153563 | H11: 160397 | I11: 174718 | J11: 179319 | K11: 153670 | L11: 187353 | M11: 149349 | N11: 142130 | O11: 131764 | P11: =SUM(D11:O11) -> 1908519
A12: Volume Billed CWPs | C12: m3 | D12: 11486 | E12: 10668 | F12: 11600 | G12: 12154 | H12: 14133 | I12: 14387 | J12: 13064 | K12: 11512 | L12: 16077 | M12: 12266 | N12: 11668 | O12: 10740 | P12: =SUM(D12:O12) -> 149755
A13: Volume Billed Institutions | C13: m3 | D13: 26963 | E13: 55060 | F13: 44468 | G13: 35028 | H13: 37753 | I13: 34783 | J13: 42220 | K13: 32146 | L13: 32817 | M13: 28516 | N13: 30666 | O13: 30647 | P13: =SUM(D13:O13) -> 431067
A14: Volume Billed Commercial/Industrial | C14: m3 | D14: 2408 | E14: 2851 | F14: 3114 | G14: 2570 | H14: 3190 | I14: 1950 | J14: 1965 | K14: 1635 | L14: 960 | M14: 746 | N14: 220 | O14: 145 | P14: =SUM(D14:O14) -> 21754
A15: Total Volume Billed Post Paid | C15: m3 | D15: =SUM(D11:D14) -> 203400 | E15: =SUM(E11:E14) -> 227320 | F15: =SUM(F11:F14) -> 214154 | G15: =SUM(G11:G14) -> 203315 | H15: =SUM(H11:H14) -> 215473 | I15: =SUM(I11:I14) -> 225838 | J15: =SUM(J11:J14) -> 236568 | K15: =SUM(K11:K14) -> 198963 | ... P15: =SUM(P11:P14) -> 2511095
A16: REVENUE WATER - PREPAID
A17: Individuals | C17: m3 | D17: 55086.6 | E17: 53695.8 | F17: 109740.2 | G17: 49046 | H17: 54795.3 | I17: 51640.6 | J17: 63486.9 | K17: 51019.5 | L17: 55681.2 | M17: 86444.3 | N17: 45750 | O17: 60117.4 | P17: =SUM(D17:O17) -> 736503.8
A18: CWPs | C18: m3 | D18: 7766.6 | E18: 7409.1 | F18: 7280.7 | G18: 9019.7 | H18: 7792.6 | I18: 8136.5 | J18: 8176.3 | K18: 8249.2 | L18: 8786.1 | M18: 8231.2 | N18: 7388.1 | O18: 7526 | P18: =SUM(D18:O18) -> 95762.1
A19: Institutions | C19: m3 | D19: 23551.2 | E19: 76944.5 | F19: 29554.7 | G19: 39065.9 | H19: 37994.7 | I19: 29341.2 | J19: 48888 | K19: 29976.4 | L19: 38909.9 | M19: 77548.6 | N19: 29875.2 | O19: 48910.5 | P19: =SUM(D19:O19) -> 510560.8
A20: Commercial/Industrial | C20: m3 | D20: 4077.7 | E20: 3927.7 | F20: 3548.7 | G20: 4275.8 | H20: 4337.4 | I20: 5500.1 | J20: 5443.4 | K20: 6352.8 | L20: 5991.2 | M20: 5003.3 | N20: 5117.6 | O20: 6048.6 | P20: =SUM(D20:O20) -> 59624.3
A21: Total Volume Prepaid | C21: m3 | D21: =SUM(D17:D20) -> 90482.1 | E21: =SUM(E17:E20) -> 141977.1 | F21: =SUM(F17:F20) -> 150124.3 | G21: =SUM(G17:G20) -> 101407.4 | H21: =SUM(H17:H20) -> 104920 | I21: =SUM(I17:I20) -> 94618.4 | J21: =SUM(J17:J20) -> 125994.6 | K21: =SUM(K17:K20) -> 95597.9 | ... P21: =SUM(P17:P20) -> 1402451
A22: TOTAL REVENUE WATER | C22: m3 | D22: =D21+D15 -> 293882.1 | E22: =E21+E15 -> 369297.1 | F22: =F21+F15 -> 364278.3 | G22: =G21+G15 -> 304722.4 | H22: =H21+H15 -> 320393 | I22: =I21+I15 -> 320456.4 | J22: =J21+J15 -> 362562.6 | K22: =K21+K15 -> 294560.9 | ... P22: =P21+P15 -> 3913546
A24: Non-Revenue Water (NRW) | B24: Volume | C24: m3 | D24: =D9-D22 -> 161842.9 | E24: =E9-E22 -> 174422.9 | F24: =F9-F22 -> 122740.7 | G24: =G9-G22 -> 176226.6 | H24: =H9-H22 -> 197022 | I24: =I9-I22 -> 195026.6 | J24: =J9-J22 -> 204158.4 | K24: =K9-K22 -> 123075.1 | ... P24: =P9-P22 -> 2090217
B25: Percentage | C25: % | D25: =IFERROR(D24/D9,0) -> 0.35513281 | E25: =IFERROR(E24/E9,0) -> 0.32079545 | F25: =IFERROR(F24/F9,0) -> 0.25202446 | G25: =IFERROR(G24/G9,0) -> 0.36641432 | H25: =IFERROR(H24/H9,0) -> 0.38078138 | I25: =IFERROR(I24/I9,0) -> 0.3783376 | J25: =IFERROR(J24/J9,0) -> 0.36024499 | K25: =IFERROR(K24/K9,0) -> 0.29469466 | ... O25: =IFERROR(O24/O9,0) -> 0.3986194 | P25: =IF(P9,P24/P9,"") -> 0.34815115
A26: OPERATING EXPENSES
A27: Chemicals
A28: Chemical | B28: Rate(MK/kg)
A29: Chlorine | B29: 7400 | C29: kg | D29: 1234.4 | E29: 1183.2 | F29: 1237.6 | G29: 1309.4 | H29: 1225 | I29: 1179 | J29: 1281 | K29: 1181 | L29: 1368.9 | M29: 1179 | N29: 1322 | O29: 1422 | P29: =SUM(D29:O29) -> 15122.5
C30: kg/mg litre | D30: =IFERROR(D29/(D9/1000),0) -> 2.7086511 | E30: =IFERROR(E29/(E9/1000),0) -> 2.1761201 | F30: =IFERROR(F29/(F9/1000),0) -> 2.541174 | G30: =IFERROR(G29/(G9/1000),0) -> 2.722534 | H30: =IFERROR(H29/(H9/1000),0) -> 2.3675386 | I30: =IFERROR(I29/(I9/1000),0) -> 2.2871753 | J30: =IFERROR(J29/(J9/1000),0) -> 2.2603715 | K30: =IFERROR(K29/(K9/1000),0) -> 2.8278214 | ... P30: =IFERROR(P29/(P9/1000),0) -> 2.5188369
A31: Aluminium sulphate | B31: 1900 | C31: kg | D31: 4542.8 | E31: 2613 | F31: 2106.4 | G31: 1941.4 | H31: 2058 | I31: 1966 | J31: 3300 | K31: 3284 | L31: 5769.1 | M31: 6924 | N31: 6071 | O31: 5489 | P31: =SUM(D31:O31) -> 46064.7
C32: kg/mg litre | D32: =IFERROR(D31/(D9/1000),0) -> 9.9682923 | E32: =IFERROR(E31/(E9/1000),0) -> 4.8057824 | F32: =IFERROR(F31/(F9/1000),0) -> 4.3250879 | G32: =IFERROR(G31/(G9/1000),0) -> 4.0366026 | H32: =IFERROR(H31/(H9/1000),0) -> 3.9774649 | I32: =IFERROR(I31/(I9/1000),0) -> 3.8138988 | J32: =IFERROR(J31/(J9/1000),0) -> 5.8229711 | K32: =IFERROR(K31/(K9/1000),0) -> 7.8633068 | ... P32: =IFERROR(P31/(P9/1000),0) -> 7.672638
A33: Soda | B33: 1900 | C33: kg | D33: 1580.1 | E33: 936.7 | F33: 986.2 | G33: 984.5 | H33: 1275 | I33: 688 | J33: 887 | K33: 933 | L33: 2102.3 | M33: 1915 | N33: 1493 | O33: 2352 | P33: =SUM(D33:O33) -> 16132.8
C34: kg/mg litre | D34: =IFERROR(D33/(D9/1000),0) -> 3.4672226 | E34: =IFERROR(E33/(E9/1000),0) -> 1.7227617 | F34: =IFERROR(F33/(F9/1000),0) -> 2.0249723 | G34: =IFERROR(G33/(G9/1000),0) -> 2.0469946 | H34: =IFERROR(H33/(H9/1000),0) -> 2.4641729 | I34: =IFERROR(I33/(I9/1000),0) -> 1.3346706 | J34: =IFERROR(J33/(J9/1000),0) -> 1.565144 | K34: =IFERROR(K33/(K9/1000),0) -> 2.2340028 | ... P34: =IFERROR(P33/(P9/1000),0) -> 2.6871147
A35: Algae floc | B35: =745345.16/200 -> 3726.7258 | C35: litres | D35: 0 | E35: 0 | F35: 0 | G35: 0 | H35: 0 | I35: 0 | J35: 0 | K35: 0 | L35: 0 | M35: 0 | N35: 0 | O35: 0
C36: litres/mg litre
A37: Sud floc | B37: =790318.72/200 -> 3951.5936 | C37: litres | D37: 0 | E37: 0 | F37: 0 | G37: 0 | H37: 0 | I37: 0 | J37: 0 | K37: 0 | L37: 0 | M37: 0 | N37: 0 | O37: 0 | P37: =SUM(D37:O37) -> 0
C38: litres/mg litre | D38: =IFERROR(D37/(D9/1000),0) -> 0 | E38: =IFERROR(E37/(E9/1000),0) -> 0 | F38: =IFERROR(F37/(F9/1000),0) -> 0 | G38: =IFERROR(G37/(G9/1000),0) -> 0 | H38: =IFERROR(H37/(H9/1000),0) -> 0 | I38: =IFERROR(I37/(I9/1000),0) -> 0 | J38: =IFERROR(J37/(J9/1000),0) -> 0 | K38: =IFERROR(K37/(K9/1000),0) -> 0 | ... P38: =IFERROR(P37/(P9/1000),0) -> 0
A39: Potasium permanganate | B39: 1950 | C39: kg | D39: 0 | E39: 0 | F39: 0 | G39: 0 | H39: 0 | I39: 0 | J39: 0 | K39: 0 | L39: 0 | M39: 0 | N39: 0 | O39: 0 | P39: =SUM(D39:O39) -> 0
C40: kg/mg litre | D40: =IFERROR(D39/(D9/1000),0) -> 0 | E40: =IFERROR(E39/(E9/1000),0) -> 0 | F40: =IFERROR(F39/(F9/1000),0) -> 0 | G40: =IFERROR(G39/(G9/1000),0) -> 0 | H40: =IFERROR(H39/(H9/1000),0) -> 0 | I40: =IFERROR(I39/(I9/1000),0) -> 0 | J40: =IFERROR(J39/(J9/1000),0) -> 0 | K40: =IFERROR(K39/(K9/1000),0) -> 0 | ... P40: =IFERROR(P39/(P9/1000),0) -> 0
A41: Cost of Chemicals | C41: Mk | D41: =(D29*$B29)+(D31*$B31)+(D33*$B33)+(D35*$B35)+(D37*$B37)+(D39*$B39) -> 20768070 | E41: =(E29*$B29)+(E31*$B31)+(E33*$B33)+(E35*$B35)+(E37*$B37)+(E39*$B39) -> 15500110 | F41: =(F29*$B29)+(F31*$B31)+(F33*$B33)+(F35*$B35)+(F37*$B37)+(F39*$B39) -> 15034180 | G41: =(G29*$B29)+(G31*$B31)+(G33*$B33)+(G35*$B35)+(G37*$B37)+(G39*$B39) -> 15248770 | H41: =(H29*$B29)+(H31*$B31)+(H33*$B33)+(H35*$B35)+(H37*$B37)+(H39*$B39) -> 15397700 | I41: =(I29*$B29)+(I31*$B31)+(I33*$B33)+(I35*$B35)+(I37*$B37)+(I39*$B39) -> 13767200 | J41: =(J29*$B29)+(J31*$B31)+(J33*$B33)+(J35*$B35)+(J37*$B37)+(J39*$B39) -> 17434700 | K41: =(K29*$B29)+(K31*$B31)+(K33*$B33)+(K35*$B35)+(K37*$B37)+(K39*$B39) -> 16751700 | ... O41: =(O29*$B29)+(O31*$B31)+(O33*$B33)+(O35*$B35)+(O37*$B37)+(O39*$B39) -> 25420700 | P41: =SUM(D41:O41) -> 230081750
A42: Cost/vol. Produced (chemicals) | C42: Mk/m3 | D42: =IFERROR(D41/D9,0) -> 45.571496 | E42: =IFERROR(E41/E9,0) -> 28.507522 | F42: =IFERROR(F41/F9,0) -> 30.869802 | G42: =IFERROR(G41/G9,0) -> 31.705586 | H42: =IFERROR(H41/H9,0) -> 29.758898 | I42: =IFERROR(I41/I9,0) -> 26.707379 | J42: =IFERROR(J41/J9,0) -> 30.764168 | K42: =IFERROR(K41/K9,0) -> 40.110766 | ... P42: =IFERROR(P41/P9,0) -> 38.322923
A43: Power
A44: Power Usage | C44: Kw | D44: 25081.9 | E44: 28322.1 | F44: 30246.2 | G44: 30813 | H44: 29240.05 | I44: 32257.34 | J44: 32556.86 | K44: 28394.66 | L44: 38181.5 | M44: 37477.24 | N44: 34535.8 | O44: 36652.12 | P44: =SUM(D44:O44) -> 383758.77
A45: Power/ Vol. Produced | C45: Kw/m3 | D45: =IFERROR(D44/D9,0) -> 0.055037358 | E45: =IFERROR(E44/E9,0) -> 0.052089495 | F45: =IFERROR(F44/F9,0) -> 0.062104764 | G45: =IFERROR(G44/G9,0) -> 0.064067084 | H45: =IFERROR(H44/H9,0) -> 0.056511794 | I45: =IFERROR(I44/I9,0) -> 0.062576923 | J45: =IFERROR(J44/J9,0) -> 0.057447774 | K45: =IFERROR(K44/K9,0) -> 0.067989014 | ... P45: =IFERROR(P44/P9,0) -> 0.063919707
A46: Cost of Power | C46: Mk | D46: =IF(D44=0,0,IF(D44>=0,0+(D44*202.25)+23390)*1.165) -> 5937078 | E46: =IF(E44=0,0,IF(E44>=0,0+(E44*202.25)+23390)*1.165) -> 6700538 | F46: =IF(F44=0,0,IF(F44>=0,0+(F44*202.25)+23390)*1.165) -> 7153896.8 | G46: =IF(G44=0,0,IF(G44>=0,0+(G44*202.25)+23390)*1.165) -> 7287446.9 | H46: =IF(H44=0,0,IF(H44>=0,0+(H44*202.25)+23390)*1.165) -> 6916826.5 | I46: =IF(I44=0,0,IF(I44>=0,0+(I44*202.25)+23390)*1.165) -> 7627764.1 | J46: =IF(J44=0,0,IF(J44>=0,0+(J44*202.25)+23390)*1.165) -> 7698337.4 | K46: =IF(K44=0,0,IF(K44>=0,0+(K44*202.25)+23390)*1.165) -> 6717634.6 | ... O46: =IF(O44=0,0,IF(O44>=0,0+(O44*202.25)+23390)*1.165) -> 8663267.7 | P46: =SUM(D46:O46) -> 90748713
A47: Cost/vol. Produced | C47: Mk/m3 | D47: =IFERROR(D46/D9,0) -> 13.027765 | E47: =IFERROR(E46/E9,0) -> 12.323508 | F47: =IFERROR(F46/F9,0) -> 14.689153 | G47: =IFERROR(G46/G9,0) -> 15.152224 | H47: =IFERROR(H46/H9,0) -> 13.368044 | I47: =IFERROR(I46/I9,0) -> 14.797315 | J47: =IFERROR(J46/J9,0) -> 13.583999 | K47: =IFERROR(K46/K9,0) -> 16.084903 | ... P47: =IFERROR(P46/P9,0) -> 15.115306
A48: Plant and Vehicle Maintenance
A49: Distances covered | C49: km | D49: 0 | E49: 0 | F49: 0 | G49: 0 | H49: 0 | I49: 0 | J49: 0 | K49: 0 | L49: 0 | M49: 0 | N49: 0 | O49: 0 | P49: =SUM(D49:O49) -> 0
A50: Fuel Used (litres) | C50: litres | D50: 0 | E50: 0 | F50: 0 | G50: 0 | H50: 0 | I50: 0 | J50: 0 | K50: 0 | L50: 0 | M50: 0 | N50: 0 | O50: 0 | P50: =SUM(D50:O50) -> 0
A51: Cost of fuel | C51: Mk | D51: 0 | E51: 0 | F51: 0 | G51: 0 | H51: 0 | I51: 0 | J51: 0 | K51: 0 | L51: 0 | M51: 0 | N51: 0 | O51: 0 | P51: =SUM(D51:O51) -> 0
A52: Maintenance | C52: Mk | D52: 0 | E52: 0 | F52: 0 | G52: 0 | H52: 0 | I52: 0 | J52: 0 | K52: 0 | L52: 0 | M52: 0 | N52: 0 | O52: 0 | P52: =SUM(D52:O52) -> 0
A53: Salaries and Wages
A54: Staff Costs | C54: MK | D54: 0 | E54: 0 | F54: 0 | G54: 0 | H54: 0 | I54: 0 | J54: 0 | K54: 0 | L54: 0 | M54: 0 | N54: 0 | O54: 0 | P54: =SUM(D54:O54) -> 0
A55: Wages | C55: MK | D55: 0 | E55: 0 | F55: 0 | G55: 0 | H55: 0 | I55: 0 | J55: 0 | K55: 0 | L55: 0 | M55: 0 | N55: 0 | O55: 0 | P55: =SUM(D55:O55) -> 0
A56: Other Overhead Costs | C56: MK | D56: 0 | E56: 0 | F56: 0 | G56: 0 | H56: 0 | I56: 0 | J56: 0 | K56: 0 | L56: 0 | M56: 0 | N56: 0 | O56: 0 | P56: =SUM(D56:O56) -> 0
A57: Operating Costs
A58: Total Operating Costs | C58: MK | D58: =D41+D46+D51+D52+D54+D55+D56 -> 26705148 | E58: =E41+E46+E51+E52+E54+E55+E56 -> 22200648 | F58: =F41+F46+F51+F52+F54+F55+F56 -> 22188077 | G58: =G41+G46+G51+G52+G54+G55+G56 -> 22536217 | H58: =H41+H46+H51+H52+H54+H55+H56 -> 22314526 | I58: =I41+I46+I51+I52+I54+I55+I56 -> 21394964 | J58: =J41+J46+J51+J52+J54+J55+J56 -> 25133037 | K58: =K41+K46+K51+K52+K54+K55+K56 -> 23469335 | ... O58: =O41+O46+O51+O52+O54+O55+O56 -> 34083968 | P58: =SUM(D58:O58) -> 3.2083046e+08
A59: Cost/Vol. Produced | C59: Mk/m3 | D59: =IFERROR(D58/D9,0) -> 58.59926 | E59: =IFERROR(E58/E9,0) -> 40.831031 | F59: =IFERROR(F58/F9,0) -> 45.558955 | G59: =IFERROR(G58/G9,0) -> 46.85781 | H59: =IFERROR(H58/H9,0) -> 43.126942 | I59: =IFERROR(I58/I9,0) -> 41.504694 | J59: =IFERROR(J58/J9,0) -> 44.348167 | K59: =IFERROR(K58/K9,0) -> 56.19567 | ... P59: =IFERROR(P58/P9,0) -> 53.438229
A60: Cost/Vol. Billed | C60: Mk/m3 | D60: =IFERROR(D58/D22,0) -> 90.870278 | E60: =IFERROR(E58/E22,0) -> 60.115955 | F60: =IFERROR(F58/F22,0) -> 60.909686 | G60: =IFERROR(G58/G22,0) -> 73.956548 | H60: =IFERROR(H58/H22,0) -> 69.64736 | I60: =IFERROR(I58/I22,0) -> 66.764041 | J60: =IFERROR(J58/J22,0) -> 69.320546 | K60: =IFERROR(K58/K22,0) -> 79.675662 | ... P60: =IFERROR(P58/P22,0) -> 81.979479
A61: Permanent Staff Employed | C61: No | D61: 64 | E61: 64 | F61: 64 | G61: 64 | H61: 64 | I61: 64 | J61: 64 | K61: 64 | L61: 64 | M61: 64 | N61: 64 | O61: 64 | P61: =O61 -> 64
A62: Staff/Vol.1000m3 of Volume Produced/hour (12 hour day) | C62: No/1000m3 | D62: =IFERROR((D61*1000*31)/D9,0) -> 4.3535027 | E62: =IFERROR((E61*1000*31)/E9,0) -> 3.648937 | F62: =IFERROR((F61*1000*31)/F9,0) -> 4.073763 | G62: =IFERROR((G61*1000*31)/G9,0) -> 4.1251775 | H62: =IFERROR((H61*1000*31)/H9,0) -> 3.8344462 | I62: =IFERROR((I61*1000*31)/I9,0) -> 3.8488175 | J62: =IFERROR((J61*1000*31)/J9,0) -> 3.5008408 | K62: =IFERROR((K61*1000*31)/K9,0) -> 4.7505483 | ... P62: =IFERROR((P61*1000*31)/P9,0) -> 0.33045941
A63: Temporary Staff Employed | C63: No | D63: 73 | E63: 75 | F63: 75 | G63: 75 | H63: 75 | I63: 75 | J63: 75 | K63: 75 | L63: 75 | M63: 75 | N63: 75 | O63: 75 | P63: =O63 -> 75
A65: Water Connections and Disconnections
A66: New Individual Water Connections | B66: Brought Forward | C66: No | D66: 25 | E66: 0 | F66: 0 | G66: 0 | H66: 0 | I66: 0 | J66: 0 | K66: 0 | L66: 0 | M66: 87 | N66: 151 | O66: 154 | P66: =D66 -> 25
B67: Applied this Month | C67: No | D67: 125 | E67: 73 | F67: 102 | G67: 121 | H67: 126 | I67: 133 | J67: 101 | K67: 69 | L67: 87 | M67: 73 | N67: 131 | O67: 111 | P67: =SUM(D67:O67) -> 1252
B68: Done this Month Postpaid | C68: No | D68: 150 | E68: 73 | F68: 102 | G68: 121 | H68: 126 | I68: 133 | J68: 101 | K68: 69 | L68: 0 | M68: 9 | N68: 128 | O68: 89 | P68: =SUM(D68:O68) -> 1101
B69: Done this Month Prepaid | C69: No | D69: 0 | E69: 0 | F69: 0 | G69: 0 | H69: 0 | I69: 0 | J69: 0 | K69: 0 | L69: 0 | M69: 0 | N69: 0 | O69: 0 | P69: =SUM(D69:O69) -> 0
B70: Total Done | C70: No | D70: =D68+D69 -> 150 | E70: =E68+E69 -> 73 | F70: =F68+F69 -> 102 | G70: =G68+G69 -> 121 | H70: =H68+H69 -> 126 | I70: =I68+I69 -> 133 | J70: =J68+J69 -> 101 | K70: =K68+K69 -> 69 | ... P70: =P68+P69 -> 1101
B71: Carried Forward | C71: No | D71: =D66+D67-D70 -> 0 | E71: =E66+E67-E70 -> 0 | F71: =F66+F67-F70 -> 0 | G71: =G66+G67-G70 -> 0 | H71: =H66+H67-H70 -> 0 | I71: =I66+I67-I70 -> 0 | J71: =J66+J67-J70 -> 0 | K71: =K66+K67-K70 -> 0 | ... P71: =P66+P67-P70 -> 176
A72: New Institutional Water Connections | B72: Brought Forward | C72: No | D72: 16 | E72: 15 | F72: 15 | G72: 16 | H72: 14 | I72: 12 | J72: 15 | K72: 17 | L72: 15 | M72: 17 | N72: 18 | O72: 18 | P72: =D72 -> 16
B73: Applied this Month | C73: No | D73: 2 | E73: 0 | F73: 3 | G73: 1 | H73: 0 | I73: 5 | J73: 2 | K73: 2 | L73: 2 | M73: 1 | N73: 1 | O73: 1 | P73: =SUM(D73:O73) -> 20
B74: Done this Month Postpaid | C74: No | D74: 3 | E74: 0 | F74: 2 | G74: 3 | H74: 2 | I74: 2 | J74: 0 | K74: 4 | L74: 0 | M74: 0 | N74: 1 | O74: 1 | P74: =SUM(D74:O74) -> 18
B75: Done this Month Prepaid | C75: No | D75: 0 | E75: 0 | F75: 0 | G75: 0 | H75: 0 | I75: 0 | J75: 0 | K75: 0 | L75: 0 | M75: 0 | N75: 0 | O75: 0 | P75: =SUM(D75:O75) -> 0
B76: Total Done | C76: No | D76: =D74+D75 -> 3 | E76: =E74+E75 -> 0 | F76: =F74+F75 -> 2 | G76: =G74+G75 -> 3 | H76: =H74+H75 -> 2 | I76: =I74+I75 -> 2 | J76: =J74+J75 -> 0 | K76: =K74+K75 -> 4 | ... P76: =P74+P75 -> 18
B77: Carried Forward | C77: No | D77: =D72+D73-D76 -> 15 | E77: =E72+E73-E76 -> 15 | F77: =F72+F73-F76 -> 16 | G77: =G72+G73-G76 -> 14 | H77: =H72+H73-H76 -> 12 | I77: =I72+I73-I76 -> 15 | J77: =J72+J73-J76 -> 17 | K77: =K72+K73-K76 -> 15 | ... P77: =P72+P73-P76 -> 18
A78: New Commercial/Industrial Water Connections | B78: Brought Forward | C78: No | D78: 1 | E78: 5 | F78: 5 | G78: 5 | H78: 7 | I78: 5 | J78: 5 | K78: 3 | L78: 1 | M78: 5 | N78: 5 | O78: 5 | P78: =D78 -> 1
B79: Applied this Month | C79: No | D79: 5 | E79: 0 | F79: 0 | G79: 3 | H79: 0 | I79: 0 | J79: 1 | K79: 0 | L79: 4 | M79: 1 | N79: 0 | O79: 4 | P79: =SUM(D79:O79) -> 18
B80: Done this Month Postpaid | C80: No | D80: 1 | E80: 0 | F80: 0 | G80: 1 | H80: 2 | I80: 0 | J80: 3 | K80: 2 | L80: 0 | M80: 1 | N80: 0 | O80: 1 | P80: =SUM(D80:O80) -> 11
B81: Done this Month Prepaid | C81: No | D81: 0 | E81: 0 | F81: 0 | G81: 0 | H81: 0 | I81: 0 | J81: 0 | K81: 0 | L81: 0 | M81: 0 | N81: 0 | O81: 0 | P81: =SUM(D81:O81) -> 0
B82: Total Done | C82: No | D82: =D80+D81 -> 1 | E82: =E80+E81 -> 0 | F82: =F80+F81 -> 0 | G82: =G80+G81 -> 1 | H82: =H80+H81 -> 2 | I82: =I80+I81 -> 0 | J82: =J80+J81 -> 3 | K82: =K80+K81 -> 2 | ... O82: =O80+O81 -> 1 | P82: =P81+P80 -> 11
B83: Carried Forward | C83: No | D83: =D78+D79-D82 -> 5 | E83: =E78+E79-E82 -> 5 | F83: =F78+F79-F82 -> 5 | G83: =G78+G79-G82 -> 7 | H83: =H78+H79-H82 -> 5 | I83: =I78+I79-I82 -> 5 | J83: =J78+J79-J82 -> 3 | K83: =K78+K79-K82 -> 1 | ... P83: =P78+P79-P82 -> 8
A84: New CWP | B84: Brought Forward | C84: No | D84: 5 | E84: 5 | F84: 5 | G84: 5 | H84: 5 | I84: 5 | J84: 6 | K84: 6 | L84: 6 | M84: 6 | N84: 6 | O84: 6 | P84: =D84 -> 5
B85: Applied this Month | C85: No | D85: 0 | E85: 0 | F85: 0 | G85: 0 | H85: 0 | I85: 1 | J85: 0 | K85: 0 | L85: 0 | M85: 0 | N85: 0 | O85: 2 | P85: =SUM(D85:O85) -> 3
B86: Done this Month Postpaid | C86: No | D86: 0 | E86: 0 | F86: 0 | G86: 0 | H86: 0 | I86: 0 | J86: 0 | K86: 0 | L86: 0 | M86: 0 | N86: 0 | O86: 5 | P86: =SUM(D86:O86) -> 5
B87: Done this Month Prepaid | C87: No | D87: 0 | E87: 0 | F87: 0 | G87: 0 | H87: 0 | I87: 0 | J87: 0 | K87: 0 | L87: 0 | M87: 0 | N87: 0 | O87: 0 | P87: =SUM(D87:O87) -> 0
B88: Total Done | C88: No | D88: =D86+D87 -> 0 | E88: =E86+E87 -> 0 | F88: =F86+F87 -> 0 | G88: =G86+G87 -> 0 | H88: =H86+H87 -> 0 | I88: =I86+I87 -> 0 | J88: =J86+J87 -> 0 | K88: =K86+K87 -> 0 | ... O88: =O86+O87 -> 5 | P88: =SUM(D88:O88) -> 5
B89: Carried Forward | C89: No | D89: =D84+D85-D88 -> 5 | E89: =E84+E85-E88 -> 5 | F89: =F84+F85-F88 -> 5 | G89: =G84+G85-G88 -> 5 | H89: =H84+H85-H88 -> 5 | I89: =I84+I85-I88 -> 6 | J89: =J84+J85-J88 -> 6 | K89: =K84+K85-K88 -> 6 | ... O89: =O84+O85-O88 -> 3 | P89: =P84+P85-P86-P87 -> 3
A90: Aggregated New Water connections | B90: Brought Forward | C90: No | D90: =D66+D72+D78+D84 -> 47 | E90: =E66+E72+E78+E84 -> 25 | F90: =F66+F72+F78+F84 -> 25 | G90: =G66+G72+G78+G84 -> 26 | H90: =H66+H72+H78+H84 -> 26 | I90: =I66+I72+I78+I84 -> 22 | J90: =J66+J72+J78+J84 -> 26 | K90: =K66+K72+K78+K84 -> 26 | ... O90: =O66+O72+O78+O84 -> 183 | P90: =D90 -> 47
B91: Applied this Month | C91: No | D91: =D67+D73+D79+D85 -> 132 | E91: =E67+E73+E79+E85 -> 73 | F91: =F67+F73+F79+F85 -> 105 | G91: =G67+G73+G79+G85 -> 125 | H91: =H67+H73+H79+H85 -> 126 | I91: =I67+I73+I79+I85 -> 139 | J91: =J67+J73+J79+J85 -> 104 | K91: =K67+K73+K79+K85 -> 71 | ... O91: =O67+O73+O79+O85 -> 118 | P91: =SUM(D91:O91) -> 1293
B92: Done this Month Postpaid | C92: No | D92: =D68+D74+D80+D86 -> 154 | E92: =E68+E74+E80+E86 -> 73 | F92: =F68+F74+F80+F86 -> 104 | G92: =G68+G74+G80+G86 -> 125 | H92: =H68+H74+H80+H86 -> 130 | I92: =I68+I74+I80+I86 -> 135 | J92: =J68+J74+J80+J86 -> 104 | K92: =K68+K74+K80+K86 -> 75 | ... O92: =O68+O74+O80+O86 -> 96 | P92: =SUM(D92:O92) -> 1135
B93: Done this Month Prepaid | D93: =D69+D75+D81+D87 -> 0 | E93: =E69+E75+E81+E87 -> 0 | F93: =F69+F75+F81+F87 -> 0 | G93: =G69+G75+G81+G87 -> 0 | H93: =H69+H75+H81+H87 -> 0 | I93: =I69+I75+I81+I87 -> 0 | J93: =J69+J75+J81+J87 -> 0 | K93: =K69+K75+K81+K87 -> 0 | ... O93: =O69+O75+O81+O87 -> 0 | P93: =SUM(D93:O93) -> 0
B94: Total Done | C94: No | D94: =D93+D92 -> 154 | E94: =E93+E92 -> 73 | F94: =F93+F92 -> 104 | G94: =G93+G92 -> 125 | H94: =H93+H92 -> 130 | I94: =I93+I92 -> 135 | J94: =J93+J92 -> 104 | K94: =K93+K92 -> 75 | ... P94: =P93+P92 -> 1135
B95: Carried Forward | C95: No | D95: =D90+D91-D94 -> 25 | E95: =E90+E91-E94 -> 25 | F95: =F90+F91-F94 -> 26 | G95: =G90+G91-G94 -> 26 | H95: =H90+H91-H94 -> 22 | I95: =I90+I91-I94 -> 26 | J95: =J90+J91-J94 -> 26 | K95: =K90+K91-K94 -> 22 | ... P95: =P90+P91-P94 -> 205
A97: Prepaid Metering
A98: Prepaid Meters Installed | C98: No | D98: 0 | E98: 0 | F98: 0 | G98: 0 | H98: 0 | I98: 0 | J98: 0 | K98: 0 | L98: 147 | M98: 22 | N98: 6 | O98: 0 | P98: =SUM(D98:O98) -> 175
A100: Active and Disconnected Accounts
A101: Disconnected Individual Accounts | C101: No | D101: 6003 | E101: 6089 | F101: 6128 | G101: 6219 | H101: 6413 | I101: 6372 | J101: 6639 | K101: 6573 | L101: 6624 | M101: 7319 | N101: 7656 | O101: 7753 | P101: =O101 -> 7753
A102: Disconnected institutional Accounts | C102: No | D102: 357 | E102: 359 | F102: 364 | G102: 366 | H102: 376 | I102: 389 | J102: 399 | K102: 432 | L102: 466 | M102: 471 | N102: 487 | O102: 505 | P102: =O102 -> 505
A103: Disconnected Commercial/Industrial Accounts | C103: No | D103: 121 | E103: 120 | F103: 125 | G103: 133 | H103: 152 | I103: 185 | J103: 186 | K103: 203 | L103: 246 | M103: 249 | N103: 275 | O103: 283 | P103: =O103 -> 283
A104: Disconnected CWP | C104: No | D104: 77 | E104: 77 | F104: 75 | G104: 74 | H104: 75 | I104: 75 | J104: 78 | K104: 83 | L104: 83 | M104: 86 | N104: 90 | O104: 91 | P104: =O104 -> 91
A105: Total Disconnected Accounts | C105: No | D105: =SUM(D101:D104) -> 6558 | E105: =SUM(E101:E104) -> 6645 | F105: =SUM(F101:F104) -> 6692 | G105: =SUM(G101:G104) -> 6792 | H105: =SUM(H101:H104) -> 7016 | I105: =SUM(I101:I104) -> 7021 | J105: =SUM(J101:J104) -> 7302 | K105: =SUM(K101:K104) -> 7291 | ... O105: =SUM(O101:O104) -> 8632 | P105: =O105 -> 8632
A106: Postpaid Consumers
...

Sheet Mwanza
A1: SOUTHERN REGION WATER BOARD
A3: MONTHLY REPORTS - 2024/2025
A4: ZOMBA ZONE
A5: MWANZA SCHEME
A7: PARAMETERS | C7: UNITS | D7: APRIL | E7: MAY | F7: JUNE | G7: JULY | H7: AUGUST | I7: SEPTEMBER | J7: OCTOBER | K7: NOVEMBER | L7: DECEMBER | M7: JANUARY | N7: FEBRUARY | O7: MARCH | P7: TOTALS
A8: PRODUCTION
A9: Volume Produced | C9: m3 | D9: 34688 | E9: 36835 | F9: 35077 | G9: 35440 | H9: 43486 | I9: 40218 | J9: 42060 | K9: 35466 | L9: 38896 | M9: 39483 | N9: 36021 | O9: 35021 | P9: =SUM(D9:O9) -> 452691
A10: REVENUE WATER - POSTPAID
A11: Volume Billed Individuals | C11: m3 | D11: 19824 | E11: 19875 | F11: 19563 | G11: 20026 | H11: 20749 | I11: 21429 | J11: 21266 | K11: 20525 | L11: 21819 | M11: 20508 | N11: 19613 | O11: 18671 | P11: =SUM(D11:O11) -> 243868
A12: Volume Billed CWPs | C12: m3 | D12: 907 | E12: 1224 | F12: 921 | G12: 967 | H12: 839 | I12: 852 | J12: 791 | K12: 782 | L12: 826 | M12: 744 | N12: 690 | O12: 766 | P12: =SUM(D12:O12) -> 10309
A13: Volume Billed Institutions | C13: m3 | D13: 156 | E13: 212 | F13: 336 | G13: 497 | H13: 361 | I13: 462 | J13: 441 | K13: 564 | L13: 626 | M13: 552 | N13: 427 | O13: 360 | P13: =SUM(D13:O13) -> 4994
A14: Volume Billed Commercial/Industrial | C14: m3 | D14: 1120 | E14: 1266 | F14: 918 | G14: 947 | H14: 809 | I14: 801 | J14: 811 | K14: 734 | L14: 666 | M14: 439 | N14: 261 | O14: 189 | P14: =SUM(D14:O14) -> 8961
A15: Total Volume Billed Post Paid | C15: m3 | D15: =SUM(D11:D14) -> 22007 | E15: =SUM(E11:E14) -> 22577 | F15: =SUM(F11:F14) -> 21738 | G15: =SUM(G11:G14) -> 22437 | H15: =SUM(H11:H14) -> 22758 | I15: =SUM(I11:I14) -> 23544 | J15: =SUM(J11:J14) -> 23309 | K15: =SUM(K11:K14) -> 22605 | ... P15: =SUM(P11:P14) -> 268132
A16: REVENUE WATER - PREPAID
A17: Individuals | C17: m3 | D17: 1727.1 | E17: 1886.4 | F17: 3796.2 | G17: 2070.3 | H17: 1889.2 | I17: 1798.2 | J17: 2023.8 | K17: 1888.8 | L17: 2005.7 | M17: 2276.7 | N17: 1569.8 | O17: 1968 | P17: =SUM(D17:O17) -> 24900.2
A18: CWPs | C18: m3 | D18: 148.9 | E18: 213.4 | F18: 201.9 | G18: 240.9 | H18: 237.4 | I18: 271.7 | J18: 197.7 | K18: 225.5 | L18: 470.2 | M18: 183.6 | N18: 94.1 | O18: 209.5 | P18: =SUM(D18:O18) -> 2694.8
A19: Institutions | C19: m3 | D19: 351.4 | E19: 1289.2 | F19: 2636.3 | G19: 4525.5 | H19: 1609.3 | I19: 2383.5 | J19: 3001.2 | K19: 3139.3 | L19: 2672.5 | M19: 4996.4 | N19: 1406.9 | O19: 630.8 | P19: =SUM(D19:O19) -> 28642.3
A20: Commercial/Industrial | C20: m3 | D20: 250.4 | E20: 252.1 | F20: 189.5 | G20: 203.7 | H20: 213.9 | I20: 344.2 | J20: 290.4 | K20: 194 | L20: 348 | M20: 342.1 | N20: 478.2 | O20: 478.4 | P20: =SUM(D20:O20) -> 3584.9
A21: Total Volume Prepaid | C21: m3 | D21: =SUM(D17:D20) -> 2477.8 | E21: =SUM(E17:E20) -> 3641.1 | F21: =SUM(F17:F20) -> 6823.9 | G21: =SUM(G17:G20) -> 7040.4 | H21: =SUM(H17:H20) -> 3949.8 | I21: =SUM(I17:I20) -> 4797.6 | J21: =SUM(J17:J20) -> 5513.1 | K21: =SUM(K17:K20) -> 5447.6 | ... P21: =SUM(P17:P20) -> 59822.2
A22: TOTAL REVENUE WATER | C22: m3 | D22: =D21+D15 -> 24484.8 | E22: =E21+E15 -> 26218.1 | F22: =F21+F15 -> 28561.9 | G22: =G21+G15 -> 29477.4 | H22: =H21+H15 -> 26707.8 | I22: =I21+I15 -> 28341.6 | J22: =J21+J15 -> 28822.1 | K22: =K21+K15 -> 28052.6 | ... P22: =P21+P15 -> 327954.2
A24: Non-Revenue Water (NRW) | B24: Volume | C24: m3 | D24: =D9-D22 -> 10203.2 | E24: =E9-E22 -> 10616.9 | F24: =F9-F22 -> 6515.1 | G24: =G9-G22 -> 5962.6 | H24: =H9-H22 -> 16778.2 | I24: =I9-I22 -> 11876.4 | J24: =J9-J22 -> 13237.9 | K24: =K9-K22 -> 7413.4 | ... P24: =P9-P22 -> 124736.8
B25: Percentage | C25: % | D25: =IFERROR(D24/D9,0) -> 0.29414207 | E25: =E24/E9 -> 0.28822859 | F25: =F24/F9 -> 0.18573709 | G25: =IFERROR(G24/G9,0) -> 0.16824492 | H25: =IFERROR(H24/H9,0) -> 0.38582992 | I25: =IFERROR(I24/I9,0) -> 0.29530061 | J25: =IFERROR(J24/J9,0) -> 0.31473847 | K25: =IFERROR(K24/K9,0) -> 0.20902837 | L25: =IFERROR(L24/L9,0) -> 0.24327951 | M25: =IFERROR(M24/M9,0) -> 0.23912063 | N25: =IFERROR(N24/N9,0) -> 0.31873074 | O25: =IFERROR(O24/O9,0) -> 0.33546444 | P25: =IF(P9,P24/P9,"") -> 0.27554513
A26: OPERATING EXPENSES
A27: Chemicals
A28: Chemical | B28: Rate(MK/kg)
A29: Chlorine | B29: 7400 | C29: kg | D29: 45 | E29: 28 | F29: 21 | G29: 23 | H29: 24 | I29: 24 | J29: 21 | K29: 17 | L29: 15.5 | M29: 17 | N29: 16.5 | O29: 10.5 | P29: =SUM(D29:O29) -> 262.5
C30: kg/mg litre | D30: =IFERROR(D29/(D9/1000),0) -> 1.2972786 | E30: =IFERROR(E29/(E9/1000),0) -> 0.7601466 | F30: =IFERROR(F29/(F9/1000),0) -> 0.5986829 | G30: =IFERROR(G29/(G9/1000),0) -> 0.6489842 | H30: =IFERROR(H29/(H9/1000),0) -> 0.55190176 | I30: =IFERROR(I29/(I9/1000),0) -> 0.59674772 | J30: =IFERROR(J29/(J9/1000),0) -> 0.49928673 | K30: =IFERROR(K29/(K9/1000),0) -> 0.47933232 | ... P30: =IFERROR(P29/(P9/1000),0) -> 0.57986574
A31: Aluminium sulphate | B31: 1900 | C31: kg | D31: 0 | E31: 0 | F31: 0 | G31: 0 | H31: 0 | I31: 0 | J31: 0 | K31: 0 | L31: 0 | M31: 0 | N31: 0 | O31: 0 | P31: =SUM(D31:O31) -> 0
C32: kg/mg litre | D32: =IFERROR(D31/(D9/1000),0) -> 0 | E32: =IFERROR(E31/(E9/1000),0) -> 0 | F32: =IFERROR(F31/(F9/1000),0) -> 0 | G32: =IFERROR(G31/(G9/1000),0) -> 0 | H32: =IFERROR(H31/(H9/1000),0) -> 0 | I32: =IFERROR(I31/(I9/1000),0) -> 0 | J32: =IFERROR(J31/(J9/1000),0) -> 0 | K32: =IFERROR(K31/(K9/1000),0) -> 0 | ... P32: =IFERROR(P31/(P9/1000),0) -> 0
A33: Soda | B33: 1900 | C33: kg | D33: 0 | E33: 0 | F33: 0 | G33: 0 | H33: 0 | I33: 0 | J33: 0 | K33: 0 | L33: 0 | M33: 0 | N33: 0 | O33: 0 | P33: =SUM(D33:O33) -> 0
C34: kg/mg litre | D34: =IFERROR(D33/(D9/1000),0) -> 0 | E34: =IFERROR(E33/(E9/1000),0) -> 0 | F34: =IFERROR(F33/(F9/1000),0) -> 0 | G34: =IFERROR(G33/(G9/1000),0) -> 0 | H34: =IFERROR(H33/(H9/1000),0) -> 0 | I34: =IFERROR(I33/(I9/1000),0) -> 0 | J34: =IFERROR(J33/(J9/1000),0) -> 0 | K34: =IFERROR(K33/(K9/1000),0) -> 0 | ... P34: =IFERROR(P33/(P9/1000),0) -> 0
A35: Algae floc | B35: =745345.16/200 -> 3726.7258 | C35: litres | D35: 0 | E35: 0 | F35: 0 | G35: 0 | H35: 0 | I35: 0 | J35: 0 | K35: 0 | L35: 0 | M35: 0 | N35: 0 | O35: 0
C36: litres/mg litre
A37: Sud floc | B37: =790318.72/200 -> 3951.5936 | C37: litres | D37: 0 | E37: 0 | F37: 0 | G37: 0 | H37: 0 | I37: 0 | J37: 0 | K37: 0 | L37: 0 | M37: 0 | N37: 0 | O37: 0 | P37: =SUM(D37:O37) -> 0
C38: litres/mg litre | D38: =IFERROR(D37/(D9/1000),0) -> 0 | E38: =IFERROR(E37/(E9/1000),0) -> 0 | F38: =IFERROR(F37/(F9/1000),0) -> 0 | G38: =IFERROR(G37/(G9/1000),0) -> 0 | H38: =IFERROR(H37/(H9/1000),0) -> 0 | I38: =IFERROR(I37/(I9/1000),0) -> 0 | J38: =IFERROR(J37/(J9/1000),0) -> 0 | K38: =IFERROR(K37/(K9/1000),0) -> 0 | ... P38: =IFERROR(P37/(P9/1000),0) -> 0
A39: Potasium permanganate | B39: 1950 | C39: kg | D39: 0 | E39: 0 | F39: 0 | G39: 0 | H39: 0 | I39: 0 | J39: 0 | K39: 0 | L39: 0 | M39: 0 | N39: 0 | O39: 0 | P39: =SUM(D39:O39) -> 0
C40: kg/mg litre | D40: =IFERROR(D39/(D9/1000),0) -> 0 | E40: =IFERROR(E39/(E9/1000),0) -> 0 | F40: =IFERROR(F39/(F9/1000),0) -> 0 | G40: =IFERROR(G39/(G9/1000),0) -> 0 | H40: =IFERROR(H39/(H9/1000),0) -> 0 | I40: =IFERROR(I39/(I9/1000),0) -> 0 | J40: =IFERROR(J39/(J9/1000),0) -> 0 | K40: =IFERROR(K39/(K9/1000),0) -> 0 | ... P40: =IFERROR(P39/(P9/1000),0) -> 0
A41: Cost of Chemicals | C41: Mk | D41: =(D29*$B29)+(D31*$B31)+(D33*$B33)+(D35*$B35)+(D37*$B37)+(D39*$B39) -> 333000 | E41: =(E29*$B29)+(E31*$B31)+(E33*$B33)+(E35*$B35)+(E37*$B37)+(E39*$B39) -> 207200 | F41: =(F29*$B29)+(F31*$B31)+(F33*$B33)+(F35*$B35)+(F37*$B37)+(F39*$B39) -> 155400 | G41: =(G29*$B29)+(G31*$B31)+(G33*$B33)+(G35*$B35)+(G37*$B37)+(G39*$B39) -> 170200 | H41: =(H29*$B29)+(H31*$B31)+(H33*$B33)+(H35*$B35)+(H37*$B37)+(H39*$B39) -> 177600 | I41: =(I29*$B29)+(I31*$B31)+(I33*$B33)+(I35*$B35)+(I37*$B37)+(I39*$B39) -> 177600 | J41: =(J29*$B29)+(J31*$B31)+(J33*$B33)+(J35*$B35)+(J37*$B37)+(J39*$B39) -> 155400 | K41: =(K29*$B29)+(K31*$B31)+(K33*$B33)+(K35*$B35)+(K37*$B37)+(K39*$B39) -> 125800 | ... O41: =(O29*$B29)+(O31*$B31)+(O33*$B33)+(O35*$B35)+(O37*$B37)+(O39*$B39) -> 77700 | P41: =SUM(D41:O41) -> 1942500
A42: Cost/vol. Produced (chemicals) | C42: Mk/m3 | D42: =IFERROR(D41/D9,0) -> 9.5998616 | E42: =IFERROR(E41/E9,0) -> 5.6250848 | F42: =IFERROR(F41/F9,0) -> 4.4302534 | G42: =IFERROR(G41/G9,0) -> 4.8024831 | H42: =IFERROR(H41/H9,0) -> 4.084073 | I42: =IFERROR(I41/I9,0) -> 4.4159332 | J42: =IFERROR(J41/J9,0) -> 3.6947218 | K42: =IFERROR(K41/K9,0) -> 3.5470592 | ... P42: =IFERROR(P41/P9,0) -> 4.2910064
A43: Power
A44: Power Usage | C44: Kw | D44: 16866 | E44: 15980 | F44: 19038 | G44: 20957 | H44: 20512 | I44: 19724 | J44: 19497 | K44: 19135 | L44: 19023 | M44: 18042 | N44: 16625 | O44: 18167 | P44: =SUM(D44:O44) -> 223566
A45: Power/ Vol. Produced | C45: Kw/m3 | D45: =IFERROR(D44/D9,0) -> 0.48622002 | E45: =IFERROR(E44/E9,0) -> 0.43382652 | F45: =IFERROR(F44/F9,0) -> 0.54274881 | G45: =IFERROR(G44/G9,0) -> 0.59133747 | H45: =IFERROR(H44/H9,0) -> 0.47169204 | I45: =IFERROR(I44/I9,0) -> 0.49042717 | J45: =IFERROR(J44/J9,0) -> 0.46355207 | K45: =IFERROR(K44/K9,0) -> 0.53953082 | ... P45: =IFERROR(P44/P9,0) -> 0.49386005
A46: Cost of Power | C46: Mk | D46: =IF(D44=0,0,IF(D44>=0,0+(D44*202.25)+23390)*1.165) -> 4001237.4 | E46: =IF(E44=0,0,IF(E44>=0,0+(E44*202.25)+23390)*1.165) -> 3792476.9 | F46: =IF(F44=0,0,IF(F44>=0,0+(F44*202.25)+23390)*1.165) -> 4513006.7 | G46: =IF(G44=0,0,IF(G44>=0,0+(G44*202.25)+23390)*1.165) -> 4965163.9 | H46: =IF(H44=0,0,IF(H44>=0,0+(H44*202.25)+23390)*1.165) -> 4860312.4 | I46: =IF(I44=0,0,IF(I44>=0,0+(I44*202.25)+23390)*1.165) -> 4674642.9 | J46: =IF(J44=0,0,IF(J44>=0,0+(J44*202.25)+23390)*1.165) -> 4621156.9 | K46: =IF(K44=0,0,IF(K44>=0,0+(K44*202.25)+23390)*1.165) -> 4535862 | ... O46: =IF(O44=0,0,IF(O44>=0,0+(O44*202.25)+23390)*1.165) -> 4307780.6 | P46: =SUM(D46:O46) -> 53003893
A47: Cost/vol. Produced | C47: Mk/m3 | D47: =IFERROR(D46/D9,0) -> 115.34932 | E47: =IFERROR(E46/E9,0) -> 102.95852 | F47: =IFERROR(F46/F9,0) -> 128.66 | G47: =IFERROR(G46/G9,0) -> 140.10056 | H47: =IFERROR(H46/H9,0) -> 111.76729 | I47: =IFERROR(I46/I9,0) -> 116.2326 | J47: =IFERROR(J46/J9,0) -> 109.87059 | K47: =IFERROR(K46/K9,0) -> 127.89325 | ... P47: =IFERROR(P46/P9,0) -> 117.08625
A48: Plant and Vehicle Maintenance
A49: Distances covered | C49: km | D49: 0 | E49: 0 | F49: 0 | G49: 0 | H49: 0 | I49: 0 | J49: 0 | K49: 0 | L49: 0 | M49: 0 | N49: 0 | O49: 0 | P49: =SUM(D49:O49) -> 0
A50: Fuel Used (litres) | C50: litres | D50: 0 | E50: 0 | F50: 0 | G50: 0 | H50: 0 | I50: 0 | J50: 0 | K50: 0 | L50: 0 | M50: 0 | N50: 0 | O50: 0 | P50: =SUM(D50:O50) -> 0
A51: Cost of fuel | C51: Mk | D51: 0 | E51: 0 | F51: 0 | G51: 0 | H51: 0 | I51: 0 | J51: 0 | K51: 0 | L51: 0 | M51: 0 | N51: 0 | O51: 0 | P51: =SUM(D51:O51) -> 0
A52: Maintenance | C52: Mk | D52: 0 | E52: 0 | F52: 0 | G52: 0 | H52: 0 | I52: 0 | J52: 0 | K52: 0 | L52: 0 | M52: 0 | N52: 0 | O52: 0 | P52: =SUM(D52:O52) -> 0
A53: Salaries and Wages
A54: Staff Costs | C54: MK | D54: 0 | E54: 0 | F54: 0 | G54: 0 | H54: 0 | I54: 0 | J54: 0 | K54: 0 | L54: 0 | M54: 0 | N54: 0 | O54: 0 | P54: =SUM(D54:O54) -> 0
A55: Wages | C55: MK | D55: 0 | E55: 0 | F55: 0 | G55: 0 | H55: 0 | I55: 0 | J55: 0 | K55: 0 | L55: 0 | M55: 0 | N55: 0 | O55: 0 | P55: =SUM(D55:O55) -> 0
A56: Other Overhead Costs | C56: MK | D56: 0 | E56: 0 | F56: 0 | G56: 0 | H56: 0 | I56: 0 | J56: 0 | K56: 0 | L56: 0 | M56: 0 | N56: 0 | O56: 0 | P56: =SUM(D56:O56) -> 0
A57: Operating Costs
A58: Total Operating Costs | C58: MK | D58: =D41+D46+D51+D52+D54+D55+D56 -> 4334237.4 | E58: =E41+E46+E51+E52+E54+E55+E56 -> 3999676.9 | F58: =F41+F46+F51+F52+F54+F55+F56 -> 4668406.7 | G58: =G41+G46+G51+G52+G54+G55+G56 -> 5135363.9 | H58: =H41+H46+H51+H52+H54+H55+H56 -> 5037912.4 | I58: =I41+I46+I51+I52+I54+I55+I56 -> 4852242.9 | J58: =J41+J46+J51+J52+J54+J55+J56 -> 4776556.9 | K58: =K41+K46+K51+K52+K54+K55+K56 -> 4661662 | ... O58: =O41+O46+O51+O52+O54+O55+O56 -> 4385480.6 | P58: =SUM(D58:O58) -> 54946393
A59: Cost/Vol. Produced | C59: Mk/m3 | D59: =IFERROR(D58/D9,0) -> 124.94919 | E59: =IFERROR(E58/E9,0) -> 108.5836 | F59: =IFERROR(F58/F9,0) -> 133.09025 | G59: =IFERROR(G58/G9,0) -> 144.90304 | H59: =IFERROR(H58/H9,0) -> 115.85136 | I59: =IFERROR(I58/I9,0) -> 120.64854 | J59: =IFERROR(J58/J9,0) -> 113.56531 | K59: =IFERROR(K58/K9,0) -> 131.44031 | ... P59: =IFERROR(P58/P9,0) -> 121.37726
A60: Cost/Vol. Billed | C60: Mk/m3 | D60: =IFERROR(D58/D22,0) -> 177.01747 | E60: =IFERROR(E58/E22,0) -> 152.55403 | F60: =IFERROR(F58/F22,0) -> 163.44874 | G60: =IFERROR(G58/G22,0) -> 174.2136 | H60: =IFERROR(H58/H22,0) -> 188.63075 | I60: =IFERROR(I58/I22,0) -> 171.20568 | J60: =IFERROR(J58/J22,0) -> 165.7255 | K60: =IFERROR(K58/K22,0) -> 166.17575 | ... P60: =IFERROR(P58/P22,0) -> 167.54288
A61: Permanent Staff Employed | C61: No | D61: 12 | E61: 12 | F61: 12 | G61: 12 | H61: 12 | I61: 12 | J61: 12 | K61: 12 | L61: 12 | M61: 12 | N61: 12 | O61: 12 | P61: =O61 -> 12
A62: Staff/Vol.1000m3 of Volume Produced/hour (12 hour day) | C62: No/1000m3 | D62: =IFERROR((D61*1000*31)/D9,0) -> 10.72417 | E62: =IFERROR((E61*1000*31)/E9,0) -> 10.099091 | F62: =IFERROR((F61*1000*31)/F9,0) -> 10.60524 | G62: =IFERROR((G61*1000*31)/G9,0) -> 10.496614 | H62: =IFERROR((H61*1000*31)/H9,0) -> 8.5544773 | I62: =IFERROR((I61*1000*31)/I9,0) -> 9.2495897 | J62: =IFERROR((J61*1000*31)/J9,0) -> 8.8445078 | K62: =IFERROR((K61*1000*31)/K9,0) -> 10.488919 | ... P62: =IFERROR((P61*1000*31)/P9,0) -> 0.82175259
A63: Temporary Staff Employed | C63: No | D63: 26 | E63: 26 | F63: 26 | G63: 26 | H63: 26 | I63: 26 | J63: 26 | K63: 26 | L63: 26 | M63: 26 | N63: 26 | O63: 26 | P63: =O63 -> 26
A65: Water Connections and Disconnections
A66: New Individual Water Connections | B66: Brought Forward | C66: No | D66: 61 | E66: 45 | F66: 49 | G66: 47 | H66: 61 | I66: 76 | J66: 97 | K66: 93 | L66: 92 | M66: 99 | N66: 95 | O66: 83 | P66: =D66 -> 61
B67: Applied this Month | C67: No | D67: 8 | E67: 22 | F67: 22 | G67: 43 | H67: 60 | I67: 41 | J67: 14 | K67: 11 | L67: 18 | M67: 6 | N67: 13 | O67: 10 | P67: =SUM(D67:O67) -> 268
B68: Done this Month Postpaid | C68: No | D68: 24 | E68: 18 | F68: 24 | G68: 29 | H68: 45 | I68: 20 | J68: 18 | K68: 12 | L68: 11 | M68: 10 | N68: 25 | O68: 31 | P68: =SUM(D68:O68) -> 267
B69: Done this Month Prepaid | C69: No | D69: 0 | E69: 0 | F69: 0 | G69: 0 | H69: 0 | I69: 0 | J69: 0 | K69: 0 | L69: 0 | M69: 0 | N69: 0 | O69: 0 | P69: =SUM(D69:O69) -> 0
B70: Total Done | C70: No | D70: =D68+D69 -> 24 | E70: =E68+E69 -> 18 | F70: =F68+F69 -> 24 | G70: =G68+G69 -> 29 | H70: =H68+H69 -> 45 | I70: =I68+I69 -> 20 | J70: =J68+J69 -> 18 | K70: =K68+K69 -> 12 | ... P70: =P68+P69 -> 267
B71: Carried Forward | C71: No | D71: =D66+D67-D70 -> 45 | E71: =E66+E67-E70 -> 49 | F71: =F66+F67-F70 -> 47 | G71: =G66+G67-G70 -> 61 | H71: =H66+H67-H70 -> 76 | I71: =I66+I67-I70 -> 97 | J71: =J66+J67-J70 -> 93 | K71: =K66+K67-K70 -> 92 | ... P71: =P66+P67-P70 -> 62
A72: New Institutional Water Connections | B72: Brought Forward | C72: No | D72: 0 | E72: 0 | F72: 0 | G72: 0 | H72: 0 | I72: 0 | J72: 0 | K72: 0 | L72: 0 | M72: 0 | N72: 0 | O72: 0 | P72: =D72 -> 0
B73: Applied this Month | C73: No | D73: 1 | E73: 0 | F73: 1 | G73: 0 | H73: 1 | I73: 0 | J73: 1 | K73: 0 | L73: 0 | M73: 0 | N73: 0 | O73: 1 | P73: =SUM(D73:O73) -> 5
B74: Done this Month Postpaid | C74: No | D74: 1 | E74: 0 | F74: 1 | G74: 0 | H74: 1 | I74: 0 | J74: 1 | K74: 0 | L74: 0 | M74: 0 | N74: 0 | O74: 1 | P74: =SUM(D74:O74) -> 5
B75: Done this Month Prepaid | C75: No | D75: 0 | E75: 0 | F75: 0 | G75: 0 | H75: 0 | I75: 0 | J75: 0 | K75: 0 | L75: 0 | M75: 0 | N75: 0 | O75: 0 | P75: =SUM(D75:O75) -> 0
B76: Total Done | C76: No | D76: =D74+D75 -> 1 | E76: =E74+E75 -> 0 | F76: =F74+F75 -> 1 | G76: =G74+G75 -> 0 | H76: =H74+H75 -> 1 | I76: =I74+I75 -> 0 | J76: =J74+J75 -> 1 | K76: =K74+K75 -> 0 | ... P76: =P74+P75 -> 5
B77: Carried Forward | C77: No | D77: =D72+D73-D76 -> 0 | E77: =E72+E73-E76 -> 0 | F77: =F72+F73-F76 -> 0 | G77: =G72+G73-G76 -> 0 | H77: =H72+H73-H76 -> 0 | I77: =I72+I73-I76 -> 0 | J77: =J72+J73-J76 -> 0 | K77: =K72+K73-K76 -> 0 | ... P77: =P72+P73-P76 -> 0
A78: New Commercial/Industrial Water Connections | B78: Brought Forward | C78: No | D78: 0 | E78: 0 | F78: 0 | G78: 0 | H78: 0 | I78: 0 | J78: 0 | K78: 2 | L78: 0 | M78: 0 | N78: 0 | O78: 0 | P78: =D78 -> 0
B79: Applied this Month | C79: No | D79: 0 | E79: 0 | F79: 0 | G79: 0 | H79: 0 | I79: 0 | J79: 2 | K79: 0 | L79: 0 | M79: 0 | N79: 0 | O79: 0 | P79: =SUM(D79:O79) -> 2
B80: Done this Month Postpaid | C80: No | D80: 0 | E80: 0 | F80: 0 | G80: 0 | H80: 0 | I80: 0 | J80: 0 | K80: 2 | L80: 0 | M80: 0 | N80: 0 | O80: 0 | P80: =SUM(D80:O80) -> 2
B81: Done this Month Prepaid | C81: No | D81: 0 | E81: 0 | F81: 0 | G81: 0 | H81: 0 | I81: 0 | J81: 0 | K81: 0 | L81: 0 | M81: 0 | N81: 0 | O81: 0 | P81: =SUM(D81:O81) -> 0
B82: Total Done | C82: No | D82: =D80+D81 -> 0 | E82: =E80+E81 -> 0 | F82: =F80+F81 -> 0 | G82: =G80+G81 -> 0 | H82: =H80+H81 -> 0 | I82: =I80+I81 -> 0 | J82: =J80+J81 -> 0 | K82: =K80+K81 -> 2 | ... O82: =O80+O81 -> 0 | P82: =P81+P80 -> 2
B83: Carried Forward | C83: No | D83: =D78+D79-D82 -> 0 | E83: =E78+E79-E82 -> 0 | F83: =F78+F79-F82 -> 0 | G83: =G78+G79-G82 -> 0 | H83: =H78+H79-H82 -> 0 | I83: =I78+I79-I82 -> 0 | J83: =J78+J79-J82 -> 2 | K83: =K78+K79-K82 -> 0 | ... P83: =P78+P79-P82 -> 0
A84: New CWP | B84: Brought Forward | C84: No | D84: 0 | E84: 0 | F84: 0 | G84: 0 | H84: 0 | I84: 0 | J84: 0 | K84: 0 | L84: 0 | M84: 0 | N84: 0 | O84: 0 | P84: =D84 -> 0
B85: Applied this Month | C85: No | D85: 0 | E85: 0 | F85: 0 | G85: 0 | H85: 0 | I85: 0 | J85: 0 | K85: 0 | L85: 0 | M85: 0 | N85: 0 | O85: 0 | P85: =SUM(D85:O85) -> 0
B86: Done this Month Postpaid | C86: No | D86: 0 | E86: 0 | F86: 0 | G86: 0 | H86: 0 | I86: 0 | J86: 0 | K86: 0 | L86: 0 | M86: 0 | N86: 0 | O86: 0 | P86: =SUM(D86:O86) -> 0
B87: Done this Month Prepaid | C87: No | D87: 0 | E87: 0 | F87: 0 | G87: 0 | H87: 0 | I87: 0 | J87: 0 | K87: 0 | L87: 0 | M87: 0 | N87: 0 | O87: 0 | P87: =SUM(D87:O87) -> 0
B88: Total Done | C88: No | D88: =D86+D87 -> 0 | E88: =E86+E87 -> 0 | F88: =F86+F87 -> 0 | G88: =G86+G87 -> 0 | H88: =H86+H87 -> 0 | I88: =I86+I87 -> 0 | J88: =J86+J87 -> 0 | K88: =K86+K87 -> 0 | ... O88: =O86+O87 -> 0 | P88: =SUM(D88:O88) -> 0
B89: Carried Forward | C89: No | D89: =D84+D85-D88 -> 0 | E89: =E84+E85-E88 -> 0 | F89: =F84+F85-F88 -> 0 | G89: =G84+G85-G88 -> 0 | H89: =H84+H85-H88 -> 0 | I89: =I84+I85-I88 -> 0 | J89: =J84+J85-J88 -> 0 | K89: =K84+K85-K88 -> 0 | ... O89: =O84+O85-O88 -> 0 | P89: =P84+P85-P86-P87 -> 0
A90: Aggregated New Water connections | B90: Brought Forward | C90: No | D90: =D66+D72+D78+D84 -> 61 | E90: =E66+E72+E78+E84 -> 45 | F90: =F66+F72+F78+F84 -> 49 | G90: =G66+G72+G78+G84 -> 47 | H90: =H66+H72+H78+H84 -> 61 | I90: =I66+I72+I78+I84 -> 76 | J90: =J66+J72+J78+J84 -> 97 | K90: =K66+K72+K78+K84 -> 95 | ... O90: =O66+O72+O78+O84 -> 83 | P90: =D90 -> 61
B91: Applied this Month | C91: No | D91: =D67+D73+D79+D85 -> 9 | E91: =E67+E73+E79+E85 -> 22 | F91: =F67+F73+F79+F85 -> 23 | G91: =G67+G73+G79+G85 -> 43 | H91: =H67+H73+H79+H85 -> 61 | I91: =I67+I73+I79+I85 -> 41 | J91: =J67+J73+J79+J85 -> 17 | K91: =K67+K73+K79+K85 -> 11 | ... O91: =O67+O73+O79+O85 -> 11 | P91: =SUM(D91:O91) -> 275
B92: Done this Month Postpaid | C92: No | D92: =D68+D74+D80+D86 -> 25 | E92: =E68+E74+E80+E86 -> 18 | F92: =F68+F74+F80+F86 -> 25 | G92: =G68+G74+G80+G86 -> 29 | H92: =H68+H74+H80+H86 -> 46 | I92: =I68+I74+I80+I86 -> 20 | J92: =J68+J74+J80+J86 -> 19 | K92: =K68+K74+K80+K86 -> 14 | ... O92: =O68+O74+O80+O86 -> 32 | P92: =SUM(D92:O92) -> 274
B93: Done this Month Prepaid | D93: =D69+D75+D81+D87 -> 0 | E93: =E69+E75+E81+E87 -> 0 | F93: =F69+F75+F81+F87 -> 0 | G93: =G69+G75+G81+G87 -> 0 | H93: =H69+H75+H81+H87 -> 0 | I93: =I69+I75+I81+I87 -> 0 | J93: =J69+J75+J81+J87 -> 0 | K93: =K69+K75+K81+K87 -> 0 | ... O93: =O69+O75+O81+O87 -> 0 | P93: =SUM(D93:O93) -> 0
B94: Total Done | C94: No | D94: =D93+D92 -> 25 | E94: =E93+E92 -> 18 | F94: =F93+F92 -> 25 | G94: =G93+G92 -> 29 | H94: =H93+H92 -> 46 | I94: =I93+I92 -> 20 | J94: =J93+J92 -> 19 | K94: =K93+K92 -> 14 | ... P94: =P93+P92 -> 274
B95: Carried Forward | C95: No | D95: =D90+D91-D94 -> 45 | E95: =E90+E91-E94 -> 49 | F95: =F90+F91-F94 -> 47 | G95: =G90+G91-G94 -> 61 | H95: =H90+H91-H94 -> 76 | I95: =I90+I91-I94 -> 97 | J95: =J90+J91-J94 -> 95 | K95: =K90+K91-K94 -> 92 | ... P95: =P90+P91-P94 -> 62
A97: Prepaid Metering
A98: Prepaid Meters Installed | C98: No | D98: 0 | E98: 0 | F98: 0 | G98: 0 | H98: 0 | I98: 2 | J98: 0 | K98: 0 | L98: 0 | M98: 0 | N98: 0 | O98: 0 | P98: =SUM(D98:O98) -> 2
A100: Active and Disconnected Accounts
A101: Disconnected Individual Accounts | C101: No | D101: 896 | E101: 860 | F101: 832 | G101: 843 | H101: 827 | I101: 816 | J101: 809 | K101: 795 | L101: 792 | M101: 888 | N101: 878 | O101: 894 | P101: =O101 -> 894
A102: Disconnected institutional Accounts | C102: No | D102: 60 | E102: 55 | F102: 55 | G102: 53 | H102: 53 | I102: 51 | J102: 51 | K102: 49 | L102: 51 | M102: 53 | N102: 53 | O102: 54 | P102: =O102 -> 54
A103: Disconnected Commercial/Industrial Accounts | C103: No | D103: 0 | E103: 1 | F103: 2 | G103: 8 | H103: 12 | I103: 13 | J103: 10 | K103: 13 | L103: 12 | M103: 19 | N103: 4 | O103: 12 | P103: =O103 -> 12
A104: Disconnected CWP | C104: No | D104: 11 | E104: 11 | F104: 11 | G104: 11 | H104: 11 | I104: 11 | J104: 11 | K104: 11 | L104: 10 | M104: 10 | N104: 10 | O104: 10 | P104: =O104 -> 10
A105: Total Disconnected Accounts | C105: No | D105: =SUM(D101:D104) -> 967 | E105: =SUM(E101:E104) -> 927 | F105: =SUM(F101:F104) -> 900 | G105: =SUM(G101:G104) -> 915 | H105: =SUM(H101:H104) -> 903 | I105: =SUM(I101:I104) -> 891 | J105: =SUM(J101:J104) -> 881 | K105: =SUM(K101:K104) -> 868 | ... O105: =SUM(O101:O104) -> 970 | P105: =O105 -> 970
A106: Postpaid Consumers
...

Sheet Domasi
A1: SOUTHERN REGION WATER BOARD
A3: MONTHLY REPORTS - 2024/2025
A4: ZOMBA ZONE
A5: DOMASI SCHEME
A7: PARAMETERS | C7: UNITS | D7: APRIL | E7: MAY | F7: JUNE | G7: JULY | H7: AUGUST | I7: SEPTEMBER | J7: OCTOBER | K7: NOVEMBER | L7: DECEMBER | M7: JANUARY | N7: FEBRUARY | O7: MARCH | P7: TOTALS
A8: PRODUCTION
A9: Volume Produced | C9: m3 | D9: 22093 | E9: 19087 | F9: 16884 | G9: 29538 | H9: 29005 | I9: 25801 | J9: 17517 | K9: 20821 | L9: 18258 | M9: 17242 | N9: 24090 | O9: 23231 | P9: =SUM(D9:O9) -> 263567
A10: REVENUE WATER - POSTPAID
A11: Volume Billed Individuals | C11: m3 | D11: 6622 | E11: 7449 | F11: 7945 | G11: 7101 | H11: 8635 | I11: 11214 | J11: 9566 | K11: 9460 | L11: 8521 | M11: 6055 | N11: 8500 | O11: 8337 | P11: =SUM(D11:O11) -> 99405
A12: Volume Billed CWPs | C12: m3 | D12: 46 | E12: 46 | F12: 27 | G12: 0 | H12: 0 | I12: 0 | J12: 0 | K12: 0 | L12: 0 | M12: 0 | N12: 0 | O12: 0 | P12: =SUM(D12:O12) -> 119
A13: Volume Billed Institutions | C13: m3 | D13: 79 | E13: 92 | F13: 83 | G13: 66 | H13: 70 | I13: 80 | J13: 116 | K13: 103 | L13: 145 | M13: 49 | N13: 49 | O13: 54 | P13: =SUM(D13:O13) -> 986
A14: Volume Billed Commercial/Industrial | C14: m3 | D14: 173 | E14: 58 | F14: 44 | G14: 20 | H14: 54 | I14: 386 | J14: 125 | K14: 42 | L14: 25 | M14: 6 | N14: 15 | O14: 9 | P14: =SUM(D14:O14) -> 957
A15: Total Volume Billed Post Paid | C15: m3 | D15: =SUM(D11:D14) -> 6920 | E15: =SUM(E11:E14) -> 7645 | F15: =SUM(F11:F14) -> 8099 | G15: =SUM(G11:G14) -> 7187 | H15: =SUM(H11:H14) -> 8759 | I15: =SUM(I11:I14) -> 11680 | J15: =SUM(J11:J14) -> 9807 | K15: =SUM(K11:K14) -> 9605 | ... P15: =SUM(P11:P14) -> 101467
A16: REVENUE WATER - PREPAID
A17: Individuals | C17: m3 | D17: 3109 | E17: 4053 | F17: 3169.7 | G17: 3636 | H17: 4347.6 | I17: 5453.6 | J17: 4241.7 | K17: 4742 | L17: 3605.9 | M17: 3763.1 | N17: 6030 | O17: 5663 | P17: =SUM(D17:O17) -> 51814.6
A18: CWPs | C18: m3 | D18: 25.9 | E18: 90.6 | F18: 125.9 | G18: 249.1 | H18: 129 | I18: 154.5 | J18: 155.5 | K18: 108.7 | L18: 149.7 | M18: 82.7 | N18: 92.3 | O18: 100.2 | P18: =SUM(D18:O18) -> 1464.1
A19: Institutions | C19: m3 | D19: 8677 | E19: 2884.8 | F19: 1759.4 | G19: 6627.5 | H19: 6922.5 | I19: 5064.9 | J19: 2780.1 | K19: 3429.6 | L19: 1620.8 | M19: 2422.7 | N19: 1842.5 | O19: 5164.1 | P19: =SUM(D19:O19) -> 49195.9
A20: Commercial/Industrial | C20: m3 | D20: 134.1 | E20: 64.8 | F20: 147.5 | G20: 524.3 | H20: 555.2 | I20: 543 | J20: 125.9 | K20: 107.5 | L20: 79.3 | M20: 145.1 | N20: 120.9 | O20: 2215.8 | P20: =SUM(D20:O20) -> 4763.4
A21: Total Volume Prepaid | C21: m3 | D21: =SUM(D17:D20) -> 11946 | E21: =SUM(E17:E20) -> 7093.2 | F21: =SUM(F17:F20) -> 5202.5 | G21: =SUM(G17:G20) -> 11036.9 | H21: =SUM(H17:H20) -> 11954.3 | I21: =SUM(I17:I20) -> 11216 | J21: =SUM(J17:J20) -> 7303.2 | K21: =SUM(K17:K20) -> 8387.8 | ... P21: =SUM(P17:P20) -> 107238
A22: TOTAL REVENUE WATER | C22: m3 | D22: =D21+D15 -> 18866 | E22: =E21+E15 -> 14738.2 | F22: =F21+F15 -> 13301.5 | G22: =G21+G15 -> 18223.9 | H22: =H21+H15 -> 20713.3 | I22: =I21+I15 -> 22896 | J22: =J21+J15 -> 17110.2 | K22: =K21+K15 -> 17992.8 | ... P22: =P21+P15 -> 208705
A24: Non-Revenue Water (NRW) | B24: Volume | C24: m3 | D24: =D9-D22 -> 3227 | E24: =E9-E22 -> 4348.8 | F24: =F9-F22 -> 3582.5 | G24: =G9-G22 -> 11314.1 | H24: =H9-H22 -> 8291.7 | I24: =I9-I22 -> 2905 | J24: =J9-J22 -> 406.8 | K24: =K9-K22 -> 2828.2 | ... P24: =P9-P22 -> 54862
B25: Percentage | C25: % | D25: =IFERROR(D24/D9,0) -> 0.14606436 | E25: =E24/E9 -> 0.22784094 | F25: =F24/F9 -> 0.21218313 | G25: =IFERROR(G24/G9,0) -> 0.38303541 | H25: =IFERROR(H24/H9,0) -> 0.2858714 | I25: =IFERROR(I24/I9,0) -> 0.11259254 | J25: =IFERROR(J24/J9,0) -> 0.023223155 | K25: =IFERROR(K24/K9,0) -> 0.13583401 | L25: =IFERROR(L24/L9,0) -> 0.225178 | M25: =IFERROR(M24/M9,0) -> 0.27365735 | N25: =IFERROR(N24/N9,0) -> 0.3088543 | O25: =IFERROR(O24/O9,0) -> 0.072657225 | P25: =IF(P9,P24/P9,"") -> 0.20815201
A26: OPERATING EXPENSES
A27: Chemicals
A28: Chemical | B28: Rate(MK/kg)
A29: Chlorine | B29: 7400 | C29: kg | D29: 48 | E29: 46 | F29: 50 | G29: 87.5 | H29: 75 | I29: 50 | J29: 50 | K29: 50 | L29: 50 | M29: 50 | N29: 52 | O29: 50 | P29: =SUM(D29:O29) -> 658.5
C30: kg/mg litre | D30: =IFERROR(D29/(D9/1000),0) -> 2.1726339 | E30: =IFERROR(E29/(E9/1000),0) -> 2.4100173 | F30: =IFERROR(F29/(F9/1000),0) -> 2.9613836 | G30: =IFERROR(G29/(G9/1000),0) -> 2.9622859 | H30: =IFERROR(H29/(H9/1000),0) -> 2.5857611 | I30: =IFERROR(I29/(I9/1000),0) -> 1.9379094 | J30: =IFERROR(J29/(J9/1000),0) -> 2.85437 | K30: =IFERROR(K29/(K9/1000),0) -> 2.4014216 | ... P30: =IFERROR(P29/(P9/1000),0) -> 2.498416
A31: Aluminium sulphate | B31: 1900 | C31: kg | D31: 0 | E31: 0 | F31: 0 | G31: 0 | H31: 0 | I31: 0 | J31: 0 | K31: 0 | L31: 100 | M31: 200 | N31: 300 | O31: 50 | P31: =SUM(D31:O31) -> 650
C32: kg/mg litre | D32: =IFERROR(D31/(D9/1000),0) -> 0 | E32: =IFERROR(E31/(E9/1000),0) -> 0 | F32: =IFERROR(F31/(F9/1000),0) -> 0 | G32: =IFERROR(G31/(G9/1000),0) -> 0 | H32: =IFERROR(H31/(H9/1000),0) -> 0 | I32: =IFERROR(I31/(I9/1000),0) -> 0 | J32: =IFERROR(J31/(J9/1000),0) -> 0 | K32: =IFERROR(K31/(K9/1000),0) -> 0 | ... P32: =IFERROR(P31/(P9/1000),0) -> 2.4661661
A33: Soda | B33: 1900 | C33: kg | D33: 0 | E33: 0 | F33: 0 | G33: 0 | H33: 0 | I33: 0 | J33: 0 | K33: 0 | L33: 37.5 | M33: 87.5 | N33: 150 | O33: 25 | P33: =SUM(D33:O33) -> 300
C34: kg/mg litre | D34: =IFERROR(D33/(D9/1000),0) -> 0 | E34: =IFERROR(E33/(E9/1000),0) -> 0 | F34: =IFERROR(F33/(F9/1000),0) -> 0 | G34: =IFERROR(G33/(G9/1000),0) -> 0 | H34: =IFERROR(H33/(H9/1000),0) -> 0 | I34: =IFERROR(I33/(I9/1000),0) -> 0 | J34: =IFERROR(J33/(J9/1000),0) -> 0 | K34: =IFERROR(K33/(K9/1000),0) -> 0 | ... P34: =IFERROR(P33/(P9/1000),0) -> 1.1382305
A35: Algae floc | B35: =745345.16/200 -> 3726.7258 | C35: litres | D35: 0 | E35: 0 | F35: 0 | G35: 0 | H35: 0 | I35: 0 | J35: 0 | K35: 0 | L35: 0 | M35: 0 | N35: 0 | O35: 0
C36: litres/mg litre
A37: Sud floc | B37: =790318.72/200 -> 3951.5936 | C37: litres | D37: 0 | E37: 0 | F37: 0 | G37: 0 | H37: 0 | I37: 0 | J37: 0 | K37: 0 | L37: 0 | M37: 0 | N37: 0 | O37: 0 | P37: =SUM(D37:O37) -> 0
C38: litres/mg litre | D38: =IFERROR(D37/(D9/1000),0) -> 0 | E38: =IFERROR(E37/(E9/1000),0) -> 0 | F38: =IFERROR(F37/(F9/1000),0) -> 0 | G38: =IFERROR(G37/(G9/1000),0) -> 0 | H38: =IFERROR(H37/(H9/1000),0) -> 0 | I38: =IFERROR(I37/(I9/1000),0) -> 0 | J38: =IFERROR(J37/(J9/1000),0) -> 0 | K38: =IFERROR(K37/(K9/1000),0) -> 0 | ... P38: =IFERROR(P37/(P9/1000),0) -> 0
A39: Potasium permanganate | B39: 1950 | C39: kg | D39: 0 | E39: 0 | F39: 0 | G39: 0 | H39: 0 | I39: 0 | J39: 0 | K39: 0 | L39: 0 | M39: 0 | N39: 0 | O39: 0 | P39: =SUM(D39:O39) -> 0
C40: kg/mg litre | D40: =IFERROR(D39/(D9/1000),0) -> 0 | E40: =IFERROR(E39/(E9/1000),0) -> 0 | F40: =IFERROR(F39/(F9/1000),0) -> 0 | G40: =IFERROR(G39/(G9/1000),0) -> 0 | H40: =IFERROR(H39/(H9/1000),0) -> 0 | I40: =IFERROR(I39/(I9/1000),0) -> 0 | J40: =IFERROR(J39/(J9/1000),0) -> 0 | K40: =IFERROR(K39/(K9/1000),0) -> 0 | ... P40: =IFERROR(P39/(P9/1000),0) -> 0
A41: Cost of Chemicals | C41: Mk | D41: =(D29*$B29)+(D31*$B31)+(D33*$B33)+(D35*$B35)+(D37*$B37)+(D39*$B39) -> 355200 | E41: =(E29*$B29)+(E31*$B31)+(E33*$B33)+(E35*$B35)+(E37*$B37)+(E39*$B39) -> 340400 | F41: =(F29*$B29)+(F31*$B31)+(F33*$B33)+(F35*$B35)+(F37*$B37)+(F39*$B39) -> 370000 | G41: =(G29*$B29)+(G31*$B31)+(G33*$B33)+(G35*$B35)+(G37*$B37)+(G39*$B39) -> 647500 | H41: =(H29*$B29)+(H31*$B31)+(H33*$B33)+(H35*$B35)+(H37*$B37)+(H39*$B39) -> 555000 | I41: =(I29*$B29)+(I31*$B31)+(I33*$B33)+(I35*$B35)+(I37*$B37)+(I39*$B39) -> 370000 | J41: =(J29*$B29)+(J31*$B31)+(J33*$B33)+(J35*$B35)+(J37*$B37)+(J39*$B39) -> 370000 | K41: =(K29*$B29)+(K31*$B31)+(K33*$B33)+(K35*$B35)+(K37*$B37)+(K39*$B39) -> 370000 | ... O41: =(O29*$B29)+(O31*$B31)+(O33*$B33)+(O35*$B35)+(O37*$B37)+(O39*$B39) -> 512500 | P41: =SUM(D41:O41) -> 6677900
A42: Cost/vol. Produced (chemicals) | C42: Mk/m3 | D42: =IFERROR(D41/D9,0) -> 16.077491 | E42: =IFERROR(E41/E9,0) -> 17.834128 | F42: =IFERROR(F41/F9,0) -> 21.914238 | G42: =IFERROR(G41/G9,0) -> 21.920915 | H42: =IFERROR(H41/H9,0) -> 19.134632 | I42: =IFERROR(I41/I9,0) -> 14.340529 | J42: =IFERROR(J41/J9,0) -> 21.122338 | K42: =IFERROR(K41/K9,0) -> 17.77052 | ... P42: =IFERROR(P41/P9,0) -> 25.336632
A43: Power
A44: Power Usage | C44: Kw | D44: 151.78 | E44: 148.72 | F44: 122.19 | G44: 173.61 | H44: 158.17 | I44: 133.21 | J44: 124.12 | K44: 118.58 | L44: 121.36 | M44: 129.41 | N44: 134.17 | O44: 91.89 | P44: =SUM(D44:O44) -> 1607.21
A45: Power/ Vol. Produced | C45: Kw/m3 | D45: =IFERROR(D44/D9,0) -> 0.0068700493 | E45: =IFERROR(E44/E9,0) -> 0.0077916907 | F45: =IFERROR(F44/F9,0) -> 0.0072370291 | G45: =IFERROR(G44/G9,0) -> 0.0058775137 | H45: =IFERROR(H44/H9,0) -> 0.0054531977 | I45: =IFERROR(I44/I9,0) -> 0.0051629782 | J45: =IFERROR(J44/J9,0) -> 0.0070856882 | K45: =IFERROR(K44/K9,0) -> 0.0056952116 | ... P45: =IFERROR(P44/P9,0) -> 0.0060979182
A46: Cost of Power | C46: Mk | D46: =IF(D44=0,0,IF(D44>=0,0+(D44*202.25)+23390)*1.165) -> 63011.943 | E46: =IF(E44=0,0,IF(E44>=0,0+(E44*202.25)+23390)*1.165) -> 62290.942 | F46: =IF(F44=0,0,IF(F44>=0,0+(F44*202.25)+23390)*1.165) -> 56039.911 | G46: =IF(G44=0,0,IF(G44>=0,0+(G44*202.25)+23390)*1.165) -> 68155.555 | H46: =IF(H44=0,0,IF(H44>=0,0+(H44*202.25)+23390)*1.165) -> 64517.563 | I46: =IF(I44=0,0,IF(I44>=0,0+(I44*202.25)+23390)*1.165) -> 58636.457 | J46: =IF(J44=0,0,IF(J44>=0,0+(J44*202.25)+23390)*1.165) -> 56494.66 | K46: =IF(K44=0,0,IF(K44>=0,0+(K44*202.25)+23390)*1.165) -> 55189.318 | ... O46: =IF(O44=0,0,IF(O44>=0,0+(O44*202.25)+23390)*1.165) -> 48900.587 | P46: =SUM(D46:O46) -> 705685.03
A47: Cost/vol. Produced | C47: Mk/m3 | D47: =IFERROR(D46/D9,0) -> 2.8521225 | E47: =IFERROR(E46/E9,0) -> 3.2635271 | F47: =IFERROR(F46/F9,0) -> 3.3191134 | G47: =IFERROR(G46/G9,0) -> 2.3073856 | H47: =IFERROR(H46/H9,0) -> 2.22436 | I47: =IFERROR(I46/I9,0) -> 2.2726428 | J47: =IFERROR(J46/J9,0) -> 3.2251333 | K47: =IFERROR(K46/K9,0) -> 2.6506564 | ... P47: =IFERROR(P46/P9,0) -> 2.6774408
A48: Plant and Vehicle Maintenance
A49: Distances covered | C49: km | D49: 0 | E49: 0 | F49: 0 | G49: 0 | H49: 0 | I49: 0 | J49: 0 | K49: 0 | L49: 0 | M49: 0 | N49: 0 | O49: 0 | P49: =SUM(D49:O49) -> 0
A50: Fuel Used (litres) | C50: litres | D50: 0 | E50: 0 | F50: 0 | G50: 0 | H50: 0 | I50: 0 | J50: 0 | K50: 0 | L50: 0 | M50: 0 | N50: 0 | O50: 0 | P50: =SUM(D50:O50) -> 0
A51: Cost of fuel | C51: Mk | D51: 0 | E51: 0 | F51: 0 | G51: 0 | H51: 0 | I51: 0 | J51: 0 | K51: 0 | L51: 0 | M51: 0 | N51: 0 | O51: 0 | P51: =SUM(D51:O51) -> 0
A52: Maintenance | C52: Mk | D52: 0 | E52: 0 | F52: 0 | G52: 0 | H52: 0 | I52: 0 | J52: 0 | K52: 0 | L52: 0 | M52: 0 | N52: 0 | O52: 0 | P52: =SUM(D52:O52) -> 0
A53: Salaries and Wages
A54: Staff Costs | C54: MK | D54: 0 | E54: 0 | F54: 0 | G54: 0 | H54: 0 | I54: 0 | J54: 0 | K54: 0 | L54: 0 | M54: 0 | N54: 0 | O54: 0 | P54: =SUM(D54:O54) -> 0
A55: Wages | C55: MK | D55: 0 | E55: 0 | F55: 0 | G55: 0 | H55: 0 | I55: 0 | J55: 0 | K55: 0 | L55: 0 | M55: 0 | N55: 0 | O55: 0 | P55: =SUM(D55:O55) -> 0
A56: Other Overhead Costs | C56: MK | D56: 0 | E56: 0 | F56: 0 | G56: 0 | H56: 0 | I56: 0 | J56: 0 | K56: 0 | L56: 0 | M56: 0 | N56: 0 | O56: 0 | P56: =SUM(D56:O56) -> 0
A57: Operating Costs
A58: Total Operating Costs | C58: MK | D58: =D41+D46+D51+D52+D54+D55+D56 -> 418211.94 | E58: =E41+E46+E51+E52+E54+E55+E56 -> 402690.94 | F58: =F41+F46+F51+F52+F54+F55+F56 -> 426039.91 | G58: =G41+G46+G51+G52+G54+G55+G56 -> 715655.56 | H58: =H41+H46+H51+H52+H54+H55+H56 -> 619517.56 | I58: =I41+I46+I51+I52+I54+I55+I56 -> 428636.46 | J58: =J41+J46+J51+J52+J54+J55+J56 -> 426494.66 | K58: =K41+K46+K51+K52+K54+K55+K56 -> 425189.32 | ... O58: =O41+O46+O51+O52+O54+O55+O56 -> 561400.59 | P58: =SUM(D58:O58) -> 7383585
A59: Cost/Vol. Produced | C59: Mk/m3 | D59: =IFERROR(D58/D9,0) -> 18.929613 | E59: =IFERROR(E58/E9,0) -> 21.097655 | F59: =IFERROR(F58/F9,0) -> 25.233352 | G59: =IFERROR(G58/G9,0) -> 24.228301 | H59: =IFERROR(H58/H9,0) -> 21.358992 | I59: =IFERROR(I58/I9,0) -> 16.613172 | J59: =IFERROR(J58/J9,0) -> 24.347472 | K59: =IFERROR(K58/K9,0) -> 20.421177 | ... P59: =IFERROR(P58/P9,0) -> 28.014072
A60: Cost/Vol. Billed | C60: Mk/m3 | D60: =IFERROR(D58/D22,0) -> 22.167494 | E60: =IFERROR(E58/E22,0) -> 27.322939 | F60: =IFERROR(F58/F22,0) -> 32.029464 | G60: =IFERROR(G58/G22,0) -> 39.270165 | H60: =IFERROR(H58/H22,0) -> 29.909168 | I60: =IFERROR(I58/I22,0) -> 18.721019 | J60: =IFERROR(J58/J22,0) -> 24.92634 | K60: =IFERROR(K58/K22,0) -> 23.631081 | ... P60: =IFERROR(P58/P22,0) -> 35.378094
A61: Permanent Staff Employed | C61: No | D61: 8 | E61: 8 | F61: 8 | G61: 8 | H61: 8 | I61: 8 | J61: 9 | K61: 9 | L61: 9 | M61: 9 | N61: 7 | O61: 7 | P61: =O61 -> 7
A62: Staff/Vol.1000m3 of Volume Produced/hour (12 hour day) | C62: No/1000m3 | D62: =IFERROR((D61*1000*31)/D9,0) -> 11.225275 | E62: =IFERROR((E61*1000*31)/E9,0) -> 12.993137 | F62: =IFERROR((F61*1000*31)/F9,0) -> 14.688462 | G62: =IFERROR((G61*1000*31)/G9,0) -> 8.3959645 | H62: =IFERROR((H61*1000*31)/H9,0) -> 8.55025 | I62: =IFERROR((I61*1000*31)/I9,0) -> 9.6120305 | J62: =IFERROR((J61*1000*31)/J9,0) -> 15.927385 | K62: =IFERROR((K61*1000*31)/K9,0) -> 13.399933 | ... P62: =IFERROR((P61*1000*31)/P9,0) -> 0.82332007
A63: Temporary Staff Employed | C63: No | D63: 17 | E63: 17 | F63: 17 | G63: 17 | H63: 17 | I63: 17 | J63: 17 | K63: 17 | L63: 17 | M63: 17 | N63: 17 | O63: 17 | P63: =O63 -> 17
A65: Water Connections and Disconnections
A66: New Individual Water Connections | B66: Brought Forward | C66: No | D66: 44 | E66: 48 | F66: 49 | G66: 41 | H66: 44 | I66: 51 | J66: 53 | K66: 55 | L66: 53 | M66: 52 | N66: 50 | O66: 52 | P66: =D66 -> 44
B67: Applied this Month | C67: No | D67: 13 | E67: 17 | F67: 16 | G67: 13 | H67: 32 | I67: 25 | J67: 21 | K67: 11 | L67: 16 | M67: 8 | N67: 16 | O67: 11 | P67: =SUM(D67:O67) -> 199
B68: Done this Month Postpaid | C68: No | D68: 9 | E68: 16 | F68: 24 | G68: 10 | H68: 25 | I68: 23 | J68: 19 | K68: 13 | L68: 17 | M68: 10 | N68: 14 | O68: 14 | P68: =SUM(D68:O68) -> 194
B69: Done this Month Prepaid | C69: No | D69: 0 | E69: 0 | F69: 0 | G69: 0 | H69: 0 | I69: 0 | J69: 0 | K69: 0 | L69: 0 | M69: 0 | N69: 0 | O69: 0 | P69: =SUM(D69:O69) -> 0
B70: Total Done | C70: No | D70: =D68+D69 -> 9 | E70: =E68+E69 -> 16 | F70: =F68+F69 -> 24 | G70: =G68+G69 -> 10 | H70: =H68+H69 -> 25 | I70: =I68+I69 -> 23 | J70: =J68+J69 -> 19 | K70: =K68+K69 -> 13 | ... P70: =P68+P69 -> 194
B71: Carried Forward | C71: No | D71: =D66+D67-D70 -> 48 | E71: =E66+E67-E70 -> 49 | F71: =F66+F67-F70 -> 41 | G71: =G66+G67-G70 -> 44 | H71: =H66+H67-H70 -> 51 | I71: =I66+I67-I70 -> 53 | J71: =J66+J67-J70 -> 55 | K71: =K66+K67-K70 -> 53 | ... P71: =P66+P67-P70 -> 49
A72: New Institutional Water Connections | B72: Brought Forward | C72: No | D72: 3 | E72: 4 | F72: 4 | G72: 4 | H72: 4 | I72: 4 | J72: 4 | K72: 4 | L72: 3 | M72: 3 | N72: 3 | O72: 3 | P72: =D72 -> 3
B73: Applied this Month | C73: No | D73: 1 | E73: 0 | F73: 0 | G73: 0 | H73: 0 | I73: 0 | J73: 0 | K73: 0 | L73: 0 | M73: 0 | N73: 0 | O73: 0 | P73: =SUM(D73:O73) -> 1
B74: Done this Month Postpaid | C74: No | D74: 0 | E74: 0 | F74: 0 | G74: 0 | H74: 0 | I74: 0 | J74: 0 | K74: 1 | L74: 0 | M74: 0 | N74: 0 | O74: 1 | P74: =SUM(D74:O74) -> 2
B75: Done this Month Prepaid | C75: No | D75: 0 | E75: 0 | F75: 0 | G75: 0 | H75: 0 | I75: 0 | J75: 0 | K75: 0 | L75: 0 | M75: 0 | N75: 0 | O75: 0 | P75: =SUM(D75:O75) -> 0
B76: Total Done | C76: No | D76: =D74+D75 -> 0 | E76: =E74+E75 -> 0 | F76: =F74+F75 -> 0 | G76: =G74+G75 -> 0 | H76: =H74+H75 -> 0 | I76: =I74+I75 -> 0 | J76: =J74+J75 -> 0 | K76: =K74+K75 -> 1 | ... P76: =P74+P75 -> 2
B77: Carried Forward | C77: No | D77: =D72+D73-D76 -> 4 | E77: =E72+E73-E76 -> 4 | F77: =F72+F73-F76 -> 4 | G77: =G72+G73-G76 -> 4 | H77: =H72+H73-H76 -> 4 | I77: =I72+I73-I76 -> 4 | J77: =J72+J73-J76 -> 4 | K77: =K72+K73-K76 -> 3 | ... P77: =P72+P73-P76 -> 2
A78: New Commercial/Industrial Water Connections | B78: Brought Forward | C78: No | D78: 3 | E78: 4 | F78: 4 | G78: 4 | H78: 4 | I78: 4 | J78: 4 | K78: 4 | L78: 3 | M78: 3 | N78: 4 | O78: 4 | P78: =D78 -> 3
B79: Applied this Month | C79: No | D79: 1 | E79: 1 | F79: 0 | G79: 0 | H79: 0 | I79: 0 | J79: 0 | K79: 0 | L79: 0 | M79: 1 | N79: 1 | O79: 0 | P79: =SUM(D79:O79) -> 4
B80: Done this Month Postpaid | C80: No | D80: 0 | E80: 1 | F80: 0 | G80: 0 | H80: 0 | I80: 0 | J80: 0 | K80: 1 | L80: 0 | M80: 0 | N80: 1 | O80: 0 | P80: =SUM(D80:O80) -> 3
B81: Done this Month Prepaid | C81: No | D81: 0 | E81: 0 | F81: 0 | G81: 0 | H81: 0 | I81: 0 | J81: 0 | K81: 0 | L81: 0 | M81: 0 | N81: 0 | O81: 0 | P81: =SUM(D81:O81) -> 0
B82: Total Done | C82: No | D82: =D80+D81 -> 0 | E82: =E80+E81 -> 1 | F82: =F80+F81 -> 0 | G82: =G80+G81 -> 0 | H82: =H80+H81 -> 0 | I82: =I80+I81 -> 0 | J82: =J80+J81 -> 0 | K82: =K80+K81 -> 1 | ... O82: =O80+O81 -> 0 | P82: =P81+P80 -> 3
B83: Carried Forward | C83: No | D83: =D78+D79-D82 -> 4 | E83: =E78+E79-E82 -> 4 | F83: =F78+F79-F82 -> 4 | G83: =G78+G79-G82 -> 4 | H83: =H78+H79-H82 -> 4 | I83: =I78+I79-I82 -> 4 | J83: =J78+J79-J82 -> 4 | K83: =K78+K79-K82 -> 3 | ... P83: =P78+P79-P82 -> 4
A84: New CWP | B84: Brought Forward | C84: No | D84: 0 | E84: 0 | F84: 0 | G84: 0 | H84: 0 | I84: 0 | J84: 0 | K84: 0 | L84: 0 | M84: 0 | N84: 0 | O84: 0 | P84: =D84 -> 0
B85: Applied this Month | C85: No | D85: 0 | E85: 0 | F85: 0 | G85: 0 | H85: 0 | I85: 0 | J85: 0 | K85: 0 | L85: 0 | M85: 0 | N85: 0 | O85: 0 | P85: =SUM(D85:O85) -> 0
B86: Done this Month Postpaid | C86: No | D86: 0 | E86: 0 | F86: 0 | G86: 0 | H86: 0 | I86: 0 | J86: 0 | K86: 0 | L86: 0 | M86: 0 | N86: 0 | O86: 0 | P86: =SUM(D86:O86) -> 0
B87: Done this Month Prepaid | C87: No | D87: 0 | E87: 0 | F87: 0 | G87: 0 | H87: 0 | I87: 0 | J87: 0 | K87: 0 | L87: 0 | M87: 0 | N87: 0 | O87: 0 | P87: =SUM(D87:O87) -> 0
B88: Total Done | C88: No | D88: =D86+D87 -> 0 | E88: =E86+E87 -> 0 | F88: =F86+F87 -> 0 | G88: =G86+G87 -> 0 | H88: =H86+H87 -> 0 | I88: =I86+I87 -> 0 | J88: =J86+J87 -> 0 | K88: =K86+K87 -> 0 | ... O88: =O86+O87 -> 0 | P88: =SUM(D88:O88) -> 0
B89: Carried Forward | C89: No | D89: =D84+D85-D88 -> 0 | E89: =E84+E85-E88 -> 0 | F89: =F84+F85-F88 -> 0 | G89: =G84+G85-G88 -> 0 | H89: =H84+H85-H88 -> 0 | I89: =I84+I85-I88 -> 0 | J89: =J84+J85-J88 -> 0 | K89: =K84+K85-K88 -> 0 | ... O89: =O84+O85-O88 -> 0 | P89: =P84+P85-P86-P87 -> 0
A90: Aggregated New Water connections | B90: Brought Forward | C90: No | D90: =D66+D72+D78+D84 -> 50 | E90: =E66+E72+E78+E84 -> 56 | F90: =F66+F72+F78+F84 -> 57 | G90: =G66+G72+G78+G84 -> 49 | H90: =H66+H72+H78+H84 -> 52 | I90: =I66+I72+I78+I84 -> 59 | J90: =J66+J72+J78+J84 -> 61 | K90: =K66+K72+K78+K84 -> 63 | ... O90: =O66+O72+O78+O84 -> 59 | P90: =D90 -> 50
B91: Applied this Month | C91: No | D91: =D67+D73+D79+D85 -> 15 | E91: =E67+E73+E79+E85 -> 18 | F91: =F67+F73+F79+F85 -> 16 | G91: =G67+G73+G79+G85 -> 13 | H91: =H67+H73+H79+H85 -> 32 | I91: =I67+I73+I79+I85 -> 25 | J91: =J67+J73+J79+J85 -> 21 | K91: =K67+K73+K79+K85 -> 11 | ... O91: =O67+O73+O79+O85 -> 11 | P91: =SUM(D91:O91) -> 204
B92: Done this Month Postpaid | C92: No | D92: =D68+D74+D80+D86 -> 9 | E92: =E68+E74+E80+E86 -> 17 | F92: =F68+F74+F80+F86 -> 24 | G92: =G68+G74+G80+G86 -> 10 | H92: =H68+H74+H80+H86 -> 25 | I92: =I68+I74+I80+I86 -> 23 | J92: =J68+J74+J80+J86 -> 19 | K92: =K68+K74+K80+K86 -> 15 | ... O92: =O68+O74+O80+O86 -> 15 | P92: =SUM(D92:O92) -> 199
B93: Done this Month Prepaid | D93: =D69+D75+D81+D87 -> 0 | E93: =E69+E75+E81+E87 -> 0 | F93: =F69+F75+F81+F87 -> 0 | G93: =G69+G75+G81+G87 -> 0 | H93: =H69+H75+H81+H87 -> 0 | I93: =I69+I75+I81+I87 -> 0 | J93: =J69+J75+J81+J87 -> 0 | K93: =K69+K75+K81+K87 -> 0 | ... O93: =O69+O75+O81+O87 -> 0 | P93: =SUM(D93:O93) -> 0
B94: Total Done | C94: No | D94: =D93+D92 -> 9 | E94: =E93+E92 -> 17 | F94: =F93+F92 -> 24 | G94: =G93+G92 -> 10 | H94: =H93+H92 -> 25 | I94: =I93+I92 -> 23 | J94: =J93+J92 -> 19 | K94: =K93+K92 -> 15 | ... P94: =P93+P92 -> 199
B95: Carried Forward | C95: No | D95: =D90+D91-D94 -> 56 | E95: =E90+E91-E94 -> 57 | F95: =F90+F91-F94 -> 49 | G95: =G90+G91-G94 -> 52 | H95: =H90+H91-H94 -> 59 | I95: =I90+I91-I94 -> 61 | J95: =J90+J91-J94 -> 63 | K95: =K90+K91-K94 -> 59 | ... P95: =P90+P91-P94 -> 55
A97: Prepaid Metering
A98: Prepaid Meters Installed | C98: No | D98: 0 | E98: 0 | F98: 0 | G98: 0 | H98: 0 | I98: 6 | J98: 0 | K98: 0 | L98: 0 | M98: 0 | N98: 0 | O98: 0 | P98: =SUM(D98:O98) -> 6
A100: Active and Disconnected Accounts
A101: Disconnected Individual Accounts | C101: No | D101: 691 | E101: 682 | F101: 662 | G101: 667 | H101: 661 | I101: 647 | J101: 648 | K101: 647 | L101: 644 | M101: 701 | N101: 686 | O101: 698 | P101: =O101 -> 698
A102: Disconnected institutional Accounts | C102: No | D102: 11 | E102: 12 | F102: 7 | G102: 9 | H102: 9 | I102: 9 | J102: 8 | K102: 8 | L102: 7 | M102: 9 | N102: 9 | O102: 9 | P102: =O102 -> 9
A103: Disconnected Commercial/Industrial Accounts | C103: No | D103: 0 | E103: 0 | F103: 5 | G103: 2 | H103: 2 | I103: 3 | J103: 2 | K103: 5 | L103: 6 | M103: 10 | N103: 7 | O103: 6 | P103: =O103 -> 6
A104: Disconnected CWP | C104: No | D104: 4 | E104: 4 | F104: 5 | G104: 5 | H104: 5 | I104: 5 | J104: 5 | K104: 5 | L104: 5 | M104: 5 | N104: 5 | O104: 5 | P104: =O104 -> 5
A105: Total Disconnected Accounts | C105: No | D105: =SUM(D101:D104) -> 706 | E105: =SUM(E101:E104) -> 698 | F105: =SUM(F101:F104) -> 679 | G105: =SUM(G101:G104) -> 683 | H105: =SUM(H101:H104) -> 677 | I105: =SUM(I101:I104) -> 664 | J105: =SUM(J101:J104) -> 663 | K105: =SUM(K101:K104) -> 665 | ... O105: =SUM(O101:O104) -> 718 | P105: =O105 -> 718
A106: Postpaid Consumers
...

Sheet Namadzi
A1: SOUTHERN REGION WATER BOARD
A3: MONTHLY REPORTS - 2024/2025
A4: ZOMBA ZONE
A5: NAMADZI SCHEME
A7: PARAMETERS | C7: UNITS | D7: APRIL | E7: MAY | F7: JUNE | G7: JULY | H7: AUGUST | I7: SEPTEMBER | J7: OCTOBER | K7: NOVEMBER | L7: DECEMBER | M7: JANUARY | N7: FEBRUARY | O7: MARCH | P7: TOTALS
A8: PRODUCTION
A9: Volume Produced | C9: m3 | D9: 4801 | E9: 5121 | F9: 13858 | G9: 5365 | H9: 10578 | I9: 5471 | J9: 5574 | K9: 10290 | L9: 4872 | M9: 9496 | N9: 4237 | O9: 3933 | P9: =SUM(D9:O9) -> 83596
A10: REVENUE WATER - POSTPAID
A11: Volume Billed Individuals | C11: m3 | D11: 1794 | E11: 2354 | F11: 2259 | G11: 2595 | H11: 2604 | I11: 2718 | J11: 2577 | K11: 2489 | L11: 2630 | M11: 1878 | N11: 1922 | O11: 1828 | P11: =SUM(D11:O11) -> 27648
A12: Volume Billed CWPs | C12: m3 | D12: 51 | E12: 59 | F12: 53 | G12: 52 | H12: 100 | I12: 80 | J12: 71 | K12: 63 | L12: 4 | M12: 4 | N12: 4 | O12: 4 | P12: =SUM(D12:O12) -> 545
A13: Volume Billed Institutions | C13: m3 | D13: 68 | E13: 56 | F13: 56 | G13: 514 | H13: 505 | I13: 454 | J13: 445 | K13: 445 | L13: 337 | M13: 190 | N13: 122 | O13: 172 | P13: =SUM(D13:O13) -> 3364
A14: Volume Billed Commercial/Industrial | C14: m3 | D14: 7 | E14: 11 | F14: 9 | G14: 10 | H14: 8 | I14: 12 | J14: 9 | K14: 16 | L14: 36 | M14: 31 | N14: 25 | O14: 8 | P14: =SUM(D14:O14) -> 182
A15: Total Volume Billed Post Paid | C15: m3 | D15: =SUM(D11:D14) -> 1920 | E15: =SUM(E11:E14) -> 2480 | F15: =SUM(F11:F14) -> 2377 | G15: =SUM(G11:G14) -> 3171 | H15: =SUM(H11:H14) -> 3217 | I15: =SUM(I11:I14) -> 3264 | J15: =SUM(J11:J14) -> 3102 | K15: =SUM(K11:K14) -> 3013 | ... P15: =SUM(P11:P14) -> 31739
A16: REVENUE WATER - PREPAID
A17: Individuals | C17: m3 | D17: 1230.7 | E17: 791 | F17: 3082.7 | G17: 797.4 | H17: 633.7 | I17: 743.7 | J17: 630.7 | K17: 595.5 | L17: 781.3 | M17: 1303.6 | N17: 561.4 | O17: 642.3 | P17: =SUM(D17:O17) -> 11794
A18: CWPs | C18: m3 | D18: 0 | E18: 0 | F18: 0 | G18: 0 | H18: 0 | I18: 0 | J18: 0 | K18: 0 | L18: 36.2 | M18: 18.8 | N18: 18.8 | O18: 3.8 | P18: =SUM(D18:O18) -> 77.6
A19: Institutions | C19: m3 | D19: 289.1 | E19: 441.3 | F19: 6081.4 | G19: 416.1 | H19: 5824.2 | I19: 987.1 | J19: 1391.1 | K19: 5536.4 | L19: 542.9 | M19: 5707.4 | N19: 520 | O19: 839.8 | P19: =SUM(D19:O19) -> 28576.8
A20: Commercial/Industrial | C20: m3 | D20: 32.9 | E20: 30.3 | F20: 43.9 | G20: 18.3 | H20: 26.9 | I20: 25.1 | J20: 35 | K20: 23.9 | L20: 24.2 | M20: 27.7 | N20: 23.1 | O20: 34.5 | P20: =SUM(D20:O20) -> 345.8
A21: Total Volume Prepaid | C21: m3 | D21: =SUM(D17:D20) -> 1552.7 | E21: =SUM(E17:E20) -> 1262.6 | F21: =SUM(F17:F20) -> 9208 | G21: =SUM(G17:G20) -> 1231.8 | H21: =SUM(H17:H20) -> 6484.8 | I21: =SUM(I17:I20) -> 1755.9 | J21: =SUM(J17:J20) -> 2056.8 | K21: =SUM(K17:K20) -> 6155.8 | ... P21: =SUM(P17:P20) -> 40794.2
A22: TOTAL REVENUE WATER | C22: m3 | D22: =D21+D15 -> 3472.7 | E22: =E21+E15 -> 3742.6 | F22: =F21+F15 -> 11585 | G22: =G21+G15 -> 4402.8 | H22: =H21+H15 -> 9701.8 | I22: =I21+I15 -> 5019.9 | J22: =J21+J15 -> 5158.8 | K22: =K21+K15 -> 9168.8 | ... P22: =P21+P15 -> 72533.2
A24: Non-Revenue Water (NRW) | B24: Volume | C24: m3 | D24: =D9-D22 -> 1328.3 | E24: =E9-E22 -> 1378.4 | F24: =F9-F22 -> 2273 | G24: =G9-G22 -> 962.2 | H24: =H9-H22 -> 876.2 | I24: =I9-I22 -> 451.1 | J24: =J9-J22 -> 415.2 | K24: =K9-K22 -> 1121.2 | ... P24: =P9-P22 -> 11062.8
B25: Percentage | C25: % | D25: =IFERROR(D24/D9,0) -> 0.27667153 | E25: =E24/E9 -> 0.26916618 | F25: =F24/F9 -> 0.16402078 | G25: =IFERROR(G24/G9,0) -> 0.17934762 | H25: =IFERROR(H24/H9,0) -> 0.082832293 | I25: =IFERROR(I24/I9,0) -> 0.082452934 | J25: =IFERROR(J24/J9,0) -> 0.074488698 | K25: =IFERROR(K24/K9,0) -> 0.10896016 | L25: =IFERROR(L24/L9,0) -> 0.098604269 | M25: =IFERROR(M24/M9,0) -> 0.035330666 | N25: =IFERROR(N24/N9,0) -> 0.2456219 | O25: =IFERROR(O24/O9,0) -> 0.10185609 | P25: =IF(P9,P24/P9,"") -> 0.13233648
A26: OPERATING EXPENSES
A27: Chemicals
A28: Chemical | B28: Rate(MK/kg)
A29: Chlorine | B29: 7400 | C29: kg | D29: 4 | E29: 4 | F29: 5 | G29: 3.25 | H29: 3.5 | I29: 4.25 | J29: 3.25 | K29: 5 | L29: 5 | M29: 5 | N29: 5 | O29: 5 | P29: =SUM(D29:O29) -> 52.25
C30: kg/mg litre | D30: =IFERROR(D29/(D9/1000),0) -> 0.83315976 | E30: =IFERROR(E29/(E9/1000),0) -> 0.78109744 | F30: =IFERROR(F29/(F9/1000),0) -> 0.36080242 | G30: =IFERROR(G29/(G9/1000),0) -> 0.60577819 | H30: =IFERROR(H29/(H9/1000),0) -> 0.3308754 | I30: =IFERROR(I29/(I9/1000),0) -> 0.77682325 | J30: =IFERROR(J29/(J9/1000),0) -> 0.58306423 | K30: =IFERROR(K29/(K9/1000),0) -> 0.48590865 | ... P30: =IFERROR(P29/(P9/1000),0) -> 0.62502991
A31: Aluminium sulphate | B31: 1900 | C31: kg | D31: 0 | E31: 0 | F31: 0 | G31: 0 | H31: 0 | I31: 0 | J31: 0 | K31: 0 | L31: 0 | M31: 0 | N31: 0 | O31: 0 | P31: =SUM(D31:O31) -> 0
C32: kg/mg litre | D32: =IFERROR(D31/(D9/1000),0) -> 0 | E32: =IFERROR(E31/(E9/1000),0) -> 0 | F32: =IFERROR(F31/(F9/1000),0) -> 0 | G32: =IFERROR(G31/(G9/1000),0) -> 0 | H32: =IFERROR(H31/(H9/1000),0) -> 0 | I32: =IFERROR(I31/(I9/1000),0) -> 0 | J32: =IFERROR(J31/(J9/1000),0) -> 0 | K32: =IFERROR(K31/(K9/1000),0) -> 0 | ... P32: =IFERROR(P31/(P9/1000),0) -> 0
A33: Soda | B33: 1900 | C33: kg | D33: 0 | E33: 0 | F33: 0 | G33: 0 | H33: 0 | I33: 0 | J33: 0 | K33: 0 | L33: 0 | M33: 0 | N33: 0 | O33: 0 | P33: =SUM(D33:O33) -> 0
C34: kg/mg litre | D34: =IFERROR(D33/(D9/1000),0) -> 0 | E34: =IFERROR(E33/(E9/1000),0) -> 0 | F34: =IFERROR(F33/(F9/1000),0) -> 0 | G34: =IFERROR(G33/(G9/1000),0) -> 0 | H34: =IFERROR(H33/(H9/1000),0) -> 0 | I34: =IFERROR(I33/(I9/1000),0) -> 0 | J34: =IFERROR(J33/(J9/1000),0) -> 0 | K34: =IFERROR(K33/(K9/1000),0) -> 0 | ... P34: =IFERROR(P33/(P9/1000),0) -> 0
A35: Algae floc | B35: =745345.16/200 -> 3726.7258 | C35: litres | D35: 0 | E35: 0 | F35: 0 | G35: 0 | H35: 0 | I35: 0 | J35: 0 | K35: 0 | L35: 0 | M35: 0 | N35: 0 | O35: 0
C36: litres/mg litre
A37: Sud floc | B37: =790318.72/200 -> 3951.5936 | C37: litres | D37: 0 | E37: 0 | F37: 0 | G37: 0 | H37: 0 | I37: 0 | J37: 0 | K37: 0 | L37: 0 | M37: 0 | N37: 0 | O37: 0 | P37: =SUM(D37:O37) -> 0
C38: litres/mg litre | D38: =IFERROR(D37/(D9/1000),0) -> 0 | E38: =IFERROR(E37/(E9/1000),0) -> 0 | F38: =IFERROR(F37/(F9/1000),0) -> 0 | G38: =IFERROR(G37/(G9/1000),0) -> 0 | H38: =IFERROR(H37/(H9/1000),0) -> 0 | I38: =IFERROR(I37/(I9/1000),0) -> 0 | J38: =IFERROR(J37/(J9/1000),0) -> 0 | K38: =IFERROR(K37/(K9/1000),0) -> 0 | ... P38: =IFERROR(P37/(P9/1000),0) -> 0
A39: Potasium permanganate | B39: 1950 | C39: kg | D39: 0 | E39: 0 | F39: 0 | G39: 0 | H39: 0 | I39: 0 | J39: 0 | K39: 0 | L39: 0 | M39: 0 | N39: 0 | O39: 0 | P39: =SUM(D39:O39) -> 0
C40: kg/mg litre | D40: =IFERROR(D39/(D9/1000),0) -> 0 | E40: =IFERROR(E39/(E9/1000),0) -> 0 | F40: =IFERROR(F39/(F9/1000),0) -> 0 | G40: =IFERROR(G39/(G9/1000),0) -> 0 | H40: =IFERROR(H39/(H9/1000),0) -> 0 | I40: =IFERROR(I39/(I9/1000),0) -> 0 | J40: =IFERROR(J39/(J9/1000),0) -> 0 | K40: =IFERROR(K39/(K9/1000),0) -> 0 | ... P40: =IFERROR(P39/(P9/1000),0) -> 0
A41: Cost of Chemicals | C41: Mk | D41: =(D29*$B29)+(D31*$B31)+(D33*$B33)+(D35*$B35)+(D37*$B37)+(D39*$B39) -> 29600 | E41: =(E29*$B29)+(E31*$B31)+(E33*$B33)+(E35*$B35)+(E37*$B37)+(E39*$B39) -> 29600 | F41: =(F29*$B29)+(F31*$B31)+(F33*$B33)+(F35*$B35)+(F37*$B37)+(F39*$B39) -> 37000 | G41: =(G29*$B29)+(G31*$B31)+(G33*$B33)+(G35*$B35)+(G37*$B37)+(G39*$B39) -> 24050 | H41: =(H29*$B29)+(H31*$B31)+(H33*$B33)+(H35*$B35)+(H37*$B37)+(H39*$B39) -> 25900 | I41: =(I29*$B29)+(I31*$B31)+(I33*$B33)+(I35*$B35)+(I37*$B37)+(I39*$B39) -> 31450 | J41: =(J29*$B29)+(J31*$B31)+(J33*$B33)+(J35*$B35)+(J37*$B37)+(J39*$B39) -> 24050 | K41: =(K29*$B29)+(K31*$B31)+(K33*$B33)+(K35*$B35)+(K37*$B37)+(K39*$B39) -> 37000 | ... O41: =(O29*$B29)+(O31*$B31)+(O33*$B33)+(O35*$B35)+(O37*$B37)+(O39*$B39) -> 37000 | P41: =SUM(D41:O41) -> 386650
A42: Cost/vol. Produced (chemicals) | C42: Mk/m3 | D42: =IFERROR(D41/D9,0) -> 6.1653822 | E42: =IFERROR(E41/E9,0) -> 5.7801211 | F42: =IFERROR(F41/F9,0) -> 2.6699379 | G42: =IFERROR(G41/G9,0) -> 4.4827586 | H42: =IFERROR(H41/H9,0) -> 2.448478 | I42: =IFERROR(I41/I9,0) -> 5.748492 | J42: =IFERROR(J41/J9,0) -> 4.3146753 | K42: =IFERROR(K41/K9,0) -> 3.595724 | ... P42: =IFERROR(P41/P9,0) -> 4.6252213
A43: Power
A44: Power Usage | C44: Kw | D44: 3221.45 | E44: 3609.13 | F44: 3366.25 | G44: 3709.82 | H44: 7130.45 | I44: 4727.62 | J44: 3748.62 | K44: 3114.25 | L44: 3065.16 | M44: 2829.66 | N44: 3403.98 | O44: 3477.88 | P44: =SUM(D44:O44) -> 45404.27
A45: Power/ Vol. Produced | C45: Kw/m3 | D45: =IFERROR(D44/D9,0) -> 0.67099563 | E45: =IFERROR(E44/E9,0) -> 0.70477055 | F45: =IFERROR(F44/F9,0) -> 0.24291023 | G45: =IFERROR(G44/G9,0) -> 0.69148555 | H45: =IFERROR(H44/H9,0) -> 0.674083 | I45: =IFERROR(I44/I9,0) -> 0.86412356 | J45: =IFERROR(J44/J9,0) -> 0.67251884 | K45: =IFERROR(K44/K9,0) -> 0.3026482 | ... P45: =IFERROR(P44/P9,0) -> 0.54313927
A46: Cost of Power | C46: Mk | D46: =IF(D44=0,0,IF(D44>=0,0+(D44*202.25)+23390)*1.165) -> 786291.43 | E46: =IF(E44=0,0,IF(E44>=0,0+(E44*202.25)+23390)*1.165) -> 877637.07 | F46: =IF(F44=0,0,IF(F44>=0,0+(F44*202.25)+23390)*1.165) -> 820409.38 | G46: =IF(G44=0,0,IF(G44>=0,0+(G44*202.25)+23390)*1.165) -> 901361.78 | H46: =IF(H44=0,0,IF(H44>=0,0+(H44*202.25)+23390)*1.165) -> 1707334.9 | I46: =IF(I44=0,0,IF(I44>=0,0+(I44*202.25)+23390)*1.165) -> 1141177.1 | J46: =IF(J44=0,0,IF(J44>=0,0+(J44*202.25)+23390)*1.165) -> 910503.88 | K46: =IF(K44=0,0,IF(K44>=0,0+(K44*202.25)+23390)*1.165) -> 761032.83 | ... O46: =IF(O44=0,0,IF(O44>=0,0+(O44*202.25)+23390)*1.165) -> 846711.78 | P46: =SUM(D46:O46) -> 11025203
A47: Cost/vol. Produced | C47: Mk/m3 | D47: =IFERROR(D46/D9,0) -> 163.77659 | E47: =IFERROR(E46/E9,0) -> 171.38002 | F47: =IFERROR(F46/F9,0) -> 59.201139 | G47: =IFERROR(G46/G9,0) -> 168.00779 | H47: =IFERROR(H46/H9,0) -> 161.40432 | I47: =IFERROR(I46/I9,0) -> 208.58656 | J47: =IFERROR(J46/J9,0) -> 163.34838 | K47: =IFERROR(K46/K9,0) -> 73.958487 | ... P47: =IFERROR(P46/P9,0) -> 131.88673
A48: Plant and Vehicle Maintenance
A49: Distances covered | C49: km | D49: 0 | E49: 0 | F49: 0 | G49: 0 | H49: 0 | I49: 0 | J49: 0 | K49: 0 | L49: 0 | M49: 0 | N49: 0 | O49: 0 | P49: =SUM(D49:O49) -> 0
A50: Fuel Used (litres) | C50: litres | D50: 0 | E50: 0 | F50: 0 | G50: 0 | H50: 0 | I50: 0 | J50: 0 | K50: 0 | L50: 0 | M50: 0 | N50: 0 | O50: 0 | P50: =SUM(D50:O50) -> 0
A51: Cost of fuel | C51: Mk | D51: 0 | E51: 0 | F51: 0 | G51: 0 | H51: 0 | I51: 0 | J51: 0 | K51: 0 | L51: 0 | M51: 0 | N51: 0 | O51: 0 | P51: =SUM(D51:O51) -> 0
A52: Maintenance | C52: Mk | D52: 0 | E52: 0 | F52: 0 | G52: 0 | H52: 0 | I52: 0 | J52: 0 | K52: 0 | L52: 0 | M52: 0 | N52: 0 | O52: 0 | P52: =SUM(D52:O52) -> 0
A53: Salaries and Wages
A54: Staff Costs | C54: MK | D54: 0 | E54: 0 | F54: 0 | G54: 0 | H54: 0 | I54: 0 | J54: 0 | K54: 0 | L54: 0 | M54: 0 | N54: 0 | O54: 0 | P54: =SUM(D54:O54) -> 0
A55: Wages | C55: MK | D55: 0 | E55: 0 | F55: 0 | G55: 0 | H55: 0 | I55: 0 | J55: 0 | K55: 0 | L55: 0 | M55: 0 | N55: 0 | O55: 0 | P55: =SUM(D55:O55) -> 0
A56: Other Overhead Costs | C56: MK | D56: 0 | E56: 0 | F56: 0 | G56: 0 | H56: 0 | I56: 0 | J56: 0 | K56: 0 | L56: 0 | M56: 0 | N56: 0 | O56: 0 | P56: =SUM(D56:O56) -> 0
A57: Operating Costs
A58: Total Operating Costs | C58: MK | D58: =D41+D46+D51+D52+D54+D55+D56 -> 815891.43 | E58: =E41+E46+E51+E52+E54+E55+E56 -> 907237.07 | F58: =F41+F46+F51+F52+F54+F55+F56 -> 857409.38 | G58: =G41+G46+G51+G52+G54+G55+G56 -> 925411.78 | H58: =H41+H46+H51+H52+H54+H55+H56 -> 1733234.9 | I58: =I41+I46+I51+I52+I54+I55+I56 -> 1172627.1 | J58: =J41+J46+J51+J52+J54+J55+J56 -> 934553.88 | K58: =K41+K46+K51+K52+K54+K55+K56 -> 798032.83 | ... O58: =O41+O46+O51+O52+O54+O55+O56 -> 883711.78 | P58: =SUM(D58:O58) -> 11411853
A59: Cost/Vol. Produced | C59: Mk/m3 | D59: =IFERROR(D58/D9,0) -> 169.94198 | E59: =IFERROR(E58/E9,0) -> 177.16014 | F59: =IFERROR(F58/F9,0) -> 61.871077 | G59: =IFERROR(G58/G9,0) -> 172.49055 | H59: =IFERROR(H58/H9,0) -> 163.8528 | I59: =IFERROR(I58/I9,0) -> 214.33505 | J59: =IFERROR(J58/J9,0) -> 167.66306 | K59: =IFERROR(K58/K9,0) -> 77.554211 | ... P59: =IFERROR(P58/P9,0) -> 136.51195
A60: Cost/Vol. Billed | C60: Mk/m3 | D60: =IFERROR(D58/D22,0) -> 234.9444 | E60: =IFERROR(E58/E22,0) -> 242.40824 | F60: =IFERROR(F58/F22,0) -> 74.010305 | G60: =IFERROR(G58/G22,0) -> 210.1871 | H60: =IFERROR(H58/H22,0) -> 178.65086 | I60: =IFERROR(I58/I22,0) -> 233.59571 | J60: =IFERROR(J58/J22,0) -> 181.15722 | K60: =IFERROR(K58/K22,0) -> 87.037871 | ... P60: =IFERROR(P58/P22,0) -> 157.33282
A61: Permanent Staff Employed | C61: No | D61: 5 | E61: 5 | F61: 5 | G61: 5 | H61: 5 | I61: 5 | J61: 5 | K61: 5 | L61: 5 | M61: 5 | N61: 5 | O61: 5 | P61: =O61 -> 5
A62: Staff/Vol.1000m3 of Volume Produced/hour (12 hour day) | C62: No/1000m3 | D62: =IFERROR((D61*1000*31)/D9,0) -> 32.284941 | E62: =IFERROR((E61*1000*31)/E9,0) -> 30.267526 | F62: =IFERROR((F61*1000*31)/F9,0) -> 11.184875 | G62: =IFERROR((G61*1000*31)/G9,0) -> 28.89096 | H62: =IFERROR((H61*1000*31)/H9,0) -> 14.653054 | I62: =IFERROR((I61*1000*31)/I9,0) -> 28.331201 | J62: =IFERROR((J61*1000*31)/J9,0) -> 27.807679 | K62: =IFERROR((K61*1000*31)/K9,0) -> 15.063168 | ... P62: =IFERROR((P61*1000*31)/P9,0) -> 1.8541557
A63: Temporary Staff Employed | C63: No | D63: 6 | E63: 6 | F63: 6 | G63: 6 | H63: 6 | I63: 6 | J63: 6 | K63: 6 | L63: 6 | M63: 5 | N63: 5 | O63: 5 | P63: =O63 -> 5
A65: Water Connections and Disconnections
A66: New Individual Water Connections | B66: Brought Forward | C66: No | D66: 72 | E66: 72 | F66: 68 | G66: 68 | H66: 68 | I66: 66 | J66: 63 | K66: 62 | L66: 60 | M66: 58 | N66: 58 | O66: 58 | P66: =D66 -> 72
B67: Applied this Month | C67: No | D67: 0 | E67: 0 | F67: 0 | G67: 0 | H67: 0 | I67: 0 | J67: 0 | K67: 0 | L67: 0 | M67: 0 | N67: 0 | O67: 0 | P67: =SUM(D67:O67) -> 0
B68: Done this Month Postpaid | C68: No | D68: 0 | E68: 4 | F68: 0 | G68: 0 | H68: 2 | I68: 3 | J68: 1 | K68: 2 | L68: 2 | M68: 0 | N68: 0 | O68: 2 | P68: =SUM(D68:O68) -> 16
B69: Done this Month Prepaid | C69: No | D69: 0 | E69: 0 | F69: 0 | G69: 0 | H69: 0 | I69: 0 | J69: 0 | K69: 0 | L69: 0 | M69: 0 | N69: 0 | O69: 0 | P69: =SUM(D69:O69) -> 0
B70: Total Done | C70: No | D70: =D68+D69 -> 0 | E70: =E68+E69 -> 4 | F70: =F68+F69 -> 0 | G70: =G68+G69 -> 0 | H70: =H68+H69 -> 2 | I70: =I68+I69 -> 3 | J70: =J68+J69 -> 1 | K70: =K68+K69 -> 2 | ... P70: =P68+P69 -> 16
B71: Carried Forward | C71: No | D71: =D66+D67-D70 -> 72 | E71: =E66+E67-E70 -> 68 | F71: =F66+F67-F70 -> 68 | G71: =G66+G67-G70 -> 68 | H71: =H66+H67-H70 -> 66 | I71: =I66+I67-I70 -> 63 | J71: =J66+J67-J70 -> 62 | K71: =K66+K67-K70 -> 60 | ... P71: =P66+P67-P70 -> 56
A72: New Institutional Water Connections | B72: Brought Forward | C72: No | D72: 0 | E72: 0 | F72: 0 | G72: 0 | H72: 0 | I72: 0 | J72: 0 | K72: 0 | L72: 0 | M72: 0 | N72: 0 | O72: 0 | P72: =D72 -> 0
B73: Applied this Month | C73: No | D73: 0 | E73: 0 | F73: 0 | G73: 0 | H73: 0 | I73: 0 | J73: 0 | K73: 0 | L73: 0 | M73: 0 | N73: 0 | O73: 0 | P73: =SUM(D73:O73) -> 0
B74: Done this Month Postpaid | C74: No | D74: 0 | E74: 0 | F74: 0 | G74: 0 | H74: 0 | I74: 0 | J74: 0 | K74: 0 | L74: 0 | M74: 0 | N74: 0 | O74: 0 | P74: =SUM(D74:O74) -> 0
B75: Done this Month Prepaid | C75: No | D75: 0 | E75: 0 | F75: 0 | G75: 0 | H75: 0 | I75: 0 | J75: 0 | K75: 0 | L75: 0 | M75: 0 | N75: 0 | O75: 0 | P75: =SUM(D75:O75) -> 0
B76: Total Done | C76: No | D76: =D74+D75 -> 0 | E76: =E74+E75 -> 0 | F76: =F74+F75 -> 0 | G76: =G74+G75 -> 0 | H76: =H74+H75 -> 0 | I76: =I74+I75 -> 0 | J76: =J74+J75 -> 0 | K76: =K74+K75 -> 0 | ... P76: =P74+P75 -> 0
B77: Carried Forward | C77: No | D77: =D72+D73-D76 -> 0 | E77: =E72+E73-E76 -> 0 | F77: =F72+F73-F76 -> 0 | G77: =G72+G73-G76 -> 0 | H77: =H72+H73-H76 -> 0 | I77: =I72+I73-I76 -> 0 | J77: =J72+J73-J76 -> 0 | K77: =K72+K73-K76 -> 0 | ... P77: =P72+P73-P76 -> 0
A78: New Commercial/Industrial Water Connections | B78: Brought Forward | C78: No | D78: 0 | E78: 0 | F78: 0 | G78: 0 | H78: 0 | I78: 0 | J78: 0 | K78: 0 | L78: 0 | M78: 0 | N78: 0 | O78: 0 | P78: =D78 -> 0
B79: Applied this Month | C79: No | D79: 0 | E79: 0 | F79: 0 | G79: 0 | H79: 0 | I79: 0 | J79: 0 | K79: 0 | L79: 0 | M79: 0 | N79: 0 | O79: 0 | P79: =SUM(D79:O79) -> 0
B80: Done this Month Postpaid | C80: No | D80: 0 | E80: 0 | F80: 0 | G80: 0 | H80: 0 | I80: 0 | J80: 0 | K80: 0 | L80: 0 | M80: 0 | N80: 0 | O80: 0 | P80: =SUM(D80:O80) -> 0
B81: Done this Month Prepaid | C81: No | D81: 0 | E81: 0 | F81: 0 | G81: 0 | H81: 0 | I81: 0 | J81: 0 | K81: 0 | L81: 0 | M81: 0 | N81: 0 | O81: 0 | P81: =SUM(D81:O81) -> 0
B82: Total Done | C82: No | D82: =D80+D81 -> 0 | E82: =E80+E81 -> 0 | F82: =F80+F81 -> 0 | G82: =G80+G81 -> 0 | H82: =H80+H81 -> 0 | I82: =I80+I81 -> 0 | J82: =J80+J81 -> 0 | K82: =K80+K81 -> 0 | ... O82: =O80+O81 -> 0 | P82: =P81+P80 -> 0
B83: Carried Forward | C83: No | D83: =D78+D79-D82 -> 0 | E83: =E78+E79-E82 -> 0 | F83: =F78+F79-F82 -> 0 | G83: =G78+G79-G82 -> 0 | H83: =H78+H79-H82 -> 0 | I83: =I78+I79-I82 -> 0 | J83: =J78+J79-J82 -> 0 | K83: =K78+K79-K82 -> 0 | ... P83: =P78+P79-P82 -> 0
A84: New CWP | B84: Brought Forward | C84: No | D84: 0 | E84: 0 | F84: 0 | G84: 0 | H84: 0 | I84: 0 | J84: 0 | K84: 0 | L84: 0 | M84: 0 | N84: 0 | O84: 0 | P84: =D84 -> 0
B85: Applied this Month | C85: No | D85: 0 | E85: 0 | F85: 0 | G85: 0 | H85: 0 | I85: 0 | J85: 0 | K85: 0 | L85: 0 | M85: 0 | N85: 0 | O85: 0 | P85: =SUM(D85:O85) -> 0
B86: Done this Month Postpaid | C86: No | D86: 0 | E86: 0 | F86: 0 | G86: 0 | H86: 0 | I86: 0 | J86: 0 | K86: 0 | L86: 0 | M86: 0 | N86: 0 | O86: 0 | P86: =SUM(D86:O86) -> 0
B87: Done this Month Prepaid | C87: No | D87: 0 | E87: 0 | F87: 0 | G87: 0 | H87: 0 | I87: 0 | J87: 0 | K87: 0 | L87: 0 | M87: 0 | N87: 0 | O87: 0 | P87: =SUM(D87:O87) -> 0
B88: Total Done | C88: No | D88: =D86+D87 -> 0 | E88: =E86+E87 -> 0 | F88: =F86+F87 -> 0 | G88: =G86+G87 -> 0 | H88: =H86+H87 -> 0 | I88: =I86+I87 -> 0 | J88: =J86+J87 -> 0 | K88: =K86+K87 -> 0 | ... O88: =O86+O87 -> 0 | P88: =SUM(D88:O88) -> 0
B89: Carried Forward | C89: No | D89: =D84+D85-D88 -> 0 | E89: =E84+E85-E88 -> 0 | F89: =F84+F85-F88 -> 0 | G89: =G84+G85-G88 -> 0 | H89: =H84+H85-H88 -> 0 | I89: =I84+I85-I88 -> 0 | J89: =J84+J85-J88 -> 0 | K89: =K84+K85-K88 -> 0 | ... O89: =O84+O85-O88 -> 0 | P89: =P84+P85-P86-P87 -> 0
A90: Aggregated New Water connections | B90: Brought Forward | C90: No | D90: =D66+D72+D78+D84 -> 72 | E90: =E66+E72+E78+E84 -> 72 | F90: =F66+F72+F78+F84 -> 68 | G90: =G66+G72+G78+G84 -> 68 | H90: =H66+H72+H78+H84 -> 68 | I90: =I66+I72+I78+I84 -> 66 | J90: =J66+J72+J78+J84 -> 63 | K90: =K66+K72+K78+K84 -> 62 | ... O90: =O66+O72+O78+O84 -> 58 | P90: =D90 -> 72
B91: Applied this Month | C91: No | D91: =D67+D73+D79+D85 -> 0 | E91: =E67+E73+E79+E85 -> 0 | F91: =F67+F73+F79+F85 -> 0 | G91: =G67+G73+G79+G85 -> 0 | H91: =H67+H73+H79+H85 -> 0 | I91: =I67+I73+I79+I85 -> 0 | J91: =J67+J73+J79+J85 -> 0 | K91: =K67+K73+K79+K85 -> 0 | ... O91: =O67+O73+O79+O85 -> 0 | P91: =SUM(D91:O91) -> 0
B92: Done this Month Postpaid | C92: No | D92: =D68+D74+D80+D86 -> 0 | E92: =E68+E74+E80+E86 -> 4 | F92: =F68+F74+F80+F86 -> 0 | G92: =G68+G74+G80+G86 -> 0 | H92: =H68+H74+H80+H86 -> 2 | I92: =I68+I74+I80+I86 -> 3 | J92: =J68+J74+J80+J86 -> 1 | K92: =K68+K74+K80+K86 -> 2 | ... O92: =O68+O74+O80+O86 -> 2 | P92: =SUM(D92:O92) -> 16
B93: Done this Month Prepaid | D93: =D69+D75+D81+D87 -> 0 | E93: =E69+E75+E81+E87 -> 0 | F93: =F69+F75+F81+F87 -> 0 | G93: =G69+G75+G81+G87 -> 0 | H93: =H69+H75+H81+H87 -> 0 | I93: =I69+I75+I81+I87 -> 0 | J93: =J69+J75+J81+J87 -> 0 | K93: =K69+K75+K81+K87 -> 0 | ... O93: =O69+O75+O81+O87 -> 0 | P93: =SUM(D93:O93) -> 0
B94: Total Done | C94: No | D94: =D93+D92 -> 0 | E94: =E93+E92 -> 4 | F94: =F93+F92 -> 0 | G94: =G93+G92 -> 0 | H94: =H93+H92 -> 2 | I94: =I93+I92 -> 3 | J94: =J93+J92 -> 1 | K94: =K93+K92 -> 2 | ... P94: =P93+P92 -> 16
B95: Carried Forward | C95: No | D95: =D90+D91-D94 -> 72 | E95: =E90+E91-E94 -> 68 | F95: =F90+F91-F94 -> 68 | G95: =G90+G91-G94 -> 68 | H95: =H90+H91-H94 -> 66 | I95: =I90+I91-I94 -> 63 | J95: =J90+J91-J94 -> 62 | K95: =K90+K91-K94 -> 60 | ... P95: =P90+P91-P94 -> 56
A97: Prepaid Metering
A98: Prepaid Meters Installed | C98: No | D98: 0 | E98: 0 | F98: 0 | G98: 0 | H98: 0 | I98: 0 | J98: 0 | K98: 0 | L98: 0 | M98: 0 | N98: 0 | O98: 0 | P98: =SUM(D98:O98) -> 0
A100: Active and Disconnected Accounts
A101: Disconnected Individual Accounts | C101: No | D101: 195 | E101: 187 | F101: 219 | G101: 212 | H101: 211 | I101: 208 | J101: 205 | K101: 203 | L101: 204 | M101: 235 | N101: 234 | O101: 236 | P101: =O101 -> 236
A102: Disconnected institutional Accounts | C102: No | D102: 11 | E102: 11 | F102: 10 | G102: 9 | H102: 9 | I102: 9 | J102: 9 | K102: 9 | L102: 9 | M102: 10 | N102: 10 | O102: 10 | P102: =O102 -> 10
A103: Disconnected Commercial/Industrial Accounts | C103: No | D103: 12 | E103: 12 | F103: 11 | G103: 11 | H103: 11 | I103: 10 | J103: 11 | K103: 10 | L103: 10 | M103: 10 | N103: 10 | O103: 11 | P103: =O103 -> 11
A104: Disconnected CWP | C104: No | D104: 2 | E104: 2 | F104: 2 | G104: 2 | H104: 2 | I104: 2 | J104: 2 | K104: 2 | L104: 2 | M104: 2 | N104: 2 | O104: 2 | P104: =O104 -> 2
A105: Total Disconnected Accounts | C105: No | D105: =SUM(D101:D104) -> 220 | E105: =SUM(E101:E104) -> 212 | F105: =SUM(F101:F104) -> 242 | G105: =SUM(G101:G104) -> 234 | H105: =SUM(H101:H104) -> 233 | I105: =SUM(I101:I104) -> 229 | J105: =SUM(J101:J104) -> 227 | K105: =SUM(K101:K104) -> 224 | ... O105: =SUM(O101:O104) -> 259 | P105: =O105 -> 259
A106: Postpaid Consumers
...

Sheet Neno
A1: SOUTHERN REGION WATER BOARD
A3: MONTHLY REPORTS - 2024/2025
A4: ZOMBA ZONE
A5: NENO SCHEME
A7: PARAMETERS | C7: UNITS | D7: APRIL | E7: MAY | F7: JUNE | G7: JULY | H7: AUGUST | I7: SEPTEMBER | J7: OCTOBER | K7: NOVEMBER | L7: DECEMBER | M7: JANUARY | N7: FEBRUARY | O7: MARCH | P7: TOTALS
A8: PRODUCTION
A9: Volume Produced | C9: m3 | D9: 7850 | E9: 7498 | F9: 6853 | G9: 8661 | H9: 6451 | I9: 4841 | J9: 5051 | K9: 4845 | L9: 4765 | M9: 9861 | N9: 5335 | O9: 4682 | P9: =SUM(D9:O9) -> 76693
A10: REVENUE WATER - POSTPAID
A11: Volume Billed Individuals | C11: m3 | D11: 3973 | E11: 4298 | F11: 4278 | G11: 4672 | H11: 4633 | I11: 3337 | J11: 2884 | K11: 3209 | L11: 3360 | M11: 3725 | N11: 3938 | O11: 3242 | P11: =SUM(D11:O11) -> 45549
A12: Volume Billed CWPs | C12: m3 | D12: 30 | E12: 78 | F12: 41 | G12: 40 | H12: 34 | I12: 23 | J12: 23 | K12: 16 | L12: 29 | M12: 27 | N12: 20 | O12: 5 | P12: =SUM(D12:O12) -> 366
A13: Volume Billed Institutions | C13: m3 | D13: 87 | E13: 72 | F13: 55 | G13: 76 | H13: 102 | I13: 77 | J13: 62 | K13: 81 | L13: 105 | M13: 86 | N13: 91 | O13: 64 | P13: =SUM(D13:O13) -> 958
A14: Volume Billed Commercial/Industrial | C14: m3 | D14: 136 | E14: 182 | F14: 117 | G14: 112 | H14: 84 | I14: 71 | J14: 48 | K14: 65 | L14: 70 | M14: 67 | N14: 126 | O14: 105 | P14: =SUM(D14:O14) -> 1183
A15: Total Volume Billed Post Paid | C15: m3 | D15: =SUM(D11:D14) -> 4226 | E15: =SUM(E11:E14) -> 4630 | F15: =SUM(F11:F14) -> 4491 | G15: =SUM(G11:G14) -> 4900 | H15: =SUM(H11:H14) -> 4853 | I15: =SUM(I11:I14) -> 3508 | J15: =SUM(J11:J14) -> 3017 | K15: =SUM(K11:K14) -> 3371 | ... P15: =SUM(P11:P14) -> 48056
A16: REVENUE WATER - PREPAID
A17: Individuals | C17: m3 | D17: 895.7 | E17: 770.9 | F17: 658.9 | G17: 1942.2 | H17: 734.4 | I17: 501.6 | J17: 321.3 | K17: 526 | L17: 730.4 | M17: 648.3 | N17: 636.5 | O17: 579.1 | P17: =SUM(D17:O17) -> 8945.3
A18: CWPs | C18: m3 | D18: 0 | E18: 0 | F18: 0 | G18: 0 | H18: 0 | I18: 0 | J18: 0 | K18: 0 | L18: 0 | M18: 0 | N18: 0 | O18: 0 | P18: =SUM(D18:O18) -> 0
A19: Institutions | C19: m3 | D19: 297.7 | E19: 127.7 | F19: 921.9 | G19: 888 | H19: 367.6 | I19: 98 | J19: 723.8 | K19: 69.7 | L19: 72.1 | M19: 4676 | N19: 93.1 | O19: 316.7 | P19: =SUM(D19:O19) -> 8652.3
A20: Commercial/Industrial | C20: m3 | D20: 51.2 | E20: 100.8 | F20: 65 | G20: 264.9 | H20: 53.3 | I20: 56.6 | J20: 68.2 | K20: 87.9 | L20: 76.6 | M20: 73.2 | N20: 76.7 | O20: 59.6 | P20: =SUM(D20:O20) -> 1034
A21: Total Volume Prepaid | C21: m3 | D21: =SUM(D17:D20) -> 1244.6 | E21: =SUM(E17:E20) -> 999.4 | F21: =SUM(F17:F20) -> 1645.8 | G21: =SUM(G17:G20) -> 3095.1 | H21: =SUM(H17:H20) -> 1155.3 | I21: =SUM(I17:I20) -> 656.2 | J21: =SUM(J17:J20) -> 1113.3 | K21: =SUM(K17:K20) -> 683.6 | ... P21: =SUM(P17:P20) -> 18631.6
A22: TOTAL REVENUE WATER | C22: m3 | D22: =D21+D15 -> 5470.6 | E22: =E21+E15 -> 5629.4 | F22: =F21+F15 -> 6136.8 | G22: =G21+G15 -> 7995.1 | H22: =H21+H15 -> 6008.3 | I22: =I21+I15 -> 4164.2 | J22: =J21+J15 -> 4130.3 | K22: =K21+K15 -> 4054.6 | ... P22: =P21+P15 -> 66687.6
A24: Non-Revenue Water (NRW) | B24: Volume | C24: m3 | D24: =D9-D22 -> 2379.4 | E24: =E9-E22 -> 1868.6 | F24: =F9-F22 -> 716.2 | G24: =G9-G22 -> 665.9 | H24: =H9-H22 -> 442.7 | I24: =I9-I22 -> 676.8 | J24: =J9-J22 -> 920.7 | K24: =K9-K22 -> 790.4 | ... P24: =P9-P22 -> 10005.4
B25: Percentage | C25: % | D25: =IFERROR(D24/D9,0) -> 0.30310828 | E25: =E24/E9 -> 0.24921312 | F25: =F24/F9 -> 0.10450897 | G25: =IFERROR(G24/G9,0) -> 0.076884886 | H25: =IFERROR(H24/H9,0) -> 0.068625019 | I25: =IFERROR(I24/I9,0) -> 0.13980583 | J25: =IFERROR(J24/J9,0) -> 0.18228074 | K25: =IFERROR(K24/K9,0) -> 0.16313725 | L25: =IFERROR(L24/L9,0) -> 0.067555089 | M25: =IFERROR(M24/M9,0) -> 0.056637258 | N25: =IFERROR(N24/N9,0) -> 0.066298032 | O25: =IFERROR(O24/O9,0) -> 0.066339171 | P25: =IF(P9,P24/P9,"") -> 0.13046041
A26: OPERATING EXPENSES
A27: Chemicals
A28: Chemical | B28: Rate(MK/kg)
A29: Chlorine | B29: 7400 | C29: kg | D29: 10 | E29: 10 | F29: 9 | G29: 15 | H29: 15 | I29: 12 | J29: 15 | K29: 8 | L29: 10 | M29: 11 | N29: 13 | O29: 10 | P29: =SUM(D29:O29) -> 138
C30: kg/mg litre | D30: =IFERROR(D29/(D9/1000),0) -> 1.2738854 | E30: =IFERROR(E29/(E9/1000),0) -> 1.333689 | F30: =IFERROR(F29/(F9/1000),0) -> 1.3132934 | G30: =IFERROR(G29/(G9/1000),0) -> 1.7319016 | H30: =IFERROR(H29/(H9/1000),0) -> 2.3252209 | I30: =IFERROR(I29/(I9/1000),0) -> 2.4788267 | J30: =IFERROR(J29/(J9/1000),0) -> 2.969709 | K30: =IFERROR(K29/(K9/1000),0) -> 1.6511868 | ... P30: =IFERROR(P29/(P9/1000),0) -> 1.799382
A31: Aluminium sulphate | B31: 1900 | C31: kg | D31: 0 | E31: 0 | F31: 0 | G31: 0 | H31: 0 | I31: 0 | J31: 0 | K31: 0 | L31: 0 | M31: 0 | N31: 0 | O31: 0 | P31: =SUM(D31:O31) -> 0
C32: kg/mg litre | D32: =IFERROR(D31/(D9/1000),0) -> 0 | E32: =IFERROR(E31/(E9/1000),0) -> 0 | F32: =IFERROR(F31/(F9/1000),0) -> 0 | G32: =IFERROR(G31/(G9/1000),0) -> 0 | H32: =IFERROR(H31/(H9/1000),0) -> 0 | I32: =IFERROR(I31/(I9/1000),0) -> 0 | J32: =IFERROR(J31/(J9/1000),0) -> 0 | K32: =IFERROR(K31/(K9/1000),0) -> 0 | ... P32: =IFERROR(P31/(P9/1000),0) -> 0
A33: Soda | B33: 1900 | C33: kg | D33: 0 | E33: 0 | F33: 0 | G33: 0 | H33: 0 | I33: 0 | J33: 0 | K33: 0 | L33: 0 | M33: 0 | N33: 0 | O33: 0 | P33: =SUM(D33:O33) -> 0
C34: kg/mg litre | D34: =IFERROR(D33/(D9/1000),0) -> 0 | E34: =IFERROR(E33/(E9/1000),0) -> 0 | F34: =IFERROR(F33/(F9/1000),0) -> 0 | G34: =IFERROR(G33/(G9/1000),0) -> 0 | H34: =IFERROR(H33/(H9/1000),0) -> 0 | I34: =IFERROR(I33/(I9/1000),0) -> 0 | J34: =IFERROR(J33/(J9/1000),0) -> 0 | K34: =IFERROR(K33/(K9/1000),0) -> 0 | ... P34: =IFERROR(P33/(P9/1000),0) -> 0
A35: Algae floc | B35: =745345.16/200 -> 3726.7258 | C35: litres | D35: 0 | E35: 0 | F35: 0 | G35: 0 | H35: 0 | I35: 0 | J35: 0 | K35: 0 | L35: 0 | M35: 0 | N35: 0 | O35: 0
C36: litres/mg litre
A37: Sud floc | B37: =790318.72/200 -> 3951.5936 | C37: litres | D37: 0 | E37: 0 | F37: 0 | G37: 0 | H37: 0 | I37: 0 | J37: 0 | K37: 0 | L37: 0 | M37: 0 | N37: 0 | O37: 0 | P37: =SUM(D37:O37) -> 0
C38: litres/mg litre | D38: =IFERROR(D37/(D9/1000),0) -> 0 | E38: =IFERROR(E37/(E9/1000),0) -> 0 | F38: =IFERROR(F37/(F9/1000),0) -> 0 | G38: =IFERROR(G37/(G9/1000),0) -> 0 | H38: =IFERROR(H37/(H9/1000),0) -> 0 | I38: =IFERROR(I37/(I9/1000),0) -> 0 | J38: =IFERROR(J37/(J9/1000),0) -> 0 | K38: =IFERROR(K37/(K9/1000),0) -> 0 | ... P38: =IFERROR(P37/(P9/1000),0) -> 0
A39: Potasium permanganate | B39: 1950 | C39: kg | D39: 0 | E39: 0 | F39: 0 | G39: 0 | H39: 0 | I39: 0 | J39: 0 | K39: 0 | L39: 0 | M39: 0 | N39: 0 | O39: 0 | P39: =SUM(D39:O39) -> 0
C40: kg/mg litre | D40: =IFERROR(D39/(D9/1000),0) -> 0 | E40: =IFERROR(E39/(E9/1000),0) -> 0 | F40: =IFERROR(F39/(F9/1000),0) -> 0 | G40: =IFERROR(G39/(G9/1000),0) -> 0 | H40: =IFERROR(H39/(H9/1000),0) -> 0 | I40: =IFERROR(I39/(I9/1000),0) -> 0 | J40: =IFERROR(J39/(J9/1000),0) -> 0 | K40: =IFERROR(K39/(K9/1000),0) -> 0 | ... P40: =IFERROR(P39/(P9/1000),0) -> 0
A41: Cost of Chemicals | C41: Mk | D41: =(D29*$B29)+(D31*$B31)+(D33*$B33)+(D35*$B35)+(D37*$B37)+(D39*$B39) -> 74000 | E41: =(E29*$B29)+(E31*$B31)+(E33*$B33)+(E35*$B35)+(E37*$B37)+(E39*$B39) -> 74000 | F41: =(F29*$B29)+(F31*$B31)+(F33*$B33)+(F35*$B35)+(F37*$B37)+(F39*$B39) -> 66600 | G41: =(G29*$B29)+(G31*$B31)+(G33*$B33)+(G35*$B35)+(G37*$B37)+(G39*$B39) -> 111000 | H41: =(H29*$B29)+(H31*$B31)+(H33*$B33)+(H35*$B35)+(H37*$B37)+(H39*$B39) -> 111000 | I41: =(I29*$B29)+(I31*$B31)+(I33*$B33)+(I35*$B35)+(I37*$B37)+(I39*$B39) -> 88800 | J41: =(J29*$B29)+(J31*$B31)+(J33*$B33)+(J35*$B35)+(J37*$B37)+(J39*$B39) -> 111000 | K41: =(K29*$B29)+(K31*$B31)+(K33*$B33)+(K35*$B35)+(K37*$B37)+(K39*$B39) -> 59200 | ... O41: =(O29*$B29)+(O31*$B31)+(O33*$B33)+(O35*$B35)+(O37*$B37)+(O39*$B39) -> 74000 | P41: =SUM(D41:O41) -> 1021200
A42: Cost/vol. Produced (chemicals) | C42: Mk/m3 | D42: =IFERROR(D41/D9,0) -> 9.4267516 | E42: =IFERROR(E41/E9,0) -> 9.8692985 | F42: =IFERROR(F41/F9,0) -> 9.7183715 | G42: =IFERROR(G41/G9,0) -> 12.816072 | H42: =IFERROR(H41/H9,0) -> 17.206635 | I42: =IFERROR(I41/I9,0) -> 18.343317 | J42: =IFERROR(J41/J9,0) -> 21.975846 | K42: =IFERROR(K41/K9,0) -> 12.218782 | ... P42: =IFERROR(P41/P9,0) -> 13.315426
A43: Power
A44: Power Usage | C44: Kw | D44: 6086.62 | E44: 5799.34 | F44: 4629.4 | G44: 6458.21 | H44: 5947.56 | I44: 4369 | J44: 5947.56 | K44: 2490 | L44: 3455.59 | M44: 4505.58 | N44: 5949.01 | O44: 3781.25 | P44: =SUM(D44:O44) -> 59419.12
A45: Power/ Vol. Produced | C45: Kw/m3 | D45: =IFERROR(D44/D9,0) -> 0.77536561 | E45: =IFERROR(E44/E9,0) -> 0.77345159 | F45: =IFERROR(F44/F9,0) -> 0.67552897 | G45: =IFERROR(G44/G9,0) -> 0.74566563 | H45: =IFERROR(H44/H9,0) -> 0.92195939 | I45: =IFERROR(I44/I9,0) -> 0.90249948 | J45: =IFERROR(J44/J9,0) -> 1.1775015 | K45: =IFERROR(K44/K9,0) -> 0.51393189 | ... P45: =IFERROR(P44/P9,0) -> 0.77476588
A46: Cost of Power | C46: Mk | D46: =IF(D44=0,0,IF(D44>=0,0+(D44*202.25)+23390)*1.165) -> 1461386.4 | E46: =IF(E44=0,0,IF(E44>=0,0+(E44*202.25)+23390)*1.165) -> 1393697.1 | F46: =IF(F44=0,0,IF(F44>=0,0+(F44*202.25)+23390)*1.165) -> 1118034.4 | G46: =IF(G44=0,0,IF(G44>=0,0+(G44*202.25)+23390)*1.165) -> 1548940.9 | H46: =IF(H44=0,0,IF(H44>=0,0+(H44*202.25)+23390)*1.165) -> 1428620.9 | I46: =IF(I44=0,0,IF(I44>=0,0+(I44*202.25)+23390)*1.165) -> 1056678.6 | J46: =IF(J44=0,0,IF(J44>=0,0+(J44*202.25)+23390)*1.165) -> 1428620.9 | K46: =IF(K44=0,0,IF(K44>=0,0+(K44*202.25)+23390)*1.165) -> 613946.26 | ... O46: =IF(O44=0,0,IF(O44>=0,0+(O44*202.25)+23390)*1.165) -> 918192.2 | P46: =SUM(D46:O46) -> 14327400
A47: Cost/vol. Produced | C47: Mk/m3 | D47: =IFERROR(D46/D9,0) -> 186.16387 | E47: =IFERROR(E46/E9,0) -> 185.87585 | F47: =IFERROR(F46/F9,0) -> 163.14525 | G47: =IFERROR(G46/G9,0) -> 178.84088 | H47: =IFERROR(H46/H9,0) -> 221.45727 | I47: =IFERROR(I46/I9,0) -> 218.27692 | J47: =IFERROR(J46/J9,0) -> 282.83921 | K47: =IFERROR(K46/K9,0) -> 126.71749 | ... P47: =IFERROR(P46/P9,0) -> 186.81496
A48: Plant and Vehicle Maintenance
A49: Distances covered | C49: km | D49: 0 | E49: 0 | F49: 0 | G49: 0 | H49: 0 | I49: 0 | J49: 0 | K49: 0 | L49: 0 | M49: 0 | N49: 0 | O49: 0 | P49: =SUM(D49:O49) -> 0
A50: Fuel Used (litres) | C50: litres | D50: 0 | E50: 0 | F50: 0 | G50: 0 | H50: 0 | I50: 0 | J50: 0 | K50: 0 | L50: 0 | M50: 0 | N50: 0 | O50: 0 | P50: =SUM(D50:O50) -> 0
A51: Cost of fuel | C51: Mk | D51: 0 | E51: 0 | F51: 0 | G51: 0 | H51: 0 | I51: 0 | J51: 0 | K51: 0 | L51: 0 | M51: 0 | N51: 0 | O51: 0 | P51: =SUM(D51:O51) -> 0
A52: Maintenance | C52: Mk | D52: 0 | E52: 0 | F52: 0 | G52: 0 | H52: 0 | I52: 0 | J52: 0 | K52: 0 | L52: 0 | M52: 0 | N52: 0 | O52: 0 | P52: =SUM(D52:O52) -> 0
A53: Salaries and Wages
A54: Staff Costs | C54: MK | D54: 0 | E54: 0 | F54: 0 | G54: 0 | H54: 0 | I54: 0 | J54: 0 | K54: 0 | L54: 0 | M54: 0 | N54: 0 | O54: 0 | P54: =SUM(D54:O54) -> 0
A55: Wages | C55: MK | D55: 0 | E55: 0 | F55: 0 | G55: 0 | H55: 0 | I55: 0 | J55: 0 | K55: 0 | L55: 0 | M55: 0 | N55: 0 | O55: 0 | P55: =SUM(D55:O55) -> 0
A56: Other Overhead Costs | C56: MK | D56: 0 | E56: 0 | F56: 0 | G56: 0 | H56: 0 | I56: 0 | J56: 0 | K56: 0 | L56: 0 | M56: 0 | N56: 0 | O56: 0 | P56: =SUM(D56:O56) -> 0
A57: Operating Costs
A58: Total Operating Costs | C58: MK | D58: =D41+D46+D51+D52+D54+D55+D56 -> 1535386.4 | E58: =E41+E46+E51+E52+E54+E55+E56 -> 1467697.1 | F58: =F41+F46+F51+F52+F54+F55+F56 -> 1184634.4 | G58: =G41+G46+G51+G52+G54+G55+G56 -> 1659940.9 | H58: =H41+H46+H51+H52+H54+H55+H56 -> 1539620.9 | I58: =I41+I46+I51+I52+I54+I55+I56 -> 1145478.6 | J58: =J41+J46+J51+J52+J54+J55+J56 -> 1539620.9 | K58: =K41+K46+K51+K52+K54+K55+K56 -> 673146.26 | ... O58: =O41+O46+O51+O52+O54+O55+O56 -> 992192.2 | P58: =SUM(D58:O58) -> 15348600
A59: Cost/Vol. Produced | C59: Mk/m3 | D59: =IFERROR(D58/D9,0) -> 195.59062 | E59: =IFERROR(E58/E9,0) -> 195.74514 | F59: =IFERROR(F58/F9,0) -> 172.86362 | G59: =IFERROR(G58/G9,0) -> 191.65695 | H59: =IFERROR(H58/H9,0) -> 238.66391 | I59: =IFERROR(I58/I9,0) -> 236.62024 | J59: =IFERROR(J58/J9,0) -> 304.81506 | K59: =IFERROR(K58/K9,0) -> 138.93628 | ... P59: =IFERROR(P58/P9,0) -> 200.13038
A60: Cost/Vol. Billed | C60: Mk/m3 | D60: =IFERROR(D58/D22,0) -> 280.66142 | E60: =IFERROR(E58/E22,0) -> 260.71999 | F60: =IFERROR(F58/F22,0) -> 193.0378 | G60: =IFERROR(G58/G22,0) -> 207.61977 | H60: =IFERROR(H58/H22,0) -> 256.249 | I60: =IFERROR(I58/I22,0) -> 275.07771 | J60: =IFERROR(J58/J22,0) -> 372.76248 | K60: =IFERROR(K58/K22,0) -> 166.02039 | ... P60: =IFERROR(P58/P22,0) -> 230.15672
A61: Permanent Staff Employed | C61: No | D61: 5 | E61: 5 | F61: 5 | G61: 5 | H61: 5 | I61: 5 | J61: 5 | K61: 5 | L61: 5 | M61: 5 | N61: 5 | O61: 5 | P61: =O61 -> 5
A62: Staff/Vol.1000m3 of Volume Produced/hour (12 hour day) | C62: No/1000m3 | D62: =IFERROR((D61*1000*31)/D9,0) -> 19.745223 | E62: =IFERROR((E61*1000*31)/E9,0) -> 20.672179 | F62: =IFERROR((F61*1000*31)/F9,0) -> 22.617832 | G62: =IFERROR((G61*1000*31)/G9,0) -> 17.896317 | H62: =IFERROR((H61*1000*31)/H9,0) -> 24.027283 | I62: =IFERROR((I61*1000*31)/I9,0) -> 32.018178 | J62: =IFERROR((J61*1000*31)/J9,0) -> 30.686993 | K62: =IFERROR((K61*1000*31)/K9,0) -> 31.991744 | ... P62: =IFERROR((P61*1000*31)/P9,0) -> 2.0210449
A63: Temporary Staff Employed | C63: No | D63: 15 | E63: 15 | F63: 15 | G63: 15 | H63: 15 | I63: 15 | J63: 15 | K63: 15 | L63: 15 | M63: 15 | N63: 15 | O63: 15 | P63: =O63 -> 15
A65: Water Connections and Disconnections
A66: New Individual Water Connections | B66: Brought Forward | C66: No | D66: 0 | E66: 0 | F66: 0 | G66: 0 | H66: 0 | I66: 0 | J66: 0 | K66: 14 | L66: 14 | M66: 10 | N66: 10 | O66: 16 | P66: =D66 -> 0
B67: Applied this Month | C67: No | D67: 8 | E67: 9 | F67: 7 | G67: 12 | H67: 12 | I67: 2 | J67: 14 | K67: 0 | L67: 0 | M67: 0 | N67: 6 | O67: 1 | P67: =SUM(D67:O67) -> 71
B68: Done this Month Postpaid | C68: No | D68: 8 | E68: 9 | F68: 7 | G68: 12 | H68: 12 | I68: 2 | J68: 0 | K68: 0 | L68: 4 | M68: 0 | N68: 0 | O68: 0 | P68: =SUM(D68:O68) -> 54
B69: Done this Month Prepaid | C69: No | D69: 0 | E69: 0 | F69: 0 | G69: 0 | H69: 0 | I69: 0 | J69: 0 | K69: 0 | L69: 0 | M69: 0 | N69: 0 | O69: 0 | P69: =SUM(D69:O69) -> 0
B70: Total Done | C70: No | D70: =D68+D69 -> 8 | E70: =E68+E69 -> 9 | F70: =F68+F69 -> 7 | G70: =G68+G69 -> 12 | H70: =H68+H69 -> 12 | I70: =I68+I69 -> 2 | J70: =J68+J69 -> 0 | K70: =K68+K69 -> 0 | ... P70: =P68+P69 -> 54
B71: Carried Forward | C71: No | D71: =D66+D67-D70 -> 0 | E71: =E66+E67-E70 -> 0 | F71: =F66+F67-F70 -> 0 | G71: =G66+G67-G70 -> 0 | H71: =H66+H67-H70 -> 0 | I71: =I66+I67-I70 -> 0 | J71: =J66+J67-J70 -> 14 | K71: =K66+K67-K70 -> 14 | ... P71: =P66+P67-P70 -> 17
A72: New Institutional Water Connections | B72: Brought Forward | C72: No | D72: 0 | E72: 0 | F72: 0 | G72: 0 | H72: 0 | I72: 0 | J72: 0 | K72: 0 | L72: 0 | M72: 0 | N72: 0 | O72: 0 | P72: =D72 -> 0
B73: Applied this Month | C73: No | D73: 0 | E73: 0 | F73: 0 | G73: 0 | H73: 0 | I73: 0 | J73: 1 | K73: 0 | L73: 0 | M73: 0 | N73: 0 | O73: 0 | P73: =SUM(D73:O73) -> 1
B74: Done this Month Postpaid | C74: No | D74: 0 | E74: 0 | F74: 0 | G74: 0 | H74: 0 | I74: 0 | J74: 1 | K74: 0 | L74: 0 | M74: 0 | N74: 0 | O74: 0 | P74: =SUM(D74:O74) -> 1
B75: Done this Month Prepaid | C75: No | D75: 0 | E75: 0 | F75: 0 | G75: 0 | H75: 0 | I75: 0 | J75: 0 | K75: 0 | L75: 0 | M75: 0 | N75: 0 | O75: 0 | P75: =SUM(D75:O75) -> 0
B76: Total Done | C76: No | D76: =D74+D75 -> 0 | E76: =E74+E75 -> 0 | F76: =F74+F75 -> 0 | G76: =G74+G75 -> 0 | H76: =H74+H75 -> 0 | I76: =I74+I75 -> 0 | J76: =J74+J75 -> 1 | K76: =K74+K75 -> 0 | ... P76: =P74+P75 -> 1
B77: Carried Forward | C77: No | D77: =D72+D73-D76 -> 0 | E77: =E72+E73-E76 -> 0 | F77: =F72+F73-F76 -> 0 | G77: =G72+G73-G76 -> 0 | H77: =H72+H73-H76 -> 0 | I77: =I72+I73-I76 -> 0 | J77: =J72+J73-J76 -> 0 | K77: =K72+K73-K76 -> 0 | ... P77: =P72+P73-P76 -> 0
A78: New Commercial/Industrial Water Connections | B78: Brought Forward | C78: No | D78: 0 | E78: 0 | F78: 0 | G78: 0 | H78: 0 | I78: 0 | J78: 0 | K78: 0 | L78: 0 | M78: 0 | N78: 0 | O78: 0 | P78: =D78 -> 0
B79: Applied this Month | C79: No | D79: 0 | E79: 0 | F79: 0 | G79: 0 | H79: 0 | I79: 0 | J79: 0 | K79: 0 | L79: 0 | M79: 0 | N79: 0 | O79: 0 | P79: =SUM(D79:O79) -> 0
B80: Done this Month Postpaid | C80: No | D80: 0 | E80: 0 | F80: 0 | G80: 0 | H80: 0 | I80: 0 | J80: 0 | K80: 0 | L80: 0 | M80: 0 | N80: 0 | O80: 0 | P80: =SUM(D80:O80) -> 0
B81: Done this Month Prepaid | C81: No | D81: 0 | E81: 0 | F81: 0 | G81: 0 | H81: 0 | I81: 0 | J81: 0 | K81: 0 | L81: 0 | M81: 0 | N81: 0 | O81: 0 | P81: =SUM(D81:O81) -> 0
B82: Total Done | C82: No | D82: =D80+D81 -> 0 | E82: =E80+E81 -> 0 | F82: =F80+F81 -> 0 | G82: =G80+G81 -> 0 | H82: =H80+H81 -> 0 | I82: =I80+I81 -> 0 | J82: =J80+J81 -> 0 | K82: =K80+K81 -> 0 | ... O82: =O80+O81 -> 0 | P82: =P81+P80 -> 0
B83: Carried Forward | C83: No | D83: =D78+D79-D82 -> 0 | E83: =E78+E79-E82 -> 0 | F83: =F78+F79-F82 -> 0 | G83: =G78+G79-G82 -> 0 | H83: =H78+H79-H82 -> 0 | I83: =I78+I79-I82 -> 0 | J83: =J78+J79-J82 -> 0 | K83: =K78+K79-K82 -> 0 | ... P83: =P78+P79-P82 -> 0
A84: New CWP | B84: Brought Forward | C84: No | D84: 0 | E84: 0 | F84: 0 | G84: 0 | H84: 0 | I84: 0 | J84: 0 | K84: 0 | L84: 0 | M84: 0 | N84: 0 | O84: 0 | P84: =D84 -> 0
B85: Applied this Month | C85: No | D85: 0 | E85: 0 | F85: 0 | G85: 0 | H85: 0 | I85: 0 | J85: 0 | K85: 0 | L85: 0 | M85: 0 | N85: 0 | O85: 0 | P85: =SUM(D85:O85) -> 0
B86: Done this Month Postpaid | C86: No | D86: 0 | E86: 0 | F86: 0 | G86: 0 | H86: 0 | I86: 0 | J86: 0 | K86: 0 | L86: 0 | M86: 0 | N86: 0 | O86: 0 | P86: =SUM(D86:O86) -> 0
B87: Done this Month Prepaid | C87: No | D87: 0 | E87: 0 | F87: 0 | G87: 0 | H87: 0 | I87: 0 | J87: 0 | K87: 0 | L87: 0 | M87: 0 | N87: 0 | O87: 0 | P87: =SUM(D87:O87) -> 0
B88: Total Done | C88: No | D88: =D86+D87 -> 0 | E88: =E86+E87 -> 0 | F88: =F86+F87 -> 0 | G88: =G86+G87 -> 0 | H88: =H86+H87 -> 0 | I88: =I86+I87 -> 0 | J88: =J86+J87 -> 0 | K88: =K86+K87 -> 0 | ... O88: =O86+O87 -> 0 | P88: =SUM(D88:O88) -> 0
B89: Carried Forward | C89: No | D89: =D84+D85-D88 -> 0 | E89: =E84+E85-E88 -> 0 | F89: =F84+F85-F88 -> 0 | G89: =G84+G85-G88 -> 0 | H89: =H84+H85-H88 -> 0 | I89: =I84+I85-I88 -> 0 | J89: =J84+J85-J88 -> 0 | K89: =K84+K85-K88 -> 0 | ... O89: =O84+O85-O88 -> 0 | P89: =P84+P85-P86-P87 -> 0
A90: Aggregated New Water connections | B90: Brought Forward | C90: No | D90: =D66+D72+D78+D84 -> 0 | E90: =E66+E72+E78+E84 -> 0 | F90: =F66+F72+F78+F84 -> 0 | G90: =G66+G72+G78+G84 -> 0 | H90: =H66+H72+H78+H84 -> 0 | I90: =I66+I72+I78+I84 -> 0 | J90: =J66+J72+J78+J84 -> 0 | K90: =K66+K72+K78+K84 -> 14 | ... O90: =O66+O72+O78+O84 -> 16 | P90: =D90 -> 0
B91: Applied this Month | C91: No | D91: =D67+D73+D79+D85 -> 8 | E91: =E67+E73+E79+E85 -> 9 | F91: =F67+F73+F79+F85 -> 7 | G91: =G67+G73+G79+G85 -> 12 | H91: =H67+H73+H79+H85 -> 12 | I91: =I67+I73+I79+I85 -> 2 | J91: =J67+J73+J79+J85 -> 15 | K91: =K67+K73+K79+K85 -> 0 | ... O91: =O67+O73+O79+O85 -> 1 | P91: =SUM(D91:O91) -> 72
B92: Done this Month Postpaid | C92: No | D92: =D68+D74+D80+D86 -> 8 | E92: =E68+E74+E80+E86 -> 9 | F92: =F68+F74+F80+F86 -> 7 | G92: =G68+G74+G80+G86 -> 12 | H92: =H68+H74+H80+H86 -> 12 | I92: =I68+I74+I80+I86 -> 2 | J92: =J68+J74+J80+J86 -> 1 | K92: =K68+K74+K80+K86 -> 0 | ... O92: =O68+O74+O80+O86 -> 0 | P92: =SUM(D92:O92) -> 55
B93: Done this Month Prepaid | D93: =D69+D75+D81+D87 -> 0 | E93: =E69+E75+E81+E87 -> 0 | F93: =F69+F75+F81+F87 -> 0 | G93: =G69+G75+G81+G87 -> 0 | H93: =H69+H75+H81+H87 -> 0 | I93: =I69+I75+I81+I87 -> 0 | J93: =J69+J75+J81+J87 -> 0 | K93: =K69+K75+K81+K87 -> 0 | ... O93: =O69+O75+O81+O87 -> 0 | P93: =SUM(D93:O93) -> 0
B94: Total Done | C94: No | D94: =D93+D92 -> 8 | E94: =E93+E92 -> 9 | F94: =F93+F92 -> 7 | G94: =G93+G92 -> 12 | H94: =H93+H92 -> 12 | I94: =I93+I92 -> 2 | J94: =J93+J92 -> 1 | K94: =K93+K92 -> 0 | ... P94: =P93+P92 -> 55
B95: Carried Forward | C95: No | D95: =D90+D91-D94 -> 0 | E95: =E90+E91-E94 -> 0 | F95: =F90+F91-F94 -> 0 | G95: =G90+G91-G94 -> 0 | H95: =H90+H91-H94 -> 0 | I95: =I90+I91-I94 -> 0 | J95: =J90+J91-J94 -> 14 | K95: =K90+K91-K94 -> 14 | ... P95: =P90+P91-P94 -> 17
A97: Prepaid Metering
A98: Prepaid Meters Installed | C98: No | D98: 0 | E98: 0 | F98: 0 | G98: 0 | H98: 0 | I98: 0 | J98: 0 | K98: 0 | L98: 0 | M98: 0 | N98: 0 | O98: 0 | P98: =SUM(D98:O98) -> 0
A100: Active and Disconnected Accounts
A101: Disconnected Individual Accounts | C101: No | D101: 151 | E101: 144 | F101: 151 | G101: 138 | H101: 139 | I101: 144 | J101: 142 | K101: 142 | L101: 143 | M101: 143 | N101: 149 | O101: 149 | P101: =O101 -> 149
A102: Disconnected institutional Accounts | C102: No | D102: 4 | E102: 4 | F102: 4 | G102: 2 | H102: 2 | I102: 3 | J102: 4 | K102: 4 | L102: 3 | M102: 3 | N102: 4 | O102: 4 | P102: =O102 -> 4
A103: Disconnected Commercial/Industrial Accounts | C103: No | D103: 0 | E103: 0 | F103: 1 | G103: 0 | H103: 0 | I103: 0 | J103: 0 | K103: 0 | L103: 0 | M103: 0 | N103: 0 | O103: 0 | P103: =O103 -> 0
A104: Disconnected CWP | C104: No | D104: 3 | E104: 3 | F104: 3 | G104: 3 | H104: 3 | I104: 3 | J104: 3 | K104: 3 | L104: 3 | M104: 3 | N104: 3 | O104: 3 | P104: =O104 -> 3
A105: Total Disconnected Accounts | C105: No | D105: =SUM(D101:D104) -> 158 | E105: =SUM(E101:E104) -> 151 | F105: =SUM(F101:F104) -> 159 | G105: =SUM(G101:G104) -> 143 | H105: =SUM(H101:H104) -> 144 | I105: =SUM(I101:I104) -> 150 | J105: =SUM(J101:J104) -> 149 | K105: =SUM(K101:K104) -> 149 | ... O105: =SUM(O101:O104) -> 156 | P105: =O105 -> 156
A106: Postpaid Consumers
...

Sheet Kuchawe
A1: SOUTHERN REGION WATER BOARD
A3: MONTHLY REPORTS - 2024/2025
A4: ZOMBA ZONE
A5: KUCHAWE SCHEME
A7: PARAMETERS | C7: UNITS | D7: APRIL | E7: MAY | F7: JUNE | G7: JULY | H7: AUGUST | I7: SEPTEMBER | J7: OCTOBER | K7: NOVEMBER | L7: DECEMBER | M7: JANUARY | N7: FEBRUARY | O7: MARCH | P7: TOTALS
A8: PRODUCTION
A9: Volume Produced | C9: m3 | D9: 3228 | E9: 4810 | F9: 4002 | G9: 4710 | H9: 4969 | I9: 5109 | J9: 4481 | K9: 3635 | L9: 4202 | M9: 3180 | N9: 3216 | O9: 4041 | P9: =SUM(D9:O9) -> 49583
A10: REVENUE WATER - POSTPAID
A11: Volume Billed Individuals | C11: m3 | D11: 546 | E11: 559 | F11: 616 | G11: 589 | H11: 823 | I11: 712 | J11: 555 | K11: 416 | L11: 485 | M11: 358 | N11: 391 | O11: 432 | P11: =SUM(D11:O11) -> 6482
A12: Volume Billed CWPs | C12: m3 | D12: 26 | E12: 18 | F12: 18 | G12: 13 | H12: 16 | I12: 3 | J12: 3 | K12: 4 | L12: 0 | M12: 0 | N12: 0 | O12: 0 | P12: =SUM(D12:O12) -> 101
A13: Volume Billed Institutions | C13: m3 | D13: 368 | E13: 787 | F13: 394 | G13: 503 | H13: 265 | I13: 432 | J13: 497 | K13: 157 | L13: 151 | M13: 149 | N13: 112 | O13: 119 | P13: =SUM(D13:O13) -> 3934
A14: Volume Billed Commercial/Industrial | C14: m3 | D14: 1 | E14: 108 | F14: 60 | G14: 53 | H14: 64 | I14: 72 | J14: 30 | K14: 9 | L14: 18 | M14: 8 | N14: 7 | O14: 11 | P14: =SUM(D14:O14) -> 441
A15: Total Volume Billed Post Paid | C15: m3 | D15: =SUM(D11:D14) -> 941 | E15: =SUM(E11:E14) -> 1472 | F15: =SUM(F11:F14) -> 1088 | G15: =SUM(G11:G14) -> 1158 | H15: =SUM(H11:H14) -> 1168 | I15: =SUM(I11:I14) -> 1219 | J15: =SUM(J11:J14) -> 1085 | K15: =SUM(K11:K14) -> 586 | ... P15: =SUM(P11:P14) -> 10958
A16: REVENUE WATER - PREPAID
A17: Individuals | C17: m3 | D17: 234.3 | E17: 324.4 | F17: 204.8 | G17: 439.1 | H17: 479.1 | I17: 311.7 | J17: 399.6 | K17: 314.9 | L17: 180.6 | M17: 232.2 | N17: 94.4 | O17: 161.5 | P17: =SUM(D17:O17) -> 3376.6
A18: CWPs | C18: m3 | D18: 259 | E18: 319.6 | F18: 265.1 | G18: 397.3 | H18: 436.1 | I18: 206.5 | J18: 110.6 | K18: 187.9 | L18: 306.1 | M18: 142.4 | N18: 81.9 | O18: 188.4 | P18: =SUM(D18:O18) -> 2900.9
A19: Institutions | C19: m3 | D19: 0.5 | E19: 39.4 | F19: 18.9 | G19: 943.2 | H19: 92 | I19: 136.6 | J19: 25.5 | K19: 27.9 | L19: 62.7 | M19: 21.8 | N19: 32.7 | O19: 23.2 | P19: =SUM(D19:O19) -> 1424.4
A20: Commercial/Industrial | C20: m3 | D20: 748 | E20: 1210 | F20: 863.3 | G20: 1221.7 | H20: 1422.3 | I20: 2827.6 | J20: 1340.8 | K20: 2200.2 | L20: 1767.2 | M20: 1959.5 | N20: 1911.6 | O20: 1559.3 | P20: =SUM(D20:O20) -> 19031.5
A21: Total Volume Prepaid | C21: m3 | D21: =SUM(D17:D20) -> 1241.8 | E21: =SUM(E17:E20) -> 1893.4 | F21: =SUM(F17:F20) -> 1352.1 | G21: =SUM(G17:G20) -> 3001.3 | H21: =SUM(H17:H20) -> 2429.5 | I21: =SUM(I17:I20) -> 3482.4 | J21: =SUM(J17:J20) -> 1876.5 | K21: =SUM(K17:K20) -> 2730.9 | ... P21: =SUM(P17:P20) -> 26733.4
A22: TOTAL REVENUE WATER | C22: m3 | D22: =D21+D15 -> 2182.8 | E22: =E21+E15 -> 3365.4 | F22: =F21+F15 -> 2440.1 | G22: =G21+G15 -> 4159.3 | H22: =H21+H15 -> 3597.5 | I22: =I21+I15 -> 4701.4 | J22: =J21+J15 -> 2961.5 | K22: =K21+K15 -> 3316.9 | ... P22: =P21+P15 -> 37691.4
A24: Non-Revenue Water (NRW) | B24: Volume | C24: m3 | D24: =D9-D22 -> 1045.2 | E24: =E9-E22 -> 1444.6 | F24: =F9-F22 -> 1561.9 | G24: =G9-G22 -> 550.7 | H24: =H9-H22 -> 1371.5 | I24: =I9-I22 -> 407.6 | J24: =J9-J22 -> 1519.5 | K24: =K9-K22 -> 318.1 | ... P24: =P9-P22 -> 11891.6
B25: Percentage | C25: % | D25: =IFERROR(D24/D9,0) -> 0.32379182 | E25: =E24/E9 -> 0.30033264 | F25: =F24/F9 -> 0.39027986 | G25: =IFERROR(G24/G9,0) -> 0.11692144 | H25: =IFERROR(H24/H9,0) -> 0.27601127 | I25: =IFERROR(I24/I9,0) -> 0.079780779 | J25: =IFERROR(J24/J9,0) -> 0.33909842 | K25: =IFERROR(K24/K9,0) -> 0.087510316 | L25: =IFERROR(L24/L9,0) -> 0.29305093 | M25: =IFERROR(M24/M9,0) -> 0.097201258 | N25: =IFERROR(N24/N9,0) -> 0.18202736 | O25: =IFERROR(O24/O9,0) -> 0.38272705 | P25: =IF(P9,P24/P9,"") -> 0.2398322
A26: OPERATING EXPENSES
A27: Chemicals
A28: Chemical | B28: Rate(MK/kg)
A29: Chlorine | B29: 7400 | C29: kg | D29: 18 | E29: 16 | F29: 15 | G29: 17 | H29: 18 | I29: 15 | J29: 18 | K29: 15 | L29: 16 | M29: 15 | N29: 12 | O29: 16 | P29: =SUM(D29:O29) -> 191
C30: kg/mg litre | D30: =IFERROR(D29/(D9/1000),0) -> 5.5762082 | E30: =IFERROR(E29/(E9/1000),0) -> 3.3264033 | F30: =IFERROR(F29/(F9/1000),0) -> 3.7481259 | G30: =IFERROR(G29/(G9/1000),0) -> 3.6093418 | H30: =IFERROR(H29/(H9/1000),0) -> 3.6224592 | I30: =IFERROR(I29/(I9/1000),0) -> 2.9359953 | J30: =IFERROR(J29/(J9/1000),0) -> 4.0169605 | K30: =IFERROR(K29/(K9/1000),0) -> 4.1265475 | ... P30: =IFERROR(P29/(P9/1000),0) -> 3.8521267
A31: Aluminium sulphate | B31: 1900 | C31: kg | D31: 0 | E31: 5 | F31: 3 | G31: 5 | H31: 6 | I31: 3 | J31: 6 | K31: 9 | L31: 18 | M31: 13 | N31: 5 | O31: 0 | P31: =SUM(D31:O31) -> 73
C32: kg/mg litre | D32: =IFERROR(D31/(D9/1000),0) -> 0 | E32: =IFERROR(E31/(E9/1000),0) -> 1.039501 | F32: =IFERROR(F31/(F9/1000),0) -> 0.74962519 | G32: =IFERROR(G31/(G9/1000),0) -> 1.0615711 | H32: =IFERROR(H31/(H9/1000),0) -> 1.2074864 | I32: =IFERROR(I31/(I9/1000),0) -> 0.58719906 | J32: =IFERROR(J31/(J9/1000),0) -> 1.3389868 | K32: =IFERROR(K31/(K9/1000),0) -> 2.4759285 | ... P32: =IFERROR(P31/(P9/1000),0) -> 1.4722788
A33: Soda | B33: 1900 | C33: kg | D33: 0 | E33: 3 | F33: 1 | G33: 2 | H33: 4 | I33: 2 | J33: 4 | K33: 5 | L33: 16 | M33: 12 | N33: 5 | O33: 0 | P33: =SUM(D33:O33) -> 54
C34: kg/mg litre | D34: =IFERROR(D33/(D9/1000),0) -> 0 | E34: =IFERROR(E33/(E9/1000),0) -> 0.62370062 | F34: =IFERROR(F33/(F9/1000),0) -> 0.24987506 | G34: =IFERROR(G33/(G9/1000),0) -> 0.42462845 | H34: =IFERROR(H33/(H9/1000),0) -> 0.80499094 | I34: =IFERROR(I33/(I9/1000),0) -> 0.39146604 | J34: =IFERROR(J33/(J9/1000),0) -> 0.89265789 | K34: =IFERROR(K33/(K9/1000),0) -> 1.3755158 | ... P34: =IFERROR(P33/(P9/1000),0) -> 1.089083
A35: Algae floc | B35: =745345.16/200 -> 3726.7258 | C35: litres | D35: 0 | E35: 0 | F35: 0 | G35: 0 | H35: 0 | I35: 0 | J35: 0 | K35: 0 | L35: 0 | M35: 0 | N35: 0 | O35: 0
C36: litres/mg litre
A37: Sud floc | B37: =790318.72/200 -> 3951.5936 | C37: litres | D37: 0 | E37: 0 | F37: 0 | G37: 0 | H37: 0 | I37: 0 | J37: 0 | K37: 0 | L37: 0 | M37: 0 | N37: 0 | O37: 0 | P37: =SUM(D37:O37) -> 0
C38: litres/mg litre | D38: =IFERROR(D37/(D9/1000),0) -> 0 | E38: =IFERROR(E37/(E9/1000),0) -> 0 | F38: =IFERROR(F37/(F9/1000),0) -> 0 | G38: =IFERROR(G37/(G9/1000),0) -> 0 | H38: =IFERROR(H37/(H9/1000),0) -> 0 | I38: =IFERROR(I37/(I9/1000),0) -> 0 | J38: =IFERROR(J37/(J9/1000),0) -> 0 | K38: =IFERROR(K37/(K9/1000),0) -> 0 | ... P38: =IFERROR(P37/(P9/1000),0) -> 0
A39: Potasium permanganate | B39: 1950 | C39: kg | D39: 0 | E39: 0 | F39: 0 | G39: 0 | H39: 0 | I39: 0 | J39: 0 | K39: 0 | L39: 0 | M39: 0 | N39: 0 | O39: 0 | P39: =SUM(D39:O39) -> 0
C40: kg/mg litre | D40: =IFERROR(D39/(D9/1000),0) -> 0 | E40: =IFERROR(E39/(E9/1000),0) -> 0 | F40: =IFERROR(F39/(F9/1000),0) -> 0 | G40: =IFERROR(G39/(G9/1000),0) -> 0 | H40: =IFERROR(H39/(H9/1000),0) -> 0 | I40: =IFERROR(I39/(I9/1000),0) -> 0 | J40: =IFERROR(J39/(J9/1000),0) -> 0 | K40: =IFERROR(K39/(K9/1000),0) -> 0 | ... P40: =IFERROR(P39/(P9/1000),0) -> 0
A41: Cost of Chemicals | C41: Mk | D41: =(D29*$B29)+(D31*$B31)+(D33*$B33)+(D35*$B35)+(D37*$B37)+(D39*$B39) -> 133200 | E41: =(E29*$B29)+(E31*$B31)+(E33*$B33)+(E35*$B35)+(E37*$B37)+(E39*$B39) -> 133600 | F41: =(F29*$B29)+(F31*$B31)+(F33*$B33)+(F35*$B35)+(F37*$B37)+(F39*$B39) -> 118600 | G41: =(G29*$B29)+(G31*$B31)+(G33*$B33)+(G35*$B35)+(G37*$B37)+(G39*$B39) -> 139100 | H41: =(H29*$B29)+(H31*$B31)+(H33*$B33)+(H35*$B35)+(H37*$B37)+(H39*$B39) -> 152200 | I41: =(I29*$B29)+(I31*$B31)+(I33*$B33)+(I35*$B35)+(I37*$B37)+(I39*$B39) -> 120500 | J41: =(J29*$B29)+(J31*$B31)+(J33*$B33)+(J35*$B35)+(J37*$B37)+(J39*$B39) -> 152200 | K41: =(K29*$B29)+(K31*$B31)+(K33*$B33)+(K35*$B35)+(K37*$B37)+(K39*$B39) -> 137600 | ... O41: =(O29*$B29)+(O31*$B31)+(O33*$B33)+(O35*$B35)+(O37*$B37)+(O39*$B39) -> 118400 | P41: =SUM(D41:O41) -> 1654700
A42: Cost/vol. Produced (chemicals) | C42: Mk/m3 | D42: =IFERROR(D41/D9,0) -> 41.263941 | E42: =IFERROR(E41/E9,0) -> 27.775468 | F42: =IFERROR(F41/F9,0) -> 29.635182 | G42: =IFERROR(G41/G9,0) -> 29.532909 | H42: =IFERROR(H41/H9,0) -> 30.629905 | I42: =IFERROR(I41/I9,0) -> 23.585829 | J42: =IFERROR(J41/J9,0) -> 33.965633 | K42: =IFERROR(K41/K9,0) -> 37.854195 | ... P42: =IFERROR(P41/P9,0) -> 33.372325
A43: Power
A44: Power Usage | C44: Kw | D44: 1686 | E44: 1560 | F44: 1402 | G44: 1726 | H44: 1794 | I44: 1539 | J44: 1639 | K44: 1421 | L44: 1376 | M44: 1424 | N44: 1315 | O44: 1548 | P44: =SUM(D44:O44) -> 18430
A45: Power/ Vol. Produced | C45: Kw/m3 | D45: =IFERROR(D44/D9,0) -> 0.52230483 | E45: =IFERROR(E44/E9,0) -> 0.32432432 | F45: =IFERROR(F44/F9,0) -> 0.35032484 | G45: =IFERROR(G44/G9,0) -> 0.36645435 | H45: =IFERROR(H44/H9,0) -> 0.36103844 | I45: =IFERROR(I44/I9,0) -> 0.30123312 | J45: =IFERROR(J44/J9,0) -> 0.36576657 | K45: =IFERROR(K44/K9,0) -> 0.3909216 | ... P45: =IFERROR(P44/P9,0) -> 0.37169998
A46: Cost of Power | C46: Mk | D46: =IF(D44=0,0,IF(D44>=0,0+(D44*202.25)+23390)*1.165) -> 424506.78 | E46: =IF(E44=0,0,IF(E44>=0,0+(E44*202.25)+23390)*1.165) -> 394818.5 | F46: =IF(F44=0,0,IF(F44>=0,0+(F44*202.25)+23390)*1.165) -> 357590.34 | G46: =IF(G44=0,0,IF(G44>=0,0+(G44*202.25)+23390)*1.165) -> 433931.63 | H46: =IF(H44=0,0,IF(H44>=0,0+(H44*202.25)+23390)*1.165) -> 449953.87 | I46: =IF(I44=0,0,IF(I44>=0,0+(I44*202.25)+23390)*1.165) -> 389870.45 | J46: =IF(J44=0,0,IF(J44>=0,0+(J44*202.25)+23390)*1.165) -> 413432.58 | K46: =IF(K44=0,0,IF(K44>=0,0+(K44*202.25)+23390)*1.165) -> 362067.15 | ... O46: =IF(O44=0,0,IF(O44>=0,0+(O44*202.25)+23390)*1.165) -> 391991.04 | P46: =SUM(D46:O46) -> 4669491.8
A47: Cost/vol. Produced | C47: Mk/m3 | D47: =IFERROR(D46/D9,0) -> 131.50768 | E47: =IFERROR(E46/E9,0) -> 82.082848 | F47: =IFERROR(F46/F9,0) -> 89.352909 | G47: =IFERROR(G46/G9,0) -> 92.129857 | H47: =IFERROR(H46/H9,0) -> 90.552198 | I47: =IFERROR(I46/I9,0) -> 76.310521 | J47: =IFERROR(J46/J9,0) -> 92.263463 | K47: =IFERROR(K46/K9,0) -> 99.605817 | ... P47: =IFERROR(P46/P9,0) -> 94.175258
A48: Plant and Vehicle Maintenance
A49: Distances covered | C49: km | D49: 0 | E49: 0 | F49: 0 | G49: 0 | H49: 0 | I49: 0 | J49: 0 | K49: 0 | L49: 0 | M49: 0 | N49: 0 | O49: 0 | P49: =SUM(D49:O49) -> 0
A50: Fuel Used (litres) | C50: litres | D50: 0 | E50: 0 | F50: 0 | G50: 0 | H50: 0 | I50: 0 | J50: 0 | K50: 0 | L50: 0 | M50: 0 | N50: 0 | O50: 0 | P50: =SUM(D50:O50) -> 0
A51: Cost of fuel | C51: Mk | D51: 0 | E51: 0 | F51: 0 | G51: 0 | H51: 0 | I51: 0 | J51: 0 | K51: 0 | L51: 0 | M51: 0 | N51: 0 | O51: 0 | P51: =SUM(D51:O51) -> 0
A52: Maintenance | C52: Mk | D52: 0 | E52: 0 | F52: 0 | G52: 0 | H52: 0 | I52: 0 | J52: 0 | K52: 0 | L52: 0 | M52: 0 | N52: 0 | O52: 0 | P52: =SUM(D52:O52) -> 0
A53: Salaries and Wages
A54: Staff Costs | C54: MK | D54: 0 | E54: 0 | F54: 0 | G54: 0 | H54: 0 | I54: 0 | J54: 0 | K54: 0 | L54: 0 | M54: 0 | N54: 0 | O54: 0 | P54: =SUM(D54:O54) -> 0
A55: Wages | C55: MK | D55: 0 | E55: 0 | F55: 0 | G55: 0 | H55: 0 | I55: 0 | J55: 0 | K55: 0 | L55: 0 | M55: 0 | N55: 0 | O55: 0 | P55: =SUM(D55:O55) -> 0
A56: Other Overhead Costs | C56: MK | D56: 0 | E56: 0 | F56: 0 | G56: 0 | H56: 0 | I56: 0 | J56: 0 | K56: 0 | L56: 0 | M56: 0 | N56: 0 | O56: 0 | P56: =SUM(D56:O56) -> 0
A57: Operating Costs
A58: Total Operating Costs | C58: MK | D58: =D41+D46+D51+D52+D54+D55+D56 -> 557706.78 | E58: =E41+E46+E51+E52+E54+E55+E56 -> 528418.5 | F58: =F41+F46+F51+F52+F54+F55+F56 -> 476190.34 | G58: =G41+G46+G51+G52+G54+G55+G56 -> 573031.63 | H58: =H41+H46+H51+H52+H54+H55+H56 -> 602153.87 | I58: =I41+I46+I51+I52+I54+I55+I56 -> 510370.45 | J58: =J41+J46+J51+J52+J54+J55+J56 -> 565632.58 | K58: =K41+K46+K51+K52+K54+K55+K56 -> 499667.15 | ... O58: =O41+O46+O51+O52+O54+O55+O56 -> 510391.04 | P58: =SUM(D58:O58) -> 6324191.8
A59: Cost/Vol. Produced | C59: Mk/m3 | D59: =IFERROR(D58/D9,0) -> 172.77162 | E59: =IFERROR(E58/E9,0) -> 109.85832 | F59: =IFERROR(F58/F9,0) -> 118.98809 | G59: =IFERROR(G58/G9,0) -> 121.66277 | H59: =IFERROR(H58/H9,0) -> 121.1821 | I59: =IFERROR(I58/I9,0) -> 99.89635 | J59: =IFERROR(J58/J9,0) -> 126.2291 | K59: =IFERROR(K58/K9,0) -> 137.46001 | ... P59: =IFERROR(P58/P9,0) -> 127.54758
A60: Cost/Vol. Billed | C60: Mk/m3 | D60: =IFERROR(D58/D22,0) -> 255.50063 | E60: =IFERROR(E58/E22,0) -> 157.01507 | F60: =IFERROR(F58/F22,0) -> 195.15198 | G60: =IFERROR(G58/G22,0) -> 137.77117 | H60: =IFERROR(H58/H22,0) -> 167.3812 | I60: =IFERROR(I58/I22,0) -> 108.55712 | J60: =IFERROR(J58/J22,0) -> 190.9953 | K60: =IFERROR(K58/K22,0) -> 150.64281 | ... P60: =IFERROR(P58/P22,0) -> 167.78872
A61: Permanent Staff Employed | C61: No | D61: 2 | E61: 3 | F61: 3 | G61: 3 | H61: 3 | I61: 3 | J61: 3 | K61: 3 | L61: 3 | M61: 3 | N61: 3 | O61: 3 | P61: =O61 -> 3
A62: Staff/Vol.1000m3 of Volume Produced/hour (12 hour day) | C62: No/1000m3 | D62: =IFERROR((D61*1000*31)/D9,0) -> 19.206939 | E62: =IFERROR((E61*1000*31)/E9,0) -> 19.334719 | F62: =IFERROR((F61*1000*31)/F9,0) -> 23.238381 | G62: =IFERROR((G61*1000*31)/G9,0) -> 19.745223 | H62: =IFERROR((H61*1000*31)/H9,0) -> 18.716039 | I62: =IFERROR((I61*1000*31)/I9,0) -> 18.203171 | J62: =IFERROR((J61*1000*31)/J9,0) -> 20.754296 | K62: =IFERROR((K61*1000*31)/K9,0) -> 25.584594 | ... P62: =IFERROR((P61*1000*31)/P9,0) -> 1.8756429
A63: Temporary Staff Employed | C63: No | D63: 5 | E63: 5 | F63: 5 | G63: 5 | H63: 5 | I63: 5 | J63: 5 | K63: 5 | L63: 5 | M63: 5 | N63: 5 | O63: 5 | P63: =O63 -> 5
A65: Water Connections and Disconnections
A66: New Individual Water Connections | B66: Brought Forward | C66: No | D66: 1 | E66: 0 | F66: 1 | G66: 3 | H66: 3 | I66: 1 | J66: 3 | K66: 3 | L66: 3 | M66: 5 | N66: 6 | O66: 9 | P66: =D66 -> 1
B67: Applied this Month | C67: No | D67: 2 | E67: 1 | F67: 2 | G67: 0 | H67: 2 | I67: 6 | J67: 2 | K67: 0 | L67: 2 | M67: 3 | N67: 3 | O67: 2 | P67: =SUM(D67:O67) -> 25
B68: Done this Month Postpaid | C68: No | D68: 3 | E68: 0 | F68: 0 | G68: 0 | H68: 4 | I68: 4 | J68: 2 | K68: 0 | L68: 0 | M68: 2 | N68: 0 | O68: 2 | P68: =SUM(D68:O68) -> 17
B69: Done this Month Prepaid | C69: No | D69: 0 | E69: 0 | F69: 0 | G69: 0 | H69: 0 | I69: 0 | J69: 0 | K69: 0 | L69: 0 | M69: 0 | N69: 0 | O69: 0 | P69: =SUM(D69:O69) -> 0
B70: Total Done | C70: No | D70: =D68+D69 -> 3 | E70: =E68+E69 -> 0 | F70: =F68+F69 -> 0 | G70: =G68+G69 -> 0 | H70: =H68+H69 -> 4 | I70: =I68+I69 -> 4 | J70: =J68+J69 -> 2 | K70: =K68+K69 -> 0 | ... P70: =P68+P69 -> 17
B71: Carried Forward | C71: No | D71: =D66+D67-D70 -> 0 | E71: =E66+E67-E70 -> 1 | F71: =F66+F67-F70 -> 3 | G71: =G66+G67-G70 -> 3 | H71: =H66+H67-H70 -> 1 | I71: =I66+I67-I70 -> 3 | J71: =J66+J67-J70 -> 3 | K71: =K66+K67-K70 -> 3 | ... P71: =P66+P67-P70 -> 9
A72: New Institutional Water Connections | B72: Brought Forward | C72: No | D72: 0 | E72: 0 | F72: 0 | G72: 0 | H72: 0 | I72: 0 | J72: 0 | K72: 0 | L72: 0 | M72: 0 | N72: 0 | O72: 0 | P72: =D72 -> 0
B73: Applied this Month | C73: No | D73: 0 | E73: 0 | F73: 0 | G73: 0 | H73: 0 | I73: 0 | J73: 0 | K73: 0 | L73: 0 | M73: 0 | N73: 0 | O73: 0 | P73: =SUM(D73:O73) -> 0
B74: Done this Month Postpaid | C74: No | D74: 0 | E74: 0 | F74: 0 | G74: 0 | H74: 0 | I74: 0 | J74: 0 | K74: 0 | L74: 0 | M74: 0 | N74: 0 | O74: 0 | P74: =SUM(D74:O74) -> 0
B75: Done this Month Prepaid | C75: No | D75: 0 | E75: 0 | F75: 0 | G75: 0 | H75: 0 | I75: 0 | J75: 0 | K75: 0 | L75: 0 | M75: 0 | N75: 0 | O75: 0 | P75: =SUM(D75:O75) -> 0
B76: Total Done | C76: No | D76: =D74+D75 -> 0 | E76: =E74+E75 -> 0 | F76: =F74+F75 -> 0 | G76: =G74+G75 -> 0 | H76: =H74+H75 -> 0 | I76: =I74+I75 -> 0 | J76: =J74+J75 -> 0 | K76: =K74+K75 -> 0 | ... P76: =P74+P75 -> 0
B77: Carried Forward | C77: No | D77: =D72+D73-D76 -> 0 | E77: =E72+E73-E76 -> 0 | F77: =F72+F73-F76 -> 0 | G77: =G72+G73-G76 -> 0 | H77: =H72+H73-H76 -> 0 | I77: =I72+I73-I76 -> 0 | J77: =J72+J73-J76 -> 0 | K77: =K72+K73-K76 -> 0 | ... P77: =P72+P73-P76 -> 0
A78: New Commercial/Industrial Water Connections | B78: Brought Forward | C78: No | D78: 0 | E78: 0 | F78: 0 | G78: 0 | H78: 0 | I78: 0 | J78: 0 | K78: 0 | L78: 0 | M78: 0 | N78: 0 | O78: 0 | P78: =D78 -> 0
B79: Applied this Month | C79: No | D79: 0 | E79: 0 | F79: 0 | G79: 0 | H79: 0 | I79: 0 | J79: 0 | K79: 0 | L79: 0 | M79: 0 | N79: 0 | O79: 0 | P79: =SUM(D79:O79) -> 0
B80: Done this Month Postpaid | C80: No | D80: 0 | E80: 0 | F80: 0 | G80: 0 | H80: 0 | I80: 0 | J80: 0 | K80: 0 | L80: 0 | M80: 0 | N80: 0 | O80: 0 | P80: =SUM(D80:O80) -> 0
B81: Done this Month Prepaid | C81: No | D81: 0 | E81: 0 | F81: 0 | G81: 0 | H81: 0 | I81: 0 | J81: 0 | K81: 0 | L81: 0 | M81: 0 | N81: 0 | O81: 0 | P81: =SUM(D81:O81) -> 0
B82: Total Done | C82: No | D82: =D80+D81 -> 0 | E82: =E80+E81 -> 0 | F82: =F80+F81 -> 0 | G82: =G80+G81 -> 0 | H82: =H80+H81 -> 0 | I82: =I80+I81 -> 0 | J82: =J80+J81 -> 0 | K82: =K80+K81 -> 0 | ... O82: =O80+O81 -> 0 | P82: =P81+P80 -> 0
B83: Carried Forward | C83: No | D83: =D78+D79-D82 -> 0 | E83: =E78+E79-E82 -> 0 | F83: =F78+F79-F82 -> 0 | G83: =G78+G79-G82 -> 0 | H83: =H78+H79-H82 -> 0 | I83: =I78+I79-I82 -> 0 | J83: =J78+J79-J82 -> 0 | K83: =K78+K79-K82 -> 0 | ... P83: =P78+P79-P82 -> 0
A84: New CWP | B84: Brought Forward | C84: No | D84: 0 | E84: 0 | F84: 0 | G84: 0 | H84: 0 | I84: 0 | J84: 0 | K84: 0 | L84: 0 | M84: 0 | N84: 0 | O84: 0 | P84: =D84 -> 0
B85: Applied this Month | C85: No | D85: 0 | E85: 0 | F85: 0 | G85: 0 | H85: 0 | I85: 0 | J85: 0 | K85: 0 | L85: 0 | M85: 0 | N85: 0 | O85: 0 | P85: =SUM(D85:O85) -> 0
B86: Done this Month Postpaid | C86: No | D86: 0 | E86: 0 | F86: 0 | G86: 0 | H86: 0 | I86: 0 | J86: 0 | K86: 0 | L86: 0 | M86: 0 | N86: 0 | O86: 0 | P86: =SUM(D86:O86) -> 0
B87: Done this Month Prepaid | C87: No | D87: 0 | E87: 0 | F87: 0 | G87: 0 | H87: 0 | I87: 0 | J87: 0 | K87: 0 | L87: 0 | M87: 0 | N87: 0 | O87: 0 | P87: =SUM(D87:O87) -> 0
B88: Total Done | C88: No | D88: =D86+D87 -> 0 | E88: =E86+E87 -> 0 | F88: =F86+F87 -> 0 | G88: =G86+G87 -> 0 | H88: =H86+H87 -> 0 | I88: =I86+I87 -> 0 | J88: =J86+J87 -> 0 | K88: =K86+K87 -> 0 | ... O88: =O86+O87 -> 0 | P88: =SUM(D88:O88) -> 0
B89: Carried Forward | C89: No | D89: =D84+D85-D88 -> 0 | E89: =E84+E85-E88 -> 0 | F89: =F84+F85-F88 -> 0 | G89: =G84+G85-G88 -> 0 | H89: =H84+H85-H88 -> 0 | I89: =I84+I85-I88 -> 0 | J89: =J84+J85-J88 -> 0 | K89: =K84+K85-K88 -> 0 | ... O89: =O84+O85-O88 -> 0 | P89: =P84+P85-P86-P87 -> 0
A90: Aggregated New Water connections | B90: Brought Forward | C90: No | D90: =D66+D72+D78+D84 -> 1 | E90: =E66+E72+E78+E84 -> 0 | F90: =F66+F72+F78+F84 -> 1 | G90: =G66+G72+G78+G84 -> 3 | H90: =H66+H72+H78+H84 -> 3 | I90: =I66+I72+I78+I84 -> 1 | J90: =J66+J72+J78+J84 -> 3 | K90: =K66+K72+K78+K84 -> 3 | ... O90: =O66+O72+O78+O84 -> 9 | P90: =D90 -> 1
B91: Applied this Month | C91: No | D91: =D67+D73+D79+D85 -> 2 | E91: =E67+E73+E79+E85 -> 1 | F91: =F67+F73+F79+F85 -> 2 | G91: =G67+G73+G79+G85 -> 0 | H91: =H67+H73+H79+H85 -> 2 | I91: =I67+I73+I79+I85 -> 6 | J91: =J67+J73+J79+J85 -> 2 | K91: =K67+K73+K79+K85 -> 0 | ... O91: =O67+O73+O79+O85 -> 2 | P91: =SUM(D91:O91) -> 25
B92: Done this Month Postpaid | C92: No | D92: =D68+D74+D80+D86 -> 3 | E92: =E68+E74+E80+E86 -> 0 | F92: =F68+F74+F80+F86 -> 0 | G92: =G68+G74+G80+G86 -> 0 | H92: =H68+H74+H80+H86 -> 4 | I92: =I68+I74+I80+I86 -> 4 | J92: =J68+J74+J80+J86 -> 2 | K92: =K68+K74+K80+K86 -> 0 | ... O92: =O68+O74+O80+O86 -> 2 | P92: =SUM(D92:O92) -> 17
B93: Done this Month Prepaid | D93: =D69+D75+D81+D87 -> 0 | E93: =E69+E75+E81+E87 -> 0 | F93: =F69+F75+F81+F87 -> 0 | G93: =G69+G75+G81+G87 -> 0 | H93: =H69+H75+H81+H87 -> 0 | I93: =I69+I75+I81+I87 -> 0 | J93: =J69+J75+J81+J87 -> 0 | K93: =K69+K75+K81+K87 -> 0 | ... O93: =O69+O75+O81+O87 -> 0 | P93: =SUM(D93:O93) -> 0
B94: Total Done | C94: No | D94: =D93+D92 -> 3 | E94: =E93+E92 -> 0 | F94: =F93+F92 -> 0 | G94: =G93+G92 -> 0 | H94: =H93+H92 -> 4 | I94: =I93+I92 -> 4 | J94: =J93+J92 -> 2 | K94: =K93+K92 -> 0 | ... P94: =P93+P92 -> 17
B95: Carried Forward | C95: No | D95: =D90+D91-D94 -> 0 | E95: =E90+E91-E94 -> 1 | F95: =F90+F91-F94 -> 3 | G95: =G90+G91-G94 -> 3 | H95: =H90+H91-H94 -> 1 | I95: =I90+I91-I94 -> 3 | J95: =J90+J91-J94 -> 3 | K95: =K90+K91-K94 -> 3 | ... P95: =P90+P91-P94 -> 9
A97: Prepaid Metering
A98: Prepaid Meters Installed | C98: No | D98: 0 | E98: 0 | F98: 0 | G98: 0 | H98: 0 | I98: 0 | J98: 0 | K98: 0 | L98: 0 | M98: 0 | N98: 0 | O98: 0 | P98: =SUM(D98:O98) -> 0
A100: Active and Disconnected Accounts
A101: Disconnected Individual Accounts | C101: No | D101: 105 | E101: 109 | F101: 108 | G101: 108 | H101: 107 | I101: 111 | J101: 112 | K101: 113 | L101: 136 | M101: 144 | N101: 137 | O101: 132 | P101: =O101 -> 132
A102: Disconnected institutional Accounts | C102: No | D102: 10 | E102: 10 | F102: 9 | G102: 9 | H102: 9 | I102: 9 | J102: 8 | K102: 8 | L102: 8 | M102: 8 | N102: 7 | O102: 8 | P102: =O102 -> 8
A103: Disconnected Commercial/Industrial Accounts | C103: No | D103: 0 | E103: 0 | F103: 0 | G103: 0 | H103: 0 | I103: 0 | J103: 0 | K103: 1 | L103: 1 | M103: 2 | N103: 3 | O103: 3 | P103: =O103 -> 3
A104: Disconnected CWP | C104: No | D104: 0 | E104: 0 | F104: 0 | G104: 0 | H104: 0 | I104: 0 | J104: 0 | K104: 0 | L104: 1 | M104: 1 | N104: 1 | O104: 1 | P104: =O104 -> 1
A105: Total Disconnected Accounts | C105: No | D105: =SUM(D101:D104) -> 115 | E105: =SUM(E101:E104) -> 119 | F105: =SUM(F101:F104) -> 117 | G105: =SUM(G101:G104) -> 117 | H105: =SUM(H101:H104) -> 116 | I105: =SUM(I101:I104) -> 120 | J105: =SUM(J101:J104) -> 120 | K105: =SUM(K101:K104) -> 122 | ... O105: =SUM(O101:O104) -> 144 | P105: =O105 -> 144
A106: Postpaid Consumers
...

Sheet Chiradzulu
A1: SOUTHERN REGION WATER BOARD
A3: MONTHLY REPORTS - 2024/2025
A4: ZOMBA ZONE
A5: CHIRADZULU SCHEME
A7: PARAMETERS | C7: UNITS | D7: APRIL | E7: MAY | F7: JUNE | G7: JULY | H7: AUGUST | I7: SEPTEMBER | J7: OCTOBER | K7: NOVEMBER | L7: DECEMBER | M7: JANUARY | N7: FEBRUARY | O7: MARCH | P7: TOTALS
A8: PRODUCTION
A9: Volume Produced | C9: m3 | D9: 2480 | E9: 2258 | F9: 7389 | G9: 1944 | H9: 1660 | I9: 1556 | J9: 1442 | K9: 1140 | L9: 1021 | M9: 2544 | N9: 2024 | O9: 2702 | P9: =SUM(D9:O9) -> 28160
A10: REVENUE WATER - POSTPAID
A11: Volume Billed Individuals | C11: m3 | D11: 1152 | E11: 1160 | F11: 1218 | G11: 979 | H11: 867 | I11: 890 | J11: 780 | K11: 580 | L11: 617 | M11: 637 | N11: 1143 | O11: 325 | P11: =SUM(D11:O11) -> 10348
A12: Volume Billed CWPs | C12: m3 | D12: 0 | E12: 0 | F12: 0 | G12: 0 | H12: 0 | I12: 0 | J12: 0 | K12: 0 | L12: 0 | M12: 0 | N12: 0 | O12: 0 | P12: =SUM(D12:O12) -> 0
A13: Volume Billed Institutions | C13: m3 | D13: 7 | E13: 11 | F13: 7 | G13: 63 | H13: 7 | I13: 20 | J13: 15 | K13: 11 | L13: 11 | M13: 13 | N13: 7 | O13: 9 | P13: =SUM(D13:O13) -> 181
A14: Volume Billed Commercial/Industrial | C14: m3 | D14: 27 | E14: 24 | F14: 29 | G14: 43 | H14: 64 | I14: 18 | J14: 18 | K14: 8 | L14: 11 | M14: 8 | N14: 30 | O14: 8 | P14: =SUM(D14:O14) -> 288
A15: Total Volume Billed Post Paid | C15: m3 | D15: =SUM(D11:D14) -> 1186 | E15: =SUM(E11:E14) -> 1195 | F15: =SUM(F11:F14) -> 1254 | G15: =SUM(G11:G14) -> 1085 | H15: =SUM(H11:H14) -> 938 | I15: =SUM(I11:I14) -> 928 | J15: =SUM(J11:J14) -> 813 | K15: =SUM(K11:K14) -> 599 | ... P15: =SUM(P11:P14) -> 10817
A16: REVENUE WATER - PREPAID
A17: Individuals | C17: m3 | D17: 495.5 | E17: 507.3 | F17: 4451.1 | G17: 451.2 | H17: 315.1 | I17: 371.4 | J17: 323.4 | K17: 241.9 | L17: 254 | M17: 1556.8 | N17: 632.9 | O17: 2000.5 | P17: =SUM(D17:O17) -> 11601.1
A18: CWPs | C18: m3 | D18: 0 | E18: 0 | F18: 0 | G18: 0 | H18: 0 | I18: 0 | J18: 0 | K18: 0 | L18: 0 | M18: 0 | N18: 0 | O18: 0 | P18: =SUM(D18:O18) -> 0
A19: Institutions | C19: m3 | D19: 137.8 | E19: 132.5 | F19: 747.7 | G19: 154.5 | H19: 266.5 | I19: 95.1 | J19: 150.6 | K19: 47.1 | L19: 70.2 | M19: 209.8 | N19: 111.7 | O19: 192.5 | P19: =SUM(D19:O19) -> 2316
A20: Commercial/Industrial | C20: m3 | D20: 7 | E20: 9.3 | F20: 9.3 | G20: 11.6 | H20: 0 | I20: 0 | J20: 6.3 | K20: 0 | L20: 8.5 | M20: 0 | N20: 27.2 | O20: 25.3 | P20: =SUM(D20:O20) -> 104.5
A21: Total Volume Prepaid | C21: m3 | D21: =SUM(D17:D20) -> 640.3 | E21: =SUM(E17:E20) -> 649.1 | F21: =SUM(F17:F20) -> 5208.1 | G21: =SUM(G17:G20) -> 617.3 | H21: =SUM(H17:H20) -> 581.6 | I21: =SUM(I17:I20) -> 466.5 | J21: =SUM(J17:J20) -> 480.3 | K21: =SUM(K17:K20) -> 289 | ... P21: =SUM(P17:P20) -> 14021.6
A22: TOTAL REVENUE WATER | C22: m3 | D22: =D21+D15 -> 1826.3 | E22: =E21+E15 -> 1844.1 | F22: =F21+F15 -> 6462.1 | G22: =G21+G15 -> 1702.3 | H22: =H21+H15 -> 1519.6 | I22: =I21+I15 -> 1394.5 | J22: =J21+J15 -> 1293.3 | K22: =K21+K15 -> 888 | ... P22: =P21+P15 -> 24838.6
A24: Non-Revenue Water (NRW) | B24: Volume | C24: m3 | D24: =D9-D22 -> 653.7 | E24: =E9-E22 -> 413.9 | F24: =F9-F22 -> 926.9 | G24: =G9-G22 -> 241.7 | H24: =H9-H22 -> 140.4 | I24: =I9-I22 -> 161.5 | J24: =J9-J22 -> 148.7 | K24: =K9-K22 -> 252 | ... P24: =P9-P22 -> 3321.4
B25: Percentage | C25: % | D25: =IFERROR(D24/D9,0) -> 0.26358871 | E25: =E24/E9 -> 0.18330381 | F25: =F24/F9 -> 0.12544323 | G25: =IFERROR(G24/G9,0) -> 0.12433128 | H25: =IFERROR(H24/H9,0) -> 0.084578313 | I25: =IFERROR(I24/I9,0) -> 0.10379177 | J25: =IFERROR(J24/J9,0) -> 0.10312067 | K25: =IFERROR(K24/K9,0) -> 0.22105263 | L25: =IFERROR(L24/L9,0) -> 0.048285994 | M25: =IFERROR(M24/M9,0) -> 0.046933962 | N25: =IFERROR(N24/N9,0) -> 0.035671937 | O25: =IFERROR(O24/O9,0) -> 0.052442635 | P25: =IF(P9,P24/P9,"") -> 0.11794744
A26: OPERATING EXPENSES
A27: Chemicals
A28: Chemical | B28: Rate(MK/kg)
A29: Chlorine | B29: 7400 | C29: kg | D29: 10.2 | E29: 9.5 | F29: 7.5 | G29: 7.75 | H29: 5.5 | I29: 6.5 | J29: 6.7 | K29: 5.5 | L29: 4.5 | M29: 8.2 | N29: 7.5 | O29: 7.55 | P29: =SUM(D29:O29) -> 86.9
C30: kg/mg litre | D30: =IFERROR(D29/(D9/1000),0) -> 4.1129032 | E30: =IFERROR(E29/(E9/1000),0) -> 4.2072631 | F30: =IFERROR(F29/(F9/1000),0) -> 1.0150223 | G30: =IFERROR(G29/(G9/1000),0) -> 3.9866255 | H30: =IFERROR(H29/(H9/1000),0) -> 3.313253 | I30: =IFERROR(I29/(I9/1000),0) -> 4.1773779 | J30: =IFERROR(J29/(J9/1000),0) -> 4.6463245 | K30: =IFERROR(K29/(K9/1000),0) -> 4.8245614 | ... P30: =IFERROR(P29/(P9/1000),0) -> 3.0859375
A31: Aluminium sulphate | B31: 1900 | C31: kg | D31: 0 | E31: 0 | F31: 0 | G31: 0 | H31: 0 | I31: 0 | J31: 0 | K31: 0 | L31: 0 | M31: 0 | N31: 0 | O31: 0 | P31: =SUM(D31:O31) -> 0
C32: kg/mg litre | D32: =IFERROR(D31/(D9/1000),0) -> 0 | E32: =IFERROR(E31/(E9/1000),0) -> 0 | F32: =IFERROR(F31/(F9/1000),0) -> 0 | G32: =IFERROR(G31/(G9/1000),0) -> 0 | H32: =IFERROR(H31/(H9/1000),0) -> 0 | I32: =IFERROR(I31/(I9/1000),0) -> 0 | J32: =IFERROR(J31/(J9/1000),0) -> 0 | K32: =IFERROR(K31/(K9/1000),0) -> 0 | ... P32: =IFERROR(P31/(P9/1000),0) -> 0
A33: Soda | B33: 1900 | C33: kg | D33: 0 | E33: 0 | F33: 0 | G33: 0 | H33: 0 | I33: 0 | J33: 0 | K33: 0 | L33: 0 | M33: 0 | N33: 0 | O33: 0 | P33: =SUM(D33:O33) -> 0
C34: kg/mg litre | D34: =IFERROR(D33/(D9/1000),0) -> 0 | E34: =IFERROR(E33/(E9/1000),0) -> 0 | F34: =IFERROR(F33/(F9/1000),0) -> 0 | G34: =IFERROR(G33/(G9/1000),0) -> 0 | H34: =IFERROR(H33/(H9/1000),0) -> 0 | I34: =IFERROR(I33/(I9/1000),0) -> 0 | J34: =IFERROR(J33/(J9/1000),0) -> 0 | K34: =IFERROR(K33/(K9/1000),0) -> 0 | ... P34: =IFERROR(P33/(P9/1000),0) -> 0
A35: Algae floc | B35: =745345.16/200 -> 3726.7258 | C35: litres | D35: 0 | E35: 0 | F35: 0 | G35: 0 | H35: 0 | I35: 0 | J35: 0 | K35: 0 | L35: 0 | M35: 0 | N35: 0 | O35: 0
C36: litres/mg litre
A37: Sud floc | B37: =790318.72/200 -> 3951.5936 | C37: litres | D37: 0 | E37: 0 | F37: 0 | G37: 0 | H37: 0 | I37: 0 | J37: 0 | K37: 0 | L37: 0 | M37: 0 | N37: 0 | O37: 0 | P37: =SUM(D37:O37) -> 0
C38: litres/mg litre | D38: =IFERROR(D37/(D9/1000),0) -> 0 | E38: =IFERROR(E37/(E9/1000),0) -> 0 | F38: =IFERROR(F37/(F9/1000),0) -> 0 | G38: =IFERROR(G37/(G9/1000),0) -> 0 | H38: =IFERROR(H37/(H9/1000),0) -> 0 | I38: =IFERROR(I37/(I9/1000),0) -> 0 | J38: =IFERROR(J37/(J9/1000),0) -> 0 | K38: =IFERROR(K37/(K9/1000),0) -> 0 | ... P38: =IFERROR(P37/(P9/1000),0) -> 0
A39: Potasium permanganate | B39: 1950 | C39: kg | D39: 0 | E39: 0 | F39: 0 | G39: 0 | H39: 0 | I39: 0 | J39: 0 | K39: 0 | L39: 0 | M39: 0 | N39: 0 | O39: 0 | P39: =SUM(D39:O39) -> 0
C40: kg/mg litre | D40: =IFERROR(D39/(D9/1000),0) -> 0 | E40: =IFERROR(E39/(E9/1000),0) -> 0 | F40: =IFERROR(F39/(F9/1000),0) -> 0 | G40: =IFERROR(G39/(G9/1000),0) -> 0 | H40: =IFERROR(H39/(H9/1000),0) -> 0 | I40: =IFERROR(I39/(I9/1000),0) -> 0 | J40: =IFERROR(J39/(J9/1000),0) -> 0 | K40: =IFERROR(K39/(K9/1000),0) -> 0 | ... P40: =IFERROR(P39/(P9/1000),0) -> 0
A41: Cost of Chemicals | C41: Mk | D41: =(D29*$B29)+(D31*$B31)+(D33*$B33)+(D35*$B35)+(D37*$B37)+(D39*$B39) -> 75480 | E41: =(E29*$B29)+(E31*$B31)+(E33*$B33)+(E35*$B35)+(E37*$B37)+(E39*$B39) -> 70300 | F41: =(F29*$B29)+(F31*$B31)+(F33*$B33)+(F35*$B35)+(F37*$B37)+(F39*$B39) -> 55500 | G41: =(G29*$B29)+(G31*$B31)+(G33*$B33)+(G35*$B35)+(G37*$B37)+(G39*$B39) -> 57350 | H41: =(H29*$B29)+(H31*$B31)+(H33*$B33)+(H35*$B35)+(H37*$B37)+(H39*$B39) -> 40700 | I41: =(I29*$B29)+(I31*$B31)+(I33*$B33)+(I35*$B35)+(I37*$B37)+(I39*$B39) -> 48100 | J41: =(J29*$B29)+(J31*$B31)+(J33*$B33)+(J35*$B35)+(J37*$B37)+(J39*$B39) -> 49580 | K41: =(K29*$B29)+(K31*$B31)+(K33*$B33)+(K35*$B35)+(K37*$B37)+(K39*$B39) -> 40700 | ... O41: =(O29*$B29)+(O31*$B31)+(O33*$B33)+(O35*$B35)+(O37*$B37)+(O39*$B39) -> 55870 | P41: =SUM(D41:O41) -> 643060
A42: Cost/vol. Produced (chemicals) | C42: Mk/m3 | D42: =IFERROR(D41/D9,0) -> 30.435484 | E42: =IFERROR(E41/E9,0) -> 31.133747 | F42: =IFERROR(F41/F9,0) -> 7.5111652 | G42: =IFERROR(G41/G9,0) -> 29.501029 | H42: =IFERROR(H41/H9,0) -> 24.518072 | I42: =IFERROR(I41/I9,0) -> 30.912596 | J42: =IFERROR(J41/J9,0) -> 34.382802 | K42: =IFERROR(K41/K9,0) -> 35.701754 | ... P42: =IFERROR(P41/P9,0) -> 22.835938
A43: Power
A44: Power Usage | C44: Kw | D44: 38.31 | E44: 18.34 | F44: 21.59 | G44: 25.3 | H44: 26.36 | I44: 27.19 | J44: 17.72 | K44: 23.66 | L44: 14.15 | M44: 17.22 | N44: 35.1 | O44: 13.48 | P44: =SUM(D44:O44) -> 278.42
A45: Power/ Vol. Produced | C45: Kw/m3 | D45: =IFERROR(D44/D9,0) -> 0.015447581 | E45: =IFERROR(E44/E9,0) -> 0.0081222321 | F45: =IFERROR(F44/F9,0) -> 0.0029219109 | G45: =IFERROR(G44/G9,0) -> 0.013014403 | H45: =IFERROR(H44/H9,0) -> 0.015879518 | I45: =IFERROR(I44/I9,0) -> 0.017474293 | J45: =IFERROR(J44/J9,0) -> 0.012288488 | K45: =IFERROR(K44/K9,0) -> 0.020754386 | ... P45: =IFERROR(P44/P9,0) -> 0.0098870739
A46: Cost of Power | C46: Mk | D46: =IF(D44=0,0,IF(D44>=0,0+(D44*202.25)+23390)*1.165) -> 36276 | E46: =IF(E44=0,0,IF(E44>=0,0+(E44*202.25)+23390)*1.165) -> 31570.644 | F46: =IF(F44=0,0,IF(F44>=0,0+(F44*202.25)+23390)*1.165) -> 32336.413 | G46: =IF(G44=0,0,IF(G44>=0,0+(G44*202.25)+23390)*1.165) -> 33210.568 | H46: =IF(H44=0,0,IF(H44>=0,0+(H44*202.25)+23390)*1.165) -> 33460.326 | I46: =IF(I44=0,0,IF(I44>=0,0+(I44*202.25)+23390)*1.165) -> 33655.892 | J46: =IF(J44=0,0,IF(J44>=0,0+(J44*202.25)+23390)*1.165) -> 31424.559 | K46: =IF(K44=0,0,IF(K44>=0,0+(K44*202.25)+23390)*1.165) -> 32824.149 | ... O46: =IF(O44=0,0,IF(O44>=0,0+(O44*202.25)+23390)*1.165) -> 30425.524 | P46: =SUM(D46:O46) -> 392593.87
A47: Cost/vol. Produced | C47: Mk/m3 | D47: =IFERROR(D46/D9,0) -> 14.627419 | E47: =IFERROR(E46/E9,0) -> 13.981685 | F47: =IFERROR(F46/F9,0) -> 4.3762908 | G47: =IFERROR(G46/G9,0) -> 17.083625 | H47: =IFERROR(H46/H9,0) -> 20.156823 | I47: =IFERROR(I46/I9,0) -> 21.629751 | J47: =IFERROR(J46/J9,0) -> 21.792343 | K47: =IFERROR(K46/K9,0) -> 28.793113 | ... P47: =IFERROR(P46/P9,0) -> 13.941544
A48: Plant and Vehicle Maintenance
A49: Distances covered | C49: km | D49: 0 | E49: 0 | F49: 0 | G49: 0 | H49: 0 | I49: 0 | J49: 0 | K49: 0 | L49: 0 | M49: 0 | N49: 0 | O49: 0 | P49: =SUM(D49:O49) -> 0
A50: Fuel Used (litres) | C50: litres | D50: 0 | E50: 0 | F50: 0 | G50: 0 | H50: 0 | I50: 0 | J50: 0 | K50: 0 | L50: 0 | M50: 0 | N50: 0 | O50: 0 | P50: =SUM(D50:O50) -> 0
A51: Cost of fuel | C51: Mk | D51: 0 | E51: 0 | F51: 0 | G51: 0 | H51: 0 | I51: 0 | J51: 0 | K51: 0 | L51: 0 | M51: 0 | N51: 0 | O51: 0 | P51: =SUM(D51:O51) -> 0
A52: Maintenance | C52: Mk | D52: 0 | E52: 0 | F52: 0 | G52: 0 | H52: 0 | I52: 0 | J52: 0 | K52: 0 | L52: 0 | M52: 0 | N52: 0 | O52: 0 | P52: =SUM(D52:O52) -> 0
A53: Salaries and Wages
A54: Staff Costs | C54: MK | D54: 0 | E54: 0 | F54: 0 | G54: 0 | H54: 0 | I54: 0 | J54: 0 | K54: 0 | L54: 0 | M54: 0 | N54: 0 | O54: 0 | P54: =SUM(D54:O54) -> 0
A55: Wages | C55: MK | D55: 0 | E55: 0 | F55: 0 | G55: 0 | H55: 0 | I55: 0 | J55: 0 | K55: 0 | L55: 0 | M55: 0 | N55: 0 | O55: 0 | P55: =SUM(D55:O55) -> 0
A56: Other Overhead Costs | C56: MK | D56: 0 | E56: 0 | F56: 0 | G56: 0 | H56: 0 | I56: 0 | J56: 0 | K56: 0 | L56: 0 | M56: 0 | N56: 0 | O56: 0 | P56: =SUM(D56:O56) -> 0
A57: Operating Costs
A58: Total Operating Costs | C58: MK | D58: =D41+D46+D51+D52+D54+D55+D56 -> 111756 | E58: =E41+E46+E51+E52+E54+E55+E56 -> 101870.64 | F58: =F41+F46+F51+F52+F54+F55+F56 -> 87836.413 | G58: =G41+G46+G51+G52+G54+G55+G56 -> 90560.568 | H58: =H41+H46+H51+H52+H54+H55+H56 -> 74160.326 | I58: =I41+I46+I51+I52+I54+I55+I56 -> 81755.892 | J58: =J41+J46+J51+J52+J54+J55+J56 -> 81004.559 | K58: =K41+K46+K51+K52+K54+K55+K56 -> 73524.149 | ... O58: =O41+O46+O51+O52+O54+O55+O56 -> 86295.524 | P58: =SUM(D58:O58) -> 1035653.9
A59: Cost/Vol. Produced | C59: Mk/m3 | D59: =IFERROR(D58/D9,0) -> 45.062903 | E59: =IFERROR(E58/E9,0) -> 45.115431 | F59: =IFERROR(F58/F9,0) -> 11.887456 | G59: =IFERROR(G58/G9,0) -> 46.584654 | H59: =IFERROR(H58/H9,0) -> 44.674895 | I59: =IFERROR(I58/I9,0) -> 52.542347 | J59: =IFERROR(J58/J9,0) -> 56.175145 | K59: =IFERROR(K58/K9,0) -> 64.494867 | ... P59: =IFERROR(P58/P9,0) -> 36.777481
A60: Cost/Vol. Billed | C60: Mk/m3 | D60: =IFERROR(D58/D22,0) -> 61.192575 | E60: =IFERROR(E58/E22,0) -> 55.241388 | F60: =IFERROR(F58/F22,0) -> 13.592549 | G60: =IFERROR(G58/G22,0) -> 53.198947 | H60: =IFERROR(H58/H22,0) -> 48.802531 | I60: =IFERROR(I58/I22,0) -> 58.627387 | J60: =IFERROR(J58/J22,0) -> 62.634005 | K60: =IFERROR(K58/K22,0) -> 82.797465 | ... P60: =IFERROR(P58/P22,0) -> 41.69534
A61: Permanent Staff Employed | C61: No | D61: 4 | E61: 4 | F61: 4 | G61: 4 | H61: 4 | I61: 4 | J61: 4 | K61: 4 | L61: 4 | M61: 4 | N61: 4 | O61: 4 | P61: =O61 -> 4
A62: Staff/Vol.1000m3 of Volume Produced/hour (12 hour day) | C62: No/1000m3 | D62: =IFERROR((D61*1000*31)/D9,0) -> 50 | E62: =IFERROR((E61*1000*31)/E9,0) -> 54.915855 | F62: =IFERROR((F61*1000*31)/F9,0) -> 16.781703 | G62: =IFERROR((G61*1000*31)/G9,0) -> 63.786008 | H62: =IFERROR((H61*1000*31)/H9,0) -> 74.698795 | I62: =IFERROR((I61*1000*31)/I9,0) -> 79.691517 | J62: =IFERROR((J61*1000*31)/J9,0) -> 85.991678 | K62: =IFERROR((K61*1000*31)/K9,0) -> 108.77193 | ... P62: =IFERROR((P61*1000*31)/P9,0) -> 4.4034091
A63: Temporary Staff Employed | C63: No | D63: 6 | E63: 6 | F63: 6 | G63: 6 | H63: 6 | I63: 6 | J63: 6 | K63: 6 | L63: 6 | M63: 6 | N63: 6 | O63: 6 | P63: =O63 -> 6
A65: Water Connections and Disconnections
A66: New Individual Water Connections | B66: Brought Forward | C66: No | D66: 1 | E66: 0 | F66: 2 | G66: 6 | H66: 6 | I66: 3 | J66: 3 | K66: 3 | L66: 3 | M66: 3 | N66: 2 | O66: 2 | P66: =D66 -> 1
B67: Applied this Month | C67: No | D67: 3 | E67: 2 | F67: 5 | G67: 0 | H67: 0 | I67: 0 | J67: 0 | K67: 0 | L67: 0 | M67: 1 | N67: 0 | O67: 10 | P67: =SUM(D67:O67) -> 21
B68: Done this Month Postpaid | C68: No | D68: 4 | E68: 0 | F68: 1 | G68: 0 | H68: 3 | I68: 0 | J68: 0 | K68: 0 | L68: 0 | M68: 2 | N68: 0 | O68: 0 | P68: =SUM(D68:O68) -> 10
B69: Done this Month Prepaid | C69: No | D69: 0 | E69: 0 | F69: 0 | G69: 0 | H69: 0 | I69: 0 | J69: 0 | K69: 0 | L69: 0 | M69: 0 | N69: 0 | O69: 0 | P69: =SUM(D69:O69) -> 0
B70: Total Done | C70: No | D70: =D68+D69 -> 4 | E70: =E68+E69 -> 0 | F70: =F68+F69 -> 1 | G70: =G68+G69 -> 0 | H70: =H68+H69 -> 3 | I70: =I68+I69 -> 0 | J70: =J68+J69 -> 0 | K70: =K68+K69 -> 0 | ... P70: =P68+P69 -> 10
B71: Carried Forward | C71: No | D71: =D66+D67-D70 -> 0 | E71: =E66+E67-E70 -> 2 | F71: =F66+F67-F70 -> 6 | G71: =G66+G67-G70 -> 6 | H71: =H66+H67-H70 -> 3 | I71: =I66+I67-I70 -> 3 | J71: =J66+J67-J70 -> 3 | K71: =K66+K67-K70 -> 3 | ... P71: =P66+P67-P70 -> 12
A72: New Institutional Water Connections | B72: Brought Forward | C72: No | D72: 0 | E72: 0 | F72: 0 | G72: 0 | H72: 0 | I72: 0 | J72: 0 | K72: 0 | L72: 0 | M72: 0 | N72: 0 | O72: 0 | P72: =D72 -> 0
B73: Applied this Month | C73: No | D73: 0 | E73: 0 | F73: 0 | G73: 0 | H73: 0 | I73: 0 | J73: 0 | K73: 0 | L73: 0 | M73: 0 | N73: 0 | O73: 0 | P73: =SUM(D73:O73) -> 0
B74: Done this Month Postpaid | C74: No | D74: 0 | E74: 0 | F74: 0 | G74: 0 | H74: 0 | I74: 0 | J74: 0 | K74: 0 | L74: 0 | M74: 0 | N74: 0 | O74: 0 | P74: =SUM(D74:O74) -> 0
B75: Done this Month Prepaid | C75: No | D75: 0 | E75: 0 | F75: 0 | G75: 0 | H75: 0 | I75: 0 | J75: 0 | K75: 0 | L75: 0 | M75: 0 | N75: 0 | O75: 0 | P75: =SUM(D75:O75) -> 0
B76: Total Done | C76: No | D76: =D74+D75 -> 0 | E76: =E74+E75 -> 0 | F76: =F74+F75 -> 0 | G76: =G74+G75 -> 0 | H76: =H74+H75 -> 0 | I76: =I74+I75 -> 0 | J76: =J74+J75 -> 0 | K76: =K74+K75 -> 0 | ... P76: =P74+P75 -> 0
B77: Carried Forward | C77: No | D77: =D72+D73-D76 -> 0 | E77: =E72+E73-E76 -> 0 | F77: =F72+F73-F76 -> 0 | G77: =G72+G73-G76 -> 0 | H77: =H72+H73-H76 -> 0 | I77: =I72+I73-I76 -> 0 | J77: =J72+J73-J76 -> 0 | K77: =K72+K73-K76 -> 0 | ... P77: =P72+P73-P76 -> 0
A78: New Commercial/Industrial Water Connections | B78: Brought Forward | C78: No | D78: 0 | E78: 0 | F78: 0 | G78: 0 | H78: 0 | I78: 0 | J78: 0 | K78: 0 | L78: 0 | M78: 0 | N78: 0 | O78: 0 | P78: =D78 -> 0
B79: Applied this Month | C79: No | D79: 0 | E79: 0 | F79: 0 | G79: 0 | H79: 3 | I79: 0 | J79: 0 | K79: 0 | L79: 0 | M79: 0 | N79: 0 | O79: 0 | P79: =SUM(D79:O79) -> 3
B80: Done this Month Postpaid | C80: No | D80: 0 | E80: 0 | F80: 0 | G80: 0 | H80: 3 | I80: 0 | J80: 0 | K80: 0 | L80: 0 | M80: 0 | N80: 0 | O80: 0 | P80: =SUM(D80:O80) -> 3
B81: Done this Month Prepaid | C81: No | D81: 0 | E81: 0 | F81: 0 | G81: 0 | H81: 0 | I81: 0 | J81: 0 | K81: 0 | L81: 0 | M81: 0 | N81: 0 | O81: 0 | P81: =SUM(D81:O81) -> 0
B82: Total Done | C82: No | D82: =D80+D81 -> 0 | E82: =E80+E81 -> 0 | F82: =F80+F81 -> 0 | G82: =G80+G81 -> 0 | H82: =H80+H81 -> 3 | I82: =I80+I81 -> 0 | J82: =J80+J81 -> 0 | K82: =K80+K81 -> 0 | ... O82: =O80+O81 -> 0 | P82: =P81+P80 -> 3
B83: Carried Forward | C83: No | D83: =D78+D79-D82 -> 0 | E83: =E78+E79-E82 -> 0 | F83: =F78+F79-F82 -> 0 | G83: =G78+G79-G82 -> 0 | H83: =H78+H79-H82 -> 0 | I83: =I78+I79-I82 -> 0 | J83: =J78+J79-J82 -> 0 | K83: =K78+K79-K82 -> 0 | ... P83: =P78+P79-P82 -> 0
A84: New CWP | B84: Brought Forward | C84: No | D84: 0 | E84: 0 | F84: 0 | G84: 0 | H84: 0 | I84: 0 | J84: 0 | K84: 0 | L84: 0 | M84: 0 | N84: 0 | O84: 0 | P84: =D84 -> 0
B85: Applied this Month | C85: No | D85: 0 | E85: 0 | F85: 0 | G85: 0 | H85: 0 | I85: 0 | J85: 0 | K85: 0 | L85: 0 | M85: 0 | N85: 0 | O85: 0 | P85: =SUM(D85:O85) -> 0
B86: Done this Month Postpaid | C86: No | D86: 0 | E86: 0 | F86: 0 | G86: 0 | H86: 0 | I86: 0 | J86: 0 | K86: 0 | L86: 0 | M86: 0 | N86: 0 | O86: 0 | P86: =SUM(D86:O86) -> 0
B87: Done this Month Prepaid | C87: No | D87: 0 | E87: 0 | F87: 0 | G87: 0 | H87: 0 | I87: 0 | J87: 0 | K87: 0 | L87: 0 | M87: 0 | N87: 0 | O87: 0 | P87: =SUM(D87:O87) -> 0
B88: Total Done | C88: No | D88: =D86+D87 -> 0 | E88: =E86+E87 -> 0 | F88: =F86+F87 -> 0 | G88: =G86+G87 -> 0 | H88: =H86+H87 -> 0 | I88: =I86+I87 -> 0 | J88: =J86+J87 -> 0 | K88: =K86+K87 -> 0 | ... O88: =O86+O87 -> 0 | P88: =SUM(D88:O88) -> 0
B89: Carried Forward | C89: No | D89: =D84+D85-D88 -> 0 | E89: =E84+E85-E88 -> 0 | F89: =F84+F85-F88 -> 0 | G89: =G84+G85-G88 -> 0 | H89: =H84+H85-H88 -> 0 | I89: =I84+I85-I88 -> 0 | J89: =J84+J85-J88 -> 0 | K89: =K84+K85-K88 -> 0 | ... O89: =O84+O85-O88 -> 0 | P89: =P84+P85-P86-P87 -> 0
A90: Aggregated New Water connections | B90: Brought Forward | C90: No | D90: =D66+D72+D78+D84 -> 1 | E90: =E66+E72+E78+E84 -> 0 | F90: =F66+F72+F78+F84 -> 2 | G90: =G66+G72+G78+G84 -> 6 | H90: =H66+H72+H78+H84 -> 6 | I90: =I66+I72+I78+I84 -> 3 | J90: =J66+J72+J78+J84 -> 3 | K90: =K66+K72+K78+K84 -> 3 | ... O90: =O66+O72+O78+O84 -> 2 | P90: =D90 -> 1
B91: Applied this Month | C91: No | D91: =D67+D73+D79+D85 -> 3 | E91: =E67+E73+E79+E85 -> 2 | F91: =F67+F73+F79+F85 -> 5 | G91: =G67+G73+G79+G85 -> 0 | H91: =H67+H73+H79+H85 -> 3 | I91: =I67+I73+I79+I85 -> 0 | J91: =J67+J73+J79+J85 -> 0 | K91: =K67+K73+K79+K85 -> 0 | ... O91: =O67+O73+O79+O85 -> 10 | P91: =SUM(D91:O91) -> 24
B92: Done this Month Postpaid | C92: No | D92: =D68+D74+D80+D86 -> 4 | E92: =E68+E74+E80+E86 -> 0 | F92: =F68+F74+F80+F86 -> 1 | G92: =G68+G74+G80+G86 -> 0 | H92: =H68+H74+H80+H86 -> 6 | I92: =I68+I74+I80+I86 -> 0 | J92: =J68+J74+J80+J86 -> 0 | K92: =K68+K74+K80+K86 -> 0 | ... O92: =O68+O74+O80+O86 -> 0 | P92: =SUM(D92:O92) -> 13
B93: Done this Month Prepaid | D93: =D69+D75+D81+D87 -> 0 | E93: =E69+E75+E81+E87 -> 0 | F93: =F69+F75+F81+F87 -> 0 | G93: =G69+G75+G81+G87 -> 0 | H93: =H69+H75+H81+H87 -> 0 | I93: =I69+I75+I81+I87 -> 0 | J93: =J69+J75+J81+J87 -> 0 | K93: =K69+K75+K81+K87 -> 0 | ... O93: =O69+O75+O81+O87 -> 0 | P93: =SUM(D93:O93) -> 0
B94: Total Done | C94: No | D94: =D93+D92 -> 4 | E94: =E93+E92 -> 0 | F94: =F93+F92 -> 1 | G94: =G93+G92 -> 0 | H94: =H93+H92 -> 6 | I94: =I93+I92 -> 0 | J94: =J93+J92 -> 0 | K94: =K93+K92 -> 0 | ... P94: =P93+P92 -> 13
B95: Carried Forward | C95: No | D95: =D90+D91-D94 -> 0 | E95: =E90+E91-E94 -> 2 | F95: =F90+F91-F94 -> 6 | G95: =G90+G91-G94 -> 6 | H95: =H90+H91-H94 -> 3 | I95: =I90+I91-I94 -> 3 | J95: =J90+J91-J94 -> 3 | K95: =K90+K91-K94 -> 3 | ... P95: =P90+P91-P94 -> 12
A97: Prepaid Metering
A98: Prepaid Meters Installed | C98: No | D98: 0 | E98: 0 | F98: 0 | G98: 0 | H98: 0 | I98: 0 | J98: 0 | K98: 0 | L98: 0 | M98: 0 | N98: 0 | O98: 0 | P98: =SUM(D98:O98) -> 0
A100: Active and Disconnected Accounts
A101: Disconnected Individual Accounts | C101: No | D101: 86 | E101: 77 | F101: 79 | G101: 74 | H101: 71 | I101: 67 | J101: 67 | K101: 67 | L101: 71 | M101: 79 | N101: 81 | O101: 78 | P101: =O101 -> 78
A102: Disconnected institutional Accounts | C102: No | D102: 47 | E102: 45 | F102: 46 | G102: 46 | H102: 46 | I102: 45 | J102: 45 | K102: 45 | L102: 45 | M102: 45 | N102: 46 | O102: 48 | P102: =O102 -> 48
A103: Disconnected Commercial/Industrial Accounts | C103: No | D103: 8 | E103: 8 | F103: 8 | G103: 8 | H103: 8 | I103: 8 | J103: 7 | K103: 7 | L103: 7 | M103: 7 | N103: 7 | O103: 9 | P103: =O103 -> 9
A104: Disconnected CWP | C104: No | D104: 0 | E104: 0 | F104: 0 | G104: 0 | H104: 0 | I104: 0 | J104: 0 | K104: 0 | L104: 0 | M104: 0 | N104: 0 | O104: 0 | P104: =O104 -> 0
A105: Total Disconnected Accounts | C105: No | D105: =SUM(D101:D104) -> 141 | E105: =SUM(E101:E104) -> 130 | F105: =SUM(F101:F104) -> 133 | G105: =SUM(G101:G104) -> 128 | H105: =SUM(H101:H104) -> 125 | I105: =SUM(I101:I104) -> 120 | J105: =SUM(J101:J104) -> 119 | K105: =SUM(K101:K104) -> 119 | ... O105: =SUM(O101:O104) -> 135 | P105: =O105 -> 135
A106: Postpaid Consumers
...

Sheet Thondwe
A1: SOUTHERN REGION WATER BOARD
A3: MONTHLY REPORTS - 2024/2025
A4: ZOMBA ZONE
A5: THONDWE SCHEME
A7: PARAMETERS | C7: UNITS | D7: APRIL | E7: MAY | F7: JUNE | G7: JULY | H7: AUGUST | I7: SEPTEMBER | J7: OCTOBER | K7: NOVEMBER | L7: DECEMBER | M7: JANUARY | N7: FEBRUARY | O7: MARCH | P7: TOTALS
A8: PRODUCTION
A9: Volume Produced | C9: m3 | D9: 2150 | E9: 3240 | F9: 2180 | G9: 2240 | H9: 3000 | I9: 2900 | J9: 2970 | K9: 2440 | L9: 4490 | M9: 5450 | N9: 5520 | O9: 5600 | P9: =SUM(D9:O9) -> 42180
A10: REVENUE WATER - POSTPAID
A11: Volume Billed Individuals | C11: m3 | D11: 1504 | E11: 2338 | F11: 1745 | G11: 1896 | H11: 1576 | I11: 1975 | J11: 1971 | K11: 1884 | L11: 2371 | M11: 1979 | N11: 1885 | O11: 2077 | P11: =SUM(D11:O11) -> 23201
A12: Volume Billed CWPs | C12: m3 | D12: 0 | E12: 0 | F12: 0 | G12: 0 | H12: 0 | I12: 0 | J12: 0 | K12: 0 | L12: 0 | M12: 0 | N12: 0 | O12: 0 | P12: =SUM(D12:O12) -> 0
A13: Volume Billed Institutions | C13: m3 | D13: 12 | E13: 8 | F13: 8 | G13: 8 | H13: 8 | I13: 22 | J13: 29 | K13: 28 | L13: 39 | M13: 34 | N13: 27 | O13: 27 | P13: =SUM(D13:O13) -> 250
A14: Volume Billed Commercial/Industrial | C14: m3 | D14: 6 | E14: 8 | F14: 8 | G14: 4 | H14: 4 | I14: 4 | J14: 4 | K14: 4 | L14: 9 | M14: 4 | N14: 4 | O14: 4 | P14: =SUM(D14:O14) -> 63
A15: Total Volume Billed Post Paid | C15: m3 | D15: =SUM(D11:D14) -> 1522 | E15: =SUM(E11:E14) -> 2354 | F15: =SUM(F11:F14) -> 1761 | G15: =SUM(G11:G14) -> 1908 | H15: =SUM(H11:H14) -> 1588 | I15: =SUM(I11:I14) -> 2001 | J15: =SUM(J11:J14) -> 2004 | K15: =SUM(K11:K14) -> 1916 | ... P15: =SUM(P11:P14) -> 23514
A16: REVENUE WATER - PREPAID
A17: Individuals | C17: m3 | D17: 55.5 | E17: 68.1 | F17: 136.7 | G17: 93.2 | H17: 41.5 | I17: 186.5 | J17: 163.9 | K17: 237.5 | L17: 192.8 | M17: 124.1 | N17: 86.2 | O17: 144.3 | P17: =SUM(D17:O17) -> 1530.3
A18: CWPs | C18: m3 | D18: 8.8 | E18: 8.8 | F18: 0 | G18: 12.9 | H18: 0.5 | I18: 7.1 | J18: 38.6 | K18: 3.3 | L18: 47.1 | M18: 18.1 | N18: 0 | O18: 0 | P18: =SUM(D18:O18) -> 145.2
A19: Institutions | C19: m3 | D19: 1.7 | E19: 4.4 | F19: 18.1 | G19: 1.3 | H19: 11.8 | I19: 13.2 | J19: 503.4 | K19: 11.5 | L19: 5.6 | M19: 343.8 | N19: 13.5 | O19: 206.3 | P19: =SUM(D19:O19) -> 1134.6
A20: Commercial/Industrial | C20: m3 | D20: 11.5 | E20: 23.4 | F20: 3.3 | G20: 9.4 | H20: 24.2 | I20: 6.6 | J20: 11.8 | K20: 39.4 | L20: 22.3 | M20: 9.4 | N20: 11.9 | O20: 29 | P20: =SUM(D20:O20) -> 202.2
A21: Total Volume Prepaid | C21: m3 | D21: =SUM(D17:D20) -> 77.5 | E21: =SUM(E17:E20) -> 104.7 | F21: =SUM(F17:F20) -> 158.1 | G21: =SUM(G17:G20) -> 116.8 | H21: =SUM(H17:H20) -> 78 | I21: =SUM(I17:I20) -> 213.4 | J21: =SUM(J17:J20) -> 717.7 | K21: =SUM(K17:K20) -> 291.7 | ... P21: =SUM(P17:P20) -> 3012.3
A22: TOTAL REVENUE WATER | C22: m3 | D22: =D21+D15 -> 1599.5 | E22: =E21+E15 -> 2458.7 | F22: =F21+F15 -> 1919.1 | G22: =G21+G15 -> 2024.8 | H22: =H21+H15 -> 1666 | I22: =I21+I15 -> 2214.4 | J22: =J21+J15 -> 2721.7 | K22: =K21+K15 -> 2207.7 | ... P22: =P21+P15 -> 26526.3
A24: Non-Revenue Water (NRW) | B24: Volume | C24: m3 | D24: =D9-D22 -> 550.5 | E24: =E9-E22 -> 781.3 | F24: =F9-F22 -> 260.9 | G24: =G9-G22 -> 215.2 | H24: =H9-H22 -> 1334 | I24: =I9-I22 -> 685.6 | J24: =J9-J22 -> 248.3 | K24: =K9-K22 -> 232.3 | ... P24: =P9-P22 -> 15653.7
B25: Percentage | C25: % | D25: =IFERROR(D24/D9,0) -> 0.25604651 | E25: =E24/E9 -> 0.24114198 | F25: =F24/F9 -> 0.1196789 | G25: =IFERROR(G24/G9,0) -> 0.096071429 | H25: =IFERROR(H24/H9,0) -> 0.44466667 | I25: =IFERROR(I24/I9,0) -> 0.23641379 | J25: =IFERROR(J24/J9,0) -> 0.083602694 | K25: =IFERROR(K24/K9,0) -> 0.095204918 | L25: =IFERROR(L24/L9,0) -> 0.40160356 | M25: =IFERROR(M24/M9,0) -> 0.53900917 | N25: =IFERROR(N24/N9,0) -> 0.63268116 | O25: =IFERROR(O24/O9,0) -> 0.55578571 | P25: =IF(P9,P24/P9,"") -> 0.37111664
A26: OPERATING EXPENSES
A27: Chemicals
A28: Chemical | B28: Rate(MK/kg)
A29: Chlorine | B29: 7400 | C29: kg | D29: 5.4 | E29: 4.3 | F29: 5 | G29: 5.6 | H29: 11 | I29: 6 | J29: 4 | K29: 7 | L29: 13.8 | M29: 11 | N29: 15 | O29: 14 | P29: =SUM(D29:O29) -> 102.1
C30: kg/mg litre | D30: =IFERROR(D29/(D9/1000),0) -> 2.5116279 | E30: =IFERROR(E29/(E9/1000),0) -> 1.3271605 | F30: =IFERROR(F29/(F9/1000),0) -> 2.293578 | G30: =IFERROR(G29/(G9/1000),0) -> 2.5 | H30: =IFERROR(H29/(H9/1000),0) -> 3.6666667 | I30: =IFERROR(I29/(I9/1000),0) -> 2.0689655 | J30: =IFERROR(J29/(J9/1000),0) -> 1.3468013 | K30: =IFERROR(K29/(K9/1000),0) -> 2.8688525 | ... P30: =IFERROR(P29/(P9/1000),0) -> 2.4205785
A31: Aluminium sulphate | B31: 1900 | C31: kg | D31: 19.7 | E31: 9.5 | F31: 8.6 | G31: 8.3 | H31: 19 | I31: 10 | J31: 11 | K31: 19 | L31: 58.1 | M31: 68 | N31: 69 | O31: 56 | P31: =SUM(D31:O31) -> 356.2
C32: kg/mg litre | D32: =IFERROR(D31/(D9/1000),0) -> 9.1627907 | E32: =IFERROR(E31/(E9/1000),0) -> 2.9320988 | F32: =IFERROR(F31/(F9/1000),0) -> 3.9449541 | G32: =IFERROR(G31/(G9/1000),0) -> 3.7053571 | H32: =IFERROR(H31/(H9/1000),0) -> 6.3333333 | I32: =IFERROR(I31/(I9/1000),0) -> 3.4482759 | J32: =IFERROR(J31/(J9/1000),0) -> 3.7037037 | K32: =IFERROR(K31/(K9/1000),0) -> 7.7868852 | ... P32: =IFERROR(P31/(P9/1000),0) -> 8.4447606
A33: Soda | B33: 1900 | C33: kg | D33: 6.9 | E33: 3.4 | F33: 4 | G33: 4.2 | H33: 12 | I33: 4 | J33: 3 | K33: 5 | L33: 21.15861 | M33: 19 | N33: 17 | O33: 24 | P33: =SUM(D33:O33) -> 123.65861
C34: kg/mg litre | D34: =IFERROR(D33/(D9/1000),0) -> 3.2093023 | E34: =IFERROR(E33/(E9/1000),0) -> 1.0493827 | F34: =IFERROR(F33/(F9/1000),0) -> 1.8348624 | G34: =IFERROR(G33/(G9/1000),0) -> 1.875 | H34: =IFERROR(H33/(H9/1000),0) -> 4 | I34: =IFERROR(I33/(I9/1000),0) -> 1.3793103 | J34: =IFERROR(J33/(J9/1000),0) -> 1.010101 | K34: =IFERROR(K33/(K9/1000),0) -> 2.0491803 | ... P34: =IFERROR(P33/(P9/1000),0) -> 2.9316882
A35: Algae floc | B35: =745345.16/200 -> 3726.7258 | C35: litres | D35: 0 | E35: 0 | F35: 0 | G35: 0 | H35: 0 | I35: 0 | J35: 0 | K35: 0 | L35: 0 | M35: 0 | N35: 0 | O35: 0
C36: litres/mg litre
A37: Sud floc | B37: =790318.72/200 -> 3951.5936 | C37: litres | D37: 0 | E37: 0 | F37: 0 | G37: 0 | H37: 0 | I37: 0 | J37: 0 | K37: 0 | L37: 0 | M37: 0 | N37: 0 | O37: 0 | P37: =SUM(D37:O37) -> 0
C38: litres/mg litre | D38: =IFERROR(D37/(D9/1000),0) -> 0 | E38: =IFERROR(E37/(E9/1000),0) -> 0 | F38: =IFERROR(F37/(F9/1000),0) -> 0 | G38: =IFERROR(G37/(G9/1000),0) -> 0 | H38: =IFERROR(H37/(H9/1000),0) -> 0 | I38: =IFERROR(I37/(I9/1000),0) -> 0 | J38: =IFERROR(J37/(J9/1000),0) -> 0 | K38: =IFERROR(K37/(K9/1000),0) -> 0 | ... P38: =IFERROR(P37/(P9/1000),0) -> 0
A39: Potasium permanganate | B39: 1950 | C39: kg | D39: 0 | E39: 0 | F39: 0 | G39: 0 | H39: 0 | I39: 0 | J39: 0 | K39: 0 | L39: 0 | M39: 0 | N39: 0 | O39: 0 | P39: =SUM(D39:O39) -> 0
C40: kg/mg litre | D40: =IFERROR(D39/(D9/1000),0) -> 0 | E40: =IFERROR(E39/(E9/1000),0) -> 0 | F40: =IFERROR(F39/(F9/1000),0) -> 0 | G40: =IFERROR(G39/(G9/1000),0) -> 0 | H40: =IFERROR(H39/(H9/1000),0) -> 0 | I40: =IFERROR(I39/(I9/1000),0) -> 0 | J40: =IFERROR(J39/(J9/1000),0) -> 0 | K40: =IFERROR(K39/(K9/1000),0) -> 0 | ... P40: =IFERROR(P39/(P9/1000),0) -> 0
A41: Cost of Chemicals | C41: Mk | D41: =(D29*$B29)+(D31*$B31)+(D33*$B33)+(D35*$B35)+(D37*$B37)+(D39*$B39) -> 90500 | E41: =(E29*$B29)+(E31*$B31)+(E33*$B33)+(E35*$B35)+(E37*$B37)+(E39*$B39) -> 56330 | F41: =(F29*$B29)+(F31*$B31)+(F33*$B33)+(F35*$B35)+(F37*$B37)+(F39*$B39) -> 60940 | G41: =(G29*$B29)+(G31*$B31)+(G33*$B33)+(G35*$B35)+(G37*$B37)+(G39*$B39) -> 65190 | H41: =(H29*$B29)+(H31*$B31)+(H33*$B33)+(H35*$B35)+(H37*$B37)+(H39*$B39) -> 140300 | I41: =(I29*$B29)+(I31*$B31)+(I33*$B33)+(I35*$B35)+(I37*$B37)+(I39*$B39) -> 71000 | J41: =(J29*$B29)+(J31*$B31)+(J33*$B33)+(J35*$B35)+(J37*$B37)+(J39*$B39) -> 56200 | K41: =(K29*$B29)+(K31*$B31)+(K33*$B33)+(K35*$B35)+(K37*$B37)+(K39*$B39) -> 97400 | ... O41: =(O29*$B29)+(O31*$B31)+(O33*$B33)+(O35*$B35)+(O37*$B37)+(O39*$B39) -> 255600 | P41: =SUM(D41:O41) -> 1667271.4
A42: Cost/vol. Produced (chemicals) | C42: Mk/m3 | D42: =IFERROR(D41/D9,0) -> 42.093023 | E42: =IFERROR(E41/E9,0) -> 17.385802 | F42: =IFERROR(F41/F9,0) -> 27.954128 | G42: =IFERROR(G41/G9,0) -> 29.102679 | H42: =IFERROR(H41/H9,0) -> 46.766667 | I42: =IFERROR(I41/I9,0) -> 24.482759 | J42: =IFERROR(J41/J9,0) -> 18.922559 | K42: =IFERROR(K41/K9,0) -> 39.918033 | ... P42: =IFERROR(P41/P9,0) -> 39.527533
A43: Power
A44: Power Usage | C44: Kw | D44: 108.8 | E44: 103.5 | F44: 123 | G44: 130.7 | H44: 271.26 | I44: 171.5 | J44: 111.21 | K44: 163.93 | L44: 384.3 | M44: 366.26 | N44: 391.5 | O44: 371.81 | P44: =SUM(D44:O44) -> 2697.77
A45: Power/ Vol. Produced | C45: Kw/m3 | D45: =IFERROR(D44/D9,0) -> 0.050604651 | E45: =IFERROR(E44/E9,0) -> 0.031944444 | F45: =IFERROR(F44/F9,0) -> 0.056422018 | G45: =IFERROR(G44/G9,0) -> 0.058348214 | H45: =IFERROR(H44/H9,0) -> 0.09042 | I45: =IFERROR(I44/I9,0) -> 0.059137931 | J45: =IFERROR(J44/J9,0) -> 0.037444444 | K45: =IFERROR(K44/K9,0) -> 0.067184426 | ... P45: =IFERROR(P44/P9,0) -> 0.063958511
A46: Cost of Power | C46: Mk | D46: =IF(D44=0,0,IF(D44>=0,0+(D44*202.25)+23390)*1.165) -> 52884.942 | E46: =IF(E44=0,0,IF(E44>=0,0+(E44*202.25)+23390)*1.165) -> 51636.149 | F46: =IF(F44=0,0,IF(F44>=0,0+(F44*202.25)+23390)*1.165) -> 56230.764 | G46: =IF(G44=0,0,IF(G44>=0,0+(G44*202.25)+23390)*1.165) -> 58045.047 | H46: =IF(H44=0,0,IF(H44>=0,0+(H44*202.25)+23390)*1.165) -> 91163.97 | I46: =IF(I44=0,0,IF(I44>=0,0+(I44*202.25)+23390)*1.165) -> 67658.394 | J46: =IF(J44=0,0,IF(J44>=0,0+(J44*202.25)+23390)*1.165) -> 53452.789 | K46: =IF(K44=0,0,IF(K44>=0,0+(K44*202.25)+23390)*1.165) -> 65874.742 | ... O46: =IF(O44=0,0,IF(O44>=0,0+(O44*202.25)+23390)*1.165) -> 114855.69 | P46: =SUM(D46:O46) -> 962644.14
A47: Cost/vol. Produced | C47: Mk/m3 | D47: =IFERROR(D46/D9,0) -> 24.597647 | E47: =IFERROR(E46/E9,0) -> 15.937083 | F47: =IFERROR(F46/F9,0) -> 25.793928 | G47: =IFERROR(G46/G9,0) -> 25.912968 | H47: =IFERROR(H46/H9,0) -> 30.38799 | I47: =IFERROR(I46/I9,0) -> 23.330481 | J47: =IFERROR(J46/J9,0) -> 17.997572 | K47: =IFERROR(K46/K9,0) -> 26.997845 | ... P47: =IFERROR(P46/P9,0) -> 22.822289
A48: Plant and Vehicle Maintenance
A49: Distances covered | C49: km | D49: 0 | E49: 0 | F49: 0 | G49: 0 | H49: 0 | I49: 0 | J49: 0 | K49: 0 | L49: 0 | M49: 0 | N49: 0 | O49: 0 | P49: =SUM(D49:O49) -> 0
A50: Fuel Used (litres) | C50: litres | D50: 0 | E50: 0 | F50: 0 | G50: 0 | H50: 0 | I50: 0 | J50: 0 | K50: 0 | L50: 0 | M50: 0 | N50: 0 | O50: 0 | P50: =SUM(D50:O50) -> 0
A51: Cost of fuel | C51: Mk | D51: 0 | E51: 0 | F51: 0 | G51: 0 | H51: 0 | I51: 0 | J51: 0 | K51: 0 | L51: 0 | M51: 0 | N51: 0 | O51: 0 | P51: =SUM(D51:O51) -> 0
A52: Maintenance | C52: Mk | D52: 0 | E52: 0 | F52: 0 | G52: 0 | H52: 0 | I52: 0 | J52: 0 | K52: 0 | L52: 0 | M52: 0 | N52: 0 | O52: 0 | P52: =SUM(D52:O52) -> 0
A53: Salaries and Wages
A54: Staff Costs | C54: MK | D54: 0 | E54: 0 | F54: 0 | G54: 0 | H54: 0 | I54: 0 | J54: 0 | K54: 0 | L54: 0 | M54: 0 | N54: 0 | O54: 0 | P54: =SUM(D54:O54) -> 0
A55: Wages | C55: MK | D55: 0 | E55: 0 | F55: 0 | G55: 0 | H55: 0 | I55: 0 | J55: 0 | K55: 0 | L55: 0 | M55: 0 | N55: 0 | O55: 0 | P55: =SUM(D55:O55) -> 0
A56: Other Overhead Costs | C56: MK | D56: 0 | E56: 0 | F56: 0 | G56: 0 | H56: 0 | I56: 0 | J56: 0 | K56: 0 | L56: 0 | M56: 0 | N56: 0 | O56: 0 | P56: =SUM(D56:O56) -> 0
A57: Operating Costs
A58: Total Operating Costs | C58: MK | D58: =D41+D46+D51+D52+D54+D55+D56 -> 143384.94 | E58: =E41+E46+E51+E52+E54+E55+E56 -> 107966.15 | F58: =F41+F46+F51+F52+F54+F55+F56 -> 117170.76 | G58: =G41+G46+G51+G52+G54+G55+G56 -> 123235.05 | H58: =H41+H46+H51+H52+H54+H55+H56 -> 231463.97 | I58: =I41+I46+I51+I52+I54+I55+I56 -> 138658.39 | J58: =J41+J46+J51+J52+J54+J55+J56 -> 109652.79 | K58: =K41+K46+K51+K52+K54+K55+K56 -> 163274.74 | ... O58: =O41+O46+O51+O52+O54+O55+O56 -> 370455.69 | P58: =SUM(D58:O58) -> 2629915.5
A59: Cost/Vol. Produced | C59: Mk/m3 | D59: =IFERROR(D58/D9,0) -> 66.690671 | E59: =IFERROR(E58/E9,0) -> 33.322886 | F59: =IFERROR(F58/F9,0) -> 53.748057 | G59: =IFERROR(G58/G9,0) -> 55.015646 | H59: =IFERROR(H58/H9,0) -> 77.154657 | I59: =IFERROR(I58/I9,0) -> 47.813239 | J59: =IFERROR(J58/J9,0) -> 36.920131 | K59: =IFERROR(K58/K9,0) -> 66.915878 | ... P59: =IFERROR(P58/P9,0) -> 62.349822
A60: Cost/Vol. Billed | C60: Mk/m3 | D60: =IFERROR(D58/D22,0) -> 89.643602 | E60: =IFERROR(E58/E22,0) -> 43.911884 | F60: =IFERROR(F58/F22,0) -> 61.055059 | G60: =IFERROR(G58/G22,0) -> 60.862825 | H60: =IFERROR(H58/H22,0) -> 138.93396 | I60: =IFERROR(I58/I22,0) -> 62.616688 | J60: =IFERROR(J58/J22,0) -> 40.288345 | K60: =IFERROR(K58/K22,0) -> 73.956942 | ... P60: =IFERROR(P58/P22,0) -> 99.143699
A61: Permanent Staff Employed | C61: No | D61: 1 | E61: 1 | F61: 1 | G61: 1 | H61: 1 | I61: 1 | J61: 1 | K61: 1 | L61: 1 | M61: 1 | N61: 1 | O61: 1 | P61: =O61 -> 1
A62: Staff/Vol.1000m3 of Volume Produced/hour (12 hour day) | C62: No/1000m3 | D62: =IFERROR((D61*1000*31)/D9,0) -> 14.418605 | E62: =IFERROR((E61*1000*31)/E9,0) -> 9.5679012 | F62: =IFERROR((F61*1000*31)/F9,0) -> 14.220183 | G62: =IFERROR((G61*1000*31)/G9,0) -> 13.839286 | H62: =IFERROR((H61*1000*31)/H9,0) -> 10.333333 | I62: =IFERROR((I61*1000*31)/I9,0) -> 10.689655 | J62: =IFERROR((J61*1000*31)/J9,0) -> 10.43771 | K62: =IFERROR((K61*1000*31)/K9,0) -> 12.704918 | ... P62: =IFERROR((P61*1000*31)/P9,0) -> 0.73494547
A63: Temporary Staff Employed | C63: No | D63: 4 | E63: 4 | F63: 4 | G63: 4 | H63: 4 | I63: 4 | J63: 4 | K63: 4 | L63: 4 | M63: 4 | N63: 4 | O63: 4 | P63: =O63 -> 4
A65: Water Connections and Disconnections
A66: New Individual Water Connections | B66: Brought Forward | C66: No | D66: 0 | E66: 0 | F66: 0 | G66: 0 | H66: 1 | I66: 0 | J66: 0 | K66: 0 | L66: 0 | M66: 2 | N66: 0 | O66: 1 | P66: =D66 -> 0
B67: Applied this Month | C67: No | D67: 0 | E67: 11 | F67: 0 | G67: 4 | H67: 1 | I67: 2 | J67: 0 | K67: 7 | L67: 2 | M67: 3 | N67: 2 | O67: 3 | P67: =SUM(D67:O67) -> 35
B68: Done this Month Postpaid | C68: No | D68: 0 | E68: 11 | F68: 0 | G68: 3 | H68: 2 | I68: 2 | J68: 0 | K68: 7 | L68: 0 | M68: 5 | N68: 1 | O68: 2 | P68: =SUM(D68:O68) -> 33
B69: Done this Month Prepaid | C69: No | D69: 0 | E69: 0 | F69: 0 | G69: 0 | H69: 0 | I69: 0 | J69: 0 | K69: 0 | L69: 0 | M69: 0 | N69: 0 | O69: 0 | P69: =SUM(D69:O69) -> 0
B70: Total Done | C70: No | D70: =D68+D69 -> 0 | E70: =E68+E69 -> 11 | F70: =F68+F69 -> 0 | G70: =G68+G69 -> 3 | H70: =H68+H69 -> 2 | I70: =I68+I69 -> 2 | J70: =J68+J69 -> 0 | K70: =K68+K69 -> 7 | ... P70: =P68+P69 -> 33
B71: Carried Forward | C71: No | D71: =D66+D67-D70 -> 0 | E71: =E66+E67-E70 -> 0 | F71: =F66+F67-F70 -> 0 | G71: =G66+G67-G70 -> 1 | H71: =H66+H67-H70 -> 0 | I71: =I66+I67-I70 -> 0 | J71: =J66+J67-J70 -> 0 | K71: =K66+K67-K70 -> 0 | ... P71: =P66+P67-P70 -> 2
A72: New Institutional Water Connections | B72: Brought Forward | C72: No | D72: 0 | E72: 0 | F72: 0 | G72: 0 | H72: 0 | I72: 0 | J72: 0 | K72: 0 | L72: 0 | M72: 0 | N72: 0 | O72: 0 | P72: =D72 -> 0
B73: Applied this Month | C73: No | D73: 0 | E73: 0 | F73: 0 | G73: 0 | H73: 0 | I73: 0 | J73: 0 | K73: 0 | L73: 0 | M73: 0 | N73: 0 | O73: 0 | P73: =SUM(D73:O73) -> 0
B74: Done this Month Postpaid | C74: No | D74: 0 | E74: 0 | F74: 0 | G74: 0 | H74: 0 | I74: 0 | J74: 0 | K74: 0 | L74: 0 | M74: 0 | N74: 0 | O74: 0 | P74: =SUM(D74:O74) -> 0
B75: Done this Month Prepaid | C75: No | D75: 0 | E75: 0 | F75: 0 | G75: 0 | H75: 0 | I75: 0 | J75: 0 | K75: 0 | L75: 0 | M75: 0 | N75: 0 | O75: 0 | P75: =SUM(D75:O75) -> 0
B76: Total Done | C76: No | D76: =D74+D75 -> 0 | E76: =E74+E75 -> 0 | F76: =F74+F75 -> 0 | G76: =G74+G75 -> 0 | H76: =H74+H75 -> 0 | I76: =I74+I75 -> 0 | J76: =J74+J75 -> 0 | K76: =K74+K75 -> 0 | ... P76: =P74+P75 -> 0
B77: Carried Forward | C77: No | D77: =D72+D73-D76 -> 0 | E77: =E72+E73-E76 -> 0 | F77: =F72+F73-F76 -> 0 | G77: =G72+G73-G76 -> 0 | H77: =H72+H73-H76 -> 0 | I77: =I72+I73-I76 -> 0 | J77: =J72+J73-J76 -> 0 | K77: =K72+K73-K76 -> 0 | ... P77: =P72+P73-P76 -> 0
A78: New Commercial/Industrial Water Connections | B78: Brought Forward | C78: No | D78: 0 | E78: 0 | F78: 0 | G78: 0 | H78: 0 | I78: 0 | J78: 0 | K78: 0 | L78: 0 | M78: 0 | N78: 0 | O78: 0 | P78: =D78 -> 0
B79: Applied this Month | C79: No | D79: 0 | E79: 0 | F79: 0 | G79: 0 | H79: 0 | I79: 0 | J79: 0 | K79: 0 | L79: 0 | M79: 0 | N79: 0 | O79: 0 | P79: =SUM(D79:O79) -> 0
B80: Done this Month Postpaid | C80: No | D80: 0 | E80: 0 | F80: 0 | G80: 0 | H80: 0 | I80: 0 | J80: 0 | K80: 0 | L80: 0 | M80: 0 | N80: 0 | O80: 0 | P80: =SUM(D80:O80) -> 0
B81: Done this Month Prepaid | C81: No | D81: 0 | E81: 0 | F81: 0 | G81: 0 | H81: 0 | I81: 0 | J81: 0 | K81: 0 | L81: 0 | M81: 0 | N81: 0 | O81: 0 | P81: =SUM(D81:O81) -> 0
B82: Total Done | C82: No | D82: =D80+D81 -> 0 | E82: =E80+E81 -> 0 | F82: =F80+F81 -> 0 | G82: =G80+G81 -> 0 | H82: =H80+H81 -> 0 | I82: =I80+I81 -> 0 | J82: =J80+J81 -> 0 | K82: =K80+K81 -> 0 | ... O82: =O80+O81 -> 0 | P82: =P81+P80 -> 0
B83: Carried Forward | C83: No | D83: =D78+D79-D82 -> 0 | E83: =E78+E79-E82 -> 0 | F83: =F78+F79-F82 -> 0 | G83: =G78+G79-G82 -> 0 | H83: =H78+H79-H82 -> 0 | I83: =I78+I79-I82 -> 0 | J83: =J78+J79-J82 -> 0 | K83: =K78+K79-K82 -> 0 | ... P83: =P78+P79-P82 -> 0
A84: New CWP | B84: Brought Forward | C84: No | D84: 0 | E84: 0 | F84: 0 | G84: 0 | H84: 0 | I84: 0 | J84: 0 | K84: 0 | L84: 0 | M84: 0 | N84: 0 | O84: 0 | P84: =D84 -> 0
B85: Applied this Month | C85: No | D85: 0 | E85: 0 | F85: 0 | G85: 0 | H85: 0 | I85: 0 | J85: 0 | K85: 0 | L85: 0 | M85: 0 | N85: 0 | O85: 0 | P85: =SUM(D85:O85) -> 0
B86: Done this Month Postpaid | C86: No | D86: 0 | E86: 0 | F86: 0 | G86: 0 | H86: 0 | I86: 0 | J86: 0 | K86: 0 | L86: 0 | M86: 0 | N86: 0 | O86: 0 | P86: =SUM(D86:O86) -> 0
B87: Done this Month Prepaid | C87: No | D87: 0 | E87: 0 | F87: 0 | G87: 0 | H87: 0 | I87: 0 | J87: 0 | K87: 0 | L87: 0 | M87: 0 | N87: 0 | O87: 0 | P87: =SUM(D87:O87) -> 0
B88: Total Done | C88: No | D88: =D86+D87 -> 0 | E88: =E86+E87 -> 0 | F88: =F86+F87 -> 0 | G88: =G86+G87 -> 0 | H88: =H86+H87 -> 0 | I88: =I86+I87 -> 0 | J88: =J86+J87 -> 0 | K88: =K86+K87 -> 0 | ... O88: =O86+O87 -> 0 | P88: =SUM(D88:O88) -> 0
B89: Carried Forward | C89: No | D89: =D84+D85-D88 -> 0 | E89: =E84+E85-E88 -> 0 | F89: =F84+F85-F88 -> 0 | G89: =G84+G85-G88 -> 0 | H89: =H84+H85-H88 -> 0 | I89: =I84+I85-I88 -> 0 | J89: =J84+J85-J88 -> 0 | K89: =K84+K85-K88 -> 0 | ... O89: =O84+O85-O88 -> 0 | P89: =P84+P85-P86-P87 -> 0
A90: Aggregated New Water connections | B90: Brought Forward | C90: No | D90: =D66+D72+D78+D84 -> 0 | E90: =E66+E72+E78+E84 -> 0 | F90: =F66+F72+F78+F84 -> 0 | G90: =G66+G72+G78+G84 -> 0 | H90: =H66+H72+H78+H84 -> 1 | I90: =I66+I72+I78+I84 -> 0 | J90: =J66+J72+J78+J84 -> 0 | K90: =K66+K72+K78+K84 -> 0 | ... O90: =O66+O72+O78+O84 -> 1 | P90: =D90 -> 0
B91: Applied this Month | C91: No | D91: =D67+D73+D79+D85 -> 0 | E91: =E67+E73+E79+E85 -> 11 | F91: =F67+F73+F79+F85 -> 0 | G91: =G67+G73+G79+G85 -> 4 | H91: =H67+H73+H79+H85 -> 1 | I91: =I67+I73+I79+I85 -> 2 | J91: =J67+J73+J79+J85 -> 0 | K91: =K67+K73+K79+K85 -> 7 | ... O91: =O67+O73+O79+O85 -> 3 | P91: =SUM(D91:O91) -> 35
B92: Done this Month Postpaid | C92: No | D92: =D68+D74+D80+D86 -> 0 | E92: =E68+E74+E80+E86 -> 11 | F92: =F68+F74+F80+F86 -> 0 | G92: =G68+G74+G80+G86 -> 3 | H92: =H68+H74+H80+H86 -> 2 | I92: =I68+I74+I80+I86 -> 2 | J92: =J68+J74+J80+J86 -> 0 | K92: =K68+K74+K80+K86 -> 7 | ... O92: =O68+O74+O80+O86 -> 2 | P92: =SUM(D92:O92) -> 33
B93: Done this Month Prepaid | D93: =D69+D75+D81+D87 -> 0 | E93: =E69+E75+E81+E87 -> 0 | F93: =F69+F75+F81+F87 -> 0 | G93: =G69+G75+G81+G87 -> 0 | H93: =H69+H75+H81+H87 -> 0 | I93: =I69+I75+I81+I87 -> 0 | J93: =J69+J75+J81+J87 -> 0 | K93: =K69+K75+K81+K87 -> 0 | ... O93: =O69+O75+O81+O87 -> 0 | P93: =SUM(D93:O93) -> 0
B94: Total Done | C94: No | D94: =D93+D92 -> 0 | E94: =E93+E92 -> 11 | F94: =F93+F92 -> 0 | G94: =G93+G92 -> 3 | H94: =H93+H92 -> 2 | I94: =I93+I92 -> 2 | J94: =J93+J92 -> 0 | K94: =K93+K92 -> 7 | ... P94: =P93+P92 -> 33
B95: Carried Forward | C95: No | D95: =D90+D91-D94 -> 0 | E95: =E90+E91-E94 -> 0 | F95: =F90+F91-F94 -> 0 | G95: =G90+G91-G94 -> 1 | H95: =H90+H91-H94 -> 0 | I95: =I90+I91-I94 -> 0 | J95: =J90+J91-J94 -> 0 | K95: =K90+K91-K94 -> 0 | ... P95: =P90+P91-P94 -> 2
A97: Prepaid Metering
A98: Prepaid Meters Installed | C98: No | D98: 0 | E98: 0 | F98: 0 | G98: 0 | H98: 0 | I98: 0 | J98: 0 | K98: 0 | L98: 0 | M98: 0 | N98: 0 | O98: 0 | P98: =SUM(D98:O98) -> 0
A100: Active and Disconnected Accounts
A101: Disconnected Individual Accounts | C101: No | D101: 138 | E101: 135 | F101: 133 | G101: 133 | H101: 157 | I101: 160 | J101: 159 | K101: 159 | L101: 134 | M101: 156 | N101: 154 | O101: 149 | P101: =O101 -> 149
A102: Disconnected institutional Accounts | C102: No | D102: 7 | E102: 7 | F102: 4 | G102: 4 | H102: 4 | I102: 4 | J102: 4 | K102: 4 | L102: 4 | M102: 4 | N102: 4 | O102: 4 | P102: =O102 -> 4
A103: Disconnected Commercial/Industrial Accounts | C103: No | D103: 9 | E103: 9 | F103: 4 | G103: 5 | H103: 5 | I103: 5 | J103: 5 | K103: 5 | L103: 0 | M103: 0 | N103: 0 | O103: 0 | P103: =O103 -> 0
A104: Disconnected CWP | C104: No | D104: 4 | E104: 4 | F104: 0 | G104: 0 | H104: 0 | I104: 0 | J104: 0 | K104: 0 | L104: 0 | M104: 0 | N104: 0 | O104: 0 | P104: =O104 -> 0
A105: Total Disconnected Accounts | C105: No | D105: =SUM(D101:D104) -> 158 | E105: =SUM(E101:E104) -> 155 | F105: =SUM(F101:F104) -> 141 | G105: =SUM(G101:G104) -> 142 | H105: =SUM(H101:H104) -> 166 | I105: =SUM(I101:I104) -> 169 | J105: =SUM(J101:J104) -> 168 | K105: =SUM(K101:K104) -> 168 | ... O105: =SUM(O101:O104) -> 153 | P105: =O105 -> 153
A106: Postpaid Consumers
...

Sheet Jali
A1: SOUTHERN REGION WATER BOARD
A3: MONTHLY REPORTS - 2024/2025
A4: ZOMBA ZONE
A5: JALI SCHEME
A7: PARAMETERS | C7: UNITS | D7: APRIL | E7: MAY | F7: JUNE | G7: JULY | H7: AUGUST | I7: SEPTEMBER | J7: OCTOBER | K7: NOVEMBER | L7: DECEMBER | M7: JANUARY | N7: FEBRUARY | O7: MARCH | P7: TOTALS
A8: PRODUCTION
A9: Volume Produced | C9: m3 | D9: 4097 | E9: 5311 | F9: 5760 | G9: 4630 | H9: 5833 | I9: 6705 | J9: 6714 | K9: 5620 | L9: 6889 | M9: 4700 | N9: 4835 | O9: 5552 | P9: =SUM(D9:O9) -> 66646
A10: REVENUE WATER - POSTPAID
A11: Volume Billed Individuals | C11: m3 | D11: 1907 | E11: 1898 | F11: 1898 | G11: 2108 | H11: 2658 | I11: 2740 | J11: 2822 | K11: 2723 | L11: 3054 | M11: 2204 | N11: 2024 | O11: 1914 | P11: =SUM(D11:O11) -> 27950
A12: Volume Billed CWPs | C12: m3 | D12: 0 | E12: 0 | F12: 0 | G12: 0 | H12: 0 | I12: 0 | J12: 0 | K12: 0 | L12: 0 | M12: 0 | N12: 0 | O12: 0 | P12: =SUM(D12:O12) -> 0
A13: Volume Billed Institutions | C13: m3 | D13: 68 | E13: 58 | F13: 45 | G13: 75 | H13: 72 | I13: 80 | J13: 37 | K13: 13 | L13: 19 | M13: 9 | N13: 10 | O13: 11 | P13: =SUM(D13:O13) -> 497
A14: Volume Billed Commercial/Industrial | C14: m3 | D14: 37 | E14: 31 | F14: 34 | G14: 33 | H14: 34 | I14: 33 | J14: 20 | K14: 0 | L14: 0 | M14: 12 | N14: 5 | O14: 8 | P14: =SUM(D14:O14) -> 247
A15: Total Volume Billed Post Paid | C15: m3 | D15: =SUM(D11:D14) -> 2012 | E15: =SUM(E11:E14) -> 1987 | F15: =SUM(F11:F14) -> 1977 | G15: =SUM(G11:G14) -> 2216 | H15: =SUM(H11:H14) -> 2764 | I15: =SUM(I11:I14) -> 2853 | J15: =SUM(J11:J14) -> 2879 | K15: =SUM(K11:K14) -> 2736 | ... P15: =SUM(P11:P14) -> 28694
A16: REVENUE WATER - PREPAID
A17: Individuals | C17: m3 | D17: 653.6 | E17: 698 | F17: 1913.4 | G17: 773.7 | H17: 805.5 | I17: 763 | J17: 875.3 | K17: 1081.9 | L17: 1032.3 | M17: 1202.1 | N17: 780.3 | O17: 1911.6 | P17: =SUM(D17:O17) -> 12490.7
A18: CWPs | C18: m3 | D18: 351.8 | E18: 563.9 | F18: 644 | G18: 635.9 | H18: 465.7 | I18: 608.9 | J18: 500.5 | K18: 572.5 | L18: 726.3 | M18: 448.7 | N18: 252.5 | O18: 395.2 | P18: =SUM(D18:O18) -> 6165.9
A19: Institutions | C19: m3 | D19: 18.6 | E19: 38 | F19: 577.2 | G19: 10.9 | H19: 38 | I19: 21.1 | J19: 340.5 | K19: 28.8 | L19: 20 | M19: 173.7 | N19: 25.3 | O19: 177.6 | P19: =SUM(D19:O19) -> 1469.7
A20: Commercial/Industrial | C20: m3 | D20: 2.6 | E20: 5.2 | F20: 0 | G20: 5.2 | H20: 22.2 | I20: 15.4 | J20: 0 | K20: 2.3 | L20: 7 | M20: 0 | N20: 2.7 | O20: 0 | P20: =SUM(D20:O20) -> 62.6
A21: Total Volume Prepaid | C21: m3 | D21: =SUM(D17:D20) -> 1026.6 | E21: =SUM(E17:E20) -> 1305.1 | F21: =SUM(F17:F20) -> 3134.6 | G21: =SUM(G17:G20) -> 1425.7 | H21: =SUM(H17:H20) -> 1331.4 | I21: =SUM(I17:I20) -> 1408.4 | J21: =SUM(J17:J20) -> 1716.3 | K21: =SUM(K17:K20) -> 1685.5 | ... P21: =SUM(P17:P20) -> 20188.9
A22: TOTAL REVENUE WATER | C22: m3 | D22: =D21+D15 -> 3038.6 | E22: =E21+E15 -> 3292.1 | F22: =F21+F15 -> 5111.6 | G22: =G21+G15 -> 3641.7 | H22: =H21+H15 -> 4095.4 | I22: =I21+I15 -> 4261.4 | J22: =J21+J15 -> 4595.3 | K22: =K21+K15 -> 4421.5 | ... P22: =P21+P15 -> 48882.9
A24: Non-Revenue Water (NRW) | B24: Volume | C24: m3 | D24: =D9-D22 -> 1058.4 | E24: =E9-E22 -> 2018.9 | F24: =F9-F22 -> 648.4 | G24: =G9-G22 -> 988.3 | H24: =H9-H22 -> 1737.6 | I24: =I9-I22 -> 2443.6 | J24: =J9-J22 -> 2118.7 | K24: =K9-K22 -> 1198.5 | ... P24: =P9-P22 -> 17763.1
B25: Percentage | C25: % | D25: =IFERROR(D24/D9,0) -> 0.25833537 | E25: =E24/E9 -> 0.38013557 | F25: =F24/F9 -> 0.11256944 | G25: =IFERROR(G24/G9,0) -> 0.21345572 | H25: =IFERROR(H24/H9,0) -> 0.29789131 | I25: =IFERROR(I24/I9,0) -> 0.36444444 | J25: =IFERROR(J24/J9,0) -> 0.31556449 | K25: =IFERROR(K24/K9,0) -> 0.21325623 | L25: =IFERROR(L24/L9,0) -> 0.29473073 | M25: =IFERROR(M24/M9,0) -> 0.13840426 | N25: =IFERROR(N24/N9,0) -> 0.35888314 | O25: =IFERROR(O24/O9,0) -> 0.20435879 | P25: =IF(P9,P24/P9,"") -> 0.26652912
A26: OPERATING EXPENSES
A27: Chemicals
A28: Chemical | B28: Rate(MK/kg)
A29: Chlorine | B29: 7400 | C29: kg | D29: 10.2 | E29: 12.5 | F29: 12.4 | G29: 15 | H29: 14 | I29: 15 | J29: 15 | K29: 16 | L29: 17.3 | M29: 10 | N29: 13 | O29: 14 | P29: =SUM(D29:O29) -> 164.4
C30: kg/mg litre | D30: =IFERROR(D29/(D9/1000),0) -> 2.4896266 | E30: =IFERROR(E29/(E9/1000),0) -> 2.3536057 | F30: =IFERROR(F29/(F9/1000),0) -> 2.1527778 | G30: =IFERROR(G29/(G9/1000),0) -> 3.2397408 | H30: =IFERROR(H29/(H9/1000),0) -> 2.4001372 | I30: =IFERROR(I29/(I9/1000),0) -> 2.2371365 | J30: =IFERROR(J29/(J9/1000),0) -> 2.2341376 | K30: =IFERROR(K29/(K9/1000),0) -> 2.8469751 | ... P30: =IFERROR(P29/(P9/1000),0) -> 2.4667647
A31: Aluminium sulphate | B31: 1900 | C31: kg | D31: 37.5 | E31: 27.5 | F31: 21 | G31: 22.3 | H31: 23 | I31: 24 | J31: 39 | K31: 44 | L31: 72.8 | M31: 58 | N31: 60 | O31: 55 | P31: =SUM(D31:O31) -> 484.1
C32: kg/mg litre | D32: =IFERROR(D31/(D9/1000),0) -> 9.1530388 | E32: =IFERROR(E31/(E9/1000),0) -> 5.1779326 | F32: =IFERROR(F31/(F9/1000),0) -> 3.6458333 | G32: =IFERROR(G31/(G9/1000),0) -> 4.8164147 | H32: =IFERROR(H31/(H9/1000),0) -> 3.9430825 | I32: =IFERROR(I31/(I9/1000),0) -> 3.5794183 | J32: =IFERROR(J31/(J9/1000),0) -> 5.8087578 | K32: =IFERROR(K31/(K9/1000),0) -> 7.8291815 | ... P32: =IFERROR(P31/(P9/1000),0) -> 7.2637518
A33: Soda | B33: 1900 | C33: kg | D33: 13.1 | E33: 9.9 | F33: 9.8 | G33: 11.3 | H33: 14 | I33: 8 | J33: 10 | K33: 12 | L33: 26.550395 | M33: 16 | N33: 15 | O33: 24 | P33: =SUM(D33:O33) -> 169.65039
C34: kg/mg litre | D34: =IFERROR(D33/(D9/1000),0) -> 3.1974616 | E34: =IFERROR(E33/(E9/1000),0) -> 1.8640557 | F34: =IFERROR(F33/(F9/1000),0) -> 1.7013889 | G34: =IFERROR(G33/(G9/1000),0) -> 2.4406048 | H34: =IFERROR(H33/(H9/1000),0) -> 2.4001372 | I34: =IFERROR(I33/(I9/1000),0) -> 1.1931394 | J34: =IFERROR(J33/(J9/1000),0) -> 1.4894251 | K34: =IFERROR(K33/(K9/1000),0) -> 2.1352313 | ... P34: =IFERROR(P33/(P9/1000),0) -> 2.545545
A35: Algae floc | B35: =745345.16/200 -> 3726.7258 | C35: litres | D35: 0 | E35: 0 | F35: 0 | G35: 0 | H35: 0 | I35: 0 | J35: 0 | K35: 0 | L35: 0 | M35: 0 | N35: 0 | O35: 0
C36: litres/mg litre
A37: Sud floc | B37: =790318.72/200 -> 3951.5936 | C37: litres | D37: 0 | E37: 0 | F37: 0 | G37: 0 | H37: 0 | I37: 0 | J37: 0 | K37: 0 | L37: 0 | M37: 0 | N37: 0 | O37: 0 | P37: =SUM(D37:O37) -> 0
C38: litres/mg litre | D38: =IFERROR(D37/(D9/1000),0) -> 0 | E38: =IFERROR(E37/(E9/1000),0) -> 0 | F38: =IFERROR(F37/(F9/1000),0) -> 0 | G38: =IFERROR(G37/(G9/1000),0) -> 0 | H38: =IFERROR(H37/(H9/1000),0) -> 0 | I38: =IFERROR(I37/(I9/1000),0) -> 0 | J38: =IFERROR(J37/(J9/1000),0) -> 0 | K38: =IFERROR(K37/(K9/1000),0) -> 0 | ... P38: =IFERROR(P37/(P9/1000),0) -> 0
A39: Potasium permanganate | B39: 1950 | C39: kg | D39: 0 | E39: 0 | F39: 0 | G39: 0 | H39: 0 | I39: 0 | J39: 0 | K39: 0 | L39: 0 | M39: 0 | N39: 0 | O39: 0 | P39: =SUM(D39:O39) -> 0
C40: kg/mg litre | D40: =IFERROR(D39/(D9/1000),0) -> 0 | E40: =IFERROR(E39/(E9/1000),0) -> 0 | F40: =IFERROR(F39/(F9/1000),0) -> 0 | G40: =IFERROR(G39/(G9/1000),0) -> 0 | H40: =IFERROR(H39/(H9/1000),0) -> 0 | I40: =IFERROR(I39/(I9/1000),0) -> 0 | J40: =IFERROR(J39/(J9/1000),0) -> 0 | K40: =IFERROR(K39/(K9/1000),0) -> 0 | ... P40: =IFERROR(P39/(P9/1000),0) -> 0
A41: Cost of Chemicals | C41: Mk | D41: =(D29*$B29)+(D31*$B31)+(D33*$B33)+(D35*$B35)+(D37*$B37)+(D39*$B39) -> 171620 | E41: =(E29*$B29)+(E31*$B31)+(E33*$B33)+(E35*$B35)+(E37*$B37)+(E39*$B39) -> 163560 | F41: =(F29*$B29)+(F31*$B31)+(F33*$B33)+(F35*$B35)+(F37*$B37)+(F39*$B39) -> 150280 | G41: =(G29*$B29)+(G31*$B31)+(G33*$B33)+(G35*$B35)+(G37*$B37)+(G39*$B39) -> 174840 | H41: =(H29*$B29)+(H31*$B31)+(H33*$B33)+(H35*$B35)+(H37*$B37)+(H39*$B39) -> 173900 | I41: =(I29*$B29)+(I31*$B31)+(I33*$B33)+(I35*$B35)+(I37*$B37)+(I39*$B39) -> 171800 | J41: =(J29*$B29)+(J31*$B31)+(J33*$B33)+(J35*$B35)+(J37*$B37)+(J39*$B39) -> 204100 | K41: =(K29*$B29)+(K31*$B31)+(K33*$B33)+(K35*$B35)+(K37*$B37)+(K39*$B39) -> 224800 | ... O41: =(O29*$B29)+(O31*$B31)+(O33*$B33)+(O35*$B35)+(O37*$B37)+(O39*$B39) -> 253700 | P41: =SUM(D41:O41) -> 2458685.7
A42: Cost/vol. Produced (chemicals) | C42: Mk/m3 | D42: =IFERROR(D41/D9,0) -> 41.889187 | E42: =IFERROR(E41/E9,0) -> 30.79646 | F42: =IFERROR(F41/F9,0) -> 26.090278 | G42: =IFERROR(G41/G9,0) -> 37.762419 | H42: =IFERROR(H41/H9,0) -> 29.813132 | I42: =IFERROR(I41/I9,0) -> 25.62267 | J42: =IFERROR(J41/J9,0) -> 30.399166 | K42: =IFERROR(K41/K9,0) -> 40 | ... P42: =IFERROR(P41/P9,0) -> 36.891723
A43: Power
A44: Power Usage | C44: Kw | D44: 207.3 | E44: 298.6 | F44: 301.8 | G44: 354.3 | H44: 329.63 | I44: 396.5 | J44: 379.02 | K44: 377.58 | L44: 482.2 | M44: 315.86 | N44: 342.9 | O44: 368.62 | P44: =SUM(D44:O44) -> 4154.31
A45: Power/ Vol. Produced | C45: Kw/m3 | D45: =IFERROR(D44/D9,0) -> 0.050597999 | E45: =IFERROR(E44/E9,0) -> 0.056222934 | F45: =IFERROR(F44/F9,0) -> 0.052395833 | G45: =IFERROR(G44/G9,0) -> 0.076522678 | H45: =IFERROR(H44/H9,0) -> 0.056511229 | I45: =IFERROR(I44/I9,0) -> 0.059134974 | J45: =IFERROR(J44/J9,0) -> 0.056452189 | K45: =IFERROR(K44/K9,0) -> 0.067185053 | ... P45: =IFERROR(P44/P9,0) -> 0.062333974
A46: Cost of Power | C46: Mk | D46: =IF(D44=0,0,IF(D44>=0,0+(D44*202.25)+23390)*1.165) -> 76093.635 | E46: =IF(E44=0,0,IF(E44>=0,0+(E44*202.25)+23390)*1.165) -> 97605.855 | F46: =IF(F44=0,0,IF(F44>=0,0+(F44*202.25)+23390)*1.165) -> 98359.843 | G46: =IF(G44=0,0,IF(G44>=0,0+(G44*202.25)+23390)*1.165) -> 110729.96 | H46: =IF(H44=0,0,IF(H44>=0,0+(H44*202.25)+23390)*1.165) -> 104917.18 | I46: =IF(I44=0,0,IF(I44>=0,0+(I44*202.25)+23390)*1.165) -> 120673.18 | J46: =IF(J44=0,0,IF(J44>=0,0+(J44*202.25)+23390)*1.165) -> 116554.52 | K46: =IF(K44=0,0,IF(K44>=0,0+(K44*202.25)+23390)*1.165) -> 116215.22 | ... O46: =IF(O44=0,0,IF(O44>=0,0+(O44*202.25)+23390)*1.165) -> 114104.06 | P46: =SUM(D46:O46) -> 1305835.9
A47: Cost/vol. Produced | C47: Mk/m3 | D47: =IFERROR(D46/D9,0) -> 18.573013 | E47: =IFERROR(E46/E9,0) -> 18.378056 | F47: =IFERROR(F46/F9,0) -> 17.076362 | G47: =IFERROR(G46/G9,0) -> 23.915758 | H47: =IFERROR(H46/H9,0) -> 17.986831 | I47: =IFERROR(I46/I9,0) -> 17.997491 | J47: =IFERROR(J46/J9,0) -> 17.359922 | K47: =IFERROR(K46/K9,0) -> 20.678865 | ... P47: =IFERROR(P46/P9,0) -> 19.593613
A48: Plant and Vehicle Maintenance
A49: Distances covered | C49: km | D49: 0 | E49: 0 | F49: 0 | G49: 0 | H49: 0 | I49: 0 | J49: 0 | K49: 0 | L49: 0 | M49: 0 | N49: 0 | O49: 0 | P49: =SUM(D49:O49) -> 0
A50: Fuel Used (litres) | C50: litres | D50: 0 | E50: 0 | F50: 0 | G50: 0 | H50: 0 | I50: 0 | J50: 0 | K50: 0 | L50: 0 | M50: 0 | N50: 0 | O50: 0 | P50: =SUM(D50:O50) -> 0
A51: Cost of fuel | C51: Mk | D51: 0 | E51: 0 | F51: 0 | G51: 0 | H51: 0 | I51: 0 | J51: 0 | K51: 0 | L51: 0 | M51: 0 | N51: 0 | O51: 0 | P51: =SUM(D51:O51) -> 0
A52: Maintenance | C52: Mk | D52: 0 | E52: 0 | F52: 0 | G52: 0 | H52: 0 | I52: 0 | J52: 0 | K52: 0 | L52: 0 | M52: 0 | N52: 0 | O52: 0 | P52: =SUM(D52:O52) -> 0
A53: Salaries and Wages
A54: Staff Costs | C54: MK | D54: 0 | E54: 0 | F54: 0 | G54: 0 | H54: 0 | I54: 0 | J54: 0 | K54: 0 | L54: 0 | M54: 0 | N54: 0 | O54: 0 | P54: =SUM(D54:O54) -> 0
A55: Wages | C55: MK | D55: 0 | E55: 0 | F55: 0 | G55: 0 | H55: 0 | I55: 0 | J55: 0 | K55: 0 | L55: 0 | M55: 0 | N55: 0 | O55: 0 | P55: =SUM(D55:O55) -> 0
A56: Other Overhead Costs | C56: MK | D56: 0 | E56: 0 | F56: 0 | G56: 0 | H56: 0 | I56: 0 | J56: 0 | K56: 0 | L56: 0 | M56: 0 | N56: 0 | O56: 0 | P56: =SUM(D56:O56) -> 0
A57: Operating Costs
A58: Total Operating Costs | C58: MK | D58: =D41+D46+D51+D52+D54+D55+D56 -> 247713.64 | E58: =E41+E46+E51+E52+E54+E55+E56 -> 261165.86 | F58: =F41+F46+F51+F52+F54+F55+F56 -> 248639.84 | G58: =G41+G46+G51+G52+G54+G55+G56 -> 285569.96 | H58: =H41+H46+H51+H52+H54+H55+H56 -> 278817.18 | I58: =I41+I46+I51+I52+I54+I55+I56 -> 292473.18 | J58: =J41+J46+J51+J52+J54+J55+J56 -> 320654.52 | K58: =K41+K46+K51+K52+K54+K55+K56 -> 341015.22 | ... O58: =O41+O46+O51+O52+O54+O55+O56 -> 367804.06 | P58: =SUM(D58:O58) -> 3764521.7
A59: Cost/Vol. Produced | C59: Mk/m3 | D59: =IFERROR(D58/D9,0) -> 60.4622 | E59: =IFERROR(E58/E9,0) -> 49.174516 | F59: =IFERROR(F58/F9,0) -> 43.166639 | G59: =IFERROR(G58/G9,0) -> 61.678177 | H59: =IFERROR(H58/H9,0) -> 47.799963 | I59: =IFERROR(I58/I9,0) -> 43.62016 | J59: =IFERROR(J58/J9,0) -> 47.759088 | K59: =IFERROR(K58/K9,0) -> 60.678865 | ... P59: =IFERROR(P58/P9,0) -> 56.485335
A60: Cost/Vol. Billed | C60: Mk/m3 | D60: =IFERROR(D58/D22,0) -> 81.522292 | E60: =IFERROR(E58/E22,0) -> 79.331082 | F60: =IFERROR(F58/F22,0) -> 48.642273 | G60: =IFERROR(G58/G22,0) -> 78.416662 | H60: =IFERROR(H58/H22,0) -> 68.080574 | I60: =IFERROR(I58/I22,0) -> 68.63312 | J60: =IFERROR(J58/J22,0) -> 69.778799 | K60: =IFERROR(K58/K22,0) -> 77.126591 | ... P60: =IFERROR(P58/P22,0) -> 77.011013
A61: Permanent Staff Employed | C61: No | D61: 1 | E61: 1 | F61: 1 | G61: 1 | H61: 1 | I61: 1 | J61: 1 | K61: 1 | L61: 1 | M61: 1 | N61: 1 | O61: 1 | P61: =O61 -> 1
A62: Staff/Vol.1000m3 of Volume Produced/hour (12 hour day) | C62: No/1000m3 | D62: =IFERROR((D61*1000*31)/D9,0) -> 7.5665121 | E62: =IFERROR((E61*1000*31)/E9,0) -> 5.8369422 | F62: =IFERROR((F61*1000*31)/F9,0) -> 5.3819444 | G62: =IFERROR((G61*1000*31)/G9,0) -> 6.6954644 | H62: =IFERROR((H61*1000*31)/H9,0) -> 5.3145894 | I62: =IFERROR((I61*1000*31)/I9,0) -> 4.6234154 | J62: =IFERROR((J61*1000*31)/J9,0) -> 4.6172178 | K62: =IFERROR((K61*1000*31)/K9,0) -> 5.5160142 | ... P62: =IFERROR((P61*1000*31)/P9,0) -> 0.46514419
A63: Temporary Staff Employed | C63: No | D63: 6 | E63: 6 | F63: 6 | G63: 6 | H63: 6 | I63: 6 | J63: 6 | K63: 6 | L63: 6 | M63: 6 | N63: 6 | O63: 6 | P63: =O63 -> 6
A65: Water Connections and Disconnections
A66: New Individual Water Connections | B66: Brought Forward | C66: No | D66: 1 | E66: 2 | F66: 2 | G66: 4 | H66: 10 | I66: 12 | J66: 3 | K66: 5 | L66: 3 | M66: 5 | N66: 3 | O66: 9 | P66: =D66 -> 1
B67: Applied this Month | C67: No | D67: 5 | E67: 6 | F67: 6 | G67: 8 | H67: 11 | I67: 0 | J67: 4 | K67: 1 | L67: 7 | M67: 3 | N67: 6 | O67: 3 | P67: =SUM(D67:O67) -> 60
B68: Done this Month Postpaid | C68: No | D68: 4 | E68: 6 | F68: 4 | G68: 2 | H68: 9 | I68: 9 | J68: 2 | K68: 3 | L68: 5 | M68: 5 | N68: 0 | O68: 7 | P68: =SUM(D68:O68) -> 56
B69: Done this Month Prepaid | C69: No | D69: 0 | E69: 0 | F69: 0 | G69: 0 | H69: 0 | I69: 0 | J69: 0 | K69: 0 | L69: 0 | M69: 0 | N69: 0 | O69: 0 | P69: =SUM(D69:O69) -> 0
B70: Total Done | C70: No | D70: =D68+D69 -> 4 | E70: =E68+E69 -> 6 | F70: =F68+F69 -> 4 | G70: =G68+G69 -> 2 | H70: =H68+H69 -> 9 | I70: =I68+I69 -> 9 | J70: =J68+J69 -> 2 | K70: =K68+K69 -> 3 | ... P70: =P68+P69 -> 56
B71: Carried Forward | C71: No | D71: =D66+D67-D70 -> 2 | E71: =E66+E67-E70 -> 2 | F71: =F66+F67-F70 -> 4 | G71: =G66+G67-G70 -> 10 | H71: =H66+H67-H70 -> 12 | I71: =I66+I67-I70 -> 3 | J71: =J66+J67-J70 -> 5 | K71: =K66+K67-K70 -> 3 | ... P71: =P66+P67-P70 -> 5
A72: New Institutional Water Connections | B72: Brought Forward | C72: No | D72: 1 | E72: 1 | F72: 1 | G72: 1 | H72: 1 | I72: 1 | J72: 1 | K72: 1 | L72: 1 | M72: 1 | N72: 1 | O72: 1 | P72: =D72 -> 1
B73: Applied this Month | C73: No | D73: 0 | E73: 0 | F73: 0 | G73: 0 | H73: 0 | I73: 0 | J73: 0 | K73: 0 | L73: 0 | M73: 0 | N73: 0 | O73: 0 | P73: =SUM(D73:O73) -> 0
B74: Done this Month Postpaid | C74: No | D74: 0 | E74: 0 | F74: 0 | G74: 0 | H74: 0 | I74: 0 | J74: 0 | K74: 0 | L74: 0 | M74: 0 | N74: 0 | O74: 0 | P74: =SUM(D74:O74) -> 0
B75: Done this Month Prepaid | C75: No | D75: 0 | E75: 0 | F75: 0 | G75: 0 | H75: 0 | I75: 0 | J75: 0 | K75: 0 | L75: 0 | M75: 0 | N75: 0 | O75: 0 | P75: =SUM(D75:O75) -> 0
B76: Total Done | C76: No | D76: =D74+D75 -> 0 | E76: =E74+E75 -> 0 | F76: =F74+F75 -> 0 | G76: =G74+G75 -> 0 | H76: =H74+H75 -> 0 | I76: =I74+I75 -> 0 | J76: =J74+J75 -> 0 | K76: =K74+K75 -> 0 | ... P76: =P74+P75 -> 0
B77: Carried Forward | C77: No | D77: =D72+D73-D76 -> 1 | E77: =E72+E73-E76 -> 1 | F77: =F72+F73-F76 -> 1 | G77: =G72+G73-G76 -> 1 | H77: =H72+H73-H76 -> 1 | I77: =I72+I73-I76 -> 1 | J77: =J72+J73-J76 -> 1 | K77: =K72+K73-K76 -> 1 | ... P77: =P72+P73-P76 -> 1
A78: New Commercial/Industrial Water Connections | B78: Brought Forward | C78: No | D78: 0 | E78: 0 | F78: 0 | G78: 0 | H78: 0 | I78: 0 | J78: 0 | K78: 0 | L78: 0 | M78: 0 | N78: 0 | O78: 0 | P78: =D78 -> 0
B79: Applied this Month | C79: No | D79: 1 | E79: 0 | F79: 0 | G79: 0 | H79: 0 | I79: 0 | J79: 0 | K79: 0 | L79: 0 | M79: 0 | N79: 0 | O79: 0 | P79: =SUM(D79:O79) -> 1
B80: Done this Month Postpaid | C80: No | D80: 1 | E80: 0 | F80: 0 | G80: 0 | H80: 0 | I80: 0 | J80: 0 | K80: 0 | L80: 0 | M80: 0 | N80: 0 | O80: 0 | P80: =SUM(D80:O80) -> 1
B81: Done this Month Prepaid | C81: No | D81: 0 | E81: 0 | F81: 0 | G81: 0 | H81: 0 | I81: 0 | J81: 0 | K81: 0 | L81: 0 | M81: 0 | N81: 0 | O81: 0 | P81: =SUM(D81:O81) -> 0
B82: Total Done | C82: No | D82: =D80+D81 -> 1 | E82: =E80+E81 -> 0 | F82: =F80+F81 -> 0 | G82: =G80+G81 -> 0 | H82: =H80+H81 -> 0 | I82: =I80+I81 -> 0 | J82: =J80+J81 -> 0 | K82: =K80+K81 -> 0 | ... O82: =O80+O81 -> 0 | P82: =P81+P80 -> 1
B83: Carried Forward | C83: No | D83: =D78+D79-D82 -> 0 | E83: =E78+E79-E82 -> 0 | F83: =F78+F79-F82 -> 0 | G83: =G78+G79-G82 -> 0 | H83: =H78+H79-H82 -> 0 | I83: =I78+I79-I82 -> 0 | J83: =J78+J79-J82 -> 0 | K83: =K78+K79-K82 -> 0 | ... P83: =P78+P79-P82 -> 0
A84: New CWP | B84: Brought Forward | C84: No | D84: 0 | E84: 0 | F84: 0 | G84: 0 | H84: 0 | I84: 0 | J84: 0 | K84: 0 | L84: 0 | M84: 0 | N84: 0 | O84: 0 | P84: =D84 -> 0
B85: Applied this Month | C85: No | D85: 0 | E85: 0 | F85: 0 | G85: 0 | H85: 0 | I85: 0 | J85: 0 | K85: 0 | L85: 0 | M85: 0 | N85: 0 | O85: 0 | P85: =SUM(D85:O85) -> 0
B86: Done this Month Postpaid | C86: No | D86: 0 | E86: 0 | F86: 0 | G86: 0 | H86: 0 | I86: 0 | J86: 0 | K86: 0 | L86: 0 | M86: 0 | N86: 0 | O86: 0 | P86: =SUM(D86:O86) -> 0
B87: Done this Month Prepaid | C87: No | D87: 0 | E87: 0 | F87: 0 | G87: 0 | H87: 0 | I87: 0 | J87: 0 | K87: 0 | L87: 0 | M87: 0 | N87: 0 | O87: 0 | P87: =SUM(D87:O87) -> 0
B88: Total Done | C88: No | D88: =D86+D87 -> 0 | E88: =E86+E87 -> 0 | F88: =F86+F87 -> 0 | G88: =G86+G87 -> 0 | H88: =H86+H87 -> 0 | I88: =I86+I87 -> 0 | J88: =J86+J87 -> 0 | K88: =K86+K87 -> 0 | ... O88: =O86+O87 -> 0 | P88: =SUM(D88:O88) -> 0
B89: Carried Forward | C89: No | D89: =D84+D85-D88 -> 0 | E89: =E84+E85-E88 -> 0 | F89: =F84+F85-F88 -> 0 | G89: =G84+G85-G88 -> 0 | H89: =H84+H85-H88 -> 0 | I89: =I84+I85-I88 -> 0 | J89: =J84+J85-J88 -> 0 | K89: =K84+K85-K88 -> 0 | ... O89: =O84+O85-O88 -> 0 | P89: =P84+P85-P86-P87 -> 0
A90: Aggregated New Water connections | B90: Brought Forward | C90: No | D90: =D66+D72+D78+D84 -> 2 | E90: =E66+E72+E78+E84 -> 3 | F90: =F66+F72+F78+F84 -> 3 | G90: =G66+G72+G78+G84 -> 5 | H90: =H66+H72+H78+H84 -> 11 | I90: =I66+I72+I78+I84 -> 13 | J90: =J66+J72+J78+J84 -> 4 | K90: =K66+K72+K78+K84 -> 6 | ... O90: =O66+O72+O78+O84 -> 10 | P90: =D90 -> 2
B91: Applied this Month | C91: No | D91: =D67+D73+D79+D85 -> 6 | E91: =E67+E73+E79+E85 -> 6 | F91: =F67+F73+F79+F85 -> 6 | G91: =G67+G73+G79+G85 -> 8 | H91: =H67+H73+H79+H85 -> 11 | I91: =I67+I73+I79+I85 -> 0 | J91: =J67+J73+J79+J85 -> 4 | K91: =K67+K73+K79+K85 -> 1 | ... O91: =O67+O73+O79+O85 -> 3 | P91: =SUM(D91:O91) -> 61
B92: Done this Month Postpaid | C92: No | D92: =D68+D74+D80+D86 -> 5 | E92: =E68+E74+E80+E86 -> 6 | F92: =F68+F74+F80+F86 -> 4 | G92: =G68+G74+G80+G86 -> 2 | H92: =H68+H74+H80+H86 -> 9 | I92: =I68+I74+I80+I86 -> 9 | J92: =J68+J74+J80+J86 -> 2 | K92: =K68+K74+K80+K86 -> 3 | ... O92: =O68+O74+O80+O86 -> 7 | P92: =SUM(D92:O92) -> 57
B93: Done this Month Prepaid | D93: =D69+D75+D81+D87 -> 0 | E93: =E69+E75+E81+E87 -> 0 | F93: =F69+F75+F81+F87 -> 0 | G93: =G69+G75+G81+G87 -> 0 | H93: =H69+H75+H81+H87 -> 0 | I93: =I69+I75+I81+I87 -> 0 | J93: =J69+J75+J81+J87 -> 0 | K93: =K69+K75+K81+K87 -> 0 | ... O93: =O69+O75+O81+O87 -> 0 | P93: =SUM(D93:O93) -> 0
B94: Total Done | C94: No | D94: =D93+D92 -> 5 | E94: =E93+E92 -> 6 | F94: =F93+F92 -> 4 | G94: =G93+G92 -> 2 | H94: =H93+H92 -> 9 | I94: =I93+I92 -> 9 | J94: =J93+J92 -> 2 | K94: =K93+K92 -> 3 | ... P94: =P93+P92 -> 57
B95: Carried Forward | C95: No | D95: =D90+D91-D94 -> 3 | E95: =E90+E91-E94 -> 3 | F95: =F90+F91-F94 -> 5 | G95: =G90+G91-G94 -> 11 | H95: =H90+H91-H94 -> 13 | I95: =I90+I91-I94 -> 4 | J95: =J90+J91-J94 -> 6 | K95: =K90+K91-K94 -> 4 | ... P95: =P90+P91-P94 -> 6
A97: Prepaid Metering
A98: Prepaid Meters Installed | C98: No | D98: 0 | E98: 0 | F98: 0 | G98: 0 | H98: 0 | I98: 0 | J98: 0 | K98: 0 | L98: 0 | M98: 0 | N98: 0 | O98: 0 | P98: =SUM(D98:O98) -> 0
A100: Active and Disconnected Accounts
A101: Disconnected Individual Accounts | C101: No | D101: 24 | E101: 24 | F101: 29 | G101: 28 | H101: 29 | I101: 27 | J101: 29 | K101: 19 | L101: 26 | M101: 29 | N101: 29 | O101: 0 | P101: =O101 -> 0
A102: Disconnected institutional Accounts | C102: No | D102: 0 | E102: 0 | F102: 1 | G102: 0 | H102: 0 | I102: 0 | J102: 0 | K102: 4 | L102: 0 | M102: 0 | N102: 0 | O102: 0 | P102: =O102 -> 0
A103: Disconnected Commercial/Industrial Accounts | C103: No | D103: 0 | E103: 0 | F103: 0 | G103: 0 | H103: 0 | I103: 0 | J103: 0 | K103: 7 | L103: 0 | M103: 0 | N103: 0 | O103: 0 | P103: =O103 -> 0
A104: Disconnected CWP | C104: No | D104: 0 | E104: 0 | F104: 0 | G104: 0 | H104: 0 | I104: 0 | J104: 0 | K104: 0 | L104: 0 | M104: 0 | N104: 0 | O104: 0 | P104: =O104 -> 0
A105: Total Disconnected Accounts | C105: No | D105: =SUM(D101:D104) -> 24 | E105: =SUM(E101:E104) -> 24 | F105: =SUM(F101:F104) -> 30 | G105: =SUM(G101:G104) -> 28 | H105: =SUM(H101:H104) -> 29 | I105: =SUM(I101:I104) -> 27 | J105: =SUM(J101:J104) -> 29 | K105: =SUM(K101:K104) -> 30 | ... O105: =SUM(O101:O104) -> 0 | P105: =O105 -> 0
A106: Postpaid Consumers
...

Sheet Lirangwe
A1: SOUTHERN REGION WATER BOARD
A3: MONTHLY REPORTS - 2024/2025
A4: ZOMBA ZONE
A5: LIRANGWE SCHEME
A7: PARAMETERS | C7: UNITS | D7: APRIL | E7: MAY | F7: JUNE | G7: JULY | H7: AUGUST | I7: SEPTEMBER | J7: OCTOBER | K7: NOVEMBER | L7: DECEMBER | M7: JANUARY | N7: FEBRUARY | O7: MARCH | P7: TOTALS
A8: PRODUCTION
A9: Volume Produced | C9: m3 | D9: 6330 | E9: 6842 | F9: 5962 | G9: 6878 | H9: 8837 | I9: 8875 | J9: 9023 | K9: 6520 | L9: 9103 | M9: 6805 | N9: 6589 | O9: 5898 | P9: =SUM(D9:O9) -> 87662
A10: REVENUE WATER - POSTPAID
A11: Volume Billed Individuals | C11: m3 | D11: 437 | E11: 573 | F11: 659 | G11: 832 | H11: 927 | I11: 1186 | J11: 1468 | K11: 813 | L11: 957 | M11: 612 | N11: 481 | O11: 325 | P11: =SUM(D11:O11) -> 9270
A12: Volume Billed CWPs | C12: m3 | D12: 0 | E12: 0 | F12: 0 | G12: 0 | H12: 0 | I12: 0 | J12: 0 | K12: 0 | L12: 0 | M12: 0 | N12: 0 | O12: 0 | P12: =SUM(D12:O12) -> 0
A13: Volume Billed Institutions | C13: m3 | D13: 11 | E13: 17 | F13: 16 | G13: 143 | H13: 354 | I13: 43 | J13: 52 | K13: 12 | L13: 25 | M13: 8 | N13: 13 | O13: 11 | P13: =SUM(D13:O13) -> 705
A14: Volume Billed Commercial/Industrial | C14: m3 | D14: 10 | E14: 6 | F14: 5 | G14: 7 | H14: 5 | I14: 10 | J14: 8 | K14: 3 | L14: 0 | M14: 0 | N14: 0 | O14: 0 | P14: =SUM(D14:O14) -> 54
A15: Total Volume Billed Post Paid | C15: m3 | D15: =SUM(D11:D14) -> 458 | E15: =SUM(E11:E14) -> 596 | F15: =SUM(F11:F14) -> 680 | G15: =SUM(G11:G14) -> 982 | H15: =SUM(H11:H14) -> 1286 | I15: =SUM(I11:I14) -> 1239 | J15: =SUM(J11:J14) -> 1528 | K15: =SUM(K11:K14) -> 828 | ... P15: =SUM(P11:P14) -> 10029
A16: REVENUE WATER - PREPAID
A17: Individuals | C17: m3 | D17: 3600.4 | E17: 4003.9 | F17: 3779.7 | G17: 3988 | H17: 4856.3 | I17: 5035.9 | J17: 5112.6 | K17: 4518.8 | L17: 5089.1 | M17: 4134.3 | N17: 3697.5 | O17: 4815.3 | P17: =SUM(D17:O17) -> 52631.8
A18: CWPs | C18: m3 | D18: 129.7 | E18: 183 | F18: 149 | G18: 176.1 | H18: 269.6 | I18: 264.8 | J18: 277.5 | K18: 222.1 | L18: 291.1 | M18: 281.1 | N18: 197.8 | O18: 327.2 | P18: =SUM(D18:O18) -> 2769
A19: Institutions | C19: m3 | D19: 202.6 | E19: 561.4 | F19: 262 | G19: 495.3 | H19: 82.6 | I19: 308.8 | J19: 349.5 | K19: 93.8 | L19: 142.8 | M19: 583.1 | N19: 272.7 | O19: 60.2 | P19: =SUM(D19:O19) -> 3414.8
A20: Commercial/Industrial | C20: m3 | D20: 10.8 | E20: 30.4 | F20: 58.1 | G20: 52.2 | H20: 80.5 | I20: 50.4 | J20: 33.9 | K20: 50 | L20: 110 | M20: 51.6 | N20: 60.9 | O20: 110.6 | P20: =SUM(D20:O20) -> 699.4
A21: Total Volume Prepaid | C21: m3 | D21: =SUM(D17:D20) -> 3943.5 | E21: =SUM(E17:E20) -> 4778.7 | F21: =SUM(F17:F20) -> 4248.8 | G21: =SUM(G17:G20) -> 4711.6 | H21: =SUM(H17:H20) -> 5289 | I21: =SUM(I17:I20) -> 5659.9 | J21: =SUM(J17:J20) -> 5773.5 | K21: =SUM(K17:K20) -> 4884.7 | ... P21: =SUM(P17:P20) -> 59515
A22: TOTAL REVENUE WATER | C22: m3 | D22: =D21+D15 -> 4401.5 | E22: =E21+E15 -> 5374.7 | F22: =F21+F15 -> 4928.8 | G22: =G21+G15 -> 5693.6 | H22: =H21+H15 -> 6575 | I22: =I21+I15 -> 6898.9 | J22: =J21+J15 -> 7301.5 | K22: =K21+K15 -> 5712.7 | ... P22: =P21+P15 -> 69544
A24: Non-Revenue Water (NRW) | B24: Volume | C24: m3 | D24: =D9-D22 -> 1928.5 | E24: =E9-E22 -> 1467.3 | F24: =F9-F22 -> 1033.2 | G24: =G9-G22 -> 1184.4 | H24: =H9-H22 -> 2262 | I24: =I9-I22 -> 1976.1 | J24: =J9-J22 -> 1721.5 | K24: =K9-K22 -> 807.3 | ... P24: =P9-P22 -> 18118
B25: Percentage | C25: % | D25: =IFERROR(D24/D9,0) -> 0.30466035 | E25: =E24/E9 -> 0.21445484 | F25: =F24/F9 -> 0.17329755 | G25: =IFERROR(G24/G9,0) -> 0.17220122 | H25: =IFERROR(H24/H9,0) -> 0.25596922 | I25: =IFERROR(I24/I9,0) -> 0.22265915 | J25: =IFERROR(J24/J9,0) -> 0.1907902 | K25: =IFERROR(K24/K9,0) -> 0.12381902 | L25: =IFERROR(L24/L9,0) -> 0.27331649 | M25: =IFERROR(M24/M9,0) -> 0.16677443 | N25: =IFERROR(N24/N9,0) -> 0.28321445 | O25: =IFERROR(O24/O9,0) -> 0.042166836 | P25: =IF(P9,P24/P9,"") -> 0.2066802
A26: OPERATING EXPENSES
A27: Chemicals
A28: Chemical | B28: Rate(MK/kg)
A29: Chlorine | B29: 7400 | C29: kg | D29: 6 | E29: 7 | F29: 6 | G29: 5 | H29: 5.5 | I29: 6 | J29: 7.5 | K29: 7 | L29: 7 | M29: 7 | N29: 7 | O29: 6 | P29: =SUM(D29:O29) -> 77
C30: kg/mg litre | D30: =IFERROR(D29/(D9/1000),0) -> 0.9478673 | E30: =IFERROR(E29/(E9/1000),0) -> 1.0230927 | F30: =IFERROR(F29/(F9/1000),0) -> 1.0063737 | G30: =IFERROR(G29/(G9/1000),0) -> 0.72695551 | H30: =IFERROR(H29/(H9/1000),0) -> 0.62238316 | I30: =IFERROR(I29/(I9/1000),0) -> 0.67605634 | J30: =IFERROR(J29/(J9/1000),0) -> 0.83120913 | K30: =IFERROR(K29/(K9/1000),0) -> 1.0736196 | ... P30: =IFERROR(P29/(P9/1000),0) -> 0.87837375
A31: Aluminium sulphate | B31: 1900 | C31: kg | D31: 0 | E31: 0 | F31: 0 | G31: 0 | H31: 0 | I31: 0 | J31: 0 | K31: 0 | L31: 0 | M31: 0 | N31: 0 | O31: 0 | P31: =SUM(D31:O31) -> 0
C32: kg/mg litre | D32: =IFERROR(D31/(D9/1000),0) -> 0 | E32: =IFERROR(E31/(E9/1000),0) -> 0 | F32: =IFERROR(F31/(F9/1000),0) -> 0 | G32: =IFERROR(G31/(G9/1000),0) -> 0 | H32: =IFERROR(H31/(H9/1000),0) -> 0 | I32: =IFERROR(I31/(I9/1000),0) -> 0 | J32: =IFERROR(J31/(J9/1000),0) -> 0 | K32: =IFERROR(K31/(K9/1000),0) -> 0 | ... P32: =IFERROR(P31/(P9/1000),0) -> 0
A33: Soda | B33: 1900 | C33: kg | D33: 0 | E33: 0 | F33: 0 | G33: 0 | H33: 0 | I33: 0 | J33: 0 | K33: 0 | L33: 0 | M33: 0 | N33: 0 | O33: 0 | P33: =SUM(D33:O33) -> 0
C34: kg/mg litre | D34: =IFERROR(D33/(D9/1000),0) -> 0 | E34: =IFERROR(E33/(E9/1000),0) -> 0 | F34: =IFERROR(F33/(F9/1000),0) -> 0 | G34: =IFERROR(G33/(G9/1000),0) -> 0 | H34: =IFERROR(H33/(H9/1000),0) -> 0 | I34: =IFERROR(I33/(I9/1000),0) -> 0 | J34: =IFERROR(J33/(J9/1000),0) -> 0 | K34: =IFERROR(K33/(K9/1000),0) -> 0 | ... P34: =IFERROR(P33/(P9/1000),0) -> 0
A35: Algae floc | B35: =745345.16/200 -> 3726.7258 | C35: litres | D35: 0 | E35: 0 | F35: 0 | G35: 0 | H35: 0 | I35: 0 | J35: 0 | K35: 0 | L35: 0 | M35: 0 | N35: 0 | O35: 0
C36: litres/mg litre
