Workbook

Sheet DataEntry
A1: RECORD DIMENSIONS | H1: WATER PRODUCTION & NRW | V1: TREATMENT CHEMICALS | AJ1: POWER | AN1: TRANSPORT & OPERATIONS | AX1: STAFFING | BA1: CONNECTIONS — INDIVIDUAL | BG1: CONNECTIONS — INSTITUTIONAL | BM1: CONNECTIONS — COMMERCIAL | BS1: CONNECTIONS — CWP | BY1: AGGREGATED CONNECTIONS | CC1: METERS & DISCONNECTIONS | CI1: ACTIVE CONSUMERS | CU1: POPULATION | CX1: STUCK METERS — INSTITUTIONAL | DC1: STUCK METERS — COMMERCIAL | DH1: STUCK METERS — CWP | DM1: STUCK METERS — INDIVIDUAL | DR1: AGGREGATED STUCK METERS | DW1: PIPE BREAKDOWNS — PVC | EJ1: PIPE BREAKDOWNS — GI | ES1: PIPE BREAKDOWNS — DI | EY1: PIPE BREAKDOWNS — HDPE & AC | FG1: TOTAL BREAKDOWNS | FH1: PUMPS & SUPPLY HOURS | FL1: DEVELOPMENT LINES | FR1: CASH COLLECTED | GC1: AMOUNTS BILLED | GN1: SERVICE CHARGES | GS1: METER RENTAL | GX1: FINANCIAL KPIs | HE1: CONNECTION PERFORMANCE | HL1: QUERY PERFORMANCE
A2: Zone | B2: Scheme | C2: Fiscal Year | D2: Year | E2: Month No. | F2: Month | G2: Quarter | H2: Volume Produced (m³) | I2: Vol Billed Individual Postpaid | J2: Vol Billed CWP Postpaid | K2: Vol Billed Institutions Postpaid | L2: Vol Billed Commercial Postpaid | M2: TOTAL Vol Billed Postpaid | N2: Vol Billed Individual Prepaid | O2: Vol Billed CWP Prepaid | P2: Vol Billed Institutions Prepaid | Q2: Vol Billed Commercial Prepaid | R2: TOTAL Vol Billed Prepaid | S2: TOTAL Revenue Water m³ | T2: Non-Revenue Water m³ | U2: % NRW | V2: Chlorine kg | W2: Chlorine kg per m³ | X2: Alum Sulphate kg | Y2: Alum Sulphate kg per m³ | Z2: Soda Ash kg | AA2: Soda Ash kg per m³ | AB2: Algae Floc litres | AC2: Algae Floc per m³ | AD2: Sud Floc litres | AE2: Sud Floc per m³ | AF2: Potassium Permanganate kg | AG2: KMnO4 per m³ | AH2: Cost of Chemicals MWK | AI2: Chem Cost per m³ | AJ2: Power Usage kWh | AK2: Power per m³ | AL2: Cost of Power MWK | AM2: Power Cost per m³ | AN2: Distances Covered km | AO2: Fuel Used litres | AP2: Cost of Fuel MWK | AQ2: Maintenance MWK | AR2: Staff Costs MWK | AS2: Wages MWK | AT2: Other Overhead MWK | AU2: TOTAL Operating Costs MWK | AV2: OpCost per m³ Produced | AW2: OpCost per m³ Billed | AX2: Permanent Staff | AY2: Staff per 1000m³ 12h | AZ2: Temporary Staff | BA2: Indiv Conn BroughtFwd | BB2: Indiv Conn Applied PP | BC2: Indiv Conn Done PP | BD2: Indiv Conn Done Prepaid | BE2: Indiv Conn TOTAL Done | BF2: Indiv Conn CarriedFwd | BG2: Inst Conn BroughtFwd | BH2: Inst Conn Applied PP | BI2: Inst Conn Done PP | BJ2: Inst Conn Done Prepaid | BK2: Inst Conn TOTAL Done | BL2: Inst Conn CarriedFwd | BM2: Comm Conn BroughtFwd | BN2: Comm Conn Applied PP | BO2: Comm Conn Done PP | BP2: Comm Conn Done Prepaid | BQ2: Comm Conn TOTAL Done | BR2: Comm Conn CarriedFwd | BS2: CWP Conn BroughtFwd | BT2: CWP Conn Applied PP | BU2: CWP Conn Done PP | BV2: CWP Conn Done Prepaid | BW2: CWP Conn TOTAL Done | BX2: CWP Conn CarriedFwd | BY2: ALL Conn BroughtFwd | BZ2: ALL Conn Applied | CA2: ALL Conn TOTAL Done | CB2: ALL Conn CarriedFwd | CC2: Prepaid Meters Installed | CD2: Disconnected Individual | CE2: Disconnected Institutional | CF2: Disconnected Commercial | CG2: Disconnected CWP | CH2: TOTAL Disconnected | CI2: Active Postpaid Individual | CJ2: Active Postpaid Institutional | CK2: Active Postpaid Commercial | CL2: Active Postpaid CWP | CM2: TOTAL Active Postpaid | CN2: Active Prepaid Individual | CO2: Active Prepaid Institutional | CP2: Active Prepaid Commercial | CQ2: Active Prepaid CWP | CR2: TOTAL Active Prepaid | CS2: TOTAL Active Customers | CT2: Total Metered Consumers | CU2: Population Supply Area | CV2: Population Supplied | CW2: Pct Population Supplied | CX2: Inst StuckM BroughtFwd | CY2: Inst StuckM New | CZ2: Inst StuckM Repaired | DA2: Inst StuckM Replaced | DB2: Inst StuckM CarriedFwd | DC2: Comm StuckM BroughtFwd | DD2: Comm StuckM New | DE2: Comm StuckM Repaired | DF2: Comm StuckM Replaced | DG2: Comm StuckM CarriedFwd | DH2: CWP StuckM BroughtFwd | DI2: CWP StuckM New | DJ2: CWP StuckM Repaired | DK2: CWP StuckM Replaced | DL2: CWP StuckM CarriedFwd | DM2: Indiv StuckM BroughtFwd | DN2: Indiv StuckM New | DO2: Indiv StuckM Repaired | DP2: Indiv StuckM Replaced | DQ2: Indiv StuckM CarriedFwd | DR2: ALL StuckM BroughtFwd | DS2: ALL StuckM New | DT2: ALL StuckM Repaired | DU2: ALL StuckM Replaced | DV2: ALL StuckM CarriedFwd | DW2: PVC 20mm | DX2: PVC 25mm | DY2: PVC 32mm | DZ2: PVC 40mm | EA2: PVC 50mm | EB2: PVC 63mm | EC2: PVC 75mm | ED2: PVC 90mm | EE2: PVC 110mm | EF2: PVC 160mm | EG2: PVC 200mm | EH2: PVC 250mm | EI2: PVC 315mm | EJ2: GI 15mm | EK2: GI 20mm | EL2: GI 25mm | EM2: GI 40mm | EN2: GI 50mm | EO2: GI 75mm | EP2: GI 100mm | EQ2: GI 150mm | ER2: GI 200mm | ES2: DI 150mm | ET2: DI 200mm | EU2: DI 250mm | EV2: DI 300mm | EW2: DI 350mm | EX2: DI 525mm | EY2: HDPE 20mm | EZ2: HDPE 25mm | FA2: HDPE 32mm | FB2: HDPE 50mm | FC2: AC 50mm | FD2: AC 75mm | FE2: AC 100mm | FF2: AC 150mm | FG2: TOTAL Pipe Breakdowns | FH2: Pump Breakdowns | FI2: Pump Hours Lost | FJ2: Normal Supply Hours | FK2: Power Failure Hours | FL2: DevLines 32mm | FM2: DevLines 50mm | FN2: DevLines 63mm | FO2: DevLines 90mm | FP2: DevLines 110mm | FQ2: TOTAL Dev Lines Done | FR2: Cash Coll Indiv PP | FS2: Cash Coll CWP PP | FT2: Cash Coll Comm PP | FU2: Cash Coll Inst PP | FV2: TOTAL Cash Coll PP | FW2: Cash Coll Indiv Prepaid | FX2: Cash Coll CWP Prepaid | FY2: Cash Coll Comm Prepaid | FZ2: Cash Coll Inst Prepaid | GA2: TOTAL Cash Coll Prepaid | GB2: TOTAL Cash Collected | GC2: Amt Billed Indiv PP | GD2: Amt Billed CWP PP | GE2: Amt Billed Inst PP | GF2: Amt Billed Comm PP | GG2: TOTAL Amt Billed PP | GH2: Amt Billed Indiv Prepaid | GI2: Amt Billed CWP Prepaid | GJ2: Amt Billed Inst Prepaid | GK2: Amt Billed Comm Prepaid | GL2: TOTAL Amt Billed Prepaid | GM2: TOTAL Amount Billed | GN2: Svc Charge Individual | GO2: Svc Charge CWP | GP2: Svc Charge Institutions | GQ2: Svc Charge Commercial | GR2: TOTAL Service Charge | GS2: Meter Rental Individual | GT2: Meter Rental CWP | GU2: Meter Rental Institutions | GV2: Meter Rental Commercial | GW2: TOTAL Meter Rental | GX2: TOTAL Sales MWK | GY2: Private Debtors MWK | GZ2: Public Debtors MWK | HA2: TOTAL Debtors MWK | HB2: OpCost per Sales | HC2: Cash Collection Rate | HD2: Collection per Total Sales | HE2: Cust Applied Connection | HF2: Days to Quotation | HG2: Cust Fully Paid | HH2: Paid-up Applicants | HI2: Days to Connect | HJ2: Connection Days | HK2: Connectivity Rate | HL2: Queries Received | HM2: Time to Resolve Queries | HN2: Response Time avg
A3: Liwonde | B3: Balaka | C3: FY2025/26 | D3: 2025 | E3: 4 | F3: April | G3: Q1 | H3: 53275 | I3: 24957 | J3: 958 | K3: 90 | L3: 11 | M3: =SUM(I3,J3,K3,L3) | N3: 9562.6 | O3: 43.4 | P3: 1612.1 | Q3: 353.8 | R3: =SUM(N3,O3,P3,Q3) | S3: =M3+R3 | T3: 15687.1 | U3: =IF(H3=0,"",T3/H3) | V3: 86 | W3: =IF(H3=0,"",V3/H3) | X3: 0 | Y3: =IF(H3=0,"",X3/H3) | Z3: 0 | AA3: =IF(H3=0,"",Z3/H3) | AB3: 0 | AC3: =IF(H3=0,"",AB3/H3) | AD3: 0 | AE3: =IF(H3=0,"",AD3/H3) | AF3: 0 | AG3: =IF(H3=0,"",AF3/H3) | AH3: 303174.94 | AI3: =IF(H3=0,"",AH3/H3) | AJ3: 28941.5 | AK3: =IF(H3=0,"",AJ3/H3) | AL3: 4857706.6 | AM3: =IF(H3=0,"",AL3/H3) | AN3: 3192 | AO3: 120 | AP3: 327600 | AQ3: 0 | AR3: 17284771 | AS3: 4389039.3 | AT3: 5018013.7 | AU3: =AH3+AL3+AP3+AQ3+AR3+AS3+AT3 | AV3: =IF(H3=0,"",AU3/H3) | AW3: =IF(S3=0,"",AU3/S3) | AX3: 14 | AY3: =IF(H3=0,"",AX3/(H3/1000/12)) | AZ3: 20 | BA3: 407 | BB3: 34 | BC3: 48 | BD3: 0 | BE3: =BC3+BD3 | BF3: =BA3+BB3-BE3 | BG3: 0 | BH3: 0 | BI3: 0 | BJ3: 0 | BK3: =BI3+BJ3 | BL3: =BG3+BH3-BK3 | BM3: 0 | BN3: 0 | BO3: 0 | BP3: 0 | BQ3: =BO3+BP3 | BR3: =BM3+BN3-BQ3 | BS3: 0 | BT3: 0 | BU3: 0 | BV3: 0 | BW3: =BU3+BV3 | BX3: =BS3+BT3-BW3 | BY3: =BA3+BG3+BM3+BS3 | BZ3: =BB3+BH3+BN3+BT3 | CA3: =BE3+BK3+BQ3+BW3 | CB3: =BF3+BL3+BR3+BX3 | CC3: 61 | CD3: 2565 | CE3: 49 | CF3: 95 | CG3: 20 | CH3: =CD3+CE3+CF3+CG3 | CI3: 3360 | CJ3: 12 | CK3: 1 | CL3: 11 | CM3: =CI3+CJ3+CK3+CL3 | CN3: 1543 | CO3: 74 | CP3: 70 | CQ3: 3 | CR3: =CN3+CO3+CP3+CQ3 | CS3: =CM3+CR3 | CT3: 7803 | CU3: 41026 | CV3: 34872 | CW3: =IF(CU3=0,"",CV3/CU3) | DB3: =CX3+CY3-CZ3-DA3 | DC3: 0 | DD3: 0 | DE3: 0 | DF3: 0 | DG3: =DC3+DD3-DE3-DF3 | DH3: 0 | DI3: 0 | DJ3: 0 | DK3: 0 | DL3: =DH3+DI3-DJ3-DK3 | DM3: 376 | DN3: 0 | DO3: 46 | DP3: 0 | DQ3: =DM3+DN3-DO3-DP3 | DR3: =CX3+DC3+DH3+DM3 | DS3: =CY3+DD3+DI3+DN3 | DT3: =CZ3+DE3+DJ3+DO3 | DU3: =DA3+DF3+DK3+DP3 | DV3: =DB3+DG3+DL3+DQ3 | DW3: 91 | DX3: 52 | DY3: 24 | DZ3: 0 | EA3: 2 | EB3: 7 | EC3: 0 | ED3: 1 | EE3: 3 | EF3: 0 | EG3: 0 | EH3: 0 | EI3: 0 | EJ3: 0 | EK3: 0 | EL3: 0 | EM3: 0 | EN3: 0 | EO3: 0 | EP3: 0 | EQ3: 0 | ER3: 0 | ES3: 0 | ET3: 0 | EU3: 0 | EV3: 0 | EW3: 0 | EX3: 0 | EY3: 0 | EZ3: 0 | FA3: 0 | FB3: 0 | FC3: 0 | FD3: 0 | FE3: 0 | FF3: 0 | FG3: =SUM(DW3,DX3,DY3,DZ3,EA3,EB3,EC3,ED3,EE3,EF3,EG3,EH3,EI3,EJ3,EK3,EL3,EM3,EN3,EO3,EP3,EQ3,ER3,ES3,ET3,EU3,EV3,EW3,EX3,EY3,EZ3,FA3,FB3,FC3,FD3,FE3,FF3) | FH3: 0 | FI3: 0 | FJ3: 72 | FK3: 504 | FL3: 0 | FM3: 0 | FN3: 0 | FO3: 0 | FP3: 0 | FQ3: =FL3+FM3+FN3+FO3+FP3 | FR3: 17408596 | FS3: 178300 | FT3: 16000 | FU3: 26000 | FV3: =FR3+FS3+FT3+FU3 | FW3: 12283138 | FX3: 9324.64 | FY3: 1687222.8 | FZ3: 4930154.2 | GA3: =FW3+FX3+FY3+FZ3 | GB3: =FV3+GA3 | GC3: 24219712 | GD3: 183246.24 | GE3: 280474.64 | GF3: 32821.45 | GG3: =GC3+GD3+GE3+GF3 | GH3: 11979413 | GI3: 9324.64 | GJ3: 4896554.2 | GK3: 1660222.8 | GL3: =GH3+GI3+GJ3+GK3 | GM3: =GG3+GL3 | GN3: 1792290.4 | GO3: 2104.08 | GP3: 40723.68 | GQ3: 4637.34 | GR3: =GN3+GO3+GP3+GQ3 | GS3: 3000480 | GT3: 9823 | GU3: 10716 | GV3: 893 | GW3: =GS3+GT3+GU3+GV3 | GX3: =GM3+GR3+GW3 | GY3: 3.1612353e+08 | GZ3: 4644828 | HA3: =GY3+GZ3 | HB3: =IF(GX3=0,"",AU3/GX3) | HC3: =IF((GX3+GY3)=0,"",GB3/(GX3+GY3)) | HD3: =IF(GX3=0,"",GB3/GX3) | HE3: 34 | HF3: 1 | HG3: 393 | HH3: 34 | HI3: 20 | HJ3: =HF3+HI3 | HK3: =IF(HE3=0,"",HH3/HE3) | HL3: 12 | HM3: 30 | HN3: =IF(HL3=0,"",HM3/HL3)
A4: Liwonde | B4: Balaka | C4: FY2025/26 | D4: 2025 | E4: 5 | F4: May | G4: Q1 | H4: 41589 | I4: 17592 | J4: 714 | K4: 80 | L4: 4 | M4: =SUM(I4,J4,K4,L4) | N4: 9832.7 | O4: 118.2 | P4: 720.8 | Q4: 595.6 | R4: =SUM(N4,O4,P4,Q4) | S4: =M4+R4 | T4: 11931.7 | U4: =IF(H4=0,"",T4/H4) | V4: 110 | W4: =IF(H4=0,"",V4/H4) | X4: 0 | Y4: =IF(H4=0,"",X4/H4) | Z4: 0 | AA4: =IF(H4=0,"",Z4/H4) | AB4: 0 | AC4: =IF(H4=0,"",AB4/H4) | AD4: 0 | AE4: =IF(H4=0,"",AD4/H4) | AF4: 0 | AG4: =IF(H4=0,"",AF4/H4) | AH4: 387781.9 | AI4: =IF(H4=0,"",AH4/H4) | AJ4: 32525.4 | AK4: =IF(H4=0,"",AJ4/H4) | AL4: 5456854.1 | AM4: =IF(H4=0,"",AL4/H4) | AN4: 4415 | AO4: 166 | AP4: 453844 | AQ4: 0 | AR4: 17895362 | AS4: 3972300.8 | AT4: 5293286.2 | AU4: =AH4+AL4+AP4+AQ4+AR4+AS4+AT4 | AV4: =IF(H4=0,"",AU4/H4) | AW4: =IF(S4=0,"",AU4/S4) | AX4: 14 | AY4: =IF(H4=0,"",AX4/(H4/1000/12)) | AZ4: 20 | BA4: 393 | BB4: 38 | BC4: 32 | BD4: 0 | BE4: =BC4+BD4 | BF4: =BA4+BB4-BE4 | BG4: 0 | BH4: 0 | BI4: 0 | BJ4: 0 | BK4: =BI4+BJ4 | BL4: =BG4+BH4-BK4 | BM4: 0 | BN4: 0 | BO4: 0 | BP4: 0 | BQ4: =BO4+BP4 | BR4: =BM4+BN4-BQ4 | BS4: 0 | BT4: 0 | BU4: 0 | BV4: 0 | BW4: =BU4+BV4 | BX4: =BS4+BT4-BW4 | BY4: =BA4+BG4+BM4+BS4 | BZ4: =BB4+BH4+BN4+BT4 | CA4: =BE4+BK4+BQ4+BW4 | CB4: =BF4+BL4+BR4+BX4 | CC4: 72 | CD4: 2601 | CE4: 49 | CF4: 99 | CG4: 20 | CH4: =CD4+CE4+CF4+CG4 | CI4: 3347 | CJ4: 13 | CK4: 1 | CL4: 11 | CM4: =CI4+CJ4+CK4+CL4 | CN4: 1554 | CO4: 73 | CP4: 70 | CQ4: 3 | CR4: =CN4+CO4+CP4+CQ4 | CS4: =CM4+CR4 | CT4: 7841 | CU4: 41118 | CV4: 34127 | CW4: =IF(CU4=0,"",CV4/CU4) | DB4: =CX4+CY4-CZ4-DA4 | DC4: 0 | DD4: 0 | DE4: 0 | DF4: 0 | DG4: =DC4+DD4-DE4-DF4 | DH4: 0 | DI4: 0 | DJ4: 0 | DK4: 0 | DL4: =DH4+DI4-DJ4-DK4 | DM4: 330 | DN4: 18 | DO4: 0 | DP4: 0 | DQ4: =DM4+DN4-DO4-DP4 | DR4: =CX4+DC4+DH4+DM4 | DS4: =CY4+DD4+DI4+DN4 | DT4: =CZ4+DE4+DJ4+DO4 | DU4: =DA4+DF4+DK4+DP4 | DV4: =DB4+DG4+DL4+DQ4 | DW4: 111 | DX4: 94 | DY4: 17 | DZ4: 0 | EA4: 6 | EB4: 7 | EC4: 0 | ED4: 0 | EE4: 0 | EF4: 0 | EG4: 0 | EH4: 0 | EI4: 0 | EJ4: 0 | EK4: 0 | EL4: 0 | EM4: 0 | EN4: 0 | EO4: 0 | EP4: 0 | EQ4: 0 | ER4: 0 | ES4: 0 | ET4: 0 | EU4: 0 | EV4: 0 | EW4: 0 | EX4: 0 | EY4: 0 | EZ4: 0 | FA4: 0 | FB4: 0 | FC4: 0 | FD4: 0 | FE4: 0 | FF4: 0 | FG4: =SUM(DW4,DX4,DY4,DZ4,EA4,EB4,EC4,ED4,EE4,EF4,EG4,EH4,EI4,EJ4,EK4,EL4,EM4,EN4,EO4,EP4,EQ4,ER4,ES4,ET4,EU4,EV4,EW4,EX4,EY4,EZ4,FA4,FB4,FC4,FD4,FE4,FF4) | FH4: 0 | FI4: 0 | FJ4: 520 | FK4: 7 | FL4: 0 | FM4: 0 | FN4: 0 | FO4: 0 | FP4: 0 | FQ4: =FL4+FM4+FN4+FO4+FP4 | FR4: 37173791 | FS4: 175400 | FT4: 0 | FU4: 52800 | FV4: =FR4+FS4+FT4+FU4 | FW4: 12632085 | FX4: 25100 | FY4: 2809910.1 | FZ4: 2466546.4 | GA4: =FW4+FX4+FY4+FZ4 | GB4: =FV4+GA4 | GC4: 18210958 | GD4: 136573.92 | GE4: 262007.18 | GF4: 8410.99 | GG4: =GC4+GD4+GE4+GF4 | GH4: 12288691 | GI4: 25100 | GJ4: 2185987.3 | GK4: 2797200.9 | GL4: =GH4+GI4+GJ4+GK4 | GM4: =GG4+GL4 | GN4: 1788460.7 | GO4: 2104.08 | GP4: 44117.32 | GQ4: 4637.34 | GR4: =GN4+GO4+GP4+GQ4 | GS4: 2988871 | GT4: 9823 | GU4: 11609 | GV4: 893 | GW4: =GS4+GT4+GU4+GV4 | GX4: =GM4+GR4+GW4 | GY4: 3.0197445e+08 | GZ4: 4837013.5 | HA4: =GY4+GZ4 | HB4: =IF(GX4=0,"",AU4/GX4) | HC4: =IF((GX4+GY4)=0,"",GB4/(GX4+GY4)) | HD4: =IF(GX4=0,"",GB4/GX4) | HE4: 38 | HF4: 1 | HG4: 399 | HH4: 38 | HI4: 20 | HJ4: =HF4+HI4 | HK4: =IF(HE4=0,"",HH4/HE4) | HL4: 15 | HM4: 30 | HN4: =IF(HL4=0,"",HM4/HL4)
A5: Liwonde | B5: Balaka | C5: FY2025/26 | D5: 2025 | E5: 6 | F5: June | G5: Q1 | H5: 45200 | I5: 17881 | J5: 633 | K5: 84 | L5: 0 | M5: =SUM(I5,J5,K5,L5) | N5: 11195.3 | O5: 125.7 | P5: 569.1 | Q5: 700.1 | R5: =SUM(N5,O5,P5,Q5) | S5: =M5+R5 | T5: 14011.8 | U5: =IF(H5=0,"",T5/H5) | V5: 128 | W5: =IF(H5=0,"",V5/H5) | X5: 0 | Y5: =IF(H5=0,"",X5/H5) | Z5: 0 | AA5: =IF(H5=0,"",Z5/H5) | AB5: 0 | AC5: =IF(H5=0,"",AB5/H5) | AD5: 0 | AE5: =IF(H5=0,"",AD5/H5) | AF5: 0 | AG5: =IF(H5=0,"",AF5/H5) | AH5: 451237.12 | AI5: =IF(H5=0,"",AH5/H5) | AJ5: 23254.6 | AK5: =IF(H5=0,"",AJ5/H5) | AL5: 3906984.9 | AM5: =IF(H5=0,"",AL5/H5) | AN5: 7525 | AO5: 282 | AP5: 769860 | AQ5: 0 | AR5: 17883497 | AS5: 4462572.3 | AT5: 10710322 | AU5: =AH5+AL5+AP5+AQ5+AR5+AS5+AT5 | AV5: =IF(H5=0,"",AU5/H5) | AW5: =IF(S5=0,"",AU5/S5) | AX5: 14 | AY5: =IF(H5=0,"",AX5/(H5/1000/12)) | AZ5: 20 | BA5: 399 | BB5: 43 | BC5: 33 | BD5: 0 | BE5: =BC5+BD5 | BF5: =BA5+BB5-BE5 | BG5: 0 | BH5: 0 | BI5: 0 | BJ5: 0 | BK5: =BI5+BJ5 | BL5: =BG5+BH5-BK5 | BM5: 0 | BN5: 0 | BO5: 0 | BP5: 0 | BQ5: =BO5+BP5 | BR5: =BM5+BN5-BQ5 | BS5: 0 | BT5: 0 | BU5: 0 | BV5: 0 | BW5: =BU5+BV5 | BX5: =BS5+BT5-BW5 | BY5: =BA5+BG5+BM5+BS5 | BZ5: =BB5+BH5+BN5+BT5 | CA5: =BE5+BK5+BQ5+BW5 | CB5: =BF5+BL5+BR5+BX5 | CC5: 65 | CD5: 2569 | CE5: 51 | CF5: 99 | CG5: 20 | CH5: =CD5+CE5+CF5+CG5 | CI5: 3054 | CJ5: 9 | CK5: 1 | CL5: 11 | CM5: =CI5+CJ5+CK5+CL5 | CN5: 1726 | CO5: 75 | CP5: 71 | CQ5: 3 | CR5: =CN5+CO5+CP5+CQ5 | CS5: =CM5+CR5 | CT5: 7689 | CU5: 41203 | CV5: 35022.55 | CW5: =IF(CU5=0,"",CV5/CU5) | DB5: =CX5+CY5-CZ5-DA5 | DC5: 0 | DD5: 0 | DE5: 0 | DF5: 0 | DG5: =DC5+DD5-DE5-DF5 | DH5: 0 | DI5: 0 | DJ5: 0 | DK5: 0 | DL5: =DH5+DI5-DJ5-DK5 | DM5: 348 | DN5: 0 | DO5: 0 | DP5: 73 | DQ5: =DM5+DN5-DO5-DP5 | DR5: =CX5+DC5+DH5+DM5 | DS5: =CY5+DD5+DI5+DN5 | DT5: =CZ5+DE5+DJ5+DO5 | DU5: =DA5+DF5+DK5+DP5 | DV5: =DB5+DG5+DL5+DQ5 | DW5: 89 | DX5: 82 | DY5: 12 | DZ5: 1 | EA5: 3 | EB5: 8 | EC5: 2 | ED5: 0 | EE5: 2 | EF5: 0 | EG5: 0 | EH5: 0 | EI5: 0 | EJ5: 0 | EK5: 0 | EL5: 0 | EM5: 0 | EN5: 0 | EO5: 0 | EP5: 0 | EQ5: 0 | ER5: 0 | ES5: 0 | ET5: 0 | EU5: 0 | EV5: 0 | EW5: 0 | EX5: 0 | EY5: 0 | EZ5: 0 | FA5: 0 | FB5: 0 | FC5: 0 | FD5: 0 | FE5: 0 | FF5: 0 | FG5: =SUM(DW5,DX5,DY5,DZ5,EA5,EB5,EC5,ED5,EE5,EF5,EG5,EH5,EI5,EJ5,EK5,EL5,EM5,EN5,EO5,EP5,EQ5,ER5,ES5,ET5,EU5,EV5,EW5,EX5,EY5,EZ5,FA5,FB5,FC5,FD5,FE5,FF5) | FH5: 0 | FI5: 0 | FJ5: 504 | FK5: 36 | FL5: 0 | FM5: 0 | FN5: 0 | FO5: 0 | FP5: 0 | FQ5: =FL5+FM5+FN5+FO5+FP5 | FR5: 56748775 | FS5: 315300 | FT5: 38600 | FU5: 301267.22 | FV5: =FR5+FS5+FT5+FU5 | FW5: 14435292 | FX5: 26845.88 | FY5: 3326633.1 | FZ5: 2412218.5 | GA5: =FW5+FX5+FY5+FZ5 | GB5: =FV5+GA5 | GC5: 17754700 | GD5: 121080.24 | GE5: 266087.19 | GF5: 8410.99 | GG5: =GC5+GD5+GE5+GF5 | GH5: 14014137 | GI5: 26845.88 | GJ5: 2119718.5 | GK5: 3274923.9 | GL5: =GH5+GI5+GJ5+GK5 | GM5: =GG5+GL5 | GN5: 1626263.3 | GO5: 2104.08 | GP5: 30542.76 | GQ5: 4637.34 | GR5: =GN5+GO5+GP5+GQ5 | GS5: 2727222 | GT5: 9823 | GU5: 8037 | GV5: 893 | GW5: =GS5+GT5+GU5+GV5 | GX5: =GM5+GR5+GW5 | GY5: 2.7122601e+08 | GZ5: 2343196 | HA5: =GY5+GZ5 | HB5: =IF(GX5=0,"",AU5/GX5) | HC5: =IF((GX5+GY5)=0,"",GB5/(GX5+GY5)) | HD5: =IF(GX5=0,"",GB5/GX5) | HE5: 43 | HF5: 1 | HG5: 409 | HH5: 43 | HI5: 20 | HJ5: =HF5+HI5 | HK5: =IF(HE5=0,"",HH5/HE5) | HL5: 12 | HM5: 30 | HN5: =IF(HL5=0,"",HM5/HL5)
A6: Liwonde | B6: Balaka | C6: FY2025/26 | D6: 2025 | E6: 7 | F6: July | G6: Q2 | H6: 62022 | I6: 25332 | J6: 1028 | K6: 101 | L6: 56 | M6: =SUM(I6,J6,K6,L6) | N6: 14278.3 | O6: 267.7 | P6: 1069 | Q6: 597.6 | R6: =SUM(N6,O6,P6,Q6) | S6: =M6+R6 | T6: 19292.4 | U6: =IF(H6=0,"",T6/H6) | V6: 200 | W6: =IF(H6=0,"",V6/H6) | X6: 0 | Y6: =IF(H6=0,"",X6/H6) | Z6: 0 | AA6: =IF(H6=0,"",Z6/H6) | AB6: 0 | AC6: =IF(H6=0,"",AB6/H6) | AD6: 0 | AE6: =IF(H6=0,"",AD6/H6) | AF6: 0 | AG6: =IF(H6=0,"",AF6/H6) | AH6: 705058 | AI6: =IF(H6=0,"",AH6/H6) | AJ6: 20456 | AK6: =IF(H6=0,"",AJ6/H6) | AL6: 3439121.9 | AM6: =IF(H6=0,"",AL6/H6) | AN6: 5432 | AO6: 198 | AP6: 540540 | AQ6: 0 | AR6: 17883497 | AS6: 4854203.2 | AT6: 5255000 | AU6: =AH6+AL6+AP6+AQ6+AR6+AS6+AT6 | AV6: =IF(H6=0,"",AU6/H6) | AW6: =IF(S6=0,"",AU6/S6) | AX6: 14 | AY6: =IF(H6=0,"",AX6/(H6/1000/12)) | AZ6: 20 | BA6: 409 | BB6: 59 | BC6: 61 | BD6: 0 | BE6: =BC6+BD6 | BF6: =BA6+BB6-BE6 | BG6: 0 | BH6: 0 | BI6: 0 | BJ6: 0 | BK6: =BI6+BJ6 | BL6: =BG6+BH6-BK6 | BM6: 0 | BN6: 0 | BO6: 0 | BP6: 0 | BQ6: =BO6+BP6 | BR6: =BM6+BN6-BQ6 | BS6: 0 | BT6: 0 | BU6: 0 | BV6: 0 | BW6: =BU6+BV6 | BX6: =BS6+BT6-BW6 | BY6: =BA6+BG6+BM6+BS6 | BZ6: =BB6+BH6+BN6+BT6 | CA6: =BE6+BK6+BQ6+BW6 | CB6: =BF6+BL6+BR6+BX6 | CC6: 121 | CD6: 2642 | CE6: 51 | CF6: 99 | CG6: 19 | CH6: =CD6+CE6+CF6+CG6 | CI6: 3156 | CJ6: 9 | CK6: 1 | CL6: 11 | CM6: =CI6+CJ6+CK6+CL6 | CN6: 1795 | CO6: 75 | CP6: 71 | CQ6: 4 | CR6: =CN6+CO6+CP6+CQ6 | CS6: =CM6+CR6 | CT6: 7933 | CU6: 41615.03 | CV6: 35373.23 | CW6: =IF(CU6=0,"",CV6/CU6) | DB6: =CX6+CY6-CZ6-DA6 | DC6: 0 | DD6: 0 | DE6: 0 | DF6: 0 | DG6: =DC6+DD6-DE6-DF6 | DH6: 0 | DI6: 0 | DJ6: 0 | DK6: 0 | DL6: =DH6+DI6-DJ6-DK6 | DM6: 275 | DN6: 0 | DO6: 0 | DP6: 32 | DQ6: =DM6+DN6-DO6-DP6 | DR6: =CX6+DC6+DH6+DM6 | DS6: =CY6+DD6+DI6+DN6 | DT6: =CZ6+DE6+DJ6+DO6 | DU6: =DA6+DF6+DK6+DP6 | DV6: =DB6+DG6+DL6+DQ6 | DW6: 104 | DX6: 75 | DY6: 10 | DZ6: 1 | EA6: 2 | EB6: 3 | EC6: 0 | ED6: 0 | EE6: 1 | EF6: 0 | EG6: 0 | EH6: 0 | EI6: 0 | EJ6: 0 | EK6: 0 | EL6: 0 | EM6: 0 | EN6: 0 | EO6: 0 | EP6: 0 | EQ6: 0 | ER6: 0 | ES6: 0 | ET6: 0 | EU6: 0 | EV6: 0 | EW6: 0 | EX6: 0 | EY6: 0 | EZ6: 0 | FA6: 0 | FB6: 0 | FC6: 0 | FD6: 0 | FE6: 0 | FF6: 0 | FG6: =SUM(DW6,DX6,DY6,DZ6,EA6,EB6,EC6,ED6,EE6,EF6,EG6,EH6,EI6,EJ6,EK6,EL6,EM6,EN6,EO6,EP6,EQ6,ER6,ES6,ET6,EU6,EV6,EW6,EX6,EY6,EZ6,FA6,FB6,FC6,FD6,FE6,FF6) | FH6: 0 | FI6: 0 | FJ6: 520 | FK6: 5 | FL6: 0 | FM6: 0 | FN6: 0 | FO6: 0 | FP6: 0 | FQ6: =FL6+FM6+FN6+FO6+FP6 | FR6: 23307260 | FS6: 263000 | FT6: 61000 | FU6: 89200 | FV6: =FR6+FS6+FT6+FU6 | FW6: 18306154 | FX6: 56900 | FY6: 2836450 | FZ6: 3510164.8 | GA6: =FW6+FX6+FY6+FZ6 | GB6: =FV6+GA6 | GC6: 23938310 | GD6: 196635.84 | GE6: 313271.24 | GF6: 254121.01 | GG6: =GC6+GD6+GE6+GF6 | GH6: 17872550 | GI6: 56900 | GJ6: 3229537.6 | GK6: 2752750 | GL6: =GH6+GI6+GJ6+GK6 | GM6: =GG6+GL6 | GN6: 1682555.7 | GO6: 2104.08 | GP6: 30542.76 | GQ6: 4637.34 | GR6: =GN6+GO6+GP6+GQ6 | GS6: 2818308 | GT6: 9823 | GU6: 8037 | GV6: 893 | GW6: =GS6+GT6+GU6+GV6 | GX6: =GM6+GR6+GW6 | GY6: 2.7712767e+08 | GZ6: 2663026.8 | HA6: =GY6+GZ6 | HB6: =IF(GX6=0,"",AU6/GX6) | HC6: =IF((GX6+GY6)=0,"",GB6/(GX6+GY6)) | HD6: =IF(GX6=0,"",GB6/GX6) | HE6: 59 | HF6: 1 | HG6: 407 | HH6: 59 | HI6: 20 | HJ6: =HF6+HI6 | HK6: =IF(HE6=0,"",HH6/HE6) | HL6: 14 | HM6: 30 | HN6: =IF(HL6=0,"",HM6/HL6)
A7: Liwonde | B7: Balaka | C7: FY2025/26 | D7: 2025 | E7: 8 | F7: August | G7: Q2 | H7: 50958 | I7: 19421 | J7: 772 | K7: 96 | L7: 11 | M7: =SUM(I7,J7,K7,L7) | N7: 13978.2 | O7: 356.5 | P7: 822.6 | Q7: 603.5 | R7: =SUM(N7,O7,P7,Q7) | S7: =M7+R7 | T7: 14897.2 | U7: =IF(H7=0,"",T7/H7) | V7: 128 | W7: =IF(H7=0,"",V7/H7) | X7: 0 | Y7: =IF(H7=0,"",X7/H7) | Z7: 0 | AA7: =IF(H7=0,"",Z7/H7) | AB7: 0 | AC7: =IF(H7=0,"",AB7/H7) | AD7: 0 | AE7: =IF(H7=0,"",AD7/H7) | AF7: 0 | AG7: =IF(H7=0,"",AF7/H7) | AH7: 451237.12 | AI7: =IF(H7=0,"",AH7/H7) | AJ7: 56715 | AK7: =IF(H7=0,"",AJ7/H7) | AL7: 9500810.9 | AM7: =IF(H7=0,"",AL7/H7) | AN7: 5843.5152 | AO7: 213 | AP7: 581490 | AQ7: 0 | AR7: 17703746 | AS7: 4932611.6 | AT7: 8078460 | AU7: =AH7+AL7+AP7+AQ7+AR7+AS7+AT7 | AV7: =IF(H7=0,"",AU7/H7) | AW7: =IF(S7=0,"",AU7/S7) | AX7: 14 | AY7: =IF(H7=0,"",AX7/(H7/1000/12)) | AZ7: 20 | BA7: 407 | BB7: 63 | BC7: 54 | BD7: 0 | BE7: =BC7+BD7 | BF7: =BA7+BB7-BE7 | BG7: 0 | BH7: 0 | BI7: 0 | BJ7: 0 | BK7: =BI7+BJ7 | BL7: =BG7+BH7-BK7 | BM7: 0 | BN7: 0 | BO7: 0 | BP7: 0 | BQ7: =BO7+BP7 | BR7: =BM7+BN7-BQ7 | BS7: 0 | BT7: 0 | BU7: 0 | BV7: 0 | BW7: =BU7+BV7 | BX7: =BS7+BT7-BW7 | BY7: =BA7+BG7+BM7+BS7 | BZ7: =BB7+BH7+BN7+BT7 | CA7: =BE7+BK7+BQ7+BW7 | CB7: =BF7+BL7+BR7+BX7 | CC7: 62 | CD7: 2554 | CE7: 50 | CF7: 98 | CG7: 18 | CH7: =CD7+CE7+CF7+CG7 | CI7: 2958 | CJ7: 9 | CK7: 2 | CL7: 11 | CM7: =CI7+CJ7+CK7+CL7 | CN7: 2135 | CO7: 76 | CP7: 71 | CQ7: 5 | CR7: =CN7+CO7+CP7+CQ7 | CS7: =CM7+CR7 | CT7: 7987 | CU7: 41615.03 | CV7: 35726.96 | CW7: =IF(CU7=0,"",CV7/CU7) | DB7: =CX7+CY7-CZ7-DA7 | DC7: 0 | DD7: 0 | DE7: 0 | DF7: 0 | DG7: =DC7+DD7-DE7-DF7 | DH7: 0 | DI7: 0 | DJ7: 0 | DK7: 0 | DL7: =DH7+DI7-DJ7-DK7 | DM7: 243 | DN7: 0 | DO7: 0 | DP7: 67 | DQ7: =DM7+DN7-DO7-DP7 | DR7: =CX7+DC7+DH7+DM7 | DS7: =CY7+DD7+DI7+DN7 | DT7: =CZ7+DE7+DJ7+DO7 | DU7: =DA7+DF7+DK7+DP7 | DV7: =DB7+DG7+DL7+DQ7 | DW7: 147 | DX7: 64 | DY7: 12 | DZ7: 0 | EA7: 0 | EB7: 9 | EC7: 0 | ED7: 0 | EE7: 1 | EF7: 0 | EG7: 0 | EH7: 0 | EI7: 0 | EJ7: 0 | EK7: 0 | EL7: 0 | EM7: 0 | EN7: 0 | EO7: 0 | EP7: 0 | EQ7: 0 | ER7: 0 | ES7: 0 | ET7: 0 | EU7: 0 | EV7: 0 | EW7: 0 | EX7: 0 | EY7: 0 | EZ7: 0 | FA7: 0 | FB7: 0 | FC7: 0 | FD7: 0 | FE7: 0 | FF7: 0 | FG7: =SUM(DW7,DX7,DY7,DZ7,EA7,EB7,EC7,ED7,EE7,EF7,EG7,EH7,EI7,EJ7,EK7,EL7,EM7,EN7,EO7,EP7,EQ7,ER7,ES7,ET7,EU7,EV7,EW7,EX7,EY7,EZ7,FA7,FB7,FC7,FD7,FE7,FF7) | FH7: 0 | FI7: 0 | FJ7: 504 | FK7: 3 | FL7: 0 | FM7: 0 | FN7: 0 | FO7: 0 | FP7: 0 | FQ7: =FL7+FM7+FN7+FO7+FP7 | FR7: 27549691 | FS7: 210800 | FT7: 67.22 | FU7: 104867.22 | FV7: =FR7+FS7+FT7+FU7 | FW7: 18757806 | FX7: 83000 | FY7: 2867900 | FZ7: 2799507 | GA7: =FW7+FX7+FY7+FZ7 | GB7: =FV7+GA7 | GC7: 18832106 | GD7: 147668.16 | GE7: 283790.6 | GF7: 30364.54 | GG7: =GC7+GD7+GE7+GF7 | GH7: 17520114 | GI7: 75740 | GJ7: 2486071.8 | GK7: 2760500 | GL7: =GH7+GI7+GJ7+GK7 | GM7: =GG7+GL7 | GN7: 1587694.1 | GO7: 2104.08 | GP7: 30542.76 | GQ7: 9274.68 | GR7: =GN7+GO7+GP7+GQ7 | GS7: 2637029 | GT7: 9823 | GU7: 8037 | GV7: 1786 | GW7: =GS7+GT7+GU7+GV7 | GX7: =GM7+GR7+GW7 | GY7: 2.703971e+08 | GZ7: 2952170.9 | HA7: =GY7+GZ7 | HB7: =IF(GX7=0,"",AU7/GX7) | HC7: =IF((GX7+GY7)=0,"",GB7/(GX7+GY7)) | HD7: =IF(GX7=0,"",GB7/GX7) | HE7: 63 | HF7: 1 | HG7: 416 | HH7: 63 | HI7: 20 | HJ7: =HF7+HI7 | HK7: =IF(HE7=0,"",HH7/HE7) | HL7: 15 | HM7: 30 | HN7: =IF(HL7=0,"",HM7/HL7)
A8: Liwonde | B8: Balaka | C8: FY2025/26 | D8: 2025 | E8: 9 | F8: September | G8: Q2 | H8: 65681 | I8: 25495 | J8: 1147 | K8: 115 | L8: 6 | M8: =SUM(I8,J8,K8,L8) | N8: 16674.6 | O8: 446.5 | P8: 1097.7 | Q8: 513.5 | R8: =SUM(N8,O8,P8,Q8) | S8: =M8+R8 | T8: 20185.7 | U8: =IF(H8=0,"",T8/H8) | V8: 130 | W8: =IF(H8=0,"",V8/H8) | X8: 0 | Y8: =IF(H8=0,"",X8/H8) | Z8: 0 | AA8: =IF(H8=0,"",Z8/H8) | AB8: 0 | AC8: =IF(H8=0,"",AB8/H8) | AD8: 0 | AE8: =IF(H8=0,"",AD8/H8) | AF8: 0 | AG8: =IF(H8=0,"",AF8/H8) | AH8: 458287.7 | AI8: =IF(H8=0,"",AH8/H8) | AJ8: 25713.7 | AK8: =IF(H8=0,"",AJ8/H8) | AL8: 4318091.1 | AM8: =IF(H8=0,"",AL8/H8) | AN8: 5426 | AO8: 375.00857 | AP8: 1312530 | AQ8: 0 | AR8: 16664236 | AS8: 6601328.2 | AT8: 1657762.1 | AU8: =AH8+AL8+AP8+AQ8+AR8+AS8+AT8 | AV8: =IF(H8=0,"",AU8/H8) | AW8: =IF(S8=0,"",AU8/S8) | AX8: 14 | AY8: =IF(H8=0,"",AX8/(H8/1000/12)) | AZ8: 39 | BA8: 416 | BB8: 48 | BC8: 42 | BD8: 0 | BE8: =BC8+BD8 | BF8: =BA8+BB8-BE8 | BG8: 0 | BH8: 0 | BI8: 0 | BJ8: 0 | BK8: =BI8+BJ8 | BL8: =BG8+BH8-BK8 | BM8: 0 | BN8: 0 | BO8: 0 | BP8: 0 | BQ8: =BO8+BP8 | BR8: =BM8+BN8-BQ8 | BS8: 0 | BT8: 0 | BU8: 0 | BV8: 0 | BW8: =BU8+BV8 | BX8: =BS8+BT8-BW8 | BY8: =BA8+BG8+BM8+BS8 | BZ8: =BB8+BH8+BN8+BT8 | CA8: =BE8+BK8+BQ8+BW8 | CB8: =BF8+BL8+BR8+BX8 | CC8: 45 | CD8: 2508 | CE8: 50 | CF8: 98 | CG8: 18 | CH8: =CD8+CE8+CF8+CG8 | CI8: 2946 | CJ8: 9 | CK8: 1 | CL8: 11 | CM8: =CI8+CJ8+CK8+CL8 | CN8: 2382 | CO8: 76 | CP8: 72 | CQ8: 5 | CR8: =CN8+CO8+CP8+CQ8 | CS8: =CM8+CR8 | CT8: 8176 | CU8: 41615.03 | CV8: 36441.54 | CW8: =IF(CU8=0,"",CV8/CU8) | DB8: =CX8+CY8-CZ8-DA8 | DC8: 0 | DD8: 0 | DE8: 0 | DF8: 0 | DG8: =DC8+DD8-DE8-DF8 | DH8: 0 | DI8: 0 | DJ8: 0 | DK8: 0 | DL8: =DH8+DI8-DJ8-DK8 | DM8: 176 | DN8: 12 | DO8: 0 | DP8: 0 | DQ8: =DM8+DN8-DO8-DP8 | DR8: =CX8+DC8+DH8+DM8 | DS8: =CY8+DD8+DI8+DN8 | DT8: =CZ8+DE8+DJ8+DO8 | DU8: =DA8+DF8+DK8+DP8 | DV8: =DB8+DG8+DL8+DQ8 | DW8: 111 | DX8: 68 | DY8: 9 | DZ8: 1 | EA8: 4 | EB8: 10 | EC8: 1 | ED8: 0 | EE8: 1 | EF8: 3 | EG8: 4 | EH8: 0 | EI8: 0 | EJ8: 0 | EK8: 0 | EL8: 0 | EM8: 0 | EN8: 0 | EO8: 0 | EP8: 0 | EQ8: 0 | ER8: 0 | ES8: 0 | ET8: 0 | EU8: 0 | EV8: 0 | EW8: 0 | EX8: 0 | EY8: 0 | EZ8: 0 | FA8: 0 | FB8: 0 | FC8: 0 | FD8: 0 | FE8: 0 | FF8: 0 | FG8: =SUM(DW8,DX8,DY8,DZ8,EA8,EB8,EC8,ED8,EE8,EF8,EG8,EH8,EI8,EJ8,EK8,EL8,EM8,EN8,EO8,EP8,EQ8,ER8,ES8,ET8,EU8,EV8,EW8,EX8,EY8,EZ8,FA8,FB8,FC8,FD8,FE8,FF8) | FH8: 0 | FI8: 0 | FJ8: 520 | FK8: 3 | FL8: 0 | FM8: 0 | FN8: 0 | FO8: 0 | FP8: 0 | FQ8: =FL8+FM8+FN8+FO8+FP8 | FR8: 21691980 | FS8: 176267.22 | FT8: 350067.22 | FU8: 67000 | FV8: =FR8+FS8+FT8+FU8 | FW8: 26130022 | FX8: 154524.64 | FY8: 2554072.8 | FZ8: 3803513.9 | GA8: =FW8+FX8+FY8+FZ8 | GB8: =FV8+GA8 | GC8: 24186379 | GD8: 219398.16 | GE8: 364727.96 | GF8: 15182.27 | GG8: =GC8+GD8+GE8+GF8 | GH8: 20822945 | GI8: 94988.87 | GJ8: 3314638.2 | GK8: 2436112.8 | GL8: =GH8+GI8+GJ8+GK8 | GM8: =GG8+GL8 | GN8: 1584702.3 | GO8: 2104.08 | GP8: 30542.76 | GQ8: 4637.34 | GR8: =GN8+GO8+GP8+GQ8 | GS8: 2630778 | GT8: 9823 | GU8: 8037 | GV8: 893 | GW8: =GS8+GT8+GU8+GV8 | GX8: =GM8+GR8+GW8 | GY8: 2.7634466e+08 | GZ8: 3372797.1 | HA8: =GY8+GZ8 | HB8: =IF(GX8=0,"",AU8/GX8) | HC8: =IF((GX8+GY8)=0,"",GB8/(GX8+GY8)) | HD8: =IF(GX8=0,"",GB8/GX8) | HE8: 48 | HF8: 1 | HG8: 422 | HH8: 48 | HI8: 20 | HJ8: =HF8+HI8 | HK8: =IF(HE8=0,"",HH8/HE8) | HL8: 40 | HM8: 30 | HN8: =IF(HL8=0,"",HM8/HL8)
A9: Liwonde | B9: Balaka | C9: FY2025/26 | D9: 2025 | E9: 10 | F9: October | G9: Q3 | H9: 46567 | I9: 17150 | J9: 809 | K9: 93 | L9: 2 | M9: =SUM(I9,J9,K9,L9) | N9: 12658 | O9: 386.9 | P9: 1415.9 | Q9: 453.7 | R9: =SUM(N9,O9,P9,Q9) | S9: =M9+R9 | T9: 13598.5 | U9: =IF(H9=0,"",T9/H9) | V9: 82 | W9: =IF(H9=0,"",V9/H9) | X9: 0 | Y9: =IF(H9=0,"",X9/H9) | Z9: 0 | AA9: =IF(H9=0,"",Z9/H9) | AB9: 0 | AC9: =IF(H9=0,"",AB9/H9) | AD9: 0 | AE9: =IF(H9=0,"",AD9/H9) | AF9: 0 | AG9: =IF(H9=0,"",AF9/H9) | AH9: 289073.78 | AI9: =IF(H9=0,"",AH9/H9) | AJ9: 14255 | AK9: =IF(H9=0,"",AJ9/H9) | AL9: 2402454.3 | AM9: =IF(H9=0,"",AL9/H9) | AN9: 4123.6657 | AO9: 285 | AP9: 778050 | AQ9: 0 | AR9: 0 | AS9: 6654152.5 | AT9: 1624766.8 | AU9: =AH9+AL9+AP9+AQ9+AR9+AS9+AT9 | AV9: =IF(H9=0,"",AU9/H9) | AW9: =IF(S9=0,"",AU9/S9) | AX9: 14 | AY9: =IF(H9=0,"",AX9/(H9/1000/12)) | AZ9: 42 | BA9: 422 | BB9: 41 | BC9: 46 | BD9: 0 | BE9: =BC9+BD9 | BF9: =BA9+BB9-BE9 | BG9: 0 | BH9: 0 | BI9: 0 | BJ9: 0 | BK9: =BI9+BJ9 | BL9: =BG9+BH9-BK9 | BM9: 0 | BN9: 0 | BO9: 0 | BP9: 0 | BQ9: =BO9+BP9 | BR9: =BM9+BN9-BQ9 | BS9: 0 | BT9: 0 | BU9: 0 | BV9: 0 | BW9: =BU9+BV9 | BX9: =BS9+BT9-BW9 | BY9: =BA9+BG9+BM9+BS9 | BZ9: =BB9+BH9+BN9+BT9 | CA9: =BE9+BK9+BQ9+BW9 | CB9: =BF9+BL9+BR9+BX9 | CC9: 35 | CD9: 2520 | CE9: 50 | CF9: 97 | CG9: 18 | CH9: =CD9+CE9+CF9+CG9 | CI9: 2980 | CJ9: 8 | CK9: 1 | CL9: 11 | CM9: =CI9+CJ9+CK9+CL9 | CN9: 2382 | CO9: 77 | CP9: 73 | CQ9: 5 | CR9: =CN9+CO9+CP9+CQ9 | CS9: =CM9+CR9 | CT9: 8222 | CU9: 41823.11 | CV9: 36623.75 | CW9: =IF(CU9=0,"",CV9/CU9) | DB9: =CX9+CY9-CZ9-DA9 | DC9: 0 | DD9: 0 | DE9: 0 | DF9: 0 | DG9: =DC9+DD9-DE9-DF9 | DH9: 0 | DI9: 0 | DJ9: 0 | DK9: 0 | DL9: =DH9+DI9-DJ9-DK9 | DM9: 188 | DN9: 5 | DO9: 0 | DP9: 0 | DQ9: =DM9+DN9-DO9-DP9 | DR9: =CX9+DC9+DH9+DM9 | DS9: =CY9+DD9+DI9+DN9 | DT9: =CZ9+DE9+DJ9+DO9 | DU9: =DA9+DF9+DK9+DP9 | DV9: =DB9+DG9+DL9+DQ9 | DW9: 84 | DX9: 42 | DY9: 8 | DZ9: 1 | EA9: 5 | EB9: 7 | EC9: 0 | ED9: 0 | EE9: 1 | EF9: 0 | EG9: 1 | EH9: 0 | EI9: 0 | EJ9: 0 | EK9: 0 | EL9: 0 | EM9: 0 | EN9: 0 | EO9: 0 | EP9: 0 | EQ9: 0 | ER9: 0 | ES9: 0 | ET9: 0 | EU9: 0 | EV9: 0 | EW9: 0 | EX9: 0 | EY9: 0 | EZ9: 0 | FA9: 0 | FB9: 0 | FC9: 0 | FD9: 0 | FE9: 0 | FF9: 0 | FG9: =SUM(DW9,DX9,DY9,DZ9,EA9,EB9,EC9,ED9,EE9,EF9,EG9,EH9,EI9,EJ9,EK9,EL9,EM9,EN9,EO9,EP9,EQ9,ER9,ES9,ET9,EU9,EV9,EW9,EX9,EY9,EZ9,FA9,FB9,FC9,FD9,FE9,FF9) | FH9: 0 | FI9: 0 | FJ9: 372 | FK9: 10 | FL9: 0 | FM9: 0 | FN9: 0 | FO9: 0 | FP9: 0 | FQ9: =FL9+FM9+FN9+FO9+FP9 | FR9: 17523448 | FS9: 148100 | FT9: 28900 | FU9: 0 | FV9: =FR9+FS9+FT9+FU9 | FW9: 19671907 | FX9: 103500 | FY9: 2239345.6 | FZ9: 4819624 | GA9: =FW9+FX9+FY9+FZ9 | GB9: =FV9+GA9 | GC9: 17807809 | GD9: 154745.52 | GE9: 277155.22 | GF9: 8410.99 | GG9: =GC9+GD9+GE9+GF9 | GH9: 15820117 | GI9: 82260 | GJ9: 4303436.5 | GK9: 2122875.8 | GL9: =GH9+GI9+GJ9+GK9 | GM9: =GG9+GL9 | GN9: 1606705.6 | GO9: 2104.08 | GP9: 27149.12 | GQ9: 4637.34 | GR9: =GN9+GO9+GP9+GQ9 | GS9: 2661140 | GT9: 9823 | GU9: 7144 | GV9: 893 | GW9: =GS9+GT9+GU9+GV9 | GX9: =GM9+GR9+GW9 | GY9: 2.4064225e+08 | GZ9: 3665086.1 | HA9: =GY9+GZ9 | HB9: =IF(GX9=0,"",AU9/GX9) | HC9: =IF((GX9+GY9)=0,"",GB9/(GX9+GY9)) | HD9: =IF(GX9=0,"",GB9/GX9) | HE9: 41 | HF9: 1 | HG9: 417 | HH9: 41 | HI9: 20 | HJ9: =HF9+HI9 | HK9: =IF(HE9=0,"",HH9/HE9) | HL9: 13 | HM9: 30 | HN9: =IF(HL9=0,"",HM9/HL9)
A10: Liwonde | B10: Balaka | C10: FY2025/26 | D10: 2025 | E10: 11 | F10: November | G10: Q3 | H10: 49897 | I10: 18041 | J10: 738 | K10: 70 | L10: 7 | M10: =SUM(I10,J10,K10,L10) | N10: 13870.4 | O10: 126 | P10: 1261.7 | Q10: 489.8 | R10: =SUM(N10,O10,P10,Q10) | S10: =M10+R10 | T10: 15293.1 | U10: =IF(H10=0,"",T10/H10) | V10: 108 | W10: =IF(H10=0,"",V10/H10) | X10: 0 | Y10: =IF(H10=0,"",X10/H10) | Z10: 0 | AA10: =IF(H10=0,"",Z10/H10) | AB10: 0 | AC10: =IF(H10=0,"",AB10/H10) | AD10: 0 | AE10: =IF(H10=0,"",AD10/H10) | AF10: 0 | AG10: =IF(H10=0,"",AF10/H10) | AH10: 380731.32 | AI10: =IF(H10=0,"",AH10/H10) | AJ10: 22349 | AK10: =IF(H10=0,"",AJ10/H10) | AL10: 3755588.9 | AM10: =IF(H10=0,"",AL10/H10) | AN10: 5234 | AO10: 220 | AP10: 770000 | AQ10: 0 | AR10: 17028073 | AS10: 6654152.5 | AT10: 7454346.6 | AU10: =AH10+AL10+AP10+AQ10+AR10+AS10+AT10 | AV10: =IF(H10=0,"",AU10/H10) | AW10: =IF(S10=0,"",AU10/S10) | AX10: 14 | AY10: =IF(H10=0,"",AX10/(H10/1000/12)) | AZ10: 47 | BA10: 417 | BB10: 27 | BC10: 32 | BD10: 0 | BE10: =BC10+BD10 | BF10: =BA10+BB10-BE10 | BG10: 0 | BH10: 0 | BI10: 0 | BJ10: 0 | BK10: =BI10+BJ10 | BL10: =BG10+BH10-BK10 | BM10: 0 | BN10: 0 | BO10: 0 | BP10: 0 | BQ10: =BO10+BP10 | BR10: =BM10+BN10-BQ10 | BS10: 0 | BT10: 0 | BU10: 0 | BV10: 0 | BW10: =BU10+BV10 | BX10: =BS10+BT10-BW10 | BY10: =BA10+BG10+BM10+BS10 | BZ10: =BB10+BH10+BN10+BT10 | CA10: =BE10+BK10+BQ10+BW10 | CB10: =BF10+BL10+BR10+BX10 | CC10: 42 | CD10: 2694 | CE10: 50 | CF10: 97 | CG10: 18 | CH10: =CD10+CE10+CF10+CG10 | CI10: 2962 | CJ10: 8 | CK10: 2 | CL10: 11 | CM10: =CI10+CJ10+CK10+CL10 | CN10: 2257 | CO10: 77 | CP10: 73 | CQ10: 5 | CR10: =CN10+CO10+CP10+CQ10 | CS10: =CM10+CR10 | CT10: 8254 | CU10: 42241.341 | CV10: 38017.207 | CW10: =IF(CU10=0,"",CV10/CU10) | DB10: =CX10+CY10-CZ10-DA10 | DC10: 0 | DD10: 0 | DE10: 0 | DF10: 0 | DG10: =DC10+DD10-DE10-DF10 | DH10: 0 | DI10: 0 | DJ10: 0 | DK10: 0 | DL10: =DH10+DI10-DJ10-DK10 | DM10: 193 | DN10: 0 | DO10: 0 | DP10: 1 | DQ10: =DM10+DN10-DO10-DP10 | DR10: =CX10+DC10+DH10+DM10 | DS10: =CY10+DD10+DI10+DN10 | DT10: =CZ10+DE10+DJ10+DO10 | DU10: =DA10+DF10+DK10+DP10 | DV10: =DB10+DG10+DL10+DQ10 | DW10: 128 | DX10: 50 | DY10: 13 | DZ10: 1 | EA10: 5 | EB10: 8 | EC10: 0 | ED10: 1 | EE10: 2 | EF10: 2 | EG10: 0 | EH10: 0 | EI10: 0 | EJ10: 0 | EK10: 0 | EL10: 0 | EM10: 0 | EN10: 0 | EO10: 0 | EP10: 0 | EQ10: 0 | ER10: 0 | ES10: 0 | ET10: 0 | EU10: 0 | EV10: 0 | EW10: 0 | EX10: 0 | EY10: 0 | EZ10: 0 | FA10: 0 | FB10: 0 | FC10: 0 | FD10: 0 | FE10: 0 | FF10: 0 | FG10: =SUM(DW10,DX10,DY10,DZ10,EA10,EB10,EC10,ED10,EE10,EF10,EG10,EH10,EI10,EJ10,EK10,EL10,EM10,EN10,EO10,EP10,EQ10,ER10,ES10,ET10,EU10,EV10,EW10,EX10,EY10,EZ10,FA10,FB10,FC10,FD10,FE10,FF10) | FH10: 0 | FI10: 0 | FJ10: 520 | FK10: 30 | FL10: 0 | FM10: 0 | FN10: 0 | FO10: 0 | FP10: 0 | FQ10: =FL10+FM10+FN10+FO10+FP10 | FR10: 19268980 | FS10: 91000 | FT10: 0 | FU10: 0 | FV10: =FR10+FS10+FT10+FU10 | FW10: 23183279 | FX10: 26700 | FY10: 2530375 | FZ10: 4358291.1 | GA10: =FW10+FX10+FY10+FZ10 | GB10: =FV10+GA10 | GC10: 17976586 | GD10: 141164.64 | GE10: 207889.96 | GF10: 20207.62 | GG10: =GC10+GD10+GE10+GF10 | GH10: 17342172 | GI10: 26700 | GJ10: 3796225.7 | GK10: 2257321.6 | GL10: =GH10+GI10+GJ10+GK10 | GM10: =GG10+GL10 | GN10: 1596633.7 | GO10: 2104.08 | GP10: 27149.12 | GQ10: 9274.68 | GR10: =GN10+GO10+GP10+GQ10 | GS10: 2645066 | GT10: 9823 | GU10: 7144 | GV10: 1786 | GW10: =GS10+GT10+GU10+GV10 | GX10: =GM10+GR10+GW10 | GY10: 1.7394829e+08 | GZ10: 3213544.6 | HA10: =GY10+GZ10 | HB10: =IF(GX10=0,"",AU10/GX10) | HC10: =IF((GX10+GY10)=0,"",GB10/(GX10+GY10)) | HD10: =IF(GX10=0,"",GB10/GX10) | HE10: 27 | HF10: 1 | HG10: 412 | HH10: 27 | HI10: 32 | HJ10: =HF10+HI10 | HK10: =IF(HE10=0,"",HH10/HE10) | HL10: 40 | HM10: 7 | HN10: =IF(HL10=0,"",HM10/HL10)
A11: Liwonde | B11: Balaka | C11: FY2025/26 | D11: 2025 | E11: 12 | F11: December | G11: Q3 | H11: 50365 | I11: 17458 | J11: 660 | K11: 80 | L11: 9 | M11: =SUM(I11,J11,K11,L11) | N11: 15062.8 | O11: 123.3 | P11: 830.9 | Q11: 451.3 | R11: =SUM(N11,O11,P11,Q11) | S11: =M11+R11 | T11: 15689.7 | U11: =IF(H11=0,"",T11/H11) | V11: 110 | W11: =IF(H11=0,"",V11/H11) | X11: 0 | Y11: =IF(H11=0,"",X11/H11) | Z11: 0 | AA11: =IF(H11=0,"",Z11/H11) | AB11: 0 | AC11: =IF(H11=0,"",AB11/H11) | AD11: 0 | AE11: =IF(H11=0,"",AD11/H11) | AF11: 0 | AG11: =IF(H11=0,"",AF11/H11) | AH11: 387781.9 | AI11: =IF(H11=0,"",AH11/H11) | AJ11: 21444 | AK11: =IF(H11=0,"",AJ11/H11) | AL11: 3604293.3 | AM11: =IF(H11=0,"",AL11/H11) | AN11: 5332 | AO11: 215 | AP11: 752500 | AQ11: 0 | AR11: 17248877 | AS11: 8030643 | AT11: 5002000 | AU11: =AH11+AL11+AP11+AQ11+AR11+AS11+AT11 | AV11: =IF(H11=0,"",AU11/H11) | AW11: =IF(S11=0,"",AU11/S11) | AX11: 15 | AY11: =IF(H11=0,"",AX11/(H11/1000/12)) | AZ11: 47 | BA11: 412 | BB11: 23 | BC11: 31 | BD11: 0 | BE11: =BC11+BD11 | BF11: =BA11+BB11-BE11 | BG11: 0 | BH11: 0 | BI11: 0 | BJ11: 0 | BK11: =BI11+BJ11 | BL11: =BG11+BH11-BK11 | BM11: 0 | BN11: 0 | BO11: 0 | BP11: 0 | BQ11: =BO11+BP11 | BR11: =BM11+BN11-BQ11 | BS11: 0 | BT11: 0 | BU11: 0 | BV11: 0 | BW11: =BU11+BV11 | BX11: =BS11+BT11-BW11 | BY11: =BA11+BG11+BM11+BS11 | BZ11: =BB11+BH11+BN11+BT11 | CA11: =BE11+BK11+BQ11+BW11 | CB11: =BF11+BL11+BR11+BX11 | CC11: 15 | CD11: 2683 | CE11: 49 | CF11: 96 | CG11: 18 | CH11: =CD11+CE11+CF11+CG11 | CI11: 2964 | CJ11: 8 | CK11: 2 | CL11: 11 | CM11: =CI11+CJ11+CK11+CL11 | CN11: 2306 | CO11: 78 | CP11: 73 | CQ11: 5 | CR11: =CN11+CO11+CP11+CQ11 | CS11: =CM11+CR11 | CT11: 8293 | CU11: 46253 | CV11: 38017 | CW11: =IF(CU11=0,"",CV11/CU11) | DB11: =CX11+CY11-CZ11-DA11 | DC11: 0 | DD11: 0 | DE11: 0 | DF11: 0 | DG11: =DC11+DD11-DE11-DF11 | DH11: 0 | DI11: 0 | DJ11: 0 | DK11: 0 | DL11: =DH11+DI11-DJ11-DK11 | DM11: 192 | DN11: 10 | DO11: 5 | DP11: 3 | DQ11: =DM11+DN11-DO11-DP11 | DR11: =CX11+DC11+DH11+DM11 | DS11: =CY11+DD11+DI11+DN11 | DT11: =CZ11+DE11+DJ11+DO11 | DU11: =DA11+DF11+DK11+DP11 | DV11: =DB11+DG11+DL11+DQ11 | DW11: 71 | DX11: 29 | DY11: 5 | DZ11: 0 | EA11: 3 | EB11: 4 | EC11: 0 | ED11: 0 | EE11: 4 | EF11: 4 | EG11: 0 | EH11: 0 | EI11: 0 | EJ11: 0 | EK11: 0 | EL11: 0 | EM11: 0 | EN11: 0 | EO11: 0 | EP11: 0 | EQ11: 0 | ER11: 0 | ES11: 0 | ET11: 0 | EU11: 0 | EV11: 0 | EW11: 0 | EX11: 0 | EY11: 0 | EZ11: 0 | FA11: 0 | FB11: 0 | FC11: 0 | FD11: 0 | FE11: 0 | FF11: 0 | FG11: =SUM(DW11,DX11,DY11,DZ11,EA11,EB11,EC11,ED11,EE11,EF11,EG11,EH11,EI11,EJ11,EK11,EL11,EM11,EN11,EO11,EP11,EQ11,ER11,ES11,ET11,EU11,EV11,EW11,EX11,EY11,EZ11,FA11,FB11,FC11,FD11,FE11,FF11) | FH11: 0 | FI11: 0 | FJ11: 644 | FK11: 88 | FL11: 0 | FM11: 0 | FN11: 18 | FO11: 0 | FP11: 180 | FQ11: =FL11+FM11+FN11+FO11+FP11 | FR11: 30042506 | FS11: 130400 | FT11: 65850 | FU11: 32000 | FV11: =FR11+FS11+FT11+FU11 | FW11: 23832534 | FX11: 26200 | FY11: 2181528.1 | FZ11: 2906763.8 | GA11: =FW11+FX11+FY11+FZ11 | GB11: =FV11+GA11 | GC11: 17732946 | GD11: 126244.8 | GE11: 228676.05 | GF11: 20207.62 | GG11: =GC11+GD11+GE11+GF11 | GH11: 18795695 | GI11: 26200 | GJ11: 2489367.9 | GK11: 2055485.7 | GL11: =GH11+GI11+GJ11+GK11 | GM11: =GG11+GL11 | GN11: 1598112.2 | GO11: 2104.08 | GP11: 27149.12 | GQ11: 9274.68 | GR11: =GN11+GO11+GP11+GQ11 | GS11: 2646852 | GT11: 9823 | GU11: 7144 | GV11: 1786 | GW11: =GS11+GT11+GU11+GV11 | GX11: =GM11+GR11+GW11 | GY11: 1.6783518e+08 | GZ11: 3443415.6 | HA11: =GY11+GZ11 | HB11: =IF(GX11=0,"",AU11/GX11) | HC11: =IF((GX11+GY11)=0,"",GB11/(GX11+GY11)) | HD11: =IF(GX11=0,"",GB11/GX11) | HE11: 23 | HF11: 1 | HG11: 404 | HH11: 23 | HI11: 20 | HJ11: =HF11+HI11 | HK11: =IF(HE11=0,"",HH11/HE11) | HL11: 45 | HM11: 7 | HN11: =IF(HL11=0,"",HM11/HL11)
A12: Liwonde | B12: Balaka | C12: FY2025/26 | D12: 2026 | E12: 1 | F12: January | G12: Q4 | H12: 47566 | I12: 15995 | J12: 666 | K12: 103 | L12: 10 | M12: 16774 | N12: 13862.7 | O12: 280.9 | P12: 962.7 | Q12: 564.9 | R12: 15671.2 | S12: 32445.2 | T12: 15120.8 | U12: 0.31789093 | V12: 42 | W12: 0.88298364 | X12: 0 | Y12: 0 | Z12: 0 | AA12: 0 | AB12: 0 | AC12: 0 | AD12: 0 | AE12: 0 | AF12: 0 | AG12: 0 | AH12: 148062.18 | AI12: 3.1127734 | AJ12: 22345 | AK12: 0.46976832 | AL12: 3754920.2 | AM12: 78.941266 | AN12: 6789 | AO12: 115 | AP12: 575000 | AQ12: 0 | AR12: 17248877 | AS12: 7732934.5 | AT12: 1654402.5 | AU12: 31114197 | AV12: 654.12683 | AW12: 958.97688 | AX12: 14 | AY12: 9.1241643 | AZ12: 50 | BA12: 404 | BB12: 27 | BC12: 23 | BD12: 0 | BE12: 23 | BF12: 408 | BG12: 0 | BH12: 0 | BI12: 0 | BJ12: 0 | BK12: 0 | BL12: 0 | BM12: 0 | BN12: 0 | BO12: 0 | BP12: 0 | BQ12: 0 | BR12: 0 | BS12: 0 | BT12: 0 | BU12: 0 | BV12: 0 | BW12: 0 | BX12: 0 | BY12: 404 | BZ12: 27 | CA12: 23 | CB12: 408 | CC12: 23 | CD12: 2740 | CE12: 51 | CF12: 95 | CG12: 18 | CH12: 2904 | CI12: 2903 | CJ12: 6 | CK12: 3 | CL12: 10 | CM12: 2922 | CN12: 2333 | CO12: 78 | CP12: 74 | CQ12: 5 | CR12: 2490 | CS12: 5412 | CT12: 8316 | CU12: 46484 | CV12: 38207 | CW12: 0.82193873 | CX12: 0 | CY12: 0 | CZ12: 0 | DA12: 0 | DB12: 0 | DC12: 0 | DD12: 0 | DE12: 0 | DF12: 0 | DG12: 0 | DH12: 0 | DI12: 0 | DJ12: 0 | DK12: 0 | DL12: 0 | DM12: 194 | DN12: 25 | DO12: 5 | DP12: 3 | DQ12: 211 | DR12: 194 | DS12: 25 | DT12: 5 | DU12: 3 | DV12: 211 | DW12: 115 | DX12: 67 | DY12: 23 | DZ12: 6 | EA12: 14 | EB12: 0 | EC12: 0 | ED12: 0 | EE12: 0 | EF12: 0 | EG12: 0 | EH12: 0 | EI12: 0 | EJ12: 0 | EK12: 0 | EL12: 0 | EM12: 0 | EN12: 0 | EO12: 0 | EP12: 0 | EQ12: 0 | ER12: 0 | ES12: 0 | ET12: 0 | EU12: 0 | EV12: 0 | EW12: 0 | EX12: 0 | EY12: 0 | EZ12: 0 | FA12: 0 | FB12: 0 | FC12: 0 | FD12: 0 | FE12: 0 | FF12: 0 | FG12: 225 | FH12: 0 | FI12: 0 | FJ12: 468 | FK12: 54 | FL12: 0 | FM12: 372 | FN12: 0 | FO12: 66 | FP12: 0 | FQ12: 438 | FR12: 24140239 | FS12: 184000 | FT12: 14000 | FU12: 77000 | FV12: 24415239 | FW12: 20269195 | FX12: 81700 | FY12: 2720500 | FZ12: 3334136.3 | GA12: 26405531 | GB12: 50820770 | GC12: 16119351 | GD12: 127392.48 | GE12: 324859.8 | GF12: 32004.25 | GG12: 16603608 | GH12: 17307497 | GI12: 59680 | GJ12: 2925000.3 | GK12: 2671960 | GL12: 22964138 | GM12: 39567745 | GN12: 1566227.6 | GO12: 1912.8 | GP12: 20361.84 | GQ12: 13912.02 | GR12: 1602414.3 | GS12: 2592379 | GT12: 8930 | GU12: 5358 | GV12: 2679 | GW12: 2609346 | GX12: 43779505 | GY12: 1.2175665e+08 | GZ12: 1757068.6 | HA12: 1.2351372e+08 | HB12: 43779505 | HC12: 1.2175665e+08 | HD12: 1757068.6 | HE12: 27 | HF12: 1 | HG12: 408 | HH12: 27 | HI12: 20 | HJ12: 0.74074074 | HK12: 5.6372549 | HL12: 20 | HM12: 15 | HN12: 1.3333333
A13: Liwonde | B13: Balaka | C13: FY2025/26 | D13: 2026 | E13: 2 | F13: February | G13: Q4 | H13: 48213 | I13: 19774 | J13: 366 | K13: 56 | L13: 10 | M13: =SUM(I13,J13,K13,L13) | N13: 11339.5 | O13: 128.9 | P13: 639.2 | Q13: 1003.5 | R13: =SUM(N13,O13,P13,Q13) | S13: =M13+R13 | T13: 14895.9 | U13: =IF(H13=0,"",T13/H13) | V13: 112 | W13: =IF(H13=0,"",V13/H13) | X13: 0 | Y13: =IF(H13=0,"",X13/H13) | Z13: 0 | AA13: =IF(H13=0,"",Z13/H13) | AB13: 0 | AC13: =IF(H13=0,"",AB13/H13) | AD13: 0 | AE13: =IF(H13=0,"",AD13/H13) | AF13: 0 | AG13: =IF(H13=0,"",AF13/H13) | AH13: 394832.48 | AI13: =IF(H13=0,"",AH13/H13) | AJ13: 12203 | AK13: =IF(H13=0,"",AJ13/H13) | AL13: 2059406 | AM13: =IF(H13=0,"",AL13/H13) | AN13: 6342 | AO13: 112 | AP13: 560000 | AQ13: 0 | AR13: 18768051 | AS13: 0 | AT13: 5351000 | AU13: =AH13+AL13+AP13+AQ13+AR13+AS13+AT13 | AV13: =IF(H13=0,"",AU13/H13) | AW13: =IF(S13=0,"",AU13/S13) | AX13: 14 | AY13: =IF(H13=0,"",AX13/(H13/1000/12)) | AZ13: 50 | BA13: 408 | BB13: 35 | BC13: 30 | BD13: 0 | BE13: =BC13+BD13 | BF13: =BA13+BB13-BE13 | BG13: 0 | BH13: 0 | BI13: 0 | BJ13: 0 | BK13: =BI13+BJ13 | BL13: =BG13+BH13-BK13 | BM13: 0 | BN13: 0 | BO13: 0 | BP13: 0 | BQ13: =BO13+BP13 | BR13: =BM13+BN13-BQ13 | BS13: 0 | BT13: 0 | BU13: 0 | BV13: 0 | BW13: =BU13+BV13 | BX13: =BS13+BT13-BW13 | BY13: =BA13+BG13+BM13+BS13 | BZ13: =BB13+BH13+BN13+BT13 | CA13: =BE13+BK13+BQ13+BW13 | CB13: =BF13+BL13+BR13+BX13 | CC13: 33 | CD13: 2696 | CE13: 51 | CF13: 95 | CG13: 18 | CH13: =CD13+CE13+CF13+CG13 | CI13: 2948 | CJ13: 6 | CK13: 3 | CL13: 10 | CM13: =CI13+CJ13+CK13+CL13 | CN13: 2362 | CO13: 78 | CP13: 74 | CQ13: 5 | CR13: =CN13+CO13+CP13+CQ13 | CS13: =CM13+CR13 | CT13: 8346 | CU13: 46948 | CV13: 38589 | CW13: =IF(CU13=0,"",CV13/CU13) | DB13: =CX13+CY13-CZ13-DA13 | DC13: 0 | DD13: 0 | DE13: 0 | DF13: 0 | DG13: =DC13+DD13-DE13-DF13 | DH13: 0 | DI13: 0 | DJ13: 0 | DK13: 0 | DL13: =DH13+DI13-DJ13-DK13 | DM13: 211 | DN13: 60 | DO13: 0 | DP13: 0 | DQ13: =DM13+DN13-DO13-DP13 | DR13: =CX13+DC13+DH13+DM13 | DS13: =CY13+DD13+DI13+DN13 | DT13: =CZ13+DE13+DJ13+DO13 | DU13: =DA13+DF13+DK13+DP13 | DV13: =DB13+DG13+DL13+DQ13 | DW13: 76 | DX13: 50 | DY13: 24 | DZ13: 2 | EA13: 3 | EB13: 4 | EC13: 0 | ED13: 0 | EE13: 2 | EF13: 0 | EG13: 2 | EH13: 0 | EI13: 0 | EJ13: 0 | EK13: 0 | EL13: 0 | EM13: 0 | EN13: 0 | EO13: 0 | EP13: 0 | EQ13: 0 | ER13: 0 | ES13: 0 | ET13: 0 | EU13: 0 | EV13: 0 | EW13: 0 | EX13: 0 | EY13: 0 | EZ13: 0 | FA13: 0 | FB13: 0 | FC13: 0 | FD13: 0 | FE13: 0 | FF13: 0 | FG13: =SUM(DW13,DX13,DY13,DZ13,EA13,EB13,EC13,ED13,EE13,EF13,EG13,EH13,EI13,EJ13,EK13,EL13,EM13,EN13,EO13,EP13,EQ13,ER13,ES13,ET13,EU13,EV13,EW13,EX13,EY13,EZ13,FA13,FB13,FC13,FD13,FE13,FF13) | FH13: 0 | FI13: 0 | FJ13: 540 | FK13: 62 | FL13: 0 | FM13: 356 | FN13: 0 | FO13: 24 | FP13: 0 | FQ13: =FL13+FM13+FN13+FO13+FP13 | FR13: 15822773 | FS13: 104000 | FT13: 34700 | FU13: 364867.22 | FV13: =FR13+FS13+FT13+FU13 | FW13: 15836709 | FX13: 42260 | FY13: 4763717.5 | FZ13: 1951714.6 | GA13: =FW13+FX13+FY13+FZ13 | GB13: =FV13+GA13 | GC13: 20211628 | GD13: 70008.48 | GE13: 137731.6 | GF13: 25232.97 | GG13: =GC13+GD13+GE13+GF13 | GH13: 14156304 | GI13: 27380 | GJ13: 1942714.6 | GK13: 4743083.4 | GL13: =GH13+GI13+GJ13+GK13 | GM13: =GG13+GL13 | GN13: 1586020.5 | GO13: 1912.8 | GP13: 20361.84 | GQ13: 13912.02 | GR13: =GN13+GO13+GP13+GQ13 | GS13: 2632564 | GT13: 8930 | GU13: 5358 | GV13: 2679 | GW13: =GS13+GT13+GU13+GV13 | GX13: =GM13+GR13+GW13 | GY13: 1.31301e+08 | GZ13: 1920766.6 | HA13: =GY13+GZ13 | HB13: =IF(GX13=0,"",AU13/GX13) | HC13: =IF((GX13+GY13)=0,"",GB13/(GX13+GY13)) | HD13: =IF(GX13=0,"",GB13/GX13) | HE13: 33 | HF13: 1 | HG13: 413 | HH13: 35 | HI13: 20 | HJ13: =HF13+HI13 | HK13: =IF(HE13=0,"",HH13/HE13) | HL13: 16 | HM13: 15 | HN13: =IF(HL13=0,"",HM13/HL13)
A14: Liwonde | B14: Balaka | C14: FY2025/26 | D14: 2026 | E14: 3 | F14: March | G14: Q4 | H14: 48339 | I14: 17560 | J14: 489 | K14: 66 | L14: 4 | M14: =SUM(I14,J14,K14,L14) | N14: 14183.8 | O14: 214 | P14: 943.3 | Q14: 318 | R14: =SUM(N14,O14,P14,Q14) | S14: =M14+R14 | T14: 14560.9 | U14: =IF(H14=0,"",T14/H14) | V14: 46 | W14: =IF(H14=0,"",V14/H14) | X14: 0 | Y14: =IF(H14=0,"",X14/H14) | Z14: 0 | AA14: =IF(H14=0,"",Z14/H14) | AB14: 0 | AC14: =IF(H14=0,"",AB14/H14) | AD14: 0 | AE14: =IF(H14=0,"",AD14/H14) | AF14: 0 | AG14: =IF(H14=0,"",AF14/H14) | AH14: 162163.34 | AI14: =IF(H14=0,"",AH14/H14) | AJ14: 27325 | AK14: =IF(H14=0,"",AJ14/H14) | AL14: 19339 | AM14: =IF(H14=0,"",AL14/H14) | AN14: 6542 | AO14: 200 | AP14: 1000000 | AQ14: 0 | AR14: 17872104 | AS14: 6951595.8 | AT14: 175400 | AU14: =AH14+AL14+AP14+AQ14+AR14+AS14+AT14 | AV14: =IF(H14=0,"",AU14/H14) | AW14: =IF(S14=0,"",AU14/S14) | AX14: 14 | AY14: =IF(H14=0,"",AX14/(H14/1000/12)) | AZ14: 50 | BA14: 413 | BB14: 30 | BC14: 24 | BD14: 0 | BE14: =BC14+BD14 | BF14: =BA14+BB14-BE14 | BG14: 0 | BH14: 0 | BI14: 0 | BJ14: 0 | BK14: =BI14+BJ14 | BL14: =BG14+BH14-BK14 | BM14: 0 | BN14: 0 | BO14: 0 | BP14: 0 | BQ14: =BO14+BP14 | BR14: =BM14+BN14-BQ14 | BS14: 0 | BT14: 0 | BU14: 0 | BV14: 0 | BW14: =BU14+BV14 | BX14: =BS14+BT14-BW14 | BY14: =BA14+BG14+BM14+BS14 | BZ14: =BB14+BH14+BN14+BT14 | CA14: =BE14+BK14+BQ14+BW14 | CB14: =BF14+BL14+BR14+BX14 | CC14: 15 | CD14: 2544 | CE14: 62 | CF14: 94 | CG14: 19 | CH14: =CD14+CE14+CF14+CG14 | CI14: 3166 | CJ14: 6 | CK14: 2 | CL14: 10 | CM14: =CI14+CJ14+CK14+CL14 | CN14: 2390 | CO14: 67 | CP14: 75 | CQ14: 5 | CR14: =CN14+CO14+CP14+CQ14 | CS14: =CM14+CR14 | CT14: 8440 | CU14: 47417 | CV14: 38974 | CW14: =IF(CU14=0,"",CV14/CU14) | DB14: =CX14+CY14-CZ14-DA14 | DC14: 0 | DD14: 0 | DE14: 0 | DF14: 0 | DG14: =DC14+DD14-DE14-DF14 | DH14: 0 | DI14: 0 | DJ14: 0 | DK14: 0 | DL14: =DH14+DI14-DJ14-DK14 | DM14: 271 | DN14: 36 | DO14: 0 | DP14: 0 | DQ14: =DM14+DN14-DO14-DP14 | DR14: =CX14+DC14+DH14+DM14 | DS14: =CY14+DD14+DI14+DN14 | DT14: =CZ14+DE14+DJ14+DO14 | DU14: =DA14+DF14+DK14+DP14 | DV14: =DB14+DG14+DL14+DQ14 | DW14: 61 | DX14: 31 | DY14: 12 | DZ14: 2 | EA14: 0 | EB14: 7 | EC14: 0 | ED14: 0 | EE14: 0 | EF14: 0 | EG14: 0 | EH14: 0 | EI14: 0 | EJ14: 0 | EK14: 0 | EL14: 0 | EM14: 0 | EN14: 0 | EO14: 0 | EP14: 0 | EQ14: 0 | ER14: 0 | ES14: 0 | ET14: 0 | EU14: 0 | EV14: 0 | EW14: 0 | EX14: 0 | EY14: 0 | EZ14: 0 | FA14: 0 | FB14: 0 | FC14: 0 | FD14: 0 | FE14: 0 | FF14: 0 | FG14: =SUM(DW14,DX14,DY14,DZ14,EA14,EB14,EC14,ED14,EE14,EF14,EG14,EH14,EI14,EJ14,EK14,EL14,EM14,EN14,EO14,EP14,EQ14,ER14,ES14,ET14,EU14,EV14,EW14,EX14,EY14,EZ14,FA14,FB14,FC14,FD14,FE14,FF14) | FH14: 0 | FI14: 0 | FJ14: 480 | FK14: 52 | FL14: 390 | FM14: 0 | FN14: 0 | FO14: 0 | FP14: 150 | FQ14: =FL14+FM14+FN14+FO14+FP14 | FR14: 25246524 | FS14: 63100 | FT14: 60000 | FU14: 247867.22 | FV14: =FR14+FS14+FT14+FU14 | FW14: 19444708 | FX14: 62580 | FY14: 1542422.8 | FZ14: 2898400 | GA14: =FW14+FX14+FY14+FZ14 | GB14: =FV14+GA14 | GC14: 17559720 | GD14: 93535.92 | GE14: 175575.51 | GF14: 16821.98 | GG14: =GC14+GD14+GE14+GF14 | GH14: 17700982 | GI14: 45486 | GJ14: 2867320 | GK14: 1503002.8 | GL14: =GH14+GI14+GJ14+GK14 | GM14: =GG14+GL14 | GN14: 1554802.8 | GO14: 1912.8 | GP14: 20361.84 | GQ14: 9274.68 | GR14: =GN14+GO14+GP14+GQ14 | GS14: 2578984 | GT14: 8930 | GU14: 5358 | GV14: 1786 | GW14: =GS14+GT14+GU14+GV14 | GX14: =GM14+GR14+GW14 | GY14: 1.2641896e+08 | GZ14: 1202893.8 | HA14: =GY14+GZ14 | HB14: =IF(GX14=0,"",AU14/GX14) | HC14: =IF((GX14+GY14)=0,"",GB14/(GX14+GY14)) | HD14: =IF(GX14=0,"",GB14/GX14) | HE14: 30 | HF14: 1 | HG14: 419 | HH14: 30 | HI14: 20 | HJ14: =HF14+HI14 | HK14: =IF(HE14=0,"",HH14/HE14) | HL14: 20 | HM14: 15 | HN14: =IF(HL14=0,"",HM14/HL14)
A15: Liwonde | B15: Liwonde | C15: FY2025/26 | D15: 2025 | E15: 4 | F15: April | G15: Q1 | H15: 64376 | I15: 30208 | J15: 970 | K15: 936 | L15: 353 | M15: =SUM(I15,J15,K15,L15) | N15: 11071.6 | O15: 0 | P15: 977.6 | Q15: 1886.7 | R15: =SUM(N15,O15,P15,Q15) | S15: =M15+R15 | T15: 17973.1 | U15: =IF(H15=0,"",T15/H15) | V15: 276 | W15: =IF(H15=0,"",V15/H15) | X15: 658 | Y15: =IF(H15=0,"",X15/H15) | Z15: 0 | AA15: =IF(H15=0,"",Z15/H15) | AB15: 0 | AC15: =IF(H15=0,"",AB15/H15) | AD15: 0 | AE15: =IF(H15=0,"",AD15/H15) | AF15: 0 | AG15: =IF(H15=0,"",AF15/H15) | AH15: 1670466.8 | AI15: =IF(H15=0,"",AH15/H15) | AJ15: 56715 | AK15: =IF(H15=0,"",AJ15/H15) | AL15: 9500810.9 | AM15: =IF(H15=0,"",AL15/H15) | AN15: 2712 | AO15: 300 | AP15: 441000 | AQ15: 0 | AR15: 15500413 | AS15: 3913343.4 | AT15: 7391853.6 | AU15: =AH15+AL15+AP15+AQ15+AR15+AS15+AT15 | AV15: =IF(H15=0,"",AU15/H15) | AW15: =IF(S15=0,"",AU15/S15) | AX15: 24 | AY15: =IF(H15=0,"",AX15/(H15/1000/12)) | AZ15: 26 | BA15: 678 | BB15: 42 | BC15: 0 | BD15: 36 | BE15: =BC15+BD15 | BF15: =BA15+BB15-BE15 | BG15: 0 | BH15: 0 | BI15: 0 | BJ15: 0 | BK15: =BI15+BJ15 | BL15: =BG15+BH15-BK15 | BM15: 0 | BN15: 0 | BO15: 0 | BP15: 0 | BQ15: =BO15+BP15 | BR15: =BM15+BN15-BQ15 | BS15: 0 | BT15: 0 | BU15: 0 | BV15: 0 | BW15: =BU15+BV15 | BX15: =BS15+BT15-BW15 | BY15: =BA15+BG15+BM15+BS15 | BZ15: =BB15+BH15+BN15+BT15 | CA15: =BE15+BK15+BQ15+BW15 | CB15: =BF15+BL15+BR15+BX15 | CC15: 36 | CD15: 1458 | CE15: 33 | CF15: 20 | CG15: 15 | CH15: =CD15+CE15+CF15+CG15 | CI15: 2896 | CJ15: 14 | CK15: 9 | CL15: 13 | CM15: =CI15+CJ15+CK15+CL15 | CN15: 1128 | CO15: 105 | CP15: 186 | CQ15: 0 | CR15: =CN15+CO15+CP15+CQ15 | CS15: =CM15+CR15 | CT15: 5877 | CU15: 33916 | CV15: 30524.4 | CW15: =IF(CU15=0,"",CV15/CU15) | DB15: =CX15+CY15-CZ15-DA15 | DC15: 0 | DD15: 0 | DE15: 0 | DF15: 0 | DG15: =DC15+DD15-DE15-DF15 | DH15: 0 | DI15: 0 | DJ15: 0 | DK15: 0 | DL15: =DH15+DI15-DJ15-DK15 | DM15: 293 | DN15: 0 | DO15: 0 | DP15: 39 | DQ15: =DM15+DN15-DO15-DP15 | DR15: =CX15+DC15+DH15+DM15 | DS15: =CY15+DD15+DI15+DN15 | DT15: =CZ15+DE15+DJ15+DO15 | DU15: =DA15+DF15+DK15+DP15 | DV15: =DB15+DG15+DL15+DQ15 | DW15: 94 | DX15: 28 | DY15: 14 | DZ15: 4 | EA15: 2 | EB15: 8 | EC15: 0 | ED15: 4 | EE15: 18 | EF15: 9 | EG15: 0 | EH15: 0 | EI15: 0 | EJ15: 0 | EK15: 0 | EL15: 0 | EM15: 0 | EN15: 0 | EO15: 0 | EP15: 0 | EQ15: 0 | ER15: 0 | ES15: 0 | ET15: 0 | EU15: 0 | EV15: 0 | EW15: 0 | EX15: 0 | EY15: 0 | EZ15: 0 | FA15: 0 | FB15: 0 | FC15: 0 | FD15: 0 | FE15: 0 | FF15: 0 | FG15: =SUM(DW15,DX15,DY15,DZ15,EA15,EB15,EC15,ED15,EE15,EF15,EG15,EH15,EI15,EJ15,EK15,EL15,EM15,EN15,EO15,EP15,EQ15,ER15,ES15,ET15,EU15,EV15,EW15,EX15,EY15,EZ15,FA15,FB15,FC15,FD15,FE15,FF15) | FH15: 1 | FI15: 56 | FJ15: 720 | FK15: 0 | FL15: 0 | FM15: 0 | FN15: 0 | FO15: 0 | FP15: 0 | FQ15: =FL15+FM15+FN15+FO15+FP15 | FR15: 22564673 | FS15: 32500 | FT15: 4754131.3 | FU15: 5141655.8 | FV15: =FR15+FS15+FT15+FU15 | FW15: 13947465 | FX15: 0 | FY15: 9263418.1 | FZ15: 3163124.8 | GA15: =FW15+FX15+FY15+FZ15 | GB15: =FV15+GA15 | GC15: 27814109 | GD15: 185541.6 | GE15: 3178071.6 | GF15: 1654100.6 | GG15: =GC15+GD15+GE15+GF15 | GH15: 13814125 | GI15: 0 | GJ15: 2971124.8 | GK15: 8921850.4 | GL15: =GH15+GI15+GJ15+GK15 | GM15: =GG15+GL15 | GN15: 1551321.1 | GO15: 2486.64 | GP15: 47510.96 | GQ15: 41736.06 | GR15: =GN15+GO15+GP15+GQ15 | GS15: 2586128 | GT15: 11609 | GU15: 12502 | GV15: 8037 | GW15: =GS15+GT15+GU15+GV15 | GX15: =GM15+GR15+GW15 | GY15: 2.2634255e+08 | GZ15: 8416922.3 | HA15: =GY15+GZ15 | HB15: =IF(GX15=0,"",AU15/GX15) | HC15: =IF((GX15+GY15)=0,"",GB15/(GX15+GY15)) | HD15: =IF(GX15=0,"",GB15/GX15) | HE15: 42 | HF15: 20 | HG15: 684 | HH15: 42 | HI15: 20 | HJ15: =HF15+HI15 | HK15: =IF(HE15=0,"",HH15/HE15) | HL15: 12 | HM15: 30 | HN15: =IF(HL15=0,"",HM15/HL15)
A16: Liwonde | B16: Liwonde | C16: FY2025/26 | D16: 2025 | E16: 5 | F16: May | G16: Q1 | H16: 60718 | I16: 23130 | J16: 476 | K16: 617 | L16: 290 | M16: =SUM(I16,J16,K16,L16) | N16: 11701.7 | O16: 0 | P16: 4927.5 | Q16: 1757.4 | R16: =SUM(N16,O16,P16,Q16) | S16: =M16+R16 | T16: 17818.4 | U16: =IF(H16=0,"",T16/H16) | V16: 324 | W16: =IF(H16=0,"",V16/H16) | X16: 225 | Y16: =IF(H16=0,"",X16/H16) | Z16: 0 | AA16: =IF(H16=0,"",Z16/H16) | AB16: 336 | AC16: =IF(H16=0,"",AB16/H16) | AD16: 0 | AE16: =IF(H16=0,"",AD16/H16) | AF16: 0 | AG16: =IF(H16=0,"",AF16/H16) | AH16: 2632876.1 | AI16: =IF(H16=0,"",AH16/H16) | AJ16: 55348.8 | AK16: =IF(H16=0,"",AJ16/H16) | AL16: 9272413 | AM16: =IF(H16=0,"",AL16/H16) | AN16: 2559 | AO16: 436 | AP16: 1192024 | AQ16: 0 | AR16: 15993839 | AS16: 4019251.1 | AT16: 293286.24 | AU16: =AH16+AL16+AP16+AQ16+AR16+AS16+AT16 | AV16: =IF(H16=0,"",AU16/H16) | AW16: =IF(S16=0,"",AU16/S16) | AX16: 24 | AY16: =IF(H16=0,"",AX16/(H16/1000/12)) | AZ16: 46 | BA16: 684 | BB16: 22 | BC16: 0 | BD16: 20 | BE16: =BC16+BD16 | BF16: =BA16+BB16-BE16 | BG16: 0 | BH16: 0 | BI16: 0 | BJ16: 0 | BK16: =BI16+BJ16 | BL16: =BG16+BH16-BK16 | BM16: 0 | BN16: 0 | BO16: 0 | BP16: 0 | BQ16: =BO16+BP16 | BR16: =BM16+BN16-BQ16 | BS16: 0 | BT16: 0 | BU16: 0 | BV16: 0 | BW16: =BU16+BV16 | BX16: =BS16+BT16-BW16 | BY16: =BA16+BG16+BM16+BS16 | BZ16: =BB16+BH16+BN16+BT16 | CA16: =BE16+BK16+BQ16+BW16 | CB16: =BF16+BL16+BR16+BX16 | CC16: 20 | CD16: 1504 | CE16: 33 | CF16: 20 | CG16: 15 | CH16: =CD16+CE16+CF16+CG16 | CI16: 2855 | CJ16: 12 | CK16: 7 | CL16: 12 | CM16: =CI16+CJ16+CK16+CL16 | CN16: 1148 | CO16: 105 | CP16: 186 | CQ16: 0 | CR16: =CN16+CO16+CP16+CQ16 | CS16: =CM16+CR16 | CT16: 5897 | CU16: 33991 | CV16: 30591 | CW16: =IF(CU16=0,"",CV16/CU16) | DB16: =CX16+CY16-CZ16-DA16 | DC16: 0 | DD16: 0 | DE16: 0 | DF16: 0 | DG16: =DC16+DD16-DE16-DF16 | DH16: 0 | DI16: 0 | DJ16: 0 | DK16: 0 | DL16: =DH16+DI16-DJ16-DK16 | DM16: 254 | DN16: 18 | DO16: 0 | DP16: 4 | DQ16: =DM16+DN16-DO16-DP16 | DR16: =CX16+DC16+DH16+DM16 | DS16: =CY16+DD16+DI16+DN16 | DT16: =CZ16+DE16+DJ16+DO16 | DU16: =DA16+DF16+DK16+DP16 | DV16: =DB16+DG16+DL16+DQ16 | DW16: 91 | DX16: 52 | DY16: 6 | DZ16: 6 | EA16: 3 | EB16: 3 | EC16: 0 | ED16: 12 | EE16: 9 | EF16: 13 | EG16: 0 | EH16: 0 | EI16: 1 | EJ16: 0 | EK16: 0 | EL16: 0 | EM16: 0 | EN16: 0 | EO16: 0 | EP16: 0 | EQ16: 0 | ER16: 0 | ES16: 0 | ET16: 0 | EU16: 0 | EV16: 0 | EW16: 0 | EX16: 0 | EY16: 0 | EZ16: 0 | FA16: 0 | FB16: 0 | FC16: 0 | FD16: 0 | FE16: 0 | FF16: 0 | FG16: =SUM(DW16,DX16,DY16,DZ16,EA16,EB16,EC16,ED16,EE16,EF16,EG16,EH16,EI16,EJ16,EK16,EL16,EM16,EN16,EO16,EP16,EQ16,ER16,ES16,ET16,EU16,EV16,EW16,EX16,EY16,EZ16,FA16,FB16,FC16,FD16,FE16,FF16) | FH16: 0 | FI16: 0 | FJ16: 720 | FK16: 0 | FL16: 0 | FM16: 0 | FN16: 0 | FO16: 500 | FP16: 0 | FQ16: =FL16+FM16+FN16+FO16+FP16 | FR16: 36178587 | FS16: 57000 | FT16: 2247970 | FU16: 94867.22 | FV16: =FR16+FS16+FT16+FU16 | FW16: 14753005 | FX16: 0 | FY16: 8492989.6 | FZ16: 15057333 | GA16: =FW16+FX16+FY16+FZ16 | GB16: =FV16+GA16 | GC16: 21883104 | GD16: 91049.28 | GE16: 2083115.4 | GF16: 1273569.6 | GG16: =GC16+GD16+GE16+GF16 | GH16: 14633439 | GI16: 0 | GJ16: 14902774 | GK16: 8286889.6 | GL16: =GH16+GI16+GJ16+GK16 | GM16: =GG16+GL16 | GN16: 1528918 | GO16: 2295.36 | GP16: 40723.68 | GQ16: 32461.38 | GR16: =GN16+GO16+GP16+GQ16 | GS16: 2549515 | GT16: 10716 | GU16: 10716 | GV16: 6251 | GW16: =GS16+GT16+GU16+GV16 | GX16: =GM16+GR16+GW16 | GY16: 2.150367e+08 | GZ16: 10616783 | HA16: =GY16+GZ16 | HB16: =IF(GX16=0,"",AU16/GX16) | HC16: =IF((GX16+GY16)=0,"",GB16/(GX16+GY16)) | HD16: =IF(GX16=0,"",GB16/GX16) | HE16: 22 | HF16: 1 | HG16: 686 | HH16: 22 | HI16: 20 | HJ16: =HF16+HI16 | HK16: =IF(HE16=0,"",HH16/HE16) | HL16: 14 | HM16: 30 | HN16: =IF(HL16=0,"",HM16/HL16)
A17: Liwonde | B17: Liwonde | C17: FY2025/26 | D17: 2025 | E17: 6 | F17: June | G17: Q1 | H17: 54718 | I17: 18981 | J17: 423 | K17: 494 | L17: 191 | M17: =SUM(I17,J17,K17,L17) | N17: 12704.8 | O17: 0 | P17: 3456.1 | Q17: 1590.8 | R17: =SUM(N17,O17,P17,Q17) | S17: =M17+R17 | T17: 16877.3 | U17: =IF(H17=0,"",T17/H17) | V17: 276 | W17: =IF(H17=0,"",V17/H17) | X17: 0 | Y17: =IF(H17=0,"",X17/H17) | Z17: 0 | AA17: =IF(H17=0,"",Z17/H17) | AB17: 432 | AC17: =IF(H17=0,"",AB17/H17) | AD17: 0 | AE17: =IF(H17=0,"",AD17/H17) | AF17: 0 | AG17: =IF(H17=0,"",AF17/H17) | AH17: 2582925.6 | AI17: =IF(H17=0,"",AH17/H17) | AJ17: 71480 | AK17: =IF(H17=0,"",AJ17/H17) | AL17: 11969187 | AM17: =IF(H17=0,"",AL17/H17) | AN17: 2274 | AO17: 294 | AP17: 803796 | AQ17: 0 | AR17: 16837532 | AS17: 5358554.3 | AT17: 19454059 | AU17: =AH17+AL17+AP17+AQ17+AR17+AS17+AT17 | AV17: =IF(H17=0,"",AU17/H17) | AW17: =IF(S17=0,"",AU17/S17) | AX17: 24 | AY17: =IF(H17=0,"",AX17/(H17/1000/12)) | AZ17: 46 | BA17: 686 | BB17: 48 | BC17: 0 | BD17: 22 | BE17: =BC17+BD17 | BF17: =BA17+BB17-BE17 | BG17: 0 | BH17: 0 | BI17: 0 | BJ17: 0 | BK17: =BI17+BJ17 | BL17: =BG17+BH17-BK17 | BM17: 0 | BN17: 0 | BO17: 0 | BP17: 0 | BQ17: =BO17+BP17 | BR17: =BM17+BN17-BQ17 | BS17: 0 | BT17: 0 | BU17: 0 | BV17: 0 | BW17: =BU17+BV17 | BX17: =BS17+BT17-BW17 | BY17: =BA17+BG17+BM17+BS17 | BZ17: =BB17+BH17+BN17+BT17 | CA17: =BE17+BK17+BQ17+BW17 | CB17: =BF17+BL17+BR17+BX17 | CC17: 63 | CD17: 1689 | CE17: 33 | CF17: 20 | CG17: 15 | CH17: =CD17+CE17+CF17+CG17 | CI17: 2604 | CJ17: 10 | CK17: 6 | CL17: 7 | CM17: =CI17+CJ17+CK17+CL17 | CN17: 1383 | CO17: 44 | CP17: 108 | CQ17: 0 | CR17: =CN17+CO17+CP17+CQ17 | CS17: =CM17+CR17 | CT17: 5919 | CU17: 34068 | CV17: 30591 | CW17: =IF(CU17=0,"",CV17/CU17) | DB17: =CX17+CY17-CZ17-DA17 | DC17: 0 | DD17: 0 | DE17: 0 | DF17: 0 | DG17: =DC17+DD17-DE17-DF17 | DH17: 0 | DI17: 0 | DJ17: 0 | DK17: 0 | DL17: =DH17+DI17-DJ17-DK17 | DM17: 268 | DN17: 3 | DO17: 0 | DP17: 0 | DQ17: =DM17+DN17-DO17-DP17 | DR17: =CX17+DC17+DH17+DM17 | DS17: =CY17+DD17+DI17+DN17 | DT17: =CZ17+DE17+DJ17+DO17 | DU17: =DA17+DF17+DK17+DP17 | DV17: =DB17+DG17+DL17+DQ17 | DW17: 72 | DX17: 44 | DY17: 28 | DZ17: 2 | EA17: 2 | EB17: 5 | EC17: 2 | ED17: 6 | EE17: 9 | EF17: 2 | EG17: 0 | EH17: 0 | EI17: 0 | EJ17: 0 | EK17: 0 | EL17: 0 | EM17: 0 | EN17: 0 | EO17: 0 | EP17: 0 | EQ17: 0 | ER17: 0 | ES17: 0 | ET17: 0 | EU17: 0 | EV17: 0 | EW17: 0 | EX17: 0 | EY17: 0 | EZ17: 0 | FA17: 0 | FB17: 0 | FC17: 0 | FD17: 0 | FE17: 0 | FF17: 0 | FG17: =SUM(DW17,DX17,DY17,DZ17,EA17,EB17,EC17,ED17,EE17,EF17,EG17,EH17,EI17,EJ17,EK17,EL17,EM17,EN17,EO17,EP17,EQ17,ER17,ES17,ET17,EU17,EV17,EW17,EX17,EY17,EZ17,FA17,FB17,FC17,FD17,FE17,FF17) | FH17: 0 | FI17: 0 | FJ17: 644 | FK17: 21 | FL17: 0 | FM17: 0 | FN17: 0 | FO17: 0 | FP17: 0 | FQ17: =FL17+FM17+FN17+FO17+FP17 | FR17: 55231037 | FS17: 337100 | FT17: 1875470 | FU17: 295934.44 | FV17: =FR17+FS17+FT17+FU17 | FW17: 16014954 | FX17: 0 | FY17: 7768191 | FZ17: 10438909 | GA17: =FW17+FX17+FY17+FZ17 | GB17: =FV17+GA17 | GC17: 17723558 | GD17: 80911.44 | GE17: 1664197.6 | GF17: 824838.04 | GG17: =GC17+GD17+GE17+GF17 | GH17: 15919639 | GI17: 0 | GJ17: 10395380 | GK17: 7454188.7 | GL17: =GH17+GI17+GJ17+GK17 | GM17: =GG17+GL17 | GN17: 1395340.9 | GO17: 1338.96 | GP17: 33936.4 | GQ17: 27824.04 | GR17: =GN17+GO17+GP17+GQ17 | GS17: 2325372 | GT17: 6251 | GU17: 8930 | GV17: 5358 | GW17: =GS17+GT17+GU17+GV17 | GX17: =GM17+GR17+GW17 | GY17: 1.8129881e+08 | GZ17: 7705017.9 | HA17: =GY17+GZ17 | HB17: =IF(GX17=0,"",AU17/GX17) | HC17: =IF((GX17+GY17)=0,"",GB17/(GX17+GY17)) | HD17: =IF(GX17=0,"",GB17/GX17) | HE17: 48 | HF17: 1 | HG17: 712 | HH17: 48 | HI17: 20 | HJ17: =HF17+HI17 | HK17: =IF(HE17=0,"",HH17/HE17) | HL17: 16 | HM17: 30 | HN17: =IF(HL17=0,"",HM17/HL17)
A18: Liwonde | B18: Liwonde | C18: FY2025/26 | D18: 2025 | E18: 7 | F18: July | G18: Q2 | H18: 75207 | I18: 28705 | J18: 650 | K18: 651 | L18: 339 | M18: =SUM(I18,J18,K18,L18) | N18: 15473.4 | O18: 0 | P18: 1749.2 | Q18: 5209.7 | R18: =SUM(N18,O18,P18,Q18) | S18: =M18+R18 | T18: 22429.7 | U18: =IF(H18=0,"",T18/H18) | V18: 369 | W18: =IF(H18=0,"",V18/H18) | X18: 0 | Y18: =IF(H18=0,"",X18/H18) | Z18: 0 | AA18: =IF(H18=0,"",Z18/H18) | AB18: 480 | AC18: =IF(H18=0,"",AB18/H18) | AD18: 0 | AE18: =IF(H18=0,"",AD18/H18) | AF18: 0 | AG18: =IF(H18=0,"",AF18/H18) | AH18: 3089660.4 | AI18: =IF(H18=0,"",AH18/H18) | AJ18: 57800 | AK18: =IF(H18=0,"",AJ18/H18) | AL18: 9682198.5 | AM18: =IF(H18=0,"",AL18/H18) | AN18: 2592 | AO18: 513 | AP18: 1402542 | AQ18: 0 | AR18: 16837532 | AS18: 7820653.4 | AT18: 156000 | AU18: =AH18+AL18+AP18+AQ18+AR18+AS18+AT18 | AV18: =IF(H18=0,"",AU18/H18) | AW18: =IF(S18=0,"",AU18/S18) | AX18: 26 | AY18: =IF(H18=0,"",AX18/(H18/1000/12)) | AZ18: 45 | BA18: 712 | BB18: 52 | BC18: 0 | BD18: 9 | BE18: =BC18+BD18 | BF18: =BA18+BB18-BE18 | BG18: 0 | BH18: 0 | BI18: 0 | BJ18: 0 | BK18: =BI18+BJ18 | BL18: =BG18+BH18-BK18 | BM18: 0 | BN18: 0 | BO18: 0 | BP18: 0 | BQ18: =BO18+BP18 | BR18: =BM18+BN18-BQ18 | BS18: 0 | BT18: 0 | BU18: 0 | BV18: 0 | BW18: =BU18+BV18 | BX18: =BS18+BT18-BW18 | BY18: =BA18+BG18+BM18+BS18 | BZ18: =BB18+BH18+BN18+BT18 | CA18: =BE18+BK18+BQ18+BW18 | CB18: =BF18+BL18+BR18+BX18 | CC18: 54 | CD18: 1689 | CE18: 33 | CF18: 20 | CG18: 15 | CH18: =CD18+CE18+CF18+CG18 | CI18: 2674 | CJ18: 9 | CK18: 7 | CL18: 7 | CM18: =CI18+CJ18+CK18+CL18 | CN18: 1437 | CO18: 37 | CP18: 122 | CQ18: 0 | CR18: =CN18+CO18+CP18+CQ18 | CS18: =CM18+CR18 | CT18: 6050 | CU18: 34068 | CV18: 30591 | CW18: =IF(CU18=0,"",CV18/CU18) | DB18: =CX18+CY18-CZ18-DA18 | DC18: 0 | DD18: 0 | DE18: 0 | DF18: 0 | DG18: =DC18+DD18-DE18-DF18 | DH18: 0 | DI18: 0 | DJ18: 0 | DK18: 0 | DL18: =DH18+DI18-DJ18-DK18 | DM18: 271 | DN18: 0 | DO18: 0 | DP18: 0 | DQ18: =DM18+DN18-DO18-DP18 | DR18: =CX18+DC18+DH18+DM18 | DS18: =CY18+DD18+DI18+DN18 | DT18: =CZ18+DE18+DJ18+DO18 | DU18: =DA18+DF18+DK18+DP18 | DV18: =DB18+DG18+DL18+DQ18 | DW18: 84 | DX18: 39 | DY18: 16 | DZ18: 0 | EA18: 2 | EB18: 2 | EC18: 0 | ED18: 2 | EE18: 7 | EF18: 3 | EG18: 0 | EH18: 0 | EI18: 0 | EJ18: 0 | EK18: 0 | EL18: 0 | EM18: 0 | EN18: 0 | EO18: 0 | EP18: 0 | EQ18: 0 | ER18: 0 | ES18: 0 | ET18: 0 | EU18: 0 | EV18: 0 | EW18: 0 | EX18: 0 | EY18: 0 | EZ18: 0 | FA18: 0 | FB18: 0 | FC18: 0 | FD18: 0 | FE18: 0 | FF18: 0 | FG18: =SUM(DW18,DX18,DY18,DZ18,EA18,EB18,EC18,ED18,EE18,EF18,EG18,EH18,EI18,EJ18,EK18,EL18,EM18,EN18,EO18,EP18,EQ18,ER18,ES18,ET18,EU18,EV18,EW18,EX18,EY18,EZ18,FA18,FB18,FC18,FD18,FE18,FF18) | FH18: 1 | FI18: 120 | FJ18: 540 | FK18: 72 | FL18: 0 | FM18: 0 | FN18: 0 | FO18: 0 | FP18: 0 | FQ18: =FL18+FM18+FN18+FO18+FP18 | FR18: 21704845 | FS18: 61600 | FT18: 1536440 | FU18: 117500 | FV18: =FR18+FS18+FT18+FU18 | FW18: 19554711 | FX18: 0 | FY18: 24809869 | FZ18: 5286447.4 | GA18: =FW18+FX18+FY18+FZ18 | GB18: =FV18+GA18 | GC18: 26356470 | GD18: 124332 | GE18: 2204247.7 | GF18: 1586676.2 | GG18: =GC18+GD18+GE18+GF18 | GH18: 19397922 | GI18: 0 | GJ18: 5280447.4 | GK18: 24536559 | GL18: =GH18+GI18+GJ18+GK18 | GM18: =GG18+GL18 | GN18: 1434754.9 | GO18: 1338.96 | GP18: 30542.76 | GQ18: 32461.38 | GR18: =GN18+GO18+GP18+GQ18 | GS18: 2387882 | GT18: 6251 | GU18: 8037 | GV18: 6251 | GW18: =GS18+GT18+GU18+GV18 | GX18: =GM18+GR18+GW18 | GY18: 1.9188286e+08 | GZ18: 8175151.4 | HA18: =GY18+GZ18 | HB18: =IF(GX18=0,"",AU18/GX18) | HC18: =IF((GX18+GY18)=0,"",GB18/(GX18+GY18)) | HD18: =IF(GX18=0,"",GB18/GX18) | HE18: 52 | HF18: 1 | HG18: 755 | HH18: 52 | HI18: 20 | HJ18: =HF18+HI18 | HK18: =IF(HE18=0,"",HH18/HE18) | HL18: 14 | HM18: 30 | HN18: =IF(HL18=0,"",HM18/HL18)
A19: Liwonde | B19: Liwonde | C19: FY2025/26 | D19: 2025 | E19: 8 | F19: August | G19: Q2 | H19: 65442 | I19: 24392 | J19: 540 | K19: 373 | L19: 119 | M19: =SUM(I19,J19,K19,L19) | N19: 14811.4 | O19: 0 | P19: 3236.7 | Q19: 1938.7 | R19: =SUM(N19,O19,P19,Q19) | S19: =M19+R19 | T19: 20031.2 | U19: =IF(H19=0,"",T19/H19) | V19: 348 | W19: =IF(H19=0,"",V19/H19) | X19: 0 | Y19: =IF(H19=0,"",X19/H19) | Z19: 0 | AA19: =IF(H19=0,"",Z19/H19) | AB19: 228 | AC19: =IF(H19=0,"",AB19/H19) | AD19: 0 | AE19: =IF(H19=0,"",AD19/H19) | AF19: 0 | AG19: =IF(H19=0,"",AF19/H19) | AH19: 2076494.4 | AI19: =IF(H19=0,"",AH19/H19) | AJ19: 56715 | AK19: =IF(H19=0,"",AJ19/H19) | AL19: 9500810.9 | AM19: =IF(H19=0,"",AL19/H19) | AN19: 1908 | AO19: 580 | AP19: 1585720 | AQ19: 0 | AR19: 16622298 | AS19: 7793633.2 | AT19: 2545700 | AU19: =AH19+AL19+AP19+AQ19+AR19+AS19+AT19 | AV19: =IF(H19=0,"",AU19/H19) | AW19: =IF(S19=0,"",AU19/S19) | AX19: 25 | AY19: =IF(H19=0,"",AX19/(H19/1000/12)) | AZ19: 53 | BA19: 755 | BB19: 76 | BC19: 0 | BD19: 22 | BE19: =BC19+BD19 | BF19: =BA19+BB19-BE19 | BG19: 0 | BH19: 0 | BI19: 0 | BJ19: 0 | BK19: =BI19+BJ19 | BL19: =BG19+BH19-BK19 | BM19: 0 | BN19: 0 | BO19: 0 | BP19: 0 | BQ19: =BO19+BP19 | BR19: =BM19+BN19-BQ19 | BS19: 0 | BT19: 0 | BU19: 0 | BV19: 0 | BW19: =BU19+BV19 | BX19: =BS19+BT19-BW19 | BY19: =BA19+BG19+BM19+BS19 | BZ19: =BB19+BH19+BN19+BT19 | CA19: =BE19+BK19+BQ19+BW19 | CB19: =BF19+BL19+BR19+BX19 | CC19: 43 | CD19: 1662 | CE19: 33 | CF19: 20 | CG19: 15 | CH19: =CD19+CE19+CF19+CG19 | CI19: 2649 | CJ19: 8 | CK19: 5 | CL19: 9 | CM19: =CI19+CJ19+CK19+CL19 | CN19: 1511 | CO19: 45 | CP19: 114 | CQ19: 1 | CR19: =CN19+CO19+CP19+CQ19 | CS19: =CM19+CR19 | CT19: 6072 | CU19: 34408.68 | CV19: 31202.82 | CW19: =IF(CU19=0,"",CV19/CU19) | DB19: =CX19+CY19-CZ19-DA19 | DC19: 0 | DD19: 0 | DE19: 0 | DF19: 0 | DG19: =DC19+DD19-DE19-DF19 | DH19: 0 | DI19: 0 | DJ19: 0 | DK19: 0 | DL19: =DH19+DI19-DJ19-DK19 | DM19: 271 | DN19: 0 | DO19: 0 | DP19: 0 | DQ19: =DM19+DN19-DO19-DP19 | DR19: =CX19+DC19+DH19+DM19 | DS19: =CY19+DD19+DI19+DN19 | DT19: =CZ19+DE19+DJ19+DO19 | DU19: =DA19+DF19+DK19+DP19 | DV19: =DB19+DG19+DL19+DQ19 | DW19: 65 | DX19: 25 | DY19: 14 | DZ19: 7 | EA19: 5 | EB19: 6 | EC19: 0 | ED19: 2 | EE19: 1 | EF19: 1 | EG19: 1 | EH19: 0 | EI19: 0 | EJ19: 0 | EK19: 0 | EL19: 0 | EM19: 0 | EN19: 0 | EO19: 0 | EP19: 0 | EQ19: 0 | ER19: 0 | ES19: 0 | ET19: 0 | EU19: 0 | EV19: 0 | EW19: 0 | EX19: 0 | EY19: 0 | EZ19: 0 | FA19: 0 | FB19: 0 | FC19: 0 | FD19: 0 | FE19: 0 | FF19: 0 | FG19: =SUM(DW19,DX19,DY19,DZ19,EA19,EB19,EC19,ED19,EE19,EF19,EG19,EH19,EI19,EJ19,EK19,EL19,EM19,EN19,EO19,EP19,EQ19,ER19,ES19,ET19,EU19,EV19,EW19,EX19,EY19,EZ19,FA19,FB19,FC19,FD19,FE19,FF19) | FH19: 1 | FI19: 6 | FJ19: 670 | FK19: 74 | FL19: 0 | FM19: 0 | FN19: 0 | FO19: 0 | FP19: 0 | FQ19: =FL19+FM19+FN19+FO19+FP19 | FR19: 28177389 | FS19: 210867.22 | FT19: 1417507.2 | FU19: 233000 | FV19: =FR19+FS19+FT19+FU19 | FW19: 19264988 | FX19: 1500 | FY19: 9513496.2 | FZ19: 9738987.1 | GA19: =FW19+FX19+FY19+FZ19 | GB19: =FV19+GA19 | GC19: 22381745 | GD19: 103291.2 | GE19: 1234495.3 | GF19: 519295.25 | GG19: =GC19+GD19+GE19+GF19 | GH19: 18567798 | GI19: 600 | GJ19: 9737787.1 | GK19: 9054878.8 | GL19: =GH19+GI19+GJ19+GK19 | GM19: =GG19+GL19 | GN19: 1420537.3 | GO19: 1721.52 | GP19: 27149.12 | GQ19: 23186.7 | GR19: =GN19+GO19+GP19+GQ19 | GS19: 2365557 | GT19: 8037 | GU19: 7144 | GV19: 4465 | GW19: =GS19+GT19+GU19+GV19 | GX19: =GM19+GR19+GW19 | GY19: 1.8634952e+08 | GZ19: 11513610 | HA19: =GY19+GZ19 | HB19: =IF(GX19=0,"",AU19/GX19) | HC19: =IF((GX19+GY19)=0,"",GB19/(GX19+GY19)) | HD19: =IF(GX19=0,"",GB19/GX19) | HE19: 76 | HF19: 1 | HG19: 809 | HH19: 76 | HI19: 20 | HJ19: =HF19+HI19 | HK19: =IF(HE19=0,"",HH19/HE19) | HL19: 9 | HM19: 30 | HN19: =IF(HL19=0,"",HM19/HL19)
A20: Liwonde | B20: Liwonde | C20: FY2025/26 | D20: 2025 | E20: 9 | F20: September | G20: Q2 | H20: 79532 | I20: 30922 | J20: 819 | K20: 474 | L20: 155 | M20: =SUM(I20,J20,K20,L20) | N20: 19401.1 | O20: 0 | P20: 1207.1 | Q20: 2262.3 | R20: =SUM(N20,O20,P20,Q20) | S20: =M20+R20 | T20: 24291.5 | U20: =IF(H20=0,"",T20/H20) | V20: 348 | W20: =IF(H20=0,"",V20/H20) | X20: 0 | Y20: =IF(H20=0,"",X20/H20) | Z20: 0 | AA20: =IF(H20=0,"",Z20/H20) | AB20: 435 | AC20: =IF(H20=0,"",AB20/H20) | AD20: 0 | AE20: =IF(H20=0,"",AD20/H20) | AF20: 0 | AG20: =IF(H20=0,"",AF20/H20) | AH20: 2847926.6 | AI20: =IF(H20=0,"",AH20/H20) | AJ20: 51921 | AK20: =IF(H20=0,"",AJ20/H20) | AL20: 8699362 | AM20: =IF(H20=0,"",AL20/H20) | AN20: 1610 | AO20: 220 | AP20: 601480 | AQ20: 0 | AR20: 16155162 | AS20: 9349269.4 | AT20: 16955302 | AU20: =AH20+AL20+AP20+AQ20+AR20+AS20+AT20 | AV20: =IF(H20=0,"",AU20/H20) | AW20: =IF(S20=0,"",AU20/S20) | AX20: 25 | AY20: =IF(H20=0,"",AX20/(H20/1000/12)) | AZ20: 53 | BA20: 809 | BB20: 57 | BC20: 0 | BD20: 32 | BE20: =BC20+BD20 | BF20: =BA20+BB20-BE20 | BG20: 0 | BH20: 0 | BI20: 0 | BJ20: 0 | BK20: =BI20+BJ20 | BL20: =BG20+BH20-BK20 | BM20: 0 | BN20: 0 | BO20: 0 | BP20: 0 | BQ20: =BO20+BP20 | BR20: =BM20+BN20-BQ20 | BS20: 0 | BT20: 0 | BU20: 0 | BV20: 0 | BW20: =BU20+BV20 | BX20: =BS20+BT20-BW20 | BY20: =BA20+BG20+BM20+BS20 | BZ20: =BB20+BH20+BN20+BT20 | CA20: =BE20+BK20+BQ20+BW20 | CB20: =BF20+BL20+BR20+BX20 | CC20: 32 | CD20: 1662 | CE20: 33 | CF20: 20 | CG20: 15 | CH20: =CD20+CE20+CF20+CG20 | CI20: 2631 | CJ20: 7 | CK20: 4 | CL20: 10 | CM20: =CI20+CJ20+CK20+CL20 | CN20: 1543 | CO20: 45 | CP20: 114 | CQ20: 1 | CR20: =CN20+CO20+CP20+CQ20 | CS20: =CM20+CR20 | CT20: 6085 | CU20: 34753 | CV20: 31515 | CW20: =IF(CU20=0,"",CV20/CU20) | DB20: =CX20+CY20-CZ20-DA20 | DC20: 0 | DD20: 0 | DE20: 0 | DF20: 0 | DG20: =DC20+DD20-DE20-DF20 | DH20: 0 | DI20: 0 | DJ20: 0 | DK20: 0 | DL20: =DH20+DI20-DJ20-DK20 | DM20: 244 | DN20: 0 | DO20: 0 | DP20: 12 | DQ20: =DM20+DN20-DO20-DP20 | DR20: =CX20+DC20+DH20+DM20 | DS20: =CY20+DD20+DI20+DN20 | DT20: =CZ20+DE20+DJ20+DO20 | DU20: =DA20+DF20+DK20+DP20 | DV20: =DB20+DG20+DL20+DQ20 | DW20: 82 | DX20: 30 | DY20: 18 | DZ20: 7 | EA20: 6 | EB20: 10 | EC20: 0 | ED20: 6 | EE20: 1 | EF20: 0 | EG20: 0 | EH20: 0 | EI20: 0 | EJ20: 5 | EK20: 0 | EL20: 0 | EM20: 0 | EN20: 0 | EO20: 0 | EP20: 0 | EQ20: 0 | ER20: 0 | ES20: 0 | ET20: 0 | EU20: 0 | EV20: 0 | EW20: 0 | EX20: 0 | EY20: 0 | EZ20: 0 | FA20: 0 | FB20: 0 | FC20: 0 | FD20: 0 | FE20: 0 | FF20: 0 | FG20: =SUM(DW20,DX20,DY20,DZ20,EA20,EB20,EC20,ED20,EE20,EF20,EG20,EH20,EI20,EJ20,EK20,EL20,EM20,EN20,EO20,EP20,EQ20,ER20,ES20,ET20,EU20,EV20,EW20,EX20,EY20,EZ20,FA20,FB20,FC20,FD20,FE20,FF20) | FH20: 1 | FI20: 80 | FJ20: 620 | FK20: 20 | FL20: 0 | FM20: 0 | FN20: 0 | FO20: 0 | FP20: 0 | FQ20: =FL20+FM20+FN20+FO20+FP20 | FR20: 23204889 | FS20: 141300 | FT20: 661540 | FU20: 7671857.6 | FV20: =FR20+FS20+FT20+FU20 | FW20: 25015888 | FX20: 2000 | FY20: 10996858 | FZ20: 3675049.2 | GA20: =FW20+FX20+FY20+FZ20 | GB20: =FV20+GA20 | GC20: 28378727 | GD20: 156658.32 | GE20: 1594442.7 | GF20: 702883.86 | GG20: =GC20+GD20+GE20+GF20 | GH20: 24201037 | GI20: 800 | GJ20: 3669049.2 | GK20: 10692908 | GL20: =GH20+GI20+GJ20+GK20 | GM20: =GG20+GL20 | GN20: 1410503.7 | GO20: 1912.8 | GP20: 23755.48 | GQ20: 18549.36 | GR20: =GN20+GO20+GP20+GQ20 | GS20: 2349483 | GT20: 8930 | GU20: 6251 | GV20: 3572 | GW20: =GS20+GT20+GU20+GV20 | GX20: =GM20+GR20+GW20 | GY20: 1.9512577e+08 | GZ20: 5845360 | HA20: =GY20+GZ20 | HB20: =IF(GX20=0,"",AU20/GX20) | HC20: =IF((GX20+GY20)=0,"",GB20/(GX20+GY20)) | HD20: =IF(GX20=0,"",GB20/GX20) | HE20: 57 | HF20: 1 | HG20: 834 | HH20: 57 | HI20: 20 | HJ20: =HF20+HI20 | HK20: =IF(HE20=0,"",HH20/HE20) | HL20: 18 | HM20: 30 | HN20: =IF(HL20=0,"",HM20/HL20)
A21: Liwonde | B21: Liwonde | C21: FY2025/26 | D21: 2025 | E21: 10 | F21: October | G21: Q3 | H21: 69610 | I21: 23928 | J21: 606 | K21: 291 | L21: 13 | M21: =SUM(I21,J21,K21,L21) | N21: 19995.9 | O21: 0 | P21: 2473.2 | Q21: 1755.6 | R21: =SUM(N21,O21,P21,Q21) | S21: =M21+R21 | T21: 20547.3 | U21: =IF(H21=0,"",T21/H21) | V21: 338 | W21: =IF(H21=0,"",V21/H21) | X21: 0 | Y21: =IF(H21=0,"",X21/H21) | Z21: 0 | AA21: =IF(H21=0,"",Z21/H21) | AB21: 0 | AC21: =IF(H21=0,"",AB21/H21) | AD21: 0 | AE21: =IF(H21=0,"",AD21/H21) | AF21: 0 | AG21: =IF(H21=0,"",AF21/H21) | AH21: 1191548 | AI21: =IF(H21=0,"",AH21/H21) | AJ21: 54690 | AK21: =IF(H21=0,"",AJ21/H21) | AL21: 9162276.5 | AM21: =IF(H21=0,"",AL21/H21) | AN21: 2459 | AO21: 252 | AP21: 688968 | AQ21: 0 | AR21: 0 | AS21: 8484854.9 | AT21: 3671766.9 | AU21: =AH21+AL21+AP21+AQ21+AR21+AS21+AT21 | AV21: =IF(H21=0,"",AU21/H21) | AW21: =IF(S21=0,"",AU21/S21) | AX21: 25 | AY21: =IF(H21=0,"",AX21/(H21/1000/12)) | AZ21: 55 | BA21: 834 | BB21: 69 | BC21: 24 | BD21: 37 | BE21: =BC21+BD21 | BF21: =BA21+BB21-BE21 | BG21: 0 | BH21: 0 | BI21: 0 | BJ21: 0 | BK21: =BI21+BJ21 | BL21: =BG21+BH21-BK21 | BM21: 0 | BN21: 0 | BO21: 0 | BP21: 0 | BQ21: =BO21+BP21 | BR21: =BM21+BN21-BQ21 | BS21: 0 | BT21: 0 | BU21: 0 | BV21: 0 | BW21: =BU21+BV21 | BX21: =BS21+BT21-BW21 | BY21: =BA21+BG21+BM21+BS21 | BZ21: =BB21+BH21+BN21+BT21 | CA21: =BE21+BK21+BQ21+BW21 | CB21: =BF21+BL21+BR21+BX21 | CC21: 45 | CD21: 1701 | CE21: 33 | CF21: 20 | CG21: 15 | CH21: =CD21+CE21+CF21+CG21 | CI21: 2553 | CJ21: 8 | CK21: 5 | CL21: 10 | CM21: =CI21+CJ21+CK21+CL21 | CN21: 1604 | CO21: 45 | CP21: 114 | CQ21: 1 | CR21: =CN21+CO21+CP21+CQ21 | CS21: =CM21+CR21 | CT21: 6109 | CU21: 35100 | CV21: 32643 | CW21: =IF(CU21=0,"",CV21/CU21) | DB21: =CX21+CY21-CZ21-DA21 | DC21: 0 | DD21: 0 | DE21: 0 | DF21: 0 | DG21: =DC21+DD21-DE21-DF21 | DH21: 0 | DI21: 0 | DJ21: 0 | DK21: 0 | DL21: =DH21+DI21-DJ21-DK21 | DM21: 232 | DN21: 85 | DO21: 0 | DP21: 0 | DQ21: =DM21+DN21-DO21-DP21 | DR21: =CX21+DC21+DH21+DM21 | DS21: =CY21+DD21+DI21+DN21 | DT21: =CZ21+DE21+DJ21+DO21 | DU21: =DA21+DF21+DK21+DP21 | DV21: =DB21+DG21+DL21+DQ21 | DW21: 59 | DX21: 20 | DY21: 17 | DZ21: 0 | EA21: 4 | EB21: 3 | EC21: 1 | ED21: 1 | EE21: 4 | EF21: 2 | EG21: 0 | EH21: 0 | EI21: 0 | EJ21: 0 | EK21: 0 | EL21: 0 | EM21: 0 | EN21: 0 | EO21: 0 | EP21: 0 | EQ21: 0 | ER21: 0 | ES21: 0 | ET21: 0 | EU21: 0 | EV21: 0 | EW21: 0 | EX21: 0 | EY21: 0 | EZ21: 0 | FA21: 0 | FB21: 0 | FC21: 0 | FD21: 0 | FE21: 0 | FF21: 0 | FG21: =SUM(DW21,DX21,DY21,DZ21,EA21,EB21,EC21,ED21,EE21,EF21,EG21,EH21,EI21,EJ21,EK21,EL21,EM21,EN21,EO21,EP21,EQ21,ER21,ES21,ET21,EU21,EV21,EW21,EX21,EY21,EZ21,FA21,FB21,FC21,FD21,FE21,FF21) | FH21: 0 | FI21: 0 | FJ21: 595 | FK21: 74 | FL21: 0 | FM21: 0 | FN21: 0 | FO21: 0 | FP21: 1158 | FQ21: =FL21+FM21+FN21+FO21+FP21 | FR21: 25387468 | FS21: 170700 | FT21: 1183440 | FU21: 30500 | FV21: =FR21+FS21+FT21+FU21 | FW21: 26037365 | FX21: 0 | FY21: 8115189.3 | FZ21: 7541179.2 | GA21: =FW21+FX21+FY21+FZ21 | GB21: =FV21+GA21 | GC21: 22010635 | GD21: 115915.68 | GE21: 978630.32 | GF21: 48826.23 | GG21: =GC21+GD21+GE21+GF21 | GH21: 25007847 | GI21: 0 | GJ21: 7499121.8 | GK21: 7801188.9 | GL21: =GH21+GI21+GJ21+GK21 | GM21: =GG21+GL21 | GN21: 1358330.2 | GO21: 1912.8 | GP21: 27149.12 | GQ21: 23186.7 | GR21: =GN21+GO21+GP21+GQ21 | GS21: 2279829 | GT21: 8930 | GU21: 7144 | GV21: 4465 | GW21: =GS21+GT21+GU21+GV21 | GX21: =GM21+GR21+GW21 | GY21: 1.9451756e+08 | GZ21: 6961042 | HA21: =GY21+GZ21 | HB21: =IF(GX21=0,"",AU21/GX21) | HC21: =IF((GX21+GY21)=0,"",GB21/(GX21+GY21)) | HD21: =IF(GX21=0,"",GB21/GX21) | HE21: 69 | HF21: 1 | HG21: 842 | HH21: 69 | HI21: 20 | HJ21: =HF21+HI21 | HK21: =IF(HE21=0,"",HH21/HE21) | HL21: 17 | HM21: 30 | HN21: =IF(HL21=0,"",HM21/HL21)
A22: Liwonde | B22: Liwonde | C22: FY2025/26 | D22: 2025 | E22: 11 | F22: November | G22: Q3 | H22: 68078 | I22: 24485 | J22: 742 | K22: 532 | L22: 93 | M22: =SUM(I22,J22,K22,L22) | N22: 20022.3 | O22: 0 | P22: 1449.6 | Q22: 0 | R22: =SUM(N22,O22,P22,Q22) | S22: =M22+R22 | T22: 20754.1 | U22: =IF(H22=0,"",T22/H22) | V22: 348 | W22: =IF(H22=0,"",V22/H22) | X22: 90 | Y22: =IF(H22=0,"",X22/H22) | Z22: 0 | AA22: =IF(H22=0,"",Z22/H22) | AB22: 368 | AC22: =IF(H22=0,"",AB22/H22) | AD22: 0 | AE22: =IF(H22=0,"",AD22/H22) | AF22: 0 | AG22: =IF(H22=0,"",AF22/H22) | AH22: 2693636.9 | AI22: =IF(H22=0,"",AH22/H22) | AJ22: 72598 | AK22: =IF(H22=0,"",AJ22/H22) | AL22: 12156091 | AM22: =IF(H22=0,"",AL22/H22) | AN22: 2589 | AO22: 342 | AP22: 1197000 | AQ22: 0 | AR22: 16385259 | AS22: 8484854.9 | AT22: 4725040.1 | AU22: =AH22+AL22+AP22+AQ22+AR22+AS22+AT22 | AV22: =IF(H22=0,"",AU22/H22) | AW22: =IF(S22=0,"",AU22/S22) | AX22: 25 | AY22: =IF(H22=0,"",AX22/(H22/1000/12)) | AZ22: 57 | BA22: 842 | BB22: 44 | BC22: 17 | BD22: 36 | BE22: =BC22+BD22 | BF22: =BA22+BB22-BE22 | BG22: 0 | BH22: 0 | BI22: 0 | BJ22: 0 | BK22: =BI22+BJ22 | BL22: =BG22+BH22-BK22 | BM22: 0 | BN22: 0 | BO22: 0 | BP22: 0 | BQ22: =BO22+BP22 | BR22: =BM22+BN22-BQ22 | BS22: 0 | BT22: 0 | BU22: 0 | BV22: 0 | BW22: =BU22+BV22 | BX22: =BS22+BT22-BW22 | BY22: =BA22+BG22+BM22+BS22 | BZ22: =BB22+BH22+BN22+BT22 | CA22: =BE22+BK22+BQ22+BW22 | CB22: =BF22+BL22+BR22+BX22 | CC22: 36 | CD22: 1701 | CE22: 33 | CF22: 20 | CG22: 15 | CH22: =CD22+CE22+CF22+CG22 | CI22: 2544 | CJ22: 9 | CK22: 5 | CL22: 11 | CM22: =CI22+CJ22+CK22+CL22 | CN22: 1636 | CO22: 45 | CP22: 114 | CQ22: 1 | CR22: =CN22+CO22+CP22+CQ22 | CS22: =CM22+CR22 | CT22: 6134 | CU22: 35451 | CV22: 32969.43 | CW22: =IF(CU22=0,"",CV22/CU22) | DB22: =CX22+CY22-CZ22-DA22 | DC22: 0 | DD22: 0 | DE22: 0 | DF22: 0 | DG22: =DC22+DD22-DE22-DF22 | DH22: 0 | DI22: 0 | DJ22: 0 | DK22: 0 | DL22: =DH22+DI22-DJ22-DK22 | DM22: 317 | DN22: 22 | DO22: 0 | DP22: 0 | DQ22: =DM22+DN22-DO22-DP22 | DR22: =CX22+DC22+DH22+DM22 | DS22: =CY22+DD22+DI22+DN22 | DT22: =CZ22+DE22+DJ22+DO22 | DU22: =DA22+DF22+DK22+DP22 | DV22: =DB22+DG22+DL22+DQ22 | DW22: 66 | DX22: 35 | DY22: 11 | DZ22: 1 | EA22: 3 | EB22: 0 | EC22: 1 | ED22: 1 | EE22: 3 | EF22: 3 | EG22: 0 | EH22: 0 | EI22: 0 | EJ22: 0 | EK22: 0 | EL22: 0 | EM22: 0 | EN22: 0 | EO22: 0 | EP22: 0 | EQ22: 0 | ER22: 0 | ES22: 0 | ET22: 0 | EU22: 0 | EV22: 0 | EW22: 0 | EX22: 0 | EY22: 0 | EZ22: 0 | FA22: 0 | FB22: 0 | FC22: 0 | FD22: 0 | FE22: 0 | FF22: 0 | FG22: =SUM(DW22,DX22,DY22,DZ22,EA22,EB22,EC22,ED22,EE22,EF22,EG22,EH22,EI22,EJ22,EK22,EL22,EM22,EN22,EO22,EP22,EQ22,ER22,ES22,ET22,EU22,EV22,EW22,EX22,EY22,EZ22,FA22,FB22,FC22,FD22,FE22,FF22) | FH22: 0 | FI22: 50 | FJ22: 744 | FK22: 124 | FL22: 0 | FM22: 0 | FN22: 0 | FO22: 0 | FP22: 792 | FQ22: =FL22+FM22+FN22+FO22+FP22 | FR22: 22317439 | FS22: 32000 | FT22: 371940 | FU22: 2353044 | FV22: =FR22+FS22+FT22+FU22 | FW22: 25943366 | FX22: 13900 | FY22: 9554361.4 | FZ22: 4432735 | GA22: =FW22+FX22+FY22+FZ22 | GB22: =FV22+GA22 | GC22: 22452052 | GD22: 141929.76 | GE22: 1799775.8 | GF22: 399814.05 | GG22: =GC22+GD22+GE22+GF22 | GH22: 25125924 | GI22: 12880 | GJ22: 4376520.4 | GK22: 9240877.4 | GL22: =GH22+GI22+GJ22+GK22 | GM22: =GG22+GL22 | GN22: 1353364.8 | GO22: 2104.08 | GP22: 30542.76 | GQ22: 23186.7 | GR22: =GN22+GO22+GP22+GQ22 | GS22: 2271792 | GT22: 9823 | GU22: 8037 | GV22: 4465 | GW22: =GS22+GT22+GU22+GV22 | GX22: =GM22+GR22+GW22 | GY22: 1.5419194e+08 | GZ22: 6518549.2 | HA22: =GY22+GZ22 | HB22: =IF(GX22=0,"",AU22/GX22) | HC22: =IF((GX22+GY22)=0,"",GB22/(GX22+GY22)) | HD22: =IF(GX22=0,"",GB22/GX22) | HE22: 44 | HF22: 1 | HG22: 833 | HH22: 44 | HI22: 44 | HJ22: =HF22+HI22 | HK22: =IF(HE22=0,"",HH22/HE22) | HL22: 18 | HM22: 30 | HN22: =IF(HL22=0,"",HM22/HL22)
A23: Liwonde | B23: Liwonde | C23: FY2025/26 | D23: 2025 | E23: 12 | F23: December | G23: Q3 | H23: 60265 | I23: 22047 | J23: 338 | K23: 313 | L23: 146 | M23: =SUM(I23,J23,K23,L23) | N23: 15879.7 | O23: 0 | P23: 2083.4 | Q23: 1766 | R23: =SUM(N23,O23,P23,Q23) | S23: =M23+R23 | T23: 17691.9 | U23: =IF(H23=0,"",T23/H23) | V23: 370 | W23: =IF(H23=0,"",V23/H23) | X23: 0 | Y23: =IF(H23=0,"",X23/H23) | Z23: 0 | AA23: =IF(H23=0,"",Z23/H23) | AB23: 522 | AC23: =IF(H23=0,"",AB23/H23) | AD23: 0 | AE23: =IF(H23=0,"",AD23/H23) | AF23: 0 | AG23: =IF(H23=0,"",AF23/H23) | AH23: 3249708.2 | AI23: =IF(H23=0,"",AH23/H23) | AJ23: 48883 | AK23: =IF(H23=0,"",AJ23/H23) | AL23: 8191476.7 | AM23: =IF(H23=0,"",AL23/H23) | AN23: 2672 | AO23: 351 | AP23: 1228500 | AQ23: 0 | AR23: 17248877 | AS23: 8030643 | AT23: 2000 | AU23: =AH23+AL23+AP23+AQ23+AR23+AS23+AT23 | AV23: =IF(H23=0,"",AU23/H23) | AW23: =IF(S23=0,"",AU23/S23) | AX23: 19 | AY23: =IF(H23=0,"",AX23/(H23/1000/12)) | AZ23: 60 | BA23: 833 | BB23: 19 | BC23: 32 | BD23: 7 | BE23: =BC23+BD23 | BF23: =BA23+BB23-BE23 | BG23: 0 | BH23: 0 | BI23: 0 | BJ23: 0 | BK23: =BI23+BJ23 | BL23: =BG23+BH23-BK23 | BM23: 0 | BN23: 0 | BO23: 0 | BP23: 0 | BQ23: =BO23+BP23 | BR23: =BM23+BN23-BQ23 | BS23: 0 | BT23: 0 | BU23: 0 | BV23: 0 | BW23: =BU23+BV23 | BX23: =BS23+BT23-BW23 | BY23: =BA23+BG23+BM23+BS23 | BZ23: =BB23+BH23+BN23+BT23 | CA23: =BE23+BK23+BQ23+BW23 | CB23: =BF23+BL23+BR23+BX23 | CC23: 7 | CD23: 1698 | CE23: 33 | CF23: 20 | CG23: 15 | CH23: =CD23+CE23+CF23+CG23 | CI23: 2587 | CJ23: 9 | CK23: 4 | CL23: 11 | CM23: =CI23+CJ23+CK23+CL23 | CN23: 1636 | CO23: 45 | CP23: 114 | CQ23: 1 | CR23: =CN23+CO23+CP23+CQ23 | CS23: =CM23+CR23 | CT23: 6173 | CU23: 42663.75 | CV23: 38397.38 | CW23: =IF(CU23=0,"",CV23/CU23) | DB23: =CX23+CY23-CZ23-DA23 | DC23: 0 | DD23: 0 | DE23: 0 | DF23: 0 | DG23: =DC23+DD23-DE23-DF23 | DH23: 0 | DI23: 0 | DJ23: 0 | DK23: 0 | DL23: =DH23+DI23-DJ23-DK23 | DM23: 339 | DN23: 10 | DO23: 4 | DP23: 3 | DQ23: =DM23+DN23-DO23-DP23 | DR23: =CX23+DC23+DH23+DM23 | DS23: =CY23+DD23+DI23+DN23 | DT23: =CZ23+DE23+DJ23+DO23 | DU23: =DA23+DF23+DK23+DP23 | DV23: =DB23+DG23+DL23+DQ23 | DW23: 71 | DX23: 29 | DY23: 5 | DZ23: 0 | EA23: 3 | EB23: 4 | EC23: 0 | ED23: 0 | EE23: 4 | EF23: 4 | EG23: 0 | EH23: 0 | EI23: 0 | EJ23: 0 | EK23: 0 | EL23: 0 | EM23: 0 | EN23: 0 | EO23: 0 | EP23: 0 | EQ23: 0 | ER23: 0 | ES23: 0 | ET23: 0 | EU23: 0 | EV23: 0 | EW23: 0 | EX23: 0 | EY23: 0 | EZ23: 0 | FA23: 0 | FB23: 0 | FC23: 0 | FD23: 0 | FE23: 0 | FF23: 0 | FG23: =SUM(DW23,DX23,DY23,DZ23,EA23,EB23,EC23,ED23,EE23,EF23,EG23,EH23,EI23,EJ23,EK23,EL23,EM23,EN23,EO23,EP23,EQ23,ER23,ES23,ET23,EU23,EV23,EW23,EX23,EY23,EZ23,FA23,FB23,FC23,FD23,FE23,FF23) | FH23: 0 | FI23: 20 | FJ23: 680 | FK23: 32 | FL23: 0 | FM23: 0 | FN23: 210 | FO23: 0 | FP23: 180 | FQ23: =FL23+FM23+FN23+FO23+FP23 | FR23: 27447376 | FS23: 142550 | FT23: 442340 | FU23: 48400 | FV23: =FR23+FS23+FT23+FU23 | FW23: 20590856 | FX23: 29200 | FY23: 9183650 | FZ23: 6262200 | GA23: =FW23+FX23+FY23+FZ23 | GB23: =FV23+GA23 | GC23: 20640652 | GD23: 64652.64 | GE23: 1029095.4 | GF23: 659676.34 | GG23: =GC23+GD23+GE23+GF23 | GH23: 19934967 | GI23: 15100 | GJ23: 6261000 | GK23: 8233600 | GL23: =GH23+GI23+GJ23+GK23 | GM23: =GG23+GL23 | GN23: 1377021.6 | GO23: 2104.08 | GP23: 30542.76 | GQ23: 18549.36 | GR23: =GN23+GO23+GP23+GQ23 | GS23: 2310191 | GT23: 9823 | GU23: 8037 | GV23: 3572 | GW23: =GS23+GT23+GU23+GV23 | GX23: =GM23+GR23+GW23 | GY23: 1.5277425e+08 | GZ23: 7741535.3 | HA23: =GY23+GZ23 | HB23: =IF(GX23=0,"",AU23/GX23) | HC23: =IF((GX23+GY23)=0,"",GB23/(GX23+GY23)) | HD23: =IF(GX23=0,"",GB23/GX23) | HE23: 19 | HF23: 1 | HG23: 813 | HH23: 19 | HI23: 30 | HJ23: =HF23+HI23 | HK23: =IF(HE23=0,"",HH23/HE23) | HL23: 15 | HM23: 30 | HN23: =IF(HL23=0,"",HM23/HL23)
A24: Liwonde | B24: Liwonde | C24: FY2025/26 | D24: 2026 | E24: 1 | F24: January | G24: Q4 | H24: 65878 | I24: 24213 | J24: 481 | K24: 279 | L24: 164 | M24: 25137 | N24: 17790 | O24: 10.6 | P24: 711.1 | Q24: 2669.2 | R24: 21180.9 | S24: 46317.9 | T24: 19560.1 | U24: 0.29691399 | V24: 384 | W24: 5.8289566 | X24: 0 | Y24: 0 | Z24: 0 | AA24: 0 | AB24: 709 | AC24: 10.762318 | AD24: 0 | AE24: 0 | AF24: 0 | AG24: 0 | AH24: 3995960 | AI24: 60.656971 | AJ24: 66276 | AK24: 1.0060415 | AL24: 11099195 | AM24: 168.48106 | AN24: 2732 | AO24: 120 | AP24: 420000 | AQ24: 0 | AR24: 0 | AS24: 6479315.9 | AT24: 7683365.9 | AU24: 29677837 | AV24: 450.49693 | AW24: 640.74228 | AX24: 26 | AY24: 12.234737 | AZ24: 60 | BA24: 813 | BB24: 33 | BC24: 28 | BD24: 0 | BE24: 28 | BF24: 818 | BG24: 0 | BH24: 0 | BI24: 0 | BJ24: 0 | BK24: 0 | BL24: 0 | BM24: 0 | BN24: 0 | BO24: 0 | BP24: 0 | BQ24: 0 | BR24: 0 | BS24: 0 | BT24: 0 | BU24: 0 | BV24: 0 | BW24: 0 | BX24: 0 | BY24: 813 | BZ24: 33 | CA24: 28 | CB24: 818 | CC24: 21 | CD24: 1689 | CE24: 33 | CF24: 20 | CG24: 15 | CH24: 1757 | CI24: 2623 | CJ24: 9 | CK24: 5 | CL24: 11 | CM24: 2648 | CN24: 1636 | CO24: 45 | CP24: 114 | CQ24: 1 | CR24: 1796 | CS24: 4444 | CT24: 6201 | CU24: 42877 | CV24: 38588 | CW24: 0.89996968 | CX24: 0 | CY24: 0 | CZ24: 0 | DA24: 0 | DB24: 0 | DC24: 0 | DD24: 0 | DE24: 0 | DF24: 0 | DG24: 0 | DH24: 0 | DI24: 0 | DJ24: 0 | DK24: 0 | DL24: 0 | DM24: 342 | DN24: 0 | DO24: 0 | DP24: 0 | DQ24: 342 | DR24: 342 | DS24: 0 | DT24: 0 | DU24: 0 | DV24: 342 | DW24: 70 | DX24: 32 | DY24: 16 | DZ24: 9 | EA24: 5 | EB24: 6 | EC24: 0 | ED24: 1 | EE24: 5 | EF24: 2 | EG24: 0 | EH24: 0 | EI24: 0 | EJ24: 0 | EK24: 0 | EL24: 0 | EM24: 0 | EN24: 0 | EO24: 0 | EP24: 0 | EQ24: 0 | ER24: 0 | ES24: 0 | ET24: 0 | EU24: 0 | EV24: 0 | EW24: 0 | EX24: 0 | EY24: 0 | EZ24: 0 | FA24: 0 | FB24: 0 | FC24: 0 | FD24: 0 | FE24: 0 | FF24: 0 | FG24: 146 | FH24: 0 | FI24: 47 | FJ24: 744 | FK24: 0 | FL24: 0 | FM24: 0 | FN24: 0 | FO24: 0 | FP24: 30 | FQ24: 30 | FR24: 26361814 | FS24: 161800 | FT24: 1290880 | FU24: 3095033.5 | FV24: 30909528 | FW24: 22981929 | FX24: 5600 | FY24: 12720637 | FZ24: 2173463.7 | GA24: 37881630 | GB24: 68791158 | GC24: 22361248 | GD24: 92005.68 | GE24: 912375.87 | GF24: 718880.03 | GG24: 24084510 | GH24: 22184431 | GI24: 2240 | GJ24: 2160885.5 | GK24: 12621697 | GL24: 36969254 | GM24: 61053764 | GN24: 1396803 | GO24: 2104.08 | GP24: 30542.76 | GQ24: 23186.7 | GR24: 1452636.5 | GS24: 2342339 | GT24: 9823 | GU24: 8037 | GV24: 4465 | GW24: 2364664 | GX24: 64871065 | GY24: 1.1077544e+08 | GZ24: 2520798.7 | HA24: 1.1329624e+08 | HB24: 64871065 | HC24: 1.1077544e+08 | HD24: 2520798.7 | HE24: 28 | HF24: 1 | HG24: 818 | HH24: 33 | HI24: 30 | HJ24: 0.90909091 | HK24: 3.4229829 | HL24: 13 | HM24: 30 | HN24: 0.43333333
A25: Liwonde | B25: Liwonde | C25: FY2025/26 | D25: 2026 | E25: 2 | F25: February | G25: Q4 | H25: 57839 | I25: 22432 | J25: 472 | K25: 394 | L25: 34 | M25: =SUM(I25,J25,K25,L25) | N25: 14953.5 | O25: 8.5 | P25: 567.9 | Q25: 1714.1 | R25: =SUM(N25,O25,P25,Q25) | S25: =M25+R25 | T25: 17263 | U25: =IF(H25=0,"",T25/H25) | V25: 308 | W25: =IF(H25=0,"",V25/H25) | X25: 25 | Y25: =IF(H25=0,"",X25/H25) | Z25: 0 | AA25: =IF(H25=0,"",Z25/H25) | AB25: 471 | AC25: =IF(H25=0,"",AB25/H25) | AD25: 0 | AE25: =IF(H25=0,"",AD25/H25) | AF25: 0 | AG25: =IF(H25=0,"",AF25/H25) | AH25: 2867577.4 | AI25: =IF(H25=0,"",AH25/H25) | AJ25: 64745.763 | AK25: =IF(H25=0,"",AJ25/H25) | AL25: 10843374 | AM25: =IF(H25=0,"",AL25/H25) | AN25: 1516 | AO25: 210 | AP25: 735000 | AQ25: 0 | AR25: 18768051 | AS25: 0 | AT25: 5351000 | AU25: =AH25+AL25+AP25+AQ25+AR25+AS25+AT25 | AV25: =IF(H25=0,"",AU25/H25) | AW25: =IF(S25=0,"",AU25/S25) | AX25: 26 | AY25: =IF(H25=0,"",AX25/(H25/1000/12)) | AZ25: 50 | BA25: 818 | BB25: 42 | BC25: 28 | BD25: 0 | BE25: =BC25+BD25 | BF25: =BA25+BB25-BE25 | BG25: 0 | BH25: 0 | BI25: 0 | BJ25: 0 | BK25: =BI25+BJ25 | BL25: =BG25+BH25-BK25 | BM25: 0 | BN25: 0 | BO25: 0 | BP25: 0 | BQ25: =BO25+BP25 | BR25: =BM25+BN25-BQ25 | BS25: 0 | BT25: 0 | BU25: 0 | BV25: 0 | BW25: =BU25+BV25 | BX25: =BS25+BT25-BW25 | BY25: =BA25+BG25+BM25+BS25 | BZ25: =BB25+BH25+BN25+BT25 | CA25: =BE25+BK25+BQ25+BW25 | CB25: =BF25+BL25+BR25+BX25 | CC25: 0 | CD25: 1690 | CE25: 33 | CF25: 20 | CG25: 15 | CH25: =CD25+CE25+CF25+CG25 | CI25: 2650 | CJ25: 9 | CK25: 5 | CL25: 11 | CM25: =CI25+CJ25+CK25+CL25 | CN25: 1636 | CO25: 45 | CP25: 114 | CQ25: 1 | CR25: =CN25+CO25+CP25+CQ25 | CS25: =CM25+CR25 | CT25: 6229 | CU25: 43305.77 | CV25: 38973.88 | CW25: =IF(CU25=0,"",CV25/CU25) | DB25: =CX25+CY25-CZ25-DA25 | DC25: 0 | DD25: 0 | DE25: 0 | DF25: 0 | DG25: =DC25+DD25-DE25-DF25 | DH25: 0 | DI25: 0 | DJ25: 0 | DK25: 0 | DL25: =DH25+DI25-DJ25-DK25 | DM25: 342 | DN25: 0 | DO25: 0 | DP25: 0 | DQ25: =DM25+DN25-DO25-DP25 | DR25: =CX25+DC25+DH25+DM25 | DS25: =CY25+DD25+DI25+DN25 | DT25: =CZ25+DE25+DJ25+DO25 | DU25: =DA25+DF25+DK25+DP25 | DV25: =DB25+DG25+DL25+DQ25 | DW25: 73 | DX25: 29 | DY25: 10 | DZ25: 2 | EA25: 7 | EB25: 3 | EC25: 0 | ED25: 2 | EE25: 3 | EF25: 0 | EG25: 0 | EH25: 0 | EI25: 0 | EJ25: 0 | EK25: 0 | EL25: 0 | EM25: 0 | EN25: 0 | EO25: 0 | EP25: 0 | EQ25: 0 | ER25: 0 | ES25: 0 | ET25: 0 | EU25: 0 | EV25: 0 | EW25: 0 | EX25: 0 | EY25: 0 | EZ25: 0 | FA25: 0 | FB25: 0 | FC25: 0 | FD25: 0 | FE25: 0 | FF25: 0 | FG25: =SUM(DW25,DX25,DY25,DZ25,EA25,EB25,EC25,ED25,EE25,EF25,EG25,EH25,EI25,EJ25,EK25,EL25,EM25,EN25,EO25,EP25,EQ25,ER25,ES25,ET25,EU25,EV25,EW25,EX25,EY25,EZ25,FA25,FB25,FC25,FD25,FE25,FF25) | FH25: 0 | FI25: 22 | FJ25: 608 | FK25: 40 | FL25: 0 | FM25: 0 | FN25: 0 | FO25: 360 | FP25: 310 | FQ25: =FL25+FM25+FN25+FO25+FP25 | FR25: 23361898 | FS25: 79178 | FT25: 1004540 | FU25: 123000 | FV25: =FR25+FS25+FT25+FU25 | FW25: 20364655 | FX25: 4500 | FY25: 8409408.4 | FZ25: 1812394 | GA25: =FW25+FX25+FY25+FZ25 | GB25: =FV25+GA25 | GC25: 21051798 | GD25: 90284.16 | GE25: 1313750.2 | GF25: 105840.39 | GG25: =GC25+GD25+GE25+GF25 | GH25: 18655880 | GI25: 1800 | GJ25: 1725754 | GK25: 8097075 | GL25: =GH25+GI25+GJ25+GK25 | GM25: =GG25+GL25 | GN25: 1411352.2 | GO25: 2104.08 | GP25: 30542.76 | GQ25: 23186.7 | GR25: =GN25+GO25+GP25+GQ25 | GS25: 2366450 | GT25: 9823 | GU25: 8037 | GV25: 4465 | GW25: =GS25+GT25+GU25+GV25 | GX25: =GM25+GR25+GW25 | GY25: 1.1129833e+08 | GZ25: 4181108.3 | HA25: =GY25+GZ25 | HB25: =IF(GX25=0,"",AU25/GX25) | HC25: =IF((GX25+GY25)=0,"",GB25/(GX25+GY25)) | HD25: =IF(GX25=0,"",GB25/GX25) | HE25: 42 | HF25: 1 | HG25: 832 | HH25: 42 | HI25: 30 | HJ25: =HF25+HI25 | HK25: =IF(HE25=0,"",HH25/HE25) | HL25: 10 | HM25: 30 | HN25: =IF(HL25=0,"",HM25/HL25)
A26: Liwonde | B26: Liwonde | C26: FY2025/26 | D26: 2026 | E26: 3 | F26: March | G26: Q4 | H26: 62352 | I26: 23896 | J26: 413 | K26: 259 | L26: 34 | M26: =SUM(I26,J26,K26,L26) | N26: 15442.6 | O26: 17.1 | P26: 1051.7 | Q26: 1905.1 | R26: =SUM(N26,O26,P26,Q26) | S26: =M26+R26 | T26: 19333.5 | U26: =IF(H26=0,"",T26/H26) | V26: 372 | W26: =IF(H26=0,"",V26/H26) | X26: 985 | Y26: =IF(H26=0,"",X26/H26) | Z26: 0 | AA26: =IF(H26=0,"",Z26/H26) | AB26: 0 | AC26: =IF(H26=0,"",AB26/H26) | AD26: 0 | AE26: =IF(H26=0,"",AD26/H26) | AF26: 0 | AG26: =IF(H26=0,"",AF26/H26) | AH26: 2355517.9 | AI26: =IF(H26=0,"",AH26/H26) | AJ26: 55635 | AK26: =IF(H26=0,"",AJ26/H26) | AL26: 19339 | AM26: =IF(H26=0,"",AL26/H26) | AN26: 2029 | AO26: 240 | AP26: 840000 | AQ26: 0 | AR26: 17418536 | AS26: 6951595.8 | AT26: 1754000 | AU26: =AH26+AL26+AP26+AQ26+AR26+AS26+AT26 | AV26: =IF(H26=0,"",AU26/H26) | AW26: =IF(S26=0,"",AU26/S26) | AX26: 26 | AY26: =IF(H26=0,"",AX26/(H26/1000/12)) | AZ26: 50 | BA26: 832 | BB26: 51 | BC26: 24 | BD26: 2 | BE26: =BC26+BD26 | BF26: =BA26+BB26-BE26 | BG26: 0 | BH26: 0 | BI26: 0 | BJ26: 0 | BK26: =BI26+BJ26 | BL26: =BG26+BH26-BK26 | BM26: 0 | BN26: 0 | BO26: 0 | BP26: 0 | BQ26: =BO26+BP26 | BR26: =BM26+BN26-BQ26 | BS26: 0 | BT26: 0 | BU26: 0 | BV26: 0 | BW26: =BU26+BV26 | BX26: =BS26+BT26-BW26 | BY26: =BA26+BG26+BM26+BS26 | BZ26: =BB26+BH26+BN26+BT26 | CA26: =BE26+BK26+BQ26+BW26 | CB26: =BF26+BL26+BR26+BX26 | CC26: 2 | CD26: 1684 | CE26: 33 | CF26: 20 | CG26: 15 | CH26: =CD26+CE26+CF26+CG26 | CI26: 2677 | CJ26: 9 | CK26: 8 | CL26: 11 | CM26: =CI26+CJ26+CK26+CL26 | CN26: 1636 | CO26: 45 | CP26: 114 | CQ26: 1 | CR26: =CN26+CO26+CP26+CQ26 | CS26: =CM26+CR26 | CT26: 6253 | CU26: 43739 | CV26: 39363 | CW26: =IF(CU26=0,"",CV26/CU26) | DB26: =CX26+CY26-CZ26-DA26 | DC26: 0 | DD26: 0 | DE26: 0 | DF26: 0 | DG26: =DC26+DD26-DE26-DF26 | DH26: 0 | DI26: 0 | DJ26: 0 | DK26: 0 | DL26: =DH26+DI26-DJ26-DK26 | DM26: 342 | DN26: 0 | DO26: 0 | DP26: 0 | DQ26: =DM26+DN26-DO26-DP26 | DR26: =CX26+DC26+DH26+DM26 | DS26: =CY26+DD26+DI26+DN26 | DT26: =CZ26+DE26+DJ26+DO26 | DU26: =DA26+DF26+DK26+DP26 | DV26: =DB26+DG26+DL26+DQ26 | DW26: 40 | DX26: 12 | DY26: 8 | DZ26: 3 | EA26: 5 | EB26: 3 | EC26: 0 | ED26: 1 | EE26: 5 | EF26: 1 | EG26: 0 | EH26: 0 | EI26: 0 | EJ26: 0 | EK26: 0 | EL26: 0 | EM26: 0 | EN26: 0 | EO26: 0 | EP26: 0 | EQ26: 0 | ER26: 0 | ES26: 0 | ET26: 0 | EU26: 0 | EV26: 0 | EW26: 0 | EX26: 0 | EY26: 0 | EZ26: 0 | FA26: 0 | FB26: 0 | FC26: 0 | FD26: 0 | FE26: 0 | FF26: 0 | FG26: =SUM(DW26,DX26,DY26,DZ26,EA26,EB26,EC26,ED26,EE26,EF26,EG26,EH26,EI26,EJ26,EK26,EL26,EM26,EN26,EO26,EP26,EQ26,ER26,ES26,ET26,EU26,EV26,EW26,EX26,EY26,EZ26,FA26,FB26,FC26,FD26,FE26,FF26) | FH26: 0 | FI26: 0 | FJ26: 744 | FK26: 12 | FL26: 30 | FM26: 0 | FN26: 122 | FO26: 0 | FP26: 0 | FQ26: =FL26+FM26+FN26+FO26+FP26 | FR26: 30088422 | FS26: 95121 | FT26: 402940 | FU26: 254600 | FV26: =FR26+FS26+FT26+FU26 | FW26: 21755861 | FX26: 9000 | FY26: 9967207.1 | FZ26: 3254854 | GA26: =FW26+FX26+FY26+FZ26 | GB26: =FV26+GA26 | GC26: 22589534 | GD26: 78998.64 | GE26: 858634.86 | GF26: 138555.62 | GG26: =GC26+GD26+GE26+GF26 | GH26: 19271306 | GI26: 3600 | GJ26: 3198022.9 | GK26: 9007103.2 | GL26: =GH26+GI26+GJ26+GK26 | GM26: =GG26+GL26 | GN26: 1425840.5 | GO26: 2104.08 | GP26: 30542.76 | GQ26: 37098.72 | GR26: =GN26+GO26+GP26+GQ26 | GS26: 2390561 | GT26: 9823 | GU26: 8037 | GV26: 7144 | GW26: =GS26+GT26+GU26+GV26 | GX26: =GM26+GR26+GW26 | GY26: 1.0332666e+08 | GZ26: 3135234.7 | HA26: =GY26+GZ26 | HB26: =IF(GX26=0,"",AU26/GX26) | HC26: =IF((GX26+GY26)=0,"",GB26/(GX26+GY26)) | HD26: =IF(GX26=0,"",GB26/GX26) | HE26: 51 | HF26: 1 | HG26: 857 | HH26: 51 | HI26: 30 | HJ26: =HF26+HI26 | HK26: =IF(HE26=0,"",HH26/HE26) | HL26: 17 | HM26: 30 | HN26: =IF(HL26=0,"",HM26/HL26)
A27: Liwonde | B27: Machinga | C27: FY2025/26 | D27: 2025 | E27: 4 | F27: April | G27: Q1 | H27: 1641 | I27: 69 | J27: 0 | K27: 32 | L27: 0 | M27: =SUM(I27,J27,K27,L27) | N27: 1274.8 | O27: 0 | P27: 2 | Q27: 16.9 | R27: =SUM(N27,O27,P27,Q27) | S27: =M27+R27 | T27: 246.3 | U27: =IF(H27=0,"",T27/H27) | V27: 9 | W27: =IF(H27=0,"",V27/H27) | X27: 0 | Y27: =IF(H27=0,"",X27/H27) | Z27: 0 | AA27: =IF(H27=0,"",Z27/H27) | AB27: 0 | AC27: =IF(H27=0,"",AB27/H27) | AD27: 0 | AE27: =IF(H27=0,"",AD27/H27) | AF27: 0 | AG27: =IF(H27=0,"",AF27/H27) | AH27: 31727.61 | AI27: =IF(H27=0,"",AH27/H27) | AJ27: 760 | AK27: =IF(H27=0,"",AJ27/H27) | AL27: 146393.9 | AM27: =IF(H27=0,"",AL27/H27) | AN27: 0 | AO27: 0 | AP27: 0 | AQ27: 0 | AR27: 718108.71 | AS27: 720000.32 | AT27: 596480 | AU27: =AH27+AL27+AP27+AQ27+AR27+AS27+AT27 | AV27: =IF(H27=0,"",AU27/H27) | AW27: =IF(S27=0,"",AU27/S27) | AX27: 3 | AY27: =IF(H27=0,"",AX27/(H27/1000/12)) | AZ27: 8 | BA27: 2 | BB27: 2 | BC27: 0 | BD27: 2 | BE27: =BC27+BD27 | BF27: =BA27+BB27-BE27 | BG27: 0 | BH27: 0 | BI27: 0 | BJ27: 0 | BK27: =BI27+BJ27 | BL27: =BG27+BH27-BK27 | BM27: 0 | BN27: 0 | BO27: 0 | BP27: 0 | BQ27: =BO27+BP27 | BR27: =BM27+BN27-BQ27 | BS27: 0 | BT27: 0 | BU27: 0 | BV27: 0 | BW27: =BU27+BV27 | BX27: =BS27+BT27-BW27 | BY27: =BA27+BG27+BM27+BS27 | BZ27: =BB27+BH27+BN27+BT27 | CA27: =BE27+BK27+BQ27+BW27 | CB27: =BF27+BL27+BR27+BX27 | CC27: 12 | CD27: 0 | CE27: 0 | CF27: 0 | CG27: 0 | CH27: =CD27+CE27+CF27+CG27 | CI27: 12 | CJ27: 1 | CK27: 0 | CL27: 0 | CM27: =CI27+CJ27+CK27+CL27 | CN27: 376 | CO27: 3 | CP27: 6 | CQ27: 0 | CR27: =CN27+CO27+CP27+CQ27 | CS27: =CM27+CR27 | CT27: 398 | CU27: 1420 | CV27: 1065 | CW27: =IF(CU27=0,"",CV27/CU27) | DB27: =CX27+CY27-CZ27-DA27 | DC27: 0 | DD27: 0 | DE27: 0 | DF27: 0 | DG27: =DC27+DD27-DE27-DF27 | DH27: 0 | DI27: 0 | DJ27: 0 | DK27: 0 | DL27: =DH27+DI27-DJ27-DK27 | DM27: 0 | DN27: 0 | DO27: 0 | DP27: 0 | DQ27: =DM27+DN27-DO27-DP27 | DR27: =CX27+DC27+DH27+DM27 | DS27: =CY27+DD27+DI27+DN27 | DT27: =CZ27+DE27+DJ27+DO27 | DU27: =DA27+DF27+DK27+DP27 | DV27: =DB27+DG27+DL27+DQ27 | DW27: 13 | DX27: 8 | DY27: 9 | DZ27: 3 | EA27: 2 | EB27: 4 | EC27: 0 | ED27: 2 | EE27: 1 | EF27: 0 | EG27: 0 | EH27: 0 | EI27: 0 | EJ27: 3 | EK27: 1 | EL27: 0 | EM27: 0 | EN27: 2 | EO27: 0 | EP27: 0 | EQ27: 0 | ER27: 0 | ES27: 0 | ET27: 0 | EU27: 0 | EV27: 0 | EW27: 0 | EX27: 0 | EY27: 0 | EZ27: 0 | FA27: 0 | FB27: 0 | FC27: 0 | FD27: 0 | FE27: 0 | FF27: 0 | FG27: =SUM(DW27,DX27,DY27,DZ27,EA27,EB27,EC27,ED27,EE27,EF27,EG27,EH27,EI27,EJ27,EK27,EL27,EM27,EN27,EO27,EP27,EQ27,ER27,ES27,ET27,EU27,EV27,EW27,EX27,EY27,EZ27,FA27,FB27,FC27,FD27,FE27,FF27) | FH27: 1 | FI27: 0 | FJ27: 0 | FK27: 39 | FL27: 0 | FM27: 0 | FN27: 0 | FO27: 0 | FP27: 0 | FQ27: =FL27+FM27+FN27+FO27+FP27 | FR27: 49800 | FS27: 0 | FT27: 0 | FU27: 0 | FV27: =FR27+FS27+FT27+FU27 | FW27: 2505983 | FX27: 0 | FY27: 80000 | FZ27: 8000 | GA27: =FW27+FX27+FY27+FZ27 | GB27: =FV27+GA27 | GC27: 66118.59 | GD27: 0 | GE27: 98236.19 | GF27: 0 | GG27: =GC27+GD27+GE27+GF27 | GH27: 1597739 | GI27: 0 | GJ27: 6200 | GK27: 80000 | GL27: =GH27+GI27+GJ27+GK27 | GM27: =GG27+GL27 | GN27: 6661.18 | GO27: 0 | GP27: 3393.64 | GQ27: 0 | GR27: =GN27+GO27+GP27+GQ27 | GS27: 10716 | GT27: 0 | GU27: 893 | GV27: 0 | GW27: =GS27+GT27+GU27+GV27 | GX27: =GM27+GR27+GW27 | GY27: 18501501 | GZ27: 1096483 | HA27: =GY27+GZ27 | HB27: =IF(GX27=0,"",AU27/GX27) | HC27: =IF((GX27+GY27)=0,"",GB27/(GX27+GY27)) | HD27: =IF(GX27=0,"",GB27/GX27) | HE27: 2 | HF27: 1 | HG27: 2 | HH27: 2 | HI27: 15 | HJ27: =HF27+HI27 | HK27: =IF(HE27=0,"",HH27/HE27) | HL27: 23 | HM27: 2 | HN27: =IF(HL27=0,"",HM27/HL27)
A28: Liwonde | B28: Machinga | C28: FY2025/26 | D28: 2025 | E28: 5 | F28: May | G28: Q1 | H28: 1921 | I28: 16 | J28: 0 | K28: 10 | L28: 0 | M28: =SUM(I28,J28,K28,L28) | N28: 1352.9 | O28: 0 | P28: 13 | Q28: 0 | R28: =SUM(N28,O28,P28,Q28) | S28: =M28+R28 | T28: 529.1 | U28: =IF(H28=0,"",T28/H28) | V28: 11 | W28: =IF(H28=0,"",V28/H28) | X28: 0 | Y28: =IF(H28=0,"",X28/H28) | Z28: 0 | AA28: =IF(H28=0,"",Z28/H28) | AB28: 0 | AC28: =IF(H28=0,"",AB28/H28) | AD28: 0 | AE28: =IF(H28=0,"",AD28/H28) | AF28: 0 | AG28: =IF(H28=0,"",AF28/H28) | AH28: 38778.19 | AI28: =IF(H28=0,"",AH28/H28) | AJ28: 2306.8051 | AK28: =IF(H28=0,"",AJ28/H28) | AL28: 404984.9 | AM28: =IF(H28=0,"",AL28/H28) | AN28: 0 | AO28: 0 | AP28: 0 | AQ28: 0 | AR28: 718108.71 | AS28: 720000.32 | AT28: 293286.24 | AU28: =AH28+AL28+AP28+AQ28+AR28+AS28+AT28 | AV28: =IF(H28=0,"",AU28/H28) | AW28: =IF(S28=0,"",AU28/S28) | AX28: 3 | AY28: =IF(H28=0,"",AX28/(H28/1000/12)) | AZ28: 8 | BA28: 2 | BB28: 3 | BC28: 0 | BD28: 0 | BE28: =BC28+BD28 | BF28: =BA28+BB28-BE28 | BG28: 0 | BH28: 0 | BI28: 0 | BJ28: 0 | BK28: =BI28+BJ28 | BL28: =BG28+BH28-BK28 | BM28: 0 | BN28: 0 | BO28: 0 | BP28: 0 | BQ28: =BO28+BP28 | BR28: =BM28+BN28-BQ28 | BS28: 0 | BT28: 0 | BU28: 0 | BV28: 0 | BW28: =BU28+BV28 | BX28: =BS28+BT28-BW28 | BY28: =BA28+BG28+BM28+BS28 | BZ28: =BB28+BH28+BN28+BT28 | CA28: =BE28+BK28+BQ28+BW28 | CB28: =BF28+BL28+BR28+BX28 | CC28: 0 | CD28: 0 | CE28: 0 | CF28: 0 | CG28: 0 | CH28: =CD28+CE28+CF28+CG28 | CI28: 2 | CJ28: 1 | CK28: 0 | CL28: 0 | CM28: =CI28+CJ28+CK28+CL28 | CN28: 376 | CO28: 3 | CP28: 6 | CQ28: 0 | CR28: =CN28+CO28+CP28+CQ28 | CS28: =CM28+CR28 | CT28: 388 | CU28: 1425 | CV28: 1065 | CW28: =IF(CU28=0,"",CV28/CU28) | DB28: =CX28+CY28-CZ28-DA28 | DC28: 0 | DD28: 0 | DE28: 0 | DF28: 0 | DG28: =DC28+DD28-DE28-DF28 | DH28: 0 | DI28: 0 | DJ28: 0 | DK28: 0 | DL28: =DH28+DI28-DJ28-DK28 | DM28: 0 | DN28: 0 | DO28: 0 | DP28: 0 | DQ28: =DM28+DN28-DO28-DP28 | DR28: =CX28+DC28+DH28+DM28 | DS28: =CY28+DD28+DI28+DN28 | DT28: =CZ28+DE28+DJ28+DO28 | DU28: =DA28+DF28+DK28+DP28 | DV28: =DB28+DG28+DL28+DQ28 | DW28: 15 | DX28: 8 | DY28: 13 | DZ28: 6 | EA28: 3 | EB28: 3 | EC28: 0 | ED28: 2 | EE28: 0 | EF28: 0 | EG28: 0 | EH28: 0 | EI28: 0 | EJ28: 1 | EK28: 0 | EL28: 0 | EM28: 0 | EN28: 3 | EO28: 0 | EP28: 0 | EQ28: 0 | ER28: 0 | ES28: 0 | ET28: 0 | EU28: 0 | EV28: 0 | EW28: 0 | EX28: 0 | EY28: 0 | EZ28: 0 | FA28: 0 | FB28: 0 | FC28: 0 | FD28: 0 | FE28: 0 | FF28: 0 | FG28: =SUM(DW28,DX28,DY28,DZ28,EA28,EB28,EC28,ED28,EE28,EF28,EG28,EH28,EI28,EJ28,EK28,EL28,EM28,EN28,EO28,EP28,EQ28,ER28,ES28,ET28,EU28,EV28,EW28,EX28,EY28,EZ28,FA28,FB28,FC28,FD28,FE28,FF28) | FH28: 1 | FI28: 0 | FJ28: 0 | FK28: 50 | FL28: 0 | FM28: 0 | FN28: 0 | FO28: 0 | FP28: 0 | FQ28: =FL28+FM28+FN28+FO28+FP28 | FR28: 124800 | FS28: 0 | FT28: 0 | FU28: 0 | FV28: =FR28+FS28+FT28+FU28 | FW28: 2316627 | FX28: 0 | FY28: 15000 | FZ28: 40000 | GA28: =FW28+FX28+FY28+FZ28 | GB28: =FV28+GA28 | GC28: 13718.12 | GD28: 0 | GE28: 24383.95 | GF28: 0 | GG28: =GC28+GD28+GE28+GF28 | GH28: 1711548.3 | GI28: 0 | GJ28: 39774.41 | GK28: 15000 | GL28: =GH28+GI28+GJ28+GK28 | GM28: =GG28+GL28 | GN28: 1089.86 | GO28: 0 | GP28: 3393.64 | GQ28: 0 | GR28: =GN28+GO28+GP28+GQ28 | GS28: 1786 | GT28: 0 | GU28: 893 | GV28: 0 | GW28: =GS28+GT28+GU28+GV28 | GX28: =GM28+GR28+GW28 | GY28: 18386758 | GZ28: 1131691.2 | HA28: =GY28+GZ28 | HB28: =IF(GX28=0,"",AU28/GX28) | HC28: =IF((GX28+GY28)=0,"",GB28/(GX28+GY28)) | HD28: =IF(GX28=0,"",GB28/GX28) | HE28: 3 | HF28: 1 | HG28: 5 | HH28: 3 | HI28: 15 | HJ28: =HF28+HI28 | HK28: =IF(HE28=0,"",HH28/HE28) | HL28: 16 | HM28: 4 | HN28: =IF(HL28=0,"",HM28/HL28)
A29: Liwonde | B29: Machinga | C29: FY2025/26 | D29: 2025 | E29: 6 | F29: June | G29: Q1 | H29: 1922 | I29: 33 | J29: 0 | K29: 13 | L29: 0 | M29: =SUM(I29,J29,K29,L29) | N29: 1498 | O29: 0 | P29: 2.3 | Q29: 4.2 | R29: =SUM(N29,O29,P29,Q29) | S29: =M29+R29 | T29: 371.5 | U29: =IF(H29=0,"",T29/H29) | V29: 7 | W29: =IF(H29=0,"",V29/H29) | X29: 0 | Y29: =IF(H29=0,"",X29/H29) | Z29: 0 | AA29: =IF(H29=0,"",Z29/H29) | AB29: 0 | AC29: =IF(H29=0,"",AB29/H29) | AD29: 0 | AE29: =IF(H29=0,"",AD29/H29) | AF29: 0 | AG29: =IF(H29=0,"",AF29/H29) | AH29: 24677.03 | AI29: =IF(H29=0,"",AH29/H29) | AJ29: 4000 | AK29: =IF(H29=0,"",AJ29/H29) | AL29: 688049 | AM29: =IF(H29=0,"",AL29/H29) | AN29: 0 | AO29: 0 | AP29: 0 | AQ29: 0 | AR29: 712768.63 | AS29: 1008001.3 | AT29: 0 | AU29: =AH29+AL29+AP29+AQ29+AR29+AS29+AT29 | AV29: =IF(H29=0,"",AU29/H29) | AW29: =IF(S29=0,"",AU29/S29) | AX29: 3 | AY29: =IF(H29=0,"",AX29/(H29/1000/12)) | AZ29: 8 | BA29: 5 | BB29: 5 | BC29: 0 | BD29: 4 | BE29: =BC29+BD29 | BF29: =BA29+BB29-BE29 | BG29: 0 | BH29: 0 | BI29: 0 | BJ29: 0 | BK29: =BI29+BJ29 | BL29: =BG29+BH29-BK29 | BM29: 0 | BN29: 0 | BO29: 0 | BP29: 0 | BQ29: =BO29+BP29 | BR29: =BM29+BN29-BQ29 | BS29: 0 | BT29: 0 | BU29: 0 | BV29: 0 | BW29: =BU29+BV29 | BX29: =BS29+BT29-BW29 | BY29: =BA29+BG29+BM29+BS29 | BZ29: =BB29+BH29+BN29+BT29 | CA29: =BE29+BK29+BQ29+BW29 | CB29: =BF29+BL29+BR29+BX29 | CC29: 8 | CD29: 223 | CE29: 0 | CF29: 0 | CG29: 0 | CH29: =CD29+CE29+CF29+CG29 | CI29: 33 | CJ29: 13 | CK29: 0 | CL29: 0 | CM29: =CI29+CJ29+CK29+CL29 | CN29: 376 | CO29: 2.3 | CP29: 4.2 | CQ29: 0 | CR29: =CN29+CO29+CP29+CQ29 | CS29: =CM29+CR29 | CT29: 651.5 | CU29: 1428 | CV29: 999.6 | CW29: =IF(CU29=0,"",CV29/CU29) | DB29: =CX29+CY29-CZ29-DA29 | DC29: 0 | DD29: 0 | DE29: 0 | DF29: 0 | DG29: =DC29+DD29-DE29-DF29 | DH29: 0 | DI29: 0 | DJ29: 0 | DK29: 0 | DL29: =DH29+DI29-DJ29-DK29 | DM29: 0 | DN29: 0 | DO29: 0 | DP29: 0 | DQ29: =DM29+DN29-DO29-DP29 | DR29: =CX29+DC29+DH29+DM29 | DS29: =CY29+DD29+DI29+DN29 | DT29: =CZ29+DE29+DJ29+DO29 | DU29: =DA29+DF29+DK29+DP29 | DV29: =DB29+DG29+DL29+DQ29 | DW29: 16 | DX29: 11 | DY29: 6 | DZ29: 4 | EA29: 3 | EB29: 2 | EC29: 0 | ED29: 1 | EE29: 0 | EF29: 0 | EG29: 0 | EH29: 0 | EI29: 0 | EJ29: 3 | EK29: 2 | EL29: 0 | EM29: 0 | EN29: 2 | EO29: 0 | EP29: 0 | EQ29: 0 | ER29: 0 | ES29: 0 | ET29: 0 | EU29: 0 | EV29: 0 | EW29: 0 | EX29: 0 | EY29: 0 | EZ29: 0 | FA29: 0 | FB29: 0 | FC29: 0 | FD29: 0 | FE29: 0 | FF29: 0 | FG29: =SUM(DW29,DX29,DY29,DZ29,EA29,EB29,EC29,ED29,EE29,EF29,EG29,EH29,EI29,EJ29,EK29,EL29,EM29,EN29,EO29,EP29,EQ29,ER29,ES29,ET29,EU29,EV29,EW29,EX29,EY29,EZ29,FA29,FB29,FC29,FD29,FE29,FF29) | FH29: 1 | FI29: 0 | FJ29: 0 | FK29: 36 | FL29: 0 | FM29: 0 | FN29: 0 | FO29: 0 | FP29: 0 | FQ29: =FL29+FM29+FN29+FO29+FP29 | FR29: 178250 | FS29: 0 | FT29: 0 | FU29: 0 | FV29: =FR29+FS29+FT29+FU29 | FW29: 2315477.1 | FX29: 0 | FY29: 20000 | FZ29: 6800 | GA29: =FW29+FX29+FY29+FZ29 | GB29: =FV29+GA29 | GC29: 31400.7 | GD29: 0 | GE29: 33408.7 | GF29: 0 | GG29: =GC29+GD29+GE29+GF29 | GH29: 1882430.4 | GI29: 0 | GJ29: 6800 | GK29: 20000 | GL29: =GH29+GI29+GJ29+GK29 | GM29: =GG29+GL29 | GN29: 1859.65 | GO29: 0 | GP29: 3393.64 | GQ29: 0 | GR29: =GN29+GO29+GP29+GQ29 | GS29: 2679 | GT29: 0 | GU29: 893 | GV29: 0 | GW29: =GS29+GT29+GU29+GV29 | GX29: =GM29+GR29+GW29 | GY29: 17886442 | GZ29: 244132.86 | HA29: =GY29+GZ29 | HB29: =IF(GX29=0,"",AU29/GX29) | HC29: =IF((GX29+GY29)=0,"",GB29/(GX29+GY29)) | HD29: =IF(GX29=0,"",GB29/GX29) | HE29: 5 | HF29: 1 | HG29: 6 | HH29: 5 | HI29: 15 | HJ29: =HF29+HI29 | HK29: =IF(HE29=0,"",HH29/HE29) | HL29: 9 | HM29: 2 | HN29: =IF(HL29=0,"",HM29/HL29)
A30: Liwonde | B30: Machinga | C30: FY2025/26 | D30: 2025 | E30: 7 | F30: July | G30: Q2 | H30: 2216 | I30: 43 | J30: 0 | K30: 8 | L30: 0 | M30: =SUM(I30,J30,K30,L30) | N30: 1615.1 | O30: 0 | P30: 338.8 | Q30: 4.1 | R30: =SUM(N30,O30,P30,Q30) | S30: =M30+R30 | T30: 207 | U30: =IF(H30=0,"",T30/H30) | V30: 8 | W30: =IF(H30=0,"",V30/H30) | X30: 0 | Y30: =IF(H30=0,"",X30/H30) | Z30: 0 | AA30: =IF(H30=0,"",Z30/H30) | AB30: 0 | AC30: =IF(H30=0,"",AB30/H30) | AD30: 0 | AE30: =IF(H30=0,"",AD30/H30) | AF30: 0 | AG30: =IF(H30=0,"",AF30/H30) | AH30: 28202.32 | AI30: =IF(H30=0,"",AH30/H30) | AJ30: 2400 | AK30: =IF(H30=0,"",AJ30/H30) | AL30: 420565 | AM30: =IF(H30=0,"",AL30/H30) | AN30: 0 | AO30: 0 | AP30: 0 | AQ30: 0 | AR30: 712768.63 | AS30: 1008001.3 | AT30: 0 | AU30: =AH30+AL30+AP30+AQ30+AR30+AS30+AT30 | AV30: =IF(H30=0,"",AU30/H30) | AW30: =IF(S30=0,"",AU30/S30) | AX30: 3 | AY30: =IF(H30=0,"",AX30/(H30/1000/12)) | AZ30: 8 | BA30: 6 | BB30: 3 | BC30: 0 | BD30: 3 | BE30: =BC30+BD30 | BF30: =BA30+BB30-BE30 | BG30: 0 | BH30: 0 | BI30: 0 | BJ30: 0 | BK30: =BI30+BJ30 | BL30: =BG30+BH30-BK30 | BM30: 0 | BN30: 0 | BO30: 0 | BP30: 0 | BQ30: =BO30+BP30 | BR30: =BM30+BN30-BQ30 | BS30: 0 | BT30: 0 | BU30: 0 | BV30: 0 | BW30: =BU30+BV30 | BX30: =BS30+BT30-BW30 | BY30: =BA30+BG30+BM30+BS30 | BZ30: =BB30+BH30+BN30+BT30 | CA30: =BE30+BK30+BQ30+BW30 | CB30: =BF30+BL30+BR30+BX30 | CC30: 3 | CD30: 223 | CE30: 0 | CF30: 0 | CG30: 0 | CH30: =CD30+CE30+CF30+CG30 | CI30: 43 | CJ30: 8 | CK30: 0 | CL30: 0 | CM30: =CI30+CJ30+CK30+CL30 | CN30: 376 | CO30: 2 | CP30: 4.1 | CQ30: 0 | CR30: =CN30+CO30+CP30+CQ30 | CS30: =CM30+CR30 | CT30: 656.1 | CU30: 1453 | CV30: 1241 | CW30: =IF(CU30=0,"",CV30/CU30) | DB30: =CX30+CY30-CZ30-DA30 | DC30: 0 | DD30: 0 | DE30: 0 | DF30: 0 | DG30: =DC30+DD30-DE30-DF30 | DH30: 0 | DI30: 0 | DJ30: 0 | DK30: 0 | DL30: =DH30+DI30-DJ30-DK30 | DM30: 0 | DN30: 0 | DO30: 0 | DP30: 0 | DQ30: =DM30+DN30-DO30-DP30 | DR30: =CX30+DC30+DH30+DM30 | DS30: =CY30+DD30+DI30+DN30 | DT30: =CZ30+DE30+DJ30+DO30 | DU30: =DA30+DF30+DK30+DP30 | DV30: =DB30+DG30+DL30+DQ30 | DW30: 12 | DX30: 10 | DY30: 7 | DZ30: 4 | EA30: 5 | EB30: 3 | EC30: 0 | ED30: 2 | EE30: 1 | EF30: 0 | EG30: 0 | EH30: 0 | EI30: 0 | EJ30: 2 | EK30: 1 | EL30: 0 | EM30: 0 | EN30: 2 | EO30: 0 | EP30: 0 | EQ30: 0 | ER30: 0 | ES30: 0 | ET30: 0 | EU30: 0 | EV30: 0 | EW30: 0 | EX30: 0 | EY30: 0 | EZ30: 0 | FA30: 0 | FB30: 0 | FC30: 0 | FD30: 0 | FE30: 0 | FF30: 0 | FG30: =SUM(DW30,DX30,DY30,DZ30,EA30,EB30,EC30,ED30,EE30,EF30,EG30,EH30,EI30,EJ30,EK30,EL30,EM30,EN30,EO30,EP30,EQ30,ER30,ES30,ET30,EU30,EV30,EW30,EX30,EY30,EZ30,FA30,FB30,FC30,FD30,FE30,FF30) | FH30: 1 | FI30: 0 | FJ30: 648 | FK30: 72 | FL30: 0 | FM30: 0 | FN30: 0 | FO30: 0 | FP30: 0 | FQ30: =FL30+FM30+FN30+FO30+FP30 | FR30: 80300 | FS30: 0 | FT30: 0 | FU30: 0 | FV30: =FR30+FS30+FT30+FU30 | FW30: 2394150 | FX30: 0 | FY30: 19500 | FZ30: 1030000 | GA30: =FW30+FX30+FY30+FZ30 | GB30: =FV30+GA30 | GC30: 42183.11 | GD30: 0 | GE30: 19059.63 | GF30: 0 | GG30: =GC30+GD30+GE30+GF30 | GH30: 2031701.6 | GI30: 0 | GJ30: 1030000 | GK30: 19500 | GL30: =GH30+GI30+GJ30+GK30 | GM30: =GG30+GL30 | GN30: 2404.58 | GO30: 0 | GP30: 3393.64 | GQ30: 0 | GR30: =GN30+GO30+GP30+GQ30 | GS30: 3572 | GT30: 0 | GU30: 893 | GV30: 0 | GW30: =GS30+GT30+GU30+GV30 | GX30: =GM30+GR30+GW30 | GY30: 17863877 | GZ30: 273137.02 | HA30: =GY30+GZ30 | HB30: =IF(GX30=0,"",AU30/GX30) | HC30: =IF((GX30+GY30)=0,"",GB30/(GX30+GY30)) | HD30: =IF(GX30=0,"",GB30/GX30) | HE30: 3 | HF30: 1 | HG30: 6 | HH30: 3 | HI30: 15 | HJ30: =HF30+HI30 | HK30: =IF(HE30=0,"",HH30/HE30) | HL30: 18 | HM30: 6 | HN30: =IF(HL30=0,"",HM30/HL30)
A31: Liwonde | B31: Machinga | C31: FY2025/26 | D31: 2025 | E31: 8 | F31: August | G31: Q2 | H31: 1967 | I31: 30 | J31: 0 | K31: 6 | L31: 0 | M31: =SUM(I31,J31,K31,L31) | N31: 1637.4 | O31: 0 | P31: 3.3 | Q31: 0 | R31: =SUM(N31,O31,P31,Q31) | S31: =M31+R31 | T31: 290.3 | U31: =IF(H31=0,"",T31/H31) | V31: 7 | W31: =IF(H31=0,"",V31/H31) | X31: 0 | Y31: =IF(H31=0,"",X31/H31) | Z31: 0 | AA31: =IF(H31=0,"",Z31/H31) | AB31: 0 | AC31: =IF(H31=0,"",AB31/H31) | AD31: 0 | AE31: =IF(H31=0,"",AD31/H31) | AF31: 0 | AG31: =IF(H31=0,"",AF31/H31) | AH31: 24677.03 | AI31: =IF(H31=0,"",AH31/H31) | AJ31: 5200 | AK31: =IF(H31=0,"",AJ31/H31) | AL31: 888662 | AM31: =IF(H31=0,"",AL31/H31) | AN31: 0 | AO31: 0 | AP31: 0 | AQ31: 0 | AR31: 712768.63 | AS31: 1008001.3 | AT31: 0 | AU31: =AH31+AL31+AP31+AQ31+AR31+AS31+AT31 | AV31: =IF(H31=0,"",AU31/H31) | AW31: =IF(S31=0,"",AU31/S31) | AX31: 0 | AY31: =IF(H31=0,"",AX31/(H31/1000/12)) | AZ31: 8 | BA31: 6 | BB31: 7 | BC31: 7 | BD31: 0 | BE31: =BC31+BD31 | BF31: =BA31+BB31-BE31 | BG31: 0 | BH31: 0 | BI31: 0 | BJ31: 0 | BK31: =BI31+BJ31 | BL31: =BG31+BH31-BK31 | BM31: 0 | BN31: 0 | BO31: 0 | BP31: 0 | BQ31: =BO31+BP31 | BR31: =BM31+BN31-BQ31 | BS31: 0 | BT31: 0 | BU31: 0 | BV31: 0 | BW31: =BU31+BV31 | BX31: =BS31+BT31-BW31 | BY31: =BA31+BG31+BM31+BS31 | BZ31: =BB31+BH31+BN31+BT31 | CA31: =BE31+BK31+BQ31+BW31 | CB31: =BF31+BL31+BR31+BX31 | CC31: 6 | CD31: 223 | CE31: 0 | CF31: 0 | CG31: 0 | CH31: =CD31+CE31+CF31+CG31 | CI31: 10 | CJ31: 0 | CK31: 0 | CL31: 0 | CM31: =CI31+CJ31+CK31+CL31 | CN31: 320 | CO31: 14 | CP31: 27 | CQ31: 0 | CR31: =CN31+CO31+CP31+CQ31 | CS31: =CM31+CR31 | CT31: 594 | CU31: 1453 | CV31: 1253 | CW31: =IF(CU31=0,"",CV31/CU31) | DB31: =CX31+CY31-CZ31-DA31 | DC31: 0 | DD31: 0 | DE31: 0 | DF31: 0 | DG31: =DC31+DD31-DE31-DF31 | DH31: 0 | DI31: 0 | DJ31: 0 | DK31: 0 | DL31: =DH31+DI31-DJ31-DK31 | DM31: 0 | DN31: 0 | DO31: 0 | DP31: 0 | DQ31: =DM31+DN31-DO31-DP31 | DR31: =CX31+DC31+DH31+DM31 | DS31: =CY31+DD31+DI31+DN31 | DT31: =CZ31+DE31+DJ31+DO31 | DU31: =DA31+DF31+DK31+DP31 | DV31: =DB31+DG31+DL31+DQ31 | DW31: 19 | DX31: 12 | DY31: 7 | DZ31: 5 | EA31: 1 | EB31: 2 | EC31: 0 | ED31: 1 | EE31: 0 | EF31: 0 | EG31: 0 | EH31: 0 | EI31: 0 | EJ31: 3 | EK31: 2 | EL31: 0 | EM31: 0 | EN31: 3 | EO31: 0 | EP31: 0 | EQ31: 0 | ER31: 0 | ES31: 0 | ET31: 0 | EU31: 0 | EV31: 0 | EW31: 0 | EX31: 0 | EY31: 0 | EZ31: 0 | FA31: 0 | FB31: 0 | FC31: 0 | FD31: 0 | FE31: 0 | FF31: 0 | FG31: =SUM(DW31,DX31,DY31,DZ31,EA31,EB31,EC31,ED31,EE31,EF31,EG31,EH31,EI31,EJ31,EK31,EL31,EM31,EN31,EO31,EP31,EQ31,ER31,ES31,ET31,EU31,EV31,EW31,EX31,EY31,EZ31,FA31,FB31,FC31,FD31,FE31,FF31) | FH31: 1 | FI31: 0 | FJ31: 0 | FK31: 48 | FL31: 0 | FM31: 0 | FN31: 0 | FO31: 0 | FP31: 0 | FQ31: =FL31+FM31+FN31+FO31+FP31 | FR31: 77208.02 | FS31: 0 | FT31: 0 | FU31: 0 | FV31: =FR31+FS31+FT31+FU31 | FW31: 2275291.6 | FX31: 0 | FY31: 2000 | FZ31: 10000 | GA31: =FW31+FX31+FY31+FZ31 | GB31: =FV31+GA31 | GC31: 39595.68 | GD31: 0 | GE31: 13735.31 | GF31: 0 | GG31: =GC31+GD31+GE31+GF31 | GH31: 2060561.2 | GI31: 0 | GJ31: 10000 | GK31: 2000 | GL31: =GH31+GI31+GJ31+GK31 | GM31: =GG31+GL31 | GN31: 5674.16 | GO31: 0 | GP31: 3393.64 | GQ31: 0 | GR31: =GN31+GO31+GP31+GQ31 | GS31: 8930 | GT31: 0 | GU31: 893 | GV31: 0 | GW31: =GS31+GT31+GU31+GV31 | GX31: =GM31+GR31+GW31 | GY31: 17833007 | GZ31: 295937.16 | HA31: =GY31+GZ31 | HB31: =IF(GX31=0,"",AU31/GX31) | HC31: =IF((GX31+GY31)=0,"",GB31/(GX31+GY31)) | HD31: =IF(GX31=0,"",GB31/GX31) | HE31: 7 | HF31: 1 | HG31: 6 | HH31: 7 | HI31: 15 | HJ31: =HF31+HI31 | HK31: =IF(HE31=0,"",HH31/HE31) | HL31: 24 | HM31: 4 | HN31: =IF(HL31=0,"",HM31/HL31)
A32: Liwonde | B32: Machinga | C32: FY2025/26 | D32: 2025 | E32: 9 | F32: September | G32: Q2 | H32: 2860 | I32: 27 | J32: 0 | K32: 21 | L32: 0 | M32: =SUM(I32,J32,K32,L32) | N32: 1860.5 | O32: 0 | P32: 14.2 | Q32: 32.5 | R32: =SUM(N32,O32,P32,Q32) | S32: =M32+R32 | T32: 904.8 | U32: =IF(H32=0,"",T32/H32) | V32: 7 | W32: =IF(H32=0,"",V32/H32) | X32: 0 | Y32: =IF(H32=0,"",X32/H32) | Z32: 0 | AA32: =IF(H32=0,"",Z32/H32) | AB32: 0 | AC32: =IF(H32=0,"",AB32/H32) | AD32: 0 | AE32: =IF(H32=0,"",AD32/H32) | AF32: 0 | AG32: =IF(H32=0,"",AF32/H32) | AH32: 24677.03 | AI32: =IF(H32=0,"",AH32/H32) | AJ32: 5100 | AK32: =IF(H32=0,"",AJ32/H32) | AL32: 871944.25 | AM32: =IF(H32=0,"",AL32/H32) | AN32: 0 | AO32: 0 | AP32: 0 | AQ32: 0 | AR32: 712768.63 | AS32: 1008001.3 | AT32: 97762.08 | AU32: =AH32+AL32+AP32+AQ32+AR32+AS32+AT32 | AV32: =IF(H32=0,"",AU32/H32) | AW32: =IF(S32=0,"",AU32/S32) | AX32: 3 | AY32: =IF(H32=0,"",AX32/(H32/1000/12)) | AZ32: 8 | BA32: 6 | BB32: 6 | BC32: 0 | BD32: 8 | BE32: =BC32+BD32 | BF32: =BA32+BB32-BE32 | BG32: 0 | BH32: 0 | BI32: 0 | BJ32: 0 | BK32: =BI32+BJ32 | BL32: =BG32+BH32-BK32 | BM32: 0 | BN32: 0 | BO32: 0 | BP32: 0 | BQ32: =BO32+BP32 | BR32: =BM32+BN32-BQ32 | BS32: 0 | BT32: 0 | BU32: 0 | BV32: 0 | BW32: =BU32+BV32 | BX32: =BS32+BT32-BW32 | BY32: =BA32+BG32+BM32+BS32 | BZ32: =BB32+BH32+BN32+BT32 | CA32: =BE32+BK32+BQ32+BW32 | CB32: =BF32+BL32+BR32+BX32 | CC32: 6 | CD32: 213 | CE32: 5 | CF32: 3 | CG32: 0 | CH32: =CD32+CE32+CF32+CG32 | CI32: 6 | CJ32: 1 | CK32: 0 | CL32: 0 | CM32: =CI32+CJ32+CK32+CL32 | CN32: 334 | CO32: 14 | CP32: 27 | CQ32: 0 | CR32: =CN32+CO32+CP32+CQ32 | CS32: =CM32+CR32 | CT32: 603 | CU32: 1463 | CV32: 1270 | CW32: =IF(CU32=0,"",CV32/CU32) | DB32: =CX32+CY32-CZ32-DA32 | DC32: 0 | DD32: 0 | DE32: 0 | DF32: 0 | DG32: =DC32+DD32-DE32-DF32 | DH32: 0 | DI32: 0 | DJ32: 0 | DK32: 0 | DL32: =DH32+DI32-DJ32-DK32 | DM32: 0 | DN32: 0 | DO32: 0 | DP32: 0 | DQ32: =DM32+DN32-DO32-DP32 | DR32: =CX32+DC32+DH32+DM32 | DS32: =CY32+DD32+DI32+DN32 | DT32: =CZ32+DE32+DJ32+DO32 | DU32: =DA32+DF32+DK32+DP32 | DV32: =DB32+DG32+DL32+DQ32 | DW32: 14 | DX32: 7 | DY32: 8 | DZ32: 3 | EA32: 5 | EB32: 2 | EC32: 0 | ED32: 0 | EE32: 0 | EF32: 0 | EG32: 0 | EH32: 0 | EI32: 0 | EJ32: 2 | EK32: 1 | EL32: 0 | EM32: 0 | EN32: 3 | EO32: 0 | EP32: 0 | EQ32: 0 | ER32: 0 | ES32: 0 | ET32: 0 | EU32: 0 | EV32: 0 | EW32: 0 | EX32: 0 | EY32: 0 | EZ32: 0 | FA32: 0 | FB32: 0 | FC32: 0 | FD32: 0 | FE32: 0 | FF32: 0 | FG32: =SUM(DW32,DX32,DY32,DZ32,EA32,EB32,EC32,ED32,EE32,EF32,EG32,EH32,EI32,EJ32,EK32,EL32,EM32,EN32,EO32,EP32,EQ32,ER32,ES32,ET32,EU32,EV32,EW32,EX32,EY32,EZ32,FA32,FB32,FC32,FD32,FE32,FF32) | FH32: 1 | FI32: 0 | FJ32: 0 | FK32: 72 | FL32: 0 | FM32: 0 | FN32: 0 | FO32: 0 | FP32: 0 | FQ32: =FL32+FM32+FN32+FO32+FP32 | FR32: 29800 | FS32: 0 | FT32: 0 | FU32: 0 | FV32: =FR32+FS32+FT32+FU32 | FW32: 2460893.8 | FX32: 0 | FY32: 154000 | FZ32: 48000 | GA32: =FW32+FX32+FY32+FZ32 | GB32: =FV32+GA32 | GC32: 28838.56 | GD32: 0 | GE32: 60182.02 | GF32: 0 | GG32: =GC32+GD32+GE32+GF32 | GH32: 2320471.6 | GI32: 0 | GJ32: 43200 | GK32: 154000 | GL32: =GH32+GI32+GJ32+GK32 | GM32: =GG32+GL32 | GN32: 3494.44 | GO32: 0 | GP32: 3393.64 | GQ32: 0 | GR32: =GN32+GO32+GP32+GQ32 | GS32: 5358 | GT32: 0 | GU32: 893 | GV32: 0 | GW32: =GS32+GT32+GU32+GV32 | GX32: =GM32+GR32+GW32 | GY32: 17831881 | GZ32: 366063.71 | HA32: =GY32+GZ32 | HB32: =IF(GX32=0,"",AU32/GX32) | HC32: =IF((GX32+GY32)=0,"",GB32/(GX32+GY32)) | HD32: =IF(GX32=0,"",GB32/GX32) | HE32: 5 | HF32: 1 | HG32: 4 | HH32: 6 | HI32: 15 | HJ32: =HF32+HI32 | HK32: =IF(HE32=0,"",HH32/HE32) | HL32: 26 | HM32: 30 | HN32: =IF(HL32=0,"",HM32/HL32)
A33: Liwonde | B33: Machinga | C33: FY2025/26 | D33: 2025 | E33: 10 | F33: October | G33: Q3 | H33: 2573 | I33: 52 | J33: 0 | K33: 24 | L33: 0 | M33: =SUM(I33,J33,K33,L33) | N33: 1705 | O33: 0 | P33: 403 | Q33: 35 | R33: =SUM(N33,O33,P33,Q33) | S33: =M33+R33 | T33: 354 | U33: =IF(H33=0,"",T33/H33) | V33: 8 | W33: =IF(H33=0,"",V33/H33) | X33: 0 | Y33: =IF(H33=0,"",X33/H33) | Z33: 0 | AA33: =IF(H33=0,"",Z33/H33) | AB33: 0 | AC33: =IF(H33=0,"",AB33/H33) | AD33: 0 | AE33: =IF(H33=0,"",AD33/H33) | AF33: 0 | AG33: =IF(H33=0,"",AF33/H33) | AH33: 28202.32 | AI33: =IF(H33=0,"",AH33/H33) | AJ33: 5300 | AK33: =IF(H33=0,"",AJ33/H33) | AL33: 905379.75 | AM33: =IF(H33=0,"",AL33/H33) | AN33: 0 | AO33: 0 | AP33: 0 | AQ33: 0 | AR33: 0 | AS33: 1008001.3 | AT33: 98000 | AU33: =AH33+AL33+AP33+AQ33+AR33+AS33+AT33 | AV33: =IF(H33=0,"",AU33/H33) | AW33: =IF(S33=0,"",AU33/S33) | AX33: 3 | AY33: =IF(H33=0,"",AX33/(H33/1000/12)) | AZ33: 8 | BA33: 4 | BB33: 4 | BC33: 0 | BD33: 4 | BE33: =BC33+BD33 | BF33: =BA33+BB33-BE33 | BG33: 0 | BH33: 0 | BI33: 0 | BJ33: 0 | BK33: =BI33+BJ33 | BL33: =BG33+BH33-BK33 | BM33: 0 | BN33: 0 | BO33: 0 | BP33: 0 | BQ33: =BO33+BP33 | BR33: =BM33+BN33-BQ33 | BS33: 0 | BT33: 0 | BU33: 0 | BV33: 0 | BW33: =BU33+BV33 | BX33: =BS33+BT33-BW33 | BY33: =BA33+BG33+BM33+BS33 | BZ33: =BB33+BH33+BN33+BT33 | CA33: =BE33+BK33+BQ33+BW33 | CB33: =BF33+BL33+BR33+BX33 | CC33: 7 | CD33: 213 | CE33: 5 | CF33: 3 | CG33: 0 | CH33: =CD33+CE33+CF33+CG33 | CI33: 4 | CJ33: 0 | CK33: 0 | CL33: 0 | CM33: =CI33+CJ33+CK33+CL33 | CN33: 341 | CO33: 14 | CP33: 27 | CQ33: 0 | CR33: =CN33+CO33+CP33+CQ33 | CS33: =CM33+CR33 | CT33: 607 | CU33: 1470 | CV33: 1276 | CW33: =IF(CU33=0,"",CV33/CU33) | DB33: =CX33+CY33-CZ33-DA33 | DC33: 0 | DD33: 0 | DE33: 0 | DF33: 0 | DG33: =DC33+DD33-DE33-DF33 | DH33: 0 | DI33: 0 | DJ33: 0 | DK33: 0 | DL33: =DH33+DI33-DJ33-DK33 | DM33: 0 | DN33: 0 | DO33: 0 | DP33: 0 | DQ33: =DM33+DN33-DO33-DP33 | DR33: =CX33+DC33+DH33+DM33 | DS33: =CY33+DD33+DI33+DN33 | DT33: =CZ33+DE33+DJ33+DO33 | DU33: =DA33+DF33+DK33+DP33 | DV33: =DB33+DG33+DL33+DQ33 | DW33: 16 | DX33: 11 | DY33: 7 | DZ33: 2 | EA33: 2 | EB33: 3 | EC33: 1 | ED33: 1 | EE33: 3 | EF33: 0 | EG33: 0 | EH33: 0 | EI33: 0 | EJ33: 3 | EK33: 1 | EL33: 1 | EM33: 0 | EN33: 2 | EO33: 0 | EP33: 0 | EQ33: 0 | ER33: 0 | ES33: 0 | ET33: 0 | EU33: 0 | EV33: 0 | EW33: 0 | EX33: 0 | EY33: 0 | EZ33: 0 | FA33: 0 | FB33: 0 | FC33: 0 | FD33: 0 | FE33: 0 | FF33: 0 | FG33: =SUM(DW33,DX33,DY33,DZ33,EA33,EB33,EC33,ED33,EE33,EF33,EG33,EH33,EI33,EJ33,EK33,EL33,EM33,EN33,EO33,EP33,EQ33,ER33,ES33,ET33,EU33,EV33,EW33,EX33,EY33,EZ33,FA33,FB33,FC33,FD33,FE33,FF33) | FH33: 1 | FI33: 0 | FJ33: 0 | FK33: 132 | FL33: 0 | FM33: 0 | FN33: 0 | FO33: 0 | FP33: 0 | FQ33: =FL33+FM33+FN33+FO33+FP33 | FR33: 99867.22 | FS33: 0 | FT33: 0 | FU33: 0 | FV33: =FR33+FS33+FT33+FU33 | FW33: 2225112.4 | FX33: 0 | FY33: 165000 | FZ33: 1231200 | GA33: =FW33+FX33+FY33+FZ33 | GB33: =FV33+GA33 | GC33: 46485.77 | GD33: 0 | GE33: 70560.43 | GF33: 0 | GG33: =GC33+GD33+GE33+GF33 | GH33: 2125328.1 | GI33: 0 | GJ33: 1224200 | GK33: 165000 | GL33: =GH33+GI33+GJ33+GK33 | GM33: =GG33+GL33 | GN33: 1859.65 | GO33: 0 | GP33: 3393.64 | GQ33: 0 | GR33: =GN33+GO33+GP33+GQ33 | GS33: 2679 | GT33: 0 | GU33: 893 | GV33: 0 | GW33: =GS33+GT33+GU33+GV33 | GX33: =GM33+GR33+GW33 | GY33: 17772066 | GZ33: 451882.05 | HA33: =GY33+GZ33 | HB33: =IF(GX33=0,"",AU33/GX33) | HC33: =IF((GX33+GY33)=0,"",GB33/(GX33+GY33)) | HD33: =IF(GX33=0,"",GB33/GX33) | HE33: 4 | HF33: 1 | HG33: 4 | HH33: 4 | HI33: 15 | HJ33: =HF33+HI33 | HK33: =IF(HE33=0,"",HH33/HE33) | HL33: 12 | HM33: 3 | HN33: =IF(HL33=0,"",HM33/HL33)
A34: Liwonde | B34: Machinga | C34: FY2025/26 | D34: 2025 | E34: 11 | F34: November | G34: Q3 | H34: 2812 | I34: 36 | J34: 0 | K34: 68 | L34: 0 | M34: =SUM(I34,J34,K34,L34) | N34: 1592.2 | O34: 0 | P34: 335.5 | Q34: 29 | R34: =SUM(N34,O34,P34,Q34) | S34: =M34+R34 | T34: 751.3 | U34: =IF(H34=0,"",T34/H34) | V34: 7 | W34: =IF(H34=0,"",V34/H34) | X34: 0 | Y34: =IF(H34=0,"",X34/H34) | Z34: 0 | AA34: =IF(H34=0,"",Z34/H34) | AB34: 0 | AC34: =IF(H34=0,"",AB34/H34) | AD34: 0 | AE34: =IF(H34=0,"",AD34/H34) | AF34: 0 | AG34: =IF(H34=0,"",AF34/H34) | AH34: 24677.03 | AI34: =IF(H34=0,"",AH34/H34) | AJ34: 5000 | AK34: =IF(H34=0,"",AJ34/H34) | AL34: 855226.5 | AM34: =IF(H34=0,"",AL34/H34) | AN34: 0 | AO34: 0 | AP34: 0 | AQ34: 0 | AR34: 712768.63 | AS34: 1008001.3 | AT34: 0 | AU34: =AH34+AL34+AP34+AQ34+AR34+AS34+AT34 | AV34: =IF(H34=0,"",AU34/H34) | AW34: =IF(S34=0,"",AU34/S34) | AX34: 3 | AY34: =IF(H34=0,"",AX34/(H34/1000/12)) | AZ34: 8 | BA34: 4 | BB34: 4 | BC34: 0 | BD34: 4 | BE34: =BC34+BD34 | BF34: =BA34+BB34-BE34 | BG34: 0 | BH34: 0 | BI34: 0 | BJ34: 0 | BK34: =BI34+BJ34 | BL34: =BG34+BH34-BK34 | BM34: 0 | BN34: 0 | BO34: 0 | BP34: 0 | BQ34: =BO34+BP34 | BR34: =BM34+BN34-BQ34 | BS34: 0 | BT34: 0 | BU34: 0 | BV34: 0 | BW34: =BU34+BV34 | BX34: =BS34+BT34-BW34 | BY34: =BA34+BG34+BM34+BS34 | BZ34: =BB34+BH34+BN34+BT34 | CA34: =BE34+BK34+BQ34+BW34 | CB34: =BF34+BL34+BR34+BX34 | CC34: 4 | CD34: 211 | CE34: 5 | CF34: 3 | CG34: 0 | CH34: =CD34+CE34+CF34+CG34 | CI34: 4 | CJ34: 1 | CK34: 0 | CL34: 0 | CM34: =CI34+CJ34+CK34+CL34 | CN34: 345 | CO34: 14 | CP34: 27 | CQ34: 0 | CR34: =CN34+CO34+CP34+CQ34 | CS34: =CM34+CR34 | CT34: 610 | CU34: 1485.0232 | CV34: 1289.1135 | CW34: =IF(CU34=0,"",CV34/CU34) | DB34: =CX34+CY34-CZ34-DA34 | DC34: 0 | DD34: 0 | DE34: 0 | DF34: 0 | DG34: =DC34+DD34-DE34-DF34 | DH34: 0 | DI34: 0 | DJ34: 0 | DK34: 0 | DL34: =DH34+DI34-DJ34-DK34 | DM34: 0 | DN34: 0 | DO34: 0 | DP34: 0 | DQ34: =DM34+DN34-DO34-DP34 | DR34: =CX34+DC34+DH34+DM34 | DS34: =CY34+DD34+DI34+DN34 | DT34: =CZ34+DE34+DJ34+DO34 | DU34: =DA34+DF34+DK34+DP34 | DV34: =DB34+DG34+DL34+DQ34 | DW34: 28 | DX34: 11 | DY34: 4 | DZ34: 7 | EA34: 3 | EB34: 2 | EC34: 0 | ED34: 1 | EE34: 1 | EF34: 0 | EG34: 0 | EH34: 0 | EI34: 0 | EJ34: 1 | EK34: 2 | EL34: 0 | EM34: 0 | EN34: 1 | EO34: 0 | EP34: 0 | EQ34: 0 | ER34: 0 | ES34: 0 | ET34: 0 | EU34: 0 | EV34: 0 | EW34: 0 | EX34: 0 | EY34: 0 | EZ34: 0 | FA34: 0 | FB34: 0 | FC34: 0 | FD34: 0 | FE34: 0 | FF34: 0 | FG34: =SUM(DW34,DX34,DY34,DZ34,EA34,EB34,EC34,ED34,EE34,EF34,EG34,EH34,EI34,EJ34,EK34,EL34,EM34,EN34,EO34,EP34,EQ34,ER34,ES34,ET34,EU34,EV34,EW34,EX34,EY34,EZ34,FA34,FB34,FC34,FD34,FE34,FF34) | FH34: 1 | FI34: 0 | FJ34: 0 | FK34: 48 | FL34: 0 | FM34: 0 | FN34: 0 | FO34: 0 | FP34: 0 | FQ34: =FL34+FM34+FN34+FO34+FP34 | FR34: 0 | FS34: 0 | FT34: 0 | FU34: 0 | FV34: =FR34+FS34+FT34+FU34 | FW34: 2207515.4 | FX34: 0 | FY34: 145000 | FZ34: 1020000 | GA34: =FW34+FX34+FY34+FZ34 | GB34: =FV34+GA34 | GC34: 32415.19 | GD34: 0 | GE34: 222777.11 | GF34: 0 | GG34: =GC34+GD34+GE34+GF34 | GH34: 2001713.6 | GI34: 0 | GJ34: 1020000 | GK34: 136000 | GL34: =GH34+GI34+GJ34+GK34 | GM34: =GG34+GL34 | GN34: 2404.58 | GO34: 0 | GP34: 3393.64 | GQ34: 0 | GR34: =GN34+GO34+GP34+GQ34 | GS34: 3572 | GT34: 0 | GU34: 893 | GV34: 0 | GW34: =GS34+GT34+GU34+GV34 | GX34: =GM34+GR34+GW34 | GY34: 12913992 | GZ34: 643457 | HA34: =GY34+GZ34 | HB34: =IF(GX34=0,"",AU34/GX34) | HC34: =IF((GX34+GY34)=0,"",GB34/(GX34+GY34)) | HD34: =IF(GX34=0,"",GB34/GX34) | HE34: 4 | HF34: 1 | HG34: 4 | HH34: 4 | HI34: 4 | HJ34: =HF34+HI34 | HK34: =IF(HE34=0,"",HH34/HE34) | HL34: 20 | HM34: 5 | HN34: =IF(HL34=0,"",HM34/HL34)
A35: Liwonde | B35: Machinga | C35: FY2025/26 | D35: 2025 | E35: 12 | F35: December | G35: Q3 | H35: 2123 | I35: 67 | J35: 0 | K35: 5 | L35: 0 | M35: =SUM(I35,J35,K35,L35) | N35: 1510.2 | O35: 0 | P35: 13.1 | Q35: 28 | R35: =SUM(N35,O35,P35,Q35) | S35: =M35+R35 | T35: 499.7 | U35: =IF(H35=0,"",T35/H35) | V35: 8 | W35: =IF(H35=0,"",V35/H35) | X35: 0 | Y35: =IF(H35=0,"",X35/H35) | Z35: 0 | AA35: =IF(H35=0,"",Z35/H35) | AB35: 0 | AC35: =IF(H35=0,"",AB35/H35) | AD35: 0 | AE35: =IF(H35=0,"",AD35/H35) | AF35: 0 | AG35: =IF(H35=0,"",AF35/H35) | AH35: 28202.32 | AI35: =IF(H35=0,"",AH35/H35) | AJ35: 5100 | AK35: =IF(H35=0,"",AJ35/H35) | AL35: 871944.25 | AM35: =IF(H35=0,"",AL35/H35) | AN35: 0 | AO35: 0 | AP35: 0 | AQ35: 0 | AR35: 712768.63 | AS35: 1008001.3 | AT35: 0 | AU35: =AH35+AL35+AP35+AQ35+AR35+AS35+AT35 | AV35: =IF(H35=0,"",AU35/H35) | AW35: =IF(S35=0,"",AU35/S35) | AX35: 3 | AY35: =IF(H35=0,"",AX35/(H35/1000/12)) | AZ35: 8 | BA35: 4 | BB35: 3 | BC35: 0 | BD35: 2 | BE35: =BC35+BD35 | BF35: =BA35+BB35-BE35 | BG35: 0 | BH35: 0 | BI35: 0 | BJ35: 0 | BK35: =BI35+BJ35 | BL35: =BG35+BH35-BK35 | BM35: 0 | BN35: 0 | BO35: 0 | BP35: 0 | BQ35: =BO35+BP35 | BR35: =BM35+BN35-BQ35 | BS35: 0 | BT35: 0 | BU35: 0 | BV35: 0 | BW35: =BU35+BV35 | BX35: =BS35+BT35-BW35 | BY35: =BA35+BG35+BM35+BS35 | BZ35: =BB35+BH35+BN35+BT35 | CA35: =BE35+BK35+BQ35+BW35 | CB35: =BF35+BL35+BR35+BX35 | CC35: 2 | CD35: 211 | CE35: 5 | CF35: 3 | CG35: 0 | CH35: =CD35+CE35+CF35+CG35 | CI35: 5 | CJ35: 1 | CK35: 0 | CL35: 0 | CM35: =CI35+CJ35+CK35+CL35 | CN35: 347 | CO35: 14 | CP35: 27 | CQ35: 0 | CR35: =CN35+CO35+CP35+CQ35 | CS35: =CM35+CR35 | CT35: 613 | CU35: 1499.85 | CV35: 1301.89 | CW35: =IF(CU35=0,"",CV35/CU35) | DB35: =CX35+CY35-CZ35-DA35 | DC35: 0 | DD35: 0 | DE35: 0 | DF35: 0 | DG35: =DC35+DD35-DE35-DF35 | DH35: 0 | DI35: 0 | DJ35: 0 | DK35: 0 | DL35: =DH35+DI35-DJ35-DK35 | DM35: 0 | DN35: 0 | DO35: 0 | DP35: 0 | DQ35: =DM35+DN35-DO35-DP35 | DR35: =CX35+DC35+DH35+DM35 | DS35: =CY35+DD35+DI35+DN35 | DT35: =CZ35+DE35+DJ35+DO35 | DU35: =DA35+DF35+DK35+DP35 | DV35: =DB35+DG35+DL35+DQ35 | DW35: 16 | DX35: 12 | DY35: 7 | DZ35: 5 | EA35: 4 | EB35: 3 | EC35: 0 | ED35: 0 | EE35: 0 | EF35: 0 | EG35: 0 | EH35: 0 | EI35: 0 | EJ35: 0 | EK35: 0 | EL35: 0 | EM35: 0 | EN35: 0 | EO35: 0 | EP35: 0 | EQ35: 0 | ER35: 0 | ES35: 0 | ET35: 0 | EU35: 0 | EV35: 0 | EW35: 0 | EX35: 0 | EY35: 0 | EZ35: 0 | FA35: 0 | FB35: 0 | FC35: 0 | FD35: 0 | FE35: 0 | FF35: 0 | FG35: =SUM(DW35,DX35,DY35,DZ35,EA35,EB35,EC35,ED35,EE35,EF35,EG35,EH35,EI35,EJ35,EK35,EL35,EM35,EN35,EO35,EP35,EQ35,ER35,ES35,ET35,EU35,EV35,EW35,EX35,EY35,EZ35,FA35,FB35,FC35,FD35,FE35,FF35) | FH35: 1 | FI35: 0 | FJ35: 0 | FK35: 24 | FL35: 0 | FM35: 0 | FN35: 0 | FO35: 0 | FP35: 0 | FQ35: =FL35+FM35+FN35+FO35+FP35 | FR35: 56000 | FS35: 0 | FT35: 0 | FU35: 0 | FV35: =FR35+FS35+FT35+FU35 | FW35: 2196867.6 | FX35: 0 | FY35: 143000 | FZ35: 42500 | GA35: =FW35+FX35+FY35+FZ35 | GB35: =FV35+GA35 | GC35: 59531.74 | GD35: 0 | GE35: 11073.15 | GF35: 0 | GG35: =GC35+GD35+GE35+GF35 | GH35: 1901276.5 | GI35: 0 | GJ35: 39500 | GK35: 133303.54 | GL35: =GH35+GI35+GJ35+GK35 | GM35: =GG35+GL35 | GN35: 3010.52 | GO35: 0 | GP35: 3393.64 | GQ35: 0 | GR35: =GN35+GO35+GP35+GQ35 | GS35: 4465 | GT35: 0 | GU35: 893 | GV35: 0 | GW35: =GS35+GT35+GU35+GV35 | GX35: =GM35+GR35+GW35 | GY35: 12915823 | GZ35: 667994.29 | HA35: =GY35+GZ35 | HB35: =IF(GX35=0,"",AU35/GX35) | HC35: =IF((GX35+GY35)=0,"",GB35/(GX35+GY35)) | HD35: =IF(GX35=0,"",GB35/GX35) | HE35: 4 | HF35: 1 | HG35: 5 | HH35: 3 | HI35: 1 | HJ35: =HF35+HI35 | HK35: =IF(HE35=0,"",HH35/HE35) | HL35: 24 | HM35: 6 | HN35: =IF(HL35=0,"",HM35/HL35)
A36: Liwonde | B36: Machinga | C36: FY2025/26 | D36: 2026 | E36: 1 | F36: January | G36: Q4 | H36: 2234 | I36: 44 | J36: 0 | K36: 6 | L36: 0 | M36: =SUM(I36,J36,K36,L36) | N36: 1659.3 | O36: 0 | P36: 12.2 | Q36: 64 | R36: =SUM(N36,O36,P36,Q36) | S36: =M36+R36 | T36: 448.5 | U36: 0.20076097 | V36: 10 | W36: 4.4762757 | X36: 0 | Y36: 0 | Z36: 0 | AA36: 0 | AB36: 0 | AC36: 0 | AD36: 0 | AE36: 0 | AF36: 0 | AG36: 0 | AH36: 35252.9 | AI36: 15.78017 | AJ36: 5200 | AK36: 2.3276634 | AL36: 888662 | AM36: 397.78962 | AN36: 0 | AO36: 0 | AP36: 0 | AQ36: 0 | AR36: 0 | AS36: 1008001.3 | AT36: 466000 | AU36: 2397916.2 | AV36: 1073.3734 | AW36: 1342.9942 | AX36: 3 | AY36: 41.629364 | AZ36: 8 | BA36: 5 | BB36: 3 | BC36: 3 | BD36: 0 | BE36: 3 | BF36: 5 | BG36: 0 | BH36: 0 | BI36: 0 | BJ36: 0 | BK36: 0 | BL36: 0 | BM36: 0 | BN36: 0 | BO36: 0 | BP36: 0 | BQ36: 0 | BR36: 0 | BS36: 0 | BT36: 0 | BU36: 0 | BV36: 0 | BW36: 0 | BX36: 0 | BY36: 5 | BZ36: 3 | CA36: 3 | CB36: 5 | CC36: 0 | CD36: 211 | CE36: 5 | CF36: 3 | CG36: 0 | CH36: 219 | CI36: 9 | CJ36: 0 | CK36: 0 | CL36: 0 | CM36: 9 | CN36: 347 | CO36: 14 | CP36: 27 | CQ36: 0 | CR36: 388 | CS36: 397 | CT36: 616 | CU36: 1507 | CV36: 1308 | CW36: 0.86794957 | CX36: 0 | CY36: 0 | CZ36: 0 | DA36: 0 | DB36: 0 | DC36: 0 | DD36: 0 | DE36: 0 | DF36: 0 | DG36: 0 | DH36: 0 | DI36: 0 | DJ36: 0 | DK36: 0 | DL36: 0 | DM36: 0 | DN36: 0 | DO36: 0 | DP36: 0 | DQ36: 0 | DR36: 0 | DS36: 0 | DT36: 0 | DU36: 0 | DV36: 0 | DW36: 15 | DX36: 9 | DY36: 6 | DZ36: 3 | EA36: 5 | EB36: 3 | EC36: 0 | ED36: 0 | EE36: 2 | EF36: 0 | EG36: 0 | EH36: 0 | EI36: 0 | EJ36: 1 | EK36: 2 | EL36: 0 | EM36: 0 | EN36: 2 | EO36: 0 | EP36: 0 | EQ36: 0 | ER36: 0 | ES36: 0 | ET36: 0 | EU36: 0 | EV36: 0 | EW36: 0 | EX36: 0 | EY36: 0 | EZ36: 0 | FA36: 0 | FB36: 0 | FC36: 0 | FD36: 0 | FE36: 0 | FF36: 0 | FG36: 48 | FH36: 1 | FI36: 0 | FJ36: 0 | FK36: 96 | FL36: 0 | FM36: 0 | FN36: 0 | FO36: 0 | FP36: 0 | FQ36: 0 | FR36: 0 | FS36: 0 | FT36: 0 | FU36: 0 | FV36: 0 | FW36: 2237101 | FX36: 0 | FY36: 304000 | FZ36: 42200 | GA36: 2583301 | GB36: 2583301 | GC36: 40153.95 | GD36: 0 | GE36: 13735.31 | GF36: 0 | GG36: 53889.26 | GH36: 2071227.7 | GI36: 0 | GJ36: 37400 | GK36: 304000 | GL36: 2412627.7 | GM36: 2466517 | GN36: 3010.52 | GO36: 0 | GP36: 3393.64 | GQ36: 0 | GR36: 6404.16 | GS36: 4465 | GT36: 0 | GU36: 893 | GV36: 0 | GW36: 5358 | GX36: 2478279.1 | GY36: 11589497 | GZ36: 185952.69 | HA36: 11775450 | HB36: 2478279.1 | HC36: 11589497 | HD36: 185952.69 | HE36: 4 | HF36: 1 | HG36: 5 | HH36: 3 | HI36: 1 | HJ36: 0 | HK36: 60 | HL36: 8 | HM36: 2 | HN36: 4
A37: Liwonde | B37: Machinga | C37: FY2025/26 | D37: 2026 | E37: 2 | F37: February | G37: Q4 | H37: 2145 | I37: 83 | J37: 0 | K37: 10 | L37: 0 | M37: =SUM(I37,J37,K37,L37) | N37: 1365.6 | O37: 0 | P37: 85 | Q37: 35 | R37: =SUM(N37,O37,P37,Q37) | S37: =M37+R37 | T37: 566.4 | U37: =IF(H37=0,"",T37/H37) | V37: 9 | W37: =IF(H37=0,"",V37/H37) | X37: 0 | Y37: =IF(H37=0,"",X37/H37) | Z37: 0 | AA37: =IF(H37=0,"",Z37/H37) | AB37: 0 | AC37: =IF(H37=0,"",AB37/H37) | AD37: 0 | AE37: =IF(H37=0,"",AD37/H37) | AF37: 0 | AG37: =IF(H37=0,"",AF37/H37) | AH37: 31727.61 | AI37: =IF(H37=0,"",AH37/H37) | AJ37: 860 | AK37: =IF(H37=0,"",AJ37/H37) | AL37: 163111.65 | AM37: =IF(H37=0,"",AL37/H37) | AN37: 0 | AO37: 0 | AP37: 0 | AQ37: 0 | AR37: 712768.63 | AS37: 0 | AT37: 79000 | AU37: =AH37+AL37+AP37+AQ37+AR37+AS37+AT37 | AV37: =IF(H37=0,"",AU37/H37) | AW37: =IF(S37=0,"",AU37/S37) | AX37: 3 | AY37: =IF(H37=0,"",AX37/(H37/1000/12)) | AZ37: 8 | BA37: 5 | BB37: 7 | BC37: 8 | BD37: 0 | BE37: =BC37+BD37 | BF37: =BA37+BB37-BE37 | BG37: 0 | BH37: 0 | BI37: 0 | BJ37: 0 | BK37: =BI37+BJ37 | BL37: =BG37+BH37-BK37 | BM37: 0 | BN37: 0 | BO37: 0 | BP37: 0 | BQ37: =BO37+BP37 | BR37: =BM37+BN37-BQ37 | BS37: 0 | BT37: 0 | BU37: 0 | BV37: 0 | BW37: =BU37+BV37 | BX37: =BS37+BT37-BW37 | BY37: =BA37+BG37+BM37+BS37 | BZ37: =BB37+BH37+BN37+BT37 | CA37: =BE37+BK37+BQ37+BW37 | CB37: =BF37+BL37+BR37+BX37 | CC37: 8 | CD37: 211 | CE37: 5 | CF37: 3 | CG37: 0 | CH37: =CD37+CE37+CF37+CG37 | CI37: 17 | CJ37: 0 | CK37: 0 | CL37: 0 | CM37: =CI37+CJ37+CK37+CL37 | CN37: 347 | CO37: 14 | CP37: 27 | CQ37: 0 | CR37: =CN37+CO37+CP37+CQ37 | CS37: =CM37+CR37 | CT37: 624 | CU37: 1522.07 | CV37: 1321 | CW37: =IF(CU37=0,"",CV37/CU37) | DB37: =CX37+CY37-CZ37-DA37 | DC37: 0 | DD37: 0 | DE37: 0 | DF37: 0 | DG37: =DC37+DD37-DE37-DF37 | DH37: 0 | DI37: 0 | DJ37: 0 | DK37: 0 | DL37: =DH37+DI37-DJ37-DK37 | DM37: 0 | DN37: 0 | DO37: 0 | DP37: 0 | DQ37: =DM37+DN37-DO37-DP37 | DR37: =CX37+DC37+DH37+DM37 | DS37: =CY37+DD37+DI37+DN37 | DT37: =CZ37+DE37+DJ37+DO37 | DU37: =DA37+DF37+DK37+DP37 | DV37: =DB37+DG37+DL37+DQ37 | DW37: 11 | DX37: 7 | DY37: 7 | DZ37: 3 | EA37: 2 | EB37: 2 | EC37: 0 | ED37: 1 | EE37: 1 | EF37: 0 | EG37: 0 | EH37: 0 | EI37: 0 | EJ37: 3 | EK37: 1 | EL37: 0 | EM37: 0 | EN37: 0 | EO37: 0 | EP37: 0 | EQ37: 0 | ER37: 0 | ES37: 0 | ET37: 0 | EU37: 0 | EV37: 0 | EW37: 0 | EX37: 0 | EY37: 0 | EZ37: 0 | FA37: 0 | FB37: 0 | FC37: 0 | FD37: 0 | FE37: 0 | FF37: 0 | FG37: =SUM(DW37,DX37,DY37,DZ37,EA37,EB37,EC37,ED37,EE37,EF37,EG37,EH37,EI37,EJ37,EK37,EL37,EM37,EN37,EO37,EP37,EQ37,ER37,ES37,ET37,EU37,EV37,EW37,EX37,EY37,EZ37,FA37,FB37,FC37,FD37,FE37,FF37) | FH37: 1 | FI37: 0 | FJ37: 0 | FK37: 102 | FL37: 0 | FM37: 0 | FN37: 0 | FO37: 0 | FP37: 0 | FQ37: =FL37+FM37+FN37+FO37+FP37 | FR37: 0 | FS37: 0 | FT37: 0 | FU37: 0 | FV37: =FR37+FS37+FT37+FU37 | FW37: 1825909 | FX37: 0 | FY37: 173000 | FZ37: 412000 | GA37: =FW37+FX37+FY37+FZ37 | GB37: =FV37+GA37 | GC37: 78565.4 | GD37: 0 | GE37: 24383.95 | GF37: 0 | GG37: =GC37+GD37+GE37+GF37 | GH37: 1704088.2 | GI37: 0 | GJ37: 258925.65 | GK37: 164000 | GL37: =GH37+GI37+GJ37+GK37 | GM37: =GG37+GL37 | GN37: 3555.45 | GO37: 0 | GP37: 3393.64 | GQ37: 0 | GR37: =GN37+GO37+GP37+GQ37 | GS37: 5358 | GT37: 0 | GU37: 893 | GV37: 0 | GW37: =GS37+GT37+GU37+GV37 | GX37: =GM37+GR37+GW37 | GY37: 11668679 | GZ37: 222920.27 | HA37: =GY37+GZ37 | HB37: =IF(GX37=0,"",AU37/GX37) | HC37: =IF((GX37+GY37)=0,"",GB37/(GX37+GY37)) | HD37: =IF(GX37=0,"",GB37/GX37) | HE37: 4 | HF37: 1 | HG37: 4 | HH37: 7 | HI37: 1 | HJ37: =HF37+HI37 | HK37: =IF(HE37=0,"",HH37/HE37) | HL37: 12 | HM37: 3 | HN37: =IF(HL37=0,"",HM37/HL37)
A38: Liwonde | B38: Machinga | C38: FY2025/26 | D38: 2026 | E38: 3 | F38: March | G38: Q4 | H38: 2085 | I38: 63 | J38: 0 | K38: 10 | L38: 0 | M38: =SUM(I38,J38,K38,L38) | N38: 1242 | O38: 0 | P38: 131 | Q38: 35 | R38: =SUM(N38,O38,P38,Q38) | S38: =M38+R38 | T38: 604 | U38: =IF(H38=0,"",T38/H38) | V38: 10 | W38: =IF(H38=0,"",V38/H38) | X38: 0 | Y38: =IF(H38=0,"",X38/H38) | Z38: 0 | AA38: =IF(H38=0,"",Z38/H38) | AB38: 0 | AC38: =IF(H38=0,"",AB38/H38) | AD38: 0 | AE38: =IF(H38=0,"",AD38/H38) | AF38: 0 | AG38: =IF(H38=0,"",AF38/H38) | AH38: 35252.9 | AI38: =IF(H38=0,"",AH38/H38) | AJ38: 4900 | AK38: =IF(H38=0,"",AJ38/H38) | AL38: 19339 | AM38: =IF(H38=0,"",AL38/H38) | AN38: 0 | AO38: 0 | AP38: 0 | AQ38: 0 | AR38: 712768.63 | AS38: 0 | AT38: 0 | AU38: =AH38+AL38+AP38+AQ38+AR38+AS38+AT38 | AV38: =IF(H38=0,"",AU38/H38) | AW38: =IF(S38=0,"",AU38/S38) | AX38: 3 | AY38: =IF(H38=0,"",AX38/(H38/1000/12)) | AZ38: 8 | BA38: 4 | BB38: 4 | BC38: 4 | BD38: 0 | BE38: =BC38+BD38 | BF38: =BA38+BB38-BE38 | BG38: 0 | BH38: 0 | BI38: 0 | BJ38: 0 | BK38: =BI38+BJ38 | BL38: =BG38+BH38-BK38 | BM38: 0 | BN38: 0 | BO38: 0 | BP38: 0 | BQ38: =BO38+BP38 | BR38: =BM38+BN38-BQ38 | BS38: 0 | BT38: 0 | BU38: 0 | BV38: 0 | BW38: =BU38+BV38 | BX38: =BS38+BT38-BW38 | BY38: =BA38+BG38+BM38+BS38 | BZ38: =BB38+BH38+BN38+BT38 | CA38: =BE38+BK38+BQ38+BW38 | CB38: =BF38+BL38+BR38+BX38 | CC38: 0 | CD38: 214 | CE38: 5 | CF38: 3 | CG38: 0 | CH38: =CD38+CE38+CF38+CG38 | CI38: 17 | CJ38: 1 | CK38: 0 | CL38: 0 | CM38: =CI38+CJ38+CK38+CL38 | CN38: 347 | CO38: 14 | CP38: 27 | CQ38: 0 | CR38: =CN38+CO38+CP38+CQ38 | CS38: =CM38+CR38 | CT38: 628 | CU38: 1537 | CV38: 1334 | CW38: =IF(CU38=0,"",CV38/CU38) | DB38: =CX38+CY38-CZ38-DA38 | DC38: 0 | DD38: 0 | DE38: 0 | DF38: 0 | DG38: =DC38+DD38-DE38-DF38 | DH38: 0 | DI38: 0 | DJ38: 0 | DK38: 0 | DL38: =DH38+DI38-DJ38-DK38 | DM38: 0 | DN38: 0 | DO38: 0 | DP38: 0 | DQ38: =DM38+DN38-DO38-DP38 | DR38: =CX38+DC38+DH38+DM38 | DS38: =CY38+DD38+DI38+DN38 | DT38: =CZ38+DE38+DJ38+DO38 | DU38: =DA38+DF38+DK38+DP38 | DV38: =DB38+DG38+DL38+DQ38 | DW38: 13 | DX38: 8 | DY38: 8 | DZ38: 3 | EA38: 2 | EB38: 4 | EC38: 0 | ED38: 2 | EE38: 0 | EF38: 0 | EG38: 0 | EH38: 0 | EI38: 0 | EJ38: 0 | EK38: 0 | EL38: 0 | EM38: 0 | EN38: 0 | EO38: 0 | EP38: 0 | EQ38: 0 | ER38: 0 | ES38: 0 | ET38: 0 | EU38: 0 | EV38: 0 | EW38: 0 | EX38: 0 | EY38: 0 | EZ38: 0 | FA38: 0 | FB38: 0 | FC38: 0 | FD38: 0 | FE38: 0 | FF38: 0 | FG38: =SUM(DW38,DX38,DY38,DZ38,EA38,EB38,EC38,ED38,EE38,EF38,EG38,EH38,EI38,EJ38,EK38,EL38,EM38,EN38,EO38,EP38,EQ38,ER38,ES38,ET38,EU38,EV38,EW38,EX38,EY38,EZ38,FA38,FB38,FC38,FD38,FE38,FF38) | FH38: 1 | FI38: 0 | FJ38: 0 | FK38: 124 | FL38: 0 | FM38: 0 | FN38: 0 | FO38: 0 | FP38: 0 | FQ38: =FL38+FM38+FN38+FO38+FP38 | FR38: 0 | FS38: 0 | FT38: 0 | FU38: 0 | FV38: =FR38+FS38+FT38+FU38 | FW38: 1615206 | FX38: 0 | FY38: 168200 | FZ38: 398500 | GA38: =FW38+FX38+FY38+FZ38 | GB38: =FV38+GA38 | GC38: 97855.46 | GD38: 0 | GE38: 24383.95 | GF38: 0 | GG38: =GC38+GD38+GE38+GF38 | GH38: 1548148 | GI38: 0 | GJ38: 398500 | GK38: 168200 | GL38: =GH38+GI38+GJ38+GK38 | GM38: =GG38+GL38 | GN38: 7747.33 | GO38: 0 | GP38: 3393.64 | GQ38: 0 | GR38: =GN38+GO38+GP38+GQ38 | GS38: 15181 | GT38: 0 | GU38: 893 | GV38: 0 | GW38: =GS38+GT38+GU38+GV38 | GX38: =GM38+GR38+GW38 | GY38: 11621972 | GZ38: 313246.89 | HA38: =GY38+GZ38 | HB38: =IF(GX38=0,"",AU38/GX38) | HC38: =IF((GX38+GY38)=0,"",GB38/(GX38+GY38)) | HD38: =IF(GX38=0,"",GB38/GX38) | HE38: 4 | HF38: 1 | HG38: 4 | HH38: 4 | HI38: 1 | HJ38: =HF38+HI38 | HK38: =IF(HE38=0,"",HH38/HE38) | HL38: 20 | HM38: 5 | HN38: =IF(HL38=0,"",HM38/HL38)
A39: Liwonde | B39: Ntaja | C39: FY2025/26 | D39: 2025 | E39: 4 | F39: April | G39: Q1 | H39: 3511 | I39: 10 | J39: 0 | K39: 3 | L39: 0 | M39: =SUM(I39,J39,K39,L39) | N39: 3010.2 | O39: 143.5 | P39: 57.8 | Q39: 48.2 | R39: =SUM(N39,O39,P39,Q39) | S39: =M39+R39 | T39: 238.3 | U39: =IF(H39=0,"",T39/H39) | V39: 14 | W39: =IF(H39=0,"",V39/H39) | X39: 0 | Y39: =IF(H39=0,"",X39/H39) | Z39: 0 | AA39: =IF(H39=0,"",Z39/H39) | AB39: 0 | AC39: =IF(H39=0,"",AB39/H39) | AD39: 0 | AE39: =IF(H39=0,"",AD39/H39) | AF39: 0 | AG39: =IF(H39=0,"",AF39/H39) | AH39: 49354.06 | AI39: =IF(H39=0,"",AH39/H39) | AJ39: 4910 | AK39: =IF(H39=0,"",AJ39/H39) | AL39: 840180.53 | AM39: =IF(H39=0,"",AL39/H39) | AN39: 0 | AO39: 0 | AP39: 0 | AQ39: 0 | AR39: 2606300.2 | AS39: 432692.5 | AT39: 25000 | AU39: =AH39+AL39+AP39+AQ39+AR39+AS39+AT39 | AV39: =IF(H39=0,"",AU39/H39) | AW39: =IF(S39=0,"",AU39/S39) | AX39: 6 | AY39: =IF(H39=0,"",AX39/(H39/1000/12)) | AZ39: 5 | BA39: 23 | BB39: 8 | BC39: 0 | BD39: 10 | BE39: =BC39+BD39 | BF39: =BA39+BB39-BE39 | BG39: 0 | BH39: 1 | BI39: 0 | BJ39: 1 | BK39: =BI39+BJ39 | BL39: =BG39+BH39-BK39 | BM39: 0 | BN39: 0 | BO39: 0 | BP39: 0 | BQ39: =BO39+BP39 | BR39: =BM39+BN39-BQ39 | BS39: 0 | BT39: 0 | BU39: 0 | BV39: 0 | BW39: =BU39+BV39 | BX39: =BS39+BT39-BW39 | BY39: =BA39+BG39+BM39+BS39 | BZ39: =BB39+BH39+BN39+BT39 | CA39: =BE39+BK39+BQ39+BW39 | CB39: =BF39+BL39+BR39+BX39 | CC39: 11 | CD39: 2 | CE39: 1 | CF39: 2 | CG39: 0 | CH39: =CD39+CE39+CF39+CG39 | CI39: 2 | CJ39: 1 | CK39: 0 | CL39: 0 | CM39: =CI39+CJ39+CK39+CL39 | CN39: 534 | CO39: 20 | CP39: 16 | CQ39: 3 | CR39: =CN39+CO39+CP39+CQ39 | CS39: =CM39+CR39 | CT39: 581 | CU39: 4200 | CV39: 2940 | CW39: =IF(CU39=0,"",CV39/CU39) | DB39: =CX39+CY39-CZ39-DA39 | DC39: 0 | DD39: 0 | DE39: 0 | DF39: 0 | DG39: =DC39+DD39-DE39-DF39 | DH39: 0 | DI39: 0 | DJ39: 0 | DK39: 0 | DL39: =DH39+DI39-DJ39-DK39 | DM39: 0 | DN39: 8 | DO39: 8 | DP39: 0 | DQ39: =DM39+DN39-DO39-DP39 | DR39: =CX39+DC39+DH39+DM39 | DS39: =CY39+DD39+DI39+DN39 | DT39: =CZ39+DE39+DJ39+DO39 | DU39: =DA39+DF39+DK39+DP39 | DV39: =DB39+DG39+DL39+DQ39 | DW39: 105 | DX39: 13 | DY39: 15 | DZ39: 0 | EA39: 3 | EB39: 3 | EC39: 0 | ED39: 0 | EE39: 0 | EF39: 0 | EG39: 0 | EH39: 0 | EI39: 0 | EJ39: 3 | EK39: 0 | EL39: 0 | EM39: 0 | EN39: 0 | EO39: 0 | EP39: 0 | EQ39: 0 | ER39: 0 | ES39: 0 | ET39: 0 | EU39: 0 | EV39: 0 | EW39: 0 | EX39: 0 | EY39: 0 | EZ39: 0 | FA39: 0 | FB39: 0 | FC39: 0 | FD39: 0 | FE39: 0 | FF39: 0 | FG39: =SUM(DW39,DX39,DY39,DZ39,EA39,EB39,EC39,ED39,EE39,EF39,EG39,EH39,EI39,EJ39,EK39,EL39,EM39,EN39,EO39,EP39,EQ39,ER39,ES39,ET39,EU39,EV39,EW39,EX39,EY39,EZ39,FA39,FB39,FC39,FD39,FE39,FF39) | FH39: 1 | FI39: 168 | FJ39: 720 | FK39: 98 | FL39: 0 | FM39: 0 | FN39: 0 | FO39: 0 | FP39: 0 | FQ39: =FL39+FM39+FN39+FO39+FP39 | FR39: 0 | FS39: 0 | FT39: 0 | FU39: 0 | FV39: =FR39+FS39+FT39+FU39 | FW39: 4030427.9 | FX39: 30500 | FY39: 247664.04 | FZ39: 176153.94 | GA39: =FW39+FX39+FY39+FZ39 | GB39: =FV39+GA39 | GC39: 9319.62 | GD39: 0 | GE39: 8410.99 | GF39: 0 | GG39: =GC39+GD39+GE39+GF39 | GH39: 3750514.6 | GI39: 30500 | GJ39: 175553.94 | GK39: 228482.38 | GL39: =GH39+GI39+GJ39+GK39 | GM39: =GG39+GL39 | GN39: 1089.86 | GO39: 0 | GP39: 3393.64 | GQ39: 0 | GR39: =GN39+GO39+GP39+GQ39 | GS39: 1786 | GT39: 0 | GU39: 893 | GV39: 0 | GW39: =GS39+GT39+GU39+GV39 | GX39: =GM39+GR39+GW39 | GY39: 0 | GZ39: 0 | HA39: =GY39+GZ39 | HB39: =IF(GX39=0,"",AU39/GX39) | HC39: =IF((GX39+GY39)=0,"",GB39/(GX39+GY39)) | HD39: =IF(GX39=0,"",GB39/GX39) | HE39: 8 | HF39: 2 | HG39: 21 | HH39: 9 | HI39: 30 | HJ39: =HF39+HI39 | HK39: =IF(HE39=0,"",HH39/HE39) | HL39: 8 | HM39: 2 | HN39: =IF(HL39=0,"",HM39/HL39)
A40: Liwonde | B40: Ntaja | C40: FY2025/26 | D40: 2025 | E40: 5 | F40: May | G40: Q1 | H40: 3880 | I40: 7 | J40: 0 | K40: 6 | L40: 0 | M40: =SUM(I40,J40,K40,L40) | N40: 3323.6 | O40: 163.3 | P40: 45 | Q40: 68.7 | R40: =SUM(N40,O40,P40,Q40) | S40: =M40+R40 | T40: 266.4 | U40: =IF(H40=0,"",T40/H40) | V40: 9 | W40: =IF(H40=0,"",V40/H40) | X40: 0 | Y40: =IF(H40=0,"",X40/H40) | Z40: 0 | AA40: =IF(H40=0,"",Z40/H40) | AB40: 0 | AC40: =IF(H40=0,"",AB40/H40) | AD40: 0 | AE40: =IF(H40=0,"",AD40/H40) | AF40: 0 | AG40: =IF(H40=0,"",AF40/H40) | AH40: 31727.61 | AI40: =IF(H40=0,"",AH40/H40) | AJ40: 4431 | AK40: =IF(H40=0,"",AJ40/H40) | AL40: 760102.5 | AM40: =IF(H40=0,"",AL40/H40) | AN40: 0 | AO40: 0 | AP40: 0 | AQ40: 0 | AR40: 2766432.4 | AS40: 429230.96 | AT40: 0 | AU40: =AH40+AL40+AP40+AQ40+AR40+AS40+AT40 | AV40: =IF(H40=0,"",AU40/H40) | AW40: =IF(S40=0,"",AU40/S40) | AX40: 6 | AY40: =IF(H40=0,"",AX40/(H40/1000/12)) | AZ40: 5 | BA40: 21 | BB40: 11 | BC40: 0 | BD40: 12 | BE40: =BC40+BD40 | BF40: =BA40+BB40-BE40 | BG40: 0 | BH40: 0 | BI40: 0 | BJ40: 0 | BK40: =BI40+BJ40 | BL40: =BG40+BH40-BK40 | BM40: 0 | BN40: 0 | BO40: 0 | BP40: 0 | BQ40: =BO40+BP40 | BR40: =BM40+BN40-BQ40 | BS40: 0 | BT40: 0 | BU40: 0 | BV40: 0 | BW40: =BU40+BV40 | BX40: =BS40+BT40-BW40 | BY40: =BA40+BG40+BM40+BS40 | BZ40: =BB40+BH40+BN40+BT40 | CA40: =BE40+BK40+BQ40+BW40 | CB40: =BF40+BL40+BR40+BX40 | CC40: 12 | CD40: 1 | CE40: 1 | CF40: 2 | CG40: 0 | CH40: =CD40+CE40+CF40+CG40 | CI40: 2 | CJ40: 1 | CK40: 0 | CL40: 0 | CM40: =CI40+CJ40+CK40+CL40 | CN40: 547 | CO40: 20 | CP40: 15 | CQ40: 3 | CR40: =CN40+CO40+CP40+CQ40 | CS40: =CM40+CR40 | CT40: 592 | CU40: 4200 | CV40: 2940 | CW40: =IF(CU40=0,"",CV40/CU40) | DB40: =CX40+CY40-CZ40-DA40 | DC40: 0 | DD40: 0 | DE40: 0 | DF40: 0 | DG40: =DC40+DD40-DE40-DF40 | DH40: 0 | DI40: 0 | DJ40: 0 | DK40: 0 | DL40: =DH40+DI40-DJ40-DK40 | DM40: 0 | DN40: 4 | DO40: 2 | DP40: 2 | DQ40: =DM40+DN40-DO40-DP40 | DR40: =CX40+DC40+DH40+DM40 | DS40: =CY40+DD40+DI40+DN40 | DT40: =CZ40+DE40+DJ40+DO40 | DU40: =DA40+DF40+DK40+DP40 | DV40: =DB40+DG40+DL40+DQ40 | DW40: 113 | DX40: 10 | DY40: 6 | DZ40: 1 | EA40: 2 | EB40: 1 | EC40: 0 | ED40: 0 | EE40: 0 | EF40: 1 | EG40: 0 | EH40: 0 | EI40: 0 | EJ40: 1 | EK40: 0 | EL40: 0 | EM40: 0 | EN40: 0 | EO40: 0 | EP40: 0 | EQ40: 0 | ER40: 0 | ES40: 0 | ET40: 0 | EU40: 0 | EV40: 0 | EW40: 0 | EX40: 0 | EY40: 0 | EZ40: 0 | FA40: 0 | FB40: 0 | FC40: 0 | FD40: 0 | FE40: 0 | FF40: 0 | FG40: =SUM(DW40,DX40,DY40,DZ40,EA40,EB40,EC40,ED40,EE40,EF40,EG40,EH40,EI40,EJ40,EK40,EL40,EM40,EN40,EO40,EP40,EQ40,ER40,ES40,ET40,EU40,EV40,EW40,EX40,EY40,EZ40,FA40,FB40,FC40,FD40,FE40,FF40) | FH40: 0 | FI40: 0 | FJ40: 464 | FK40: 121 | FL40: 0 | FM40: 0 | FN40: 0 | FO40: 0 | FP40: 0 | FQ40: =FL40+FM40+FN40+FO40+FP40 | FR40: 0 | FS40: 0 | FT40: 0 | FU40: 0 | FV40: =FR40+FS40+FT40+FU40 | FW40: 4359874.3 | FX40: 34700 | FY40: 366177 | FZ40: 137300 | GA40: =FW40+FX40+FY40+FZ40 | GB40: =FV40+GA40 | GC40: 6680.52 | GD40: 0 | GE40: 13735.31 | GF40: 0 | GG40: =GC40+GD40+GE40+GF40 | GH40: 4190697.2 | GI40: 34700 | GJ40: 136700 | GK40: 326378.46 | GL40: =GH40+GI40+GJ40+GK40 | GM40: =GG40+GL40 | GN40: 1089.86 | GO40: 0 | GP40: 3393.64 | GQ40: 0 | GR40: =GN40+GO40+GP40+GQ40 | GS40: 1786 | GT40: 0 | GU40: 893 | GV40: 0 | GW40: =GS40+GT40+GU40+GV40 | GX40: =GM40+GR40+GW40 | GY40: 0 | GZ40: 0 | HA40: =GY40+GZ40 | HB40: =IF(GX40=0,"",AU40/GX40) | HC40: =IF((GX40+GY40)=0,"",GB40/(GX40+GY40)) | HD40: =IF(GX40=0,"",GB40/GX40) | HE40: 19 | HF40: 3 | HG40: 20 | HH40: 11 | HI40: 30 | HJ40: =HF40+HI40 | HK40: =IF(HE40=0,"",HH40/HE40) | HL40: 12 | HM40: 2 | HN40: =IF(HL40=0,"",HM40/HL40)
A41: Liwonde | B41: Ntaja | C41: FY2025/26 | D41: 2025 | E41: 6 | F41: June | G41: Q1 | H41: 4209 | I41: 10 | J41: 0 | K41: 8 | L41: 0 | M41: =SUM(I41,J41,K41,L41) | N41: 3568.5 | O41: 200 | P41: 38.6 | Q41: 40.6 | R41: =SUM(N41,O41,P41,Q41) | S41: =M41+R41 | T41: 343.3 | U41: =IF(H41=0,"",T41/H41) | V41: 9 | W41: =IF(H41=0,"",V41/H41) | X41: 0 | Y41: =IF(H41=0,"",X41/H41) | Z41: 0 | AA41: =IF(H41=0,"",Z41/H41) | AB41: 0 | AC41: =IF(H41=0,"",AB41/H41) | AD41: 0 | AE41: =IF(H41=0,"",AD41/H41) | AF41: 0 | AG41: =IF(H41=0,"",AF41/H41) | AH41: 31727.61 | AI41: =IF(H41=0,"",AH41/H41) | AJ41: 4511 | AK41: =IF(H41=0,"",AJ41/H41) | AL41: 773476.7 | AM41: =IF(H41=0,"",AL41/H41) | AN41: 0 | AO41: 0 | AP41: 0 | AQ41: 0 | AR41: 24996337 | AS41: 615462.32 | AT41: 0 | AU41: =AH41+AL41+AP41+AQ41+AR41+AS41+AT41 | AV41: =IF(H41=0,"",AU41/H41) | AW41: =IF(S41=0,"",AU41/S41) | AX41: 6 | AY41: =IF(H41=0,"",AX41/(H41/1000/12)) | AZ41: 5 | BA41: 20 | BB41: 45 | BC41: 0 | BD41: 0 | BE41: =BC41+BD41 | BF41: =BA41+BB41-BE41 | BG41: 0 | BH41: 0 | BI41: 0 | BJ41: 0 | BK41: =BI41+BJ41 | BL41: =BG41+BH41-BK41 | BM41: 0 | BN41: 0 | BO41: 0 | BP41: 0 | BQ41: =BO41+BP41 | BR41: =BM41+BN41-BQ41 | BS41: 0 | BT41: 0 | BU41: 0 | BV41: 0 | BW41: =BU41+BV41 | BX41: =BS41+BT41-BW41 | BY41: =BA41+BG41+BM41+BS41 | BZ41: =BB41+BH41+BN41+BT41 | CA41: =BE41+BK41+BQ41+BW41 | CB41: =BF41+BL41+BR41+BX41 | CC41: 0 | CD41: 1 | CE41: 1 | CF41: 2 | CG41: 0 | CH41: =CD41+CE41+CF41+CG41 | CI41: 1 | CJ41: 2 | CK41: 0 | CL41: 0 | CM41: =CI41+CJ41+CK41+CL41 | CN41: 567 | CO41: 20 | CP41: 15 | CQ41: 3 | CR41: =CN41+CO41+CP41+CQ41 | CS41: =CM41+CR41 | CT41: 612 | CU41: 4200 | CV41: 2940 | CW41: =IF(CU41=0,"",CV41/CU41) | DB41: =CX41+CY41-CZ41-DA41 | DC41: 0 | DD41: 0 | DE41: 0 | DF41: 0 | DG41: =DC41+DD41-DE41-DF41 | DH41: 0 | DI41: 0 | DJ41: 0 | DK41: 0 | DL41: =DH41+DI41-DJ41-DK41 | DM41: 0 | DN41: 6 | DO41: 5 | DP41: 1 | DQ41: =DM41+DN41-DO41-DP41 | DR41: =CX41+DC41+DH41+DM41 | DS41: =CY41+DD41+DI41+DN41 | DT41: =CZ41+DE41+DJ41+DO41 | DU41: =DA41+DF41+DK41+DP41 | DV41: =DB41+DG41+DL41+DQ41 | DW41: 77 | DX41: 15 | DY41: 9 | DZ41: 0 | EA41: 3 | EB41: 0 | EC41: 0 | ED41: 1 | EE41: 0 | EF41: 0 | EG41: 0 | EH41: 0 | EI41: 0 | EJ41: 0 | EK41: 0 | EL41: 0 | EM41: 0 | EN41: 0 | EO41: 0 | EP41: 0 | EQ41: 0 | ER41: 0 | ES41: 0 | ET41: 0 | EU41: 0 | EV41: 0 | EW41: 0 | EX41: 0 | EY41: 0 | EZ41: 0 | FA41: 0 | FB41: 0 | FC41: 0 | FD41: 0 | FE41: 0 | FF41: 0 | FG41: =SUM(DW41,DX41,DY41,DZ41,EA41,EB41,EC41,ED41,EE41,EF41,EG41,EH41,EI41,EJ41,EK41,EL41,EM41,EN41,EO41,EP41,EQ41,ER41,ES41,ET41,EU41,EV41,EW41,EX41,EY41,EZ41,FA41,FB41,FC41,FD41,FE41,FF41) | FH41: 0 | FI41: 0 | FJ41: 720 | FK41: 148 | FL41: 0 | FM41: 0 | FN41: 0 | FO41: 0 | FP41: 0 | FQ41: =FL41+FM41+FN41+FO41+FP41 | FR41: 0 | FS41: 0 | FT41: 0 | FU41: 0 | FV41: =FR41+FS41+FT41+FU41 | FW41: 4669512.2 | FX41: 42500 | FY41: 191200 | FZ41: 118415 | GA41: =FW41+FX41+FY41+FZ41 | GB41: =FV41+GA41 | GC41: 11079.02 | GD41: 0 | GE41: 19059.63 | GF41: 0 | GG41: =GC41+GD41+GE41+GF41 | GH41: 4521318.4 | GI41: 42500 | GJ41: 117215 | GK41: 191200 | GL41: =GH41+GI41+GJ41+GK41 | GM41: =GG41+GL41 | GN41: 1089.86 | GO41: 0 | GP41: 3393.64 | GQ41: 0 | GR41: =GN41+GO41+GP41+GQ41 | GS41: 1786 | GT41: 0 | GU41: 893 | GV41: 0 | GW41: =GS41+GT41+GU41+GV41 | GX41: =GM41+GR41+GW41 | GY41: 593245.55 | GZ41: 0 | HA41: =GY41+GZ41 | HB41: =IF(GX41=0,"",AU41/GX41) | HC41: =IF((GX41+GY41)=0,"",GB41/(GX41+GY41)) | HD41: =IF(GX41=0,"",GB41/GX41) | HE41: 61 | HF41: 3 | HG41: 65 | HH41: 45 | HI41: 0 | HJ41: =HF41+HI41 | HK41: =IF(HE41=0,"",HH41/HE41) | HL41: 28 | HM41: 5 | HN41: =IF(HL41=0,"",HM41/HL41)
A42: Liwonde | B42: Ntaja | C42: FY2025/26 | D42: 2025 | E42: 7 | F42: July | G42: Q2 | H42: 3827 | I42: 15 | J42: 0 | K42: 3 | L42: 0 | M42: =SUM(I42,J42,K42,L42) | N42: 3235.4 | O42: 80.5 | P42: 44.2 | Q42: 50.4 | R42: =SUM(N42,O42,P42,Q42) | S42: =M42+R42 | T42: 398.5 | U42: =IF(H42=0,"",T42/H42) | V42: 9 | W42: =IF(H42=0,"",V42/H42) | X42: 0 | Y42: =IF(H42=0,"",X42/H42) | Z42: 0 | AA42: =IF(H42=0,"",Z42/H42) | AB42: 0 | AC42: =IF(H42=0,"",AB42/H42) | AD42: 0 | AE42: =IF(H42=0,"",AD42/H42) | AF42: 0 | AG42: =IF(H42=0,"",AF42/H42) | AH42: 31727.61 | AI42: =IF(H42=0,"",AH42/H42) | AJ42: 4400 | AK42: =IF(H42=0,"",AJ42/H42) | AL42: 754920 | AM42: =IF(H42=0,"",AL42/H42) | AN42: 0 | AO42: 0 | AP42: 0 | AQ42: 0 | AR42: 2496337.2 | AS42: 630000.8 | AT42: 0 | AU42: =AH42+AL42+AP42+AQ42+AR42+AS42+AT42 | AV42: =IF(H42=0,"",AU42/H42) | AW42: =IF(S42=0,"",AU42/S42) | AX42: 6 | AY42: =IF(H42=0,"",AX42/(H42/1000/12)) | AZ42: 5 | BA42: 45 | BB42: 22 | BC42: 0 | BD42: 25 | BE42: =BC42+BD42 | BF42: =BA42+BB42-BE42 | BG42: 3 | BH42: 0 | BI42: 0 | BJ42: 0 | BK42: =BI42+BJ42 | BL42: =BG42+BH42-BK42 | BM42: 0 | BN42: 1 | BO42: 0 | BP42: 1 | BQ42: =BO42+BP42 | BR42: =BM42+BN42-BQ42 | BS42: 0 | BT42: 0 | BU42: 0 | BV42: 0 | BW42: =BU42+BV42 | BX42: =BS42+BT42-BW42 | BY42: =BA42+BG42+BM42+BS42 | BZ42: =BB42+BH42+BN42+BT42 | CA42: =BE42+BK42+BQ42+BW42 | CB42: =BF42+BL42+BR42+BX42 | CC42: 28 | CD42: 1 | CE42: 1 | CF42: 2 | CG42: 0 | CH42: =CD42+CE42+CF42+CG42 | CI42: 1 | CJ42: 2 | CK42: 0 | CL42: 0 | CM42: =CI42+CJ42+CK42+CL42 | CN42: 592 | CO42: 20 | CP42: 16 | CQ42: 3 | CR42: =CN42+CO42+CP42+CQ42 | CS42: =CM42+CR42 | CT42: 638 | CU42: 4220 | CV42: 2940 | CW42: =IF(CU42=0,"",CV42/CU42) | DB42: =CX42+CY42-CZ42-DA42 | DC42: 0 | DD42: 0 | DE42: 0 | DF42: 0 | DG42: =DC42+DD42-DE42-DF42 | DH42: 0 | DI42: 0 | DJ42: 0 | DK42: 0 | DL42: =DH42+DI42-DJ42-DK42 | DM42: 0 | DN42: 4 | DO42: 1 | DP42: 3 | DQ42: =DM42+DN42-DO42-DP42 | DR42: =CX42+DC42+DH42+DM42 | DS42: =CY42+DD42+DI42+DN42 | DT42: =CZ42+DE42+DJ42+DO42 | DU42: =DA42+DF42+DK42+DP42 | DV42: =DB42+DG42+DL42+DQ42 | DW42: 58 | DX42: 5 | DY42: 3 | DZ42: 0 | EA42: 0 | EB42: 0 | EC42: 0 | ED42: 1 | EE42: 0 | EF42: 0 | EG42: 0 | EH42: 0 | EI42: 0 | EJ42: 0 | EK42: 0 | EL42: 0 | EM42: 0 | EN42: 0 | EO42: 0 | EP42: 0 | EQ42: 0 | ER42: 0 | ES42: 0 | ET42: 0 | EU42: 0 | EV42: 0 | EW42: 0 | EX42: 0 | EY42: 0 | EZ42: 0 | FA42: 0 | FB42: 0 | FC42: 0 | FD42: 0 | FE42: 0 | FF42: 0 | FG42: =SUM(DW42,DX42,DY42,DZ42,EA42,EB42,EC42,ED42,EE42,EF42,EG42,EH42,EI42,EJ42,EK42,EL42,EM42,EN42,EO42,EP42,EQ42,ER42,ES42,ET42,EU42,EV42,EW42,EX42,EY42,EZ42,FA42,FB42,FC42,FD42,FE42,FF42) | FH42: 0 | FI42: 0 | FJ42: 720 | FK42: 158 | FL42: 0 | FM42: 0 | FN42: 0 | FO42: 0 | FP42: 0 | FQ42: =FL42+FM42+FN42+FO42+FP42 | FR42: 0 | FS42: 0 | FT42: 0 | FU42: 0 | FV42: =FR42+FS42+FT42+FU42 | FW42: 4182405.2 | FX42: 17100 | FY42: 237024.64 | FZ42: 133400 | GA42: =FW42+FX42+FY42+FZ42 | GB42: =FV42+GA42 | GC42: 12873.6 | GD42: 0 | GE42: 8410.99 | GF42: 0 | GG42: =GC42+GD42+GE42+GF42 | GH42: 4083798.9 | GI42: 17100 | GJ42: 133400 | GK42: 237024.64 | GL42: =GH42+GI42+GJ42+GK42 | GM42: =GG42+GL42 | GN42: 1089.86 | GO42: 0 | GP42: 3393.64 | GQ42: 0 | GR42: =GN42+GO42+GP42+GQ42 | GS42: 1786 | GT42: 0 | GU42: 893 | GV42: 0 | GW42: =GS42+GT42+GU42+GV42 | GX42: =GM42+GR42+GW42 | GY42: 621692.64 | GZ42: 0 | HA42: =GY42+GZ42 | HB42: =IF(GX42=0,"",AU42/GX42) | HC42: =IF((GX42+GY42)=0,"",GB42/(GX42+GY42)) | HD42: =IF(GX42=0,"",GB42/GX42) | HE42: 30 | HF42: 3 | HG42: 45 | HH42: 23 | HI42: 30 | HJ42: =HF42+HI42 | HK42: =IF(HE42=0,"",HH42/HE42) | HL42: 22 | HM42: 5 | HN42: =IF(HL42=0,"",HM42/HL42)
A43: Liwonde | B43: Ntaja | C43: FY2025/26 | D43: 2025 | E43: 8 | F43: August | G43: Q2 | H43: 3820 | I43: 17 | J43: 0 | K43: 3 | L43: 0 | M43: =SUM(I43,J43,K43,L43) | N43: 3300.9 | O43: 92.7 | P43: 35.6 | Q43: 32.5 | R43: =SUM(N43,O43,P43,Q43) | S43: =M43+R43 | T43: 338.3 | U43: =IF(H43=0,"",T43/H43) | V43: 9 | W43: =IF(H43=0,"",V43/H43) | X43: 0 | Y43: =IF(H43=0,"",X43/H43) | Z43: 0 | AA43: =IF(H43=0,"",Z43/H43) | AB43: 0 | AC43: =IF(H43=0,"",AB43/H43) | AD43: 0 | AE43: =IF(H43=0,"",AD43/H43) | AF43: 0 | AG43: =IF(H43=0,"",AF43/H43) | AH43: 31727.61 | AI43: =IF(H43=0,"",AH43/H43) | AJ43: 3912 | AK43: =IF(H43=0,"",AJ43/H43) | AL43: 673337.38 | AM43: =IF(H43=0,"",AL43/H43) | AN43: 0 | AO43: 0 | AP43: 0 | AQ43: 0 | AR43: 2552411.7 | AS43: 625154.64 | AT43: 0 | AU43: =AH43+AL43+AP43+AQ43+AR43+AS43+AT43 | AV43: =IF(H43=0,"",AU43/H43) | AW43: =IF(S43=0,"",AU43/S43) | AX43: 6 | AY43: =IF(H43=0,"",AX43/(H43/1000/12)) | AZ43: 5 | BA43: 42 | BB43: 18 | BC43: 0 | BD43: 30 | BE43: =BC43+BD43 | BF43: =BA43+BB43-BE43 | BG43: 3 | BH43: 0 | BI43: 0 | BJ43: 0 | BK43: =BI43+BJ43 | BL43: =BG43+BH43-BK43 | BM43: 0 | BN43: 0 | BO43: 0 | BP43: 0 | BQ43: =BO43+BP43 | BR43: =BM43+BN43-BQ43 | BS43: 0 | BT43: 0 | BU43: 0 | BV43: 0 | BW43: =BU43+BV43 | BX43: =BS43+BT43-BW43 | BY43: =BA43+BG43+BM43+BS43 | BZ43: =BB43+BH43+BN43+BT43 | CA43: =BE43+BK43+BQ43+BW43 | CB43: =BF43+BL43+BR43+BX43 | CC43: 30 | CD43: 0 | CE43: 0 | CF43: 2 | CG43: 0 | CH43: =CD43+CE43+CF43+CG43 | CI43: 1 | CJ43: 2 | CK43: 0 | CL43: 0 | CM43: =CI43+CJ43+CK43+CL43 | CN43: 623 | CO43: 21 | CP43: 17 | CQ43: 3 | CR43: =CN43+CO43+CP43+CQ43 | CS43: =CM43+CR43 | CT43: 669 | CU43: 4220 | CV43: 2955 | CW43: =IF(CU43=0,"",CV43/CU43) | DB43: =CX43+CY43-CZ43-DA43 | DC43: 0 | DD43: 1 | DE43: 0 | DF43: 1 | DG43: =DC43+DD43-DE43-DF43 | DH43: 0 | DI43: 0 | DJ43: 0 | DK43: 0 | DL43: =DH43+DI43-DJ43-DK43 | DM43: 0 | DN43: 4 | DO43: 2 | DP43: 2 | DQ43: =DM43+DN43-DO43-DP43 | DR43: =CX43+DC43+DH43+DM43 | DS43: =CY43+DD43+DI43+DN43 | DT43: =CZ43+DE43+DJ43+DO43 | DU43: =DA43+DF43+DK43+DP43 | DV43: =DB43+DG43+DL43+DQ43 | DW43: 35 | DX43: 4 | DY43: 6 | DZ43: 0 | EA43: 0 | EB43: 0 | EC43: 0 | ED43: 0 | EE43: 0 | EF43: 0 | EG43: 0 | EH43: 0 | EI43: 0 | EJ43: 0 | EK43: 0 | EL43: 0 | EM43: 0 | EN43: 0 | EO43: 0 | EP43: 0 | EQ43: 0 | ER43: 0 | ES43: 0 | ET43: 0 | EU43: 0 | EV43: 0 | EW43: 0 | EX43: 0 | EY43: 0 | EZ43: 0 | FA43: 0 | FB43: 0 | FC43: 0 | FD43: 0 | FE43: 0 | FF43: 0 | FG43: =SUM(DW43,DX43,DY43,DZ43,EA43,EB43,EC43,ED43,EE43,EF43,EG43,EH43,EI43,EJ43,EK43,EL43,EM43,EN43,EO43,EP43,EQ43,ER43,ES43,ET43,EU43,EV43,EW43,EX43,EY43,EZ43,FA43,FB43,FC43,FD43,FE43,FF43) | FH43: 0 | FI43: 0 | FJ43: 288 | FK43: 149 | FL43: 0 | FM43: 0 | FN43: 0 | FO43: 0 | FP43: 0 | FQ43: =FL43+FM43+FN43+FO43+FP43 | FR43: 0 | FS43: 0 | FT43: 0 | FU43: 0 | FV43: =FR43+FS43+FT43+FU43 | FW43: 4225893.8 | FX43: 19700 | FY43: 155318.43 | FZ43: 115900 | GA43: =FW43+FX43+FY43+FZ43 | GB43: =FV43+GA43 | GC43: 15618.24 | GD43: 0 | GE43: 8410.99 | GF43: 0 | GG43: =GC43+GD43+GE43+GF43 | GH43: 4141173.8 | GI43: 19700 | GJ43: 108100 | GK43: 155318.43 | GL43: =GH43+GI43+GJ43+GK43 | GM43: =GG43+GL43 | GN43: 1089.86 | GO43: 0 | GP43: 3393.64 | GQ43: 0 | GR43: =GN43+GO43+GP43+GQ43 | GS43: 1786 | GT43: 0 | GU43: 893 | GV43: 0 | GW43: =GS43+GT43+GU43+GV43 | GX43: =GM43+GR43+GW43 | GY43: 408488.65 | GZ43: 244395.72 | HA43: =GY43+GZ43 | HB43: =IF(GX43=0,"",AU43/GX43) | HC43: =IF((GX43+GY43)=0,"",GB43/(GX43+GY43)) | HD43: =IF(GX43=0,"",GB43/GX43) | HE43: 28 | HF43: 1 | HG43: 33 | HH43: 18 | HI43: 14 | HJ43: =HF43+HI43 | HK43: =IF(HE43=0,"",HH43/HE43) | HL43: 10 | HM43: 2 | HN43: =IF(HL43=0,"",HM43/HL43)
A44: Liwonde | B44: Ntaja | C44: FY2025/26 | D44: 2025 | E44: 9 | F44: September | G44: Q2 | H44: 3400 | I44: 13 | J44: 0 | K44: 2 | L44: 0 | M44: =SUM(I44,J44,K44,L44) | N44: 3078.2 | O44: 54.1 | P44: 86.4 | Q44: 61.2 | R44: =SUM(N44,O44,P44,Q44) | S44: =M44+R44 | T44: 105.1 | U44: =IF(H44=0,"",T44/H44) | V44: 9 | W44: =IF(H44=0,"",V44/H44) | X44: 0 | Y44: =IF(H44=0,"",X44/H44) | Z44: 0 | AA44: =IF(H44=0,"",Z44/H44) | AB44: 0 | AC44: =IF(H44=0,"",AB44/H44) | AD44: 0 | AE44: =IF(H44=0,"",AD44/H44) | AF44: 0 | AG44: =IF(H44=0,"",AF44/H44) | AH44: 31727.61 | AI44: =IF(H44=0,"",AH44/H44) | AJ44: 3634 | AK44: =IF(H44=0,"",AJ44/H44) | AL44: 626862.04 | AM44: =IF(H44=0,"",AL44/H44) | AN44: 0 | AO44: 0 | AP44: 0 | AQ44: 0 | AR44: 2702468.5 | AS44: 615462.32 | AT44: 0 | AU44: =AH44+AL44+AP44+AQ44+AR44+AS44+AT44 | AV44: =IF(H44=0,"",AU44/H44) | AW44: =IF(S44=0,"",AU44/S44) | AX44: 6 | AY44: =IF(H44=0,"",AX44/(H44/1000/12)) | AZ44: 5 | BA44: 30 | BB44: 11 | BC44: 0 | BD44: 14 | BE44: =BC44+BD44 | BF44: =BA44+BB44-BE44 | BG44: 3 | BH44: 0 | BI44: 0 | BJ44: 0 | BK44: =BI44+BJ44 | BL44: =BG44+BH44-BK44 | BM44: 0 | BN44: 0 | BO44: 0 | BP44: 0 | BQ44: =BO44+BP44 | BR44: =BM44+BN44-BQ44 | BS44: 0 | BT44: 0 | BU44: 0 | BV44: 0 | BW44: =BU44+BV44 | BX44: =BS44+BT44-BW44 | BY44: =BA44+BG44+BM44+BS44 | BZ44: =BB44+BH44+BN44+BT44 | CA44: =BE44+BK44+BQ44+BW44 | CB44: =BF44+BL44+BR44+BX44 | CC44: 14 | CD44: 0 | CE44: 0 | CF44: 2 | CG44: 0 | CH44: =CD44+CE44+CF44+CG44 | CI44: 1 | CJ44: 2 | CK44: 0 | CL44: 0 | CM44: =CI44+CJ44+CK44+CL44 | CN44: 637 | CO44: 21 | CP44: 17 | CQ44: 3 | CR44: =CN44+CO44+CP44+CQ44 | CS44: =CM44+CR44 | CT44: 683 | CU44: 4220 | CV44: 2807.25 | CW44: =IF(CU44=0,"",CV44/CU44) | DB44: =CX44+CY44-CZ44-DA44 | DC44: 0 | DD44: 0 | DE44: 0 | DF44: 0 | DG44: =DC44+DD44-DE44-DF44 | DH44: 0 | DI44: 0 | DJ44: 0 | DK44: 0 | DL44: =DH44+DI44-DJ44-DK44 | DM44: 0 | DN44: 1 | DO44: 0 | DP44: 1 | DQ44: =DM44+DN44-DO44-DP44 | DR44: =CX44+DC44+DH44+DM44 | DS44: =CY44+DD44+DI44+DN44 | DT44: =CZ44+DE44+DJ44+DO44 | DU44: =DA44+DF44+DK44+DP44 | DV44: =DB44+DG44+DL44+DQ44 | DW44: 36 | DX44: 5 | DY44: 7 | DZ44: 0 | EA44: 0 | EB44: 1 | EC44: 1 | ED44: 0 | EE44: 0 | EF44: 1 | EG44: 0 | EH44: 0 | EI44: 0 | EJ44: 0 | EK44: 0 | EL44: 0 | EM44: 0 | EN44: 0 | EO44: 0 | EP44: 0 | EQ44: 0 | ER44: 0 | ES44: 0 | ET44: 0 | EU44: 0 | EV44: 0 | EW44: 0 | EX44: 0 | EY44: 0 | EZ44: 0 | FA44: 0 | FB44: 0 | FC44: 0 | FD44: 0 | FE44: 0 | FF44: 0 | FG44: =SUM(DW44,DX44,DY44,DZ44,EA44,EB44,EC44,ED44,EE44,EF44,EG44,EH44,EI44,EJ44,EK44,EL44,EM44,EN44,EO44,EP44,EQ44,ER44,ES44,ET44,EU44,EV44,EW44,EX44,EY44,EZ44,FA44,FB44,FC44,FD44,FE44,FF44) | FH44: 0 | FI44: 0 | FJ44: 720 | FK44: 170 | FL44: 0 | FM44: 0 | FN44: 0 | FO44: 0 | FP44: 0 | FQ44: =FL44+FM44+FN44+FO44+FP44 | FR44: 0 | FS44: 0 | FT44: 0 | FU44: 0 | FV44: =FR44+FS44+FT44+FU44 | FW44: 3912616.9 | FX44: 11500 | FY44: 292200 | FZ44: 263439.4 | GA44: =FW44+FX44+FY44+FZ44 | GB44: =FV44+GA44 | GC44: 13788.48 | GD44: 0 | GE44: 8410.99 | GF44: 0 | GG44: =GC44+GD44+GE44+GF44 | GH44: 3832541.8 | GI44: 11500 | GJ44: 262839.4 | GK44: 292200 | GL44: =GH44+GI44+GJ44+GK44 | GM44: =GG44+GL44 | GN44: 1089.86 | GO44: 0 | GP44: 3393.64 | GQ44: 0 | GR44: =GN44+GO44+GP44+GQ44 | GS44: 1786 | GT44: 0 | GU44: 893 | GV44: 0 | GW44: =GS44+GT44+GU44+GV44 | GX44: =GM44+GR44+GW44 | GY44: 408488.65 | GZ44: 244395.72 | HA44: =GY44+GZ44 | HB44: =IF(GX44=0,"",AU44/GX44) | HC44: =IF((GX44+GY44)=0,"",GB44/(GX44+GY44)) | HD44: =IF(GX44=0,"",GB44/GX44) | HE44: 20 | HF44: 1 | HG44: 30 | HH44: 11 | HI44: 14 | HJ44: =HF44+HI44 | HK44: =IF(HE44=0,"",HH44/HE44) | HL44: 28 | HM44: 2 | HN44: =IF(HL44=0,"",HM44/HL44)
A45: Liwonde | B45: Ntaja | C45: FY2025/26 | D45: 2025 | E45: 10 | F45: October | G45: Q3 | H45: 2850 | I45: 4 | J45: 0 | K45: 1 | L45: 0 | M45: =SUM(I45,J45,K45,L45) | N45: 2527.3 | O45: 40 | P45: 73.8 | Q45: 42.7 | R45: =SUM(N45,O45,P45,Q45) | S45: =M45+R45 | T45: 161.2 | U45: =IF(H45=0,"",T45/H45) | V45: 6 | W45: =IF(H45=0,"",V45/H45) | X45: 0 | Y45: =IF(H45=0,"",X45/H45) | Z45: 0 | AA45: =IF(H45=0,"",Z45/H45) | AB45: 0 | AC45: =IF(H45=0,"",AB45/H45) | AD45: 0 | AE45: =IF(H45=0,"",AD45/H45) | AF45: 0 | AG45: =IF(H45=0,"",AF45/H45) | AH45: 21151.74 | AI45: =IF(H45=0,"",AH45/H45) | AJ45: 2627 | AK45: =IF(H45=0,"",AJ45/H45) | AL45: 458514.29 | AM45: =IF(H45=0,"",AL45/H45) | AN45: 0 | AO45: 0 | AP45: 0 | AQ45: 0 | AR45: 0 | AS45: 625154.64 | AT45: 110000 | AU45: =AH45+AL45+AP45+AQ45+AR45+AS45+AT45 | AV45: =IF(H45=0,"",AU45/H45) | AW45: =IF(S45=0,"",AU45/S45) | AX45: 6 | AY45: =IF(H45=0,"",AX45/(H45/1000/12)) | AZ45: 5 | BA45: 27 | BB45: 10 | BC45: 0 | BD45: 16 | BE45: =BC45+BD45 | BF45: =BA45+BB45-BE45 | BG45: 3 | BH45: 0 | BI45: 0 | BJ45: 0 | BK45: =BI45+BJ45 | BL45: =BG45+BH45-BK45 | BM45: 0 | BN45: 0 | BO45: 0 | BP45: 0 | BQ45: =BO45+BP45 | BR45: =BM45+BN45-BQ45 | BS45: 0 | BT45: 0 | BU45: 0 | BV45: 0 | BW45: =BU45+BV45 | BX45: =BS45+BT45-BW45 | BY45: =BA45+BG45+BM45+BS45 | BZ45: =BB45+BH45+BN45+BT45 | CA45: =BE45+BK45+BQ45+BW45 | CB45: =BF45+BL45+BR45+BX45 | CC45: 16 | CD45: 0 | CE45: 0 | CF45: 2 | CG45: 0 | CH45: =CD45+CE45+CF45+CG45 | CI45: 1 | CJ45: 2 | CK45: 0 | CL45: 0 | CM45: =CI45+CJ45+CK45+CL45 | CN45: 653 | CO45: 21 | CP45: 17 | CQ45: 3 | CR45: =CN45+CO45+CP45+CQ45 | CS45: =CM45+CR45 | CT45: 699 | CU45: 4241.1 | CV45: 2821.04 | CW45: =IF(CU45=0,"",CV45/CU45) | DB45: =CX45+CY45-CZ45-DA45 | DC45: 0 | DD45: 0 | DE45: 0 | DF45: 0 | DG45: =DC45+DD45-DE45-DF45 | DH45: 0 | DI45: 0 | DJ45: 0 | DK45: 0 | DL45: =DH45+DI45-DJ45-DK45 | DM45: 0 | DN45: 4 | DO45: 3 | DP45: 1 | DQ45: =DM45+DN45-DO45-DP45 | DR45: =CX45+DC45+DH45+DM45 | DS45: =CY45+DD45+DI45+DN45 | DT45: =CZ45+DE45+DJ45+DO45 | DU45: =DA45+DF45+DK45+DP45 | DV45: =DB45+DG45+DL45+DQ45 | DW45: 18 | DX45: 6 | DY45: 4 | DZ45: 0 | EA45: 2 | EB45: 0 | EC45: 0 | ED45: 0 | EE45: 0 | EF45: 0 | EG45: 0 | EH45: 0 | EI45: 0 | EJ45: 0 | EK45: 0 | EL45: 0 | EM45: 0 | EN45: 0 | EO45: 0 | EP45: 0 | EQ45: 0 | ER45: 0 | ES45: 0 | ET45: 0 | EU45: 0 | EV45: 0 | EW45: 0 | EX45: 0 | EY45: 0 | EZ45: 0 | FA45: 0 | FB45: 0 | FC45: 0 | FD45: 0 | FE45: 0 | FF45: 0 | FG45: =SUM(DW45,DX45,DY45,DZ45,EA45,EB45,EC45,ED45,EE45,EF45,EG45,EH45,EI45,EJ45,EK45,EL45,EM45,EN45,EO45,EP45,EQ45,ER45,ES45,ET45,EU45,EV45,EW45,EX45,EY45,EZ45,FA45,FB45,FC45,FD45,FE45,FF45) | FH45: 1 | FI45: 264 | FJ45: 720 | FK45: 192 | FL45: 0 | FM45: 0 | FN45: 0 | FO45: 0 | FP45: 0 | FQ45: =FL45+FM45+FN45+FO45+FP45 | FR45: 3000 | FS45: 0 | FT45: 0 | FU45: 0 | FV45: =FR45+FS45+FT45+FU45 | FW45: 3166862.2 | FX45: 8500 | FY45: 201800 | FZ45: 224200 | GA45: =FW45+FX45+FY45+FZ45 | GB45: =FV45+GA45 | GC45: 6680.52 | GD45: 0 | GE45: 8410.99 | GF45: 0 | GG45: =GC45+GD45+GE45+GF45 | GH45: 3147072.6 | GI45: 8500 | GJ45: 224200 | GK45: 201800 | GL45: =GH45+GI45+GJ45+GK45 | GM45: =GG45+GL45 | GN45: 1089.86 | GO45: 0 | GP45: 3393.64 | GQ45: 0 | GR45: =GN45+GO45+GP45+GQ45 | GS45: 1786 | GT45: 0 | GU45: 893 | GV45: 0 | GW45: =GS45+GT45+GU45+GV45 | GX45: =GM45+GR45+GW45 | GY45: 405448.65 | GZ45: 296011.7 | HA45: =GY45+GZ45 | HB45: =IF(GX45=0,"",AU45/GX45) | HC45: =IF((GX45+GY45)=0,"",GB45/(GX45+GY45)) | HD45: =IF(GX45=0,"",GB45/GX45) | HE45: 18 | HF45: 1 | HG45: 24 | HH45: 10 | HI45: 14 | HJ45: =HF45+HI45 | HK45: =IF(HE45=0,"",HH45/HE45) | HL45: 60 | HM45: 6 | HN45: =IF(HL45=0,"",HM45/HL45)
A46: Liwonde | B46: Ntaja | C46: FY2025/26 | D46: 2025 | E46: 11 | F46: November | G46: Q3 | H46: 2810 | I46: 6 | J46: 0 | K46: 2 | L46: 0 | M46: =SUM(I46,J46,K46,L46) | N46: 2304.5 | O46: 53.2 | P46: 23.1 | Q46: 15 | R46: =SUM(N46,O46,P46,Q46) | S46: =M46+R46 | T46: 406.2 | U46: =IF(H46=0,"",T46/H46) | V46: 6 | W46: =IF(H46=0,"",V46/H46) | X46: 0 | Y46: =IF(H46=0,"",X46/H46) | Z46: 0 | AA46: =IF(H46=0,"",Z46/H46) | AB46: 0 | AC46: =IF(H46=0,"",AB46/H46) | AD46: 0 | AE46: =IF(H46=0,"",AD46/H46) | AF46: 0 | AG46: =IF(H46=0,"",AF46/H46) | AH46: 21151.74 | AI46: =IF(H46=0,"",AH46/H46) | AJ46: 2726 | AK46: =IF(H46=0,"",AJ46/H46) | AL46: 475064.86 | AM46: =IF(H46=0,"",AL46/H46) | AN46: 0 | AO46: 0 | AP46: 0 | AQ46: 0 | AR46: 2536578.9 | AS46: 625154.64 | AT46: 0 | AU46: =AH46+AL46+AP46+AQ46+AR46+AS46+AT46 | AV46: =IF(H46=0,"",AU46/H46) | AW46: =IF(S46=0,"",AU46/S46) | AX46: 6 | AY46: =IF(H46=0,"",AX46/(H46/1000/12)) | AZ46: 5 | BA46: 21 | BB46: 2 | BC46: 0 | BD46: 6 | BE46: =BC46+BD46 | BF46: =BA46+BB46-BE46 | BG46: 3 | BH46: 0 | BI46: 0 | BJ46: 0 | BK46: =BI46+BJ46 | BL46: =BG46+BH46-BK46 | BM46: 0 | BN46: 0 | BO46: 0 | BP46: 0 | BQ46: =BO46+BP46 | BR46: =BM46+BN46-BQ46 | BS46: 0 | BT46: 0 | BU46: 0 | BV46: 0 | BW46: =BU46+BV46 | BX46: =BS46+BT46-BW46 | BY46: =BA46+BG46+BM46+BS46 | BZ46: =BB46+BH46+BN46+BT46 | CA46: =BE46+BK46+BQ46+BW46 | CB46: =BF46+BL46+BR46+BX46 | CC46: 6 | CD46: 0 | CE46: 0 | CF46: 2 | CG46: 0 | CH46: =CD46+CE46+CF46+CG46 | CI46: 1 | CJ46: 2 | CK46: 0 | CL46: 0 | CM46: =CI46+CJ46+CK46+CL46 | CN46: 659 | CO46: 21 | CP46: 17 | CQ46: 3 | CR46: =CN46+CO46+CP46+CQ46 | CS46: =CM46+CR46 | CT46: 705 | CU46: 4283.511 | CV46: 2849.2504 | CW46: =IF(CU46=0,"",CV46/CU46) | DB46: =CX46+CY46-CZ46-DA46 | DC46: 0 | DD46: 0 | DE46: 0 | DF46: 0 | DG46: =DC46+DD46-DE46-DF46 | DH46: 0 | DI46: 0 | DJ46: 0 | DK46: 0 | DL46: =DH46+DI46-DJ46-DK46 | DM46: 0 | DN46: 2 | DO46: 0 | DP46: 2 | DQ46: =DM46+DN46-DO46-DP46 | DR46: =CX46+DC46+DH46+DM46 | DS46: =CY46+DD46+DI46+DN46 | DT46: =CZ46+DE46+DJ46+DO46 | DU46: =DA46+DF46+DK46+DP46 | DV46: =DB46+DG46+DL46+DQ46 | DW46: 23 | DX46: 3 | DY46: 1 | DZ46: 0 | EA46: 3 | EB46: 0 | EC46: 0 | ED46: 0 | EE46: 0 | EF46: 0 | EG46: 0 | EH46: 0 | EI46: 0 | EJ46: 0 | EK46: 0 | EL46: 0 | EM46: 0 | EN46: 0 | EO46: 0 | EP46: 0 | EQ46: 0 | ER46: 0 | ES46: 0 | ET46: 0 | EU46: 0 | EV46: 0 | EW46: 0 | EX46: 0 | EY46: 0 | EZ46: 0 | FA46: 0 | FB46: 0 | FC46: 0 | FD46: 0 | FE46: 0 | FF46: 0 | FG46: =SUM(DW46,DX46,DY46,DZ46,EA46,EB46,EC46,ED46,EE46,EF46,EG46,EH46,EI46,EJ46,EK46,EL46,EM46,EN46,EO46,EP46,EQ46,ER46,ES46,ET46,EU46,EV46,EW46,EX46,EY46,EZ46,FA46,FB46,FC46,FD46,FE46,FF46) | FH46: 0 | FI46: 0 | FJ46: 720 | FK46: 151 | FL46: 0 | FM46: 0 | FN46: 0 | FO46: 0 | FP46: 0 | FQ46: =FL46+FM46+FN46+FO46+FP46 | FR46: 3000 | FS46: 0 | FT46: 0 | FU46: 0 | FV46: =FR46+FS46+FT46+FU46 | FW46: 2918232.9 | FX46: 11300 | FY46: 72000 | FZ46: 70200 | GA46: =FW46+FX46+FY46+FZ46 | GB46: =FV46+GA46 | GC46: 8439.92 | GD46: 0 | GE46: 8410.99 | GF46: 0 | GG46: =GC46+GD46+GE46+GF46 | GH46: 2884808.1 | GI46: 11300 | GJ46: 70200 | GK46: 72000 | GL46: =GH46+GI46+GJ46+GK46 | GM46: =GG46+GL46 | GN46: 1089.86 | GO46: 0 | GP46: 3393.64 | GQ46: 0 | GR46: =GN46+GO46+GP46+GQ46 | GS46: 1786 | GT46: 0 | GU46: 893 | GV46: 0 | GW46: =GS46+GT46+GU46+GV46 | GX46: =GM46+GR46+GW46 | GY46: 448876.44 | GZ46: 320025.11 | HA46: =GY46+GZ46 | HB46: =IF(GX46=0,"",AU46/GX46) | HC46: =IF((GX46+GY46)=0,"",GB46/(GX46+GY46)) | HD46: =IF(GX46=0,"",GB46/GX46) | HE46: 6 | HF46: 1 | HG46: 20 | HH46: 2 | HI46: 14 | HJ46: =HF46+HI46 | HK46: =IF(HE46=0,"",HH46/HE46) | HL46: 60 | HM46: 6 | HN46: =IF(HL46=0,"",HM46/HL46)
A47: Liwonde | B47: Ntaja | C47: FY2025/26 | D47: 2025 | E47: 12 | F47: December | G47: Q3 | H47: 2580 | I47: 4 | J47: 3 | K47: 0 | L47: 0 | M47: =SUM(I47,J47,K47,L47) | N47: 2320.5 | O47: 9.5 | P47: 0 | Q47: 0 | R47: =SUM(N47,O47,P47,Q47) | S47: =M47+R47 | T47: 243 | U47: =IF(H47=0,"",T47/H47) | V47: 6 | W47: =IF(H47=0,"",V47/H47) | X47: 0 | Y47: =IF(H47=0,"",X47/H47) | Z47: 0 | AA47: =IF(H47=0,"",Z47/H47) | AB47: 0 | AC47: =IF(H47=0,"",AB47/H47) | AD47: 0 | AE47: =IF(H47=0,"",AD47/H47) | AF47: 0 | AG47: =IF(H47=0,"",AF47/H47) | AH47: 21151.74 | AI47: =IF(H47=0,"",AH47/H47) | AJ47: 3720 | AK47: =IF(H47=0,"",AJ47/H47) | AL47: 641239.3 | AM47: =IF(H47=0,"",AL47/H47) | AN47: 0 | AO47: 0 | AP47: 0 | AQ47: 0 | AR47: 2888042.2 | AS47: 504000.64 | AT47: 0 | AU47: =AH47+AL47+AP47+AQ47+AR47+AS47+AT47 | AV47: =IF(H47=0,"",AU47/H47) | AW47: =IF(S47=0,"",AU47/S47) | AX47: 6 | AY47: =IF(H47=0,"",AX47/(H47/1000/12)) | AZ47: 5 | BA47: 17 | BB47: 1 | BC47: 0 | BD47: 3 | BE47: =BC47+BD47 | BF47: =BA47+BB47-BE47 | BG47: 3 | BH47: 0 | BI47: 0 | BJ47: 0 | BK47: =BI47+BJ47 | BL47: =BG47+BH47-BK47 | BM47: 0 | BN47: 0 | BO47: 0 | BP47: 0 | BQ47: =BO47+BP47 | BR47: =BM47+BN47-BQ47 | BS47: 0 | BT47: 0 | BU47: 0 | BV47: 0 | BW47: =BU47+BV47 | BX47: =BS47+BT47-BW47 | BY47: =BA47+BG47+BM47+BS47 | BZ47: =BB47+BH47+BN47+BT47 | CA47: =BE47+BK47+BQ47+BW47 | CB47: =BF47+BL47+BR47+BX47 | CC47: 3 | CD47: 0 | CE47: 0 | CF47: 3 | CG47: 0 | CH47: =CD47+CE47+CF47+CG47 | CI47: 1 | CJ47: 2 | CK47: 0 | CL47: 0 | CM47: =CI47+CJ47+CK47+CL47 | CN47: 662 | CO47: 21 | CP47: 17 | CQ47: 3 | CR47: =CN47+CO47+CP47+CQ47 | CS47: =CM47+CR47 | CT47: 709 | CU47: 4326.84 | CV47: 2877.49 | CW47: =IF(CU47=0,"",CV47/CU47) | DB47: =CX47+CY47-CZ47-DA47 | DC47: 0 | DD47: 0 | DE47: 0 | DF47: 0 | DG47: =DC47+DD47-DE47-DF47 | DH47: 0 | DI47: 0 | DJ47: 0 | DK47: 0 | DL47: =DH47+DI47-DJ47-DK47 | DM47: 0 | DN47: 3 | DO47: 2 | DP47: 1 | DQ47: =DM47+DN47-DO47-DP47 | DR47: =CX47+DC47+DH47+DM47 | DS47: =CY47+DD47+DI47+DN47 | DT47: =CZ47+DE47+DJ47+DO47 | DU47: =DA47+DF47+DK47+DP47 | DV47: =DB47+DG47+DL47+DQ47 | DW47: 56 | DX47: 6 | DY47: 5 | DZ47: 0 | EA47: 0 | EB47: 0 | EC47: 0 | ED47: 0 | EE47: 0 | EF47: 0 | EG47: 0 | EH47: 0 | EI47: 0 | EJ47: 0 | EK47: 0 | EL47: 0 | EM47: 0 | EN47: 0 | EO47: 0 | EP47: 0 | EQ47: 0 | ER47: 0 | ES47: 0 | ET47: 0 | EU47: 0 | EV47: 0 | EW47: 0 | EX47: 0 | EY47: 0 | EZ47: 0 | FA47: 0 | FB47: 0 | FC47: 0 | FD47: 0 | FE47: 0 | FF47: 0 | FG47: =SUM(DW47,DX47,DY47,DZ47,EA47,EB47,EC47,ED47,EE47,EF47,EG47,EH47,EI47,EJ47,EK47,EL47,EM47,EN47,EO47,EP47,EQ47,ER47,ES47,ET47,EU47,EV47,EW47,EX47,EY47,EZ47,FA47,FB47,FC47,FD47,FE47,FF47) | FH47: 1 | FI47: 312 | FJ47: 720 | FK47: 179 | FL47: 0 | FM47: 0 | FN47: 0 | FO47: 0 | FP47: 0 | FQ47: =FL47+FM47+FN47+FO47+FP47 | FR47: 0 | FS47: 0 | FT47: 0 | FU47: 0 | FV47: =FR47+FS47+FT47+FU47 | FW47: 3146565.9 | FX47: 2000 | FY47: 97400 | FZ47: 25500 | GA47: =FW47+FX47+FY47+FZ47 | GB47: =FV47+GA47 | GC47: 6680.52 | GD47: 0 | GE47: 8410.99 | GF47: 0 | GG47: =GC47+GD47+GE47+GF47 | GH47: 2905065.9 | GI47: 2000 | GJ47: 25500 | GK47: 97400 | GL47: =GH47+GI47+GJ47+GK47 | GM47: =GG47+GL47 | GN47: 1089.86 | GO47: 0 | GP47: 3393.64 | GQ47: 0 | GR47: =GN47+GO47+GP47+GQ47 | GS47: 1786 | GT47: 0 | GU47: 893 | GV47: 0 | GW47: =GS47+GT47+GU47+GV47 | GX47: =GM47+GR47+GW47 | GY47: 444876.44 | GZ47: 342279.12 | HA47: =GY47+GZ47 | HB47: =IF(GX47=0,"",AU47/GX47) | HC47: =IF((GX47+GY47)=0,"",GB47/(GX47+GY47)) | HD47: =IF(GX47=0,"",GB47/GX47) | HE47: 3 | HF47: 1 | HG47: 18 | HH47: 1 | HI47: 0 | HJ47: =HF47+HI47 | HK47: =IF(HE47=0,"",HH47/HE47) | HL47: 28 | HM47: 4 | HN47: =IF(HL47=0,"",HM47/HL47)
A48: Liwonde | B48: Ntaja | C48: FY2025/26 | D48: 2026 | E48: 1 | F48: January | G48: Q4 | H48: 3204 | I48: 5 | J48: 0 | K48: 1 | L48: 0 | M48: 6 | N48: 2770.9 | O48: 87.1 | P48: 61.5 | Q48: 24.5 | R48: 2944 | S48: 2950 | T48: 254 | U48: 0.079275905 | V48: 8 | W48: 2.4968789 | X48: 0 | Y48: 0 | Z48: 0 | AA48: 0 | AB48: 0 | AC48: 0 | AD48: 0 | AE48: 0 | AF48: 0 | AG48: 0 | AH48: 28202.32 | AI48: 8.8022222 | AJ48: 4301 | AK48: 1.3423845 | AL48: 738369.43 | AM48: 230.45238 | AN48: 0 | AO48: 0 | AP48: 0 | AQ48: 0 | AR48: 0 | AS48: 494308.32 | AT48: 0 | AU48: 1260880.1 | AV48: 393.5331 | AW48: 427.41697 | AX48: 6 | AY48: 58.052434 | AZ48: 4 | BA48: 15 | BB48: 0 | BC48: 0 | BD48: 2 | BE48: 2 | BF48: 13 | BG48: 3 | BH48: 0 | BI48: 0 | BJ48: 0 | BK48: 0 | BL48: 3 | BM48: 0 | BN48: 0 | BO48: 0 | BP48: 0 | BQ48: 0 | BR48: 0 | BS48: 0 | BT48: 0 | BU48: 0 | BV48: 0 | BW48: 0 | BX48: 0 | BY48: 18 | BZ48: 0 | CA48: 2 | CB48: 16 | CC48: 2 | CD48: 0 | CE48: 0 | CF48: 3 | CG48: 0 | CH48: 3 | CI48: 1 | CJ48: 2 | CK48: 0 | CL48: 0 | CM48: 3 | CN48: 664 | CO48: 21 | CP48: 17 | CQ48: 3 | CR48: 705 | CS48: 708 | CT48: 711 | CU48: 4348 | CV48: 2891 | CW48: 0.6649034 | CX48: 0 | CY48: 0 | CZ48: 0 | DA48: 0 | DB48: 0 | DC48: 0 | DD48: 0 | DE48: 0 | DF48: 0 | DG48: 0 | DH48: 0 | DI48: 0 | DJ48: 0 | DK48: 0 | DL48: 0 | DM48: 0 | DN48: 0 | DO48: 0 | DP48: 0 | DQ48: 0 | DR48: 0 | DS48: 0 | DT48: 0 | DU48: 0 | DV48: 0 | DW48: 63 | DX48: 6 | DY48: 4 | DZ48: 2 | EA48: 4 | EB48: 0 | EC48: 0 | ED48: 0 | EE48: 0 | EF48: 0 | EG48: 0 | EH48: 0 | EI48: 0 | EJ48: 0 | EK48: 0 | EL48: 0 | EM48: 0 | EN48: 0 | EO48: 0 | EP48: 0 | EQ48: 0 | ER48: 0 | ES48: 0 | ET48: 0 | EU48: 0 | EV48: 0 | EW48: 0 | EX48: 0 | EY48: 0 | EZ48: 0 | FA48: 0 | FB48: 0 | FC48: 0 | FD48: 0 | FE48: 0 | FF48: 0 | FG48: 79 | FH48: 1 | FI48: 720 | FJ48: 720 | FK48: 96 | FL48: 0 | FM48: 0 | FN48: 0 | FO48: 0 | FP48: 0 | FQ48: 0 | FR48: 0 | FS48: 0 | FT48: 0 | FU48: 0 | FV48: 0 | FW48: 3495380 | FX48: 18500 | FY48: 116700 | FZ48: 186400 | GA48: 3816980 | GB48: 3816980 | GC48: 7560.22 | GD48: 0 | GE48: 8410.99 | GF48: 0 | GG48: 15971.21 | GH48: 3452567.4 | GI48: 18500 | GJ48: 186366.08 | GK48: 116700 | GL48: 3774133.5 | GM48: 3790104.7 | GN48: 1089.86 | GO48: 0 | GP48: 3393.64 | GQ48: 0 | GR48: 4483.5 | GS48: 1786 | GT48: 0 | GU48: 893 | GV48: 0 | GW48: 2679 | GX48: 3797267.2 | GY48: 444876.44 | GZ48: 232433.45 | HA48: 677309.89 | HB48: 3797267.2 | HC48: 444876.44 | HD48: 232433.45 | HE48: 11 | HF48: 1 | HG48: 16 | HH48: 0 | HI48: 0 | HK48: 0 | HL48: 30 | HM48: 3 | HN48: 10
A49: Liwonde | B49: Ntaja | C49: FY2025/26 | D49: 2026 | E49: 2 | F49: February | G49: Q4 | H49: 3033 | I49: 6 | J49: 0 | K49: 4 | L49: 0 | M49: =SUM(I49,J49,K49,L49) | N49: 2517.3 | O49: 131.8 | P49: 57.7 | Q49: 39.4 | R49: =SUM(N49,O49,P49,Q49) | S49: =M49+R49 | T49: 276.8 | U49: =IF(H49=0,"",T49/H49) | V49: 8 | W49: =IF(H49=0,"",V49/H49) | X49: 0 | Y49: =IF(H49=0,"",X49/H49) | Z49: 0 | AA49: =IF(H49=0,"",Z49/H49) | AB49: 0 | AC49: =IF(H49=0,"",AB49/H49) | AD49: 0 | AE49: =IF(H49=0,"",AD49/H49) | AF49: 0 | AG49: =IF(H49=0,"",AF49/H49) | AH49: 28202.32 | AI49: =IF(H49=0,"",AH49/H49) | AJ49: 2884 | AK49: =IF(H49=0,"",AJ49/H49) | AL49: 501478.91 | AM49: =IF(H49=0,"",AL49/H49) | AN49: 0 | AO49: 0 | AP49: 0 | AQ49: 0 | AR49: 2570883.3 | AS49: 0 | AT49: 0 | AU49: =AH49+AL49+AP49+AQ49+AR49+AS49+AT49 | AV49: =IF(H49=0,"",AU49/H49) | AW49: =IF(S49=0,"",AU49/S49) | AX49: 5 | AY49: =IF(H49=0,"",AX49/(H49/1000/12)) | AZ49: 5 | BA49: 13 | BB49: 2 | BC49: 0 | BD49: 0 | BE49: =BC49+BD49 | BF49: =BA49+BB49-BE49 | BG49: 3 | BH49: 0 | BI49: 0 | BJ49: 0 | BK49: =BI49+BJ49 | BL49: =BG49+BH49-BK49 | BM49: 0 | BN49: 0 | BO49: 0 | BP49: 0 | BQ49: =BO49+BP49 | BR49: =BM49+BN49-BQ49 | BS49: 0 | BT49: 0 | BU49: 0 | BV49: 0 | BW49: =BU49+BV49 | BX49: =BS49+BT49-BW49 | BY49: =BA49+BG49+BM49+BS49 | BZ49: =BB49+BH49+BN49+BT49 | CA49: =BE49+BK49+BQ49+BW49 | CB49: =BF49+BL49+BR49+BX49 | CC49: 0 | CD49: 0 | CE49: 0 | CF49: 3 | CG49: 0 | CH49: =CD49+CE49+CF49+CG49 | CI49: 1 | CJ49: 2 | CK49: 0 | CL49: 0 | CM49: =CI49+CJ49+CK49+CL49 | CN49: 664 | CO49: 21 | CP49: 17 | CQ49: 3 | CR49: =CN49+CO49+CP49+CQ49 | CS49: =CM49+CR49 | CT49: 711 | CU49: 4261 | CV49: 2833 | CW49: =IF(CU49=0,"",CV49/CU49) | DB49: =CX49+CY49-CZ49-DA49 | DC49: 0 | DD49: 0 | DE49: 0 | DF49: 0 | DG49: =DC49+DD49-DE49-DF49 | DH49: 0 | DI49: 0 | DJ49: 0 | DK49: 0 | DL49: =DH49+DI49-DJ49-DK49 | DM49: 0 | DN49: 0 | DO49: 0 | DP49: 0 | DQ49: =DM49+DN49-DO49-DP49 | DR49: =CX49+DC49+DH49+DM49 | DS49: =CY49+DD49+DI49+DN49 | DT49: =CZ49+DE49+DJ49+DO49 | DU49: =DA49+DF49+DK49+DP49 | DV49: =DB49+DG49+DL49+DQ49 | DW49: 51 | DX49: 6 | DY49: 3 | DZ49: 2 | EA49: 1 | EB49: 0 | EC49: 0 | ED49: 1 | EE49: 0 | EF49: 0 | EG49: 0 | EH49: 0 | EI49: 0 | EJ49: 0 | EK49: 0 | EL49: 0 | EM49: 0 | EN49: 0 | EO49: 0 | EP49: 0 | EQ49: 0 | ER49: 0 | ES49: 0 | ET49: 0 | EU49: 0 | EV49: 0 | EW49: 0 | EX49: 0 | EY49: 0 | EZ49: 0 | FA49: 0 | FB49: 0 | FC49: 0 | FD49: 0 | FE49: 0 | FF49: 0 | FG49: =SUM(DW49,DX49,DY49,DZ49,EA49,EB49,EC49,ED49,EE49,EF49,EG49,EH49,EI49,EJ49,EK49,EL49,EM49,EN49,EO49,EP49,EQ49,ER49,ES49,ET49,EU49,EV49,EW49,EX49,EY49,EZ49,FA49,FB49,FC49,FD49,FE49,FF49) | FH49: 1 | FI49: 600 | FJ49: 720 | FK49: 56 | FL49: 0 | FM49: 0 | FN49: 0 | FO49: 0 | FP49: 0 | FQ49: =FL49+FM49+FN49+FO49+FP49 | FR49: 0 | FS49: 0 | FT49: 0 | FU49: 0 | FV49: =FR49+FS49+FT49+FU49 | FW49: 3159978.8 | FX49: 28000 | FY49: 186600 | FZ49: 176100 | GA49: =FW49+FX49+FY49+FZ49 | GB49: =FV49+GA49 | GC49: 7560.22 | GD49: 0 | GE49: 8410.99 | GF49: 0 | GG49: =GC49+GD49+GE49+GF49 | GH49: 3135558.8 | GI49: 28000 | GJ49: 175500 | GK49: 186600 | GL49: =GH49+GI49+GJ49+GK49 | GM49: =GG49+GL49 | GN49: 1089.86 | GO49: 0 | GP49: 3393.64 | GQ49: 0 | GR49: =GN49+GO49+GP49+GQ49 | GS49: 1786 | GT49: 0 | GU49: 893 | GV49: 0 | GW49: =GS49+GT49+GU49+GV49 | GX49: =GM49+GR49+GW49 | GY49: 444876.44 | GZ49: 255567.16 | HA49: =GY49+GZ49 | HB49: =IF(GX49=0,"",AU49/GX49) | HC49: =IF((GX49+GY49)=0,"",GB49/(GX49+GY49)) | HD49: =IF(GX49=0,"",GB49/GX49) | HE49: 2 | HF49: 1 | HG49: 18 | HH49: 2 | HI49: 0 | HJ49: =HF49+HI49 | HK49: =IF(HE49=0,"",HH49/HE49) | HL49: 19 | HM49: 3 | HN49: =IF(HL49=0,"",HM49/HL49)
A50: Liwonde | B50: Ntaja | C50: FY2025/26 | D50: 2026 | E50: 3 | F50: March | G50: Q4 | H50: 2612 | I50: 4 | J50: 0 | K50: 1 | L50: 0 | M50: =SUM(I50,J50,K50,L50) | N50: 2214.5 | O50: 9.4 | P50: 67.9 | Q50: 56.2 | R50: =SUM(N50,O50,P50,Q50) | S50: =M50+R50 | T50: 259 | U50: =IF(H50=0,"",T50/H50) | V50: 8 | W50: =IF(H50=0,"",V50/H50) | X50: 0 | Y50: =IF(H50=0,"",X50/H50) | Z50: 0 | AA50: =IF(H50=0,"",Z50/H50) | AB50: 0 | AC50: =IF(H50=0,"",AB50/H50) | AD50: 0 | AE50: =IF(H50=0,"",AD50/H50) | AF50: 0 | AG50: =IF(H50=0,"",AF50/H50) | AH50: 28202.32 | AI50: =IF(H50=0,"",AH50/H50) | AJ50: 3390 | AK50: =IF(H50=0,"",AJ50/H50) | AL50: 19339 | AM50: =IF(H50=0,"",AL50/H50) | AN50: 0 | AO50: 0 | AP50: 0 | AQ50: 0 | AR50: 2512829.7 | AS50: 0 | AT50: 0 | AU50: =AH50+AL50+AP50+AQ50+AR50+AS50+AT50 | AV50: =IF(H50=0,"",AU50/H50) | AW50: =IF(S50=0,"",AU50/S50) | AX50: 5 | AY50: =IF(H50=0,"",AX50/(H50/1000/12)) | AZ50: 5 | BA50: 15 | BB50: 3 | BC50: 0 | BD50: 3 | BE50: =BC50+BD50 | BF50: =BA50+BB50-BE50 | BG50: 3 | BH50: 0 | BI50: 0 | BJ50: 0 | BK50: =BI50+BJ50 | BL50: =BG50+BH50-BK50 | BM50: 0 | BN50: 0 | BO50: 0 | BP50: 0 | BQ50: =BO50+BP50 | BR50: =BM50+BN50-BQ50 | BS50: 0 | BT50: 0 | BU50: 0 | BV50: 0 | BW50: =BU50+BV50 | BX50: =BS50+BT50-BW50 | BY50: =BA50+BG50+BM50+BS50 | BZ50: =BB50+BH50+BN50+BT50 | CA50: =BE50+BK50+BQ50+BW50 | CB50: =BF50+BL50+BR50+BX50 | CC50: 0 | CD50: 0 | CE50: 0 | CF50: 3 | CG50: 0 | CH50: =CD50+CE50+CF50+CG50 | CI50: 1 | CJ50: 2 | CK50: 0 | CL50: 0 | CM50: =CI50+CJ50+CK50+CL50 | CN50: 667 | CO50: 21 | CP50: 17 | CQ50: 3 | CR50: =CN50+CO50+CP50+CQ50 | CS50: =CM50+CR50 | CT50: 714 | CU50: 4303 | CV50: 2861 | CW50: =IF(CU50=0,"",CV50/CU50) | DB50: =CX50+CY50-CZ50-DA50 | DC50: 0 | DD50: 0 | DE50: 0 | DF50: 0 | DG50: =DC50+DD50-DE50-DF50 | DH50: 0 | DI50: 0 | DJ50: 0 | DK50: 0 | DL50: =DH50+DI50-DJ50-DK50 | DM50: 0 | DN50: 0 | DO50: 0 | DP50: 0 | DQ50: =DM50+DN50-DO50-DP50 | DR50: =CX50+DC50+DH50+DM50 | DS50: =CY50+DD50+DI50+DN50 | DT50: =CZ50+DE50+DJ50+DO50 | DU50: =DA50+DF50+DK50+DP50 | DV50: =DB50+DG50+DL50+DQ50 | DW50: 55 | DX50: 11 | DY50: 3 | DZ50: 2 | EA50: 2 | EB50: 0 | EC50: 0 | ED50: 1 | EE50: 0 | EF50: 0 | EG50: 0 | EH50: 0 | EI50: 0 | EJ50: 0 | EK50: 0 | EL50: 0 | EM50: 0 | EN50: 0 | EO50: 0 | EP50: 0 | EQ50: 0 | ER50: 0 | ES50: 0 | ET50: 0 | EU50: 0 | EV50: 0 | EW50: 0 | EX50: 0 | EY50: 0 | EZ50: 0 | FA50: 0 | FB50: 0 | FC50: 0 | FD50: 0 | FE50: 0 | FF50: 0 | FG50: =SUM(DW50,DX50,DY50,DZ50,EA50,EB50,EC50,ED50,EE50,EF50,EG50,EH50,EI50,EJ50,EK50,EL50,EM50,EN50,EO50,EP50,EQ50,ER50,ES50,ET50,EU50,EV50,EW50,EX50,EY50,EZ50,FA50,FB50,FC50,FD50,FE50,FF50) | FH50: 0 | FI50: 0 | FJ50: 720 | FK50: 119 | FL50: 0 | FM50: 0 | FN50: 0 | FO50: 0 | FP50: 0 | FQ50: =FL50+FM50+FN50+FO50+FP50 | FR50: 0 | FS50: 0 | FT50: 0 | FU50: 0 | FV50: =FR50+FS50+FT50+FU50 | FW50: 2785030 | FX50: 2000 | FY50: 265500 | FZ50: 206600 | GA50: =FW50+FX50+FY50+FZ50 | GB50: =FV50+GA50 | GC50: 2759255.9 | GD50: 0 | GE50: 206600 | GF50: 265500 | GG50: =GC50+GD50+GE50+GF50 | GH50: 2759255.9 | GI50: 2000 | GJ50: 206600 | GK50: 265500 | GL50: =GH50+GI50+GJ50+GK50 | GM50: =GG50+GL50 | GN50: 1089.86 | GO50: 0 | GP50: 3393.64 | GQ50: 0 | GR50: =GN50+GO50+GP50+GQ50 | GS50: 1786 | GT50: 0 | GU50: 893 | GV50: 0 | GW50: =GS50+GT50+GU50+GV50 | GX50: =GM50+GR50+GW50 | GY50: 670270.15 | GZ50: 17475.82 | HA50: =GY50+GZ50 | HB50: =IF(GX50=0,"",AU50/GX50) | HC50: =IF((GX50+GY50)=0,"",GB50/(GX50+GY50)) | HD50: =IF(GX50=0,"",GB50/GX50) | HE50: 10 | HF50: 1 | HG50: 18 | HH50: 3 | HI50: 14 | HJ50: =HF50+HI50 | HK50: =IF(HE50=0,"",HH50/HE50) | HL50: 23 | HM50: 3 | HN50: =IF(HL50=0,"",HM50/HL50)
A51: Mangochi | B51: Mangochi | C51: FY2025/26 | D51: 2025 | E51: 4 | F51: April | G51: Q1 | H51: 121625 | I51: 50468 | J51: 0 | K51: 193 | L51: 0 | M51: =SUM(I51,J51,K51,L51) | N51: 17179.5 | O51: 3825.4 | P51: 7141.5 | Q51: 2594 | R51: =SUM(N51,O51,P51,Q51) | S51: =M51+R51 | T51: 40223.6 | U51: =IF(H51=0,"",T51/H51) | V51: 350 | W51: =IF(H51=0,"",V51/H51) | X51: 0 | Y51: =IF(H51=0,"",X51/H51) | Z51: 0 | AA51: =IF(H51=0,"",Z51/H51) | AB51: 0 | AC51: =IF(H51=0,"",AB51/H51) | AD51: 0 | AE51: =IF(H51=0,"",AD51/H51) | AF51: 0 | AG51: =IF(H51=0,"",AF51/H51) | AH51: 8375185 | AI51: =IF(H51=0,"",AH51/H51) | AJ51: 42853.11 | AK51: =IF(H51=0,"",AJ51/H51) | AL51: 7183414.8 | AM51: =IF(H51=0,"",AL51/H51) | AN51: 7060 | AO51: 625.91 | AP51: 1711237.9 | AQ51: 0 | AR51: 30379530 | AS51: 3518439.1 | AT51: 2246300 | AU51: =AH51+AL51+AP51+AQ51+AR51+AS51+AT51 | AV51: =IF(H51=0,"",AU51/H51) | AW51: =IF(S51=0,"",AU51/S51) | AX51: 25 | AY51: =IF(H51=0,"",AX51/(H51/1000/12)) | AZ51: 29 | BA51: 1515 | BB51: 144 | BC51: 0 | BD51: 77 | BE51: =BC51+BD51 | BF51: =BA51+BB51-BE51 | BG51: 4 | BH51: 0 | BI51: 0 | BJ51: 0 | BK51: =BI51+BJ51 | BL51: =BG51+BH51-BK51 | BM51: 16 | BN51: 2 | BO51: 0 | BP51: 4 | BQ51: =BO51+BP51 | BR51: =BM51+BN51-BQ51 | BS51: 0 | BT51: 0 | BU51: 0 | BV51: 0 | BW51: =BU51+BV51 | BX51: =BS51+BT51-BW51 | BY51: =BA51+BG51+BM51+BS51 | BZ51: =BB51+BH51+BN51+BT51 | CA51: =BE51+BK51+BQ51+BW51 | CB51: =BF51+BL51+BR51+BX51 | CC51: 77 | CD51: 2329 | CE51: 3 | CF51: 203 | CG51: 10 | CH51: =CD51+CE51+CF51+CG51 | CI51: 4079 | CJ51: 4 | CK51: 0 | CL51: 0 | CM51: =CI51+CJ51+CK51+CL51 | CN51: 2997 | CO51: 148 | CP51: 402 | CQ51: 68 | CR51: =CN51+CO51+CP51+CQ51 | CS51: =CM51+CR51 | CT51: 10243 | CU51: 51306 | CV51: 47099 | CW51: =IF(CU51=0,"",CV51/CU51) | DB51: =CX51+CY51-CZ51-DA51 | DC51: 0 | DD51: 0 | DE51: 0 | DF51: 0 | DG51: =DC51+DD51-DE51-DF51 | DH51: 0 | DI51: 0 | DJ51: 0 | DK51: 0 | DL51: =DH51+DI51-DJ51-DK51 | DM51: 151 | DN51: 7 | DO51: 0 | DP51: 0 | DQ51: =DM51+DN51-DO51-DP51 | DR51: =CX51+DC51+DH51+DM51 | DS51: =CY51+DD51+DI51+DN51 | DT51: =CZ51+DE51+DJ51+DO51 | DU51: =DA51+DF51+DK51+DP51 | DV51: =DB51+DG51+DL51+DQ51 | DW51: 83 | DX51: 42 | DY51: 18 | DZ51: 11 | EA51: 8 | EB51: 5 | EC51: 2 | ED51: 1 | EE51: 0 | EF51: 0 | EG51: 0 | EH51: 0 | EI51: 0 | EJ51: 9 | EK51: 6 | EL51: 1 | EM51: 0 | EN51: 0 | EO51: 0 | EP51: 0 | EQ51: 0 | ER51: 0 | ES51: 0 | ET51: 0 | EU51: 0 | EV51: 0 | EW51: 0 | EX51: 0 | EY51: 0 | EZ51: 0 | FA51: 0 | FB51: 0 | FC51: 0 | FD51: 0 | FE51: 0 | FF51: 0 | FG51: =SUM(DW51,DX51,DY51,DZ51,EA51,EB51,EC51,ED51,EE51,EF51,EG51,EH51,EI51,EJ51,EK51,EL51,EM51,EN51,EO51,EP51,EQ51,ER51,ES51,ET51,EU51,EV51,EW51,EX51,EY51,EZ51,FA51,FB51,FC51,FD51,FE51,FF51) | FH51: 7 | FI51: 563 | FJ51: 0 | FK51: 108 | FL51: 0 | FM51: 0 | FN51: 0 | FO51: 0 | FP51: 0 | FQ51: =FL51+FM51+FN51+FO51+FP51 | FR51: 46196455 | FS51: 0 | FT51: 0 | FU51: 0 | FV51: =FR51+FS51+FT51+FU51 | FW51: 21896688 | FX51: 817055 | FY51: 12566346 | FZ51: 21722776 | GA51: =FW51+FX51+FY51+FZ51 | GB51: =FV51+GA51 | GC51: 45911688 | GD51: 0 | GE51: 631769.21 | GF51: 0 | GG51: =GC51+GD51+GE51+GF51 | GH51: 21842010 | GI51: 813155 | GJ51: 21697776 | GK51: 12162734 | GL51: =GH51+GI51+GJ51+GK51 | GM51: =GG51+GL51 | GN51: 2215377 | GO51: 0 | GP51: 13574.56 | GQ51: 0 | GR51: =GN51+GO51+GP51+GQ51 | GS51: 3642547 | GT51: 0 | GU51: 3572 | GV51: 0 | GW51: =GS51+GT51+GU51+GV51 | GX51: =GM51+GR51+GW51 | GY51: 1.8535024e+08 | GZ51: 4.4318396e+08 | HA51: =GY51+GZ51 | HB51: =IF(GX51=0,"",AU51/GX51) | HC51: =IF((GX51+GY51)=0,"",GB51/(GX51+GY51)) | HD51: =IF(GX51=0,"",GB51/GX51) | HE51: 0 | HF51: 1 | HG51: 1600 | HH51: 146 | HI51: 11364 | HJ51: =HF51+HI51 | HK51: =IF(HE51=0,"",HH51/HE51) | HL51: 19 | HM51: 0 | HN51: =IF(HL51=0,"",HM51/HL51)
A52: Mangochi | B52: Mangochi | C52: FY2025/26 | D52: 2025 | E52: 5 | F52: May | G52: Q1 | H52: 129093 | I52: 59315 | J52: 0 | K52: 130 | L52: 0 | M52: =SUM(I52,J52,K52,L52) | N52: 18803.9 | O52: 4278.2 | P52: 4180.1 | Q52: 1790.1 | R52: =SUM(N52,O52,P52,Q52) | S52: =M52+R52 | T52: 40595.7 | U52: =IF(H52=0,"",T52/H52) | V52: 350 | W52: =IF(H52=0,"",V52/H52) | X52: 0 | Y52: =IF(H52=0,"",X52/H52) | Z52: 0 | AA52: =IF(H52=0,"",Z52/H52) | AB52: 0 | AC52: =IF(H52=0,"",AB52/H52) | AD52: 0 | AE52: =IF(H52=0,"",AD52/H52) | AF52: 0 | AG52: =IF(H52=0,"",AF52/H52) | AH52: 8375185 | AI52: =IF(H52=0,"",AH52/H52) | AJ52: 47291.89 | AK52: =IF(H52=0,"",AJ52/H52) | AL52: 7925478.9 | AM52: =IF(H52=0,"",AL52/H52) | AN52: 4691 | AO52: 324.66 | AP52: 888550 | AQ52: 0 | AR52: 31556136 | AS52: 3612117 | AT52: 2253550 | AU52: =AH52+AL52+AP52+AQ52+AR52+AS52+AT52 | AV52: =IF(H52=0,"",AU52/H52) | AW52: =IF(S52=0,"",AU52/S52) | AX52: 25 | AY52: =IF(H52=0,"",AX52/(H52/1000/12)) | AZ52: 29 | BA52: 1582 | BB52: 146 | BC52: 0 | BD52: 88 | BE52: =BC52+BD52 | BF52: =BA52+BB52-BE52 | BG52: 4 | BH52: 0 | BI52: 0 | BJ52: 0 | BK52: =BI52+BJ52 | BL52: =BG52+BH52-BK52 | BM52: 18 | BN52: 5 | BO52: 0 | BP52: 1 | BQ52: =BO52+BP52 | BR52: =BM52+BN52-BQ52 | BS52: 0 | BT52: 0 | BU52: 0 | BV52: 0 | BW52: =BU52+BV52 | BX52: =BS52+BT52-BW52 | BY52: =BA52+BG52+BM52+BS52 | BZ52: =BB52+BH52+BN52+BT52 | CA52: =BE52+BK52+BQ52+BW52 | CB52: =BF52+BL52+BR52+BX52 | CC52: 89 | CD52: 2316 | CE52: 58 | CF52: 124 | CG52: 10 | CH52: =CD52+CE52+CF52+CG52 | CI52: 4110 | CJ52: 4 | CK52: 0 | CL52: 0 | CM52: =CI52+CJ52+CK52+CL52 | CN52: 3075 | CO52: 148 | CP52: 403 | CQ52: 68 | CR52: =CN52+CO52+CP52+CQ52 | CS52: =CM52+CR52 | CT52: 10316 | CU52: 51381 | CV52: 47524 | CW52: =IF(CU52=0,"",CV52/CU52) | DB52: =CX52+CY52-CZ52-DA52 | DC52: 0 | DD52: 0 | DE52: 0 | DF52: 0 | DG52: =DC52+DD52-DE52-DF52 | DH52: 0 | DI52: 0 | DJ52: 0 | DK52: 0 | DL52: =DH52+DI52-DJ52-DK52 | DM52: 158 | DN52: 7 | DO52: 0 | DP52: 0 | DQ52: =DM52+DN52-DO52-DP52 | DR52: =CX52+DC52+DH52+DM52 | DS52: =CY52+DD52+DI52+DN52 | DT52: =CZ52+DE52+DJ52+DO52 | DU52: =DA52+DF52+DK52+DP52 | DV52: =DB52+DG52+DL52+DQ52 | DW52: 86 | DX52: 53 | DY52: 20 | DZ52: 14 | EA52: 13 | EB52: 4 | EC52: 0 | ED52: 3 | EE52: 0 | EF52: 3 | EG52: 0 | EH52: 0 | EI52: 0 | EJ52: 12 | EK52: 7 | EL52: 0 | EM52: 0 | EN52: 0 | EO52: 0 | EP52: 0 | EQ52: 1 | ER52: 0 | ES52: 0 | ET52: 0 | EU52: 0 | EV52: 0 | EW52: 0 | EX52: 0 | EY52: 0 | EZ52: 0 | FA52: 0 | FB52: 0 | FC52: 0 | FD52: 0 | FE52: 0 | FF52: 0 | FG52: =SUM(DW52,DX52,DY52,DZ52,EA52,EB52,EC52,ED52,EE52,EF52,EG52,EH52,EI52,EJ52,EK52,EL52,EM52,EN52,EO52,EP52,EQ52,ER52,ES52,ET52,EU52,EV52,EW52,EX52,EY52,EZ52,FA52,FB52,FC52,FD52,FE52,FF52) | FH52: 6 | FI52: 662 | FJ52: 22 | FK52: 64.75 | FL52: 0 | FM52: 0 | FN52: 0 | FO52: 0 | FP52: 0 | FQ52: =FL52+FM52+FN52+FO52+FP52 | FR52: 64335797 | FS52: 193901.66 | FT52: 18567.22 | FU52: 0 | FV52: =FR52+FS52+FT52+FU52 | FW52: 25322673 | FX52: 916350 | FY52: 8683750 | FZ52: 12700421 | GA52: =FW52+FX52+FY52+FZ52 | GB52: =FV52+GA52 | GC52: 44918275 | GD52: 0 | GE52: 406903.66 | GF52: 0 | GG52: =GC52+GD52+GE52+GF52 | GH52: 25280853 | GI52: 909385.32 | GJ52: 12700421 | GK52: 8391748.9 | GL52: =GH52+GI52+GJ52+GK52 | GM52: =GG52+GL52 | GN52: 2232800 | GO52: 0 | GP52: 13574.56 | GQ52: 0 | GR52: =GN52+GO52+GP52+GQ52 | GS52: 3670230 | GT52: 0 | GU52: 3572 | GV52: 0 | GW52: =GS52+GT52+GU52+GV52 | GX52: =GM52+GR52+GW52 | GY52: 1.8061971e+08 | GZ52: 4.3461158e+08 | HA52: =GY52+GZ52 | HB52: =IF(GX52=0,"",AU52/GX52) | HC52: =IF((GX52+GY52)=0,"",GB52/(GX52+GY52)) | HD52: =IF(GX52=0,"",GB52/GX52) | HE52: 1666 | HF52: 1 | HG52: 1666 | HH52: 151 | HI52: 14777 | HJ52: =HF52+HI52 | HK52: =IF(HE52=0,"",HH52/HE52) | HL52: 38 | HM52: 3 | HN52: =IF(HL52=0,"",HM52/HL52)
A53: Mangochi | B53: Mangochi | C53: FY2025/26 | D53: 2025 | E53: 6 | F53: June | G53: Q1 | H53: 163707 | I53: 75001 | J53: 0 | K53: 254 | L53: 0 | M53: =SUM(I53,J53,K53,L53) | N53: 18415.2 | O53: 4947.5 | P53: 2750 | Q53: 2308.7 | R53: =SUM(N53,O53,P53,Q53) | S53: =M53+R53 | T53: 60030.6 | U53: =IF(H53=0,"",T53/H53) | V53: 270 | W53: =IF(H53=0,"",V53/H53) | X53: 0 | Y53: =IF(H53=0,"",X53/H53) | Z53: 0 | AA53: =IF(H53=0,"",Z53/H53) | AB53: 0 | AC53: =IF(H53=0,"",AB53/H53) | AD53: 0 | AE53: =IF(H53=0,"",AD53/H53) | AF53: 0 | AG53: =IF(H53=0,"",AF53/H53) | AH53: 6460857 | AI53: =IF(H53=0,"",AH53/H53) | AJ53: 49898.34 | AK53: =IF(H53=0,"",AJ53/H53) | AL53: 8361218.7 | AM53: =IF(H53=0,"",AL53/H53) | AN53: 386 | AO53: 291.21 | AP53: 796168.02 | AQ53: 0 | AR53: 29055452 | AS53: 4268319.4 | AT53: 2245900 | AU53: =AH53+AL53+AP53+AQ53+AR53+AS53+AT53 | AV53: =IF(H53=0,"",AU53/H53) | AW53: =IF(S53=0,"",AU53/S53) | AX53: 24 | AY53: =IF(H53=0,"",AX53/(H53/1000/12)) | AZ53: 29 | BA53: 1640 | BB53: 144 | BC53: 0 | BD53: 57 | BE53: =BC53+BD53 | BF53: =BA53+BB53-BE53 | BG53: 4 | BH53: 0 | BI53: 0 | BJ53: 0 | BK53: =BI53+BJ53 | BL53: =BG53+BH53-BK53 | BM53: 22 | BN53: 0 | BO53: 0 | BP53: 8 | BQ53: =BO53+BP53 | BR53: =BM53+BN53-BQ53 | BS53: 0 | BT53: 0 | BU53: 0 | BV53: 0 | BW53: =BU53+BV53 | BX53: =BS53+BT53-BW53 | BY53: =BA53+BG53+BM53+BS53 | BZ53: =BB53+BH53+BN53+BT53 | CA53: =BE53+BK53+BQ53+BW53 | CB53: =BF53+BL53+BR53+BX53 | CC53: 65 | CD53: 2257 | CE53: 57 | CF53: 124 | CG53: 9 | CH53: =CD53+CE53+CF53+CG53 | CI53: 4299 | CJ53: 4 | CK53: 0 | CL53: 0 | CM53: =CI53+CJ53+CK53+CL53 | CN53: 3132 | CO53: 148 | CP53: 411 | CQ53: 68 | CR53: =CN53+CO53+CP53+CQ53 | CS53: =CM53+CR53 | CT53: 10509 | CU53: 51456 | CV53: 47809 | CW53: =IF(CU53=0,"",CV53/CU53) | DB53: =CX53+CY53-CZ53-DA53 | DC53: 0 | DD53: 0 | DE53: 0 | DF53: 0 | DG53: =DC53+DD53-DE53-DF53 | DH53: 0 | DI53: 0 | DJ53: 0 | DK53: 0 | DL53: =DH53+DI53-DJ53-DK53 | DM53: 165 | DN53: 6 | DO53: 0 | DP53: 0 | DQ53: =DM53+DN53-DO53-DP53 | DR53: =CX53+DC53+DH53+DM53 | DS53: =CY53+DD53+DI53+DN53 | DT53: =CZ53+DE53+DJ53+DO53 | DU53: =DA53+DF53+DK53+DP53 | DV53: =DB53+DG53+DL53+DQ53 | DW53: 90 | DX53: 52 | DY53: 24 | DZ53: 12 | EA53: 8 | EB53: 5 | EC53: 2 | ED53: 1 | EE53: 0 | EF53: 1 | EG53: 1 | EH53: 0 | EI53: 0 | EJ53: 10 | EK53: 6 | EL53: 0 | EM53: 0 | EN53: 0 | EO53: 0 | EP53: 0 | EQ53: 0 | ER53: 0 | ES53: 0 | ET53: 0 | EU53: 0 | EV53: 0 | EW53: 0 | EX53: 0 | EY53: 0 | EZ53: 0 | FA53: 0 | FB53: 0 | FC53: 0 | FD53: 0 | FE53: 0 | FF53: 0 | FG53: =SUM(DW53,DX53,DY53,DZ53,EA53,EB53,EC53,ED53,EE53,EF53,EG53,EH53,EI53,EJ53,EK53,EL53,EM53,EN53,EO53,EP53,EQ53,ER53,ES53,ET53,EU53,EV53,EW53,EX53,EY53,EZ53,FA53,FB53,FC53,FD53,FE53,FF53) | FH53: 6 | FI53: 637.25 | FJ53: 0 | FK53: 17.25 | FL53: 0 | FM53: 0 | FN53: 0 | FO53: 0 | FP53: 0 | FQ53: =FL53+FM53+FN53+FO53+FP53 | FR53: 182367865 | FS53: 294867.22 | FT53: 0 | FU53: 70200 | FV53: =FR53+FS53+FT53+FU53 | FW53: 22961055 | FX53: 1051600 | FY53: 10934502 | FZ53: 8310100 | GA53: =FW53+FX53+FY53+FZ53 | GB53: =FV53+GA53 | GC53: 34522633 | GD53: 0 | GE53: 823308.52 | GF53: 0 | GG53: =GC53+GD53+GE53+GF53 | GH53: 22966460 | GI53: 1051600 | GJ53: 8310100 | GK53: 10791664 | GL53: =GH53+GI53+GJ53+GK53 | GM53: =GG53+GL53 | GN53: 2040081 | GO53: 0 | GP53: 20361.84 | GQ53: 0 | GR53: =GN53+GO53+GP53+GQ53 | GS53: 3355001 | GT53: 0 | GU53: 5358 | GV53: 0 | GW53: =GS53+GT53+GU53+GV53 | GX53: =GM53+GR53+GW53 | GY53: 72844644 | GZ53: 4.2053644e+08 | HA53: =GY53+GZ53 | HB53: =IF(GX53=0,"",AU53/GX53) | HC53: =IF((GX53+GY53)=0,"",GB53/(GX53+GY53)) | HD53: =IF(GX53=0,"",GB53/GX53) | HE53: 1753 | HF53: 1 | HG53: 1745 | HH53: 144 | HI53: 11792 | HJ53: =HF53+HI53 | HK53: =IF(HE53=0,"",HH53/HE53) | HL53: 38 | HM53: 6 | HN53: =IF(HL53=0,"",HM53/HL53)
A54: Mangochi | B54: Mangochi | C54: FY2025/26 | D54: 2025 | E54: 7 | F54: July | G54: Q2 | H54: 164857 | I54: 64837 | J54: 0 | K54: 221 | L54: 0 | M54: =SUM(I54,J54,K54,L54) | N54: 30127 | O54: 5305.6 | P54: 4390.5 | Q54: 3451 | R54: =SUM(N54,O54,P54,Q54) | S54: =M54+R54 | T54: 56524.9 | U54: =IF(H54=0,"",T54/H54) | V54: 252 | W54: =IF(H54=0,"",V54/H54) | X54: 0 | Y54: =IF(H54=0,"",X54/H54) | Z54: 0 | AA54: =IF(H54=0,"",Z54/H54) | AB54: 0 | AC54: =IF(H54=0,"",AB54/H54) | AD54: 0 | AE54: =IF(H54=0,"",AD54/H54) | AF54: 0 | AG54: =IF(H54=0,"",AF54/H54) | AH54: 6030133.2 | AI54: =IF(H54=0,"",AH54/H54) | AJ54: 46701.2 | AK54: =IF(H54=0,"",AJ54/H54) | AL54: 7826728.9 | AM54: =IF(H54=0,"",AL54/H54) | AN54: 1324 | AO54: 101 | AP54: 490807.68 | AQ54: 0 | AR54: 29055752 | AS54: 4386683.5 | AT54: 2822180 | AU54: =AH54+AL54+AP54+AQ54+AR54+AS54+AT54 | AV54: =IF(H54=0,"",AU54/H54) | AW54: =IF(S54=0,"",AU54/S54) | AX54: 24 | AY54: =IF(H54=0,"",AX54/(H54/1000/12)) | AZ54: 28 | BA54: 1727 | BB54: 151 | BC54: 0 | BD54: 49 | BE54: =BC54+BD54 | BF54: =BA54+BB54-BE54 | BG54: 4 | BH54: 2 | BI54: 0 | BJ54: 1 | BK54: =BI54+BJ54 | BL54: =BG54+BH54-BK54 | BM54: 14 | BN54: 6 | BO54: 0 | BP54: 0 | BQ54: =BO54+BP54 | BR54: =BM54+BN54-BQ54 | BS54: 0 | BT54: 0 | BU54: 0 | BV54: 0 | BW54: =BU54+BV54 | BX54: =BS54+BT54-BW54 | BY54: =BA54+BG54+BM54+BS54 | BZ54: =BB54+BH54+BN54+BT54 | CA54: =BE54+BK54+BQ54+BW54 | CB54: =BF54+BL54+BR54+BX54 | CC54: 50 | CD54: 2490 | CE54: 58 | CF54: 124 | CG54: 10 | CH54: =CD54+CE54+CF54+CG54 | CI54: 4063 | CJ54: 5 | CK54: 0 | CL54: 0 | CM54: =CI54+CJ54+CK54+CL54 | CN54: 3194 | CO54: 155 | CP54: 418 | CQ54: 72 | CR54: =CN54+CO54+CP54+CQ54 | CS54: =CM54+CR54 | CT54: 10589 | CU54: 51531 | CV54: 48099 | CW54: =IF(CU54=0,"",CV54/CU54) | DB54: =CX54+CY54-CZ54-DA54 | DC54: 0 | DD54: 0 | DE54: 0 | DF54: 0 | DG54: =DC54+DD54-DE54-DF54 | DH54: 0 | DI54: 0 | DJ54: 0 | DK54: 0 | DL54: =DH54+DI54-DJ54-DK54 | DM54: 171 | DN54: 21 | DO54: 0 | DP54: 0 | DQ54: =DM54+DN54-DO54-DP54 | DR54: =CX54+DC54+DH54+DM54 | DS54: =CY54+DD54+DI54+DN54 | DT54: =CZ54+DE54+DJ54+DO54 | DU54: =DA54+DF54+DK54+DP54 | DV54: =DB54+DG54+DL54+DQ54 | DW54: 86 | DX54: 55 | DY54: 24 | DZ54: 17 | EA54: 9 | EB54: 7 | EC54: 2 | ED54: 3 | EE54: 1 | EF54: 0 | EG54: 0 | EH54: 0 | EI54: 0 | EJ54: 12 | EK54: 9 | EL54: 0 | EM54: 0 | EN54: 0 | EO54: 0 | EP54: 0 | EQ54: 0 | ER54: 0 | ES54: 0 | ET54: 0 | EU54: 0 | EV54: 0 | EW54: 0 | EX54: 0 | EY54: 0 | EZ54: 0 | FA54: 0 | FB54: 0 | FC54: 0 | FD54: 0 | FE54: 0 | FF54: 0 | FG54: =SUM(DW54,DX54,DY54,DZ54,EA54,EB54,EC54,ED54,EE54,EF54,EG54,EH54,EI54,EJ54,EK54,EL54,EM54,EN54,EO54,EP54,EQ54,ER54,ES54,ET54,EU54,EV54,EW54,EX54,EY54,EZ54,FA54,FB54,FC54,FD54,FE54,FF54) | FH54: 6 | FI54: 592 | FJ54: 22 | FK54: 28 | FL54: 0 | FM54: 0 | FN54: 0 | FO54: 0 | FP54: 0 | FQ54: =FL54+FM54+FN54+FO54+FP54 | FR54: 33221593 | FS54: 169417.22 | FT54: 47867.22 | FU54: 0 | FV54: =FR54+FS54+FT54+FU54 | FW54: 27882560 | FX54: 1127400 | FY54: 17398512 | FZ54: 13266883 | GA54: =FW54+FX54+FY54+FZ54 | GB54: =FV54+GA54 | GC54: 59220570 | GD54: 0 | GE54: 716167.52 | GF54: 0 | GG54: =GC54+GD54+GE54+GF54 | GH54: 27922799 | GI54: 1127400 | GJ54: 13266883 | GK54: 17268312 | GL54: =GH54+GI54+GJ54+GK54 | GM54: =GG54+GL54 | GN54: 2207885.7 | GO54: 0 | GP54: 16968.2 | GQ54: 0 | GR54: =GN54+GO54+GP54+GQ54 | GS54: 3628259 | GT54: 0 | GU54: 4465 | GV54: 0 | GW54: =GS54+GT54+GU54+GV54 | GX54: =GM54+GR54+GW54 | GY54: 90783230 | GZ54: 4.3524082e+08 | HA54: =GY54+GZ54 | HB54: =IF(GX54=0,"",AU54/GX54) | HC54: =IF((GX54+GY54)=0,"",GB54/(GX54+GY54)) | HD54: =IF(GX54=0,"",GB54/GX54) | HE54: 1854 | HF54: 1 | HG54: 1854 | HH54: 159 | HI54: 8235 | HJ54: =HF54+HI54 | HK54: =IF(HE54=0,"",HH54/HE54) | HL54: 47 | HM54: 7 | HN54: =IF(HL54=0,"",HM54/HL54)
A55: Mangochi | B55: Mangochi | C55: FY2025/26 | D55: 2025 | E55: 8 | F55: August | G55: Q2 | H55: 163955 | I55: 47290 | J55: 76 | K55: 259 | L55: 15 | M55: =SUM(I55,J55,K55,L55) | N55: 42238.5 | O55: 5573.2 | P55: 3212.8 | Q55: 2154.3 | R55: =SUM(N55,O55,P55,Q55) | S55: =M55+R55 | T55: 63136.2 | U55: =IF(H55=0,"",T55/H55) | V55: 300 | W55: =IF(H55=0,"",V55/H55) | X55: 0 | Y55: =IF(H55=0,"",X55/H55) | Z55: 0 | AA55: =IF(H55=0,"",Z55/H55) | AB55: 0 | AC55: =IF(H55=0,"",AB55/H55) | AD55: 0 | AE55: =IF(H55=0,"",AD55/H55) | AF55: 0 | AG55: =IF(H55=0,"",AF55/H55) | AH55: 7178730 | AI55: =IF(H55=0,"",AH55/H55) | AJ55: 50035.01 | AK55: =IF(H55=0,"",AJ55/H55) | AL55: 8384066.9 | AM55: =IF(H55=0,"",AL55/H55) | AN55: 1579 | AO55: 108.64 | AP55: 413606 | AQ55: 0 | AR55: 31521700 | AS55: 4559327.9 | AT55: 3108080 | AU55: =AH55+AL55+AP55+AQ55+AR55+AS55+AT55 | AV55: =IF(H55=0,"",AU55/H55) | AW55: =IF(S55=0,"",AU55/S55) | AX55: 23 | AY55: =IF(H55=0,"",AX55/(H55/1000/12)) | AZ55: 27 | BA55: 1829 | BB55: 178 | BC55: 0 | BD55: 84 | BE55: =BC55+BD55 | BF55: =BA55+BB55-BE55 | BG55: 5 | BH55: 0 | BI55: 0 | BJ55: 1 | BK55: =BI55+BJ55 | BL55: =BG55+BH55-BK55 | BM55: 20 | BN55: 1 | BO55: 0 | BP55: 4 | BQ55: =BO55+BP55 | BR55: =BM55+BN55-BQ55 | BS55: 0 | BT55: 0 | BU55: 0 | BV55: 0 | BW55: =BU55+BV55 | BX55: =BS55+BT55-BW55 | BY55: =BA55+BG55+BM55+BS55 | BZ55: =BB55+BH55+BN55+BT55 | CA55: =BE55+BK55+BQ55+BW55 | CB55: =BF55+BL55+BR55+BX55 | CC55: 89 | CD55: 2419 | CE55: 56 | CF55: 121 | CG55: 8 | CH55: =CD55+CE55+CF55+CG55 | CI55: 4138 | CJ55: 5 | CK55: 2 | CL55: 1 | CM55: =CI55+CJ55+CK55+CL55 | CN55: 3278 | CO55: 156 | CP55: 422 | CQ55: 72 | CR55: =CN55+CO55+CP55+CQ55 | CS55: =CM55+CR55 | CT55: 10678 | CU55: 51606 | CV55: 48544 | CW55: =IF(CU55=0,"",CV55/CU55) | DB55: =CX55+CY55-CZ55-DA55 | DC55: 1 | DD55: 0 | DE55: 0 | DF55: 0 | DG55: =DC55+DD55-DE55-DF55 | DH55: 0 | DI55: 0 | DJ55: 0 | DK55: 0 | DL55: =DH55+DI55-DJ55-DK55 | DM55: 192 | DN55: 40 | DO55: 7 | DP55: 6 | DQ55: =DM55+DN55-DO55-DP55 | DR55: =CX55+DC55+DH55+DM55 | DS55: =CY55+DD55+DI55+DN55 | DT55: =CZ55+DE55+DJ55+DO55 | DU55: =DA55+DF55+DK55+DP55 | DV55: =DB55+DG55+DL55+DQ55 | DW55: 70 | DX55: 44 | DY55: 18 | DZ55: 11 | EA55: 8 | EB55: 3 | EC55: 2 | ED55: 3 | EE55: 0 | EF55: 2 | EG55: 0 | EH55: 0 | EI55: 0 | EJ55: 8 | EK55: 6 | EL55: 0 | EM55: 0 | EN55: 0 | EO55: 0 | EP55: 0 | EQ55: 0 | ER55: 0 | ES55: 0 | ET55: 0 | EU55: 0 | EV55: 0 | EW55: 0 | EX55: 0 | EY55: 0 | EZ55: 0 | FA55: 0 | FB55: 0 | FC55: 0 | FD55: 0 | FE55: 0 | FF55: 0 | FG55: =SUM(DW55,DX55,DY55,DZ55,EA55,EB55,EC55,ED55,EE55,EF55,EG55,EH55,EI55,EJ55,EK55,EL55,EM55,EN55,EO55,EP55,EQ55,ER55,ES55,ET55,EU55,EV55,EW55,EX55,EY55,EZ55,FA55,FB55,FC55,FD55,FE55,FF55) | FH55: 6 | FI55: 598 | FJ55: 0 | FK55: 41 | FL55: 0 | FM55: 0 | FN55: 0 | FO55: 0 | FP55: 0 | FQ55: =FL55+FM55+FN55+FO55+FP55 | FR55: 61486183 | FS55: 0 | FT55: 42000 | FU55: 94867.22 | FV55: =FR55+FS55+FT55+FU55 | FW55: 28922823 | FX55: 1184359 | FY55: 10306280 | FZ55: 9731100 | GA55: =FW55+FX55+FY55+FZ55 | GB55: =FV55+GA55 | GC55: 42922261 | GD55: 14537.28 | GE55: 851086.85 | GF55: 41232.44 | GG55: =GC55+GD55+GE55+GF55 | GH55: 28969018 | GI55: 1184359 | GJ55: 9688740 | GK55: 10090880 | GL55: =GH55+GI55+GJ55+GK55 | GM55: =GG55+GL55 | GN55: 2248836 | GO55: 191.28 | GP55: 16968.2 | GQ55: 9274.68 | GR55: =GN55+GO55+GP55+GQ55 | GS55: 3695234 | GT55: 893 | GU55: 4465 | GV55: 1786 | GW55: =GS55+GT55+GU55+GV55 | GX55: =GM55+GR55+GW55 | GY55: 79021487 | GZ55: 4.2249766e+08 | HA55: =GY55+GZ55 | HB55: =IF(GX55=0,"",AU55/GX55) | HC55: =IF((GX55+GY55)=0,"",GB55/(GX55+GY55)) | HD55: =IF(GX55=0,"",GB55/GX55) | HE55: 0 | HF55: 7 | HG55: 1944 | HH55: 179 | HI55: 14883 | HJ55: =HF55+HI55 | HK55: =IF(HE55=0,"",HH55/HE55) | HL55: 36 | HM55: 6 | HN55: =IF(HL55=0,"",HM55/HL55)
A56: Mangochi | B56: Mangochi | C56: FY2025/26 | D56: 2025 | E56: 9 | F56: September | G56: Q2 | H56: 160930.5 | I56: 54470 | J56: 40 | K56: 238 | L56: 8 | M56: =SUM(I56,J56,K56,L56) | N56: 24541.4 | O56: 5760.6 | P56: 4458.9 | Q56: 2781 | R56: =SUM(N56,O56,P56,Q56) | S56: =M56+R56 | T56: 68632.6 | U56: =IF(H56=0,"",T56/H56) | V56: 418 | W56: =IF(H56=0,"",V56/H56) | X56: 0 | Y56: =IF(H56=0,"",X56/H56) | Z56: 0 | AA56: =IF(H56=0,"",Z56/H56) | AB56: 0 | AC56: =IF(H56=0,"",AB56/H56) | AD56: 0 | AE56: =IF(H56=0,"",AD56/H56) | AF56: 0 | AG56: =IF(H56=0,"",AF56/H56) | AH56: 10002364 | AI56: =IF(H56=0,"",AH56/H56) | AJ56: 44399.6 | AK56: =IF(H56=0,"",AJ56/H56) | AL56: 7441953.1 | AM56: =IF(H56=0,"",AL56/H56) | AN56: 4175 | AO56: 433.66 | AP56: 1186556 | AQ56: 0 | AR56: 30076340 | AS56: 4519195.6 | AT56: 3206170 | AU56: =AH56+AL56+AP56+AQ56+AR56+AS56+AT56 | AV56: =IF(H56=0,"",AU56/H56) | AW56: =IF(S56=0,"",AU56/S56) | AX56: 24 | AY56: =IF(H56=0,"",AX56/(H56/1000/12)) | AZ56: 27 | BA56: 1923 | BB56: 104 | BC56: 0 | BD56: 96 | BE56: =BC56+BD56 | BF56: =BA56+BB56-BE56 | BG56: 4 | BH56: 0 | BI56: 0 | BJ56: 1 | BK56: =BI56+BJ56 | BL56: =BG56+BH56-BK56 | BM56: 17 | BN56: 1 | BO56: 0 | BP56: 5 | BQ56: =BO56+BP56 | BR56: =BM56+BN56-BQ56 | BS56: 0 | BT56: 0 | BU56: 0 | BV56: 0 | BW56: =BU56+BV56 | BX56: =BS56+BT56-BW56 | BY56: =BA56+BG56+BM56+BS56 | BZ56: =BB56+BH56+BN56+BT56 | CA56: =BE56+BK56+BQ56+BW56 | CB56: =BF56+BL56+BR56+BX56 | CC56: 102 | CD56: 2358 | CE56: 56 | CF56: 121 | CG56: 8 | CH56: =CD56+CE56+CF56+CG56 | CI56: 4199 | CJ56: 5 | CK56: 2 | CL56: 1 | CM56: =CI56+CJ56+CK56+CL56 | CN56: 3374 | CO56: 157 | CP56: 427 | CQ56: 72 | CR56: =CN56+CO56+CP56+CQ56 | CS56: =CM56+CR56 | CT56: 10780 | CU56: 50781 | CV56: 47854 | CW56: =IF(CU56=0,"",CV56/CU56) | DB56: =CX56+CY56-CZ56-DA56 | DC56: 0 | DD56: 0 | DE56: 0 | DF56: 0 | DG56: =DC56+DD56-DE56-DF56 | DH56: 0 | DI56: 0 | DJ56: 0 | DK56: 0 | DL56: =DH56+DI56-DJ56-DK56 | DM56: 219 | DN56: 31 | DO56: 0 | DP56: 11 | DQ56: =DM56+DN56-DO56-DP56 | DR56: =CX56+DC56+DH56+DM56 | DS56: =CY56+DD56+DI56+DN56 | DT56: =CZ56+DE56+DJ56+DO56 | DU56: =DA56+DF56+DK56+DP56 | DV56: =DB56+DG56+DL56+DQ56 | DW56: 73 | DX56: 48 | DY56: 21 | DZ56: 13 | EA56: 7 | EB56: 2 | EC56: 0 | ED56: 2 | EE56: 0 | EF56: 2 | EG56: 0 | EH56: 0 | EI56: 0 | EJ56: 11 | EK56: 7 | EL56: 0 | EM56: 0 | EN56: 0 | EO56: 0 | EP56: 0 | EQ56: 0 | ER56: 0 | ES56: 0 | ET56: 0 | EU56: 0 | EV56: 0 | EW56: 0 | EX56: 0 | EY56: 0 | EZ56: 0 | FA56: 0 | FB56: 0 | FC56: 0 | FD56: 0 | FE56: 0 | FF56: 0 | FG56: =SUM(DW56,DX56,DY56,DZ56,EA56,EB56,EC56,ED56,EE56,EF56,EG56,EH56,EI56,EJ56,EK56,EL56,EM56,EN56,EO56,EP56,EQ56,ER56,ES56,ET56,EU56,EV56,EW56,EX56,EY56,EZ56,FA56,FB56,FC56,FD56,FE56,FF56) | FH56: 6 | FI56: 649.5 | FJ56: 0 | FK56: 42.5 | FL56: 0 | FM56: 0 | FN56: 0 | FO56: 0 | FP56: 0 | FQ56: =FL56+FM56+FN56+FO56+FP56 | FR56: 47934800 | FS56: 0 | FT56: 10600 | FU56: 0 | FV56: =FR56+FS56+FT56+FU56 | FW56: 30516325 | FX56: 1224217 | FY56: 13352859 | FZ56: 13791732 | GA56: =FW56+FX56+FY56+FZ56 | GB56: =FV56+GA56 | GC56: 49572975 | GD56: 7651.2 | GE56: 771519.04 | GF56: 20207.62 | GG56: =GC56+GD56+GE56+GF56 | GH56: 30602645 | GI56: 1224217 | GJ56: 13545732 | GK56: 13142739 | GL56: =GH56+GI56+GJ56+GK56 | GM56: =GG56+GL56 | GN56: 2282381 | GO56: 191.28 | GP56: 16968.2 | GQ56: 9274.68 | GR56: =GN56+GO56+GP56+GQ56 | GS56: 3749707 | GT56: 893 | GU56: 4465 | GV56: 1786 | GW56: =GS56+GT56+GU56+GV56 | GX56: =GM56+GR56+GW56 | GY56: 93013527 | GZ56: 4.1708987e+08 | HA56: =GY56+GZ56 | HB56: =IF(GX56=0,"",AU56/GX56) | HC56: =IF((GX56+GY56)=0,"",GB56/(GX56+GY56)) | HD56: =IF(GX56=0,"",GB56/GX56) | HE56: 1947 | HF56: 1 | HG56: 1947 | HH56: 105 | HI56: 19708 | HJ56: =HF56+HI56 | HK56: =IF(HE56=0,"",HH56/HE56) | HL56: 46 | HM56: 6 | HN56: =IF(HL56=0,"",HM56/HL56)
