Workbook

Sheet Balaka
A1: SOUTHERN REGION WATER BOARD
A3: MONTHLY REPORTS - 2023/2024
A4: LIWONDE ZONE
A5: LIWONDE ZONE
A7: PARAMETERS | C7: UNITS | D7: APRIL | E7: MAY | F7: JUNE | G7: JULY | H7: AUGUST | I7: SEPTEMBER | J7: OCTOBER | K7: NOVEMBER | L7: DECEMBER | M7: JANUARY | N7: FEBRUARY | O7: MARCH | P7: TOTALS
A8: PRODUCTION | Q8: APR | R8: MAY | S8: JUN | T8: JUL | U8: AUG | V8: SEP | W8: OCT | X8: NOV | Y8: DEC | Z8: JAN | AA8: FEB | AB8: MAR | AC8: TOTAL
A9: Volume Produced | C9: m3 | D9: 48530 | E9: 61068 | F9: 63082 | G9: 60779 | H9: 62610 | I9: 67798 | J9: 70492 | K9: 72435 | L9: 66190 | M9: 65670 | N9: 65071 | O9: 52112 | P9: =SUM(D9:O9) -> 755837 | Q9: 0 | R9: 0 | S9: 0 | T9: 0 | U9: 0 | V9: 0 | W9: 0 | X9: 0 | Y9: 0 | Z9: 0 | AA9: 0 | AB9: 0 | AC9: 0
A10: REVENUE WATER - POSTPAID | Q10: 0 | R10: 0 | S10: 0 | T10: 0 | U10: 0 | V10: 0 | W10: 0 | X10: 0 | Y10: 0 | Z10: 0 | AA10: 0 | AB10: 0 | AC10: 0
A11: Volume Billed Individuals | C11: m3 | D11: 23018 | E11: 26253 | F11: 25377 | G11: 25441 | H11: 27639 | I11: 31483 | J11: 33851 | K11: 37133 | L11: 31345 | M11: 34534 | N11: 31684 | O11: 29326 | P11: =SUM(D11:O11) -> 357084 | Q11: 0 | R11: 0 | S11: 0 | T11: 0 | U11: 0 | V11: 0 | W11: 0 | X11: 0 | Y11: 0 | Z11: 0 | AA11: 0 | AB11: 0 | AC11: 0
A12: Volume Billed CWPs | C12: m3 | D12: 1035 | E12: 1000 | F12: 434 | G12: 1049 | H12: 1254 | I12: 1228 | J12: 1323 | K12: 1269 | L12: 1173 | M12: 1037 | N12: 1267 | O12: 844 | P12: =SUM(D12:O12) -> 12913 | Q12: 0 | R12: 0 | S12: 0 | T12: 0 | U12: 0 | V12: 0 | W12: 0 | X12: 0 | Y12: 0 | Z12: 0 | AA12: 0 | AB12: 0 | AC12: 0
A13: Volume Billed Institutions | C13: m3 | D13: 552 | E13: 200 | F13: 2451 | G13: 228 | H13: 290 | I13: 390 | J13: 421 | K13: 199 | L13: 171 | M13: 420 | N13: 143 | O13: 160 | P13: =SUM(D13:O13) -> 5625 | Q13: 0 | R13: 0 | S13: 0 | T13: 0 | U13: 0 | V13: 0 | W13: 0 | X13: 0 | Y13: 0 | Z13: 0 | AA13: 0 | AB13: 0 | AC13: 0
A14: Volume Billed Commercial/Industrial | C14: m3 | D14: 55 | E14: 53 | F14: 150 | G14: 43 | H14: 150 | I14: 149 | J14: 110 | K14: 39 | L14: 38 | M14: 35 | N14: 82 | O14: 91 | P14: =SUM(D14:O14) -> 995 | Q14: 0 | R14: 0 | S14: 0 | T14: 0 | U14: 0 | V14: 0 | W14: 0 | X14: 0 | Y14: 0 | Z14: 0 | AA14: 0 | AB14: 0 | AC14: 0
A15: Total Volume Billed Post Paid | C15: m3 | D15: =SUM(D11:D14) -> 24660 | E15: =SUM(E11:E14) -> 27506 | F15: =SUM(F11:F14) -> 28412 | G15: =SUM(G11:G14) -> 26761 | H15: =SUM(H11:H14) -> 29333 | I15: =SUM(I11:I14) -> 33250 | J15: =SUM(J11:J14) -> 35705 | K15: =SUM(K11:K14) -> 38640 | ... P15: =SUM(P11:P14) -> 376617 | Q15: 0 | R15: 0 | S15: 0 | T15: 0 | U15: 0 | V15: 0 | W15: 0 | X15: 0 | Y15: 0 | Z15: 0 | AA15: 0 | AB15: 0 | AC15: 0
A16: REVENUE WATER - PREPAID
A17: Individuals | C17: m3 | D17: 6897 | E17: 7593 | F17: 7232 | G17: 6169 | H17: 7905 | I17: 6351 | J17: 6689 | K17: 6507 | L17: 7205 | M17: 5531 | N17: 9809 | O17: 5458 | P17: =SUM(D17:O17) -> 83346
A18: CWPs | C18: m3 | D18: 0 | E18: 0 | F18: 0 | G18: 0 | H18: 0 | I18: 0 | K18: 0 | L18: 0 | M18: 0 | N18: 0 | O18: 47 | P18: =SUM(D18:O18) -> 47
A19: Institutions | C19: m3 | D19: 0 | E19: 0 | F19: 0 | G19: 0 | H19: 0 | I19: 1374 | J19: 1462 | K19: 1418 | L19: 1559 | M19: 1196 | N19: 2120 | O19: 392 | P19: =SUM(D19:O19) -> 9521
A20: Commercial/Industrial | C20: m3 | D20: 0 | E20: 0 | F20: 0 | G20: 0 | H20: 0 | I20: 551 | J20: 566 | K20: 549 | L20: 605 | M20: 466 | N20: 827 | O20: 390 | P20: =SUM(D20:O20) -> 3954
A21: Total Volume Prepaid | C21: m3 | D21: =SUM(D17:D20) -> 6897 | E21: =SUM(E17:E20) -> 7593 | F21: =SUM(F17:F20) -> 7232 | G21: =SUM(G17:G20) -> 6169 | H21: =SUM(H17:H20) -> 7905 | I21: =SUM(I17:I20) -> 8276 | J21: =SUM(J17:J20) -> 8717 | K21: =SUM(K17:K20) -> 8474 | ... P21: =SUM(P17:P20) -> 96868
A22: TOTAL REVENUE WATER | C22: m3 | D22: =D21+D15 -> 31557 | E22: =E21+E15 -> 35099 | F22: =F21+F15 -> 35644 | G22: =G21+G15 -> 32930 | H22: =H21+H15 -> 37238 | I22: =I21+I15 -> 41526 | J22: =J21+J15 -> 44422 | K22: =K21+K15 -> 47114 | ... P22: =P21+P15 -> 473485
A24: Non-Revenue Water (NRW) | B24: Volume | C24: m3 | D24: =D9-D22 -> 16973 | E24: =E9-E22 -> 25969 | F24: =F9-F22 -> 27438 | G24: =G9-G22 -> 27849 | H24: =H9-H22 -> 25372 | I24: =I9-I22 -> 26272 | J24: =J9-J22 -> 26070 | K24: =K9-K22 -> 25321 | ... P24: =P9-P22 -> 282352
B25: Percentage | C25: % | D25: =D24/D9 -> 0.34974243 | E25: =E24/E9 -> 0.42524727 | F25: =F24/F9 -> 0.43495767 | G25: =G24/G9 -> 0.45820102 | H25: =H24/H9 -> 0.40523878 | I25: =I24/I9 -> 0.38750406 | J25: =J24/J9 -> 0.3698292 | K25: =K24/K9 -> 0.34956858 | ... P25: =P24/P9 -> 0.37356202
A26: OPERATING EXPENSES
A27: Chemicals
A28: Chemical | B28: Rate(MK/kg)
A29: Chlorine | B29: =176264.5/50 -> 3525.29 | C29: kg | D29: 98 | E29: 120 | F29: 122 | G29: 96 | H29: 114 | I29: 110 | J29: 115 | K29: 121 | L29: 121 | M29: 119 | N29: 125 | O29: 84 | P29: =SUM(D29:O29) -> 1345
C30: kg/mg litre | D30: =D29/(D9/1000) -> 2.0193695 | E30: =E29/(E9/1000) -> 1.9650226 | F30: =F29/(F9/1000) -> 1.9339907 | G30: =G29/(G9/1000) -> 1.5794929 | H30: =H29/(H9/1000) -> 1.8207954 | I30: =I29/(I9/1000) -> 1.6224667 | J30: =J29/(J9/1000) -> 1.6313908 | K30: =K29/(K9/1000) -> 1.6704632 | ... P30: =P29/(P9/1000) -> 1.7794842
A31: Aluminium sulphate | B31: =53000.511/50 -> 1060.0102 | C31: kg | P31: =SUM(D31:O31) -> 0
C32: kg/mg litre | D32: =D31/(D9/1000) -> 0 | E32: =E31/(E9/1000) -> 0 | F32: =F31/(F9/1000) -> 0 | G32: =G31/(G9/1000) -> 0 | H32: =H31/(H9/1000) -> 0 | I32: =I31/(I9/1000) -> 0 | J32: =J31/(J9/1000) -> 0 | K32: =K31/(K9/1000) -> 0 | ... P32: =P31/(P9/1000) -> 0
A33: Soda | B33: =61414.43/50 -> 1228.2886 | C33: kg | P33: =SUM(D33:O33) -> 0
C34: kg/mg litre | D34: =D33/(D9/1000) -> 0 | E34: =E33/(E9/1000) -> 0 | F34: =F33/(F9/1000) -> 0 | G34: =G33/(G9/1000) -> 0 | H34: =H33/(H9/1000) -> 0 | I34: =I33/(I9/1000) -> 0 | J34: =J33/(J9/1000) -> 0 | K34: =K33/(K9/1000) -> 0 | ... P34: =P33/(P9/1000) -> 0
A35: Algae floc | B35: =745345.16/200 -> 3726.7258 | C35: litres
C36: litres/mg litre
A37: Sud floc | B37: =790318.72/200 -> 3951.5936 | C37: litres | D37: 0 | E37: 0 | F37: 0 | G37: 0 | H37: 0 | I37: 0 | J37: 0 | K37: 0 | L37: 0 | M37: 0 | N37: 0 | O37: 0 | P37: =SUM(D37:O37) -> 0
C38: litres/mg litre | D38: =D37/(D9/1000) -> 0 | E38: =E37/(E9/1000) -> 0 | F38: =F37/(F9/1000) -> 0 | G38: =G37/(G9/1000) -> 0 | H38: =H37/(H9/1000) -> 0 | I38: =I37/(I9/1000) -> 0 | J38: =J37/(J9/1000) -> 0 | K38: =K37/(K9/1000) -> 0 | ... P38: =P37/(P9/1000) -> 0
A39: Potasium permanganate | B39: 1950 | C39: kg | D39: 0 | E39: 0 | F39: 0 | G39: 0 | H39: 0 | I39: 0 | J39: 0 | K39: 0 | L39: 0 | M39: 0 | N39: 0 | O39: 0 | P39: =SUM(D39:O39) -> 0
C40: kg/mg litre | D40: =D39/(D9/1000) -> 0 | E40: =E39/(E9/1000) -> 0 | F40: =F39/(F9/1000) -> 0 | G40: =G39/(G9/1000) -> 0 | H40: =H39/(H9/1000) -> 0 | I40: =I39/(I9/1000) -> 0 | J40: =J39/(J9/1000) -> 0 | K40: =K39/(K9/1000) -> 0 | ... P40: =P39/(P9/1000) -> 0
A41: Cost of Chemicals | C41: Mk | D41: =(D29*$B29)+(D31*$B31)+(D33*$B33)+(D35*$B35)+(D37*$B37)+(D39*$B39) -> 345478.42 | E41: =(E29*$B29)+(E31*$B31)+(E33*$B33)+(E35*$B35)+(E37*$B37)+(E39*$B39) -> 423034.8 | F41: =(F29*$B29)+(F31*$B31)+(F33*$B33)+(F35*$B35)+(F37*$B37)+(F39*$B39) -> 430085.38 | G41: =(G29*$B29)+(G31*$B31)+(G33*$B33)+(G35*$B35)+(G37*$B37)+(G39*$B39) -> 338427.84 | H41: =(H29*$B29)+(H31*$B31)+(H33*$B33)+(H35*$B35)+(H37*$B37)+(H39*$B39) -> 401883.06 | I41: =(I29*$B29)+(I31*$B31)+(I33*$B33)+(I35*$B35)+(I37*$B37)+(I39*$B39) -> 387781.9 | J41: =(J29*$B29)+(J31*$B31)+(J33*$B33)+(J35*$B35)+(J37*$B37)+(J39*$B39) -> 405408.35 | K41: =(K29*$B29)+(K31*$B31)+(K33*$B33)+(K35*$B35)+(K37*$B37)+(K39*$B39) -> 426560.09 | ... O41: =(O29*$B29)+(O31*$B31)+(O33*$B33)+(O35*$B35)+(O37*$B37)+(O39*$B39) -> 296124.36 | P41: =SUM(D41:O41) -> 4741515
A42: Cost/vol. Produced (chemicals) | C42: Mk/m3 | D42: =D41/D9 -> 7.118863 | E42: =E41/E9 -> 6.9272745 | F42: =F41/F9 -> 6.817878 | G42: =G41/G9 -> 5.5681706 | H42: =H41/H9 -> 6.4188318 | I42: =I41/I9 -> 5.7196658 | J42: =J41/J9 -> 5.7511257 | K42: =K41/K9 -> 5.8888671 | ... P42: =P41/P9 -> 6.2731979
A43: Power
A44: Power Usage | C44: Kw | D44: 33186 | E44: 55310 | F44: 34660 | G44: 35100 | H44: 45036 | I44: 45713 | J44: 36779 | K44: 40320 | L44: 42320 | O44: 35000 | P44: =SUM(D44:O44) -> 403424
A45: Power/ Vol. Produced | C45: Kw/m3 | D45: =D44/D9 -> 0.68382444 | E45: =E44/E9 -> 0.90571167 | F45: =F44/F9 -> 0.54944358 | G45: =G44/G9 -> 0.5775021 | H45: =H44/H9 -> 0.71931001 | I45: =I44/I9 -> 0.67425293 | J45: =J44/J9 -> 0.52174715 | K45: =K44/K9 -> 0.55663698 | ... P45: =P44/P9 -> 0.53374471
A46: Cost of Power | C46: Mk | D46: =1.165*(14100+(D44*119.1)) -> 4621033.8 | E46: =1.165*(14100+(E44*119.1)) -> 7690772 | F46: =1.165*(14100+(F44*119.1)) -> 4825553.5 | G46: =1.165*(14100+(G44*119.1)) -> 4886604.2 | H46: =1.165*(16600+(H44*143.5)) -> 7548344.9 | I46: =1.165*(16600+(I44*143.5)) -> 7661524.1 | J46: =1.165*(16600+(J44*143.5)) -> 6167960.3 | K46: =1.165*(16600+(K44*143.5)) -> 6759935.8 | L46: =1.165*(16600+(L44*143.5)) -> 7094290.8 | N46: 4500000 | O46: 4500000 | P46: =SUM(D46:O46) -> 66256019
A47: Cost/vol. Produced | C47: Mk/m3 | D47: =D46/D9 -> 95.220148 | E47: =E46/E9 -> 125.93784 | F47: =F46/F9 -> 76.49652 | G47: =G46/G9 -> 80.399548 | H47: =H46/H9 -> 120.56133 | I47: =I46/I9 -> 113.00516 | J47: =J46/J9 -> 87.498727 | K47: =K46/K9 -> 93.324164 | ... P47: =P46/P9 -> 87.659137
A48: Plant and Vehicle Maintenance
A49: Distances covered | C49: km | D49: 1537 | E49: 2146 | F49: 2897 | G49: 2795 | H49: 2600 | I49: 2650 | J49: 1570 | K49: 1589 | L49: 1690 | P49: =SUM(D49:O49) -> 19474
A50: Fuel Used (litres) | C50: litres | D50: 143 | E50: 200 | F50: 270 | G50: 270 | H50: 300 | I50: 270 | J50: 330 | K50: 330 | L50: 240 | P50: =SUM(D50:O50) -> 2353
A51: Cost of fuel | C51: Mk | D51: 250000 | E51: 349200 | F51: 520200 | G51: 754650 | H51: 520200 | I51: 518400 | J51: 633600 | K51: 902220 | L51: 656160 | N51: 782660 | P51: =SUM(D51:O51) -> 5887290
A52: Maintenance | C52: Mk | D52: 0 | E52: 0 | F52: 0 | H52: 0 | I52: 0 | J52: 0 | K52: 0 | L52: 0 | M52: 0 | N52: 0 | O52: 0 | P52: =SUM(D52:O52) -> 0
A53: Salaries and Wages
A54: Staff Costs | C54: MK | D54: 5280746.5 | E54: 6508570.2 | F54: 5314966.4 | G54: 5314966.4 | H54: 6942503.3 | I54: 6436205 | J54: 6181810.3 | K54: 6181810.3 | L54: 9127422.7 | M54: 7179966.6 | N54: 6426300.1 | O54: 9950510.1 | P54: =SUM(D54:O54) -> 80845778
A55: Wages | C55: MK | D55: 1036581.9 | E55: 2375478.8 | F55: 1037927.2 | G55: 1037927.2 | H55: 1282113.1 | I55: 1288749 | J55: 2693851.4 | K55: 2983323.2 | L55: 2736761.6 | M55: 2109381.5 | N55: 2150256.4 | O55: 2659792.5 | P55: =SUM(D55:O55) -> 23392144
A56: Other Overhead Costs | C56: MK | D56: 1852737 | E56: 459000 | F56: 3423380 | G56: 3423380 | H56: 5232830 | I56: 10060346 | J56: 1194264.1 | K56: 6545720 | L56: 7626862.8 | M56: 10166850 | N56: 15260837 | O56: 13919151 | P56: =SUM(D56:O56) -> 79165359
A57: Operating Costs
A58: Total Operating Costs | C58: MK | D58: =D41+D46+D51+D52+D54+D55+D56 -> 13386578 | E58: =E41+E46+E51+E52+E54+E55+E56 -> 17806056 | F58: =F41+F46+F51+F52+F54+F55+F56 -> 15552112 | G58: =G41+G46+G51+G52+G54+G55+G56 -> 15755956 | H58: =H41+H46+H51+H52+H54+H55+H56 -> 21927874 | I58: =I41+I46+I51+I52+I54+I55+I56 -> 26353006 | J58: =J41+J46+J51+J52+J54+J55+J56 -> 17276894 | K58: =K41+K46+K51+K52+K54+K55+K56 -> 23799569 | ... O58: =O41+O46+O51+O52+O54+O55+O56 -> 31325578 | P58: =SUM(D58:O58) -> 2.602881e+08
A59: Cost/Vol. Produced | C59: Mk/m3 | D59: =D58/D9 -> 275.84129 | E59: =E58/E9 -> 291.57752 | F59: =F58/F9 -> 246.53804 | G59: =G58/G9 -> 259.23354 | H59: =H58/H9 -> 350.22959 | I59: =I58/I9 -> 388.69887 | J59: =J58/J9 -> 245.09014 | K59: =K58/K9 -> 328.5645 | ... P59: =P58/P9 -> 344.37068
A60: Cost/Vol. Billed | C60: Mk/m3 | D60: =D58/D22 -> 424.20311 | E60: =E58/E22 -> 507.30949 | F60: =F58/F22 -> 436.31782 | G60: =G58/G22 -> 478.46813 | H60: =H58/H22 -> 588.85747 | I60: =I58/I22 -> 634.61461 | J60: =J58/J22 -> 388.92653 | K60: =K58/K22 -> 505.14856 | ... P60: =P58/P22 -> 549.7283
A61: Permanent Staff Employed | C61: No | D61: 15 | E61: 15 | F61: 16 | G61: 15 | H61: 15 | I61: 15 | J61: 15 | K61: 14 | L61: 14 | M61: 14 | N61: 14 | O61: 14 | P61: =O61 -> 14
A62: Staff/Vol.1000m3 of Volume Produced/hour (12 hour day) | C62: No/1000m3 | D62: =(D61*1000*31)/D9 -> 9.581702 | E62: =(E61*1000*31)/E9 -> 7.6144626 | F62: =(F61*1000*31)/F9 -> 7.8627818 | G62: =(G61*1000*31)/G9 -> 7.6506688 | H62: =(H61*1000*31)/H9 -> 7.4269286 | I62: =(I61*1000*31)/I9 -> 6.8586094 | J62: =(J61*1000*31)/J9 -> 6.5964932 | K62: =(K61*1000*31)/K9 -> 5.9915787 | ... P62: =(P61*1000*31)/P9 -> 0.57419788
A63: Temporary Staff Employed | C63: No | D63: 17 | E63: 17 | F63: 21 | G63: 21 | H63: 21 | I63: 21 | J63: 21 | K63: 21 | L63: 21 | M63: 20 | N63: 20 | O63: 20 | P63: =SUM(D63:O63) -> 241
A65: Water Connections and Disconnections
A66: New Individual Water Connections | B66: Brought Forward | C66: No | D66: 435 | E66: 421 | F66: 426 | G66: 420 | H66: 435 | I66: 442 | J66: 442 | K66: 420 | L66: 417 | M66: 408 | N66: 407 | O66: 423 | P66: =D66 -> 435
B67: Applied this Month | C67: No | D67: 11 | E67: 27 | F67: 35 | G67: 41 | H67: 70 | I67: 34 | J67: 31 | K67: 34 | L67: 21 | M67: 24 | N67: 58 | O67: 28 | P67: =SUM(D67:O67) -> 414
B68: Done this Month Postpaid | C68: No | D68: 25 | E68: 22 | F68: 41 | G68: 26 | H68: 63 | I68: 34 | J68: 53 | K68: 37 | L68: 30 | M68: 25 | N68: 42 | O68: 10 | P68: =SUM(D68:O68) -> 408
B69: Done this Month Prepaid | C69: No | D69: 0 | E69: 0 | F69: 0 | G69: 0 | H69: 0 | I69: 0 | J69: 0 | K69: 0 | L69: 0 | M69: 0 | N69: 0 | O69: 0 | P69: =SUM(D69:O69) -> 0
B70: Total Done | C70: No | D70: =D68+D69 -> 25 | E70: =E68+E69 -> 22 | F70: =F68+F69 -> 41 | G70: =G68+G69 -> 26 | H70: =H68+H69 -> 63 | I70: =I68+I69 -> 34 | J70: =J68+J69 -> 53 | K70: =K68+K69 -> 37 | ... P70: =P68+P69 -> 408
B71: Carried Forward | C71: No | D71: =D66+D67-D70 -> 421 | E71: =E66+E67-E70 -> 426 | F71: =F66+F67-F70 -> 420 | G71: =G66+G67-G70 -> 435 | H71: =H66+H67-H70 -> 442 | I71: =I66+I67-I70 -> 442 | J71: =J66+J67-J70 -> 420 | K71: =K66+K67-K70 -> 417 | ... P71: =P66+P67-P70 -> 441
A72: New Institutional Water Connections | B72: Brought Forward | C72: No | P72: =D72 -> 0
B73: Applied this Month | C73: No | P73: =SUM(D73:O73) -> 0
B74: Done this Month Postpaid | C74: No | P74: =SUM(D74:O74) -> 0
B75: Done this Month Prepaid | C75: No | P75: =SUM(D75:O75) -> 0
B76: Total Done | C76: No | D76: =D74+D75 -> 0 | E76: =E74+E75 -> 0 | F76: =F74+F75 -> 0 | G76: =G74+G75 -> 0 | H76: =H74+H75 -> 0 | I76: =I74+I75 -> 0 | J76: =J74+J75 -> 0 | K76: =K74+K75 -> 0 | ... P76: =P74+P75 -> 0
B77: Carried Forward | C77: No | D77: =D72+D73-D76 -> 0 | E77: =E72+E73-E76 -> 0 | F77: =F72+F73-F76 -> 0 | G77: =G72+G73-G76 -> 0 | H77: =H72+H73-H76 -> 0 | I77: =I72+I73-I76 -> 0 | J77: =J72+J73-J76 -> 0 | K77: =K72+K73-K76 -> 0 | ... P77: =P72+P73-P76 -> 0
A78: New Commercial/Industrial Water Connections | B78: Brought Forward | C78: No | P78: =D78 -> 0
B79: Applied this Month | C79: No | P79: =SUM(D79:O79) -> 0
B80: Done this Month Postpaid | C80: No | P80: =SUM(D80:O80) -> 0
B81: Done this Month Prepaid | C81: No | P81: =SUM(D81:O81) -> 0
B82: Total Done | C82: No | D82: =D80+D81 -> 0 | E82: =E80+E81 -> 0 | F82: =F80+F81 -> 0 | G82: =G80+G81 -> 0 | H82: =H80+H81 -> 0 | I82: =I80+I81 -> 0 | J82: =J80+J81 -> 0 | K82: =K80+K81 -> 0 | L82: =L80+L81 -> 0 | M82: =M81+M80 -> 0 | N82: =N81+N80 -> 0 | O82: =O81+O80 -> 0 | P82: =P81+P80 -> 0
B83: Carried Forward | C83: No | D83: =D78+D79-D82 -> 0 | E83: =E78+E79-E82 -> 0 | F83: =F78+F79-F82 -> 0 | G83: =G78+G79-G82 -> 0 | H83: =H78+H79-H82 -> 0 | I83: =I78+I79-I82 -> 0 | J83: =J78+J79-J82 -> 0 | K83: =K78+K79-K82 -> 0 | ... P83: =P78+P79-P82 -> 0
A84: New CWP | B84: Brought Forward | C84: No | P84: =D84 -> 0
B85: Applied this Month | C85: No | P85: =SUM(D85:O85) -> 0
B86: Done this Month Postpaid | C86: No | P86: =SUM(D86:O86) -> 0
B87: Done this Month Prepaid | C87: No | P87: =SUM(D87:O87) -> 0
B88: Total Done | C88: No | D88: =D86+D87 -> 0 | E88: =E86+E87 -> 0 | F88: =F86+F87 -> 0 | G88: =G86+G87 -> 0 | H88: =H86+H87 -> 0 | I88: =I86+I87 -> 0 | J88: =J86+J87 -> 0 | K88: =K86+K87 -> 0 | ... M88: =M86+M87 -> 0 | N88: 0 | O88: 0 | P88: =SUM(D88:O88) -> 0
B89: Carried Forward | C89: No | D89: =D84+D85-D88 -> 0 | E89: =E84+E85-E88 -> 0 | F89: =F84+F85-F88 -> 0 | G89: =G84+G85-G88 -> 0 | H89: =H84+H85-H88 -> 0 | I89: =I84+I85-I88 -> 0 | J89: =J84+J85-J88 -> 0 | K89: =K84+K85-K88 -> 0 | ... M89: =M84+M85-M88 -> 0 | N89: =N84+N85-N86-N87 -> 0 | O89: =O84+O85-O86-O87 -> 0 | P89: =P84+P85-P86-P87 -> 0
A90: Aggregated New Water connections | B90: Brought Forward | C90: No | D90: =D66+D72+D78+D84 -> 435 | E90: =E66+E72+E78+E84 -> 421 | F90: =F66+F72+F78+F84 -> 426 | G90: =G66+G72+G78+G84 -> 420 | H90: =H66+H72+H78+H84 -> 435 | I90: =I66+I72+I78+I84 -> 442 | J90: =J66+J72+J78+J84 -> 442 | K90: =K66+K72+K78+K84 -> 420 | ... O90: =O66+O72+O78+O84 -> 423 | P90: =D90 -> 435
B91: Applied this Month | C91: No | D91: =D67+D73+D79+D85 -> 11 | E91: =E67+E73+E79+E85 -> 27 | F91: =F67+F73+F79+F85 -> 35 | G91: =G67+G73+G79+G85 -> 41 | H91: =H67+H73+H79+H85 -> 70 | I91: =I67+I73+I79+I85 -> 34 | J91: =J67+J73+J79+J85 -> 31 | K91: =K67+K73+K79+K85 -> 34 | ... O91: =O67+O73+O79+O85 -> 28 | P91: =SUM(D91:O91) -> 414
B92: Done this Month Postpaid | C92: No | D92: =D68+D74+D80+D86 -> 25 | E92: =E68+E74+E80+E86 -> 22 | F92: =F68+F74+F80+F86 -> 41 | G92: =G68+G74+G80+G86 -> 26 | H92: =H68+H74+H80+H86 -> 63 | I92: =I68+I74+I80+I86 -> 34 | J92: =J68+J74+J80+J86 -> 53 | K92: =K68+K74+K80+K86 -> 37 | ... O92: =O68+O74+O80+O86 -> 10 | P92: =SUM(D92:O92) -> 408
B93: Done this Month Prepaid | D93: =D69+D75+D81+D87 -> 0 | E93: =E69+E75+E81+E87 -> 0 | F93: =F69+F75+F81+F87 -> 0 | G93: =G69+G75+G81+G87 -> 0 | H93: =H69+H75+H81+H87 -> 0 | I93: =I69+I75+I81+I87 -> 0 | J93: =J69+J75+J81+J87 -> 0 | K93: =K69+K75+K81+K87 -> 0 | ... O93: =O69+O75+O81+O87 -> 0 | P93: =SUM(D93:O93) -> 0
B94: Total Done | C94: No | D94: =D93+D92 -> 25 | E94: =E93+E92 -> 22 | F94: =F93+F92 -> 41 | G94: =G93+G92 -> 26 | H94: =H93+H92 -> 63 | I94: =I93+I92 -> 34 | J94: =J93+J92 -> 53 | K94: =K93+K92 -> 37 | ... P94: =P93+P92 -> 408
B95: Carried Forward | C95: No | D95: =D90+D91-D94 -> 421 | E95: =E90+E91-E94 -> 426 | F95: =F90+F91-F94 -> 420 | G95: =G90+G91-G94 -> 435 | H95: =H90+H91-H94 -> 442 | I95: =I90+I91-I94 -> 442 | J95: =J90+J91-J94 -> 420 | K95: =K90+K91-K94 -> 417 | ... P95: =P90+P91-P94 -> 441
A97: Prepaid Metering
A98: Prepaid Meters Installed | C98: No | D98: 933 | E98: 933 | F98: 933 | G98: 933 | H98: 933 | I98: 933 | J98: 933 | K98: 933 | L98: 933 | M98: 933 | N98: 933 | O98: 933 | P98: =SUM(D98:O98) -> 11196
A100: Active and Disconnected Accounts
A101: Disconnected Individual Accounts | C101: No | D101: 1979 | E101: 1979 | F101: 1938 | G101: 1910 | H101: 1897 | I101: 1946 | J101: 2165 | K101: 2183 | L101: 2289 | M101: 2369 | N101: 2385 | O101: 2275 | P101: =O101 -> 2275
A102: Disconnected institutional Accounts | C102: No | D102: 36 | E102: 36 | F102: 36 | G102: 36 | H102: 36 | I102: 36 | J102: 36 | K102: 36 | L102: 36 | M102: 43 | N102: 43 | O102: 43 | P102: =O102 -> 43
A103: Disconnected Commercial/Industrial Accounts | C103: No | D103: 98 | E103: 98 | F103: 98 | G103: 98 | H103: 98 | I103: 98 | J103: 98 | K103: 98 | L103: 98 | M103: 118 | N103: 118 | O103: 118 | P103: =O103 -> 118
A104: Disconnected CWP | C104: No | D104: 17 | E104: 17 | F104: 17 | G104: 17 | H104: 17 | I104: 17 | J104: 17 | K104: 17 | L104: 17 | M104: 17 | N104: 17 | O104: 17 | P104: =O104 -> 17
A105: Total Disconnected Accounts | C105: No | D105: =SUM(D101:D104) -> 2130 | E105: =SUM(E101:E104) -> 2130 | F105: =SUM(F101:F104) -> 2089 | G105: =SUM(G101:G104) -> 2061 | H105: =SUM(H101:H104) -> 2048 | I105: =SUM(I101:I104) -> 2097 | J105: =SUM(J101:J104) -> 2316 | K105: =SUM(K101:K104) -> 2334 | ... O105: =SUM(O101:O104) -> 2453 | P105: =O105 -> 2453
A106: Postpaid Consumers
...

Sheet Liwonde
A1: SOUTHERN REGION WATER BOARD
A3: MONTHLY REPORTS - 2023/2024
A4: LIWONDE ZONE
A5: LIWONDE ZONE
A7: PARAMETERS | C7: UNITS | D7: APRIL | E7: MAY | F7: JUNE | G7: JULY | H7: AUGUST | I7: SEPTEMBER | J7: OCTOBER | K7: NOVEMBER | L7: DECEMBER | M7: JANUARY | N7: FEBRUARY | O7: MARCH | P7: TOTALS
A8: PRODUCTION
A9: Volume Produced | C9: m3 | D9: 60894 | E9: 61758 | F9: 58637 | G9: 62605 | H9: 63644 | I9: 71038 | J9: 75247 | K9: 71539 | L9: 71453.7 | M9: 74738 | N9: 63503 | O9: 53806 | P9: =SUM(D9:O9) -> 788862.7
A10: REVENUE WATER - POSTPAID
A11: Volume Billed Individuals | C11: m3 | D11: 20785 | E11: 24461 | F11: 25377 | G11: 24942 | H11: 26711 | I11: 27302 | J11: 29478 | K11: 29318 | L11: 29302 | M11: 42884 | N11: 30836 | O11: 27911 | P11: =SUM(D11:O11) -> 339307
A12: Volume Billed CWPs | C12: m3 | D12: 287 | E12: 438 | F12: 434 | G12: 428 | H12: 522 | I12: 498 | J12: 581 | K12: 426 | L12: 521 | M12: 455 | N12: 467 | O12: 478 | P12: =SUM(D12:O12) -> 5535
A13: Volume Billed Institutions | C13: m3 | D13: 2010 | E13: 2233 | F13: 2451 | G13: 2340 | H13: 2297 | I13: 2337 | J13: 2422 | K13: 2635 | L13: 2709 | M13: 1068 | N13: 804 | O13: 850 | P13: =SUM(D13:O13) -> 24156
A14: Volume Billed Commercial/Industrial | C14: m3 | D14: 122 | E14: 144 | F14: 150 | G14: 189 | H14: 216 | I14: 223 | J14: 217 | K14: 238 | L14: 386 | M14: 211 | N14: 500 | O14: 554 | P14: =SUM(D14:O14) -> 3150
A15: Total Volume Billed Post Paid | C15: m3 | D15: =SUM(D11:D14) -> 23204 | E15: =SUM(E11:E14) -> 27276 | F15: =SUM(F11:F14) -> 28412 | G15: =SUM(G11:G14) -> 27899 | H15: =SUM(H11:H14) -> 29746 | I15: =SUM(I11:I14) -> 30360 | J15: =SUM(J11:J14) -> 32698 | K15: =SUM(K11:K14) -> 32617 | ... P15: =SUM(P11:P14) -> 372148
A16: REVENUE WATER - PREPAID
A17: Individuals | C17: m3 | D17: 10799 | E17: 11460 | F17: 8397.3 | G17: 9867.2 | H17: 8837 | I17: 9833.9 | J17: 13000 | K17: 9774.7 | L17: 10968.3 | M17: 9105 | N17: 12756 | O17: 9575.3 | P17: =SUM(D17:O17) -> 124373.7
A18: CWPs | C18: m3 | D18: 0 | E18: 0 | P18: =SUM(D18:O18) -> 0
A19: Institutions | C19: m3 | D19: 0 | E19: 0 | P19: =SUM(D19:O19) -> 0
A20: Commercial/Industrial | C20: m3 | D20: 0 | E20: 0 | P20: =SUM(D20:O20) -> 0
A21: Total Volume Prepaid | C21: m3 | D21: =SUM(D17:D20) -> 10799 | E21: =SUM(E17:E20) -> 11460 | F21: =SUM(F17:F20) -> 8397.3 | G21: =SUM(G17:G20) -> 9867.2 | H21: =SUM(H17:H20) -> 8837 | I21: =SUM(I17:I20) -> 9833.9 | J21: =SUM(J17:J20) -> 13000 | K21: =SUM(K17:K20) -> 9774.7 | ... P21: =SUM(P17:P20) -> 124373.7
A22: TOTAL REVENUE WATER | C22: m3 | D22: =D21+D15 -> 34003 | E22: =E21+E15 -> 38736 | F22: =F21+F15 -> 36809.3 | G22: =G21+G15 -> 37766.2 | H22: =H21+H15 -> 38583 | I22: =I21+I15 -> 40193.9 | J22: =J21+J15 -> 45698 | K22: =K21+K15 -> 42391.7 | ... P22: =P21+P15 -> 496521.7
A24: Non-Revenue Water (NRW) | B24: Volume | C24: m3 | D24: =D9-D22 -> 26891 | E24: =E9-E22 -> 23022 | F24: =F9-F22 -> 21827.7 | G24: =G9-G22 -> 24838.8 | H24: =H9-H22 -> 25061 | I24: =I9-I22 -> 30844.1 | J24: =J9-J22 -> 29549 | K24: =K9-K22 -> 29147.3 | ... P24: =P9-P22 -> 292341
B25: Percentage | C25: % | D25: =D24/D9 -> 0.44160344 | E25: =E24/E9 -> 0.37277762 | F25: =F24/F9 -> 0.37225131 | G25: =G24/G9 -> 0.39675425 | H25: =H24/H9 -> 0.39376846 | I25: =I24/I9 -> 0.43419156 | J25: =J24/J9 -> 0.3926934 | K25: =K24/K9 -> 0.40743231 | ... P25: =P24/P9 -> 0.3705854
A26: OPERATING EXPENSES
A27: Chemicals
A28: Chemical | B28: Rate(MK/kg)
A29: Chlorine | B29: =176264.5/50 -> 3525.29 | C29: kg | D29: 333 | E29: 480 | F29: 237 | G29: 283 | H29: 209 | I29: 341 | J29: 468 | K29: 377 | L29: 368 | M29: 372 | N29: 348 | O29: 372 | P29: =SUM(D29:O29) -> 4188
C30: kg/mg litre | D30: =D29/(D9/1000) -> 5.4685191 | E30: =E29/(E9/1000) -> 7.7722724 | F30: =F29/(F9/1000) -> 4.0418166 | G30: =G29/(G9/1000) -> 4.5204057 | H30: =H29/(H9/1000) -> 3.2838916 | I30: =I29/(I9/1000) -> 4.8002478 | J30: =J29/(J9/1000) -> 6.2195171 | K30: =K29/(K9/1000) -> 5.2698528 | ... P30: =P29/(P9/1000) -> 5.3089086
A31: Aluminium sulphate | B31: =53000.511/50 -> 1060.0102 | C31: kg | P31: =SUM(D31:O31) -> 0
C32: kg/mg litre | D32: =D31/(D9/1000) -> 0 | E32: =E31/(E9/1000) -> 0 | F32: =F31/(F9/1000) -> 0 | G32: =G31/(G9/1000) -> 0 | H32: =H31/(H9/1000) -> 0 | I32: =I31/(I9/1000) -> 0 | J32: =J31/(J9/1000) -> 0 | K32: =K31/(K9/1000) -> 0 | ... P32: =P31/(P9/1000) -> 0
A33: Soda | B33: =61414.43/50 -> 1228.2886 | C33: kg | P33: =SUM(D33:O33) -> 0
C34: kg/mg litre | D34: =D33/(D9/1000) -> 0 | E34: =E33/(E9/1000) -> 0 | F34: =F33/(F9/1000) -> 0 | G34: =G33/(G9/1000) -> 0 | H34: =H33/(H9/1000) -> 0 | I34: =I33/(I9/1000) -> 0 | J34: =J33/(J9/1000) -> 0 | K34: =K33/(K9/1000) -> 0 | ... P34: =P33/(P9/1000) -> 0
A35: Algae floc | B35: =745345.16/200 -> 3726.7258 | C35: litres | E35: 248 | F35: 301 | G35: 224 | H35: 139 | I35: 155 | J35: 143 | K35: 110 | L35: 141 | M35: 473 | N35: 555 | O35: 465
C36: litres/mg litre | D36: =D35/(D9/1000) -> 0 | E36: =E35/(E9/1000) -> 4.0156741 | F36: =F35/(F9/1000) -> 5.1332776 | G36: =G35/(G9/1000) -> 3.577989 | H36: =H35/(H9/1000) -> 2.1840236 | I36: =I35/(I9/1000) -> 2.1819308 | J36: =J35/(J9/1000) -> 1.900408 | K36: =K35/(K9/1000) -> 1.5376228 | ... O36: =O35/(O9/1000) -> 8.6421589
A37: Sud floc | B37: =790318.72/200 -> 3951.5936 | C37: litres | D37: 0 | E37: 0 | F37: 0 | G37: 0 | H37: 0 | I37: 0 | J37: 0 | K37: 0 | L37: 0 | M37: 0 | N37: 0 | O37: 0 | P37: =SUM(D37:O37) -> 0
C38: litres/mg litre | D38: =D37/(D9/1000) -> 0 | E38: =E37/(E9/1000) -> 0 | F38: =F37/(F9/1000) -> 0 | G38: =G37/(G9/1000) -> 0 | H38: =H37/(H9/1000) -> 0 | I38: =I37/(I9/1000) -> 0 | J38: =J37/(J9/1000) -> 0 | K38: =K37/(K9/1000) -> 0 | ... P38: =P37/(P9/1000) -> 0
A39: Potasium permanganate | B39: 1950 | C39: kg | D39: 0 | E39: 0 | F39: 0 | G39: 0 | H39: 0 | I39: 0 | J39: 0 | K39: 0 | L39: 0 | M39: 0 | N39: 0 | O39: 0 | P39: =SUM(D39:O39) -> 0
C40: kg/mg litre | D40: =D39/(D9/1000) -> 0 | E40: =E39/(E9/1000) -> 0 | F40: =F39/(F9/1000) -> 0 | G40: =G39/(G9/1000) -> 0 | H40: =H39/(H9/1000) -> 0 | I40: =I39/(I9/1000) -> 0 | J40: =J39/(J9/1000) -> 0 | K40: =K39/(K9/1000) -> 0 | ... P40: =P39/(P9/1000) -> 0
A41: Cost of Chemicals | C41: Mk | D41: =(D29*$B29)+(D31*$B31)+(D33*$B33)+(D35*$B35)+(D37*$B37)+(D39*$B39) -> 1173921.6 | E41: =(E29*$B29)+(E31*$B31)+(E33*$B33)+(E35*$B35)+(E37*$B37)+(E39*$B39) -> 2616367.2 | F41: =(F29*$B29)+(F31*$B31)+(F33*$B33)+(F35*$B35)+(F37*$B37)+(F39*$B39) -> 1957238.2 | G41: =(G29*$B29)+(G31*$B31)+(G33*$B33)+(G35*$B35)+(G37*$B37)+(G39*$B39) -> 1832443.6 | H41: =(H29*$B29)+(H31*$B31)+(H33*$B33)+(H35*$B35)+(H37*$B37)+(H39*$B39) -> 1254800.5 | I41: =(I29*$B29)+(I31*$B31)+(I33*$B33)+(I35*$B35)+(I37*$B37)+(I39*$B39) -> 1779766.4 | J41: =(J29*$B29)+(J31*$B31)+(J33*$B33)+(J35*$B35)+(J37*$B37)+(J39*$B39) -> 2182757.5 | K41: =(K29*$B29)+(K31*$B31)+(K33*$B33)+(K35*$B35)+(K37*$B37)+(K39*$B39) -> 1738974.2 | ... O41: =(O29*$B29)+(O31*$B31)+(O33*$B33)+(O35*$B35)+(O37*$B37)+(O39*$B39) -> 3044335.4 | P41: =SUM(D41:O41) -> 25772663
A42: Cost/vol. Produced (chemicals) | C42: Mk/m3 | D42: =D41/D9 -> 19.278116 | E42: =E41/E9 -> 42.36483 | F42: =F41/F9 -> 33.378894 | G42: =G41/G9 -> 29.269925 | H42: =H41/H9 -> 19.715928 | I42: =I41/I9 -> 25.053723 | J42: =J41/J9 -> 29.007901 | K42: =K41/K9 -> 24.308058 | ... P42: =P41/P9 -> 32.670657
A43: Power
A44: Power Usage | C44: Kw | D44: 58220 | E44: 62314 | F44: 80016 | G44: 80016 | H44: 59746.46 | I44: 75397.09 | J44: 79061.46 | K44: 45632.8 | L44: 91364.46 | M44: 89974.21 | N44: 81920.69 | O44: 74974.77 | P44: =SUM(D44:O44) -> 878637.94
A45: Power/ Vol. Produced | C45: Kw/m3 | D45: =D44/D9 -> 0.95608763 | E45: =E44/E9 -> 1.0090029 | F45: =F44/F9 -> 1.3645991 | G45: =G44/G9 -> 1.2781088 | H45: =H44/H9 -> 0.93876029 | I45: =I44/I9 -> 1.0613628 | J45: =J44/J9 -> 1.0506925 | K45: =K44/K9 -> 0.63787305 | ... P45: =P44/P9 -> 1.1138034
A46: Cost of Power | C46: Mk | D46: =1.165*(14100+(D44*119.1)) -> 8094538.8 | E46: =1.165*(14100+(E44*119.1)) -> 8662587.5 | F46: =1.165*(14100+(F44*119.1)) -> 11118767 | G46: =1.165*(14100+(G44*119.1)) -> 11118767 | H46: =1.165*(16600+(H44*143.5)) -> 10007603 | I46: =1.165*(16600+(I44*143.5)) -> 12624036 | J46: =1.165*(16600+(J44*143.5)) -> 13236636 | K46: =1.165*(16600+(K44*143.5)) -> 7648116.4 | L46: =1.165*(16600+(L44*143.5)) -> 15293421 | M46: =1.165*(16600+(M44*143.5)) -> 15061002 | N46: =1.165*(16600+(N44*143.5)) -> 13714635 | O46: =1.165*(16600+(O44*143.5)) -> 12553434 | P46: =SUM(D46:O46) -> 1.3913354e+08
A47: Cost/vol. Produced | C47: Mk/m3 | D47: =D46/D9 -> 132.92835 | E47: =E46/E9 -> 140.26665 | F47: =F46/F9 -> 189.62032 | G47: =G46/G9 -> 177.60189 | H47: =H46/H9 -> 157.24346 | I47: =I46/I9 -> 177.70821 | J47: =J46/J9 -> 175.90916 | K47: =K46/K9 -> 106.90835 | ... P47: =P46/P9 -> 176.37232
A48: Plant and Vehicle Maintenance
A49: Distances covered | C49: km | D49: 2317 | E49: 2317 | F49: 2899 | G49: 3100 | H49: 2496 | I49: 2817 | J49: 2234 | K49: 2499 | L49: 3071 | M49: 1430 | N49: 1120 | O49: 3257 | P49: =SUM(D49:O49) -> 29557
A50: Fuel Used (litres) | C50: litres | D50: 287 | E50: 287 | F50: 189 | G50: 201 | H50: 213.86 | I50: 245 | J50: 136.7 | K50: 211 | L50: 278.33 | M50: 141 | N50: 98.29 | O50: 327 | P50: =SUM(D50:O50) -> 2615.18
A51: Cost of fuel | C51: Mk | D51: 551040 | E51: 551040 | F51: 362880 | G51: 385920 | H51: 410611.2 | I51: 470400 | J51: 262464 | K51: 575561.68 | L51: 1312320 | M51: 270720 | N51: 1438820 | O51: 627840 | P51: =SUM(D51:O51) -> 7219616.9
A52: Maintenance | C52: Mk | D52: 0 | E52: 0 | F52: 0 | G52: 0 | H52: 0 | I52: 0 | J52: 0 | K52: 0 | L52: 0 | M52: 0 | N52: 0 | O52: 0 | P52: =SUM(D52:O52) -> 0
A53: Salaries and Wages
A54: Staff Costs | C54: MK | D54: 7769395.8 | E54: 9535795.8 | F54: 9413858.5 | G54: 9413858.5 | H54: 8475099.7 | I54: 8060789.9 | J54: 8686302.5 | K54: 8606302.5 | L54: 11266594 | M54: 9781830 | N54: 7879712.3 | O54: 17045057 | P54: =SUM(D54:O54) -> 1.159346e+08
A55: Wages | C55: MK | D55: 4213745.2 | E55: 4056761.1 | F55: 4015255.4 | G55: 4015255.4 | H55: 1151550 | I55: 3699928.7 | J55: 3764540.5 | K55: 4067681.9 | L55: 3897829.3 | M55: 4276444.2 | N55: 2614435.4 | O55: 4076960.6 | P55: =SUM(D55:O55) -> 43850388
A56: Other Overhead Costs | C56: MK | D56: 129000 | E56: 1755122 | F56: 625000 | G56: 625000 | H56: 1903515 | I56: 6549300 | J56: 987000 | K56: 5184000 | L56: 3698661.5 | M56: 0 | N56: 2951890.7 | O56: 6297411.7 | P56: =SUM(D56:O56) -> 30705901
A57: Operating Costs
A58: Total Operating Costs | C58: MK | D58: =D41+D46+D51+D52+D54+D55+D56 -> 21931641 | E58: =E41+E46+E51+E52+E54+E55+E56 -> 27177674 | F58: =F41+F46+F51+F52+F54+F55+F56 -> 27492999 | G58: =G41+G46+G51+G52+G54+G55+G56 -> 27391244 | H58: =H41+H46+H51+H52+H54+H55+H56 -> 23203179 | I58: =I41+I46+I51+I52+I54+I55+I56 -> 33184221 | J58: =J41+J46+J51+J52+J54+J55+J56 -> 29119701 | K58: =K41+K46+K51+K52+K54+K55+K56 -> 27820637 | ... O58: =O41+O46+O51+O52+O54+O55+O56 -> 43645038 | P58: =SUM(D58:O58) -> 3.6261671e+08
A59: Cost/Vol. Produced | C59: Mk/m3 | D59: =D58/D9 -> 360.16096 | E59: =E58/E9 -> 440.06726 | F59: =F58/F9 -> 468.86776 | G59: =G58/G9 -> 437.52486 | H59: =H58/H9 -> 364.57764 | I59: =I58/I9 -> 467.13338 | J59: =J58/J9 -> 386.9882 | K59: =K58/K9 -> 388.88769 | ... P59: =P58/P9 -> 459.67024
A60: Cost/Vol. Billed | C60: Mk/m3 | D60: =D58/D22 -> 644.99137 | E60: =E58/E22 -> 701.61281 | F60: =F58/F22 -> 746.9036 | G60: =G58/G22 -> 725.28462 | H60: =H58/H22 -> 601.38349 | I60: =I58/I22 -> 825.60341 | J60: =J58/J22 -> 637.22046 | K60: =K58/K22 -> 656.27556 | ... P60: =P58/P22 -> 730.31392
A61: Permanent Staff Employed | C61: No | D61: 13 | E61: 13 | F61: 13 | G61: 13 | H61: 13 | I61: 13 | J61: 13 | K61: 13 | L61: 13 | M61: 13 | N61: 13 | O61: 13 | P61: =O61 -> 13
A62: Staff/Vol.1000m3 of Volume Produced/hour (12 hour day) | C62: No/1000m3 | D62: =(D61*1000*31)/D9 -> 6.6180576 | E62: =(E61*1000*31)/E9 -> 6.5254704 | F62: =(F61*1000*31)/F9 -> 6.8727936 | G62: =(G61*1000*31)/G9 -> 6.4371855 | H62: =(H61*1000*31)/H9 -> 6.3320973 | I62: =(I61*1000*31)/I9 -> 5.6730201 | J62: =(J61*1000*31)/J9 -> 5.3556952 | K62: =(K61*1000*31)/K9 -> 5.6332909 | ... P62: =(P61*1000*31)/P9 -> 0.51086203
A63: Temporary Staff Employed | C63: No | D63: 19 | E63: 19 | F63: 19 | G63: 19 | H63: 19 | I63: 19 | J63: 19 | K63: 19 | L63: 19 | M63: 38 | N63: 38 | O63: 38 | P63: =SUM(D63:O63) -> 285
A65: Water Connections and Disconnections
A66: New Individual Water Connections | B66: Brought Forward | C66: No | D66: 288 | E66: 305 | F66: 295 | G66: =F71 -> 319 | H66: 336 | I66: 348 | J66: 352 | K66: 349 | L66: 336 | M66: 339 | N66: 350 | O66: 341 | P66: =D66 -> 288
B67: Applied this Month | C67: No | D67: 24 | E67: 29 | F67: 59 | G67: 48 | H67: 51 | I67: 32 | J67: 38 | K67: 22 | L67: 40 | M67: 25 | N67: 21 | O67: 38 | P67: =SUM(D67:O67) -> 427
B68: Done this Month Postpaid | C68: No | D68: 7 | E68: 16 | F68: 35 | G68: 31 | H68: 39 | I68: 28 | J68: 41 | K68: 35 | L68: 37 | M68: 14 | N68: 30 | O68: 25 | P68: =SUM(D68:O68) -> 338
B69: Done this Month Prepaid | C69: No | D69: 0 | E69: 23 | F69: 0 | G69: 0 | H69: 0 | I69: 0 | J69: 0 | K69: 0 | L69: 0 | M69: 0 | N69: 0 | O69: 0 | P69: =SUM(D69:O69) -> 23
B70: Total Done | C70: No | D70: =D68+D69 -> 7 | E70: =E68+E69 -> 39 | F70: =F68+F69 -> 35 | G70: =G68+G69 -> 31 | H70: =H68+H69 -> 39 | I70: =I68+I69 -> 28 | J70: =J68+J69 -> 41 | K70: =K68+K69 -> 35 | ... P70: =P68+P69 -> 361
B71: Carried Forward | C71: No | D71: =D66+D67-D70 -> 305 | E71: =E66+E67-E70 -> 295 | F71: =F66+F67-F70 -> 319 | G71: =G66+G67-G70 -> 336 | H71: =H66+H67-H70 -> 348 | I71: =I66+I67-I70 -> 352 | J71: =J66+J67-J70 -> 349 | K71: =K66+K67-K70 -> 336 | ... P71: =P66+P67-P70 -> 354
A72: New Institutional Water Connections | B72: Brought Forward | C72: No | P72: =D72 -> 0
B73: Applied this Month | C73: No | P73: =SUM(D73:O73) -> 0
B74: Done this Month Postpaid | C74: No | P74: =SUM(D74:O74) -> 0
B75: Done this Month Prepaid | C75: No | P75: =SUM(D75:O75) -> 0
B76: Total Done | C76: No | D76: =D74+D75 -> 0 | E76: =E74+E75 -> 0 | F76: =F74+F75 -> 0 | G76: =G74+G75 -> 0 | H76: =H74+H75 -> 0 | I76: =I74+I75 -> 0 | J76: =J74+J75 -> 0 | K76: =K74+K75 -> 0 | ... P76: =P74+P75 -> 0
B77: Carried Forward | C77: No | D77: =D72+D73-D76 -> 0 | E77: =E72+E73-E76 -> 0 | F77: =F72+F73-F76 -> 0 | G77: =G72+G73-G76 -> 0 | H77: =H72+H73-H76 -> 0 | I77: =I72+I73-I76 -> 0 | J77: =J72+J73-J76 -> 0 | K77: =K72+K73-K76 -> 0 | ... P77: =P72+P73-P76 -> 0
A78: New Commercial/Industrial Water Connections | B78: Brought Forward | C78: No | P78: =D78 -> 0
B79: Applied this Month | C79: No | P79: =SUM(D79:O79) -> 0
B80: Done this Month Postpaid | C80: No | P80: =SUM(D80:O80) -> 0
B81: Done this Month Prepaid | C81: No | P81: =SUM(D81:O81) -> 0
B82: Total Done | C82: No | D82: =D81+D80 -> 0 | E82: =E81+E80 -> 0 | F82: =F81+F80 -> 0 | G82: =G81+G80 -> 0 | H82: =H81+H80 -> 0 | I82: =I81+I80 -> 0 | J82: =J81+J80 -> 0 | K82: =K81+K80 -> 0 | ... P82: =P81+P80 -> 0
B83: Carried Forward | C83: No | D83: =D78+D79-D82 -> 0 | E83: =E78+E79-E82 -> 0 | F83: =F78+F79-F82 -> 0 | G83: =G78+G79-G82 -> 0 | H83: =H78+H79-H82 -> 0 | I83: =I78+I79-I82 -> 0 | J83: =J78+J79-J82 -> 0 | K83: =K78+K79-K82 -> 0 | ... P83: =P78+P79-P82 -> 0
A84: New CWP | B84: Brought Forward | C84: No | D84: 0 | E84: 0 | F84: 0 | P84: =D84 -> 0
B85: Applied this Month | C85: No | D85: 0 | E85: 0 | F85: 0 | P85: =SUM(D85:O85) -> 0
B86: Done this Month Postpaid | C86: No | D86: 0 | E86: 0 | F86: 0 | P86: =SUM(D86:O86) -> 0
B87: Done this Month Prepaid | C87: No | D87: 0 | E87: 0 | F87: 0 | P87: =SUM(D87:O87) -> 0
B88: Total Done | C88: No | D88: =D87+D86 -> 0 | E88: =E87+E86 -> 0 | F88: =F87+F86 -> 0 | G88: =G87+G86 -> 0 | H88: =H87+H86 -> 0 | I88: =I87+I86 -> 0 | J88: =J87+J86 -> 0 | K88: =K87+K86 -> 0 | ... O88: =O87+O86 -> 0 | P88: =SUM(D88:O88) -> 0
B89: Carried Forward | C89: No | D89: =D84+D85-D88 -> 0 | E89: =E84+E85-E88 -> 0 | F89: =F84+F85-F88 -> 0 | G89: =G84+G85-G88 -> 0 | H89: =H84+H85-H88 -> 0 | I89: =I84+I85-I88 -> 0 | J89: =J84+J85-J88 -> 0 | K89: =K84+K85-K88 -> 0 | ... O89: =O84+O85-O88 -> 0 | P89: =P84+P85-P86-P87 -> 0
A90: Aggregated New Water connections | B90: Brought Forward | C90: No | D90: =D66+D72+D78+D84 -> 288 | E90: =E66+E72+E78+E84 -> 305 | F90: =F66+F72+F78+F84 -> 295 | G90: =G66+G72+G78+G84 -> 319 | H90: =H66+H72+H78+H84 -> 336 | I90: =I66+I72+I78+I84 -> 348 | J90: =J66+J72+J78+J84 -> 352 | K90: =K66+K72+K78+K84 -> 349 | ... O90: =O66+O72+O78+O84 -> 341 | P90: =D90 -> 288
B91: Applied this Month | C91: No | D91: =D67+D73+D79+D85 -> 24 | E91: =E67+E73+E79+E85 -> 29 | F91: =F67+F73+F79+F85 -> 59 | G91: =G67+G73+G79+G85 -> 48 | H91: =H67+H73+H79+H85 -> 51 | I91: =I67+I73+I79+I85 -> 32 | J91: =J67+J73+J79+J85 -> 38 | K91: =K67+K73+K79+K85 -> 22 | ... O91: =O67+O73+O79+O85 -> 38 | P91: =SUM(D91:O91) -> 427
B92: Done this Month Postpaid | C92: No | D92: =D68+D74+D80+D86 -> 7 | E92: =E68+E74+E80+E86 -> 16 | F92: =F68+F74+F80+F86 -> 35 | G92: =G68+G74+G80+G86 -> 31 | H92: =H68+H74+H80+H86 -> 39 | I92: =I68+I74+I80+I86 -> 28 | J92: =J68+J74+J80+J86 -> 41 | K92: =K68+K74+K80+K86 -> 35 | ... O92: =O68+O74+O80+O86 -> 25 | P92: =SUM(D92:O92) -> 338
B93: Done this Month Prepaid | D93: =D69+D75+D81+D87 -> 0 | E93: =E69+E75+E81+E87 -> 23 | F93: =F69+F75+F81+F87 -> 0 | G93: =G69+G75+G81+G87 -> 0 | H93: =H69+H75+H81+H87 -> 0 | I93: =I69+I75+I81+I87 -> 0 | J93: =J69+J75+J81+J87 -> 0 | K93: =K69+K75+K81+K87 -> 0 | ... O93: =O69+O75+O81+O87 -> 0 | P93: =SUM(D93:O93) -> 23
B94: Total Done | C94: No | D94: =D93+D92 -> 7 | E94: =E93+E92 -> 39 | F94: =F93+F92 -> 35 | G94: =G93+G92 -> 31 | H94: =H93+H92 -> 39 | I94: =I93+I92 -> 28 | J94: =J93+J92 -> 41 | K94: =K93+K92 -> 35 | ... P94: =P93+P92 -> 361
B95: Carried Forward | C95: No | D95: =D90+D91-D94 -> 305 | E95: =E90+E91-E94 -> 295 | F95: =F90+F91-F94 -> 319 | G95: =G90+G91-G94 -> 336 | H95: =H90+H91-H94 -> 348 | I95: =I90+I91-I94 -> 352 | J95: =J90+J91-J94 -> 349 | K95: =K90+K91-K94 -> 336 | ... P95: =P90+P91-P94 -> 354
A97: Prepaid Metering
A98: Prepaid Meters Installed | C98: No | D98: 696 | E98: 719 | F98: 719 | G98: 719 | H98: 719 | I98: 719 | J98: 719 | K98: 719 | L98: 719 | M98: 719 | N98: 719 | O98: 719 | P98: =SUM(D98:O98) -> 8605
A100: Active and Disconnected Accounts
A101: Disconnected Individual Accounts | C101: No | D101: 2188 | E101: 1307 | F101: 1307 | G101: 1296 | H101: 1255 | I101: 1329 | J101: 1352 | K101: 1412 | L101: 1398 | M101: 1443 | N101: 1409 | O101: 1388 | P101: =O101 -> 1388
A102: Disconnected institutional Accounts | C102: No | D102: 119 | E102: 40 | F102: 40 | G102: 42 | H102: 41 | I102: 43 | J102: 42 | K102: 42 | L102: 40 | M102: 39 | N102: 39 | O102: 39 | P102: =O102 -> 39
A103: Disconnected Commercial/Industrial Accounts | C103: No | D103: 253 | E103: 65 | F103: 65 | G103: 62 | H103: 61 | I103: 64 | J103: 68 | K103: 66 | L103: 67 | M103: 73 | N103: 69 | O103: 66 | P103: =O103 -> 66
A104: Disconnected CWP | C104: No | D104: 15 | E104: 15 | F104: 15 | G104: 15 | H104: 15 | I104: 15 | J104: 15 | K104: 15 | L104: 15 | M104: 15 | N104: 15 | O104: 15 | P104: =O104 -> 15
A105: Total Disconnected Accounts | C105: No | D105: =SUM(D101:D104) -> 2575 | E105: =SUM(E101:E104) -> 1427 | F105: =SUM(F101:F104) -> 1427 | G105: =SUM(G101:G104) -> 1415 | H105: =SUM(H101:H104) -> 1372 | I105: =SUM(I101:I104) -> 1451 | J105: =SUM(J101:J104) -> 1477 | K105: =SUM(K101:K104) -> 1535 | ... O105: =SUM(O101:O104) -> 1508 | P105: =O105 -> 1508
A106: Postpaid Consumers
...

Sheet Machinga
A1: SOUTHERN REGION WATER BOARD
A3: MONTHLY REPORTS - 2023/2024
A4: LIWONDE ZONE
A5: LIWONDE ZONE
A7: PARAMETERS | C7: UNITS | D7: APRIL | E7: MAY | F7: JUNE | G7: JULY | H7: AUGUST | I7: SEPTEMBER | J7: OCTOBER | K7: NOVEMBER | L7: DECEMBER | M7: JANUARY | N7: FEBRUARY | O7: MARCH | P7: TOTALS
A8: PRODUCTION | Q8: APR | R8: MAY | S8: JUN | T8: JUL | U8: AUG | V8: SEP | W8: OCT | X8: NOV | Y8: DEC | Z8: JAN | AA8: FEB | AB8: MAR | AC8: TOTAL
A9: Volume Produced | C9: m3 | D9: 3300 | E9: 3402 | F9: 3360 | G9: 3075 | H9: 2765 | I9: 3240 | J9: 3348 | K9: 3075 | L9: 2911 | M9: 2816 | N9: 3190 | O9: 2809 | P9: =SUM(D9:O9) -> 37291 | Q9: 0 | R9: 0 | S9: 0 | T9: 0 | U9: 0 | V9: 0 | W9: 0 | X9: 0 | Y9: 0 | Z9: 0 | AA9: 0 | AB9: 0 | AC9: 0
A10: REVENUE WATER - POSTPAID | Q10: 0 | R10: 0 | S10: 0 | T10: 0 | U10: 0 | V10: 0 | W10: 0 | X10: 0 | Y10: 0 | Z10: 0 | AA10: 0 | AB10: 0 | AC10: 0
A11: Volume Billed Individuals | C11: m3 | D11: 2555 | E11: 804 | F11: 1009 | G11: 796 | H11: 952 | I11: 1247 | J11: 1176 | K11: 1197 | L11: 1036 | M11: 994 | N11: 932 | O11: 902 | P11: =SUM(D11:O11) -> 13600 | Q11: 0 | R11: 0 | S11: 0 | T11: 0 | U11: 0 | V11: 0 | W11: 0 | X11: 0 | Y11: 0 | Z11: 0 | AA11: 0 | AB11: 0 | AC11: 0
A12: Volume Billed CWPs | C12: m3 | P12: =SUM(D12:O12) -> 0 | Q12: 0 | R12: 0 | S12: 0 | T12: 0 | U12: 0 | V12: 0 | W12: 0 | X12: 0 | Y12: 0 | Z12: 0 | AA12: 0 | AB12: 0 | AC12: 0
A13: Volume Billed Institutions | C13: m3 | E13: 1676 | F13: 41 | G13: 43 | H13: 52 | I13: 44 | J13: 30 | K13: 38 | L13: 40 | M13: 29 | N13: 19 | O13: 33 | P13: =SUM(D13:O13) -> 2045 | Q13: 0 | R13: 0 | S13: 0 | T13: 0 | U13: 0 | V13: 0 | W13: 0 | X13: 0 | Y13: 0 | Z13: 0 | AA13: 0 | AB13: 0 | AC13: 0
A14: Volume Billed Commercial/Industrial | C14: m3 | P14: =SUM(D14:O14) -> 0 | Q14: 0 | R14: 0 | S14: 0 | T14: 0 | U14: 0 | V14: 0 | W14: 0 | X14: 0 | Y14: 0 | Z14: 0 | AA14: 0 | AB14: 0 | AC14: 0
A15: Total Volume Billed Post Paid | C15: m3 | D15: =SUM(D11:D14) -> 2555 | E15: =SUM(E11:E14) -> 2480 | F15: =SUM(F11:F14) -> 1050 | G15: =SUM(G11:G14) -> 839 | H15: =SUM(H11:H14) -> 1004 | I15: =SUM(I11:I14) -> 1291 | J15: =SUM(J11:J14) -> 1206 | K15: =SUM(K11:K14) -> 1235 | ... P15: =SUM(P11:P14) -> 15645 | Q15: 0 | R15: 0 | S15: 0 | T15: 0 | U15: 0 | V15: 0 | W15: 0 | X15: 0 | Y15: 0 | Z15: 0 | AA15: 0 | AB15: 0 | AC15: 0
A16: REVENUE WATER - PREPAID
A17: Individuals | C17: m3 | E17: 901 | F17: 1670.2 | G17: 1542.6 | H17: 1742 | I17: 1492 | J17: 1575 | K17: 1517 | L17: 1537.3 | M17: 1467 | N17: 2066.88 | O17: 1602 | P17: =SUM(D17:O17) -> 17112.98
A18: CWPs | C18: m3 | P18: =SUM(D18:O18) -> 0
A19: Institutions | C19: m3 | P19: =SUM(D19:O19) -> 0
A20: Commercial/Industrial | C20: m3 | P20: =SUM(D20:O20) -> 0
A21: Total Volume Prepaid | C21: m3 | D21: =SUM(D17:D20) -> 0 | E21: =SUM(E17:E20) -> 901 | F21: =SUM(F17:F20) -> 1670.2 | G21: =SUM(G17:G20) -> 1542.6 | H21: =SUM(H17:H20) -> 1742 | I21: =SUM(I17:I20) -> 1492 | J21: =SUM(J17:J20) -> 1575 | K21: =SUM(K17:K20) -> 1517 | ... P21: =SUM(P17:P20) -> 17112.98
A22: TOTAL REVENUE WATER | C22: m3 | D22: =D21+D15 -> 2555 | E22: =E21+E15 -> 3381 | F22: =F21+F15 -> 2720.2 | G22: =G21+G15 -> 2381.6 | H22: =H21+H15 -> 2746 | I22: =I21+I15 -> 2783 | J22: =J21+J15 -> 2781 | K22: =K21+K15 -> 2752 | ... P22: =P21+P15 -> 32757.98
A24: Non-Revenue Water (NRW) | B24: Volume | C24: m3 | D24: =D9-D22 -> 745 | E24: =E9-E22 -> 21 | F24: =F9-F22 -> 639.8 | G24: =G9-G22 -> 693.4 | H24: =H9-H22 -> 19 | I24: =I9-I22 -> 457 | J24: =J9-J22 -> 567 | K24: =K9-K22 -> 323 | ... P24: =P9-P22 -> 4533.02
B25: Percentage | C25: % | D25: =D24/D9 -> 0.22575758 | E25: =E24/E9 -> 0.0061728395 | F25: =F24/F9 -> 0.19041667 | G25: =G24/G9 -> 0.22549593 | H25: =H24/H9 -> 0.0068716094 | I25: =I24/I9 -> 0.14104938 | J25: =J24/J9 -> 0.16935484 | K25: =K24/K9 -> 0.10504065 | ... P25: =P24/P9 -> 0.12155802
A26: OPERATING EXPENSES
A27: Chemicals
A28: Chemical | B28: Rate(MK/kg)
A29: Chlorine | B29: =176264.5/50 -> 3525.29 | C29: kg | D29: 12 | E29: 11 | F29: 10 | G29: 10 | H29: 10 | I29: 10 | J29: 11 | K29: 10 | L29: 11 | M29: 8 | N29: 7 | O29: 8 | P29: =SUM(D29:O29) -> 118
C30: kg/mg litre | D30: =D29/(D9/1000) -> 3.6363636 | E30: =E29/(E9/1000) -> 3.2333921 | F30: =F29/(F9/1000) -> 2.9761905 | G30: =G29/(G9/1000) -> 3.2520325 | H30: =H29/(H9/1000) -> 3.6166365 | I30: =I29/(I9/1000) -> 3.0864198 | J30: =J29/(J9/1000) -> 3.2855436 | K30: =K29/(K9/1000) -> 3.2520325 | ... P30: =P29/(P9/1000) -> 3.1643024
A31: Aluminium sulphate | B31: =53000.511/50 -> 1060.0102 | C31: kg | P31: =SUM(D31:O31) -> 0
C32: kg/mg litre | D32: =D31/(D9/1000) -> 0 | E32: =E31/(E9/1000) -> 0 | F32: =F31/(F9/1000) -> 0 | G32: =G31/(G9/1000) -> 0 | H32: =H31/(H9/1000) -> 0 | I32: =I31/(I9/1000) -> 0 | J32: =J31/(J9/1000) -> 0 | K32: =K31/(K9/1000) -> 0 | ... P32: =P31/(P9/1000) -> 0
A33: Soda | B33: =61414.43/50 -> 1228.2886 | C33: kg | P33: =SUM(D33:O33) -> 0
C34: kg/mg litre | D34: =D33/(D9/1000) -> 0 | E34: =E33/(E9/1000) -> 0 | F34: =F33/(F9/1000) -> 0 | G34: =G33/(G9/1000) -> 0 | H34: =H33/(H9/1000) -> 0 | I34: =I33/(I9/1000) -> 0 | J34: =J33/(J9/1000) -> 0 | K34: =K33/(K9/1000) -> 0 | ... P34: =P33/(P9/1000) -> 0
A35: Algae floc | B35: =745345.16/200 -> 3726.7258 | C35: litres
C36: litres/mg litre
A37: Sud floc | B37: =790318.72/200 -> 3951.5936 | C37: litres | D37: 0 | E37: 0 | F37: 0 | G37: 0 | H37: 0 | I37: 0 | J37: 0 | K37: 0 | L37: 0 | M37: 0 | N37: 0 | O37: 0 | P37: =SUM(D37:O37) -> 0
C38: litres/mg litre | D38: =D37/(D9/1000) -> 0 | E38: =E37/(E9/1000) -> 0 | F38: =F37/(F9/1000) -> 0 | G38: =G37/(G9/1000) -> 0 | H38: =H37/(H9/1000) -> 0 | I38: =I37/(I9/1000) -> 0 | J38: =J37/(J9/1000) -> 0 | K38: =K37/(K9/1000) -> 0 | ... P38: =P37/(P9/1000) -> 0
A39: Potasium permanganate | B39: 1950 | C39: kg | D39: 0 | E39: 0 | F39: 0 | G39: 0 | H39: 0 | I39: 0 | J39: 0 | K39: 0 | L39: 0 | M39: 0 | N39: 0 | O39: 0 | P39: =SUM(D39:O39) -> 0
C40: kg/mg litre | D40: =D39/(D9/1000) -> 0 | E40: =E39/(E9/1000) -> 0 | F40: =F39/(F9/1000) -> 0 | G40: =G39/(G9/1000) -> 0 | H40: =H39/(H9/1000) -> 0 | I40: =I39/(I9/1000) -> 0 | J40: =J39/(J9/1000) -> 0 | K40: =K39/(K9/1000) -> 0 | ... P40: =P39/(P9/1000) -> 0
A41: Cost of Chemicals | C41: Mk | D41: =(D29*$B29)+(D31*$B31)+(D33*$B33)+(D35*$B35)+(D37*$B37)+(D39*$B39) -> 42303.48 | E41: =(E29*$B29)+(E31*$B31)+(E33*$B33)+(E35*$B35)+(E37*$B37)+(E39*$B39) -> 38778.19 | F41: =(F29*$B29)+(F31*$B31)+(F33*$B33)+(F35*$B35)+(F37*$B37)+(F39*$B39) -> 35252.9 | G41: =(G29*$B29)+(G31*$B31)+(G33*$B33)+(G35*$B35)+(G37*$B37)+(G39*$B39) -> 35252.9 | H41: =(H29*$B29)+(H31*$B31)+(H33*$B33)+(H35*$B35)+(H37*$B37)+(H39*$B39) -> 35252.9 | I41: =(I29*$B29)+(I31*$B31)+(I33*$B33)+(I35*$B35)+(I37*$B37)+(I39*$B39) -> 35252.9 | J41: =(J29*$B29)+(J31*$B31)+(J33*$B33)+(J35*$B35)+(J37*$B37)+(J39*$B39) -> 38778.19 | K41: =(K29*$B29)+(K31*$B31)+(K33*$B33)+(K35*$B35)+(K37*$B37)+(K39*$B39) -> 35252.9 | ... O41: =(O29*$B29)+(O31*$B31)+(O33*$B33)+(O35*$B35)+(O37*$B37)+(O39*$B39) -> 28202.32 | P41: =SUM(D41:O41) -> 415984.22
A42: Cost/vol. Produced (chemicals) | C42: Mk/m3 | D42: =D41/D9 -> 12.819236 | E42: =E41/E9 -> 11.398645 | F42: =F41/F9 -> 10.491935 | G42: =G41/G9 -> 11.464358 | H42: =H41/H9 -> 12.749693 | I42: =I41/I9 -> 10.880525 | J42: =J41/J9 -> 11.582494 | K42: =K41/K9 -> 11.464358 | ... P42: =P41/P9 -> 11.155084
A43: Power
A44: Power Usage | C44: Kw | D44: 180 | E44: 496 | F44: 600 | G44: 217 | H44: 600 | I44: 496 | J44: 620 | K44: 444 | L44: 620 | M44: 428 | N44: 368 | O44: 300 | P44: =SUM(D44:O44) -> 5369
A45: Power/ Vol. Produced | C45: Kw/m3 | D45: =D44/D9 -> 0.054545455 | E45: =E44/E9 -> 0.14579659 | F45: =F44/F9 -> 0.17857143 | G45: =G44/G9 -> 0.070569106 | H45: =H44/H9 -> 0.21699819 | I45: =I44/I9 -> 0.15308642 | J45: =J44/J9 -> 0.18518519 | K45: =K44/K9 -> 0.14439024 | ... P45: =P44/P9 -> 0.14397576
A46: Cost of Power | C46: Mk | D46: =1.165*(14100+(D44*119.1)) -> 41401.77 | E46: =1.165*(14100+(E44*119.1)) -> 85247.244 | F46: =1.165*(14100+(F44*119.1)) -> 99677.4 | G46: =1.165*(14100+(G44*119.1)) -> 46535.575 | H46: =1.165*(16600+(H44*143.5)) -> 119645.5 | I46: =1.165*(16600+(I44*143.5)) -> 102259.04 | J46: =1.165*(16600+(J44*143.5)) -> 122989.05 | K46: =1.165*(16600+(K44*143.5)) -> 93565.81 | L46: =1.165*(16600+(L44*143.5)) -> 122989.05 | M46: =1.165*(16600+(M44*143.5)) -> 90890.97 | N46: =1.165*(16600+(N44*143.5)) -> 80860.32 | O46: =1.165*(16600+(O44*143.5)) -> 69492.25 | P46: =SUM(D46:O46) -> 1075554
A47: Cost/vol. Produced | C47: Mk/m3 | D47: =D46/D9 -> 12.545991 | E47: =E46/E9 -> 25.057979 | F47: =F46/F9 -> 29.665893 | G47: =G46/G9 -> 15.13352 | H47: =H46/H9 -> 43.271429 | I47: =I46/I9 -> 31.561432 | J47: =J46/J9 -> 36.735081 | K47: =K46/K9 -> 30.427906 | ... P47: =P46/P9 -> 28.842187
A48: Plant and Vehicle Maintenance
A49: Distances covered | C49: km | D49: 0 | E49: 0 | F49: 0 | P49: =SUM(D49:O49) -> 0
A50: Fuel Used (litres) | C50: litres | D50: 0 | E50: 0 | F50: 0 | P50: =SUM(D50:O50) -> 0
A51: Cost of fuel | C51: Mk | D51: 0 | E51: 0 | F51: 0 | P51: =SUM(D51:O51) -> 0
A52: Maintenance | C52: Mk | D52: 0 | E52: 0 | F52: 0 | G52: 0 | H52: 0 | I52: 0 | J52: 0 | K52: 0 | L52: 0 | M52: 0 | N52: 0 | O52: 0 | P52: =SUM(D52:O52) -> 0
A53: Salaries and Wages
A54: Staff Costs | C54: MK | D54: 986812.98 | E54: 1080861.3 | F54: 1080861.3 | G54: 1080861.3 | H54: 1426052.4 | I54: 1388916.9 | J54: 1412104.3 | K54: 1412104.3 | L54: 2624243 | M54: 1623699.6 | N54: 515333.54 | O54: 449769.11 | P54: =SUM(D54:O54) -> 15081620
A55: Wages | C55: MK | D55: 314683.76 | E55: 1051023.3 | F55: 1051023.3 | G55: 1051023.3 | H55: 371831.43 | I55: 360804.61 | J55: 378378.61 | K55: 864773.4 | L55: 358359.87 | M55: 184970.71 | N55: 163439.18 | O55: 450411.44 | P55: =SUM(D55:O55) -> 6600722.8
A56: Other Overhead Costs | C56: MK | D56: 13500 | E56: 1403000 | F56: 1403000 | G56: 1403000 | H56: 16500 | I56: 507500 | J56: 120000 | K56: 13500 | L56: 159384.8 | M56: 237346.44 | N56: 178846.44 | O56: 354160 | P56: =SUM(D56:O56) -> 5809737.7
A57: Operating Costs
A58: Total Operating Costs | C58: MK | D58: =D41+D46+D51+D52+D54+D55+D56 -> 1398702 | E58: =E41+E46+E51+E52+E54+E55+E56 -> 3658910 | F58: =F41+F46+F51+F52+F54+F55+F56 -> 3669814.9 | G58: =G41+G46+G51+G52+G54+G55+G56 -> 3616673 | H58: =H41+H46+H51+H52+H54+H55+H56 -> 1969282.2 | I58: =I41+I46+I51+I52+I54+I55+I56 -> 2394733.4 | J58: =J41+J46+J51+J52+J54+J55+J56 -> 2072250.2 | K58: =K41+K46+K51+K52+K54+K55+K56 -> 2419196.4 | ... O58: =O41+O46+O51+O52+O54+O55+O56 -> 1352035.1 | P58: =SUM(D58:O58) -> 28983619
A59: Cost/Vol. Produced | C59: Mk/m3 | D59: =D58/D9 -> 423.84909 | E59: =E58/E9 -> 1075.5173 | F59: =F58/F9 -> 1092.2068 | G59: =G58/G9 -> 1176.1538 | H59: =H58/H9 -> 712.21779 | I59: =I58/I9 -> 739.11526 | J59: =J58/J9 -> 618.95167 | K59: =K58/K9 -> 786.73055 | ... P59: =P58/P9 -> 777.22825
A60: Cost/Vol. Billed | C60: Mk/m3 | D60: =D58/D22 -> 547.43718 | E60: =E58/E22 -> 1082.1976 | F60: =F58/F22 -> 1349.0974 | G60: =G58/G22 -> 1518.5896 | H60: =H58/H22 -> 717.14574 | I60: =I58/I22 -> 860.48632 | J60: =J58/J22 -> 745.1457 | K60: =K58/K22 -> 879.06847 | ... P60: =P58/P22 -> 884.7804
A61: Permanent Staff Employed | C61: No | D61: 2 | E61: 2 | F61: 2 | G61: 3 | H61: 3 | I61: 3 | J61: 3 | K61: 3 | L61: 3 | M61: 3 | N61: 3 | O61: 3 | P61: =O61 -> 3
A62: Staff/Vol.1000m3 of Volume Produced/hour (12 hour day) | C62: No/1000m3 | D62: =(D61*1000*31)/D9 -> 18.787879 | E62: =(E61*1000*31)/E9 -> 18.224574 | F62: =(F61*1000*31)/F9 -> 18.452381 | G62: =(G61*1000*31)/G9 -> 30.243902 | H62: =(H61*1000*31)/H9 -> 33.63472 | I62: =(I61*1000*31)/I9 -> 28.703704 | J62: =(J61*1000*31)/J9 -> 27.777778 | K62: =(K61*1000*31)/K9 -> 30.243902 | ... P62: =(P61*1000*31)/P9 -> 2.4938993
A63: Temporary Staff Employed | C63: No | D63: 15 | E63: 15 | F63: 6 | G63: 6 | H63: 6 | I63: 6 | J63: 6 | K63: 6 | L63: 6 | M63: 8 | N63: 7 | O63: 8 | P63: =SUM(D63:O63) -> 95
A65: Water Connections and Disconnections
A66: New Individual Water Connections | B66: Brought Forward | C66: No | D66: 22 | E66: 22 | F66: 22 | G66: 12 | H66: 12 | I66: 12 | J66: 12 | K66: 11 | L66: 11 | M66: 11 | N66: 11 | O66: 11 | P66: =D66 -> 22
B67: Applied this Month | C67: No | D67: 2 | E67: 21 | F67: 4 | G67: 6 | H67: 5 | I67: 2 | J67: 1 | K67: 1 | L67: 1 | M67: 5 | N67: 1 | O67: 2 | P67: =SUM(D67:O67) -> 51
B68: Done this Month Postpaid | C68: No | D68: 2 | E68: 2 | F68: 2 | G68: 6 | H68: 5 | I68: 2 | J68: 2 | K68: 1 | L68: 1 | M68: 5 | N68: 1 | O68: 2 | P68: =SUM(D68:O68) -> 31
B69: Done this Month Prepaid | C69: No | D69: 0 | E69: 19 | F69: 12 | G69: 0 | H69: 0 | I69: 0 | J69: 0 | K69: 0 | L69: 0 | M69: 0 | N69: 0 | O69: 0 | P69: =SUM(D69:O69) -> 31
B70: Total Done | C70: No | D70: =D68+D69 -> 2 | E70: =E68+E69 -> 21 | F70: =F68+F69 -> 14 | G70: =G68+G69 -> 6 | H70: =H68+H69 -> 5 | I70: =I68+I69 -> 2 | J70: 2 | K70: =K68+K69 -> 1 | L70: =L68+L69 -> 1 | M70: =M68+M69 -> 5 | N70: =N68+N69 -> 1 | O70: =O68+O69 -> 2 | P70: =P68+P69 -> 62
B71: Carried Forward | C71: No | D71: =D66+D67-D70 -> 22 | E71: =E66+E67-E70 -> 22 | F71: =F66+F67-F70 -> 12 | G71: =G66+G67-G70 -> 12 | H71: =H66+H67-H70 -> 12 | I71: =I66+I67-I70 -> 12 | J71: =J66+J67-J70 -> 11 | K71: =K66+K67-K70 -> 11 | ... P71: =P66+P67-P70 -> 11
A72: New Institutional Water Connections | B72: Brought Forward | C72: No | G72: 0 | P72: =D72 -> 0
B73: Applied this Month | C73: No | G73: 1 | N73: 1 | P73: =SUM(D73:O73) -> 2
B74: Done this Month Postpaid | C74: No | G74: 1 | N74: 1 | P74: =SUM(D74:O74) -> 2
B75: Done this Month Prepaid | C75: No | G75: 0 | P75: =SUM(D75:O75) -> 0
B76: Total Done | C76: No | D76: =D74+D75 -> 0 | E76: =E74+E75 -> 0 | F76: =F74+F75 -> 0 | G76: =G74+G75 -> 1 | H76: =H74+H75 -> 0 | I76: =I74+I75 -> 0 | J76: =J74+J75 -> 0 | K76: =K74+K75 -> 0 | ... M76: =M74+M75 -> 0 | N76: 1 | O76: =O74+O75 -> 0 | P76: =P74+P75 -> 2
B77: Carried Forward | C77: No | D77: =D72+D73-D76 -> 0 | E77: =E72+E73-E76 -> 0 | F77: =F72+F73-F76 -> 0 | G77: =G72+G73-G76 -> 0 | H77: =H72+H73-H76 -> 0 | I77: =I72+I73-I76 -> 0 | J77: =J72+J73-J76 -> 0 | K77: =K72+K73-K76 -> 0 | ... P77: =P72+P73-P76 -> 0
A78: New Commercial/Industrial Water Connections | B78: Brought Forward | C78: No | P78: =D78 -> 0
B79: Applied this Month | C79: No | P79: =SUM(D79:O79) -> 0
B80: Done this Month Postpaid | C80: No | P80: =SUM(D80:O80) -> 0
B81: Done this Month Prepaid | C81: No | P81: =SUM(D81:O81) -> 0
B82: Total Done | C82: No | D82: =D81+D80 -> 0 | E82: =E81+E80 -> 0 | F82: =F81+F80 -> 0 | G82: =G81+G80 -> 0 | H82: =H81+H80 -> 0 | I82: =I81+I80 -> 0 | J82: =J81+J80 -> 0 | K82: =K81+K80 -> 0 | ... P82: =P81+P80 -> 0
B83: Carried Forward | C83: No | D83: =D78+D79-D82 -> 0 | E83: =E78+E79-E82 -> 0 | F83: =F78+F79-F82 -> 0 | G83: =G78+G79-G82 -> 0 | H83: =H78+H79-H82 -> 0 | I83: =I78+I79-I82 -> 0 | J83: =J78+J79-J82 -> 0 | K83: =K78+K79-K82 -> 0 | ... P83: =P78+P79-P82 -> 0
A84: New CWP | B84: Brought Forward | C84: No | D84: 0 | E84: 0 | F84: 0 | P84: =D84 -> 0
B85: Applied this Month | C85: No | D85: 0 | E85: 0 | F85: 0 | P85: =SUM(D85:O85) -> 0
B86: Done this Month Postpaid | C86: No | D86: 0 | E86: 0 | F86: 0 | P86: =SUM(D86:O86) -> 0
B87: Done this Month Prepaid | C87: No | D87: 0 | E87: 0 | F87: 0 | P87: =SUM(D87:O87) -> 0
B88: Total Done | C88: No | D88: =D87+D86 -> 0 | E88: =E87+E86 -> 0 | F88: =F87+F86 -> 0 | G88: =G87+G86 -> 0 | H88: =H87+H86 -> 0 | I88: =I87+I86 -> 0 | J88: =J87+J86 -> 0 | K88: =K87+K86 -> 0 | ... O88: =O87+O86 -> 0 | P88: =SUM(D88:O88) -> 0
B89: Carried Forward | C89: No | D89: =D84+D85-D88 -> 0 | E89: =E84+E85-E88 -> 0 | F89: =F84+F85-F88 -> 0 | G89: =G84+G85-G88 -> 0 | H89: =H84+H85-H88 -> 0 | I89: =I84+I85-I88 -> 0 | J89: =J84+J85-J88 -> 0 | K89: =K84+K85-K88 -> 0 | ... P89: =P84+P85-P88 -> 0
A90: Aggregated New Water connections | B90: Brought Forward | C90: No | D90: =D66+D72+D78+D84 -> 22 | E90: =E66+E72+E78+E84 -> 22 | F90: =F66+F72+F78+F84 -> 22 | G90: =G66+G72+G78+G84 -> 12 | H90: =H66+H72+H78+H84 -> 12 | I90: =I66+I72+I78+I84 -> 12 | J90: =J66+J72+J78+J84 -> 12 | K90: =K66+K72+K78+K84 -> 11 | ... O90: =O66+O72+O78+O84 -> 11 | P90: =D90 -> 22
B91: Applied this Month | C91: No | D91: =D67+D73+D79+D85 -> 2 | E91: =E67+E73+E79+E85 -> 21 | F91: =F67+F73+F79+F85 -> 4 | G91: =G67+G73+G79+G85 -> 7 | H91: =H67+H73+H79+H85 -> 5 | I91: =I67+I73+I79+I85 -> 2 | J91: =J67+J73+J79+J85 -> 1 | K91: =K67+K73+K79+K85 -> 1 | ... O91: =O67+O73+O79+O85 -> 2 | P91: =SUM(D91:O91) -> 53
B92: Done this Month Postpaid | C92: No | D92: =D68+D74+D80+D86 -> 2 | E92: =E68+E74+E80+E86 -> 2 | F92: =F68+F74+F80+F86 -> 2 | G92: =G68+G74+G80+G86 -> 7 | H92: =H68+H74+H80+H86 -> 5 | I92: =I68+I74+I80+I86 -> 2 | J92: =J68+J74+J80+J86 -> 2 | K92: =K68+K74+K80+K86 -> 1 | ... O92: =O68+O74+O80+O86 -> 2 | P92: =SUM(D92:O92) -> 33
B93: Done this Month Prepaid | D93: =D69+D75+D81+D87 -> 0 | E93: =E69+E75+E81+E87 -> 19 | F93: =F69+F75+F81+F87 -> 12 | G93: =G69+G75+G81+G87 -> 0 | H93: =H69+H75+H81+H87 -> 0 | I93: =I69+I75+I81+I87 -> 0 | J93: =J69+J75+J81+J87 -> 0 | K93: =K69+K75+K81+K87 -> 0 | ... O93: =O69+O75+O81+O87 -> 0 | P93: =SUM(D93:O93) -> 31
B94: Total Done | C94: No | D94: =D93+D92 -> 2 | E94: =E93+E92 -> 21 | F94: =F93+F92 -> 14 | G94: =G93+G92 -> 7 | H94: =H93+H92 -> 5 | I94: =I93+I92 -> 2 | J94: =J93+J92 -> 2 | K94: =K93+K92 -> 1 | ... P94: =P93+P92 -> 64
B95: Carried Forward | C95: No | D95: =D90+D91-D94 -> 22 | E95: =E90+E91-E94 -> 22 | F95: =F90+F91-F94 -> 12 | G95: =G90+G91-G94 -> 12 | H95: =H90+H91-H94 -> 12 | I95: =I90+I91-I94 -> 12 | J95: =J90+J91-J94 -> 11 | K95: =K90+K91-K94 -> 11 | ... P95: =P90+P91-P94 -> 11
A97: Prepaid Metering
A98: Prepaid Meters Installed | C98: No | D98: 104 | E98: 127 | F98: 139 | G98: 139 | H98: 139 | I98: 139 | J98: 139 | K98: 139 | L98: 139 | M98: 139 | N98: 139 | O98: 139 | P98: =SUM(D98:O98) -> 1621
A100: Active and Disconnected Accounts
A101: Disconnected Individual Accounts | C101: No | P101: =O101 -> 0
A102: Disconnected institutional Accounts | C102: No | P102: =O102 -> 0
A103: Disconnected Commercial/Industrial Accounts | C103: No | P103: =O103 -> 0
A104: Disconnected CWP | C104: No | P104: =O104 -> 0
A105: Total Disconnected Accounts | C105: No | D105: =SUM(D101:D104) -> 0 | E105: =SUM(E101:E104) -> 0 | F105: =SUM(F101:F104) -> 0 | G105: =SUM(G101:G104) -> 0 | H105: =SUM(H101:H104) -> 0 | I105: =SUM(I101:I104) -> 0 | J105: =SUM(J101:J104) -> 0 | K105: =SUM(K101:K104) -> 0 | ... O105: =SUM(O101:O104) -> 0 | P105: =O105 -> 0
A106: Postpaid Consumers
...

Sheet Ntaja
A1: SOUTHERN REGION WATER BOARD
A3: MONTHLY REPORTS - 2023/2024
A4: LIWONDE ZONE
A5: LIWONDE ZONE
A7: PARAMETERS | C7: UNITS | D7: APRIL | E7: MAY | F7: JUNE | G7: JULY | H7: AUGUST | I7: SEPTEMBER | J7: OCTOBER | K7: NOVEMBER | L7: DECEMBER | M7: JANUARY | N7: FEBRUARY | O7: MARCH | P7: TOTALS
A8: PRODUCTION | Q8: APR | R8: MAY | S8: JUN | T8: JUL | U8: AUG | V8: SEP | W8: OCT | X8: NOV | Y8: DEC | Z8: JAN | AA8: FEB | AB8: MAR | AC8: TOTAL
A9: Volume Produced | C9: m3 | D9: 6552 | E9: 1800 | F9: 2556.01 | G9: 2432 | H9: 2810 | I9: 2860 | J9: 2921 | K9: 2981 | L9: 3069 | M9: 2518 | N9: 2718 | O9: 2909 | P9: =SUM(D9:O9) -> 36126.01 | Q9: 0 | R9: 0 | S9: 0 | T9: 0 | U9: 0 | V9: 0 | W9: 0 | X9: 0 | Y9: 0 | Z9: 0 | AA9: 0 | AB9: 0 | AC9: 0
A10: REVENUE WATER - POSTPAID | Q10: 0 | R10: 0 | S10: 0 | T10: 0 | U10: 0 | V10: 0 | W10: 0 | X10: 0 | Y10: 0 | Z10: 0 | AA10: 0 | AB10: 0 | AC10: 0
A11: Volume Billed Individuals | C11: m3 | D11: 620 | E11: 446 | F11: 5 | G11: 4 | H11: 5 | I11: 5 | J11: 37 | K11: 65 | L11: 103 | M11: 92 | N11: 47 | O11: 76 | P11: =SUM(D11:O11) -> 1505 | Q11: 0 | R11: 0 | S11: 0 | T11: 0 | U11: 0 | V11: 0 | W11: 0 | X11: 0 | Y11: 0 | Z11: 0 | AA11: 0 | AB11: 0 | AC11: 0
A12: Volume Billed CWPs | C12: m3 | D12: 0 | E12: 0 | F12: 0 | G12: 0 | H12: 0 | I12: 0 | J12: 0 | K12: 0 | L12: 0 | M12: 0 | N12: 0 | O12: 0 | P12: =SUM(D12:O12) -> 0 | Q12: 0 | R12: 0 | S12: 0 | T12: 0 | U12: 0 | V12: 0 | W12: 0 | X12: 0 | Y12: 0 | Z12: 0 | AA12: 0 | AB12: 0 | AC12: 0
A13: Volume Billed Institutions | C13: m3 | D13: 23 | E13: 8 | F13: 14 | G13: 13 | H13: 14 | I13: 32 | J13: 6 | K13: 5 | M13: 11 | N13: 11 | O13: 19 | P13: =SUM(D13:O13) -> 156 | Q13: 0 | R13: 0 | S13: 0 | T13: 0 | U13: 0 | V13: 0 | W13: 0 | X13: 0 | Y13: 0 | Z13: 0 | AA13: 0 | AB13: 0 | AC13: 0
A14: Volume Billed Commercial/Industrial | C14: m3 | D14: 0 | E14: 2 | F14: 0 | G14: 0 | H14: 0 | I14: 0 | J14: 0 | K14: 0 | L14: 0 | M14: 0 | N14: 0 | O14: 0 | P14: =SUM(D14:O14) -> 2 | Q14: 0 | R14: 0 | S14: 0 | T14: 0 | U14: 0 | V14: 0 | W14: 0 | X14: 0 | Y14: 0 | Z14: 0 | AA14: 0 | AB14: 0 | AC14: 0
A15: Total Volume Billed Post Paid | C15: m3 | D15: =SUM(D11:D14) -> 643 | E15: =SUM(E11:E14) -> 456 | F15: =SUM(F11:F14) -> 19 | G15: =SUM(G11:G14) -> 17 | H15: =SUM(H11:H14) -> 19 | I15: =SUM(I11:I14) -> 37 | J15: =SUM(J11:J14) -> 43 | K15: =SUM(K11:K14) -> 70 | ... P15: =SUM(P11:P14) -> 1663 | Q15: 0 | R15: 0 | S15: 0 | T15: 0 | U15: 0 | V15: 0 | W15: 0 | X15: 0 | Y15: 0 | Z15: 0 | AA15: 0 | AB15: 0 | AC15: 0
A16: REVENUE WATER - PREPAID | Q16: 0 | R16: 0 | S16: 0 | T16: 0 | U16: 0 | V16: 0 | W16: 0 | X16: 0 | Y16: 0 | Z16: 0 | AA16: 0 | AB16: 0 | AC16: 0
A17: Individuals | C17: m3 | D17: 577 | E17: 659 | F17: 2068.9 | G17: 2081 | H17: 2351 | I17: 2038 | J17: 2301 | K17: 2423 | L17: 2340 | M17: 1890 | N17: 2069 | O17: 2305 | P17: =SUM(D17:O17) -> 23102.9
A18: CWPs | C18: m3 | D18: 21 | E18: 11 | F18: 60 | G18: 75 | H18: 71 | I18: 86 | J18: 131 | K18: 148 | L18: 118 | M18: 118 | N18: 104 | O18: 94 | P18: =SUM(D18:O18) -> 1037
A19: Institutions | C19: m3 | D19: 23 | E19: 30 | F19: 75 | G19: 61 | H19: 52 | I19: 97 | J19: 88 | K19: 64 | L19: 201 | M19: 44 | N19: 48 | O19: 45 | P19: =SUM(D19:O19) -> 828
A20: Commercial/Industrial | C20: m3 | D20: 52 | E20: 28 | F20: 83 | G20: 86 | H20: 81 | I20: 120 | J20: 95 | K20: 156 | L20: 116 | M20: 86 | N20: 111 | O20: 113 | P20: =SUM(D20:O20) -> 1127
A21: Total Volume Prepaid | C21: m3 | D21: =SUM(D17:D20) -> 673 | E21: =SUM(E17:E20) -> 728 | F21: =SUM(F17:F20) -> 2286.9 | G21: =SUM(G17:G20) -> 2303 | H21: =SUM(H17:H20) -> 2555 | I21: =SUM(I17:I20) -> 2341 | J21: =SUM(J17:J20) -> 2615 | K21: =SUM(K17:K20) -> 2791 | ... P21: =SUM(P17:P20) -> 26094.9
A22: TOTAL REVENUE WATER | C22: m3 | D22: =D21+D15 -> 1316 | E22: =E21+E15 -> 1184 | F22: =F21+F15 -> 2305.9 | G22: =G21+G15 -> 2320 | H22: =H21+H15 -> 2574 | I22: =I21+I15 -> 2378 | J22: =J21+J15 -> 2658 | K22: =K21+K15 -> 2861 | ... P22: =P21+P15 -> 27757.9
A24: Non-Revenue Water (NRW) | B24: Volume | C24: m3 | D24: =D9-D22 -> 5236 | E24: =E9-E22 -> 616 | F24: =F9-F22 -> 250.11 | G24: =G9-G22 -> 112 | H24: =H9-H22 -> 236 | I24: =I9-I22 -> 482 | J24: =J9-J22 -> 263 | K24: =K9-K22 -> 120 | ... P24: =P9-P22 -> 8368.11
B25: Percentage | C25: % | D25: =D24/D9 -> 0.7991453 | E25: =E24/E9 -> 0.34222222 | F25: =F24/F9 -> 0.09785173 | G25: =G24/G9 -> 0.046052632 | H25: =H24/H9 -> 0.083985765 | I25: =I24/I9 -> 0.16853147 | J25: =J24/J9 -> 0.090037658 | K25: =K24/K9 -> 0.040254948 | ... P25: =P24/P9 -> 0.23163671
A26: OPERATING EXPENSES
A27: Chemicals
A28: Chemical | B28: Rate(MK/kg)
A29: Chlorine | B29: =176264.5/50 -> 3525.29 | C29: kg | D29: 8 | E29: 8 | F29: 4 | G29: 8 | H29: 8 | I29: 8 | J29: 8 | K29: 9 | L29: 11 | M29: 13 | N29: 12 | O29: 6 | P29: =SUM(D29:O29) -> 103
C30: kg/mg litre | D30: =D29/(D9/1000) -> 1.2210012 | E30: =E29/(E9/1000) -> 4.4444444 | F30: =F29/(F9/1000) -> 1.5649391 | G30: =G29/(G9/1000) -> 3.2894737 | H30: =H29/(H9/1000) -> 2.8469751 | I30: =I29/(I9/1000) -> 2.7972028 | J30: =J29/(J9/1000) -> 2.7387881 | K30: =K29/(K9/1000) -> 3.0191211 | ... P30: =P29/(P9/1000) -> 2.8511314
A31: Aluminium sulphate | B31: =53000.511/50 -> 1060.0102 | C31: kg | P31: =SUM(D31:O31) -> 0
C32: kg/mg litre | D32: =D31/(D9/1000) -> 0 | E32: =E31/(E9/1000) -> 0 | F32: =F31/(F9/1000) -> 0 | G32: =G31/(G9/1000) -> 0 | H32: =H31/(H9/1000) -> 0 | I32: =I31/(I9/1000) -> 0 | J32: =J31/(J9/1000) -> 0 | K32: =K31/(K9/1000) -> 0 | ... P32: =P31/(P9/1000) -> 0
A33: Soda | B33: =61414.43/50 -> 1228.2886 | C33: kg | P33: =SUM(D33:O33) -> 0
C34: kg/mg litre | D34: =D33/(D9/1000) -> 0 | E34: =E33/(E9/1000) -> 0 | F34: =F33/(F9/1000) -> 0 | G34: =G33/(G9/1000) -> 0 | H34: =H33/(H9/1000) -> 0 | I34: =I33/(I9/1000) -> 0 | J34: =J33/(J9/1000) -> 0 | K34: =K33/(K9/1000) -> 0 | ... P34: =P33/(P9/1000) -> 0
A35: Algae floc | B35: =745345.16/200 -> 3726.7258 | C35: litres
C36: litres/mg litre
A37: Sud floc | B37: =790318.72/200 -> 3951.5936 | C37: litres | D37: 0 | E37: 0 | F37: 0 | G37: 0 | H37: 0 | I37: 0 | J37: 0 | K37: 0 | L37: 0 | M37: 0 | N37: 0 | O37: 0 | P37: =SUM(D37:O37) -> 0
C38: litres/mg litre | D38: =D37/(D9/1000) -> 0 | E38: =E37/(E9/1000) -> 0 | F38: =F37/(F9/1000) -> 0 | G38: =G37/(G9/1000) -> 0 | H38: =H37/(H9/1000) -> 0 | I38: =I37/(I9/1000) -> 0 | J38: =J37/(J9/1000) -> 0 | K38: =K37/(K9/1000) -> 0 | ... P38: =P37/(P9/1000) -> 0
A39: Potasium permanganate | B39: 1950 | C39: kg | D39: 0 | E39: 0 | F39: 0 | G39: 0 | H39: 0 | I39: 0 | J39: 0 | K39: 0 | L39: 0 | M39: 0 | N39: 0 | O39: 0 | P39: =SUM(D39:O39) -> 0
C40: kg/mg litre | D40: =D39/(D9/1000) -> 0 | E40: =E39/(E9/1000) -> 0 | F40: =F39/(F9/1000) -> 0 | G40: =G39/(G9/1000) -> 0 | H40: =H39/(H9/1000) -> 0 | I40: =I39/(I9/1000) -> 0 | J40: =J39/(J9/1000) -> 0 | K40: =K39/(K9/1000) -> 0 | ... P40: =P39/(P9/1000) -> 0
A41: Cost of Chemicals | C41: Mk | D41: =(D29*$B29)+(D31*$B31)+(D33*$B33)+(D35*$B35)+(D37*$B37)+(D39*$B39) -> 28202.32 | E41: =(E29*$B29)+(E31*$B31)+(E33*$B33)+(E35*$B35)+(E37*$B37)+(E39*$B39) -> 28202.32 | F41: =(F29*$B29)+(F31*$B31)+(F33*$B33)+(F35*$B35)+(F37*$B37)+(F39*$B39) -> 14101.16 | G41: =(G29*$B29)+(G31*$B31)+(G33*$B33)+(G35*$B35)+(G37*$B37)+(G39*$B39) -> 28202.32 | H41: =(H29*$B29)+(H31*$B31)+(H33*$B33)+(H35*$B35)+(H37*$B37)+(H39*$B39) -> 28202.32 | I41: =(I29*$B29)+(I31*$B31)+(I33*$B33)+(I35*$B35)+(I37*$B37)+(I39*$B39) -> 28202.32 | J41: =(J29*$B29)+(J31*$B31)+(J33*$B33)+(J35*$B35)+(J37*$B37)+(J39*$B39) -> 28202.32 | K41: =(K29*$B29)+(K31*$B31)+(K33*$B33)+(K35*$B35)+(K37*$B37)+(K39*$B39) -> 31727.61 | ... O41: =(O29*$B29)+(O31*$B31)+(O33*$B33)+(O35*$B35)+(O37*$B37)+(O39*$B39) -> 21151.74 | P41: =SUM(D41:O41) -> 363104.87
A42: Cost/vol. Produced (chemicals) | C42: Mk/m3 | D42: =D41/D9 -> 4.3043834 | E42: =E41/E9 -> 15.667956 | F42: =F41/F9 -> 5.5168642 | G42: =G41/G9 -> 11.596349 | H42: =H41/H9 -> 10.036413 | I42: =I41/I9 -> 9.860951 | J42: =J41/J9 -> 9.6550223 | K42: =K41/K9 -> 10.643277 | ... P42: =P41/P9 -> 10.051065
A43: Power
A44: Power Usage | C44: Kw | D44: 3373.34 | E44: 3911 | F44: 3813.35 | G44: 3781.36 | H44: 3724 | I44: 3621 | J44: 3480.08 | K44: 2821 | L44: 4312 | M44: 4380 | N44: 4210 | O44: 4398 | P44: =SUM(D44:O44) -> 45825.13
A45: Power/ Vol. Produced | C45: Kw/m3 | D45: =D44/D9 -> 0.51485653 | E45: =E44/E9 -> 2.1727778 | F45: =F44/F9 -> 1.4919151 | G45: =G44/G9 -> 1.5548355 | H45: =H44/H9 -> 1.3252669 | I45: =I44/I9 -> 1.2660839 | J45: =J44/J9 -> 1.1914002 | K45: =K44/K9 -> 0.94632674 | ... P45: =P44/P9 -> 1.2684802
A46: Cost of Power | C46: Mk | D46: =1.165*(14100+(D44*119.1)) -> 484482.49 | E46: =1.165*(14100+(E44*119.1)) -> 559083.62 | F46: =1.165*(14100+(F44*119.1)) -> 545534.53 | G46: =1.165*(14100+(G44*119.1)) -> 541095.87 | H46: =1.165*(16600+(H44*143.5)) -> 641908.01 | I46: =1.165*(16600+(I44*143.5)) -> 624688.73 | J46: =1.165*(16600+(J44*143.5)) -> 601130.07 | K46: =1.165*(16600+(K44*143.5)) -> 490946.73 | L46: 490946.73 | M46: 490946.73 | N46: 490946.73 | O46: 490946.73 | P46: =SUM(D46:O46) -> 6452657
A47: Cost/vol. Produced | C47: Mk/m3 | D47: =D46/D9 -> 73.944213 | E47: =E46/E9 -> 310.60201 | F47: =F46/F9 -> 213.43208 | G47: =G46/G9 -> 222.49008 | H47: =H46/H9 -> 228.43701 | I47: =I46/I9 -> 218.42263 | J47: =J46/J9 -> 205.79599 | K47: =K46/K9 -> 164.69196 | ... P47: =P46/P9 -> 178.61527
A48: Plant and Vehicle Maintenance
A49: Distances covered | C49: km | P49: =SUM(D49:O49) -> 0
A50: Fuel Used (litres) | C50: litres | I50: 15 | K50: 20 | N50: 16 | O50: 4 | P50: =SUM(D50:O50) -> 55
A51: Cost of fuel | C51: Mk | I51: 26190 | K51: 50600 | P51: =SUM(D51:O51) -> 76790
A52: Maintenance | C52: Mk | D52: 0 | E52: 0 | F52: 0 | G52: 0 | H52: 0 | I52: 0 | J52: 0 | K52: 0 | L52: 0 | M52: 0 | N52: 0 | O52: 0 | P52: =SUM(D52:O52) -> 0
A53: Salaries and Wages
A54: Staff Costs | C54: MK | D54: 1995277.1 | E54: 1380254.3 | F54: 1380254.3 | G54: 1380254.3 | H54: 1273091.7 | I54: 1357556.9 | J54: 1405880.8 | K54: 1405880.8 | L54: 2559348.3 | M54: 1223684.2 | N54: 2244726.3 | O54: 2142163 | P54: =SUM(D54:O54) -> 19748372
A55: Wages | C55: MK | D55: 299544.51 | E55: 321587.71 | F55: 321587.71 | G55: 388462.24 | H55: 407682.96 | I55: 315385.12 | J55: 288462 | K55: 544231.64 | L55: 707593.44 | M55: 157692.56 | N55: 165384.87 | O55: 359615.96 | P55: =SUM(D55:O55) -> 4277230.7
A56: Other Overhead Costs | C56: MK | D56: 0 | E56: 36000 | F56: 36000 | G56: 36000 | H56: 226000 | I56: 1215686.8 | J56: 112000 | K56: 30000 | L56: 20000 | M56: 162500 | N56: 162500 | O56: 88000 | P56: =SUM(D56:O56) -> 2124686.8
A57: Operating Costs
A58: Total Operating Costs | C58: MK | D58: =D41+D46+D51+D52+D54+D55+D56 -> 2807506.4 | E58: =E41+E46+E51+E52+E54+E55+E56 -> 2325127.9 | F58: =F41+F46+F51+F52+F54+F55+F56 -> 2297477.7 | G58: =G41+G46+G51+G52+G54+G55+G56 -> 2374014.7 | H58: =H41+H46+H51+H52+H54+H55+H56 -> 2576885 | I58: =I41+I46+I51+I52+I54+I55+I56 -> 3567709.9 | J58: =J41+J46+J51+J52+J54+J55+J56 -> 2435675.2 | K58: =K41+K46+K51+K52+K54+K55+K56 -> 2553386.8 | ... O58: =O41+O46+O51+O52+O54+O55+O56 -> 3101877.4 | P58: =SUM(D58:O58) -> 33042841
A59: Cost/Vol. Produced | C59: Mk/m3 | D59: =D58/D9 -> 428.49609 | E59: =E58/E9 -> 1291.7377 | F59: =F58/F9 -> 898.85316 | G59: =G58/G9 -> 976.15736 | H59: =H58/H9 -> 917.04093 | I59: =I58/I9 -> 1247.451 | J59: =J58/J9 -> 833.84978 | K59: =K58/K9 -> 856.55377 | ... P59: =P58/P9 -> 914.65516
A60: Cost/Vol. Billed | C60: Mk/m3 | D60: =D58/D22 -> 2133.3635 | E60: =E58/E22 -> 1963.7905 | F60: =F58/F22 -> 996.34749 | G60: =G58/G22 -> 1023.2822 | H60: =H58/H22 -> 1001.1208 | I60: =I58/I22 -> 1500.2985 | J60: =J58/J22 -> 916.35636 | K60: =K58/K22 -> 892.48053 | ... P60: =P58/P22 -> 1190.3941
A61: Permanent Staff Employed | C61: No | D61: 9 | E61: 6 | F61: 6 | G61: 6 | H61: 6 | I61: 6 | J61: 6 | K61: 6 | L61: 6 | M61: 6 | N61: 6 | O61: 9 | P61: =O61 -> 9
A62: Staff/Vol.1000m3 of Volume Produced/hour (12 hour day) | C62: No/1000m3 | D62: =(D61*1000*31)/D9 -> 42.582418 | E62: =(E61*1000*31)/E9 -> 103.33333 | F62: =(F61*1000*31)/F9 -> 72.769668 | G62: =(G61*1000*31)/G9 -> 76.480263 | H62: =(H61*1000*31)/H9 -> 66.192171 | I62: =(I61*1000*31)/I9 -> 65.034965 | J62: =(J61*1000*31)/J9 -> 63.676823 | K62: =(K61*1000*31)/K9 -> 62.395169 | ... P62: =(P61*1000*31)/P9 -> 7.7229675
A63: Temporary Staff Employed | C63: No | D63: 6 | E63: 6 | F63: 6 | G63: 8 | H63: 9 | I63: 6 | J63: 6 | K63: 14 | L63: 6 | M63: 6 | N63: 6 | O63: 6 | P63: =SUM(D63:O63) -> 85
A65: Water Connections and Disconnections
A66: New Individual Water Connections | B66: Brought Forward | C66: No | D66: 2 | E66: 2 | F66: 7 | G66: 13 | H66: 7 | I66: 22 | J66: 32 | K66: 38 | L66: 38 | M66: 59 | N66: 64 | O66: 67 | P66: =D66 -> 2
B67: Applied this Month | C67: No | D67: 8 | E67: 11 | F67: 18 | G67: 25 | H67: 46 | I67: 14 | J67: 6 | K67: 0 | L67: 21 | M67: 5 | N67: 7 | O67: 3 | P67: =SUM(D67:O67) -> 164
B68: Done this Month Postpaid | C68: No | D68: 0 | E68: 0 | F68: 0 | G68: 0 | H68: 0 | I68: 0 | J68: 0 | K68: 0 | L68: 0 | M68: 0 | N68: 4 | O68: 0 | P68: =SUM(D68:O68) -> 4
B69: Done this Month Prepaid | C69: No | D69: 8 | E69: 6 | F69: 12 | G69: 31 | H69: 31 | I69: 4 | J69: 0 | K69: 0 | M69: 0 | N69: 0 | O69: 3 | P69: =SUM(D69:O69) -> 95
B70: Total Done | C70: No | D70: =D68+D69 -> 8 | E70: =E68+E69 -> 6 | F70: =F68+F69 -> 12 | G70: =G68+G69 -> 31 | H70: 31 | I70: =I68+I69 -> 4 | J70: =J68+J69 -> 0 | K70: =K68+K69 -> 0 | L70: =L68+L69 -> 0 | M70: =M68+M69 -> 0 | N70: =N68+N69 -> 4 | O70: =O68+O69 -> 3 | P70: =P68+P69 -> 99
B71: Carried Forward | C71: No | D71: =D66+D67-D70 -> 2 | E71: =E66+E67-E70 -> 7 | F71: =F66+F67-F70 -> 13 | G71: =G66+G67-G70 -> 7 | H71: =H66+H67-H70 -> 22 | I71: =I66+I67-I70 -> 32 | J71: =J66+J67-J70 -> 38 | K71: =K66+K67-K70 -> 38 | ... P71: =P66+P67-P70 -> 67
A72: New Institutional Water Connections | B72: Brought Forward | C72: No | D72: 0 | E72: 0 | F72: 0 | H72: 0 | P72: =D72 -> 0
B73: Applied this Month | C73: No | D73: 0 | E73: 0 | F73: 0 | H73: 1 | P73: =SUM(D73:O73) -> 1
B74: Done this Month Postpaid | C74: No | D74: 0 | E74: 0 | F74: 0 | P74: =SUM(D74:O74) -> 0
B75: Done this Month Prepaid | C75: No | D75: 0 | E75: 0 | F75: 0 | H75: 1 | P75: =SUM(D75:O75) -> 1
B76: Total Done | C76: No | D76: =D74+D75 -> 0 | E76: =E74+E75 -> 0 | F76: =F74+F75 -> 0 | G76: =G74+G75 -> 0 | H76: 1 | I76: =I74+I75 -> 0 | J76: =J74+J75 -> 0 | K76: =K74+K75 -> 0 | L76: =L74+L75 -> 0 | M76: =M74+M75 -> 0 | N76: =N74+N75 -> 0 | O76: =O74+O75 -> 0 | P76: =P74+P75 -> 1
B77: Carried Forward | C77: No | D77: =D72+D73-D76 -> 0 | E77: =E73+E74-E76 -> 0 | F77: =F73+F74-F76 -> 0 | G77: =G73+G74-G76 -> 0 | H77: =H73+H74-H76 -> 0 | I77: =I73+I74-I76 -> 0 | J77: =J73+J74-J76 -> 0 | K77: =K73+K74-K76 -> 0 | L77: =L73+L74-L76 -> 0 | ... P77: =P73+P74-P76 -> 0
A78: New Commercial/Industrial Water Connections | B78: Brought Forward | C78: No | D78: 0 | E78: 0 | F78: 0 | P78: =D78 -> 0
B79: Applied this Month | C79: No | D79: 0 | E79: 0 | F79: 0 | P79: =SUM(D79:O79) -> 0
B80: Done this Month Postpaid | C80: No | D80: 0 | E80: 0 | F80: 0 | P80: =SUM(D80:O80) -> 0
B81: Done this Month Prepaid | C81: No | D81: 0 | E81: 0 | F81: 0 | P81: =SUM(D81:O81) -> 0
B82: Total Done | C82: No | D82: =D81+D80 -> 0 | E82: =E81+E80 -> 0 | F82: =F81+F80 -> 0 | G82: =G81+G80 -> 0 | H82: =H81+H80 -> 0 | I82: =I81+I80 -> 0 | J82: =J81+J80 -> 0 | K82: =K81+K80 -> 0 | ... P82: =P81+P80 -> 0
B83: Carried Forward | C83: No | D83: =D78+D79-D82 -> 0 | E83: =E78+E79-E82 -> 0 | F83: =F78+F79-F82 -> 0 | G83: =G78+G79-G82 -> 0 | H83: =H78+H79-H82 -> 0 | I83: =I78+I79-I82 -> 0 | J83: =J78+J79-J82 -> 0 | K83: =K78+K79-K82 -> 0 | ... P83: =P78+P79-P82 -> 0
A84: New CWP | B84: Brought Forward | C84: No | D84: 0 | E84: 0 | F84: 0 | P84: =D84 -> 0
B85: Applied this Month | C85: No | D85: 0 | E85: 0 | F85: 0 | P85: =SUM(D85:O85) -> 0
B86: Done this Month Postpaid | C86: No | D86: 0 | E86: 0 | F86: 0 | P86: =SUM(D86:O86) -> 0
B87: Done this Month Prepaid | C87: No | D87: 0 | E87: 0 | F87: 0 | P87: =SUM(D87:O87) -> 0
B88: Total Done | C88: No | D88: 0 | E88: 0 | F88: 0 | G88: 0 | H88: 0 | I88: 0 | J88: 0 | K88: 0 | L88: 0 | M88: 0 | N88: 0 | O88: 0
B89: Carried Forward | C89: No | D89: =D84+D85-D88 -> 0 | E89: =E84+E85-E88 -> 0 | F89: =F84+F85-F88 -> 0 | G89: =G84+G85-G88 -> 0 | H89: =H84+H85-H88 -> 0 | I89: =I84+I85-I88 -> 0 | J89: =J84+J85-J88 -> 0 | K89: =K84+K85-K88 -> 0 | ... O89: =O84+O85-O88 -> 0 | P89: =P84+P85-P86-P87 -> 0
A90: Aggregated New Water connections | B90: Brought Forward | C90: No | D90: =D66+D72+D78+D84 -> 2 | E90: =E66+E72+E78+E84 -> 2 | F90: =F66+F72+F78+F84 -> 7 | G90: =G66+G72+G78+G84 -> 13 | H90: =H66+H72+H78+H84 -> 7 | I90: =I66+I72+I78+I84 -> 22 | J90: =J66+J72+J78+J84 -> 32 | K90: =K66+K72+K78+K84 -> 38 | ... O90: =O66+O72+O78+O84 -> 67 | P90: =D90 -> 2
B91: Applied this Month | C91: No | D91: =D67+D73+D79+D85 -> 8 | E91: =E67+E73+E79+E85 -> 11 | F91: =F67+F73+F79+F85 -> 18 | G91: =G67+G73+G79+G85 -> 25 | H91: =H67+H73+H79+H85 -> 47 | I91: =I67+I73+I79+I85 -> 14 | J91: =J67+J73+J79+J85 -> 6 | K91: =K67+K73+K79+K85 -> 0 | ... O91: =O67+O73+O79+O85 -> 3 | P91: =SUM(D91:O91) -> 165
B92: Done this Month Postpaid | C92: No | D92: =D68+D74+D80+D86 -> 0 | E92: =E68+E74+E80+E86 -> 0 | F92: =F68+F74+F80+F86 -> 0 | G92: =G68+G74+G80+G86 -> 0 | H92: =H68+H74+H80+H86 -> 0 | I92: =I68+I74+I80+I86 -> 0 | J92: =J68+J74+J80+J86 -> 0 | K92: =K68+K74+K80+K86 -> 0 | ... O92: =O68+O74+O80+O86 -> 0 | P92: =SUM(D92:O92) -> 4
B93: Done this Month Prepaid | D93: =D69+D75+D81+D87 -> 8 | E93: =E69+E75+E81+E87 -> 6 | F93: =F69+F75+F81+F87 -> 12 | G93: =G69+G75+G81+G87 -> 31 | H93: =H69+H75+H81+H87 -> 32 | I93: =I69+I75+I81+I87 -> 4 | J93: =J69+J75+J81+J87 -> 0 | K93: =K69+K75+K81+K87 -> 0 | ... O93: =O69+O75+O81+O87 -> 3 | P93: =SUM(D93:O93) -> 96
B94: Total Done | C94: No | D94: =D93+D92 -> 8 | E94: =E93+E92 -> 6 | F94: =F93+F92 -> 12 | G94: =G93+G92 -> 31 | H94: =H93+H92 -> 32 | I94: =I93+I92 -> 4 | J94: =J93+J92 -> 0 | K94: =K93+K92 -> 0 | ... P94: =P93+P92 -> 100
B95: Carried Forward | C95: No | D95: =D90+D91-D94 -> 2 | E95: =E90+E91-E94 -> 7 | F95: =F90+F91-F94 -> 13 | G95: =G90+G91-G94 -> 7 | H95: =H90+H91-H94 -> 22 | I95: =I90+I91-I94 -> 32 | J95: =J90+J91-J94 -> 38 | K95: =K90+K91-K94 -> 38 | ... P95: =P90+P91-P94 -> 67
A97: Prepaid Metering
A98: Prepaid Meters Installed | C98: No | D98: 50 | E98: 102 | F98: 40 | G98: 25 | H98: 32 | I98: 4 | J98: 0 | N98: 4 | O98: 50 | P98: =SUM(D98:O98) -> 307
A100: Active and Disconnected Accounts
A101: Disconnected Individual Accounts | C101: No | D101: 0 | F101: 4 | G101: 3 | H101: 3 | I101: 3 | J101: 5 | K101: 4 | L101: 4 | M101: 7 | N101: 9 | O101: 12 | P101: =O101 -> 12
A102: Disconnected institutional Accounts | C102: No | D102: 1 | E102: 1 | F102: 1 | G102: 1 | H102: 1 | I102: 1 | J102: 0 | K102: 0 | L102: 1 | M102: 0 | N102: 0 | O102: 0 | P102: =O102 -> 0
A103: Disconnected Commercial/Industrial Accounts | C103: No | D103: 0 | E103: 0 | F103: 0 | G103: 0 | H103: 0 | I103: 0 | J103: 1 | K103: 1 | L103: 2 | M103: 2 | N103: 2 | O103: 2 | P103: =O103 -> 2
A104: Disconnected CWP | C104: No | D104: 0 | E104: 12 | F104: 15 | G104: 15 | H104: 15 | I104: 15 | J104: 15 | K104: 15 | L104: 15 | M104: 15 | N104: 15 | O104: 15 | P104: =O104 -> 15
A105: Total Disconnected Accounts | C105: No | D105: =SUM(D101:D104) -> 1 | E105: =SUM(E101:E104) -> 13 | F105: =SUM(F101:F104) -> 20 | G105: =SUM(G101:G104) -> 19 | H105: =SUM(H101:H104) -> 19 | I105: =SUM(I101:I104) -> 19 | J105: =SUM(J101:J104) -> 21 | K105: =SUM(K101:K104) -> 20 | ... O105: =SUM(O101:O104) -> 29 | P105: =O105 -> 29
A106: Postpaid Consumers
...

Sheet Zone Monthly
A1: SOUTHERN REGION WATER BOARD
A3: MONTHLY REPORTS - 2023/2024
A4: LIWONDE ZONE
A5: LIWONDE ZONE
A7: PARAMETERS | C7: UNITS | D7: APRIL | E7: MAY | F7: JUNE | G7: JULY | H7: AUGUST | I7: SEPTEMBER | J7: OCTOBER | K7: NOVEMBER | L7: DECEMBER | M7: JANUARY | N7: FEBRUARY | O7: MARCH | P7: TOTALS
A8: PRODUCTION
A9: Volume Produced | C9: m3 | D9: =Balaka!D9+Liwonde!D9+Machinga!D9+Ntaja!D9 -> 119276 | E9: =Balaka!E9+Liwonde!E9+Machinga!E9+Ntaja!E9 -> 128028 | F9: =Balaka!F9+Liwonde!F9+Machinga!F9+Ntaja!F9 -> 127635.01 | G9: =Balaka!G9+Liwonde!G9+Machinga!G9+Ntaja!G9 -> 128891 | H9: =Balaka!H9+Liwonde!H9+Machinga!H9+Ntaja!H9 -> 131829 | I9: =Balaka!I9+Liwonde!I9+Machinga!I9+Ntaja!I9 -> 144936 | J9: =Balaka!J9+Liwonde!J9+Machinga!J9+Ntaja!J9 -> 152008 | K9: =Balaka!K9+Liwonde!K9+Machinga!K9+Ntaja!K9 -> 150030 | ... O9: =Balaka!O9+Liwonde!O9+Machinga!O9+Ntaja!O9 -> 111636 | P9: =SUM(D9:O9) -> 1618116.7
A10: REVENUE WATER - POSTPAID
A11: Volume Billed Individuals | C11: m3 | D11: =Balaka!D11+Liwonde!D11+Machinga!D11+Ntaja!D11 -> 46978 | E11: =Balaka!E11+Liwonde!E11+Machinga!E11+Ntaja!E11 -> 51964 | F11: =Balaka!F11+Liwonde!F11+Machinga!F11+Ntaja!F11 -> 51768 | G11: =Balaka!G11+Liwonde!G11+Machinga!G11+Ntaja!G11 -> 51183 | H11: =Balaka!H11+Liwonde!H11+Machinga!H11+Ntaja!H11 -> 55307 | I11: =Balaka!I11+Liwonde!I11+Machinga!I11+Ntaja!I11 -> 60037 | J11: =Balaka!J11+Liwonde!J11+Machinga!J11+Ntaja!J11 -> 64542 | K11: =Balaka!K11+Liwonde!K11+Machinga!K11+Ntaja!K11 -> 67713 | ... O11: =Balaka!O11+Liwonde!O11+Machinga!O11+Ntaja!O11 -> 58215 | P11: =SUM(D11:O11) -> 711496
A12: Volume Billed CWPs | C12: m3 | D12: =Balaka!D12+Liwonde!D12+Machinga!D12+Ntaja!D12 -> 1322 | E12: =Balaka!E12+Liwonde!E12+Machinga!E12+Ntaja!E12 -> 1438 | F12: =Balaka!F12+Liwonde!F12+Machinga!F12+Ntaja!F12 -> 868 | G12: =Balaka!G12+Liwonde!G12+Machinga!G12+Ntaja!G12 -> 1477 | H12: =Balaka!H12+Liwonde!H12+Machinga!H12+Ntaja!H12 -> 1776 | I12: =Balaka!I12+Liwonde!I12+Machinga!I12+Ntaja!I12 -> 1726 | J12: =Balaka!J12+Liwonde!J12+Machinga!J12+Ntaja!J12 -> 1904 | K12: =Balaka!K12+Liwonde!K12+Machinga!K12+Ntaja!K12 -> 1695 | ... O12: =Balaka!O12+Liwonde!O12+Machinga!O12+Ntaja!O12 -> 1322 | P12: =SUM(D12:O12) -> 18448
A13: Volume Billed Institutions | C13: m3 | D13: =Balaka!D13+Liwonde!D13+Machinga!D13+Ntaja!D13 -> 2585 | E13: =Balaka!E13+Liwonde!E13+Machinga!E13+Ntaja!E13 -> 4117 | F13: =Balaka!F13+Liwonde!F13+Machinga!F13+Ntaja!F13 -> 4957 | G13: =Balaka!G13+Liwonde!G13+Machinga!G13+Ntaja!G13 -> 2624 | H13: =Balaka!H13+Liwonde!H13+Machinga!H13+Ntaja!H13 -> 2653 | I13: =Balaka!I13+Liwonde!I13+Machinga!I13+Ntaja!I13 -> 2803 | J13: =Balaka!J13+Liwonde!J13+Machinga!J13+Ntaja!J13 -> 2879 | K13: =Balaka!K13+Liwonde!K13+Machinga!K13+Ntaja!K13 -> 2877 | ... O13: =Balaka!O13+Liwonde!O13+Machinga!O13+Ntaja!O13 -> 1062 | P13: =SUM(D13:O13) -> 31982
A14: Volume Billed Commercial/Industrial | C14: m3 | D14: =Balaka!D14+Liwonde!D14+Machinga!D14+Ntaja!D14 -> 177 | E14: =Balaka!E14+Liwonde!E14+Machinga!E14+Ntaja!E14 -> 199 | F14: =Balaka!F14+Liwonde!F14+Machinga!F14+Ntaja!F14 -> 300 | G14: =Balaka!G14+Liwonde!G14+Machinga!G14+Ntaja!G14 -> 232 | H14: =Balaka!H14+Liwonde!H14+Machinga!H14+Ntaja!H14 -> 366 | I14: =Balaka!I14+Liwonde!I14+Machinga!I14+Ntaja!I14 -> 372 | J14: =Balaka!J14+Liwonde!J14+Machinga!J14+Ntaja!J14 -> 327 | K14: =Balaka!K14+Liwonde!K14+Machinga!K14+Ntaja!K14 -> 277 | ... O14: =Balaka!O14+Liwonde!O14+Machinga!O14+Ntaja!O14 -> 645 | P14: =SUM(D14:O14) -> 4147
A15: Total Volume Billed Post Paid | C15: m3 | D15: =SUM(D11:D14) -> 51062 | E15: =SUM(E11:E14) -> 57718 | F15: =SUM(F11:F14) -> 57893 | G15: =SUM(G11:G14) -> 55516 | H15: =SUM(H11:H14) -> 60102 | I15: =SUM(I11:I14) -> 64938 | J15: =SUM(J11:J14) -> 69652 | K15: =SUM(K11:K14) -> 72562 | ... P15: =SUM(P11:P14) -> 766073
A16: REVENUE WATER - PREPAID
A17: Individuals | C17: m3 | D17: =Balaka!D17+Liwonde!D17+Machinga!D17+Ntaja!D17 -> 18273 | E17: =Balaka!E17+Liwonde!E17+Machinga!E17+Ntaja!E17 -> 20613 | F17: =Balaka!F17+Liwonde!F17+Machinga!F17+Ntaja!F17 -> 19368.4 | G17: =Balaka!G17+Liwonde!G17+Machinga!G17+Ntaja!G17 -> 19659.8 | H17: =Balaka!H17+Liwonde!H17+Machinga!H17+Ntaja!H17 -> 20835 | I17: =Balaka!I17+Liwonde!I17+Machinga!I17+Ntaja!I17 -> 19714.9 | J17: =Balaka!J17+Liwonde!J17+Machinga!J17+Ntaja!J17 -> 23565 | K17: =Balaka!K17+Liwonde!K17+Machinga!K17+Ntaja!K17 -> 20221.7 | ... O17: =Balaka!O17+Liwonde!O17+Machinga!O17+Ntaja!O17 -> 18940.3 | P17: =SUM(D17:O17) -> 247935.58
A18: CWPs | C18: m3 | D18: =Balaka!D18+Liwonde!D18+Machinga!D18+Ntaja!D18 -> 21 | E18: =Balaka!E18+Liwonde!E18+Machinga!E18+Ntaja!E18 -> 11 | F18: =Balaka!F18+Liwonde!F18+Machinga!F18+Ntaja!F18 -> 60 | G18: =Balaka!G18+Liwonde!G18+Machinga!G18+Ntaja!G18 -> 75 | H18: =Balaka!H18+Liwonde!H18+Machinga!H18+Ntaja!H18 -> 71 | I18: =Balaka!I18+Liwonde!I18+Machinga!I18+Ntaja!I18 -> 86 | J18: =Balaka!J18+Liwonde!J18+Machinga!J18+Ntaja!J18 -> 131 | K18: =Balaka!K18+Liwonde!K18+Machinga!K18+Ntaja!K18 -> 148 | ... O18: =Balaka!O18+Liwonde!O18+Machinga!O18+Ntaja!O18 -> 141 | P18: =SUM(D18:O18) -> 1084
A19: Institutions | C19: m3 | D19: =Balaka!D19+Liwonde!D19+Machinga!D19+Ntaja!D19 -> 23 | E19: =Balaka!E19+Liwonde!E19+Machinga!E19+Ntaja!E19 -> 30 | F19: =Balaka!F19+Liwonde!F19+Machinga!F19+Ntaja!F19 -> 75 | G19: =Balaka!G19+Liwonde!G19+Machinga!G19+Ntaja!G19 -> 61 | H19: =Balaka!H19+Liwonde!H19+Machinga!H19+Ntaja!H19 -> 52 | I19: =Balaka!I19+Liwonde!I19+Machinga!I19+Ntaja!I19 -> 1471 | J19: =Balaka!J19+Liwonde!J19+Machinga!J19+Ntaja!J19 -> 1550 | K19: =Balaka!K19+Liwonde!K19+Machinga!K19+Ntaja!K19 -> 1482 | ... O19: =Balaka!O19+Liwonde!O19+Machinga!O19+Ntaja!O19 -> 437 | P19: =SUM(D19:O19) -> 10349
A20: Commercial/Industrial | C20: m3 | D20: =Balaka!D20+Liwonde!D20+Machinga!D20+Ntaja!D20 -> 52 | E20: =Balaka!E20+Liwonde!E20+Machinga!E20+Ntaja!E20 -> 28 | F20: =Balaka!F20+Liwonde!F20+Machinga!F20+Ntaja!F20 -> 83 | G20: =Balaka!G20+Liwonde!G20+Machinga!G20+Ntaja!G20 -> 86 | H20: =Balaka!H20+Liwonde!H20+Machinga!H20+Ntaja!H20 -> 81 | I20: =Balaka!I20+Liwonde!I20+Machinga!I20+Ntaja!I20 -> 671 | J20: =Balaka!J20+Liwonde!J20+Machinga!J20+Ntaja!J20 -> 661 | K20: =Balaka!K20+Liwonde!K20+Machinga!K20+Ntaja!K20 -> 705 | ... O20: =Balaka!O20+Liwonde!O20+Machinga!O20+Ntaja!O20 -> 503 | P20: =SUM(D20:O20) -> 5081
A21: Total Volume Prepaid | C21: m3 | D21: =SUM(D17:D20) -> 18369 | E21: =SUM(E17:E20) -> 20682 | F21: =SUM(F17:F20) -> 19586.4 | G21: =SUM(G17:G20) -> 19881.8 | H21: =SUM(H17:H20) -> 21039 | I21: =SUM(I17:I20) -> 21942.9 | J21: =SUM(J17:J20) -> 25907 | K21: =SUM(K17:K20) -> 22556.7 | ... P21: =SUM(P17:P20) -> 264449.58
A22: TOTAL REVENUE WATER | C22: m3 | D22: =D21+D15 -> 69431 | E22: =E21+E15 -> 78400 | F22: =F21+F15 -> 77479.4 | G22: =G21+G15 -> 75397.8 | H22: =H21+H15 -> 81141 | I22: =I21+I15 -> 86880.9 | J22: =J21+J15 -> 95559 | K22: =K21+K15 -> 95118.7 | ... P22: =P21+P15 -> 1030522.6
A24: Non-Revenue Water (NRW) | B24: Volume | C24: m3 | D24: =Balaka!D24+Liwonde!D24+Machinga!D24+Ntaja!D24 -> 49845 | E24: =Balaka!E24+Liwonde!E24+Machinga!E24+Ntaja!E24 -> 49628 | F24: =Balaka!F24+Liwonde!F24+Machinga!F24+Ntaja!F24 -> 50155.61 | G24: =Balaka!G24+Liwonde!G24+Machinga!G24+Ntaja!G24 -> 53493.2 | H24: =Balaka!H24+Liwonde!H24+Machinga!H24+Ntaja!H24 -> 50688 | I24: =Balaka!I24+Liwonde!I24+Machinga!I24+Ntaja!I24 -> 58055.1 | J24: =Balaka!J24+Liwonde!J24+Machinga!J24+Ntaja!J24 -> 56449 | K24: =Balaka!K24+Liwonde!K24+Machinga!K24+Ntaja!K24 -> 54911.3 | ... O24: =Balaka!O24+Liwonde!O24+Machinga!O24+Ntaja!O24 -> 30370.7 | P24: =P9-P22 -> 587594.13
B25: Percentage | C25: % | D25: =D24/D9 -> 0.41789631 | E25: =E24/E9 -> 0.38763396 | F25: =F24/F9 -> 0.39296123 | G25: =G24/G9 -> 0.41502665 | H25: =H24/H9 -> 0.3844981 | I25: =I24/I9 -> 0.4005568 | J25: =J24/J9 -> 0.37135545 | K25: =K24/K9 -> 0.36600213 | ... P25: =P24/P9 -> 0.36313458
A26: OPERATING EXPENSES
A27: Chemicals
A28: Chemical | B28: Rate(MK/kg)
A29: Chlorine | B29: =176264.5/50 -> 3525.29 | C29: kg | D29: =Balaka!D29+Liwonde!D29+Machinga!D29+Ntaja!D29 -> 451 | E29: =Balaka!E29+Liwonde!E29+Machinga!E29+Ntaja!E29 -> 619 | F29: =Balaka!F29+Liwonde!F29+Machinga!F29+Ntaja!F29 -> 373 | G29: =Balaka!G29+Liwonde!G29+Machinga!G29+Ntaja!G29 -> 397 | H29: =Balaka!H29+Liwonde!H29+Machinga!H29+Ntaja!H29 -> 341 | I29: =Balaka!I29+Liwonde!I29+Machinga!I29+Ntaja!I29 -> 469 | J29: =Balaka!J29+Liwonde!J29+Machinga!J29+Ntaja!J29 -> 602 | K29: =Balaka!K29+Liwonde!K29+Machinga!K29+Ntaja!K29 -> 517 | ... O29: =Balaka!O29+Liwonde!O29+Machinga!O29+Ntaja!O29 -> 470 | P29: =SUM(D29:O29) -> 5754
C30: kg/mg litre | D30: =D29/(D9/1000) -> 3.7811462 | E30: =E29/(E9/1000) -> 4.8348799 | F30: =F29/(F9/1000) -> 2.9223957 | G30: =G29/(G9/1000) -> 3.080122 | H30: =H29/(H9/1000) -> 2.5866843 | I30: =I29/(I9/1000) -> 3.235911 | J30: =J29/(J9/1000) -> 3.9603179 | K30: =K29/(K9/1000) -> 3.4459775 | ... P30: =P29/(P9/1000) -> 3.5559858
A31: Aluminium sulphate | B31: =53000.511/50 -> 1060.0102 | C31: kg | D31: =Balaka!D31+Liwonde!D31+Machinga!D31+Ntaja!D31 -> 0 | E31: =Balaka!E31+Liwonde!E31+Machinga!E31+Ntaja!E31 -> 0 | F31: =Balaka!F31+Liwonde!F31+Machinga!F31+Ntaja!F31 -> 0 | G31: =Balaka!G31+Liwonde!G31+Machinga!G31+Ntaja!G31 -> 0 | H31: =Balaka!H31+Liwonde!H31+Machinga!H31+Ntaja!H31 -> 0 | I31: =Balaka!I31+Liwonde!I31+Machinga!I31+Ntaja!I31 -> 0 | J31: =Balaka!J31+Liwonde!J31+Machinga!J31+Ntaja!J31 -> 0 | K31: =Balaka!K31+Liwonde!K31+Machinga!K31+Ntaja!K31 -> 0 | ... O31: =Balaka!O31+Liwonde!O31+Machinga!O31+Ntaja!O31 -> 0 | P31: =SUM(D31:O31) -> 0
C32: kg/mg litre | D32: =D31/(D9/1000) -> 0 | E32: =E31/(E9/1000) -> 0 | F32: =F31/(F9/1000) -> 0 | G32: =G31/(G9/1000) -> 0 | H32: =H31/(H9/1000) -> 0 | I32: =I31/(I9/1000) -> 0 | J32: =J31/(J9/1000) -> 0 | K32: =K31/(K9/1000) -> 0 | ... P32: =P31/(P9/1000) -> 0
A33: Soda | B33: =61414.43/50 -> 1228.2886 | C33: kg | D33: =Balaka!D33+Liwonde!D33+Machinga!D33+Ntaja!D33 -> 0 | E33: =Balaka!E33+Liwonde!E33+Machinga!E33+Ntaja!E33 -> 0 | F33: =Balaka!F33+Liwonde!F33+Machinga!F33+Ntaja!F33 -> 0 | G33: =Balaka!G33+Liwonde!G33+Machinga!G33+Ntaja!G33 -> 0 | H33: =Balaka!H33+Liwonde!H33+Machinga!H33+Ntaja!H33 -> 0 | I33: =Balaka!I33+Liwonde!I33+Machinga!I33+Ntaja!I33 -> 0 | J33: =Balaka!J33+Liwonde!J33+Machinga!J33+Ntaja!J33 -> 0 | K33: =Balaka!K33+Liwonde!K33+Machinga!K33+Ntaja!K33 -> 0 | ... O33: =Balaka!O33+Liwonde!O33+Machinga!O33+Ntaja!O33 -> 0 | P33: =SUM(D33:O33) -> 0
C34: kg/mg litre | D34: =D33/(D9/1000) -> 0 | E34: =E33/(E9/1000) -> 0 | F34: =F33/(F9/1000) -> 0 | G34: =G33/(G9/1000) -> 0 | H34: =H33/(H9/1000) -> 0 | I34: =I33/(I9/1000) -> 0 | J34: =J33/(J9/1000) -> 0 | K34: =K33/(K9/1000) -> 0 | ... P34: =P33/(P9/1000) -> 0
A35: Algae floc | B35: =745345.16/200 -> 3726.7258 | C35: litres | D35: =Balaka!D35+Liwonde!D35+Machinga!D35+Ntaja!D35 -> 0 | E35: =Balaka!E35+Liwonde!E35+Machinga!E35+Ntaja!E35 -> 248 | F35: =Balaka!F35+Liwonde!F35+Machinga!F35+Ntaja!F35 -> 301 | G35: =Balaka!G35+Liwonde!G35+Machinga!G35+Ntaja!G35 -> 224 | H35: =Balaka!H35+Liwonde!H35+Machinga!H35+Ntaja!H35 -> 139 | I35: =Balaka!I35+Liwonde!I35+Machinga!I35+Ntaja!I35 -> 155 | J35: =Balaka!J35+Liwonde!J35+Machinga!J35+Ntaja!J35 -> 143 | K35: =Balaka!K35+Liwonde!K35+Machinga!K35+Ntaja!K35 -> 110 | ... O35: =Balaka!O35+Liwonde!O35+Machinga!O35+Ntaja!O35 -> 465
C36: litres/mg litre
A37: Sud floc | B37: =790318.72/200 -> 3951.5936 | C37: litres | D37: =Balaka!D37+Liwonde!D37+Machinga!D37+Ntaja!D37 -> 0 | E37: =Balaka!E37+Liwonde!E37+Machinga!E37+Ntaja!E37 -> 0 | F37: =Balaka!F37+Liwonde!F37+Machinga!F37+Ntaja!F37 -> 0 | G37: =Balaka!G37+Liwonde!G37+Machinga!G37+Ntaja!G37 -> 0 | H37: =Balaka!H37+Liwonde!H37+Machinga!H37+Ntaja!H37 -> 0 | I37: =Balaka!I37+Liwonde!I37+Machinga!I37+Ntaja!I37 -> 0 | J37: =Balaka!J37+Liwonde!J37+Machinga!J37+Ntaja!J37 -> 0 | K37: =Balaka!K37+Liwonde!K37+Machinga!K37+Ntaja!K37 -> 0 | ... O37: =Balaka!O37+Liwonde!O37+Machinga!O37+Ntaja!O37 -> 0 | P37: =SUM(D37:O37) -> 0
C38: litres/mg litre | D38: =D37/(D9/1000) -> 0 | E38: =E37/(E9/1000) -> 0 | F38: =F37/(F9/1000) -> 0 | G38: =G37/(G9/1000) -> 0 | H38: =H37/(H9/1000) -> 0 | I38: =I37/(I9/1000) -> 0 | J38: =J37/(J9/1000) -> 0 | K38: =K37/(K9/1000) -> 0 | ... P38: =P37/(P9/1000) -> 0
A39: Potasium permanganate | B39: 1950 | C39: kg | D39: =Balaka!D39+Liwonde!D39+Machinga!D39+Ntaja!D39 -> 0 | E39: =Balaka!E39+Liwonde!E39+Machinga!E39+Ntaja!E39 -> 0 | F39: =Balaka!F39+Liwonde!F39+Machinga!F39+Ntaja!F39 -> 0 | G39: =Balaka!G39+Liwonde!G39+Machinga!G39+Ntaja!G39 -> 0 | H39: =Balaka!H39+Liwonde!H39+Machinga!H39+Ntaja!H39 -> 0 | I39: =Balaka!I39+Liwonde!I39+Machinga!I39+Ntaja!I39 -> 0 | J39: =Balaka!J39+Liwonde!J39+Machinga!J39+Ntaja!J39 -> 0 | K39: =Balaka!K39+Liwonde!K39+Machinga!K39+Ntaja!K39 -> 0 | ... O39: =Balaka!O39+Liwonde!O39+Machinga!O39+Ntaja!O39 -> 0 | P39: =SUM(D39:O39) -> 0
C40: kg/mg litre | D40: =D39/(D9/1000) -> 0 | E40: =E39/(E9/1000) -> 0 | F40: =F39/(F9/1000) -> 0 | G40: =G39/(G9/1000) -> 0 | H40: =H39/(H9/1000) -> 0 | I40: =I39/(I9/1000) -> 0 | J40: =J39/(J9/1000) -> 0 | K40: =K39/(K9/1000) -> 0 | ... P40: =P39/(P9/1000) -> 0
A41: Cost of Chemicals | C41: Mk | D41: =(D29*$B29)+(D31*$B31)+(D33*$B33)+(D35*$B35)+(D37*$B37)+(D39*$B39) -> 1589905.8 | E41: =(E29*$B29)+(E31*$B31)+(E33*$B33)+(E35*$B35)+(E37*$B37)+(E39*$B39) -> 3106382.5 | F41: =(F29*$B29)+(F31*$B31)+(F33*$B33)+(F35*$B35)+(F37*$B37)+(F39*$B39) -> 2436677.6 | G41: =(G29*$B29)+(G31*$B31)+(G33*$B33)+(G35*$B35)+(G37*$B37)+(G39*$B39) -> 2234326.7 | H41: =(H29*$B29)+(H31*$B31)+(H33*$B33)+(H35*$B35)+(H37*$B37)+(H39*$B39) -> 1720138.8 | I41: =(I29*$B29)+(I31*$B31)+(I33*$B33)+(I35*$B35)+(I37*$B37)+(I39*$B39) -> 2231003.5 | J41: =(J29*$B29)+(J31*$B31)+(J33*$B33)+(J35*$B35)+(J37*$B37)+(J39*$B39) -> 2655146.4 | K41: =(K29*$B29)+(K31*$B31)+(K33*$B33)+(K35*$B35)+(K37*$B37)+(K39*$B39) -> 2232514.8 | ... O41: =(O29*$B29)+(O31*$B31)+(O33*$B33)+(O35*$B35)+(O37*$B37)+(O39*$B39) -> 3389813.8 | P41: =SUM(D41:O41) -> 31293267
A42: Cost/vol. Produced (chemicals) | C42: Mk/m3 | D42: =D41/D9 -> 13.329637 | E42: =E41/E9 -> 24.263306 | F42: =F41/F9 -> 19.090982 | G42: =G41/G9 -> 17.335009 | H42: =H41/H9 -> 13.048258 | I42: =I41/I9 -> 15.393025 | J42: =J41/J9 -> 17.467149 | K42: =K41/K9 -> 14.880456 | ... P42: =P41/P9 -> 19.339314
A43: Power
A44: Power Usage | C44: Kw | D44: =Balaka!D44+Liwonde!D44+Machinga!D44+Ntaja!D44 -> 94959.34 | E44: =Balaka!E44+Liwonde!E44+Machinga!E44+Ntaja!E44 -> 122031 | F44: =Balaka!F44+Liwonde!F44+Machinga!F44+Ntaja!F44 -> 119089.35 | G44: =Balaka!G44+Liwonde!G44+Machinga!G44+Ntaja!G44 -> 119114.36 | H44: =Balaka!H44+Liwonde!H44+Machinga!H44+Ntaja!H44 -> 109106.46 | I44: =Balaka!I44+Liwonde!I44+Machinga!I44+Ntaja!I44 -> 125227.09 | J44: =Balaka!J44+Liwonde!J44+Machinga!J44+Ntaja!J44 -> 119940.54 | K44: =Balaka!K44+Liwonde!K44+Machinga!K44+Ntaja!K44 -> 89217.8 | ... O44: =Balaka!O44+Liwonde!O44+Machinga!O44+Ntaja!O44 -> 114672.77 | P44: =SUM(D44:O44) -> 1333256.1
A45: Power/ Vol. Produced | C45: Kw/m3 | D45: =D44/D9 -> 0.79613116 | E45: =E44/E9 -> 0.95315868 | F45: =F44/F9 -> 0.93304611 | G45: =G44/G9 -> 0.924148 | H45: =H44/H9 -> 0.82763626 | I45: =I44/I9 -> 0.86401646 | J45: =J44/J9 -> 0.78904097 | K45: =K44/K9 -> 0.5946664 | ... P45: =P44/P9 -> 0.82395544
A46: Cost of Power | C46: Mk | D46: =Balaka!D46+Liwonde!D46+Machinga!D46+Ntaja!D46 -> 13241457 | E46: =Balaka!E46+Liwonde!E46+Machinga!E46+Ntaja!E46 -> 16997690 | F46: =Balaka!F46+Liwonde!F46+Machinga!F46+Ntaja!F46 -> 16589532 | G46: =Balaka!G46+Liwonde!G46+Machinga!G46+Ntaja!G46 -> 16593002 | H46: =Balaka!H46+Liwonde!H46+Machinga!H46+Ntaja!H46 -> 18317501 | I46: =Balaka!I46+Liwonde!I46+Machinga!I46+Ntaja!I46 -> 21012508 | J46: =Balaka!J46+Liwonde!J46+Machinga!J46+Ntaja!J46 -> 20128716 | K46: =Balaka!K46+Liwonde!K46+Machinga!K46+Ntaja!K46 -> 14992565 | ... O46: =Balaka!O46+Liwonde!O46+Machinga!O46+Ntaja!O46 -> 17613873 | P46: =SUM(D46:O46) -> 2.1291777e+08
A47: Cost/vol. Produced | C47: Mk/m3 | D47: =D46/D9 -> 111.01527 | E47: =E46/E9 -> 132.76541 | F47: =F46/F9 -> 129.97634 | G47: =G46/G9 -> 128.7367 | H47: =H46/H9 -> 138.94895 | I47: =I46/I9 -> 144.97784 | J47: =J46/J9 -> 132.41879 | K47: =K46/K9 -> 99.930446 | ... P47: =P46/P9 -> 131.58369
A48: Plant and Vehicle Maintenance
A49: Distances covered | C49: km | D49: =Balaka!D49+Liwonde!D49+Machinga!D49+Ntaja!D49 -> 3854 | E49: =Balaka!E49+Liwonde!E49+Machinga!E49+Ntaja!E49 -> 4463 | F49: =Balaka!F49+Liwonde!F49+Machinga!F49+Ntaja!F49 -> 5796 | G49: =Balaka!G49+Liwonde!G49+Machinga!G49+Ntaja!G49 -> 5895 | H49: =Balaka!H49+Liwonde!H49+Machinga!H49+Ntaja!H49 -> 5096 | I49: =Balaka!I49+Liwonde!I49+Machinga!I49+Ntaja!I49 -> 5467 | J49: =Balaka!J49+Liwonde!J49+Machinga!J49+Ntaja!J49 -> 3804 | K49: =Balaka!K49+Liwonde!K49+Machinga!K49+Ntaja!K49 -> 4088 | ... O49: =Balaka!O49+Liwonde!O49+Machinga!O49+Ntaja!O49 -> 3257 | P49: =SUM(D49:O49) -> 49031
A50: Fuel Used (litres) | C50: litres | D50: =Balaka!D50+Liwonde!D50+Machinga!D50+Ntaja!D50 -> 430 | E50: =Balaka!E50+Liwonde!E50+Machinga!E50+Ntaja!E50 -> 487 | F50: =Balaka!F50+Liwonde!F50+Machinga!F50+Ntaja!F50 -> 459 | G50: =Balaka!G50+Liwonde!G50+Machinga!G50+Ntaja!G50 -> 471 | H50: =Balaka!H50+Liwonde!H50+Machinga!H50+Ntaja!H50 -> 513.86 | I50: =Balaka!I50+Liwonde!I50+Machinga!I50+Ntaja!I50 -> 530 | J50: =Balaka!J50+Liwonde!J50+Machinga!J50+Ntaja!J50 -> 466.7 | K50: =Balaka!K50+Liwonde!K50+Machinga!K50+Ntaja!K50 -> 561 | ... O50: =Balaka!O50+Liwonde!O50+Machinga!O50+Ntaja!O50 -> 331 | P50: =SUM(D50:O50) -> 5023.18
A51: Cost of fuel | C51: Mk | D51: =Balaka!D51+Liwonde!D51+Machinga!D51+Ntaja!D51 -> 801040 | E51: =Balaka!E51+Liwonde!E51+Machinga!E51+Ntaja!E51 -> 900240 | F51: =Balaka!F51+Liwonde!F51+Machinga!F51+Ntaja!F51 -> 883080 | G51: =Balaka!G51+Liwonde!G51+Machinga!G51+Ntaja!G51 -> 1140570 | H51: =Balaka!H51+Liwonde!H51+Machinga!H51+Ntaja!H51 -> 930811.2 | I51: =Balaka!I51+Liwonde!I51+Machinga!I51+Ntaja!I51 -> 1014990 | J51: =Balaka!J51+Liwonde!J51+Machinga!J51+Ntaja!J51 -> 896064 | K51: =Balaka!K51+Liwonde!K51+Machinga!K51+Ntaja!K51 -> 1528381.7 | ... O51: =Balaka!O51+Liwonde!O51+Machinga!O51+Ntaja!O51 -> 627840 | P51: =SUM(D51:O51) -> 13183697
A52: Maintenance | C52: Mk | D52: =Balaka!D52+Liwonde!D52+Machinga!D52+Ntaja!D52 -> 0 | E52: =Balaka!E52+Liwonde!E52+Machinga!E52+Ntaja!E52 -> 0 | F52: =Balaka!F52+Liwonde!F52+Machinga!F52+Ntaja!F52 -> 0 | G52: =Balaka!G52+Liwonde!G52+Machinga!G52+Ntaja!G52 -> 0 | H52: =Balaka!H52+Liwonde!H52+Machinga!H52+Ntaja!H52 -> 0 | I52: =Balaka!I52+Liwonde!I52+Machinga!I52+Ntaja!I52 -> 0 | J52: =Balaka!J52+Liwonde!J52+Machinga!J52+Ntaja!J52 -> 0 | K52: =Balaka!K52+Liwonde!K52+Machinga!K52+Ntaja!K52 -> 0 | ... O52: =Balaka!O52+Liwonde!O52+Machinga!O52+Ntaja!O52 -> 0 | P52: =SUM(D52:O52) -> 0
A53: Salaries and Wages
A54: Staff Costs | C54: MK | D54: =Balaka!D54+Liwonde!D54+Machinga!D54+Ntaja!D54 -> 16032232 | E54: =Balaka!E54+Liwonde!E54+Machinga!E54+Ntaja!E54 -> 18505482 | F54: =Balaka!F54+Liwonde!F54+Machinga!F54+Ntaja!F54 -> 17189940 | G54: =Balaka!G54+Liwonde!G54+Machinga!G54+Ntaja!G54 -> 17189940 | H54: =Balaka!H54+Liwonde!H54+Machinga!H54+Ntaja!H54 -> 18116747 | I54: =Balaka!I54+Liwonde!I54+Machinga!I54+Ntaja!I54 -> 17243469 | J54: =Balaka!J54+Liwonde!J54+Machinga!J54+Ntaja!J54 -> 17686098 | K54: =Balaka!K54+Liwonde!K54+Machinga!K54+Ntaja!K54 -> 17606098 | ... O54: =Balaka!O54+Liwonde!O54+Machinga!O54+Ntaja!O54 -> 29587499 | P54: =SUM(D54:O54) -> 2.3161037e+08
A55: Wages | C55: MK | D55: =Balaka!D55+Liwonde!D55+Machinga!D55+Ntaja!D55 -> 5864555.4 | E55: =Balaka!E55+Liwonde!E55+Machinga!E55+Ntaja!E55 -> 7804850.9 | F55: =Balaka!F55+Liwonde!F55+Machinga!F55+Ntaja!F55 -> 6425793.5 | G55: =Balaka!G55+Liwonde!G55+Machinga!G55+Ntaja!G55 -> 6492668 | H55: =Balaka!H55+Liwonde!H55+Machinga!H55+Ntaja!H55 -> 3213177.5 | I55: =Balaka!I55+Liwonde!I55+Machinga!I55+Ntaja!I55 -> 5664867.5 | J55: =Balaka!J55+Liwonde!J55+Machinga!J55+Ntaja!J55 -> 7125232.4 | K55: =Balaka!K55+Liwonde!K55+Machinga!K55+Ntaja!K55 -> 8460010.2 | ... O55: =Balaka!O55+Liwonde!O55+Machinga!O55+Ntaja!O55 -> 7546780.5 | P55: =SUM(D55:O55) -> 78120485
A56: Other Overhead Costs | C56: MK | D56: =Balaka!D56+Liwonde!D56+Machinga!D56+Ntaja!D56 -> 1995237 | E56: =Balaka!E56+Liwonde!E56+Machinga!E56+Ntaja!E56 -> 3653122 | F56: =Balaka!F56+Liwonde!F56+Machinga!F56+Ntaja!F56 -> 5487380 | G56: =Balaka!G56+Liwonde!G56+Machinga!G56+Ntaja!G56 -> 5487380 | H56: =Balaka!H56+Liwonde!H56+Machinga!H56+Ntaja!H56 -> 7378845 | I56: =Balaka!I56+Liwonde!I56+Machinga!I56+Ntaja!I56 -> 18332833 | J56: =Balaka!J56+Liwonde!J56+Machinga!J56+Ntaja!J56 -> 2413264.1 | K56: =Balaka!K56+Liwonde!K56+Machinga!K56+Ntaja!K56 -> 11773220 | ... O56: =Balaka!O56+Liwonde!O56+Machinga!O56+Ntaja!O56 -> 20658723 | P56: =SUM(D56:O56) -> 1.1780568e+08
A57: Operating Costs
A58: Total Operating Costs | C58: MK | D58: =D41+D46+D51+D52+D54+D55+D56 -> 39524427 | E58: =E41+E46+E51+E52+E54+E55+E56 -> 50967767 | F58: =F41+F46+F51+F52+F54+F55+F56 -> 49012404 | G58: =G41+G46+G51+G52+G54+G55+G56 -> 49137887 | H58: =H41+H46+H51+H52+H54+H55+H56 -> 49677221 | I58: =I41+I46+I51+I52+I54+I55+I56 -> 65499670 | J58: =J41+J46+J51+J52+J54+J55+J56 -> 50904521 | K58: =K41+K46+K51+K52+K54+K55+K56 -> 56592789 | ... O58: =O41+O46+O51+O52+O54+O55+O56 -> 79424528 | P58: =SUM(D58:O58) -> 6.8493127e+08
A59: Cost/Vol. Produced | C59: Mk/m3 | D59: =D58/D9 -> 331.36949 | E59: =E58/E9 -> 398.0986 | F59: =F58/F9 -> 384.00439 | G59: =G58/G9 -> 381.23598 | H59: =H58/H9 -> 376.83075 | I59: =I58/I9 -> 451.92133 | J59: =J58/J9 -> 334.88054 | K59: =K58/K9 -> 377.20982 | ... P59: =P58/P9 -> 423.28917
A60: Cost/Vol. Billed | C60: Mk/m3 | D60: =D58/D22 -> 569.26196 | E60: =E58/E22 -> 650.09907 | F60: =F58/F22 -> 632.58626 | G60: =G58/G22 -> 651.71513 | H60: =H58/H22 -> 612.23328 | I60: =I58/I22 -> 753.90184 | J60: =J58/J22 -> 532.70252 | K60: =K58/K22 -> 594.97017 | ... P60: =P58/P22 -> 664.6446
A61: Permanent Staff Employed | C61: No | D61: =Balaka!D61+Liwonde!D61+Machinga!D61+Ntaja!D61 -> 39 | E61: =Balaka!E61+Liwonde!E61+Machinga!E61+Ntaja!E61 -> 36 | F61: =Balaka!F61+Liwonde!F61+Machinga!F61+Ntaja!F61 -> 37 | G61: =Balaka!G61+Liwonde!G61+Machinga!G61+Ntaja!G61 -> 37 | H61: =Balaka!H61+Liwonde!H61+Machinga!H61+Ntaja!H61 -> 37 | I61: =Balaka!I61+Liwonde!I61+Machinga!I61+Ntaja!I61 -> 37 | J61: =Balaka!J61+Liwonde!J61+Machinga!J61+Ntaja!J61 -> 37 | K61: =Balaka!K61+Liwonde!K61+Machinga!K61+Ntaja!K61 -> 36 | ... O61: =Balaka!O61+Liwonde!O61+Machinga!O61+Ntaja!O61 -> 39 | P61: =O61 -> 39
A62: Staff/Vol.1000m3 of Volume Produced/hour (12 hour day) | C62: No/1000m3 | D62: =(D61*1000*31)/D9 -> 10.136155 | E62: =(E61*1000*31)/E9 -> 8.7168432 | F62: =(F61*1000*31)/F9 -> 8.9865625 | G62: =(G61*1000*31)/G9 -> 8.8989922 | H62: =(H61*1000*31)/H9 -> 8.7006653 | I62: =(I61*1000*31)/I9 -> 7.9138378 | J62: =(J61*1000*31)/J9 -> 7.5456555 | K62: =(K61*1000*31)/K9 -> 7.4385123 | ... P62: =(P61*1000*31)/P9 -> 0.74716489
A63: Temporary Staff Employed | C63: No | D63: =Balaka!D63+Liwonde!D63+Machinga!D63+Ntaja!D63 -> 57 | E63: =Balaka!E63+Liwonde!E63+Machinga!E63+Ntaja!E63 -> 57 | F63: =Balaka!F63+Liwonde!F63+Machinga!F63+Ntaja!F63 -> 52 | G63: =Balaka!G63+Liwonde!G63+Machinga!G63+Ntaja!G63 -> 54 | H63: =Balaka!H63+Liwonde!H63+Machinga!H63+Ntaja!H63 -> 55 | I63: =Balaka!I63+Liwonde!I63+Machinga!I63+Ntaja!I63 -> 52 | J63: =Balaka!J63+Liwonde!J63+Machinga!J63+Ntaja!J63 -> 52 | K63: =Balaka!K63+Liwonde!K63+Machinga!K63+Ntaja!K63 -> 60 | ... O63: =Balaka!O63+Liwonde!O63+Machinga!O63+Ntaja!O63 -> 72 | P63: =SUM(D63:O63) -> 706
A65: Water Connections and Disconnections
A66: New Individual Water Connections | B66: Brought Forward | C66: No | D66: =Balaka!D66+Liwonde!D66+Machinga!D66+Ntaja!D66 -> 747 | E66: =Balaka!E66+Liwonde!E66+Machinga!E66+Ntaja!E66 -> 750 | F66: =Balaka!F66+Liwonde!F66+Machinga!F66+Ntaja!F66 -> 750 | G66: =Balaka!G66+Liwonde!G66+Machinga!G66+Ntaja!G66 -> 764 | H66: =Balaka!H66+Liwonde!H66+Machinga!H66+Ntaja!H66 -> 790 | I66: =Balaka!I66+Liwonde!I66+Machinga!I66+Ntaja!I66 -> 824 | J66: =Balaka!J66+Liwonde!J66+Machinga!J66+Ntaja!J66 -> 838 | K66: =Balaka!K66+Liwonde!K66+Machinga!K66+Ntaja!K66 -> 818 | ... O66: =Balaka!O66+Liwonde!O66+Machinga!O66+Ntaja!O66 -> 842 | P66: =D66 -> 747
B67: Applied this Month | C67: No | D67: =Balaka!D67+Liwonde!D67+Machinga!D67+Ntaja!D67 -> 45 | E67: =Balaka!E67+Liwonde!E67+Machinga!E67+Ntaja!E67 -> 88 | F67: =Balaka!F67+Liwonde!F67+Machinga!F67+Ntaja!F67 -> 116 | G67: =Balaka!G67+Liwonde!G67+Machinga!G67+Ntaja!G67 -> 120 | H67: =Balaka!H67+Liwonde!H67+Machinga!H67+Ntaja!H67 -> 172 | I67: =Balaka!I67+Liwonde!I67+Machinga!I67+Ntaja!I67 -> 82 | J67: =Balaka!J67+Liwonde!J67+Machinga!J67+Ntaja!J67 -> 76 | K67: =Balaka!K67+Liwonde!K67+Machinga!K67+Ntaja!K67 -> 57 | ... O67: =Balaka!O67+Liwonde!O67+Machinga!O67+Ntaja!O67 -> 71 | P67: =SUM(D67:O67) -> 1056
B68: Done this Month Postpaid | C68: No | D68: =Balaka!D68+Liwonde!D68+Machinga!D68+Ntaja!D68 -> 34 | E68: =Balaka!E68+Liwonde!E68+Machinga!E68+Ntaja!E68 -> 40 | F68: =Balaka!F68+Liwonde!F68+Machinga!F68+Ntaja!F68 -> 78 | G68: =Balaka!G68+Liwonde!G68+Machinga!G68+Ntaja!G68 -> 63 | H68: =Balaka!H68+Liwonde!H68+Machinga!H68+Ntaja!H68 -> 107 | I68: =Balaka!I68+Liwonde!I68+Machinga!I68+Ntaja!I68 -> 64 | J68: =Balaka!J68+Liwonde!J68+Machinga!J68+Ntaja!J68 -> 96 | K68: =Balaka!K68+Liwonde!K68+Machinga!K68+Ntaja!K68 -> 73 | ... O68: =Balaka!O68+Liwonde!O68+Machinga!O68+Ntaja!O68 -> 37 | P68: =SUM(D68:O68) -> 781
B69: Done this Month Prepaid | C69: No | D69: =Balaka!D69+Liwonde!D69+Machinga!D69+Ntaja!D69 -> 8 | E69: =Balaka!E69+Liwonde!E69+Machinga!E69+Ntaja!E69 -> 48 | F69: =Balaka!F69+Liwonde!F69+Machinga!F69+Ntaja!F69 -> 24 | G69: =Balaka!G69+Liwonde!G69+Machinga!G69+Ntaja!G69 -> 31 | H69: =Balaka!H69+Liwonde!H69+Machinga!H69+Ntaja!H69 -> 31 | I69: =Balaka!I69+Liwonde!I69+Machinga!I69+Ntaja!I69 -> 4 | J69: =Balaka!J69+Liwonde!J69+Machinga!J69+Ntaja!J69 -> 0 | K69: =Balaka!K69+Liwonde!K69+Machinga!K69+Ntaja!K69 -> 0 | ... O69: =Balaka!O69+Liwonde!O69+Machinga!O69+Ntaja!O69 -> 3 | P69: =SUM(D69:O69) -> 149
B70: Total Done | C70: No | D70: =D68+D69 -> 42 | E70: =E68+E69 -> 88 | F70: =F68+F69 -> 102 | G70: =G68+G69 -> 94 | H70: =H68+H69 -> 138 | I70: =I68+I69 -> 68 | J70: =J68+J69 -> 96 | K70: =K68+K69 -> 73 | ... P70: =P68+P69 -> 930
B71: Carried Forward | C71: No | D71: =D66+D67-D70 -> 750 | E71: =E66+E67-E70 -> 750 | F71: =F66+F67-F70 -> 764 | G71: =G66+G67-G70 -> 790 | H71: =H66+H67-H70 -> 824 | I71: =I66+I67-I70 -> 838 | J71: =J66+J67-J70 -> 818 | K71: =K66+K67-K70 -> 802 | ... P71: =P66+P67-P70 -> 873
A72: New Institutional Water Connections | B72: Brought Forward | C72: No | D72: =Balaka!D72+Liwonde!D72+Machinga!D72+Ntaja!D72 -> 0 | E72: =Balaka!E72+Liwonde!E72+Machinga!E72+Ntaja!E72 -> 0 | F72: =Balaka!F72+Liwonde!F72+Machinga!F72+Ntaja!F72 -> 0 | G72: =Balaka!G72+Liwonde!G72+Machinga!G72+Ntaja!G72 -> 0 | H72: =Balaka!H72+Liwonde!H72+Machinga!H72+Ntaja!H72 -> 0 | I72: =Balaka!I72+Liwonde!I72+Machinga!I72+Ntaja!I72 -> 0 | J72: =Balaka!J72+Liwonde!J72+Machinga!J72+Ntaja!J72 -> 0 | K72: =Balaka!K72+Liwonde!K72+Machinga!K72+Ntaja!K72 -> 0 | ... O72: =Balaka!O72+Liwonde!O72+Machinga!O72+Ntaja!O72 -> 0 | P72: =D72 -> 0
B73: Applied this Month | C73: No | D73: =Balaka!D73+Liwonde!D73+Machinga!D73+Ntaja!D73 -> 0 | E73: =Balaka!E73+Liwonde!E73+Machinga!E73+Ntaja!E73 -> 0 | F73: =Balaka!F73+Liwonde!F73+Machinga!F73+Ntaja!F73 -> 0 | G73: =Balaka!G73+Liwonde!G73+Machinga!G73+Ntaja!G73 -> 1 | H73: =Balaka!H73+Liwonde!H73+Machinga!H73+Ntaja!H73 -> 1 | I73: =Balaka!I73+Liwonde!I73+Machinga!I73+Ntaja!I73 -> 0 | J73: =Balaka!J73+Liwonde!J73+Machinga!J73+Ntaja!J73 -> 0 | K73: =Balaka!K73+Liwonde!K73+Machinga!K73+Ntaja!K73 -> 0 | ... O73: =Balaka!O73+Liwonde!O73+Machinga!O73+Ntaja!O73 -> 0 | P73: =SUM(D73:O73) -> 3
B74: Done this Month Postpaid | C74: No | D74: =Balaka!D74+Liwonde!D74+Machinga!D74+Ntaja!D74 -> 0 | E74: =Balaka!E74+Liwonde!E74+Machinga!E74+Ntaja!E74 -> 0 | F74: =Balaka!F74+Liwonde!F74+Machinga!F74+Ntaja!F74 -> 0 | G74: =Balaka!G74+Liwonde!G74+Machinga!G74+Ntaja!G74 -> 1 | H74: =Balaka!H74+Liwonde!H74+Machinga!H74+Ntaja!H74 -> 0 | I74: =Balaka!I74+Liwonde!I74+Machinga!I74+Ntaja!I74 -> 0 | J74: =Balaka!J74+Liwonde!J74+Machinga!J74+Ntaja!J74 -> 0 | K74: =Balaka!K74+Liwonde!K74+Machinga!K74+Ntaja!K74 -> 0 | ... O74: =Balaka!O74+Liwonde!O74+Machinga!O74+Ntaja!O74 -> 0 | P74: =SUM(D74:O74) -> 2
B75: Done this Month Prepaid | C75: No | D75: =Balaka!D75+Liwonde!D75+Machinga!D75+Ntaja!D75 -> 0 | E75: =Balaka!E75+Liwonde!E75+Machinga!E75+Ntaja!E75 -> 0 | F75: =Balaka!F75+Liwonde!F75+Machinga!F75+Ntaja!F75 -> 0 | G75: =Balaka!G75+Liwonde!G75+Machinga!G75+Ntaja!G75 -> 0 | H75: =Balaka!H75+Liwonde!H75+Machinga!H75+Ntaja!H75 -> 1 | I75: =Balaka!I75+Liwonde!I75+Machinga!I75+Ntaja!I75 -> 0 | J75: =Balaka!J75+Liwonde!J75+Machinga!J75+Ntaja!J75 -> 0 | K75: =Balaka!K75+Liwonde!K75+Machinga!K75+Ntaja!K75 -> 0 | ... O75: =Balaka!O75+Liwonde!O75+Machinga!O75+Ntaja!O75 -> 0
B76: Total Done | C76: No | D76: =D74+D75 -> 0 | E76: =E74+E75 -> 0 | F76: =F74+F75 -> 0 | G76: =G74+G75 -> 1 | H76: =H74+H75 -> 1 | I76: =I74+I75 -> 0 | J76: =J74+J75 -> 0 | K76: =K74+K75 -> 0 | ... P76: =P74+P75 -> 2
B77: Carried Forward | C77: No | D77: =D72+D73-D76 -> 0 | E77: =E72+E73-E76 -> 0 | F77: =F72+F73-F76 -> 0 | G77: =G72+G73-G76 -> 0 | H77: =H72+H73-H76 -> 0 | I77: =I72+I73-I76 -> 0 | J77: =J72+J73-J76 -> 0 | K77: =K72+K73-K76 -> 0 | ... O77: =O72+O73-O76 -> 0 | P77: =P73+P74-P76 -> 3
A78: New Commercial/Industrial Water Connections | B78: Brought Forward | C78: No | D78: =Balaka!D78+Liwonde!D78+Machinga!D78+Ntaja!D78 -> 0 | E78: =Balaka!E78+Liwonde!E78+Machinga!E78+Ntaja!E78 -> 0 | F78: =Balaka!F78+Liwonde!F78+Machinga!F78+Ntaja!F78 -> 0 | G78: =Balaka!G78+Liwonde!G78+Machinga!G78+Ntaja!G78 -> 0 | H78: =Balaka!H78+Liwonde!H78+Machinga!H78+Ntaja!H78 -> 0 | I78: =Balaka!I78+Liwonde!I78+Machinga!I78+Ntaja!I78 -> 0 | J78: =Balaka!J78+Liwonde!J78+Machinga!J78+Ntaja!J78 -> 0 | K78: =Balaka!K78+Liwonde!K78+Machinga!K78+Ntaja!K78 -> 0 | ... O78: =Balaka!O78+Liwonde!O78+Machinga!O78+Ntaja!O78 -> 0 | P78: =D78 -> 0
B79: Applied this Month | C79: No | D79: =Balaka!D79+Liwonde!D79+Machinga!D79+Ntaja!D79 -> 0 | E79: =Balaka!E79+Liwonde!E79+Machinga!E79+Ntaja!E79 -> 0 | F79: =Balaka!F79+Liwonde!F79+Machinga!F79+Ntaja!F79 -> 0 | G79: =Balaka!G79+Liwonde!G79+Machinga!G79+Ntaja!G79 -> 0 | H79: =Balaka!H79+Liwonde!H79+Machinga!H79+Ntaja!H79 -> 0 | I79: =Balaka!I79+Liwonde!I79+Machinga!I79+Ntaja!I79 -> 0 | J79: =Balaka!J79+Liwonde!J79+Machinga!J79+Ntaja!J79 -> 0 | K79: =Balaka!K79+Liwonde!K79+Machinga!K79+Ntaja!K79 -> 0 | ... O79: =Balaka!O79+Liwonde!O79+Machinga!O79+Ntaja!O79 -> 0 | P79: =SUM(D79:O79) -> 0
B80: Done this Month Postpaid | C80: No | D80: =Balaka!D80+Liwonde!D80+Machinga!D80+Ntaja!D80 -> 0 | E80: =Balaka!E80+Liwonde!E80+Machinga!E80+Ntaja!E80 -> 0 | F80: =Balaka!F80+Liwonde!F80+Machinga!F80+Ntaja!F80 -> 0 | G80: =Balaka!G80+Liwonde!G80+Machinga!G80+Ntaja!G80 -> 0 | H80: =Balaka!H80+Liwonde!H80+Machinga!H80+Ntaja!H80 -> 0 | I80: =Balaka!I80+Liwonde!I80+Machinga!I80+Ntaja!I80 -> 0 | J80: =Balaka!J80+Liwonde!J80+Machinga!J80+Ntaja!J80 -> 0 | K80: =Balaka!K80+Liwonde!K80+Machinga!K80+Ntaja!K80 -> 0 | ... O80: =Balaka!O80+Liwonde!O80+Machinga!O80+Ntaja!O80 -> 0
B81: Done this Month Prepaid | C81: No | D81: =Balaka!D81+Liwonde!D81+Machinga!D81+Ntaja!D81 -> 0 | E81: =Balaka!E81+Liwonde!E81+Machinga!E81+Ntaja!E81 -> 0 | F81: =Balaka!F81+Liwonde!F81+Machinga!F81+Ntaja!F81 -> 0 | G81: =Balaka!G81+Liwonde!G81+Machinga!G81+Ntaja!G81 -> 0 | H81: =Balaka!H81+Liwonde!H81+Machinga!H81+Ntaja!H81 -> 0 | I81: =Balaka!I81+Liwonde!I81+Machinga!I81+Ntaja!I81 -> 0 | J81: =Balaka!J81+Liwonde!J81+Machinga!J81+Ntaja!J81 -> 0 | K81: =Balaka!K81+Liwonde!K81+Machinga!K81+Ntaja!K81 -> 0 | ... O81: =Balaka!O81+Liwonde!O81+Machinga!O81+Ntaja!O81 -> 0 | P81: =SUM(D81:O81) -> 0
B82: Total Done | C82: No | D82: =D81+D80 -> 0 | E82: =E81+E80 -> 0 | F82: =F81+F80 -> 0 | G82: =G81+G80 -> 0 | H82: =H81+H80 -> 0 | I82: =I81+I80 -> 0 | J82: =J81+J80 -> 0 | K82: =K81+K80 -> 0 | ... P82: =P81+P80 -> 0
B83: Carried Forward | C83: No | D83: =D78+D79-D82 -> 0 | E83: =E78+E79-E82 -> 0 | F83: =F78+F79-F82 -> 0 | G83: =G78+G79-G82 -> 0 | H83: =H78+H79-H82 -> 0 | I83: =I78+I79-I82 -> 0 | J83: =J78+J79-J82 -> 0 | K83: =K78+K79-K82 -> 0 | ... P83: =P78+P79-P82 -> 0
A84: New CWP | B84: Brought Forward | C84: No | D84: =Balaka!D84+Liwonde!D84+Machinga!D84+Ntaja!D84 -> 0 | E84: =Balaka!E84+Liwonde!E84+Machinga!E84+Ntaja!E84 -> 0 | F84: =Balaka!F84+Liwonde!F84+Machinga!F84+Ntaja!F84 -> 0 | G84: =Balaka!G84+Liwonde!G84+Machinga!G84+Ntaja!G84 -> 0 | H84: =Balaka!H84+Liwonde!H84+Machinga!H84+Ntaja!H84 -> 0 | I84: =Balaka!I84+Liwonde!I84+Machinga!I84+Ntaja!I84 -> 0 | J84: =Balaka!J84+Liwonde!J84+Machinga!J84+Ntaja!J84 -> 0 | K84: =Balaka!K84+Liwonde!K84+Machinga!K84+Ntaja!K84 -> 0 | ... O84: =Balaka!O84+Liwonde!O84+Machinga!O84+Ntaja!O84 -> 0 | P84: =D84 -> 0
B85: Applied this Month | C85: No | D85: =Balaka!D85+Liwonde!D85+Machinga!D85+Ntaja!D85 -> 0 | E85: =Balaka!E85+Liwonde!E85+Machinga!E85+Ntaja!E85 -> 0 | F85: =Balaka!F85+Liwonde!F85+Machinga!F85+Ntaja!F85 -> 0 | G85: =Balaka!G85+Liwonde!G85+Machinga!G85+Ntaja!G85 -> 0 | H85: =Balaka!H85+Liwonde!H85+Machinga!H85+Ntaja!H85 -> 0 | I85: =Balaka!I85+Liwonde!I85+Machinga!I85+Ntaja!I85 -> 0 | J85: =Balaka!J85+Liwonde!J85+Machinga!J85+Ntaja!J85 -> 0 | K85: =Balaka!K85+Liwonde!K85+Machinga!K85+Ntaja!K85 -> 0 | ... O85: =Balaka!O85+Liwonde!O85+Machinga!O85+Ntaja!O85 -> 0 | P85: =SUM(D85:O85) -> 0
B86: Done this Month Postpaid | C86: No | D86: =Balaka!D86+Liwonde!D86+Machinga!D86+Ntaja!D86 -> 0 | E86: =Balaka!E86+Liwonde!E86+Machinga!E86+Ntaja!E86 -> 0 | F86: =Balaka!F86+Liwonde!F86+Machinga!F86+Ntaja!F86 -> 0 | G86: =Balaka!G86+Liwonde!G86+Machinga!G86+Ntaja!G86 -> 0 | H86: =Balaka!H86+Liwonde!H86+Machinga!H86+Ntaja!H86 -> 0 | I86: =Balaka!I86+Liwonde!I86+Machinga!I86+Ntaja!I86 -> 0 | J86: =Balaka!J86+Liwonde!J86+Machinga!J86+Ntaja!J86 -> 0 | K86: =Balaka!K86+Liwonde!K86+Machinga!K86+Ntaja!K86 -> 0 | ... O86: =Balaka!O86+Liwonde!O86+Machinga!O86+Ntaja!O86 -> 0
B87: Done this Month Prepaid | C87: No | D87: =Balaka!D87+Liwonde!D87+Machinga!D87+Ntaja!D87 -> 0 | E87: =Balaka!E87+Liwonde!E87+Machinga!E87+Ntaja!E87 -> 0 | F87: =Balaka!F87+Liwonde!F87+Machinga!F87+Ntaja!F87 -> 0 | G87: =Balaka!G87+Liwonde!G87+Machinga!G87+Ntaja!G87 -> 0 | H87: =Balaka!H87+Liwonde!H87+Machinga!H87+Ntaja!H87 -> 0 | I87: =Balaka!I87+Liwonde!I87+Machinga!I87+Ntaja!I87 -> 0 | J87: =Balaka!J87+Liwonde!J87+Machinga!J87+Ntaja!J87 -> 0 | K87: =Balaka!K87+Liwonde!K87+Machinga!K87+Ntaja!K87 -> 0 | ... O87: =Balaka!O87+Liwonde!O87+Machinga!O87+Ntaja!O87 -> 0 | P87: =SUM(D87:O87) -> 0
B88: Total Done | C88: No | D88: =D87+D86 -> 0 | E88: =E87+E86 -> 0 | F88: =F87+F86 -> 0 | G88: =G87+G86 -> 0 | H88: =H87+H86 -> 0 | I88: =I87+I86 -> 0 | J88: =J87+J86 -> 0 | K88: =K87+K86 -> 0 | ... O88: =O87+O86 -> 0
B89: Carried Forward | C89: No | D89: =D84+D85-D88 -> 0 | E89: =E84+E85-E88 -> 0 | F89: =F84+F85-F88 -> 0 | G89: =G84+G85-G88 -> 0 | H89: =H84+H85-H88 -> 0 | I89: =I84+I85-I88 -> 0 | J89: =J84+J85-J88 -> 0 | K89: =K84+K85-K88 -> 0 | ... O89: =O84+O85-O88 -> 0 | P89: =P84+P85-P86-P87 -> 0
A90: Aggregated New Water connections | B90: Brought Forward | C90: No | D90: =D66+D72+D78+D84 -> 747 | E90: =E66+E72+E78+E84 -> 750 | F90: =F66+F72+F78+F84 -> 750 | G90: =G66+G72+G78+G84 -> 764 | H90: =H66+H72+H78+H84 -> 790 | I90: =I66+I72+I78+I84 -> 824 | J90: =J66+J72+J78+J84 -> 838 | K90: =K66+K72+K78+K84 -> 818 | ... O90: =O66+O72+O78+O84 -> 842 | P90: =D90 -> 747
B91: Applied this Month | C91: No | D91: =D67+D73+D79+D85 -> 45 | E91: =E67+E73+E79+E85 -> 88 | F91: =F67+F73+F79+F85 -> 116 | G91: =G67+G73+G79+G85 -> 121 | H91: =H67+H73+H79+H85 -> 173 | I91: =I67+I73+I79+I85 -> 82 | J91: =J67+J73+J79+J85 -> 76 | K91: =K67+K73+K79+K85 -> 57 | ... O91: =O67+O73+O79+O85 -> 71 | P91: =SUM(D91:O91) -> 1059
B92: Done this Month Postpaid | C92: No | D92: =D68+D74+D80+D86 -> 34 | E92: =E68+E74+E80+E86 -> 40 | F92: =F68+F74+F80+F86 -> 78 | G92: =G68+G74+G80+G86 -> 64 | H92: =H68+H74+H80+H86 -> 107 | I92: =I68+I74+I80+I86 -> 64 | J92: =J68+J74+J80+J86 -> 96 | K92: =K68+K74+K80+K86 -> 73 | ... O92: =O68+O74+O80+O86 -> 37 | P92: =SUM(D92:O92) -> 783
B93: Done this Month Prepaid | D93: =D69+D75+D81+D87 -> 8 | E93: =E69+E75+E81+E87 -> 48 | F93: =F69+F75+F81+F87 -> 24 | G93: =G69+G75+G81+G87 -> 31 | H93: =H69+H75+H81+H87 -> 32 | I93: =I69+I75+I81+I87 -> 4 | J93: =J69+J75+J81+J87 -> 0 | K93: =K69+K75+K81+K87 -> 0 | ... O93: =O69+O75+O81+O87 -> 3 | P93: =SUM(D93:O93) -> 150
B94: Total Done | C94: No | D94: =D93+D92 -> 42 | E94: =E93+E92 -> 88 | F94: =F93+F92 -> 102 | G94: =G93+G92 -> 95 | H94: =H93+H92 -> 139 | I94: =I93+I92 -> 68 | J94: =J93+J92 -> 96 | K94: =K93+K92 -> 73 | ... P94: =P93+P92 -> 933
B95: Carried Forward | C95: No | D95: =D90+D91-D94 -> 750 | E95: =E90+E91-E94 -> 750 | F95: =F90+F91-F94 -> 764 | G95: =G90+G91-G94 -> 790 | H95: =H90+H91-H94 -> 824 | I95: =I90+I91-I94 -> 838 | J95: =J90+J91-J94 -> 818 | K95: =K90+K91-K94 -> 802 | ... P95: =P90+P91-P94 -> 873
A97: Prepaid Metering
A98: Prepaid Meters Installed | C98: No | D98: =Balaka!D98+Liwonde!D98+Machinga!D98+Ntaja!D98 -> 1783 | E98: =Balaka!E98+Liwonde!E98+Machinga!E98+Ntaja!E98 -> 1881 | F98: =Balaka!F98+Liwonde!F98+Machinga!F98+Ntaja!F98 -> 1831 | G98: =Balaka!G98+Liwonde!G98+Machinga!G98+Ntaja!G98 -> 1816 | H98: =Balaka!H98+Liwonde!H98+Machinga!H98+Ntaja!H98 -> 1823 | I98: =Balaka!I98+Liwonde!I98+Machinga!I98+Ntaja!I98 -> 1795 | J98: =Balaka!J98+Liwonde!J98+Machinga!J98+Ntaja!J98 -> 1791 | K98: =Balaka!K98+Liwonde!K98+Machinga!K98+Ntaja!K98 -> 1791 | ... O98: =Balaka!O98+Liwonde!O98+Machinga!O98+Ntaja!O98 -> 1841 | P98: =SUM(D98:O98) -> 21729
A100: Active and Disconnected Accounts
A101: Disconnected Individual Accounts | C101: No | D101: =Balaka!D101+Liwonde!D101+Machinga!D101+Ntaja!D101 -> 4167 | E101: =Balaka!E101+Liwonde!E101+Machinga!E101+Ntaja!E101 -> 3286 | F101: =Balaka!F101+Liwonde!F101+Machinga!F101+Ntaja!F101 -> 3249 | G101: =Balaka!G101+Liwonde!G101+Machinga!G101+Ntaja!G101 -> 3209 | H101: =Balaka!H101+Liwonde!H101+Machinga!H101+Ntaja!H101 -> 3155 | I101: =Balaka!I101+Liwonde!I101+Machinga!I101+Ntaja!I101 -> 3278 | J101: =Balaka!J101+Liwonde!J101+Machinga!J101+Ntaja!J101 -> 3522 | K101: =Balaka!K101+Liwonde!K101+Machinga!K101+Ntaja!K101 -> 3599 | ... O101: =Balaka!O101+Liwonde!O101+Machinga!O101+Ntaja!O101 -> 3675 | P101: =O101 -> 3675
A102: Disconnected institutional Accounts | C102: No | D102: =Balaka!D102+Liwonde!D102+Machinga!D102+Ntaja!D102 -> 156 | E102: =Balaka!E102+Liwonde!E102+Machinga!E102+Ntaja!E102 -> 77 | F102: =Balaka!F102+Liwonde!F102+Machinga!F102+Ntaja!F102 -> 77 | G102: =Balaka!G102+Liwonde!G102+Machinga!G102+Ntaja!G102 -> 79 | H102: =Balaka!H102+Liwonde!H102+Machinga!H102+Ntaja!H102 -> 78 | I102: =Balaka!I102+Liwonde!I102+Machinga!I102+Ntaja!I102 -> 80 | J102: =Balaka!J102+Liwonde!J102+Machinga!J102+Ntaja!J102 -> 78 | K102: =Balaka!K102+Liwonde!K102+Machinga!K102+Ntaja!K102 -> 78 | ... O102: =Balaka!O102+Liwonde!O102+Machinga!O102+Ntaja!O102 -> 82 | P102: =O102 -> 82
A103: Disconnected Commercial/Industrial Accounts | C103: No | D103: =Balaka!D103+Liwonde!D103+Machinga!D103+Ntaja!D103 -> 351 | E103: =Balaka!E103+Liwonde!E103+Machinga!E103+Ntaja!E103 -> 163 | F103: =Balaka!F103+Liwonde!F103+Machinga!F103+Ntaja!F103 -> 163 | G103: =Balaka!G103+Liwonde!G103+Machinga!G103+Ntaja!G103 -> 160 | H103: =Balaka!H103+Liwonde!H103+Machinga!H103+Ntaja!H103 -> 159 | I103: =Balaka!I103+Liwonde!I103+Machinga!I103+Ntaja!I103 -> 162 | J103: =Balaka!J103+Liwonde!J103+Machinga!J103+Ntaja!J103 -> 167 | K103: =Balaka!K103+Liwonde!K103+Machinga!K103+Ntaja!K103 -> 165 | ... O103: =Balaka!O103+Liwonde!O103+Machinga!O103+Ntaja!O103 -> 186 | P103: =O103 -> 186
A104: Disconnected CWP | C104: No | D104: =Balaka!D104+Liwonde!D104+Machinga!D104+Ntaja!D104 -> 32 | E104: =Balaka!E104+Liwonde!E104+Machinga!E104+Ntaja!E104 -> 44 | F104: =Balaka!F104+Liwonde!F104+Machinga!F104+Ntaja!F104 -> 47 | G104: =Balaka!G104+Liwonde!G104+Machinga!G104+Ntaja!G104 -> 47 | H104: =Balaka!H104+Liwonde!H104+Machinga!H104+Ntaja!H104 -> 47 | I104: =Balaka!I104+Liwonde!I104+Machinga!I104+Ntaja!I104 -> 47 | J104: =Balaka!J104+Liwonde!J104+Machinga!J104+Ntaja!J104 -> 47 | K104: =Balaka!K104+Liwonde!K104+Machinga!K104+Ntaja!K104 -> 47 | ... O104: =Balaka!O104+Liwonde!O104+Machinga!O104+Ntaja!O104 -> 47 | P104: =O104 -> 47
A105: Total Disconnected Accounts | C105: No | D105: =SUM(D101:D104) -> 4706 | E105: =SUM(E101:E104) -> 3570 | F105: =SUM(F101:F104) -> 3536 | G105: =SUM(G101:G104) -> 3495 | H105: =SUM(H101:H104) -> 3439 | I105: =SUM(I101:I104) -> 3567 | J105: =SUM(J101:J104) -> 3814 | K105: =SUM(K101:K104) -> 3889 | ... O105: =SUM(O101:O104) -> 3990 | P105: =O105 -> 3990
A106: Postpaid Consumers
...

Sheet 1st QTR
A1: SOUTHERN REGION WATER BOARD
A3: MONTHLY REPORTS - 2023/2024
A4: LIWONDE ZONE
A5: LIWONDE ZONE
A7: PARAMETERS | C7: UNITS | D7: Balaka | E7: Liwonde | F7: Machinga | G7: Ntaja | H7: TOTALS
A8: PRODUCTION
A9: Volume Produced | C9: m3 | D9: =Balaka!D9+Balaka!E9+Balaka!F9 -> 172680 | E9: =Liwonde!D9+Liwonde!E9+Liwonde!F9 -> 181289 | F9: =Machinga!D9+Machinga!E9+Machinga!F9 -> 10062 | G9: =Ntaja!D9+Ntaja!E9+Ntaja!F9 -> 10908.01 | H9: =SUM(D9:G9) -> 374939.01
A10: REVENUE WATER - POSTPAID
A11: Volume Billed Individuals | C11: m3 | D11: =Balaka!D11+Balaka!E11+Balaka!F11 -> 74648 | E11: =Liwonde!D11+Liwonde!E11+Liwonde!F11 -> 70623 | F11: =Machinga!D11+Machinga!E11+Machinga!F11 -> 4368 | G11: =Ntaja!D11+Ntaja!E11+Ntaja!F11 -> 1071 | H11: =SUM(D11:G11) -> 150710
A12: Volume Billed CWPs | C12: m3 | D12: =Balaka!D12+Balaka!E12+Balaka!F12 -> 2469 | E12: =Liwonde!D12+Liwonde!E12+Liwonde!F12 -> 1159 | F12: =Machinga!D12+Machinga!E12+Machinga!F12 -> 0 | G12: =Ntaja!D12+Ntaja!E12+Ntaja!F12 -> 0 | H12: =SUM(D12:G12) -> 3628
A13: Volume Billed Institutions | C13: m3 | D13: =Balaka!D13+Balaka!E13+Balaka!F13 -> 3203 | E13: =Liwonde!D13+Liwonde!E13+Liwonde!F13 -> 6694 | F13: =Machinga!D13+Machinga!E13+Machinga!F13 -> 1717 | G13: =Ntaja!D13+Ntaja!E13+Ntaja!F13 -> 45 | H13: =SUM(D13:G13) -> 11659
A14: Volume Billed Commercial/Industrial | C14: m3 | D14: =Balaka!D14+Balaka!E14+Balaka!F14 -> 258 | E14: =Liwonde!D14+Liwonde!E14+Liwonde!F14 -> 416 | F14: =Machinga!D14+Machinga!E14+Machinga!F14 -> 0 | G14: =Ntaja!D14+Ntaja!E14+Ntaja!F14 -> 2 | H14: =SUM(D14:G14) -> 676
A15: Total Volume Billed Post Paid | C15: m3 | D15: =SUM(D11:D14) -> 80578 | E15: =SUM(E11:E14) -> 78892 | F15: =SUM(F11:F14) -> 6085 | G15: =SUM(G11:G14) -> 1118 | H15: =SUM(H11:H14) -> 166673
A16: REVENUE WATER - PREPAID
A17: Individuals | C17: m3 | D17: =Balaka!D17+Balaka!E17+Balaka!F17 -> 21722 | E17: =Liwonde!D17+Liwonde!E17+Liwonde!F17 -> 30656.3 | F17: =Machinga!D17+Machinga!E17+Machinga!F17 -> 2571.2 | G17: =Ntaja!D17+Ntaja!E17+Ntaja!F17 -> 3304.9 | H17: =SUM(D17:G17) -> 58254.4
A18: CWPs | C18: m3 | D18: =Balaka!D18+Balaka!E18+Balaka!F18 -> 0 | E18: =Liwonde!D18+Liwonde!E18+Liwonde!F18 -> 0 | F18: =Machinga!D18+Machinga!E18+Machinga!F18 -> 0 | G18: =Ntaja!D18+Ntaja!E18+Ntaja!F18 -> 92 | H18: =SUM(D18:G18) -> 92
A19: Institutions | C19: m3 | D19: =Balaka!D19+Balaka!E19+Balaka!F19 -> 0 | E19: =Liwonde!D19+Liwonde!E19+Liwonde!F19 -> 0 | F19: =Machinga!D19+Machinga!E19+Machinga!F19 -> 0 | G19: =Ntaja!D19+Ntaja!E19+Ntaja!F19 -> 128 | H19: =SUM(D19:G19) -> 128
A20: Commercial/Industrial | C20: m3 | D20: =Balaka!D20+Balaka!E20+Balaka!F20 -> 0 | E20: =Liwonde!D20+Liwonde!E20+Liwonde!F20 -> 0 | F20: =Machinga!D20+Machinga!E20+Machinga!F20 -> 0 | G20: =Ntaja!D20+Ntaja!E20+Ntaja!F20 -> 163 | H20: =SUM(D20:G20) -> 163
A21: Total Volume Prepaid | C21: m3 | D21: =SUM(D17:D20) -> 21722 | E21: =SUM(E17:E20) -> 30656.3 | F21: =SUM(F17:F20) -> 2571.2 | G21: =SUM(G17:G20) -> 3687.9 | H21: =SUM(H17:H20) -> 58637.4
A22: TOTAL REVENUE WATER | C22: m3 | D22: =D21+D15 -> 102300 | E22: =E21+E15 -> 109548.3 | F22: =F21+F15 -> 8656.2 | G22: =G21+G15 -> 4805.9 | H22: =H21+H15 -> 225310.4
A23: NON-REVENUE WATER (NRW)
A24: Non-Revenue Water (NRW) | B24: Volume | C24: m3 | D24: =D9-D22 -> 70380 | E24: =E9-E22 -> 71740.7 | F24: =F9-F22 -> 1405.8 | G24: =G9-G22 -> 6102.11 | H24: =H9-H22 -> 149628.61
B25: Percentage | C25: % | D25: =D24/D9 -> 0.4075747 | E25: =E24/E9 -> 0.39572561 | F25: =F24/F9 -> 0.13971377 | G25: =G24/G9 -> 0.55941551 | H25: =H24/H9 -> 0.39907453
A26: OPERATING EXPENSES
A27: Chemicals
A28: Chemical | B28: Rate(MK/kg)
A29: Chlorine | B29: =176264.5/50 -> 3525.29 | C29: kg | D29: =Balaka!D29+Balaka!E29+Balaka!F29 -> 340 | E29: =Liwonde!D29+Liwonde!E29+Liwonde!F29 -> 1050 | F29: =Machinga!D29+Machinga!E29+Machinga!F29 -> 33 | G29: =Ntaja!D29+Ntaja!E29+Ntaja!F29 -> 20 | H29: =SUM(D29:G29) -> 1443
C30: kg/mg litre | D30: =D29/(D9/1000) -> 1.9689599 | E30: =E29/(E9/1000) -> 5.7918572 | F30: =F29/(F9/1000) -> 3.2796661 | G30: =G29/(G9/1000) -> 1.833515 | H30: =H29/(H9/1000) -> 3.8486259
A31: Aluminium sulphate | B31: =53000.511/50 -> 1060.0102 | C31: kg | D31: =Balaka!D31+Balaka!E31+Balaka!F31 -> 0 | E31: =Liwonde!D31+Liwonde!E31+Liwonde!F31 -> 0 | F31: =Machinga!D31+Machinga!E31+Machinga!F31 -> 0 | G31: =Ntaja!D31+Ntaja!E31+Ntaja!F31 -> 0 | H31: =SUM(D31:G31) -> 0
C32: kg/mg litre | D32: =D31/(D9/1000) -> 0 | E32: =E31/(E9/1000) -> 0 | F32: =F31/(F9/1000) -> 0 | G32: =G31/(G9/1000) -> 0 | H32: =H31/(H9/1000) -> 0
A33: Soda | B33: =61414.43/50 -> 1228.2886 | C33: kg | D33: =Balaka!D33+Balaka!E33+Balaka!F33 -> 0 | E33: =Liwonde!D33+Liwonde!E33+Liwonde!F33 -> 0 | F33: =Machinga!D33+Machinga!E33+Machinga!F33 -> 0 | G33: =Ntaja!D33+Ntaja!E33+Ntaja!F33 -> 0 | H33: =SUM(D33:G33) -> 0
C34: kg/mg litre | D34: =D33/(D9/1000) -> 0 | E34: =E33/(E9/1000) -> 0 | F34: =F33/(F9/1000) -> 0 | G34: =G33/(G9/1000) -> 0 | H34: =H33/(H9/1000) -> 0
A35: Algae floc | B35: =745345.16/200 -> 3726.7258 | C35: litres | D35: =Balaka!D35+Balaka!E35+Balaka!F35 -> 0 | E35: =Liwonde!D35+Liwonde!E35+Liwonde!F35 -> 549 | F35: =Machinga!D35+Machinga!E35+Machinga!F35 -> 0 | G35: =Ntaja!D35+Ntaja!E35+Ntaja!F35 -> 0 | H35: =SUM(D35:G35) -> 549
C36: litres/mg litre | D36: =D35/(D11/1000) -> 0 | E36: =E35/(E11/1000) -> 7.7736715 | F36: =F35/(F11/1000) -> 0 | G36: =G35/(G11/1000) -> 0 | H36: =H35/(H11/1000) -> 3.6427576
A37: Sud floc | B37: =790318.72/200 -> 3951.5936 | C37: litres | D37: =Balaka!D37+Balaka!E37+Balaka!F37 -> 0 | E37: =Liwonde!D37+Liwonde!E37+Liwonde!F37 -> 0 | F37: =Machinga!D37+Machinga!E37+Machinga!F37 -> 0 | G37: =Ntaja!D37+Ntaja!E37+Ntaja!F37 -> 0 | H37: =SUM(D37:G37) -> 0
C38: litres/mg litre | D38: =D37/(D13/1000) -> 0 | E38: =E37/(E13/1000) -> 0 | F38: =F37/(F13/1000) -> 0 | G38: =G37/(G13/1000) -> 0 | H38: =H37/(H13/1000) -> 0
A39: Potasium permanganate | B39: 1950 | C39: kg | D39: =Balaka!D39+Balaka!E39+Balaka!F39 -> 0 | E39: =Liwonde!D39+Liwonde!E39+Liwonde!F39 -> 0 | F39: =Machinga!D39+Machinga!E39+Machinga!F39 -> 0 | G39: =Ntaja!D39+Ntaja!E39+Ntaja!F39 -> 0 | H39: =SUM(D39:G39) -> 0
C40: kg/mg litre | D40: =D39/(D9/1000) -> 0 | E40: =E39/(E9/1000) -> 0 | F40: =F39/(F9/1000) -> 0 | G40: =G39/(G9/1000) -> 0 | H40: =H39/(H9/1000) -> 0
A41: Cost of Chemicals | C41: Mk | D41: =(D29*$B29)+(D31*$B31)+(D33*$B33)+(D35*$B35)+(D37*$B37)+(D39*$B39) -> 1198598.6 | E41: =(E29*$B29)+(E31*$B31)+(E33*$B33)+(E35*$B35)+(E37*$B37)+(E39*$B39) -> 5747527 | F41: =(F29*$B29)+(F31*$B31)+(F33*$B33)+(F35*$B35)+(F37*$B37)+(F39*$B39) -> 116334.57 | G41: =(G29*$B29)+(G31*$B31)+(G33*$B33)+(G35*$B35)+(G37*$B37)+(G39*$B39) -> 70505.8 | H41: =SUM(D41:G41) -> 7132965.9
A42: Cost/vol. Produced (chemicals) | C42: Mk/m3 | D42: =D41/D9 -> 6.9411547 | E42: =E41/E9 -> 31.703672 | F42: =F41/F9 -> 11.561774 | G42: =G41/G9 -> 6.4636721 | H42: =H41/H9 -> 19.024337
A43: Power
A44: Power Usage | C44: Kw | D44: =Balaka!D44+Balaka!E44+Balaka!F44 -> 123156 | E44: =Liwonde!D44+Liwonde!E44+Liwonde!F44 -> 200550 | F44: =Machinga!D44+Machinga!E44+Machinga!F44 -> 1276 | G44: =Ntaja!D44+Ntaja!E44+Ntaja!F44 -> 11097.69 | H44: =SUM(D44:G44) -> 336079.69
A45: Power/ Vol. Produced | C45: Kw/m3 | D45: =D44/D9 -> 0.71320361 | E45: =E44/E9 -> 1.1062447 | F45: =F44/F9 -> 0.12681375 | G45: =G44/G9 -> 1.0173891 | H45: =H44/H9 -> 0.89635829
A46: Cost of Power | C46: Mk | D46: =Balaka!D46+Balaka!E46+Balaka!F46 -> 17137359 | E46: =Liwonde!D46+Liwonde!E46+Liwonde!F46 -> 27875893 | F46: =Machinga!D46+Machinga!E46+Machinga!F46 -> 226326.41 | G46: =Ntaja!D46+Ntaja!E46+Ntaja!F46 -> 1589100.6 | H46: =SUM(D46:G46) -> 46828679
A47: Cost/vol. Produced | C47: Mk/m3 | D47: =D46/D9 -> 99.243452 | E47: =E46/E9 -> 153.76494 | F47: =F46/F9 -> 22.493184 | G47: =G46/G9 -> 145.68199 | H47: =H46/H9 -> 124.89679
A48: Plant and Vehicle Maintenance
A49: Distances covered | C49: km | D49: =Balaka!D49+Balaka!E49+Balaka!F49 -> 6580 | E49: =Liwonde!D49+Liwonde!E49+Liwonde!F49 -> 7533 | F49: =Machinga!D49+Machinga!E49+Machinga!F49 -> 0 | G49: =Ntaja!D49+Ntaja!E49+Ntaja!F49 -> 0 | H49: =SUM(D49:G49) -> 14113
A50: Fuel Used (litres) | C50: litres | D50: =Balaka!D50+Balaka!E50+Balaka!F50 -> 613 | E50: =Liwonde!D50+Liwonde!E50+Liwonde!F50 -> 763 | F50: =Machinga!D50+Machinga!E50+Machinga!F50 -> 0 | G50: =Ntaja!D50+Ntaja!E50+Ntaja!F50 -> 0 | H50: =SUM(D50:G50) -> 1376
A51: Cost of fuel | C51: Mk | D51: =Balaka!D51+Balaka!E51+Balaka!F51 -> 1119400 | E51: =Liwonde!D51+Liwonde!E51+Liwonde!F51 -> 1464960 | F51: =Machinga!D51+Machinga!E51+Machinga!F51 -> 0 | G51: =Ntaja!D51+Ntaja!E51+Ntaja!F51 -> 0 | H51: =SUM(D51:G51) -> 2584360
A52: Maintenance | C52: Mk | D52: =Balaka!D52+Balaka!E52+Balaka!F52 -> 0 | E52: =Liwonde!D52+Liwonde!E52+Liwonde!F52 -> 0 | F52: =Machinga!D52+Machinga!E52+Machinga!F52 -> 0 | G52: =Ntaja!D52+Ntaja!E52+Ntaja!F52 -> 0 | H52: =SUM(D52:G52) -> 0
A53: Salaries and Wages
A54: Staff Costs | C54: MK | D54: =Balaka!D54+Balaka!E54+Balaka!F54 -> 17104283 | E54: =Liwonde!D54+Liwonde!E54+Liwonde!F54 -> 26719050 | F54: =Machinga!D54+Machinga!E54+Machinga!F54 -> 3148535.6 | G54: =Ntaja!D54+Ntaja!E54+Ntaja!F54 -> 4755785.6 | H54: =SUM(D54:G54) -> 51727654
A55: Wages | C55: MK | D55: =Balaka!D55+Balaka!E55+Balaka!F55 -> 4449987.9 | E55: =Liwonde!D55+Liwonde!E55+Liwonde!F55 -> 12285762 | F55: =Machinga!D55+Machinga!E55+Machinga!F55 -> 2416730.3 | G55: =Ntaja!D55+Ntaja!E55+Ntaja!F55 -> 942719.93 | H55: =SUM(D55:G55) -> 20095200
A56: Other Overhead Costs | C56: MK | D56: =Balaka!D56+Balaka!E56+Balaka!F56 -> 5735117 | E56: =Liwonde!D56+Liwonde!E56+Liwonde!F56 -> 2509122 | F56: =Machinga!D56+Machinga!E56+Machinga!F56 -> 2819500 | G56: =Ntaja!D56+Ntaja!E56+Ntaja!F56 -> 72000 | H56: =SUM(D56:G56) -> 11135739
A57: Operating Costs
A58: Total Operating Costs | C58: MK | D58: =D41+D46+D51+D52+D54+D55+D56 -> 46744746 | E58: =E41+E46+E51+E52+E54+E55+E56 -> 76602314 | F58: =F41+F46+F51+F52+F54+F55+F56 -> 8727426.8 | G58: =G41+G46+G51+G52+G54+G55+G56 -> 7430112 | H58: =SUM(D58:G58) -> 1.395046e+08
A59: Cost/Vol. Produced | C59: Mk/m3 | D59: =D58/D9 -> 270.70156 | E59: =E58/E9 -> 422.54254 | F59: =F58/F9 -> 867.36502 | G59: =G58/G9 -> 681.16109 | H59: =H58/H9 -> 372.07278
A60: Cost/Vol. Billed | C60: Mk/m3 | D60: =D58/D22 -> 456.93789 | E60: =E58/E22 -> 699.25607 | F60: =F58/F22 -> 1008.2284 | G60: =G58/G22 -> 1546.0397 | H60: =H58/H22 -> 619.16626
A61: Permanent Staff Employed | C61: No | D61: =Balaka!F61 -> 16 | E61: =Liwonde!F61 -> 13 | F61: =Machinga!F61 -> 2 | G61: =Ntaja!F61 -> 6 | H61: =SUM(D61:G61) -> 37
A62: Staff/Vol.1000m3 of Volume Produced/hour (12 hour day) | C62: No/1000m3 | D62: =(D61*1000*31)/D9 -> 2.8723651 | E62: =(E61*1000*31)/E9 -> 2.22297 | F62: =(F61*1000*31)/F9 -> 6.1617969 | G62: =(G61*1000*31)/G9 -> 17.05169 | H62: =(H61*1000*31)/H9 -> 3.0591642
A63: Temporary Staff Employed | C63: No | D63: =Balaka!F63 -> 21 | E63: =Liwonde!F63 -> 19 | F63: =Machinga!F63 -> 6 | G63: =Ntaja!F63 -> 6 | H63: =SUM(D63:G63) -> 52
A65: Water Connections and Disconnections
A66: New Individual Water Connections | B66: Brought Forward | C66: No | D66: =Balaka!D66 -> 435 | E66: =Liwonde!D66 -> 288 | F66: =Machinga!D66 -> 22 | G66: =Ntaja!D66 -> 2 | H66: =SUM(D66:G66) -> 747
B67: Applied this Month | C67: No | D67: =Balaka!D67+Balaka!E67+Balaka!F67 -> 73 | E67: =Liwonde!D67+Liwonde!E67+Liwonde!F67 -> 112 | F67: =Machinga!D67+Machinga!E67+Machinga!F67 -> 27 | G67: =Ntaja!D67+Ntaja!E67+Ntaja!F67 -> 37 | H67: =SUM(D67:G67) -> 249
B68: Done this Month Postpaid | C68: No | D68: =Balaka!D68+Balaka!E68+Balaka!F68 -> 88 | E68: =Liwonde!D68+Liwonde!E68+Liwonde!F68 -> 58 | F68: =Machinga!D68+Machinga!E68+Machinga!F68 -> 6 | G68: =Ntaja!D68+Ntaja!E68+Ntaja!F68 -> 0 | H68: =SUM(D68:G68) -> 152
B69: Done this Month Prepaid | C69: No | D69: =Balaka!D69+Balaka!E69+Balaka!F69 -> 0 | E69: =Liwonde!D69+Liwonde!E69+Liwonde!F69 -> 23 | F69: =Machinga!D69+Machinga!E69+Machinga!F69 -> 31 | G69: =Ntaja!D69+Ntaja!E69+Ntaja!F69 -> 26 | H69: =SUM(D69:G69) -> 80
B70: Total Done | C70: No | D70: =D68+D69 -> 88 | E70: =E68+E69 -> 81 | F70: =F68+F69 -> 37 | G70: =G68+G69 -> 26 | H70: =H68+H69 -> 232
B71: Carried Forward | C71: No | D71: =D66+D67-D70 -> 420 | E71: =E66+E67-E70 -> 319 | F71: =F66+F67-F70 -> 12 | G71: =G66+G67-G70 -> 13 | H71: =H66+H67-H70 -> 764
A72: New Institutional Water Connections | B72: Brought Forward | C72: No | D72: =Balaka!D72 -> 0 | E72: =Liwonde!D72 -> 0 | F72: =Machinga!D72 -> 0 | G72: =Ntaja!D72 -> 0 | H72: =SUM(D72:G72) -> 0
B73: Applied this Month | C73: No | D73: =Balaka!D73+Balaka!E73+Balaka!F73 -> 0 | E73: =Liwonde!D73+Liwonde!E73+Liwonde!F73 -> 0 | F73: =Machinga!D73+Machinga!E73+Machinga!F73 -> 0 | G73: =Ntaja!D73+Ntaja!E73+Ntaja!F73 -> 0 | H73: =SUM(D73:G73) -> 0
B74: Done this Month Postpaid | C74: No | D74: =Balaka!D74+Balaka!E74+Balaka!F74 -> 0 | E74: =Liwonde!D74+Liwonde!E74+Liwonde!F74 -> 0 | F74: =Machinga!D74+Machinga!E74+Machinga!F74 -> 0 | G74: =Ntaja!D74+Ntaja!E74+Ntaja!F74 -> 0 | H74: =SUM(D74:G74) -> 0
B75: Done this Month Prepaid | C75: No | D75: =Balaka!D75+Balaka!E75+Balaka!F75 -> 0 | E75: =Liwonde!D75+Liwonde!E75+Liwonde!F75 -> 0 | F75: =Machinga!D75+Machinga!E75+Machinga!F75 -> 0 | G75: =Ntaja!D75+Ntaja!E75+Ntaja!F75 -> 0 | H75: =SUM(D75:G75) -> 0
B76: Total Done | C76: No | D76: =D74+D75 -> 0 | E76: =E74+E75 -> 0 | F76: =F74+F75 -> 0 | G76: =G74+G75 -> 0 | H76: =H74+H75 -> 0
B77: Carried Forward | C77: No | D77: =D73+D74-D76 -> 0 | E77: =E73+E74-E76 -> 0 | F77: =F73+F74-F76 -> 0 | G77: =G73+G74-G76 -> 0 | H77: =H73+H74-H76 -> 0
A78: New Commercial/Industrial Water Connections | B78: Brought Forward | C78: No | D78: =Balaka!D78 -> 0 | E78: =Liwonde!D78 -> 0 | F78: =Machinga!D78 -> 0 | G78: =Ntaja!D78 -> 0 | H78: =SUM(D78:G78) -> 0
B79: Applied this Month | C79: No | D79: =Balaka!D79+Balaka!E79+Balaka!F79 -> 0 | E79: =Liwonde!D79+Liwonde!E79+Liwonde!F79 -> 0 | F79: =Machinga!D79+Machinga!E79+Machinga!F79 -> 0 | G79: =Ntaja!D79+Ntaja!E79+Ntaja!F79 -> 0 | H79: =SUM(D79:G79) -> 0
B80: Done this Month Postpaid | C80: No | D80: =Balaka!D80+Balaka!E80+Balaka!F80 -> 0 | E80: =Liwonde!D80+Liwonde!E80+Liwonde!F80 -> 0 | F80: =Machinga!D80+Machinga!E80+Machinga!F80 -> 0 | G80: =Ntaja!D80+Ntaja!E80+Ntaja!F80 -> 0 | H80: =SUM(D80:G80) -> 0
B81: Done this Month Prepaid | C81: No | D81: =Balaka!D81+Balaka!E81+Balaka!F81 -> 0 | E81: =Liwonde!D81+Liwonde!E81+Liwonde!F81 -> 0 | F81: =Machinga!D81+Machinga!E81+Machinga!F81 -> 0 | G81: =Ntaja!D81+Ntaja!E81+Ntaja!F81 -> 0 | H81: =SUM(D81:G81) -> 0
B82: Total Done | C82: No | D82: =D81+D80 -> 0 | E82: =E81+E80 -> 0 | F82: =F81+F80 -> 0 | G82: =G81+G80 -> 0 | H82: =H81+H80 -> 0
B83: Carried Forward | C83: No | D83: =D78+D79-D82 -> 0 | E83: =E78+E79-E82 -> 0 | F83: =F78+F79-F82 -> 0 | G83: =G78+G79-G82 -> 0 | H83: =H78+H79-H82 -> 0
A84: New CWP | B84: Brought Forward | C84: No | D84: =Balaka!D84 -> 0 | E84: =Liwonde!D84 -> 0 | F84: =Machinga!D84 -> 0 | G84: =Ntaja!D84 -> 0 | H84: =SUM(D84:G84) -> 0
B85: Applied this Month | C85: No | D85: =Balaka!D85+Balaka!E85+Balaka!F85 -> 0 | E85: =Liwonde!D85+Liwonde!E85+Liwonde!F85 -> 0 | F85: =Machinga!D85+Machinga!E85+Machinga!F85 -> 0 | G85: =Ntaja!D85+Ntaja!E85+Ntaja!F85 -> 0 | H85: =SUM(D85:G85) -> 0
B86: Done this Month Postpaid | C86: No | D86: =Balaka!D86+Balaka!E86+Balaka!F86 -> 0 | E86: =Liwonde!D86+Liwonde!E86+Liwonde!F86 -> 0 | F86: =Machinga!D86+Machinga!E86+Machinga!F86 -> 0 | G86: =Ntaja!D86+Ntaja!E86+Ntaja!F86 -> 0 | H86: =SUM(D86:G86) -> 0
B87: Done this Month Prepaid | C87: No | D87: =Balaka!D87+Balaka!E87+Balaka!F87 -> 0 | E87: =Liwonde!D87+Liwonde!E87+Liwonde!F87 -> 0 | F87: =Machinga!D87+Machinga!E87+Machinga!F87 -> 0 | G87: =Ntaja!D87+Ntaja!E87+Ntaja!F87 -> 0 | H87: =SUM(D87:G87) -> 0
B88: Total Done | C88: No | D88: =D87+D86 -> 0 | E88: =E87+E86 -> 0 | F88: =F87+F86 -> 0 | G88: =G87+G86 -> 0 | H88: =SUM(D88:G88) -> 0
B89: Carried Forward | C89: No | D89: =D84+D85-D88 -> 0 | E89: =E84+E85-E88 -> 0 | F89: =F84+F85-F88 -> 0 | G89: =G84+G85-G88 -> 0 | H89: =H84+H85-H86-H87 -> 0
A90: Aggregated New Water connections | B90: Brought Forward | C90: No | D90: =D66+D72+D78+D84 -> 435 | E90: =E66+E72+E78+E84 -> 288 | F90: =F66+F72+F78+F84 -> 22 | G90: =G66+G72+G78+G84 -> 2 | H90: =SUM(D90:G90) -> 747
B91: Applied this Month | C91: No | D91: =D67+D73+D79+D85 -> 73 | E91: =E67+E73+E79+E85 -> 112 | F91: =F67+F73+F79+F85 -> 27 | G91: =G67+G73+G79+G85 -> 37 | H91: =SUM(D91:G91) -> 249
B92: Done this Month Postpaid | C92: No | D92: =D68+D74+D80+D86 -> 88 | E92: =E68+E74+E80+E86 -> 58 | F92: =F68+F74+F80+F86 -> 6 | G92: =G68+G74+G80+G86 -> 0 | H92: =SUM(D92:G92) -> 152
B93: Done this Month Prepaid | D93: =D69+D75+D81+D87 -> 0 | E93: =E69+E75+E81+E87 -> 23 | F93: =F69+F75+F81+F87 -> 31 | G93: =G69+G75+G81+G87 -> 26 | H93: =SUM(D93:G93) -> 80
B94: Total Done | C94: No | D94: =D93+D92 -> 88 | E94: =E93+E92 -> 81 | F94: =F93+F92 -> 37 | G94: =G93+G92 -> 26 | H94: =H93+H92 -> 232
B95: Carried Forward | C95: No | D95: =D90+D91-D94 -> 420 | E95: =E90+E91-E94 -> 319 | F95: =F90+F91-F94 -> 12 | G95: =G90+G91-G94 -> 13 | H95: =H90+H91-H94 -> 764
A97: Prepaid Metering
A98: Prepaid Meters Installed | C98: No | D98: =Balaka!D98+Balaka!E98+Balaka!F98 -> 2799 | E98: =Liwonde!D98+Liwonde!E98+Liwonde!F98 -> 2134 | F98: =Machinga!D98+Machinga!E98+Machinga!F98 -> 370 | G98: =Ntaja!D98+Ntaja!E98+Ntaja!F98 -> 192 | H98: =SUM(D98:G98) -> 5495
A100: Active and Disconnected Accounts
A101: Disconnected Individual Accounts | C101: No | D101: =Balaka!F101 -> 1938 | E101: =Liwonde!F101 -> 1307 | F101: =Machinga!F101 -> 0 | G101: =Ntaja!F101 -> 4 | H101: =SUM(D101:G101) -> 3249
A102: Disconnected institutional Accounts | C102: No | D102: =Balaka!F102 -> 36 | E102: =Liwonde!F102 -> 40 | F102: =Machinga!F102 -> 0 | G102: =Ntaja!F102 -> 1 | H102: =SUM(D102:G102) -> 77
A103: Disconnected Commercial/Industrial Accounts | C103: No | D103: =Balaka!F103 -> 98 | E103: =Liwonde!F103 -> 65 | F103: =Machinga!F103 -> 0 | G103: =Ntaja!F103 -> 0 | H103: =SUM(D103:G103) -> 163
A104: Disconnected CWP | C104: No | D104: =Balaka!F104 -> 17 | E104: =Liwonde!F104 -> 15 | F104: =Machinga!F104 -> 0 | G104: =Ntaja!F104 -> 15 | H104: =SUM(D104:G104) -> 47
A105: Total Disconnected Accounts | C105: No | D105: =SUM(D101:D104) -> 2089 | E105: =SUM(E101:E104) -> 1427 | F105: =SUM(F101:F104) -> 0 | G105: =SUM(G101:G104) -> 20 | H105: =SUM(D105:G105) -> 3536
...

Sheet 2nd QTR 
A1: SOUTHERN REGION WATER BOARD
A3: MONTHLY REPORTS - 2023/2024
A4: LIWONDE ZONE
A5: LIWONDE ZONE
A7: PARAMETERS | C7: UNITS | D7: Balaka | E7: Liwonde | F7: Machinga | G7: Ntaja | H7: TOTALS
A8: PRODUCTION
A9: Volume Produced | C9: m3 | D9: =Balaka!G9+Balaka!H9+Balaka!I9 -> 191187 | E9: =Liwonde!G9+Liwonde!H9+Liwonde!I9 -> 197287 | F9: =Machinga!G9+Machinga!H9+Machinga!I9 -> 9080 | G9: =Ntaja!G9+Ntaja!H9+Ntaja!I9 -> 8102 | H9: =SUM(D9:G9) -> 405656
A10: REVENUE WATER - POSTPAID
A11: Volume Billed Individuals | C11: m3 | D11: =Balaka!G11+Balaka!H11+Balaka!I11 -> 84563 | E11: =Liwonde!G11+Liwonde!H11+Liwonde!I11 -> 78955 | F11: =Machinga!G11+Machinga!H11+Machinga!I11 -> 2995 | G11: =Ntaja!G11+Ntaja!H11+Ntaja!I11 -> 14 | H11: =SUM(D11:G11) -> 166527
A12: Volume Billed CWPs | C12: m3 | D12: =Balaka!G12+Balaka!H12+Balaka!I12 -> 3531 | E12: =Liwonde!G12+Liwonde!H12+Liwonde!I12 -> 1448 | F12: =Machinga!G12+Machinga!H12+Machinga!I12 -> 0 | G12: =Ntaja!G12+Ntaja!H12+Ntaja!I12 -> 0 | H12: =SUM(D12:G12) -> 4979
A13: Volume Billed Institutions | C13: m3 | D13: =Balaka!G13+Balaka!H13+Balaka!I13 -> 908 | E13: =Liwonde!G13+Liwonde!H13+Liwonde!I13 -> 6974 | F13: =Machinga!G13+Machinga!H13+Machinga!I13 -> 139 | G13: =Ntaja!G13+Ntaja!H13+Ntaja!I13 -> 59 | H13: =SUM(D13:G13) -> 8080
A14: Volume Billed Commercial/Industrial | C14: m3 | D14: =Balaka!G14+Balaka!H14+Balaka!I14 -> 342 | E14: =Liwonde!G14+Liwonde!H14+Liwonde!I14 -> 628 | F14: =Machinga!G14+Machinga!H14+Machinga!I14 -> 0 | G14: =Ntaja!G14+Ntaja!H14+Ntaja!I14 -> 0 | H14: =SUM(D14:G14) -> 970
A15: Total Volume Billed Post Paid | C15: m3 | D15: =SUM(D11:D14) -> 89344 | E15: =SUM(E11:E14) -> 88005 | F15: =SUM(F11:F14) -> 3134 | G15: =SUM(G11:G14) -> 73 | H15: =SUM(H11:H14) -> 180556
A16: REVENUE WATER - PREPAID
A17: Individuals | C17: m3 | D17: =Balaka!G17+Balaka!H17+Balaka!I17 -> 20425 | E17: =Liwonde!G17+Liwonde!H17+Liwonde!I17 -> 28538.1 | F17: =Machinga!G17+Machinga!H17+Machinga!I17 -> 4776.6 | G17: =Ntaja!G17+Ntaja!H17+Ntaja!I17 -> 6470 | H17: =SUM(D17:G17) -> 60209.7
A18: CWPs | C18: m3 | D18: =Balaka!G18+Balaka!H18+Balaka!I18 -> 0 | E18: =Liwonde!G18+Liwonde!H18+Liwonde!I18 -> 0 | F18: =Machinga!G18+Machinga!H18+Machinga!I18 -> 0 | G18: =Ntaja!G18+Ntaja!H18+Ntaja!I18 -> 232 | H18: =SUM(D18:G18) -> 232
A19: Institutions | C19: m3 | D19: =Balaka!G19+Balaka!H19+Balaka!I19 -> 1374 | E19: =Liwonde!G19+Liwonde!H19+Liwonde!I19 -> 0 | F19: =Machinga!G19+Machinga!H19+Machinga!I19 -> 0 | G19: =Ntaja!G19+Ntaja!H19+Ntaja!I19 -> 210 | H19: =SUM(D19:G19) -> 1584
A20: Commercial/Industrial | C20: m3 | D20: =Balaka!G20+Balaka!H20+Balaka!I20 -> 551 | E20: =Liwonde!G20+Liwonde!H20+Liwonde!I20 -> 0 | F20: =Machinga!G20+Machinga!H20+Machinga!I20 -> 0 | G20: =Ntaja!G20+Ntaja!H20+Ntaja!I20 -> 287 | H20: =SUM(D20:G20) -> 838
A21: Total Volume Prepaid | C21: m3 | D21: =SUM(D17:D20) -> 22350 | E21: =SUM(E17:E20) -> 28538.1 | F21: =SUM(F17:F20) -> 4776.6 | G21: =SUM(G17:G20) -> 7199 | H21: =SUM(H17:H20) -> 62863.7
A22: TOTAL REVENUE WATER | C22: m3 | D22: =D21+D15 -> 111694 | E22: =E21+E15 -> 116543.1 | F22: =F21+F15 -> 7910.6 | G22: =G21+G15 -> 7272 | H22: =H21+H15 -> 243419.7
A23: NON-REVENUE WATER (NRW)
A24: Non-Revenue Water (NRW) | B24: Volume | C24: m3 | D24: =D9-D22 -> 79493 | E24: =E9-E22 -> 80743.9 | F24: =F9-F22 -> 1169.4 | G24: =G9-G22 -> 830 | H24: =H9-H22 -> 162236.3
B25: Percentage | C25: % | D25: =D24/D9 -> 0.41578664 | E25: =E24/E9 -> 0.40927126 | F25: =F24/F9 -> 0.12878855 | G25: =G24/G9 -> 0.10244384 | H25: =H24/H9 -> 0.39993566
A26: OPERATING EXPENSES
A27: Chemicals
A28: Chemical | B28: Rate(MK/kg)
A29: Chlorine | B29: =176264.5/50 -> 3525.29 | C29: kg | D29: =Balaka!G29+Balaka!H29+Balaka!I29 -> 320 | E29: =Liwonde!G29+Liwonde!H29+Liwonde!I29 -> 833 | F29: =Machinga!G29+Machinga!H29+Machinga!I29 -> 30 | G29: =Ntaja!G29+Ntaja!H29+Ntaja!I29 -> 24 | H29: =SUM(D29:G29) -> 1207
C30: kg/mg litre | D30: =D29/(D9/1000) -> 1.673754 | E30: =E29/(E9/1000) -> 4.2222752 | F30: =F29/(F9/1000) -> 3.3039648 | G30: =G29/(G9/1000) -> 2.9622315 | H30: =H29/(H9/1000) -> 2.9754275
A31: Aluminium sulphate | B31: =53000.511/50 -> 1060.0102 | C31: kg | D31: =Balaka!G31+Balaka!H31+Balaka!I31 -> 0 | E31: =Liwonde!G31+Liwonde!H31+Liwonde!I31 -> 0 | F31: =Machinga!G31+Machinga!H31+Machinga!I31 -> 0 | G31: =Ntaja!G31+Ntaja!H31+Ntaja!I31 -> 0 | H31: =SUM(D31:G31) -> 0
C32: kg/mg litre | D32: =D31/(D9/1000) -> 0 | E32: =E31/(E9/1000) -> 0 | F32: =F31/(F9/1000) -> 0 | G32: =G31/(G9/1000) -> 0 | H32: =H31/(H9/1000) -> 0
A33: Soda | B33: =61414.43/50 -> 1228.2886 | C33: kg | D33: =Balaka!G33+Balaka!H33+Balaka!I33 -> 0 | E33: =Liwonde!G33+Liwonde!H33+Liwonde!I33 -> 0 | F33: =Machinga!G33+Machinga!H33+Machinga!I33 -> 0 | G33: =Ntaja!G33+Ntaja!H33+Ntaja!I33 -> 0 | H33: =SUM(D33:G33) -> 0
C34: kg/mg litre | D34: =D33/(D9/1000) -> 0 | E34: =E33/(E9/1000) -> 0 | F34: =F33/(F9/1000) -> 0 | G34: =G33/(G9/1000) -> 0 | H34: =H33/(H9/1000) -> 0
A35: Algae floc | B35: =745345.16/200 -> 3726.7258 | C35: litres | D35: =Balaka!G35+Balaka!H35+Balaka!I35 -> 0 | E35: =Liwonde!G35+Liwonde!H35+Liwonde!I35 -> 518 | F35: =Machinga!G35+Machinga!H35+Machinga!I35 -> 0 | G35: =Ntaja!G35+Ntaja!H35+Ntaja!I35 -> 0
C36: litres/mg litre
A37: Sud floc | B37: =790318.72/200 -> 3951.5936 | C37: litres | D37: =Balaka!G37+Balaka!H37+Balaka!I37 -> 0 | E37: =Liwonde!G37+Liwonde!H37+Liwonde!I37 -> 0 | F37: =Machinga!G37+Machinga!H37+Machinga!I37 -> 0 | G37: =Ntaja!G37+Ntaja!H37+Ntaja!I37 -> 0 | H37: =SUM(D37:G37) -> 0
C38: litres/mg litre | D38: =D37/(D9/1000) -> 0 | E38: =E37/(E9/1000) -> 0 | F38: =F37/(F9/1000) -> 0 | G38: =G37/(G9/1000) -> 0 | H38: =H37/(H9/1000) -> 0
A39: Potasium permanganate | B39: 1950 | C39: kg | D39: =Balaka!G39+Balaka!H39+Balaka!I39 -> 0 | E39: =Liwonde!G39+Liwonde!H39+Liwonde!I39 -> 0 | F39: =Machinga!G39+Machinga!H39+Machinga!I39 -> 0 | G39: =Ntaja!G39+Ntaja!H39+Ntaja!I39 -> 0 | H39: =SUM(D39:G39) -> 0
C40: kg/mg litre | D40: =D39/(D9/1000) -> 0 | E40: =E39/(E9/1000) -> 0 | F40: =F39/(F9/1000) -> 0 | G40: =G39/(G9/1000) -> 0 | H40: =H39/(H9/1000) -> 0
A41: Cost of Chemicals | C41: Mk | D41: =(D29*$B29)+(D31*$B31)+(D33*$B33)+(D35*$B35)+(D37*$B37)+(D39*$B39) -> 1128092.8 | E41: =(E29*$B29)+(E31*$B31)+(E33*$B33)+(E35*$B35)+(E37*$B37)+(E39*$B39) -> 4867010.5 | F41: =(F29*$B29)+(F31*$B31)+(F33*$B33)+(F35*$B35)+(F37*$B37)+(F39*$B39) -> 105758.7 | G41: =(G29*$B29)+(G31*$B31)+(G33*$B33)+(G35*$B35)+(G37*$B37)+(G39*$B39) -> 84606.96 | H41: =SUM(D41:G41) -> 6185469
A42: Cost/vol. Produced (chemicals) | C42: Mk/m3 | D42: =D41/D9 -> 5.9004681 | E42: =E41/E9 -> 24.669697 | F42: =F41/F9 -> 11.647434 | G42: =G41/G9 -> 10.442725 | H42: =H41/H9 -> 15.248065
A43: Power
A44: Power Usage | C44: Kw | D44: =Balaka!G44+Balaka!H44+Balaka!I44 -> 125849 | E44: =Liwonde!G44+Liwonde!H44+Liwonde!I44 -> 215159.55 | F44: =Machinga!G44+Machinga!H44+Machinga!I44 -> 1313 | G44: =Ntaja!G44+Ntaja!H44+Ntaja!I44 -> 11126.36 | H44: =SUM(D44:G44) -> 353447.91
A45: Power/ Vol. Produced | C45: Kw/m3 | D45: =D44/D9 -> 0.65825082 | E45: =E44/E9 -> 1.0905916 | F45: =F44/F9 -> 0.14460352 | G45: =G44/G9 -> 1.3732856 | H45: =H44/H9 -> 0.8712996
A46: Cost of Power | C46: Mk | D46: =Balaka!G46+Balaka!H46+Balaka!I46 -> 20096473 | E46: =Liwonde!G46+Liwonde!H46+Liwonde!I46 -> 33750405 | F46: =Machinga!G46+Machinga!H46+Machinga!I46 -> 268440.12 | G46: =Ntaja!G46+Ntaja!H46+Ntaja!I46 -> 1807692.6 | H46: =SUM(D46:G46) -> 55923011
A47: Cost/vol. Produced | C47: Mk/m3 | D47: =D46/D9 -> 105.11422 | E47: =E46/E9 -> 171.07263 | F47: =F46/F9 -> 29.563889 | G47: =G46/G9 -> 223.11684 | H47: =H46/H9 -> 137.85821
A48: Plant and Vehicle Maintenance
A49: Distances covered | C49: km | D49: =Balaka!G49+Balaka!H49+Balaka!I49 -> 8045 | E49: =Liwonde!G49+Liwonde!H49+Liwonde!I49 -> 8413 | F49: =Machinga!G49+Machinga!H49+Machinga!I49 -> 0 | G49: =Ntaja!G49+Ntaja!H49+Ntaja!I49 -> 0 | H49: =SUM(D49:G49) -> 16458
A50: Fuel Used (litres) | C50: litres | D50: =Balaka!G50+Balaka!H50+Balaka!I50 -> 840 | E50: =Liwonde!G50+Liwonde!H50+Liwonde!I50 -> 659.86 | F50: =Machinga!G50+Machinga!H50+Machinga!I50 -> 0 | G50: =Ntaja!G50+Ntaja!H50+Ntaja!I50 -> 15 | H50: =SUM(D50:G50) -> 1514.86
A51: Cost of fuel | C51: Mk | D51: =Balaka!G51+Balaka!H51+Balaka!I51 -> 1793250 | E51: =Liwonde!G51+Liwonde!H51+Liwonde!I51 -> 1266931.2 | F51: =Machinga!G51+Machinga!H51+Machinga!I51 -> 0 | G51: =Ntaja!G51+Ntaja!H51+Ntaja!I51 -> 26190 | H51: =SUM(D51:G51) -> 3086371.2
A52: Maintenance | C52: Mk | D52: =Balaka!G52+Balaka!H52+Balaka!I52 -> 0 | E52: =Liwonde!G52+Liwonde!H52+Liwonde!I52 -> 0 | F52: =Machinga!G52+Machinga!H52+Machinga!I52 -> 0 | G52: =Ntaja!G52+Ntaja!H52+Ntaja!I52 -> 0 | H52: =SUM(D52:G52) -> 0
A53: Salaries and Wages
A54: Staff Costs | C54: MK | D54: =Balaka!G54+Balaka!H54+Balaka!I54 -> 18693675 | E54: =Liwonde!G54+Liwonde!H54+Liwonde!I54 -> 25949748 | F54: =Machinga!G54+Machinga!H54+Machinga!I54 -> 3895830.5 | G54: =Ntaja!G54+Ntaja!H54+Ntaja!I54 -> 4010902.9 | H54: =SUM(D54:G54) -> 52550156
A55: Wages | C55: MK | D55: =Balaka!G55+Balaka!H55+Balaka!I55 -> 3608789.3 | E55: =Liwonde!G55+Liwonde!H55+Liwonde!I55 -> 8866734.1 | F55: =Machinga!G55+Machinga!H55+Machinga!I55 -> 1783659.3 | G55: =Ntaja!G55+Ntaja!H55+Ntaja!I55 -> 1111530.3 | H55: =SUM(D55:G55) -> 15370713
A56: Other Overhead Costs | C56: MK | D56: =Balaka!G56+Balaka!H56+Balaka!I56 -> 18716556 | E56: =Liwonde!G56+Liwonde!H56+Liwonde!I56 -> 9077815 | F56: =Machinga!G56+Machinga!H56+Machinga!I56 -> 1927000 | G56: =Ntaja!G56+Ntaja!H56+Ntaja!I56 -> 1477686.8 | H56: =SUM(D56:G56) -> 31199058
A57: Operating Costs
A58: Total Operating Costs | C58: MK | D58: =D41+D46+D51+D52+D54+D55+D56 -> 64036836 | E58: =E41+E46+E51+E52+E54+E55+E56 -> 83778644 | F58: =F41+F46+F51+F52+F54+F55+F56 -> 7980688.7 | G58: =G41+G46+G51+G52+G54+G55+G56 -> 8518609.6 | H58: =SUM(D58:G58) -> 1.6431478e+08
A59: Cost/Vol. Produced | C59: Mk/m3 | D59: =D58/D9 -> 334.94346 | E59: =E58/E9 -> 424.65365 | F59: =F58/F9 -> 878.93047 | G59: =G58/G9 -> 1051.4206 | H59: =H58/H9 -> 405.05941
A60: Cost/Vol. Billed | C60: Mk/m3 | D60: =D58/D22 -> 573.32387 | E60: =E58/E22 -> 718.86404 | F60: =F58/F22 -> 1008.8601 | G60: =G58/G22 -> 1171.426 | H60: =H58/H22 -> 675.02663
A61: Permanent Staff Employed | C61: No | D61: =Balaka!I61 -> 15 | E61: =Liwonde!I61 -> 13 | F61: =Machinga!I61 -> 3 | G61: =Ntaja!I61 -> 6 | H61: =SUM(D61:G61) -> 37
A62: Staff/Vol.1000m3 of Volume Produced/hour (12 hour day) | C62: No/1000m3 | D62: =(D61*1000*31)/D9 -> 2.4321737 | E62: =(E61*1000*31)/E9 -> 2.0427094 | F62: =(F61*1000*31)/F9 -> 10.242291 | G62: =(G61*1000*31)/G9 -> 22.957294 | H62: =(H61*1000*31)/H9 -> 2.8275189
A63: Temporary Staff Employed | C63: No | D63: =Balaka!G63+Balaka!H63+Balaka!I63 -> 63 | E63: =Liwonde!G63+Liwonde!H63+Liwonde!I63 -> 57 | F63: =Machinga!G63+Machinga!H63+Machinga!I63 -> 18 | G63: =Ntaja!G63+Ntaja!H63+Ntaja!I63 -> 23 | H63: =SUM(D63:G63) -> 161
A65: Water Connections and Disconnections
A66: New Individual Water Connections | B66: Brought Forward | C66: No | D66: =Balaka!G66 -> 420 | E66: =Liwonde!G66 -> 319 | F66: =Machinga!G66 -> 12 | G66: =Ntaja!G66 -> 13 | H66: =SUM(D66:G66) -> 764
B67: Applied this Month | C67: No | D67: =Balaka!G67+Balaka!H67+Balaka!I67 -> 145 | E67: =Liwonde!G67+Liwonde!H67+Liwonde!I67 -> 131 | F67: =Machinga!G67+Machinga!H67+Machinga!I67 -> 13 | G67: =Ntaja!G67+Ntaja!H67+Ntaja!I67 -> 85 | H67: =SUM(D67:G67) -> 374
B68: Done this Month Postpaid | C68: No | D68: =Balaka!G68+Balaka!H68+Balaka!I68 -> 123 | E68: =Liwonde!G68+Liwonde!H68+Liwonde!I68 -> 98 | F68: =Machinga!G68+Machinga!H68+Machinga!I68 -> 13 | G68: =Ntaja!G68+Ntaja!H68+Ntaja!I68 -> 0 | H68: =SUM(D68:G68) -> 234
B69: Done this Month Prepaid | C69: No | D69: =Balaka!G69+Balaka!H69+Balaka!I69 -> 0 | E69: =Liwonde!G69+Liwonde!H69+Liwonde!I69 -> 0 | F69: =Machinga!G69+Machinga!H69+Machinga!I69 -> 0 | G69: =Ntaja!G69+Ntaja!H69+Ntaja!I69 -> 66 | H69: =SUM(D69:G69) -> 66
B70: Total Done | C70: No | D70: =D68+D69 -> 123 | E70: =E68+E69 -> 98 | F70: =F68+F69 -> 13 | G70: =G68+G69 -> 66 | H70: =H68+H69 -> 300
B71: Carried Forward | C71: No | D71: =D66+D67-D70 -> 442 | E71: =E66+E67-E70 -> 352 | F71: =F66+F67-F70 -> 12 | G71: =G66+G67-G70 -> 32 | H71: =H66+H67-H70 -> 838
A72: New Institutional Water Connections | B72: Brought Forward | C72: No | D72: =Balaka!G72 -> 0 | E72: =Liwonde!G72 -> 0 | F72: =Machinga!G72 -> 0 | G72: =Ntaja!G72 -> 0 | H72: =SUM(D72:G72) -> 0
B73: Applied this Month | C73: No | D73: =Balaka!G73+Balaka!H73+Balaka!I73 -> 0 | E73: =Liwonde!G73+Liwonde!H73+Liwonde!I73 -> 0 | F73: =Machinga!G73+Machinga!H73+Machinga!I73 -> 1 | G73: =Ntaja!G73+Ntaja!H73+Ntaja!I73 -> 1 | H73: =SUM(D73:G73) -> 2
B74: Done this Month Postpaid | C74: No | D74: =Balaka!G74+Balaka!H74+Balaka!I74 -> 0 | E74: =Liwonde!G74+Liwonde!H74+Liwonde!I74 -> 0 | F74: =Machinga!G74+Machinga!H74+Machinga!I74 -> 1 | G74: =Ntaja!G74+Ntaja!H74+Ntaja!I74 -> 0 | H74: =SUM(D74:G74) -> 1
B75: Done this Month Prepaid | C75: No | D75: =Balaka!G75+Balaka!H75+Balaka!I75 -> 0 | E75: =Liwonde!G75+Liwonde!H75+Liwonde!I75 -> 0 | F75: =Machinga!G75+Machinga!H75+Machinga!I75 -> 0 | G75: =Ntaja!G75+Ntaja!H75+Ntaja!I75 -> 1 | H75: =SUM(D75:G75) -> 1
B76: Total Done | C76: No | D76: =D74+D75 -> 0 | E76: =E74+E75 -> 0 | F76: =F74+F75 -> 1 | G76: =G74+G75 -> 1 | H76: =H74+H75 -> 2
B77: Carried Forward | C77: No | D77: =D73+D74-D76 -> 0 | E77: =E73+E74-E76 -> 0 | F77: =F73+F74-F76 -> 1 | G77: =G73+G74-G76 -> 0 | H77: =H73+H74-H76 -> 1
A78: New Commercial/Industrial Water Connections | B78: Brought Forward | C78: No | D78: =Balaka!G78 -> 0 | E78: =Liwonde!G78 -> 0 | F78: =Machinga!G78 -> 0 | G78: =Ntaja!G78 -> 0 | H78: =SUM(D78:G78) -> 0
B79: Applied this Month | C79: No | D79: =Balaka!G79+Balaka!H79+Balaka!I79 -> 0 | E79: =Liwonde!G79+Liwonde!H79+Liwonde!I79 -> 0 | F79: =Machinga!G79+Machinga!H79+Machinga!I79 -> 0 | G79: =Ntaja!G79+Ntaja!H79+Ntaja!I79 -> 0 | H79: =SUM(D79:G79) -> 0
B80: Done this Month Postpaid | C80: No | D80: =Balaka!G80+Balaka!H80+Balaka!I80 -> 0 | E80: =Liwonde!G80+Liwonde!H80+Liwonde!I80 -> 0 | F80: =Machinga!G80+Machinga!H80+Machinga!I80 -> 0 | G80: =Ntaja!G80+Ntaja!H80+Ntaja!I80 -> 0 | H80: =SUM(D80:G80) -> 0
B81: Done this Month Prepaid | C81: No | D81: =Balaka!G81+Balaka!H81+Balaka!I81 -> 0 | E81: =Liwonde!G81+Liwonde!H81+Liwonde!I81 -> 0 | F81: =Machinga!G81+Machinga!H81+Machinga!I81 -> 0 | G81: =Ntaja!G81+Ntaja!H81+Ntaja!I81 -> 0 | H81: =SUM(D81:G81) -> 0
B82: Total Done | C82: No | D82: =D81+D80 -> 0 | E82: =E81+E80 -> 0 | F82: =F81+F80 -> 0 | G82: =G81+G80 -> 0 | H82: =H81+H80 -> 0
B83: Carried Forward | C83: No | D83: =D78+D79-D82 -> 0 | E83: =E78+E79-E82 -> 0 | F83: =F78+F79-F82 -> 0 | G83: =G78+G79-G82 -> 0 | H83: =H78+H79-H82 -> 0
A84: New CWP | B84: Brought Forward | C84: No | D84: =Balaka!G84 -> 0 | E84: =Liwonde!G84 -> 0 | F84: =Machinga!G84 -> 0 | G84: =Ntaja!G84 -> 0 | H84: =SUM(D84:G84) -> 0
B85: Applied this Month | C85: No | D85: =Balaka!G85+Balaka!H85+Balaka!I85 -> 0 | E85: =Liwonde!G85+Liwonde!H85+Liwonde!I85 -> 0 | F85: =Machinga!G85+Machinga!H85+Machinga!I85 -> 0 | G85: =Ntaja!G85+Ntaja!H85+Ntaja!I85 -> 0 | H85: =SUM(D85:G85) -> 0
B86: Done this Month Postpaid | C86: No | D86: =Balaka!G86+Balaka!H86+Balaka!I86 -> 0 | E86: =Liwonde!G86+Liwonde!H86+Liwonde!I86 -> 0 | F86: =Machinga!G86+Machinga!H86+Machinga!I86 -> 0 | G86: =Ntaja!G86+Ntaja!H86+Ntaja!I86 -> 0 | H86: =SUM(D86:G86) -> 0
B87: Done this Month Prepaid | C87: No | D87: =Balaka!G87+Balaka!H87+Balaka!I87 -> 0 | E87: =Liwonde!G87+Liwonde!H87+Liwonde!I87 -> 0 | F87: =Machinga!G87+Machinga!H87+Machinga!I87 -> 0 | G87: =Ntaja!G87+Ntaja!H87+Ntaja!I87 -> 0 | H87: =SUM(D87:G87) -> 0
B88: Total Done | C88: No | D88: =D87+D86 -> 0 | E88: =E87+E86 -> 0 | F88: =F87+F86 -> 0 | G88: =G87+G86 -> 0
B89: Carried Forward | C89: No | D89: =D84+D85-D88 -> 0 | E89: =E84+E85-E88 -> 0 | F89: =F84+F85-F88 -> 0 | G89: =G84+G85-G88 -> 0 | H89: =H84+H85-H86-H87 -> 0
A90: Aggregated New Water connections | B90: Brought Forward | C90: No | D90: =D66+D72+D78+D84 -> 420 | E90: =E66+E72+E78+E84 -> 319 | F90: =F66+F72+F78+F84 -> 12 | G90: =G66+G72+G78+G84 -> 13 | H90: =SUM(D90:G90) -> 764
B91: Applied this Month | C91: No | D91: =D67+D73+D79+D85 -> 145 | E91: =E67+E73+E79+E85 -> 131 | F91: =F67+F73+F79+F85 -> 14 | G91: =G67+G73+G79+G85 -> 86 | H91: =SUM(D91:G91) -> 376
B92: Done this Month Postpaid | C92: No | D92: =D68+D74+D80+D86 -> 123 | E92: =E68+E74+E80+E86 -> 98 | F92: =F68+F74+F80+F86 -> 14 | G92: =G68+G74+G80+G86 -> 0 | H92: =SUM(D92:G92) -> 235
B93: Done this Month Prepaid | D93: =D69+D75+D81+D87 -> 0 | E93: =E69+E75+E81+E87 -> 0 | F93: =F69+F75+F81+F87 -> 0 | G93: =G69+G75+G81+G87 -> 67 | H93: =SUM(D93:G93) -> 67
B94: Total Done | C94: No | D94: =D93+D92 -> 123 | E94: =E93+E92 -> 98 | F94: =F93+F92 -> 14 | G94: =G93+G92 -> 67 | H94: =H93+H92 -> 302
B95: Carried Forward | C95: No | D95: =D90+D91-D94 -> 442 | E95: =E90+E91-E94 -> 352 | F95: =F90+F91-F94 -> 12 | G95: =G90+G91-G94 -> 32 | H95: =H90+H91-H94 -> 838
A97: Prepaid Metering
A98: Prepaid Meters Installed | C98: No | D98: =Balaka!G98+Balaka!H98+Balaka!I98 -> 2799 | E98: =Liwonde!G98+Liwonde!H98+Liwonde!I98 -> 2157 | F98: =Machinga!G98+Machinga!H98+Machinga!I98 -> 417 | G98: =Ntaja!G98+Ntaja!H98+Ntaja!I98 -> 61 | H98: =SUM(D98:G98) -> 5434
A100: Active and Disconnected Accounts
A101: Disconnected Individual Accounts | C101: No | D101: =Balaka!I101 -> 1946 | E101: =Liwonde!I101 -> 1329 | F101: =Machinga!I101 -> 0 | G101: =Ntaja!I101 -> 3 | H101: =SUM(D101:G101) -> 3278
A102: Disconnected institutional Accounts | C102: No | D102: =Balaka!I102 -> 36 | E102: =Liwonde!I102 -> 43 | F102: =Machinga!I102 -> 0 | G102: =Ntaja!I102 -> 1 | H102: =SUM(D102:G102) -> 80
A103: Disconnected Commercial/Industrial Accounts | C103: No | D103: =Balaka!I103 -> 98 | E103: =Liwonde!I103 -> 64 | F103: =Machinga!I103 -> 0 | G103: =Ntaja!I103 -> 0 | H103: =SUM(D103:G103) -> 162
A104: Disconnected CWP | C104: No | D104: =Balaka!I104 -> 17 | E104: =Liwonde!I104 -> 15 | F104: =Machinga!I104 -> 0 | G104: =Ntaja!I104 -> 15 | H104: =SUM(D104:G104) -> 47
A105: Total Disconnected Accounts | C105: No | D105: =SUM(D101:D104) -> 2097 | E105: =SUM(E101:E104) -> 1451 | F105: =SUM(F101:F104) -> 0 | G105: =SUM(G101:G104) -> 19 | H105: =SUM(D105:G105) -> 3567
...

Sheet Midyear Summary
A1: SOUTHERN REGION WATER BOARD
A3: MONTHLY REPORTS - 2023/2024
A4: LIWONDE ZONE
A5: LIWONDE ZONE
A7: PARAMETERS | C7: UNITS | D7: Balaka | E7: Liwonde | F7: Machinga | G7: Ntaja | H7: TOTALS
A8: PRODUCTION
A9: Volume Produced | C9: m3 | D9: =Balaka!D9+Balaka!E9+Balaka!F9+Balaka!G9+Balaka!H9+Balaka!I9 -> 363867 | E9: =Liwonde!D9+Liwonde!E9+Liwonde!F9+Liwonde!G9+Liwonde!H9+Liwonde!I9 -> 378576 | F9: =Machinga!D9+Machinga!E9+Machinga!F9+Machinga!G9+Machinga!H9+Machinga!I9 -> 19142 | G9: =Ntaja!D9+Ntaja!E9+Ntaja!F9+Ntaja!G9+Ntaja!H9+Ntaja!I9 -> 19010.01 | H9: =SUM(D9:G9) -> 780595.01
A10: REVENUE WATER - POSTPAID
A11: Volume Billed Individuals | C11: m3 | D11: =Balaka!D11+Balaka!E11+Balaka!F11+Balaka!G11+Balaka!H11+Balaka!I11 -> 159211 | E11: =Liwonde!D11+Liwonde!E11+Liwonde!F11+Liwonde!G11+Liwonde!H11+Liwonde!I11 -> 149578 | F11: =Machinga!D11+Machinga!E11+Machinga!F11+Machinga!G11+Machinga!H11+Machinga!I11 -> 7363 | G11: =Ntaja!D11+Ntaja!E11+Ntaja!F11+Ntaja!G11+Ntaja!H11+Ntaja!I11 -> 1085 | H11: =SUM(D11:G11) -> 317237
A12: Volume Billed CWPs | C12: m3 | D12: =Balaka!D12+Balaka!E12+Balaka!F12+Balaka!G12+Balaka!H12+Balaka!I12 -> 6000 | E12: =Liwonde!D12+Liwonde!E12+Liwonde!F12+Liwonde!G12+Liwonde!H12+Liwonde!I12 -> 2607 | F12: =Machinga!D12+Machinga!E12+Machinga!F12+Machinga!G12+Machinga!H12+Machinga!I12 -> 0 | G12: =Ntaja!D12+Ntaja!E12+Ntaja!F12+Ntaja!G12+Ntaja!H12+Ntaja!I12 -> 0 | H12: =SUM(D12:G12) -> 8607
A13: Volume Billed Institutions | C13: m3 | D13: =Balaka!D13+Balaka!E13+Balaka!F13+Balaka!G13+Balaka!H13+Balaka!I13 -> 4111 | E13: =Liwonde!D13+Liwonde!E13+Liwonde!F13+Liwonde!G13+Liwonde!H13+Liwonde!I13 -> 13668 | F13: =Machinga!D13+Machinga!E13+Machinga!F13+Machinga!G13+Machinga!H13+Machinga!I13 -> 1856 | G13: =Ntaja!D13+Ntaja!E13+Ntaja!F13+Ntaja!G13+Ntaja!H13+Ntaja!I13 -> 104 | H13: =SUM(D13:G13) -> 19739
A14: Volume Billed Commercial/Industrial | C14: m3 | D14: =Balaka!D14+Balaka!E14+Balaka!F14+Balaka!G14+Balaka!H14+Balaka!I14 -> 600 | E14: =Liwonde!D14+Liwonde!E14+Liwonde!F14+Liwonde!G14+Liwonde!H14+Liwonde!I14 -> 1044 | F14: =Machinga!D14+Machinga!E14+Machinga!F14+Machinga!G14+Machinga!H14+Machinga!I14 -> 0 | G14: =Ntaja!D14+Ntaja!E14+Ntaja!F14+Ntaja!G14+Ntaja!H14+Ntaja!I14 -> 2 | H14: =SUM(D14:G14) -> 1646
A15: Total Volume Billed Post Paid | C15: m3 | D15: =SUM(D11:D14) -> 169922 | E15: =SUM(E11:E14) -> 166897 | F15: =SUM(F11:F14) -> 9219 | G15: =SUM(G11:G14) -> 1191 | H15: =SUM(H11:H14) -> 347229
A16: REVENUE WATER - PREPAID
A17: Individuals | C17: m3 | D17: =Balaka!D17+Balaka!E17+Balaka!F17+Balaka!G17+Balaka!H17+Balaka!I17 -> 42147 | E17: =Liwonde!D17+Liwonde!E17+Liwonde!F17+Liwonde!G17+Liwonde!H17+Liwonde!I17 -> 59194.4 | F17: =Machinga!D17+Machinga!E17+Machinga!F17+Machinga!G17+Machinga!H17+Machinga!I17 -> 7347.8 | G17: =Ntaja!D17+Ntaja!E17+Ntaja!F17+Ntaja!G17+Ntaja!H17+Ntaja!I17 -> 9774.9 | H17: =SUM(D17:G17) -> 118464.1
A18: CWPs | C18: m3 | D18: =Balaka!D18+Balaka!E18+Balaka!F18+Balaka!G18+Balaka!H18+Balaka!I18 -> 0 | E18: =Liwonde!D18+Liwonde!E18+Liwonde!F18+Liwonde!G18+Liwonde!H18+Liwonde!I18 -> 0 | F18: =Machinga!D18+Machinga!E18+Machinga!F18+Machinga!G18+Machinga!H18+Machinga!I18 -> 0 | G18: =Ntaja!D18+Ntaja!E18+Ntaja!F18+Ntaja!G18+Ntaja!H18+Ntaja!I18 -> 324 | H18: =SUM(D18:G18) -> 324
A19: Institutions | C19: m3 | D19: =Balaka!D19+Balaka!E19+Balaka!F19+Balaka!G19+Balaka!H19+Balaka!I19 -> 1374 | E19: =Liwonde!D19+Liwonde!E19+Liwonde!F19+Liwonde!G19+Liwonde!H19+Liwonde!I19 -> 0 | F19: =Machinga!D19+Machinga!E19+Machinga!F19+Machinga!G19+Machinga!H19+Machinga!I19 -> 0 | G19: =Ntaja!D19+Ntaja!E19+Ntaja!F19+Ntaja!G19+Ntaja!H19+Ntaja!I19 -> 338 | H19: =SUM(D19:G19) -> 1712
A20: Commercial/Industrial | C20: m3 | D20: =Balaka!D20+Balaka!E20+Balaka!F20+Balaka!G20+Balaka!H20+Balaka!I20 -> 551 | E20: =Liwonde!D20+Liwonde!E20+Liwonde!F20+Liwonde!G20+Liwonde!H20+Liwonde!I20 -> 0 | F20: =Machinga!D20+Machinga!E20+Machinga!F20+Machinga!G20+Machinga!H20+Machinga!I20 -> 0 | G20: =Ntaja!D20+Ntaja!E20+Ntaja!F20+Ntaja!G20+Ntaja!H20+Ntaja!I20 -> 450 | H20: =SUM(D20:G20) -> 1001
A21: Total Volume Prepaid | C21: m3 | D21: =SUM(D17:D20) -> 44072 | E21: =SUM(E17:E20) -> 59194.4 | F21: =SUM(F17:F20) -> 7347.8 | G21: =SUM(G17:G20) -> 10886.9 | H21: =SUM(H17:H20) -> 121501.1
A22: TOTAL REVENUE WATER | C22: m3 | D22: =D21+D15 -> 213994 | E22: =E21+E15 -> 226091.4 | F22: =F21+F15 -> 16566.8 | G22: =G21+G15 -> 12077.9 | H22: =H21+H15 -> 468730.1
A23: NON-REVENUE WATER (NRW)
A24: Non-Revenue Water (NRW) | B24: Volume | C24: m3 | D24: =D9-D22 -> 149873 | E24: =E9-E22 -> 152484.6 | F24: =F9-F22 -> 2575.2 | G24: =G9-G22 -> 6932.11 | H24: =SUM(D24:G24) -> 311864.91
B25: Percentage | C25: % | D25: =D24/D9 -> 0.41188951 | E25: =E24/E9 -> 0.40278465 | F25: =F24/F9 -> 0.1345314 | G25: =G24/G9 -> 0.36465578 | H25: =H24/H9 -> 0.39952204
A26: OPERATING EXPENSES
A27: Chemicals
A28: Chemical | B28: Rate(MK/kg)
A29: Chlorine | B29: =176264.5/50 -> 3525.29 | C29: kg | D29: =Balaka!D29+Balaka!E29+Balaka!F29+Balaka!G29+Balaka!H29+Balaka!I29 -> 660 | E29: =Liwonde!D29+Liwonde!E29+Liwonde!F29+Liwonde!G29+Liwonde!H29+Liwonde!I29 -> 1883 | F29: =Machinga!D29+Machinga!E29+Machinga!F29+Machinga!G29+Machinga!H29+Machinga!I29 -> 63 | G29: =Ntaja!D29+Ntaja!E29+Ntaja!F29+Ntaja!G29+Ntaja!H29+Ntaja!I29 -> 44 | H29: =SUM(D29:G29) -> 2650
C30: kg/mg litre | D30: =D29/(D9/1000) -> 1.8138496 | E30: =E29/(E9/1000) -> 4.9739022 | F30: =F29/(F9/1000) -> 3.2911921 | G30: =G29/(G9/1000) -> 2.3145701 | H30: =H29/(H9/1000) -> 3.3948462
A31: Aluminium sulphate | B31: =53000.511/50 -> 1060.0102 | C31: kg | D31: =Balaka!D31+Balaka!E31+Balaka!F31+Balaka!G31+Balaka!H31+Balaka!I31 -> 0 | E31: =Liwonde!D31+Liwonde!E31+Liwonde!F31+Liwonde!G31+Liwonde!H31+Liwonde!I31 -> 0 | F31: =Machinga!D31+Machinga!E31+Machinga!F31+Machinga!G31+Machinga!H31+Machinga!I31 -> 0 | G31: =Ntaja!D31+Ntaja!E31+Ntaja!F31+Ntaja!G31+Ntaja!H31+Ntaja!I31 -> 0 | H31: =SUM(D31:G31) -> 0
C32: kg/mg litre | D32: =D31/(D9/1000) -> 0 | E32: =E31/(E9/1000) -> 0 | F32: =F31/(F9/1000) -> 0 | G32: =G31/(G9/1000) -> 0 | H32: =H31/(H9/1000) -> 0
A33: Soda | B33: =61414.43/50 -> 1228.2886 | C33: kg | D33: =Balaka!D33+Balaka!E33+Balaka!F33+Balaka!G33+Balaka!H33+Balaka!I33 -> 0 | E33: =Liwonde!D33+Liwonde!E33+Liwonde!F33+Liwonde!G33+Liwonde!H33+Liwonde!I33 -> 0 | F33: =Machinga!D33+Machinga!E33+Machinga!F33+Machinga!G33+Machinga!H33+Machinga!I33 -> 0 | G33: =Ntaja!D33+Ntaja!E33+Ntaja!F33+Ntaja!G33+Ntaja!H33+Ntaja!I33 -> 0 | H33: =SUM(D33:G33) -> 0
C34: kg/mg litre | D34: =D33/(D9/1000) -> 0 | E34: =E33/(E9/1000) -> 0 | F34: =F33/(F9/1000) -> 0 | G34: =G33/(G9/1000) -> 0 | H34: =H33/(H9/1000) -> 0
A35: Algae floc | B35: =745345.16/200 -> 3726.7258 | C35: litres | D35: =Balaka!D35+Balaka!E35+Balaka!F35+Balaka!G35+Balaka!H35+Balaka!I35 -> 0 | E35: =Liwonde!D35+Liwonde!E35+Liwonde!F35+Liwonde!G35+Liwonde!H35+Liwonde!I35 -> 1067 | F35: =Machinga!D35+Machinga!E35+Machinga!F35+Machinga!G35+Machinga!H35+Machinga!I35 -> 0 | G35: =Ntaja!D35+Ntaja!E35+Ntaja!F35+Ntaja!G35+Ntaja!H35+Ntaja!I35 -> 0 | H35: =SUM(D35:G35) -> 1067
C36: litres/mg litre | H36: =SUM(D36:G36) -> 0
A37: Sud floc | B37: =790318.72/200 -> 3951.5936 | C37: litres | D37: =Balaka!D37+Balaka!E37+Balaka!F37+Balaka!G37+Balaka!H37+Balaka!I37 -> 0 | E37: =Liwonde!D37+Liwonde!E37+Liwonde!F37+Liwonde!G37+Liwonde!H37+Liwonde!I37 -> 0 | F37: =Machinga!D37+Machinga!E37+Machinga!F37+Machinga!G37+Machinga!H37+Machinga!I37 -> 0 | G37: =Ntaja!D37+Ntaja!E37+Ntaja!F37+Ntaja!G37+Ntaja!H37+Ntaja!I37 -> 0 | H37: =SUM(D37:G37) -> 0
C38: litres/mg litre | D38: =D37/(D9/1000) -> 0 | E38: =E37/(E9/1000) -> 0 | F38: =F37/(F9/1000) -> 0 | G38: =G37/(G9/1000) -> 0 | H38: =H37/(H9/1000) -> 0
A39: Potasium permanganate | B39: 1950 | C39: kg | D39: =Balaka!D39+Balaka!E39+Balaka!F39+Balaka!G39+Balaka!H39+Balaka!I39 -> 0 | E39: =Liwonde!D39+Liwonde!E39+Liwonde!F39+Liwonde!G39+Liwonde!H39+Liwonde!I39 -> 0 | F39: =Machinga!D39+Machinga!E39+Machinga!F39+Machinga!G39+Machinga!H39+Machinga!I39 -> 0 | G39: =Ntaja!D39+Ntaja!E39+Ntaja!F39+Ntaja!G39+Ntaja!H39+Ntaja!I39 -> 0 | H39: =SUM(D39:G39) -> 0
C40: kg/mg litre | D40: =D39/(D9/1000) -> 0 | E40: =E39/(E9/1000) -> 0 | F40: =F39/(F9/1000) -> 0 | G40: =G39/(G9/1000) -> 0 | H40: =H39/(H9/1000) -> 0
A41: Cost of Chemicals | C41: Mk | D41: =(D29*$B29)+(D31*$B31)+(D33*$B33)+(D35*$B35)+(D37*$B37)+(D39*$B39) -> 2326691.4 | E41: =(E29*$B29)+(E31*$B31)+(E33*$B33)+(E35*$B35)+(E37*$B37)+(E39*$B39) -> 10614537 | F41: =(F29*$B29)+(F31*$B31)+(F33*$B33)+(F35*$B35)+(F37*$B37)+(F39*$B39) -> 222093.27 | G41: =(G29*$B29)+(G31*$B31)+(G33*$B33)+(G35*$B35)+(G37*$B37)+(G39*$B39) -> 155112.76 | H41: =SUM(D41:G41) -> 13318435
A42: Cost/vol. Produced (chemicals) | C42: Mk/m3 | D42: =D41/D9 -> 6.3943457 | E42: =E41/E9 -> 28.038062 | F42: =F41/F9 -> 11.602407 | G42: =G41/G9 -> 8.1595307 | H42: =H41/H9 -> 17.061901
A43: Power
A44: Power Usage | C44: Kw | D44: =Balaka!D44+Balaka!E44+Balaka!F44+Balaka!G44+Balaka!H44+Balaka!I44 -> 249005 | E44: =Liwonde!D44+Liwonde!E44+Liwonde!F44+Liwonde!G44+Liwonde!H44+Liwonde!I44 -> 415709.55 | F44: =Machinga!D44+Machinga!E44+Machinga!F44+Machinga!G44+Machinga!H44+Machinga!I44 -> 2589 | G44: =Ntaja!D44+Ntaja!E44+Ntaja!F44+Ntaja!G44+Ntaja!H44+Ntaja!I44 -> 22224.05 | H44: =SUM(D44:G44) -> 689527.6
A45: Power/ Vol. Produced | C45: Kw/m3 | D45: =D44/D9 -> 0.68432971 | E45: =E44/E9 -> 1.0980874 | F45: =F44/F9 -> 0.13525232 | G45: =G44/G9 -> 1.1690709 | H45: =H44/H9 -> 0.88333591
A46: Cost of Power | C46: Mk | D46: =Balaka!D46+Balaka!E46+Balaka!F46+Balaka!G46+Balaka!H46+Balaka!I46 -> 37233832 | E46: =Liwonde!D46+Liwonde!E46+Liwonde!F46+Liwonde!G46+Liwonde!H46+Liwonde!I46 -> 61626298 | F46: =Machinga!D46+Machinga!E46+Machinga!F46+Machinga!G46+Machinga!H46+Machinga!I46 -> 494766.53 | G46: =Ntaja!D46+Ntaja!E46+Ntaja!F46+Ntaja!G46+Ntaja!H46+Ntaja!I46 -> 3396793.2 | H46: =SUM(D46:G46) -> 1.0275169e+08
A47: Cost/vol. Produced | C47: Mk/m3 | D47: =D46/D9 -> 102.32814 | E47: =E46/E9 -> 162.78448 | F47: =F46/F9 -> 25.84717 | G47: =G46/G9 -> 178.68445 | H47: =H46/H9 -> 131.63252
A48: Plant and Vehicle Maintenance
A49: Distances covered | C49: km | D49: =Balaka!D49+Balaka!E49+Balaka!F49+Balaka!G49+Balaka!H49+Balaka!I49 -> 14625 | E49: =Liwonde!D49+Liwonde!E49+Liwonde!F49+Liwonde!G49+Liwonde!H49+Liwonde!I49 -> 15946 | F49: =Machinga!D49+Machinga!E49+Machinga!F49+Machinga!G49+Machinga!H49+Machinga!I49 -> 0 | G49: =Ntaja!D49+Ntaja!E49+Ntaja!F49+Ntaja!G49+Ntaja!H49+Ntaja!I49 -> 0 | H49: =SUM(D49:G49) -> 30571
A50: Fuel Used (litres) | C50: litres | D50: =Balaka!D50+Balaka!E50+Balaka!F50+Balaka!G50+Balaka!H50+Balaka!I50 -> 1453 | E50: =Liwonde!D50+Liwonde!E50+Liwonde!F50+Liwonde!G50+Liwonde!H50+Liwonde!I50 -> 1422.86 | F50: =Machinga!D50+Machinga!E50+Machinga!F50+Machinga!G50+Machinga!H50+Machinga!I50 -> 0 | G50: =Ntaja!D50+Ntaja!E50+Ntaja!F50+Ntaja!G50+Ntaja!H50+Ntaja!I50 -> 15 | H50: =SUM(D50:G50) -> 2890.86
A51: Cost of fuel | C51: Mk | D51: =Balaka!D51+Balaka!E51+Balaka!F51+Balaka!G51+Balaka!H51+Balaka!I51 -> 2912650 | E51: =Liwonde!D51+Liwonde!E51+Liwonde!F51+Liwonde!G51+Liwonde!H51+Liwonde!I51 -> 2731891.2 | F51: =Machinga!D51+Machinga!E51+Machinga!F51+Machinga!G51+Machinga!H51+Machinga!I51 -> 0 | G51: =Ntaja!D51+Ntaja!E51+Ntaja!F51+Ntaja!G51+Ntaja!H51+Ntaja!I51 -> 26190 | H51: =SUM(D51:G51) -> 5670731.2
A52: Maintenance | C52: Mk | D52: =Balaka!D52+Balaka!E52+Balaka!F52+Balaka!G52+Balaka!H52+Balaka!I52 -> 0 | E52: =Balaka!E52+Balaka!F52+Balaka!G52+Balaka!H52+Balaka!I52+Balaka!J52 -> 0 | F52: =Balaka!F52+Balaka!G52+Balaka!H52+Balaka!I52+Balaka!J52+Balaka!K52 -> 0 | G52: =Balaka!G52+Balaka!H52+Balaka!I52+Balaka!J52+Balaka!K52+Balaka!L52 -> 0 | H52: =SUM(D52:G52) -> 0
A53: Salaries and Wages
A54: Staff Costs | C54: MK | D54: =Balaka!D54+Balaka!E54+Balaka!F54+Balaka!G54+Balaka!H54+Balaka!I54 -> 35797958 | E54: =Liwonde!D54+Liwonde!E54+Liwonde!F54+Liwonde!G54+Liwonde!H54+Liwonde!I54 -> 52668798 | F54: =Machinga!D54+Machinga!E54+Machinga!F54+Machinga!G54+Machinga!H54+Machinga!I54 -> 7044366.1 | G54: =Ntaja!D54+Ntaja!E54+Ntaja!F54+Ntaja!G54+Ntaja!H54+Ntaja!I54 -> 8766688.5 | H54: =SUM(D54:G54) -> 1.0427781e+08
A55: Wages | C55: MK | D55: =Balaka!D55+Balaka!E55+Balaka!F55+Balaka!G55+Balaka!H55+Balaka!I55 -> 8058777.2 | E55: =Liwonde!D55+Liwonde!E55+Liwonde!F55+Liwonde!G55+Liwonde!H55+Liwonde!I55 -> 21152496 | F55: =Machinga!D55+Machinga!E55+Machinga!F55+Machinga!G55+Machinga!H55+Machinga!I55 -> 4200389.6 | G55: =Ntaja!D55+Ntaja!E55+Ntaja!F55+Ntaja!G55+Ntaja!H55+Ntaja!I55 -> 2054250.2 | H55: =SUM(D55:G55) -> 35465913
A56: Other Overhead Costs | C56: MK | D56: =Balaka!D56+Balaka!E56+Balaka!F56+Balaka!G56+Balaka!H56+Balaka!I56 -> 24451673 | E56: =Liwonde!D56+Liwonde!E56+Liwonde!F56+Liwonde!G56+Liwonde!H56+Liwonde!I56 -> 11586937 | F56: =Machinga!D56+Machinga!E56+Machinga!F56+Machinga!G56+Machinga!H56+Machinga!I56 -> 4746500 | G56: =Ntaja!D56+Ntaja!E56+Ntaja!F56+Ntaja!G56+Ntaja!H56+Ntaja!I56 -> 1549686.8 | H56: =SUM(D56:G56) -> 42334797
A57: Operating Costs
A58: Total Operating Costs | C58: MK | D58: =D41+D46+D51+D52+D54+D55+D56 -> 1.1078158e+08 | E58: =E41+E46+E51+E52+E54+E55+E56 -> 1.6038096e+08 | F58: =F41+F46+F51+F52+F54+F55+F56 -> 16708116 | G58: =G41+G46+G51+G52+G54+G55+G56 -> 15948722 | H58: =SUM(D58:G58) -> 3.0381938e+08
A59: Cost/Vol. Produced | C59: Mk/m3 | D59: =D58/D9 -> 304.45625 | E59: =E58/E9 -> 423.6427 | F59: =F58/F9 -> 872.85109 | G59: =G58/G9 -> 838.9644 | H59: =H58/H9 -> 389.21512
A60: Cost/Vol. Billed | C60: Mk/m3 | D60: =D58/D22 -> 517.68546 | E60: =E58/E22 -> 709.36337 | F60: =F58/F22 -> 1008.53 | G60: =G58/G22 -> 1320.488 | H60: =H58/H22 -> 648.17552
A61: Permanent Staff Employed | C61: No | D61: =Balaka!I61 -> 15 | E61: =Liwonde!I61 -> 13 | F61: =Machinga!I61 -> 3 | G61: =Ntaja!I61 -> 6 | H61: =SUM(D61:G61) -> 37
A62: Staff/Vol.1000m3 of Volume Produced/hour (12 hour day) | C62: No/1000m3 | D62: =(D61*1000*31)/D9 -> 1.2779395 | E62: =(E61*1000*31)/E9 -> 1.0645154 | F62: =(F61*1000*31)/F9 -> 4.8584265 | G62: =(G61*1000*31)/G9 -> 9.7843189 | H62: =(H61*1000*31)/H9 -> 1.4693919
A63: Temporary Staff Employed | C63: No | D63: =Balaka!I63 -> 21 | E63: =Liwonde!I63 -> 19 | F63: =Machinga!I63 -> 6 | G63: =Ntaja!I63 -> 6 | H63: =SUM(D63:G63) -> 52
A65: Water Connections and Disconnections
A66: New Individual Water Connections | B66: Brought Forward | C66: No | D66: =Balaka!D66 -> 435 | E66: =Liwonde!D66 -> 288 | F66: =Machinga!D66 -> 22 | G66: =Ntaja!D66 -> 2 | H66: =SUM(D66:G66) -> 747
B67: Applied this Month | C67: No | D67: =Balaka!D67+Balaka!E67+Balaka!F67+Balaka!G67+Balaka!H67+Balaka!I67 -> 218 | E67: =Liwonde!D67+Liwonde!E67+Liwonde!F67+Liwonde!G67+Liwonde!H67+Liwonde!I67 -> 243 | F67: =Machinga!D67+Machinga!E67+Machinga!F67+Machinga!G67+Machinga!H67+Machinga!I67 -> 40 | G67: =Ntaja!D67+Ntaja!E67+Ntaja!F67+Ntaja!G67+Ntaja!H67+Ntaja!I67 -> 122 | H67: =SUM(D67:G67) -> 623
B68: Done this Month Postpaid | C68: No | D68: =Balaka!D68+Balaka!E68+Balaka!F68+Balaka!G68+Balaka!H68+Balaka!I68 -> 211 | E68: =Liwonde!D68+Liwonde!E68+Liwonde!F68+Liwonde!G68+Liwonde!H68+Liwonde!I68 -> 156 | F68: =Machinga!D68+Machinga!E68+Machinga!F68+Machinga!G68+Machinga!H68+Machinga!I68 -> 19 | G68: =Ntaja!D68+Ntaja!E68+Ntaja!F68+Ntaja!G68+Ntaja!H68+Ntaja!I68 -> 0 | H68: =SUM(D68:G68) -> 386
B69: Done this Month Prepaid | C69: No | D69: =Balaka!D69+Balaka!E69+Balaka!F69+Balaka!G69+Balaka!H69+Balaka!I69 -> 0 | E69: =Liwonde!D69+Liwonde!E69+Liwonde!F69+Liwonde!G69+Liwonde!H69+Liwonde!I69 -> 23 | F69: =Machinga!D69+Machinga!E69+Machinga!F69+Machinga!G69+Machinga!H69+Machinga!I69 -> 31 | G69: =Ntaja!D69+Ntaja!E69+Ntaja!F69+Ntaja!G69+Ntaja!H69+Ntaja!I69 -> 92 | H69: =SUM(D69:G69) -> 146
B70: Total Done | C70: No | D70: =D68+D69 -> 211 | E70: =E68+E69 -> 179 | F70: =F68+F69 -> 50 | G70: =G68+G69 -> 92 | H70: =H68+H69 -> 532
B71: Carried Forward | C71: No | D71: =D66+D67-D70 -> 442 | E71: =E66+E67-E70 -> 352 | F71: =F66+F67-F70 -> 12 | G71: =G66+G67-G70 -> 32 | H71: =H66+H67-H70 -> 838
A72: New Institutional Water Connections | B72: Brought Forward | C72: No | D72: =Balaka!D72 -> 0 | E72: =Liwonde!D72 -> 0 | F72: =Machinga!D72 -> 0 | G72: =Ntaja!D72 -> 0 | H72: =SUM(D72:G72) -> 0
B73: Applied this Month | C73: No | D73: =Balaka!D73+Balaka!E73+Balaka!F73+Balaka!G73+Balaka!H73+Balaka!I73 -> 0 | E73: =Liwonde!D73+Liwonde!E73+Liwonde!F73+Liwonde!G73+Liwonde!H73+Liwonde!I73 -> 0 | F73: =Machinga!D73+Machinga!E73+Machinga!F73+Machinga!G73+Machinga!H73+Machinga!I73 -> 1 | G73: =Ntaja!D73+Ntaja!E73+Ntaja!F73+Ntaja!G73+Ntaja!H73+Ntaja!I73 -> 1 | H73: =SUM(D73:G73) -> 2
B74: Done this Month Postpaid | C74: No | D74: =Balaka!D74+Balaka!E74+Balaka!F74+Balaka!G74+Balaka!H74+Balaka!I74 -> 0 | E74: =Liwonde!D74+Liwonde!E74+Liwonde!F74+Liwonde!G74+Liwonde!H74+Liwonde!I74 -> 0 | F74: =Machinga!D74+Machinga!E74+Machinga!F74+Machinga!G74+Machinga!H74+Machinga!I74 -> 1 | G74: =Ntaja!D74+Ntaja!E74+Ntaja!F74+Ntaja!G74+Ntaja!H74+Ntaja!I74 -> 0 | H74: =SUM(D74:G74) -> 1
B75: Done this Month Prepaid | C75: No | D75: =Balaka!D75+Balaka!E75+Balaka!F75+Balaka!G75+Balaka!H75+Balaka!I75 -> 0 | E75: =Liwonde!D75+Liwonde!E75+Liwonde!F75+Liwonde!G75+Liwonde!H75+Liwonde!I75 -> 0 | F75: =Machinga!D75+Machinga!E75+Machinga!F75+Machinga!G75+Machinga!H75+Machinga!I75 -> 0 | G75: =Ntaja!D75+Ntaja!E75+Ntaja!F75+Ntaja!G75+Ntaja!H75+Ntaja!I75 -> 1
B76: Total Done | C76: No | D76: =D74+D75 -> 0 | E76: =E74+E75 -> 0 | F76: =F74+F75 -> 1 | G76: =G74+G75 -> 1 | H76: =H74+H75 -> 1
B77: Carried Forward | C77: No | D77: =D73+D74-D76 -> 0 | E77: =E73+E74-E76 -> 0 | F77: =F73+F74-F76 -> 1 | G77: =G73+G74-G76 -> 0 | H77: =H73+H74-H76 -> 2
A78: New Commercial/Industrial Water Connections | B78: Brought Forward | C78: No | D78: =Balaka!D78 -> 0 | E78: =Liwonde!D78 -> 0 | F78: =Machinga!D78 -> 0 | G78: =Ntaja!D78 -> 0 | H78: =SUM(D78:G78) -> 0
B79: Applied this Month | C79: No | D79: =Balaka!D79+Balaka!E79+Balaka!F79+Balaka!G79+Balaka!H79+Balaka!I79 -> 0 | E79: =Liwonde!D79+Liwonde!E79+Liwonde!F79+Liwonde!G79+Liwonde!H79+Liwonde!I79 -> 0 | F79: =Machinga!D79+Machinga!E79+Machinga!F79+Machinga!G79+Machinga!H79+Machinga!I79 -> 0 | G79: =Ntaja!D79+Ntaja!E79+Ntaja!F79+Ntaja!G79+Ntaja!H79+Ntaja!I79 -> 0 | H79: =SUM(D79:G79) -> 0
B80: Done this Month Postpaid | C80: No | D80: =Balaka!D80+Balaka!E80+Balaka!F80+Balaka!G80+Balaka!H80+Balaka!I80 -> 0 | E80: =Liwonde!D80+Liwonde!E80+Liwonde!F80+Liwonde!G80+Liwonde!H80+Liwonde!I80 -> 0 | F80: =Machinga!D80+Machinga!E80+Machinga!F80+Machinga!G80+Machinga!H80+Machinga!I80 -> 0 | G80: =Ntaja!D80+Ntaja!E80+Ntaja!F80+Ntaja!G80+Ntaja!H80+Ntaja!I80 -> 0
B81: Done this Month Prepaid | C81: No | D81: =Balaka!D81+Balaka!E81+Balaka!F81+Balaka!G81+Balaka!H81+Balaka!I81 -> 0 | E81: =Liwonde!D81+Liwonde!E81+Liwonde!F81+Liwonde!G81+Liwonde!H81+Liwonde!I81 -> 0 | F81: =Machinga!D81+Machinga!E81+Machinga!F81+Machinga!G81+Machinga!H81+Machinga!I81 -> 0 | G81: =Ntaja!D81+Ntaja!E81+Ntaja!F81+Ntaja!G81+Ntaja!H81+Ntaja!I81 -> 0 | H81: =SUM(D81:G81) -> 0
B82: Total Done | C82: No | D82: =D81+D80 -> 0 | E82: =E81+E80 -> 0 | F82: =F81+F80 -> 0 | G82: =G81+G80 -> 0 | H82: =H81+H80 -> 0
B83: Carried Forward | C83: No | D83: =D78+D79-D82 -> 0 | E83: =E78+E79-E82 -> 0 | F83: =F78+F79-F82 -> 0 | G83: =G78+G79-G82 -> 0 | H83: =H78+H79-H82 -> 0
A84: New CWP | B84: Brought Forward | C84: No | D84: =Balaka!D84 -> 0 | E84: =Liwonde!D84 -> 0 | F84: =Machinga!D84 -> 0 | G84: =Ntaja!D84 -> 0 | H84: =SUM(D84:G84) -> 0
B85: Applied this Month | C85: No | D85: =Balaka!D85+Balaka!E85+Balaka!F85+Balaka!G85+Balaka!H85+Balaka!I85 -> 0 | E85: =Liwonde!D85+Liwonde!E85+Liwonde!F85+Liwonde!G85+Liwonde!H85+Liwonde!I85 -> 0 | F85: =Machinga!D85+Machinga!E85+Machinga!F85+Machinga!G85+Machinga!H85+Machinga!I85 -> 0 | G85: =Ntaja!D85+Ntaja!E85+Ntaja!F85+Ntaja!G85+Ntaja!H85+Ntaja!I85 -> 0 | H85: =SUM(D85:G85) -> 0
B86: Done this Month Postpaid | C86: No | D86: =Balaka!D86+Balaka!E86+Balaka!F86+Balaka!G86+Balaka!H86+Balaka!I86 -> 0 | E86: =Liwonde!D86+Liwonde!E86+Liwonde!F86+Liwonde!G86+Liwonde!H86+Liwonde!I86 -> 0 | F86: =Machinga!D86+Machinga!E86+Machinga!F86+Machinga!G86+Machinga!H86+Machinga!I86 -> 0 | G86: =Ntaja!D86+Ntaja!E86+Ntaja!F86+Ntaja!G86+Ntaja!H86+Ntaja!I86 -> 0
B87: Done this Month Prepaid | C87: No | D87: =Balaka!D87+Balaka!E87+Balaka!F87+Balaka!G87+Balaka!H87+Balaka!I87 -> 0 | E87: =Liwonde!D87+Liwonde!E87+Liwonde!F87+Liwonde!G87+Liwonde!H87+Liwonde!I87 -> 0 | F87: =Machinga!D87+Machinga!E87+Machinga!F87+Machinga!G87+Machinga!H87+Machinga!I87 -> 0 | G87: =Ntaja!D87+Ntaja!E87+Ntaja!F87+Ntaja!G87+Ntaja!H87+Ntaja!I87 -> 0 | H87: =SUM(D87:G87) -> 0
B88: Total Done | C88: No | D88: =D87+D86 -> 0 | E88: =E87+E86 -> 0 | F88: =F87+F86 -> 0 | G88: =G87+G86 -> 0
B89: Carried Forward | C89: No | D89: =D84+D85-D88 -> 0 | E89: =E84+E85-E88 -> 0 | F89: =F84+F85-F88 -> 0 | G89: =G84+G85-G88 -> 0 | H89: =H84+H85-H86-H87 -> 0
A90: Aggregated New Water connections | B90: Brought Forward | C90: No | D90: =D66+D72+D78+D84 -> 435 | E90: =E66+E72+E78+E84 -> 288 | F90: =F66+F72+F78+F84 -> 22 | G90: =G66+G72+G78+G84 -> 2 | H90: =SUM(D90:G90) -> 747
B91: Applied this Month | C91: No | D91: =D67+D73+D79+D85 -> 218 | E91: =E67+E73+E79+E85 -> 243 | F91: =F67+F73+F79+F85 -> 41 | G91: =G67+G73+G79+G85 -> 123 | H91: =SUM(D91:G91) -> 625
B92: Done this Month Postpaid | C92: No | D92: =D68+D74+D80+D86 -> 211 | E92: =E68+E74+E80+E86 -> 156 | F92: =F68+F74+F80+F86 -> 20 | G92: =G68+G74+G80+G86 -> 0 | H92: =SUM(D92:G92) -> 387
B93: Done this Month Prepaid | D93: =D69+D75+D81+D87 -> 0 | E93: =E69+E75+E81+E87 -> 23 | F93: =F69+F75+F81+F87 -> 31 | G93: =G69+G75+G81+G87 -> 93 | H93: =SUM(D93:G93) -> 147
B94: Total Done | C94: No | D94: =D93+D92 -> 211 | E94: =E93+E92 -> 179 | F94: =F93+F92 -> 51 | G94: =G93+G92 -> 93 | H94: =H93+H92 -> 534
B95: Carried Forward | C95: No | D95: =D90+D91-D94 -> 442 | E95: =E90+E91-E94 -> 352 | F95: =F90+F91-F94 -> 12 | G95: =G90+G91-G94 -> 32 | H95: =H90+H91-H94 -> 838
A97: Prepaid Metering
A98: Prepaid Meters Installed | C98: No | D98: =Balaka!D98+Balaka!E98+Balaka!F98+Balaka!G98+Balaka!H98+Balaka!I98 -> 5598 | E98: =Liwonde!D98+Liwonde!E98+Liwonde!F98+Liwonde!G98+Liwonde!H98+Liwonde!I98 -> 4291 | F98: =Machinga!D98+Machinga!E98+Machinga!F98+Machinga!G98+Machinga!H98+Machinga!I98 -> 787 | G98: =Ntaja!D98+Ntaja!E98+Ntaja!F98+Ntaja!G98+Ntaja!H98+Ntaja!I98 -> 253 | H98: =SUM(D98:G98) -> 10929
A100: Active and Disconnected Accounts
A101: Disconnected Individual Accounts | C101: No | D101: =Balaka!I101 -> 1946 | E101: =Liwonde!I101 -> 1329 | F101: =Machinga!I101 -> 0 | G101: =Ntaja!I101 -> 3 | H101: =SUM(D101:G101) -> 3278
A102: Disconnected institutional Accounts | C102: No | D102: =Balaka!I102 -> 36 | E102: =Liwonde!I102 -> 43 | F102: =Machinga!I102 -> 0 | G102: =Ntaja!I102 -> 1 | H102: =SUM(D102:G102) -> 80
A103: Disconnected Commercial/Industrial Accounts | C103: No | D103: =Balaka!I103 -> 98 | E103: =Liwonde!I103 -> 64 | F103: =Machinga!I103 -> 0 | G103: =Ntaja!I103 -> 0 | H103: =SUM(D103:G103) -> 162
A104: Disconnected CWP | C104: No | D104: =Balaka!I104 -> 17 | E104: =Liwonde!I104 -> 15 | F104: =Machinga!I104 -> 0 | G104: =Ntaja!I104 -> 15 | H104: =SUM(D104:G104) -> 47
A105: Total Disconnected Accounts | C105: No | D105: =SUM(D101:D104) -> 2097 | E105: =SUM(E101:E104) -> 1451 | F105: =SUM(F101:F104) -> 0 | G105: =SUM(G101:G104) -> 19 | H105: =SUM(H101:H104) -> 3567
...

Sheet 3rd QTR
A1: SOUTHERN REGION WATER BOARD
A3: MONTHLY REPORTS - 2023/2024
A4: LIWONDE ZONE
A5: LIWONDE ZONE
A7: PARAMETERS | C7: UNITS | D7: Balaka | E7: Liwonde | F7: Machinga | G7: Ntaja | H7: TOTALS
A8: PRODUCTION
A9: Volume Produced | C9: m3 | D9: =Balaka!J9+Balaka!K9+Balaka!L9 -> 209117 | E9: =Liwonde!J9+Liwonde!K9+Liwonde!L9 -> 218239.7 | F9: =Machinga!J9+Machinga!K9+Machinga!L9 -> 9334 | G9: =Ntaja!J9+Ntaja!K9+Ntaja!L9 -> 8971 | H9: =SUM(D9:G9) -> 445661.7
A10: REVENUE WATER - POSTPAID
A11: Volume Billed Individuals | C11: m3 | D11: =Balaka!J11+Balaka!K11+Balaka!L11 -> 102329 | E11: =Liwonde!J11+Liwonde!K11+Liwonde!L11 -> 88098 | F11: =Machinga!J11+Machinga!K11+Machinga!L11 -> 3409 | G11: =Ntaja!J11+Ntaja!K11+Ntaja!L11 -> 205 | H11: =SUM(D11:G11) -> 194041
A12: Volume Billed CWPs | C12: m3 | D12: =Balaka!J12+Balaka!K12+Balaka!L12 -> 3765 | E12: =Liwonde!J12+Liwonde!K12+Liwonde!L12 -> 1528 | F12: =Machinga!J12+Machinga!K12+Machinga!L12 -> 0 | G12: =Ntaja!J12+Ntaja!K12+Ntaja!L12 -> 0 | H12: =SUM(D12:G12) -> 5293
A13: Volume Billed Institutions | C13: m3 | D13: =Balaka!J13+Balaka!K13+Balaka!L13 -> 791 | E13: =Liwonde!J13+Liwonde!K13+Liwonde!L13 -> 7766 | F13: =Machinga!J13+Machinga!K13+Machinga!L13 -> 108 | G13: =Ntaja!J13+Ntaja!K13+Ntaja!L13 -> 11 | H13: =SUM(D13:G13) -> 8676
A14: Volume Billed Commercial/Industrial | C14: m3 | D14: =Balaka!J14+Balaka!K14+Balaka!L14 -> 187 | E14: =Liwonde!J14+Liwonde!K14+Liwonde!L14 -> 841 | F14: =Machinga!J14+Machinga!K14+Machinga!L14 -> 0 | G14: =Ntaja!J14+Ntaja!K14+Ntaja!L14 -> 0 | H14: =SUM(D14:G14) -> 1028
A15: Total Volume Billed Post Paid | C15: m3 | D15: =SUM(D11:D14) -> 107072 | E15: =SUM(E11:E14) -> 98233 | F15: =SUM(F11:F14) -> 3517 | G15: =SUM(G11:G14) -> 216 | H15: =SUM(H11:H14) -> 209038
A16: REVENUE WATER - PREPAID
A17: Individuals | C17: m3 | D17: =Balaka!J17+Balaka!K17+Balaka!L17 -> 20401 | E17: =Liwonde!J17+Liwonde!K17+Liwonde!L17 -> 33743 | F17: =Machinga!J17+Machinga!K17+Machinga!L17 -> 4629.3 | G17: =Ntaja!J17+Ntaja!K17+Ntaja!L17 -> 7064 | H17: =SUM(D17:G17) -> 65837.3
A18: CWPs | C18: m3 | D18: =Balaka!J18+Balaka!K18+Balaka!L18 -> 0 | E18: =Liwonde!J18+Liwonde!K18+Liwonde!L18 -> 0 | F18: =Machinga!J18+Machinga!K18+Machinga!L18 -> 0 | G18: =Ntaja!J18+Ntaja!K18+Ntaja!L18 -> 397 | H18: =SUM(D18:G18) -> 397
A19: Institutions | C19: m3 | D19: =Balaka!J19+Balaka!K19+Balaka!L19 -> 4439 | E19: =Liwonde!J19+Liwonde!K19+Liwonde!L19 -> 0 | F19: =Machinga!J19+Machinga!K19+Machinga!L19 -> 0 | G19: =Ntaja!J19+Ntaja!K19+Ntaja!L19 -> 353 | H19: =SUM(D19:G19) -> 4792
A20: Commercial/Industrial | C20: m3 | D20: =Balaka!J20+Balaka!K20+Balaka!L20 -> 1720 | E20: =Liwonde!J20+Liwonde!K20+Liwonde!L20 -> 0 | F20: =Machinga!J20+Machinga!K20+Machinga!L20 -> 0 | G20: =Ntaja!J20+Ntaja!K20+Ntaja!L20 -> 367 | H20: =SUM(D20:G20) -> 2087
A21: Total Volume Prepaid | C21: m3 | D21: =SUM(D17:D20) -> 26560 | E21: =SUM(E17:E20) -> 33743 | F21: =SUM(F17:F20) -> 4629.3 | G21: =SUM(G17:G20) -> 8181 | H21: =SUM(H17:H20) -> 73113.3
A22: TOTAL REVENUE WATER | C22: m3 | D22: =D21+D15 -> 133632 | E22: =E21+E15 -> 131976 | F22: =F21+F15 -> 8146.3 | G22: =G21+G15 -> 8397 | H22: =H21+H15 -> 282151.3
A23: NON-REVENUE WATER (NRW)
A24: Non-Revenue Water (NRW) | B24: Volume | C24: m3 | D24: =D9-D22 -> 75485 | E24: =E9-E22 -> 86263.7 | F24: =F9-F22 -> 1187.7 | G24: =G9-G22 -> 574 | H24: =H9-H22 -> 163510.4
B25: Percentage | C25: % | D25: =D24/D9 -> 0.36097017 | E25: =E24/E9 -> 0.39527043 | F25: =F24/F9 -> 0.12724448 | G25: =G24/G9 -> 0.063983948 | H25: =H24/H9 -> 0.36689354
A26: OPERATING EXPENSES
A27: Chemicals
A28: Chemical | B28: Rate(MK/kg)
A29: Chlorine | B29: =176264.5/50 -> 3525.29 | C29: kg | D29: =Balaka!J29+Balaka!K29+Balaka!L29 -> 357 | E29: =Liwonde!J29+Liwonde!K29+Liwonde!L29 -> 1213 | F29: =Machinga!J29+Machinga!K29+Machinga!L29 -> 32 | G29: =Ntaja!J29+Ntaja!K29+Ntaja!L29 -> 28 | H29: =SUM(D29:G29) -> 1630
C30: kg/mg litre | D30: =D29/(D9/1000) -> 1.7071783 | E30: =E29/(E9/1000) -> 5.5581088 | F30: =F29/(F9/1000) -> 3.4283265 | G30: =G29/(G9/1000) -> 3.1211682 | H30: =H29/(H9/1000) -> 3.6574828
A31: Aluminium sulphate | B31: =53000.511/50 -> 1060.0102 | C31: kg | D31: =Balaka!J31+Balaka!K31+Balaka!L31 -> 0 | E31: =Liwonde!J31+Liwonde!K31+Liwonde!L31 -> 0 | F31: =Machinga!J31+Machinga!K31+Machinga!L31 -> 0 | G31: =Ntaja!J31+Ntaja!K31+Ntaja!L31 -> 0 | H31: =SUM(D31:G31) -> 0
C32: kg/mg litre | D32: =D31/(D9/1000) -> 0 | E32: =E31/(E9/1000) -> 0 | F32: =F31/(F9/1000) -> 0 | G32: =G31/(G9/1000) -> 0 | H32: =H31/(H9/1000) -> 0
A33: Soda | B33: =61414.43/50 -> 1228.2886 | C33: kg | D33: =Balaka!J33+Balaka!K33+Balaka!L33 -> 0 | E33: =Liwonde!J33+Liwonde!K33+Liwonde!L33 -> 0 | F33: =Machinga!J33+Machinga!K33+Machinga!L33 -> 0 | G33: =Ntaja!J33+Ntaja!K33+Ntaja!L33 -> 0 | H33: =SUM(D33:G33) -> 0
C34: kg/mg litre | D34: =D33/(D9/1000) -> 0 | E34: =E33/(E9/1000) -> 0 | F34: =F33/(F9/1000) -> 0 | G34: =G33/(G9/1000) -> 0 | H34: =H33/(H9/1000) -> 0
A35: Algae floc | B35: =745345.16/200 -> 3726.7258 | C35: litres | D35: =Balaka!J35+Balaka!K35+Balaka!L35 -> 0 | E35: =Liwonde!J35+Liwonde!K35+Liwonde!L35 -> 394 | F35: =Machinga!J35+Machinga!K35+Machinga!L35 -> 0 | G35: =Ntaja!J35+Ntaja!K35+Ntaja!L35 -> 0
C36: litres/mg litre
A37: Sud floc | B37: =790318.72/200 -> 3951.5936 | C37: litres | D37: =Balaka!J37+Balaka!K37+Balaka!L37 -> 0 | E37: =Liwonde!J37+Liwonde!K37+Liwonde!L37 -> 0 | F37: =Machinga!J37+Machinga!K37+Machinga!L37 -> 0 | G37: =Ntaja!J37+Ntaja!K37+Ntaja!L37 -> 0 | H37: =SUM(D37:G37) -> 0
C38: litres/mg litre | D38: =D37/(D9/1000) -> 0 | E38: =E37/(E9/1000) -> 0 | F38: =F37/(F9/1000) -> 0 | G38: =G37/(G9/1000) -> 0 | H38: =H37/(H9/1000) -> 0
A39: Potasium permanganate | B39: 1950 | C39: kg | D39: =Balaka!J39+Balaka!K39+Balaka!L39 -> 0 | E39: =Liwonde!J39+Liwonde!K39+Liwonde!L39 -> 0 | F39: =Machinga!J39+Machinga!K39+Machinga!L39 -> 0 | G39: =Ntaja!J39+Ntaja!K39+Ntaja!L39 -> 0 | H39: =SUM(D39:G39) -> 0
C40: kg/mg litre | D40: =D39/(D9/1000) -> 0 | E40: =E39/(E9/1000) -> 0 | F40: =F39/(F9/1000) -> 0 | G40: =G39/(G9/1000) -> 0 | H40: =H39/(H9/1000) -> 0
A41: Cost of Chemicals | C41: Mk | D41: =(D29*$B29)+(D31*$B31)+(D33*$B33)+(D35*$B35)+(D37*$B37)+(D39*$B39) -> 1258528.5 | E41: =(E29*$B29)+(E31*$B31)+(E33*$B33)+(E35*$B35)+(E37*$B37)+(E39*$B39) -> 5744506.7 | F41: =(F29*$B29)+(F31*$B31)+(F33*$B33)+(F35*$B35)+(F37*$B37)+(F39*$B39) -> 112809.28 | G41: =(G29*$B29)+(G31*$B31)+(G33*$B33)+(G35*$B35)+(G37*$B37)+(G39*$B39) -> 98708.12 | H41: =SUM(D41:G41) -> 7214552.7
A42: Cost/vol. Produced (chemicals) | C42: Mk/m3 | D42: =D41/D9 -> 6.0182985 | E42: =E41/E9 -> 26.322006 | F42: =F41/F9 -> 12.085845 | G42: =G41/G9 -> 11.003023 | H42: =H41/H9 -> 16.188406
A43: Power
A44: Power Usage | C44: Kw | D44: =Balaka!J44+Balaka!K44+Balaka!L44 -> 119419 | E44: =Liwonde!J44+Liwonde!K44+Liwonde!L44 -> 216058.72 | F44: =Machinga!J44+Machinga!K44+Machinga!L44 -> 1684 | G44: =Ntaja!J44+Ntaja!K44+Ntaja!L44 -> 10613.08 | H44: =SUM(D44:G44) -> 347774.8
A45: Power/ Vol. Produced | C45: Kw/m3 | D45: =D44/D9 -> 0.57106309 | E45: =E44/E9 -> 0.99000649 | F45: =F44/F9 -> 0.18041568 | G45: =G44/G9 -> 1.1830431 | H45: =H44/H9 -> 0.78035604
A46: Cost of Power | C46: Mk | D46: =Balaka!J46+Balaka!K46+Balaka!L46 -> 20022187 | E46: =Liwonde!J46+Liwonde!K46+Liwonde!L46 -> 36178174 | F46: =Machinga!J46+Machinga!K46+Machinga!L46 -> 339543.91 | G46: =Ntaja!J46+Ntaja!K46+Ntaja!L46 -> 1583023.5 | H46: =SUM(D46:G46) -> 58122928
A47: Cost/vol. Produced | C47: Mk/m3 | D47: =D46/D9 -> 95.746338 | E47: =E46/E9 -> 165.77265 | F47: =F46/F9 -> 36.377106 | G47: =G46/G9 -> 176.4601 | H47: =H46/H9 -> 130.41939
A48: Plant and Vehicle Maintenance
A49: Distances covered | C49: km | D49: =Balaka!J49+Balaka!K49+Balaka!L49 -> 4849 | E49: =Liwonde!J49+Liwonde!K49+Liwonde!L49 -> 7804 | F49: =Machinga!J49+Machinga!K49+Machinga!L49 -> 0 | G49: =Ntaja!J49+Ntaja!K49+Ntaja!L49 -> 0 | H49: =SUM(D49:G49) -> 12653
A50: Fuel Used (litres) | C50: litres | D50: =Balaka!J50+Balaka!K50+Balaka!L50 -> 900 | E50: =Liwonde!J50+Liwonde!K50+Liwonde!L50 -> 626.03 | F50: =Machinga!J50+Machinga!K50+Machinga!L50 -> 0 | G50: =Ntaja!J50+Ntaja!K50+Ntaja!L50 -> 20 | H50: =SUM(D50:G50) -> 1546.03
A51: Cost of fuel | C51: Mk | D51: =Balaka!J51+Balaka!K51+Balaka!L51 -> 2191980 | E51: =Liwonde!J51+Liwonde!K51+Liwonde!L51 -> 2150345.7 | F51: =Machinga!J51+Machinga!K51+Machinga!L51 -> 0 | G51: =Ntaja!J51+Ntaja!K51+Ntaja!L51 -> 50600 | H51: =SUM(D51:G51) -> 4392925.7
A52: Maintenance | C52: Mk | D52: =Balaka!J52+Balaka!K52+Balaka!L52 -> 0 | E52: =Liwonde!J52+Liwonde!K52+Liwonde!L52 -> 0 | F52: =Machinga!J52+Machinga!K52+Machinga!L52 -> 0 | G52: =Ntaja!J52+Ntaja!K52+Ntaja!L52 -> 0 | H52: =SUM(D52:G52) -> 0
A53: Salaries and Wages
A54: Staff Costs | C54: MK | D54: =Balaka!J54+Balaka!K54+Balaka!L54 -> 21491043 | E54: =Liwonde!J54+Liwonde!K54+Liwonde!L54 -> 28559199 | F54: =Machinga!J54+Machinga!K54+Machinga!L54 -> 5448451.6 | G54: =Ntaja!J54+Ntaja!K54+Ntaja!L54 -> 5371109.9 | H54: =SUM(D54:G54) -> 60869804
A55: Wages | C55: MK | D55: =Balaka!J55+Balaka!K55+Balaka!L55 -> 8413936.2 | E55: =Liwonde!J55+Liwonde!K55+Liwonde!L55 -> 11730052 | F55: =Machinga!J55+Machinga!K55+Machinga!L55 -> 1601511.9 | G55: =Ntaja!J55+Ntaja!K55+Ntaja!L55 -> 1540287.1 | H55: =SUM(D55:G55) -> 23285787
A56: Other Overhead Costs | C56: MK | D56: =Balaka!J56+Balaka!K56+Balaka!L56 -> 15366847 | E56: =Liwonde!J56+Liwonde!K56+Liwonde!L56 -> 9869661.5 | F56: =Machinga!J56+Machinga!K56+Machinga!L56 -> 292884.8 | G56: =Ntaja!J56+Ntaja!K56+Ntaja!L56 -> 162000 | H56: =SUM(D56:G56) -> 25691393
A57: Operating Costs
A58: Total Operating Costs | C58: MK | D58: =D41+D46+D51+D52+D54+D55+D56 -> 68744522 | E58: =E41+E46+E51+E52+E54+E55+E56 -> 94231938 | F58: =F41+F46+F51+F52+F54+F55+F56 -> 7795201.5 | G58: =G41+G46+G51+G52+G54+G55+G56 -> 8805728.6 | H58: =SUM(D58:G58) -> 1.7957739e+08
A59: Cost/Vol. Produced | C59: Mk/m3 | D59: =D58/D9 -> 328.73713 | E59: =E58/E9 -> 431.78183 | F59: =F58/F9 -> 835.14051 | G59: =G58/G9 -> 981.57715 | H59: =H58/H9 -> 402.94553
A60: Cost/Vol. Billed | C60: Mk/m3 | D60: =D58/D22 -> 514.43159 | E60: =E58/E22 -> 714.00814 | F60: =F58/F22 -> 956.90086 | G60: =G58/G22 -> 1048.6756 | H60: =H58/H22 -> 636.45778
A61: Permanent Staff Employed | C61: No | D61: =Balaka!J61+Balaka!K61+Balaka!L61 -> 43 | E61: =Liwonde!J61+Liwonde!K61+Liwonde!L61 -> 39 | F61: =Machinga!J61+Machinga!K61+Machinga!L61 -> 9 | H61: =SUM(D61:G61) -> 91
A62: Staff/Vol.1000m3 of Volume Produced/hour (12 hour day) | C62: No/1000m3 | D62: =(D61*1000*31)/D9 -> 6.374422 | E62: =(E61*1000*31)/E9 -> 5.5397803 | F62: =(F61*1000*31)/F9 -> 29.890722 | G62: =(G61*1000*31)/G9 -> 0 | H62: =(H61*1000*31)/H9 -> 6.3299135
A63: Temporary Staff Employed | C63: No | D63: =Balaka!J63+Balaka!K63+Balaka!L63 -> 63 | E63: =Liwonde!J63+Liwonde!K63+Liwonde!L63 -> 57 | F63: =Machinga!J63+Machinga!K63+Machinga!L63 -> 18 | H63: =SUM(D63:G63) -> 138
A65: Water Connections and Disconnections
A66: New Individual Water Connections | B66: Brought Forward | C66: No | D66: =Balaka!J66 -> 442 | E66: =Liwonde!J66 -> 352 | F66: =Machinga!J66 -> 12 | G66: =Ntaja!J66 -> 32 | H66: =SUM(D66:G66) -> 838
B67: Applied this Month | C67: No | D67: =Balaka!J67+Balaka!K67+Balaka!L67 -> 86 | E67: =Liwonde!J67+Liwonde!K67+Liwonde!L67 -> 100 | F67: =Machinga!J67+Machinga!K67+Machinga!L67 -> 3 | G67: =Ntaja!J67+Ntaja!K67+Ntaja!L67 -> 27 | H67: =SUM(D67:G67) -> 216
B68: Done this Month Postpaid | C68: No | D68: =Balaka!J68+Balaka!K68+Balaka!L68 -> 120 | E68: =Liwonde!J68+Liwonde!K68+Liwonde!L68 -> 113 | F68: =Machinga!J68+Machinga!K68+Machinga!L68 -> 4 | G68: =Ntaja!J68+Ntaja!K68+Ntaja!L68 -> 0 | H68: =SUM(D68:G68) -> 237
B69: Done this Month Prepaid | C69: No | D69: =Balaka!J69+Balaka!K69+Balaka!L69 -> 0 | E69: =Liwonde!J69+Liwonde!K69+Liwonde!L69 -> 0 | F69: =Machinga!J69+Machinga!K69+Machinga!L69 -> 0 | G69: =Ntaja!J69+Ntaja!K69+Ntaja!L69 -> 0 | H69: =SUM(D69:G69) -> 0
B70: Total Done | C70: No | D70: =D68+D69 -> 120 | E70: =E68+E69 -> 113 | F70: =F68+F69 -> 4 | G70: =G68+G69 -> 0 | H70: =H68+H69 -> 237
B71: Carried Forward | C71: No | D71: =D66+D67-D70 -> 408 | E71: =E66+E67-E70 -> 339 | F71: =F66+F67-F70 -> 11 | G71: =G66+G67-G70 -> 59 | H71: =H66+H67-H70 -> 817
A72: New Institutional Water Connections | B72: Brought Forward | C72: No | D72: =Balaka!J72 -> 0 | E72: =Liwonde!J72 -> 0 | F72: =Machinga!J72 -> 0 | G72: =Ntaja!J72 -> 0 | H72: =SUM(D72:G72) -> 0
B73: Applied this Month | C73: No | D73: =Balaka!J73+Balaka!K73+Balaka!L73 -> 0 | E73: =Liwonde!J73+Liwonde!K73+Liwonde!L73 -> 0 | F73: =Machinga!J73+Machinga!K73+Machinga!L73 -> 0 | G73: =Ntaja!J73+Ntaja!K73+Ntaja!L73 -> 0 | H73: =SUM(D73:G73) -> 0
B74: Done this Month Postpaid | C74: No | D74: =Balaka!J74+Balaka!K74+Balaka!L74 -> 0 | E74: =Liwonde!J74+Liwonde!K74+Liwonde!L74 -> 0 | F74: =Machinga!J74+Machinga!K74+Machinga!L74 -> 0 | G74: =Ntaja!J74+Ntaja!K74+Ntaja!L74 -> 0 | H74: =SUM(D74:G74) -> 0
B75: Done this Month Prepaid | C75: No | D75: =Balaka!J75+Balaka!K75+Balaka!L75 -> 0 | E75: =Liwonde!J75+Liwonde!K75+Liwonde!L75 -> 0 | F75: =Machinga!J75+Machinga!K75+Machinga!L75 -> 0 | G75: =Ntaja!J75+Ntaja!K75+Ntaja!L75 -> 0 | H75: =SUM(D75:G75) -> 0
B76: Total Done | C76: No | D76: =D74+D75 -> 0 | E76: =E74+E75 -> 0 | F76: =F74+F75 -> 0 | G76: =G74+G75 -> 0 | H76: =H74+H75 -> 0
B77: Carried Forward | C77: No | D77: =D73+D74-D76 -> 0 | E77: =E73+E74-E76 -> 0 | F77: =F73+F74-F76 -> 0 | G77: =G73+G74-G76 -> 0 | H77: =H73+H74-H76 -> 0
A78: New Commercial/Industrial Water Connections | B78: Brought Forward | C78: No | D78: =Balaka!J78 -> 0 | E78: =Liwonde!J78 -> 0 | F78: =Machinga!J78 -> 0 | G78: =Ntaja!J78 -> 0 | H78: =SUM(D78:G78) -> 0
B79: Applied this Month | C79: No | D79: =Balaka!J79+Balaka!K79+Balaka!L79 -> 0 | E79: =Liwonde!J79+Liwonde!K79+Liwonde!L79 -> 0 | F79: =Machinga!J79+Machinga!K79+Machinga!L79 -> 0 | G79: =Ntaja!J79+Ntaja!K79+Ntaja!L79 -> 0 | H79: =SUM(D79:G79) -> 0
B80: Done this Month Postpaid | C80: No | D80: =Balaka!J80+Balaka!K80+Balaka!L80 -> 0 | E80: =Liwonde!J80+Liwonde!K80+Liwonde!L80 -> 0 | F80: =Machinga!J80+Machinga!K80+Machinga!L80 -> 0 | G80: =Ntaja!J80+Ntaja!K80+Ntaja!L80 -> 0 | H80: =SUM(D80:G80) -> 0
B81: Done this Month Prepaid | C81: No | D81: =Balaka!J81+Balaka!K81+Balaka!L81 -> 0 | E81: =Liwonde!J81+Liwonde!K81+Liwonde!L81 -> 0 | F81: =Machinga!J81+Machinga!K81+Machinga!L81 -> 0 | G81: =Ntaja!J81+Ntaja!K81+Ntaja!L81 -> 0 | H81: =SUM(D81:G81) -> 0
B82: Total Done | C82: No | D82: =D81+D80 -> 0 | E82: =E81+E80 -> 0 | F82: =F81+F80 -> 0 | G82: =G81+G80 -> 0 | H82: =H81+H80 -> 0
B83: Carried Forward | C83: No | D83: =D78+D79-D82 -> 0 | E83: =Liwonde!J83+Liwonde!K83+Liwonde!L83 -> 0 | F83: =F78+F79-F82 -> 0 | G83: =G78+G79-G82 -> 0 | H83: =H78+H79-H82 -> 0
A84: New CWP | B84: Brought Forward | C84: No | D84: =Balaka!J84 -> 0 | E84: =Liwonde!J84 -> 0 | F84: =Machinga!J84 -> 0 | G84: =Ntaja!J84 -> 0 | H84: =SUM(D84:G84) -> 0
B85: Applied this Month | C85: No | D85: =Balaka!J85+Balaka!K85+Balaka!L85 -> 0 | E85: =Liwonde!J85+Liwonde!K85+Liwonde!L85 -> 0 | F85: =Machinga!J85+Machinga!K85+Machinga!L85 -> 0 | G85: =Ntaja!J85+Ntaja!K85+Ntaja!L85 -> 0 | H85: =SUM(D85:G85) -> 0
B86: Done this Month Postpaid | C86: No | D86: =Balaka!J86+Balaka!K86+Balaka!L86 -> 0 | E86: =Liwonde!J86+Liwonde!K86+Liwonde!L86 -> 0 | F86: =Machinga!J86+Machinga!K86+Machinga!L86 -> 0 | G86: =Ntaja!J86+Ntaja!K86+Ntaja!L86 -> 0 | H86: =SUM(D86:G86) -> 0
B87: Done this Month Prepaid | C87: No | D87: =Balaka!J87+Balaka!K87+Balaka!L87 -> 0 | E87: =Liwonde!J87+Liwonde!K87+Liwonde!L87 -> 0 | F87: =Machinga!J87+Machinga!K87+Machinga!L87 -> 0 | G87: =Ntaja!J87+Ntaja!K87+Ntaja!L87 -> 0 | H87: =SUM(D87:G87) -> 0
B88: Total Done | C88: No | D88: =D87+D86 -> 0 | E88: =E87+E86 -> 0 | F88: =F87+F86 -> 0 | G88: =G87+G86 -> 0
B89: Carried Forward | C89: No | D89: =D84+D85-D88 -> 0 | E89: =E84+E85-E88 -> 0 | F89: =F84+F85-F88 -> 0 | G89: =G84+G85-G88 -> 0 | H89: =H84+H85-H86-H87 -> 0
A90: Aggregated New Water connections | B90: Brought Forward | C90: No | D90: =D66+D72+D78+D84 -> 442 | E90: =E66+E72+E78+E84 -> 352 | F90: =F66+F72+F78+F84 -> 12 | G90: =G66+G72+G78+G84 -> 32 | H90: =SUM(D90:G90) -> 838
B91: Applied this Month | C91: No | D91: =D67+D73+D79+D85 -> 86 | E91: =E67+E73+E79+E85 -> 100 | F91: =F67+F73+F79+F85 -> 3 | G91: =G67+G73+G79+G85 -> 27 | H91: =SUM(D91:G91) -> 216
B92: Done this Month Postpaid | C92: No | D92: =D68+D74+D80+D86 -> 120 | E92: =E68+E74+E80+E86 -> 113 | F92: =F68+F74+F80+F86 -> 4 | G92: =G68+G74+G80+G86 -> 0 | H92: =SUM(D92:G92) -> 237
B93: Done this Month Prepaid | D93: =D69+D75+D81+D87 -> 0 | E93: =E69+E75+E81+E87 -> 0 | F93: =F69+F75+F81+F87 -> 0 | G93: =G69+G75+G81+G87 -> 0 | H93: =SUM(D93:G93) -> 0
B94: Total Done | C94: No | D94: =D93+D92 -> 120 | E94: =E93+E92 -> 113 | F94: =F93+F92 -> 4 | G94: =G93+G92 -> 0 | H94: =H93+H92 -> 237
B95: Carried Forward | C95: No | D95: =D90+D91-D94 -> 408 | E95: =E90+E91-E94 -> 339 | F95: =F90+F91-F94 -> 11 | G95: =G90+G91-G94 -> 59 | H95: =H90+H91-H94 -> 817
A97: Prepaid Metering
A98: Prepaid Meters Installed | C98: No | D98: =Balaka!J98+Balaka!K98+Balaka!L98 -> 2799 | E98: =Liwonde!J98+Liwonde!K98+Liwonde!L98 -> 2157 | F98: =Machinga!J98+Machinga!K98+Machinga!L98 -> 417 | G98: =Ntaja!J98+Ntaja!K98+Ntaja!L98 -> 0 | H98: =SUM(D98:G98) -> 5373
A100: Active and Disconnected Accounts
A101: Disconnected Individual Accounts | C101: No | D101: =Balaka!L101 -> 2289 | E101: =Liwonde!L101 -> 1398 | F101: =Machinga!L101 -> 0 | G101: =Ntaja!L101 -> 4 | H101: =SUM(D101:G101) -> 3691
A102: Disconnected institutional Accounts | C102: No | D102: =Balaka!L102 -> 36 | E102: =Liwonde!L102 -> 40 | F102: =Machinga!L102 -> 0 | G102: =Ntaja!L102 -> 1 | H102: =SUM(D102:G102) -> 77
A103: Disconnected Commercial/Industrial Accounts | C103: No | D103: =Balaka!L103 -> 98 | E103: =Liwonde!L103 -> 67 | F103: =Machinga!L103 -> 0 | G103: =Ntaja!L103 -> 2 | H103: =SUM(D103:G103) -> 167
A104: Disconnected CWP | C104: No | D104: =Balaka!L104 -> 17 | E104: =Liwonde!L104 -> 15 | F104: =Machinga!L104 -> 0 | G104: =Ntaja!L104 -> 15 | H104: =SUM(D104:G104) -> 47
A105: Total Disconnected Accounts | C105: No | D105: =SUM(D101:D104) -> 2440 | E105: =SUM(E101:E104) -> 1520 | F105: =SUM(F101:F104) -> 0 | G105: =SUM(G101:G104) -> 22 | H105: =SUM(D105:G105) -> 3982
...

Sheet 4th QTR
A1: SOUTHERN REGION WATER BOARD
A3: MONTHLY REPORTS - 2023/2024
A4: LIWONDE ZONE
A5: LIWONDE ZONE
A7: PARAMETERS | C7: UNITS | D7: Balaka | E7: Liwonde | F7: Machinga | G7: Ntaja | H7: TOTALS
A8: PRODUCTION
A9: Volume Produced | C9: m3 | D9: =Balaka!M9+Balaka!N9+Balaka!O9 -> 182853 | E9: =Liwonde!M9+Liwonde!N9+Liwonde!O9 -> 192047 | F9: =Machinga!M9+Machinga!N9+Machinga!O9 -> 8815 | G9: =Ntaja!M9+Ntaja!N9+Ntaja!O9 -> 8145 | H9: =SUM(D9:G9) -> 391860
A10: REVENUE WATER - POSTPAID
A11: Volume Billed Individuals | C11: m3 | D11: =Balaka!M11+Balaka!N11+Balaka!O11 -> 95544 | E11: =Liwonde!M11+Liwonde!N11+Liwonde!O11 -> 101631 | F11: =Machinga!M11+Machinga!N11+Machinga!O11 -> 2828 | G11: =Ntaja!M11+Ntaja!N11+Ntaja!O11 -> 215 | H11: =SUM(D11:G11) -> 200218
A12: Volume Billed CWPs | C12: m3 | D12: =Balaka!M12+Balaka!N12+Balaka!O12 -> 3148 | E12: =Liwonde!M12+Liwonde!N12+Liwonde!O12 -> 1400 | F12: =Machinga!M12+Machinga!N12+Machinga!O12 -> 0 | G12: =Ntaja!M12+Ntaja!N12+Ntaja!O12 -> 0 | H12: =SUM(D12:G12) -> 4548
A13: Volume Billed Institutions | C13: m3 | D13: =Balaka!M13+Balaka!N13+Balaka!O13 -> 723 | E13: =Liwonde!M13+Liwonde!N13+Liwonde!O13 -> 2722 | F13: =Machinga!M13+Machinga!N13+Machinga!O13 -> 81 | G13: =Ntaja!M13+Ntaja!N13+Ntaja!O13 -> 41 | H13: =SUM(D13:G13) -> 3567
A14: Volume Billed Commercial/Industrial | C14: m3 | D14: =Balaka!M14+Balaka!N14+Balaka!O14 -> 208 | E14: =Liwonde!M14+Liwonde!N14+Liwonde!O14 -> 1265 | F14: =Machinga!M14+Machinga!N14+Machinga!O14 -> 0 | G14: =Ntaja!M14+Ntaja!N14+Ntaja!O14 -> 0 | H14: =SUM(D14:G14) -> 1473
A15: Total Volume Billed Post Paid | C15: m3 | D15: =SUM(D11:D14) -> 99623 | E15: =SUM(E11:E14) -> 107018 | F15: =SUM(F11:F14) -> 2909 | G15: =SUM(G11:G14) -> 256 | H15: =SUM(H11:H14) -> 209806
A16: REVENUE WATER - PREPAID
A17: Individuals | C17: m3 | D17: =Balaka!M17+Balaka!N17+Balaka!O17 -> 20798 | E17: =Liwonde!M17+Liwonde!N17+Liwonde!O17 -> 31436.3 | F17: =Machinga!M17+Machinga!N17+Machinga!O17 -> 5135.88 | G17: =Ntaja!M17+Ntaja!N17+Ntaja!O17 -> 6264 | H17: =SUM(D17:G17) -> 63634.18
A18: CWPs | C18: m3 | D18: =Balaka!M18+Balaka!N18+Balaka!O18 -> 47 | E18: =Liwonde!M18+Liwonde!N18+Liwonde!O18 -> 0 | F18: =Machinga!M18+Machinga!N18+Machinga!O18 -> 0 | G18: =Ntaja!M18+Ntaja!N18+Ntaja!O18 -> 316 | H18: =SUM(D18:G18) -> 363
A19: Institutions | C19: m3 | D19: =Balaka!M19+Balaka!N19+Balaka!O19 -> 3708 | E19: =Liwonde!M19+Liwonde!N19+Liwonde!O19 -> 0 | F19: =Machinga!M19+Machinga!N19+Machinga!O19 -> 0 | G19: =Ntaja!M19+Ntaja!N19+Ntaja!O19 -> 137 | H19: =SUM(D19:G19) -> 3845
A20: Commercial/Industrial | C20: m3 | D20: =Balaka!M20+Balaka!N20+Balaka!O20 -> 1683 | E20: =Liwonde!M20+Liwonde!N20+Liwonde!O20 -> 0 | F20: =Machinga!M20+Machinga!N20+Machinga!O20 -> 0 | G20: =Ntaja!M20+Ntaja!N20+Ntaja!O20 -> 310 | H20: =SUM(D20:G20) -> 1993
A21: Total Volume Prepaid | C21: m3 | D21: =SUM(D17:D20) -> 26236 | E21: =SUM(E17:E20) -> 31436.3 | F21: =SUM(F17:F20) -> 5135.88 | G21: =SUM(G17:G20) -> 7027 | H21: =SUM(H17:H20) -> 69835.18
A22: TOTAL REVENUE WATER | C22: m3 | D22: =D21+D15 -> 125859 | E22: =E21+E15 -> 138454.3 | F22: =F21+F15 -> 8044.88 | G22: =G21+G15 -> 7283 | H22: =H21+H15 -> 279641.18
A23: NON-REVENUE WATER (NRW)
A24: Non-Revenue Water (NRW) | B24: Volume | C24: m3 | D24: =D9-D22 -> 56994 | E24: =E9-E22 -> 53592.7 | F24: =F9-F22 -> 770.12 | G24: =G9-G22 -> 862 | H24: =H9-H22 -> 112218.82
B25: Percentage | C25: % | D25: =D24/D9 -> 0.311693 | E25: =E24/E9 -> 0.27906033 | F25: =F24/F9 -> 0.087364719 | G25: =G24/G9 -> 0.1058318 | H25: =H24/H9 -> 0.28637478
A26: OPERATING EXPENSES
A27: Chemicals
A28: Chemical | B28: Rate(MK/kg)
