Workbook

Sheet Mangochi
A1: SOUTHERN REGION WATER BOARD
A3: MONTHLY REPORTS - 2023/2024
A4: MANGOCHI ZONE
A5: MANGOCHI ZONE
A7: PARAMETERS | C7: UNITS | D7: APRIL | E7: MAY | F7: JUNE | G7: JULY | H7: AUGUST | I7: SEPTEMBER | J7: OCTOBER | K7: NOVEMBER | L7: DECEMBER | M7: JANUARY | N7: FEBRUARY | O7: MARCH | P7: TOTALS
A8: PRODUCTION | Q8: APR
A9: Volume Produced | C9: m3 | D9: 128967 | E9: 126274 | F9: 133435 | G9: 129170 | H9: 127011 | I9: 120296 | J9: 123700 | K9: 153120 | L9: 138608 | M9: 141058 | N9: 129551 | O9: 124206 | P9: =SUM(D9:O9) -> 1575396 | Q9: 0
A10: REVENUE WATER - POSTPAID
A11: Volume Billed Individuals | C11: m3 | D11: 53390 | E11: 57141 | F11: 57885 | G11: 57872 | H11: 59635 | I11: 60374 | J11: 63088 | K11: 63200 | L11: 58777 | M11: 64972 | N11: 67205 | O11: 68023 | P11: =SUM(D11:O11) -> 731562
A12: Volume Billed CWPs | C12: m3 | D12: 0 | E12: 0 | F12: 0 | G12: 0 | H12: 0 | I12: 0 | J12: 0 | K12: 0 | M12: 0 | N12: 0 | O12: 0 | P12: =SUM(D12:O12) -> 0
A13: Volume Billed Institutions | C13: m3 | D13: 315 | E13: 296 | F13: 309 | G13: 231 | H13: 307 | I13: 309 | J13: 289 | K13: 276 | L13: 279 | M13: 142 | N13: 120 | O13: 174 | P13: =SUM(D13:O13) -> 3047
A14: Volume Billed Commercial/Industrial | C14: m3 | D14: 217 | E14: 217 | F14: 78 | G14: 22 | H14: 105 | I14: 42 | J14: 47 | K14: 78 | L14: 105 | M14: 57 | N14: 60 | O14: 59 | P14: =SUM(D14:O14) -> 1087
A15: Total Volume Billed Post Paid | C15: m3 | D15: =SUM(D11:D14) -> 53922 | E15: =SUM(E11:E14) -> 57654 | F15: =SUM(F11:F14) -> 58272 | G15: =SUM(G11:G14) -> 58125 | H15: =SUM(H11:H14) -> 60047 | I15: =SUM(I11:I14) -> 60725 | J15: =SUM(J11:J14) -> 63424 | K15: =SUM(K11:K14) -> 63554 | ... P15: =SUM(P11:P14) -> 735696
A16: REVENUE WATER - PREPAID
A17: Individuals | C17: m3 | D17: 13086.4 | E17: 17006.9 | F17: 14082 | G17: 16217.3 | H17: 15436 | I17: 15196.9 | J17: 16970.2 | K17: 17078.1 | L17: 18202 | M17: 17323.6 | N17: 23958.5 | O17: 17257.6 | P17: =SUM(D17:O17) -> 201815.5
A18: CWPs | C18: m3 | D18: 0 | E18: 0 | F18: 0 | G18: 0 | H18: 0 | I18: 0 | J18: 0 | K18: 0 | L18: 0 | M18: 0 | N18: 0 | O18: 0 | P18: =SUM(D18:O18) -> 0
A19: Institutions | C19: m3 | D19: 0 | E19: 0 | F19: 0 | G19: 0 | H19: 0 | I19: 0 | J19: 0 | K19: 0 | L19: 0 | M19: 0 | N19: 0 | O19: 0 | P19: =SUM(D19:O19) -> 0
A20: Commercial/Industrial | C20: m3 | D20: 0 | E20: 0 | F20: 0 | G20: 0 | H20: 0 | I20: 0 | J20: 0 | K20: 0 | L20: 0 | M20: 0 | N20: 0 | O20: 0 | P20: =SUM(D20:O20) -> 0
A21: Total Volume Prepaid | C21: m3 | D21: =SUM(D17:D20) -> 13086.4 | E21: =SUM(E17:E20) -> 17006.9 | F21: =SUM(F17:F20) -> 14082 | G21: =SUM(G17:G20) -> 16217.3 | H21: =SUM(H17:H20) -> 15436 | I21: =SUM(I17:I20) -> 15196.9 | J21: =SUM(J17:J20) -> 16970.2 | K21: =SUM(K17:K20) -> 17078.1 | ... P21: =SUM(P17:P20) -> 201815.5
A22: TOTAL REVENUE WATER | C22: m3 | D22: =D21+D15 -> 67008.4 | E22: =E21+E15 -> 74660.9 | F22: =F21+F15 -> 72354 | G22: =G21+G15 -> 74342.3 | H22: =H21+H15 -> 75483 | I22: =I21+I15 -> 75921.9 | J22: =J21+J15 -> 80394.2 | K22: =K21+K15 -> 80632.1 | ... P22: =P21+P15 -> 937511.5
D23: 0 | E23: 0 | F23: 0 | G23: 0 | H23: 0 | I23: 0 | J23: 0 | K23: 0 | L23: 0
A24: Non-Revenue Water (NRW) | B24: Volume | C24: m3 | D24: =D9-D22 -> 61958.6 | E24: =E9-E22 -> 51613.1 | F24: =F9-F22 -> 61081 | G24: =G9-G22 -> 54827.7 | H24: =H9-H22 -> 51528 | I24: =I9-I22 -> 44374.1 | J24: =J9-J22 -> 43305.8 | K24: =K9-K22 -> 72487.9 | ... P24: =P9-P22 -> 637884.5
B25: Percentage | C25: % | D25: =D24/D9 -> 0.48042212 | E25: =E24/E9 -> 0.40873893 | F25: =F24/F9 -> 0.45775846 | G25: =G24/G9 -> 0.42446156 | H25: =H24/H9 -> 0.40569714 | I25: =I24/I9 -> 0.36887428 | J25: =J24/J9 -> 0.35008731 | K25: =K24/K9 -> 0.47340583 | ... P25: =P24/P9 -> 0.40490423
A26: OPERATING EXPENSES
A27: Chemicals
A28: Chemical | B28: Rate(MK/kg) | D28: 0 | E28: 0 | F28: 0 | G28: 0
A29: Chlorine | B29: 3525.29 | C29: kg | D29: 393 | E29: 637 | F29: 599 | G29: 539 | H29: 517 | I29: 500 | J29: 525 | K29: 520 | L29: 450 | M29: 460 | N29: 546 | O29: 550 | P29: =SUM(D29:O29) -> 6236
C30: kg/mg litre | D30: =D29/(D9/1000) -> 3.0472912 | E30: =E29/(E9/1000) -> 5.0445856 | F30: =F29/(F9/1000) -> 4.4890771 | G30: =G29/(G9/1000) -> 4.1727955 | H30: =H29/(H9/1000) -> 4.0705136 | I30: =I29/(I9/1000) -> 4.1564142 | J30: =J29/(J9/1000) -> 4.244139 | K30: =K29/(K9/1000) -> 3.3960293 | ... P30: =P29/(P9/1000) -> 3.9583698
A31: Aluminium sulphate | B31: 1060.0102 | C31: kg | D31: 800 | E31: 0 | F31: 0 | G31: 0 | M31: 200 | N31: 50 | O31: 50 | P31: =SUM(D31:O31) -> 1100
C32: kg/mg litre | D32: =D31/(D9/1000) -> 6.2031372 | E32: =E31/(E9/1000) -> 0 | F32: =F31/(F9/1000) -> 0 | G32: =G31/(G9/1000) -> 0 | H32: =H31/(H9/1000) -> 0 | I32: =I31/(I9/1000) -> 0 | J32: =J31/(J9/1000) -> 0 | K32: =K31/(K9/1000) -> 0 | ... P32: =P31/(P9/1000) -> 0.69823714
A33: Soda | B33: 1228.2886 | C33: kg | D33: 0 | E33: 0 | F33: 0 | G33: 0 | P33: =SUM(D33:O33) -> 0
C34: kg/mg litre | D34: =D33/(D9/1000) -> 0 | E34: =E33/(E9/1000) -> 0 | F34: =F33/(F9/1000) -> 0 | G34: =G33/(G9/1000) -> 0 | H34: =H33/(H9/1000) -> 0 | I34: =I33/(I9/1000) -> 0 | J34: =J33/(J9/1000) -> 0 | K34: =K33/(K9/1000) -> 0 | ... P34: =P33/(P9/1000) -> 0
A35: Algae floc | B35: 3726.7258 | C35: litres | D35: 0 | E35: 0 | F35: 0 | G35: 0
C36: litres/mg litre | D36: 0 | E36: 0 | F36: 0 | G36: 0
A37: Sud floc | B37: 3951.5936 | C37: litres | D37: 0 | E37: 0 | F37: 0 | G37: 0 | H37: 0 | I37: 0 | J37: 0 | K37: 0 | L37: 0 | M37: 0 | N37: 0 | O37: 0 | P37: =SUM(D37:O37) -> 0
C38: litres/mg litre | D38: =D37/(D9/1000) -> 0 | E38: =E37/(E9/1000) -> 0 | F38: =F37/(F9/1000) -> 0 | G38: =G37/(G9/1000) -> 0 | H38: =H37/(H9/1000) -> 0 | I38: =I37/(I9/1000) -> 0 | J38: =J37/(J9/1000) -> 0 | K38: =K37/(K9/1000) -> 0 | ... P38: =P37/(P9/1000) -> 0
A39: Potasium permanganate | B39: 1950 | C39: kg | D39: 0 | E39: 0 | F39: 0 | G39: 0 | H39: 0 | I39: 0 | J39: 0 | K39: 0 | L39: 0 | M39: 0 | N39: 0 | O39: 0 | P39: =SUM(D39:O39) -> 0
C40: kg/mg litre | D40: =D39/(D9/1000) -> 0 | E40: =E39/(E9/1000) -> 0 | F40: =F39/(F9/1000) -> 0 | G40: =G39/(G9/1000) -> 0 | H40: =H39/(H9/1000) -> 0 | I40: =I39/(I9/1000) -> 0 | J40: =J39/(J9/1000) -> 0 | K40: =K39/(K9/1000) -> 0 | ... P40: =P39/(P9/1000) -> 0
A41: Cost of Chemicals | C41: Mk | D41: =(D29*$B29)+(D31*$B31)+(D33*$B33)+(D35*$B35)+(D37*$B37)+(D39*$B39) -> 2233447.1 | E41: =(E29*$B29)+(E31*$B31)+(E33*$B33)+(E35*$B35)+(E37*$B37)+(E39*$B39) -> 2245609.7 | F41: =(F29*$B29)+(F31*$B31)+(F33*$B33)+(F35*$B35)+(F37*$B37)+(F39*$B39) -> 2111648.7 | G41: =(G29*$B29)+(G31*$B31)+(G33*$B33)+(G35*$B35)+(G37*$B37)+(G39*$B39) -> 1900131.3 | H41: =(H29*$B29)+(H31*$B31)+(H33*$B33)+(H35*$B35)+(H37*$B37)+(H39*$B39) -> 1822574.9 | I41: =(I29*$B29)+(I31*$B31)+(I33*$B33)+(I35*$B35)+(I37*$B37)+(I39*$B39) -> 1762645 | J41: =(J29*$B29)+(J31*$B31)+(J33*$B33)+(J35*$B35)+(J37*$B37)+(J39*$B39) -> 1850777.2 | K41: =(K29*$B29)+(K31*$B31)+(K33*$B33)+(K35*$B35)+(K37*$B37)+(K39*$B39) -> 1833150.8 | ... O41: =(O29*$B29)+(O31*$B31)+(O33*$B33)+(O35*$B35)+(O37*$B37)+(O39*$B39) -> 1991910 | P41: =SUM(D41:O41) -> 23149720
A42: Cost/vol. Produced (chemicals) | C42: Mk/m3 | D42: =D41/D9 -> 17.317974 | E42: =E41/E9 -> 17.783627 | F42: =F41/F9 -> 15.825299 | G42: =G41/G9 -> 14.710314 | H42: =H41/H9 -> 14.349741 | I42: =I41/I9 -> 14.652565 | J42: =J41/J9 -> 14.961821 | K42: =K41/K9 -> 11.971988 | ... P42: =P41/P9 -> 14.69454
A43: Power
A44: Power Usage | C44: Kw | D44: 54247.48 | E44: 51735.72 | F44: 55889.72 | G44: 43469.55 | H44: 53270 | I44: 46683.67 | J44: 50503.33 | K44: 49244.12 | L44: 48473.76 | M44: 48761.13 | N44: 48477.65 | O44: 47239.52 | P44: =SUM(D44:O44) -> 597995.65
A45: Power/ Vol. Produced | C45: Kw/m3 | D45: =D44/D9 -> 0.4206307 | E45: =E44/E9 -> 0.40971 | F45: =F44/F9 -> 0.41885352 | G45: =G44/G9 -> 0.33652977 | H45: =H44/H9 -> 0.41941249 | I45: =I44/I9 -> 0.38807334 | J45: =J44/J9 -> 0.40827268 | K45: =K44/K9 -> 0.32160475 | ... P45: =P44/P9 -> 0.37958434
A46: Cost of Power | C46: Mk | D46: =1.165*(14100+(D44*119.1)) -> 7543345.7 | E46: =1.165*(14100+(E44*119.1)) -> 7194835.3 | F46: =1.165*(14100+(F44*119.1)) -> 7771209 | G46: =1.165*(14100+(G44*119.1)) -> 6047891.8 | H46: =1.165*(16600+(H44*143.5)) -> 8924884.4 | I46: =1.165*(16600+(I44*143.5)) -> 7823798.2 | J46: =1.165*(16600+(J44*143.5)) -> 8462359.5 | K46: =1.165*(16600+(K44*143.5)) -> 8251847.9 | L46: =1.165*(16600+(L44*143.5)) -> 8123061 | M46: =1.165*(16600+(M44*143.5)) -> 8171102.8 | N46: =1.165*(16600+(N44*143.5)) -> 8123711.3 | O46: =1.165*(16600+(O44*143.5)) -> 7916723.9 | P46: =SUM(D46:O46) -> 94354771
A47: Cost/vol. Produced | C47: Mk/m3 | D47: =D46/D9 -> 58.490511 | E47: =E46/E9 -> 56.977963 | F47: =F46/F9 -> 58.23966 | G47: =G46/G9 -> 46.82118 | H47: =H46/H9 -> 70.268594 | I47: =I46/I9 -> 65.037892 | J47: =J46/J9 -> 68.410343 | K47: =K46/K9 -> 53.891378 | ... P47: =P46/P9 -> 59.892732
A48: Plant and Vehicle Maintenance
A49: Distances covered | C49: km | D49: 3211 | E49: 4124 | F49: 4745 | G49: 6046 | H49: 5954 | I49: 7600 | J49: 7264 | K49: 4441 | L49: 4918 | M49: 12493 | N49: 10021 | O49: 8233 | P49: =SUM(D49:O49) -> 79050
A50: Fuel Used (litres) | C50: litres | D50: 908.93 | E50: 872.37 | F50: 1019.8 | G50: 970.56 | H50: 740.24 | I50: 935.5 | J50: 1312.42 | K50: 1044.84 | L50: 1089.26 | M50: 1230.21 | N50: 900.26 | O50: 1001.95 | P50: =SUM(D50:O50) -> 12026.34
A51: Cost of fuel | C51: Mk | D51: 1745280 | E51: 1674240 | F51: 1958400 | G51: 1864320 | H51: 1420800 | I51: 1797120 | J51: 2519846.4 | K51: 2856629.4 | L51: 2978036.8 | M51: 3362820 | N51: 2460600 | O51: 2739340.4 | P51: =SUM(D51:O51) -> 27377433
A52: Maintenance | C52: Mk | D52: 0 | E52: 0 | F52: 0 | G52: 0 | H52: 0 | I52: 0 | J52: 0 | K52: 0 | L52: 0 | M52: 0 | N52: 0 | O52: 0 | P52: =SUM(D52:O52) -> 0
A53: Salaries and Wages
A54: Staff Costs | C54: MK | D54: 14882805 | E54: 15681987 | F54: 15211801 | G54: 10225636 | H54: 10566276 | I54: 13911789 | J54: 8899666.8 | K54: 14295109 | L54: 20707414 | M54: 22340441 | N54: 22340441 | O54: 17246250 | P54: =SUM(D54:O54) -> 1.8630962e+08
A55: Wages | C55: MK | D55: 1799822.6 | E55: 1745495.6 | F55: 1660699.8 | G55: 2076986.5 | H55: 2621037.9 | I55: 3355774.6 | J55: 4258720.8 | K55: 2997000 | L55: 2725485.1 | M55: 4874442.8 | N55: 9592035.5 | O55: 9343453.6 | P55: =SUM(D55:O55) -> 47050955
A56: Other Overhead Costs | C56: MK | D56: 1519850 | E56: 1518000 | F56: 1526250 | G56: 1531700 | H56: 1538600 | I56: 1552250 | J56: 1561400 | K56: 1564450 | L56: 1558750 | M56: 1400450 | N56: 1756800 | O56: 1678850 | P56: =SUM(D56:O56) -> 18707350
A57: Operating Costs | P57: =SUM(D57:O57) -> 0
A58: Total Operating Costs | C58: MK | D58: =D41+D46+D51+D52+D54+D55+D56 -> 29724551 | E58: =E41+E46+E51+E52+E54+E55+E56 -> 30060168 | F58: =F41+F46+F51+F52+F54+F55+F56 -> 30240009 | G58: =G41+G46+G51+G52+G54+G55+G56 -> 23646666 | H58: =H41+H46+H51+H52+H54+H55+H56 -> 26894173 | I58: =I41+I46+I51+I52+I54+I55+I56 -> 30203377 | J58: =J41+J46+J51+J52+J54+J55+J56 -> 27552771 | K58: =K41+K46+K51+K52+K54+K55+K56 -> 31798187 | ... O58: =O41+O46+O51+O52+O54+O55+O56 -> 40916528 | P58: =SUM(D58:O58) -> 3.9694985e+08
A59: Cost/Vol. Produced | C59: Mk/m3 | D59: =D58/D9 -> 230.48183 | E59: =E58/E9 -> 238.05509 | F59: =F58/F9 -> 226.62726 | G59: =G58/G9 -> 183.06623 | H59: =H58/H9 -> 211.7468 | I59: =I58/I9 -> 251.07549 | J59: =J58/J9 -> 222.73865 | K59: =K58/K9 -> 207.66841 | ... P59: =P58/P9 -> 251.9683
A60: Cost/Vol. Billed | C60: Mk/m3 | D60: =D58/D22 -> 443.5944 | E60: =E58/E22 -> 402.62263 | F60: =F58/F22 -> 417.94523 | G60: =G58/G22 -> 318.07821 | H60: =H58/H22 -> 356.29444 | I60: =I58/I22 -> 397.82167 | J60: =J58/J22 -> 342.72088 | K60: =K58/K22 -> 394.36139 | ... P60: =P58/P22 -> 423.40798
A61: Permanent Staff Employed | C61: No | D61: 24 | E61: 24 | F61: 24 | G61: 24 | H61: 24 | I61: 24 | J61: 24 | K61: 33 | L61: 33 | M61: 33 | N61: 33 | O61: 33 | P61: =O61 -> 33
A62: Staff/Vol.1000m3 of Volume Produced/hour (12 hour day) | C62: No/1000m3 | D62: =(D61*1000*31)/D9 -> 5.7689176 | E62: =(E61*1000*31)/E9 -> 5.8919493 | F62: =(F61*1000*31)/F9 -> 5.5757485 | G62: =(G61*1000*31)/G9 -> 5.7598514 | H62: =(H61*1000*31)/H9 -> 5.8577604 | I62: =(I61*1000*31)/I9 -> 6.1847443 | J62: =(J61*1000*31)/J9 -> 6.0145513 | K62: =(K61*1000*31)/K9 -> 6.6810345 | ... P62: =(P61*1000*31)/P9 -> 0.64936054
A63: Temporary Staff Employed | C63: No | D63: 25 | E63: 25 | F63: 25 | G63: 47 | I63: 25 | J63: 105 | K63: 136 | L63: 52 | M63: 90 | N63: 91 | O63: 91 | P63: =SUM(D63:O63) -> 712
A65: Water Connections and Disconnections
A66: New Individual Water Connections | B66: Brought Forward | C66: No | D66: 1052 | E66: 1074 | F66: 1172 | G66: 1315 | H66: 1265 | I66: 1364 | J66: 1445 | K66: 838 | L66: 815 | M66: 857 | N66: 973 | O66: 810 | P66: =D66 -> 1052
B67: Applied this Month | C67: No | D67: 68 | E67: 123 | F67: 161 | G67: 27 | H67: 135 | I67: 111 | J67: 2134 | K67: 150 | L67: 108 | M67: 237 | N67: 200 | O67: 96 | P67: =SUM(D67:O67) -> 3550
B68: Done this Month Postpaid | C68: No | D68: 0 | E68: 7 | F68: 0 | G68: 0 | H68: 0 | I68: 0 | J68: 0 | K68: 0 | L68: 0 | M68: 0 | N68: 0 | O68: 0 | P68: =SUM(D68:O68) -> 7
B69: Done this Month Prepaid | C69: No | D69: 46 | E69: 18 | F69: 18 | G69: 77 | H69: 36 | I69: 30 | J69: 10 | K69: 6 | L69: 20 | M69: 121 | N69: 163 | O69: 190 | P69: =SUM(D69:O69) -> 735
B70: Total Done | C70: No | D70: =D68+D69 -> 46 | E70: =E68+E69 -> 25 | F70: =F68+F69 -> 18 | G70: =G68+G69 -> 77 | H70: 36 | I70: =I68+I69 -> 30 | J70: =J68+J69 -> 10 | K70: =K68+K69 -> 6 | L70: =L68+L69 -> 20 | M70: =M68+M69 -> 121 | N70: =N68+N69 -> 163 | O70: =O68+O69 -> 190 | P70: =P68+P69 -> 742
B71: Carried Forward | C71: No | D71: =D66+D67-D70 -> 1074 | E71: =E66+E67-E70 -> 1172 | F71: =F66+F67-F70 -> 1315 | G71: =G66+G67-G70 -> 1265 | H71: =H66+H67-H70 -> 1364 | I71: =I66+I67-I70 -> 1445 | J71: =J66+J67-J70 -> 3569 | K71: =K66+K67-K70 -> 982 | ... P71: =P66+P67-P70 -> 3860
A72: New Institutional Water Connections | B72: Brought Forward | C72: No | D72: 8 | E72: 8 | F72: 8 | G72: 8 | H72: 8 | I72: 8 | J72: 8 | K72: 8 | L72: 8 | P72: =D72 -> 8
B73: Applied this Month | C73: No | D73: 0 | E73: 0 | F73: 0 | G73: 0 | M73: 2 | N73: 2 | P73: =SUM(D73:O73) -> 4
B74: Done this Month Postpaid | C74: No | D74: 0 | E74: 0 | F74: 0 | G74: 0 | N74: 0 | P74: =SUM(D74:O74) -> 0
B75: Done this Month Prepaid | C75: No | D75: 0 | E75: 0 | F75: 0 | G75: 0 | M75: 2 | N75: 2 | P75: =SUM(D75:O75) -> 4
B76: Total Done | C76: No | D76: =D74+D75 -> 0 | E76: =E74+E75 -> 0 | F76: =F74+F75 -> 0 | G76: 0 | H76: =H74+H75 -> 0 | I76: =I74+I75 -> 0 | J76: =J74+J75 -> 0 | K76: =K74+K75 -> 0 | L76: =L74+L75 -> 0 | M76: =M74+M75 -> 2 | N76: =N74+N75 -> 2 | O76: =O74+O75 -> 0 | P76: =P74+P75 -> 4
B77: Carried Forward | C77: No | D77: =D72+D73-D76 -> 8 | E77: =E72+E73-E76 -> 8 | F77: =F72+F73-F76 -> 8 | G77: =G72+G73-G76 -> 8 | H77: =H72+H73-H76 -> 8 | I77: =I72+I73-I76 -> 8 | J77: =J72+J73-J76 -> 8 | K77: =K72+K73-K76 -> 8 | ... P77: =P72+P73-P76 -> 8
A78: New Commercial/Industrial Water Connections | B78: Brought Forward | C78: No | D78: 9 | E78: 9 | F78: 9 | G78: 9 | H78: 9 | I78: 9 | J78: 9 | K78: 9 | N78: 1 | O78: 1 | P78: =D78 -> 9
B79: Applied this Month | C79: No | D79: 0 | E79: 0 | F79: 0 | G79: 0 | M79: 10 | N79: 4 | O79: 8 | P79: =SUM(D79:O79) -> 22
B80: Done this Month Postpaid | C80: No | D80: 0 | E80: 0 | F80: 0 | G80: 0 | P80: =SUM(D80:O80) -> 0
B81: Done this Month Prepaid | C81: No | D81: 0 | E81: 0 | F81: 0 | G81: 0 | M81: 9 | N81: 4 | O81: 8 | P81: =SUM(D81:O81) -> 21
B82: Total Done | C82: No | D82: =D80+D81 -> 0 | E82: =E80+E81 -> 0 | F82: =F80+F81 -> 0 | G82: 0 | H82: =H80+H81 -> 0 | I82: =I80+I81 -> 0 | J82: =J80+J81 -> 0 | K82: =K80+K81 -> 0 | L82: =L80+L81 -> 0 | M82: 9 | N82: =N81+N80 -> 4 | O82: =O81+O80 -> 8 | P82: =P81+P80 -> 21
B83: Carried Forward | C83: No | D83: 8 | E83: =E78+E79-E82 -> 9 | F83: =F78+F79-F82 -> 9 | G83: =G78+G79-G82 -> 9 | H83: =H78+H79-H82 -> 9 | I83: =I78+I79-I82 -> 9 | J83: =J78+J79-J82 -> 9 | K83: =K78+K79-K82 -> 9 | L83: 9 | M83: =M78+M79-M82 -> 1 | N83: =N78+N79-N82 -> 1 | O83: =O78+O79-O82 -> 1 | P83: =P78+P79-P82 -> 10
A84: New CWP | B84: Brought Forward | C84: No | D84: 0 | E84: 0 | F84: 0 | G84: 0 | P84: =D84 -> 0
B85: Applied this Month | C85: No | D85: 0 | E85: 0 | F85: 0 | G85: 0 | P85: =SUM(D85:O85) -> 0
B86: Done this Month Postpaid | C86: No | D86: 0 | E86: 0 | F86: 0 | G86: 0 | P86: =SUM(D86:O86) -> 0
B87: Done this Month Prepaid | C87: No | D87: 0 | E87: 0 | F87: 0 | G87: 0 | P87: =SUM(D87:O87) -> 0
B88: Total Done | C88: No | D88: 0 | E88: 0 | F88: 0 | G88: 0 | H88: =H86+H87 -> 0 | I88: =I86+I87 -> 0 | J88: =J86+J87 -> 0 | K88: =K86+K87 -> 0 | L88: =L86+L87 -> 0 | M88: =M86+M87 -> 0 | N88: 0 | O88: 0 | P88: =SUM(D88:O88) -> 0
B89: Carried Forward | C89: No | D89: =D84+D85-D88 -> 0 | E89: =E84+E85-E88 -> 0 | F89: =F84+F85-F88 -> 0 | G89: =G84+G85-G88 -> 0 | H89: =H84+H85-H88 -> 0 | I89: =I84+I85-I88 -> 0 | J89: =J84+J85-J88 -> 0 | K89: =K84+K85-K88 -> 0 | ... M89: =M84+M85-M88 -> 0 | N89: =N84+N85-N86-N87 -> 0 | O89: =O84+O85-O86-O87 -> 0 | P89: =P84+P85-P86-P87 -> 0
A90: Aggregated New Water connections | B90: Brought Forward | C90: No | D90: =D66+D72+D78+D84 -> 1069 | E90: =E66+E72+E78+E84 -> 1091 | F90: =F66+F72+F78+F84 -> 1189 | G90: =G66+G72+G78+G84 -> 1332 | H90: =H66+H72+H78+H84 -> 1282 | I90: =I66+I72+I78+I84 -> 1381 | J90: =J66+J72+J78+J84 -> 1462 | K90: =K66+K72+K78+K84 -> 855 | ... O90: =O66+O72+O78+O84 -> 811 | P90: =D90 -> 1069
B91: Applied this Month | C91: No | D91: =D67+D73+D79+D85 -> 68 | E91: =E67+E73+E79+E85 -> 123 | F91: =F67+F73+F79+F85 -> 161 | G91: =G67+G73+G79+G85 -> 27 | H91: =H67+H73+H79+H85 -> 135 | I91: =I67+I73+I79+I85 -> 111 | J91: =J67+J73+J79+J85 -> 2134 | K91: =K67+K73+K79+K85 -> 150 | ... O91: =O67+O73+O79+O85 -> 104 | P91: =SUM(D91:O91) -> 3576
B92: Done this Month Postpaid | C92: No | D92: =D68+D74+D80+D86 -> 0 | E92: =E68+E74+E80+E86 -> 7 | F92: =F68+F74+F80+F86 -> 0 | G92: =G68+G74+G80+G86 -> 0 | H92: =H68+H74+H80+H86 -> 0 | I92: =I68+I74+I80+I86 -> 0 | J92: =J68+J74+J80+J86 -> 0 | K92: =K68+K74+K80+K86 -> 0 | ... O92: =O68+O74+O80+O86 -> 0 | P92: =SUM(D92:O92) -> 7
B93: Done this Month Prepaid | D93: =D69+D75+D81+D87 -> 46 | E93: =E69+E75+E81+E87 -> 18 | F93: =F69+F75+F81+F87 -> 18 | G93: =G69+G75+G81+G87 -> 77 | H93: =H69+H75+H81+H87 -> 36 | I93: =I69+I75+I81+I87 -> 30 | J93: =J69+J75+J81+J87 -> 10 | K93: =K69+K75+K81+K87 -> 6 | ... O93: =O69+O75+O81+O87 -> 198 | P93: =SUM(D93:O93) -> 760
B94: Total Done | C94: No | D94: =D93+D92 -> 46 | E94: =E93+E92 -> 25 | F94: =F93+F92 -> 18 | G94: =G93+G92 -> 77 | H94: =H93+H92 -> 36 | I94: =I93+I92 -> 30 | J94: =J93+J92 -> 10 | K94: =K93+K92 -> 6 | ... P94: =P93+P92 -> 767
B95: Carried Forward | C95: No | D95: =D90+D91-D94 -> 1091 | E95: =E90+E91-E94 -> 1189 | F95: =F90+F91-F94 -> 1332 | G95: =G90+G91-G94 -> 1282 | H95: =H90+H91-H94 -> 1381 | I95: =I90+I91-I94 -> 1462 | J95: =J90+J91-J94 -> 3586 | K95: =K90+K91-K94 -> 999 | ... P95: =P90+P91-P94 -> 3878
D96: 0 | E96: 0 | F96: 0 | G96: 0 | H96: 0
A97: Prepaid Metering
A98: Prepaid Meters Installed | C98: No | D98: 46 | E98: 20 | F98: 18 | G98: 86 | H98: 36 | I98: 30 | J98: 10 | K98: 6 | L98: 20 | M98: 132 | N98: 169 | O98: 198 | P98: =SUM(D98:O98) -> 771
D99: 0 | E99: 0 | F99: 0 | G99: 0 | H99: 0 | I99: 0 | J99: 0 | K99: 0
A100: Active and Disconnected Accounts
A101: Disconnected Individual Accounts | C101: No | D101: 1882 | E101: 1878 | F101: 1855 | G101: 1831 | H101: 1826 | I101: 1796 | J101: 1777 | K101: 1764 | L101: 1745 | M101: 1873 | N101: 1867 | O101: 1850 | P101: =O101 -> 1850
A102: Disconnected institutional Accounts | C102: No | D102: 3 | E102: 4 | F102: 4 | G102: 5 | H102: 5 | I102: 5 | J102: 5 | K102: 5 | L102: 3 | M102: 2 | N102: 2 | O102: 2 | P102: =O102 -> 2
A103: Disconnected Commercial/Industrial Accounts | C103: No | D103: 141 | E103: 139 | F103: 141 | G103: 141 | H103: 142 | I103: 142 | J103: 141 | K103: 141 | L103: 141 | M103: 142 | N103: 141 | O103: 142 | P103: =O103 -> 142
...

Sheet Monkey Bay
A1: SOUTHERN REGION WATER BOARD
A3: MONTHLY REPORTS - 2023/2024
A4: MANGOCHI ZONE
A5: MANGOCHI ZONE
A7: PARAMETERS | C7: UNITS | D7: APRIL | E7: MAY | F7: JUNE | G7: JULY | H7: AUGUST | I7: SEPTEMBER | J7: OCTOBER | K7: NOVEMBER | L7: DECEMBER | M7: JANUARY | N7: FEBRUARY | O7: MARCH | P7: TOTALS
A8: PRODUCTION
A9: Volume Produced | C9: m3 | D9: 55692 | E9: 62300 | F9: 62717 | G9: 59070 | H9: 62919 | I9: 65109 | J9: 73800 | K9: 69579 | L9: 53793 | M9: 60549 | N9: 62890 | O9: 54660 | P9: =SUM(D9:O9) -> 743078
A10: REVENUE WATER - POSTPAID
A11: Volume Billed Individuals | C11: m3 | D11: 17067 | E11: 17057 | F11: 18777 | G11: 19307 | H11: 19682 | I11: 20446 | J11: 23429 | K11: 29339 | L11: 18848 | M11: 18956 | N11: 22084 | O11: 18370 | P11: =SUM(D11:O11) -> 243362
A12: Volume Billed CWPs | C12: m3 | D12: 0 | E12: 0 | F12: 0 | G12: 0 | P12: =SUM(D12:O12) -> 0
A13: Volume Billed Institutions | C13: m3 | D13: 20124 | E13: 18545 | F13: 22583 | G13: 21093 | H13: 18587 | I13: 29123 | J13: 22837 | K13: 21844 | L13: 12572 | M13: 24760 | N13: 21318 | O13: 21442 | P13: =SUM(D13:O13) -> 254828
A14: Volume Billed Commercial/Industrial | C14: m3 | D14: 855 | E14: 719 | F14: 7732 | G14: 717 | H14: 590 | I14: 60 | J14: 102 | K14: 151 | L14: 98 | M14: 90 | N14: 104 | O14: 80 | P14: =SUM(D14:O14) -> 11298
A15: Total Volume Billed Post Paid | C15: m3 | D15: =SUM(D11:D14) -> 38046 | E15: =SUM(E11:E14) -> 36321 | F15: =SUM(F11:F14) -> 49092 | G15: =SUM(G11:G14) -> 41117 | H15: =SUM(H11:H14) -> 38859 | I15: =SUM(I11:I14) -> 49629 | J15: =SUM(J11:J14) -> 46368 | K15: =SUM(K11:K14) -> 51334 | ... P15: =SUM(P11:P14) -> 509488
A16: REVENUE WATER - PREPAID
A17: Individuals | C17: m3 | D17: 2147 | E17: 2953 | F17: 2866 | G17: 3265 | H17: 2916 | I17: 3004 | J17: 3124 | K17: 3025 | L17: 11038 | M17: 2957 | N17: 2818 | O17: 3261 | P17: =SUM(D17:O17) -> 43374
A18: CWPs | C18: m3 | D18: 1201 | E18: 1204 | F18: 1117 | G18: 1425 | H18: 1203 | I18: 1159 | J18: 1219 | K18: 1021 | M18: 1498 | N18: 1601 | O18: 1354 | P18: =SUM(D18:O18) -> 14002
A19: Institutions | C19: m3 | D19: 2821 | E19: 3616 | F19: 2878 | G19: 2311 | H19: 2905 | I19: 3579 | J19: 3724 | K19: 3856 | M19: 5001 | N19: 4672 | O19: 3363 | P19: =SUM(D19:O19) -> 38726
A20: Commercial/Industrial | C20: m3 | D20: 395 | E20: 539 | F20: 461 | G20: 294 | H20: 485 | I20: 495 | J20: 485 | K20: 401 | M20: 501 | N20: 496 | O20: 388 | P20: =SUM(D20:O20) -> 4940
A21: Total Volume Prepaid | C21: m3 | D21: =SUM(D17:D20) -> 6564 | E21: =SUM(E17:E20) -> 8312 | F21: =SUM(F17:F20) -> 7322 | G21: =SUM(G17:G20) -> 7295 | H21: =SUM(H17:H20) -> 7509 | I21: =SUM(I17:I20) -> 8237 | J21: =SUM(J17:J20) -> 8552 | K21: 8303 | L21: =SUM(L17:L20) -> 11038 | M21: =SUM(M17:M20) -> 9957 | N21: =SUM(N17:N20) -> 9587 | O21: =SUM(O17:O20) -> 8366 | P21: =SUM(P17:P20) -> 101042
A22: TOTAL REVENUE WATER | C22: m3 | D22: =D21+D15 -> 44610 | E22: =E21+E15 -> 44633 | F22: =F21+F15 -> 56414 | G22: =G21+G15 -> 48412 | H22: =H21+H15 -> 46368 | I22: =I21+I15 -> 57866 | J22: =J21+J15 -> 54920 | K22: =K21+K15 -> 59637 | ... P22: =P21+P15 -> 610530
A24: Non-Revenue Water (NRW) | B24: Volume | C24: m3 | D24: =D9-D22 -> 11082 | E24: =E9-E22 -> 17667 | F24: =F9-F22 -> 6303 | G24: =G9-G22 -> 10658 | H24: =H9-H22 -> 16551 | I24: =I9-I22 -> 7243 | J24: =J9-J22 -> 18880 | K24: =K9-K22 -> 9942 | ... P24: =P9-P22 -> 132548
B25: Percentage | C25: % | D25: =D24/D9 -> 0.19898729 | E25: =E24/E9 -> 0.28357945 | F25: =F24/F9 -> 0.10049907 | G25: =G24/G9 -> 0.18043 | H25: =H24/H9 -> 0.2630525 | I25: =I24/I9 -> 0.11124422 | J25: =J24/J9 -> 0.25582656 | K25: =K24/K9 -> 0.14288794 | ... P25: =P24/P9 -> 0.17837697
A26: OPERATING EXPENSES
A27: Chemicals
A28: Chemical | B28: Rate(MK/kg)
A29: Chlorine | B29: =176264.5/50 -> 3525.29 | C29: kg | D29: 150 | E29: 155 | F29: 150 | G29: 155 | H29: 155 | I29: 150 | J29: 155 | K29: 155 | L29: 155 | M29: 155 | N29: 145 | O29: 155 | P29: =SUM(D29:O29) -> 1835
C30: kg/mg litre | D30: =D29/(D9/1000) -> 2.693385 | E30: =E29/(E9/1000) -> 2.4879615 | F30: =F29/(F9/1000) -> 2.391696 | G30: =G29/(G9/1000) -> 2.6240054 | H30: =H29/(H9/1000) -> 2.4634848 | I30: =I29/(I9/1000) -> 2.303829 | J30: =J29/(J9/1000) -> 2.100271 | K30: =K29/(K9/1000) -> 2.2276836 | ... P30: =P29/(P9/1000) -> 2.4694581
A31: Aluminium sulphate | B31: =53000.511/50 -> 1060.0102 | C31: kg | P31: =SUM(D31:O31) -> 0
C32: kg/mg litre | D32: =D31/(D9/1000) -> 0 | E32: =E31/(E9/1000) -> 0 | F32: =F31/(F9/1000) -> 0 | G32: =G31/(G9/1000) -> 0 | H32: =H31/(H9/1000) -> 0 | I32: =I31/(I9/1000) -> 0 | J32: =J31/(J9/1000) -> 0 | K32: =K31/(K9/1000) -> 0 | ... P32: =P31/(P9/1000) -> 0
A33: Soda | B33: =61414.43/50 -> 1228.2886 | C33: kg | P33: =SUM(D33:O33) -> 0
C34: kg/mg litre | D34: =D33/(D9/1000) -> 0 | E34: =E33/(E9/1000) -> 0 | F34: =F33/(F9/1000) -> 0 | G34: =G33/(G9/1000) -> 0 | H34: =H33/(H9/1000) -> 0 | I34: =I33/(I9/1000) -> 0 | J34: =J33/(J9/1000) -> 0 | K34: =K33/(K9/1000) -> 0 | ... P34: =P33/(P9/1000) -> 0
A35: Algae floc | B35: =745345.16/200 -> 3726.7258 | C35: litres
C36: litres/mg litre
A37: Sud floc | B37: =790318.72/200 -> 3951.5936 | C37: litres | D37: 0 | E37: 0 | F37: 0 | G37: 0 | H37: 0 | I37: 0 | J37: 0 | K37: 0 | L37: 0 | M37: 0 | N37: 0 | O37: 0 | P37: =SUM(D37:O37) -> 0
C38: litres/mg litre | D38: =D37/(D9/1000) -> 0 | E38: =E37/(E9/1000) -> 0 | F38: =F37/(F9/1000) -> 0 | G38: =G37/(G9/1000) -> 0 | H38: =H37/(H9/1000) -> 0 | I38: =I37/(I9/1000) -> 0 | J38: =J37/(J9/1000) -> 0 | K38: =K37/(K9/1000) -> 0 | ... P38: =P37/(P9/1000) -> 0
A39: Potasium permanganate | B39: 1950 | C39: kg | D39: 0 | E39: 0 | F39: 0 | G39: 0 | H39: 0 | I39: 0 | J39: 0 | K39: 0 | L39: 0 | M39: 0 | N39: 0 | O39: 0 | P39: =SUM(D39:O39) -> 0
C40: kg/mg litre | D40: =D39/(D9/1000) -> 0 | E40: =E39/(E9/1000) -> 0 | F40: =F39/(F9/1000) -> 0 | G40: =G39/(G9/1000) -> 0 | H40: =H39/(H9/1000) -> 0 | I40: =I39/(I9/1000) -> 0 | J40: =J39/(J9/1000) -> 0 | K40: =K39/(K9/1000) -> 0 | ... P40: =P39/(P9/1000) -> 0
A41: Cost of Chemicals | C41: Mk | D41: =(D29*$B29)+(D31*$B31)+(D33*$B33)+(D35*$B35)+(D37*$B37)+(D39*$B39) -> 528793.5 | E41: =(E29*$B29)+(E31*$B31)+(E33*$B33)+(E35*$B35)+(E37*$B37)+(E39*$B39) -> 546419.95 | F41: =(F29*$B29)+(F31*$B31)+(F33*$B33)+(F35*$B35)+(F37*$B37)+(F39*$B39) -> 528793.5 | G41: =(G29*$B29)+(G31*$B31)+(G33*$B33)+(G35*$B35)+(G37*$B37)+(G39*$B39) -> 546419.95 | H41: =(H29*$B29)+(H31*$B31)+(H33*$B33)+(H35*$B35)+(H37*$B37)+(H39*$B39) -> 546419.95 | I41: =(I29*$B29)+(I31*$B31)+(I33*$B33)+(I35*$B35)+(I37*$B37)+(I39*$B39) -> 528793.5 | J41: =(J29*$B29)+(J31*$B31)+(J33*$B33)+(J35*$B35)+(J37*$B37)+(J39*$B39) -> 546419.95 | K41: =(K29*$B29)+(K31*$B31)+(K33*$B33)+(K35*$B35)+(K37*$B37)+(K39*$B39) -> 546419.95 | ... O41: =(O29*$B29)+(O31*$B31)+(O33*$B33)+(O35*$B35)+(O37*$B37)+(O39*$B39) -> 546419.95 | P41: =SUM(D41:O41) -> 6468907.2
A42: Cost/vol. Produced (chemicals) | C42: Mk/m3 | D42: =D41/D9 -> 9.4949634 | E42: =E41/E9 -> 8.7707857 | F42: =F41/F9 -> 8.4314221 | G42: =G41/G9 -> 9.2503801 | H42: =H41/H9 -> 8.6844983 | I42: =I41/I9 -> 8.1216652 | J42: =J41/J9 -> 7.4040644 | K42: =K41/K9 -> 7.8532309 | ... P42: =P41/P9 -> 8.705556
A43: Power
A44: Power Usage | C44: Kw | D44: 25477 | E44: 27187 | F44: 27608 | G44: 28581 | H44: 27335 | I44: 29830 | J44: 32075 | K44: 29315 | L44: 27517 | M44: 26891 | N44: 28859 | O44: 24362 | P44: =SUM(D44:O44) -> 335037
A45: Power/ Vol. Produced | C45: Kw/m3 | D45: =D44/D9 -> 0.45746247 | E45: =E44/E9 -> 0.43638844 | F45: =F44/F9 -> 0.44019963 | G45: =G44/G9 -> 0.48384967 | H45: =H44/H9 -> 0.43444746 | I45: =I44/I9 -> 0.45815479 | J45: =J44/J9 -> 0.4346206 | K45: =K44/K9 -> 0.42131965 | ... P45: =P44/P9 -> 0.4508773
A46: Cost of Power | C46: Mk | D46: =1.165*(14100+(D44*119.1)) -> 3551398.5 | E46: =1.165*(14100+(E44*119.1)) -> 3788663.5 | F46: =1.165*(14100+(F44*119.1)) -> 3847077.9 | G46: =1.165*(14100+(G44*119.1)) -> 3982083.1 | H46: =1.165*(16600+(H44*143.5)) -> 4589136 | I46: =1.165*(16600+(I44*143.5)) -> 5006243.8 | J46: =1.165*(16600+(J44*143.5)) -> 5381557.3 | K46: =1.165*(16600+(K44*143.5)) -> 4920147.4 | L46: =1.165*(16600+(L44*143.5)) -> 4619562.3 | M46: =1.165*(16600+(M44*143.5)) -> 4514909.2 | N46: =1.165*(16600+(N44*143.5)) -> 4843914.5 | O46: =1.165*(16600+(O44*143.5)) -> 4092117.3 | P46: =SUM(D46:O46) -> 53136811
A47: Cost/vol. Produced | C47: Mk/m3 | D47: =D46/D9 -> 63.768557 | E47: =E46/E9 -> 60.813219 | F47: =F46/F9 -> 61.340273 | G47: =G46/G9 -> 67.412953 | H47: =H46/H9 -> 72.937204 | I47: =I46/I9 -> 76.890197 | J47: =J46/J9 -> 72.920831 | K47: =K46/K9 -> 70.713109 | ... P47: =P46/P9 -> 71.509062
A48: Plant and Vehicle Maintenance
A49: Distances covered | C49: km | D49: 2175 | E49: 268 | F49: 2384 | G49: 2900 | H49: 3016 | I49: 4159 | J49: 6631 | K49: 5222 | L49: 3622 | M49: 4729 | N49: 1629 | O49: 843 | P49: =SUM(D49:O49) -> 37578
A50: Fuel Used (litres) | C50: litres | D50: 207 | E50: 58.6 | F50: 183.2 | G50: 176 | H50: 247 | I50: 266.9 | J50: 520.4 | K50: 333 | L50: 192.5 | M50: 364 | N50: 208 | O50: 93 | P50: =SUM(D50:O50) -> 2849.6
A51: Cost of fuel | C51: Mk | D51: 397440 | E51: 112512 | F51: 351744 | G51: 338308 | H51: 474240 | I51: 512448 | J51: 199168 | K51: 910422 | L51: 526295 | M51: 995176 | N51: 568672 | O51: 254262 | P51: =SUM(D51:O51) -> 5640687
A52: Maintenance | C52: Mk | D52: 0 | E52: 0 | F52: 0 | G52: 0 | H52: 0 | I52: 0 | J52: 0 | K52: 0 | L52: 0 | M52: 0 | N52: 0 | O52: 0 | P52: =SUM(D52:O52) -> 0
A53: Salaries and Wages
A54: Staff Costs | C54: MK | D54: 3513729.9 | E54: 4297411.6 | F54: 3419523.3 | G54: 3292981.3 | H54: 3695021.4 | I54: 3247315.1 | J54: 2367032.7 | K54: 2609689 | L54: 3490323.8 | M54: 3509235 | N54: 3509235 | O54: 3126948 | P54: =SUM(D54:O54) -> 40078446
A55: Wages | C55: MK | D55: 590385.56 | E55: 613462.52 | F55: 525722 | G55: 521154.68 | H55: 533654.7 | I55: 1166828.8 | J55: 3118755 | K55: 2321157.6 | L55: 2392311.5 | M55: 2268513.2 | N55: 1181250.5 | O55: 1070481.2 | P55: =SUM(D55:O55) -> 16303677
A56: Other Overhead Costs | C56: MK | D56: 425000 | E56: 425100 | F56: 427350 | G56: 431200 | H56: 432750 | I56: 436200 | J56: 439200 | K56: 443750 | L56: 447400 | M56: 453800 | N56: 448100 | O56: 462100 | P56: =SUM(D56:O56) -> 5271950
A57: Operating Costs
A58: Total Operating Costs | C58: MK | D58: =D41+D46+D51+D52+D54+D55+D56 -> 9006747.4 | E58: =E41+E46+E51+E52+E54+E55+E56 -> 9783569.6 | F58: =F41+F46+F51+F52+F54+F55+F56 -> 9100210.7 | G58: =G41+G46+G51+G52+G54+G55+G56 -> 9112147 | H58: =H41+H46+H51+H52+H54+H55+H56 -> 10271222 | I58: =I41+I46+I51+I52+I54+I55+I56 -> 10897829 | J58: =J41+J46+J51+J52+J54+J55+J56 -> 12052133 | K58: =K41+K46+K51+K52+K54+K55+K56 -> 11751586 | ... O58: =O41+O46+O51+O52+O54+O55+O56 -> 9552328.5 | P58: =SUM(D58:O58) -> 1.2690048e+08
A59: Cost/Vol. Produced | C59: Mk/m3 | D59: =D58/D9 -> 161.72426 | E59: =E58/E9 -> 157.03964 | F59: =F58/F9 -> 145.09959 | G59: =G58/G9 -> 154.26015 | H59: =H58/H9 -> 163.24516 | I59: =I58/I9 -> 167.37823 | J59: =J58/J9 -> 163.30803 | K59: =K58/K9 -> 168.89558 | ... P59: =P58/P9 -> 170.77679
A60: Cost/Vol. Billed | C60: Mk/m3 | D60: =D58/D22 -> 201.89974 | E60: =E58/E22 -> 219.20036 | F60: =F58/F22 -> 161.31121 | G60: =G58/G22 -> 188.22083 | H60: =H58/H22 -> 221.51531 | I60: =I58/I22 -> 188.32871 | J60: =J58/J22 -> 219.44889 | K60: =K58/K22 -> 197.05193 | ... P60: =P58/P22 -> 207.85298
A61: Permanent Staff Employed | C61: No | D61: 7 | E61: 7 | F61: 5 | G61: 7 | H61: 7 | I61: 7 | J61: 6 | K61: 6 | L61: 6 | M61: 7 | N61: 6 | O61: 6 | P61: =O61 -> 6
A62: Staff/Vol.1000m3 of Volume Produced/hour (12 hour day) | C62: No/1000m3 | D62: =(D61*1000*31)/D9 -> 3.8964304 | E62: =(E61*1000*31)/E9 -> 3.4831461 | F62: =(F61*1000*31)/F9 -> 2.4714192 | G62: =(G61*1000*31)/G9 -> 3.6736076 | H62: =(H61*1000*31)/H9 -> 3.4488787 | I62: =(I61*1000*31)/I9 -> 3.3328726 | J62: =(J61*1000*31)/J9 -> 2.5203252 | K62: =(K61*1000*31)/K9 -> 2.6732204 | ... P62: =(P61*1000*31)/P9 -> 0.2503102
A63: Temporary Staff Employed | C63: No | D63: 9 | E63: 9 | F63: 9 | G63: 9 | H63: 9 | I63: 9 | J63: 12 | K63: 12 | L63: 38 | M63: 9 | N63: 20 | O63: 20 | P63: =SUM(D63:O63) -> 165
A65: Water Connections and Disconnections
A66: New Individual Water Connections | B66: Brought Forward | C66: No | D66: 99 | E66: 97 | F66: 111 | G66: 66 | H66: 91 | I66: 81 | J66: 70 | K66: 73 | L66: 96 | M66: 90 | N66: 79 | O66: 89 | P66: =D66 -> 99
B67: Applied this Month | C67: No | D67: 5 | E67: 24 | F67: 12 | G67: 22 | H67: 24 | I67: 3 | J67: 9 | K67: 5 | L67: 21 | M67: 17 | N67: 10 | O67: 23 | P67: =SUM(D67:O67) -> 175
B68: Done this Month Postpaid | C68: No | D68: 0 | E68: 0 | F68: 0 | G68: 0 | L68: 20 | M68: 0 | N68: 0 | O68: 5 | P68: =SUM(D68:O68) -> 25
B69: Done this Month Prepaid | C69: No | D69: 7 | E69: 10 | F69: 10 | G69: 26 | H69: 14 | I69: 4 | J69: 12 | K69: 28 | L69: 0 | M69: 28 | N69: 0 | O69: 0 | P69: =SUM(D69:O69) -> 139
B70: Total Done | C70: No | D70: =D68+D69 -> 7 | E70: =E68+E69 -> 10 | F70: =F68+F69 -> 10 | G70: =G68+G69 -> 26 | H70: 14 | I70: =I68+I69 -> 4 | J70: =J68+J69 -> 12 | K70: =K68+K69 -> 28 | L70: =L68+L69 -> 20 | M70: =M68+M69 -> 28 | N70: =N68+N69 -> 0 | O70: =O68+O69 -> 5 | P70: =P68+P69 -> 164
B71: Carried Forward | C71: No | D71: =D66+D67-D70 -> 97 | E71: =E66+E67-E70 -> 111 | F71: =F66+F67-F70 -> 113 | G71: =G66+G67-G70 -> 62 | H71: =H66+H67-H70 -> 101 | I71: =I66+I67-I70 -> 80 | J71: =J66+J67-J70 -> 67 | K71: =K66+K67-K70 -> 50 | ... P71: =P66+P67-P70 -> 110
A72: New Institutional Water Connections | B72: Brought Forward | C72: No | D72: 0 | E72: 0 | F72: 0 | G72: 0 | P72: =D72 -> 0
B73: Applied this Month | C73: No | D73: 0 | E73: 0 | F73: 0 | G73: 0 | P73: =SUM(D73:O73) -> 0
B74: Done this Month Postpaid | C74: No | D74: 0 | E74: 0 | F74: 0 | G74: 0 | P74: =SUM(D74:O74) -> 0
B75: Done this Month Prepaid | C75: No | D75: 0 | E75: 0 | F75: 0 | G75: 0 | P75: =SUM(D75:O75) -> 0
B76: Total Done | C76: No | D76: 0 | E76: 0 | F76: 0 | G76: =G74+G75 -> 0 | H76: =H74+H75 -> 0 | I76: =I74+I75 -> 0 | J76: =J74+J75 -> 0 | K76: =K74+K75 -> 0 | L76: =L74+L75 -> 0 | M76: =M74+M75 -> 0 | N76: =N74+N75 -> 0 | ... P76: =P74+P75 -> 0
B77: Carried Forward | C77: No | D77: =D72+D73-D76 -> 0 | E77: =E72+E73-E76 -> 0 | F77: =F72+F73-F76 -> 0 | G77: =G72+G73-G76 -> 0 | H77: =H72+H73-H76 -> 0 | I77: =I72+I73-I76 -> 0 | J77: =J72+J73-J76 -> 0 | K77: =K72+K73-K76 -> 0 | ... P77: =P72+P73-P76 -> 0
A78: New Commercial/Industrial Water Connections | B78: Brought Forward | C78: No | D78: 2 | E78: 2 | F78: 2 | G78: 2 | H78: 2 | I78: 2 | J78: 2 | K78: 2 | L78: 2 | P78: =D78 -> 2
B79: Applied this Month | C79: No | D79: 2 | E79: 0 | F79: 0 | G79: 0 | I79: 0 | L79: 3 | P79: =SUM(D79:O79) -> 5
B80: Done this Month Postpaid | C80: No | D80: 0 | E80: 0 | F80: 0 | G80: 0 | P80: =SUM(D80:O80) -> 0
B81: Done this Month Prepaid | C81: No | D81: 2 | E81: 2 | F81: 0 | G81: 0 | I81: 2 | P81: =SUM(D81:O81) -> 6
B82: Total Done | C82: No | D82: =D81+D80 -> 2 | E82: =E81+E80 -> 2 | F82: =F81+F80 -> 0 | G82: =G81+G80 -> 0 | H82: =H81+H80 -> 0 | I82: =I81+I80 -> 2 | J82: =J81+J80 -> 0 | K82: =K81+K80 -> 0 | ... P82: =P81+P80 -> 6
B83: Carried Forward | C83: No | D83: =D78+D79-D82 -> 2 | E83: =E78+E79-E82 -> 0 | F83: =F78+F79-F82 -> 2 | G83: =G78+G79-G82 -> 2 | H83: =H78+H79-H82 -> 2 | I83: =I78+I79-I82 -> 0 | J83: =J78+J79-J82 -> 2 | K83: =K78+K79-K82 -> 2 | ... P83: =P78+P79-P82 -> 1
A84: New CWP | B84: Brought Forward | C84: No | D84: 0 | E84: 0 | F84: 0 | G84: 0 | P84: =D84 -> 0
B85: Applied this Month | C85: No | D85: 0 | E85: 0 | F85: 0 | G85: 0 | P85: =SUM(D85:O85) -> 0
B86: Done this Month Postpaid | C86: No | D86: 0 | E86: 0 | F86: 0 | G86: 0 | P86: =SUM(D86:O86) -> 0
B87: Done this Month Prepaid | C87: No | D87: 0 | E87: 0 | F87: 0 | G87: 0 | P87: =SUM(D87:O87) -> 0
B88: Total Done | C88: No | D88: =D87+D86 -> 0 | E88: =E87+E86 -> 0 | F88: =F87+F86 -> 0 | G88: =G87+G86 -> 0 | H88: =H87+H86 -> 0 | I88: =I87+I86 -> 0 | J88: =J87+J86 -> 0 | K88: =K87+K86 -> 0 | ... O88: =O87+O86 -> 0 | P88: =SUM(D88:O88) -> 0
B89: Carried Forward | C89: No | D89: =D84+D85-D88 -> 0 | E89: =E84+E85-E88 -> 0 | F89: =F84+F85-F88 -> 0 | G89: =G84+G85-G88 -> 0 | H89: =H84+H85-H88 -> 0 | I89: =I84+I85-I88 -> 0 | J89: =J84+J85-J88 -> 0 | K89: =K84+K85-K88 -> 0 | ... O89: =O84+O85-O88 -> 0 | P89: =P84+P85-P86-P87 -> 0
A90: Aggregated New Water connections | B90: Brought Forward | C90: No | D90: =D66+D72+D78+D84 -> 101 | E90: =E66+E72+E78+E84 -> 99 | F90: =F66+F72+F78+F84 -> 113 | G90: =G66+G72+G78+G84 -> 68 | H90: =H66+H72+H78+H84 -> 93 | I90: =I66+I72+I78+I84 -> 83 | J90: =J66+J72+J78+J84 -> 72 | K90: =K66+K72+K78+K84 -> 75 | ... O90: =O66+O72+O78+O84 -> 89 | P90: =D90 -> 101
B91: Applied this Month | C91: No | D91: =D67+D73+D79+D85 -> 7 | E91: =E67+E73+E79+E85 -> 24 | F91: =F67+F73+F79+F85 -> 12 | G91: =G67+G73+G79+G85 -> 22 | H91: =H67+H73+H79+H85 -> 24 | I91: =I67+I73+I79+I85 -> 3 | J91: =J67+J73+J79+J85 -> 9 | K91: =K67+K73+K79+K85 -> 5 | ... O91: =O67+O73+O79+O85 -> 23 | P91: =SUM(D91:O91) -> 180
B92: Done this Month Postpaid | C92: No | D92: =D68+D74+D80+D86 -> 0 | E92: =E68+E74+E80+E86 -> 0 | F92: =F68+F74+F80+F86 -> 0 | G92: =G68+G74+G80+G86 -> 0 | H92: =H68+H74+H80+H86 -> 0 | I92: =I68+I74+I80+I86 -> 0 | J92: =J68+J74+J80+J86 -> 0 | K92: =K68+K74+K80+K86 -> 0 | ... O92: =O68+O74+O80+O86 -> 5 | P92: =SUM(D92:O92) -> 25
B93: Done this Month Prepaid | D93: =D69+D75+D81+D87 -> 9 | E93: =E69+E75+E81+E87 -> 12 | F93: =F69+F75+F81+F87 -> 10 | G93: =G69+G75+G81+G87 -> 26 | H93: =H69+H75+H81+H87 -> 14 | I93: =I69+I75+I81+I87 -> 6 | J93: =J69+J75+J81+J87 -> 12 | K93: =K69+K75+K81+K87 -> 28 | ... O93: =O69+O75+O81+O87 -> 0 | P93: =SUM(D93:O93) -> 145
B94: Total Done | C94: No | D94: =D93+D92 -> 9 | E94: =E93+E92 -> 12 | F94: =F93+F92 -> 10 | G94: =G93+G92 -> 26 | H94: =H93+H92 -> 14 | I94: =I93+I92 -> 6 | J94: =J93+J92 -> 12 | K94: =K93+K92 -> 28 | ... P94: =P93+P92 -> 170
B95: Carried Forward | C95: No | D95: =D90+D91-D94 -> 99 | E95: =E90+E91-E94 -> 111 | F95: =F90+F91-F94 -> 115 | G95: =G90+G91-G94 -> 64 | H95: =H90+H91-H94 -> 103 | I95: =I90+I91-I94 -> 80 | J95: =J90+J91-J94 -> 69 | K95: =K90+K91-K94 -> 52 | ... P95: =P90+P91-P94 -> 111
A97: Prepaid Metering
A98: Prepaid Meters Installed | C98: No | D98: 9 | E98: 12 | F98: 10 | G98: 26 | H98: 14 | I98: 6 | J98: 12 | K98: 28 | L98: 103 | M98: 28 | N98: 0 | O98: 0 | P98: =SUM(D98:O98) -> 248
A100: Active and Disconnected Accounts
A101: Disconnected Individual Accounts | C101: No | D101: 457 | E101: 445 | F101: 425 | G101: 427 | H101: 400 | I101: 397 | J101: 381 | K101: 350 | L101: 330 | M101: 331 | N101: 326 | O101: 328 | P101: =O101 -> 328
A102: Disconnected institutional Accounts | C102: No | D102: 0 | E102: 0 | F102: 0 | G102: 0 | H102: 0 | I102: 0 | J102: 0 | K102: 0 | L102: 0 | M102: 0 | N102: 0 | O102: 0 | P102: =O102 -> 0
A103: Disconnected Commercial/Industrial Accounts | C103: No | D103: 0 | E103: 0 | F103: 0 | G103: 0 | H103: 0 | I103: 0 | J103: 0 | K103: 0 | L103: 0 | M103: 0 | N103: 0 | O103: 0 | P103: =O103 -> 0
A104: Disconnected CWP | C104: No | D104: 0 | E104: 0 | F104: 0 | G104: 0 | H104: 0 | I104: 0 | J104: 0 | K104: 0 | L104: 0 | M104: 0 | N104: 0 | O104: 0 | P104: =O104 -> 0
A105: Total Disconnected Accounts | C105: No | D105: =SUM(D101:D104) -> 457 | E105: =SUM(E101:E104) -> 445 | F105: =SUM(F101:F104) -> 425 | G105: =SUM(G101:G104) -> 427 | H105: =SUM(H101:H104) -> 400 | I105: =SUM(I101:I104) -> 397 | J105: =SUM(J101:J104) -> 381 | K105: =SUM(K101:K104) -> 350 | ... O105: =SUM(O101:O104) -> 328 | P105: =O105 -> 328
A106: Postpaid Consumers
...

Sheet Namwera
A1: SOUTHERN REGION WATER BOARD
A3: MONTHLY REPORTS - 2023/2024
A4: MANGOCHI ZONE
A5: MANGOCHI ZONE
A7: PARAMETERS | C7: UNITS | D7: APRIL | E7: MAY | F7: JUNE | G7: JULY | H7: AUGUST | I7: SEPTEMBER | J7: OCTOBER | K7: NOVEMBER | L7: DECEMBER | M7: JANUARY | N7: FEBRUARY | O7: MARCH | P7: TOTALS
A8: PRODUCTION
A9: Volume Produced | C9: m3 | D9: 4151 | E9: 6307 | F9: 5434 | G9: 5272 | H9: 4870 | I9: 6120 | J9: 5217 | K9: 4619 | L9: 4389 | M9: 4509 | N9: 4052 | O9: 3782 | P9: =SUM(D9:O9) -> 58722
A10: REVENUE WATER - POSTPAID
A11: Volume Billed Individuals | C11: m3 | D11: 1751 | E11: 1706 | F11: 2117 | G11: 2161 | H11: 1868 | I11: 2079 | J11: 2011 | K11: 1825 | L11: 2027 | M11: 1559 | N11: 1915 | O11: 1719 | P11: =SUM(D11:O11) -> 22738
A12: Volume Billed CWPs | C12: m3 | D12: 0 | E12: 0 | F12: 0 | G12: 0 | H12: 0 | I12: 0 | J12: 0 | K12: 0 | L12: 0 | M12: 0 | N12: 0 | O12: 0 | P12: =SUM(D12:O12) -> 0
A13: Volume Billed Institutions | C13: m3 | D13: 12 | E13: 11 | F13: 16 | G13: 16 | H13: 14 | I13: 14 | J13: 16 | K13: 11 | L13: 11 | M13: 4 | N13: 2 | O13: 2 | P13: =SUM(D13:O13) -> 129
A14: Volume Billed Commercial/Industrial | C14: m3 | D14: 0 | E14: 0 | F14: 0 | G14: 0 | H14: 0 | I14: 0 | J14: 0 | K14: 0 | L14: 0 | M14: 0 | N14: 0 | O14: 0 | P14: =SUM(D14:O14) -> 0
A15: Total Volume Billed Post Paid | C15: m3 | D15: =SUM(D11:D14) -> 1763 | E15: =SUM(E11:E14) -> 1717 | F15: =SUM(F11:F14) -> 2133 | G15: =SUM(G11:G14) -> 2177 | H15: =SUM(H11:H14) -> 1882 | I15: =SUM(I11:I14) -> 2093 | J15: =SUM(J11:J14) -> 2027 | K15: =SUM(K11:K14) -> 1836 | ... P15: =SUM(P11:P14) -> 22867
A16: REVENUE WATER - PREPAID
A17: Individuals | C17: m3 | D17: 851 | E17: 1529 | F17: 1121 | G17: 1393 | H17: 1221 | I17: 1374 | J17: 1235 | K17: 1318 | L17: 1000 | M17: 1145 | N17: 1228 | O17: 959 | P17: =SUM(D17:O17) -> 14374
A18: CWPs | C18: m3 | D18: 0 | E18: 0 | F18: 0 | G18: 0 | H18: 7 | I18: 0 | J18: 0 | K18: 0 | L18: 0 | M18: 8 | N18: 0 | O18: 1 | P18: =SUM(D18:O18) -> 16
A19: Institutions | C19: m3 | D19: 265 | E19: 409 | F19: 595 | G19: 462 | H19: 496 | I19: 559 | J19: 742 | K19: 657 | L19: 200 | M19: 280 | N19: 126 | O19: 110 | P19: =SUM(D19:O19) -> 4901
A20: Commercial/Industrial | C20: m3 | D20: 19 | E20: 26 | F20: 21 | G20: 60 | H20: 54 | I20: 44 | J20: 65 | K20: 40 | L20: 33 | M20: 44 | N20: 80 | O20: 46 | P20: =SUM(D20:O20) -> 532
A21: Total Volume Prepaid | C21: m3 | D21: =SUM(D17:D20) -> 1135 | E21: =SUM(E17:E20) -> 1964 | F21: =SUM(F17:F20) -> 1737 | G21: =SUM(G17:G20) -> 1915 | H21: =SUM(H17:H20) -> 1778 | I21: =SUM(I17:I20) -> 1977 | J21: =SUM(J17:J20) -> 2042 | K21: =SUM(K17:K20) -> 2015 | ... P21: =SUM(P17:P20) -> 19823
A22: TOTAL REVENUE WATER | C22: m3 | D22: =D21+D15 -> 2898 | E22: =E21+E15 -> 3681 | F22: =F21+F15 -> 3870 | G22: =G21+G15 -> 4092 | H22: =H21+H15 -> 3660 | I22: =I21+I15 -> 4070 | J22: =J21+J15 -> 4069 | K22: =K21+K15 -> 3851 | ... P22: =P21+P15 -> 42690
A24: Non-Revenue Water (NRW) | B24: Volume | C24: m3 | D24: =D9-D22 -> 1253 | E24: =E9-E22 -> 2626 | F24: =F9-F22 -> 1564 | G24: =G9-G22 -> 1180 | H24: =H9-H22 -> 1210 | I24: =I9-I22 -> 2050 | J24: =J9-J22 -> 1148 | K24: =K9-K22 -> 768 | ... P24: =P9-P22 -> 16032
B25: Percentage | C25: % | D25: =D24/D9 -> 0.30185497 | E25: =E24/E9 -> 0.41636277 | F25: =F24/F9 -> 0.28781745 | G25: =G24/G9 -> 0.22382398 | H25: =H24/H9 -> 0.24845996 | I25: =I24/I9 -> 0.33496732 | J25: =J24/J9 -> 0.22004984 | K25: =K24/K9 -> 0.16626976 | ... P25: =P24/P9 -> 0.27301522
A26: OPERATING EXPENSES
A27: Chemicals
A28: Chemical | B28: Rate(MK/kg)
A29: Chlorine | B29: =176264.5/50 -> 3525.29 | C29: kg | D29: 9 | E29: 15 | F29: 11.5 | G29: 16 | H29: 12 | I29: 13 | J29: 15 | K29: 15 | L29: 16 | M29: 16 | N29: 13.5 | O29: 16 | P29: =SUM(D29:O29) -> 168
C30: kg/mg litre | D30: =D29/(D9/1000) -> 2.1681523 | E30: =E29/(E9/1000) -> 2.3783098 | F30: =F29/(F9/1000) -> 2.1163047 | G30: =G29/(G9/1000) -> 3.0349014 | H30: =H29/(H9/1000) -> 2.4640657 | I30: =I29/(I9/1000) -> 2.124183 | J30: =J29/(J9/1000) -> 2.8752156 | K30: =K29/(K9/1000) -> 3.2474562 | ... P30: =P29/(P9/1000) -> 2.860938
A31: Aluminium sulphate | B31: =53000.511/50 -> 1060.0102 | C31: kg | P31: =SUM(D31:O31) -> 0
C32: kg/mg litre | D32: =D31/(D9/1000) -> 0 | E32: =E31/(E9/1000) -> 0 | F32: =F31/(F9/1000) -> 0 | G32: =G31/(G9/1000) -> 0 | H32: =H31/(H9/1000) -> 0 | I32: =I31/(I9/1000) -> 0 | J32: =J31/(J9/1000) -> 0 | K32: =K31/(K9/1000) -> 0 | ... P32: =P31/(P9/1000) -> 0
A33: Soda | B33: =61414.43/50 -> 1228.2886 | C33: kg | P33: =SUM(D33:O33) -> 0
C34: kg/mg litre | D34: =D33/(D9/1000) -> 0 | E34: =E33/(E9/1000) -> 0 | F34: =F33/(F9/1000) -> 0 | G34: =G33/(G9/1000) -> 0 | H34: =H33/(H9/1000) -> 0 | I34: =I33/(I9/1000) -> 0 | J34: =J33/(J9/1000) -> 0 | K34: =K33/(K9/1000) -> 0 | ... P34: =P33/(P9/1000) -> 0
A35: Algae floc | B35: =745345.16/200 -> 3726.7258 | C35: litres
C36: litres/mg litre
A37: Sud floc | B37: =790318.72/200 -> 3951.5936 | C37: litres | D37: 0 | E37: 0 | F37: 0 | G37: 0 | H37: 0 | I37: 0 | J37: 0 | K37: 0 | L37: 0 | M37: 0 | N37: 0 | O37: 0 | P37: =SUM(D37:O37) -> 0
C38: litres/mg litre | D38: =D37/(D9/1000) -> 0 | E38: =E37/(E9/1000) -> 0 | F38: =F37/(F9/1000) -> 0 | G38: =G37/(G9/1000) -> 0 | H38: =H37/(H9/1000) -> 0 | I38: =I37/(I9/1000) -> 0 | J38: =J37/(J9/1000) -> 0 | K38: =K37/(K9/1000) -> 0 | ... P38: =P37/(P9/1000) -> 0
A39: Potasium permanganate | B39: 1950 | C39: kg | D39: 0 | E39: 0 | F39: 0 | G39: 0 | H39: 0 | I39: 0 | J39: 0 | K39: 0 | L39: 0 | M39: 0 | N39: 0 | O39: 0 | P39: =SUM(D39:O39) -> 0
C40: kg/mg litre | D40: =D39/(D9/1000) -> 0 | E40: =E39/(E9/1000) -> 0 | F40: =F39/(F9/1000) -> 0 | G40: =G39/(G9/1000) -> 0 | H40: =H39/(H9/1000) -> 0 | I40: =I39/(I9/1000) -> 0 | J40: =J39/(J9/1000) -> 0 | K40: =K39/(K9/1000) -> 0 | ... P40: =P39/(P9/1000) -> 0
A41: Cost of Chemicals | C41: Mk | D41: =(D29*$B29)+(D31*$B31)+(D33*$B33)+(D35*$B35)+(D37*$B37)+(D39*$B39) -> 31727.61 | E41: =(E29*$B29)+(E31*$B31)+(E33*$B33)+(E35*$B35)+(E37*$B37)+(E39*$B39) -> 52879.35 | F41: =(F29*$B29)+(F31*$B31)+(F33*$B33)+(F35*$B35)+(F37*$B37)+(F39*$B39) -> 40540.835 | G41: =(G29*$B29)+(G31*$B31)+(G33*$B33)+(G35*$B35)+(G37*$B37)+(G39*$B39) -> 56404.64 | H41: =(H29*$B29)+(H31*$B31)+(H33*$B33)+(H35*$B35)+(H37*$B37)+(H39*$B39) -> 42303.48 | I41: =(I29*$B29)+(I31*$B31)+(I33*$B33)+(I35*$B35)+(I37*$B37)+(I39*$B39) -> 45828.77 | J41: =(J29*$B29)+(J31*$B31)+(J33*$B33)+(J35*$B35)+(J37*$B37)+(J39*$B39) -> 52879.35 | K41: =(K29*$B29)+(K31*$B31)+(K33*$B33)+(K35*$B35)+(K37*$B37)+(K39*$B39) -> 52879.35 | ... O41: =(O29*$B29)+(O31*$B31)+(O33*$B33)+(O35*$B35)+(O37*$B37)+(O39*$B39) -> 56404.64 | P41: =SUM(D41:O41) -> 592248.72
A42: Cost/vol. Produced (chemicals) | C42: Mk/m3 | D42: =D41/D9 -> 7.6433655 | E42: =E41/E9 -> 8.3842318 | F42: =F41/F9 -> 7.460588 | G42: =G41/G9 -> 10.698907 | H42: =H41/H9 -> 8.6865462 | I42: =I41/I9 -> 7.4883611 | J42: =J41/J9 -> 10.135969 | K42: =K41/K9 -> 11.448225 | ... P42: =P41/P9 -> 10.085636
A43: Power
A44: Power Usage | C44: Kw | D44: 3268 | E44: 4910 | F44: 3140 | G44: 3997 | H44: 3558 | I44: 4703 | J44: 4930 | K44: 4233 | L44: 5501 | M44: 5938 | N44: 4537 | O44: 6484 | P44: =SUM(D44:O44) -> 55199
A45: Power/ Vol. Produced | C45: Kw/m3 | D45: =D44/D9 -> 0.78728017 | E45: =E44/E9 -> 0.77850008 | F45: =F44/F9 -> 0.57784321 | G45: =G44/G9 -> 0.7581563 | H45: =H44/H9 -> 0.73059548 | I45: =I44/I9 -> 0.76846405 | J45: =J44/J9 -> 0.94498754 | K45: =K44/K9 -> 0.91643213 | ... P45: =P44/P9 -> 0.94000545
A46: Cost of Power | C46: Mk | D46: =1.165*(14100+(D44*119.1)) -> 469866.4 | E46: =1.165*(14100+(E44*119.1)) -> 697696.36 | F46: =1.165*(14100+(F44*119.1)) -> 452106.21 | G46: =1.165*(14100+(G44*119.1)) -> 571016.25 | H46: =1.165*(16600+(H44*143.5)) -> 614156.55 | I46: =1.165*(16600+(I44*143.5)) -> 805574.78 | J46: =1.165*(16600+(J44*143.5)) -> 843524.08 | K46: =1.165*(16600+(K44*143.5)) -> 727001.36 | L46: =1.165*(16600+(L44*143.5)) -> 938982.43 | M46: =1.165*(16600+(M44*143.5)) -> 1012039 | N46: =1.165*(16600+(N44*143.5)) -> 777823.32 | O46: =1.165*(16600+(O44*143.5)) -> 1103317.9 | P46: =SUM(D46:O46) -> 9013104.6
A47: Cost/vol. Produced | C47: Mk/m3 | D47: =D46/D9 -> 113.19354 | E47: =E46/E9 -> 110.62254 | F47: =F46/F9 -> 83.199523 | G47: =G46/G9 -> 108.31112 | H47: =H46/H9 -> 126.11017 | I47: =I46/I9 -> 131.62987 | J47: =J46/J9 -> 161.68757 | K47: =K46/K9 -> 157.39367 | ... P47: =P46/P9 -> 153.4877
A48: Plant and Vehicle Maintenance
A49: Distances covered | C49: km | E49: 298 | F49: 0 | G49: 278 | H49: 114 | I49: 0 | J49: 100 | P49: =SUM(D49:O49) -> 790
A50: Fuel Used (litres) | C50: litres | D50: 140 | E50: 160 | F50: 235 | G50: 100 | H50: 40 | I50: 40 | J50: 20 | P50: =SUM(D50:O50) -> 735
A51: Cost of fuel | C51: Mk | D51: 268800 | E51: 303520 | F51: 452200 | G51: 188520 | H51: 76800 | I51: 76800 | J51: 34520 | P51: =SUM(D51:O51) -> 1401160
A52: Maintenance | C52: Mk | D52: 0 | E52: 0 | F52: 0 | G52: 0 | H52: 10000 | I52: 0 | J52: 0 | K52: 0 | L52: 0 | M52: 0 | N52: 0 | O52: 0 | P52: =SUM(D52:O52) -> 10000
A53: Salaries and Wages
A54: Staff Costs | C54: MK | D54: 1840096.3 | E54: 2271434.9 | F54: 1915869.3 | G54: 1761007.6 | H54: 1846464.1 | I54: 1789794.5 | J54: 1208365.9 | K54: 1386825 | L54: 1913234.5 | M54: 1932995.6 | N54: 1932995.6 | O54: 1782844.5 | P54: =SUM(D54:O54) -> 21581928
A55: Wages | C55: MK | D55: 394531.88 | E55: 397176.12 | F55: 418930.9 | G55: 384555.9 | H55: 374159.25 | I55: 381370.8 | J55: 386899.66 | K55: 388341.97 | L55: 371875.6 | M55: 403846.8 | N55: 667644.53 | O55: 638870.48 | P55: =SUM(D55:O55) -> 5208203.9
A56: Other Overhead Costs | C56: MK | D56: 118600 | E56: 118600 | F56: 119600 | G56: 119800 | H56: 121700 | I56: 122350 | J56: 124900 | K56: 124900 | L56: 126550 | M56: 129500 | N56: 131800 | O56: 132750 | P56: =SUM(D56:O56) -> 1491050
A57: Operating Costs
A58: Total Operating Costs | C58: MK | D58: =D41+D46+D51+D52+D54+D55+D56 -> 3123622.2 | E58: =E41+E46+E51+E52+E54+E55+E56 -> 3841306.7 | F58: =F41+F46+F51+F52+F54+F55+F56 -> 3399247.3 | G58: =G41+G46+G51+G52+G54+G55+G56 -> 3081304.3 | H58: =H41+H46+H51+H52+H54+H55+H56 -> 3085583.4 | I58: =I41+I46+I51+I52+I54+I55+I56 -> 3221718.9 | J58: =J41+J46+J51+J52+J54+J55+J56 -> 2651088.9 | K58: =K41+K46+K51+K52+K54+K55+K56 -> 2679947.6 | ... O58: =O41+O46+O51+O52+O54+O55+O56 -> 3714187.6 | P58: =SUM(D58:O58) -> 39297695
A59: Cost/Vol. Produced | C59: Mk/m3 | D59: =D58/D9 -> 752.49873 | E59: =E58/E9 -> 609.0545 | F59: =F58/F9 -> 625.55158 | G59: =G58/G9 -> 584.46592 | H59: =H58/H9 -> 633.59002 | I59: =I58/I9 -> 526.42465 | J59: =J58/J9 -> 508.16349 | K59: =K58/K9 -> 580.20083 | ... P59: =P58/P9 -> 669.21588
A60: Cost/Vol. Billed | C60: Mk/m3 | D60: =D58/D22 -> 1077.8545 | E60: =E58/E22 -> 1043.5498 | F60: =F58/F22 -> 878.35847 | G60: =G58/G22 -> 753.00693 | H60: =H58/H22 -> 843.05557 | I60: =I58/I22 -> 791.57712 | J60: =J58/J22 -> 651.53328 | K60: =K58/K22 -> 695.90954 | ... P60: =P58/P22 -> 920.53631
A61: Permanent Staff Employed | C61: No | D61: 4 | E61: 4 | F61: 4 | G61: 4 | H61: 3 | I61: 3 | J61: 3 | K61: 3 | L61: 3 | M61: 3 | N61: 3 | O61: 3 | P61: =O61 -> 3
A62: Staff/Vol.1000m3 of Volume Produced/hour (12 hour day) | C62: No/1000m3 | D62: =(D61*1000*31)/D9 -> 29.87232 | E62: =(E61*1000*31)/E9 -> 19.660694 | F62: =(F61*1000*31)/F9 -> 22.819286 | G62: =(G61*1000*31)/G9 -> 23.520486 | H62: =(H61*1000*31)/H9 -> 19.096509 | I62: =(I61*1000*31)/I9 -> 15.196078 | J62: =(J61*1000*31)/J9 -> 17.826337 | K62: =(K61*1000*31)/K9 -> 20.134228 | ... P62: =(P61*1000*31)/P9 -> 1.5837335
A63: Temporary Staff Employed | C63: No | D63: 6 | E63: 6 | F63: 6 | G63: 6 | H63: 6 | I63: 6 | J63: 6 | K63: 6 | L63: 6 | M63: 6 | N63: 6 | O63: 6 | P63: =SUM(D63:O63) -> 72
A65: Water Connections and Disconnections
A66: New Individual Water Connections | B66: Brought Forward | C66: No | D66: 55 | E66: 51 | F66: 50 | G66: 59 | H66: 76 | I66: 66 | J66: 81 | K66: 83 | L66: 41 | M66: 41 | N66: 43 | O66: 43 | P66: =D66 -> 55
B67: Applied this Month | C67: No | D67: 1 | E67: 2 | F67: 4 | G67: 10 | H67: 5 | I67: 14 | J67: 4 | K67: 7 | M67: 2 | N67: 5 | O67: 12 | P67: =SUM(D67:O67) -> 66
B68: Done this Month Postpaid | C68: No | D68: 0 | K68: 0 | P68: =SUM(D68:O68) -> 0
B69: Done this Month Prepaid | C69: No | D69: 5 | E69: 3 | F69: 10 | G69: 7 | H69: 15 | J69: 10 | K69: 11 | L69: 29 | N69: 5 | O69: 10 | P69: =SUM(D69:O69) -> 105
B70: Total Done | C70: No | D70: =D68+D69 -> 5 | E70: =E68+E69 -> 3 | F70: =F68+F69 -> 10 | G70: =G68+G69 -> 7 | H70: 15 | I70: =I68+I69 -> 0 | J70: =J68+J69 -> 10 | K70: 11 | L70: 29 | M70: =M68+M69 -> 0 | N70: =N68+N69 -> 5 | O70: =O68+O69 -> 10 | P70: =P68+P69 -> 105
B71: Carried Forward | C71: No | D71: =D66+D67-D70 -> 51 | E71: =E66+E67-E70 -> 50 | F71: =F66+F67-F70 -> 44 | G71: =G66+G67-G70 -> 62 | H71: =H66+H67-H70 -> 66 | I71: =I66+I67-I70 -> 80 | J71: =J66+J67-J70 -> 75 | K71: =K66+K67-K70 -> 79 | ... P71: =P66+P67-P70 -> 16
A72: New Institutional Water Connections | B72: Brought Forward | C72: No | D72: 3 | E72: 3 | F72: 3 | G72: 4 | I72: 3 | J72: 3 | N72: 3 | O72: 3 | P72: =D72 -> 3
B73: Applied this Month | C73: No | D73: 0 | E73: 0 | F73: 0 | G73: 0 | N73: 0 | P73: =SUM(D73:O73) -> 0
B74: Done this Month Postpaid | C74: No | D74: 0 | E74: 0 | F74: 0 | G74: 0 | N74: 0 | P74: =SUM(D74:O74) -> 0
B75: Done this Month Prepaid | C75: No | D75: 0 | E75: 0 | F75: 0 | G75: 0 | P75: =SUM(D75:O75) -> 0
B76: Total Done | C76: No | D76: =D74+D75 -> 0 | E76: =E74+E75 -> 0 | F76: =F74+F75 -> 0 | G76: 0 | H76: =H74+H75 -> 0 | I76: =I74+I75 -> 0 | J76: =J74+J75 -> 0 | K76: =K74+K75 -> 0 | L76: =L74+L75 -> 0 | M76: =M74+M75 -> 0 | N76: =N74+N75 -> 0 | O76: =O74+O75 -> 0 | P76: =P74+P75 -> 0
B77: Carried Forward | C77: No | D77: =D72+D73-D76 -> 3 | E77: =E72+E73-E76 -> 3 | F77: =F72+F73-F76 -> 3 | G77: =G72+G73-G76 -> 4 | H77: =H72+H73-H76 -> 0 | I77: =I72+I73-I76 -> 3 | J77: =J72+J73-J76 -> 3 | K77: 3 | L77: 3 | M77: =M72+M73-M76 -> 0 | N77: =N72+N73-N76 -> 3 | O77: =O72+O73-O76 -> 3 | P77: =P72+P73-P76 -> 3
A78: New Commercial/Industrial Water Connections | B78: Brought Forward | C78: No | D78: 0 | E78: 0 | F78: 0 | P78: =D78 -> 0
B79: Applied this Month | C79: No | D79: 0 | E79: 0 | F79: 0 | P79: =SUM(D79:O79) -> 0
B80: Done this Month Postpaid | C80: No | D80: 0 | E80: 0 | F80: 0 | P80: =SUM(D80:O80) -> 0
B81: Done this Month Prepaid | C81: No | D81: 0 | E81: 0 | F81: 0 | P81: =SUM(D81:O81) -> 0
B82: Total Done | C82: No | D82: =D81+D80 -> 0 | E82: =E81+E80 -> 0 | F82: =F81+F80 -> 0 | G82: =G81+G80 -> 0 | H82: =H81+H80 -> 0 | I82: =I81+I80 -> 0 | J82: =J81+J80 -> 0 | K82: =K81+K80 -> 0 | ... P82: =P81+P80 -> 0
B83: Carried Forward | C83: No | D83: =D78+D79-D82 -> 0 | E83: =E78+E79-E82 -> 0 | F83: =F78+F79-F82 -> 0 | G83: =G78+G79-G82 -> 0 | H83: =H78+H79-H82 -> 0 | I83: =I78+I79-I82 -> 0 | J83: =J78+J79-J82 -> 0 | K83: =K78+K79-K82 -> 0 | M83: =M78+M79-M82 -> 0 | N83: =N78+N79-N82 -> 0 | O83: =O78+O79-O82 -> 0 | P83: =P78+P79-P82 -> 0
A84: New CWP | B84: Brought Forward | C84: No | D84: 0 | E84: 0 | F84: 0 | P84: =D84 -> 0
B85: Applied this Month | C85: No | D85: 0 | E85: 0 | F85: 0 | P85: =SUM(D85:O85) -> 0
B86: Done this Month Postpaid | C86: No | D86: 0 | E86: 0 | F86: 0 | P86: =SUM(D86:O86) -> 0
B87: Done this Month Prepaid | C87: No | D87: 0 | E87: 0 | F87: 0 | P87: =SUM(D87:O87) -> 0
B88: Total Done | C88: No | D88: =D87+D86 -> 0 | E88: =E87+E86 -> 0 | F88: =F87+F86 -> 0 | G88: =G87+G86 -> 0 | H88: =H87+H86 -> 0 | I88: =I87+I86 -> 0 | J88: =J87+J86 -> 0 | K88: =K87+K86 -> 0 | ... O88: =O87+O86 -> 0 | P88: =SUM(D88:O88) -> 0
B89: Carried Forward | C89: No | D89: =D84+D85-D88 -> 0 | E89: =E84+E85-E88 -> 0 | F89: =F84+F85-F88 -> 0 | G89: =G84+G85-G88 -> 0 | H89: =H84+H85-H88 -> 0 | I89: =I84+I85-I88 -> 0 | J89: =J84+J85-J88 -> 0 | K89: =K84+K85-K88 -> 0 | ... P89: =P84+P85-P88 -> 0
A90: Aggregated New Water connections | B90: Brought Forward | C90: No | D90: =D66+D72+D78+D84 -> 58 | E90: =E66+E72+E78+E84 -> 54 | F90: =F66+F72+F78+F84 -> 53 | G90: =G66+G72+G78+G84 -> 63 | H90: =H66+H72+H78+H84 -> 76 | I90: =I66+I72+I78+I84 -> 69 | J90: =J66+J72+J78+J84 -> 84 | K90: =K66+K72+K78+K84 -> 83 | ... O90: =O66+O72+O78+O84 -> 46 | P90: =D90 -> 58
B91: Applied this Month | C91: No | D91: =D67+D73+D79+D85 -> 1 | E91: =E67+E73+E79+E85 -> 2 | F91: =F67+F73+F79+F85 -> 4 | G91: =G67+G73+G79+G85 -> 10 | H91: =H67+H73+H79+H85 -> 5 | I91: =I67+I73+I79+I85 -> 14 | J91: =J67+J73+J79+J85 -> 4 | K91: =K67+K73+K79+K85 -> 7 | ... O91: =O67+O73+O79+O85 -> 12 | P91: =SUM(D91:O91) -> 66
B92: Done this Month Postpaid | C92: No | D92: =D68+D74+D80+D86 -> 0 | E92: =E68+E74+E80+E86 -> 0 | F92: =F68+F74+F80+F86 -> 0 | G92: =G68+G74+G80+G86 -> 0 | H92: =H68+H74+H80+H86 -> 0 | I92: =I68+I74+I80+I86 -> 0 | J92: =J68+J74+J80+J86 -> 0 | K92: =K68+K74+K80+K86 -> 0 | ... O92: =O68+O74+O80+O86 -> 0 | P92: =SUM(D92:O92) -> 0
B93: Done this Month Prepaid | D93: =D69+D75+D81+D87 -> 5 | E93: =E69+E75+E81+E87 -> 3 | F93: =F69+F75+F81+F87 -> 10 | G93: =G69+G75+G81+G87 -> 7 | H93: =H69+H75+H81+H87 -> 15 | I93: =I69+I75+I81+I87 -> 0 | J93: =J69+J75+J81+J87 -> 10 | K93: =K69+K75+K81+K87 -> 11 | ... O93: =O69+O75+O81+O87 -> 10 | P93: =SUM(D93:O93) -> 105
B94: Total Done | C94: No | D94: =D93+D92 -> 5 | E94: =E93+E92 -> 3 | F94: =F93+F92 -> 10 | G94: =G93+G92 -> 7 | H94: =H93+H92 -> 15 | I94: =I93+I92 -> 0 | J94: =J93+J92 -> 10 | K94: =K93+K92 -> 11 | ... P94: =P93+P92 -> 105
B95: Carried Forward | C95: No | D95: =D90+D91-D94 -> 54 | E95: =E90+E91-E94 -> 53 | F95: =F90+F91-F94 -> 47 | G95: =G90+G91-G94 -> 66 | H95: =H90+H91-H94 -> 66 | I95: =I90+I91-I94 -> 83 | J95: =J90+J91-J94 -> 78 | K95: =K90+K91-K94 -> 79 | ... P95: =P90+P91-P94 -> 19
A97: Prepaid Metering
A98: Prepaid Meters Installed | C98: No | D98: 5 | E98: 3 | F98: 10 | G98: 7 | H98: 15 | I98: 0 | J98: 10 | K98: 11 | L98: 29 | M98: 0 | N98: 5 | O98: 10 | P98: =SUM(D98:O98) -> 105
A100: Active and Disconnected Accounts
A101: Disconnected Individual Accounts | C101: No | D101: 221 | E101: 222 | F101: 220 | G101: 220 | H101: 220 | I101: 218 | J101: 248 | K101: 247 | L101: 246 | M101: 260 | N101: 290 | O101: 292 | P101: =O101 -> 292
A102: Disconnected institutional Accounts | C102: No | D102: 7 | E102: 7 | F102: 7 | G102: 7 | H102: 7 | I102: 7 | J102: 7 | K102: 7 | L102: 7 | M102: 7 | N102: 0 | O102: 0 | P102: =O102 -> 0
A103: Disconnected Commercial/Industrial Accounts | C103: No | D103: 2 | E103: 2 | F103: 2 | G103: 2 | H103: 2 | I103: 2 | J103: 2 | K103: 2 | L103: 2 | M103: 2 | N103: 0 | O103: 0 | P103: =O103 -> 0
A104: Disconnected CWP | C104: No | D104: 5 | E104: 5 | F104: 5 | G104: 5 | H104: 5 | I104: 5 | J104: 5 | K104: 5 | L104: 5 | M104: 5 | N104: 0 | O104: 0 | P104: =O104 -> 0
A105: Total Disconnected Accounts | C105: No | D105: =SUM(D101:D104) -> 235 | E105: =SUM(E101:E104) -> 236 | F105: =SUM(F101:F104) -> 234 | G105: =SUM(G101:G104) -> 234 | H105: =SUM(H101:H104) -> 234 | I105: =SUM(I101:I104) -> 232 | J105: =SUM(J101:J104) -> 262 | K105: =SUM(K101:K104) -> 261 | ... O105: =SUM(O101:O104) -> 292 | P105: =O105 -> 292
A106: Postpaid Consumers
...

Sheet Nkhudzi
A1: SOUTHERN REGION WATER BOARD
A3: MONTHLY REPORTS - 2023/2024
A4: MANGOCHI ZONE
A5: MANGOCHI ZONE
A7: PARAMETERS | C7: UNITS | D7: APRIL | E7: MAY | F7: JUNE | G7: JULY | H7: AUGUST | I7: SEPTEMBER | J7: OCTOBER | K7: NOVEMBER | L7: DECEMBER | M7: JANUARY | N7: FEBRUARY | O7: MARCH | P7: TOTALS
A8: PRODUCTION
A9: Volume Produced | C9: m3 | D9: 0 | E9: 0 | F9: 0 | G9: 0 | H9: 0 | I9: 0 | J9: 2578 | K9: 3087.1 | L9: 4408 | M9: 3878 | N9: 4121.7 | O9: 3043 | P9: =SUM(J9:O9) -> 21115.8
A10: REVENUE WATER - POSTPAID
A11: Volume Billed Individuals | C11: m3 | D11: 0 | E11: 0 | F11: 0 | G11: 0 | H11: 0 | I11: 0 | J11: 0 | K11: 0 | L11: 0 | M11: 0 | N11: 0 | O11: 8 | P11: =SUM(J11:O11) -> 8
A12: Volume Billed CWPs | C12: m3 | D12: 0 | E12: 0 | F12: 0 | G12: 0 | H12: 0 | I12: 0 | J12: 0 | K12: 0 | L12: 0 | M12: 0 | N12: 0 | O12: 0 | P12: =SUM(J12:O12) -> 0
A13: Volume Billed Institutions | C13: m3 | D13: 0 | E13: 0 | F13: 0 | G13: 0 | H13: 0 | I13: 0 | J13: 0 | K13: 0 | L13: 0 | M13: 0 | N13: 0 | O13: 0 | P13: =SUM(J13:O13) -> 0
A14: Volume Billed Commercial/Industrial | C14: m3 | D14: 0 | E14: 0 | F14: 0 | G14: 0 | H14: 0 | I14: 0 | J14: 0 | K14: 0 | L14: 0 | M14: 0 | N14: 0 | O14: 0 | P14: =SUM(J14:O14) -> 0
A15: Total Volume Billed Post Paid | C15: m3 | D15: =SUM(D11:D14) -> 0 | E15: =SUM(E11:E14) -> 0 | F15: =SUM(F11:F14) -> 0 | G15: =SUM(G11:G14) -> 0 | H15: =SUM(H11:H14) -> 0 | I15: =SUM(I11:I14) -> 0 | J15: =SUM(J11:J14) -> 0 | K15: =SUM(K11:K14) -> 0 | ... P15: =SUM(P11:P14) -> 8
A16: REVENUE WATER - PREPAID
A17: Individuals | C17: m3 | D17: 0 | E17: 0 | F17: 0 | G17: 0 | H17: 0 | I17: 0 | J17: 2578 | K17: 3087.1 | L17: 4408 | M17: 3877.9 | N17: 4121.7 | O17: 2834 | P17: =SUM(J17:O17) -> 20906.7
A18: CWPs | C18: m3 | D18: 0 | E18: 0 | F18: 0 | G18: 0 | H18: 0 | I18: 0 | J18: 0 | K18: 0 | L18: 0 | M18: 0 | N18: 0 | O18: 71 | P18: =SUM(J18:O18) -> 71
A19: Institutions | C19: m3 | D19: 0 | E19: 0 | F19: 0 | G19: 0 | H19: 0 | I19: 0 | J19: 0 | K19: 0 | L19: 0 | M19: 0 | N19: 0 | O19: 30 | P19: =SUM(J19:O19) -> 30
A20: Commercial/Industrial | C20: m3 | D20: 0 | E20: 0 | F20: 0 | G20: 0 | H20: 0 | I20: 0 | J20: 0 | K20: 0 | L20: 0 | M20: 0 | N20: 0 | O20: 100 | P20: =SUM(J20:O20) -> 100
A21: Total Volume Prepaid | C21: m3 | D21: =SUM(D17:D20) -> 0 | E21: =SUM(E17:E20) -> 0 | F21: =SUM(F17:F20) -> 0 | G21: =SUM(G17:G20) -> 0 | H21: =SUM(H17:H20) -> 0 | I21: =SUM(I17:I20) -> 0 | J21: =SUM(J17:J20) -> 2578 | K21: =SUM(K17:K20) -> 3087.1 | ... P21: =SUM(P17:P20) -> 21107.7
A22: TOTAL REVENUE WATER | C22: m3 | D22: =D21+D15 -> 0 | E22: =E21+E15 -> 0 | F22: =F21+F15 -> 0 | G22: =G21+G15 -> 0 | H22: =H21+H15 -> 0 | I22: =I21+I15 -> 0 | J22: =J21+J15 -> 2578 | K22: =K21+K15 -> 3087.1 | ... P22: =P21+P15 -> 21115.7
A24: Non-Revenue Water (NRW) | B24: Volume | C24: m3 | D24: =D9-D22 -> 0 | E24: =E9-E22 -> 0 | F24: =F9-F22 -> 0 | G24: =G9-G22 -> 0 | H24: =H9-H22 -> 0 | I24: =I9-I22 -> 0 | J24: =J9-J22 -> 0 | K24: =K9-K22 -> 0 | ... P24: =P9-P22 -> 0.1
B25: Percentage | C25: % | D25: =D24/D9 -> #DIV/0! | E25: =E24/E9 -> #DIV/0! | F25: =F24/F9 -> #DIV/0! | G25: =G24/G9 -> #DIV/0! | H25: =H24/H9 -> #DIV/0! | I25: =I24/I9 -> #DIV/0! | J25: =J24/J9 -> 0 | K25: =K24/K9 -> 0 | ... P25: =P24/P9 -> 4.7357903e-06
A26: OPERATING EXPENSES
A27: Chemicals
A28: Chemical | B28: Rate(MK/kg)
A29: Chlorine | B29: =176264.5/50 -> 3525.29 | C29: kg | D29: 0 | E29: 0 | F29: 0 | G29: 0 | H29: 0 | I29: 0 | J29: 225 | K29: 125 | L29: 125 | M29: 125 | N29: 125 | O29: 150 | P29: =SUM(J29:O29) -> 875
C30: kg/mg litre | D30: =D29/(D9/1000) -> #DIV/0! | E30: =E29/(E9/1000) -> #DIV/0! | F30: =F29/(F9/1000) -> #DIV/0! | G30: =G29/(G9/1000) -> #DIV/0! | H30: =H29/(H9/1000) -> #DIV/0! | I30: =I29/(I9/1000) -> #DIV/0! | J30: =J29/(J9/1000) -> 87.276959 | K30: =K29/(K9/1000) -> 40.491076 | ... P30: =P29/(P9/1000) -> 41.438165
A31: Aluminium sulphate | B31: =53000.511/50 -> 1060.0102 | C31: kg | P31: =SUM(J31:O31) -> 0
C32: kg/mg litre | D32: =D31/(D9/1000) -> #DIV/0! | E32: =E31/(E9/1000) -> #DIV/0! | F32: =F31/(F9/1000) -> #DIV/0! | G32: =G31/(G9/1000) -> #DIV/0! | H32: =H31/(H9/1000) -> #DIV/0! | I32: =I31/(I9/1000) -> #DIV/0! | J32: =J31/(J9/1000) -> 0 | K32: =K31/(K9/1000) -> 0 | ... P32: =P31/(P9/1000) -> 0
A33: Soda | B33: =61414.43/50 -> 1228.2886 | C33: kg | P33: =SUM(J33:O33) -> 0
C34: kg/mg litre | D34: =D33/(D9/1000) -> #DIV/0! | E34: =E33/(E9/1000) -> #DIV/0! | F34: =F33/(F9/1000) -> #DIV/0! | G34: =G33/(G9/1000) -> #DIV/0! | H34: =H33/(H9/1000) -> #DIV/0! | I34: =I33/(I9/1000) -> #DIV/0! | J34: =J33/(J9/1000) -> 0 | K34: =K33/(K9/1000) -> 0 | ... P34: =P33/(P9/1000) -> 0
A35: Algae floc | B35: =745345.16/200 -> 3726.7258 | C35: litres
C36: litres/mg litre
A37: Sud floc | B37: =790318.72/200 -> 3951.5936 | C37: litres | D37: 0 | E37: 0 | F37: 0 | G37: 0 | H37: 0 | I37: 0 | J37: 0 | K37: 0 | L37: 0 | M37: 0 | N37: 0 | O37: 0 | P37: =SUM(J37:O37) -> 0
C38: litres/mg litre | D38: =D37/(D9/1000) -> #DIV/0! | E38: =E37/(E9/1000) -> #DIV/0! | F38: =F37/(F9/1000) -> #DIV/0! | G38: =G37/(G9/1000) -> #DIV/0! | H38: =H37/(H9/1000) -> #DIV/0! | I38: =I37/(I9/1000) -> #DIV/0! | J38: =J37/(J9/1000) -> 0 | K38: =K37/(K9/1000) -> 0 | ... P38: =P37/(P9/1000) -> 0
A39: Potasium permanganate | B39: 1950 | C39: kg | D39: 0 | E39: 0 | F39: 0 | G39: 0 | H39: 0 | I39: 0 | J39: 0 | K39: 0 | L39: 0 | M39: 0 | N39: 0 | O39: 0 | P39: =SUM(J39:O39) -> 0
C40: kg/mg litre | D40: =D39/(D9/1000) -> #DIV/0! | E40: =E39/(E9/1000) -> #DIV/0! | F40: =F39/(F9/1000) -> #DIV/0! | G40: =G39/(G9/1000) -> #DIV/0! | H40: =H39/(H9/1000) -> #DIV/0! | I40: =I39/(I9/1000) -> #DIV/0! | J40: =J39/(J9/1000) -> 0 | K40: =K39/(K9/1000) -> 0 | ... P40: =P39/(P9/1000) -> 0
A41: Cost of Chemicals | C41: Mk | D41: =(D29*$B29)+(D31*$B31)+(D33*$B33)+(D35*$B35)+(D37*$B37)+(D39*$B39) -> 0 | E41: =(E29*$B29)+(E31*$B31)+(E33*$B33)+(E35*$B35)+(E37*$B37)+(E39*$B39) -> 0 | F41: =(F29*$B29)+(F31*$B31)+(F33*$B33)+(F35*$B35)+(F37*$B37)+(F39*$B39) -> 0 | G41: =(G29*$B29)+(G31*$B31)+(G33*$B33)+(G35*$B35)+(G37*$B37)+(G39*$B39) -> 0 | H41: =(H29*$B29)+(H31*$B31)+(H33*$B33)+(H35*$B35)+(H37*$B37)+(H39*$B39) -> 0 | I41: =(I29*$B29)+(I31*$B31)+(I33*$B33)+(I35*$B35)+(I37*$B37)+(I39*$B39) -> 0 | J41: =(J29*$B29)+(J31*$B31)+(J33*$B33)+(J35*$B35)+(J37*$B37)+(J39*$B39) -> 793190.25 | K41: =(K29*$B29)+(K31*$B31)+(K33*$B33)+(K35*$B35)+(K37*$B37)+(K39*$B39) -> 440661.25 | ... O41: =(O29*$B29)+(O31*$B31)+(O33*$B33)+(O35*$B35)+(O37*$B37)+(O39*$B39) -> 528793.5 | P41: =SUM(J41:O41) -> 3084628.8
A42: Cost/vol. Produced (chemicals) | C42: Mk/m3 | D42: =D41/D9 -> #DIV/0! | E42: =E41/E9 -> #DIV/0! | F42: =F41/F9 -> #DIV/0! | G42: =G41/G9 -> #DIV/0! | H42: =H41/H9 -> #DIV/0! | I42: =I41/I9 -> #DIV/0! | J42: =J41/J9 -> 307.67659 | K42: =K41/K9 -> 142.74278 | ... P42: =P41/P9 -> 146.08155
A43: Power
A44: Power Usage | C44: Kw | D44: 0 | E44: 0 | F44: 0 | G44: 0 | H44: 0 | I44: 0 | L44: 37905 | M44: 97263 | N44: 50632.6 | O44: 46535.6 | P44: =SUM(J44:O44) -> 232336.2
A45: Power/ Vol. Produced | C45: Kw/m3 | D45: =D44/D9 -> #DIV/0! | E45: =E44/E9 -> #DIV/0! | F45: =F44/F9 -> #DIV/0! | G45: =G44/G9 -> #DIV/0! | H45: =H44/H9 -> #DIV/0! | I45: =I44/I9 -> #DIV/0! | J45: =J44/J9 -> 0 | K45: =K44/K9 -> 0 | ... P45: =P44/P9 -> 11.002955
A46: Cost of Power | C46: Mk | D46: =1.165*(14100+(D44*119.1)) -> 16426.5 | E46: =1.165*(14100+(E44*119.1)) -> 16426.5 | F46: =1.165*(14100+(F44*119.1)) -> 16426.5 | G46: =1.165*(14100+(G44*119.1)) -> 16426.5 | H46: =1.165*(16600+(H44*143.5)) -> 19339 | I46: =1.165*(16600+(I44*143.5)) -> 19339 | J46: 21782946 | K46: 20372084 | L46: 42587038 | M46: 42587038 | N46: 42587038 | O46: 42587038 | P46: =SUM(J46:O46) -> 2.1250318e+08
A47: Cost/vol. Produced | C47: Mk/m3 | D47: =D46/D9 -> #DIV/0! | E47: =E46/E9 -> #DIV/0! | F47: =F46/F9 -> #DIV/0! | G47: =G46/G9 -> #DIV/0! | H47: =H46/H9 -> #DIV/0! | I47: =I46/I9 -> #DIV/0! | J47: =J46/J9 -> 8449.5523 | K47: =K46/K9 -> 6599.1006 | ... P47: =P46/P9 -> 10063.705
A48: Plant and Vehicle Maintenance
A49: Distances covered | C49: km | D49: 0 | E49: 0 | F49: 0 | G49: 0 | H49: 0 | I49: 0 | J49: 0 | K49: 0 | L49: 0 | M49: 0 | N49: 0 | O49: 0 | P49: =SUM(J49:O49) -> 0
A50: Fuel Used (litres) | C50: litres | D50: 0 | E50: 0 | F50: 0 | G50: 0 | H50: 0 | I50: 0 | J50: 0 | K50: 0 | L50: 0 | M50: 0 | N50: 0 | O50: 0 | P50: =SUM(J50:O50) -> 0
A51: Cost of fuel | C51: Mk | D51: 0 | E51: 0 | F51: 0 | G51: 0 | H51: 0 | I51: 0 | J51: 0 | K51: 0 | L51: 0 | M51: 0 | N51: 0 | O51: 0 | P51: =SUM(J51:O51) -> 0
A52: Maintenance | C52: Mk | D52: 0 | E52: 0 | F52: 0 | G52: 0 | H52: 0 | I52: 0 | J52: 0 | K52: 0 | L52: 0 | M52: 0 | N52: 0 | O52: 0 | P52: =SUM(J52:O52) -> 0
A53: Salaries and Wages
A54: Staff Costs | C54: MK | D54: 0 | E54: 0 | F54: 0 | G54: 0 | H54: 0 | I54: 0 | J54: 2647693 | K54: 5149018.7 | L54: 6089140.7 | M54: 7081634.8 | N54: 7081634.8 | O54: 6922099.5 | P54: =SUM(J54:O54) -> 34971221
A55: Wages | C55: MK | D55: 0 | E55: 0 | F55: 0 | G55: 0 | H55: 0 | I55: 0 | J55: 0 | K55: 0 | L55: 0 | M55: 0 | N55: 3378030.4 | O55: 3501131.4 | P55: =SUM(J55:O55) -> 6879161.7
A56: Other Overhead Costs | C56: MK | D56: 0 | E56: 0 | F56: 0 | G56: 0 | H56: 0 | I56: 0 | J56: 0 | K56: 0 | L56: 0 | M56: 0 | N56: 123300 | O56: 134700 | P56: =SUM(J56:O56) -> 258000
A57: Operating Costs
A58: Total Operating Costs | C58: MK | D58: =D41+D46+D51+D52+D54+D55+D56 -> 16426.5 | E58: =E41+E46+E51+E52+E54+E55+E56 -> 16426.5 | F58: =F41+F46+F51+F52+F54+F55+F56 -> 16426.5 | G58: =G41+G46+G51+G52+G54+G55+G56 -> 16426.5 | H58: =H41+H46+H51+H52+H54+H55+H56 -> 19339 | I58: =I41+I46+I51+I52+I54+I55+I56 -> 19339 | J58: =J41+J46+J51+J52+J54+J55+J56 -> 25223829 | K58: =K41+K46+K51+K52+K54+K55+K56 -> 25961763 | ... O58: =O41+O46+O51+O52+O54+O55+O56 -> 53673762 | P58: =SUM(J58:O58) -> 2.5769619e+08
A59: Cost/Vol. Produced | C59: Mk/m3 | D59: =D58/D9 -> #DIV/0! | E59: =E58/E9 -> #DIV/0! | F59: =F58/F9 -> #DIV/0! | G59: =G58/G9 -> #DIV/0! | H59: =H58/H9 -> #DIV/0! | I59: =I58/I9 -> #DIV/0! | J59: =J58/J9 -> 9784.2626 | K59: =K58/K9 -> 8409.7578 | ... P59: =P58/P9 -> 12203.951
A60: Cost/Vol. Billed | C60: Mk/m3 | D60: =D58/D22 -> #DIV/0! | E60: =E58/E22 -> #DIV/0! | F60: =F58/F22 -> #DIV/0! | G60: =G58/G22 -> #DIV/0! | H60: =H58/H22 -> #DIV/0! | I60: =I58/I22 -> #DIV/0! | J60: =J58/J22 -> 9784.2626 | K60: =K58/K22 -> 8409.7578 | ... P60: =P58/P22 -> 12204.009
A61: Permanent Staff Employed | C61: No | D61: 0 | E61: 4 | F61: 4 | G61: 4 | H61: 3 | I61: 3 | J61: 8 | K61: 8 | L61: 10 | M61: 12 | N61: 14 | O61: 14 | P61: =O61 -> 14
A62: Staff/Vol.1000m3 of Volume Produced/hour (12 hour day) | C62: No/1000m3 | D62: =(D61*1000*31)/D9 -> #DIV/0! | E62: =(E61*1000*31)/E9 -> #DIV/0! | F62: =(F61*1000*31)/F9 -> #DIV/0! | G62: =(G61*1000*31)/G9 -> #DIV/0! | H62: =(H61*1000*31)/H9 -> #DIV/0! | I62: =(I61*1000*31)/I9 -> #DIV/0! | J62: =(J61*1000*31)/J9 -> 96.198604 | K62: =(K61*1000*31)/K9 -> 80.334294 | ... P62: =(P61*1000*31)/P9 -> 20.55333
A63: Temporary Staff Employed | C63: No | D63: 0 | E63: 6 | F63: 6 | G63: 6 | H63: 6 | I63: 6 | J63: 16 | K63: 16 | L63: 17 | M63: 43 | N63: 56 | O63: 56 | P63: =SUM(J63:O63) -> 204
A65: Water Connections and Disconnections
A66: New Individual Water Connections | B66: Brought Forward | C66: No | D66: 0 | E66: 0 | F66: 0 | G66: 0 | H66: 0 | I66: 0 | K66: 141 | L66: 153 | M66: 153 | N66: 653 | O66: 631 | P66: =J66 -> 0
B67: Applied this Month | C67: No | D67: 0 | E67: 0 | F67: 0 | G67: 0 | H67: 0 | I67: 0 | K67: 15 | L67: 10 | M67: 591 | N67: 25 | O67: 67 | P67: =SUM(J67:O67) -> 708
B68: Done this Month Postpaid | C68: No | D68: 0 | E68: 0 | F68: 0 | G68: 0 | H68: 0 | I68: 0 | L68: 1 | P68: =SUM(J68:O68) -> 1
B69: Done this Month Prepaid | C69: No | D69: 0 | E69: 0 | F69: 0 | G69: 0 | H69: 0 | I69: 0 | J69: 1009 | K69: 3 | L69: 9 | M69: 91 | N69: 47 | O69: 92 | P69: =SUM(J69:O69) -> 1251
B70: Total Done | C70: No | D70: 0 | E70: 0 | F70: 0 | G70: 0 | H70: 0 | I70: 0 | J70: =J68+J69 -> 1009 | K70: 3 | L70: =L68+L69 -> 10 | M70: =M68+M69 -> 91 | N70: =N68+N69 -> 47 | O70: =O68+O69 -> 92 | P70: =P68+P69 -> 1252
B71: Carried Forward | C71: No | D71: =D66+D67-D70 -> 0 | E71: =E66+E67-E70 -> 0 | F71: =F66+F67-F70 -> 0 | G71: =G66+G67-G70 -> 0 | H71: =H66+H67-H70 -> 0 | I71: =I66+I67-I70 -> 0 | J71: 0 | K71: =K66+K67-K70 -> 153 | L71: =L66+L67-L70 -> 153 | M71: =M66+M67-M70 -> 653 | N71: =N66+N67-N70 -> 631 | O71: =O66+O67-O70 -> 606 | P71: =P66+P67-P70 -> -544
A72: New Institutional Water Connections | B72: Brought Forward | C72: No | D72: 0 | E72: 0 | F72: 0 | G72: 0 | H72: 0 | I72: 0 | K72: 2 | L72: 2 | P72: =J72 -> 0
B73: Applied this Month | C73: No | D73: 0 | E73: 0 | F73: 0 | G73: 0 | H73: 0 | I73: 0 | J73: 0 | K73: 0 | L73: 0 | M73: 0 | N73: 0 | O73: 0 | P73: =SUM(J73:O73) -> 0
B74: Done this Month Postpaid | C74: No | D74: 0 | E74: 0 | F74: 0 | G74: 0 | H74: 0 | I74: 0 | J74: 0 | K74: 0 | L74: 0 | M74: 0 | N74: 0 | O74: 0 | P74: =SUM(J74:O74) -> 0
B75: Done this Month Prepaid | C75: No | D75: 0 | E75: 0 | F75: 0 | G75: 0 | H75: 0 | I75: 0 | J75: 0 | K75: 0 | L75: 0 | M75: 0 | N75: 0 | O75: 0 | P75: =SUM(J75:O75) -> 0
B76: Total Done | C76: No | D76: =D74+D75 -> 0 | E76: =E74+E75 -> 0 | F76: =F74+F75 -> 0 | G76: =G74+G75 -> 0 | H76: =H74+H75 -> 0 | I76: =I74+I75 -> 0 | J76: =J74+J75 -> 0 | K76: =K74+K75 -> 0 | ... P76: =P74+P75 -> 0
B77: Carried Forward | C77: No | D77: =D72+D73-D76 -> 0 | E77: =E72+E73-E76 -> 0 | F77: =F72+F73-F76 -> 0 | G77: =G72+G73-G76 -> 0 | H77: =H72+H73-H76 -> 0 | I77: =I72+I73-I76 -> 0 | J77: =J72+J73-J76 -> 0 | K77: =K72+K73-K76 -> 2 | ... P77: =P72+P73-P76 -> 0
A78: New Commercial/Industrial Water Connections | B78: Brought Forward | C78: No | D78: 0 | E78: 0 | F78: 0 | G78: 0 | H78: 0 | I78: 0 | K78: 2 | P78: =J78 -> 0
B79: Applied this Month | C79: No | D79: 0 | E79: 0 | F79: 0 | G79: 0 | H79: 0 | I79: 0 | J79: 0 | K79: 0 | L79: 0 | M79: 0 | N79: 0 | O79: 0 | P79: =SUM(J79:O79) -> 0
B80: Done this Month Postpaid | C80: No | D80: 0 | E80: 0 | F80: 0 | G80: 0 | H80: 0 | I80: 0 | J80: 0 | K80: 0 | L80: 0 | M80: 0 | N80: 0 | O80: 0 | P80: =SUM(J80:O80) -> 0
B81: Done this Month Prepaid | C81: No | D81: 0 | E81: 0 | F81: 0 | P81: =SUM(J81:O81) -> 0
B82: Total Done | C82: No | D82: =D81+D80 -> 0 | E82: =E81+E80 -> 0 | F82: =F81+F80 -> 0 | G82: =G81+G80 -> 0 | H82: =H81+H80 -> 0 | I82: =I81+I80 -> 0 | J82: =J81+J80 -> 0 | K82: =K81+K80 -> 0 | ... P82: =P81+P80 -> 0
B83: Carried Forward | C83: No | D83: =D78+D79-D82 -> 0 | E83: =E78+E79-E82 -> 0 | F83: =F78+F79-F82 -> 0 | G83: =G78+G79-G82 -> 0 | H83: =H78+H79-H82 -> 0 | I83: =I78+I79-I82 -> 0 | J83: =J78+J79-J82 -> 0 | K83: =K78+K79-K82 -> 2 | ... P83: =P78+P79-P82 -> 0
A84: New CWP | B84: Brought Forward | C84: No | D84: 0 | E84: 0 | F84: 0 | P84: =J84 -> 0
B85: Applied this Month | C85: No | D85: 0 | E85: 0 | F85: 0 | P85: =SUM(J85:O85) -> 0
B86: Done this Month Postpaid | C86: No | D86: 0 | E86: 0 | F86: 0 | P86: =SUM(J86:O86) -> 0
B87: Done this Month Prepaid | C87: No | D87: 0 | E87: 0 | F87: 0 | P87: =SUM(J87:O87) -> 0
B88: Total Done | C88: No | D88: =D87+D86 -> 0 | E88: =E87+E86 -> 0 | F88: =F87+F86 -> 0 | G88: =G87+G86 -> 0 | H88: =H87+H86 -> 0 | I88: =I87+I86 -> 0 | J88: =J87+J86 -> 0 | K88: =K87+K86 -> 0 | ... O88: =O87+O86 -> 0 | P88: =SUM(J88:O88) -> 0
B89: Carried Forward | C89: No | D89: =D84+D85-D88 -> 0 | E89: =E84+E85-E88 -> 0 | F89: =F84+F85-F88 -> 0 | G89: =G84+G85-G88 -> 0 | H89: =H84+H85-H88 -> 0 | I89: =I84+I85-I88 -> 0 | J89: =J84+J85-J88 -> 0 | K89: =K84+K85-K88 -> 0 | ... P89: =P84+P85-P88 -> 0
A90: Aggregated New Water connections | B90: Brought Forward | C90: No | D90: =D66+D72+D78+D84 -> 0 | E90: =E66+E72+E78+E84 -> 0 | F90: =F66+F72+F78+F84 -> 0 | G90: =G66+G72+G78+G84 -> 0 | H90: =H66+H72+H78+H84 -> 0 | I90: =I66+I72+I78+I84 -> 0 | J90: =J66+J72+J78+J84 -> 0 | K90: =K66+K72+K78+K84 -> 145 | ... O90: =O66+O72+O78+O84 -> 631 | P90: =J90 -> 0
B91: Applied this Month | C91: No | D91: =D67+D73+D79+D85 -> 0 | E91: =E67+E73+E79+E85 -> 0 | F91: =F67+F73+F79+F85 -> 0 | G91: =G67+G73+G79+G85 -> 0 | H91: =H67+H73+H79+H85 -> 0 | I91: =I67+I73+I79+I85 -> 0 | J91: =J67+J73+J79+J85 -> 0 | K91: =K67+K73+K79+K85 -> 15 | ... O91: =O67+O73+O79+O85 -> 67 | P91: =SUM(J91:O91) -> 708
B92: Done this Month Postpaid | C92: No | D92: =D68+D74+D80+D86 -> 0 | E92: =E68+E74+E80+E86 -> 0 | F92: =F68+F74+F80+F86 -> 0 | G92: =G68+G74+G80+G86 -> 0 | H92: =H68+H74+H80+H86 -> 0 | I92: =I68+I74+I80+I86 -> 0 | J92: =J68+J74+J80+J86 -> 0 | K92: =K68+K74+K80+K86 -> 0 | ... O92: =O68+O74+O80+O86 -> 0 | P92: =SUM(J92:O92) -> 1
B93: Done this Month Prepaid | D93: =D69+D75+D81+D87 -> 0 | E93: =E69+E75+E81+E87 -> 0 | F93: =F69+F75+F81+F87 -> 0 | G93: =G69+G75+G81+G87 -> 0 | H93: =H69+H75+H81+H87 -> 0 | I93: =I69+I75+I81+I87 -> 0 | J93: =J69+J75+J81+J87 -> 1009 | K93: =K69+K75+K81+K87 -> 3 | ... O93: =O69+O75+O81+O87 -> 92 | P93: =SUM(J93:O93) -> 1251
B94: Total Done | C94: No | D94: =D93+D92 -> 0 | E94: =E93+E92 -> 0 | F94: =F93+F92 -> 0 | G94: =G93+G92 -> 0 | H94: =H93+H92 -> 0 | I94: =I93+I92 -> 0 | J94: =J93+J92 -> 1009 | K94: =K93+K92 -> 3 | ... P94: =P93+P92 -> 1252
B95: Carried Forward | C95: No | D95: =D90+D91-D94 -> 0 | E95: =E90+E91-E94 -> 0 | F95: =F90+F91-F94 -> 0 | G95: =G90+G91-G94 -> 0 | H95: =H90+H91-H94 -> 0 | I95: =I90+I91-I94 -> 0 | J95: 0 | K95: =K90+K91-K94 -> 157 | L95: =L90+L91-L94 -> 155 | M95: =M90+M91-M94 -> 653 | N95: =N90+N91-N94 -> 631 | O95: =O90+O91-O94 -> 606 | P95: =P90+P91-P94 -> -544
A97: Prepaid Metering
A98: Prepaid Meters Installed | C98: No | D98: 0 | E98: 0 | F98: 0 | G98: 0 | H98: 0 | I98: 0 | J98: 1128 | K98: 3 | L98: 12 | M98: 91 | N98: 47 | O98: 92 | P98: =SUM(J98:O98) -> 1373
A100: Active and Disconnected Accounts
A101: Disconnected Individual Accounts | C101: No | D101: 0 | E101: 0 | F101: 0 | G101: 0 | H101: 0 | I101: 0 | J101: 0 | K101: 0 | L101: 0 | M101: 0 | N101: 0 | O101: 0 | P101: =O101 -> 0
A102: Disconnected institutional Accounts | C102: No | D102: 0 | E102: 0 | F102: 0 | G102: 0 | H102: 0 | I102: 0 | J102: 0 | K102: 0 | L102: 0 | M102: 0 | N102: 0 | O102: 0 | P102: =O102 -> 0
A103: Disconnected Commercial/Industrial Accounts | C103: No | D103: 0 | E103: 0 | F103: 0 | G103: 0 | H103: 0 | I103: 0 | J103: 0 | K103: 0 | L103: 0 | M103: 0 | N103: 0 | O103: 0 | P103: =O103 -> 0
A104: Disconnected CWP | C104: No | D104: 0 | E104: 0 | F104: 0 | G104: 0 | H104: 0 | I104: 0 | J104: 0 | K104: 0 | L104: 0 | M104: 0 | N104: 0 | O104: 0 | P104: =O104 -> 0
A105: Total Disconnected Accounts | C105: No | D105: =SUM(D101:D104) -> 0 | E105: =SUM(E101:E104) -> 0 | F105: =SUM(F101:F104) -> 0 | G105: =SUM(G101:G104) -> 0 | H105: =SUM(H101:H104) -> 0 | I105: =SUM(I101:I104) -> 0 | J105: =SUM(J101:J104) -> 0 | K105: =SUM(K101:K104) -> 0 | ... O105: =SUM(O101:O104) -> 0 | P105: =O105 -> 0
A106: Postpaid Consumers
...

Sheet Zone Monthly
A1: SOUTHERN REGION WATER BOARD
A3: MONTHLY REPORTS - 2023/2024
A4: MANGOCHI ZONE
A5: MANGOCHI ZONE
A7: PARAMETERS | C7: UNITS | D7: APRIL | E7: MAY | F7: JUNE | G7: JULY | H7: AUGUST | I7: SEPTEMBER | J7: OCTOBER | K7: NOVEMBER | L7: DECEMBER | M7: JANUARY | N7: FEBRUARY | O7: MARCH | P7: TOTALS
A8: PRODUCTION
A9: Volume Produced | C9: m3 | D9: =Mangochi!D9+'Monkey Bay'!D9+Namwera!D9 -> 188810 | E9: =Mangochi!E9+'Monkey Bay'!E9+Namwera!E9 -> 194881 | F9: =Mangochi!F9+'Monkey Bay'!F9+Namwera!F9 -> 201586 | G9: =Mangochi!G9+'Monkey Bay'!G9+Namwera!G9 -> 193512 | H9: =Mangochi!H9+'Monkey Bay'!H9+Namwera!H9 -> 194800 | I9: =Mangochi!I9+'Monkey Bay'!I9+Namwera!I9 -> 191525 | J9: =Mangochi!J9+'Monkey Bay'!J9+Namwera!J9+Nkhudzi!J9 -> 205295 | K9: =Mangochi!K9+'Monkey Bay'!K9+Namwera!K9+Nkhudzi!K9 -> 230405.1 | L9: =Mangochi!L9+'Monkey Bay'!L9+Namwera!L9+Nkhudzi!L9 -> 201198 | M9: =Mangochi!M9+'Monkey Bay'!M9+Namwera!M9+Nkhudzi!M9 -> 209994 | N9: =Mangochi!N9+'Monkey Bay'!N9+Namwera!N9+Nkhudzi!N9 -> 200614.7 | O9: =Mangochi!O9+'Monkey Bay'!O9+Namwera!O9+Nkhudzi!O9 -> 185691 | P9: =SUM(D9:O9) -> 2398311.8
A10: REVENUE WATER - POSTPAID
A11: Volume Billed Individuals | C11: m3 | D11: =Mangochi!D11+'Monkey Bay'!D11+Namwera!D11 -> 72208 | E11: =Mangochi!E11+'Monkey Bay'!E11+Namwera!E11 -> 75904 | F11: =Mangochi!F11+'Monkey Bay'!F11+Namwera!F11 -> 78779 | G11: =Mangochi!G11+'Monkey Bay'!G11+Namwera!G11 -> 79340 | H11: =Mangochi!H11+'Monkey Bay'!H11+Namwera!H11 -> 81185 | I11: =Mangochi!I11+'Monkey Bay'!I11+Namwera!I11 -> 82899 | J11: =Mangochi!J11+'Monkey Bay'!J11+Namwera!J11+Nkhudzi!J11 -> 88528 | K11: =Mangochi!K11+'Monkey Bay'!K11+Namwera!K11+Nkhudzi!K11 -> 94364 | L11: =Mangochi!L11+'Monkey Bay'!L11+Namwera!L11+Nkhudzi!L11 -> 79652 | M11: =Mangochi!M11+'Monkey Bay'!M11+Namwera!M11+Nkhudzi!M11 -> 85487 | N11: =Mangochi!N11+'Monkey Bay'!N11+Namwera!N11+Nkhudzi!N11 -> 91204 | O11: =Mangochi!O11+'Monkey Bay'!O11+Namwera!O11+Nkhudzi!O11 -> 88120 | P11: =SUM(D11:O11) -> 997670
A12: Volume Billed CWPs | C12: m3 | D12: =Mangochi!D12+'Monkey Bay'!D12+Namwera!D12 -> 0 | E12: =Mangochi!E12+'Monkey Bay'!E12+Namwera!E12 -> 0 | F12: =Mangochi!F12+'Monkey Bay'!F12+Namwera!F12 -> 0 | G12: =Mangochi!G12+'Monkey Bay'!G12+Namwera!G12 -> 0 | H12: =Mangochi!H12+'Monkey Bay'!H12+Namwera!H12 -> 0 | I12: =Mangochi!I12+'Monkey Bay'!I12+Namwera!I12 -> 0 | J12: =Mangochi!J12+'Monkey Bay'!J12+Namwera!J12+Nkhudzi!J12 -> 0 | K12: =Mangochi!K12+'Monkey Bay'!K12+Namwera!K12+Nkhudzi!K12 -> 0 | L12: =Mangochi!L12+'Monkey Bay'!L12+Namwera!L12+Nkhudzi!L12 -> 0 | M12: =Mangochi!M12+'Monkey Bay'!M12+Namwera!M12+Nkhudzi!M12 -> 0 | N12: =Mangochi!N12+'Monkey Bay'!N12+Namwera!N12+Nkhudzi!N12 -> 0 | O12: =Mangochi!O12+'Monkey Bay'!O12+Namwera!O12+Nkhudzi!O12 -> 0 | P12: =SUM(D12:O12) -> 0
A13: Volume Billed Institutions | C13: m3 | D13: =Mangochi!D13+'Monkey Bay'!D13+Namwera!D13 -> 20451 | E13: =Mangochi!E13+'Monkey Bay'!E13+Namwera!E13 -> 18852 | F13: =Mangochi!F13+'Monkey Bay'!F13+Namwera!F13 -> 22908 | G13: =Mangochi!G13+'Monkey Bay'!G13+Namwera!G13 -> 21340 | H13: =Mangochi!H13+'Monkey Bay'!H13+Namwera!H13 -> 18908 | I13: =Mangochi!I13+'Monkey Bay'!I13+Namwera!I13 -> 29446 | J13: =Mangochi!J13+'Monkey Bay'!J13+Namwera!J13+Nkhudzi!J13 -> 23142 | K13: =Mangochi!K13+'Monkey Bay'!K13+Namwera!K13+Nkhudzi!K13 -> 22131 | L13: =Mangochi!L13+'Monkey Bay'!L13+Namwera!L13+Nkhudzi!L13 -> 12862 | M13: =Mangochi!M13+'Monkey Bay'!M13+Namwera!M13+Nkhudzi!M13 -> 24906 | N13: =Mangochi!N13+'Monkey Bay'!N13+Namwera!N13+Nkhudzi!N13 -> 21440 | O13: =Mangochi!O13+'Monkey Bay'!O13+Namwera!O13+Nkhudzi!O13 -> 21618 | P13: =SUM(D13:O13) -> 258004
A14: Volume Billed Commercial/Industrial | C14: m3 | D14: =Mangochi!D14+'Monkey Bay'!D14+Namwera!D14 -> 1072 | E14: =Mangochi!E14+'Monkey Bay'!E14+Namwera!E14 -> 936 | F14: =Mangochi!F14+'Monkey Bay'!F14+Namwera!F14 -> 7810 | G14: =Mangochi!G14+'Monkey Bay'!G14+Namwera!G14 -> 739 | H14: =Mangochi!H14+'Monkey Bay'!H14+Namwera!H14 -> 695 | I14: =Mangochi!I14+'Monkey Bay'!I14+Namwera!I14 -> 102 | J14: =Mangochi!J14+'Monkey Bay'!J14+Namwera!J14+Nkhudzi!J14 -> 149 | K14: =Mangochi!K14+'Monkey Bay'!K14+Namwera!K14+Nkhudzi!K14 -> 229 | L14: =Mangochi!L14+'Monkey Bay'!L14+Namwera!L14+Nkhudzi!L14 -> 203 | M14: =Mangochi!M14+'Monkey Bay'!M14+Namwera!M14+Nkhudzi!M14 -> 147 | N14: =Mangochi!N14+'Monkey Bay'!N14+Namwera!N14+Nkhudzi!N14 -> 164 | O14: =Mangochi!O14+'Monkey Bay'!O14+Namwera!O14+Nkhudzi!O14 -> 139 | P14: =SUM(D14:O14) -> 12385
A15: Total Volume Billed Post Paid | C15: m3 | D15: =SUM(D11:D14) -> 93731 | E15: =SUM(E11:E14) -> 95692 | F15: =SUM(F11:F14) -> 109497 | G15: =SUM(G11:G14) -> 101419 | H15: =SUM(H11:H14) -> 100788 | I15: =SUM(I11:I14) -> 112447 | J15: =SUM(J11:J14) -> 111819 | K15: =SUM(K11:K14) -> 116724 | ... P15: =SUM(P11:P14) -> 1268059
A16: REVENUE WATER - PREPAID
A17: Individuals | C17: m3 | D17: =Mangochi!D17+'Monkey Bay'!D17+Namwera!D17 -> 16084.4 | E17: =Mangochi!E17+'Monkey Bay'!E17+Namwera!E17 -> 21488.9 | F17: =Mangochi!F17+'Monkey Bay'!F17+Namwera!F17 -> 18069 | G17: =Mangochi!G17+'Monkey Bay'!G17+Namwera!G17 -> 20875.3 | H17: =Mangochi!H17+'Monkey Bay'!H17+Namwera!H17 -> 19573 | I17: =Mangochi!I17+'Monkey Bay'!I17+Namwera!I17 -> 19574.9 | J17: =Mangochi!J17+'Monkey Bay'!J17+Namwera!J17+Nkhudzi!J17 -> 23907.2 | K17: =Mangochi!K17+'Monkey Bay'!K17+Namwera!K17+Nkhudzi!K17 -> 24508.2 | L17: =Mangochi!L17+'Monkey Bay'!L17+Namwera!L17+Nkhudzi!L17 -> 34648 | M17: =Mangochi!M17+'Monkey Bay'!M17+Namwera!M17+Nkhudzi!M17 -> 25303.5 | N17: =Mangochi!N17+'Monkey Bay'!N17+Namwera!N17+Nkhudzi!N17 -> 32126.2 | O17: =Mangochi!O17+'Monkey Bay'!O17+Namwera!O17+Nkhudzi!O17 -> 24311.6 | P17: =SUM(D17:O17) -> 280470.2
A18: CWPs | C18: m3 | D18: =Mangochi!D18+'Monkey Bay'!D18+Namwera!D18 -> 1201 | E18: =Mangochi!E18+'Monkey Bay'!E18+Namwera!E18 -> 1204 | F18: =Mangochi!F18+'Monkey Bay'!F18+Namwera!F18 -> 1117 | G18: =Mangochi!G18+'Monkey Bay'!G18+Namwera!G18 -> 1425 | H18: =Mangochi!H18+'Monkey Bay'!H18+Namwera!H18 -> 1210 | I18: =Mangochi!I18+'Monkey Bay'!I18+Namwera!I18 -> 1159 | J18: =Mangochi!J18+'Monkey Bay'!J18+Namwera!J18+Nkhudzi!J18 -> 1219 | K18: =Mangochi!K18+'Monkey Bay'!K18+Namwera!K18+Nkhudzi!K18 -> 1021 | L18: =Mangochi!L18+'Monkey Bay'!L18+Namwera!L18+Nkhudzi!L18 -> 0 | M18: =Mangochi!M18+'Monkey Bay'!M18+Namwera!M18+Nkhudzi!M18 -> 1506 | N18: =Mangochi!N18+'Monkey Bay'!N18+Namwera!N18+Nkhudzi!N18 -> 1601 | O18: =Mangochi!O18+'Monkey Bay'!O18+Namwera!O18+Nkhudzi!O18 -> 1426 | P18: =SUM(D18:O18) -> 14089
A19: Institutions | C19: m3 | D19: =Mangochi!D19+'Monkey Bay'!D19+Namwera!D19 -> 3086 | E19: =Mangochi!E19+'Monkey Bay'!E19+Namwera!E19 -> 4025 | F19: =Mangochi!F19+'Monkey Bay'!F19+Namwera!F19 -> 3473 | G19: =Mangochi!G19+'Monkey Bay'!G19+Namwera!G19 -> 2773 | H19: =Mangochi!H19+'Monkey Bay'!H19+Namwera!H19 -> 3401 | I19: =Mangochi!I19+'Monkey Bay'!I19+Namwera!I19 -> 4138 | J19: =Mangochi!J19+'Monkey Bay'!J19+Namwera!J19+Nkhudzi!J19 -> 4466 | K19: =Mangochi!K19+'Monkey Bay'!K19+Namwera!K19+Nkhudzi!K19 -> 4513 | L19: =Mangochi!L19+'Monkey Bay'!L19+Namwera!L19+Nkhudzi!L19 -> 200 | M19: =Mangochi!M19+'Monkey Bay'!M19+Namwera!M19+Nkhudzi!M19 -> 5281 | N19: =Mangochi!N19+'Monkey Bay'!N19+Namwera!N19+Nkhudzi!N19 -> 4798 | O19: =Mangochi!O19+'Monkey Bay'!O19+Namwera!O19+Nkhudzi!O19 -> 3503 | P19: =SUM(D19:O19) -> 43657
A20: Commercial/Industrial | C20: m3 | D20: =Mangochi!D20+'Monkey Bay'!D20+Namwera!D20 -> 414 | E20: =Mangochi!E20+'Monkey Bay'!E20+Namwera!E20 -> 565 | F20: =Mangochi!F20+'Monkey Bay'!F20+Namwera!F20 -> 482 | G20: =Mangochi!G20+'Monkey Bay'!G20+Namwera!G20 -> 354 | H20: =Mangochi!H20+'Monkey Bay'!H20+Namwera!H20 -> 539 | I20: =Mangochi!I20+'Monkey Bay'!I20+Namwera!I20 -> 539 | J20: =Mangochi!J20+'Monkey Bay'!J20+Namwera!J20+Nkhudzi!J20 -> 550 | K20: =Mangochi!K20+'Monkey Bay'!K20+Namwera!K20+Nkhudzi!K20 -> 441 | L20: =Mangochi!L20+'Monkey Bay'!L20+Namwera!L20+Nkhudzi!L20 -> 33 | M20: =Mangochi!M20+'Monkey Bay'!M20+Namwera!M20+Nkhudzi!M20 -> 545 | N20: =Mangochi!N20+'Monkey Bay'!N20+Namwera!N20+Nkhudzi!N20 -> 576 | O20: =Mangochi!O20+'Monkey Bay'!O20+Namwera!O20+Nkhudzi!O20 -> 534 | P20: =SUM(D20:O20) -> 5572
A21: Total Volume Prepaid | C21: m3 | D21: =SUM(D17:D20) -> 20785.4 | E21: =SUM(E17:E20) -> 27282.9 | F21: =SUM(F17:F20) -> 23141 | G21: =SUM(G17:G20) -> 25427.3 | H21: =SUM(H17:H20) -> 24723 | I21: =SUM(I17:I20) -> 25410.9 | J21: =SUM(J17:J20) -> 30142.2 | K21: =SUM(K17:K20) -> 30483.2 | ... P21: =SUM(P17:P20) -> 343788.2
A22: TOTAL REVENUE WATER | C22: m3 | D22: =D21+D15 -> 114516.4 | E22: =E21+E15 -> 122974.9 | F22: =F21+F15 -> 132638 | G22: =G21+G15 -> 126846.3 | H22: =H21+H15 -> 125511 | I22: =I21+I15 -> 137857.9 | J22: =J21+J15 -> 141961.2 | K22: =K21+K15 -> 147207.2 | ... P22: =P21+P15 -> 1611847.2
A24: Non-Revenue Water (NRW) | B24: Volume | C24: m3 | D24: =D9-D22 -> 74293.6 | E24: =E9-E22 -> 71906.1 | F24: =F9-F22 -> 68948 | G24: =G9-G22 -> 66665.7 | H24: =H9-H22 -> 69289 | I24: =I9-I22 -> 53667.1 | J24: =J9-J22 -> 63333.8 | K24: =K9-K22 -> 83197.9 | ... P24: =P9-P22 -> 786464.6
B25: Percentage | C25: % | D25: =D24/D9 -> 0.3934834 | E25: =E24/E9 -> 0.3689744 | F25: =F24/F9 -> 0.34202772 | G25: =G24/G9 -> 0.34450422 | H25: =H24/H9 -> 0.35569302 | I25: =I24/I9 -> 0.28020937 | J25: =J24/J9 -> 0.30850142 | K25: =K24/K9 -> 0.361094 | ... P25: =P24/P9 -> 0.32792425
A26: OPERATING EXPENSES
A27: Chemicals
A28: Chemical | B28: Rate(MK/kg)
A29: Chlorine | B29: 7400 | C29: kg | D29: =Mangochi!D29+'Monkey Bay'!D29+Namwera!D29 -> 552 | E29: =Mangochi!E29+'Monkey Bay'!E29+Namwera!E29 -> 807 | F29: =Mangochi!F29+'Monkey Bay'!F29+Namwera!F29 -> 760.5 | G29: =Mangochi!G29+'Monkey Bay'!G29+Namwera!G29 -> 710 | H29: =Mangochi!H29+'Monkey Bay'!H29+Namwera!H29 -> 684 | I29: =Mangochi!I29+'Monkey Bay'!I29+Namwera!I29 -> 663 | J29: =Mangochi!J29+'Monkey Bay'!J29+Namwera!J29+Nkhudzi!J29 -> 920 | K29: =Mangochi!K29+'Monkey Bay'!K29+Namwera!K29+Nkhudzi!K29 -> 815 | L29: =Mangochi!L29+'Monkey Bay'!L29+Namwera!L29+Nkhudzi!L29 -> 746 | M29: =Mangochi!M29+'Monkey Bay'!M29+Namwera!M29+Nkhudzi!M29 -> 756 | N29: =Mangochi!N29+'Monkey Bay'!N29+Namwera!N29+Nkhudzi!N29 -> 829.5 | O29: =Mangochi!O29+'Monkey Bay'!O29+Namwera!O29+Nkhudzi!O29 -> 871 | P29: =SUM(D29:O29) -> 9114
C30: kg/mg litre | D30: =Mangochi!D30+'Monkey Bay'!D30+Namwera!D30 -> 7.9088285 | E30: =Mangochi!E30+'Monkey Bay'!E30+Namwera!E30 -> 9.9108569 | F30: =Mangochi!F30+'Monkey Bay'!F30+Namwera!F30 -> 8.9970779 | G30: =Mangochi!G30+'Monkey Bay'!G30+Namwera!G30 -> 9.8317023 | H30: =Mangochi!H30+'Monkey Bay'!H30+Namwera!H30 -> 8.9980641 | I30: =Mangochi!I30+'Monkey Bay'!I30+Namwera!I30 -> 8.5844261 | J30: =Mangochi!J30+'Monkey Bay'!J30+Namwera!J30+Nkhudzi!J30 -> 96.496585 | K30: =Mangochi!K30+'Monkey Bay'!K30+Namwera!K30+Nkhudzi!K30 -> 49.362245 | L30: =Mangochi!L30+'Monkey Bay'!L30+Namwera!L30+Nkhudzi!L30 -> 38.130991 | M30: =Mangochi!M30+'Monkey Bay'!M30+Namwera!M30+Nkhudzi!M30 -> 41.602549 | N30: =Mangochi!N30+'Monkey Bay'!N30+Namwera!N30+Nkhudzi!N30 -> 40.17915 | O30: =Mangochi!O30+'Monkey Bay'!O30+Namwera!O30+Nkhudzi!O30 -> 60.787865 | P30: =P29/(P9/1000) -> 3.8001731
A31: Aluminium sulphate | B31: 1900 | C31: kg | D31: =Mangochi!D31+'Monkey Bay'!D31+Namwera!D31 -> 800 | E31: =Mangochi!E31+'Monkey Bay'!E31+Namwera!E31 -> 0 | F31: =Mangochi!F31+'Monkey Bay'!F31+Namwera!F31 -> 0 | G31: =Mangochi!G31+'Monkey Bay'!G31+Namwera!G31 -> 0 | H31: =Mangochi!H31+'Monkey Bay'!H31+Namwera!H31 -> 0 | I31: =Mangochi!I31+'Monkey Bay'!I31+Namwera!I31 -> 0 | J31: =Mangochi!J31+'Monkey Bay'!J31+Namwera!J31 -> 0 | K31: =Mangochi!K31+'Monkey Bay'!K31+Namwera!K31 -> 0 | ... O31: =Mangochi!O31+'Monkey Bay'!O31+Namwera!O31 -> 50 | P31: =SUM(D31:O31) -> 1100
C32: kg/mg litre | D32: =Mangochi!D32+'Monkey Bay'!D32+Namwera!D32 -> 6.2031372 | E32: =Mangochi!E32+'Monkey Bay'!E32+Namwera!E32 -> 0 | F32: =Mangochi!F32+'Monkey Bay'!F32+Namwera!F32 -> 0 | G32: =Mangochi!G32+'Monkey Bay'!G32+Namwera!G32 -> 0 | H32: =Mangochi!H32+'Monkey Bay'!H32+Namwera!H32 -> 0 | I32: =Mangochi!I32+'Monkey Bay'!I32+Namwera!I32 -> 0 | J32: =Mangochi!J32+'Monkey Bay'!J32+Namwera!J32 -> 0 | K32: =Mangochi!K32+'Monkey Bay'!K32+Namwera!K32 -> 0 | ... O32: =Mangochi!O32+'Monkey Bay'!O32+Namwera!O32 -> 0.40255704 | P32: =P31/(P9/1000) -> 0.45865596
A33: Soda | B33: 1900 | C33: kg | D33: =Mangochi!D33+'Monkey Bay'!D33+Namwera!D33 -> 0 | E33: =Mangochi!E33+'Monkey Bay'!E33+Namwera!E33 -> 0 | F33: =Mangochi!F33+'Monkey Bay'!F33+Namwera!F33 -> 0 | G33: =Mangochi!G33+'Monkey Bay'!G33+Namwera!G33 -> 0 | H33: =Mangochi!H33+'Monkey Bay'!H33+Namwera!H33 -> 0 | I33: =Mangochi!I33+'Monkey Bay'!I33+Namwera!I33 -> 0 | J33: =Mangochi!J33+'Monkey Bay'!J33+Namwera!J33 -> 0 | K33: =Mangochi!K33+'Monkey Bay'!K33+Namwera!K33 -> 0 | ... O33: =Mangochi!O33+'Monkey Bay'!O33+Namwera!O33 -> 0 | P33: =SUM(D33:O33) -> 0
C34: kg/mg litre | D34: =Mangochi!D34+'Monkey Bay'!D34+Namwera!D34 -> 0 | E34: =Mangochi!E34+'Monkey Bay'!E34+Namwera!E34 -> 0 | F34: =Mangochi!F34+'Monkey Bay'!F34+Namwera!F34 -> 0 | G34: =Mangochi!G34+'Monkey Bay'!G34+Namwera!G34 -> 0 | H34: =Mangochi!H34+'Monkey Bay'!H34+Namwera!H34 -> 0 | I34: =Mangochi!I34+'Monkey Bay'!I34+Namwera!I34 -> 0 | J34: =Mangochi!J34+'Monkey Bay'!J34+Namwera!J34 -> 0 | K34: =Mangochi!K34+'Monkey Bay'!K34+Namwera!K34 -> 0 | ... O34: =Mangochi!O34+'Monkey Bay'!O34+Namwera!O34 -> 0 | P34: =P33/(P9/1000) -> 0
A35: Algae floc | B35: =745345.16/200 -> 3726.7258 | C35: litres | D35: =Mangochi!D35+'Monkey Bay'!D35+Namwera!D35 -> 0 | E35: =Mangochi!E35+'Monkey Bay'!E35+Namwera!E35 -> 0 | F35: =Mangochi!F35+'Monkey Bay'!F35+Namwera!F35 -> 0 | G35: =Mangochi!G35+'Monkey Bay'!G35+Namwera!G35 -> 0 | H35: =Mangochi!H35+'Monkey Bay'!H35+Namwera!H35 -> 0 | I35: =Mangochi!I35+'Monkey Bay'!I35+Namwera!I35 -> 0 | J35: =Mangochi!J35+'Monkey Bay'!J35+Namwera!J35 -> 0 | K35: =Mangochi!K35+'Monkey Bay'!K35+Namwera!K35 -> 0 | ... O35: =Mangochi!O35+'Monkey Bay'!O35+Namwera!O35 -> 0
C36: litres/mg litre
A37: Sud floc | B37: =790318.72/200 -> 3951.5936 | C37: litres | D37: =Mangochi!D37+'Monkey Bay'!D37+Namwera!D37 -> 0 | E37: =Mangochi!E37+'Monkey Bay'!E37+Namwera!E37 -> 0 | F37: =Mangochi!F37+'Monkey Bay'!F37+Namwera!F37 -> 0 | G37: =Mangochi!G37+'Monkey Bay'!G37+Namwera!G37 -> 0 | H37: =Mangochi!H37+'Monkey Bay'!H37+Namwera!H37 -> 0 | I37: =Mangochi!I37+'Monkey Bay'!I37+Namwera!I37 -> 0 | J37: =Mangochi!J37+'Monkey Bay'!J37+Namwera!J37 -> 0 | K37: =Mangochi!K37+'Monkey Bay'!K37+Namwera!K37 -> 0 | ... O37: =Mangochi!O37+'Monkey Bay'!O37+Namwera!O37 -> 0 | P37: =SUM(D37:O37) -> 0
C38: litres/mg litre | D38: =Mangochi!D38+'Monkey Bay'!D38+Namwera!D38 -> 0 | E38: =Mangochi!E38+'Monkey Bay'!E38+Namwera!E38 -> 0 | F38: =Mangochi!F38+'Monkey Bay'!F38+Namwera!F38 -> 0 | G38: =Mangochi!G38+'Monkey Bay'!G38+Namwera!G38 -> 0 | H38: =Mangochi!H38+'Monkey Bay'!H38+Namwera!H38 -> 0 | I38: =Mangochi!I38+'Monkey Bay'!I38+Namwera!I38 -> 0 | J38: =Mangochi!J38+'Monkey Bay'!J38+Namwera!J38 -> 0 | K38: =Mangochi!K38+'Monkey Bay'!K38+Namwera!K38 -> 0 | ... O38: =Mangochi!O38+'Monkey Bay'!O38+Namwera!O38 -> 0 | P38: =P37/(P9/1000) -> 0
A39: Potasium permanganate | B39: 1950 | C39: kg | D39: =Mangochi!D39+'Monkey Bay'!D39+Namwera!D39 -> 0 | E39: =Mangochi!E39+'Monkey Bay'!E39+Namwera!E39 -> 0 | F39: =Mangochi!F39+'Monkey Bay'!F39+Namwera!F39 -> 0 | G39: =Mangochi!G39+'Monkey Bay'!G39+Namwera!G39 -> 0 | H39: =Mangochi!H39+'Monkey Bay'!H39+Namwera!H39 -> 0 | I39: =Mangochi!I39+'Monkey Bay'!I39+Namwera!I39 -> 0 | J39: =Mangochi!J39+'Monkey Bay'!J39+Namwera!J39 -> 0 | K39: =Mangochi!K39+'Monkey Bay'!K39+Namwera!K39 -> 0 | ... O39: =Mangochi!O39+'Monkey Bay'!O39+Namwera!O39 -> 0 | P39: =SUM(D39:O39) -> 0
C40: kg/mg litre | D40: =Mangochi!D40+'Monkey Bay'!D40+Namwera!D40 -> 0 | E40: =Mangochi!E40+'Monkey Bay'!E40+Namwera!E40 -> 0 | F40: =Mangochi!F40+'Monkey Bay'!F40+Namwera!F40 -> 0 | G40: =Mangochi!G40+'Monkey Bay'!G40+Namwera!G40 -> 0 | H40: =Mangochi!H40+'Monkey Bay'!H40+Namwera!H40 -> 0 | I40: =Mangochi!I40+'Monkey Bay'!I40+Namwera!I40 -> 0 | J40: =Mangochi!J40+'Monkey Bay'!J40+Namwera!J40 -> 0 | K40: =Mangochi!K40+'Monkey Bay'!K40+Namwera!K40 -> 0 | ... O40: =Mangochi!O40+'Monkey Bay'!O40+Namwera!O40 -> 0 | P40: =P39/(P9/1000) -> 0
A41: Cost of Chemicals | C41: Mk | D41: =Mangochi!D41+'Monkey Bay'!D41+Namwera!D41 -> 2793968.3 | E41: =Mangochi!E41+'Monkey Bay'!E41+Namwera!E41 -> 2844909 | F41: =Mangochi!F41+'Monkey Bay'!F41+Namwera!F41 -> 2680983 | G41: =Mangochi!G41+'Monkey Bay'!G41+Namwera!G41 -> 2502955.9 | H41: =Mangochi!H41+'Monkey Bay'!H41+Namwera!H41 -> 2411298.4 | I41: =Mangochi!I41+'Monkey Bay'!I41+Namwera!I41 -> 2337267.3 | J41: =Mangochi!J41+'Monkey Bay'!J41+Namwera!J41+Nkhudzi!J41 -> 3243266.8 | K41: =Mangochi!K41+'Monkey Bay'!K41+Namwera!K41+Nkhudzi!K41 -> 2873111.4 | L41: =Mangochi!L41+'Monkey Bay'!L41+Namwera!L41+Nkhudzi!L41 -> 2629866.3 | M41: =Mangochi!M41+'Monkey Bay'!M41+Namwera!M41+Nkhudzi!M41 -> 2877121.3 | N41: =Mangochi!N41+'Monkey Bay'!N41+Namwera!N41+Nkhudzi!N41 -> 2977228.6 | O41: =Mangochi!O41+'Monkey Bay'!O41+Namwera!O41+Nkhudzi!O41 -> 3123528.1 | P41: =SUM(D41:O41) -> 33295504
A42: Cost/vol. Produced (chemicals) | C42: Mk/m3 | D42: =Mangochi!D42+'Monkey Bay'!D42+Namwera!D42 -> 34.456303 | E42: =Mangochi!E42+'Monkey Bay'!E42+Namwera!E42 -> 34.938645 | F42: =Mangochi!F42+'Monkey Bay'!F42+Namwera!F42 -> 31.717309 | G42: =Mangochi!G42+'Monkey Bay'!G42+Namwera!G42 -> 34.659602 | H42: =Mangochi!H42+'Monkey Bay'!H42+Namwera!H42 -> 31.720785 | I42: =Mangochi!I42+'Monkey Bay'!I42+Namwera!I42 -> 30.262592 | J42: =Mangochi!J42+'Monkey Bay'!J42+Namwera!J42+Nkhudzi!J42 -> 340.17844 | K42: =Mangochi!K42+'Monkey Bay'!K42+Namwera!K42+Nkhudzi!K42 -> 174.01623 | L42: =Mangochi!L42+'Monkey Bay'!L42+Namwera!L42+Nkhudzi!L42 -> 134.4228 | M42: =Mangochi!M42+'Monkey Bay'!M42+Namwera!M42+Nkhudzi!M42 -> 148.16399 | N42: =Mangochi!N42+'Monkey Bay'!N42+Namwera!N42+Nkhudzi!N42 -> 142.05226 | O42: =Mangochi!O42+'Monkey Bay'!O42+Namwera!O42+Nkhudzi!O42 -> 214.72157 | P42: =P41/P9 -> 13.882892
A43: Power
A44: Power Usage | C44: Kw | D44: =Mangochi!D44+'Monkey Bay'!D44+Namwera!D44 -> 82992.48 | E44: =Mangochi!E44+'Monkey Bay'!E44+Namwera!E44 -> 83832.72 | F44: =Mangochi!F44+'Monkey Bay'!F44+Namwera!F44 -> 86637.72 | G44: =Mangochi!G44+'Monkey Bay'!G44+Namwera!G44 -> 76047.55 | H44: =Mangochi!H44+'Monkey Bay'!H44+Namwera!H44 -> 84163 | I44: =Mangochi!I44+'Monkey Bay'!I44+Namwera!I44 -> 81216.67 | J44: =Mangochi!J44+'Monkey Bay'!J44+Namwera!J44+Nkhudzi!J44 -> 87508.33 | K44: =Mangochi!K44+'Monkey Bay'!K44+Namwera!K44+Nkhudzi!K44 -> 82792.12 | L44: =Mangochi!L44+'Monkey Bay'!L44+Namwera!L44+Nkhudzi!L44 -> 119396.76 | M44: =Mangochi!M44+'Monkey Bay'!M44+Namwera!M44+Nkhudzi!M44 -> 178853.13 | N44: =Mangochi!N44+'Monkey Bay'!N44+Namwera!N44+Nkhudzi!N44 -> 132506.25 | O44: =Mangochi!O44+'Monkey Bay'!O44+Namwera!O44+Nkhudzi!O44 -> 124621.12 | P44: =SUM(D44:O44) -> 1220567.9
A45: Power/ Vol. Produced | C45: Kw/m3 | D45: =Mangochi!D45+'Monkey Bay'!D45+Namwera!D45 -> 1.6653733 | E45: =Mangochi!E45+'Monkey Bay'!E45+Namwera!E45 -> 1.6245985 | F45: =Mangochi!F45+'Monkey Bay'!F45+Namwera!F45 -> 1.4368964 | G45: =Mangochi!G45+'Monkey Bay'!G45+Namwera!G45 -> 1.5785357 | H45: =Mangochi!H45+'Monkey Bay'!H45+Namwera!H45 -> 1.5844554 | I45: =Mangochi!I45+'Monkey Bay'!I45+Namwera!I45 -> 1.6146922 | J45: =Mangochi!J45+'Monkey Bay'!J45+Namwera!J45+Nkhudzi!J45 -> 1.7878808 | K45: =Mangochi!K45+'Monkey Bay'!K45+Namwera!K45+Nkhudzi!K45 -> 1.6593565 | L45: =Mangochi!L45+'Monkey Bay'!L45+Namwera!L45+Nkhudzi!L45 -> 10.713752 | M45: =Mangochi!M45+'Monkey Bay'!M45+Namwera!M45+Nkhudzi!M45 -> 27.187434 | N45: =Mangochi!N45+'Monkey Bay'!N45+Namwera!N45+Nkhudzi!N45 -> 14.237169 | O45: =Mangochi!O45+'Monkey Bay'!O45+Namwera!O45+Nkhudzi!O45 -> 17.833141 | P45: =P44/P9 -> 0.50892793
A46: Cost of Power | C46: Mk | D46: =Mangochi!D46+'Monkey Bay'!D46+Namwera!D46 -> 11564611 | E46: =Mangochi!E46+'Monkey Bay'!E46+Namwera!E46 -> 11681195 | F46: =Mangochi!F46+'Monkey Bay'!F46+Namwera!F46 -> 12070393 | G46: =Mangochi!G46+'Monkey Bay'!G46+Namwera!G46 -> 10600991 | H46: =Mangochi!H46+'Monkey Bay'!H46+Namwera!H46 -> 14128177 | I46: =Mangochi!I46+'Monkey Bay'!I46+Namwera!I46 -> 13635617 | J46: =Mangochi!J46+'Monkey Bay'!J46+Namwera!J46+Nkhudzi!J46 -> 36470387 | K46: =Mangochi!K46+'Monkey Bay'!K46+Namwera!K46+Nkhudzi!K46 -> 34271080 | L46: =Mangochi!L46+'Monkey Bay'!L46+Namwera!L46+Nkhudzi!L46 -> 56268643 | M46: =Mangochi!M46+'Monkey Bay'!M46+Namwera!M46+Nkhudzi!M46 -> 56285088 | N46: =Mangochi!N46+'Monkey Bay'!N46+Namwera!N46+Nkhudzi!N46 -> 56332487 | O46: =Mangochi!O46+'Monkey Bay'!O46+Namwera!O46+Nkhudzi!O46 -> 55699197 | P46: =SUM(D46:O46) -> 3.6900787e+08
A47: Cost/vol. Produced | C47: Mk/m3 | D47: =Mangochi!D47+'Monkey Bay'!D47+Namwera!D47 -> 235.45261 | E47: =Mangochi!E47+'Monkey Bay'!E47+Namwera!E47 -> 228.41372 | F47: =Mangochi!F47+'Monkey Bay'!F47+Namwera!F47 -> 202.77946 | G47: =Mangochi!G47+'Monkey Bay'!G47+Namwera!G47 -> 222.54526 | H47: =Mangochi!H47+'Monkey Bay'!H47+Namwera!H47 -> 269.31597 | I47: =Mangochi!I47+'Monkey Bay'!I47+Namwera!I47 -> 273.55796 | J47: =Mangochi!J47+'Monkey Bay'!J47+Namwera!J47+Nkhudzi!J47 -> 8752.571 | K47: =Mangochi!K47+'Monkey Bay'!K47+Namwera!K47+Nkhudzi!K47 -> 6881.0988 | L47: =Mangochi!L47+'Monkey Bay'!L47+Namwera!L47+Nkhudzi!L47 -> 10019.727 | M47: =Mangochi!M47+'Monkey Bay'!M47+Namwera!M47+Nkhudzi!M47 -> 11338.643 | N47: =Mangochi!N47+'Monkey Bay'!N47+Namwera!N47+Nkhudzi!N47 -> 10664.085 | O47: =Mangochi!O47+'Monkey Bay'!O47+Namwera!O47+Nkhudzi!O47 -> 14425.415 | P47: =P46/P9 -> 153.86151
A48: Plant and Vehicle Maintenance
A49: Distances covered | C49: km | D49: =Mangochi!D49+'Monkey Bay'!D49+Namwera!D49 -> 5386 | E49: =Mangochi!E49+'Monkey Bay'!E49+Namwera!E49 -> 4690 | F49: =Mangochi!F49+'Monkey Bay'!F49+Namwera!F49 -> 7129 | G49: =Mangochi!G49+'Monkey Bay'!G49+Namwera!G49 -> 9224 | H49: =Mangochi!H49+'Monkey Bay'!H49+Namwera!H49 -> 9084 | I49: =Mangochi!I49+'Monkey Bay'!I49+Namwera!I49 -> 11759 | J49: =Mangochi!J49+'Monkey Bay'!J49+Namwera!J49+Nkhudzi!J49 -> 13995 | K49: =Mangochi!K49+'Monkey Bay'!K49+Namwera!K49+Nkhudzi!K49 -> 9663 | L49: =Mangochi!L49+'Monkey Bay'!L49+Namwera!L49+Nkhudzi!L49 -> 8540 | M49: =Mangochi!M49+'Monkey Bay'!M49+Namwera!M49+Nkhudzi!M49 -> 17222 | N49: =Mangochi!N49+'Monkey Bay'!N49+Namwera!N49+Nkhudzi!N49 -> 11650 | O49: =Mangochi!O49+'Monkey Bay'!O49+Namwera!O49+Nkhudzi!O49 -> 9076 | P49: =SUM(D49:O49) -> 117418
A50: Fuel Used (litres) | C50: litres | D50: =Mangochi!D50+'Monkey Bay'!D50+Namwera!D50 -> 1255.93 | E50: =Mangochi!E50+'Monkey Bay'!E50+Namwera!E50 -> 1090.97 | F50: =Mangochi!F50+'Monkey Bay'!F50+Namwera!F50 -> 1438 | G50: =Mangochi!G50+'Monkey Bay'!G50+Namwera!G50 -> 1246.56 | H50: =Mangochi!H50+'Monkey Bay'!H50+Namwera!H50 -> 1027.24 | I50: =Mangochi!I50+'Monkey Bay'!I50+Namwera!I50 -> 1242.4 | J50: =Mangochi!J50+'Monkey Bay'!J50+Namwera!J50+Nkhudzi!J50 -> 1852.82 | K50: =Mangochi!K50+'Monkey Bay'!K50+Namwera!K50+Nkhudzi!K50 -> 1377.84 | L50: =Mangochi!L50+'Monkey Bay'!L50+Namwera!L50+Nkhudzi!L50 -> 1281.76 | M50: =Mangochi!M50+'Monkey Bay'!M50+Namwera!M50+Nkhudzi!M50 -> 1594.21 | N50: =Mangochi!N50+'Monkey Bay'!N50+Namwera!N50+Nkhudzi!N50 -> 1108.26 | O50: =Mangochi!O50+'Monkey Bay'!O50+Namwera!O50+Nkhudzi!O50 -> 1094.95 | P50: =SUM(D50:O50) -> 15610.94
A51: Cost of fuel | C51: Mk | D51: =Mangochi!D51+'Monkey Bay'!D51+Namwera!D51 -> 2411520 | E51: =Mangochi!E51+'Monkey Bay'!E51+Namwera!E51 -> 2090272 | F51: =Mangochi!F51+'Monkey Bay'!F51+Namwera!F51 -> 2762344 | G51: =Mangochi!G51+'Monkey Bay'!G51+Namwera!G51 -> 2391148 | H51: =Mangochi!H51+'Monkey Bay'!H51+Namwera!H51 -> 1971840 | I51: =Mangochi!I51+'Monkey Bay'!I51+Namwera!I51 -> 2386368 | J51: =Mangochi!J51+'Monkey Bay'!J51+Namwera!J51+Nkhudzi!J51 -> 2753534.4 | K51: =Mangochi!K51+'Monkey Bay'!K51+Namwera!K51+Nkhudzi!K51 -> 3767051.4 | L51: =Mangochi!L51+'Monkey Bay'!L51+Namwera!L51+Nkhudzi!L51 -> 3504331.8 | M51: =Mangochi!M51+'Monkey Bay'!M51+Namwera!M51+Nkhudzi!M51 -> 4357996 | N51: =Mangochi!N51+'Monkey Bay'!N51+Namwera!N51+Nkhudzi!N51 -> 3029272 | O51: =Mangochi!O51+'Monkey Bay'!O51+Namwera!O51+Nkhudzi!O51 -> 2993602.4 | P51: =SUM(D51:O51) -> 34419280
A52: Maintenance | C52: Mk | D52: =Mangochi!D52+'Monkey Bay'!D52+Namwera!D52 -> 0 | E52: =Mangochi!E52+'Monkey Bay'!E52+Namwera!E52 -> 0 | F52: =Mangochi!F52+'Monkey Bay'!F52+Namwera!F52 -> 0 | G52: =Mangochi!G52+'Monkey Bay'!G52+Namwera!G52 -> 0 | H52: =Mangochi!H52+'Monkey Bay'!H52+Namwera!H52 -> 10000 | I52: =Mangochi!I52+'Monkey Bay'!I52+Namwera!I52 -> 0 | J52: =Mangochi!J52+'Monkey Bay'!J52+Namwera!J52+Nkhudzi!J52 -> 0 | K52: =Mangochi!K52+'Monkey Bay'!K52+Namwera!K52+Nkhudzi!K52 -> 0 | L52: =Mangochi!L52+'Monkey Bay'!L52+Namwera!L52 -> 0 | M52: =Mangochi!M52+'Monkey Bay'!M52+Namwera!M52 -> 0 | N52: =Mangochi!N52+'Monkey Bay'!N52+Namwera!N52 -> 0 | O52: =Mangochi!O52+'Monkey Bay'!O52+Namwera!O52 -> 0 | P52: =SUM(D52:O52) -> 10000
A53: Salaries and Wages
A54: Staff Costs | C54: MK | D54: =Mangochi!D54+'Monkey Bay'!D54+Namwera!D54 -> 20236632 | E54: =Mangochi!E54+'Monkey Bay'!E54+Namwera!E54 -> 22250834 | F54: =Mangochi!F54+'Monkey Bay'!F54+Namwera!F54 -> 20547194 | G54: =Mangochi!G54+'Monkey Bay'!G54+Namwera!G54 -> 15279625 | H54: =Mangochi!H54+'Monkey Bay'!H54+Namwera!H54 -> 16107761 | I54: =Mangochi!I54+'Monkey Bay'!I54+Namwera!I54 -> 18948899 | J54: =Mangochi!J54+'Monkey Bay'!J54+Namwera!J54+Nkhudzi!J54 -> 15122758 | K54: =Mangochi!K54+'Monkey Bay'!K54+Namwera!K54+Nkhudzi!K54 -> 23440642 | L54: =Mangochi!L54+'Monkey Bay'!L54+Namwera!L54+Nkhudzi!L54 -> 32200113 | M54: =Mangochi!M54+'Monkey Bay'!M54+Namwera!M54+Nkhudzi!M54 -> 34864306 | N54: =Mangochi!N54+'Monkey Bay'!N54+Namwera!N54+Nkhudzi!N54 -> 34864306 | O54: =Mangochi!O54+'Monkey Bay'!O54+Namwera!O54+Nkhudzi!O54 -> 29078142 | P54: =SUM(D54:O54) -> 2.8294121e+08
A55: Wages | C55: MK | D55: =Mangochi!D55+'Monkey Bay'!D55+Namwera!D55 -> 2784740 | E55: =Mangochi!E55+'Monkey Bay'!E55+Namwera!E55 -> 2756134.2 | F55: =Mangochi!F55+'Monkey Bay'!F55+Namwera!F55 -> 2605352.7 | G55: =Mangochi!G55+'Monkey Bay'!G55+Namwera!G55 -> 2982697.1 | H55: =Mangochi!H55+'Monkey Bay'!H55+Namwera!H55 -> 3528851.8 | I55: =Mangochi!I55+'Monkey Bay'!I55+Namwera!I55 -> 4903974.2 | J55: =Mangochi!J55+'Monkey Bay'!J55+Namwera!J55+Nkhudzi!J55 -> 7764375.4 | K55: =Mangochi!K55+'Monkey Bay'!K55+Namwera!K55+Nkhudzi!K55 -> 5706499.5 | L55: =Mangochi!L55+'Monkey Bay'!L55+Namwera!L55+Nkhudzi!L55 -> 5489672.2 | M55: =Mangochi!M55+'Monkey Bay'!M55+Namwera!M55+Nkhudzi!M55 -> 7546802.9 | N55: =Mangochi!N55+'Monkey Bay'!N55+Namwera!N55+Nkhudzi!N55 -> 14818961 | O55: =Mangochi!O55+'Monkey Bay'!O55+Namwera!O55+Nkhudzi!O55 -> 14553937 | P55: =SUM(D55:O55) -> 75441998
A56: Other Overhead Costs | C56: MK | D56: =Mangochi!D56+'Monkey Bay'!D56+Namwera!D56 -> 2063450 | E56: =Mangochi!E56+'Monkey Bay'!E56+Namwera!E56 -> 2061700 | F56: =Mangochi!F56+'Monkey Bay'!F56+Namwera!F56 -> 2073200 | G56: =Mangochi!G56+'Monkey Bay'!G56+Namwera!G56 -> 2082700 | H56: =Mangochi!H56+'Monkey Bay'!H56+Namwera!H56 -> 2093050 | I56: =Mangochi!I56+'Monkey Bay'!I56+Namwera!I56 -> 2110800 | J56: =Mangochi!J56+'Monkey Bay'!J56+Namwera!J56+Nkhudzi!J56 -> 2125500 | K56: =Mangochi!K56+'Monkey Bay'!K56+Namwera!K56+Nkhudzi!K56 -> 2133100 | L56: =Mangochi!L56+'Monkey Bay'!L56+Namwera!L56+Nkhudzi!L56 -> 2132700 | M56: =Mangochi!M56+'Monkey Bay'!M56+Namwera!M56+Nkhudzi!M56 -> 1983750 | N56: =Mangochi!N56+'Monkey Bay'!N56+Namwera!N56+Nkhudzi!N56 -> 2460000 | O56: =Mangochi!O56+'Monkey Bay'!O56+Namwera!O56+Nkhudzi!O56 -> 2408400 | P56: =SUM(D56:O56) -> 25728350
A57: Operating Costs
A58: Total Operating Costs | C58: MK | D58: =D41+D46+D51+D52+D54+D55+D56 -> 41854920 | E58: =E41+E46+E51+E52+E54+E55+E56 -> 43685044 | F58: =F41+F46+F51+F52+F54+F55+F56 -> 42739467 | G58: =G41+G46+G51+G52+G54+G55+G56 -> 35840117 | H58: =H41+H46+H51+H52+H54+H55+H56 -> 40250978 | I58: =I41+I46+I51+I52+I54+I55+I56 -> 44322925 | J58: =J41+J46+J51+J52+J54+J55+J56 -> 67479822 | K58: =K41+K46+K51+K52+K54+K55+K56 -> 72191484 | ... O58: =O41+O46+O51+O52+O54+O55+O56 -> 1.0785681e+08 | P58: =SUM(D58:O58) -> 8.2084421e+08
A59: Cost/Vol. Produced | C59: Mk/m3 | D59: =D58/D9 -> 221.67746 | E59: =E58/E9 -> 224.16267 | F59: =F58/F9 -> 212.01605 | G59: =G58/G9 -> 185.20876 | H59: =H58/H9 -> 206.6272 | I59: =I58/I9 -> 231.42109 | J59: =J58/J9 -> 328.69686 | K59: =K58/K9 -> 313.32416 | ... P59: =P58/P9 -> 342.25917
A60: Cost/Vol. Billed | C60: Mk/m3 | D60: =D58/D22 -> 365.49281 | E60: =E58/E22 -> 355.23545 | F60: =F58/F22 -> 322.22641 | G60: =G58/G22 -> 282.54759 | H60: =H58/H22 -> 320.69682 | I60: =I58/I22 -> 321.51168 | J60: =J58/J22 -> 475.33989 | K60: =K58/K22 -> 490.40729 | ... P60: =P58/P22 -> 509.25684
A61: Permanent Staff Employed | C61: No | D61: =Mangochi!D61+'Monkey Bay'!D61+Namwera!D61 -> 35 | E61: =Mangochi!E61+'Monkey Bay'!E61+Namwera!E61 -> 35 | F61: =Mangochi!F61+'Monkey Bay'!F61+Namwera!F61 -> 33 | G61: =Mangochi!G61+'Monkey Bay'!G61+Namwera!G61 -> 35 | H61: =Mangochi!H61+'Monkey Bay'!H61+Namwera!H61 -> 34 | I61: =Mangochi!I61+'Monkey Bay'!I61+Namwera!I61 -> 34 | J61: =Mangochi!J61+'Monkey Bay'!J61+Namwera!J61+Nkhudzi!J61 -> 41 | K61: =Mangochi!K61+'Monkey Bay'!K61+Namwera!K61+Nkhudzi!K61 -> 50 | L61: =Mangochi!L61+'Monkey Bay'!L61+Namwera!L61+Nkhudzi!L61 -> 52 | M61: =Mangochi!M61+'Monkey Bay'!M61+Namwera!M61+Nkhudzi!M61 -> 55 | N61: =Mangochi!N61+'Monkey Bay'!N61+Namwera!N61+Nkhudzi!N61 -> 56 | O61: =Mangochi!O61+'Monkey Bay'!O61+Namwera!O61+Nkhudzi!O61 -> 56 | P61: =O61 -> 56
A62: Staff/Vol.1000m3 of Volume Produced/hour (12 hour day) | C62: No/1000m3 | D62: =Mangochi!D62+'Monkey Bay'!D62+Namwera!D62 -> 39.537668 | E62: =Mangochi!E62+'Monkey Bay'!E62+Namwera!E62 -> 29.03579 | F62: =Mangochi!F62+'Monkey Bay'!F62+Namwera!F62 -> 30.866454 | G62: =Mangochi!G62+'Monkey Bay'!G62+Namwera!G62 -> 32.953945 | H62: =Mangochi!H62+'Monkey Bay'!H62+Namwera!H62 -> 28.403148 | I62: =Mangochi!I62+'Monkey Bay'!I62+Namwera!I62 -> 24.713695 | J62: =Mangochi!J62+'Monkey Bay'!J62+Namwera!J62+Nkhudzi!J62 -> 122.55982 | K62: =Mangochi!K62+'Monkey Bay'!K62+Namwera!K62+Nkhudzi!K62 -> 109.82278 | L62: =Mangochi!L62+'Monkey Bay'!L62+Namwera!L62+Nkhudzi!L62 -> 102.35424 | M62: =Mangochi!M62+'Monkey Bay'!M62+Namwera!M62+Nkhudzi!M62 -> 127.38736 | N62: =Mangochi!N62+'Monkey Bay'!N62+Namwera!N62+Nkhudzi!N62 -> 139.10204 | O62: =Mangochi!O62+'Monkey Bay'!O62+Namwera!O62+Nkhudzi!O62 -> 178.85175 | P62: =(P61*1000*31)/P9 -> 0.7238425
A63: Temporary Staff Employed | C63: No | D63: =Mangochi!D63+'Monkey Bay'!D63+Namwera!D63 -> 40 | E63: =Mangochi!E63+'Monkey Bay'!E63+Namwera!E63 -> 40 | F63: =Mangochi!F63+'Monkey Bay'!F63+Namwera!F63 -> 40 | G63: =Mangochi!G63+'Monkey Bay'!G63+Namwera!G63 -> 62 | H63: =Mangochi!H63+'Monkey Bay'!H63+Namwera!H63 -> 15 | I63: =Mangochi!I63+'Monkey Bay'!I63+Namwera!I63 -> 40 | J63: =Mangochi!J63+'Monkey Bay'!J63+Namwera!J63+Nkhudzi!J63 -> 139 | K63: =Mangochi!K63+'Monkey Bay'!K63+Namwera!K63+Nkhudzi!K63 -> 170 | L63: =Mangochi!L63+'Monkey Bay'!L63+Namwera!L63+Nkhudzi!L63 -> 113 | M63: =Mangochi!M63+'Monkey Bay'!M63+Namwera!M63+Nkhudzi!M63 -> 148 | N63: =Mangochi!N63+'Monkey Bay'!N63+Namwera!N63+Nkhudzi!N63 -> 173 | O63: =Mangochi!O63+'Monkey Bay'!O63+Namwera!O63+Nkhudzi!O63 -> 173 | P63: =SUM(D63:O63) -> 1153
A65: Water Connections and Disconnections
A66: New Individual Water Connections | B66: Brought Forward | C66: No | D66: =Mangochi!D66+'Monkey Bay'!D66+Namwera!D66 -> 1206 | E66: =Mangochi!E66+'Monkey Bay'!E66+Namwera!E66 -> 1222 | F66: =Mangochi!F66+'Monkey Bay'!F66+Namwera!F66 -> 1333 | G66: =Mangochi!G66+'Monkey Bay'!G66+Namwera!G66 -> 1440 | H66: =Mangochi!H66+'Monkey Bay'!H66+Namwera!H66 -> 1432 | I66: =Mangochi!I66+'Monkey Bay'!I66+Namwera!I66 -> 1511 | J66: =Mangochi!J66+'Monkey Bay'!J66+Namwera!J66+Nkhudzi!J66 -> 1596 | K66: =Mangochi!K66+'Monkey Bay'!K66+Namwera!K66+Nkhudzi!K66 -> 1135 | L66: =Mangochi!L66+'Monkey Bay'!L66+Namwera!L66+Nkhudzi!L66 -> 1105 | M66: =Mangochi!M66+'Monkey Bay'!M66+Namwera!M66+Nkhudzi!M66 -> 1141 | N66: =Mangochi!N66+'Monkey Bay'!N66+Namwera!N66+Nkhudzi!N66 -> 1748 | O66: =Mangochi!O66+'Monkey Bay'!O66+Namwera!O66+Nkhudzi!O66 -> 1573 | P66: =Mangochi!P66+'Monkey Bay'!P66+Namwera!P66 -> 1206
B67: Applied this Month | C67: No | D67: =Mangochi!D67+'Monkey Bay'!D67+Namwera!D67 -> 74 | E67: =Mangochi!E67+'Monkey Bay'!E67+Namwera!E67 -> 149 | F67: =Mangochi!F67+'Monkey Bay'!F67+Namwera!F67 -> 177 | G67: =Mangochi!G67+'Monkey Bay'!G67+Namwera!G67 -> 59 | H67: =Mangochi!H67+'Monkey Bay'!H67+Namwera!H67 -> 164 | I67: =Mangochi!I67+'Monkey Bay'!I67+Namwera!I67 -> 128 | J67: =Mangochi!J67+'Monkey Bay'!J67+Namwera!J67+Nkhudzi!J67 -> 2147 | K67: =Mangochi!K67+'Monkey Bay'!K67+Namwera!K67+Nkhudzi!K67 -> 177 | L67: =Mangochi!L67+'Monkey Bay'!L67+Namwera!L67+Nkhudzi!L67 -> 139 | M67: =Mangochi!M67+'Monkey Bay'!M67+Namwera!M67+Nkhudzi!M67 -> 847 | N67: =Mangochi!N67+'Monkey Bay'!N67+Namwera!N67+Nkhudzi!N67 -> 240 | O67: =Mangochi!O67+'Monkey Bay'!O67+Namwera!O67+Nkhudzi!O67 -> 198 | P67: =Mangochi!P67+'Monkey Bay'!P67+Namwera!P67 -> 3791
B68: Done this Month Postpaid | C68: No | D68: =Mangochi!D68+'Monkey Bay'!D68+Namwera!D68 -> 0 | E68: =Mangochi!E68+'Monkey Bay'!E68+Namwera!E68 -> 7 | F68: =Mangochi!F68+'Monkey Bay'!F68+Namwera!F68 -> 0 | G68: =Mangochi!G68+'Monkey Bay'!G68+Namwera!G68 -> 0 | H68: =Mangochi!H68+'Monkey Bay'!H68+Namwera!H68 -> 0 | I68: =Mangochi!I68+'Monkey Bay'!I68+Namwera!I68 -> 0 | J68: =Mangochi!J68+'Monkey Bay'!J68+Namwera!J68+Nkhudzi!J68 -> 0 | K68: =Mangochi!K68+'Monkey Bay'!K68+Namwera!K68+Nkhudzi!K68 -> 0 | L68: =Mangochi!L68+'Monkey Bay'!L68+Namwera!L68+Nkhudzi!L68 -> 21 | M68: =Mangochi!M68+'Monkey Bay'!M68+Namwera!M68+Nkhudzi!M68 -> 0 | N68: =Mangochi!N68+'Monkey Bay'!N68+Namwera!N68+Nkhudzi!N68 -> 0 | O68: =Mangochi!O68+'Monkey Bay'!O68+Namwera!O68+Nkhudzi!O68 -> 5 | P68: =Mangochi!P68+'Monkey Bay'!P68+Namwera!P68 -> 32
B69: Done this Month Prepaid | C69: No | D69: =Mangochi!D69+'Monkey Bay'!D69+Namwera!D69 -> 58 | E69: =Mangochi!E69+'Monkey Bay'!E69+Namwera!E69 -> 31 | F69: =Mangochi!F69+'Monkey Bay'!F69+Namwera!F69 -> 38 | G69: =Mangochi!G69+'Monkey Bay'!G69+Namwera!G69 -> 110 | H69: =Mangochi!H69+'Monkey Bay'!H69+Namwera!H69 -> 65 | I69: =Mangochi!I69+'Monkey Bay'!I69+Namwera!I69 -> 34 | J69: =Mangochi!J69+'Monkey Bay'!J69+Namwera!J69+Nkhudzi!J69 -> 1041 | K69: =Mangochi!K69+'Monkey Bay'!K69+Namwera!K69+Nkhudzi!K69 -> 48 | L69: =Mangochi!L69+'Monkey Bay'!L69+Namwera!L69+Nkhudzi!L69 -> 58 | M69: =Mangochi!M69+'Monkey Bay'!M69+Namwera!M69+Nkhudzi!M69 -> 240 | N69: =Mangochi!N69+'Monkey Bay'!N69+Namwera!N69+Nkhudzi!N69 -> 215 | O69: =Mangochi!O69+'Monkey Bay'!O69+Namwera!O69+Nkhudzi!O69 -> 292 | P69: =Mangochi!P69+'Monkey Bay'!P69+Namwera!P69 -> 979
B70: Total Done | C70: No | D70: =Mangochi!D70+'Monkey Bay'!D70+Namwera!D70 -> 58 | E70: =Mangochi!E70+'Monkey Bay'!E70+Namwera!E70 -> 38 | F70: =Mangochi!F70+'Monkey Bay'!F70+Namwera!F70 -> 38 | G70: =Mangochi!G70+'Monkey Bay'!G70+Namwera!G70 -> 110 | H70: =Mangochi!H70+'Monkey Bay'!H70+Namwera!H70 -> 65 | I70: =Mangochi!I70+'Monkey Bay'!I70+Namwera!I70 -> 34 | J70: =Mangochi!J70+'Monkey Bay'!J70+Namwera!J70+Nkhudzi!J70 -> 1041 | K70: =Mangochi!K70+'Monkey Bay'!K70+Namwera!K70+Nkhudzi!K70 -> 48 | L70: =Mangochi!L70+'Monkey Bay'!L70+Namwera!L70+Nkhudzi!L70 -> 79 | M70: =Mangochi!M70+'Monkey Bay'!M70+Namwera!M70+Nkhudzi!M70 -> 240 | N70: =Mangochi!N70+'Monkey Bay'!N70+Namwera!N70+Nkhudzi!N70 -> 215 | O70: =Mangochi!O70+'Monkey Bay'!O70+Namwera!O70+Nkhudzi!O70 -> 297 | P70: =Mangochi!P70+'Monkey Bay'!P70+Namwera!P70 -> 1011
B71: Carried Forward | C71: No | D71: =Mangochi!D71+'Monkey Bay'!D71+Namwera!D71 -> 1222 | E71: =Mangochi!E71+'Monkey Bay'!E71+Namwera!E71 -> 1333 | F71: =Mangochi!F71+'Monkey Bay'!F71+Namwera!F71 -> 1472 | G71: =Mangochi!G71+'Monkey Bay'!G71+Namwera!G71 -> 1389 | H71: =Mangochi!H71+'Monkey Bay'!H71+Namwera!H71 -> 1531 | I71: =Mangochi!I71+'Monkey Bay'!I71+Namwera!I71 -> 1605 | J71: =Mangochi!J71+'Monkey Bay'!J71+Namwera!J71+Nkhudzi!J71 -> 3711 | K71: =Mangochi!K71+'Monkey Bay'!K71+Namwera!K71+Nkhudzi!K71 -> 1264 | L71: =Mangochi!L71+'Monkey Bay'!L71+Namwera!L71+Nkhudzi!L71 -> 1165 | M71: =Mangochi!M71+'Monkey Bay'!M71+Namwera!M71+Nkhudzi!M71 -> 1748 | N71: =Mangochi!N71+'Monkey Bay'!N71+Namwera!N71+Nkhudzi!N71 -> 1773 | O71: =Mangochi!O71+'Monkey Bay'!O71+Namwera!O71+Nkhudzi!O71 -> 1474 | P71: =Mangochi!P71+'Monkey Bay'!P71+Namwera!P71 -> 3986
A72: New Institutional Water Connections | B72: Brought Forward | C72: No | D72: =Mangochi!D72+'Monkey Bay'!D72+Namwera!D72 -> 11 | E72: =Mangochi!E72+'Monkey Bay'!E72+Namwera!E72 -> 11 | F72: =Mangochi!F72+'Monkey Bay'!F72+Namwera!F72 -> 11 | G72: =Mangochi!G72+'Monkey Bay'!G72+Namwera!G72 -> 12 | H72: =Mangochi!H72+'Monkey Bay'!H72+Namwera!H72 -> 8 | I72: =Mangochi!I72+'Monkey Bay'!I72+Namwera!I72 -> 11 | J72: =Mangochi!J72+'Monkey Bay'!J72+Namwera!J72+Nkhudzi!J72 -> 11 | K72: =Mangochi!K72+'Monkey Bay'!K72+Namwera!K72+Nkhudzi!K72 -> 10 | L72: =Mangochi!L72+'Monkey Bay'!L72+Namwera!L72+Nkhudzi!L72 -> 10 | M72: =Mangochi!M72+'Monkey Bay'!M72+Namwera!M72+Nkhudzi!M72 -> 0 | N72: =Mangochi!N72+'Monkey Bay'!N72+Namwera!N72+Nkhudzi!N72 -> 3 | O72: =Mangochi!O72+'Monkey Bay'!O72+Namwera!O72+Nkhudzi!O72 -> 3 | P72: =Mangochi!P72+'Monkey Bay'!P72+Namwera!P72 -> 11
B73: Applied this Month | C73: No | D73: =Mangochi!D73+'Monkey Bay'!D73+Namwera!D73 -> 0 | E73: =Mangochi!E73+'Monkey Bay'!E73+Namwera!E73 -> 0 | F73: =Mangochi!F73+'Monkey Bay'!F73+Namwera!F73 -> 0 | G73: =Mangochi!G73+'Monkey Bay'!G73+Namwera!G73 -> 0 | H73: =Mangochi!H73+'Monkey Bay'!H73+Namwera!H73 -> 0 | I73: =Mangochi!I73+'Monkey Bay'!I73+Namwera!I73 -> 0 | J73: =Mangochi!J73+'Monkey Bay'!J73+Namwera!J73+Nkhudzi!J73 -> 0 | K73: =Mangochi!K73+'Monkey Bay'!K73+Namwera!K73+Nkhudzi!K73 -> 0 | L73: =Mangochi!L73+'Monkey Bay'!L73+Namwera!L73+Nkhudzi!L73 -> 0 | M73: =Mangochi!M73+'Monkey Bay'!M73+Namwera!M73+Nkhudzi!M73 -> 2 | N73: =Mangochi!N73+'Monkey Bay'!N73+Namwera!N73+Nkhudzi!N73 -> 2 | O73: =Mangochi!O73+'Monkey Bay'!O73+Namwera!O73+Nkhudzi!O73 -> 0 | P73: =Mangochi!P73+'Monkey Bay'!P73+Namwera!P73 -> 4
B74: Done this Month Postpaid | C74: No | D74: =Mangochi!D74+'Monkey Bay'!D74+Namwera!D74 -> 0 | E74: =Mangochi!E74+'Monkey Bay'!E74+Namwera!E74 -> 0 | F74: =Mangochi!F74+'Monkey Bay'!F74+Namwera!F74 -> 0 | G74: =Mangochi!G74+'Monkey Bay'!G74+Namwera!G74 -> 0 | H74: =Mangochi!H74+'Monkey Bay'!H74+Namwera!H74 -> 0 | I74: =Mangochi!I74+'Monkey Bay'!I74+Namwera!I74 -> 0 | J74: =Mangochi!J74+'Monkey Bay'!J74+Namwera!J74+Nkhudzi!J74 -> 0 | K74: =Mangochi!K74+'Monkey Bay'!K74+Namwera!K74+Nkhudzi!K74 -> 0 | L74: =Mangochi!L74+'Monkey Bay'!L74+Namwera!L74+Nkhudzi!L74 -> 0 | M74: =Mangochi!M74+'Monkey Bay'!M74+Namwera!M74+Nkhudzi!M74 -> 0 | N74: =Mangochi!N74+'Monkey Bay'!N74+Namwera!N74+Nkhudzi!N74 -> 0 | O74: =Mangochi!O74+'Monkey Bay'!O74+Namwera!O74+Nkhudzi!O74 -> 0 | P74: =Mangochi!P74+'Monkey Bay'!P74+Namwera!P74 -> 0
B75: Done this Month Prepaid | C75: No | D75: =Mangochi!D75+'Monkey Bay'!D75+Namwera!D75 -> 0 | E75: =Mangochi!E75+'Monkey Bay'!E75+Namwera!E75 -> 0 | F75: =Mangochi!F75+'Monkey Bay'!F75+Namwera!F75 -> 0 | G75: =Mangochi!G75+'Monkey Bay'!G75+Namwera!G75 -> 0 | H75: =Mangochi!H75+'Monkey Bay'!H75+Namwera!H75 -> 0 | I75: =Mangochi!I75+'Monkey Bay'!I75+Namwera!I75 -> 0 | J75: =Mangochi!J75+'Monkey Bay'!J75+Namwera!J75+Nkhudzi!J75 -> 0 | K75: =Mangochi!K75+'Monkey Bay'!K75+Namwera!K75+Nkhudzi!K75 -> 0 | L75: =Mangochi!L75+'Monkey Bay'!L75+Namwera!L75+Nkhudzi!L75 -> 0 | M75: =Mangochi!M75+'Monkey Bay'!M75+Namwera!M75+Nkhudzi!M75 -> 2 | N75: =Mangochi!N75+'Monkey Bay'!N75+Namwera!N75+Nkhudzi!N75 -> 2 | O75: =Mangochi!O75+'Monkey Bay'!O75+Namwera!O75+Nkhudzi!O75 -> 0 | P75: =Mangochi!P75+'Monkey Bay'!P75+Namwera!P75 -> 4
B76: Total Done | C76: No | D76: =Mangochi!D76+'Monkey Bay'!D76+Namwera!D76 -> 0 | E76: =Mangochi!E76+'Monkey Bay'!E76+Namwera!E76 -> 0 | F76: =Mangochi!F76+'Monkey Bay'!F76+Namwera!F76 -> 0 | G76: =Mangochi!G76+'Monkey Bay'!G76+Namwera!G76 -> 0 | H76: =Mangochi!H76+'Monkey Bay'!H76+Namwera!H76 -> 0 | I76: =Mangochi!I76+'Monkey Bay'!I76+Namwera!I76 -> 0 | J76: =Mangochi!J76+'Monkey Bay'!J76+Namwera!J76+Nkhudzi!J76 -> 0 | K76: =Mangochi!K76+'Monkey Bay'!K76+Namwera!K76+Nkhudzi!K76 -> 0 | L76: =Mangochi!L76+'Monkey Bay'!L76+Namwera!L76+Nkhudzi!L76 -> 0 | M76: =Mangochi!M76+'Monkey Bay'!M76+Namwera!M76+Nkhudzi!M76 -> 2 | N76: =Mangochi!N76+'Monkey Bay'!N76+Namwera!N76+Nkhudzi!N76 -> 2 | O76: =Mangochi!O76+'Monkey Bay'!O76+Namwera!O76+Nkhudzi!O76 -> 0 | P76: =Mangochi!P76+'Monkey Bay'!P76+Namwera!P76 -> 4
B77: Carried Forward | C77: No | D77: =Mangochi!D77+'Monkey Bay'!D77+Namwera!D77 -> 11 | E77: =Mangochi!E77+'Monkey Bay'!E77+Namwera!E77 -> 11 | F77: =Mangochi!F77+'Monkey Bay'!F77+Namwera!F77 -> 11 | G77: =Mangochi!G77+'Monkey Bay'!G77+Namwera!G77 -> 12 | H77: =Mangochi!H77+'Monkey Bay'!H77+Namwera!H77 -> 8 | I77: =Mangochi!I77+'Monkey Bay'!I77+Namwera!I77 -> 11 | J77: =Mangochi!J77+'Monkey Bay'!J77+Namwera!J77+Nkhudzi!J77 -> 11 | K77: =Mangochi!K77+'Monkey Bay'!K77+Namwera!K77+Nkhudzi!K77 -> 13 | L77: =Mangochi!L77+'Monkey Bay'!L77+Namwera!L77+Nkhudzi!L77 -> 13 | M77: =Mangochi!M77+'Monkey Bay'!M77+Namwera!M77+Nkhudzi!M77 -> 0 | N77: =Mangochi!N77+'Monkey Bay'!N77+Namwera!N77+Nkhudzi!N77 -> 3 | O77: =Mangochi!O77+'Monkey Bay'!O77+Namwera!O77+Nkhudzi!O77 -> 3 | P77: =Mangochi!P77+'Monkey Bay'!P77+Namwera!P77 -> 11
A78: New Commercial/Industrial Water Connections | B78: Brought Forward | C78: No | D78: =Mangochi!D78+'Monkey Bay'!D78+Namwera!D78 -> 11 | E78: =Mangochi!E78+'Monkey Bay'!E78+Namwera!E78 -> 11 | F78: =Mangochi!F78+'Monkey Bay'!F78+Namwera!F78 -> 11 | G78: =Mangochi!G78+'Monkey Bay'!G78+Namwera!G78 -> 11 | H78: =Mangochi!H78+'Monkey Bay'!H78+Namwera!H78 -> 11 | I78: =Mangochi!I78+'Monkey Bay'!I78+Namwera!I78 -> 11 | J78: =Mangochi!J78+'Monkey Bay'!J78+Namwera!J78+Nkhudzi!J78 -> 11 | K78: =Mangochi!K78+'Monkey Bay'!K78+Namwera!K78+Nkhudzi!K78 -> 13 | L78: =Mangochi!L78+'Monkey Bay'!L78+Namwera!L78+Nkhudzi!L78 -> 2 | M78: =Mangochi!M78+'Monkey Bay'!M78+Namwera!M78+Nkhudzi!M78 -> 0 | N78: =Mangochi!N78+'Monkey Bay'!N78+Namwera!N78+Nkhudzi!N78 -> 1 | O78: =Mangochi!O78+'Monkey Bay'!O78+Namwera!O78+Nkhudzi!O78 -> 1 | P78: =Mangochi!P78+'Monkey Bay'!P78+Namwera!P78 -> 11
B79: Applied this Month | C79: No | D79: =Mangochi!D79+'Monkey Bay'!D79+Namwera!D79 -> 2 | E79: =Mangochi!E79+'Monkey Bay'!E79+Namwera!E79 -> 0 | F79: =Mangochi!F79+'Monkey Bay'!F79+Namwera!F79 -> 0 | G79: =Mangochi!G79+'Monkey Bay'!G79+Namwera!G79 -> 0 | H79: =Mangochi!H79+'Monkey Bay'!H79+Namwera!H79 -> 0 | I79: =Mangochi!I79+'Monkey Bay'!I79+Namwera!I79 -> 0 | J79: =Mangochi!J79+'Monkey Bay'!J79+Namwera!J79+Nkhudzi!J79 -> 0 | K79: =Mangochi!K79+'Monkey Bay'!K79+Namwera!K79+Nkhudzi!K79 -> 0 | L79: =Mangochi!L79+'Monkey Bay'!L79+Namwera!L79+Nkhudzi!L79 -> 3 | M79: =Mangochi!M79+'Monkey Bay'!M79+Namwera!M79+Nkhudzi!M79 -> 10 | N79: =Mangochi!N79+'Monkey Bay'!N79+Namwera!N79+Nkhudzi!N79 -> 4 | O79: =Mangochi!O79+'Monkey Bay'!O79+Namwera!O79+Nkhudzi!O79 -> 8 | P79: =Mangochi!P79+'Monkey Bay'!P79+Namwera!P79 -> 27
B80: Done this Month Postpaid | C80: No | D80: =Mangochi!D80+'Monkey Bay'!D80+Namwera!D80 -> 0 | E80: =Mangochi!E80+'Monkey Bay'!E80+Namwera!E80 -> 0 | F80: =Mangochi!F80+'Monkey Bay'!F80+Namwera!F80 -> 0 | G80: =Mangochi!G80+'Monkey Bay'!G80+Namwera!G80 -> 0 | H80: =Mangochi!H80+'Monkey Bay'!H80+Namwera!H80 -> 0 | I80: =Mangochi!I80+'Monkey Bay'!I80+Namwera!I80 -> 0 | J80: =Mangochi!J80+'Monkey Bay'!J80+Namwera!J80+Nkhudzi!J80 -> 0 | K80: =Mangochi!K80+'Monkey Bay'!K80+Namwera!K80+Nkhudzi!K80 -> 0 | L80: =Mangochi!L80+'Monkey Bay'!L80+Namwera!L80+Nkhudzi!L80 -> 0 | M80: =Mangochi!M80+'Monkey Bay'!M80+Namwera!M80+Nkhudzi!M80 -> 0 | N80: =Mangochi!N80+'Monkey Bay'!N80+Namwera!N80+Nkhudzi!N80 -> 0 | O80: =Mangochi!O80+'Monkey Bay'!O80+Namwera!O80+Nkhudzi!O80 -> 0 | P80: =Mangochi!P80+'Monkey Bay'!P80+Namwera!P80 -> 0
B81: Done this Month Prepaid | C81: No | D81: =Mangochi!D81+'Monkey Bay'!D81+Namwera!D81 -> 2 | E81: =Mangochi!E81+'Monkey Bay'!E81+Namwera!E81 -> 2 | F81: =Mangochi!F81+'Monkey Bay'!F81+Namwera!F81 -> 0 | G81: =Mangochi!G81+'Monkey Bay'!G81+Namwera!G81 -> 0 | H81: =Mangochi!H81+'Monkey Bay'!H81+Namwera!H81 -> 0 | I81: =Mangochi!I81+'Monkey Bay'!I81+Namwera!I81 -> 2 | J81: =Mangochi!J81+'Monkey Bay'!J81+Namwera!J81+Nkhudzi!J81 -> 0 | K81: =Mangochi!K81+'Monkey Bay'!K81+Namwera!K81+Nkhudzi!K81 -> 0 | L81: =Mangochi!L81+'Monkey Bay'!L81+Namwera!L81+Nkhudzi!L81 -> 0 | M81: =Mangochi!M81+'Monkey Bay'!M81+Namwera!M81+Nkhudzi!M81 -> 9 | N81: =Mangochi!N81+'Monkey Bay'!N81+Namwera!N81+Nkhudzi!N81 -> 4 | O81: =Mangochi!O81+'Monkey Bay'!O81+Namwera!O81+Nkhudzi!O81 -> 8 | P81: =Mangochi!P81+'Monkey Bay'!P81+Namwera!P81 -> 27
B82: Total Done | C82: No | D82: =Mangochi!D82+'Monkey Bay'!D82+Namwera!D82 -> 2 | E82: =Mangochi!E82+'Monkey Bay'!E82+Namwera!E82 -> 2 | F82: =Mangochi!F82+'Monkey Bay'!F82+Namwera!F82 -> 0 | G82: =Mangochi!G82+'Monkey Bay'!G82+Namwera!G82 -> 0 | H82: =Mangochi!H82+'Monkey Bay'!H82+Namwera!H82 -> 0 | I82: =Mangochi!I82+'Monkey Bay'!I82+Namwera!I82 -> 2 | J82: =Mangochi!J82+'Monkey Bay'!J82+Namwera!J82+Nkhudzi!J82 -> 0 | K82: =Mangochi!K82+'Monkey Bay'!K82+Namwera!K82+Nkhudzi!K82 -> 0 | L82: =Mangochi!L82+'Monkey Bay'!L82+Namwera!L82+Nkhudzi!L82 -> 0 | M82: =Mangochi!M82+'Monkey Bay'!M82+Namwera!M82+Nkhudzi!M82 -> 9 | N82: =Mangochi!N82+'Monkey Bay'!N82+Namwera!N82+Nkhudzi!N82 -> 4 | O82: =Mangochi!O82+'Monkey Bay'!O82+Namwera!O82+Nkhudzi!O82 -> 8 | P82: =Mangochi!P82+'Monkey Bay'!P82+Namwera!P82 -> 27
B83: Carried Forward | C83: No | D83: =Mangochi!D83+'Monkey Bay'!D83+Namwera!D83 -> 10 | E83: =Mangochi!E83+'Monkey Bay'!E83+Namwera!E83 -> 9 | F83: =Mangochi!F83+'Monkey Bay'!F83+Namwera!F83 -> 11 | G83: =Mangochi!G83+'Monkey Bay'!G83+Namwera!G83 -> 11 | H83: =Mangochi!H83+'Monkey Bay'!H83+Namwera!H83 -> 11 | I83: =Mangochi!I83+'Monkey Bay'!I83+Namwera!I83 -> 9 | J83: =Mangochi!J83+'Monkey Bay'!J83+Namwera!J83+Nkhudzi!J83 -> 11 | K83: =Mangochi!K83+'Monkey Bay'!K83+Namwera!K83+Nkhudzi!K83 -> 13 | L83: =Mangochi!L83+'Monkey Bay'!L83+Namwera!L83+Nkhudzi!L83 -> 14 | M83: =Mangochi!M83+'Monkey Bay'!M83+Namwera!M83+Nkhudzi!M83 -> 1 | N83: =Mangochi!N83+'Monkey Bay'!N83+Namwera!N83+Nkhudzi!N83 -> 1 | O83: =Mangochi!O83+'Monkey Bay'!O83+Namwera!O83+Nkhudzi!O83 -> 1 | P83: =Mangochi!P83+'Monkey Bay'!P83+Namwera!P83 -> 11
A84: New CWP | B84: Brought Forward | C84: No | D84: =Mangochi!D84+'Monkey Bay'!D84+Namwera!D84 -> 0 | E84: =Mangochi!E84+'Monkey Bay'!E84+Namwera!E84 -> 0 | F84: =Mangochi!F84+'Monkey Bay'!F84+Namwera!F84 -> 0 | G84: =Mangochi!G84+'Monkey Bay'!G84+Namwera!G84 -> 0 | H84: =Mangochi!H84+'Monkey Bay'!H84+Namwera!H84 -> 0 | I84: =Mangochi!I84+'Monkey Bay'!I84+Namwera!I84 -> 0 | J84: =Mangochi!J84+'Monkey Bay'!J84+Namwera!J84+Nkhudzi!J84 -> 0 | K84: =Mangochi!K84+'Monkey Bay'!K84+Namwera!K84+Nkhudzi!K84 -> 0 | L84: =Mangochi!L84+'Monkey Bay'!L84+Namwera!L84+Nkhudzi!L84 -> 0 | M84: =Mangochi!M84+'Monkey Bay'!M84+Namwera!M84+Nkhudzi!M84 -> 0 | N84: =Mangochi!N84+'Monkey Bay'!N84+Namwera!N84+Nkhudzi!N84 -> 0 | O84: =Mangochi!O84+'Monkey Bay'!O84+Namwera!O84+Nkhudzi!O84 -> 0 | P84: =Mangochi!P84+'Monkey Bay'!P84+Namwera!P84 -> 0
B85: Applied this Month | C85: No | D85: =Mangochi!D85+'Monkey Bay'!D85+Namwera!D85 -> 0 | E85: =Mangochi!E85+'Monkey Bay'!E85+Namwera!E85 -> 0 | F85: =Mangochi!F85+'Monkey Bay'!F85+Namwera!F85 -> 0 | G85: =Mangochi!G85+'Monkey Bay'!G85+Namwera!G85 -> 0 | H85: =Mangochi!H85+'Monkey Bay'!H85+Namwera!H85 -> 0 | I85: =Mangochi!I85+'Monkey Bay'!I85+Namwera!I85 -> 0 | J85: =Mangochi!J85+'Monkey Bay'!J85+Namwera!J85+Nkhudzi!J85 -> 0 | K85: =Mangochi!K85+'Monkey Bay'!K85+Namwera!K85+Nkhudzi!K85 -> 0 | L85: =Mangochi!L85+'Monkey Bay'!L85+Namwera!L85+Nkhudzi!L85 -> 0 | M85: =Mangochi!M85+'Monkey Bay'!M85+Namwera!M85+Nkhudzi!M85 -> 0 | N85: =Mangochi!N85+'Monkey Bay'!N85+Namwera!N85+Nkhudzi!N85 -> 0 | O85: =Mangochi!O85+'Monkey Bay'!O85+Namwera!O85+Nkhudzi!O85 -> 0 | P85: =Mangochi!P85+'Monkey Bay'!P85+Namwera!P85 -> 0
B86: Done this Month Postpaid | C86: No | D86: =Mangochi!D86+'Monkey Bay'!D86+Namwera!D86 -> 0 | E86: =Mangochi!E86+'Monkey Bay'!E86+Namwera!E86 -> 0 | F86: =Mangochi!F86+'Monkey Bay'!F86+Namwera!F86 -> 0 | G86: =Mangochi!G86+'Monkey Bay'!G86+Namwera!G86 -> 0 | H86: =Mangochi!H86+'Monkey Bay'!H86+Namwera!H86 -> 0 | I86: =Mangochi!I86+'Monkey Bay'!I86+Namwera!I86 -> 0 | J86: =Mangochi!J86+'Monkey Bay'!J86+Namwera!J86+Nkhudzi!J86 -> 0 | K86: =Mangochi!K86+'Monkey Bay'!K86+Namwera!K86+Nkhudzi!K86 -> 0 | L86: =Mangochi!L86+'Monkey Bay'!L86+Namwera!L86+Nkhudzi!L86 -> 0 | M86: =Mangochi!M86+'Monkey Bay'!M86+Namwera!M86+Nkhudzi!M86 -> 0 | N86: =Mangochi!N86+'Monkey Bay'!N86+Namwera!N86+Nkhudzi!N86 -> 0 | O86: =Mangochi!O86+'Monkey Bay'!O86+Namwera!O86+Nkhudzi!O86 -> 0 | P86: =Mangochi!P86+'Monkey Bay'!P86+Namwera!P86 -> 0
B87: Done this Month Prepaid | C87: No | D87: =Mangochi!D87+'Monkey Bay'!D87+Namwera!D87 -> 0 | E87: =Mangochi!E87+'Monkey Bay'!E87+Namwera!E87 -> 0 | F87: =Mangochi!F87+'Monkey Bay'!F87+Namwera!F87 -> 0 | G87: =Mangochi!G87+'Monkey Bay'!G87+Namwera!G87 -> 0 | H87: =Mangochi!H87+'Monkey Bay'!H87+Namwera!H87 -> 0 | I87: =Mangochi!I87+'Monkey Bay'!I87+Namwera!I87 -> 0 | J87: =Mangochi!J87+'Monkey Bay'!J87+Namwera!J87+Nkhudzi!J87 -> 0 | K87: =Mangochi!K87+'Monkey Bay'!K87+Namwera!K87+Nkhudzi!K87 -> 0 | L87: =Mangochi!L87+'Monkey Bay'!L87+Namwera!L87+Nkhudzi!L87 -> 0 | M87: =Mangochi!M87+'Monkey Bay'!M87+Namwera!M87+Nkhudzi!M87 -> 0 | N87: =Mangochi!N87+'Monkey Bay'!N87+Namwera!N87+Nkhudzi!N87 -> 0 | O87: =Mangochi!O87+'Monkey Bay'!O87+Namwera!O87+Nkhudzi!O87 -> 0 | P87: =Mangochi!P87+'Monkey Bay'!P87+Namwera!P87 -> 0
B88: Total Done | C88: No | D88: =Mangochi!D88+'Monkey Bay'!D88+Namwera!D88 -> 0 | E88: =Mangochi!E88+'Monkey Bay'!E88+Namwera!E88 -> 0 | F88: =Mangochi!F88+'Monkey Bay'!F88+Namwera!F88 -> 0 | G88: =Mangochi!G88+'Monkey Bay'!G88+Namwera!G88 -> 0 | H88: =Mangochi!H88+'Monkey Bay'!H88+Namwera!H88 -> 0 | I88: =Mangochi!I88+'Monkey Bay'!I88+Namwera!I88 -> 0 | J88: =Mangochi!J88+'Monkey Bay'!J88+Namwera!J88+Nkhudzi!J88 -> 0 | K88: =Mangochi!K88+'Monkey Bay'!K88+Namwera!K88+Nkhudzi!K88 -> 0 | L88: =Mangochi!L88+'Monkey Bay'!L88+Namwera!L88+Nkhudzi!L88 -> 0 | M88: =Mangochi!M88+'Monkey Bay'!M88+Namwera!M88+Nkhudzi!M88 -> 0 | N88: =Mangochi!N88+'Monkey Bay'!N88+Namwera!N88+Nkhudzi!N88 -> 0 | O88: =Mangochi!O88+'Monkey Bay'!O88+Namwera!O88+Nkhudzi!O88 -> 0 | P88: =Mangochi!P88+'Monkey Bay'!P88+Namwera!P88 -> 0
B89: Carried Forward | C89: No | D89: =Mangochi!D89+'Monkey Bay'!D89+Namwera!D89 -> 0 | E89: =Mangochi!E89+'Monkey Bay'!E89+Namwera!E89 -> 0 | F89: =Mangochi!F89+'Monkey Bay'!F89+Namwera!F89 -> 0 | G89: =Mangochi!G89+'Monkey Bay'!G89+Namwera!G89 -> 0 | H89: =Mangochi!H89+'Monkey Bay'!H89+Namwera!H89 -> 0 | I89: =Mangochi!I89+'Monkey Bay'!I89+Namwera!I89 -> 0 | J89: =Mangochi!J89+'Monkey Bay'!J89+Namwera!J89+Nkhudzi!J89 -> 0 | K89: =Mangochi!K89+'Monkey Bay'!K89+Namwera!K89+Nkhudzi!K89 -> 0 | L89: =Mangochi!L89+'Monkey Bay'!L89+Namwera!L89+Nkhudzi!L89 -> 0 | M89: =Mangochi!M89+'Monkey Bay'!M89+Namwera!M89+Nkhudzi!M89 -> 0 | N89: =Mangochi!N89+'Monkey Bay'!N89+Namwera!N89+Nkhudzi!N89 -> 0 | O89: =Mangochi!O89+'Monkey Bay'!O89+Namwera!O89+Nkhudzi!O89 -> 0 | P89: =Mangochi!P89+'Monkey Bay'!P89+Namwera!P89 -> 0
A90: Aggregated New Water connections | B90: Brought Forward | C90: No | D90: =Mangochi!D90+'Monkey Bay'!D90+Namwera!D90 -> 1228 | E90: =Mangochi!E90+'Monkey Bay'!E90+Namwera!E90 -> 1244 | F90: =Mangochi!F90+'Monkey Bay'!F90+Namwera!F90 -> 1355 | G90: =Mangochi!G90+'Monkey Bay'!G90+Namwera!G90 -> 1463 | H90: =Mangochi!H90+'Monkey Bay'!H90+Namwera!H90 -> 1451 | I90: =Mangochi!I90+'Monkey Bay'!I90+Namwera!I90 -> 1533 | J90: =Mangochi!J90+'Monkey Bay'!J90+Namwera!J90+Nkhudzi!J90 -> 1618 | K90: =Mangochi!K90+'Monkey Bay'!K90+Namwera!K90+Nkhudzi!K90 -> 1158 | L90: =Mangochi!L90+'Monkey Bay'!L90+Namwera!L90+Nkhudzi!L90 -> 1117 | M90: =Mangochi!M90+'Monkey Bay'!M90+Namwera!M90+Nkhudzi!M90 -> 1141 | N90: =Mangochi!N90+'Monkey Bay'!N90+Namwera!N90+Nkhudzi!N90 -> 1752 | O90: =Mangochi!O90+'Monkey Bay'!O90+Namwera!O90+Nkhudzi!O90 -> 1577 | P90: =Mangochi!P90+'Monkey Bay'!P90+Namwera!P90 -> 1228
B91: Applied this Month | C91: No | D91: =Mangochi!D91+'Monkey Bay'!D91+Namwera!D91 -> 76 | E91: =Mangochi!E91+'Monkey Bay'!E91+Namwera!E91 -> 149 | F91: =Mangochi!F91+'Monkey Bay'!F91+Namwera!F91 -> 177 | G91: =Mangochi!G91+'Monkey Bay'!G91+Namwera!G91 -> 59 | H91: =Mangochi!H91+'Monkey Bay'!H91+Namwera!H91 -> 164 | I91: =Mangochi!I91+'Monkey Bay'!I91+Namwera!I91 -> 128 | J91: =Mangochi!J91+'Monkey Bay'!J91+Namwera!J91+Nkhudzi!J91 -> 2147 | K91: =Mangochi!K91+'Monkey Bay'!K91+Namwera!K91+Nkhudzi!K91 -> 177 | L91: =Mangochi!L91+'Monkey Bay'!L91+Namwera!L91+Nkhudzi!L91 -> 142 | M91: =Mangochi!M91+'Monkey Bay'!M91+Namwera!M91+Nkhudzi!M91 -> 859 | N91: =Mangochi!N91+'Monkey Bay'!N91+Namwera!N91+Nkhudzi!N91 -> 246 | O91: =Mangochi!O91+'Monkey Bay'!O91+Namwera!O91+Nkhudzi!O91 -> 206 | P91: =Mangochi!P91+'Monkey Bay'!P91+Namwera!P91 -> 3822
B92: Done this Month Postpaid | C92: No | D92: =Mangochi!D92+'Monkey Bay'!D92+Namwera!D92 -> 0 | E92: =Mangochi!E92+'Monkey Bay'!E92+Namwera!E92 -> 7 | F92: =Mangochi!F92+'Monkey Bay'!F92+Namwera!F92 -> 0 | G92: =Mangochi!G92+'Monkey Bay'!G92+Namwera!G92 -> 0 | H92: =Mangochi!H92+'Monkey Bay'!H92+Namwera!H92 -> 0 | I92: =Mangochi!I92+'Monkey Bay'!I92+Namwera!I92 -> 0 | J92: =Mangochi!J92+'Monkey Bay'!J92+Namwera!J92+Nkhudzi!J92 -> 0 | K92: =Mangochi!K92+'Monkey Bay'!K92+Namwera!K92+Nkhudzi!K92 -> 0 | L92: =Mangochi!L92+'Monkey Bay'!L92+Namwera!L92+Nkhudzi!L92 -> 21 | M92: =Mangochi!M92+'Monkey Bay'!M92+Namwera!M92+Nkhudzi!M92 -> 0 | N92: =Mangochi!N92+'Monkey Bay'!N92+Namwera!N92+Nkhudzi!N92 -> 0 | O92: =Mangochi!O92+'Monkey Bay'!O92+Namwera!O92+Nkhudzi!O92 -> 5 | P92: =Mangochi!P92+'Monkey Bay'!P92+Namwera!P92 -> 32
B93: Done this Month Prepaid | D93: =Mangochi!D93+'Monkey Bay'!D93+Namwera!D93 -> 60 | E93: =Mangochi!E93+'Monkey Bay'!E93+Namwera!E93 -> 33 | F93: =Mangochi!F93+'Monkey Bay'!F93+Namwera!F93 -> 38 | G93: =Mangochi!G93+'Monkey Bay'!G93+Namwera!G93 -> 110 | H93: =Mangochi!H93+'Monkey Bay'!H93+Namwera!H93 -> 65 | I93: =Mangochi!I93+'Monkey Bay'!I93+Namwera!I93 -> 36 | J93: =Mangochi!J93+'Monkey Bay'!J93+Namwera!J93+Nkhudzi!J93 -> 1041 | K93: =Mangochi!K93+'Monkey Bay'!K93+Namwera!K93+Nkhudzi!K93 -> 48 | L93: =Mangochi!L93+'Monkey Bay'!L93+Namwera!L93+Nkhudzi!L93 -> 58 | M93: =Mangochi!M93+'Monkey Bay'!M93+Namwera!M93+Nkhudzi!M93 -> 251 | N93: =Mangochi!N93+'Monkey Bay'!N93+Namwera!N93+Nkhudzi!N93 -> 221 | O93: =Mangochi!O93+'Monkey Bay'!O93+Namwera!O93+Nkhudzi!O93 -> 300 | P93: =Mangochi!P93+'Monkey Bay'!P93+Namwera!P93 -> 1010
B94: Total Done | C94: No | D94: =Mangochi!D94+'Monkey Bay'!D94+Namwera!D94 -> 60 | E94: =Mangochi!E94+'Monkey Bay'!E94+Namwera!E94 -> 40 | F94: =Mangochi!F94+'Monkey Bay'!F94+Namwera!F94 -> 38 | G94: =Mangochi!G94+'Monkey Bay'!G94+Namwera!G94 -> 110 | H94: =Mangochi!H94+'Monkey Bay'!H94+Namwera!H94 -> 65 | I94: =Mangochi!I94+'Monkey Bay'!I94+Namwera!I94 -> 36 | J94: =Mangochi!J94+'Monkey Bay'!J94+Namwera!J94+Nkhudzi!J94 -> 1041 | K94: =Mangochi!K94+'Monkey Bay'!K94+Namwera!K94+Nkhudzi!K94 -> 48 | L94: =Mangochi!L94+'Monkey Bay'!L94+Namwera!L94+Nkhudzi!L94 -> 79 | M94: =Mangochi!M94+'Monkey Bay'!M94+Namwera!M94+Nkhudzi!M94 -> 251 | N94: =Mangochi!N94+'Monkey Bay'!N94+Namwera!N94+Nkhudzi!N94 -> 221 | O94: =Mangochi!O94+'Monkey Bay'!O94+Namwera!O94+Nkhudzi!O94 -> 305 | P94: =Mangochi!P94+'Monkey Bay'!P94+Namwera!P94 -> 1042
B95: Carried Forward | C95: No | D95: =Mangochi!D95+'Monkey Bay'!D95+Namwera!D95 -> 1244 | E95: =Mangochi!E95+'Monkey Bay'!E95+Namwera!E95 -> 1353 | F95: =Mangochi!F95+'Monkey Bay'!F95+Namwera!F95 -> 1494 | G95: =Mangochi!G95+'Monkey Bay'!G95+Namwera!G95 -> 1412 | H95: =Mangochi!H95+'Monkey Bay'!H95+Namwera!H95 -> 1550 | I95: =Mangochi!I95+'Monkey Bay'!I95+Namwera!I95 -> 1625 | J95: =Mangochi!J95+'Monkey Bay'!J95+Namwera!J95+Nkhudzi!J95 -> 3733 | K95: =Mangochi!K95+'Monkey Bay'!K95+Namwera!K95+Nkhudzi!K95 -> 1287 | L95: =Mangochi!L95+'Monkey Bay'!L95+Namwera!L95+Nkhudzi!L95 -> 1180 | M95: =Mangochi!M95+'Monkey Bay'!M95+Namwera!M95+Nkhudzi!M95 -> 1749 | N95: =Mangochi!N95+'Monkey Bay'!N95+Namwera!N95+Nkhudzi!N95 -> 1777 | O95: =Mangochi!O95+'Monkey Bay'!O95+Namwera!O95+Nkhudzi!O95 -> 1478 | P95: =Mangochi!P95+'Monkey Bay'!P95+Namwera!P95 -> 4008
J96: =Mangochi!J96+'Monkey Bay'!J96+Namwera!J96+Nkhudzi!J96 -> 0 | K96: =Mangochi!K96+'Monkey Bay'!K96+Namwera!K96+Nkhudzi!K96 -> 0 | L96: =Mangochi!L96+'Monkey Bay'!L96+Namwera!L96+Nkhudzi!L96 -> 0 | M96: =Mangochi!M96+'Monkey Bay'!M96+Namwera!M96+Nkhudzi!M96 -> 0 | N96: =Mangochi!N96+'Monkey Bay'!N96+Namwera!N96+Nkhudzi!N96 -> 0 | O96: =Mangochi!O96+'Monkey Bay'!O96+Namwera!O96+Nkhudzi!O96 -> 0
A97: Prepaid Metering | J97: =Mangochi!J97+'Monkey Bay'!J97+Namwera!J97+Nkhudzi!J97 -> 0 | K97: =Mangochi!K97+'Monkey Bay'!K97+Namwera!K97+Nkhudzi!K97 -> 0
A98: Prepaid Meters Installed | C98: No | D98: =Mangochi!D98+'Monkey Bay'!D98+Namwera!D98 -> 60 | E98: =Mangochi!E98+'Monkey Bay'!E98+Namwera!E98 -> 35 | F98: =Mangochi!F98+'Monkey Bay'!F98+Namwera!F98 -> 38 | G98: =Mangochi!G98+'Monkey Bay'!G98+Namwera!G98 -> 119 | H98: =Mangochi!H98+'Monkey Bay'!H98+Namwera!H98 -> 65 | I98: =Mangochi!I98+'Monkey Bay'!I98+Namwera!I98 -> 36 | J98: =Mangochi!J98+'Monkey Bay'!J98+Namwera!J98+Nkhudzi!J98 -> 1160 | K98: =Mangochi!K98+'Monkey Bay'!K98+Namwera!K98+Nkhudzi!K98 -> 48 | L98: =Mangochi!L98+'Monkey Bay'!L98+Namwera!L98+Nkhudzi!L98 -> 164 | M98: =Mangochi!M98+'Monkey Bay'!M98+Namwera!M98+Nkhudzi!M98 -> 251 | N98: =Mangochi!N98+'Monkey Bay'!N98+Namwera!N98+Nkhudzi!N98 -> 221 | O98: =Mangochi!O98+'Monkey Bay'!O98+Namwera!O98+Nkhudzi!O98 -> 300 | P98: =SUM(D98:O98) -> 2497
A100: Active and Disconnected Accounts
A101: Disconnected Individual Accounts | C101: No | D101: =Mangochi!D101+'Monkey Bay'!D101+Namwera!D101 -> 2560 | E101: =Mangochi!E101+'Monkey Bay'!E101+Namwera!E101 -> 2545 | F101: =Mangochi!F101+'Monkey Bay'!F101+Namwera!F101 -> 2500 | G101: =Mangochi!G101+'Monkey Bay'!G101+Namwera!G101 -> 2478 | H101: =Mangochi!H101+'Monkey Bay'!H101+Namwera!H101 -> 2446 | I101: =Mangochi!I101+'Monkey Bay'!I101+Namwera!I101 -> 2411 | J101: =Mangochi!J101+'Monkey Bay'!J101+Namwera!J101+Nkhudzi!J101 -> 2406 | K101: =Mangochi!K101+'Monkey Bay'!K101+Namwera!K101+Nkhudzi!K101 -> 2361 | L101: =Mangochi!L101+'Monkey Bay'!L101+Namwera!L101+Nkhudzi!L101 -> 2321 | M101: =Mangochi!M101+'Monkey Bay'!M101+Namwera!M101+Nkhudzi!M101 -> 2464 | N101: =Mangochi!N101+'Monkey Bay'!N101+Namwera!N101+Nkhudzi!N101 -> 2483 | O101: =Mangochi!O101+'Monkey Bay'!O101+Namwera!O101+Nkhudzi!O101 -> 2470 | P101: =O101 -> 2470
A102: Disconnected institutional Accounts | C102: No | D102: =Mangochi!D102+'Monkey Bay'!D102+Namwera!D102 -> 10 | E102: =Mangochi!E102+'Monkey Bay'!E102+Namwera!E102 -> 11 | F102: =Mangochi!F102+'Monkey Bay'!F102+Namwera!F102 -> 11 | G102: =Mangochi!G102+'Monkey Bay'!G102+Namwera!G102 -> 12 | H102: =Mangochi!H102+'Monkey Bay'!H102+Namwera!H102 -> 12 | I102: =Mangochi!I102+'Monkey Bay'!I102+Namwera!I102 -> 12 | J102: =Mangochi!J102+'Monkey Bay'!J102+Namwera!J102+Nkhudzi!J102 -> 12 | K102: =Mangochi!K102+'Monkey Bay'!K102+Namwera!K102+Nkhudzi!K102 -> 12 | L102: =Mangochi!L102+'Monkey Bay'!L102+Namwera!L102+Nkhudzi!L102 -> 10 | M102: =Mangochi!M102+'Monkey Bay'!M102+Namwera!M102+Nkhudzi!M102 -> 9 | N102: =Mangochi!N102+'Monkey Bay'!N102+Namwera!N102+Nkhudzi!N102 -> 2 | O102: =Mangochi!O102+'Monkey Bay'!O102+Namwera!O102+Nkhudzi!O102 -> 2 | P102: =O102 -> 2
A103: Disconnected Commercial/Industrial Accounts | C103: No | D103: =Mangochi!D103+'Monkey Bay'!D103+Namwera!D103 -> 143 | E103: =Mangochi!E103+'Monkey Bay'!E103+Namwera!E103 -> 141 | F103: =Mangochi!F103+'Monkey Bay'!F103+Namwera!F103 -> 143 | G103: =Mangochi!G103+'Monkey Bay'!G103+Namwera!G103 -> 143 | H103: =Mangochi!H103+'Monkey Bay'!H103+Namwera!H103 -> 144 | I103: =Mangochi!I103+'Monkey Bay'!I103+Namwera!I103 -> 144 | J103: =Mangochi!J103+'Monkey Bay'!J103+Namwera!J103+Nkhudzi!J103 -> 143 | K103: =Mangochi!K103+'Monkey Bay'!K103+Namwera!K103+Nkhudzi!K103 -> 143 | L103: =Mangochi!L103+'Monkey Bay'!L103+Namwera!L103+Nkhudzi!L103 -> 143 | M103: =Mangochi!M103+'Monkey Bay'!M103+Namwera!M103+Nkhudzi!M103 -> 144 | N103: =Mangochi!N103+'Monkey Bay'!N103+Namwera!N103+Nkhudzi!N103 -> 141 | O103: =Mangochi!O103+'Monkey Bay'!O103+Namwera!O103+Nkhudzi!O103 -> 142 | P103: =O103 -> 142
A104: Disconnected CWP | C104: No | D104: =Mangochi!D104+'Monkey Bay'!D104+Namwera!D104 -> 23 | E104: =Mangochi!E104+'Monkey Bay'!E104+Namwera!E104 -> 23 | F104: =Mangochi!F104+'Monkey Bay'!F104+Namwera!F104 -> 23 | G104: =Mangochi!G104+'Monkey Bay'!G104+Namwera!G104 -> 15 | H104: =Mangochi!H104+'Monkey Bay'!H104+Namwera!H104 -> 15 | I104: =Mangochi!I104+'Monkey Bay'!I104+Namwera!I104 -> 15 | J104: =Mangochi!J104+'Monkey Bay'!J104+Namwera!J104+Nkhudzi!J104 -> 15 | K104: =Mangochi!K104+'Monkey Bay'!K104+Namwera!K104+Nkhudzi!K104 -> 15 | L104: =Mangochi!L104+'Monkey Bay'!L104+Namwera!L104+Nkhudzi!L104 -> 15 | M104: =Mangochi!M104+'Monkey Bay'!M104+Namwera!M104+Nkhudzi!M104 -> 15 | N104: =Mangochi!N104+'Monkey Bay'!N104+Namwera!N104+Nkhudzi!N104 -> 10 | O104: =Mangochi!O104+'Monkey Bay'!O104+Namwera!O104+Nkhudzi!O104 -> 10 | P104: =O104 -> 10
A105: Total Disconnected Accounts | C105: No | D105: =SUM(D101:D104) -> 2736 | E105: =SUM(E101:E104) -> 2720 | F105: =SUM(F101:F104) -> 2677 | G105: =SUM(G101:G104) -> 2648 | H105: =SUM(H101:H104) -> 2617 | I105: =SUM(I101:I104) -> 2582 | J105: =SUM(J101:J104) -> 2576 | K105: =SUM(K101:K104) -> 2531 | ... O105: =SUM(O101:O104) -> 2624 | P105: =O105 -> 2624
...

Sheet 1st QTR
A1: SOUTHERN REGION WATER BOARD
A3: MONTHLY REPORTS - 2023/2024
A4: MANGOCHI ZONE
A5: MANGOCHI ZONE
A7: PARAMETERS | C7: UNITS | D7: Mangochi | E7: Monkey Bay | F7: Namwera | G7: Nkhudzi | H7: TOTALS
A8: PRODUCTION
A9: Volume Produced | C9: m3 | D9: =Mangochi!D9+Mangochi!E9+Mangochi!F9 -> 388676 | E9: ='Monkey Bay'!D9+'Monkey Bay'!E9+'Monkey Bay'!F9 -> 180709 | F9: =Namwera!D9+Namwera!E9+Namwera!F9 -> 15892 | H9: =SUM(D9:F9) -> 585277
A10: REVENUE WATER - POSTPAID
A11: Volume Billed Individuals | C11: m3 | D11: =Mangochi!D11+Mangochi!E11+Mangochi!F11 -> 168416 | E11: ='Monkey Bay'!D11+'Monkey Bay'!E11+'Monkey Bay'!F11 -> 52901 | F11: =Namwera!D11+Namwera!E11+Namwera!F11 -> 5574 | H11: =SUM(D11:F11) -> 226891
A12: Volume Billed CWPs | C12: m3 | D12: =Mangochi!D12+Mangochi!E12+Mangochi!F12 -> 0 | E12: ='Monkey Bay'!D12+'Monkey Bay'!E12+'Monkey Bay'!F12 -> 0 | F12: =Namwera!D12+Namwera!E12+Namwera!F12 -> 0 | H12: =SUM(D12:F12) -> 0
A13: Volume Billed Institutions | C13: m3 | D13: =Mangochi!D13+Mangochi!E13+Mangochi!F13 -> 920 | E13: ='Monkey Bay'!D13+'Monkey Bay'!E13+'Monkey Bay'!F13 -> 61252 | F13: =Namwera!D13+Namwera!E13+Namwera!F13 -> 39 | H13: =SUM(D13:F13) -> 62211
A14: Volume Billed Commercial/Industrial | C14: m3 | D14: =Mangochi!D14+Mangochi!E14+Mangochi!F14 -> 512 | E14: ='Monkey Bay'!D14+'Monkey Bay'!E14+'Monkey Bay'!F14 -> 9306 | F14: =Namwera!D14+Namwera!E14+Namwera!F14 -> 0 | H14: =SUM(D14:F14) -> 9818
A15: Total Volume Billed Post Paid | C15: m3 | D15: =SUM(D11:D14) -> 169848 | E15: =SUM(E11:E14) -> 123459 | F15: =SUM(F11:F14) -> 5613 | H15: =SUM(H11:H14) -> 298920
A16: REVENUE WATER - PREPAID
A17: Individuals | C17: m3 | D17: =Mangochi!D17+Mangochi!E17+Mangochi!F17 -> 44175.3 | E17: ='Monkey Bay'!D17+'Monkey Bay'!E17+'Monkey Bay'!F17 -> 7966 | F17: =Namwera!D17+Namwera!E17+Namwera!F17 -> 3501 | H17: =SUM(D17:F17) -> 55642.3
A18: CWPs | C18: m3 | D18: =Mangochi!D18+Mangochi!E18+Mangochi!F18 -> 0 | E18: ='Monkey Bay'!D18+'Monkey Bay'!E18+'Monkey Bay'!F18 -> 3522 | F18: =Namwera!D18+Namwera!E18+Namwera!F18 -> 0 | H18: =SUM(D18:F18) -> 3522
A19: Institutions | C19: m3 | D19: =Mangochi!D19+Mangochi!E19+Mangochi!F19 -> 0 | E19: ='Monkey Bay'!D19+'Monkey Bay'!E19+'Monkey Bay'!F19 -> 9315 | F19: =Namwera!D19+Namwera!E19+Namwera!F19 -> 1269 | H19: =SUM(D19:F19) -> 10584
A20: Commercial/Industrial | C20: m3 | D20: =Mangochi!D20+Mangochi!E20+Mangochi!F20 -> 0 | E20: ='Monkey Bay'!D20+'Monkey Bay'!E20+'Monkey Bay'!F20 -> 1395 | F20: =Namwera!D20+Namwera!E20+Namwera!F20 -> 66 | H20: =SUM(D20:F20) -> 1461
A21: Total Volume Prepaid | C21: m3 | D21: =SUM(D17:D20) -> 44175.3 | E21: =SUM(E17:E20) -> 22198 | F21: =SUM(F17:F20) -> 4836 | H21: =SUM(H17:H20) -> 71209.3
A22: TOTAL REVENUE WATER | C22: m3 | D22: =D21+D15 -> 214023.3 | E22: =E21+E15 -> 145657 | F22: =F21+F15 -> 10449 | H22: =H21+H15 -> 370129.3
A23: NON-REVENUE WATER (NRW)
A24: Non-Revenue Water (NRW) | B24: Volume | C24: m3 | D24: =D9-D22 -> 174652.7 | E24: =E9-E22 -> 35052 | F24: =F9-F22 -> 5443 | H24: =H9-H22 -> 215147.7
B25: Percentage | C25: % | D25: =D24/D9 -> 0.44935293 | E25: =E24/E9 -> 0.19396931 | F25: =F24/F9 -> 0.34249937 | H25: =H24/H9 -> 0.36759979
A26: OPERATING EXPENSES
A27: Chemicals
A28: Chemical | B28: Rate(MK/kg)
A29: Chlorine | B29: 7400 | C29: kg | D29: =Mangochi!D29+Mangochi!E29+Mangochi!F29 -> 1629 | E29: ='Monkey Bay'!D29+'Monkey Bay'!E29+'Monkey Bay'!F29 -> 455 | F29: =Namwera!D29+Namwera!E29+Namwera!F29 -> 35.5 | H29: =SUM(D29:F29) -> 2119.5
C30: kg/mg litre | D30: =D29/(D9/1000) -> 4.1911515 | E30: =E29/(E9/1000) -> 2.5178602 | F30: =F29/(F9/1000) -> 2.2338283 | H30: =H29/(H9/1000) -> 3.6213622
A31: Aluminium sulphate | B31: 1900 | C31: kg | D31: =Mangochi!D31+Mangochi!E31+Mangochi!F31 -> 800 | E31: ='Monkey Bay'!D31+'Monkey Bay'!E31+'Monkey Bay'!F31 -> 0 | F31: =Namwera!D31+Namwera!E31+Namwera!F31 -> 0 | H31: =SUM(D31:F31) -> 800
C32: kg/mg litre | D32: =D31/(D9/1000) -> 2.0582696 | E32: =E31/(E9/1000) -> 0 | F32: =F31/(F9/1000) -> 0 | H32: =H31/(H9/1000) -> 1.3668741
A33: Soda | B33: 1900 | C33: kg | D33: =Mangochi!D33+Mangochi!E33+Mangochi!F33 -> 0 | E33: ='Monkey Bay'!D33+'Monkey Bay'!E33+'Monkey Bay'!F33 -> 0 | F33: =Namwera!D33+Namwera!E33+Namwera!F33 -> 0 | H33: =SUM(D33:F33) -> 0
C34: kg/mg litre | D34: =D33/(D9/1000) -> 0 | E34: =E33/(E9/1000) -> 0 | F34: =F33/(F9/1000) -> 0 | H34: =H33/(H9/1000) -> 0
A35: Algae floc | B35: =745345.16/200 -> 3726.7258 | C35: litres | D35: =Mangochi!D35+Mangochi!E35+Mangochi!F35 -> 0 | E35: ='Monkey Bay'!D35+'Monkey Bay'!E35+'Monkey Bay'!F35 -> 0 | F35: =Namwera!D35+Namwera!E35+Namwera!F35 -> 0 | H35: =SUM(D35:F35) -> 0
C36: litres/mg litre | D36: =D35/(D11/1000) -> 0 | E36: =E35/(E11/1000) -> 0 | F36: =F35/(F11/1000) -> 0 | H36: =H35/(H11/1000) -> 0
A37: Sud floc | B37: =790318.72/200 -> 3951.5936 | C37: litres | D37: =Mangochi!D37+Mangochi!E37+Mangochi!F37 -> 0 | E37: ='Monkey Bay'!D37+'Monkey Bay'!E37+'Monkey Bay'!F37 -> 0 | F37: =Namwera!D37+Namwera!E37+Namwera!F37 -> 0 | H37: =SUM(D37:F37) -> 0
C38: litres/mg litre | D38: =D37/(D13/1000) -> 0 | E38: =E37/(E13/1000) -> 0 | F38: =F37/(F13/1000) -> 0 | H38: =H37/(H13/1000) -> 0
A39: Potasium permanganate | B39: 1950 | C39: kg | D39: =Mangochi!D39+Mangochi!E39+Mangochi!F39 -> 0 | E39: ='Monkey Bay'!D39+'Monkey Bay'!E39+'Monkey Bay'!F39 -> 0 | F39: =Namwera!D39+Namwera!E39+Namwera!F39 -> 0 | H39: =SUM(D39:F39) -> 0
C40: kg/mg litre | D40: =D39/(D9/1000) -> 0 | E40: =E39/(E9/1000) -> 0 | F40: =F39/(F9/1000) -> 0 | H40: =H39/(H9/1000) -> 0
A41: Cost of Chemicals | C41: Mk | D41: =(D29*$B29)+(D31*$B31)+(D33*$B33)+(D35*$B35)+(D37*$B37)+(D39*$B39) -> 13574600 | E41: =(E29*$B29)+(E31*$B31)+(E33*$B33)+(E35*$B35)+(E37*$B37)+(E39*$B39) -> 3367000 | F41: =(F29*$B29)+(F31*$B31)+(F33*$B33)+(F35*$B35)+(F37*$B37)+(F39*$B39) -> 262700 | H41: =SUM(D41:F41) -> 17204300
A42: Cost/vol. Produced (chemicals) | C42: Mk/m3 | D42: =D41/D9 -> 34.925233 | E42: =E41/E9 -> 18.632166 | F42: =F41/F9 -> 16.53033 | H42: =H41/H9 -> 29.395141
A43: Power
A44: Power Usage | C44: Kw | D44: =Mangochi!D44+Mangochi!E44+Mangochi!F44 -> 161872.92 | E44: ='Monkey Bay'!D44+'Monkey Bay'!E44+'Monkey Bay'!F44 -> 80272 | F44: =Namwera!D44+Namwera!E44+Namwera!F44 -> 11318 | H44: =SUM(D44:F44) -> 253462.92
A45: Power/ Vol. Produced | C45: Kw/m3 | D45: =D44/D9 -> 0.41647264 | E45: =E44/E9 -> 0.44420588 | F45: =F44/F9 -> 0.71218223 | H45: =H44/H9 -> 0.43306489
A46: Cost of Power | C46: Mk | D46: =Mangochi!D46+Mangochi!E46+Mangochi!F46 -> 22509390 | E46: ='Monkey Bay'!D46+'Monkey Bay'!E46+'Monkey Bay'!F46 -> 11187140 | F46: =Namwera!D46+Namwera!E46+Namwera!F46 -> 1619669 | H46: =SUM(D46:F46) -> 35316199
A47: Cost/vol. Produced | C47: Mk/m3 | D47: =D46/D9 -> 57.912992 | E47: =E46/E9 -> 61.906933 | F47: =F46/F9 -> 101.91725 | H47: =H46/H9 -> 60.340999
A48: Plant and Vehicle Maintenance
A49: Distances covered | C49: km | D49: =Mangochi!D49+Mangochi!E49+Mangochi!F49 -> 12080 | E49: ='Monkey Bay'!D49+'Monkey Bay'!E49+'Monkey Bay'!F49 -> 4827 | F49: =Namwera!D49+Namwera!E49+Namwera!F49 -> 298 | H49: =SUM(D49:F49) -> 17205
A50: Fuel Used (litres) | C50: litres | D50: =Mangochi!D50+Mangochi!E50+Mangochi!F50 -> 2801.1 | E50: ='Monkey Bay'!D50+'Monkey Bay'!E50+'Monkey Bay'!F50 -> 448.8 | F50: =Namwera!D50+Namwera!E50+Namwera!F50 -> 535 | H50: =SUM(D50:F50) -> 3784.9
A51: Cost of fuel | C51: Mk | D51: =Mangochi!D51+Mangochi!E51+Mangochi!F51 -> 5377920 | E51: ='Monkey Bay'!D51+'Monkey Bay'!E51+'Monkey Bay'!F51 -> 861696 | F51: =Namwera!D51+Namwera!E51+Namwera!F51 -> 1024520 | H51: =SUM(D51:F51) -> 7264136
A52: Maintenance | C52: Mk | D52: =Mangochi!D52+Mangochi!E52+Mangochi!F52 -> 0 | E52: ='Monkey Bay'!D52+'Monkey Bay'!E52+'Monkey Bay'!F52 -> 0 | F52: =Namwera!D52+Namwera!E52+Namwera!F52 -> 0 | H52: =SUM(D52:F52) -> 0
A53: Salaries and Wages
A54: Staff Costs | C54: MK | D54: =Mangochi!D54+Mangochi!E54+Mangochi!F54 -> 45776594 | E54: ='Monkey Bay'!D54+'Monkey Bay'!E54+'Monkey Bay'!F54 -> 11230665 | F54: =Namwera!D54+Namwera!E54+Namwera!F54 -> 6027400.5 | H54: =SUM(D54:F54) -> 63034660
A55: Wages | C55: MK | D55: =Mangochi!D55+Mangochi!E55+Mangochi!F55 -> 5206017.9 | E55: ='Monkey Bay'!D55+'Monkey Bay'!E55+'Monkey Bay'!F55 -> 1729570.1 | F55: =Namwera!D55+Namwera!E55+Namwera!F55 -> 1210638.9 | H55: =SUM(D55:F55) -> 8146226.9
A56: Other Overhead Costs | C56: MK | D56: =Mangochi!D56+Mangochi!E56+Mangochi!F56 -> 4564100 | E56: ='Monkey Bay'!D56+'Monkey Bay'!E56+'Monkey Bay'!F56 -> 1277450 | F56: =Namwera!D56+Namwera!E56+Namwera!F56 -> 356800 | H56: =SUM(D56:F56) -> 6198350
A57: Operating Costs
A58: Total Operating Costs | C58: MK | D58: =D41+D46+D51+D52+D54+D55+D56 -> 97008622 | E58: =E41+E46+E51+E52+E54+E55+E56 -> 29653521 | F58: =F41+F46+F51+F52+F54+F55+F56 -> 10501728 | H58: =SUM(D58:F58) -> 1.3716387e+08
A59: Cost/Vol. Produced | C59: Mk/m3 | D59: =D58/D9 -> 249.58737 | E59: =E58/E9 -> 164.09543 | F59: =F58/F9 -> 660.81855 | H59: =H58/H9 -> 234.35719
A60: Cost/Vol. Billed | C60: Mk/m3 | D60: =D58/D22 -> 453.26197 | E60: =E58/E22 -> 203.58459 | F60: =F58/F22 -> 1005.0463 | H60: =H58/H22 -> 370.58366
A61: Permanent Staff Employed | C61: No | D61: =Mangochi!F61 -> 24 | E61: ='Monkey Bay'!F61 -> 5 | F61: =Namwera!F61 -> 4 | H61: =SUM(D61:F61) -> 33
A62: Staff/Vol.1000m3 of Volume Produced/hour (12 hour day) | C62: No/1000m3 | D62: =(D61*1000*31)/D9 -> 1.9141907 | E62: =(E61*1000*31)/E9 -> 0.8577326 | F62: =(F61*1000*31)/F9 -> 7.802668 | H62: =(H61*1000*31)/H9 -> 1.7478903
A63: Temporary Staff Employed | C63: No | D63: =Mangochi!F63 -> 25 | E63: ='Monkey Bay'!F63 -> 9 | F63: =Namwera!F63 -> 6 | H63: =SUM(D63:F63) -> 40
A65: Water Connections and Disconnections
A66: New Individual Water Connections | B66: Brought Forward | C66: No | D66: =Mangochi!D66 -> 1052 | E66: ='Monkey Bay'!D66 -> 99 | F66: =Namwera!D66 -> 55 | H66: =SUM(D66:F66) -> 1206
B67: Applied this Month | C67: No | D67: =Mangochi!D67+Mangochi!E67+Mangochi!F67 -> 352 | E67: ='Monkey Bay'!D67+'Monkey Bay'!E67+'Monkey Bay'!F67 -> 41 | F67: =Namwera!D67+Namwera!E67+Namwera!F67 -> 7 | H67: =SUM(D67:F67) -> 400
B68: Done this Month Postpaid | C68: No | D68: =Mangochi!D68+Mangochi!E68+Mangochi!F68 -> 7 | E68: ='Monkey Bay'!D68+'Monkey Bay'!E68+'Monkey Bay'!F68 -> 0 | F68: =Namwera!D68+Namwera!E68+Namwera!F68 -> 0 | H68: =SUM(D68:F68) -> 7
B69: Done this Month Prepaid | C69: No | D69: =Mangochi!D69+Mangochi!E69+Mangochi!F69 -> 82 | E69: ='Monkey Bay'!D69+'Monkey Bay'!E69+'Monkey Bay'!F69 -> 27 | F69: =Namwera!D69+Namwera!E69+Namwera!F69 -> 18 | H69: =SUM(D69:F69) -> 127
B70: Total Done | C70: No | D70: =D68+D69 -> 89 | E70: =E68+E69 -> 27 | F70: =F68+F69 -> 18 | H70: =H68+H69 -> 134
B71: Carried Forward | C71: No | D71: =D66+D67-D70 -> 1315 | E71: =E66+E67-E70 -> 113 | F71: =F66+F67-F70 -> 44 | H71: =H66+H67-H70 -> 1472
A72: New Institutional Water Connections | B72: Brought Forward | C72: No | D72: =Mangochi!D72 -> 8 | E72: ='Monkey Bay'!D72 -> 0 | F72: =Namwera!D72 -> 3 | H72: =SUM(D72:F72) -> 11
B73: Applied this Month | C73: No | D73: =Mangochi!D73+Mangochi!E73+Mangochi!F73 -> 0 | E73: ='Monkey Bay'!D73+'Monkey Bay'!E73+'Monkey Bay'!F73 -> 0 | F73: =Namwera!D73+Namwera!E73+Namwera!F73 -> 0 | H73: =SUM(D73:F73) -> 0
B74: Done this Month Postpaid | C74: No | D74: =Mangochi!D74+Mangochi!E74+Mangochi!F74 -> 0 | E74: ='Monkey Bay'!D74+'Monkey Bay'!E74+'Monkey Bay'!F74 -> 0 | F74: =Namwera!D74+Namwera!E74+Namwera!F74 -> 0 | H74: =SUM(D74:F74) -> 0
B75: Done this Month Prepaid | C75: No | D75: =Mangochi!D75+Mangochi!E75+Mangochi!F75 -> 0 | E75: ='Monkey Bay'!D75+'Monkey Bay'!E75+'Monkey Bay'!F75 -> 0 | F75: =Namwera!D75+Namwera!E75+Namwera!F75 -> 0 | H75: =SUM(D75:F75) -> 0
B76: Total Done | C76: No | D76: =D74+D75 -> 0 | E76: =E74+E75 -> 0 | F76: =F74+F75 -> 0 | H76: =H74+H75 -> 0
B77: Carried Forward | C77: No | D77: =D73+D74-D76 -> 0 | E77: =E73+E74-E76 -> 0 | F77: =F73+F74-F76 -> 0 | H77: =H73+H74-H76 -> 0
A78: New Commercial/Industrial Water Connections | B78: Brought Forward | C78: No | D78: =Mangochi!D78 -> 9 | E78: ='Monkey Bay'!D78 -> 2 | F78: =Namwera!D78 -> 0 | H78: =SUM(D78:F78) -> 11
B79: Applied this Month | C79: No | D79: =Mangochi!D79+Mangochi!E79+Mangochi!F79 -> 0 | E79: ='Monkey Bay'!D79+'Monkey Bay'!E79+'Monkey Bay'!F79 -> 2 | F79: =Namwera!D79+Namwera!E79+Namwera!F79 -> 0 | H79: =SUM(D79:F79) -> 2
B80: Done this Month Postpaid | C80: No | D80: =Mangochi!D80+Mangochi!E80+Mangochi!F80 -> 0 | E80: ='Monkey Bay'!D80+'Monkey Bay'!E80+'Monkey Bay'!F80 -> 0 | F80: =Namwera!D80+Namwera!E80+Namwera!F80 -> 0 | H80: =SUM(D80:F80) -> 0
B81: Done this Month Prepaid | C81: No | D81: =Mangochi!D81+Mangochi!E81+Mangochi!F81 -> 0 | E81: ='Monkey Bay'!D81+'Monkey Bay'!E81+'Monkey Bay'!F81 -> 4 | F81: =Namwera!D81+Namwera!E81+Namwera!F81 -> 0 | H81: =SUM(D81:F81) -> 4
B82: Total Done | C82: No | D82: =D81+D80 -> 0 | E82: =E81+E80 -> 4 | F82: =F81+F80 -> 0 | H82: =H81+H80 -> 4
B83: Carried Forward | C83: No | D83: =D78+D79-D82 -> 9 | E83: =E78+E79-E82 -> 0 | F83: =F78+F79-F82 -> 0 | H83: =H78+H79-H82 -> 9
A84: New CWP | B84: Brought Forward | C84: No | D84: =Mangochi!D84 -> 0 | E84: ='Monkey Bay'!D84 -> 0 | F84: =Namwera!D84 -> 0 | H84: =SUM(D84:F84) -> 0
B85: Applied this Month | C85: No | D85: =Mangochi!D85+Mangochi!E85+Mangochi!F85 -> 0 | E85: ='Monkey Bay'!D85+'Monkey Bay'!E85+'Monkey Bay'!F85 -> 0 | F85: =Namwera!D85+Namwera!E85+Namwera!F85 -> 0 | H85: =SUM(D85:F85) -> 0
B86: Done this Month Postpaid | C86: No | D86: =Mangochi!D86+Mangochi!E86+Mangochi!F86 -> 0 | E86: ='Monkey Bay'!D86+'Monkey Bay'!E86+'Monkey Bay'!F86 -> 0 | F86: =Namwera!D86+Namwera!E86+Namwera!F86 -> 0 | H86: =SUM(D86:F86) -> 0
B87: Done this Month Prepaid | C87: No | D87: =Mangochi!D87+Mangochi!E87+Mangochi!F87 -> 0 | E87: ='Monkey Bay'!D87+'Monkey Bay'!E87+'Monkey Bay'!F87 -> 0 | F87: =Namwera!D87+Namwera!E87+Namwera!F87 -> 0 | H87: =SUM(D87:F87) -> 0
B88: Total Done | C88: No | D88: =D87+D86 -> 0 | E88: =E87+E86 -> 0 | F88: =F87+F86 -> 0 | H88: =SUM(D88:F88) -> 0
B89: Carried Forward | C89: No | D89: =D84+D85-D88 -> 0 | E89: =E84+E85-E88 -> 0 | F89: =F84+F85-F88 -> 0 | H89: =H84+H85-H86-H87 -> 0
A90: Aggregated New Water connections | B90: Brought Forward | C90: No | D90: =D66+D72+D78+D84 -> 1069 | E90: =E66+E72+E78+E84 -> 101 | F90: =F66+F72+F78+F84 -> 58 | H90: =SUM(D90:F90) -> 1228
B91: Applied this Month | C91: No | D91: =D67+D73+D79+D85 -> 352 | E91: =E67+E73+E79+E85 -> 43 | F91: =F67+F73+F79+F85 -> 7 | H91: =SUM(D91:F91) -> 402
B92: Done this Month Postpaid | C92: No | D92: =D68+D74+D80+D86 -> 7 | E92: =E68+E74+E80+E86 -> 0 | F92: =F68+F74+F80+F86 -> 0 | H92: =SUM(D92:F92) -> 7
B93: Done this Month Prepaid | D93: =D69+D75+D81+D87 -> 82 | E93: =E69+E75+E81+E87 -> 31 | F93: =F69+F75+F81+F87 -> 18 | H93: =SUM(D93:F93) -> 131
B94: Total Done | C94: No | D94: =D93+D92 -> 89 | E94: =E93+E92 -> 31 | F94: =F93+F92 -> 18 | H94: =H93+H92 -> 138
B95: Carried Forward | C95: No | D95: =D90+D91-D94 -> 1332 | E95: =E90+E91-E94 -> 113 | F95: =F90+F91-F94 -> 47 | H95: =H90+H91-H94 -> 1492
A97: Prepaid Metering
A98: Prepaid Meters Installed | C98: No | D98: =Mangochi!D98+Mangochi!E98+Mangochi!F98 -> 84 | E98: ='Monkey Bay'!D98+'Monkey Bay'!E98+'Monkey Bay'!F98 -> 31 | F98: =Namwera!D98+Namwera!E98+Namwera!F98 -> 18 | H98: =SUM(D98:F98) -> 133
A100: Active and Disconnected Accounts
A101: Disconnected Individual Accounts | C101: No | D101: =Mangochi!F101 -> 1855 | E101: ='Monkey Bay'!F101 -> 425 | F101: =Namwera!F101 -> 220 | H101: =SUM(D101:F101) -> 2500
A102: Disconnected institutional Accounts | C102: No | D102: =Mangochi!F102 -> 4 | E102: ='Monkey Bay'!F102 -> 0 | F102: =Namwera!F102 -> 7 | H102: =SUM(D102:F102) -> 11
A103: Disconnected Commercial/Industrial Accounts | C103: No | D103: =Mangochi!F103 -> 141 | E103: ='Monkey Bay'!F103 -> 0 | F103: =Namwera!F103 -> 2 | H103: =SUM(D103:F103) -> 143
A104: Disconnected CWP | C104: No | D104: =Mangochi!F104 -> 18 | E104: ='Monkey Bay'!F104 -> 0 | F104: =Namwera!F104 -> 5 | H104: =SUM(D104:F104) -> 23
A105: Total Disconnected Accounts | C105: No | D105: =SUM(D101:D104) -> 2018 | E105: =SUM(E101:E104) -> 425 | F105: =SUM(F101:F104) -> 234 | H105: =SUM(D105:F105) -> 2677
...

Sheet 2nd QTR 
A1: SOUTHERN REGION WATER BOARD
A3: MONTHLY REPORTS - 2023/2024
A4: MANGOCHI ZONE
A5: MANGOCHI ZONE
A7: PARAMETERS | C7: UNITS | D7: Mangochi | E7: Monkey Bay | F7: Namwera | G7: Nkhudzi | H7: TOTALS
A8: PRODUCTION
A9: Volume Produced | C9: m3 | D9: =Mangochi!G9+Mangochi!H9+Mangochi!I9 -> 376477 | E9: ='Monkey Bay'!G9+'Monkey Bay'!H9+'Monkey Bay'!I9 -> 187098 | F9: =Namwera!G9+Namwera!H9+Namwera!I9 -> 16262 | H9: =SUM(D9:F9) -> 579837
A10: REVENUE WATER - POSTPAID
A11: Volume Billed Individuals | C11: m3 | D11: =Mangochi!G11+Mangochi!H11+Mangochi!I11 -> 177881 | E11: ='Monkey Bay'!G11+'Monkey Bay'!H11+'Monkey Bay'!I11 -> 59435 | F11: =Namwera!G11+Namwera!H11+Namwera!I11 -> 6108 | H11: =SUM(D11:F11) -> 243424
A12: Volume Billed CWPs | C12: m3 | D12: =Mangochi!G12+Mangochi!H12+Mangochi!I12 -> 0 | E12: ='Monkey Bay'!G12+'Monkey Bay'!H12+'Monkey Bay'!I12 -> 0 | F12: =Namwera!G12+Namwera!H12+Namwera!I12 -> 0 | H12: =SUM(D12:F12) -> 0
A13: Volume Billed Institutions | C13: m3 | D13: =Mangochi!G13+Mangochi!H13+Mangochi!I13 -> 847 | E13: ='Monkey Bay'!G13+'Monkey Bay'!H13+'Monkey Bay'!I13 -> 68803 | F13: =Namwera!G13+Namwera!H13+Namwera!I13 -> 44 | H13: =SUM(D13:F13) -> 69694
A14: Volume Billed Commercial/Industrial | C14: m3 | D14: =Mangochi!G14+Mangochi!H14+Mangochi!I14 -> 169 | E14: ='Monkey Bay'!G14+'Monkey Bay'!H14+'Monkey Bay'!I14 -> 1367 | F14: =Namwera!G14+Namwera!H14+Namwera!I14 -> 0 | H14: =SUM(D14:F14) -> 1536
A15: Total Volume Billed Post Paid | C15: m3 | D15: =SUM(D11:D14) -> 178897 | E15: =SUM(E11:E14) -> 129605 | F15: =SUM(F11:F14) -> 6152 | H15: =SUM(H11:H14) -> 314654
A16: REVENUE WATER - PREPAID
A17: Individuals | C17: m3 | D17: =Mangochi!G17+Mangochi!H17+Mangochi!I17 -> 46850.2 | E17: ='Monkey Bay'!G17+'Monkey Bay'!H17+'Monkey Bay'!I17 -> 9185 | F17: =Namwera!G17+Namwera!H17+Namwera!I17 -> 3988 | H17: =SUM(D17:F17) -> 60023.2
A18: CWPs | C18: m3 | D18: =Mangochi!G18+Mangochi!H18+Mangochi!I18 -> 0 | E18: ='Monkey Bay'!G18+'Monkey Bay'!H18+'Monkey Bay'!I18 -> 3787 | F18: =Namwera!G18+Namwera!H18+Namwera!I18 -> 7 | H18: =SUM(D18:F18) -> 3794
A19: Institutions | C19: m3 | D19: =Mangochi!G19+Mangochi!H19+Mangochi!I19 -> 0 | E19: ='Monkey Bay'!G19+'Monkey Bay'!H19+'Monkey Bay'!I19 -> 8795 | F19: =Namwera!G19+Namwera!H19+Namwera!I19 -> 1517 | H19: =SUM(D19:F19) -> 10312
A20: Commercial/Industrial | C20: m3 | D20: =Mangochi!G20+Mangochi!H20+Mangochi!I20 -> 0 | E20: ='Monkey Bay'!G20+'Monkey Bay'!H20+'Monkey Bay'!I20 -> 1274 | F20: =Namwera!G20+Namwera!H20+Namwera!I20 -> 158 | H20: =SUM(D20:F20) -> 1432
A21: Total Volume Prepaid | C21: m3 | D21: =SUM(D17:D20) -> 46850.2 | E21: =SUM(E17:E20) -> 23041 | F21: =SUM(F17:F20) -> 5670 | H21: =SUM(H17:H20) -> 75561.2
A22: TOTAL REVENUE WATER | C22: m3 | D22: =D21+D15 -> 225747.2 | E22: =E21+E15 -> 152646 | F22: =F21+F15 -> 11822 | H22: =H21+H15 -> 390215.2
A23: NON-REVENUE WATER (NRW)
A24: Non-Revenue Water (NRW) | B24: Volume | C24: m3 | D24: =D9-D22 -> 150729.8 | E24: =E9-E22 -> 34452 | F24: =F9-F22 -> 4440 | H24: =H9-H22 -> 189621.8
B25: Percentage | C25: % | D25: =D24/D9 -> 0.40036921 | E25: =E24/E9 -> 0.18413879 | F25: =F24/F9 -> 0.27302915 | H25: =H24/H9 -> 0.32702604
A26: OPERATING EXPENSES
A27: Chemicals
A28: Chemical | B28: Rate(MK/kg)
A29: Chlorine | B29: 7400 | C29: kg | D29: =Mangochi!G29+Mangochi!H29+Mangochi!I29 -> 1556 | E29: ='Monkey Bay'!G29+'Monkey Bay'!H29+'Monkey Bay'!I29 -> 460 | F29: =Namwera!G29+Namwera!H29+Namwera!I29 -> 41 | H29: =SUM(D29:F29) -> 2057
C30: kg/mg litre | D30: =D29/(D9/1000) -> 4.1330546 | E30: =E29/(E9/1000) -> 2.4586046 | F30: =F29/(F9/1000) -> 2.5212151 | H30: =H29/(H9/1000) -> 3.5475487
A31: Aluminium sulphate | B31: 1900 | C31: kg | D31: =Mangochi!G31+Mangochi!H31+Mangochi!I31 -> 0 | E31: ='Monkey Bay'!G31+'Monkey Bay'!H31+'Monkey Bay'!I31 -> 0 | F31: =Namwera!G31+Namwera!H31+Namwera!I31 -> 0 | H31: =SUM(D31:F31) -> 0
C32: kg/mg litre | D32: =D31/(D9/1000) -> 0 | E32: =E31/(E9/1000) -> 0 | F32: =F31/(F9/1000) -> 0 | H32: =H31/(H9/1000) -> 0
A33: Soda | B33: 1900 | C33: kg | D33: =Mangochi!G33+Mangochi!H33+Mangochi!I33 -> 0 | E33: ='Monkey Bay'!G33+'Monkey Bay'!H33+'Monkey Bay'!I33 -> 0 | F33: =Namwera!G33+Namwera!H33+Namwera!I33 -> 0 | H33: =SUM(D33:F33) -> 0
C34: kg/mg litre | D34: =D33/(D9/1000) -> 0 | E34: =E33/(E9/1000) -> 0 | F34: =F33/(F9/1000) -> 0 | H34: =H33/(H9/1000) -> 0
A35: Algae floc | B35: =745345.16/200 -> 3726.7258 | C35: litres | D35: =Mangochi!G35+Mangochi!H35+Mangochi!I35 -> 0 | E35: ='Monkey Bay'!G35+'Monkey Bay'!H35+'Monkey Bay'!I35 -> 0 | F35: =Namwera!G35+Namwera!H35+Namwera!I35 -> 0
C36: litres/mg litre
A37: Sud floc | B37: =790318.72/200 -> 3951.5936 | C37: litres | D37: =Mangochi!G37+Mangochi!H37+Mangochi!I37 -> 0 | E37: ='Monkey Bay'!G37+'Monkey Bay'!H37+'Monkey Bay'!I37 -> 0 | F37: =Namwera!G37+Namwera!H37+Namwera!I37 -> 0 | H37: =SUM(D37:F37) -> 0
C38: litres/mg litre | D38: =D37/(D9/1000) -> 0 | E38: =E37/(E9/1000) -> 0 | F38: =F37/(F9/1000) -> 0 | H38: =H37/(H9/1000) -> 0
A39: Potasium permanganate | B39: 1950 | C39: kg | D39: =Mangochi!G39+Mangochi!H39+Mangochi!I39 -> 0 | E39: ='Monkey Bay'!G39+'Monkey Bay'!H39+'Monkey Bay'!I39 -> 0 | F39: =Namwera!G39+Namwera!H39+Namwera!I39 -> 0 | H39: =SUM(D39:F39) -> 0
C40: kg/mg litre | D40: =D39/(D9/1000) -> 0 | E40: =E39/(E9/1000) -> 0 | F40: =F39/(F9/1000) -> 0 | H40: =H39/(H9/1000) -> 0
A41: Cost of Chemicals | C41: Mk | D41: =(D29*$B29)+(D31*$B31)+(D33*$B33)+(D35*$B35)+(D37*$B37)+(D39*$B39) -> 11514400 | E41: =(E29*$B29)+(E31*$B31)+(E33*$B33)+(E35*$B35)+(E37*$B37)+(E39*$B39) -> 3404000 | F41: =(F29*$B29)+(F31*$B31)+(F33*$B33)+(F35*$B35)+(F37*$B37)+(F39*$B39) -> 303400 | H41: =SUM(D41:F41) -> 15221800
A42: Cost/vol. Produced (chemicals) | C42: Mk/m3 | D42: =D41/D9 -> 30.584604 | E42: =E41/E9 -> 18.193674 | F42: =F41/F9 -> 18.656992 | H42: =H41/H9 -> 26.25186
A43: Power
A44: Power Usage | C44: Kw | D44: =Mangochi!G44+Mangochi!H44+Mangochi!I44 -> 143423.22 | E44: ='Monkey Bay'!G44+'Monkey Bay'!H44+'Monkey Bay'!I44 -> 85746 | F44: =Namwera!G44+Namwera!H44+Namwera!I44 -> 12258 | H44: =SUM(D44:F44) -> 241427.22
A45: Power/ Vol. Produced | C45: Kw/m3 | D45: =D44/D9 -> 0.38096144 | E45: =E44/E9 -> 0.45829458 | F45: =F44/F9 -> 0.75378182 | H45: =H44/H9 -> 0.41637084
A46: Cost of Power | C46: Mk | D46: =Mangochi!G46+Mangochi!H46+Mangochi!I46 -> 22796574 | E46: ='Monkey Bay'!G46+'Monkey Bay'!H46+'Monkey Bay'!I46 -> 13577463 | F46: =Namwera!G46+Namwera!H46+Namwera!I46 -> 1990747.6 | H46: =SUM(D46:F46) -> 38364785
A47: Cost/vol. Produced | C47: Mk/m3 | D47: =D46/D9 -> 60.55237 | E47: =E46/E9 -> 72.568723 | F47: =F46/F9 -> 122.41714 | H47: =H46/H9 -> 66.164775
A48: Plant and Vehicle Maintenance
A49: Distances covered | C49: km | D49: =Mangochi!G49+Mangochi!H49+Mangochi!I49 -> 19600 | E49: ='Monkey Bay'!G49+'Monkey Bay'!H49+'Monkey Bay'!I49 -> 10075 | F49: =Namwera!G49+Namwera!H49+Namwera!I49 -> 392 | H49: =SUM(D49:F49) -> 30067
A50: Fuel Used (litres) | C50: litres | D50: =Mangochi!G50+Mangochi!H50+Mangochi!I50 -> 2646.3 | E50: ='Monkey Bay'!G50+'Monkey Bay'!H50+'Monkey Bay'!I50 -> 689.9 | F50: =Namwera!G50+Namwera!H50+Namwera!I50 -> 180 | H50: =SUM(D50:F50) -> 3516.2
A51: Cost of fuel | C51: Mk | D51: =Mangochi!G51+Mangochi!H51+Mangochi!I51 -> 5082240 | E51: ='Monkey Bay'!G51+'Monkey Bay'!H51+'Monkey Bay'!I51 -> 1324996 | F51: =Namwera!G51+Namwera!H51+Namwera!I51 -> 342120 | H51: =SUM(D51:F51) -> 6749356
A52: Maintenance | C52: Mk | D52: =Mangochi!G52+Mangochi!H52+Mangochi!I52 -> 0 | E52: ='Monkey Bay'!G52+'Monkey Bay'!H52+'Monkey Bay'!I52 -> 0 | F52: =Namwera!G52+Namwera!H52+Namwera!I52 -> 10000 | H52: =SUM(D52:F52) -> 10000
A53: Salaries and Wages
A54: Staff Costs | C54: MK | D54: =Mangochi!G54+Mangochi!H54+Mangochi!I54 -> 34703701 | E54: ='Monkey Bay'!G54+'Monkey Bay'!H54+'Monkey Bay'!I54 -> 10235318 | F54: =Namwera!G54+Namwera!H54+Namwera!I54 -> 5397266.2 | H54: =SUM(D54:F54) -> 50336285
A55: Wages | C55: MK | D55: =Mangochi!G55+Mangochi!H55+Mangochi!I55 -> 8053798.9 | E55: ='Monkey Bay'!G55+'Monkey Bay'!H55+'Monkey Bay'!I55 -> 2221638.2 | F55: =Namwera!G55+Namwera!H55+Namwera!I55 -> 1140085.9 | H55: =SUM(D55:F55) -> 11415523
A56: Other Overhead Costs | C56: MK | D56: =Mangochi!G56+Mangochi!H56+Mangochi!I56 -> 4622550 | E56: ='Monkey Bay'!G56+'Monkey Bay'!H56+'Monkey Bay'!I56 -> 1300150 | F56: =Namwera!G56+Namwera!H56+Namwera!I56 -> 363850 | H56: =SUM(D56:F56) -> 6286550
A57: Operating Costs
A58: Total Operating Costs | C58: MK | D58: =D41+D46+D51+D52+D54+D55+D56 -> 86773264 | E58: =E41+E46+E51+E52+E54+E55+E56 -> 32063565 | F58: =F41+F46+F51+F52+F54+F55+F56 -> 9547469.7 | H58: =SUM(D58:F58) -> 1.283843e+08
A59: Cost/Vol. Produced | C59: Mk/m3 | D59: =D58/D9 -> 230.48756 | E59: =E58/E9 -> 171.3731 | F59: =F58/F9 -> 587.10305 | H59: =H58/H9 -> 221.41446
A60: Cost/Vol. Billed | C60: Mk/m3 | D60: =D58/D22 -> 384.38246 | E60: =E58/E22 -> 210.05179 | F60: =F58/F22 -> 807.60191 | H60: =H58/H22 -> 329.00896
A61: Permanent Staff Employed | C61: No | D61: =Mangochi!I61 -> 24 | E61: ='Monkey Bay'!I61 -> 7 | F61: =Namwera!I61 -> 3 | H61: =SUM(D61:F61) -> 34
A62: Staff/Vol.1000m3 of Volume Produced/hour (12 hour day) | C62: No/1000m3 | D62: =(D61*1000*31)/D9 -> 1.9762163 | E62: =(E61*1000*31)/E9 -> 1.15982 | F62: =(F61*1000*31)/F9 -> 5.7188538 | H62: =(H61*1000*31)/H9 -> 1.8177522
A63: Temporary Staff Employed | C63: No | D63: =Mangochi!G63+Mangochi!H63+Mangochi!I63 -> 72 | E63: ='Monkey Bay'!G63+'Monkey Bay'!H63+'Monkey Bay'!I63 -> 27 | F63: =Namwera!G63+Namwera!H63+Namwera!I63 -> 18 | H63: =SUM(D63:F63) -> 117
A65: Water Connections and Disconnections
A66: New Individual Water Connections | B66: Brought Forward | C66: No | D66: =Mangochi!G66 -> 1315 | E66: ='Monkey Bay'!G66 -> 66 | F66: =Namwera!G66 -> 59 | H66: =SUM(D66:F66) -> 1440
B67: Applied this Month | C67: No | D67: =Mangochi!G67+Mangochi!H67+Mangochi!I67 -> 273 | E67: ='Monkey Bay'!G67+'Monkey Bay'!H67+'Monkey Bay'!I67 -> 49 | F67: =Namwera!G67+Namwera!H67+Namwera!I67 -> 29 | H67: =SUM(D67:F67) -> 351
B68: Done this Month Postpaid | C68: No | D68: =Mangochi!G68+Mangochi!H68+Mangochi!I68 -> 0 | E68: ='Monkey Bay'!G68+'Monkey Bay'!H68+'Monkey Bay'!I68 -> 0 | F68: =Namwera!G68+Namwera!H68+Namwera!I68 -> 0 | H68: =SUM(D68:F68) -> 0
B69: Done this Month Prepaid | C69: No | D69: =Mangochi!G69+Mangochi!H69+Mangochi!I69 -> 143 | E69: ='Monkey Bay'!G69+'Monkey Bay'!H69+'Monkey Bay'!I69 -> 44 | F69: =Namwera!G69+Namwera!H69+Namwera!I69 -> 22 | H69: =SUM(D69:F69) -> 209
B70: Total Done | C70: No | D70: =D68+D69 -> 143 | E70: =E68+E69 -> 44 | F70: =F68+F69 -> 22 | H70: =H68+H69 -> 209
B71: Carried Forward | C71: No | D71: =D66+D67-D70 -> 1445 | E71: =E66+E67-E70 -> 71 | F71: =F66+F67-F70 -> 66 | H71: =H66+H67-H70 -> 1582
A72: New Institutional Water Connections | B72: Brought Forward | C72: No | D72: =Mangochi!G72 -> 8 | E72: ='Monkey Bay'!G72 -> 0 | F72: =Namwera!G72 -> 4 | H72: =SUM(D72:F72) -> 12
B73: Applied this Month | C73: No | D73: =Mangochi!G73+Mangochi!H73+Mangochi!I73 -> 0 | E73: ='Monkey Bay'!G73+'Monkey Bay'!H73+'Monkey Bay'!I73 -> 0 | F73: =Namwera!G73+Namwera!H73+Namwera!I73 -> 0 | H73: =SUM(D73:F73) -> 0
B74: Done this Month Postpaid | C74: No | D74: =Mangochi!G74+Mangochi!H74+Mangochi!I74 -> 0 | E74: ='Monkey Bay'!G74+'Monkey Bay'!H74+'Monkey Bay'!I74 -> 0 | F74: =Namwera!G74+Namwera!H74+Namwera!I74 -> 0 | H74: =SUM(D74:F74) -> 0
B75: Done this Month Prepaid | C75: No | D75: =Mangochi!G75+Mangochi!H75+Mangochi!I75 -> 0 | E75: ='Monkey Bay'!G75+'Monkey Bay'!H75+'Monkey Bay'!I75 -> 0 | F75: =Namwera!G75+Namwera!H75+Namwera!I75 -> 0 | H75: =SUM(D75:F75) -> 0
B76: Total Done | C76: No | D76: =D74+D75 -> 0 | E76: =E74+E75 -> 0 | F76: =F74+F75 -> 0 | H76: =H74+H75 -> 0
B77: Carried Forward | C77: No | D77: =D73+D74-D76 -> 0 | E77: =E73+E74-E76 -> 0 | F77: =F73+F74-F76 -> 0 | H77: =H73+H74-H76 -> 0
A78: New Commercial/Industrial Water Connections | B78: Brought Forward | C78: No | D78: =Mangochi!G78 -> 9 | E78: ='Monkey Bay'!G78 -> 2 | F78: =Namwera!G78 -> 0 | H78: =SUM(D78:F78) -> 11
B79: Applied this Month | C79: No | D79: =Mangochi!G79+Mangochi!H79+Mangochi!I79 -> 0 | E79: ='Monkey Bay'!G79+'Monkey Bay'!H79+'Monkey Bay'!I79 -> 0 | F79: =Namwera!G79+Namwera!H79+Namwera!I79 -> 0 | H79: =SUM(D79:F79) -> 0
B80: Done this Month Postpaid | C80: No | D80: =Mangochi!G80+Mangochi!H80+Mangochi!I80 -> 0 | E80: ='Monkey Bay'!G80+'Monkey Bay'!H80+'Monkey Bay'!I80 -> 0 | F80: =Namwera!G80+Namwera!H80+Namwera!I80 -> 0 | H80: =SUM(D80:F80) -> 0
B81: Done this Month Prepaid | C81: No | D81: =Mangochi!G81+Mangochi!H81+Mangochi!I81 -> 0 | E81: ='Monkey Bay'!G81+'Monkey Bay'!H81+'Monkey Bay'!I81 -> 2 | F81: =Namwera!G81+Namwera!H81+Namwera!I81 -> 0 | H81: =SUM(D81:F81) -> 2
B82: Total Done | C82: No | D82: =D81+D80 -> 0 | E82: =E81+E80 -> 2 | F82: =F81+F80 -> 0 | H82: =H81+H80 -> 2
B83: Carried Forward | C83: No | D83: =D78+D79-D82 -> 9 | E83: =E78+E79-E82 -> 0 | F83: =F78+F79-F82 -> 0 | H83: =H78+H79-H82 -> 9
A84: New CWP | B84: Brought Forward | C84: No | D84: =Mangochi!G84 -> 0 | E84: ='Monkey Bay'!G84 -> 0 | F84: =Namwera!G84 -> 0 | H84: =SUM(D84:F84) -> 0
B85: Applied this Month | C85: No | D85: =Mangochi!G85+Mangochi!H85+Mangochi!I85 -> 0 | E85: ='Monkey Bay'!G85+'Monkey Bay'!H85+'Monkey Bay'!I85 -> 0 | F85: =Namwera!G85+Namwera!H85+Namwera!I85 -> 0 | H85: =SUM(D85:F85) -> 0
B86: Done this Month Postpaid | C86: No | D86: =Mangochi!G86+Mangochi!H86+Mangochi!I86 -> 0 | E86: ='Monkey Bay'!G86+'Monkey Bay'!H86+'Monkey Bay'!I86 -> 0 | F86: =Namwera!G86+Namwera!H86+Namwera!I86 -> 0 | H86: =SUM(D86:F86) -> 0
B87: Done this Month Prepaid | C87: No | D87: =Mangochi!G87+Mangochi!H87+Mangochi!I87 -> 0 | E87: ='Monkey Bay'!G87+'Monkey Bay'!H87+'Monkey Bay'!I87 -> 0 | F87: =Namwera!G87+Namwera!H87+Namwera!I87 -> 0 | H87: =SUM(D87:F87) -> 0
B88: Total Done | C88: No | D88: =D87+D86 -> 0 | E88: =E87+E86 -> 0 | F88: =F87+F86 -> 0
B89: Carried Forward | C89: No | D89: =D84+D85-D88 -> 0 | E89: =E84+E85-E88 -> 0 | F89: =F84+F85-F88 -> 0 | H89: =H84+H85-H86-H87 -> 0
A90: Aggregated New Water connections | B90: Brought Forward | C90: No | D90: =D66+D72+D78+D84 -> 1332 | E90: =E66+E72+E78+E84 -> 68 | F90: =F66+F72+F78+F84 -> 63 | H90: =SUM(D90:F90) -> 1463
B91: Applied this Month | C91: No | D91: =D67+D73+D79+D85 -> 273 | E91: =E67+E73+E79+E85 -> 49 | F91: =F67+F73+F79+F85 -> 29 | H91: =SUM(D91:F91) -> 351
B92: Done this Month Postpaid | C92: No | D92: =D68+D74+D80+D86 -> 0 | E92: =E68+E74+E80+E86 -> 0 | F92: =F68+F74+F80+F86 -> 0 | H92: =SUM(D92:F92) -> 0
B93: Done this Month Prepaid | D93: =D69+D75+D81+D87 -> 143 | E93: =E69+E75+E81+E87 -> 46 | F93: =F69+F75+F81+F87 -> 22 | H93: =SUM(D93:F93) -> 211
B94: Total Done | C94: No | D94: =D93+D92 -> 143 | E94: =E93+E92 -> 46 | F94: =F93+F92 -> 22 | H94: =H93+H92 -> 211
B95: Carried Forward | C95: No | D95: =D90+D91-D94 -> 1462 | E95: =E90+E91-E94 -> 71 | F95: =F90+F91-F94 -> 70 | H95: =H90+H91-H94 -> 1603
A97: Prepaid Metering
A98: Prepaid Meters Installed | C98: No | D98: =Mangochi!G98+Mangochi!H98+Mangochi!I98 -> 152 | E98: ='Monkey Bay'!G98+'Monkey Bay'!H98+'Monkey Bay'!I98 -> 46 | F98: =Namwera!G98+Namwera!H98+Namwera!I98 -> 22 | H98: =SUM(D98:F98) -> 220
A100: Active and Disconnected Accounts
A101: Disconnected Individual Accounts | C101: No | D101: =Mangochi!I101 -> 1796 | E101: ='Monkey Bay'!I101 -> 397 | F101: =Namwera!I101 -> 218 | H101: =SUM(D101:F101) -> 2411
A102: Disconnected institutional Accounts | C102: No | D102: =Mangochi!I102 -> 5 | E102: ='Monkey Bay'!I102 -> 0 | F102: =Namwera!I102 -> 7 | H102: =SUM(D102:F102) -> 12
A103: Disconnected Commercial/Industrial Accounts | C103: No | D103: =Mangochi!I103 -> 142 | E103: ='Monkey Bay'!I103 -> 0 | F103: =Namwera!I103 -> 2 | H103: =SUM(D103:F103) -> 144
A104: Disconnected CWP | C104: No | D104: =Mangochi!I104 -> 10 | E104: ='Monkey Bay'!I104 -> 0 | F104: =Namwera!I104 -> 5 | H104: =SUM(D104:F104) -> 15
A105: Total Disconnected Accounts | C105: No | D105: =SUM(D101:D104) -> 1953 | E105: =SUM(E101:E104) -> 397 | F105: =SUM(F101:F104) -> 232 | H105: =SUM(D105:F105) -> 2582
...

Sheet Midyear Summary
A1: SOUTHERN REGION WATER BOARD
A3: MONTHLY REPORTS - 2023/2024
A4: MANGOCHI ZONE
A5: MANGOCHI ZONE
A7: PARAMETERS | C7: UNITS | D7: Mangochi | E7: Monkey Bay | F7: Namwera | G7: Nkhudzi | H7: TOTALS
A8: PRODUCTION
A9: Volume Produced | C9: m3 | D9: =Mangochi!D9+Mangochi!E9+Mangochi!F9+Mangochi!G9+Mangochi!H9+Mangochi!I9 -> 765153 | E9: ='Monkey Bay'!D9+'Monkey Bay'!E9+'Monkey Bay'!F9+'Monkey Bay'!G9+'Monkey Bay'!H9+'Monkey Bay'!I9 -> 367807 | F9: =Namwera!D9+Namwera!E9+Namwera!F9+Namwera!G9+Namwera!H9+Namwera!I9 -> 32154 | H9: =SUM(D9:F9) -> 1165114
A10: REVENUE WATER - POSTPAID
A11: Volume Billed Individuals | C11: m3 | D11: =Mangochi!D11+Mangochi!E11+Mangochi!F11+Mangochi!G11+Mangochi!H11+Mangochi!I11 -> 346297 | E11: ='Monkey Bay'!D11+'Monkey Bay'!E11+'Monkey Bay'!F11+'Monkey Bay'!G11+'Monkey Bay'!H11+'Monkey Bay'!I11 -> 112336 | F11: =Namwera!D11+Namwera!E11+Namwera!F11+Namwera!G11+Namwera!H11+Namwera!I11 -> 11682 | H11: =SUM(D11:F11) -> 470315
A12: Volume Billed CWPs | C12: m3 | D12: =Mangochi!D12+Mangochi!E12+Mangochi!F12+Mangochi!G12+Mangochi!H12+Mangochi!I12 -> 0 | E12: ='Monkey Bay'!D12+'Monkey Bay'!E12+'Monkey Bay'!F12+'Monkey Bay'!G12+'Monkey Bay'!H12+'Monkey Bay'!I12 -> 0 | F12: =Namwera!D12+Namwera!E12+Namwera!F12+Namwera!G12+Namwera!H12+Namwera!I12 -> 0 | H12: =SUM(D12:F12) -> 0
A13: Volume Billed Institutions | C13: m3 | D13: =Mangochi!D13+Mangochi!E13+Mangochi!F13+Mangochi!G13+Mangochi!H13+Mangochi!I13 -> 1767 | E13: ='Monkey Bay'!D13+'Monkey Bay'!E13+'Monkey Bay'!F13+'Monkey Bay'!G13+'Monkey Bay'!H13+'Monkey Bay'!I13 -> 130055 | F13: =Namwera!D13+Namwera!E13+Namwera!F13+Namwera!G13+Namwera!H13+Namwera!I13 -> 83 | H13: =SUM(D13:F13) -> 131905
A14: Volume Billed Commercial/Industrial | C14: m3 | D14: =Mangochi!D14+Mangochi!E14+Mangochi!F14+Mangochi!G14+Mangochi!H14+Mangochi!I14 -> 681 | E14: ='Monkey Bay'!D14+'Monkey Bay'!E14+'Monkey Bay'!F14+'Monkey Bay'!G14+'Monkey Bay'!H14+'Monkey Bay'!I14 -> 10673 | F14: =Namwera!D14+Namwera!E14+Namwera!F14+Namwera!G14+Namwera!H14+Namwera!I14 -> 0 | H14: =SUM(D14:F14) -> 11354
A15: Total Volume Billed Post Paid | C15: m3 | D15: =SUM(D11:D14) -> 348745 | E15: =SUM(E11:E14) -> 253064 | F15: =SUM(F11:F14) -> 11765 | H15: =SUM(H11:H14) -> 613574
A16: REVENUE WATER - PREPAID
A17: Individuals | C17: m3 | D17: =Mangochi!D17+Mangochi!E17+Mangochi!F17+Mangochi!G17+Mangochi!H17+Mangochi!I17 -> 91025.5 | E17: ='Monkey Bay'!D17+'Monkey Bay'!E17+'Monkey Bay'!F17+'Monkey Bay'!G17+'Monkey Bay'!H17+'Monkey Bay'!I17 -> 17151 | F17: =Namwera!D17+Namwera!E17+Namwera!F17+Namwera!G17+Namwera!H17+Namwera!I17 -> 7489 | H17: =SUM(D17:F17) -> 115665.5
A18: CWPs | C18: m3 | D18: =Mangochi!D18+Mangochi!E18+Mangochi!F18+Mangochi!G18+Mangochi!H18+Mangochi!I18 -> 0 | E18: ='Monkey Bay'!D18+'Monkey Bay'!E18+'Monkey Bay'!F18+'Monkey Bay'!G18+'Monkey Bay'!H18+'Monkey Bay'!I18 -> 7309 | F18: =Namwera!D18+Namwera!E18+Namwera!F18+Namwera!G18+Namwera!H18+Namwera!I18 -> 7 | H18: =SUM(D18:F18) -> 7316
A19: Institutions | C19: m3 | D19: =Mangochi!D19+Mangochi!E19+Mangochi!F19+Mangochi!G19+Mangochi!H19+Mangochi!I19 -> 0 | E19: ='Monkey Bay'!D19+'Monkey Bay'!E19+'Monkey Bay'!F19+'Monkey Bay'!G19+'Monkey Bay'!H19+'Monkey Bay'!I19 -> 18110 | F19: =Namwera!D19+Namwera!E19+Namwera!F19+Namwera!G19+Namwera!H19+Namwera!I19 -> 2786 | H19: =SUM(D19:F19) -> 20896
A20: Commercial/Industrial | C20: m3 | D20: =Mangochi!D20+Mangochi!E20+Mangochi!F20+Mangochi!G20+Mangochi!H20+Mangochi!I20 -> 0 | E20: ='Monkey Bay'!D20+'Monkey Bay'!E20+'Monkey Bay'!F20+'Monkey Bay'!G20+'Monkey Bay'!H20+'Monkey Bay'!I20 -> 2669 | F20: =Namwera!D20+Namwera!E20+Namwera!F20+Namwera!G20+Namwera!H20+Namwera!I20 -> 224 | H20: =SUM(D20:F20) -> 2893
A21: Total Volume Prepaid | C21: m3 | D21: =SUM(D17:D20) -> 91025.5 | E21: =SUM(E17:E20) -> 45239 | F21: =SUM(F17:F20) -> 10506 | H21: =SUM(H17:H20) -> 146770.5
A22: TOTAL REVENUE WATER | C22: m3 | D22: =D21+D15 -> 439770.5 | E22: =E21+E15 -> 298303 | F22: =F21+F15 -> 22271 | H22: =H21+H15 -> 760344.5
A23: NON-REVENUE WATER (NRW)
A24: Non-Revenue Water (NRW) | B24: Volume | C24: m3 | D24: =D9-D22 -> 325382.5 | E24: =E9-E22 -> 69504 | F24: =F9-F22 -> 9883 | H24: =SUM(D24:F24) -> 404769.5
B25: Percentage | C25: % | D25: =D24/D9 -> 0.42525155 | E25: =E24/E9 -> 0.18896867 | F25: =F24/F9 -> 0.30736456 | H25: =H24/H9 -> 0.34740764
A26: OPERATING EXPENSES
A27: Chemicals
A28: Chemical | B28: Rate(MK/kg)
A29: Chlorine | B29: 7400 | C29: kg | D29: =Mangochi!D29+Mangochi!E29+Mangochi!F29+Mangochi!G29+Mangochi!H29+Mangochi!I29 -> 3185 | E29: ='Monkey Bay'!D29+'Monkey Bay'!E29+'Monkey Bay'!F29+'Monkey Bay'!G29+'Monkey Bay'!H29+'Monkey Bay'!I29 -> 915 | F29: =Namwera!D29+Namwera!E29+Namwera!F29+Namwera!G29+Namwera!H29+Namwera!I29 -> 76.5 | H29: =SUM(D29:F29) -> 4176.5
C30: kg/mg litre | D30: =D29/(D9/1000) -> 4.1625662 | E30: =E29/(E9/1000) -> 2.4877177 | F30: =F29/(F9/1000) -> 2.3791752 | H30: =H29/(H9/1000) -> 3.5846278
A31: Aluminium sulphate | B31: 1900 | C31: kg | D31: =Mangochi!D31+Mangochi!E31+Mangochi!F31+Mangochi!G31+Mangochi!H31+Mangochi!I31 -> 800 | E31: ='Monkey Bay'!D31+'Monkey Bay'!E31+'Monkey Bay'!F31+'Monkey Bay'!G31+'Monkey Bay'!H31+'Monkey Bay'!I31 -> 0 | F31: =Namwera!D31+Namwera!E31+Namwera!F31+Namwera!G31+Namwera!H31+Namwera!I31 -> 0 | H31: =SUM(D31:F31) -> 800
C32: kg/mg litre | D32: =D31/(D9/1000) -> 1.0455425 | E32: =E31/(E9/1000) -> 0 | F32: =F31/(F9/1000) -> 0 | H32: =H31/(H9/1000) -> 0.68662809
A33: Soda | B33: 1900 | C33: kg | D33: =Mangochi!D33+Mangochi!E33+Mangochi!F33+Mangochi!G33+Mangochi!H33+Mangochi!I33 -> 0 | E33: ='Monkey Bay'!D33+'Monkey Bay'!E33+'Monkey Bay'!F33+'Monkey Bay'!G33+'Monkey Bay'!H33+'Monkey Bay'!I33 -> 0 | F33: =Namwera!D33+Namwera!E33+Namwera!F33+Namwera!G33+Namwera!H33+Namwera!I33 -> 0 | H33: =SUM(D33:F33) -> 0
C34: kg/mg litre | D34: =D33/(D9/1000) -> 0 | E34: =E33/(E9/1000) -> 0 | F34: =F33/(F9/1000) -> 0 | H34: =H33/(H9/1000) -> 0
A35: Algae floc | B35: =745345.16/200 -> 3726.7258 | C35: litres | D35: =Mangochi!D35+Mangochi!E35+Mangochi!F35+Mangochi!G35+Mangochi!H35+Mangochi!I35 -> 0 | E35: ='Monkey Bay'!D35+'Monkey Bay'!E35+'Monkey Bay'!F35+'Monkey Bay'!G35+'Monkey Bay'!H35+'Monkey Bay'!I35 -> 0 | F35: =Namwera!D35+Namwera!E35+Namwera!F35+Namwera!G35+Namwera!H35+Namwera!I35 -> 0 | H35: =SUM(D35:F35) -> 0
C36: litres/mg litre | H36: =SUM(D36:F36) -> 0
A37: Sud floc | B37: =790318.72/200 -> 3951.5936 | C37: litres | D37: =Mangochi!D37+Mangochi!E37+Mangochi!F37+Mangochi!G37+Mangochi!H37+Mangochi!I37 -> 0 | E37: ='Monkey Bay'!D37+'Monkey Bay'!E37+'Monkey Bay'!F37+'Monkey Bay'!G37+'Monkey Bay'!H37+'Monkey Bay'!I37 -> 0 | F37: =Namwera!D37+Namwera!E37+Namwera!F37+Namwera!G37+Namwera!H37+Namwera!I37 -> 0 | H37: =SUM(D37:F37) -> 0
C38: litres/mg litre | D38: =D37/(D9/1000) -> 0 | E38: =E37/(E9/1000) -> 0 | F38: =F37/(F9/1000) -> 0 | H38: =H37/(H9/1000) -> 0
A39: Potasium permanganate | B39: 1950 | C39: kg | D39: =Mangochi!D39+Mangochi!E39+Mangochi!F39+Mangochi!G39+Mangochi!H39+Mangochi!I39 -> 0 | E39: ='Monkey Bay'!D39+'Monkey Bay'!E39+'Monkey Bay'!F39+'Monkey Bay'!G39+'Monkey Bay'!H39+'Monkey Bay'!I39 -> 0 | F39: =Namwera!D39+Namwera!E39+Namwera!F39+Namwera!G39+Namwera!H39+Namwera!I39 -> 0 | H39: =SUM(D39:F39) -> 0
C40: kg/mg litre | D40: =D39/(D9/1000) -> 0 | E40: =E39/(E9/1000) -> 0 | F40: =F39/(F9/1000) -> 0 | H40: =H39/(H9/1000) -> 0
A41: Cost of Chemicals | C41: Mk | D41: =(D29*$B29)+(D31*$B31)+(D33*$B33)+(D35*$B35)+(D37*$B37)+(D39*$B39) -> 25089000 | E41: =(E29*$B29)+(E31*$B31)+(E33*$B33)+(E35*$B35)+(E37*$B37)+(E39*$B39) -> 6771000 | F41: =(F29*$B29)+(F31*$B31)+(F33*$B33)+(F35*$B35)+(F37*$B37)+(F39*$B39) -> 566100 | H41: =SUM(D41:F41) -> 32426100
A42: Cost/vol. Produced (chemicals) | C42: Mk/m3 | D42: =D41/D9 -> 32.789521 | E42: =E41/E9 -> 18.409111 | F42: =F41/F9 -> 17.605897 | H42: =H41/H9 -> 27.830839
A43: Power
A44: Power Usage | C44: Kw | D44: =Mangochi!D44+Mangochi!E44+Mangochi!F44+Mangochi!G44+Mangochi!H44+Mangochi!I44 -> 305296.14 | E44: ='Monkey Bay'!D44+'Monkey Bay'!E44+'Monkey Bay'!F44+'Monkey Bay'!G44+'Monkey Bay'!H44+'Monkey Bay'!I44 -> 166018 | F44: =Namwera!D44+Namwera!E44+Namwera!F44+Namwera!G44+Namwera!H44+Namwera!I44 -> 23576 | H44: =SUM(D44:F44) -> 494890.14
A45: Power/ Vol. Produced | C45: Kw/m3 | D45: =D44/D9 -> 0.39900012 | E45: =E44/E9 -> 0.45137259 | F45: =F44/F9 -> 0.73322137 | H45: =H44/H9 -> 0.42475684
A46: Cost of Power | C46: Mk | D46: =Mangochi!D46+Mangochi!E46+Mangochi!F46+Mangochi!G46+Mangochi!H46+Mangochi!I46 -> 45305964 | E46: ='Monkey Bay'!D46+'Monkey Bay'!E46+'Monkey Bay'!F46+'Monkey Bay'!G46+'Monkey Bay'!H46+'Monkey Bay'!I46 -> 24764603 | F46: =Namwera!D46+Namwera!E46+Namwera!F46+Namwera!G46+Namwera!H46+Namwera!I46 -> 3610416.5 | H46: =SUM(D46:F46) -> 73680984
A47: Cost/vol. Produced | C47: Mk/m3 | D47: =D46/D9 -> 59.211641 | E47: =E46/E9 -> 67.330428 | F47: =F46/F9 -> 112.28514 | H47: =H46/H9 -> 63.239291
A48: Plant and Vehicle Maintenance
A49: Distances covered | C49: km | D49: =Mangochi!D49+Mangochi!E49+Mangochi!F49+Mangochi!G49+Mangochi!H49+Mangochi!I49 -> 31680 | E49: ='Monkey Bay'!D49+'Monkey Bay'!E49+'Monkey Bay'!F49+'Monkey Bay'!G49+'Monkey Bay'!H49+'Monkey Bay'!I49 -> 14902 | F49: =Namwera!D49+Namwera!E49+Namwera!F49+Namwera!G49+Namwera!H49+Namwera!I49 -> 690 | H49: =SUM(D49:F49) -> 47272
A50: Fuel Used (litres) | C50: litres | D50: =Mangochi!D50+Mangochi!E50+Mangochi!F50+Mangochi!G50+Mangochi!H50+Mangochi!I50 -> 5447.4 | E50: ='Monkey Bay'!D50+'Monkey Bay'!E50+'Monkey Bay'!F50+'Monkey Bay'!G50+'Monkey Bay'!H50+'Monkey Bay'!I50 -> 1138.7 | F50: =Namwera!D50+Namwera!E50+Namwera!F50+Namwera!G50+Namwera!H50+Namwera!I50 -> 715 | H50: =SUM(D50:F50) -> 7301.1
A51: Cost of fuel | C51: Mk | D51: =Mangochi!D51+Mangochi!E51+Mangochi!F51+Mangochi!G51+Mangochi!H51+Mangochi!I51 -> 10460160 | E51: ='Monkey Bay'!D51+'Monkey Bay'!E51+'Monkey Bay'!F51+'Monkey Bay'!G51+'Monkey Bay'!H51+'Monkey Bay'!I51 -> 2186692 | F51: =Namwera!D51+Namwera!E51+Namwera!F51+Namwera!G51+Namwera!H51+Namwera!I51 -> 1366640 | H51: =SUM(D51:F51) -> 14013492
A52: Maintenance | C52: Mk | D52: =Mangochi!D52+Mangochi!E52+Mangochi!F52+Mangochi!G52+Mangochi!H52+Mangochi!I52 -> 0 | E52: =Mangochi!E52+Mangochi!F52+Mangochi!G52+Mangochi!H52+Mangochi!I52+Mangochi!J52 -> 0 | F52: =Mangochi!F52+Mangochi!G52+Mangochi!H52+Mangochi!I52+Mangochi!J52+Mangochi!K52 -> 0 | H52: =SUM(D52:F52) -> 0
A53: Salaries and Wages
A54: Staff Costs | C54: MK | D54: =Mangochi!D54+Mangochi!E54+Mangochi!F54+Mangochi!G54+Mangochi!H54+Mangochi!I54 -> 80480295 | E54: ='Monkey Bay'!D54+'Monkey Bay'!E54+'Monkey Bay'!F54+'Monkey Bay'!G54+'Monkey Bay'!H54+'Monkey Bay'!I54 -> 21465983 | F54: =Namwera!D54+Namwera!E54+Namwera!F54+Namwera!G54+Namwera!H54+Namwera!I54 -> 11424667 | H54: =SUM(D54:F54) -> 1.1337094e+08
A55: Wages | C55: MK | D55: =Mangochi!D55+Mangochi!E55+Mangochi!F55+Mangochi!G55+Mangochi!H55+Mangochi!I55 -> 13259817 | E55: ='Monkey Bay'!D55+'Monkey Bay'!E55+'Monkey Bay'!F55+'Monkey Bay'!G55+'Monkey Bay'!H55+'Monkey Bay'!I55 -> 3951208.2 | F55: =Namwera!D55+Namwera!E55+Namwera!F55+Namwera!G55+Namwera!H55+Namwera!I55 -> 2350724.8 | H55: =SUM(D55:F55) -> 19561750
A56: Other Overhead Costs | C56: MK | D56: =Mangochi!D56+Mangochi!E56+Mangochi!F56+Mangochi!G56+Mangochi!H56+Mangochi!I56 -> 9186650 | E56: ='Monkey Bay'!D56+'Monkey Bay'!E56+'Monkey Bay'!F56+'Monkey Bay'!G56+'Monkey Bay'!H56+'Monkey Bay'!I56 -> 2577600 | F56: =Namwera!D56+Namwera!E56+Namwera!F56+Namwera!G56+Namwera!H56+Namwera!I56 -> 720650 | H56: =SUM(D56:F56) -> 12484900
A57: Operating Costs
A58: Total Operating Costs | C58: MK | D58: =D41+D46+D51+D52+D54+D55+D56 -> 1.8378189e+08 | E58: =E41+E46+E51+E52+E54+E55+E56 -> 61717086 | F58: =F41+F46+F51+F52+F54+F55+F56 -> 20039198 | H58: =SUM(D58:F58) -> 2.6553817e+08
A59: Cost/Vol. Produced | C59: Mk/m3 | D59: =D58/D9 -> 240.18972 | E59: =E58/E9 -> 167.79747 | F59: =F58/F9 -> 623.22567 | H59: =H58/H9 -> 227.90746
A60: Cost/Vol. Billed | C60: Mk/m3 | D60: =D58/D22 -> 417.90408 | E60: =E58/E22 -> 206.89395 | F60: =F58/F22 -> 899.78888 | H60: =H58/H22 -> 349.23403
A61: Permanent Staff Employed | C61: No | D61: =Mangochi!I61 -> 24 | E61: ='Monkey Bay'!I61 -> 7 | F61: =Namwera!I61 -> 3 | H61: =SUM(D61:F61) -> 34
A62: Staff/Vol.1000m3 of Volume Produced/hour (12 hour day) | C62: No/1000m3 | D62: =(D61*1000*31)/D9 -> 0.97235455 | E62: =(E61*1000*31)/E9 -> 0.58998333 | F62: =(F61*1000*31)/F9 -> 2.8923307 | H62: =(H61*1000*31)/H9 -> 0.90463251
A63: Temporary Staff Employed | C63: No | D63: =Mangochi!I63 -> 25 | E63: ='Monkey Bay'!I63 -> 9 | F63: =Namwera!I63 -> 6 | H63: =SUM(D63:F63) -> 40
A65: Water Connections and Disconnections
A66: New Individual Water Connections | B66: Brought Forward | C66: No | D66: =Mangochi!D66 -> 1052 | E66: ='Monkey Bay'!D66 -> 99 | F66: =Namwera!D66 -> 55 | H66: =SUM(D66:F66) -> 1206
B67: Applied this Month | C67: No | D67: =Mangochi!D67+Mangochi!E67+Mangochi!F67+Mangochi!G67+Mangochi!H67+Mangochi!I67 -> 625 | E67: ='Monkey Bay'!D67+'Monkey Bay'!E67+'Monkey Bay'!F67+'Monkey Bay'!G67+'Monkey Bay'!H67+'Monkey Bay'!I67 -> 90 | F67: =Namwera!D67+Namwera!E67+Namwera!F67+Namwera!G67+Namwera!H67+Namwera!I67 -> 36 | H67: =SUM(D67:F67) -> 751
B68: Done this Month Postpaid | C68: No | D68: =Mangochi!D68+Mangochi!E68+Mangochi!F68+Mangochi!G68+Mangochi!H68+Mangochi!I68 -> 7 | E68: ='Monkey Bay'!D68+'Monkey Bay'!E68+'Monkey Bay'!F68+'Monkey Bay'!G68+'Monkey Bay'!H68+'Monkey Bay'!I68 -> 0 | F68: =Namwera!D68+Namwera!E68+Namwera!F68+Namwera!G68+Namwera!H68+Namwera!I68 -> 0 | H68: =SUM(D68:F68) -> 7
B69: Done this Month Prepaid | C69: No | D69: =Mangochi!D69+Mangochi!E69+Mangochi!F69+Mangochi!G69+Mangochi!H69+Mangochi!I69 -> 225 | E69: ='Monkey Bay'!D69+'Monkey Bay'!E69+'Monkey Bay'!F69+'Monkey Bay'!G69+'Monkey Bay'!H69+'Monkey Bay'!I69 -> 71 | F69: =Namwera!D69+Namwera!E69+Namwera!F69+Namwera!G69+Namwera!H69+Namwera!I69 -> 40 | H69: =SUM(D69:F69) -> 336
B70: Total Done | C70: No | D70: =D68+D69 -> 232 | E70: =E68+E69 -> 71 | F70: =F68+F69 -> 40 | H70: =H68+H69 -> 343
B71: Carried Forward | C71: No | D71: =D66+D67-D70 -> 1445 | E71: =E66+E67-E70 -> 118 | F71: =F66+F67-F70 -> 51 | H71: =H66+H67-H70 -> 1614
A72: New Institutional Water Connections | B72: Brought Forward | C72: No | D72: =Mangochi!D72 -> 8 | E72: ='Monkey Bay'!D72 -> 0 | F72: =Namwera!D72 -> 3 | H72: =SUM(D72:F72) -> 11
B73: Applied this Month | C73: No | D73: =Mangochi!D73+Mangochi!E73+Mangochi!F73+Mangochi!G73+Mangochi!H73+Mangochi!I73 -> 0 | E73: ='Monkey Bay'!D73+'Monkey Bay'!E73+'Monkey Bay'!F73+'Monkey Bay'!G73+'Monkey Bay'!H73+'Monkey Bay'!I73 -> 0 | F73: =Namwera!D73+Namwera!E73+Namwera!F73+Namwera!G73+Namwera!H73+Namwera!I73 -> 0 | H73: =SUM(D73:F73) -> 0
B74: Done this Month Postpaid | C74: No | D74: =Mangochi!D74+Mangochi!E74+Mangochi!F74+Mangochi!G74+Mangochi!H74+Mangochi!I74 -> 0 | E74: ='Monkey Bay'!D74+'Monkey Bay'!E74+'Monkey Bay'!F74+'Monkey Bay'!G74+'Monkey Bay'!H74+'Monkey Bay'!I74 -> 0 | F74: =Namwera!D74+Namwera!E74+Namwera!F74+Namwera!G74+Namwera!H74+Namwera!I74 -> 0 | H74: =SUM(D74:F74) -> 0
B75: Done this Month Prepaid | C75: No | D75: =Mangochi!D75+Mangochi!E75+Mangochi!F75+Mangochi!G75+Mangochi!H75+Mangochi!I75 -> 0 | E75: ='Monkey Bay'!D75+'Monkey Bay'!E75+'Monkey Bay'!F75+'Monkey Bay'!G75+'Monkey Bay'!H75+'Monkey Bay'!I75 -> 0 | F75: =Namwera!D75+Namwera!E75+Namwera!F75+Namwera!G75+Namwera!H75+Namwera!I75 -> 0
B76: Total Done | C76: No | D76: =D74+D75 -> 0 | E76: =E74+E75 -> 0 | F76: =F74+F75 -> 0 | H76: =H74+H75 -> 0
B77: Carried Forward | C77: No | D77: =D73+D74-D76 -> 0 | E77: =E73+E74-E76 -> 0 | F77: =F73+F74-F76 -> 0 | H77: =H73+H74-H76 -> 0
A78: New Commercial/Industrial Water Connections | B78: Brought Forward | C78: No | D78: =Mangochi!D78 -> 9 | E78: ='Monkey Bay'!D78 -> 2 | F78: =Namwera!D78 -> 0 | H78: =SUM(D78:F78) -> 11
B79: Applied this Month | C79: No | D79: =Mangochi!D79+Mangochi!E79+Mangochi!F79+Mangochi!G79+Mangochi!H79+Mangochi!I79 -> 0 | E79: ='Monkey Bay'!D79+'Monkey Bay'!E79+'Monkey Bay'!F79+'Monkey Bay'!G79+'Monkey Bay'!H79+'Monkey Bay'!I79 -> 2 | F79: =Namwera!D79+Namwera!E79+Namwera!F79+Namwera!G79+Namwera!H79+Namwera!I79 -> 0 | H79: =SUM(D79:F79) -> 2
B80: Done this Month Postpaid | C80: No | D80: =Mangochi!D80+Mangochi!E80+Mangochi!F80+Mangochi!G80+Mangochi!H80+Mangochi!I80 -> 0 | E80: ='Monkey Bay'!D80+'Monkey Bay'!E80+'Monkey Bay'!F80+'Monkey Bay'!G80+'Monkey Bay'!H80+'Monkey Bay'!I80 -> 0 | F80: =Namwera!D80+Namwera!E80+Namwera!F80+Namwera!G80+Namwera!H80+Namwera!I80 -> 0
B81: Done this Month Prepaid | C81: No | D81: =Mangochi!D81+Mangochi!E81+Mangochi!F81+Mangochi!G81+Mangochi!H81+Mangochi!I81 -> 0 | E81: ='Monkey Bay'!D81+'Monkey Bay'!E81+'Monkey Bay'!F81+'Monkey Bay'!G81+'Monkey Bay'!H81+'Monkey Bay'!I81 -> 6 | F81: =Namwera!D81+Namwera!E81+Namwera!F81+Namwera!G81+Namwera!H81+Namwera!I81 -> 0 | H81: =SUM(D81:F81) -> 6
B82: Total Done | C82: No | D82: =D81+D80 -> 0 | E82: =E81+E80 -> 6 | F82: =F81+F80 -> 0 | H82: =H81+H80 -> 6
B83: Carried Forward | C83: No | D83: =D78+D79-D82 -> 9 | E83: =E78+E79-E82 -> -2 | F83: =F78+F79-F82 -> 0 | H83: =H78+H79-H82 -> 7
A84: New CWP | B84: Brought Forward | C84: No | D84: =Mangochi!D84 -> 0 | E84: ='Monkey Bay'!D84 -> 0 | F84: =Namwera!D84 -> 0 | H84: =SUM(D84:F84) -> 0
B85: Applied this Month | C85: No | D85: =Mangochi!D85+Mangochi!E85+Mangochi!F85+Mangochi!G85+Mangochi!H85+Mangochi!I85 -> 0 | E85: ='Monkey Bay'!D85+'Monkey Bay'!E85+'Monkey Bay'!F85+'Monkey Bay'!G85+'Monkey Bay'!H85+'Monkey Bay'!I85 -> 0 | F85: =Namwera!D85+Namwera!E85+Namwera!F85+Namwera!G85+Namwera!H85+Namwera!I85 -> 0 | H85: =SUM(D85:F85) -> 0
B86: Done this Month Postpaid | C86: No | D86: =Mangochi!D86+Mangochi!E86+Mangochi!F86+Mangochi!G86+Mangochi!H86+Mangochi!I86 -> 0 | E86: ='Monkey Bay'!D86+'Monkey Bay'!E86+'Monkey Bay'!F86+'Monkey Bay'!G86+'Monkey Bay'!H86+'Monkey Bay'!I86 -> 0 | F86: =Namwera!D86+Namwera!E86+Namwera!F86+Namwera!G86+Namwera!H86+Namwera!I86 -> 0
B87: Done this Month Prepaid | C87: No | D87: =Mangochi!D87+Mangochi!E87+Mangochi!F87+Mangochi!G87+Mangochi!H87+Mangochi!I87 -> 0 | E87: ='Monkey Bay'!D87+'Monkey Bay'!E87+'Monkey Bay'!F87+'Monkey Bay'!G87+'Monkey Bay'!H87+'Monkey Bay'!I87 -> 0 | F87: =Namwera!D87+Namwera!E87+Namwera!F87+Namwera!G87+Namwera!H87+Namwera!I87 -> 0 | H87: =SUM(D87:F87) -> 0
B88: Total Done | C88: No | D88: =D87+D86 -> 0 | E88: =E87+E86 -> 0 | F88: =F87+F86 -> 0
B89: Carried Forward | C89: No | D89: =D84+D85-D88 -> 0 | E89: =E84+E85-E88 -> 0 | F89: =F84+F85-F88 -> 0 | H89: =H84+H85-H86-H87 -> 0
A90: Aggregated New Water connections | B90: Brought Forward | C90: No | D90: =D66+D72+D78+D84 -> 1069 | E90: =E66+E72+E78+E84 -> 101 | F90: =F66+F72+F78+F84 -> 58 | H90: =SUM(D90:F90) -> 1228
B91: Applied this Month | C91: No | D91: =D67+D73+D79+D85 -> 625 | E91: =E67+E73+E79+E85 -> 92 | F91: =F67+F73+F79+F85 -> 36 | H91: =SUM(D91:F91) -> 753
B92: Done this Month Postpaid | C92: No | D92: =D68+D74+D80+D86 -> 7 | E92: =E68+E74+E80+E86 -> 0 | F92: =F68+F74+F80+F86 -> 0 | H92: =SUM(D92:F92) -> 7
B93: Done this Month Prepaid | D93: =D69+D75+D81+D87 -> 225 | E93: =E69+E75+E81+E87 -> 77 | F93: =F69+F75+F81+F87 -> 40 | H93: =SUM(D93:F93) -> 342
B94: Total Done | C94: No | D94: =D93+D92 -> 232 | E94: =E93+E92 -> 77 | F94: =F93+F92 -> 40 | H94: =H93+H92 -> 349
B95: Carried Forward | C95: No | D95: =D90+D91-D94 -> 1462 | E95: =E90+E91-E94 -> 116 | F95: =F90+F91-F94 -> 54 | H95: =H90+H91-H94 -> 1632
A97: Prepaid Metering
A98: Prepaid Meters Installed | C98: No | D98: =Mangochi!D98+Mangochi!E98+Mangochi!F98+Mangochi!G98+Mangochi!H98+Mangochi!I98 -> 236 | E98: ='Monkey Bay'!D98+'Monkey Bay'!E98+'Monkey Bay'!F98+'Monkey Bay'!G98+'Monkey Bay'!H98+'Monkey Bay'!I98 -> 77 | F98: =Namwera!D98+Namwera!E98+Namwera!F98+Namwera!G98+Namwera!H98+Namwera!I98 -> 40 | H98: =SUM(D98:F98) -> 353
A100: Active and Disconnected Accounts
A101: Disconnected Individual Accounts | C101: No | D101: =Mangochi!I101 -> 1796 | E101: ='Monkey Bay'!I101 -> 397 | F101: =Namwera!I101 -> 218 | H101: =SUM(D101:F101) -> 2411
A102: Disconnected institutional Accounts | C102: No | D102: =Mangochi!I102 -> 5 | E102: ='Monkey Bay'!I102 -> 0 | F102: =Namwera!I102 -> 7 | H102: =SUM(D102:F102) -> 12
A103: Disconnected Commercial/Industrial Accounts | C103: No | D103: =Mangochi!I103 -> 142 | E103: ='Monkey Bay'!I103 -> 0 | F103: =Namwera!I103 -> 2 | H103: =SUM(D103:F103) -> 144
A104: Disconnected CWP | C104: No | D104: =Mangochi!I104 -> 10 | E104: ='Monkey Bay'!I104 -> 0 | F104: =Namwera!I104 -> 5 | H104: =SUM(D104:F104) -> 15
A105: Total Disconnected Accounts | C105: No | D105: =SUM(D101:D104) -> 1953 | E105: =SUM(E101:E104) -> 397 | F105: =SUM(F101:F104) -> 232 | H105: =SUM(H101:H104) -> 2582
...

Sheet 3rd QTR
A1: SOUTHERN REGION WATER BOARD
A3: MONTHLY REPORTS - 2023/2024
A4: MANGOCHI ZONE
A5: MANGOCHI ZONE
A7: PARAMETERS | C7: UNITS | D7: Mangochi | E7: Monkey Bay | F7: Namwera | G7: Nkhudzi | H7: TOTALS
A8: PRODUCTION
A9: Volume Produced | C9: m3 | D9: =Mangochi!J9+Mangochi!K9+Mangochi!L9 -> 415428 | E9: ='Monkey Bay'!J9+'Monkey Bay'!K9+'Monkey Bay'!L9 -> 197172 | F9: =Namwera!J9+Namwera!K9+Namwera!L9 -> 14225 | G9: =Nkhudzi!J9+Nkhudzi!K9+Nkhudzi!L9 -> 10073.1 | H9: =SUM(D9:F9) -> 626825
A10: REVENUE WATER - POSTPAID
A11: Volume Billed Individuals | C11: m3 | D11: =Mangochi!J11+Mangochi!K11+Mangochi!L11 -> 185065 | E11: ='Monkey Bay'!J11+'Monkey Bay'!K11+'Monkey Bay'!L11 -> 71616 | F11: =Namwera!J11+Namwera!K11+Namwera!L11 -> 5863 | G11: =Nkhudzi!J11+Nkhudzi!K11+Nkhudzi!L11 -> 0 | H11: =SUM(D11:F11) -> 262544
A12: Volume Billed CWPs | C12: m3 | D12: =Mangochi!J12+Mangochi!K12+Mangochi!L12 -> 0 | E12: ='Monkey Bay'!J12+'Monkey Bay'!K12+'Monkey Bay'!L12 -> 0 | F12: =Namwera!J12+Namwera!K12+Namwera!L12 -> 0 | G12: =Nkhudzi!J12+Nkhudzi!K12+Nkhudzi!L12 -> 0 | H12: =SUM(D12:F12) -> 0
A13: Volume Billed Institutions | C13: m3 | D13: =Mangochi!J13+Mangochi!K13+Mangochi!L13 -> 844 | E13: ='Monkey Bay'!J13+'Monkey Bay'!K13+'Monkey Bay'!L13 -> 57253 | F13: =Namwera!J13+Namwera!K13+Namwera!L13 -> 38 | G13: =Nkhudzi!J13+Nkhudzi!K13+Nkhudzi!L13 -> 0 | H13: =SUM(D13:F13) -> 58135
A14: Volume Billed Commercial/Industrial | C14: m3 | D14: =Mangochi!J14+Mangochi!K14+Mangochi!L14 -> 230 | E14: ='Monkey Bay'!J14+'Monkey Bay'!K14+'Monkey Bay'!L14 -> 351 | F14: =Namwera!J14+Namwera!K14+Namwera!L14 -> 0 | G14: =Nkhudzi!J14+Nkhudzi!K14+Nkhudzi!L14 -> 0 | H14: =SUM(D14:F14) -> 581
A15: Total Volume Billed Post Paid | C15: m3 | D15: =SUM(D11:D14) -> 186139 | E15: =SUM(E11:E14) -> 129220 | F15: =SUM(F11:F14) -> 5901 | G15: =SUM(G11:G14) -> 0 | H15: =SUM(H11:H14) -> 321260
A16: REVENUE WATER - PREPAID
A17: Individuals | C17: m3 | D17: =Mangochi!J17+Mangochi!K17+Mangochi!L17 -> 52250.3 | E17: ='Monkey Bay'!J17+'Monkey Bay'!K17+'Monkey Bay'!L17 -> 17187 | F17: =Namwera!J17+Namwera!K17+Namwera!L17 -> 3553 | G17: =Nkhudzi!J17+Nkhudzi!K17+Nkhudzi!L17 -> 10073.1 | H17: =SUM(D17:F17) -> 72990.3
A18: CWPs | C18: m3 | D18: =Mangochi!J18+Mangochi!K18+Mangochi!L18 -> 0 | E18: ='Monkey Bay'!J18+'Monkey Bay'!K18+'Monkey Bay'!L18 -> 2240 | F18: =Namwera!J18+Namwera!K18+Namwera!L18 -> 0 | G18: =Nkhudzi!J18+Nkhudzi!K18+Nkhudzi!L18 -> 0 | H18: =SUM(D18:F18) -> 2240
A19: Institutions | C19: m3 | D19: =Mangochi!J19+Mangochi!K19+Mangochi!L19 -> 0 | E19: ='Monkey Bay'!J19+'Monkey Bay'!K19+'Monkey Bay'!L19 -> 7580 | F19: =Namwera!J19+Namwera!K19+Namwera!L19 -> 1599 | G19: =Nkhudzi!J19+Nkhudzi!K19+Nkhudzi!L19 -> 0 | H19: =SUM(D19:F19) -> 9179
A20: Commercial/Industrial | C20: m3 | D20: =Mangochi!J20+Mangochi!K20+Mangochi!L20 -> 0 | E20: ='Monkey Bay'!J20+'Monkey Bay'!K20+'Monkey Bay'!L20 -> 886 | F20: =Namwera!J20+Namwera!K20+Namwera!L20 -> 138 | G20: =Nkhudzi!J20+Nkhudzi!K20+Nkhudzi!L20 -> 0 | H20: =SUM(D20:F20) -> 1024
A21: Total Volume Prepaid | C21: m3 | D21: =SUM(D17:D20) -> 52250.3 | E21: =SUM(E17:E20) -> 27893 | F21: =SUM(F17:F20) -> 5290 | G21: =SUM(G17:G20) -> 10073.1 | H21: =SUM(H17:H20) -> 85433.3
A22: TOTAL REVENUE WATER | C22: m3 | D22: =D21+D15 -> 238389.3 | E22: =E21+E15 -> 157113 | F22: =F21+F15 -> 11191 | G22: =G21+G15 -> 10073.1 | H22: =H21+H15 -> 406693.3
A23: NON-REVENUE WATER (NRW)
A24: Non-Revenue Water (NRW) | B24: Volume | C24: m3 | D24: =D9-D22 -> 177038.7 | E24: =E9-E22 -> 40059 | F24: =F9-F22 -> 3034 | G24: =G9-G22 -> 0 | H24: =H9-H22 -> 220131.7
B25: Percentage | C25: % | D25: =D24/D9 -> 0.42615977 | E25: =E24/E9 -> 0.20316779 | F25: =F24/F9 -> 0.21328647 | G25: =G24/G9 -> 0 | H25: =H24/H9 -> 0.35118526
A26: OPERATING EXPENSES
A27: Chemicals
A28: Chemical | B28: Rate(MK/kg)
A29: Chlorine | B29: 7400 | C29: kg | D29: =Mangochi!J29+Mangochi!K29+Mangochi!L29 -> 1495 | E29: ='Monkey Bay'!J29+'Monkey Bay'!K29+'Monkey Bay'!L29 -> 465 | F29: =Namwera!J29+Namwera!K29+Namwera!L29 -> 46 | G29: =Nkhudzi!J29+Nkhudzi!K29+Nkhudzi!L29 -> 475 | H29: =SUM(D29:F29) -> 2006
C30: kg/mg litre | D30: =D29/(D9/1000) -> 3.5986982 | E30: =E29/(E9/1000) -> 2.358347 | F30: =F29/(F9/1000) -> 3.2337434 | G30: =G29/(G9/1000) -> 47.155295 | H30: =H29/(H9/1000) -> 3.2002553
A31: Aluminium sulphate | B31: 1900 | C31: kg | D31: =Mangochi!J31+Mangochi!K31+Mangochi!L31 -> 0 | E31: ='Monkey Bay'!J31+'Monkey Bay'!K31+'Monkey Bay'!L31 -> 0 | F31: =Namwera!J31+Namwera!K31+Namwera!L31 -> 0 | G31: =Nkhudzi!J31+Nkhudzi!K31+Nkhudzi!L31 -> 0 | H31: =SUM(D31:F31) -> 0
C32: kg/mg litre | D32: =D31/(D9/1000) -> 0 | E32: =E31/(E9/1000) -> 0 | F32: =F31/(F9/1000) -> 0 | G32: =Nkhudzi!J32+Nkhudzi!K32+Nkhudzi!L32 -> 0 | H32: =H31/(H9/1000) -> 0
A33: Soda | B33: 1900 | C33: kg | D33: =Mangochi!J33+Mangochi!K33+Mangochi!L33 -> 0 | E33: ='Monkey Bay'!J33+'Monkey Bay'!K33+'Monkey Bay'!L33 -> 0 | F33: =Namwera!J33+Namwera!K33+Namwera!L33 -> 0 | G33: =Nkhudzi!J33+Nkhudzi!K33+Nkhudzi!L33 -> 0 | H33: =SUM(D33:F33) -> 0
C34: kg/mg litre | D34: =D33/(D9/1000) -> 0 | E34: =E33/(E9/1000) -> 0 | F34: =F33/(F9/1000) -> 0 | G34: =Nkhudzi!J34+Nkhudzi!K34+Nkhudzi!L34 -> 0 | H34: =H33/(H9/1000) -> 0
A35: Algae floc | B35: =745345.16/200 -> 3726.7258 | C35: litres | D35: =Mangochi!J35+Mangochi!K35+Mangochi!L35 -> 0 | E35: ='Monkey Bay'!J35+'Monkey Bay'!K35+'Monkey Bay'!L35 -> 0 | F35: =Namwera!J35+Namwera!K35+Namwera!L35 -> 0 | G35: =Nkhudzi!J35+Nkhudzi!K35+Nkhudzi!L35 -> 0
C36: litres/mg litre | G36: =Nkhudzi!J36+Nkhudzi!K36+Nkhudzi!L36 -> 0
A37: Sud floc | B37: =790318.72/200 -> 3951.5936 | C37: litres | D37: =Mangochi!J37+Mangochi!K37+Mangochi!L37 -> 0 | E37: ='Monkey Bay'!J37+'Monkey Bay'!K37+'Monkey Bay'!L37 -> 0 | F37: =Namwera!J37+Namwera!K37+Namwera!L37 -> 0 | G37: =Nkhudzi!J37+Nkhudzi!K37+Nkhudzi!L37 -> 0 | H37: =SUM(D37:F37) -> 0
C38: litres/mg litre | D38: =D37/(D9/1000) -> 0 | E38: =E37/(E9/1000) -> 0 | F38: =F37/(F9/1000) -> 0 | G38: =Nkhudzi!J38+Nkhudzi!K38+Nkhudzi!L38 -> 0 | H38: =H37/(H9/1000) -> 0
A39: Potasium permanganate | B39: 1950 | C39: kg | D39: =Mangochi!J39+Mangochi!K39+Mangochi!L39 -> 0 | E39: ='Monkey Bay'!J39+'Monkey Bay'!K39+'Monkey Bay'!L39 -> 0 | F39: =Namwera!J39+Namwera!K39+Namwera!L39 -> 0 | G39: =Nkhudzi!J39+Nkhudzi!K39+Nkhudzi!L39 -> 0 | H39: =SUM(D39:F39) -> 0
C40: kg/mg litre | D40: =D39/(D9/1000) -> 0 | E40: =E39/(E9/1000) -> 0 | F40: =F39/(F9/1000) -> 0 | G40: =Nkhudzi!J40+Nkhudzi!K40+Nkhudzi!L40 -> 0 | H40: =H39/(H9/1000) -> 0
A41: Cost of Chemicals | C41: Mk | D41: =(D29*$B29)+(D31*$B31)+(D33*$B33)+(D35*$B35)+(D37*$B37)+(D39*$B39) -> 11063000 | E41: =(E29*$B29)+(E31*$B31)+(E33*$B33)+(E35*$B35)+(E37*$B37)+(E39*$B39) -> 3441000 | F41: =(F29*$B29)+(F31*$B31)+(F33*$B33)+(F35*$B35)+(F37*$B37)+(F39*$B39) -> 340400 | G41: =(G29*$B29)+(G31*$B31)+(G33*$B33)+(G35*$B35)+(G37*$B37)+(G39*$B39) -> 3515000 | H41: =SUM(D41:F41) -> 14844400
A42: Cost/vol. Produced (chemicals) | C42: Mk/m3 | D42: =D41/D9 -> 26.630367 | E42: =E41/E9 -> 17.451768 | F42: =F41/F9 -> 23.929701 | G42: =G41/G9 -> 348.94918 | H42: =H41/H9 -> 23.681889
A43: Power
A44: Power Usage | C44: Kw | D44: =Mangochi!J44+Mangochi!K44+Mangochi!L44 -> 148221.21 | E44: ='Monkey Bay'!J44+'Monkey Bay'!K44+'Monkey Bay'!L44 -> 88907 | F44: =Namwera!J44+Namwera!K44+Namwera!L44 -> 14664 | G44: =Nkhudzi!J44+Nkhudzi!K44+Nkhudzi!L44 -> 37905 | H44: =SUM(D44:F44) -> 251792.21
A45: Power/ Vol. Produced | C45: Kw/m3 | D45: =D44/D9 -> 0.35679157 | E45: =E44/E9 -> 0.45091088 | F45: =F44/F9 -> 1.0308612 | G45: =G44/G9 -> 3.7629925 | H45: =H44/H9 -> 0.40169459
A46: Cost of Power | C46: Mk | D46: =Mangochi!J46+Mangochi!K46+Mangochi!L46 -> 24837268 | E46: ='Monkey Bay'!J46+'Monkey Bay'!K46+'Monkey Bay'!L46 -> 14921267 | F46: =Namwera!J46+Namwera!K46+Namwera!L46 -> 2509507.9 | G46: =Nkhudzi!J46+Nkhudzi!K46+Nkhudzi!L46 -> 84742067 | H46: =SUM(D46:F46) -> 42268043
A47: Cost/vol. Produced | C47: Mk/m3 | D47: =D46/D9 -> 59.787179 | E47: =E46/E9 -> 75.676399 | F47: =F46/F9 -> 176.41532 | G47: =G46/G9 -> 8412.7098 | H47: =H46/H9 -> 67.431968
