Workbook

Sheet Mulanje
A1: SOUTHERN REGION WATER BOARD
A3: MONTHLY REPORTS - 2023/2024
A4: MULANJE ZONE
A5: MULANJE ZONE
A7: PARAMETERS | C7: UNITS | D7: APRIL | E7: MAY | F7: JUNE | G7: JULY | H7: AUGUST | I7: SEPTEMBER | J7: OCTOBER | K7: NOVEMBER | L7: DECEMBER | M7: JANUARY | N7: FEBRUARY | O7: MARCH | P7: TOTALS
A8: PRODUCTION
A9: Volume Produced | C9: m3 | D9: 43953 | E9: 41245 | F9: 41892 | G9: 39179 | H9: 52514 | I9: 43543 | J9: 44155 | K9: 44934 | L9: 45410 | M9: 45896 | N9: 43928 | O9: 51845 | P9: =SUM(D9:O9) -> 538494
A10: REVENUE WATER - POSTPAID
A11: Volume Billed Individuals | C11: m3 | D11: =1286+3748+14504 -> 19538 | E11: =1322+3787+15196 -> 20305 | F11: 20935 | G11: =1253+3719+14646 -> 19618 | H11: 20388 | I11: 22357 | J11: 22373 | K11: 22000 | L11: 21079 | M11: =1274+4377+17891 -> 23542 | N11: 20468 | O11: 39141 | P11: =SUM(D11:O11) -> 271744
A12: Volume Billed CWPs | C12: m3 | D12: 1143 | E12: 1047 | F12: 1140 | G12: 1021 | H12: 1030 | I12: 1108 | J12: 1178 | K12: 1200 | L12: 1175 | M12: 958 | N12: 946 | O12: 870 | P12: =SUM(D12:O12) -> 12816
A13: Volume Billed Institutions | C13: m3 | D13: 4078 | E13: 210 | F13: 230 | G13: 195 | H13: 202 | I13: 213 | J13: 241 | K13: 250 | L13: 191 | M13: 166 | N13: 220 | O13: 202 | P13: =SUM(D13:O13) -> 6398
A14: Volume Billed Commercial/Industrial | C14: m3 | D14: 48 | E14: 45 | F14: 52 | G14: 61 | H14: 55 | I14: 69 | J14: 64 | K14: 68 | L14: 79 | M14: 89 | N14: 83 | O14: 89 | P14: =SUM(D14:O14) -> 802
A15: Total Volume Billed Post Paid | C15: m3 | D15: =SUM(D11:D14) -> 24807 | E15: =SUM(E11:E14) -> 21607 | F15: =SUM(F11:F14) -> 22357 | G15: =SUM(G11:G14) -> 20895 | H15: =SUM(H11:H14) -> 21675 | I15: =SUM(I11:I14) -> 23747 | J15: =SUM(J11:J14) -> 23856 | K15: =SUM(K11:K14) -> 23518 | ... N15: =SUM(N11:N14) -> 21717 | O15: 40302 | P15: =SUM(P11:P14) -> 291760
A16: REVENUE WATER - PREPAID
A17: Individuals | C17: m3 | D17: 1856 | E17: 2120 | F17: 4154 | G17: 1736 | H17: 9567.1 | I17: =8146-6327 -> 1819 | J17: =8048.9-3607 -> 4441.9 | K17: 3500 | L17: 2896 | M17: 2998 | N17: 3162 | O17: 2822 | P17: =SUM(D17:O17) -> 41072
A18: CWPs | C18: m3 | D18: 65 | E18: 72 | F18: 110 | G18: 73 | H18: 162 | I18: 98 | J18: 127 | K18: 133 | L18: 141 | M18: 461 | N18: 427 | O18: 231 | P18: =SUM(D18:O18) -> 2100
A19: Institutions | C19: m3 | D19: 5022 | E19: =6753-2485 -> 4268 | F19: 5180 | G19: =5492-2007 -> 3485 | H19: 5051 | I19: 6055 | J19: =5+7+72+36+362+362+362+742+145+22+724+36+36+47+200 -> 3158 | K19: =7885-3333 -> 4552 | L19: 4620 | M19: 5450 | N19: 10505 | O19: 1449 | P19: =SUM(D19:O19) -> 58795
A20: Commercial/Industrial | C20: m3 | D20: =7058-6943 -> 115 | E20: 293 | F20: =9685-9444 -> 241 | G20: 198 | H20: 2841 | I20: 174 | J20: =17.7+37+46.5+46.5+17.5+23+116.3+17.7 -> 322.2 | K20: 416 | L20: 407 | M20: =9732.4-8909 -> 823.4 | N20: 1185 | O20: 486 | P20: =SUM(D20:O20) -> 7501.6
A21: Total Volume Prepaid | C21: m3 | D21: =SUM(D17:D20) -> 7058 | E21: =SUM(E17:E20) -> 6753 | F21: =SUM(F17:F20) -> 9685 | G21: =SUM(G17:G20) -> 5492 | H21: =SUM(H17:H20) -> 17621.1 | I21: =SUM(I17:I20) -> 8146 | J21: =SUM(J17:J20) -> 8049.1 | K21: =SUM(K17:K20) -> 8601 | ... N21: =SUM(N17:N20) -> 15279 | O21: 4988 | P21: =SUM(P17:P20) -> 109468.6
A22: TOTAL REVENUE WATER | C22: m3 | D22: =D21+D15 -> 31865 | E22: =E21+E15 -> 28360 | F22: =F21+F15 -> 32042 | G22: =G21+G15 -> 26387 | H22: =H21+H15 -> 39296.1 | I22: =I21+I15 -> 31893 | J22: =J21+J15 -> 31905.1 | K22: =K21+K15 -> 32119 | ... N22: =N21+N15 -> 36996 | O22: 45290 | P22: =P21+P15 -> 401228.6
A24: Non-Revenue Water (NRW) | B24: Volume | C24: m3 | D24: =D9-D22 -> 12088 | E24: =E9-E22 -> 12885 | F24: =F9-F22 -> 9850 | G24: =G9-G22 -> 12792 | H24: =H9-H22 -> 13217.9 | I24: =I9-I22 -> 11650 | J24: =J9-J22 -> 12249.9 | K24: =K9-K22 -> 12815 | ... N24: =N9-N22 -> 6932 | O24: 6555 | P24: =P9-P22 -> 137265.4
B25: Percentage | C25: % | D25: =D24/D9 -> 0.27502105 | E25: =E24/E9 -> 0.3124015 | F25: =F24/F9 -> 0.23512843 | G25: =G24/G9 -> 0.32650144 | H25: =H24/H9 -> 0.2517024 | I25: =I24/I9 -> 0.26755162 | J25: =J24/J9 -> 0.27742951 | K25: =K24/K9 -> 0.28519607 | ... N25: =N24/N9 -> 0.15780368 | O25: 0.12643456 | P25: =P24/P9 -> 0.25490609
A26: OPERATING EXPENSES
A27: Chemicals
A28: Chemical | B28: Rate(MK/kg)
A29: Chlorine | B29: 5111.67 | C29: kg | D29: 88 | E29: 87 | F29: 89 | G29: 96 | H29: 90 | I29: 93 | J29: 91 | K29: 93 | L29: 90 | M29: 88 | N29: 86 | O29: 88 | P29: =SUM(D29:O29) -> 1079
C30: kg/mg litre | D30: =D29/(D9/1000) -> 2.0021386 | E30: =E29/(E9/1000) -> 2.1093466 | F30: =F29/(F9/1000) -> 2.1245106 | G30: =G29/(G9/1000) -> 2.4502922 | H30: =H29/(H9/1000) -> 1.7138287 | I30: =I29/(I9/1000) -> 2.1358198 | J30: =J29/(J9/1000) -> 2.0609218 | K30: =K29/(K9/1000) -> 2.0697022 | L30: 1.9819423 | M30: =M29/(M9/1000) -> 1.9173784 | N30: =N29/(N9/1000) -> 1.957749 | O30: 1.6973672 | P30: =P29/(P9/1000) -> 2.0037363
A31: Aluminium sulphate | B31: 1537 | C31: kg | F31: 0 | P31: =SUM(D31:O31) -> 0
C32: kg/mg litre | D32: =D31/(D9/1000) -> 0 | E32: =E31/(E9/1000) -> 0 | F32: =F31/(F9/1000) -> 0 | G32: =G31/(G9/1000) -> 0 | H32: =H31/(H9/1000) -> 0 | I32: =I31/(I9/1000) -> 0 | J32: =J31/(J9/1000) -> 0 | K32: =K31/(K9/1000) -> 0 | ... N32: =N31/(N9/1000) -> 0 | O32: 0 | P32: =P31/(P9/1000) -> 0
A33: Soda | B33: 1781.02 | C33: kg | F33: 0 | P33: =SUM(D33:O33) -> 0
C34: kg/mg litre | D34: =D33/(D9/1000) -> 0 | E34: =E33/(E9/1000) -> 0 | F34: =F33/(F9/1000) -> 0 | G34: =G33/(G9/1000) -> 0 | H34: =H33/(H9/1000) -> 0 | I34: =I33/(I9/1000) -> 0 | J34: =J33/(J9/1000) -> 0 | K34: =K33/(K9/1000) -> 0 | ... N34: =N33/(N9/1000) -> 0 | O34: 0 | P34: =P33/(P9/1000) -> 0
A35: Algae floc | B35: 5979.95 | C35: litres | D35: 0 | F35: 0
C36: litres/mg litre
A37: Sud floc | B37: 5403.75 | C37: litres | D37: 0 | E37: 0 | F37: 0 | G37: 0 | H37: 0 | I37: 0 | J37: 0 | K37: 0 | L37: 0 | M37: 0 | N37: 0 | O37: 0 | P37: =SUM(D37:O37) -> 0
C38: litres/mg litre | D38: =D37/(D9/1000) -> 0 | E38: =E37/(E9/1000) -> 0 | F38: =F37/(F9/1000) -> 0 | G38: =G37/(G9/1000) -> 0 | H38: =H37/(H9/1000) -> 0 | I38: =I37/(I9/1000) -> 0 | J38: =J37/(J9/1000) -> 0 | K38: =K37/(K9/1000) -> 0 | ... N38: =N37/(N9/1000) -> 0 | O38: 0 | P38: =P37/(P9/1000) -> 0
A39: Potasium permanganate | B39: 1950 | C39: kg | D39: 0 | E39: 0 | F39: 0 | G39: 0 | H39: 0 | I39: 0 | J39: 0 | K39: 0 | L39: 0 | M39: 0 | N39: 0 | O39: 0 | P39: =SUM(D39:O39) -> 0
C40: kg/mg litre | D40: =D39/(D9/1000) -> 0 | E40: =E39/(E9/1000) -> 0 | F40: =F39/(F9/1000) -> 0 | G40: =G39/(G9/1000) -> 0 | H40: =H39/(H9/1000) -> 0 | I40: =I39/(I9/1000) -> 0 | J40: =J39/(J9/1000) -> 0 | K40: =K39/(K9/1000) -> 0 | ... N40: =N39/(N9/1000) -> 0 | O40: 0 | P40: =P39/(P9/1000) -> 0
A41: Cost of Chemicals | C41: Mk | D41: =(D29*$B29)+(D31*$B31)+(D33*$B33)+(D35*$B35)+(D37*$B37)+(D39*$B39) -> 449826.96 | E41: =(E29*$B29)+(E31*$B31)+(E33*$B33)+(E35*$B35)+(E37*$B37)+(E39*$B39) -> 444715.29 | F41: =(F29*$B29)+(F31*$B31)+(F33*$B33)+(F35*$B35)+(F37*$B37)+(F39*$B39) -> 454938.63 | G41: =(G29*$B29)+(G31*$B31)+(G33*$B33)+(G35*$B35)+(G37*$B37)+(G39*$B39) -> 490720.32 | H41: =(H29*$B29)+(H31*$B31)+(H33*$B33)+(H35*$B35)+(H37*$B37)+(H39*$B39) -> 460050.3 | I41: =(I29*$B29)+(I31*$B31)+(I33*$B33)+(I35*$B35)+(I37*$B37)+(I39*$B39) -> 475385.31 | J41: =(J29*$B29)+(J31*$B31)+(J33*$B33)+(J35*$B35)+(J37*$B37)+(J39*$B39) -> 465161.97 | K41: =(K29*$B29)+(K31*$B31)+(K33*$B33)+(K35*$B35)+(K37*$B37)+(K39*$B39) -> 475385.31 | ... N41: =(N29*$B29)+(N31*$B31)+(N33*$B33)+(N35*$B35)+(N37*$B37)+(N39*$B39) -> 439603.62 | O41: 449826.96 | P41: =SUM(D41:O41) -> 5515491.9
A42: Cost/vol. Produced (chemicals) | C42: Mk/m3 | D42: =D41/D9 -> 10.234272 | E42: =E41/E9 -> 10.782284 | F42: =F41/F9 -> 10.859797 | G42: =G41/G9 -> 12.525085 | H42: =H41/H9 -> 8.7605267 | I42: =I41/I9 -> 10.917606 | J42: =J41/J9 -> 10.534752 | K42: =K41/K9 -> 10.579635 | ... N42: =N41/N9 -> 10.007367 | O42: 8.6763808 | P42: =P41/P9 -> 10.242439
A43: Power
A44: Power Usage | C44: Kw | D44: 21 | E44: 17 | F44: 29 | G44: 37 | H44: 20 | I44: 29 | J44: 32 | K44: 28 | L44: 25 | M44: 34 | N44: 56 | O44: 55 | P44: =SUM(D44:O44) -> 383
A45: Power/ Vol. Produced | C45: Kw/m3 | D45: =D44/D9 -> 0.00047778309 | E45: =E44/E9 -> 0.00041217117 | F45: =F44/F9 -> 0.00069225628 | G45: =G44/G9 -> 0.00094438347 | H45: =H44/H9 -> 0.00038085082 | I45: =I44/I9 -> 0.00066600831 | J45: =J44/J9 -> 0.00072471974 | K45: =K44/K9 -> 0.00062313616 | ... N45: =N44/N9 -> 0.0012748133 | O45: 0.0010608545 | P45: =P44/P9 -> 0.00071124284
A46: Cost of Power | C46: Mk | D46: =122.92*D44 -> 2581.32 | E46: =122.92*E44 -> 2089.64 | F46: =122.92*F44 -> 3564.68 | G46: =122.92*G44 -> 4548.04 | H46: =122.92*H44 -> 2458.4 | I46: =122.92*I44 -> 3564.68 | J46: =1.165*(14100+(J44*119.1)) -> 20866.548 | K46: =1.165*(14100+(K44*119.1)) -> 20311.542 | L46: =1.165*(14100+(L44*119.1)) -> 19895.288 | M46: =1.165*(14100+(M44*119.1)) -> 21144.051 | N46: =1.165*(14100+(N44*119.1)) -> 24196.584 | O46: 24057.833 | P46: =SUM(D46:O46) -> 149278.61
A47: Cost/vol. Produced | C47: Mk/m3 | D47: =D46/D9 -> 0.058729097 | E47: =E46/E9 -> 0.05066408 | F47: =F46/F9 -> 0.085092142 | G47: =G46/G9 -> 0.11608362 | H47: =H46/H9 -> 0.046814183 | I47: =I46/I9 -> 0.081865742 | J47: =J46/J9 -> 0.47257497 | K47: =K46/K9 -> 0.45203058 | ... N47: =N46/N9 -> 0.55082371 | O47: 0.4640338 | P47: =P46/P9 -> 0.27721498
A48: Plant and Vehicle Maintenance
A49: Distances covered | C49: km | D49: 1684 | E49: 2342 | F49: 1997 | G49: 1142 | H49: 2878 | I49: 2067 | J49: 1645 | K49: 3050 | L49: 2174 | M49: 2581 | N49: 2207 | O49: 1622 | P49: =SUM(D49:O49) -> 25389
A50: Fuel Used (litres) | C50: litres | D50: 72 | E50: 204 | F50: 161 | G50: 85 | H50: 231 | I50: 179 | J50: 131 | K50: 271 | L50: 184 | M50: 196 | N50: 197 | O50: 135 | P50: =SUM(D50:O50) -> 2046
A51: Cost of fuel | C51: Mk | D51: 138240 | E51: 391680 | F51: 309120 | G51: 163200 | H51: 442867.2 | I51: =179*1920 -> 343680 | J51: 251020.8 | K51: 740914 | L51: 502372.5 | M51: 534551.68 | N51: 538598 | O51: 370019.56 | P51: =SUM(D51:O51) -> 4726263.7
A52: Maintenance | C52: Mk | D52: 0 | E52: 0 | F52: 0 | G52: 0 | H52: 0 | I52: 0 | J52: 0 | K52: 80000 | L52: 0 | M52: 0 | N52: 0 | O52: 0 | P52: =SUM(D52:O52) -> 80000
A53: Salaries and Wages
A54: Staff Costs | C54: MK | D54: 4350816.3 | E54: 4180816.4 | F54: 3984013.3 | G54: 4350816.3 | H54: 4350816.3 | I54: 4350816.3 | J54: 4350816.3 | K54: 4412963.8 | L54: 4854260.1 | M54: 8150816.3 | N54: 4350816.3 | O54: 9861113.5 | P54: =SUM(D54:O54) -> 61548881
A55: Wages | C55: MK | D55: 1218480.2 | E55: 1318480.2 | F55: 1237972.4 | G55: 1218480.2 | H55: 1218480.2 | I55: 1218480.2 | J55: 1218480.2 | K55: 1321486.3 | L55: 1581485 | M55: 1218480.2 | N55: 1218480.2 | O55: 1218480.2 | P55: =SUM(D55:O55) -> 15207266
A56: Other Overhead Costs | C56: MK | D56: 569840 | E56: 409487.33 | F56: 380620 | G56: 569840 | H56: 569840 | I56: 569840 | J56: 569840 | K56: 489971.54 | L56: 434249.26 | M56: 515975.2 | N56: 569840 | O56: 286980 | P56: =SUM(D56:O56) -> 5936323.3
A57: Operating Costs
A58: Total Operating Costs | C58: MK | D58: =D41+D46+D51+D52+D54+D55+D56 -> 6729784.8 | E58: =E41+E46+E51+E52+E54+E55+E56 -> 6747268.8 | F58: =F41+F46+F51+F52+F54+F55+F56 -> 6370229 | G58: =G41+G46+G51+G52+G54+G55+G56 -> 6797604.9 | H58: =H41+H46+H51+H52+H54+H55+H56 -> 7044512.5 | I58: =I41+I46+I51+I52+I54+I55+I56 -> 6961766.5 | J58: =J41+J46+J51+J52+J54+J55+J56 -> 6876185.9 | K58: =K41+K46+K51+K52+K54+K55+K56 -> 7541032.4 | ... N58: =N41+N46+N51+N52+N54+N55+N56 -> 7141534.8 | O58: 12210478 | P58: =SUM(D58:O58) -> 93163505
A59: Cost/Vol. Produced | C59: Mk/m3 | D59: =D58/D9 -> 153.11321 | E59: =E58/E9 -> 163.58998 | F59: =F58/F9 -> 152.06314 | G59: =G58/G9 -> 173.50124 | H59: =H58/H9 -> 134.14542 | I59: =I58/I9 -> 159.88257 | J59: =J58/J9 -> 155.72836 | K59: =K58/K9 -> 167.82464 | ... N59: =N58/N9 -> 162.57364 | O59: 235.51891 | P59: =P58/P9 -> 173.00751
A60: Cost/Vol. Billed | C60: Mk/m3 | D60: =D58/D22 -> 211.19676 | E60: =E58/E22 -> 237.91498 | F60: =F58/F22 -> 198.80872 | G60: =G58/G22 -> 257.61189 | H60: =H58/H22 -> 179.26747 | I60: =I58/I22 -> 218.2851 | J60: =J58/J22 -> 215.51996 | K60: =K58/K22 -> 234.78416 | ... N60: =N58/N22 -> 193.03532 | O60: 269.60649 | P60: =P58/P22 -> 232.19557
A61: Permanent Staff Employed | C61: No | D61: 12 | E61: 12 | F61: 12 | G61: 12 | H61: 12 | I61: 12 | J61: 12 | K61: 12 | L61: 12 | M61: 10 | N61: 10 | O61: 10 | P61: =O61 -> 10
A62: Staff/Vol.1000m3 of Volume Produced/hour (12 hour day) | C62: No/1000m3 | D62: =(D61*1000*31)/D9 -> 8.4635861 | E62: =(E61*1000*31)/E9 -> 9.0192751 | F62: =(F61*1000*31)/F9 -> 8.8799771 | G62: =(G61*1000*31)/G9 -> 9.4948825 | H62: =(H61*1000*31)/H9 -> 7.0838253 | I62: =(I61*1000*31)/I9 -> 8.5432791 | J62: =(J61*1000*31)/J9 -> 8.4248669 | K62: =(K61*1000*31)/K9 -> 8.2788089 | L62: 8.1920282 | M62: =(M61*1000*31)/M9 -> 6.7544013 | N62: =(N61*1000*31)/N9 -> 7.0570024 | O62: 5.9793616 | P62: =(P61*1000*31)/P9 -> 0.57567958
A63: Temporary Staff Employed | C63: No | D63: 27 | E63: 27 | F63: 27 | G63: 27 | H63: 27 | I63: 27 | J63: 27 | K63: 27 | L63: 27 | M63: 23 | N63: 23 | O63: 27 | P63: =SUM(D63:O63) -> 316
A65: Water Connections and Disconnections
A66: New Individual Water Connections | B66: Brought Forward | C66: No | D66: 589 | E66: =D71 -> 599 | F66: =E71 -> 583 | G66: =F71 -> 561 | H66: =G71 -> 544 | I66: =H71 -> 533 | J66: =I71 -> 501 | K66: =J71 -> 489 | L66: 475 | M66: 463 | N66: 468 | O66: 470 | P66: =D66 -> 589
B67: Applied this Month | C67: No | D67: 10 | E67: 8 | F67: 5 | G67: 4 | H67: 10 | I67: 6 | J67: 20 | K67: 15 | L67: 12 | M67: 18 | N67: 20 | O67: 11 | P67: =SUM(D67:O67) -> 139
B68: Done this Month Postpaid | C68: No | D68: 0 | E68: 24 | F68: 27 | G68: 21 | H68: 21 | I68: 38 | J68: 32 | K68: 29 | L68: 24 | M68: 12 | N68: 18 | O68: 22 | P68: =SUM(D68:O68) -> 268
B69: Done this Month Prepaid | C69: No | D69: 0 | E69: 0 | F69: 0 | G69: 0 | H69: 0 | I69: 0 | K69: 0 | L69: 0 | M69: 1 | N69: 0 | O69: 0 | P69: =SUM(D69:O69) -> 1
B70: Total Done | C70: No | D70: =D68+D69 -> 0 | E70: =E68+E69 -> 24 | F70: =F68+F69 -> 27 | G70: =G68+G69 -> 21 | H70: =H68+H69 -> 21 | I70: =I68+I69 -> 38 | J70: =J68+J69 -> 32 | K70: =K68+K69 -> 29 | L70: 24 | M70: =M68+M69 -> 13 | N70: 18 | O70: 22 | P70: =P68+P69 -> 269
B71: Carried Forward | C71: No | D71: =D66+D67-D70 -> 599 | E71: =E66+E67-E70 -> 583 | F71: =F66+F67-F70 -> 561 | G71: =G66+G67-G70 -> 544 | H71: =H66+H67-H70 -> 533 | I71: =I66+I67-I70 -> 501 | J71: =J66+J67-J70 -> 489 | K71: =K66+K67-K70 -> 475 | L71: 463 | M71: =M66+M67-M70 -> 468 | N71: 470 | O71: 459 | P71: =P66+P67-P70 -> 459
A72: New Institutional Water Connections | B72: Brought Forward | C72: No | D72: 1 | E72: =D77 -> 1 | F72: =E77 -> 1 | G72: =F77 -> 1 | H72: =G77 -> 1 | I72: =H77 -> 1 | J72: 1 | K72: =J77 -> 1 | L72: 1 | P72: =D72 -> 1
B73: Applied this Month | C73: No | D73: 0 | E73: 0 | F73: 0 | G73: 0 | H73: 0 | L73: 0 | P73: =SUM(D73:O73) -> 0
B74: Done this Month Postpaid | C74: No | D74: 0 | E74: 0 | F74: 0 | G74: 0 | H74: 0 | L74: 1 | P74: =SUM(D74:O74) -> 1
B75: Done this Month Prepaid | C75: No | D75: 0 | E75: 0 | F75: 0 | G75: 0 | H75: 0 | L75: 0 | P75: =SUM(D75:O75) -> 0
B76: Total Done | C76: No | D76: =D74+D75 -> 0 | E76: =E74+E75 -> 0 | F76: =F74+F75 -> 0 | G76: =G74+G75 -> 0 | H76: =H74+H75 -> 0 | I76: =I74+I75 -> 0 | J76: =J74+J75 -> 0 | K76: =K74+K75 -> 0 | L76: 1 | M76: =M74+M75 -> 0 | N76: =N74+N75 -> 0 | O76: 0 | P76: =P74+P75 -> 1
B77: Carried Forward | C77: No | D77: =D72+D73+D74-D76 -> 1 | E77: =E72+E73+E74-E76 -> 1 | F77: =F72+F73+F74-F76 -> 1 | G77: =G72+G73+G74-G76 -> 1 | H77: =H72+H73+H74-H76 -> 1 | I77: =I72+I73-I76 -> 1 | J77: 1 | K77: =K72+K73-K76 -> 1 | L77: 0 | M77: =M72+M73-M76 -> 0 | N77: =N72+N73-N76 -> 0 | O77: 0 | P77: =P72+P73-P76 -> 0
A78: New Commercial/Industrial Water Connections | B78: Brought Forward | C78: No | D78: 1 | E78: =D83 -> 1 | F78: =E83 -> 1 | G78: =F83 -> 1 | H78: =G83 -> 1 | I78: =H83 -> 1 | J78: =I83 -> 1 | K78: 1 | L78: 0 | P78: =D78 -> 1
B79: Applied this Month | C79: No | D79: 0 | E79: 4 | F79: 0 | G79: 2 | H79: 6 | K79: 1 | L79: 0 | P79: =SUM(D79:O79) -> 13
B80: Done this Month Postpaid | C80: No | D80: 0 | E80: 0 | F80: 0 | G80: 2 | H80: 6 | K80: 2 | L80: 0 | P80: =SUM(D80:O80) -> 10
B81: Done this Month Prepaid | C81: No | D81: 0 | E81: 4 | F81: 0 | G81: 0 | H81: 0 | L81: 0 | P81: =SUM(D81:O81) -> 4
B82: Total Done | C82: No | D82: =D81+D80 -> 0 | E82: =E81+E80 -> 4 | F82: =F81+F80 -> 0 | G82: =G81+G80 -> 2 | H82: =H81+H80 -> 6 | I82: =I80+I81 -> 0 | J82: =J80+J81 -> 0 | K82: =K80+K81 -> 2 | L82: 0 | M82: =M81+M80 -> 0 | N82: =N81+N80 -> 0 | O82: 0 | P82: =P81+P80 -> 14
B83: Carried Forward | C83: No | D83: =D78+D79-D82 -> 1 | E83: =E78+E79-E82 -> 1 | F83: =F78+F79-F82 -> 1 | G83: =G78+G79-G82 -> 1 | H83: =H78+H79-H82 -> 1 | I83: =I78+I79-I82 -> 1 | J83: =J78+J79-J82 -> 1 | K83: =K78+K79-K82 -> 0 | L83: 0 | M83: =M78+M79-M82 -> 0 | N83: =N78+N79-N82 -> 0 | O83: 0 | P83: =P78+P79-P82 -> 0
A84: New CWP | B84: Brought Forward | C84: No | D84: 0 | E84: =D89 -> 0 | F84: =E89 -> 0 | G84: =F89 -> 0 | H84: =G89 -> 0 | L84: 0 | P84: =D84 -> 0
B85: Applied this Month | C85: No | D85: 0 | E85: 0 | F85: 0 | G85: 0 | H85: 0 | K85: 2 | L85: 0 | P85: =SUM(D85:O85) -> 2
B86: Done this Month Postpaid | C86: No | D86: 0 | E86: 0 | F86: 0 | G86: 0 | H86: 0 | L86: 0 | P86: =SUM(D86:O86) -> 0
B87: Done this Month Prepaid | C87: No | D87: 0 | E87: 0 | F87: 0 | G87: 0 | H87: 0 | K87: 2 | L87: 0 | P87: =SUM(D87:O87) -> 2
B88: Total Done | C88: No | D88: =D86+D87 -> 0 | E88: =E86+E87 -> 0 | F88: =F86+F87 -> 0 | G88: =G86+G87 -> 0 | H88: =H86+H87 -> 0 | I88: =I86+I87 -> 0 | J88: =J86+J87 -> 0 | K88: =K86+K87 -> 2 | L88: 0 | M88: =M86+M87 -> 0 | N88: 0 | O88: 0 | P88: =SUM(D88:O88) -> 2
B89: Carried Forward | C89: No | D89: =D84+D85-D88 -> 0 | E89: =E84+E85-E88 -> 0 | F89: =F84+F85-F88 -> 0 | G89: =G84+G85-G88 -> 0 | H89: =H84+H85-H88 -> 0 | I89: =I84+I85-I88 -> 0 | J89: =J84+J85-J88 -> 0 | K89: =K84+K85-K88 -> 0 | L89: 0 | M89: =M84+M85-M88 -> 0 | N89: =N84+N85-N86-N87 -> 0 | O89: 0 | P89: =P84+P85-P86-P87 -> 0
A90: Aggregated New Water connections | B90: Brought Forward | C90: No | D90: =D66+D72+D78+D84 -> 591 | E90: =E66+E72+E78+E84 -> 601 | F90: =F66+F72+F78+F84 -> 585 | G90: =G66+G72+G78+G84 -> 563 | H90: =H66+H72+H78+H84 -> 546 | I90: =I66+I72+I78+I84 -> 535 | J90: =J66+J72+J78+J84 -> 503 | K90: =K66+K72+K78+K84 -> 491 | ... N90: =N66+N72+N78+N84 -> 468 | O90: 470 | P90: =D90 -> 591
B91: Applied this Month | C91: No | D91: =D67+D73+D79+D85 -> 10 | E91: =E67+E73+E79+E85 -> 12 | F91: =F67+F73+F79+F85 -> 5 | G91: =G67+G73+G79+G85 -> 6 | H91: =H67+H73+H79+H85 -> 16 | I91: =I67+I73+I79+I85 -> 6 | J91: =J67+J73+J79+J85 -> 20 | K91: =K67+K73+K79+K85 -> 18 | ... N91: =N67+N73+N79+N85 -> 20 | O91: 11 | P91: =SUM(D91:O91) -> 154
B92: Done this Month Postpaid | C92: No | D92: =D68+D74+D80+D86 -> 0 | E92: =E68+E74+E80+E86 -> 24 | F92: =F68+F74+F80+F86 -> 27 | G92: =G68+G74+G80+G86 -> 23 | H92: =H68+H74+H80+H86 -> 27 | I92: =I68+I74+I80+I86 -> 38 | J92: =J68+J74+J80+J86 -> 32 | K92: =K68+K74+K80+K86 -> 31 | ... N92: =N68+N74+N80+N86 -> 18 | O92: 22 | P92: =SUM(D92:O92) -> 279
B93: Done this Month Prepaid | D93: =D69+D75+D81+D87 -> 0 | E93: =E69+E75+E81+E87 -> 4 | F93: =F69+F75+F81+F87 -> 0 | G93: =G69+G75+G81+G87 -> 0 | H93: =H69+H75+H81+H87 -> 0 | I93: =I69+I75+I81+I87 -> 0 | J93: =J69+J75+J81+J87 -> 0 | K93: =K69+K75+K81+K87 -> 2 | ... N93: =N69+N75+N81+N87 -> 0 | O93: 0 | P93: =SUM(D93:O93) -> 7
B94: Total Done | C94: No | D94: =D93+D92 -> 0 | E94: =E93+E92 -> 28 | F94: =F93+F92 -> 27 | G94: =G93+G92 -> 23 | H94: =H93+H92 -> 27 | I94: =I93+I92 -> 38 | J94: =J93+J92 -> 32 | K94: =K93+K92 -> 33 | ... N94: =N93+N92 -> 18 | O94: 22 | P94: =P93+P92 -> 286
B95: Carried Forward | C95: No | D95: =D90+D91-D94 -> 601 | E95: =E90+E91-E94 -> 585 | F95: =F90+F91-F94 -> 563 | G95: =G90+G91-G94 -> 546 | H95: =H90+H91-H94 -> 535 | I95: =I90+I91-I94 -> 503 | J95: =J90+J91-J94 -> 491 | K95: =K90+K91-K94 -> 476 | ... N95: =N90+N91-N94 -> 470 | O95: 459 | P95: =P90+P91-P94 -> 459
A97: Prepaid Metering
A98: Prepaid Meters Installed | C98: No | D98: 0 | E98: 4 | F98: 1 | G98: 0 | H98: 0 | I98: 3 | J98: 1 | K98: 2 | L98: 1 | M98: 1 | P98: =SUM(D98:O98) -> 13
A100: Active and Disconnected Accounts
A101: Disconnected Individual Accounts | C101: No | D101: 657 | E101: 652 | F101: 638 | G101: 631 | H101: 623 | I101: 612 | J101: 673 | K101: 666 | L101: 664 | M101: 723 | N101: 688 | O101: 675 | P101: =O101 -> 675
A102: Disconnected institutional Accounts | C102: No | D102: 45 | E102: 45 | F102: 27 | G102: 45 | H102: 45 | I102: 45 | J102: 45 | K102: 45 | L102: 45 | M102: 45 | N102: 45 | O102: 46 | P102: =O102 -> 46
A103: Disconnected Commercial/Industrial Accounts | C103: No | D103: 82 | E103: 82 | F103: 7 | G103: 82 | H103: 82 | I103: 82 | J103: 82 | K103: 82 | L103: 82 | M103: 82 | N103: 82 | O103: 81 | P103: =O103 -> 81
A104: Disconnected CWP | C104: No | D104: 15 | E104: 15 | F104: 15 | G104: 15 | H104: 15 | I104: 15 | J104: 15 | K104: 15 | L104: 15 | M104: 15 | N104: 15 | O104: 15 | P104: =O104 -> 15
A105: Total Disconnected Accounts | C105: No | D105: =SUM(D101:D104) -> 799 | E105: =SUM(E101:E104) -> 794 | F105: =SUM(F101:F104) -> 687 | G105: =SUM(G101:G104) -> 773 | H105: =SUM(H101:H104) -> 765 | I105: =SUM(I101:I104) -> 754 | J105: =SUM(J101:J104) -> 815 | K105: =SUM(K101:K104) -> 808 | ... N105: =SUM(N101:N104) -> 830 | O105: 817 | P105: =O105 -> 817
A106: Postpaid Consumers
...

Sheet Luchenza
A1: SOUTHERN REGION WATER BOARD
A3: MONTHLY REPORTS - 2023/2024
A4: MULANJE ZONE
A5: MULANJE ZONE
A7: PARAMETERS | C7: UNITS | D7: APRIL | E7: MAY | F7: JUNE | G7: JULY | H7: AUGUST | I7: SEPTEMBER | J7: OCTOBER | K7: NOVEMBER | L7: DECEMBER | M7: JANUARY | N7: FEBRUARY | O7: MARCH | P7: TOTALS
A8: PRODUCTION
A9: Volume Produced | C9: m3 | D9: 14568 | E9: 14182 | F9: 16548 | G9: 16789 | H9: 18130 | I9: 17000 | J9: 19105 | K9: 17500 | L9: 19189 | M9: 16635 | N9: 16303 | O9: 15772 | P9: =SUM(D9:O9) -> 201721
A10: REVENUE WATER - POSTPAID
A11: Volume Billed Individuals | C11: m3 | D11: =756+1266+5487 -> 7509 | E11: =601+1401+4891 -> 6893 | F11: =655+1293+5174 -> 7122 | G11: =613+1197+5045 -> 6855 | H11: =664+928+4571 -> 6163 | I11: =659+1118+5665 -> 7442 | J11: 3352 | K11: =757+1235+5328 -> 7320 | L11: 7818 | M11: 7897 | N11: 7333 | O11: 6795 | P11: =SUM(D11:O11) -> 82499
A12: Volume Billed CWPs | C12: m3 | D12: 20 | E12: 23 | F12: 23 | G12: 32 | H12: 11 | I12: 10 | J12: 4 | K12: 14 | L12: 14 | M12: 7 | N12: 6 | O12: 7 | P12: =SUM(D12:O12) -> 171
A13: Volume Billed Institutions | C13: m3 | D13: 1093 | E13: 1249 | F13: 3956 | G13: 3585 | H13: 3350 | I13: 3802 | J13: 4986 | K13: 3034 | L13: 3477 | M13: 1455 | N13: 2265 | O13: 2705 | P13: =SUM(D13:O13) -> 34957
A14: Volume Billed Commercial/Industrial | C14: m3 | D14: 88 | E14: 99 | F14: 146 | G14: 174 | H14: 260 | I14: 184 | J14: 2976 | K14: 1700 | L14: 177 | M14: 147 | N14: 91 | O14: 194 | P14: =SUM(D14:O14) -> 6236
A15: Total Volume Billed Post Paid | C15: m3 | D15: =SUM(D11:D14) -> 8710 | E15: =SUM(E11:E14) -> 8264 | F15: =SUM(F11:F14) -> 11247 | G15: =SUM(G11:G14) -> 10646 | H15: =SUM(H11:H14) -> 9784 | I15: =SUM(I11:I14) -> 11438 | J15: =SUM(J11:J14) -> 11318 | K15: =SUM(K11:K14) -> 12068 | ... N15: =SUM(N11:N14) -> 9695 | O15: 9701 | P15: =SUM(P11:P14) -> 123863
A16: REVENUE WATER - PREPAID
A17: Individuals | C17: m3 | D17: 1066 | E17: =630+530 -> 1160 | F17: 920 | G17: 752 | H17: 1498 | I17: 524 | J17: 1170 | K17: 611 | L17: 640 | M17: 692 | N17: 723 | O17: 694 | P17: =SUM(D17:O17) -> 10450
A18: CWPs | C18: m3 | D18: 0 | E18: 0 | F18: 0 | G18: 0 | H18: 0 | I18: 0 | J18: 0 | K18: 0 | L18: 0 | N18: 0 | O18: 0 | P18: =SUM(D18:O18) -> 0
A19: Institutions | C19: m3 | D19: 1241 | E19: 230 | F19: 253 | G19: 745 | H19: 1624 | I19: 646 | J19: 384 | K19: 253 | L19: 521 | M19: 513 | N19: 2218 | O19: 387 | P19: =SUM(D19:O19) -> 9015
A20: Commercial/Industrial | C20: m3 | D20: =2433-2307 -> 126 | E20: =1862-1390 -> 472 | F20: =1447-1173 -> 274 | G20: 189 | H20: =3562-3120 -> 442 | I20: =177+92 -> 269 | J20: 293 | K20: =1228-1080 -> 148 | L20: 230 | M20: 229 | N20: 690 | O20: 31 | P20: =SUM(D20:O20) -> 3393
A21: Total Volume Prepaid | C21: m3 | D21: =SUM(D17:D20) -> 2433 | E21: =SUM(E17:E20) -> 1862 | F21: =SUM(F17:F20) -> 1447 | G21: =SUM(G17:G20) -> 1686 | H21: =SUM(H17:H20) -> 3564 | I21: =SUM(I17:I20) -> 1439 | J21: =SUM(J17:J20) -> 1847 | K21: =SUM(K17:K20) -> 1012 | ... N21: =SUM(N17:N20) -> 3631 | O21: 1112 | P21: =SUM(P17:P20) -> 22858
A22: TOTAL REVENUE WATER | C22: m3 | D22: =D21+D15 -> 11143 | E22: =E21+E15 -> 10126 | F22: =F21+F15 -> 12694 | G22: =G21+G15 -> 12332 | H22: =H21+H15 -> 13348 | I22: =I21+I15 -> 12877 | J22: =J21+J15 -> 13165 | K22: =K21+K15 -> 13080 | ... N22: =N21+N15 -> 13326 | O22: 10813 | P22: =P21+P15 -> 146721
A24: Non-Revenue Water (NRW) | B24: Volume | C24: m3 | D24: =D9-D22 -> 3425 | E24: =E9-E22 -> 4056 | F24: =F9-F22 -> 3854 | G24: =G9-G22 -> 4457 | H24: =H9-H22 -> 4782 | I24: =I9-I22 -> 4123 | J24: =J9-J22 -> 5940 | K24: =K9-K22 -> 4420 | ... N24: =N9-N22 -> 2977 | O24: 4959 | P24: =P9-P22 -> 55000
B25: Percentage | C25: % | D25: =D24/D9 -> 0.23510434 | E25: =E24/E9 -> 0.28599633 | F25: =F24/F9 -> 0.23289824 | G25: =G24/G9 -> 0.26547144 | H25: =H24/H9 -> 0.26376172 | I25: =I24/I9 -> 0.24252941 | J25: =J24/J9 -> 0.31091337 | K25: =K24/K9 -> 0.25257143 | ... N25: =N24/N9 -> 0.18260443 | O25: 0.31441796 | P25: =P24/P9 -> 0.27265381
A26: OPERATING EXPENSES
A27: Chemicals
A28: Chemical | B28: Rate(MK/kg)
A29: Chlorine | B29: 5111.67 | C29: kg | D29: 50 | E29: 50 | F29: 50 | G29: 49 | H29: 39 | I29: 35 | J29: 42 | K29: 42 | L29: 40 | M29: 39 | N29: 41 | O29: 40 | P29: =SUM(D29:O29) -> 517
C30: kg/mg litre | D30: =D29/(D9/1000) -> 3.4321801 | E30: =E29/(E9/1000) -> 3.5255958 | F30: =F29/(F9/1000) -> 3.0215132 | G30: =G29/(G9/1000) -> 2.9185776 | H30: =H29/(H9/1000) -> 2.1511307 | I30: =I29/(I9/1000) -> 2.0588235 | J30: =J29/(J9/1000) -> 2.1983774 | K30: =K29/(K9/1000) -> 2.4 | L30: 2.0845276 | M30: =M29/(M9/1000) -> 2.3444545 | N30: =N29/(N9/1000) -> 2.5148746 | O30: 2.53614 | P30: =P29/(P9/1000) -> 2.5629459
A31: Aluminium sulphate | B31: 1537 | C31: kg | P31: =SUM(D31:O31) -> 0
C32: kg/mg litre | D32: =D31/(D9/1000) -> 0 | E32: =E31/(E9/1000) -> 0 | F32: =F31/(F9/1000) -> 0 | G32: =G31/(G9/1000) -> 0 | H32: =H31/(H9/1000) -> 0 | I32: =I31/(I9/1000) -> 0 | J32: =J31/(J9/1000) -> 0 | K32: =K31/(K9/1000) -> 0 | ... N32: =N31/(N9/1000) -> 0 | O32: 0 | P32: =P31/(P9/1000) -> 0
A33: Soda | B33: 1781.02 | C33: kg | P33: =SUM(D33:O33) -> 0
C34: kg/mg litre | D34: =D33/(D9/1000) -> 0 | E34: =E33/(E9/1000) -> 0 | F34: =F33/(F9/1000) -> 0 | G34: =G33/(G9/1000) -> 0 | H34: =H33/(H9/1000) -> 0 | I34: =I33/(I9/1000) -> 0 | J34: =J33/(J9/1000) -> 0 | K34: =K33/(K9/1000) -> 0 | ... N34: =N33/(N9/1000) -> 0 | O34: 0 | P34: =P33/(P9/1000) -> 0
A35: Algae floc | B35: 5979.95 | C35: litres | D35: 0
C36: litres/mg litre
A37: Sud floc | B37: 5403.75 | C37: litres | D37: 0 | E37: 0 | F37: 0 | G37: 0 | H37: 0 | I37: 0 | J37: 0 | K37: 0 | L37: 0 | M37: 0 | N37: 0 | O37: 0 | P37: =SUM(D37:O37) -> 0
C38: litres/mg litre | D38: =D37/(D9/1000) -> 0 | E38: =E37/(E9/1000) -> 0 | F38: =F37/(F9/1000) -> 0 | G38: =G37/(G9/1000) -> 0 | H38: =H37/(H9/1000) -> 0 | I38: =I37/(I9/1000) -> 0 | J38: =J37/(J9/1000) -> 0 | K38: =K37/(K9/1000) -> 0 | ... N38: =N37/(N9/1000) -> 0 | O38: 0 | P38: =P37/(P9/1000) -> 0
A39: Potasium permanganate | B39: 1950 | C39: kg | D39: 0 | E39: 0 | F39: 0 | G39: 0 | H39: 0 | I39: 0 | J39: 0 | K39: 0 | L39: 0 | M39: 0 | N39: 0 | O39: 0 | P39: =SUM(D39:O39) -> 0
C40: kg/mg litre | D40: =D39/(D9/1000) -> 0 | E40: =E39/(E9/1000) -> 0 | F40: =F39/(F9/1000) -> 0 | G40: =G39/(G9/1000) -> 0 | H40: =H39/(H9/1000) -> 0 | I40: =I39/(I9/1000) -> 0 | J40: =J39/(J9/1000) -> 0 | K40: =K39/(K9/1000) -> 0 | ... N40: =N39/(N9/1000) -> 0 | O40: 0 | P40: =P39/(P9/1000) -> 0
A41: Cost of Chemicals | C41: Mk | D41: =(D29*$B29)+(D31*$B31)+(D33*$B33)+(D35*$B35)+(D37*$B37)+(D39*$B39) -> 255583.5 | E41: =(E29*$B29)+(E31*$B31)+(E33*$B33)+(E35*$B35)+(E37*$B37)+(E39*$B39) -> 255583.5 | F41: =(F29*$B29)+(F31*$B31)+(F33*$B33)+(F35*$B35)+(F37*$B37)+(F39*$B39) -> 255583.5 | G41: =(G29*$B29)+(G31*$B31)+(G33*$B33)+(G35*$B35)+(G37*$B37)+(G39*$B39) -> 250471.83 | H41: =(H29*$B29)+(H31*$B31)+(H33*$B33)+(H35*$B35)+(H37*$B37)+(H39*$B39) -> 199355.13 | I41: =(I29*$B29)+(I31*$B31)+(I33*$B33)+(I35*$B35)+(I37*$B37)+(I39*$B39) -> 178908.45 | J41: =(J29*$B29)+(J31*$B31)+(J33*$B33)+(J35*$B35)+(J37*$B37)+(J39*$B39) -> 214690.14 | K41: =(K29*$B29)+(K31*$B31)+(K33*$B33)+(K35*$B35)+(K37*$B37)+(K39*$B39) -> 214690.14 | ... N41: =(N29*$B29)+(N31*$B31)+(N33*$B33)+(N35*$B35)+(N37*$B37)+(N39*$B39) -> 209578.47 | O41: 204466.8 | P41: =SUM(D41:O41) -> 2642733.4
A42: Cost/vol. Produced (chemicals) | C42: Mk/m3 | D42: =D41/D9 -> 17.544172 | E42: =E41/E9 -> 18.021682 | F42: =F41/F9 -> 15.444978 | G42: =G41/G9 -> 14.918806 | H42: =H41/H9 -> 10.99587 | I42: =I41/I9 -> 10.524026 | J42: =J41/J9 -> 11.23738 | K42: =K41/K9 -> 12.268008 | ... N42: =N41/N9 -> 12.855209 | O42: 12.963911 | P42: =P41/P9 -> 13.100933
A43: Power
A44: Power Usage | C44: Kw | D44: 7392 | E44: 8345 | F44: 9368 | G44: 9345 | H44: 6080 | I44: 7251 | J44: 12487 | K44: 8789 | L44: 10886 | M44: 9473 | N44: 8766 | O44: 8157 | P44: =SUM(D44:O44) -> 106339
A45: Power/ Vol. Produced | C45: Kw/m3 | D45: =D44/D9 -> 0.50741351 | E45: =E44/E9 -> 0.58842194 | F45: =F44/F9 -> 0.56611071 | G45: =G44/G9 -> 0.55661445 | H45: =H44/H9 -> 0.33535576 | I45: =I44/I9 -> 0.42652941 | J45: =J44/J9 -> 0.65359853 | K45: =K44/K9 -> 0.50222857 | L45: 0.56730418 | M45: =M44/M9 -> 0.56946198 | N45: =N44/N9 -> 0.53769245 | O45: 0.51718235 | P45: =P44/P9 -> 0.5271588
A46: Cost of Power | C46: Mk | D46: =1.165*(14100+(D44*119.1)) -> 1042077.6 | E46: =1.165*(14100+(E44*119.1)) -> 1174307.8 | F46: =1.165*(14100+(F44*119.1)) -> 1316250.6 | G46: =1.165*(14100+(G44*119.1)) -> 1313059.3 | H46: =1.165*(14100+(H44*119.1)) -> 860035.62 | I46: 891292.92 | J46: =1.165*(14100+(J44*119.1)) -> 1749016.5 | K46: =1.165*(14100+(K44*119.1)) -> 1235913.4 | L46: =1.165*(14100+(L44*119.1)) -> 1526875.3 | M46: =1.165*(14100+(M44*119.1)) -> 1330819.5 | N46: =1.165*(14100+(N44*119.1)) -> 1232722.1 | O46: 1148222.5 | P46: =SUM(D46:O46) -> 14820593
A47: Cost/vol. Produced | C47: Mk/m3 | D47: =D46/D9 -> 71.53196 | E47: =E46/E9 -> 82.802691 | F47: =F46/F9 -> 79.541368 | G47: =G46/G9 -> 78.209498 | H47: =H46/H9 -> 47.437155 | I47: =I46/I9 -> 52.428995 | J47: =J46/J9 -> 91.547578 | K47: =K46/K9 -> 70.623625 | ... N47: =N46/N9 -> 75.613209 | O47: 72.801324 | P47: =P46/P9 -> 73.470749
A48: Plant and Vehicle Maintenance
A49: Distances covered | C49: km | D49: 0 | E49: 0 | F49: 0 | G49: 0 | P49: =SUM(D49:O49) -> 0
A50: Fuel Used (litres) | C50: litres | D50: 0 | E50: 0 | F50: 0 | G50: 0 | P50: =SUM(D50:O50) -> 0
A51: Cost of fuel | C51: Mk | D51: 0 | E51: 0 | F51: 0 | G51: 0 | P51: =SUM(D51:O51) -> 0
A52: Maintenance | C52: Mk | D52: 0 | E52: 0 | F52: 0 | G52: 0 | H52: 0 | I52: 0 | J52: 0 | K52: 0 | L52: 0 | M52: 0 | N52: 0 | O52: 0 | P52: =SUM(D52:O52) -> 0
A53: Salaries and Wages
A54: Staff Costs | C54: MK | D54: 3430711.6 | E54: 4211831.3 | F54: 3379844.5 | G54: =AVERAGE(D54:F54) -> 3674129.1 | H54: 3522179.2 | I54: =AVERAGE(D54:H54) -> 3643739.2 | J54: 3591772.4 | K54: 3684749.7 | L54: 3021763.2 | M54: 5899475.6 | O54: 4898086 | P54: =SUM(D54:O54) -> 42958282
A55: Wages | C55: MK | D55: 1207512.4 | E55: 1287617.9 | F55: 1218619.2 | G55: =AVERAGE(D55:F55) -> 1237916.5 | H55: 1238975.4 | I55: 1199872.2 | J55: 1203875.9 | K55: 1218319.7 | L55: 1058794.7 | M55: 1170215.6 | O55: 1375759 | P55: =SUM(D55:O55) -> 13417479
A56: Other Overhead Costs | C56: MK | D56: 761702.12 | E56: 596817 | F56: 524678 | G56: 327821.34 | H56: =AVERAGE(D56:G56) -> 552754.61 | I56: 491650.21 | J56: 411741.95 | K56: 395200 | L56: 695940 | M56: 498633.04 | O56: 429250 | P56: =SUM(D56:O56) -> 5686188.3
A57: Operating Costs
A58: Total Operating Costs | C58: MK | D58: =D41+D46+D51+D52+D54+D55+D56 -> 6697587.2 | E58: =E41+E46+E51+E52+E54+E55+E56 -> 7526157.4 | F58: =F41+F46+F51+F52+F54+F55+F56 -> 6694975.8 | G58: =G41+G46+G51+G52+G54+G55+G56 -> 6803398.1 | H58: =H41+H46+H51+H52+H54+H55+H56 -> 6373300 | I58: =I41+I46+I51+I52+I54+I55+I56 -> 6405462.9 | J58: =J41+J46+J51+J52+J54+J55+J56 -> 7171096.9 | K58: =K41+K46+K51+K52+K54+K55+K56 -> 6748872.9 | ... N58: =N41+N46+N51+N52+N54+N55+N56 -> 1442300.6 | O58: 8055784.3 | P58: =SUM(D58:O58) -> 79525275
A59: Cost/Vol. Produced | C59: Mk/m3 | D59: =D58/D9 -> 459.74651 | E59: =E58/E9 -> 530.68378 | F59: =F58/F9 -> 404.57915 | G59: =G58/G9 -> 405.2295 | H59: =H58/H9 -> 351.53337 | I59: =I58/I9 -> 376.79194 | J59: =J58/J9 -> 375.35184 | K59: =K58/K9 -> 385.64988 | ... N59: =N58/N9 -> 88.468418 | O59: 510.76492 | P59: =P58/P9 -> 394.23399
A60: Cost/Vol. Billed | C60: Mk/m3 | D60: =D58/D22 -> 601.05781 | E60: =E58/E22 -> 743.25078 | F60: =F58/F22 -> 527.41262 | G60: =G58/G22 -> 551.68651 | H60: =H58/H22 -> 477.47228 | I60: =I58/I22 -> 497.43441 | J60: =J58/J22 -> 544.70922 | K60: =K58/K22 -> 515.96888 | ... N60: =N58/N22 -> 108.23207 | O60: 745.00918 | P60: =P58/P22 -> 542.01699
A61: Permanent Staff Employed | C61: No | D61: 8 | E61: 8 | F61: 8 | G61: 8 | H61: 8 | I61: 8 | J61: 8 | K61: 8 | L61: 7 | M61: 7 | N61: 7 | O61: 8 | P61: =O61 -> 8
A62: Staff/Vol.1000m3 of Volume Produced/hour (12 hour day) | C62: No/1000m3 | D62: =(D61*1000*31)/D9 -> 17.023613 | E62: =(E61*1000*31)/E9 -> 17.486955 | F62: =(F61*1000*31)/F9 -> 14.986705 | G62: =(G61*1000*31)/G9 -> 14.771577 | H62: =(H61*1000*31)/H9 -> 13.678985 | I62: =(I61*1000*31)/I9 -> 14.588235 | J62: =(J61*1000*31)/J9 -> 12.980895 | K62: =(K61*1000*31)/K9 -> 14.171429 | L62: 11.308562 | M62: =(M61*1000*31)/M9 -> 13.044785 | N62: =(N61*1000*31)/N9 -> 13.310434 | O62: 15.724068 | P62: =(P61*1000*31)/P9 -> 1.2294208
A63: Temporary Staff Employed | C63: No | D63: 12 | E63: 12 | F63: 17 | G63: 17 | H63: 17 | I63: 17 | J63: 13 | K63: 13 | L63: 13 | M63: 13 | N63: 13 | O63: 13 | P63: =SUM(D63:O63) -> 170
A65: Water Connections and Disconnections
A66: New Individual Water Connections | B66: Brought Forward | C66: No | D66: 10 | E66: =D71 -> 16 | F66: =E71 -> 27 | G66: =F71 -> 26 | H66: =G71 -> 30 | I66: =H71 -> 45 | J66: =I71 -> 38 | K66: =J71 -> 51 | L66: 36 | M66: 46 | N66: 44 | O66: 42 | P66: =D66 -> 10
B67: Applied this Month | C67: No | D67: 15 | E67: 20 | F67: 8 | G67: 20 | H67: 30 | I67: 20 | J67: 25 | K67: 0 | L67: 20 | M67: 8 | N67: 10 | O67: 15 | P67: =SUM(D67:O67) -> 191
B68: Done this Month Postpaid | C68: No | D68: 9 | E68: 9 | F68: 9 | G68: 16 | H68: 15 | I68: 27 | J68: 12 | K68: 15 | L68: 10 | M68: 10 | N68: 12 | O68: 12 | P68: =SUM(D68:O68) -> 156
B69: Done this Month Prepaid | C69: No | D69: 0 | E69: 0 | F69: 0 | G69: 0 | H69: 0 | I69: 0 | K69: 0 | L69: 0 | M69: 0 | N69: 0 | O69: 0 | P69: =SUM(D69:O69) -> 0
B70: Total Done | C70: No | D70: =D68+D69 -> 9 | E70: =E68+E69 -> 9 | F70: =F68+F69 -> 9 | G70: =G68+G69 -> 16 | H70: =H68+H69 -> 15 | I70: =I68+I69 -> 27 | J70: =J68+J69 -> 12 | K70: =K68+K69 -> 15 | L70: 10 | M70: 10 | N70: 12 | O70: 12 | P70: =P68+P69 -> 156
B71: Carried Forward | C71: No | D71: =D66+D67-D70 -> 16 | E71: =E66+E67-E70 -> 27 | F71: =F66+F67-F70 -> 26 | G71: =G66+G67-G70 -> 30 | H71: =H66+H67-H70 -> 45 | I71: =I66+I67-I70 -> 38 | J71: =J66+J67-J70 -> 51 | K71: =K66+K67-K70 -> 36 | L71: 46 | M71: 44 | N71: 42 | O71: 45 | P71: =P66+P67-P70 -> 45
A72: New Institutional Water Connections | B72: Brought Forward | C72: No | D72: 0 | E72: =D77 -> 1 | F72: =E77 -> 0 | G72: =F77 -> 1 | H72: =G77 -> 1 | I72: =H77 -> 1 | J72: =I77 -> 1 | K72: =J77 -> 1 | L72: 1 | M72: 1 | N72: 1 | O72: 1 | P72: =D72 -> 0
B73: Applied this Month | C73: No | D73: 1 | E73: 0 | F73: 1 | G73: 1 | H73: 0 | L73: 0 | M73: 0 | N73: 0 | O73: 0 | P73: =SUM(D73:O73) -> 3
B74: Done this Month Postpaid | C74: No | D74: 0 | E74: 0 | F74: 1 | G74: 0 | H74: 0 | L74: 0 | M74: 0 | N74: 0 | O74: 1 | P74: =SUM(D74:O74) -> 2
B75: Done this Month Prepaid | C75: No | D75: 0 | E75: 0 | F75: 0 | G75: 0 | H75: 1 | L75: 0 | M75: 0 | N75: 0 | O75: 0 | P75: =SUM(D75:O75) -> 1
B76: Total Done | C76: No | D76: =D74+D75 -> 0 | E76: =E74+E75 -> 0 | F76: =F74+F75 -> 1 | G76: =G74+G75 -> 0 | H76: =H74+H75 -> 1 | I76: =I74+I75 -> 0 | J76: =J74+J75 -> 0 | K76: =K74+K75 -> 0 | L76: 0 | M76: 0 | N76: 0 | O76: 1 | P76: =P74+P75 -> 3
B77: Carried Forward | C77: No | D77: =D73+D74-D76 -> 1 | E77: =E73+E74-E76 -> 0 | F77: =F73+F74-F76 -> 1 | G77: =G73+G74-G76 -> 1 | H77: 1 | I77: =I72+I73-I76 -> 1 | J77: =J72+J73-J76 -> 1 | K77: =K72+K73-K76 -> 1 | L77: 1 | M77: 1 | N77: 1 | O77: 0 | P77: =P72+P73-P76 -> 0
A78: New Commercial/Industrial Water Connections | B78: Brought Forward | C78: No | D78: 0 | E78: =D83 -> 0 | F78: =E83 -> 0 | G78: =F83 -> 0 | H78: =G83 -> 0 | L78: 0 | M78: 0 | P78: =D78 -> 0
B79: Applied this Month | C79: No | D79: 0 | E79: 0 | F79: 0 | G79: 0 | H79: 0 | L79: 0 | M79: 0 | P79: =SUM(D79:O79) -> 0
B80: Done this Month Postpaid | C80: No | D80: 0 | E80: 0 | F80: 0 | G80: 0 | H80: 0 | L80: 0 | M80: 0 | P80: =SUM(D80:O80) -> 0
B81: Done this Month Prepaid | C81: No | D81: 0 | E81: 0 | F81: 0 | G81: 0 | H81: 0 | L81: 0 | M81: 0 | P81: =SUM(D81:O81) -> 0
B82: Total Done | C82: No | D82: =D81+D80 -> 0 | E82: =E81+E80 -> 0 | F82: =F81+F80 -> 0 | G82: =G81+G80 -> 0 | H82: =H81+H80 -> 0 | I82: =I81+I80 -> 0 | J82: =J81+J80 -> 0 | K82: =K81+K80 -> 0 | L82: 0 | M82: 0 | N82: =N81+N80 -> 0 | O82: 0 | P82: =P81+P80 -> 0
B83: Carried Forward | C83: No | D83: =D78+D79-D82 -> 0 | E83: =E78+E79-E82 -> 0 | F83: =F78+F79-F82 -> 0 | G83: =G78+G79-G82 -> 0 | H83: =H78+H79-H82 -> 0 | I83: =I78+I79-I82 -> 0 | J83: =J78+J79-J82 -> 0 | K83: =K78+K79-K82 -> 0 | L83: 0 | M83: 0 | N83: =N78+N79-N82 -> 0 | O83: 0 | P83: =P78+P79-P82 -> 0
A84: New CWP | B84: Brought Forward | C84: No | D84: 0 | E84: =D89 -> 0 | F84: =E89 -> 0 | G84: =F89 -> 0 | H84: =G89 -> 0 | L84: 0 | M84: 0 | P84: =D84 -> 0
B85: Applied this Month | C85: No | D85: 0 | E85: 0 | F85: 0 | G85: 0 | H85: 0 | L85: 0 | M85: 0 | P85: =SUM(D85:O85) -> 0
B86: Done this Month Postpaid | C86: No | D86: 0 | E86: 0 | F86: 0 | G86: 0 | H86: 0 | L86: 0 | M86: 0 | P86: =SUM(D86:O86) -> 0
B87: Done this Month Prepaid | C87: No | D87: 0 | E87: 0 | F87: 0 | G87: 0 | H87: 0 | L87: 0 | M87: 0 | P87: =SUM(D87:O87) -> 0
B88: Total Done | C88: No | D88: =D86+D87 -> 0 | E88: =E86+E87 -> 0 | F88: =F86+F87 -> 0 | G88: =G86+G87 -> 0 | H88: =H86+H87 -> 0 | I88: =I87+I86 -> 0 | J88: =J87+J86 -> 0 | K88: =K87+K86 -> 0 | L88: 0 | M88: 0 | N88: =N87+N86 -> 0 | O88: 0 | P88: =SUM(D88:O88) -> 0
B89: Carried Forward | C89: No | D89: =D84+D85-D88 -> 0 | E89: =E84+E85-E88 -> 0 | F89: =F84+F85-F88 -> 0 | G89: =G84+G85-G88 -> 0 | H89: =H84+H85-H88 -> 0 | I89: =I84+I85-I88 -> 0 | J89: =J84+J85-J88 -> 0 | K89: =K84+K85-K88 -> 0 | L89: 0 | M89: 0 | N89: =N84+N85-N88 -> 0 | O89: 0 | P89: =P84+P85-P86-P87 -> 0
A90: Aggregated New Water connections | B90: Brought Forward | C90: No | D90: =D66+D72+D78+D84 -> 10 | E90: =E66+E72+E78+E84 -> 17 | F90: =F66+F72+F78+F84 -> 27 | G90: =G66+G72+G78+G84 -> 27 | H90: =H66+H72+H78+H84 -> 31 | I90: =I66+I72+I78+I84 -> 46 | J90: =J66+J72+J78+J84 -> 39 | K90: =K66+K72+K78+K84 -> 52 | ... N90: =N66+N72+N78+N84 -> 45 | O90: 43 | P90: =D90 -> 10
B91: Applied this Month | C91: No | D91: =D67+D73+D79+D85 -> 16 | E91: =E67+E73+E79+E85 -> 20 | F91: =F67+F73+F79+F85 -> 9 | G91: =G67+G73+G79+G85 -> 21 | H91: =H67+H73+H79+H85 -> 30 | I91: =I67+I73+I79+I85 -> 20 | J91: =J67+J73+J79+J85 -> 25 | K91: =K67+K73+K79+K85 -> 0 | ... N91: =N67+N73+N79+N85 -> 10 | O91: 15 | P91: =SUM(D91:O91) -> 194
B92: Done this Month Postpaid | C92: No | D92: =D68+D74+D80+D86 -> 9 | E92: =E68+E74+E80+E86 -> 9 | F92: =F68+F74+F80+F86 -> 10 | G92: =G68+G74+G80+G86 -> 16 | H92: =H68+H74+H80+H86 -> 15 | I92: =I68+I74+I80+I86 -> 27 | J92: =J68+J74+J80+J86 -> 12 | K92: =K68+K74+K80+K86 -> 15 | ... N92: =N68+N74+N80+N86 -> 12 | O92: 13 | P92: =SUM(D92:O92) -> 158
B93: Done this Month Prepaid | D93: =D69+D75+D81+D87 -> 0 | E93: =E69+E75+E81+E87 -> 0 | F93: =F69+F75+F81+F87 -> 0 | G93: =G69+G75+G81+G87 -> 0 | H93: =H69+H75+H81+H87 -> 1 | I93: =I69+I75+I81+I87 -> 0 | J93: =J69+J75+J81+J87 -> 0 | K93: =K69+K75+K81+K87 -> 0 | ... N93: =N69+N75+N81+N87 -> 0 | O93: 0 | P93: =SUM(D93:O93) -> 1
B94: Total Done | C94: No | D94: =D93+D92 -> 9 | E94: =E93+E92 -> 9 | F94: =F93+F92 -> 10 | G94: =G93+G92 -> 16 | H94: =H93+H92 -> 16 | I94: =I93+I92 -> 27 | J94: =J93+J92 -> 12 | K94: =K93+K92 -> 15 | ... N94: =N93+N92 -> 12 | O94: 13 | P94: =P93+P92 -> 159
B95: Carried Forward | C95: No | D95: =D90+D91-D94 -> 17 | E95: =E90+E91-E94 -> 28 | F95: =F90+F91-F94 -> 26 | G95: =G90+G91-G94 -> 32 | H95: =H90+H91-H94 -> 45 | I95: =I90+I91-I94 -> 39 | J95: =J90+J91-J94 -> 52 | K95: =K90+K91-K94 -> 37 | ... N95: =N90+N91-N94 -> 43 | O95: 45 | P95: =P90+P91-P94 -> 45
A97: Prepaid Metering
A98: Prepaid Meters Installed | C98: No | H98: 1 | I98: 10 | J98: 1 | L98: 1 | P98: =SUM(D98:O98) -> 13
A100: Active and Disconnected Accounts
A101: Disconnected Individual Accounts | C101: No | D101: 984 | E101: 978 | F101: 941 | G101: 961 | H101: 976 | I101: 986 | J101: 967 | K101: 966 | L101: 1012 | M101: 1100 | N101: 1094 | O101: 1068 | P101: =O101 -> 1068
A102: Disconnected institutional Accounts | C102: No | D102: 12 | E102: 12 | F102: 12 | G102: 12 | H102: 12 | I102: 12 | J102: 12 | K102: 12 | L102: 12 | M102: 12 | N102: 12 | O102: 12 | P102: =O102 -> 12
A103: Disconnected Commercial/Industrial Accounts | C103: No | D103: 29 | E103: 29 | F103: 29 | G103: 35 | H103: 35 | I103: 35 | J103: 35 | K103: 35 | L103: 35 | M103: 35 | N103: 35 | O103: 35 | P103: =O103 -> 35
A104: Disconnected CWP | C104: No | D104: 9 | E104: 16 | F104: 16 | G104: 16 | H104: 16 | I104: 21 | J104: 21 | K104: 21 | L104: 22 | M104: 22 | N104: 22 | O104: 20 | P104: =O104 -> 20
A105: Total Disconnected Accounts | C105: No | D105: =SUM(D101:D104) -> 1034 | E105: =SUM(E101:E104) -> 1035 | F105: =SUM(F101:F104) -> 998 | G105: =SUM(G101:G104) -> 1024 | H105: =SUM(H101:H104) -> 1039 | I105: =SUM(I101:I104) -> 1054 | J105: =SUM(J101:J104) -> 1035 | K105: =SUM(K101:K104) -> 1034 | ... N105: =SUM(N101:N104) -> 1163 | O105: 1135 | P105: =O105 -> 1135
A106: Postpaid Consumers
...

Sheet Thyolo
A1: SOUTHERN REGION WATER BOARD
A3: MONTHLY REPORTS - 2023/2024
A4: MULANJE ZONE
A5: MULANJE ZONE
A7: PARAMETERS | C7: UNITS | D7: APRIL | E7: MAY | F7: JUNE | G7: JULY | H7: AUGUST | I7: SEPTEMBER | J7: OCTOBER | K7: NOVEMBER | L7: DECEMBER | M7: JANUARY | N7: FEBRUARY | O7: MARCH | P7: TOTALS
A8: PRODUCTION
A9: Volume Produced | C9: m3 | D9: 25590 | E9: 26150 | F9: 24640 | G9: 25540 | H9: 21660 | I9: 20110 | J9: 20310 | K9: 19870 | L9: 19380 | M9: 20340 | N9: 26980 | O9: 23260 | P9: =SUM(D9:O9) -> 273830
A10: REVENUE WATER - POSTPAID
A11: Volume Billed Individuals | C11: m3 | D11: =1935+1375+3536 -> 6846 | E11: =2383+1663+4047 -> 8093 | F11: =2444+1749+4501 -> 8694 | G11: =2286+1623+4149 -> 8058 | H11: 7825 | I11: =2165+1712+4109 -> 7986 | J11: =1831+1140+3358 -> 6329 | K11: =2104+1428+3829 -> 7361 | L11: 7548 | M11: 7070 | N11: 7437 | O11: 6813 | P11: =SUM(D11:O11) -> 90060
A12: Volume Billed CWPs | C12: m3 | D12: 16 | E12: 22 | F12: 17 | G12: 23 | H12: 21 | I12: 23 | J12: 17 | K12: 20 | L12: 25 | M12: 16 | N12: 16 | O12: 16 | P12: =SUM(D12:O12) -> 232
A13: Volume Billed Institutions | C13: m3 | D13: 1427 | E13: 1303 | F13: 2262 | G13: 1099 | H13: 77 | I13: 85 | J13: 77 | K13: 84 | L13: 89 | M13: 53 | N13: 41 | O13: 33 | P13: =SUM(D13:O13) -> 6630
A14: Volume Billed Commercial/Industrial | C14: m3 | D14: 278 | E14: 321 | F14: 366 | G14: 231 | H14: 230 | I14: 270 | J14: 218 | K14: 217 | L14: 211 | M14: 215 | N14: 227 | O14: 202 | P14: =SUM(D14:O14) -> 2986
A15: Total Volume Billed Post Paid | C15: m3 | D15: =SUM(D11:D14) -> 8567 | E15: =SUM(E11:E14) -> 9739 | F15: =SUM(F11:F14) -> 11339 | G15: =SUM(G11:G14) -> 9411 | H15: =SUM(H11:H14) -> 8153 | I15: =SUM(I11:I14) -> 8364 | J15: =SUM(J11:J14) -> 6641 | K15: =SUM(K11:K14) -> 7682 | ... N15: =SUM(N11:N14) -> 7721 | O15: 7064 | P15: =SUM(P11:P14) -> 99908
A16: REVENUE WATER - PREPAID
A17: Individuals | C17: m3 | D17: 1208 | E17: 1102 | F17: 1875 | G17: 1086 | H17: =3925-1372-240 -> 2313 | I17: =1308 -> 1308 | J17: 1294 | K17: 1383 | L17: 1482 | M17: 2094 | N17: 1219 | O17: 3173 | P17: =SUM(D17:O17) -> 19537
A18: CWPs | C18: m3 | D18: 0 | E18: 0 | F18: 0 | G18: 0 | H18: 0 | I18: 0 | J18: 0 | K18: 0 | L18: 0 | M18: 0 | N18: 0 | O18: 0 | P18: =SUM(D18:O18) -> 0
A19: Institutions | C19: m3 | D19: 1384 | E19: =193+1329 -> 1522 | F19: 2262 | G19: =2341-1357 -> 984 | H19: =240+988 -> 1228 | I19: =2441-1544 -> 897 | J19: 1361 | K19: =2788-1758 -> 1030 | L19: 1637 | M19: 3186 | N19: 720 | O19: 829 | P19: =SUM(D19:O19) -> 17040
A20: Commercial/Industrial | C20: m3 | D20: =2755-2592 -> 163 | E20: 229 | F20: 366 | G20: 271 | H20: 388 | I20: 236 | J20: =2836-2655 -> 181 | K20: 375 | L20: 223 | M20: 474 | N20: 281 | O20: 471 | P20: =SUM(D20:O20) -> 3658
A21: Total Volume Prepaid | C21: m3 | D21: =SUM(D17:D20) -> 2755 | E21: =SUM(E17:E20) -> 2853 | F21: =SUM(F17:F20) -> 4503 | G21: =SUM(G17:G20) -> 2341 | H21: =SUM(H17:H20) -> 3929 | I21: =SUM(I17:I20) -> 2441 | J21: =SUM(J17:J20) -> 2836 | K21: =SUM(K17:K20) -> 2788 | ... N21: =SUM(N17:N20) -> 2220 | O21: 4473 | P21: =SUM(P17:P20) -> 40235
A22: TOTAL REVENUE WATER | C22: m3 | D22: =D21+D15 -> 11322 | E22: =E21+E15 -> 12592 | F22: =F21+F15 -> 15842 | G22: =G21+G15 -> 11752 | H22: =H21+H15 -> 12082 | I22: =I21+I15 -> 10805 | J22: =J21+J15 -> 9477 | K22: =K21+K15 -> 10470 | ... N22: =N21+N15 -> 9941 | O22: 11537 | P22: =P21+P15 -> 140143
A24: Non-Revenue Water (NRW) | B24: Volume | C24: m3 | D24: =D9-D22 -> 14268 | E24: =E9-E22 -> 13558 | F24: =F9-F22 -> 8798 | G24: =G9-G22 -> 13788 | H24: =H9-H22 -> 9578 | I24: =I9-I22 -> 9305 | J24: =J9-J22 -> 10833 | K24: =K9-K22 -> 9400 | ... N24: =N9-N22 -> 17039 | O24: 11723 | P24: =P9-P22 -> 133687
B25: Percentage | C25: % | D25: =D24/D9 -> 0.55756155 | E25: =E24/E9 -> 0.51847036 | F25: =F24/F9 -> 0.35706169 | G25: =G24/G9 -> 0.53985904 | H25: =H24/H9 -> 0.4421976 | I25: =I24/I9 -> 0.46270512 | J25: =J24/J9 -> 0.53338257 | K25: =K24/K9 -> 0.47307499 | ... N25: =N24/N9 -> 0.63154188 | O25: 0.50399828 | P25: =P24/P9 -> 0.48821166
A26: OPERATING EXPENSES
A27: Chemicals
A28: Chemical | B28: Rate(MK/kg)
A29: Chlorine | B29: 5111.67 | C29: kg | D29: 82 | E29: 86 | F29: 76 | G29: 100 | H29: 88 | I29: 100 | J29: 75 | K29: 73 | L29: 80 | M29: 70 | N29: 84 | O29: 74 | P29: =SUM(D29:O29) -> 988
C30: kg/mg litre | D30: =D29/(D9/1000) -> 3.2043767 | E30: =E29/(E9/1000) -> 3.2887189 | F30: =F29/(F9/1000) -> 3.0844156 | G30: =G29/(G9/1000) -> 3.9154268 | H30: =H29/(H9/1000) -> 4.0627886 | I30: =I29/(I9/1000) -> 4.9726504 | J30: =J29/(J9/1000) -> 3.6927622 | K30: =K29/(K9/1000) -> 3.6738802 | L30: 4.127967 | M30: =M29/(M9/1000) -> 3.4414946 | N30: =N29/(N9/1000) -> 3.1134173 | O30: 3.1814273 | P30: =P29/(P9/1000) -> 3.608078
A31: Aluminium sulphate | B31: 1537 | C31: kg | F31: 0 | P31: =SUM(D31:O31) -> 0
C32: kg/mg litre | D32: =D31/(D9/1000) -> 0 | E32: =E31/(E9/1000) -> 0 | F32: =F31/(F9/1000) -> 0 | G32: =G31/(G9/1000) -> 0 | H32: =H31/(H9/1000) -> 0 | I32: =I31/(I9/1000) -> 0 | J32: =J31/(J9/1000) -> 0 | K32: =K31/(K9/1000) -> 0 | ... N32: =N31/(N9/1000) -> 0 | O32: 0 | P32: =P31/(P9/1000) -> 0
A33: Soda | B33: 1781.02 | C33: kg | F33: 0 | P33: =SUM(D33:O33) -> 0
C34: kg/mg litre | D34: =D33/(D9/1000) -> 0 | E34: =E33/(E9/1000) -> 0 | F34: =F33/(F9/1000) -> 0 | G34: =G33/(G9/1000) -> 0 | H34: =H33/(H9/1000) -> 0 | I34: =I33/(I9/1000) -> 0 | J34: =J33/(J9/1000) -> 0 | K34: =K33/(K9/1000) -> 0 | ... N34: =N33/(N9/1000) -> 0 | O34: 0 | P34: =P33/(P9/1000) -> 0
A35: Algae floc | B35: 5979.95 | C35: litres | D35: 72 | E35: 84 | F35: 72 | G35: 78 | H35: 78 | I35: 79 | J35: 79 | K35: 86 | L35: 118 | M35: 65 | O35: 117
C36: litres/mg litre | D36: =D35/(D15/1000) -> 8.4043422
A37: Sud floc | B37: 5403.75 | C37: litres | D37: 0 | E37: 0 | F37: 0 | G37: 0 | H37: 0 | I37: 0 | J37: 0 | K37: 0 | L37: 0 | M37: 0 | N37: 0 | O37: 0 | P37: =SUM(D37:O37) -> 0
C38: litres/mg litre | D38: =D37/(D9/1000) -> 0 | E38: =E37/(E9/1000) -> 0 | F38: =F37/(F9/1000) -> 0 | G38: =G37/(G9/1000) -> 0 | H38: =H37/(H9/1000) -> 0 | I38: =I37/(I9/1000) -> 0 | J38: =J37/(J9/1000) -> 0 | K38: =K37/(K9/1000) -> 0 | ... N38: =N37/(N9/1000) -> 0 | O38: 0 | P38: =P37/(P9/1000) -> 0
A39: Potasium permanganate | B39: 1950 | C39: kg | D39: 0 | E39: 0 | F39: 0 | G39: 0 | H39: 0 | I39: 0 | J39: 0 | K39: 0 | L39: 0 | M39: 0 | N39: 0 | O39: 0 | P39: =SUM(D39:O39) -> 0
C40: kg/mg litre | D40: =D39/(D9/1000) -> 0 | E40: =E39/(E9/1000) -> 0 | F40: =F39/(F9/1000) -> 0 | G40: =G39/(G9/1000) -> 0 | H40: =H39/(H9/1000) -> 0 | I40: =I39/(I9/1000) -> 0 | J40: =J39/(J9/1000) -> 0 | K40: =K39/(K9/1000) -> 0 | ... N40: =N39/(N9/1000) -> 0 | O40: 0 | P40: =P39/(P9/1000) -> 0
A41: Cost of Chemicals | C41: Mk | D41: =(D29*$B29)+(D31*$B31)+(D33*$B33)+(D35*$B35)+(D37*$B37)+(D39*$B39) -> 849713.34 | E41: =(E29*$B29)+(E31*$B31)+(E33*$B33)+(E35*$B35)+(E37*$B37)+(E39*$B39) -> 941919.42 | F41: =(F29*$B29)+(F31*$B31)+(F33*$B33)+(F35*$B35)+(F37*$B37)+(F39*$B39) -> 819043.32 | G41: =(G29*$B29)+(G31*$B31)+(G33*$B33)+(G35*$B35)+(G37*$B37)+(G39*$B39) -> 977603.1 | H41: =(H29*$B29)+(H31*$B31)+(H33*$B33)+(H35*$B35)+(H37*$B37)+(H39*$B39) -> 916263.06 | I41: =(I29*$B29)+(I31*$B31)+(I33*$B33)+(I35*$B35)+(I37*$B37)+(I39*$B39) -> 983583.05 | J41: =(J29*$B29)+(J31*$B31)+(J33*$B33)+(J35*$B35)+(J37*$B37)+(J39*$B39) -> 855791.3 | K41: =(K29*$B29)+(K31*$B31)+(K33*$B33)+(K35*$B35)+(K37*$B37)+(K39*$B39) -> 887427.61 | ... N41: =(N29*$B29)+(N31*$B31)+(N33*$B33)+(N35*$B35)+(N37*$B37)+(N39*$B39) -> 429380.28 | O41: 1077917.7 | P41: =SUM(D41:O41) -> 10599724
A42: Cost/vol. Produced (chemicals) | C42: Mk/m3 | D42: =D41/D9 -> 33.204898 | E42: =E41/E9 -> 36.019863 | F42: =F41/F9 -> 33.240394 | G42: =G41/G9 -> 38.277334 | H42: =H41/H9 -> 42.30208 | I42: =I41/I9 -> 48.910147 | J42: =J41/J9 -> 42.13645 | K42: =K41/K9 -> 44.661681 | ... N42: =N41/N9 -> 15.914762 | O42: 46.342121 | P42: =P41/P9 -> 38.709139
A43: Power
A44: Power Usage | C44: Kw | D44: 150 | E44: 214 | F44: 1180 | G44: 6196 | H44: 5349 | I44: 4964 | J44: 5149 | K44: 6629 | L44: 7250 | M44: 6413 | N44: 8448 | O44: 7092 | P44: =SUM(D44:O44) -> 59034
A45: Power/ Vol. Produced | C45: Kw/m3 | D45: =D44/D9 -> 0.0058616647 | E45: =E44/E9 -> 0.0081835564 | F45: =F44/F9 -> 0.04788961 | G45: =G44/G9 -> 0.24259984 | H45: =H44/H9 -> 0.24695291 | I45: =I44/I9 -> 0.24684237 | J45: =J44/J9 -> 0.25352043 | K45: =K44/K9 -> 0.33361852 | L45: 0.37409701 | M45: =M44/M9 -> 0.31529007 | N45: =N44/N9 -> 0.31312083 | O45: 0.30490112 | P45: =P44/P9 -> 0.21558631
A46: Cost of Power | C46: Mk | D46: =1.165*(14100+(D44*119.1)) -> 37239.225 | E46: =1.165*(14100+(E44*119.1)) -> 46119.321 | F46: =1.165*(14100+(F44*119.1)) -> 180153.27 | G46: =1.165*(14100+(G44*119.1)) -> 876130.79 | H46: =1.165*(14100+(H44*119.1)) -> 758608.27 | I46: =1.165*(14100+(I44*119.1)) -> 705188.95 | J46: =1.165*(14100+(J44*119.1)) -> 730857.97 | K46: =1.165*(14100+(K44*119.1)) -> 936210.19 | ... N46: =1.165*(14100+(N44*119.1)) -> 1188599.2 | O46: 1000452.1 | P46: =SUM(D46:O46) -> 8388174.1
A47: Cost/vol. Produced | C47: Mk/m3 | D47: =D46/D9 -> 1.4552257 | E47: =E46/E9 -> 1.7636452 | F47: =F46/F9 -> 7.3114152 | G47: =G46/G9 -> 34.30426 | H47: =H46/H9 -> 35.023466 | I47: =I46/I9 -> 35.066581 | J47: =J46/J9 -> 35.985129 | K47: =K46/K9 -> 47.116769 | ... N47: =N46/N9 -> 44.054825 | O47: 43.0117 | P47: =P46/P9 -> 30.63278
A48: Plant and Vehicle Maintenance
A49: Distances covered | C49: km | D49: 1686 | E49: 1493 | F49: 2108 | G49: 1120 | H49: 1223 | I49: 1522 | J49: 1894 | K49: 1234 | L49: 1134 | M49: 1322 | N49: 1640 | O49: 1444.8 | P49: =SUM(D49:O49) -> 17820.8
A50: Fuel Used (litres) | C50: litres | D50: 171 | E50: 141 | F50: 202 | G50: 132 | H50: 141 | I50: 158 | J50: 194 | K50: =1234/7.3 -> 169.0411 | L50: 162 | M50: 148 | N50: 159 | O50: 166.40822 | P50: =SUM(D50:O50) -> 1943.4493
A51: Cost of fuel | C51: Mk | D51: =D50*1920 -> 328320 | E51: =141*1920 -> 270720 | F51: =202*1920 -> 387840 | G51: =132*1920 -> 253440 | H51: =141*1920 -> 270720 | I51: =1920*I50 -> 303360 | J51: =194*1920 -> 372480 | K51: =169*2734 -> 462046 | L51: 425200 | M51: 404632 | N51: 434706 | O51: 454960.07 | P51: =SUM(D51:O51) -> 4368424.1
A52: Maintenance | C52: Mk | D52: 20000 | E52: 38920 | F52: 272332 | G52: 185000 | H52: 79830 | I52: 261245 | J52: 0 | K52: =200*2734 -> 546800 | L52: 0 | M52: 0 | N52: 0 | O52: 0 | P52: =SUM(D52:O52) -> 1404127
A53: Salaries and Wages
A54: Staff Costs | C54: MK | D54: 3969141.5 | E54: 4682119.3 | F54: 3681524.6 | G54: =AVERAGE(D54:F54) -> 4110928.5 | H54: 4081739.6 | I54: =4784883.8 -> 4784883.8 | J54: 4463146 | K54: 4352197.2 | L54: 5263372.2 | M54: 8789469.3 | O54: 12048609 | P54: =SUM(D54:O54) -> 60227131
A55: Wages | C55: MK | D55: 1150644.6 | E55: 1106932 | F55: 1009631 | G55: =AVERAGE(D55:F55) -> 1089069.2 | H55: 1810669.3 | I55: 913463 | J55: 915386.08 | K55: 988463.02 | L55: 1292309.8 | M55: 1681021.7 | N55: 1117549.9 | O55: 2719942 | P55: =SUM(D55:O55) -> 15795082
A56: Other Overhead Costs | C56: MK | D56: 753026.09 | E56: 237289 | F56: 197000 | G56: =AVERAGE(D56:F56) -> 395771.7 | H56: 487619.86 | I56: 308270 | J56: 291800 | K56: =AVERAGE(F56:J56) -> 336092.31 | L56: 396874.22 | M56: 341588.84 | N56: 738463.06 | O56: 497750 | P56: =SUM(D56:O56) -> 4981545.1
A57: Operating Costs
A58: Total Operating Costs | C58: MK | D58: =D41+D46+D51+D52+D54+D55+D56 -> 7108084.8 | E58: =E41+E46+E51+E52+E54+E55+E56 -> 7324019 | F58: =F41+F46+F51+F52+F54+F55+F56 -> 6547524.2 | G58: =G41+G46+G51+G52+G54+G55+G56 -> 7887943.3 | H58: =H41+H46+H51+H52+H54+H55+H56 -> 8405450.1 | I58: =I41+I46+I51+I52+I54+I55+I56 -> 8259993.8 | J58: =J41+J46+J51+J52+J54+J55+J56 -> 7629461.4 | K58: =K41+K46+K51+K52+K54+K55+K56 -> 8509236.4 | ... N58: =N41+N46+N51+N52+N54+N55+N56 -> 3908698.4 | O58: 17799631 | P58: =SUM(D58:O58) -> 1.0576421e+08
A59: Cost/Vol. Produced | C59: Mk/m3 | D59: =D58/D9 -> 277.76807 | E59: =E58/E9 -> 280.07721 | F59: =F58/F9 -> 265.72744 | G59: =G58/G9 -> 308.84664 | H59: =H58/H9 -> 388.06325 | I59: =I58/I9 -> 410.74062 | J59: =J58/J9 -> 375.65049 | K59: =K58/K9 -> 428.24541 | ... N59: =N58/N9 -> 144.87392 | O59: 765.24639 | P59: =P58/P9 -> 386.24039
A60: Cost/Vol. Billed | C60: Mk/m3 | D60: =D58/D22 -> 627.81176 | E60: =E58/E22 -> 581.64065 | F60: =F58/F22 -> 413.30162 | G60: =G58/G22 -> 671.20007 | H60: =H58/H22 -> 695.70022 | I60: =I58/I22 -> 764.46032 | J60: =J58/J22 -> 805.05026 | K60: =K58/K22 -> 812.72554 | ... N60: =N58/N22 -> 393.18966 | O60: 1542.8301 | P60: =P58/P22 -> 754.68776
A61: Permanent Staff Employed | C61: No | D61: 10 | E61: 10 | F61: 10 | G61: 10 | H61: 10 | I61: 10 | J61: 10 | K61: 10 | L61: 9 | M61: 10 | N61: 10 | O61: 18 | P61: =O61 -> 18
A62: Staff/Vol.1000m3 of Volume Produced/hour (12 hour day) | C62: No/1000m3 | D62: =(D61*1000*31)/D9 -> 12.114107 | E62: =(E61*1000*31)/E9 -> 11.854685 | F62: =(F61*1000*31)/F9 -> 12.581169 | G62: =(G61*1000*31)/G9 -> 12.137823 | H62: =(H61*1000*31)/H9 -> 14.312096 | I62: =(I61*1000*31)/I9 -> 15.415216 | J62: =(J61*1000*31)/J9 -> 15.263417 | K62: =(K61*1000*31)/K9 -> 15.601409 | L62: 14.396285 | M62: =(M61*1000*31)/M9 -> 15.240905 | N62: =(N61*1000*31)/N9 -> 11.489993 | O62: 23.989682 | P62: =(P61*1000*31)/P9 -> 2.0377607
A63: Temporary Staff Employed | C63: No | D63: 16 | E63: 14 | F63: 14 | G63: 14 | H63: 15 | I63: 15 | J63: 15 | K63: 15 | L63: 27 | M63: 27 | N63: 27 | O63: 27 | P63: =SUM(D63:O63) -> 226
A65: Water Connections and Disconnections
A66: New Individual Water Connections | B66: Brought Forward | C66: No | D66: 11 | E66: =D71 -> 9 | F66: =E71 -> 10 | G66: =F71 -> 17 | H66: =G71 -> 15 | I66: =H71 -> 11 | J66: =I71 -> 7 | K66: =J71 -> 15 | L66: 18 | M66: 14 | N66: 13 | O66: 12 | P66: =D66 -> 11
B67: Applied this Month | C67: No | D67: 5 | E67: 5 | F67: 18 | G67: 8 | H67: 9 | I67: 7 | J67: 20 | K67: 11 | L67: 5 | M67: 5 | N67: 5 | O67: 10 | P67: =SUM(D67:O67) -> 108
B68: Done this Month Postpaid | C68: No | D68: 7 | E68: 4 | F68: 11 | G68: 10 | H68: 13 | I68: 11 | J68: 12 | K68: 8 | L68: 8 | M68: 6 | N68: 6 | O68: 19 | P68: =SUM(D68:O68) -> 115
B69: Done this Month Prepaid | C69: No | D69: 0 | E69: 0 | F69: 0 | G69: 0 | H69: 0 | I69: 0 | J69: 0 | K69: 0 | L69: 1 | M69: 0 | N69: 0 | O69: 1 | P69: =SUM(D69:O69) -> 2
B70: Total Done | C70: No | D70: =D68+D69 -> 7 | E70: =E68+E69 -> 4 | F70: =F68+F69 -> 11 | G70: =G68+G69 -> 10 | H70: =H68+H69 -> 13 | I70: =I68+I69 -> 11 | J70: =J68+J69 -> 12 | K70: =K68+K69 -> 8 | L70: 9 | M70: 6 | N70: 6 | O70: 20 | P70: =P68+P69 -> 117
B71: Carried Forward | C71: No | D71: =D66+D67-D70 -> 9 | E71: =E66+E67-E70 -> 10 | F71: =F66+F67-F70 -> 17 | G71: =G66+G67-G70 -> 15 | H71: =H66+H67-H70 -> 11 | I71: =I66+I67-I70 -> 7 | J71: =J66+J67-J70 -> 15 | K71: =K66+K67-K70 -> 18 | L71: 14 | M71: 13 | N71: 12 | O71: 2 | P71: =P66+P67-P70 -> 2
A72: New Institutional Water Connections | B72: Brought Forward | C72: No | D72: 0 | E72: =D77 -> 0 | F72: =E77 -> 0 | G72: =F77 -> 0 | H72: =G77 -> 0 | P72: =D72 -> 0
B73: Applied this Month | C73: No | D73: 0 | E73: 0 | F73: 0 | G73: 0 | H73: 0 | P73: =SUM(D73:O73) -> 0
B74: Done this Month Postpaid | C74: No | D74: 0 | E74: 0 | F74: 0 | G74: 0 | H74: 0 | P74: =SUM(D74:O74) -> 0
B75: Done this Month Prepaid | C75: No | D75: 0 | E75: 0 | F75: 0 | G75: 0 | H75: 0 | P75: =SUM(D75:O75) -> 0
B76: Total Done | C76: No | D76: =D74+D75 -> 0 | E76: =E74+E75 -> 0 | F76: =F74+F75 -> 0 | G76: =G74+G75 -> 0 | H76: =H74+H75 -> 0 | I76: =I74+I75 -> 0 | J76: =J74+J75 -> 0 | K76: =K74+K75 -> 0 | ... N76: =N74+N75 -> 0 | O76: 0 | P76: =P74+P75 -> 0
B77: Carried Forward | C77: No | D77: =D73+D74-D76 -> 0 | E77: =E73+E74-E76 -> 0 | F77: =F73+F74-F76 -> 0 | G77: =G73+G74-G76 -> 0 | H77: =H73+H74-H76 -> 0 | I77: =I72+I73-I76 -> 0 | J77: =J72+J73-J76 -> 0 | K77: =K72+K73-K76 -> 0 | L77: =L72+L73-L76 -> 0 | M77: =M72+M73-M76 -> 0 | N77: =N72+N73-N76 -> 0 | O77: 0 | P77: =P72+P73-P76 -> 0
A78: New Commercial/Industrial Water Connections | B78: Brought Forward | C78: No | D78: 0 | E78: =D83 -> 0 | F78: =E83 -> 1 | G78: =F83 -> 0 | H78: =G83 -> 0 | K78: =J83 -> 1 | P78: =D78 -> 0
B79: Applied this Month | C79: No | D79: 0 | E79: 1 | F79: 0 | G79: 0 | H79: 0 | J79: 1 | P79: =SUM(D79:O79) -> 2
B80: Done this Month Postpaid | C80: No | D80: 0 | E80: 0 | F80: 0 | G80: 0 | H80: 0 | K80: 1 | P80: =SUM(D80:O80) -> 1
B81: Done this Month Prepaid | C81: No | D81: 0 | E81: 0 | F81: 1 | G81: 0 | H81: 0 | P81: =SUM(D81:O81) -> 1
B82: Total Done | C82: No | D82: =D81+D80 -> 0 | E82: =E81+E80 -> 0 | F82: =F81+F80 -> 1 | G82: =G81+G80 -> 0 | H82: =H81+H80 -> 0 | I82: =I81+I80 -> 0 | J82: =J81+J80 -> 0 | K82: =K81+K80 -> 1 | ... N82: =N81+N80 -> 0 | O82: 0 | P82: =P81+P80 -> 2
B83: Carried Forward | C83: No | D83: =D78+D79-D82 -> 0 | E83: =E78+E79-E82 -> 1 | F83: =F78+F79-F82 -> 0 | G83: =G78+G79-G82 -> 0 | H83: =H78+H79-H82 -> 0 | I83: =I78+I79-I82 -> 0 | J83: =J78+J79-J82 -> 1 | K83: =K78+K79-K82 -> 0 | ... N83: =N78+N79-N82 -> 0 | O83: 0 | P83: =P78+P79-P82 -> 0
A84: New CWP | B84: Brought Forward | C84: No | D84: 0 | E84: =D89 -> 0 | F84: =E89 -> 0 | G84: =F89 -> 0 | H84: =G89 -> 0 | P84: =D84 -> 0
B85: Applied this Month | C85: No | D85: 0 | E85: 0 | F85: 0 | G85: 0 | H85: 0 | P85: =SUM(D85:O85) -> 0
B86: Done this Month Postpaid | C86: No | D86: 0 | E86: 0 | F86: 0 | G86: 0 | H86: 0 | P86: =SUM(D86:O86) -> 0
B87: Done this Month Prepaid | C87: No | D87: 0 | E87: 0 | F87: 0 | G87: 0 | H87: 0 | P87: =SUM(D87:O87) -> 0
B88: Total Done | C88: No | D88: =D86+D87 -> 0 | E88: =E86+E87 -> 0 | F88: =F86+F87 -> 0 | G88: =G86+G87 -> 0 | H88: =H86+H87 -> 0 | I88: =I87+I86 -> 0 | J88: =J87+J86 -> 0 | K88: =K87+K86 -> 0 | L88: =L87+L86 -> 0 | M88: =M87+M86 -> 0 | N88: =N87+N86 -> 0 | O88: 0 | P88: =SUM(D88:O88) -> 0
B89: Carried Forward | C89: No | D89: =D84+D85-D88 -> 0 | E89: =E84+E85-E88 -> 0 | F89: =F84+F85-F88 -> 0 | G89: =G84+G85-G88 -> 0 | H89: =H84+H85-H88 -> 0 | I89: =I84+I85-I88 -> 0 | J89: =J84+J85-J88 -> 0 | K89: =K84+K85-K88 -> 0 | ... N89: =N84+N85-N88 -> 0 | O89: 0 | P89: =P84+P85-P88 -> 0
A90: Aggregated New Water connections | B90: Brought Forward | C90: No | D90: =D66+D72+D78+D84 -> 11 | E90: =E66+E72+E78+E84 -> 9 | F90: =F66+F72+F78+F84 -> 11 | G90: =G66+G72+G78+G84 -> 17 | H90: =H66+H72+H78+H84 -> 15 | I90: =I66+I72+I78+I84 -> 11 | J90: =J66+J72+J78+J84 -> 7 | K90: =K66+K72+K78+K84 -> 16 | ... N90: =N66+N72+N78+N84 -> 13 | O90: 12 | P90: =D90 -> 11
B91: Applied this Month | C91: No | D91: =D67+D73+D79+D85 -> 5 | E91: =E67+E73+E79+E85 -> 6 | F91: =F67+F73+F79+F85 -> 18 | G91: =G67+G73+G79+G85 -> 8 | H91: =H67+H73+H79+H85 -> 9 | I91: =I67+I73+I79+I85 -> 7 | J91: =J67+J73+J79+J85 -> 21 | K91: =K67+K73+K79+K85 -> 11 | ... N91: =N67+N73+N79+N85 -> 5 | O91: 10 | P91: =SUM(D91:O91) -> 110
B92: Done this Month Postpaid | C92: No | D92: =D68+D74+D80+D86 -> 7 | E92: =E68+E74+E80+E86 -> 4 | F92: =F68+F74+F80+F86 -> 11 | G92: =G68+G74+G80+G86 -> 10 | H92: =H68+H74+H80+H86 -> 13 | I92: =I68+I74+I80+I86 -> 11 | J92: =J68+J74+J80+J86 -> 12 | K92: =K68+K74+K80+K86 -> 9 | ... N92: =N68+N74+N80+N86 -> 6 | O92: 19 | P92: =SUM(D92:O92) -> 116
B93: Done this Month Prepaid | D93: =D69+D75+D81+D87 -> 0 | E93: =E69+E75+E81+E87 -> 0 | F93: =F69+F75+F81+F87 -> 1 | G93: =G69+G75+G81+G87 -> 0 | H93: =H69+H75+H81+H87 -> 0 | I93: =I69+I75+I81+I87 -> 0 | J93: =J69+J75+J81+J87 -> 0 | K93: =K69+K75+K81+K87 -> 0 | ... N93: =N69+N75+N81+N87 -> 0 | O93: 1 | P93: =SUM(D93:O93) -> 3
B94: Total Done | C94: No | D94: =D93+D92 -> 7 | E94: =E93+E92 -> 4 | F94: =F93+F92 -> 12 | G94: =G93+G92 -> 10 | H94: =H93+H92 -> 13 | I94: =I93+I92 -> 11 | J94: =J93+J92 -> 12 | K94: =K93+K92 -> 9 | ... N94: =N93+N92 -> 6 | O94: 20 | P94: =P93+P92 -> 119
B95: Carried Forward | C95: No | D95: =D90+D91-D94 -> 9 | E95: =E90+E91-E94 -> 11 | F95: =F90+F91-F94 -> 17 | G95: =G90+G91-G94 -> 15 | H95: =H90+H91-H94 -> 11 | I95: =I90+I91-I94 -> 7 | J95: =J90+J91-J94 -> 16 | K95: =K90+K91-K94 -> 18 | ... N95: =N90+N91-N94 -> 12 | O95: 2 | P95: =P90+P91-P94 -> 2
A97: Prepaid Metering
A98: Prepaid Meters Installed | C98: No | F98: 3 | G98: 1 | H98: 45 | J98: 2 | L98: 3 | O98: 2 | P98: =SUM(D98:O98) -> 56
A100: Active and Disconnected Accounts
A101: Disconnected Individual Accounts | C101: No | D101: 509 | E101: 501 | F101: 497 | G101: 491 | H101: 480 | I101: 482 | J101: 485 | K101: 473 | L101: 454 | M101: 499 | N101: 490 | O101: 485 | P101: =O101 -> 485
A102: Disconnected institutional Accounts | C102: No | D102: 14 | E102: 14 | F102: 14 | G102: 14 | H102: 15 | I102: 15 | J102: 17 | K102: 17 | L102: 17 | M102: 18 | N102: 18 | O102: 18 | P102: =O102 -> 18
A103: Disconnected Commercial/Industrial Accounts | C103: No | D103: 62 | E103: 62 | F103: 60 | G103: 60 | H103: 60 | I103: 60 | J103: 81 | K103: 81 | L103: 81 | M103: 82 | N103: 82 | O103: 82 | P103: =O103 -> 82
A104: Disconnected CWP | C104: No | D104: 16 | E104: 16 | F104: 16 | G104: 16 | H104: 16 | I104: 16 | J104: 16 | K104: 16 | L104: 16 | M104: 16 | N104: 16 | O104: 16 | P104: =O104 -> 16
A105: Total Disconnected Accounts | C105: No | D105: =SUM(D101:D104) -> 601 | E105: =SUM(E101:E104) -> 593 | F105: =SUM(F101:F104) -> 587 | G105: =SUM(G101:G104) -> 581 | H105: =SUM(H101:H104) -> 571 | I105: =SUM(I101:I104) -> 573 | J105: =SUM(J101:J104) -> 599 | K105: =SUM(K101:K104) -> 587 | ... N105: =SUM(N101:N104) -> 606 | O105: 601 | P105: =O105 -> 601
A106: Postpaid Consumers
...

Sheet Muloza
A1: SOUTHERN REGION WATER BOARD
A3: MONTHLY REPORTS - 2023/2024
A4: MULANJE ZONE
A5: MULANJE ZONE
A7: PARAMETERS | C7: UNITS | D7: APRIL | E7: MAY | F7: JUNE | G7: JULY | H7: AUGUST | I7: SEPTEMBER | J7: OCTOBER | K7: NOVEMBER | L7: DECEMBER | M7: JANUARY | N7: FEBRUARY | O7: MARCH | P7: TOTALS
A8: PRODUCTION
A9: Volume Produced | C9: m3 | D9: 5343 | E9: 8541 | F9: 7689 | G9: 7562 | H9: 8349 | I9: 7182 | J9: 8063 | K9: 7892 | L9: 8596 | M9: 9482 | N9: 9222 | O9: 9113 | P9: =SUM(D9:O9) -> 97034
A10: REVENUE WATER - POSTPAID
A11: Volume Billed Individuals | C11: m3 | D11: =480+11+2737 -> 3228 | E11: =696+9+3465 -> 4170 | F11: =604+11+3577 -> 4192 | G11: =490+10+3109 -> 3609 | H11: =642+11+3625 -> 4278 | I11: =488+11+3383 -> 3882 | J11: =714+10+4332 -> 5056 | K11: 5000 | L11: 5333 | M11: 5127 | N11: 5090 | O11: 4876 | P11: =SUM(D11:O11) -> 53841
A12: Volume Billed CWPs | C12: m3 | D12: 6 | E12: 8 | F12: 11 | G12: 11 | H12: 12 | I12: 15 | J12: 6 | K12: 8 | L12: 31 | M12: 21 | N12: 26 | O12: 19 | P12: =SUM(D12:O12) -> 174
A13: Volume Billed Institutions | C13: m3 | D13: 238 | E13: 425 | F13: 691 | G13: 752 | H13: 343 | I13: 72 | J13: 129 | K13: 91 | L13: 275 | M13: 246 | N13: 513 | O13: 524 | P13: =SUM(D13:O13) -> 4299
A14: Volume Billed Commercial/Industrial | C14: m3 | D14: 90 | E14: 106 | F14: 145 | G14: 86 | H14: 127 | I14: 97 | J14: 102 | K14: 131 | L14: 106 | M14: 105 | N14: 99 | O14: 90 | P14: =SUM(D14:O14) -> 1284
A15: Total Volume Billed Post Paid | C15: m3 | D15: =SUM(D11:D14) -> 3562 | E15: =SUM(E11:E14) -> 4709 | F15: =SUM(F11:F14) -> 5039 | G15: =SUM(G11:G14) -> 4458 | H15: =SUM(H11:H14) -> 4760 | I15: =SUM(I11:I14) -> 4066 | J15: =SUM(J11:J14) -> 5293 | K15: =SUM(K11:K14) -> 5230 | ... N15: =SUM(N11:N14) -> 5728 | O15: 5509 | P15: =SUM(P11:P14) -> 59598
A16: REVENUE WATER - PREPAID
A17: Individuals | C17: m3 | D17: 752 | E17: 1203 | F17: 912 | G17: 927 | H17: 911 | I17: 726 | J17: 998 | K17: 960 | L17: 1266 | M17: 871 | N17: 720 | O17: 912 | P17: =SUM(D17:O17) -> 11158
A18: CWPs | C18: m3 | D18: 0 | E18: 0 | F18: 0 | G18: 0 | H18: 0 | I18: 0 | J18: 0 | K18: 0 | L18: 0 | M18: 0 | N18: 0 | O18: 0 | P18: =SUM(D18:O18) -> 0
A19: Institutions | C19: m3 | D19: 104 | E19: =108+125 -> 233 | F19: 123 | G19: 163 | H19: 134 | I19: =1094-927 -> 167 | J19: 197 | K19: 77 | L19: 71 | M19: 62 | N19: 84 | O19: 106 | P19: =SUM(D19:O19) -> 1521
A20: Commercial/Industrial | C20: m3 | D20: 198 | E20: 355 | F20: =1157-1035 -> 122 | G20: =1366-1090 -> 276 | H20: =1264-1045 -> 219 | I20: 201 | J20: =1407-1195 -> 212 | K20: =108+73 -> 181 | L20: 208 | M20: 182.1 | N20: 417.6 | O20: 139 | P20: =SUM(D20:O20) -> 2710.7
A21: Total Volume Prepaid | C21: m3 | D21: =SUM(D17:D20) -> 1054 | E21: =SUM(E17:E20) -> 1791 | F21: =SUM(F17:F20) -> 1157 | G21: =SUM(G17:G20) -> 1366 | H21: =SUM(H17:H20) -> 1264 | I21: =SUM(I17:I20) -> 1094 | J21: =SUM(J17:J20) -> 1407 | K21: =SUM(K17:K20) -> 1218 | ... N21: =SUM(N17:N20) -> 1221.6 | O21: 1157 | P21: =SUM(P17:P20) -> 15389.7
A22: TOTAL REVENUE WATER | C22: m3 | D22: =D21+D15 -> 4616 | E22: =E21+E15 -> 6500 | F22: =F21+F15 -> 6196 | G22: =G21+G15 -> 5824 | H22: =H21+H15 -> 6024 | I22: =I21+I15 -> 5160 | J22: =J21+J15 -> 6700 | K22: =K21+K15 -> 6448 | ... N22: =N21+N15 -> 6949.6 | O22: 6666 | P22: =P21+P15 -> 74987.7
A24: Non-Revenue Water (NRW) | B24: Volume | C24: m3 | D24: =D9-D22 -> 727 | E24: =E9-E22 -> 2041 | F24: =F9-F22 -> 1493 | G24: =G9-G22 -> 1738 | H24: =H9-H22 -> 2325 | I24: =I9-I22 -> 2022 | J24: =J9-J22 -> 1363 | K24: =K9-K22 -> 1444 | ... N24: =N9-N22 -> 2272.4 | O24: 2447 | P24: =P9-P22 -> 22046.3
B25: Percentage | C25: % | D25: =D24/D9 -> 0.13606588 | E25: =E24/E9 -> 0.23896499 | F25: =F24/F9 -> 0.19417349 | G25: =G24/G9 -> 0.22983338 | H25: =H24/H9 -> 0.27847646 | I25: =I24/I9 -> 0.28153718 | J25: =J24/J9 -> 0.16904378 | K25: =K24/K9 -> 0.1829701 | ... N25: =N24/N9 -> 0.24641076 | O25: 0.2685175 | P25: =P24/P9 -> 0.22720181
A26: OPERATING EXPENSES
A27: Chemicals
A28: Chemical | B28: Rate(MK/kg)
A29: Chlorine | B29: 5111.67 | C29: kg | D29: 6 | E29: 14 | F29: 16 | G29: 15 | H29: 8 | I29: 8 | J29: 7 | K29: 8 | L29: 10 | M29: 11 | N29: 9 | O29: 7 | P29: =SUM(D29:O29) -> 119
C30: kg/mg litre | D30: =D29/(D9/1000) -> 1.1229646 | E30: =E29/(E9/1000) -> 1.6391523 | F30: =F29/(F9/1000) -> 2.0808948 | G30: =G29/(G9/1000) -> 1.9836022 | H30: =H29/(H9/1000) -> 0.95819859 | I30: =I29/(I9/1000) -> 1.1138959 | J30: =J29/(J9/1000) -> 0.86816321 | K30: =K29/(K9/1000) -> 1.0136847 | L30: 1.1633318 | M30: =M29/(M9/1000) -> 1.1600928 | N30: =N29/(N9/1000) -> 0.97592713 | O30: 0.76813344 | P30: =P29/(P9/1000) -> 1.2263743
A31: Aluminium sulphate | B31: 1537 | C31: kg | P31: =SUM(D31:O31) -> 0
C32: kg/mg litre | D32: =D31/(D9/1000) -> 0 | E32: =E31/(E9/1000) -> 0 | F32: =F31/(F9/1000) -> 0 | G32: =G31/(G9/1000) -> 0 | H32: =H31/(H9/1000) -> 0 | I32: =I31/(I9/1000) -> 0 | J32: =J31/(J9/1000) -> 0 | K32: =K31/(K9/1000) -> 0 | ... N32: =N31/(N9/1000) -> 0 | O32: 0 | P32: =P31/(P9/1000) -> 0
A33: Soda | B33: 1781.02 | C33: kg | P33: =SUM(D33:O33) -> 0
C34: kg/mg litre | D34: =D33/(D9/1000) -> 0 | E34: =E33/(E9/1000) -> 0 | F34: =F33/(F9/1000) -> 0 | G34: =G33/(G9/1000) -> 0 | H34: =H33/(H9/1000) -> 0 | I34: =I33/(I9/1000) -> 0 | J34: =J33/(J9/1000) -> 0 | K34: =K33/(K9/1000) -> 0 | ... N34: =N33/(N9/1000) -> 0 | O34: 0 | P34: =P33/(P9/1000) -> 0
A35: Algae floc | B35: 5979.95 | C35: litres | D35: 0
C36: litres/mg litre
A37: Sud floc | B37: 5403.75 | C37: litres | D37: 0 | E37: 0 | F37: 0 | G37: 0 | H37: 0 | I37: 0 | J37: 0 | K37: 0 | L37: 0 | M37: 0 | N37: 0 | O37: 0 | P37: =SUM(D37:O37) -> 0
C38: litres/mg litre | D38: =D37/(D9/1000) -> 0 | E38: =E37/(E9/1000) -> 0 | F38: =F37/(F9/1000) -> 0 | G38: =G37/(G9/1000) -> 0 | H38: =H37/(H9/1000) -> 0 | I38: =I37/(I9/1000) -> 0 | J38: =J37/(J9/1000) -> 0 | K38: =K37/(K9/1000) -> 0 | ... N38: =N37/(N9/1000) -> 0 | O38: 0 | P38: =P37/(P9/1000) -> 0
A39: Potasium permanganate | B39: 1950 | C39: kg | D39: 0 | E39: 0 | F39: 0 | G39: 0 | H39: 0 | I39: 0 | J39: 0 | K39: 0 | L39: 0 | M39: 0 | N39: 0 | O39: 0 | P39: =SUM(D39:O39) -> 0
C40: kg/mg litre | D40: =D39/(D9/1000) -> 0 | E40: =E39/(E9/1000) -> 0 | F40: =F39/(F9/1000) -> 0 | G40: =G39/(G9/1000) -> 0 | H40: =H39/(H9/1000) -> 0 | I40: =I39/(I9/1000) -> 0 | J40: =J39/(J9/1000) -> 0 | K40: =K39/(K9/1000) -> 0 | ... N40: =N39/(N9/1000) -> 0 | O40: 0 | P40: =P39/(P9/1000) -> 0
A41: Cost of Chemicals | C41: Mk | D41: =(D29*$B29)+(D31*$B31)+(D33*$B33)+(D35*$B35)+(D37*$B37)+(D39*$B39) -> 30670.02 | E41: =(E29*$B29)+(E31*$B31)+(E33*$B33)+(E35*$B35)+(E37*$B37)+(E39*$B39) -> 71563.38 | F41: =(F29*$B29)+(F31*$B31)+(F33*$B33)+(F35*$B35)+(F37*$B37)+(F39*$B39) -> 81786.72 | G41: =(G29*$B29)+(G31*$B31)+(G33*$B33)+(G35*$B35)+(G37*$B37)+(G39*$B39) -> 76675.05 | H41: =(H29*$B29)+(H31*$B31)+(H33*$B33)+(H35*$B35)+(H37*$B37)+(H39*$B39) -> 40893.36 | I41: =(I29*$B29)+(I31*$B31)+(I33*$B33)+(I35*$B35)+(I37*$B37)+(I39*$B39) -> 40893.36 | J41: =(J29*$B29)+(J31*$B31)+(J33*$B33)+(J35*$B35)+(J37*$B37)+(J39*$B39) -> 35781.69 | K41: =(K29*$B29)+(K31*$B31)+(K33*$B33)+(K35*$B35)+(K37*$B37)+(K39*$B39) -> 40893.36 | ... N41: =(N29*$B29)+(N31*$B31)+(N33*$B33)+(N35*$B35)+(N37*$B37)+(N39*$B39) -> 46005.03 | O41: 35781.69 | P41: =SUM(D41:O41) -> 608288.73
A42: Cost/vol. Produced (chemicals) | C42: Mk/m3 | D42: =D41/D9 -> 5.7402246 | E42: =E41/E9 -> 8.3788058 | F42: =F41/F9 -> 10.636847 | G42: =G41/G9 -> 10.13952 | H42: =H41/H9 -> 4.897995 | I42: =I41/I9 -> 5.693868 | J42: =J41/J9 -> 4.4377639 | K42: =K41/K9 -> 5.1816219 | ... N42: =N41/N9 -> 4.9886174 | O42: 3.9264446 | P42: =P41/P9 -> 6.2688205
A43: Power
A44: Power Usage | C44: Kw | D44: 4964 | E44: 9127 | F44: 7643 | G44: 7067 | H44: 8028 | I44: 9732 | J44: 8653 | K44: 9833 | L44: 12326 | M44: 9497 | N44: 8566 | O44: 8196 | P44: =SUM(D44:O44) -> 103632
A45: Power/ Vol. Produced | C45: Kw/m3 | D45: =D44/D9 -> 0.92906607 | E45: =E44/E9 -> 1.0686102 | F45: =F44/F9 -> 0.99401743 | G45: =G44/G9 -> 0.93454113 | H45: =H44/H9 -> 0.96155228 | I45: =I44/I9 -> 1.3550543 | J45: =J44/J9 -> 1.0731738 | K45: =K44/K9 -> 1.2459453 | ... N45: =N44/N9 -> 0.92886576 | O45: 0.89937452 | P45: =P44/P9 -> 1.0679968
A46: Cost of Power | C46: Mk | D46: =1.165*(14100+(D44*119.1)) -> 705188.95 | E46: =1.165*(14100+(E44*119.1)) -> 1282811.4 | F46: =1.165*(14100+(F44*119.1)) -> 1076904.2 | G46: =1.165*(14100+(G44*119.1)) -> 996983.35 | H46: =1.165*(14100+(H44*119.1)) -> 1130323.5 | I46: =1.165*(14100+(I44*119.1)) -> 1366756.1 | J46: =1.165*(14100+(J44*119.1)) -> 1217043.2 | K46: =1.165*(14100+(K44*119.1)) -> 1380770 | ... N46: =1.165*(14100+(N44*119.1)) -> 1204971.8 | O46: 1153633.8 | P46: =SUM(D46:O46) -> 14576213
A47: Cost/vol. Produced | C47: Mk/m3 | D47: =D46/D9 -> 131.98371 | E47: =E46/E9 -> 150.19453 | F47: =F46/F9 -> 140.05777 | G47: =G46/G9 -> 131.84123 | H47: =H46/H9 -> 135.3843 | I47: =I46/I9 -> 190.30299 | J47: =J46/J9 -> 150.94174 | K47: =K46/K9 -> 174.95819 | ... N47: =N46/N9 -> 130.66275 | O47: 126.5921 | P47: =P46/P9 -> 150.21759
A48: Plant and Vehicle Maintenance
A49: Distances covered | C49: km | D49: 400 | E49: 762 | F49: 3212 | G49: 2210 | H49: 1495 | I49: 1093 | J49: 2446 | K49: 1179 | L49: 1727 | M49: 2210 | N49: 1676 | O49: 2571 | P49: =SUM(D49:O49) -> 20981
A50: Fuel Used (litres) | C50: litres | D50: 119 | E50: 59 | F50: 287 | G50: 151 | H50: 154.07 | I50: 136 | J50: 183 | K50: 111 | L50: 171 | M50: 201 | N50: 130 | O50: 234 | P50: =SUM(D50:O50) -> 1936.07
A51: Cost of fuel | C51: Mk | D51: 229305 | E51: 112492.8 | F51: 551462.4 | G51: 289209.6 | H51: 295814.4 | I51: 261081.6 | J51: 351340.8 | K51: 304458.24 | L51: 466229.02 | M51: 549451.98 | N51: 356212.86 | O51: 640275.46 | P51: =SUM(D51:O51) -> 4407334.2
A52: Maintenance | C52: Mk | D52: 0 | E52: 0 | F52: 0 | H52: 0 | I52: 0 | J52: 0 | K52: 0 | L52: 0 | M52: 0 | N52: 0 | O52: 0 | P52: =SUM(D52:O52) -> 0
A53: Salaries and Wages
A54: Staff Costs | C54: MK | D54: 2392832.8 | E54: 2584166.2 | F54: 2376159.5 | G54: =AVERAGE(D54:F54) -> 2451052.8 | H54: 2391824.5 | I54: =AVERAGE(D54:H54) -> 2439207.2 | J54: 2486741.2 | K54: 2505133.5 | L54: 2755646.9 | M54: 5034876.8 | N54: =AVERAGE(K54:M54) -> 3431885.7 | O54: 3075443.8 | P54: =SUM(D54:O54) -> 33924971
A55: Wages | C55: MK | D55: 590228.64 | E55: 603017 | F55: 587653.72 | G55: =AVERAGE(D55:F55) -> 593633.12 | H55: 598634.63 | I55: 586943.78 | J55: 572487.56 | K55: 613893.27 | L55: 582974.23 | M55: 589074.71 | N55: =AVERAGE(K55:M55) -> 595314.07 | O55: 613189 | P55: =SUM(D55:O55) -> 7127043.7
A56: Other Overhead Costs | C56: MK | D56: 508690.1 | E56: 468000 | F56: 387944 | G56: =AVERAGE(D56:F56) -> 454878.03 | H56: 387925 | I56: =AVERAGE(D56:H56) -> 441487.43 | J56: 390873.84 | K56: 424981.62 | L56: 341827.41 | M56: 399792.57 | N56: =AVERAGE(K56:M56) -> 388867.2 | O56: 141500 | P56: =SUM(D56:O56) -> 4736767.2
A57: Operating Costs
A58: Total Operating Costs | C58: MK | D58: =D41+D46+D51+D52+D54+D55+D56 -> 4456915.5 | E58: =E41+E46+E51+E52+E54+E55+E56 -> 5122050.9 | F58: =F41+F46+F51+F52+F54+F55+F56 -> 5061910.6 | G58: =G41+G46+G51+G52+G54+G55+G56 -> 4862432 | H58: =H41+H46+H51+H52+H54+H55+H56 -> 4845415.5 | I58: =I41+I46+I51+I52+I54+I55+I56 -> 5136369.5 | J58: =J41+J46+J51+J52+J54+J55+J56 -> 5054268.3 | K58: =K41+K46+K51+K52+K54+K55+K56 -> 5270130 | ... N58: =N41+N46+N51+N52+N54+N55+N56 -> 6023256.7 | O58: 5659823.7 | P58: =SUM(D58:O58) -> 65380618
A59: Cost/Vol. Produced | C59: Mk/m3 | D59: =D58/D9 -> 834.15974 | E59: =E58/E9 -> 599.70154 | F59: =F58/F9 -> 658.33146 | G59: =G58/G9 -> 643.00873 | H59: =H58/H9 -> 580.35878 | I59: =I58/I9 -> 715.17258 | J59: =J58/J9 -> 626.84712 | K59: =K58/K9 -> 667.7813 | ... N59: =N58/N9 -> 653.13996 | O59: 621.0714 | P59: =P58/P9 -> 673.79082
A60: Cost/Vol. Billed | C60: Mk/m3 | D60: =D58/D22 -> 965.53629 | E60: =E58/E22 -> 788.00782 | F60: =F58/F22 -> 816.96426 | G60: =G58/G22 -> 834.8956 | H60: =H58/H22 -> 804.35184 | I60: =I58/I22 -> 995.42044 | J60: =J58/J22 -> 754.36841 | K60: =K58/K22 -> 817.32786 | ... N60: =N58/N22 -> 866.70553 | O60: 849.05846 | P60: =P58/P22 -> 871.88457
A61: Permanent Staff Employed | C61: No | D61: 6 | E61: 6 | F61: 6 | G61: 6 | H61: 6 | I61: 6 | J61: 6 | K61: 6 | L61: 6 | M61: 6 | N61: 6 | O61: 6 | P61: =O61 -> 6
A62: Staff/Vol.1000m3 of Volume Produced/hour (12 hour day) | C62: No/1000m3 | D62: =(D61*1000*31)/D9 -> 34.811903 | E62: =(E61*1000*31)/E9 -> 21.777309 | F62: =(F61*1000*31)/F9 -> 24.190402 | G62: =(G61*1000*31)/G9 -> 24.596668 | H62: =(H61*1000*31)/H9 -> 22.278117 | I62: =(I61*1000*31)/I9 -> 25.898079 | J62: =(J61*1000*31)/J9 -> 23.068337 | K62: =(K61*1000*31)/K9 -> 23.56817 | ... N62: =(N61*1000*31)/N9 -> 20.169161 | O62: 20.410403 | P62: =(P61*1000*31)/P9 -> 1.9168539
A63: Temporary Staff Employed | C63: No | D63: 9 | E63: 9 | F63: 9 | G63: 14 | H63: 8 | I63: 7 | J63: 7 | K63: 8 | L63: 8 | M63: 6 | N63: 8 | O63: 7 | P63: =SUM(D63:O63) -> 100
A65: Water Connections and Disconnections
A66: New Individual Water Connections | B66: Brought Forward | C66: No | D66: 98 | E66: =D71 -> 109 | F66: =E71 -> 138 | G66: =F71 -> 134 | H66: =G71 -> 131 | I66: =H71 -> 123 | J66: =I71 -> 119 | K66: =J71 -> 124 | L66: 119 | M66: 123 | N66: 138 | O66: 130 | P66: =D66 -> 98
B67: Applied this Month | C67: No | D67: 12 | E67: 29 | F67: 14 | G67: 11 | H67: 18 | I67: 15 | J67: 13 | K67: 7 | L67: 12 | M67: 19 | N67: 11 | O67: 8 | P67: =SUM(D67:O67) -> 169
B68: Done this Month Postpaid | C68: No | D68: 1 | E68: 0 | F68: 18 | G68: 14 | H68: 26 | I68: 19 | J68: 8 | K68: 12 | L68: 8 | M68: 4 | N68: 19 | O68: 11 | P68: =SUM(D68:O68) -> 140
B69: Done this Month Prepaid | C69: No | D69: 0 | E69: 0 | F69: 0 | G69: 0 | H69: 0 | I69: 0 | J69: 0 | K69: 0 | L69: 0 | M69: 0 | N69: 0 | O69: 0 | P69: =SUM(D69:O69) -> 0
B70: Total Done | C70: No | D70: =D68+D69 -> 1 | E70: =E68+E69 -> 0 | F70: =F68+F69 -> 18 | G70: =G68+G69 -> 14 | H70: =H68+H69 -> 26 | I70: =I68+I69 -> 19 | J70: =J68+J69 -> 8 | K70: =K68+K69 -> 12 | L70: 8 | M70: 4 | N70: 19 | O70: 11 | P70: =P68+P69 -> 140
B71: Carried Forward | C71: No | D71: =D66+D67-D70 -> 109 | E71: =E66+E67-E70 -> 138 | F71: =F66+F67-F70 -> 134 | G71: =G66+G67-G70 -> 131 | H71: =H66+H67-H70 -> 123 | I71: =I66+I67-I70 -> 119 | J71: =J66+J67-J70 -> 124 | K71: =K66+K67-K70 -> 119 | L71: 123 | M71: 138 | N71: 130 | O71: 127 | P71: =P66+P67-P70 -> 127
A72: New Institutional Water Connections | B72: Brought Forward | C72: No | E72: =D77 -> 0 | F72: =E77 -> 1 | G72: =F77 -> 0 | H72: =G77 -> 0 | L72: 1 | P72: =D72 -> 0
B73: Applied this Month | C73: No | E73: 1 | F73: 0 | G73: 0 | H73: 0 | K73: 1 | L73: 0 | O73: 1 | P73: =SUM(D73:O73) -> 3
B74: Done this Month Postpaid | C74: No | E74: 0 | F74: 0 | G74: 0 | H74: 0 | L74: 0 | O74: 1 | P74: =SUM(D74:O74) -> 1
B75: Done this Month Prepaid | C75: No | E75: 0 | F75: 0 | G75: 0 | H75: 0 | L75: 0 | P75: =SUM(D75:O75) -> 0
B76: Total Done | C76: No | D76: =D74+D75 -> 0 | E76: =E74+E75 -> 0 | F76: =F74+F75 -> 0 | G76: =G74+G75 -> 0 | H76: =H74+H75 -> 0 | I76: =I74+I75 -> 0 | J76: =J74+J75 -> 0 | K76: =K74+K75 -> 0 | L76: 0 | M76: =M74+M75 -> 0 | N76: =N74+N75 -> 0 | O76: 1 | P76: =P74+P75 -> 1
B77: Carried Forward | C77: No | D77: =D73+D74-D76 -> 0 | E77: =E73+E74-E76 -> 1 | F77: =F73+F74-F76 -> 0 | G77: =G73+G74-G76 -> 0 | H77: =H73+H74-H76 -> 0 | I77: =I73+I74-I76 -> 0 | J77: =J73+J74-J76 -> 0 | K77: =K73+K74-K76 -> 1 | L77: 0 | M77: =M73+M74-M76 -> 0 | N77: =N73+N74-N76 -> 0 | O77: 1 | P77: =P73+P74-P76 -> 3
A78: New Commercial/Industrial Water Connections | B78: Brought Forward | C78: No | E78: =D83 -> 0 | F78: =E83 -> 1 | G78: =F83 -> 0 | H78: =G83 -> 0 | K78: =J83 -> 1 | L78: 1 | M78: 1 | N78: 1 | P78: =D78 -> 0
B79: Applied this Month | C79: No | E79: 1 | F79: 0 | G79: 0 | H79: 0 | J79: 1 | L79: 0 | N79: 0 | P79: =SUM(D79:O79) -> 2
B80: Done this Month Postpaid | C80: No | E80: 0 | F80: 1 | G80: 0 | H80: 0 | L80: 0 | N80: 1 | P80: =SUM(D80:O80) -> 2
B81: Done this Month Prepaid | C81: No | E81: 0 | F81: 0 | G81: 0 | H81: 0 | L81: 0 | N81: 0 | P81: =SUM(D81:O81) -> 0
B82: Total Done | C82: No | D82: =D81+D80 -> 0 | E82: =E81+E80 -> 0 | F82: =F81+F80 -> 1 | G82: =G80+G81 -> 0 | H82: =H81+H80 -> 0 | I82: =I81+I80 -> 0 | J82: =J81+J80 -> 0 | K82: =K81+K80 -> 0 | L82: 0 | M82: =M81+M80 -> 0 | N82: 1 | O82: 0 | P82: =P81+P80 -> 2
B83: Carried Forward | C83: No | D83: =D78+D79-D82 -> 0 | E83: =E78+E79-E82 -> 1 | F83: =F78+F79-F82 -> 0 | G83: =G79+G80-G82 -> 0 | H83: =H78+H79-H82 -> 0 | I83: =I78+I79-I82 -> 0 | J83: =J78+J79-J82 -> 1 | K83: =K78+K79-K82 -> 1 | L83: 1 | M83: =M78+M79-M82 -> 1 | N83: 0 | O83: 0 | P83: =P78+P79-P82 -> 0
A84: New CWP | B84: Brought Forward | C84: No | E84: =D89 -> 0 | F84: =E89 -> 0 | H84: =G89 -> 0 | L84: 0 | P84: =D84 -> 0
B85: Applied this Month | C85: No | E85: 0 | F85: 0 | H85: 0 | L85: 0 | P85: =SUM(D85:O85) -> 0
B86: Done this Month Postpaid | C86: No | E86: 0 | F86: 0 | H86: 0 | L86: 0 | P86: =SUM(D86:O86) -> 0
B87: Done this Month Prepaid | C87: No | E87: 0 | F87: 0 | H87: 0 | L87: 0 | P87: =SUM(D87:O87) -> 0
B88: Total Done | C88: No | D88: =D86+D87 -> 0 | E88: =E86+E87 -> 0 | F88: =F86+F87 -> 0 | G88: =G86+G87 -> 0 | H88: =H86+H87 -> 0 | I88: 0 | J88: 0 | K88: 0 | L88: 0 | M88: 0 | N88: 0 | O88: 0
B89: Carried Forward | C89: No | D89: =D84+D85-D88 -> 0 | E89: =E84+E85-E88 -> 0 | F89: =F84+F85-F88 -> 0 | G89: =G84+G85-G88 -> 0 | H89: =H84+H85-H88 -> 0 | I89: =I84+I85-I88 -> 0 | J89: =J84+J85-J88 -> 0 | K89: =K84+K85-K88 -> 0 | L89: 0 | M89: =M84+M85-M88 -> 0 | N89: =N84+N85-N88 -> 0 | O89: 0 | P89: =P84+P85-P86-P87 -> 0
A90: Aggregated New Water connections | B90: Brought Forward | C90: No | D90: =D66+D72+D78+D84 -> 98 | E90: =E66+E72+E78+E84 -> 109 | F90: =F66+F72+F78+F84 -> 140 | G90: =G66+G72+G78+G84 -> 134 | H90: =H66+H72+H78+H84 -> 131 | I90: =I66+I72+I78+I84 -> 123 | J90: =J66+J72+J78+J84 -> 119 | K90: =K66+K72+K78+K84 -> 125 | ... N90: =N66+N72+N78+N84 -> 139 | O90: 130 | P90: =D90 -> 98
B91: Applied this Month | C91: No | D91: =D67+D73+D79+D85 -> 12 | E91: =E67+E73+E79+E85 -> 31 | F91: =F67+F73+F79+F85 -> 14 | G91: =G67+G73+G79+G85 -> 11 | H91: =H67+H73+H79+H85 -> 18 | I91: =I67+I73+I79+I85 -> 15 | J91: =J67+J73+J79+J85 -> 14 | K91: =K67+K73+K79+K85 -> 8 | ... N91: =N67+N73+N79+N85 -> 11 | O91: 9 | P91: =SUM(D91:O91) -> 174
B92: Done this Month Postpaid | C92: No | D92: =D68+D74+D80+D86 -> 1 | E92: =E68+E74+E80+E86 -> 0 | F92: =F68+F74+F80+F86 -> 19 | G92: =G68+G74+G80+G86 -> 14 | H92: =H68+H74+H80+H86 -> 26 | I92: =I68+I74+I80+I86 -> 19 | J92: =J68+J74+J80+J86 -> 8 | K92: =K68+K74+K80+K86 -> 12 | ... N92: =N68+N74+N80+N86 -> 20 | O92: 12 | P92: =SUM(D92:O92) -> 143
B93: Done this Month Prepaid | D93: =D69+D75+D81+D87 -> 0 | E93: =E69+E75+E81+E87 -> 0 | F93: =F69+F75+F81+F87 -> 0 | G93: =G69+G75+G81+G87 -> 0 | H93: =H69+H75+H81+H87 -> 0 | I93: =I69+I75+I81+I87 -> 0 | J93: =J69+J75+J81+J87 -> 0 | K93: =K69+K75+K81+K87 -> 0 | ... N93: =N69+N75+N81+N87 -> 0 | O93: 0 | P93: =SUM(D93:O93) -> 0
B94: Total Done | C94: No | D94: =D93+D92 -> 1 | E94: =E93+E92 -> 0 | F94: =F93+F92 -> 19 | G94: =G93+G92 -> 14 | H94: =H93+H92 -> 26 | I94: =I93+I92 -> 19 | J94: =J93+J92 -> 8 | K94: =K93+K92 -> 12 | ... N94: =N93+N92 -> 20 | O94: 12 | P94: =P93+P92 -> 143
B95: Carried Forward | C95: No | D95: =D90+D91-D94 -> 109 | E95: =E90+E91-E94 -> 140 | F95: =F90+F91-F94 -> 135 | G95: =G90+G91-G94 -> 131 | H95: =H90+H91-H94 -> 123 | I95: =I90+I91-I94 -> 119 | J95: =J90+J91-J94 -> 125 | K95: =K90+K91-K94 -> 121 | ... N95: =N90+N91-N94 -> 130 | O95: 127 | P95: =P90+P91-P94 -> 129
A97: Prepaid Metering
A98: Prepaid Meters Installed | C98: No | G98: =G93 -> 0 | L98: 4 | M98: 4 | P98: =SUM(D98:O98) -> 8
A100: Active and Disconnected Accounts
A101: Disconnected Individual Accounts | C101: No | D101: 464 | E101: 484 | F101: 478 | G101: 473 | H101: 470 | I101: 465 | J101: 465 | K101: 477 | L101: 469 | M101: 512 | N101: 504 | O101: 498 | P101: =O101 -> 498
A102: Disconnected institutional Accounts | C102: No | D102: 17 | E102: 18 | F102: 18 | G102: 18 | H102: 18 | I102: 18 | J102: 18 | K102: 18 | L102: 18 | M102: 18 | N102: 18 | O102: 18 | P102: =O102 -> 18
A103: Disconnected Commercial/Industrial Accounts | C103: No | D103: 75 | E103: 75 | F103: 75 | G103: 74 | H103: 74 | I103: 74 | J103: 75 | K103: 75 | L103: 74 | M103: 74 | N103: 73 | O103: 73 | P103: =O103 -> 73
A104: Disconnected CWP | C104: No | D104: 0 | E104: 0 | F104: 0 | G104: 0 | J104: 0 | M104: 0 | P104: =O104 -> 0
A105: Total Disconnected Accounts | C105: No | D105: =SUM(D101:D104) -> 556 | E105: =SUM(E101:E104) -> 577 | F105: =SUM(F101:F104) -> 571 | G105: =SUM(G101:G104) -> 565 | H105: =SUM(H101:H104) -> 562 | I105: =SUM(I101:I104) -> 557 | J105: =SUM(J101:J104) -> 558 | K105: =SUM(K101:K104) -> 570 | ... N105: =SUM(N101:N104) -> 595 | O105: 589 | P105: =O105 -> 589
A106: Postpaid Consumers
...

Sheet MUST
A1: SOUTHERN REGION WATER BOARD
A3: MONTHLY REPORTS - 2023/2024
A4: MULANJE ZONE
A5: MULANJE ZONE
A7: PARAMETERS | C7: UNITS | D7: APRIL | E7: MAY | F7: JUNE | G7: JULY | H7: AUGUST | I7: SEPTEMBER | J7: OCTOBER | K7: NOVEMBER | L7: DECEMBER | M7: JANUARY | N7: FEBRUARY | O7: MARCH | P7: TOTALS
A8: PRODUCTION
A9: Volume Produced | C9: m3 | D9: 20543 | E9: 14001 | F9: 9442 | G9: 13028 | H9: 26032 | I9: 14779 | J9: 15745 | K9: 16982 | L9: 16346 | M9: 2257 | N9: 14870 | O9: 15646 | P9: =SUM(D9:O9) -> 179671
A10: REVENUE WATER - POSTPAID
A11: Volume Billed Individuals | C11: m3 | D11: =544+214 -> 758 | E11: =538+32 -> 570 | F11: =193+842 -> 1035 | G11: =211+628 -> 839 | H11: =226+805 -> 1031 | I11: =194+815 -> 1009 | J11: =186+897 -> 1083 | K11: =126+969 -> 1095 | L11: 989 | M11: 855 | N11: 964 | O11: 1236 | P11: =SUM(D11:O11) -> 11464
A12: Volume Billed CWPs | C12: m3 | D12: 0 | E12: 0 | F12: 0 | G12: 0 | H12: 0 | I12: 0 | J12: 0 | K12: 0 | L12: 0 | M12: 0 | N12: 0 | O12: 0 | P12: =SUM(D12:O12) -> 0
A13: Volume Billed Institutions | C13: m3 | D13: 14800 | E13: 10356 | F13: 6309 | G13: 9357 | H13: =8499 -> 8499 | I13: 30 | J13: 30 | K13: 31 | L13: 37 | M13: 29 | N13: 29 | O13: 24 | P13: =SUM(D13:O13) -> 49531
A14: Volume Billed Commercial/Industrial | C14: m3 | D14: 51 | E14: 65 | F14: 54 | G14: 56 | H14: 60 | I14: 65 | J14: 43 | K14: 32 | L14: 24 | M14: 20 | N14: 32 | O14: 8 | P14: =SUM(D14:O14) -> 510
A15: Total Volume Billed Post Paid | C15: m3 | D15: =SUM(D11:D14) -> 15609 | E15: =SUM(E11:E14) -> 10991 | F15: =SUM(F11:F14) -> 7398 | G15: =SUM(G11:G14) -> 10252 | H15: =SUM(H11:H14) -> 9590 | I15: =SUM(I11:I14) -> 1104 | J15: =SUM(J11:J14) -> 1156 | K15: =SUM(K11:K14) -> 1158 | ... N15: =SUM(N11:N14) -> 1025 | O15: 1268 | P15: =SUM(P11:P14) -> 61505
A16: REVENUE WATER - PREPAID
A17: Individuals | C17: m3 | D17: =159.3+0.8 -> 160.1 | E17: 268 | F17: 291 | G17: 327 | H17: 307 | I17: 295 | J17: 263.6 | K17: =13.6+217.4 -> 231 | L17: 221 | M17: 192 | N17: 213 | O17: 254.3 | P17: =SUM(D17:O17) -> 3023
A18: CWPs | C18: m3 | D18: 0 | E18: 0 | F18: 0 | G18: 0 | H18: 0 | I18: 0 | J18: 0 | K18: 0 | L18: 0 | M18: 0 | N18: 0 | O18: 0 | P18: =SUM(D18:O18) -> 0
A19: Institutions | C19: m3 | D19: 0 | E19: 0 | F19: 0 | G19: 0 | H19: 11399 | I19: 10929 | J19: 10857 | K19: 11041 | L19: 11037 | M19: 0 | N19: 11037 | O19: 11762 | P19: =SUM(D19:O19) -> 78062
A20: Commercial/Industrial | C20: m3 | D20: 857 | E20: 858 | F20: 536 | G20: 751 | H20: 729 | I20: 715 | J20: 713 | K20: 749 | L20: 1447 | M20: 749 | N20: 717 | O20: 726 | P20: =SUM(D20:O20) -> 9547
A21: Total Volume Prepaid | C21: m3 | D21: =SUM(D17:D20) -> 1017.1 | E21: =SUM(E17:E20) -> 1126 | F21: =SUM(F17:F20) -> 827 | G21: =SUM(G17:G20) -> 1078 | H21: =SUM(H17:H20) -> 12435 | I21: =SUM(I17:I20) -> 11939 | J21: =SUM(J17:J20) -> 11833.6 | K21: =SUM(K17:K20) -> 12021 | ... N21: =SUM(N17:N20) -> 11967 | O21: 12742.3 | P21: =SUM(P17:P20) -> 90632
A22: TOTAL REVENUE WATER | C22: m3 | D22: =D21+D15 -> 16626.1 | E22: =E21+E15 -> 12117 | F22: =F21+F15 -> 8225 | G22: =G21+G15 -> 11330 | H22: =H21+H15 -> 22025 | I22: =I21+I15 -> 13043 | J22: =J21+J15 -> 12989.6 | K22: =K21+K15 -> 13179 | ... N22: =N21+N15 -> 12992 | O22: 14010.3 | P22: =P21+P15 -> 152137
A24: Non-Revenue Water (NRW) | B24: Volume | C24: m3 | D24: =D9-D22 -> 3916.9 | E24: =E9-E22 -> 1884 | F24: =F9-F22 -> 1217 | G24: =G9-G22 -> 1698 | H24: =H9-H22 -> 4007 | I24: =I9-I22 -> 1736 | J24: =J9-J22 -> 2755.4 | K24: =K9-K22 -> 3803 | ... N24: =N9-N22 -> 1878 | O24: 1635.7 | P24: =P9-P22 -> 27534
B25: Percentage | C25: % | D25: =D24/D9 -> 0.19066835 | E25: =E24/E9 -> 0.13456182 | F25: =F24/F9 -> 0.12889218 | G25: =G24/G9 -> 0.13033466 | H25: =H24/H9 -> 0.15392594 | I25: =I24/I9 -> 0.11746397 | J25: =J24/J9 -> 0.17500159 | K25: =K24/K9 -> 0.223943 | ... N25: =N24/N9 -> 0.12629455 | O25: 0.10454429 | P25: =P24/P9 -> 0.15324677
A26: OPERATING EXPENSES
A27: Chemicals
A28: Chemical | B28: Rate(MK/kg)
A29: Chlorine | B29: 5111.67 | C29: kg | D29: 16 | E29: 16 | F29: 10 | G29: 15 | H29: 17 | I29: 15 | J29: 17 | K29: 18 | L29: 9 | M29: 12 | N29: 14 | O29: 17 | P29: =SUM(D29:O29) -> 176
C30: kg/mg litre | D30: =D29/(D9/1000) -> 0.77885411 | E30: =E29/(E9/1000) -> 1.1427755 | F30: =F29/(F9/1000) -> 1.0590976 | G30: =G29/(G9/1000) -> 1.1513663 | H30: =H29/(H9/1000) -> 0.65304241 | I30: =I29/(I9/1000) -> 1.0149537 | J30: =J29/(J9/1000) -> 1.0797078 | K30: =K29/(K9/1000) -> 1.0599458 | L30: 0.55059342 | M30: =M29/(M9/1000) -> 5.3167922 | N30: =N29/(N9/1000) -> 0.94149294 | O30: 1.0865397 | P30: =P29/(P9/1000) -> 0.97956821
A31: Aluminium sulphate | B31: 1537 | C31: kg | P31: =SUM(D31:O31) -> 0
C32: kg/mg litre | D32: =D31/(D9/1000) -> 0 | E32: =E31/(E9/1000) -> 0 | F32: =F31/(F9/1000) -> 0 | G32: =G31/(G9/1000) -> 0 | H32: =H31/(H9/1000) -> 0 | I32: =I31/(I9/1000) -> 0 | J32: =J31/(J9/1000) -> 0 | K32: =K31/(K9/1000) -> 0 | ... N32: =N31/(N9/1000) -> 0 | O32: 0 | P32: =P31/(P9/1000) -> 0
A33: Soda | B33: 1781.02 | C33: kg | P33: =SUM(D33:O33) -> 0
C34: kg/mg litre | D34: =D33/(D9/1000) -> 0 | E34: =E33/(E9/1000) -> 0 | F34: =F33/(F9/1000) -> 0 | G34: =G33/(G9/1000) -> 0 | H34: =H33/(H9/1000) -> 0 | I34: =I33/(I9/1000) -> 0 | J34: =J33/(J9/1000) -> 0 | K34: =K33/(K9/1000) -> 0 | ... N34: =N33/(N9/1000) -> 0 | O34: 0 | P34: =P33/(P9/1000) -> 0
A35: Algae floc | B35: 5979.95 | C35: litres
C36: litres/mg litre
A37: Sud floc | B37: 5403.75 | C37: litres | D37: 0 | E37: 0 | F37: 0 | G37: 0 | H37: 0 | I37: 0 | J37: 0 | K37: 0 | L37: 0 | M37: 0 | N37: 0 | O37: 0 | P37: =SUM(D37:O37) -> 0
C38: litres/mg litre | D38: =D37/(D9/1000) -> 0 | E38: =E37/(E9/1000) -> 0 | F38: =F37/(F9/1000) -> 0 | G38: =G37/(G9/1000) -> 0 | H38: =H37/(H9/1000) -> 0 | I38: =I37/(I9/1000) -> 0 | J38: =J37/(J9/1000) -> 0 | K38: =K37/(K9/1000) -> 0 | ... N38: =N37/(N9/1000) -> 0 | O38: 0 | P38: =P37/(P9/1000) -> 0
A39: Potasium permanganate | B39: 1950 | C39: kg | D39: 0 | E39: 0 | F39: 0 | G39: 0 | H39: 0 | I39: 0 | J39: 0 | K39: 0 | L39: 0 | M39: 0 | N39: 0 | O39: 0 | P39: =SUM(D39:O39) -> 0
C40: kg/mg litre | D40: =D39/(D9/1000) -> 0 | E40: =E39/(E9/1000) -> 0 | F40: =F39/(F9/1000) -> 0 | G40: =G39/(G9/1000) -> 0 | H40: =H39/(H9/1000) -> 0 | I40: =I39/(I9/1000) -> 0 | J40: =J39/(J9/1000) -> 0 | K40: =K39/(K9/1000) -> 0 | ... N40: =N39/(N9/1000) -> 0 | O40: 0 | P40: =P39/(P9/1000) -> 0
A41: Cost of Chemicals | C41: Mk | D41: =(D29*$B29)+(D31*$B31)+(D33*$B33)+(D35*$B35)+(D37*$B37)+(D39*$B39) -> 81786.72 | E41: =(E29*$B29)+(E31*$B31)+(E33*$B33)+(E35*$B35)+(E37*$B37)+(E39*$B39) -> 81786.72 | F41: =(F29*$B29)+(F31*$B31)+(F33*$B33)+(F35*$B35)+(F37*$B37)+(F39*$B39) -> 51116.7 | G41: =(G29*$B29)+(G31*$B31)+(G33*$B33)+(G35*$B35)+(G37*$B37)+(G39*$B39) -> 76675.05 | H41: =(H29*$B29)+(H31*$B31)+(H33*$B33)+(H35*$B35)+(H37*$B37)+(H39*$B39) -> 86898.39 | I41: =(I29*$B29)+(I31*$B31)+(I33*$B33)+(I35*$B35)+(I37*$B37)+(I39*$B39) -> 76675.05 | J41: =(J29*$B29)+(J31*$B31)+(J33*$B33)+(J35*$B35)+(J37*$B37)+(J39*$B39) -> 86898.39 | K41: =(K29*$B29)+(K31*$B31)+(K33*$B33)+(K35*$B35)+(K37*$B37)+(K39*$B39) -> 92010.06 | ... N41: =(N29*$B29)+(N31*$B31)+(N33*$B33)+(N35*$B35)+(N37*$B37)+(N39*$B39) -> 71563.38 | O41: 86898.39 | P41: =SUM(D41:O41) -> 899653.92
A42: Cost/vol. Produced (chemicals) | C42: Mk/m3 | D42: =D41/D9 -> 3.9812452 | E42: =E41/E9 -> 5.8414913 | F42: =F41/F9 -> 5.4137577 | G42: =G41/G9 -> 5.8854045 | H42: =H41/H9 -> 3.3381373 | I42: =I41/I9 -> 5.1881081 | J42: =J41/J9 -> 5.5191102 | K42: =K41/K9 -> 5.4180933 | ... N42: =N41/N9 -> 4.8126012 | O42: 5.5540323 | P42: =P41/P9 -> 5.0072294
A43: Power
A44: Power Usage | C44: Kw | D44: 7309 | E44: 6540 | F44: 5826 | G44: 6060 | H44: 7017 | I44: 5208 | J44: 5510 | K44: 7309 | L44: 3779 | M44: 5211 | N44: 5307 | O44: 6525 | P44: =SUM(D44:O44) -> 71601
A45: Power/ Vol. Produced | C45: Kw/m3 | D45: =D44/D9 -> 0.35579029 | E45: =E44/E9 -> 0.46710949 | F45: =F44/F9 -> 0.61703029 | G45: =G44/G9 -> 0.46515198 | H45: =H44/H9 -> 0.26955286 | I45: =I44/I9 -> 0.35239191 | J45: =J44/J9 -> 0.34995237 | K45: =K44/K9 -> 0.43039689 | L45: 0.23118806 | M45: 2.308817 | N45: =N44/N9 -> 0.35689307 | O45: 0.4170395 | P45: =P44/P9 -> 0.39851172
A46: Cost of Power | C46: Mk | D46: =1.165*(14100+(D44*119.1)) -> 1030561.2 | E46: =1.165*(14100+(E44*119.1)) -> 923861.31 | F46: =1.165*(14100+(F44*119.1)) -> 824792.74 | G46: =1.165*(14100+(G44*119.1)) -> 857260.59 | H46: =1.165*(14100+(H44*119.1)) -> 990045.78 | I46: =1.165*(14100+(I44*119.1)) -> 739044.31 | J46: =1.165*(14100+(J44*119.1)) -> 780947.27 | K46: =1.165*(14100+(K44*119.1)) -> 1030561.2 | ... N46: =1.165*(14100+(N44*119.1)) -> 752780.71 | O46: 921780.04 | P46: =SUM(D46:O46) -> 10131864
A47: Cost/vol. Produced | C47: Mk/m3 | D47: =D46/D9 -> 50.166052 | E47: =E46/E9 -> 65.98538 | F47: =F46/F9 -> 87.353605 | G47: =G46/G9 -> 65.801396 | H47: =H46/H9 -> 38.031875 | I47: =I46/I9 -> 50.006381 | J47: =J46/J9 -> 49.599699 | K47: =K46/K9 -> 60.685503 | ... N47: =N46/N9 -> 50.624123 | O47: 58.914741 | P47: =P46/P9 -> 56.391205
A48: Plant and Vehicle Maintenance
A49: Distances covered | C49: km | D49: =117*20 -> 2340 | E49: =105*20 -> 2100 | F49: 1625 | G49: 1180 | H49: =84*20 -> 1680 | I49: =I50*20 -> 2860 | J49: 2384 | K49: =36*20 -> 720 | L49: 1470 | M49: 2400 | N49: 760 | O49: 1800 | P49: =SUM(D49:O49) -> 21319
A50: Fuel Used (litres) | C50: litres | D50: 117 | E50: 105 | F50: 65 | G50: 136 | H50: 84 | I50: 143 | J50: 133 | K50: 36 | L50: 210 | M50: 120 | N50: 38 | O50: 72 | P50: =SUM(D50:O50) -> 1259
A51: Cost of fuel | C51: Mk | D51: 225000 | E51: 200000 | F51: 150000 | G51: 256000 | H51: 155000 | I51: 294000 | J51: 255516 | K51: 105550 | L51: 564978 | M51: 303600 | N51: 103740 | O51: 194400 | P51: =SUM(D51:O51) -> 2807784
A52: Maintenance | C52: Mk | D52: 0 | E52: 0 | F52: 0 | G52: 0 | H52: 0 | I52: 0 | J52: 0 | K52: 0 | L52: 0 | M52: 0 | N52: 0 | O52: 0 | P52: =SUM(D52:O52) -> 0
A53: Salaries and Wages
A54: Staff Costs | C54: MK | D54: 1783477.4 | E54: 1837957.7 | F54: 1643587.8 | G54: =AVERAGE(D54:F54) -> 1755007.6 | H54: =AVERAGE(F54:G54) -> 1699297.7 | I54: =AVERAGE(D54:H54) -> 1743865.6 | J54: =AVERAGE(H54:I54) -> 1721581.7 | K54: 1803746.2 | L54: 1984120.8 | M54: 3469247.9 | P54: =SUM(D54:O54) -> 19441890
A55: Wages | C55: MK | D55: 480000 | E55: 507212.35 | F55: 316700 | G55: 319220.99 | H55: 417308.36 | I55: 437000 | J55: =AVERAGE(H55:I55) -> 427154.18 | K55: 388462.16 | L55: 389845 | M55: 396154.2 | N55: 377272 | O55: 415385 | P55: =SUM(D55:O55) -> 4871714.2
A56: Other Overhead Costs | C56: MK | D56: 294000 | E56: 64000 | F56: 64000 | G56: 64000 | H56: 64000 | I56: 64000 | J56: 64000 | K56: 64000 | L56: 438000 | M56: 73000 | N56: 64000 | O56: 64000 | P56: =SUM(D56:O56) -> 1381000
A57: Operating Costs
A58: Total Operating Costs | C58: MK | D58: =D41+D46+D51+D52+D54+D55+D56 -> 3894825.3 | E58: =E41+E46+E51+E52+E54+E55+E56 -> 3614818 | F58: =F41+F46+F51+F52+F54+F55+F56 -> 3050197.3 | G58: =G41+G46+G51+G52+G54+G55+G56 -> 3328164.2 | H58: =H41+H46+H51+H52+H54+H55+H56 -> 3412550.2 | I58: =I41+I46+I51+I52+I54+I55+I56 -> 3354585 | J58: =J41+J46+J51+J52+J54+J55+J56 -> 3336097.5 | K58: =K41+K46+K51+K52+K54+K55+K56 -> 3484329.7 | ... N58: =N41+N46+N51+N52+N54+N55+N56 -> 1369356.1 | O58: 1682463.4 | P58: =SUM(D58:O58) -> 39533907
A59: Cost/Vol. Produced | C59: Mk/m3 | D59: =D58/D9 -> 189.59379 | E59: =E58/E9 -> 258.18285 | F59: =F58/F9 -> 323.04567 | G59: =G58/G9 -> 255.46241 | H59: =H58/H9 -> 131.09059 | I59: =I58/I9 -> 226.98322 | J59: =J58/J9 -> 211.88298 | K59: =K58/K9 -> 205.17781 | ... N59: =N58/N9 -> 92.088506 | O59: 107.53313 | P59: =P58/P9 -> 220.03499
A60: Cost/Vol. Billed | C60: Mk/m3 | D60: =D58/D22 -> 234.25971 | E60: =E58/E22 -> 298.32616 | F60: =F58/F22 -> 370.84465 | G60: =G58/G22 -> 293.74795 | H60: =H58/H22 -> 154.93985 | I60: =I58/I22 -> 257.19428 | J60: =J58/J22 -> 256.82835 | K60: =K58/K22 -> 264.38498 | ... N60: =N58/N22 -> 105.39995 | O60: 120.08761 | P60: =P58/P22 -> 259.85728
A61: Permanent Staff Employed | C61: No | D61: 5 | E61: 5 | F61: 4 | G61: 4 | H61: 4 | I61: 4 | J61: 4 | K61: 4 | L61: 4 | M61: 4 | N61: 4 | O61: 4 | P61: =O61 -> 4
A62: Staff/Vol.1000m3 of Volume Produced/hour (12 hour day) | C62: No/1000m3 | D62: =(D61*1000*31)/D9 -> 7.5451492 | E62: =(E61*1000*31)/E9 -> 11.070638 | F62: =(F61*1000*31)/F9 -> 13.132811 | G62: =(G61*1000*31)/G9 -> 9.5179613 | H62: =(H61*1000*31)/H9 -> 4.7633682 | I62: =(I61*1000*31)/I9 -> 8.3902835 | J62: =(J61*1000*31)/J9 -> 7.875516 | K62: =(K61*1000*31)/K9 -> 7.301849 | ... N62: =(N61*1000*31)/N9 -> 8.3389375 | O62: 7.9253483 | P62: =(P61*1000*31)/P9 -> 0.69015033
A63: Temporary Staff Employed | C63: No | D63: 8 | E63: 8 | F63: 6 | G63: 6 | H63: 6 | I63: 5 | J63: 7 | K63: 7 | L63: 10 | M63: 7 | N63: 7 | O63: 10 | P63: =SUM(D63:O63) -> 87
A65: Water Connections and Disconnections
A66: New Individual Water Connections | B66: Brought Forward | C66: No | D66: 5 | E66: =D71 -> 10 | F66: =E71 -> 5 | G66: =F71 -> 9 | H66: =G71 -> 8 | I66: =H71 -> 11 | J66: =I71 -> 9 | K66: 5 | L66: 3 | M66: 6 | N66: 8 | O66: 7 | P66: =D66 -> 5
B67: Applied this Month | C67: No | D67: 5 | E67: 11 | F67: 5 | G67: 0 | H67: 6 | I67: 1 | J67: 0 | K67: 6 | L67: 6 | M67: 5 | N67: 1 | O67: 1 | P67: =SUM(D67:O67) -> 47
B68: Done this Month Postpaid | C68: No | D68: 0 | E68: 8 | F68: 1 | G68: 1 | H68: 3 | I68: 3 | J68: 2 | K68: 8 | L68: 3 | M68: 3 | N68: 2 | O68: 3 | P68: =SUM(D68:O68) -> 37
B69: Done this Month Prepaid | C69: No | D69: 0 | E69: 8 | F69: 0 | G69: 0 | H69: 0 | I69: 0 | J69: 0 | K69: 0 | L69: 0 | M69: 0 | N69: 0 | O69: 0 | P69: =SUM(D69:O69) -> 8
B70: Total Done | C70: No | D70: =D68+D69 -> 0 | E70: =E68+E69 -> 16 | F70: =F68+F69 -> 1 | G70: =G68+G69 -> 1 | H70: =H68+H69 -> 3 | I70: =I68+I69 -> 3 | J70: =J68+J69 -> 2 | K70: =K68+K69 -> 8 | L70: 3 | M70: 3 | N70: 2 | O70: 3 | P70: =P68+P69 -> 45
B71: Carried Forward | C71: No | D71: =D66+D67-D70 -> 10 | E71: =E66+E67-E70 -> 5 | F71: =F66+F67-F70 -> 9 | G71: =G66+G67-G70 -> 8 | H71: =H66+H67-H70 -> 11 | I71: =I66+I67-I70 -> 9 | J71: =J66+J67-J70 -> 7 | K71: =K66+K67-K70 -> 3 | L71: 6 | M71: 8 | N71: 7 | O71: 5 | P71: =P66+P67-P70 -> 7
A72: New Institutional Water Connections | B72: Brought Forward | C72: No | D72: 0 | E72: =D77 -> 0 | F72: =E77 -> 0 | G72: =F77 -> 0 | H72: =G77 -> 0 | M72: 0 | P72: =D72 -> 0
B73: Applied this Month | C73: No | D73: 0 | E73: 0 | F73: 0 | G73: 0 | H73: 0 | M73: 0 | P73: =SUM(D73:O73) -> 0
B74: Done this Month Postpaid | C74: No | D74: 0 | E74: 0 | F74: 0 | G74: 0 | H74: 0 | M74: 0 | P74: =SUM(D74:O74) -> 0
B75: Done this Month Prepaid | C75: No | D75: 0 | E75: 0 | F75: 0 | G75: 0 | H75: 0 | M75: 0 | P75: =SUM(D75:O75) -> 0
B76: Total Done | C76: No | D76: =D74+D75 -> 0 | E76: =E74+E75 -> 0 | F76: =F74+F75 -> 0 | G76: =G74+G75 -> 0 | H76: =H74+H75 -> 0 | I76: =I74+I75 -> 0 | J76: =J74+J75 -> 0 | K76: =K74+K75 -> 0 | L76: =L74+L75 -> 0 | M76: 0 | N76: =N74+N75 -> 0 | O76: 0 | P76: =SUM(D76:O76) -> 0
B77: Carried Forward | C77: No | D77: =D73+D74-D76 -> 0 | E77: =E73+E74-E76 -> 0 | F77: =F73+F74-F76 -> 0 | G77: =G73+G74-G76 -> 0 | H77: =H73+H74-H76 -> 0 | I77: =I72+I73-I76 -> 0 | J77: =J72+J73-J76 -> 0 | K77: =K72+K73-K76 -> 0 | L77: =L72+L73-L76 -> 0 | M77: 0 | N77: =N72+N73-N76 -> 0 | O77: 0 | P77: =P72+P73-P76 -> 0
A78: New Commercial/Industrial Water Connections | B78: Brought Forward | C78: No | D78: 0 | E78: =D83 -> 0 | F78: =E83 -> 0 | G78: =F83 -> 0 | H78: =G83 -> 0 | M78: 0 | P78: =D78 -> 0
B79: Applied this Month | C79: No | D79: 0 | E79: 0 | F79: 0 | G79: 0 | H79: 0 | M79: 0 | P79: =SUM(D79:O79) -> 0
B80: Done this Month Postpaid | C80: No | D80: 0 | E80: 0 | F80: 0 | G80: 0 | H80: 0 | M80: 0 | P80: =SUM(D80:O80) -> 0
B81: Done this Month Prepaid | C81: No | D81: 0 | E81: 0 | F81: 0 | G81: 0 | H81: 0 | M81: 0 | P81: =SUM(D81:O81) -> 0
B82: Total Done | C82: No | D82: =D81+D80 -> 0 | E82: =E81+E80 -> 0 | F82: =F81+F80 -> 0 | G82: =G81+G80 -> 0 | H82: =H81+H80 -> 0 | I82: =I81+I80 -> 0 | J82: =J81+J80 -> 0 | K82: =K81+K80 -> 0 | L82: =L81+L80 -> 0 | M82: 0 | N82: =N81+N80 -> 0 | O82: 0 | P82: =P81+P80 -> 0
B83: Carried Forward | C83: No | D83: =D78+D79-D82 -> 0 | E83: =E78+E79-E82 -> 0 | F83: =F78+F79-F82 -> 0 | G83: =G78+G79-G82 -> 0 | H83: =H78+H79-H82 -> 0 | I83: =I78+I79-I82 -> 0 | J83: =J78+J79-J82 -> 0 | K83: =K78+K79-K82 -> 0 | L83: =L78+L79-L82 -> 0 | M83: 0 | N83: =N78+N79-N82 -> 0 | O83: 0 | P83: =P78+P79-P82 -> 0
A84: New CWP | B84: Brought Forward | C84: No | D84: 0 | E84: =D89 -> 0 | F84: =E89 -> 0 | G84: =F89 -> 0 | H84: =G89 -> 0 | M84: 0 | P84: =D84 -> 0
B85: Applied this Month | C85: No | D85: 0 | E85: 0 | F85: 0 | G85: 0 | H85: 0 | M85: 0 | P85: =SUM(D85:O85) -> 0
B86: Done this Month Postpaid | C86: No | D86: 0 | E86: 0 | F86: 0 | G86: 0 | H86: 0 | M86: 0 | P86: =SUM(D86:O86) -> 0
B87: Done this Month Prepaid | C87: No | D87: 0 | E87: 0 | F87: 0 | G87: 0 | H87: 0 | M87: 0 | P87: =SUM(D87:O87) -> 0
B88: Total Done | C88: No | D88: =D86+D87 -> 0 | E88: =E86+E87 -> 0 | F88: =F86+F87 -> 0 | G88: =G86+G87 -> 0 | H88: =H86+H87 -> 0 | I88: 0 | J88: 0 | K88: 0 | L88: 0 | M88: 0 | N88: 0 | O88: 0 | P88: =SUM(D88:O88) -> 0
B89: Carried Forward | C89: No | D89: =D84+D85-D88 -> 0 | E89: =E84+E85-E88 -> 0 | F89: =F84+F85-F88 -> 0 | G89: =G84+G85-G88 -> 0 | H89: =H84+H85-H88 -> 0 | I89: =I84+I85-I88 -> 0 | J89: =J84+J85-J88 -> 0 | K89: =K84+K85-K88 -> 0 | L89: =L84+L85-L88 -> 0 | M89: 0 | N89: =N84+N85-N88 -> 0 | O89: 0 | P89: =P84+P85-P88 -> 0
A90: Aggregated New Water connections | B90: Brought Forward | C90: No | D90: =D66+D72+D78+D84 -> 5 | E90: =E66+E72+E78+E84 -> 10 | F90: =F66+F72+F78+F84 -> 5 | G90: =G66+G72+G78+G84 -> 9 | H90: =H66+H72+H78+H84 -> 8 | I90: =I66+I72+I78+I84 -> 11 | J90: =J66+J72+J78+J84 -> 9 | K90: =K66+K72+K78+K84 -> 5 | ... N90: =N66+N72+N78+N84 -> 8 | O90: 7 | P90: =D90 -> 5
B91: Applied this Month | C91: No | D91: =D67+D73+D79+D85 -> 5 | E91: =E67+E73+E79+E85 -> 11 | F91: =F67+F73+F79+F85 -> 5 | G91: =G67+G73+G79+G85 -> 0 | H91: =H67+H73+H79+H85 -> 6 | I91: =I67+I73+I79+I85 -> 1 | J91: =J67+J73+J79+J85 -> 0 | K91: =K67+K73+K79+K85 -> 6 | ... N91: =N67+N73+N79+N85 -> 1 | O91: 1 | P91: =SUM(D91:O91) -> 47
B92: Done this Month Postpaid | C92: No | D92: =D68+D74+D80+D86 -> 0 | E92: =E68+E74+E80+E86 -> 8 | F92: =F68+F74+F80+F86 -> 1 | G92: =G68+G74+G80+G86 -> 1 | H92: =H68+H74+H80+H86 -> 3 | I92: =I68+I74+I80+I86 -> 3 | J92: =J68+J74+J80+J86 -> 2 | K92: =K68+K74+K80+K86 -> 8 | ... N92: =N68+N74+N80+N86 -> 2 | O92: 3 | P92: =SUM(D92:O92) -> 37
B93: Done this Month Prepaid | D93: =D69+D75+D81+D87 -> 0 | E93: =E69+E75+E81+E87 -> 8 | F93: =F69+F75+F81+F87 -> 0 | G93: =G69+G75+G81+G87 -> 0 | H93: =H69+H75+H81+H87 -> 0 | I93: =I69+I75+I81+I87 -> 0 | J93: =J69+J75+J81+J87 -> 0 | K93: =K69+K75+K81+K87 -> 0 | ... N93: =N69+N75+N81+N87 -> 0 | O93: 0 | P93: =SUM(D93:O93) -> 8
B94: Total Done | C94: No | D94: =D93+D92 -> 0 | E94: =E93+E92 -> 16 | F94: =F93+F92 -> 1 | G94: =G93+G92 -> 1 | H94: =H93+H92 -> 3 | I94: =I93+I92 -> 3 | J94: =J93+J92 -> 2 | K94: =K93+K92 -> 8 | ... N94: =N93+N92 -> 2 | O94: 3 | P94: =P93+P92 -> 45
B95: Carried Forward | C95: No | D95: =D90+D91-D94 -> 10 | E95: =E90+E91-E94 -> 5 | F95: =F90+F91-F94 -> 9 | G95: =G90+G91-G94 -> 8 | H95: =H90+H91-H94 -> 11 | I95: =I90+I91-I94 -> 9 | J95: =J90+J91-J94 -> 7 | K95: =K90+K91-K94 -> 3 | ... N95: =N90+N91-N94 -> 7 | O95: 5 | P95: =P90+P91-P94 -> 7
A97: Prepaid Metering
A98: Prepaid Meters Installed | C98: No | D98: 0 | E98: 8 | F98: 0 | G98: 0 | H98: 0 | I98: 6 | J98: 0 | P98: =SUM(D98:O98) -> 14
A100: Active and Disconnected Accounts
A101: Disconnected Individual Accounts | C101: No | D101: 19 | E101: 19 | F101: 17 | G101: 17 | H101: 17 | I101: 18 | J101: 21 | K101: 21 | L101: 22 | M101: 24 | N101: 25 | O101: 25 | P101: =O101 -> 25
A102: Disconnected institutional Accounts | C102: No | D102: 1 | E102: 1 | F102: 1 | G102: 1 | H102: 1 | I102: 1 | J102: 1 | K102: 1 | L102: 1 | M102: 1 | N102: 1 | O102: 1 | P102: =O102 -> 1
A103: Disconnected Commercial/Industrial Accounts | C103: No | D103: 11 | E103: 11 | F103: 11 | G103: 11 | H103: 11 | I103: 11 | J103: 11 | K103: 11 | L103: 11 | M103: 11 | N103: 11 | O103: 11 | P103: =O103 -> 11
A104: Disconnected CWP | C104: No | D104: 0 | E104: 0 | F104: 0 | J104: 0 | K104: 0 | L104: 0 | N104: 0 | O104: 0 | P104: =O104 -> 0
A105: Total Disconnected Accounts | C105: No | D105: =SUM(D101:D104) -> 31 | E105: =SUM(E101:E104) -> 31 | F105: =SUM(F101:F104) -> 29 | G105: =SUM(G101:G104) -> 29 | H105: =SUM(H101:H104) -> 29 | I105: =SUM(I101:I104) -> 30 | J105: =SUM(J101:J104) -> 33 | K105: =SUM(K101:K104) -> 33 | ... N105: =SUM(N101:N104) -> 37 | O105: 37 | P105: =O105 -> 37
A106: Postpaid Consumers
...

Sheet Phalombe
A1: SOUTHERN REGION WATER BOARD
A3: MONTHLY REPORTS - 2023/2024
A4: MULANJE ZONE
A5: MULANJE ZONE
A7: PARAMETERS | C7: UNITS | D7: APRIL | E7: MAY | F7: JUNE | G7: JULY | H7: AUGUST | I7: SEPTEMBER | J7: OCTOBER | K7: NOVEMBER | L7: DECEMBER | M7: JANUARY | N7: FEBRUARY | O7: MARCH | P7: TOTALS
A8: PRODUCTION
A9: Volume Produced | C9: m3 | D9: 8853 | E9: 17966 | F9: 13530 | G9: 8346 | H9: 11917 | I9: 10995 | J9: 10454 | K9: 10025 | L9: 9226 | M9: 9471 | N9: 9893 | O9: 8353 | P9: =SUM(D9:O9) -> 129029
A10: REVENUE WATER - POSTPAID
A11: Volume Billed Individuals | C11: m3 | D11: =4+512+3329 -> 3845 | E11: =7+766+13396 -> 14169 | F11: =7+789+4099 -> 4895 | G11: =8+693+3910 -> 4611 | H11: =24+705+4340 -> 5069 | I11: =10+753+5193 -> 5956 | J11: 5657 | K11: 5700 | L11: 5045 | M11: 4578 | N11: =5+593+4185 -> 4783 | O11: 4288 | P11: =SUM(D11:O11) -> 68596
A12: Volume Billed CWPs | C12: m3 | D12: 0 | E12: 0 | F12: 0 | G12: 0 | H12: 0 | I12: 0 | J12: 0 | K12: 0 | L12: 0 | M12: 0 | N12: 0 | O12: 0 | P12: =SUM(D12:O12) -> 0
A13: Volume Billed Institutions | C13: m3 | D13: 352 | E13: 480 | F13: 401 | G13: 63 | H13: 27 | I13: 32 | J13: 33 | K13: 31 | L13: 9 | M13: 10 | N13: 26 | O13: 14 | P13: =SUM(D13:O13) -> 1478
A14: Volume Billed Commercial/Industrial | C14: m3 | D14: 53 | E14: 53 | F14: 37 | G14: 47 | H14: 45 | I14: 37 | J14: 45 | K14: 17 | L14: 21 | M14: 23 | N14: 21 | O14: 23 | P14: =SUM(D14:O14) -> 422
A15: Total Volume Billed Post Paid | C15: m3 | D15: =SUM(D11:D14) -> 4250 | E15: =SUM(E11:E14) -> 14702 | F15: =SUM(F11:F14) -> 5333 | G15: =SUM(G11:G14) -> 4721 | H15: =SUM(H11:H14) -> 5141 | I15: =SUM(I11:I14) -> 6025 | J15: =SUM(J11:J14) -> 5735 | K15: =SUM(K11:K14) -> 5748 | ... N15: =SUM(N11:N14) -> 4830 | O15: 4325 | P15: =SUM(P11:P14) -> 70496
A16: REVENUE WATER - PREPAID
A17: Individuals | C17: m3 | D17: 738 | E17: =2+684 -> 686 | F17: 911 | G17: =783 -> 783 | H17: 1421.4 | I17: 802 | J17: 992.1 | K17: =19+896.2 -> 915.2 | L17: 858 | M17: 1684 | N17: 430.3 | O17: 785.7 | P17: =SUM(D17:O17) -> 11006.7 | Q17: =P17/14458% -> 76.128787
A18: CWPs | C18: m3 | D18: 0 | E18: 0 | F18: 0 | G18: 0 | H18: 0 | I18: 0 | J18: 0 | K18: 0 | L18: 0 | M18: 0 | O18: 0 | P18: =SUM(D18:O18) -> 0 | Q18: =P18/14458% -> 0
A19: Institutions | C19: m3 | D19: =864+27 -> 891 | E19: 118 | F19: 3803 | G19: 92 | H19: 978 | I19: 148 | J19: =48 -> 48 | K19: 108 | L19: 90 | M19: 384 | N19: 2104 | O19: 224 | P19: =SUM(D19:O19) -> 8988 | Q19: =P19/14458% -> 62.166275
A20: Commercial/Industrial | C20: m3 | D20: 102 | E20: 72 | F20: =4981-4848 -> 133 | G20: 37 | H20: 53.6 | I20: 51 | J20: =65.6+5 -> 70.6 | K20: 76.3 | L20: 37 | M20: 76 | N20: 63 | O20: 65 | P20: =SUM(D20:O20) -> 836.5 | Q20: =P20/14458% -> 5.7857242
A21: Total Volume Prepaid | C21: m3 | D21: =SUM(D17:D20) -> 1731 | E21: =SUM(E17:E20) -> 876 | F21: =SUM(F17:F20) -> 4847 | G21: =SUM(G17:G20) -> 912 | H21: =SUM(H17:H20) -> 2453 | I21: =SUM(I17:I20) -> 1001 | J21: =SUM(J17:J20) -> 1110.7 | K21: =SUM(K17:K20) -> 1099.5 | ... N21: =SUM(N17:N20) -> 2597.3 | O21: 1074.7 | P21: =SUM(P17:P20) -> 20831.2 | Q21: =P21/14458% -> 144.08079
A22: TOTAL REVENUE WATER | C22: m3 | D22: =D21+D15 -> 5981 | E22: =E21+E15 -> 15578 | F22: =F21+F15 -> 10180 | G22: =G21+G15 -> 5633 | H22: =H21+H15 -> 7594 | I22: =I21+I15 -> 7026 | J22: =J21+J15 -> 6845.7 | K22: =K21+K15 -> 6847.5 | ... N22: =N21+N15 -> 7427.3 | O22: 5399.7 | P22: =P21+P15 -> 91327.2
A24: Non-Revenue Water (NRW) | B24: Volume | C24: m3 | D24: =D9-D22 -> 2872 | E24: =E9-E22 -> 2388 | F24: =F9-F22 -> 3350 | G24: =G9-G22 -> 2713 | H24: =H9-H22 -> 4323 | I24: =I9-I22 -> 3969 | J24: =J9-J22 -> 3608.3 | K24: =K9-K22 -> 3177.5 | ... N24: =N9-N22 -> 2465.7 | O24: 2953.3 | P24: =P9-P22 -> 37701.8
B25: Percentage | C25: % | D25: =D24/D9 -> 0.3244098 | E25: =E24/E9 -> 0.13291773 | F25: =F24/F9 -> 0.24759793 | G25: =G24/G9 -> 0.3250659 | H25: =H24/H9 -> 0.36275908 | I25: =I24/I9 -> 0.36098226 | J25: =J24/J9 -> 0.34515975 | K25: =K24/K9 -> 0.31695761 | ... N25: =N24/N9 -> 0.24923683 | O25: 0.35356159 | P25: =P24/P9 -> 0.29219633
A26: OPERATING EXPENSES
A27: Chemicals
A28: Chemical | B28: Rate(MK/kg)
A29: Chlorine | B29: 5111.67 | C29: kg | D29: 30 | E29: 31 | F29: 30 | G29: 30 | H29: 25 | I29: 24 | J29: 24 | K29: 24 | L29: 24 | M29: 24 | N29: 24 | O29: 24 | P29: =SUM(D29:O29) -> 314
C30: kg/mg litre | D30: =D29/(D9/1000) -> 3.3886818 | E30: =E29/(E9/1000) -> 1.7254815 | F30: =F29/(F9/1000) -> 2.2172949 | G30: =G29/(G9/1000) -> 3.5945363 | H30: =H29/(H9/1000) -> 2.0978434 | I30: =I29/(I9/1000) -> 2.1828104 | J30: =J29/(J9/1000) -> 2.295772 | K30: =K29/(K9/1000) -> 2.394015 | L30: 2.601344 | M30: =M29/(M9/1000) -> 2.5340513 | N30: =N29/(N9/1000) -> 2.4259577 | O30: 2.8732192 | P30: =P29/(P9/1000) -> 2.4335614
A31: Aluminium sulphate | B31: 1537 | C31: kg | P31: =SUM(D31:O31) -> 0
C32: kg/mg litre | D32: =D31/(D9/1000) -> 0 | E32: =E31/(E9/1000) -> 0 | F32: =F31/(F9/1000) -> 0 | G32: =G31/(G9/1000) -> 0 | H32: =H31/(H9/1000) -> 0 | I32: =I31/(I9/1000) -> 0 | J32: =J31/(J9/1000) -> 0 | K32: =K31/(K9/1000) -> 0 | ... N32: =N31/(N9/1000) -> 0 | O32: 0 | P32: =P31/(P9/1000) -> 0
A33: Soda | B33: 1781.02 | C33: kg | P33: =SUM(D33:O33) -> 0
C34: kg/mg litre | D34: =D33/(D9/1000) -> 0 | E34: =E33/(E9/1000) -> 0 | F34: =F33/(F9/1000) -> 0 | G34: =G33/(G9/1000) -> 0 | H34: =H33/(H9/1000) -> 0 | I34: =I33/(I9/1000) -> 0 | J34: =J33/(J9/1000) -> 0 | K34: =K33/(K9/1000) -> 0 | ... N34: =N33/(N9/1000) -> 0 | O34: 0 | P34: =P33/(P9/1000) -> 0
A35: Algae floc | B35: 5979.95 | C35: litres
C36: litres/mg litre
A37: Sud floc | B37: 5403.75 | C37: litres | D37: 0 | E37: 0 | F37: 0 | G37: 0 | H37: 0 | I37: 0 | J37: 0 | K37: 0 | L37: 0 | M37: 0 | N37: 0 | O37: 0 | P37: =SUM(D37:O37) -> 0
C38: litres/mg litre | D38: =D37/(D9/1000) -> 0 | E38: =E37/(E9/1000) -> 0 | F38: =F37/(F9/1000) -> 0 | G38: =G37/(G9/1000) -> 0 | H38: =H37/(H9/1000) -> 0 | I38: =I37/(I9/1000) -> 0 | J38: =J37/(J9/1000) -> 0 | K38: =K37/(K9/1000) -> 0 | ... N38: =N37/(N9/1000) -> 0 | O38: 0 | P38: =P37/(P9/1000) -> 0
A39: Potasium permanganate | B39: 1950 | C39: kg | D39: 0 | E39: 0 | F39: 0 | G39: 0 | H39: 0 | I39: 0 | J39: 0 | K39: 0 | L39: 0 | M39: 0 | N39: 0 | O39: 0 | P39: =SUM(D39:O39) -> 0
C40: kg/mg litre | D40: =D39/(D9/1000) -> 0 | E40: =E39/(E9/1000) -> 0 | F40: =F39/(F9/1000) -> 0 | G40: =G39/(G9/1000) -> 0 | H40: =H39/(H9/1000) -> 0 | I40: =I39/(I9/1000) -> 0 | J40: =J39/(J9/1000) -> 0 | K40: =K39/(K9/1000) -> 0 | ... N40: =N39/(N9/1000) -> 0 | O40: 0 | P40: =P39/(P9/1000) -> 0
A41: Cost of Chemicals | C41: Mk | D41: =(D29*$B29)+(D31*$B31)+(D33*$B33)+(D35*$B35)+(D37*$B37)+(D39*$B39) -> 153350.1 | E41: =(E29*$B29)+(E31*$B31)+(E33*$B33)+(E35*$B35)+(E37*$B37)+(E39*$B39) -> 158461.77 | F41: =(F29*$B29)+(F31*$B31)+(F33*$B33)+(F35*$B35)+(F37*$B37)+(F39*$B39) -> 153350.1 | G41: =(G29*$B29)+(G31*$B31)+(G33*$B33)+(G35*$B35)+(G37*$B37)+(G39*$B39) -> 153350.1 | H41: =(H29*$B29)+(H31*$B31)+(H33*$B33)+(H35*$B35)+(H37*$B37)+(H39*$B39) -> 127791.75 | I41: =(I29*$B29)+(I31*$B31)+(I33*$B33)+(I35*$B35)+(I37*$B37)+(I39*$B39) -> 122680.08 | J41: =(J29*$B29)+(J31*$B31)+(J33*$B33)+(J35*$B35)+(J37*$B37)+(J39*$B39) -> 122680.08 | K41: =(K29*$B29)+(K31*$B31)+(K33*$B33)+(K35*$B35)+(K37*$B37)+(K39*$B39) -> 122680.08 | ... N41: =(N29*$B29)+(N31*$B31)+(N33*$B33)+(N35*$B35)+(N37*$B37)+(N39*$B39) -> 122680.08 | O41: 122680.08 | P41: =SUM(D41:O41) -> 1605064.4
A42: Cost/vol. Produced (chemicals) | C42: Mk/m3 | D42: =D41/D9 -> 17.321823 | E42: =E41/E9 -> 8.8200918 | F42: =F41/F9 -> 11.33408 | G42: =G41/G9 -> 18.374083 | H42: =H41/H9 -> 10.723483 | I42: =I41/I9 -> 11.157806 | J42: =J41/J9 -> 11.735229 | K42: =K41/K9 -> 12.237414 | ... N42: =N41/N9 -> 12.400695 | O42: 14.686948 | P42: =P41/P9 -> 12.439563
A43: Power
A44: Power Usage | C44: Kw | D44: 1461.78 | E44: 1662.36 | F44: 1424.83 | G44: 0 | P44: =SUM(D44:O44) -> 4548.97
A45: Power/ Vol. Produced | C45: Kw/m3 | D45: =D44/D9 -> 0.16511691 | E45: =E44/E9 -> 0.092528109 | F45: =F44/F9 -> 0.10530894 | G45: =G44/G9 -> 0 | H45: =H44/H9 -> 0 | I45: =I44/I9 -> 0 | J45: =J44/J9 -> 0 | K45: =K44/K9 -> 0 | ... N45: =N44/N9 -> 0 | O45: 0 | P45: =P44/P9 -> 0.035255408
A46: Cost of Power | C46: Mk | D46: =1.165*(14100+(D44*119.1)) -> 219250.67 | E46: =1.165*(14100+(E44*119.1)) -> 247081.44 | F46: =1.165*(14100+(F44*119.1)) -> 214123.8 | G46: =122.92*G44 -> 0 | H46: 0 | I46: =1.165*(14100+(I44*119.1)) -> 16426.5 | J46: =1.165*(14100+(J44*119.1)) -> 16426.5 | K46: =1.165*(14100+(K44*119.1)) -> 16426.5 | L46: =1.165*(14100+(L44*119.1)) -> 16426.5 | M46: =1.165*(14100+(M44*119.1)) -> 16426.5 | N46: =1.165*(14100+(N44*119.1)) -> 16426.5 | O46: 16426.5 | P46: =SUM(D46:O46) -> 795441.41
A47: Cost/vol. Produced | C47: Mk/m3 | D47: =D46/D9 -> 24.765692 | E47: =E46/E9 -> 13.752724 | F47: =F46/F9 -> 15.825854 | G47: =G46/G9 -> 0 | H47: =H46/H9 -> 0 | I47: =I46/I9 -> 1.4939973 | J47: =J46/J9 -> 1.5713124 | K47: =K46/K9 -> 1.6385536 | ... N47: =N46/N9 -> 1.6604165 | O47: 1.966539 | P47: =P46/P9 -> 6.1648266
A48: Plant and Vehicle Maintenance
A49: Distances covered | C49: km | D49: 0 | E49: 0 | F49: 0 | P49: =SUM(D49:O49) -> 0
A50: Fuel Used (litres) | C50: litres | D50: =D49/D14 -> 0 | E50: =E49/E14 -> 0 | F50: =F49/F14 -> 0 | P50: =SUM(D50:O50) -> 0
A51: Cost of fuel | C51: Mk | D51: =122.92*D49 -> 0 | E51: =122.92*E49 -> 0 | F51: =122.92*F49 -> 0 | P51: =SUM(D51:O51) -> 0
A52: Maintenance | C52: Mk | D52: 0 | E52: 0 | F52: 0 | G52: 0 | H52: 0 | I52: 0 | J52: 0 | K52: 0 | L52: 0 | M52: 0 | N52: 0 | O52: 0 | P52: 0
A53: Salaries and Wages
A54: Staff Costs | C54: MK | D54: 1750757.7 | E54: 1942624.2 | F54: 1896374.2 | G54: =AVERAGE(D54:F54) -> 1863252.1 | H54: 1789263.9 | I54: =AVERAGE(D54:H54) -> 1848454.4 | J54: 1811843.3 | K54: 1864452.3 | L54: 2050897.5 | M54: 3872791.7 | N54: 2901325.9 | O54: 2825711 | P54: =SUM(D54:O54) -> 26417748
A55: Wages | C55: MK | D55: 420056.31 | E55: 461087 | F55: 412831.22 | G55: =AVERAGE(D55:F55) -> 431324.84 | H55: 408875.62 | I55: =AVERAGE(D55:H55) -> 426835 | J55: 396977.8 | K55: 403872.26 | L55: 434692 | M55: 721527.84 | O55: 653326 | P55: =SUM(D55:O55) -> 5171405.9
A56: Other Overhead Costs | C56: MK | D56: 167915 | E56: 189700 | F56: 158960 | G56: =AVERAGE(D56:F56) -> 172191.67 | H56: 162367.56 | I56: =AVERAGE(D56:H56) -> 170226.85 | J56: =AVERAGE(G56:I56) -> 168262.02 | K56: 172400 | L56: 189082.62 | M56: 174992.87 | N56: 76000 | O56: 18600 | P56: =SUM(D56:O56) -> 1820698.6
A57: Operating Costs
A58: Total Operating Costs | C58: MK | D58: =D41+D46+D51+D52+D54+D55+D56 -> 2711329.8 | E58: =E41+E46+E51+E52+E54+E55+E56 -> 2998954.4 | F58: =F41+F46+F51+F52+F54+F55+F56 -> 2835639.4 | G58: =G41+G46+G51+G52+G54+G55+G56 -> 2620118.7 | H58: =H41+H46+H51+H52+H54+H55+H56 -> 2488298.8 | I58: =I41+I46+I51+I52+I54+I55+I56 -> 2584622.9 | J58: =J41+J46+J51+J52+J54+J55+J56 -> 2516189.7 | K58: =K41+K46+K51+K52+K54+K55+K56 -> 2579831.2 | ... N58: =N41+N46+N51+N52+N54+N55+N56 -> 3116432.5 | O58: 3636743.6 | P58: =SUM(D58:O58) -> 35810359
A59: Cost/Vol. Produced | C59: Mk/m3 | D59: =D58/D9 -> 306.26113 | E59: =E58/E9 -> 166.92388 | F59: =F58/F9 -> 209.58162 | G59: =G58/G9 -> 313.93706 | H59: =H58/H9 -> 208.80245 | I59: =I58/I9 -> 235.07257 | J59: =J58/J9 -> 240.69157 | K59: =K58/K9 -> 257.33977 | ... N59: =N58/N9 -> 315.0139 | O59: 435.38173 | P59: =P58/P9 -> 277.53729
A60: Cost/Vol. Billed | C60: Mk/m3 | D60: =D58/D22 -> 453.32383 | E60: =E58/E22 -> 192.51216 | F60: =F58/F22 -> 278.55004 | G60: =G58/G22 -> 465.13735 | H60: =H58/H22 -> 327.66643 | I60: =I58/I22 -> 367.86548 | J60: =J58/J22 -> 367.55769 | K60: =K58/K22 -> 376.75519 | ... N60: =N58/N22 -> 419.59158 | O60: 673.50845 | P60: =P58/P22 -> 392.11055
A61: Permanent Staff Employed | C61: No | D61: 4 | E61: 4 | F61: 4 | G61: 4 | H61: 4 | I61: 4 | J61: 4 | K61: 4 | L61: 5 | M61: 5 | N61: 5 | O61: 5 | P61: =O61 -> 5
A62: Staff/Vol.1000m3 of Volume Produced/hour (12 hour day) | C62: No/1000m3 | D62: =(D61*1000*31)/D9 -> 14.006551 | E62: =(E61*1000*31)/E9 -> 6.9019259 | F62: =(F61*1000*31)/F9 -> 9.1648189 | G62: =(G61*1000*31)/G9 -> 14.857417 | H62: =(H61*1000*31)/H9 -> 10.405303 | I62: =(I61*1000*31)/I9 -> 11.277854 | J62: =(J61*1000*31)/J9 -> 11.861488 | K62: =(K61*1000*31)/K9 -> 12.369077 | ... N62: =(N61*1000*31)/N9 -> 15.667644 | O62: 18.556207 | P62: =(P61*1000*31)/P9 -> 1.2012803
A63: Temporary Staff Employed | C63: No | D63: 12 | E63: 7 | F63: 7 | G63: 7 | H63: 7 | I63: 7 | J63: 7 | K63: 7 | L63: 7 | M63: 8 | N63: 8 | O63: 8 | P63: =SUM(D63:O63) -> 92
A65: Water Connections and Disconnections
A66: New Individual Water Connections | B66: Brought Forward | C66: No | D66: 78 | E66: =D71 -> 78 | F66: =E71 -> 78 | G66: =F71 -> 52 | H66: =G71 -> 39 | I66: =H71 -> 34 | J66: =I71 -> 29 | K66: =J71 -> 46 | L66: 46 | M66: 45 | N66: =M71 -> 46 | O66: 48 | P66: =D66 -> 78
B67: Applied this Month | C67: No | D67: 4 | E67: 5 | F67: 2 | G67: 1 | H67: 1 | I67: 1 | J67: 19 | K67: 0 | L67: 0 | M67: 1 | N67: 2 | O67: 1 | P67: =SUM(D67:O67) -> 37
B68: Done this Month Postpaid | C68: No | D68: 4 | E68: 5 | F68: 3 | G68: 8 | H68: 6 | I68: 5 | J68: 2 | K68: 0 | L68: 0 | M68: 0 | N68: 0 | O68: 4 | P68: =SUM(D68:O68) -> 37
B69: Done this Month Prepaid | C69: No | D69: 0 | E69: 0 | F69: 25 | G69: 6 | H69: 0 | I69: 1 | J69: 0 | K69: 0 | L69: 1 | M69: 0 | N69: 0 | O69: 0 | P69: =SUM(D69:O69) -> 33
B70: Total Done | C70: No | D70: =D68+D69 -> 4 | E70: =E68+E69 -> 5 | F70: =F68+F69 -> 28 | G70: =G68+G69 -> 14 | H70: =H68+H69 -> 6 | I70: =I68+I69 -> 6 | J70: =J68+J69 -> 2 | K70: =K68+K69 -> 0 | L70: 1 | M70: 0 | N70: =N68+N69 -> 0 | O70: 4 | P70: =P68+P69 -> 70
B71: Carried Forward | C71: No | D71: =D66+D67-D70 -> 78 | E71: =E66+E67-E70 -> 78 | F71: =F66+F67-F70 -> 52 | G71: =G66+G67-G70 -> 39 | H71: =H66+H67-H70 -> 34 | I71: =I66+I67-I70 -> 29 | J71: =J66+J67-J70 -> 46 | K71: =K66+K67-K70 -> 46 | L71: 45 | M71: 46 | N71: =N66+N67-N70 -> 48 | O71: 45 | P71: =P66+P67-P70 -> 45
A72: New Institutional Water Connections | B72: Brought Forward | C72: No | D72: 0 | E72: =D77 -> 0 | F72: =E77 -> 0 | G72: =F77 -> 0 | H72: =G77 -> 0 | M72: 0 | O72: 4 | P72: =D72 -> 0
B73: Applied this Month | C73: No | D73: 0 | F73: 0 | G73: 0 | H73: 0 | M73: 0 | O73: 0 | P73: =SUM(D73:O73) -> 0
B74: Done this Month Postpaid | C74: No | D74: 0 | F74: 0 | G74: 0 | H74: 0 | M74: 0 | O74: 0 | P74: =SUM(D74:O74) -> 0
B75: Done this Month Prepaid | C75: No | D75: 0 | F75: 0 | G75: 0 | H75: 0 | M75: 0 | O75: 0 | P75: =SUM(D75:O75) -> 0
B76: Total Done | C76: No | D76: =D74+D75 -> 0 | E76: =E74+E75 -> 0 | F76: =F74+F75 -> 0 | G76: =G74+G75 -> 0 | H76: =H74+H75 -> 0 | I76: =I74+I75 -> 0 | J76: =J74+J75 -> 0 | K76: =K74+K75 -> 0 | L76: =L74+L75 -> 0 | M76: 0 | N76: =N74+N75 -> 0 | O76: 0 | P76: =P74+P75 -> 0
B77: Carried Forward | C77: No | D77: =D73+D74-D76 -> 0 | E77: =E73+E74-E76 -> 0 | F77: =F73+F74-F76 -> 0 | G77: =G73+G74-G76 -> 0 | H77: =H73+H74-H76 -> 0 | I77: =I72+I73-I76 -> 0 | J77: =J72+J73-J76 -> 0 | K77: =K72+K73-K76 -> 0 | L77: =L72+L73-L76 -> 0 | M77: 0 | N77: =N72+N73-N76 -> 0 | O77: 4 | P77: =P72+P73-P76 -> 0
A78: New Commercial/Industrial Water Connections | B78: Brought Forward | C78: No | D78: 4 | E78: =D83 -> 4 | F78: =E83 -> 4 | G78: =F83 -> 4 | H78: =G83 -> 4 | I78: =H83 -> 4 | J78: =I83 -> 4 | K78: =J83 -> 4 | L78: 4 | M78: 4 | N78: =M83 -> 4 | P78: =D78 -> 4
B79: Applied this Month | C79: No | D79: 0 | E79: 0 | F79: 0 | G79: 0 | H79: 0 | L79: 0 | M79: 0 | N79: 0 | P79: =SUM(D79:O79) -> 0
B80: Done this Month Postpaid | C80: No | D80: 0 | E80: 0 | F80: 0 | G80: 0 | H80: 0 | L80: 0 | M80: 0 | N80: 0 | P80: =SUM(D80:O80) -> 0
B81: Done this Month Prepaid | C81: No | D81: 0 | E81: 0 | F81: 0 | G81: 0 | H81: 0 | L81: 0 | M81: 0 | N81: 0 | P81: =SUM(D81:O81) -> 0
B82: Total Done | C82: No | D82: =D81+D80 -> 0 | E82: =E81+E80 -> 0 | F82: =F81+F80 -> 0 | G82: =G81+G80 -> 0 | H82: =H81+H80 -> 0 | I82: =I81+I80 -> 0 | J82: =J81+J80 -> 0 | K82: =K81+K80 -> 0 | L82: 0 | M82: 0 | N82: =N81+N80 -> 0 | O82: 0 | P82: =P81+P80 -> 0
B83: Carried Forward | C83: No | D83: =D78+D79-D82 -> 4 | E83: =E78+E79-E82 -> 4 | F83: =F78+F79-F82 -> 4 | G83: =G78+G79-G82 -> 4 | H83: =H78+H79-H82 -> 4 | I83: =I78+I79-I82 -> 4 | J83: =J78+J79-J82 -> 4 | K83: =K78+K79-K82 -> 4 | L83: 4 | M83: 4 | N83: =N78+N79-N82 -> 4 | O83: 0 | P83: =P78+P79-P82 -> 4
A84: New CWP | B84: Brought Forward | C84: No | D84: 0 | E84: =D89 -> 0 | F84: =E89 -> 0 | G84: =F89 -> 0 | H84: =G89 -> 0 | M84: 0 | P84: =D84 -> 0
B85: Applied this Month | C85: No | D85: 0 | E85: 0 | F85: 0 | G85: 0 | H85: 0 | M85: 0 | P85: =SUM(D85:O85) -> 0
B86: Done this Month Postpaid | C86: No | D86: 0 | E86: 0 | F86: 0 | G86: 0 | H86: 0 | M86: 0 | P86: =SUM(D86:O86) -> 0
B87: Done this Month Prepaid | C87: No | D87: 0 | E87: 0 | F87: 0 | G87: 0 | H87: 0 | M87: 0 | P87: =SUM(D87:O87) -> 0
B88: Total Done | C88: No | D88: =D86+D87 -> 0 | E88: =E86+E87 -> 0 | F88: =F86+F87 -> 0 | G88: =G86+G87 -> 0 | H88: =H86+H87 -> 0 | I88: 0 | J88: 0 | K88: 0 | L88: 0 | M88: 0 | N88: 0 | O88: 0 | P88: =SUM(D88:O88) -> 0
B89: Carried Forward | C89: No | D89: =D84+D85-D88 -> 0 | E89: =E84+E85-E88 -> 0 | F89: =F84+F85-F88 -> 0 | G89: =G84+G85-G88 -> 0 | H89: =H84+H85-H88 -> 0 | I89: =I84+I85-I88 -> 0 | J89: =J84+J85-J88 -> 0 | K89: =K84+K85-K88 -> 0 | L89: =L84+L85-L88 -> 0 | M89: 0 | N89: =N84+N85-N88 -> 0 | O89: 0 | P89: =P84+P85-P88 -> 0
A90: Aggregated New Water connections | B90: Brought Forward | C90: No | D90: =D66+D72+D78+D84 -> 82 | E90: =E66+E72+E78+E84 -> 82 | F90: =F66+F72+F78+F84 -> 82 | G90: =G66+G72+G78+G84 -> 56 | H90: =H66+H72+H78+H84 -> 43 | I90: =I66+I72+I78+I84 -> 38 | J90: =J66+J72+J78+J84 -> 33 | K90: =K66+K72+K78+K84 -> 50 | ... N90: =N66+N72+N78+N84 -> 50 | O90: 52 | P90: =D90 -> 82
B91: Applied this Month | C91: No | D91: =D67+D73+D79+D85 -> 4 | E91: =E67+E73+E79+E85 -> 5 | F91: =F67+F73+F79+F85 -> 2 | G91: =G67+G73+G79+G85 -> 1 | H91: =H67+H73+H79+H85 -> 1 | I91: =I67+I73+I79+I85 -> 1 | J91: =J67+J73+J79+J85 -> 19 | K91: =K67+K73+K79+K85 -> 0 | ... N91: =N67+N73+N79+N85 -> 2 | O91: 1 | P91: =SUM(D91:O91) -> 37
B92: Done this Month Postpaid | C92: No | D92: =D68+D74+D80+D86 -> 4 | E92: =E68+E74+E80+E86 -> 5 | F92: =F68+F74+F80+F86 -> 3 | G92: =G68+G74+G80+G86 -> 8 | H92: =H68+H74+H80+H86 -> 6 | I92: =I68+I74+I80+I86 -> 5 | J92: =J68+J74+J80+J86 -> 2 | K92: =K68+K74+K80+K86 -> 0 | ... N92: =N68+N74+N80+N86 -> 0 | O92: 4 | P92: =SUM(D92:O92) -> 37
B93: Done this Month Prepaid | D93: =D69+D75+D81+D87 -> 0 | E93: =E69+E75+E81+E87 -> 0 | F93: =F69+F75+F81+F87 -> 25 | G93: =G69+G75+G81+G87 -> 6 | H93: =H69+H75+H81+H87 -> 0 | I93: =I69+I75+I81+I87 -> 1 | J93: =J69+J75+J81+J87 -> 0 | K93: =K69+K75+K81+K87 -> 0 | ... N93: =N69+N75+N81+N87 -> 0 | O93: 0 | P93: =SUM(D93:O93) -> 33
B94: Total Done | C94: No | D94: =D93+D92 -> 4 | E94: =E93+E92 -> 5 | F94: =F93+F92 -> 28 | G94: =G93+G92 -> 14 | H94: =H93+H92 -> 6 | I94: =I93+I92 -> 6 | J94: =J93+J92 -> 2 | K94: =K93+K92 -> 0 | ... N94: =N93+N92 -> 0 | O94: 4 | P94: =P93+P92 -> 70
B95: Carried Forward | C95: No | D95: =D90+D91-D94 -> 82 | E95: =E90+E91-E94 -> 82 | F95: =F90+F91-F94 -> 56 | G95: =G90+G91-G94 -> 43 | H95: =H90+H91-H94 -> 38 | I95: =I90+I91-I94 -> 33 | J95: =J90+J91-J94 -> 50 | K95: =K90+K91-K94 -> 50 | ... N95: =N90+N91-N94 -> 52 | O95: 49 | P95: =P90+P91-P94 -> 49
A97: Prepaid Metering
A98: Prepaid Meters Installed | C98: No | D98: 0 | E98: 4 | F98: 27 | G98: 7 | H98: 2 | I98: 1 | J98: 3 | L98: 1 | P98: =SUM(D98:O98) -> 45
A100: Active and Disconnected Accounts
A101: Disconnected Individual Accounts | C101: No | D101: 214 | E101: 213 | F101: 207 | G101: 207 | H101: 218 | I101: 219 | J101: 218 | K101: 213 | L101: 214 | M101: 246 | N101: 243 | O101: 238 | P101: =O101 -> 238
A102: Disconnected institutional Accounts | C102: No | D102: 12 | E102: 12 | F102: 14 | G102: 17 | H102: 17 | I102: 17 | J102: 17 | K102: 14 | L102: 14 | M102: 14 | N102: 14 | O102: 14 | P102: =O102 -> 14
A103: Disconnected Commercial/Industrial Accounts | C103: No | D103: 24 | E103: 24 | F103: 24 | G103: 24 | H103: 24 | I103: 25 | J103: 25 | K103: 25 | L103: 25 | M103: 25 | N103: 25 | O103: 25 | P103: =O103 -> 25
A104: Disconnected CWP | C104: No | D104: 0 | E104: 0 | F104: 0 | G104: 0 | M104: 0 | P104: =O104 -> 0
A105: Total Disconnected Accounts | C105: No | D105: =SUM(D101:D104) -> 250 | E105: =SUM(E101:E104) -> 249 | F105: =SUM(F101:F104) -> 245 | G105: =SUM(G101:G104) -> 248 | H105: =SUM(H101:H104) -> 259 | I105: =SUM(I101:I104) -> 261 | J105: =SUM(J101:J104) -> 260 | K105: =SUM(K101:K104) -> 252 | ... N105: =SUM(N101:N104) -> 282 | O105: 277 | P105: =O105 -> 277
A106: Postpaid Consumers
...

Sheet Mikolongwe
A1: SOUTHERN REGION WATER BOARD
A3: MONTHLY REPORTS - 2023/2024
A4: MULANJE ZONE
A5: MULANJE ZONE
A7: PARAMETERS | C7: UNITS | D7: APRIL | E7: MAY | F7: JUNE | G7: JULY | H7: AUGUST | I7: SEPTEMBER | J7: OCTOBER | K7: NOVEMBER | L7: DECEMBER | M7: JANUARY | N7: FEBRUARY | O7: MARCH | P7: TOTALS
A8: PRODUCTION
A9: Volume Produced | C9: m3 | D9: 312 | E9: 952 | F9: 3195 | G9: 931 | H9: 487 | I9: 603 | J9: 467 | K9: 383 | L9: 1571 | M9: 632 | N9: 292 | O9: 417 | P9: =SUM(D9:O9) -> 10242
A10: REVENUE WATER - POSTPAID
A11: Volume Billed Individuals | C11: m3 | D11: =84+32 -> 116 | E11: =193+108 -> 301 | F11: =33+78 -> 111 | G11: =29+81 -> 110 | H11: =32+80 -> 112 | I11: =30+66 -> 96 | J11: =59+68 -> 127 | K11: =23+80 -> 103 | L11: 177 | M11: 99 | N11: =29+91 -> 120 | O11: 109 | P11: =SUM(D11:O11) -> 1581
A12: Volume Billed CWPs | C12: m3 | D12: 0 | E12: 0 | F12: 0 | G12: 0 | H12: 0 | P12: =SUM(D12:O12) -> 0
A13: Volume Billed Institutions | C13: m3 | D13: 0 | F13: 0 | G13: 0 | H13: 0 | P13: =SUM(D13:O13) -> 0
A14: Volume Billed Commercial/Industrial | C14: m3 | D14: 0 | F14: 0 | G14: 0 | H14: 0 | P14: =SUM(D14:O14) -> 0
A15: Total Volume Billed Post Paid | C15: m3 | D15: =SUM(D11:D14) -> 116 | E15: =SUM(E11:E14) -> 301 | F15: =SUM(F11:F14) -> 111 | G15: =SUM(G11:G14) -> 110 | H15: =SUM(H11:H14) -> 112 | I15: =SUM(I11:I14) -> 96 | J15: =SUM(J11:J14) -> 127 | K15: =SUM(K11:K14) -> 103 | ... N15: =SUM(N11:N14) -> 120 | O15: 109 | P15: =SUM(P11:P14) -> 1581
A16: REVENUE WATER - PREPAID
A17: Individuals | C17: m3 | D17: 54 | E17: 139 | F17: 598.3 | G17: 54 | H17: 46 | I17: 57 | J17: 46 | K17: 61 | L17: 257 | M17: 55.1 | N17: =62.8+2.9 -> 65.7 | O17: 27.9 | P17: =SUM(D17:O17) -> 1461
A18: CWPs | C18: m3 | F18: 0 | G18: 0 | H18: 0 | I18: 0 | J18: 0 | K18: 0 | L18: 0 | O18: 0 | P18: =SUM(D18:O18) -> 0
A19: Institutions | C19: m3 | D19: 80 | E19: 332 | F19: 1824.6 | G19: 459 | H19: 216 | I19: 363 | J19: 162.2 | K19: 34 | L19: 869 | M19: 365.1 | O19: 188.4 | P19: =SUM(D19:O19) -> 4893.3
A20: Commercial/Industrial | C20: m3 | F20: 0 | H20: 0 | K20: 0 | O20: 0 | P20: =SUM(D20:O20) -> 0
A21: Total Volume Prepaid | C21: m3 | D21: =SUM(D17:D20) -> 134 | E21: =SUM(E17:E20) -> 471 | F21: =SUM(F17:F20) -> 2422.9 | G21: =SUM(G17:G20) -> 513 | H21: =SUM(H17:H20) -> 262 | I21: =SUM(I17:I20) -> 420 | J21: =SUM(J17:J20) -> 208.2 | K21: =SUM(K17:K20) -> 95 | ... N21: =SUM(N17:N20) -> 65.7 | O21: 216.3 | P21: =SUM(P17:P20) -> 6354.3
A22: TOTAL REVENUE WATER | C22: m3 | D22: =D21+D15 -> 250 | E22: =E21+E15 -> 772 | F22: =F21+F15 -> 2533.9 | G22: =G21+G15 -> 623 | H22: =H21+H15 -> 374 | I22: =I21+I15 -> 516 | J22: =J21+J15 -> 335.2 | K22: =K21+K15 -> 198 | ... N22: =N21+N15 -> 185.7 | O22: 325.3 | P22: =P21+P15 -> 7935.3
A24: Non-Revenue Water (NRW) | B24: Volume | C24: m3 | D24: =D9-D22 -> 62 | E24: =E9-E22 -> 180 | F24: =F9-F22 -> 661.1 | G24: =G9-G22 -> 308 | H24: =H9-H22 -> 113 | I24: =I9-I22 -> 87 | J24: =J9-J22 -> 131.8 | K24: =K9-K22 -> 185 | ... N24: =N9-N22 -> 106.3 | O24: 91.7 | P24: =P9-P22 -> 2306.7
B25: Percentage | C25: % | D25: =D24/D9 -> 0.19871795 | E25: =E24/E9 -> 0.18907563 | F25: =F24/F9 -> 0.20691706 | G25: =G24/G9 -> 0.33082707 | H25: =H24/H9 -> 0.23203285 | I25: =I24/I9 -> 0.14427861 | J25: =J24/J9 -> 0.28222698 | K25: =K24/K9 -> 0.48302872 | ... N25: =N24/N9 -> 0.3640411 | O25: 0.21990408 | P25: =P24/P9 -> 0.22521968
A26: OPERATING EXPENSES
A27: Chemicals
A28: Chemical | B28: Rate(MK/kg)
A29: Chlorine | B29: 5111.67 | C29: kg | D29: 3 | E29: 5 | F29: 4 | G29: 2 | H29: 3 | I29: 3 | J29: 4 | K29: 4 | L29: 4 | M29: 3 | N29: 1 | O29: 4 | P29: =SUM(D29:O29) -> 40
C30: kg/mg litre | D30: =D29/(D9/1000) -> 9.6153846 | E30: =E29/(E9/1000) -> 5.2521008 | F30: =F29/(F9/1000) -> 1.2519562 | G30: =G29/(G9/1000) -> 2.1482277 | H30: =H29/(H9/1000) -> 6.1601643 | I30: =I29/(I9/1000) -> 4.9751244 | J30: =J29/(J9/1000) -> 8.5653105 | K30: =K29/(K9/1000) -> 10.443864 | L30: 2.5461489 | M30: =M29/(M9/1000) -> 4.7468354 | N30: =N29/(N9/1000) -> 3.4246575 | O30: 9.5923261 | P30: =P29/(P9/1000) -> 3.9054872
A31: Aluminium sulphate | B31: 1537 | C31: kg | P31: =SUM(D31:O31) -> 0
C32: kg/mg litre | D32: =D31/(D9/1000) -> 0 | E32: =E31/(E9/1000) -> 0 | F32: =F31/(F9/1000) -> 0 | G32: =G31/(G9/1000) -> 0 | H32: =H31/(H9/1000) -> 0 | I32: =I31/(I9/1000) -> 0 | J32: =J31/(J9/1000) -> 0 | K32: =K31/(K9/1000) -> 0 | ... N32: =N31/(N9/1000) -> 0 | O32: 0 | P32: =P31/(P9/1000) -> 0
A33: Soda | B33: 1781.02 | C33: kg | P33: =SUM(D33:O33) -> 0
C34: kg/mg litre | D34: =D33/(D9/1000) -> 0 | E34: =E33/(E9/1000) -> 0 | F34: =F33/(F9/1000) -> 0 | G34: =G33/(G9/1000) -> 0 | H34: =H33/(H9/1000) -> 0 | I34: =I33/(I9/1000) -> 0 | J34: =J33/(J9/1000) -> 0 | K34: =K33/(K9/1000) -> 0 | ... N34: =N33/(N9/1000) -> 0 | O34: 0 | P34: =P33/(P9/1000) -> 0
A35: Algae floc | B35: 5979.95 | C35: litres
C36: litres/mg litre
A37: Sud floc | B37: 5403.75 | C37: litres | D37: 0 | E37: 0 | F37: 0 | G37: 0 | H37: 0 | I37: 0 | J37: 0 | K37: 0 | L37: 0 | M37: 0 | N37: 0 | O37: 0 | P37: =SUM(D37:O37) -> 0
C38: litres/mg litre | D38: =D37/(D9/1000) -> 0 | E38: =E37/(E9/1000) -> 0 | F38: =F37/(F9/1000) -> 0 | G38: =G37/(G9/1000) -> 0 | H38: =H37/(H9/1000) -> 0 | I38: =I37/(I9/1000) -> 0 | J38: =J37/(J9/1000) -> 0 | K38: =K37/(K9/1000) -> 0 | ... N38: =N37/(N9/1000) -> 0 | O38: 0 | P38: =P37/(P9/1000) -> 0
A39: Potasium permanganate | B39: 1950 | C39: kg | D39: 0 | E39: 0 | F39: 0 | G39: 0 | H39: 0 | I39: 0 | J39: 0 | K39: 0 | L39: 0 | M39: 0 | N39: 0 | O39: 0 | P39: =SUM(D39:O39) -> 0
C40: kg/mg litre | D40: =D39/(D9/1000) -> 0 | E40: =E39/(E9/1000) -> 0 | F40: =F39/(F9/1000) -> 0 | G40: =G39/(G9/1000) -> 0 | H40: =H39/(H9/1000) -> 0 | I40: =I39/(I9/1000) -> 0 | J40: =J39/(J9/1000) -> 0 | K40: =K39/(K9/1000) -> 0 | ... N40: =N39/(N9/1000) -> 0 | O40: 0 | P40: =P39/(P9/1000) -> 0
A41: Cost of Chemicals | C41: Mk | D41: =(D29*$B29)+(D31*$B31)+(D33*$B33)+(D35*$B35)+(D37*$B37)+(D39*$B39) -> 15335.01 | E41: =(E29*$B29)+(E31*$B31)+(E33*$B33)+(E35*$B35)+(E37*$B37)+(E39*$B39) -> 25558.35 | F41: =(F29*$B29)+(F31*$B31)+(F33*$B33)+(F35*$B35)+(F37*$B37)+(F39*$B39) -> 20446.68 | G41: =(G29*$B29)+(G31*$B31)+(G33*$B33)+(G35*$B35)+(G37*$B37)+(G39*$B39) -> 10223.34 | H41: =(H29*$B29)+(H31*$B31)+(H33*$B33)+(H35*$B35)+(H37*$B37)+(H39*$B39) -> 15335.01 | I41: =(I29*$B29)+(I31*$B31)+(I33*$B33)+(I35*$B35)+(I37*$B37)+(I39*$B39) -> 15335.01 | J41: =(J29*$B29)+(J31*$B31)+(J33*$B33)+(J35*$B35)+(J37*$B37)+(J39*$B39) -> 20446.68 | K41: =(K29*$B29)+(K31*$B31)+(K33*$B33)+(K35*$B35)+(K37*$B37)+(K39*$B39) -> 20446.68 | ... N41: =(N29*$B29)+(N31*$B31)+(N33*$B33)+(N35*$B35)+(N37*$B37)+(N39*$B39) -> 5111.67 | O41: 20446.68 | P41: =SUM(D41:O41) -> 204466.8
A42: Cost/vol. Produced (chemicals) | C42: Mk/m3 | D42: =D41/D9 -> 49.150673 | E42: =E41/E9 -> 26.847006 | F42: =F41/F9 -> 6.3995869 | G42: =G41/G9 -> 10.981031 | H42: =H41/H9 -> 31.488727 | I42: =I41/I9 -> 25.431194 | J42: =J41/J9 -> 43.783041 | K42: =K41/K9 -> 53.385587 | ... N42: =N41/N9 -> 17.505719 | O42: 49.032806 | P42: =P41/P9 -> 19.963562
A43: Power
A44: Power Usage | C44: Kw | D44: 353 | E44: 365 | F44: 489 | G44: 259 | H44: 355 | I44: 339 | J44: 386 | K44: 308 | L44: 412 | M44: 355 | O44: 494 | P44: =SUM(D44:O44) -> 4115
A45: Power/ Vol. Produced | C45: Kw/m3 | D45: =D44/D9 -> 1.1314103 | E45: =E44/E9 -> 0.38340336 | F45: =F44/F9 -> 0.15305164 | G45: =G44/G9 -> 0.27819549 | H45: =H44/H9 -> 0.72895277 | I45: =I44/I9 -> 0.56218905 | J45: =J44/J9 -> 0.82655246 | K45: =K44/K9 -> 0.80417755 | L45: =L44/L9 -> 0.26225334 | M45: 0.56170886 | N45: =N44/N9 -> 0 | O45: 1.1846523 | P45: =P44/P9 -> 0.401777
A46: Cost of Power | C46: Mk | D46: =1.165*(14100+(D44*119.1)) -> 65405.779 | E46: =1.165*(14100+(E44*119.1)) -> 67070.798 | F46: =1.165*(14100+(F44*119.1)) -> 84275.984 | G46: =1.165*(14100+(G44*119.1)) -> 52363.138 | H46: =1.165*(14100+(H44*119.1)) -> 65683.283 | I46: =1.165*(14100+(I44*119.1)) -> 63463.259 | J46: =1.165*(14100+(J44*119.1)) -> 69984.579 | K46: =1.165*(14100+(K44*119.1)) -> 59161.962 | ... N46: =1.165*(14100+(N44*119.1)) -> 16426.5 | O46: 84969.741 | P46: =SUM(D46:O46) -> 768080.42
A47: Cost/vol. Produced | C47: Mk/m3 | D47: =D46/D9 -> 209.63391 | E47: =E46/E9 -> 70.452518 | F47: =F46/F9 -> 26.37746 | G47: =G46/G9 -> 56.243973 | H47: =H46/H9 -> 134.87327 | I47: =I46/I9 -> 105.24587 | J47: =J46/J9 -> 149.85991 | K47: =K46/K9 -> 154.46987 | ... N47: =N46/N9 -> 56.255137 | O47: 203.76437 | P47: =P46/P9 -> 74.993207
A48: Plant and Vehicle Maintenance
A49: Distances covered | C49: km | P49: =SUM(D49:O49) -> 0
A50: Fuel Used (litres) | C50: litres | P50: =SUM(D50:O50) -> 0
A51: Cost of fuel | C51: Mk | P51: =SUM(D51:O51) -> 0
A52: Maintenance | C52: Mk | D52: 0 | E52: 0 | F52: 0 | G52: 0 | H52: 0 | I52: 0 | J52: 0 | K52: 0 | L52: 0 | M52: 0 | N52: 0 | O52: 0 | P52: =SUM(D52:O52) -> 0
A53: Salaries and Wages
A54: Staff Costs | C54: MK | P54: =SUM(D54:O54) -> 0
A55: Wages | C55: MK | D55: 160600 | E55: 115384.6 | F55: 119800 | G55: =AVERAGE(D55:F55) -> 131928.2 | H55: 126923.28 | I55: 136000 | J55: =AVERAGE(D55:I55) -> 131772.68 | K55: 129615.56 | L55: 107870 | M55: 116340 | N55: 116580 | O55: 126923 | P55: =SUM(D55:O55) -> 1519737.3
A56: Other Overhead Costs | C56: MK | D56: 120000 | E56: 10000 | F56: 10000 | G56: =AVERAGE(D56:F56) -> 46666.667 | H56: 10000 | I56: 10000 | J56: 10000 | K56: 10000 | L56: 12200 | M56: 10000 | N56: 10000 | O56: 10000 | P56: =SUM(D56:O56) -> 268866.67
A57: Operating Costs
A58: Total Operating Costs | C58: MK | D58: =D41+D46+D51+D52+D54+D55+D56 -> 361340.79 | E58: =E41+E46+E51+E52+E54+E55+E56 -> 218013.75 | F58: =F41+F46+F51+F52+F54+F55+F56 -> 234522.66 | G58: =G41+G46+G51+G52+G54+G55+G56 -> 241181.35 | H58: =H41+H46+H51+H52+H54+H55+H56 -> 217941.57 | I58: =I41+I46+I51+I52+I54+I55+I56 -> 224798.27 | J58: =J41+J46+J51+J52+J54+J55+J56 -> 232203.94 | K58: =K41+K46+K51+K52+K54+K55+K56 -> 219224.2 | ... N58: =N41+N46+N51+N52+N54+N55+N56 -> 148118.17 | O58: 242339.42 | P58: =SUM(D58:O58) -> 2761151.2
A59: Cost/Vol. Produced | C59: Mk/m3 | D59: =D58/D9 -> 1158.1436 | E59: =E58/E9 -> 229.00604 | F59: =F58/F9 -> 73.403025 | G59: =G58/G9 -> 259.05622 | H59: =H58/H9 -> 447.51863 | I59: =I58/I9 -> 372.79978 | J59: =J58/J9 -> 497.22471 | K59: =K58/K9 -> 572.38695 | ... N59: =N58/N9 -> 507.25401 | O59: 581.14969 | P59: =P58/P9 -> 269.59102
A60: Cost/Vol. Billed | C60: Mk/m3 | D60: =D58/D22 -> 1445.3632 | E60: =E58/E22 -> 282.40123 | F60: =F58/F22 -> 92.554033 | G60: =G58/G22 -> 387.12896 | H60: =H58/H22 -> 582.73148 | I60: =I58/I22 -> 435.65556 | J60: =J58/J22 -> 692.73251 | K60: =K58/K22 -> 1107.1929 | ... N60: =N58/N22 -> 797.62073 | O60: 744.97209 | P60: =P58/P22 -> 347.95801
A61: Permanent Staff Employed | C61: No | D61: 0 | E61: 0 | F61: 0 | G61: 0 | P61: =O61 -> 0
A62: Staff/Vol.1000m3 of Volume Produced/hour (12 hour day) | C62: No/1000m3 | D62: =(D61*1000*31)/D9 -> 0 | E62: =(E61*1000*31)/E9 -> 0 | F62: =(F61*1000*31)/F9 -> 0 | G62: =(G61*1000*31)/G9 -> 0 | H62: =(H61*1000*31)/H9 -> 0 | I62: =(I61*1000*31)/I9 -> 0 | J62: =(J61*1000*31)/J9 -> 0 | K62: =(K61*1000*31)/K9 -> 0 | ... N62: =(N61*1000*31)/N9 -> 0 | O62: 0 | P62: =(P61*1000*31)/P9 -> 0
A63: Temporary Staff Employed | C63: No | D63: 7 | E63: 2 | F63: 2 | G63: 2 | H63: 2 | I63: 2 | J63: 2 | K63: 2 | L63: 2 | M63: 2 | N63: 2 | O63: 2 | P63: =SUM(D63:O63) -> 29
A65: Water Connections and Disconnections
A66: New Individual Water Connections | B66: Brought Forward | C66: No | D66: 0 | E66: 0 | F66: 0 | G66: 0 | H66: =G71 -> 0 | M66: 0 | P66: =D66 -> 0
B67: Applied this Month | C67: No | D67: 0 | E67: 0 | F67: 0 | G67: 0 | H67: 0 | M67: 0 | P67: =SUM(D67:O67) -> 0
B68: Done this Month Postpaid | C68: No | D68: 0 | E68: 0 | F68: 0 | G68: 0 | H68: 0 | M68: 0 | P68: =SUM(D68:O68) -> 0
B69: Done this Month Prepaid | C69: No | D69: 0 | E69: 0 | F69: 0 | G69: 0 | H69: 0 | M69: 0 | P69: =SUM(D69:O69) -> 0
B70: Total Done | C70: No | D70: =D68+D69 -> 0 | E70: =E68+E69 -> 0 | F70: =F68+F69 -> 0 | G70: =G68+G69 -> 0 | H70: =H68+H69 -> 0 | I70: =I68+I69 -> 0 | J70: =J68+J69 -> 0 | K70: =K68+K69 -> 0 | L70: =L68+L69 -> 0 | M70: 0 | N70: =N68+N69 -> 0 | O70: 0 | P70: =P68+P69 -> 0
B71: Carried Forward | C71: No | D71: =D66+D67-D70 -> 0 | E71: =E66+E67-E70 -> 0 | F71: =F66+F67-F70 -> 0 | G71: =G66+G67-G70 -> 0 | H71: =H66+H67-H70 -> 0 | I71: =I66+I67-I70 -> 0 | J71: =J66+J67-J70 -> 0 | K71: =K66+K67-K70 -> 0 | L71: =L66+L67-L70 -> 0 | M71: 0 | N71: =N66+N67-N70 -> 0 | O71: 0 | P71: =P66+P67-P70 -> 0
A72: New Institutional Water Connections | B72: Brought Forward | C72: No | D72: 0 | E72: 0 | F72: 0 | G72: 0 | H72: =G77 -> 0 | P72: =D72 -> 0
B73: Applied this Month | C73: No | D73: 0 | E73: 0 | F73: 0 | G73: 0 | P73: =SUM(D73:O73) -> 0
B74: Done this Month Postpaid | C74: No | D74: 0 | E74: 0 | F74: 0 | G74: 0 | P74: =SUM(D74:O74) -> 0
B75: Done this Month Prepaid | C75: No | D75: 0 | E75: 0 | F75: 0 | G75: 0 | P75: =SUM(D75:O75) -> 0
B76: Total Done | C76: No | D76: =D74+D75 -> 0 | E76: =E74+E75 -> 0 | F76: =F74+F75 -> 0 | G76: =G74+G75 -> 0 | H76: =H74+H75 -> 0 | I76: =I74+I75 -> 0 | J76: =J74+J75 -> 0 | K76: =K74+K75 -> 0 | ... N76: =N74+N75 -> 0 | O76: 0 | P76: =P74+P75 -> 0
B77: Carried Forward | C77: No | D77: =D73+D74-D76 -> 0 | E77: =E73+E74-E76 -> 0 | F77: =F73+F74-F76 -> 0 | G77: =G73+G74-G76 -> 0 | H77: =H73+H74-H76 -> 0 | I77: =I73+I74-I76 -> 0 | J77: =J73+J74-J76 -> 0 | K77: =K73+K74-K76 -> 0 | ... N77: =N73+N74-N76 -> 0 | O77: 0 | P77: =P73+P74-P76 -> 0
A78: New Commercial/Industrial Water Connections | B78: Brought Forward | C78: No | D78: 0 | E78: 0 | F78: 0 | G78: 0 | P78: =D78 -> 0
B79: Applied this Month | C79: No | D79: 0 | E79: 0 | F79: 0 | G79: 0 | P79: =SUM(D79:O79) -> 0
B80: Done this Month Postpaid | C80: No | D80: 0 | E80: 0 | F80: 0 | G80: 0 | P80: =SUM(D80:O80) -> 0
B81: Done this Month Prepaid | C81: No | D81: 0 | E81: 0 | F81: 0 | G81: 0 | P81: =SUM(D81:O81) -> 0
B82: Total Done | C82: No | D82: =D81+D80 -> 0 | E82: =E81+E80 -> 0 | F82: =F81+F80 -> 0 | G82: =G81+G80 -> 0 | H82: =H81+H80 -> 0 | I82: =I81+I80 -> 0 | J82: =J81+J80 -> 0 | K82: =K81+K80 -> 0 | ... N82: =N81+N80 -> 0 | O82: 0 | P82: =P81+P80 -> 0
B83: Carried Forward | C83: No | D83: =D78+D79-D82 -> 0 | E83: =E78+E79-E82 -> 0 | F83: =F78+F79-F82 -> 0 | G83: =G78+G79-G82 -> 0 | H83: =H78+H79-H82 -> 0 | I83: =I78+I79-I82 -> 0 | J83: =J78+J79-J82 -> 0 | K83: =K78+K79-K82 -> 0 | ... N83: =N78+N79-N82 -> 0 | O83: 0 | P83: =P78+P79-P82 -> 0
A84: New CWP | B84: Brought Forward | C84: No | D84: 0 | E84: =D89 -> 0 | F84: =E89 -> 0 | G84: =F89 -> 0 | P84: =D84 -> 0
B85: Applied this Month | C85: No | D85: 0 | E85: 0 | F85: 0 | G85: 0 | P85: =SUM(D85:O85) -> 0
B86: Done this Month Postpaid | C86: No | D86: 0 | E86: 0 | F86: 0 | G86: 0 | P86: =SUM(D86:O86) -> 0
B87: Done this Month Prepaid | C87: No | D87: 0 | E87: 0 | F87: 0 | G87: 0 | P87: =SUM(D87:O87) -> 0
B88: Total Done | C88: No | D88: =D86+D87 -> 0 | E88: =E86+E87 -> 0 | F88: =F86+F87 -> 0 | G88: =G86+G87 -> 0 | H88: =H87+H86 -> 0 | I88: =I87+I86 -> 0 | J88: =J87+J86 -> 0 | K88: =K87+K86 -> 0 | L88: =L87+L86 -> 0 | M88: =M87+M86 -> 0 | N88: =N87+N86 -> 0 | O88: 0 | P88: =SUM(D88:O88) -> 0
B89: Carried Forward | C89: No | D89: =D84+D85-D88 -> 0 | E89: 0 | F89: 0 | G89: 0 | H89: =H84+H85-H88 -> 0 | I89: =I84+I85-I88 -> 0 | J89: =J84+J85-J88 -> 0 | K89: =K84+K85-K88 -> 0 | L89: =L84+L85-L88 -> 0 | M89: =M84+M85-M88 -> 0 | N89: =N84+N85-N88 -> 0 | O89: 0 | P89: =P84+P85-P86-P87 -> 0
A90: Aggregated New Water connections | B90: Brought Forward | C90: No | D90: =D66+D72+D78+D84 -> 0 | E90: =E66+E72+E78+E84 -> 0 | F90: =F66+F72+F78+F84 -> 0 | G90: =G66+G72+G78+G84 -> 0 | H90: =H66+H72+H78+H84 -> 0 | I90: =I66+I72+I78+I84 -> 0 | J90: =J66+J72+J78+J84 -> 0 | K90: =K66+K72+K78+K84 -> 0 | ... N90: =N66+N72+N78+N84 -> 0 | O90: 0 | P90: =D90 -> 0
B91: Applied this Month | C91: No | D91: =D67+D73+D79+D85 -> 0 | E91: =E67+E73+E79+E85 -> 0 | F91: =F67+F73+F79+F85 -> 0 | G91: =G67+G73+G79+G85 -> 0 | H91: =H67+H73+H79+H85 -> 0 | I91: =I67+I73+I79+I85 -> 0 | J91: =J67+J73+J79+J85 -> 0 | K91: =K67+K73+K79+K85 -> 0 | ... N91: =N67+N73+N79+N85 -> 0 | O91: 0 | P91: =SUM(D91:O91) -> 0
B92: Done this Month Postpaid | C92: No | D92: =D68+D74+D80+D86 -> 0 | E92: =E68+E74+E80+E86 -> 0 | F92: =F68+F74+F80+F86 -> 0 | G92: =G68+G74+G80+G86 -> 0 | H92: =H68+H74+H80+H86 -> 0 | I92: =I68+I74+I80+I86 -> 0 | J92: =J68+J74+J80+J86 -> 0 | K92: =K68+K74+K80+K86 -> 0 | ... N92: =N68+N74+N80+N86 -> 0 | O92: 0 | P92: =SUM(D92:O92) -> 0
B93: Done this Month Prepaid | D93: =D69+D75+D81+D87 -> 0 | E93: =E69+E75+E81+E87 -> 0 | F93: =F69+F75+F81+F87 -> 0 | G93: =G69+G75+G81+G87 -> 0 | H93: =H69+H75+H81+H87 -> 0 | I93: =I69+I75+I81+I87 -> 0 | J93: =J69+J75+J81+J87 -> 0 | K93: =K69+K75+K81+K87 -> 0 | ... N93: =N69+N75+N81+N87 -> 0 | O93: 0 | P93: =SUM(D93:O93) -> 0
B94: Total Done | C94: No | D94: =D93+D92 -> 0 | E94: =E93+E92 -> 0 | F94: =F93+F92 -> 0 | G94: =G93+G92 -> 0 | H94: =H93+H92 -> 0 | I94: =I93+I92 -> 0 | J94: =J93+J92 -> 0 | K94: =K93+K92 -> 0 | ... N94: =N93+N92 -> 0 | O94: 0 | P94: =P93+P92 -> 0
B95: Carried Forward | C95: No | D95: =D90+D91-D94 -> 0 | E95: =E90+E91-E94 -> 0 | F95: =F90+F91-F94 -> 0 | G95: =G90+G91-G94 -> 0 | H95: =H90+H91-H94 -> 0 | I95: =I90+I91-I94 -> 0 | J95: =J90+J91-J94 -> 0 | K95: =K90+K91-K94 -> 0 | ... N95: =N90+N91-N94 -> 0 | O95: 0 | P95: =P90+P91-P94 -> 0
A97: Prepaid Metering
A98: Prepaid Meters Installed | C98: No | P98: =SUM(D98:O98) -> 0
A100: Active and Disconnected Accounts
A101: Disconnected Individual Accounts | C101: No | D101: 12 | E101: 15 | F101: 14 | G101: 14 | H101: 15 | I101: 15 | J101: 17 | K101: 16 | L101: 16 | M101: 16 | N101: 16 | O101: 16 | P101: =O101 -> 16
A102: Disconnected institutional Accounts | C102: No | D102: 2 | E102: 2 | F102: 1 | G102: 2 | H102: 2 | I102: 2 | J102: 2 | K102: 2 | L102: 2 | M102: 2 | N102: 2 | O102: 2 | P102: =O102 -> 2
A103: Disconnected Commercial/Industrial Accounts | C103: No | D103: 0 | E103: 0 | F103: 1 | G103: 0 | P103: =O103 -> 0
A104: Disconnected CWP | C104: No | D104: 0 | E104: 0 | F104: 0 | G104: 0 | P104: =O104 -> 0
A105: Total Disconnected Accounts | C105: No | D105: =SUM(D101:D104) -> 14 | E105: =SUM(E101:E104) -> 17 | F105: =SUM(F101:F104) -> 16 | G105: =SUM(G101:G104) -> 16 | H105: =SUM(H101:H104) -> 17 | I105: =SUM(I101:I104) -> 17 | J105: =SUM(J101:J104) -> 19 | K105: =SUM(K101:K104) -> 18 | ... N105: =SUM(N101:N104) -> 18 | O105: 18 | P105: =O105 -> 18
A106: Postpaid Consumers
...

Sheet Migowi
A1: SOUTHERN REGION WATER BOARD
A3: MONTHLY REPORTS - 2023/2024
A4: MULANJE ZONE
A5: MULANJE ZONE
A7: PARAMETERS | C7: UNITS | D7: APRIL | E7: MAY | F7: JUNE | G7: JULY | H7: AUGUST | I7: SEPTEMBER | J7: OCTOBER | K7: NOVEMBER | L7: DECEMBER | M7: JANUARY | N7: FEBRUARY | O7: MARCH | P7: TOTALS
A8: PRODUCTION
A9: Volume Produced | C9: m3 | D9: 1386 | E9: 2405 | F9: 4660 | G9: 3405 | H9: 3163 | I9: 3546 | J9: 3456 | K9: 3113 | L9: 3888 | M9: 3391 | N9: 6091 | O9: 4293 | P9: =SUM(D9:O9) -> 42797
A10: REVENUE WATER - POSTPAID
A11: Volume Billed Individuals | C11: m3 | D11: 0 | E11: 0 | F11: 0 | O11: 688.7 | P11: =SUM(D11:O11) -> 688.7
A12: Volume Billed CWPs | C12: m3 | D12: 0 | E12: 0 | F12: 0 | O12: 0 | P12: =SUM(D12:O12) -> 0
A13: Volume Billed Institutions | C13: m3 | D13: 0 | E13: 0 | F13: 0 | O13: 3258 | P13: =SUM(D13:O13) -> 3258
A14: Volume Billed Commercial/Industrial | C14: m3 | D14: 0 | E14: 0 | F14: 0 | O14: 0 | P14: =SUM(D14:O14) -> 0
A15: Total Volume Billed Post Paid | C15: m3 | D15: =SUM(D11:D14) -> 0 | E15: =SUM(E11:E14) -> 0 | F15: =SUM(F11:F14) -> 0 | G15: =SUM(G11:G14) -> 0 | H15: =SUM(H11:H14) -> 0 | I15: =SUM(I11:I14) -> 0 | J15: =SUM(J11:J14) -> 0 | K15: =SUM(K11:K14) -> 0 | ... N15: =SUM(N11:N14) -> 0 | O15: 3946.7 | P15: =SUM(P11:P14) -> 3946.7
A16: REVENUE WATER - PREPAID
A17: Individuals | C17: m3 | D17: 931 | E17: 734 | F17: 865.6 | G17: =966.5+0.1 -> 966.6 | H17: 883 | I17: 920 | J17: 758.3 | K17: =7+907 -> 914 | L17: 769 | M17: 848 | N17: 830 | P17: =SUM(D17:O17) -> 9419.5
A18: CWPs | C18: m3 | D18: 0 | E18: 0 | F18: 0 | G18: 0 | I18: 0 | J18: 0 | K18: 0 | L18: 0 | P18: =SUM(D18:O18) -> 0
A19: Institutions | C19: m3 | D19: 100 | E19: 1086 | F19: 2804 | G19: 1847 | H19: 1788 | I19: =2171+14 -> 2185 | J19: 2172 | K19: =109+1281 -> 1390 | L19: 2548 | M19: 2172 | N19: 4357 | P19: =SUM(D19:O19) -> 22449
A20: Commercial/Industrial | C20: m3 | D20: 0 | E20: 0 | F20: 0 | G20: 0 | P20: =SUM(D20:O20) -> 0
A21: Total Volume Prepaid | C21: m3 | D21: =SUM(D17:D20) -> 1031 | E21: =SUM(E17:E20) -> 1820 | F21: =SUM(F17:F20) -> 3669.6 | G21: =SUM(G17:G20) -> 2813.6 | H21: =SUM(H17:H20) -> 2671 | I21: =SUM(I17:I20) -> 3105 | J21: =SUM(J17:J20) -> 2930.3 | K21: =SUM(K17:K20) -> 2304 | ... N21: =SUM(N17:N20) -> 5187 | O21: 0 | P21: =SUM(P17:P20) -> 31868.5
A22: TOTAL REVENUE WATER | C22: m3 | D22: =D21+D15 -> 1031 | E22: =E21+E15 -> 1820 | F22: =F21+F15 -> 3669.6 | G22: =G21+G15 -> 2813.6 | H22: =H21+H15 -> 2671 | I22: =I21+I15 -> 3105 | J22: =J21+J15 -> 2930.3 | K22: =K21+K15 -> 2304 | ... N22: =N21+N15 -> 5187 | O22: 3946.7 | P22: =P21+P15 -> 35815.2
A24: Non-Revenue Water (NRW) | B24: Volume | C24: m3 | D24: =D9-D22 -> 355 | E24: =E9-E22 -> 585 | F24: =F9-F22 -> 990.4 | G24: =G9-G22 -> 591.4 | H24: =H9-H22 -> 492 | I24: =I9-I22 -> 441 | J24: =J9-J22 -> 525.7 | K24: =K9-K22 -> 809 | ... N24: =N9-N22 -> 904 | O24: 346.3 | P24: =P9-P22 -> 6981.8
B25: Percentage | C25: % | D25: =D24/D9 -> 0.25613276 | E25: =E24/E9 -> 0.24324324 | F25: =F24/F9 -> 0.21253219 | G25: =G24/G9 -> 0.17368576 | H25: =H24/H9 -> 0.15554853 | I25: =I24/I9 -> 0.12436548 | J25: =J24/J9 -> 0.15211227 | K25: =K24/K9 -> 0.25987793 | ... N25: =N24/N9 -> 0.1484157 | O25: 0.080666201 | P25: =P24/P9 -> 0.1631376
A26: OPERATING EXPENSES
A27: Chemicals
A28: Chemical | B28: Rate(MK/kg)
A29: Chlorine | B29: 5111.67 | C29: kg | D29: 5 | E29: 8 | F29: 8 | G29: 7 | H29: 4 | I29: 1 | J29: 1 | K29: 1 | L29: 1 | M29: 2 | N29: 3 | O29: 1 | P29: =SUM(D29:O29) -> 42
C30: kg/mg litre | D30: =D29/(D9/1000) -> 3.6075036 | E30: =E29/(E9/1000) -> 3.3264033 | F30: =F29/(F9/1000) -> 1.7167382 | G30: =G29/(G9/1000) -> 2.0558003 | H30: =H29/(Migowi!H9/1000) -> 1.2646222 | I30: =I29/(I9/1000) -> 0.2820079 | J30: =J29/(J9/1000) -> 0.28935185 | K30: =K29/(K9/1000) -> 0.32123354 | L30: 0.25720165 | M30: =M29/(M9/1000) -> 0.58979652 | N30: =N29/(N9/1000) -> 0.49252996 | O30: 0.23293734 | P30: =P29/(P9/1000) -> 0.9813772
A31: Aluminium sulphate | B31: 1537 | C31: kg | P31: =SUM(D31:O31) -> 0
C32: kg/mg litre | D32: =D31/(D9/1000) -> 0 | E32: =E31/(E9/1000) -> 0 | F32: =F31/(F9/1000) -> 0 | G32: =G31/(G9/1000) -> 0 | H32: 0 | I32: =I31/(I9/1000) -> 0 | J32: =J31/(J9/1000) -> 0 | K32: =K31/(K9/1000) -> 0 | L32: =L31/(L9/1000) -> 0 | M32: =M31/(M9/1000) -> 0 | N32: =N31/(N9/1000) -> 0 | O32: 0 | P32: =P31/(P9/1000) -> 0
A33: Soda | B33: 1781.02 | C33: kg | P33: =SUM(D33:O33) -> 0
C34: kg/mg litre | D34: =D33/(D9/1000) -> 0 | E34: =E33/(E9/1000) -> 0 | F34: =F33/(F9/1000) -> 0 | G34: =G33/(G9/1000) -> 0 | H34: 0 | I34: =I33/(I9/1000) -> 0 | J34: =J33/(J9/1000) -> 0 | K34: =K33/(K9/1000) -> 0 | L34: =L33/(L9/1000) -> 0 | M34: =M33/(M9/1000) -> 0 | N34: =N33/(N9/1000) -> 0 | O34: 0 | P34: =P33/(P9/1000) -> 0
A35: Algae floc | B35: 5979.95 | C35: litres
C36: litres/mg litre
A37: Sud floc | B37: 5403.75 | C37: litres | D37: 0 | E37: 0 | F37: 0 | G37: 0 | H37: 0 | I37: 0 | J37: 0 | K37: 0 | L37: 0 | M37: 0 | N37: 0 | O37: 0 | P37: =SUM(D37:O37) -> 0
C38: litres/mg litre | D38: =D37/(D9/1000) -> 0 | E38: =E37/(E9/1000) -> 0 | F38: =F37/(F9/1000) -> 0 | G38: =G37/(G9/1000) -> 0 | H38: =H37/(H9/1000) -> 0 | I38: =I37/(I9/1000) -> 0 | J38: =J37/(J9/1000) -> 0 | K38: =K37/(K9/1000) -> 0 | ... N38: =N37/(N9/1000) -> 0 | O38: 0 | P38: =P37/(P9/1000) -> 0
A39: Potasium permanganate | B39: 1950 | C39: kg | D39: 0 | E39: 0 | F39: 0 | G39: 0 | H39: 0 | I39: 0 | J39: 0 | K39: 0 | L39: 0 | M39: 0 | N39: 0 | O39: 0 | P39: =SUM(D39:O39) -> 0
C40: kg/mg litre | D40: =D39/(D9/1000) -> 0 | E40: =E39/(E9/1000) -> 0 | F40: =F39/(F9/1000) -> 0 | G40: =G39/(G9/1000) -> 0 | H40: =H39/(H9/1000) -> 0 | I40: =I39/(I9/1000) -> 0 | J40: =J39/(J9/1000) -> 0 | K40: =K39/(K9/1000) -> 0 | ... N40: =N39/(N9/1000) -> 0 | O40: 0 | P40: =P39/(P9/1000) -> 0
A41: Cost of Chemicals | C41: Mk | D41: =(D29*$B29)+(D31*$B31)+(D33*$B33)+(D35*$B35)+(D37*$B37)+(D39*$B39) -> 25558.35 | E41: =(E29*$B29)+(E31*$B31)+(E33*$B33)+(E35*$B35)+(E37*$B37)+(E39*$B39) -> 40893.36 | F41: =(F29*$B29)+(F31*$B31)+(F33*$B33)+(F35*$B35)+(F37*$B37)+(F39*$B39) -> 40893.36 | G41: =(G29*$B29)+(G31*$B31)+(G33*$B33)+(G35*$B35)+(G37*$B37)+(G39*$B39) -> 35781.69 | H41: =(H29*$B29)+(H31*$B31)+(H33*$B33)+(H35*$B35)+(H37*$B37)+(H39*$B39) -> 20446.68 | I41: =(I29*$B29)+(I31*$B31)+(I33*$B33)+(I35*$B35)+(I37*$B37)+(I39*$B39) -> 5111.67 | J41: =(J29*$B29)+(J31*$B31)+(J33*$B33)+(J35*$B35)+(J37*$B37)+(J39*$B39) -> 5111.67 | K41: =(K29*$B29)+(K31*$B31)+(K33*$B33)+(K35*$B35)+(K37*$B37)+(K39*$B39) -> 5111.67 | ... N41: =(N29*$B29)+(N31*$B31)+(N33*$B33)+(N35*$B35)+(N37*$B37)+(N39*$B39) -> 15335.01 | O41: 5111.67 | P41: =SUM(D41:O41) -> 214690.14
A42: Cost/vol. Produced (chemicals) | C42: Mk/m3 | D42: =D41/D9 -> 18.440368 | E42: =E41/E9 -> 17.003476 | F42: =F41/F9 -> 8.7753991 | G42: =G41/G9 -> 10.508573 | H42: =H41/Migowi!H9 -> 6.4643313 | I42: =I41/I9 -> 1.4415313 | J42: =J41/J9 -> 1.4790712 | K42: =K41/K9 -> 1.6420398 | L42: =L41/L9 -> 1.3147299 | M42: =M41/M9 -> 3.0148452 | N42: =N41/N9 -> 2.5176506 | O42: 1.1906988 | P42: =P41/P9 -> 5.0164764
A43: Power
A44: Power Usage | C44: Kw | D44: 1447 | E44: 1130 | F44: 1784 | G44: 1945 | H44: 1468 | I44: 1621 | J44: 1046 | K44: 1182 | L44: 976 | M44: 1156 | N44: 1150 | O44: 989 | P44: =SUM(D44:O44) -> 15894
A45: Power/ Vol. Produced | C45: Kw/m3 | D45: =D44/D9 -> 1.0440115 | E45: =E44/E9 -> 0.46985447 | F45: =F44/F9 -> 0.38283262 | G45: =G44/G9 -> 0.5712188 | H45: =H44/Migowi!H9 -> 0.46411635 | I45: =I44/I9 -> 0.4571348 | J45: =J44/J9 -> 0.30266204 | K45: =K44/K9 -> 0.37969804 | L45: =L44/L9 -> 0.25102881 | M45: =M44/M9 -> 0.34090239 | N45: =N44/N9 -> 0.18880315 | O45: 0.23037503 | P45: =P44/P9 -> 0.37138117
A46: Cost of Power | C46: Mk | D46: =1.165*(14100+(D44*119.1)) -> 217199.92 | E46: =1.165*(14100+(E44*119.1)) -> 173215.7 | F46: =1.165*(14100+(F44*119.1)) -> 263959.18 | G46: =122.92*G44 -> 239079.4 | H46: =122.92*H44 -> 180446.56 | I46: =122.92*I44 -> 199253.32 | J46: =122.92*J44 -> 128574.32 | K46: =122.92*K44 -> 145291.44 | L46: 119969.92 | M46: 142095.52 | N46: =122.92*N44 -> 141358 | O46: 121567.88 | P46: =SUM(D46:O46) -> 2072011.2
A47: Cost/vol. Produced | C47: Mk/m3 | D47: =D46/D9 -> 156.7099 | E47: =E46/E9 -> 72.023158 | F47: =F46/F9 -> 56.6436 | G47: =G46/G9 -> 70.214214 | H47: =H46/Migowi!H9 -> 57.049181 | I47: =I46/I9 -> 56.19101 | J47: =J46/J9 -> 37.203218 | K47: =K46/K9 -> 46.672483 | L47: =L46/L9 -> 30.856461 | M47: =M46/M9 -> 41.903722 | N47: =N46/N9 -> 23.207683 | O47: 28.317699 | P47: =P46/P9 -> 48.414869
A48: Plant and Vehicle Maintenance
A49: Distances covered | C49: km | P49: =SUM(D49:O49) -> 0
A50: Fuel Used (litres) | C50: litres | P50: =SUM(D50:O50) -> 0
A51: Cost of fuel | C51: Mk | P51: =SUM(D51:O51) -> 0
A52: Maintenance | C52: Mk | D52: 0 | E52: 0 | F52: 0 | G52: 0 | H52: 0 | I52: 0 | J52: 0 | K52: 0 | L52: 0 | M52: 0 | N52: 0 | O52: 0 | P52: =SUM(D52:O52) -> 0
A53: Salaries and Wages
A54: Staff Costs | C54: MK | K54: 368124.46 | L54: 374231.62 | P54: =SUM(D54:O54) -> 742356.08
A55: Wages | C55: MK | D55: 99874.39 | E55: 101264.5 | F55: 106894.44 | G55: =AVERAGE(D55:F55) -> 102677.78 | H55: 104754.35 | I55: 101840.6 | J55: =AVERAGE(D55:I55) -> 102884.34 | K55: 105872.36 | L55: 124275.56 | M55: 71600 | N55: 65384.72 | O55: 91783.16 | P55: =SUM(D55:O55) -> 1179106.2
A56: Other Overhead Costs | C56: MK | D56: 10000 | E56: 84100 | F56: 89120 | G56: =AVERAGE(D56:F56) -> 61073.333 | H56: 72857.94 | I56: 78460 | J56: =AVERAGE(D56:I56) -> 65935.212 | K56: 86479.71 | L56: 101653.2 | M56: 92400 | O56: 95653.728 | P56: =SUM(D56:O56) -> 837733.12
A57: Operating Costs
A58: Total Operating Costs | C58: MK | D58: =D41+D46+D51+D52+D54+D55+D56 -> 352632.66 | E58: =E41+E46+E51+E52+E54+E55+E56 -> 399473.55 | F58: =F41+F46+F51+F52+F54+F55+F56 -> 500866.98 | G58: =G41+G46+G51+G52+G54+G55+G56 -> 438612.2 | H58: =H41+H46+H51+H52+H54+H55+H56 -> 378505.53 | I58: =I41+I46+I51+I52+I54+I55+I56 -> 384665.59 | J58: =J41+J46+J51+J52+J54+J55+J56 -> 302505.55 | K58: =K41+K46+K51+K52+K54+K55+K56 -> 710879.64 | ... N58: =N41+N46+N51+N52+N54+N55+N56 -> 222077.73 | O58: 314116.44 | P58: =SUM(D58:O58) -> 5045896.7
A59: Cost/Vol. Produced | C59: Mk/m3 | D59: =D58/D9 -> 254.42472 | E59: =E58/E9 -> 166.10127 | F59: =F58/F9 -> 107.48218 | G59: =G58/G9 -> 128.81416 | H59: =H58/Migowi!H9 -> 119.66662 | I59: =I58/I9 -> 108.47873 | J59: =J58/J9 -> 87.53054 | K59: =K58/K9 -> 228.35838 | L59: =L58/L9 -> 186.53343 | M59: =M58/M9 -> 93.281881 | N59: =N58/N9 -> 36.459979 | O59: 73.169447 | P59: =P58/P9 -> 117.90305
A60: Cost/Vol. Billed | C60: Mk/m3 | D60: =D58/D22 -> 342.02974 | E60: =E58/E22 -> 219.49096 | F60: =F58/F22 -> 136.49089 | G60: =G58/G22 -> 155.89003 | H60: =H58/H22 -> 141.7093 | I60: =I58/I22 -> 123.88586 | J60: =J58/J22 -> 103.23364 | K60: =K58/K22 -> 308.54151 | ... N60: =N58/N22 -> 42.814291 | O60: 79.589641 | P60: =P58/P22 -> 140.88702
A61: Permanent Staff Employed | C61: No | D61: 1 | E61: 1 | F61: 1 | G61: 1 | H61: 1 | I61: 1 | J61: 1 | K61: 1 | L61: 1 | P61: =O61 -> 0
A62: Staff/Vol.1000m3 of Volume Produced/hour (12 hour day) | C62: No/1000m3 | D62: =(D61*1000*31)/D9 -> 22.366522 | E62: =(E61*1000*31)/E9 -> 12.889813 | F62: =(F61*1000*31)/F9 -> 6.6523605 | G62: =(G61*1000*31)/G9 -> 9.1042584 | H62: =(H61*1000*31)/Migowi!H9 -> 9.800822 | I62: =(I61*1000*31)/I9 -> 8.7422448 | J62: =(J61*1000*31)/J9 -> 8.9699074 | K62: =(K61*1000*31)/K9 -> 9.9582396 | L62: =(L61*1000*31)/L9 -> 7.973251 | M62: =(M61*1000*31)/M9 -> 0 | N62: =(N61*1000*31)/N9 -> 0 | O62: 0 | P62: =(P61*1000*31)/P9 -> 0
A63: Temporary Staff Employed | C63: No | D63: 2 | E63: 2 | F63: 2 | G63: 2 | H63: 2 | I63: 2 | J63: 2 | K63: 2 | L63: 2 | M63: 2 | N63: 2 | O63: 2 | P63: =SUM(D63:O63) -> 24
A65: Water Connections and Disconnections
A66: New Individual Water Connections | B66: Brought Forward | C66: No | D66: 0 | E66: =D71 -> 0 | F66: =E71 -> 0 | G66: =F71 -> 0 | P66: =D66 -> 0
B67: Applied this Month | C67: No | D67: 0 | E67: 0 | G67: 0 | P67: =SUM(D67:O67) -> 0
B68: Done this Month Postpaid | C68: No | D68: 0 | E68: 0 | G68: 0 | P68: =SUM(D68:O68) -> 0
B69: Done this Month Prepaid | C69: No | D69: 0 | E69: 0 | G69: 0 | P69: =SUM(D69:O69) -> 0
B70: Total Done | C70: No | D70: =D68+D69 -> 0 | E70: =E68+E69 -> 0 | F70: =F68+F69 -> 0 | G70: =G68+G69 -> 0 | H70: =H68+H69 -> 0 | I70: =I68+I69 -> 0 | J70: =J68+J69 -> 0 | K70: =K68+K69 -> 0 | ... N70: =N68+N69 -> 0 | O70: 0 | P70: =P68+P69 -> 0
B71: Carried Forward | C71: No | D71: =D66+D67-D70 -> 0 | E71: =E66+E67-E70 -> 0 | F71: =F66+F67-F70 -> 0 | G71: =G66+G67-G70 -> 0 | H71: =H66+H67-H70 -> 0 | I71: =I66+I67-I70 -> 0 | J71: =J66+J67-J70 -> 0 | K71: =K66+K67-K70 -> 0 | ... N71: =N66+N67-N70 -> 0 | O71: 0 | P71: =P66+P67-P70 -> 0
A72: New Institutional Water Connections | B72: Brought Forward | C72: No | D72: 0 | E72: =D77 -> 0 | F72: =E77 -> 0 | G72: =F77 -> 0 | P72: =D72 -> 0
B73: Applied this Month | C73: No | D73: 0 | E73: 0 | G73: 0 | P73: =SUM(D73:O73) -> 0
B74: Done this Month Postpaid | C74: No | D74: 0 | E74: 0 | G74: 0 | P74: =SUM(D74:O74) -> 0
B75: Done this Month Prepaid | C75: No | D75: 0 | E75: 0 | G75: 0 | P75: =SUM(D75:O75) -> 0
B76: Total Done | C76: No | D76: =D74+D75 -> 0 | E76: =E74+E75 -> 0 | F76: =F74+F75 -> 0 | G76: =G74+G75 -> 0 | H76: =H74+H75 -> 0 | I76: =I74+I75 -> 0 | J76: =J74+J75 -> 0 | K76: =K74+K75 -> 0 | ... N76: =N74+N75 -> 0 | O76: 0 | P76: =P74+P75 -> 0
B77: Carried Forward | C77: No | D77: =D73+D74-D76 -> 0 | E77: =E73+E74-E76 -> 0 | F77: =F73+F74-F76 -> 0 | G77: =G73+G74-G76 -> 0 | H77: =H73+H74-H76 -> 0 | I77: =I73+I74-I76 -> 0 | J77: =J73+J74-J76 -> 0 | K77: =K73+K74-K76 -> 0 | ... N77: =N73+N74-N76 -> 0 | O77: 0 | P77: =P73+P74-P76 -> 0
A78: New Commercial/Industrial Water Connections | B78: Brought Forward | C78: No | D78: 0 | E78: =D83 -> 0 | F78: =E83 -> 0 | G78: =F83 -> 0 | P78: =D78 -> 0
B79: Applied this Month | C79: No | D79: 0 | E79: 0 | G79: 0 | P79: =SUM(D79:O79) -> 0
B80: Done this Month Postpaid | C80: No | D80: 0 | E80: 0 | G80: 0 | P80: =SUM(D80:O80) -> 0
B81: Done this Month Prepaid | C81: No | D81: 0 | E81: 0 | G81: 0 | P81: =SUM(D81:O81) -> 0
B82: Total Done | C82: No | D82: =D81+D80 -> 0 | E82: =E81+E80 -> 0 | F82: =F81+F80 -> 0 | G82: =G81+G80 -> 0 | H82: =H81+H80 -> 0 | I82: =I81+I80 -> 0 | J82: =J81+J80 -> 0 | K82: =K81+K80 -> 0 | ... N82: =N81+N80 -> 0 | O82: 0 | P82: =P81+P80 -> 0
B83: Carried Forward | C83: No | D83: =D78+D79-D82 -> 0 | E83: =E78+E79-E82 -> 0 | F83: =F78+F79-F82 -> 0 | G83: =G78+G79-G82 -> 0 | H83: =H78+H79-H82 -> 0 | I83: =I78+I79-I82 -> 0 | J83: =J78+J79-J82 -> 0 | K83: =K78+K79-K82 -> 0 | ... N83: =N78+N79-N82 -> 0 | O83: 0 | P83: =P78+P79-P82 -> 0
A84: New CWP | B84: Brought Forward | C84: No | D84: 0 | E84: =D89 -> 0 | F84: =E89 -> 0 | G84: =F89 -> 0 | P84: =D84 -> 0
B85: Applied this Month | C85: No | D85: 0 | E85: 0 | F85: 0 | G85: 0 | P85: =SUM(D85:O85) -> 0
B86: Done this Month Postpaid | C86: No | D86: 0 | E86: 0 | F86: 0 | G86: 0 | P86: =SUM(D86:O86) -> 0
B87: Done this Month Prepaid | C87: No | D87: 0 | E87: 0 | F87: 0 | G87: 0 | P87: =SUM(D87:O87) -> 0
B88: Total Done | C88: No | D88: =D86+D87 -> 0 | E88: =E86+E87 -> 0 | F88: =F86+F87 -> 0 | G88: =G86+G87 -> 0 | H88: 0 | I88: 0 | J88: 0 | K88: 0 | L88: 0 | M88: 0 | N88: 0 | O88: 0 | P88: =SUM(D88:O88) -> 0
B89: Carried Forward | C89: No | D89: =D84+D85-D88 -> 0 | E89: =E84+E85-E88 -> 0 | F89: =F84+F85-F88 -> 0 | G89: =G84+G85-G88 -> 0 | H89: 0 | I89: 0 | J89: 0 | K89: 0 | L89: 0 | M89: 0 | N89: 0 | O89: 0 | P89: 0
A90: Aggregated New Water connections | B90: Brought Forward | C90: No | D90: =D66+D72+D78+D84 -> 0 | E90: =E66+E72+E78+E84 -> 0 | F90: =F66+F72+F78+F84 -> 0 | G90: =G66+G72+G78+G84 -> 0 | H90: =H66+H72+H78+H84 -> 0 | I90: =I66+I72+I78+I84 -> 0 | J90: =J66+J72+J78+J84 -> 0 | K90: =K66+K72+K78+K84 -> 0 | ... N90: =N66+N72+N78+N84 -> 0 | O90: 0 | P90: =D90 -> 0
B91: Applied this Month | C91: No | D91: =D67+D73+D79+D85 -> 0 | E91: =E67+E73+E79+E85 -> 0 | F91: =F67+F73+F79+F85 -> 0 | G91: =G67+G73+G79+G85 -> 0 | H91: =H67+H73+H79+H85 -> 0 | I91: =I67+I73+I79+I85 -> 0 | J91: =J67+J73+J79+J85 -> 0 | K91: =K67+K73+K79+K85 -> 0 | ... N91: =N67+N73+N79+N85 -> 0 | O91: 0 | P91: =SUM(D91:O91) -> 0
B92: Done this Month Postpaid | C92: No | D92: =D68+D74+D80+D86 -> 0 | E92: =E68+E74+E80+E86 -> 0 | F92: =F68+F74+F80+F86 -> 0 | G92: =G68+G74+G80+G86 -> 0 | H92: =H68+H74+H80+H86 -> 0 | I92: =I68+I74+I80+I86 -> 0 | J92: =J68+J74+J80+J86 -> 0 | K92: =K68+K74+K80+K86 -> 0 | ... N92: =N68+N74+N80+N86 -> 0 | O92: 0 | P92: =SUM(D92:O92) -> 0
B93: Done this Month Prepaid | D93: =D69+D75+D81+D87 -> 0 | E93: =E69+E75+E81+E87 -> 0 | F93: =F69+F75+F81+F87 -> 0 | G93: =G69+G75+G81+G87 -> 0 | H93: =H69+H75+H81+H87 -> 0 | I93: =I69+I75+I81+I87 -> 0 | J93: =J69+J75+J81+J87 -> 0 | K93: =K69+K75+K81+K87 -> 0 | ... N93: =N69+N75+N81+N87 -> 0 | O93: 0 | P93: =SUM(D93:O93) -> 0
B94: Total Done | C94: No | D94: =D93+D92 -> 0 | E94: =E93+E92 -> 0 | F94: =F93+F92 -> 0 | G94: =G93+G92 -> 0 | H94: =H93+H92 -> 0 | I94: =I93+I92 -> 0 | J94: =J93+J92 -> 0 | K94: =K93+K92 -> 0 | ... N94: =N93+N92 -> 0 | O94: 0 | P94: =P93+P92 -> 0
B95: Carried Forward | C95: No | D95: =D90+D91-D94 -> 0 | E95: =E90+E91-E94 -> 0 | F95: =F90+F91-F94 -> 0 | G95: =G90+G91-G94 -> 0 | H95: =H90+H91-H94 -> 0 | I95: =I90+I91-I94 -> 0 | J95: =J90+J91-J94 -> 0 | K95: =K90+K91-K94 -> 0 | ... N95: =N90+N91-N94 -> 0 | O95: 0 | P95: =P90+P91-P94 -> 0
A97: Prepaid Metering
A98: Prepaid Meters Installed | C98: No | D98: 1 | E98: 0 | F98: 0 | P98: =SUM(D98:O98) -> 1
A100: Active and Disconnected Accounts
A101: Disconnected Individual Accounts | C101: No | D101: 0 | E101: 0 | F101: 0 | P101: =O101 -> 0
A102: Disconnected institutional Accounts | C102: No | D102: 0 | E102: 0 | F102: 0 | P102: =O102 -> 0
A103: Disconnected Commercial/Industrial Accounts | C103: No | D103: 0 | E103: 0 | F103: 0 | P103: =O103 -> 0
A104: Disconnected CWP | C104: No | D104: 0 | E104: 0 | F104: 0 | P104: =O104 -> 0
A105: Total Disconnected Accounts | C105: No | D105: =SUM(D101:D104) -> 0 | E105: =SUM(E101:E104) -> 0 | F105: =SUM(F101:F104) -> 0 | G105: =SUM(G101:G104) -> 0 | H105: =SUM(H101:H104) -> 0 | I105: =SUM(I101:I104) -> 0 | J105: =SUM(J101:J104) -> 0 | K105: =SUM(K101:K104) -> 0 | ... N105: =SUM(N101:N104) -> 0 | O105: 0 | P105: =O105 -> 0
A106: Postpaid Consumers
...

Sheet Nkando
A1: SOUTHERN REGION WATER BOARD
A3: MONTHLY REPORTS - 2023/2024
A4: MULANJE ZONE
A5: MULANJE ZONE
A7: PARAMETERS | C7: UNITS | D7: APRIL | E7: MAY | F7: JUNE | G7: JULY | H7: AUGUST | I7: SEPTEMBER | J7: OCTOBER | K7: NOVEMBER | L7: DECEMBER | M7: JANUARY | N7: FEBRUARY | O7: MARCH | P7: TOTALS
A8: 0
A9: Volume Produced | C9: m3 | D9: 0 | E9: 0 | F9: 0 | G9: 0 | H9: 0 | I9: 0 | J9: 0 | K9: 0 | L9: 0 | M9: 2440 | N9: 3384 | O9: 1824 | P9: =SUM(D9:O9) -> 7648
A10: .
A11: Volume Billed Individuals | C11: m3 | D11: 0 | E11: 0 | F11: 0 | G11: 0 | H11: 0 | I11: 0 | J11: 0 | K11: 0 | L11: 0 | M11: 1493 | N11: =286+1122 -> 1408 | O11: 998 | P11: =SUM(D11:O11) -> 3899
A12: Volume Billed CWPs | C12: m3 | D12: 0 | E12: 0 | F12: 0 | G12: . | H12: 0 | N12: 15 | O12: 4 | P12: =SUM(D12:O12) -> 19
A13: Volume Billed Institutions | C13: m3 | D13: 0 | F13: 0 | G13: 0 | H13: 0 | M13: 221 | N13: 1317 | O13: 164 | P13: =SUM(D13:O13) -> 1702
A14: Volume Billed Commercial/Industrial | C14: m3 | D14: 0 | F14: 0 | G14: 0 | H14: 0 | M14: 259 | N14: 173 | O14: 271 | P14: =SUM(D14:O14) -> 703
A15: Total Volume Billed Post Paid | C15: m3 | D15: =SUM(D11:D14) -> 0 | E15: =SUM(E11:E14) -> 0 | F15: =SUM(F11:F14) -> 0 | G15: =SUM(G11:G14) -> 0 | H15: =SUM(H11:H14) -> 0 | I15: =SUM(I11:I14) -> 0 | J15: =SUM(J11:J14) -> 0 | K15: =SUM(K11:K14) -> 0 | ... N15: =SUM(N11:N14) -> 2913 | O15: 1437 | P15: =SUM(P11:P14) -> 6323
A16: REVENUE WATER - PREPAID
A17: Individuals | C17: m3 | D17: 0 | E17: 0 | F17: 0 | G17: 0 | H17: 0 | I17: 0 | J17: 0 | K17: 0 | L17: 0 | P17: =SUM(D17:O17) -> 0
A18: CWPs | C18: m3 | F18: 0 | G18: 0 | H18: 0 | I18: 0 | J18: 0 | K18: 0 | L18: 0 | P18: =SUM(D18:O18) -> 0
A19: Institutions | C19: m3 | D19: 0 | E19: 0 | F19: 0 | G19: 0 | H19: 0 | I19: 0 | J19: 0 | K19: 0 | L19: 0 | P19: =SUM(D19:O19) -> 0
A20: Commercial/Industrial | C20: m3 | F20: 0 | H20: 0 | K20: 0 | P20: =SUM(D20:O20) -> 0
A21: Total Volume Prepaid | C21: m3 | D21: =SUM(D17:D20) -> 0 | E21: =SUM(E17:E20) -> 0 | F21: =SUM(F17:F20) -> 0 | G21: =SUM(G17:G20) -> 0 | H21: =SUM(H17:H20) -> 0 | I21: =SUM(I17:I20) -> 0 | J21: =SUM(J17:J20) -> 0 | K21: =SUM(K17:K20) -> 0 | ... N21: =SUM(N17:N20) -> 0 | O21: 0 | P21: =SUM(P17:P20) -> 0
A22: TOTAL REVENUE WATER | C22: m3 | D22: =D21+D15 -> 0 | E22: =E21+E15 -> 0 | F22: =F21+F15 -> 0 | G22: =G21+G15 -> 0 | H22: =H21+H15 -> 0 | I22: =I21+I15 -> 0 | J22: =J21+J15 -> 0 | K22: =K21+K15 -> 0 | ... N22: =N21+N15 -> 2913 | O22: 1437 | P22: =P21+P15 -> 6323
A24: Non-Revenue Water (NRW) | B24: Volume | C24: m3 | D24: =D9-D22 -> 0 | E24: =E9-E22 -> 0 | F24: =F9-F22 -> 0 | G24: =G9-G22 -> 0 | H24: =H9-H22 -> 0 | I24: =I9-I22 -> 0 | J24: =J9-J22 -> 0 | K24: =K9-K22 -> 0 | ... N24: =N9-N22 -> 471 | O24: 387 | P24: =P9-P22 -> 1325
B25: Percentage | C25: % | D25: =D24/D9 -> #DIV/0! | E25: =E24/E9 -> #DIV/0! | F25: =F24/F9 -> #DIV/0! | G25: =G24/G9 -> #DIV/0! | H25: =H24/H9 -> #DIV/0! | I25: =I24/I9 -> #DIV/0! | J25: =J24/J9 -> #DIV/0! | K25: =K24/K9 -> #DIV/0! | ... N25: =N24/N9 -> 0.1391844 | O25: 0.21217105 | P25: =P24/P9 -> 0.17324791
A26: OPERATING EXPENSES
A27: Chemicals
A28: Chemical | B28: Rate(MK/kg)
A29: Chlorine | B29: 5111.67 | C29: kg | D29: 0 | E29: 0 | F29: 0 | G29: 0 | H29: 0 | I29: 0 | J29: 0 | K29: 0 | L29: 0 | N29: 1 | O29: 1 | P29: =SUM(D29:O29) -> 2
C30: kg/mg litre | D30: =D29/(D9/1000) -> #DIV/0! | E30: =E29/(E9/1000) -> #DIV/0! | F30: =F29/(F9/1000) -> #DIV/0! | G30: =G29/(G9/1000) -> #DIV/0! | H30: =H29/(H9/1000) -> #DIV/0! | I30: =I29/(I9/1000) -> #DIV/0! | J30: =J29/(J9/1000) -> #DIV/0! | K30: =K29/(K9/1000) -> #DIV/0! | L30: 0 | M30: =M29/(M9/1000) -> 0 | N30: =N29/(N9/1000) -> 0.29550827 | O30: 0.54824561 | P30: =P29/(P9/1000) -> 0.26150628
A31: Aluminium sulphate | B31: 1537 | C31: kg | P31: =SUM(D31:O31) -> 0
C32: kg/mg litre | D32: =D31/(D9/1000) -> #DIV/0! | E32: =E31/(E9/1000) -> #DIV/0! | F32: =F31/(F9/1000) -> #DIV/0! | G32: =G31/(G9/1000) -> #DIV/0! | H32: =H31/(H9/1000) -> #DIV/0! | I32: =I31/(I9/1000) -> #DIV/0! | J32: =J31/(J9/1000) -> #DIV/0! | K32: =K31/(K9/1000) -> #DIV/0! | ... N32: =N31/(N9/1000) -> 0 | O32: 0 | P32: =P31/(P9/1000) -> 0
A33: Soda | B33: 1781.02 | C33: kg | P33: =SUM(D33:O33) -> 0
C34: kg/mg litre | D34: =D33/(D9/1000) -> #DIV/0! | E34: =E33/(E9/1000) -> #DIV/0! | F34: =F33/(F9/1000) -> #DIV/0! | G34: =G33/(G9/1000) -> #DIV/0! | H34: =H33/(H9/1000) -> #DIV/0! | I34: =I33/(I9/1000) -> #DIV/0! | J34: =J33/(J9/1000) -> #DIV/0! | K34: =K33/(K9/1000) -> #DIV/0! | ... N34: =N33/(N9/1000) -> 0 | O34: 0 | P34: =P33/(P9/1000) -> 0
A35: Algae floc | B35: 5979.95 | C35: litres
C36: litres/mg litre
A37: Sud floc | B37: 5403.75 | C37: litres | D37: 0 | E37: 0 | F37: 0 | G37: 0 | H37: 0 | I37: 0 | J37: 0 | K37: 0 | L37: 0 | M37: 0 | N37: 0 | O37: 0 | P37: =SUM(D37:O37) -> 0
C38: litres/mg litre | D38: =D37/(D9/1000) -> #DIV/0! | E38: =E37/(E9/1000) -> #DIV/0! | F38: =F37/(F9/1000) -> #DIV/0! | G38: =G37/(G9/1000) -> #DIV/0! | H38: =H37/(H9/1000) -> #DIV/0! | I38: =I37/(I9/1000) -> #DIV/0! | J38: =J37/(J9/1000) -> #DIV/0! | K38: =K37/(K9/1000) -> #DIV/0! | ... N38: =N37/(N9/1000) -> 0 | O38: 0 | P38: =P37/(P9/1000) -> 0
A39: Potasium permanganate | B39: 1950 | C39: kg | D39: 0 | E39: 0 | F39: 0 | G39: 0 | H39: 0 | I39: 0 | J39: 0 | K39: 0 | L39: 0 | M39: 0 | N39: 0 | O39: 0 | P39: =SUM(D39:O39) -> 0
C40: kg/mg litre | D40: =D39/(D9/1000) -> #DIV/0! | E40: =E39/(E9/1000) -> #DIV/0! | F40: =F39/(F9/1000) -> #DIV/0! | G40: =G39/(G9/1000) -> #DIV/0! | H40: =H39/(H9/1000) -> #DIV/0! | I40: =I39/(I9/1000) -> #DIV/0! | J40: =J39/(J9/1000) -> #DIV/0! | K40: =K39/(K9/1000) -> #DIV/0! | ... N40: =N39/(N9/1000) -> 0 | O40: 0 | P40: =P39/(P9/1000) -> 0
A41: Cost of Chemicals | C41: Mk | D41: =(D29*$B29)+(D31*$B31)+(D33*$B33)+(D35*$B35)+(D37*$B37)+(D39*$B39) -> 0 | E41: =(E29*$B29)+(E31*$B31)+(E33*$B33)+(E35*$B35)+(E37*$B37)+(E39*$B39) -> 0 | F41: =(F29*$B29)+(F31*$B31)+(F33*$B33)+(F35*$B35)+(F37*$B37)+(F39*$B39) -> 0 | G41: =(G29*$B29)+(G31*$B31)+(G33*$B33)+(G35*$B35)+(G37*$B37)+(G39*$B39) -> 0 | H41: =(H29*$B29)+(H31*$B31)+(H33*$B33)+(H35*$B35)+(H37*$B37)+(H39*$B39) -> 0 | I41: =(I29*$B29)+(I31*$B31)+(I33*$B33)+(I35*$B35)+(I37*$B37)+(I39*$B39) -> 0 | J41: =(J29*$B29)+(J31*$B31)+(J33*$B33)+(J35*$B35)+(J37*$B37)+(J39*$B39) -> 0 | K41: =(K29*$B29)+(K31*$B31)+(K33*$B33)+(K35*$B35)+(K37*$B37)+(K39*$B39) -> 0 | ... N41: =(N29*$B29)+(N31*$B31)+(N33*$B33)+(N35*$B35)+(N37*$B37)+(N39*$B39) -> 5111.67 | O41: 5111.67 | P41: =SUM(D41:O41) -> 10223.34
A42: Cost/vol. Produced (chemicals) | C42: Mk/m3 | D42: =D41/D9 -> #DIV/0! | E42: =E41/E9 -> #DIV/0! | F42: =F41/F9 -> #DIV/0! | G42: =G41/G9 -> #DIV/0! | H42: =H41/H9 -> #DIV/0! | I42: =I41/I9 -> #DIV/0! | J42: =J41/J9 -> #DIV/0! | K42: =K41/K9 -> #DIV/0! | ... N42: =N41/N9 -> 1.5105408 | O42: 2.8024507 | P42: =P41/P9 -> 1.3367338
A43: Power
A44: Power Usage | C44: Kw | D44: 0 | E44: 0 | F44: 0 | G44: 0 | H44: 0 | I44: 0 | J44: 0 | K44: 0 | L44: 0 | M44: 334 | N44: 461 | O44: 3061 | P44: =SUM(D44:O44) -> 3856
A45: Power/ Vol. Produced | C45: Kw/m3 | D45: =D44/D9 -> #DIV/0! | E45: =E44/E9 -> #DIV/0! | F45: =F44/F9 -> #DIV/0! | G45: =G44/G9 -> #DIV/0! | H45: =H44/H9 -> #DIV/0! | I45: =I44/I9 -> #DIV/0! | J45: =J44/J9 -> #DIV/0! | K45: =K44/K9 -> #DIV/0! | ... N45: =N44/N9 -> 0.13622931 | O45: 1.6781798 | P45: =P44/P9 -> 0.5041841
A46: Cost of Power | C46: Mk | D46: =1.165*(14100+(D44*119.1)) -> 16426.5 | E46: =1.165*(14100+(E44*119.1)) -> 16426.5 | F46: =1.165*(14100+(F44*119.1)) -> 16426.5 | G46: =1.165*(14100+(G44*119.1)) -> 16426.5 | H46: =1.165*(14100+(H44*119.1)) -> 16426.5 | I46: =1.165*(14100+(I44*119.1)) -> 16426.5 | J46: =1.165*(14100+(J44*119.1)) -> 16426.5 | K46: =1.165*(14100+(K44*119.1)) -> 16426.5 | ... N46: =1.165*(14100+(N44*119.1)) -> 80390.942 | O46: 441144.84 | P46: =SUM(D46:O46) -> 732143.78
A47: Cost/vol. Produced | C47: Mk/m3 | D47: =D46/D9 -> #DIV/0! | E47: =E46/E9 -> #DIV/0! | F47: =F46/F9 -> #DIV/0! | G47: =G46/G9 -> #DIV/0! | H47: =H46/H9 -> #DIV/0! | I47: =I46/I9 -> #DIV/0! | J47: =J46/J9 -> #DIV/0! | K47: =K46/K9 -> #DIV/0! | ... N47: =N46/N9 -> 23.756188 | O47: 241.85572 | P47: =P46/P9 -> 95.730097
A48: Plant and Vehicle Maintenance
A49: Distances covered | C49: km | M49: 210 | P49: =SUM(D49:O49) -> 210
A50: Fuel Used (litres) | C50: litres | M50: 7 | P50: =SUM(D50:O50) -> 7
A51: Cost of fuel | C51: Mk | M51: 17710 | P51: =SUM(D51:O51) -> 17710
A52: Maintenance | C52: Mk | D52: 0 | E52: 0 | F52: 0 | G52: 0 | H52: 0 | I52: 0 | J52: 0 | K52: 0 | L52: 0 | M52: 1200 | N52: 0 | O52: 0 | P52: =SUM(D52:O52) -> 1200
A53: Salaries and Wages
A54: Staff Costs | C54: MK | M54: 246361.25 | N54: =40000*6 -> 240000 | O54: 536538.7 | P54: =SUM(D54:O54) -> 1022899.9
A55: Wages | C55: MK | D55: 0 | E55: 0 | F55: 0 | G55: =AVERAGE(D55:F55) -> 0 | H55: 0 | I55: 0 | J55: =AVERAGE(D55:I55) -> 0 | K55: 0 | L55: 0 | M55: 32000 | N55: 32000 | O55: 32000 | P55: =SUM(D55:O55) -> 96000
A56: Other Overhead Costs | C56: MK | D56: 0 | E56: 0 | F56: 0 | G56: =AVERAGE(D56:F56) -> 0 | H56: 0 | I56: 0 | J56: 0 | K56: 0 | L56: 0 | O56: 280000 | P56: =SUM(D56:O56) -> 280000
A57: Operating Costs
A58: Total Operating Costs | C58: MK | D58: =D41+D46+D51+D52+D54+D55+D56 -> 16426.5 | E58: =E41+E46+E51+E52+E54+E55+E56 -> 16426.5 | F58: =F41+F46+F51+F52+F54+F55+F56 -> 16426.5 | G58: =G41+G46+G51+G52+G54+G55+G56 -> 16426.5 | H58: =H41+H46+H51+H52+H54+H55+H56 -> 16426.5 | I58: =I41+I46+I51+I52+I54+I55+I56 -> 16426.5 | J58: =J41+J46+J51+J52+J54+J55+J56 -> 16426.5 | K58: =K41+K46+K51+K52+K54+K55+K56 -> 16426.5 | ... N58: =N41+N46+N51+N52+N54+N55+N56 -> 357502.61 | O58: 1294795.2 | P58: =SUM(D58:O58) -> 2160177.1
A59: Cost/Vol. Produced | C59: Mk/m3 | D59: =D58/D9 -> #DIV/0! | E59: =E58/E9 -> #DIV/0! | F59: =F58/F9 -> #DIV/0! | G59: =G58/G9 -> #DIV/0! | H59: =H58/H9 -> #DIV/0! | I59: =I58/I9 -> #DIV/0! | J59: =J58/J9 -> #DIV/0! | K59: =K58/K9 -> #DIV/0! | ... N59: =N58/N9 -> 105.64498 | O59: 709.8658 | P59: =P58/P9 -> 282.44993
A60: Cost/Vol. Billed | C60: Mk/m3 | D60: =D58/D22 -> #DIV/0! | E60: =E58/E22 -> #DIV/0! | F60: =F58/F22 -> #DIV/0! | G60: =G58/G22 -> #DIV/0! | H60: =H58/H22 -> #DIV/0! | I60: =I58/I22 -> #DIV/0! | J60: =J58/J22 -> #DIV/0! | K60: =K58/K22 -> #DIV/0! | ... N60: =N58/N22 -> 122.72661 | O60: 901.04051 | P60: =P58/P22 -> 341.638
A61: Permanent Staff Employed | C61: No | D61: 0 | E61: 0 | F61: 0 | G61: 0 | M61: 6 | N61: 6 | O61: 6 | P61: =O61 -> 6
A62: Staff/Vol.1000m3 of Volume Produced/hour (12 hour day) | C62: No/1000m3 | D62: =(D61*1000*31)/D9 -> #DIV/0! | E62: =(E61*1000*31)/E9 -> #DIV/0! | F62: =(F61*1000*31)/F9 -> #DIV/0! | G62: =(G61*1000*31)/G9 -> #DIV/0! | H62: =(H61*1000*31)/H9 -> #DIV/0! | I62: =(I61*1000*31)/I9 -> #DIV/0! | J62: =(J61*1000*31)/J9 -> #DIV/0! | K62: =(K61*1000*31)/K9 -> #DIV/0! | ... N62: =(N61*1000*31)/N9 -> 54.964539 | O62: 101.97368 | P62: =(P61*1000*31)/P9 -> 24.320084
A63: Temporary Staff Employed | C63: No | D63: 0 | E63: 0 | F63: 0 | G63: 0 | H63: 0 | I63: 0 | J63: 0 | K63: 0 | L63: 0 | M63: 2 | N63: 2 | O63: 2 | P63: =SUM(D63:O63) -> 6
A65: Water Connections and Disconnections
A66: New Individual Water Connections | B66: Brought Forward | C66: No | D66: 0 | E66: 0 | F66: 0 | G66: 0 | H66: =G71 -> 0 | M66: 1 | N66: =M71 -> 1 | O66: 1 | P66: =D66 -> 0
B67: Applied this Month | C67: No | D67: 0 | E67: 0 | F67: 0 | G67: 0 | H67: 0 | N67: 0 | P67: =SUM(D67:O67) -> 0
B68: Done this Month Postpaid | C68: No | D68: 0 | E68: 0 | F68: 0 | G68: 0 | H68: 0 | N68: 0 | P68: =SUM(D68:O68) -> 0
B69: Done this Month Prepaid | C69: No | D69: 0 | E69: 0 | F69: 0 | G69: 0 | H69: 0 | N69: 0 | P69: =SUM(D69:O69) -> 0
B70: Total Done | C70: No | D70: =D68+D69 -> 0 | E70: =E68+E69 -> 0 | F70: =F68+F69 -> 0 | G70: =G68+G69 -> 0 | H70: =H68+H69 -> 0 | I70: =I68+I69 -> 0 | J70: =J68+J69 -> 0 | K70: =K68+K69 -> 0 | ... N70: =N68+N69 -> 0 | O70: 0 | P70: =P68+P69 -> 0
B71: Carried Forward | C71: No | D71: =D66+D67-D70 -> 0 | E71: =E66+E67-E70 -> 0 | F71: =F66+F67-F70 -> 0 | G71: =G66+G67-G70 -> 0 | H71: =H66+H67-H70 -> 0 | I71: =I66+I67-I70 -> 0 | J71: =J66+J67-J70 -> 0 | K71: =K66+K67-K70 -> 0 | ... N71: =N66+N67-N70 -> 1 | O71: 1 | P71: =P66+P67-P70 -> 0
A72: New Institutional Water Connections | B72: Brought Forward | C72: No | D72: 0 | E72: 0 | F72: 0 | G72: 0 | H72: =G77 -> 0 | P72: =D72 -> 0
B73: Applied this Month | C73: No | D73: 0 | E73: 0 | F73: 0 | G73: 0 | P73: =SUM(D73:O73) -> 0
B74: Done this Month Postpaid | C74: No | D74: 0 | E74: 0 | F74: 0 | G74: 0 | P74: =SUM(D74:O74) -> 0
B75: Done this Month Prepaid | C75: No | D75: 0 | E75: 0 | F75: 0 | G75: 0 | P75: =SUM(D75:O75) -> 0
B76: Total Done | C76: No | D76: =D74+D75 -> 0 | E76: =E74+E75 -> 0 | F76: =F74+F75 -> 0 | G76: =G74+G75 -> 0 | H76: =H74+H75 -> 0 | I76: =I74+I75 -> 0 | J76: =J74+J75 -> 0 | K76: =K74+K75 -> 0 | ... N76: =N74+N75 -> 0 | O76: 0 | P76: =P74+P75 -> 0
B77: Carried Forward | C77: No | D77: =D73+D74-D76 -> 0 | E77: =E73+E74-E76 -> 0 | F77: =F73+F74-F76 -> 0 | G77: =G73+G74-G76 -> 0 | H77: =H73+H74-H76 -> 0 | I77: =I73+I74-I76 -> 0 | J77: =J73+J74-J76 -> 0 | K77: =K73+K74-K76 -> 0 | ... N77: =N73+N74-N76 -> 0 | O77: 0 | P77: =P73+P74-P76 -> 0
A78: New Commercial/Industrial Water Connections | B78: Brought Forward | C78: No | D78: 0 | E78: 0 | F78: 0 | G78: 0 | P78: =D78 -> 0
B79: Applied this Month | C79: No | D79: 0 | E79: 0 | F79: 0 | G79: 0 | P79: =SUM(D79:O79) -> 0
B80: Done this Month Postpaid | C80: No | D80: 0 | E80: 0 | F80: 0 | G80: 0 | P80: =SUM(D80:O80) -> 0
B81: Done this Month Prepaid | C81: No | D81: 0 | E81: 0 | F81: 0 | G81: 0 | P81: =SUM(D81:O81) -> 0
B82: Total Done | C82: No | D82: =D81+D80 -> 0 | E82: =E81+E80 -> 0 | F82: =F81+F80 -> 0 | G82: =G81+G80 -> 0 | H82: =H81+H80 -> 0 | I82: =I81+I80 -> 0 | J82: =J81+J80 -> 0 | K82: =K81+K80 -> 0 | ... N82: =N81+N80 -> 0 | O82: 0 | P82: =P81+P80 -> 0
B83: Carried Forward | C83: No | D83: =D78+D79-D82 -> 0 | E83: =E78+E79-E82 -> 0 | F83: =F78+F79-F82 -> 0 | G83: =G78+G79-G82 -> 0 | H83: =H78+H79-H82 -> 0 | I83: =I78+I79-I82 -> 0 | J83: =J78+J79-J82 -> 0 | K83: =K78+K79-K82 -> 0 | ... N83: =N78+N79-N82 -> 0 | O83: 0 | P83: =P78+P79-P82 -> 0
A84: New CWP | B84: Brought Forward | C84: No | D84: 0 | E84: =D89 -> 0 | F84: =E89 -> 0 | G84: =F89 -> 0 | P84: =D84 -> 0
B85: Applied this Month | C85: No | D85: 0 | E85: 0 | F85: 0 | G85: 0 | P85: =SUM(D85:O85) -> 0
B86: Done this Month Postpaid | C86: No | D86: 0 | E86: 0 | F86: 0 | G86: 0 | P86: =SUM(D86:O86) -> 0
B87: Done this Month Prepaid | C87: No | D87: 0 | E87: 0 | F87: 0 | G87: 0 | P87: =SUM(D87:O87) -> 0
B88: Total Done | C88: No | D88: =D86+D87 -> 0 | E88: =E86+E87 -> 0 | F88: =F86+F87 -> 0 | G88: =G86+G87 -> 0 | H88: =H87+H86 -> 0 | I88: =I87+I86 -> 0 | J88: =J87+J86 -> 0 | K88: =K87+K86 -> 0 | L88: =L87+L86 -> 0 | M88: =M87+M86 -> 0 | N88: =N87+N86 -> 0 | O88: 0 | P88: =SUM(D88:O88) -> 0
B89: Carried Forward | C89: No | D89: =D84+D85-D88 -> 0 | E89: 0 | F89: 0 | G89: 0 | H89: =H84+H85-H88 -> 0 | I89: =I84+I85-I88 -> 0 | J89: =J84+J85-J88 -> 0 | K89: =K84+K85-K88 -> 0 | L89: =L84+L85-L88 -> 0 | M89: =M84+M85-M88 -> 0 | N89: =N84+N85-N88 -> 0 | O89: 0 | P89: =P84+P85-P86-P87 -> 0
A90: Aggregated New Water connections | B90: Brought Forward | C90: No | D90: =D66+D72+D78+D84 -> 0 | E90: =E66+E72+E78+E84 -> 0 | F90: =F66+F72+F78+F84 -> 0 | G90: =G66+G72+G78+G84 -> 0 | H90: =H66+H72+H78+H84 -> 0 | I90: =I66+I72+I78+I84 -> 0 | J90: =J66+J72+J78+J84 -> 0 | K90: =K66+K72+K78+K84 -> 0 | ... N90: =N66+N72+N78+N84 -> 1 | O90: 1 | P90: =D90 -> 0
B91: Applied this Month | C91: No | D91: =D67+D73+D79+D85 -> 0 | E91: =E67+E73+E79+E85 -> 0 | F91: =F67+F73+F79+F85 -> 0 | G91: =G67+G73+G79+G85 -> 0 | H91: =H67+H73+H79+H85 -> 0 | I91: =I67+I73+I79+I85 -> 0 | J91: =J67+J73+J79+J85 -> 0 | K91: =K67+K73+K79+K85 -> 0 | ... N91: =N67+N73+N79+N85 -> 0 | O91: 0 | P91: =SUM(D91:O91) -> 0
B92: Done this Month Postpaid | C92: No | D92: =D68+D74+D80+D86 -> 0 | E92: =E68+E74+E80+E86 -> 0 | F92: =F68+F74+F80+F86 -> 0 | G92: =G68+G74+G80+G86 -> 0 | H92: =H68+H74+H80+H86 -> 0 | I92: =I68+I74+I80+I86 -> 0 | J92: =J68+J74+J80+J86 -> 0 | K92: =K68+K74+K80+K86 -> 0 | ... N92: =N68+N74+N80+N86 -> 0 | O92: 0 | P92: =SUM(D92:O92) -> 0
B93: Done this Month Prepaid | D93: =D69+D75+D81+D87 -> 0 | E93: =E69+E75+E81+E87 -> 0 | F93: =F69+F75+F81+F87 -> 0 | G93: =G69+G75+G81+G87 -> 0 | H93: =H69+H75+H81+H87 -> 0 | I93: =I69+I75+I81+I87 -> 0 | J93: =J69+J75+J81+J87 -> 0 | K93: =K69+K75+K81+K87 -> 0 | ... N93: =N69+N75+N81+N87 -> 0 | O93: 0 | P93: =SUM(D93:O93) -> 0
B94: Total Done | C94: No | D94: =D93+D92 -> 0 | E94: =E93+E92 -> 0 | F94: =F93+F92 -> 0 | G94: =G93+G92 -> 0 | H94: =H93+H92 -> 0 | I94: =I93+I92 -> 0 | J94: =J93+J92 -> 0 | K94: =K93+K92 -> 0 | ... N94: =N93+N92 -> 0 | O94: 0 | P94: =P93+P92 -> 0
B95: Carried Forward | C95: No | D95: =D90+D91-D94 -> 0 | E95: =E90+E91-E94 -> 0 | F95: =F90+F91-F94 -> 0 | G95: =G90+G91-G94 -> 0 | H95: =H90+H91-H94 -> 0 | I95: =I90+I91-I94 -> 0 | J95: =J90+J91-J94 -> 0 | K95: =K90+K91-K94 -> 0 | ... N95: =N90+N91-N94 -> 1 | O95: 1 | P95: =P90+P91-P94 -> 0
A97: Prepaid Metering
A98: Prepaid Meters Installed | C98: No | P98: =SUM(D98:O98) -> 0
A100: Active and Disconnected Accounts
A101: Disconnected Individual Accounts | C101: No | D101: 0 | E101: 0 | F101: 0 | G101: 0 | H101: 0 | I101: 0 | J101: 0 | K101: 0 | L101: 0 | M101: 46 | N101: 46 | O101: 46 | P101: =O101 -> 46
A102: Disconnected institutional Accounts | C102: No | D102: 0 | E102: 0 | F102: 0 | G102: 0 | H102: 0 | I102: 0 | J102: 0 | K102: 0 | L102: 0 | M102: 6 | N102: 6 | O102: 6 | P102: =O102 -> 6
A103: Disconnected Commercial/Industrial Accounts | C103: No | D103: 0 | E103: 0 | F103: 0 | G103: 0 | M103: 5 | N103: 6 | O103: 5 | P103: =O103 -> 5
A104: Disconnected CWP | C104: No | D104: 0 | E104: 0 | F104: 0 | G104: 0 | M104: 11 | N104: 11 | O104: 11 | P104: =O104 -> 11
A105: Total Disconnected Accounts | C105: No | D105: =SUM(D101:D104) -> 0 | E105: =SUM(E101:E104) -> 0 | F105: =SUM(F101:F104) -> 0 | G105: =SUM(G101:G104) -> 0 | H105: =SUM(H101:H104) -> 0 | I105: =SUM(I101:I104) -> 0 | J105: =SUM(J101:J104) -> 0 | K105: =SUM(K101:K104) -> 0 | ... N105: =SUM(N101:N104) -> 69 | O105: 68 | P105: =O105 -> 68
A106: Postpaid Consumers
...

Sheet Zone Monthly
A1: SOUTHERN REGION WATER BOARD
A3: MONTHLY REPORTS - 2023/2024
A4: MULANJEZONE
A5: MULANJE ZONE
A7: PARAMETERS | C7: UNITS | D7: APRIL | E7: MAY | F7: JUNE | G7: JULY | H7: AUGUST | I7: SEPTEMBER | J7: OCTOBER | K7: NOVEMBER | L7: DECEMBER | M7: JANUARY | N7: FEBRUARY | O7: MARCH | P7: TOTALS
A8: PRODUCTION
A9: Volume Produced | C9: m3 | D9: =Mulanje!D9+Luchenza!D9+Thyolo!D9+Muloza!D9+MUST!D9+Phalombe!D9+Mikolongwe!D9+Migowi!D9 -> 120548 | E9: =Mulanje!E9+Luchenza!E9+Thyolo!E9+Muloza!E9+MUST!E9+Phalombe!E9+Mikolongwe!E9+Migowi!E9 -> 125442 | F9: =Mulanje!F9+Luchenza!F9+Thyolo!F9+Muloza!F9+MUST!F9+Phalombe!F9+Mikolongwe!F9+Migowi!F9 -> 121596 | G9: =Mulanje!G9+Luchenza!G9+Thyolo!G9+Muloza!G9+MUST!G9+Phalombe!G9+Mikolongwe!G9+Migowi!G9 -> 114780 | H9: =Mulanje!H9+Luchenza!H9+Thyolo!H9+Muloza!H9+MUST!H9+Phalombe!H9+Mikolongwe!H9+Migowi!H9 -> 142252 | I9: =Mulanje!I9+Luchenza!I9+Thyolo!I9+Muloza!I9+MUST!I9+Phalombe!I9+Mikolongwe!I9+Migowi!I9 -> 117758 | J9: =Mulanje!J9+Luchenza!J9+Thyolo!J9+Muloza!J9+MUST!J9+Phalombe!J9+Mikolongwe!J9+Migowi!J9 -> 121755 | K9: =Mulanje!K9+Luchenza!K9+Thyolo!K9+Muloza!K9+MUST!K9+Phalombe!K9+Mikolongwe!K9+Migowi!K9 -> 120699 | L9: =Mulanje!L9+Luchenza!L9+Thyolo!L9+Muloza!L9+MUST!L9+Phalombe!L9+Mikolongwe!L9+Migowi!L9 -> 123606 | M9: =Mulanje!M9+Luchenza!M9+Thyolo!M9+Muloza!M9+MUST!M9+Phalombe!M9+Mikolongwe!M9+Migowi!M9+Nkando!M9 -> 110544 | N9: =Mulanje!N9+Luchenza!N9+Thyolo!N9+Muloza!N9+MUST!N9+Phalombe!N9+Mikolongwe!N9+Migowi!N9+Nkando!N9 -> 130963 | O9: =Mulanje!O9+Luchenza!O9+Thyolo!O9+Muloza!O9+MUST!O9+Phalombe!O9+Mikolongwe!O9+Migowi!O9+Nkando!O9 -> 130523 | P9: =SUM(D9:O9) -> 1480466
A10: REVENUE WATER - POSTPAID
A11: Volume Billed Individuals | C11: m3 | D11: =Mulanje!D11+Luchenza!D11+Thyolo!D11+Muloza!D11+MUST!D11+Phalombe!D11+Mikolongwe!D11+Migowi!D11 -> 41840 | E11: =Mulanje!E11+Luchenza!E11+Thyolo!E11+Muloza!E11+MUST!E11+Phalombe!E11+Mikolongwe!E11+Migowi!E11 -> 54501 | F11: =Mulanje!F11+Luchenza!F11+Thyolo!F11+Muloza!F11+MUST!F11+Phalombe!F11+Mikolongwe!F11+Migowi!F11 -> 46984 | G11: =Mulanje!G11+Luchenza!G11+Thyolo!G11+Muloza!G11+MUST!G11+Phalombe!G11+Mikolongwe!G11+Migowi!G11 -> 43700 | H11: =Mulanje!H11+Luchenza!H11+Thyolo!H11+Muloza!H11+MUST!H11+Phalombe!H11+Mikolongwe!H11+Migowi!H11 -> 44866 | I11: =Mulanje!I11+Luchenza!I11+Thyolo!I11+Muloza!I11+MUST!I11+Phalombe!I11+Mikolongwe!I11+Migowi!I11 -> 48728 | J11: =Mulanje!J11+Luchenza!J11+Thyolo!J11+Muloza!J11+MUST!J11+Phalombe!J11+Mikolongwe!J11+Migowi!J11 -> 43977 | K11: =Mulanje!K11+Luchenza!K11+Thyolo!K11+Muloza!K11+MUST!K11+Phalombe!K11+Mikolongwe!K11+Migowi!K11 -> 48579 | L11: =Mulanje!L11+Luchenza!L11+Thyolo!L11+Muloza!L11+MUST!L11+Phalombe!L11+Mikolongwe!L11+Migowi!L11 -> 47989 | M11: =Mulanje!M11+Luchenza!M11+Thyolo!M11+Muloza!M11+MUST!M11+Phalombe!M11+Mikolongwe!M11+Migowi!M11+Nkando!M11 -> 50661 | N11: =Mulanje!N11+Luchenza!N11+Thyolo!N11+Muloza!N11+MUST!N11+Phalombe!N11+Mikolongwe!N11+Migowi!N11+Nkando!N11 -> 47603 | O11: =Mulanje!O11+Luchenza!O11+Thyolo!O11+Muloza!O11+MUST!O11+Phalombe!O11+Mikolongwe!O11+Migowi!O11+Nkando!O11 -> 64944.7 | P11: =SUM(D11:O11) -> 584372.7
A12: Volume Billed CWPs | C12: m3 | D12: =Mulanje!D12+Luchenza!D12+Thyolo!D12+Muloza!D12+MUST!D12+Phalombe!D12+Mikolongwe!D12+Migowi!D12 -> 1185 | E12: =Mulanje!E12+Luchenza!E12+Thyolo!E12+Muloza!E12+MUST!E12+Phalombe!E12+Mikolongwe!E12+Migowi!E12 -> 1100 | F12: =Mulanje!F12+Luchenza!F12+Thyolo!F12+Muloza!F12+MUST!F12+Phalombe!F12+Mikolongwe!F12+Migowi!F12 -> 1191 | G12: =Mulanje!G12+Luchenza!G12+Thyolo!G12+Muloza!G12+MUST!G12+Phalombe!G12+Mikolongwe!G12+Migowi!G12 -> 1087 | H12: =Mulanje!H12+Luchenza!H12+Thyolo!H12+Muloza!H12+MUST!H12+Phalombe!H12+Mikolongwe!H12+Migowi!H12 -> 1074 | I12: =Mulanje!I12+Luchenza!I12+Thyolo!I12+Muloza!I12+MUST!I12+Phalombe!I12+Mikolongwe!I12+Migowi!I12 -> 1156 | J12: =Mulanje!J12+Luchenza!J12+Thyolo!J12+Muloza!J12+MUST!J12+Phalombe!J12+Mikolongwe!J12+Migowi!J12 -> 1205 | K12: =Mulanje!K12+Luchenza!K12+Thyolo!K12+Muloza!K12+MUST!K12+Phalombe!K12+Mikolongwe!K12+Migowi!K12 -> 1242 | L12: =Mulanje!L12+Luchenza!L12+Thyolo!L12+Muloza!L12+MUST!L12+Phalombe!L12+Mikolongwe!L12+Migowi!L12 -> 1245 | M12: =Mulanje!M12+Luchenza!M12+Thyolo!M12+Muloza!M12+MUST!M12+Phalombe!M12+Mikolongwe!M12+Migowi!M12+Nkando!M12 -> 1002 | N12: =Mulanje!N12+Luchenza!N12+Thyolo!N12+Muloza!N12+MUST!N12+Phalombe!N12+Mikolongwe!N12+Migowi!N12+Nkando!N12 -> 1009 | O12: =Mulanje!O12+Luchenza!O12+Thyolo!O12+Muloza!O12+MUST!O12+Phalombe!O12+Mikolongwe!O12+Migowi!O12+Nkando!O12 -> 916 | P12: =SUM(D12:O12) -> 13412
A13: Volume Billed Institutions | C13: m3 | D13: =Mulanje!D13+Luchenza!D13+Thyolo!D13+Muloza!D13+MUST!D13+Phalombe!D13+Mikolongwe!D13+Migowi!D13 -> 21988 | E13: =Mulanje!E13+Luchenza!E13+Thyolo!E13+Muloza!E13+MUST!E13+Phalombe!E13+Mikolongwe!E13+Migowi!E13 -> 14023 | F13: =Mulanje!F13+Luchenza!F13+Thyolo!F13+Muloza!F13+MUST!F13+Phalombe!F13+Mikolongwe!F13+Migowi!F13 -> 13849 | G13: =Mulanje!G13+Luchenza!G13+Thyolo!G13+Muloza!G13+MUST!G13+Phalombe!G13+Mikolongwe!G13+Migowi!G13 -> 15051 | H13: =Mulanje!H13+Luchenza!H13+Thyolo!H13+Muloza!H13+MUST!H13+Phalombe!H13+Mikolongwe!H13+Migowi!H13 -> 12498 | I13: =Mulanje!I13+Luchenza!I13+Thyolo!I13+Muloza!I13+MUST!I13+Phalombe!I13+Mikolongwe!I13+Migowi!I13 -> 4234 | J13: =Mulanje!J13+Luchenza!J13+Thyolo!J13+Muloza!J13+MUST!J13+Phalombe!J13+Mikolongwe!J13+Migowi!J13 -> 5496 | K13: =Mulanje!K13+Luchenza!K13+Thyolo!K13+Muloza!K13+MUST!K13+Phalombe!K13+Mikolongwe!K13+Migowi!K13 -> 3521 | L13: =Mulanje!L13+Luchenza!L13+Thyolo!L13+Muloza!L13+MUST!L13+Phalombe!L13+Mikolongwe!L13+Migowi!L13 -> 4078 | M13: =Mulanje!M13+Luchenza!M13+Thyolo!M13+Muloza!M13+MUST!M13+Phalombe!M13+Mikolongwe!M13+Migowi!M13+Nkando!M13 -> 2180 | N13: =Mulanje!N13+Luchenza!N13+Thyolo!N13+Muloza!N13+MUST!N13+Phalombe!N13+Mikolongwe!N13+Migowi!N13+Nkando!N13 -> 4411 | O13: =Mulanje!O13+Luchenza!O13+Thyolo!O13+Muloza!O13+MUST!O13+Phalombe!O13+Mikolongwe!O13+Migowi!O13+Nkando!O13 -> 6924 | P13: =SUM(D13:O13) -> 108253
A14: Volume Billed Commercial/Industrial | C14: m3 | D14: =Mulanje!D14+Luchenza!D14+Thyolo!D14+Muloza!D14+MUST!D14+Phalombe!D14+Mikolongwe!D14+Migowi!D14 -> 608 | E14: =Mulanje!E14+Luchenza!E14+Thyolo!E14+Muloza!E14+MUST!E14+Phalombe!E14+Mikolongwe!E14+Migowi!E14 -> 689 | F14: =Mulanje!F14+Luchenza!F14+Thyolo!F14+Muloza!F14+MUST!F14+Phalombe!F14+Mikolongwe!F14+Migowi!F14 -> 800 | G14: =Mulanje!G14+Luchenza!G14+Thyolo!G14+Muloza!G14+MUST!G14+Phalombe!G14+Mikolongwe!G14+Migowi!G14 -> 655 | H14: =Mulanje!H14+Luchenza!H14+Thyolo!H14+Muloza!H14+MUST!H14+Phalombe!H14+Mikolongwe!H14+Migowi!H14 -> 777 | I14: =Mulanje!I14+Luchenza!I14+Thyolo!I14+Muloza!I14+MUST!I14+Phalombe!I14+Mikolongwe!I14+Migowi!I14 -> 722 | J14: =Mulanje!J14+Luchenza!J14+Thyolo!J14+Muloza!J14+MUST!J14+Phalombe!J14+Mikolongwe!J14+Migowi!J14 -> 3448 | K14: =Mulanje!K14+Luchenza!K14+Thyolo!K14+Muloza!K14+MUST!K14+Phalombe!K14+Mikolongwe!K14+Migowi!K14 -> 2165 | L14: =Mulanje!L14+Luchenza!L14+Thyolo!L14+Muloza!L14+MUST!L14+Phalombe!L14+Mikolongwe!L14+Migowi!L14 -> 618 | M14: =Mulanje!M14+Luchenza!M14+Thyolo!M14+Muloza!M14+MUST!M14+Phalombe!M14+Mikolongwe!M14+Migowi!M14+Nkando!M14 -> 858 | N14: =Mulanje!N14+Luchenza!N14+Thyolo!N14+Muloza!N14+MUST!N14+Phalombe!N14+Mikolongwe!N14+Migowi!N14+Nkando!N14 -> 726 | O14: =Mulanje!O14+Luchenza!O14+Thyolo!O14+Muloza!O14+MUST!O14+Phalombe!O14+Mikolongwe!O14+Migowi!O14+Nkando!O14 -> 877 | P14: =SUM(D14:O14) -> 12943
A15: Total Volume Billed Post Paid | C15: m3 | D15: =SUM(D11:D14) -> 65621 | E15: =SUM(E11:E14) -> 70313 | F15: =SUM(F11:F14) -> 62824 | G15: =SUM(G11:G14) -> 60493 | H15: =SUM(H11:H14) -> 59215 | I15: =SUM(I11:I14) -> 54840 | J15: =SUM(J11:J14) -> 54126 | K15: =SUM(K11:K14) -> 55507 | ... P15: =SUM(P11:P14) -> 718980.7
A16: REVENUE WATER - PREPAID
A17: Individuals | C17: m3 | D17: =Mulanje!D17+Luchenza!D17+Thyolo!D17+Muloza!D17+MUST!D17+Phalombe!D17+Mikolongwe!D17+Migowi!D17 -> 6765.1 | E17: =Mulanje!E17+Luchenza!E17+Thyolo!E17+Muloza!E17+MUST!E17+Phalombe!E17+Mikolongwe!E17+Migowi!E17 -> 7412 | F17: =Mulanje!F17+Luchenza!F17+Thyolo!F17+Muloza!F17+MUST!F17+Phalombe!F17+Mikolongwe!F17+Migowi!F17 -> 10526.9 | G17: =Mulanje!G17+Luchenza!G17+Thyolo!G17+Muloza!G17+MUST!G17+Phalombe!G17+Mikolongwe!G17+Migowi!G17 -> 6631.6 | H17: =Mulanje!H17+Luchenza!H17+Thyolo!H17+Muloza!H17+MUST!H17+Phalombe!H17+Mikolongwe!H17+Migowi!H17 -> 16946.5 | I17: =Mulanje!I17+Luchenza!I17+Thyolo!I17+Muloza!I17+MUST!I17+Phalombe!I17+Mikolongwe!I17+Migowi!I17 -> 6451 | J17: =Mulanje!J17+Luchenza!J17+Thyolo!J17+Muloza!J17+MUST!J17+Phalombe!J17+Mikolongwe!J17+Migowi!J17 -> 9963.9 | K17: =Mulanje!K17+Luchenza!K17+Thyolo!K17+Muloza!K17+MUST!K17+Phalombe!K17+Mikolongwe!K17+Migowi!K17 -> 8575.2 | L17: =Mulanje!L17+Luchenza!L17+Thyolo!L17+Muloza!L17+MUST!L17+Phalombe!L17+Mikolongwe!L17+Migowi!L17 -> 8389 | M17: =Mulanje!M17+Luchenza!M17+Thyolo!M17+Muloza!M17+MUST!M17+Phalombe!M17+Mikolongwe!M17+Migowi!M17+Nkando!M17 -> 9434.1 | N17: =Mulanje!N17+Luchenza!N17+Thyolo!N17+Muloza!N17+MUST!N17+Phalombe!N17+Mikolongwe!N17+Migowi!N17+Nkando!N17 -> 7363 | O17: =Mulanje!O17+Luchenza!O17+Thyolo!O17+Muloza!O17+MUST!O17+Phalombe!O17+Mikolongwe!O17+Migowi!O17+Nkando!O17 -> 8668.9 | P17: =SUM(D17:O17) -> 107127.2
A18: CWPs | C18: m3 | D18: =Mulanje!D18+Luchenza!D18+Thyolo!D18+Muloza!D18+MUST!D18+Phalombe!D18+Mikolongwe!D18+Migowi!D18 -> 65 | E18: =Mulanje!E18+Luchenza!E18+Thyolo!E18+Muloza!E18+MUST!E18+Phalombe!E18+Mikolongwe!E18+Migowi!E18 -> 72 | F18: =Mulanje!F18+Luchenza!F18+Thyolo!F18+Muloza!F18+MUST!F18+Phalombe!F18+Mikolongwe!F18+Migowi!F18 -> 110 | G18: =Mulanje!G18+Luchenza!G18+Thyolo!G18+Muloza!G18+MUST!G18+Phalombe!G18+Mikolongwe!G18+Migowi!G18 -> 73 | H18: =Mulanje!H18+Luchenza!H18+Thyolo!H18+Muloza!H18+MUST!H18+Phalombe!H18+Mikolongwe!H18+Migowi!H18 -> 162 | I18: =Mulanje!I18+Luchenza!I18+Thyolo!I18+Muloza!I18+MUST!I18+Phalombe!I18+Mikolongwe!I18+Migowi!I18 -> 98 | J18: =Mulanje!J18+Luchenza!J18+Thyolo!J18+Muloza!J18+MUST!J18+Phalombe!J18+Mikolongwe!J18+Migowi!J18 -> 127 | K18: =Mulanje!K18+Luchenza!K18+Thyolo!K18+Muloza!K18+MUST!K18+Phalombe!K18+Mikolongwe!K18+Migowi!K18 -> 133 | L18: =Mulanje!L18+Luchenza!L18+Thyolo!L18+Muloza!L18+MUST!L18+Phalombe!L18+Mikolongwe!L18+Migowi!L18 -> 141 | M18: =Mulanje!M18+Luchenza!M18+Thyolo!M18+Muloza!M18+MUST!M18+Phalombe!M18+Mikolongwe!M18+Migowi!M18+Nkando!M18 -> 461 | N18: =Mulanje!N18+Luchenza!N18+Thyolo!N18+Muloza!N18+MUST!N18+Phalombe!N18+Mikolongwe!N18+Migowi!N18+Nkando!N18 -> 427 | O18: =Mulanje!O18+Luchenza!O18+Thyolo!O18+Muloza!O18+MUST!O18+Phalombe!O18+Mikolongwe!O18+Migowi!O18+Nkando!O18 -> 231 | P18: =SUM(D18:O18) -> 2100
A19: Institutions | C19: m3 | D19: =Mulanje!D19+Luchenza!D19+Thyolo!D19+Muloza!D19+MUST!D19+Phalombe!D19+Mikolongwe!D19+Migowi!D19 -> 8822 | E19: =Mulanje!E19+Luchenza!E19+Thyolo!E19+Muloza!E19+MUST!E19+Phalombe!E19+Mikolongwe!E19+Migowi!E19 -> 7789 | F19: =Mulanje!F19+Luchenza!F19+Thyolo!F19+Muloza!F19+MUST!F19+Phalombe!F19+Mikolongwe!F19+Migowi!F19 -> 16249.6 | G19: =Mulanje!G19+Luchenza!G19+Thyolo!G19+Muloza!G19+MUST!G19+Phalombe!G19+Mikolongwe!G19+Migowi!G19 -> 7775 | H19: =Mulanje!H19+Luchenza!H19+Thyolo!H19+Muloza!H19+MUST!H19+Phalombe!H19+Mikolongwe!H19+Migowi!H19 -> 22418 | I19: =Mulanje!I19+Luchenza!I19+Thyolo!I19+Muloza!I19+MUST!I19+Phalombe!I19+Mikolongwe!I19+Migowi!I19 -> 21390 | J19: =Mulanje!J19+Luchenza!J19+Thyolo!J19+Muloza!J19+MUST!J19+Phalombe!J19+Mikolongwe!J19+Migowi!J19 -> 18339.2 | K19: =Mulanje!K19+Luchenza!K19+Thyolo!K19+Muloza!K19+MUST!K19+Phalombe!K19+Mikolongwe!K19+Migowi!K19 -> 18485 | L19: =Mulanje!L19+Luchenza!L19+Thyolo!L19+Muloza!L19+MUST!L19+Phalombe!L19+Mikolongwe!L19+Migowi!L19 -> 21393 | M19: =Mulanje!M19+Luchenza!M19+Thyolo!M19+Muloza!M19+MUST!M19+Phalombe!M19+Mikolongwe!M19+Migowi!M19+Nkando!M19 -> 12132.1 | N19: =Mulanje!N19+Luchenza!N19+Thyolo!N19+Muloza!N19+MUST!N19+Phalombe!N19+Mikolongwe!N19+Migowi!N19+Nkando!N19 -> 31025 | O19: =Mulanje!O19+Luchenza!O19+Thyolo!O19+Muloza!O19+MUST!O19+Phalombe!O19+Mikolongwe!O19+Migowi!O19+Nkando!O19 -> 14945.4 | P19: =SUM(D19:O19) -> 200763.3
A20: Commercial/Industrial | C20: m3 | D20: =Mulanje!D20+Luchenza!D20+Thyolo!D20+Muloza!D20+MUST!D20+Phalombe!D20+Mikolongwe!D20+Migowi!D20 -> 1561 | E20: =Mulanje!E20+Luchenza!E20+Thyolo!E20+Muloza!E20+MUST!E20+Phalombe!E20+Mikolongwe!E20+Migowi!E20 -> 2279 | F20: =Mulanje!F20+Luchenza!F20+Thyolo!F20+Muloza!F20+MUST!F20+Phalombe!F20+Mikolongwe!F20+Migowi!F20 -> 1672 | G20: =Mulanje!G20+Luchenza!G20+Thyolo!G20+Muloza!G20+MUST!G20+Phalombe!G20+Mikolongwe!G20+Migowi!G20 -> 1722 | H20: =Mulanje!H20+Luchenza!H20+Thyolo!H20+Muloza!H20+MUST!H20+Phalombe!H20+Mikolongwe!H20+Migowi!H20 -> 4672.6 | I20: =Mulanje!I20+Luchenza!I20+Thyolo!I20+Muloza!I20+MUST!I20+Phalombe!I20+Mikolongwe!I20+Migowi!I20 -> 1646 | J20: =Mulanje!J20+Luchenza!J20+Thyolo!J20+Muloza!J20+MUST!J20+Phalombe!J20+Mikolongwe!J20+Migowi!J20 -> 1791.8 | K20: =Mulanje!K20+Luchenza!K20+Thyolo!K20+Muloza!K20+MUST!K20+Phalombe!K20+Mikolongwe!K20+Migowi!K20 -> 1945.3 | L20: =Mulanje!L20+Luchenza!L20+Thyolo!L20+Muloza!L20+MUST!L20+Phalombe!L20+Mikolongwe!L20+Migowi!L20 -> 2552 | M20: =Mulanje!M20+Luchenza!M20+Thyolo!M20+Muloza!M20+MUST!M20+Phalombe!M20+Mikolongwe!M20+Migowi!M20+Nkando!M20 -> 2533.5 | N20: =Mulanje!N20+Luchenza!N20+Thyolo!N20+Muloza!N20+MUST!N20+Phalombe!N20+Mikolongwe!N20+Migowi!N20+Nkando!N20 -> 3353.6 | O20: =Mulanje!O20+Luchenza!O20+Thyolo!O20+Muloza!O20+MUST!O20+Phalombe!O20+Mikolongwe!O20+Migowi!O20+Nkando!O20 -> 1918 | P20: =SUM(D20:O20) -> 27646.8
A21: Total Volume Prepaid | C21: m3 | D21: =SUM(D17:D20) -> 17213.1 | E21: =SUM(E17:E20) -> 17552 | F21: =SUM(F17:F20) -> 28558.5 | G21: =SUM(G17:G20) -> 16201.6 | H21: =SUM(H17:H20) -> 44199.1 | I21: =SUM(I17:I20) -> 29585 | J21: =SUM(J17:J20) -> 30221.9 | K21: =SUM(K17:K20) -> 29138.5 | ... P21: =SUM(P17:P20) -> 337637.3
A22: TOTAL REVENUE WATER | C22: m3 | D22: =D21+D15 -> 82834.1 | E22: =E21+E15 -> 87865 | F22: =F21+F15 -> 91382.5 | G22: =G21+G15 -> 76694.6 | H22: =H21+H15 -> 103414.1 | I22: =I21+I15 -> 84425 | J22: =J21+J15 -> 84347.9 | K22: =K21+K15 -> 84645.5 | ... P22: =P21+P15 -> 1056618
A24: Non-Revenue Water (NRW) | B24: Volume | C24: m3 | D24: =D9-D22 -> 37713.9 | E24: =E9-E22 -> 37577 | F24: =F9-F22 -> 30213.5 | G24: =G9-G22 -> 38085.4 | H24: =H9-H22 -> 38837.9 | I24: =I9-I22 -> 33333 | J24: =J9-J22 -> 37407.1 | K24: =K9-K22 -> 36053.5 | ... P24: =P9-P22 -> 423848
B25: Percentage | C25: % | D25: =D24/D9 -> 0.3128538 | E25: =E24/E9 -> 0.29955677 | F25: =F24/F9 -> 0.24847446 | G25: =G24/G9 -> 0.33181216 | H25: =H24/H9 -> 0.27302182 | I25: =I24/I9 -> 0.28306357 | J25: =J24/J9 -> 0.30723256 | K25: =K24/K9 -> 0.29870587 | ... P25: =P24/P9 -> 0.28629364
A26: OPERATING EXPENSES
A27: Chemicals
A28: Chemical | B28: Rate(MK/kg)
A29: Chlorine | B29: 5111.67 | C29: kg | D29: =Mulanje!D29+Luchenza!D29+Thyolo!D29+Muloza!D29+MUST!D29+Phalombe!D29+Mikolongwe!D29+Migowi!D29 -> 280 | E29: =Mulanje!E29+Luchenza!E29+Thyolo!E29+Muloza!E29+MUST!E29+Phalombe!E29+Mikolongwe!E29+Migowi!E29 -> 297 | F29: =Mulanje!F29+Luchenza!F29+Thyolo!F29+Muloza!F29+MUST!F29+Phalombe!F29+Mikolongwe!F29+Migowi!F29 -> 283 | G29: =Mulanje!G29+Luchenza!G29+Thyolo!G29+Muloza!G29+MUST!G29+Phalombe!G29+Mikolongwe!G29+Migowi!G29 -> 314 | H29: =Mulanje!H29+Luchenza!H29+Thyolo!H29+Muloza!H29+MUST!H29+Phalombe!H29+Mikolongwe!H29+Migowi!H29 -> 274 | I29: =Mulanje!I29+Luchenza!I29+Thyolo!I29+Muloza!I29+MUST!I29+Phalombe!I29+Mikolongwe!I29+Migowi!I29 -> 279 | J29: =Mulanje!J29+Luchenza!J29+Thyolo!J29+Muloza!J29+MUST!J29+Phalombe!J29+Mikolongwe!J29+Migowi!J29 -> 261 | K29: =Mulanje!K29+Luchenza!K29+Thyolo!K29+Muloza!K29+MUST!K29+Phalombe!K29+Mikolongwe!K29+Migowi!K29 -> 263 | L29: =Mulanje!L29+Luchenza!L29+Thyolo!L29+Muloza!L29+MUST!L29+Phalombe!L29+Mikolongwe!L29+Migowi!L29 -> 258 | M29: =Mulanje!M29+Luchenza!M29+Thyolo!M29+Muloza!M29+MUST!M29+Phalombe!M29+Mikolongwe!M29+Migowi!M29+Nkando!M29 -> 249 | N29: =Mulanje!N29+Luchenza!N29+Thyolo!N29+Muloza!N29+MUST!N29+Phalombe!N29+Mikolongwe!N29+Migowi!N29+Nkando!N29 -> 263 | O29: =Mulanje!O29+Luchenza!O29+Thyolo!O29+Muloza!O29+MUST!O29+Phalombe!O29+Mikolongwe!O29+Migowi!O29+Nkando!O29 -> 256 | P29: =SUM(D29:O29) -> 3277
C30: kg/mg litre | D30: =D29/(D9/1000) -> 2.3227262 | E30: =E29/(E9/1000) -> 2.3676281 | F30: =F29/(F9/1000) -> 2.3273792 | G30: =G29/(G9/1000) -> 2.7356682 | H30: =H29/(H9/1000) -> 1.9261592 | I30: =I29/(I9/1000) -> 2.3692658 | J30: =J29/(J9/1000) -> 2.1436491 | K30: =K29/(K9/1000) -> 2.1789741 | ... P30: =P29/(P9/1000) -> 2.2134922
A31: Aluminium sulphate | B31: 1537 | C31: kg | D31: =Mulanje!D31+Luchenza!D31+Thyolo!D31+Muloza!D31+MUST!D31+Phalombe!D31+Mikolongwe!D31+Migowi!D31 -> 0 | E31: =Mulanje!E31+Luchenza!E31+Thyolo!E31+Muloza!E31+MUST!E31+Phalombe!E31+Mikolongwe!E31+Migowi!E31 -> 0 | F31: =Mulanje!F31+Luchenza!F31+Thyolo!F31+Muloza!F31+MUST!F31+Phalombe!F31+Mikolongwe!F31+Migowi!F31 -> 0 | G31: =Mulanje!G31+Luchenza!G31+Thyolo!G31+Muloza!G31+MUST!G31+Phalombe!G31+Mikolongwe!G31+Migowi!G31 -> 0 | H31: =Mulanje!H31+Luchenza!H31+Thyolo!H31+Muloza!H31+MUST!H31+Phalombe!H31+Mikolongwe!H31+Migowi!H31 -> 0 | I31: =Mulanje!I31+Luchenza!I31+Thyolo!I31+Muloza!I31+MUST!I31+Phalombe!I31+Mikolongwe!I31+Migowi!I31 -> 0 | J31: =Mulanje!J31+Luchenza!J31+Thyolo!J31+Muloza!J31+MUST!J31+Phalombe!J31+Mikolongwe!J31+Migowi!J31 -> 0 | K31: =Mulanje!K31+Luchenza!K31+Thyolo!K31+Muloza!K31+MUST!K31+Phalombe!K31+Mikolongwe!K31+Migowi!K31 -> 0 | L31: =Mulanje!L31+Luchenza!L31+Thyolo!L31+Muloza!L31+MUST!L31+Phalombe!L31+Mikolongwe!L31+Migowi!L31 -> 0 | M31: =Mulanje!M31+Luchenza!M31+Thyolo!M31+Muloza!M31+MUST!M31+Phalombe!M31+Mikolongwe!M31+Migowi!M31+Nkando!M31 -> 0 | N31: =Mulanje!N31+Luchenza!N31+Thyolo!N31+Muloza!N31+MUST!N31+Phalombe!N31+Mikolongwe!N31+Migowi!N31+Nkando!N31 -> 0 | O31: =Mulanje!O31+Luchenza!O31+Thyolo!O31+Muloza!O31+MUST!O31+Phalombe!O31+Mikolongwe!O31+Migowi!O31+Nkando!O31 -> 0 | P31: =SUM(D31:O31) -> 0
C32: kg/mg litre | D32: =D31/(D9/1000) -> 0 | E32: =E31/(E9/1000) -> 0 | F32: =F31/(F9/1000) -> 0 | G32: =G31/(G9/1000) -> 0 | H32: =H31/(H9/1000) -> 0 | I32: =I31/(I9/1000) -> 0 | J32: =J31/(J9/1000) -> 0 | K32: =K31/(K9/1000) -> 0 | ... P32: =P31/(P9/1000) -> 0
