Workbook

Sheet Bangula
A1: SOUTHERN REGION WATER BOARD
A3: MONTHLY REPORTS - 2023/2024
A4: NGABU ZONE
A5: NGABU ZONE
A7: PARAMETERS | C7: UNITS | D7: APRIL | E7: MAY | F7: JUNE | G7: JULY | H7: AUGUST | I7: SEPTEMBER | J7: OCTOBER | K7: NOVEMBER | L7: DECEMBER | M7: JANUARY | N7: FEBRUARY | O7: MARCH | P7: TOTALS
A8: PRODUCTION
A9: Volume Produced | C9: m3 | D9: 11837 | E9: 11868 | F9: 11498 | G9: 11420 | H9: 11560 | I9: 11251 | J9: 11739 | K9: 11906 | L9: 10701 | M9: 8807 | N9: 8766 | O9: 7883 | P9: =SUM(D9:O9) -> 129236
A10: REVENUE WATER - POSTPAID
A11: Volume Billed Individuals | C11: m3 | D11: 5274 | E11: =27+661+4051 -> 4739 | F11: =33+705+3999 -> 4737 | G11: =41+697+3719 -> 4457 | H11: =28+839+3952 -> 4819 | I11: =31+821+4291 -> 5143 | J11: =37+825+4739 -> 5601 | K11: =42+830+4718 -> 5590 | L11: 5132 | M11: 4517 | N11: 4557 | O11: 3742 | P11: =SUM(D11:O11) -> 58308
A12: Volume Billed CWPs | C12: m3 | D12: 2253 | E12: 1750 | F12: 1597 | G12: 1696 | H12: 1782 | I12: 1175 | J12: 1291 | K12: 1319 | L12: 1208 | M12: 1029 | N12: 1005 | O12: 930 | P12: =SUM(D12:O12) -> 17035
A13: Volume Billed Institutions | C13: m3 | D13: 67 | E13: 55 | F13: 58 | G13: 67 | H13: 53 | I13: 55 | J13: 33 | K13: 61 | L13: 177 | M13: 56 | N13: 39 | O13: 33 | P13: =SUM(D13:O13) -> 754
A14: Volume Billed Commercial/Industrial | C14: m3 | D14: 5 | E14: 7 | F14: 13 | G14: 1 | I14: 26 | P14: =SUM(D14:O14) -> 52
A15: Total Volume Billed Post Paid | C15: m3 | D15: =SUM(D11:D14) -> 7599 | E15: =SUM(E11:E14) -> 6551 | F15: =SUM(F11:F14) -> 6405 | G15: =SUM(G11:G14) -> 6221 | H15: =SUM(H11:H14) -> 6654 | I15: =SUM(I11:I14) -> 6399 | J15: =SUM(J11:J14) -> 6925 | K15: =SUM(K11:K14) -> 6970 | ... N15: =SUM(N11:N14) -> 5601 | O15: 4705 | P15: =SUM(P11:P14) -> 76149
A16: REVENUE WATER - PREPAID
A17: Individuals | C17: m3 | D17: 0 | F17: 1796 | G17: 1646 | I17: 1604 | J17: 1034 | K17: 1436 | L17: 1556 | M17: 1711 | N17: 1465 | O17: 1044 | P17: =SUM(D17:O17) -> 13292
A18: CWPs | C18: m3 | D18: 0 | I18: 57 | K18: 1 | L18: 1 | P18: =SUM(D18:O18) -> 59
A19: Institutions | C19: m3 | D19: 2139 | E19: 3686.9 | F19: 583 | G19: 981 | H19: 3018.5 | I19: 309 | J19: 583 | K19: 614 | L19: 463 | M19: 165 | N19: 389 | O19: 180 | P19: =SUM(D19:O19) -> 13111.4
A20: Commercial/Industrial | C20: m3 | D20: 0 | F20: 264 | G20: 392 | I20: 286 | J20: 416 | K20: 387 | L20: 327 | M20: 187 | N20: 192 | O20: 217 | P20: =SUM(D20:O20) -> 2668
A21: Total Volume Prepaid | C21: m3 | D21: =SUM(D17:D20) -> 2139 | E21: =SUM(E17:E20) -> 3686.9 | F21: =SUM(F17:F20) -> 2643 | G21: =SUM(G17:G20) -> 3019 | H21: =SUM(H17:H20) -> 3018.5 | I21: =SUM(I17:I20) -> 2256 | J21: =SUM(J17:J20) -> 2033 | K21: =SUM(K17:K20) -> 2438 | ... N21: =SUM(N17:N20) -> 2046 | O21: 1441 | P21: =SUM(P17:P20) -> 29130.4
A22: TOTAL REVENUE WATER | C22: m3 | D22: =D21+D15 -> 9738 | E22: =E21+E15 -> 10237.9 | F22: =F21+F15 -> 9048 | G22: =G21+G15 -> 9240 | H22: =H21+H15 -> 9672.5 | I22: =I21+I15 -> 8655 | J22: =J21+J15 -> 8958 | K22: =K21+K15 -> 9408 | ... N22: =N21+N15 -> 7647 | O22: 6146 | P22: =P21+P15 -> 105279.4
A24: Non-Revenue Water (NRW) | B24: Volume | C24: m3 | D24: =D9-D22 -> 2099 | E24: =E9-E22 -> 1630.1 | F24: =F9-F22 -> 2450 | G24: =G9-G22 -> 2180 | H24: =H9-H22 -> 1887.5 | I24: =I9-I22 -> 2596 | J24: =J9-J22 -> 2781 | K24: =K9-K22 -> 2498 | ... N24: =N9-N22 -> 1119 | O24: 1737 | P24: =P9-P22 -> 23956.6
B25: Percentage | C25: % | D25: =D24/D9 -> 0.17732534 | E25: =E24/E9 -> 0.13735254 | F25: =F24/F9 -> 0.21308054 | G25: =G24/G9 -> 0.19089317 | H25: =H24/H9 -> 0.16327855 | I25: =I24/I9 -> 0.23073505 | J25: =J24/J9 -> 0.23690263 | K25: =K24/K9 -> 0.20981018 | ... N25: =N24/N9 -> 0.12765229 | O25: 0.22034758 | P25: =P24/P9 -> 0.18537095
A26: OPERATING EXPENSES
A27: Chemicals
A28: Chemical | B28: Rate(MK/kg)
A29: Chlorine | B29: 3525.29 | C29: kg | D29: 14 | E29: 12 | F29: 14 | G29: 14 | H29: 16 | I29: 18 | J29: 18 | K29: 16 | L29: 16 | M29: 16 | N29: 12 | O29: 12 | P29: =SUM(D29:O29) -> 178
C30: kg/mg litre | D30: =D29/(D9/1000) -> 1.1827321 | E30: =E29/(E9/1000) -> 1.0111223 | F30: =F29/(F9/1000) -> 1.2176031 | G30: =G29/(G9/1000) -> 1.2259194 | H30: =H29/(H9/1000) -> 1.384083 | I30: =I29/(I9/1000) -> 1.5998578 | J30: =J29/(J9/1000) -> 1.5333504 | K30: =K29/(K9/1000) -> 1.3438602 | L30: 1.4951874 | M30: 1.8167367 | N30: =N29/(N9/1000) -> 1.3689254 | O30: 1.5222631 | P30: =P29/(P9/1000) -> 1.3773252
A31: Aluminium sulphate | C31: kg | P31: =SUM(D31:O31) -> 0
B32: 1060.01 | C32: kg/mg litre | D32: =D31/(D9/1000) -> 0 | E32: =E31/(E9/1000) -> 0 | F32: =F31/(F9/1000) -> 0 | G32: =G31/(G9/1000) -> 0 | H32: =H31/(H9/1000) -> 0 | I32: =I31/(I9/1000) -> 0 | J32: =J31/(J9/1000) -> 0 | K32: =K31/(K9/1000) -> 0 | ... N32: =N31/(N9/1000) -> 0 | O32: 0 | P32: =P31/(P9/1000) -> 0
A33: Soda | C33: kg | P33: =SUM(D33:O33) -> 0
B34: 1228.29 | C34: kg/mg litre | D34: =D33/(D9/1000) -> 0 | E34: =E33/(E9/1000) -> 0 | F34: =F33/(F9/1000) -> 0 | G34: =G33/(G9/1000) -> 0 | H34: =H33/(H9/1000) -> 0 | I34: =I33/(I9/1000) -> 0 | J34: =J33/(J9/1000) -> 0 | K34: =K33/(K9/1000) -> 0 | ... N34: =N33/(N9/1000) -> 0 | O34: 0 | P34: =P33/(P9/1000) -> 0
A35: Algae floc | C35: litres
B36: 3726.73 | C36: litres/mg litre | E36: =E35/(E11/1000) -> 0
A37: Sud floc | C37: litres | G37: 0 | H37: 0 | I37: 0 | J37: 0 | K37: 0 | L37: 0 | M37: 0 | N37: 0 | O37: 0 | P37: =SUM(D37:O37) -> 0
B38: 3951.59 | C38: litres/mg litre | D38: =D37/(D13/1000) -> 0 | E38: =E37/(E13/1000) -> 0 | F38: =F37/(F13/1000) -> 0 | G38: =G37/(G9/1000) -> 0 | H38: =H37/(H9/1000) -> 0 | I38: =I37/(I9/1000) -> 0 | J38: =J37/(J9/1000) -> 0 | K38: =K37/(K9/1000) -> 0 | L38: =L37/(L9/1000) -> 0 | M38: =M37/(M9/1000) -> 0 | N38: =N37/(N9/1000) -> 0 | O38: 0 | P38: =P37/(P9/1000) -> 0
A39: Potasium permanganate | C39: kg | G39: 0 | H39: 0 | I39: 0 | J39: 0 | K39: 0 | L39: 0 | M39: 0 | N39: 0 | O39: 0 | P39: =SUM(D39:O39) -> 0
B40: 1950 | C40: kg/mg litre | D40: =D39/(D15/1000) -> 0 | E40: =E39/(E15/1000) -> 0 | F40: =F39/(F15/1000) -> 0 | G40: =G39/(G9/1000) -> 0 | H40: =H39/(H9/1000) -> 0 | I40: =I39/(I9/1000) -> 0 | J40: =J39/(J9/1000) -> 0 | K40: =K39/(K9/1000) -> 0 | L40: =L39/(L9/1000) -> 0 | M40: =M39/(M9/1000) -> 0 | N40: =N39/(N9/1000) -> 0 | O40: 0 | P40: =P39/(P9/1000) -> 0
A41: Cost of Chemicals | C41: Mk | D41: =(D29*$B29)+(D31*$B31)+(D33*$B33)+(D35*$B35)+(D37*$B37)+(D39*$B39) -> 49354.06 | E41: =(E29*$B29)+(E31*$B31)+(E33*$B33)+(E35*$B35)+(E37*$B37)+(E39*$B39) -> 42303.48 | F41: =(F29*$B29)+(F31*$B31)+(F33*$B33)+(F35*$B35)+(F37*$B37)+(F39*$B39) -> 49354.06 | G41: =(G29*$B29)+(G31*$B31)+(G33*$B33)+(G35*$B35)+(G37*$B37)+(G39*$B39) -> 49354.06 | H41: =(H29*$B29)+(H31*$B31)+(H33*$B33)+(H35*$B35)+(H37*$B37)+(H39*$B39) -> 56404.64 | I41: =(I29*$B29)+(I31*$B31)+(I33*$B33)+(I35*$B35)+(I37*$B37)+(I39*$B39) -> 63455.22 | J41: =(J29*$B29)+(J31*$B31)+(J33*$B33)+(J35*$B35)+(J37*$B37)+(J39*$B39) -> 63455.22 | K41: =(K29*$B29)+(K31*$B31)+(K33*$B33)+(K35*$B35)+(K37*$B37)+(K39*$B39) -> 56404.64 | ... N41: =(N29*$B29)+(N31*$B31)+(N33*$B33)+(N35*$B35)+(N37*$B37)+(N39*$B39) -> 42303.48 | O41: 42303.48 | P41: =SUM(D41:O41) -> 627501.62
A42: Cost/vol. Produced (chemicals) | C42: Mk/m3 | D42: =D41/D9 -> 4.1694737 | E42: =E41/E9 -> 3.5644995 | F42: =F41/F9 -> 4.2924039 | G42: =G41/G9 -> 4.3217215 | H42: =H41/H9 -> 4.8792941 | I42: =I41/I9 -> 5.6399627 | J42: =J41/J9 -> 5.4055047 | K42: =K41/K9 -> 4.7374971 | ... N42: =N41/N9 -> 4.825859 | O42: 5.3664189 | P42: =P41/P9 -> 4.8554708
A43: Power
A44: Power Usage | C44: Kw | D44: 442.03 | E44: 4272.59 | F44: 4219.15 | G44: 5540.94 | H44: 4426.74 | I44: 41180.03 | J44: 4661.69 | K44: 4630.14 | L44: 4319 | M44: 2916.3 | N44: 2832.34 | O44: 2774.95 | P44: =SUM(D44:O44) -> 82215.9
A45: Power/ Vol. Produced | C45: Kw/m3 | D45: 0.037343077 | E45: =E44/E9 -> 0.36000927 | F45: =F44/F9 -> 0.36694643 | G45: =G44/G9 -> 0.48519615 | H45: =H44/H9 -> 0.38293599 | I45: =I44/I9 -> 3.6601218 | J45: =J44/J9 -> 0.39711134 | K45: =K44/K9 -> 0.38889132 | L45: 0.40360714 | M45: 0.33113432 | N45: =N44/N9 -> 0.32310518 | O45: 0.352017 | P45: =P44/P9 -> 0.63616871
A46: Cost of Power | C46: Mk | D46: 66790.733 | E46: =151.1*E44 -> 645588.35 | F46: =151.1*F44 -> 637513.56 | G46: =151.1*G44 -> 837236.03 | H46: =151.1*H44 -> 668880.41 | I46: =151.1*I44 -> 6222302.5 | J46: =1.165*(14100+(J44*119.1)) -> 663242.98 | K46: =1.165*(14100+(K44*119.1)) -> 658865.37 | L46: =1.165*(14100+(L44*119.1)) -> 615694.23 | M46: =1.165*(14100+(M44*119.1)) -> 421067.5 | N46: =1.165*(14100+(N44*119.1)) -> 409417.92 | O46: 401454.97 | P46: =SUM(D46:O46) -> 12248055
A47: Cost/vol. Produced | C47: Mk/m3 | D47: 5.6425389 | E47: =E46/E9 -> 54.3974 | F47: =F46/F9 -> 55.445605 | G47: =G46/G9 -> 73.313138 | H47: =H46/H9 -> 57.861628 | I47: =I46/I9 -> 553.0444 | J47: =J46/J9 -> 56.499104 | K47: =K46/K9 -> 55.338936 | L47: =L46/L9 -> 57.536139 | ... N47: =N46/N9 -> 46.705216 | O47: 50.926674 | P47: =P46/P9 -> 94.772777
A48: Plant and Vehicle Maintenance
A49: Distances covered | C49: km | D49: 346 | E49: 301 | F49: 373 | G49: 114 | H49: 238 | I49: 298 | J49: 394 | K49: 223 | L49: 278 | O49: 132 | P49: =SUM(D49:O49) -> 2697
A50: Fuel Used (litres) | C50: litres | D50: 12 | E50: 10 | F50: 10 | G50: 8 | H50: 11.5 | I50: 22 | J50: 25.19 | K50: 10 | L50: 27.9 | O50: 14.2 | P50: =SUM(D50:O50) -> 150.79
A51: Cost of fuel | C51: Mk | D51: =D50*1470 -> 17640 | E51: =E50*1470 -> 14700 | F51: =F50*1470 -> 14700 | G51: =G50*1470 -> 11760 | H51: =H50*1470 -> 16905 | I51: =I50*1470 -> 32340 | J51: =J50*1470 -> 37029.3 | K51: =K50*1470 -> 14700 | L51: 41013 | O51: 20874 | P51: =SUM(D51:O51) -> 221661.3
A52: Maintenance | C52: Mk | D52: 50000 | E52: 65000 | H52: 0 | I52: 0 | J52: 0 | K52: 0 | L52: 0 | M52: 0 | N52: 0 | O52: 0 | P52: =SUM(D52:O52) -> 115000
A53: Salaries and Wages
A54: Staff Costs | C54: MK | D54: 836669.75 | E54: 836669.75 | F54: 836669.75 | G54: 836669.75 | H54: 836669.75 | I54: 836669.75 | J54: 836669.75 | K54: 836669.75 | P54: =SUM(D54:O54) -> 6693358
A55: Wages | C55: MK | D55: 165475.13 | E55: 165475.13 | F55: 165475.13 | G55: 165475.13 | H55: 165475.13 | I55: 165475.13 | J55: 165475.13 | K55: 165475.13 | P55: =SUM(D55:O55) -> 1323801
A56: Other Overhead Costs | C56: MK | P56: =SUM(D56:O56) -> 0
A57: Operating Costs
A58: Total Operating Costs | C58: MK | D58: =D41+D46+D51+D52+D54+D55+D56 -> 1185929.7 | E58: =E41+E46+E51+E52+E54+E55+E56 -> 1769736.7 | F58: =F41+F46+F51+F52+F54+F55+F56 -> 1703712.5 | G58: =G41+G46+G51+G52+G54+G55+G56 -> 1900495 | H58: =H41+H46+H51+H52+H54+H55+H56 -> 1744334.9 | I58: =I41+I46+I51+I52+I54+I55+I56 -> 7320242.6 | J58: =J41+J46+J51+J52+J54+J55+J56 -> 1765872.4 | K58: =K41+K46+K51+K52+K54+K55+K56 -> 1732114.9 | ... N58: =N41+N46+N51+N52+N54+N55+N56 -> 451721.4 | O58: 464632.45 | P58: =SUM(D58:O58) -> 21229377
A59: Cost/Vol. Produced | C59: Mk/m3 | D59: =D58/D9 -> 100.18836 | E59: =E58/E9 -> 149.11836 | F59: =F58/F9 -> 148.17468 | G59: =G58/G9 -> 166.41812 | H59: =H58/H9 -> 150.89403 | I59: =I58/I9 -> 650.6304 | J59: =J58/J9 -> 150.42784 | K59: =K58/K9 -> 145.48252 | ... N59: =N58/N9 -> 51.531075 | O59: 58.94107 | P59: =P58/P9 -> 164.26829
A60: Cost/Vol. Billed | C60: Mk/m3 | D60: =D58/D22 -> 121.7837 | E60: =E58/E22 -> 172.8613 | F60: =F58/F22 -> 188.29714 | G60: =G58/G22 -> 205.68127 | H60: =H58/H22 -> 180.33962 | I60: =I58/I22 -> 845.78193 | J60: =J58/J22 -> 197.12797 | K60: =K58/K22 -> 184.11085 | ... N60: =N58/N22 -> 59.071715 | O60: 75.599163 | P60: =P58/P22 -> 201.64796
A61: Permanent Staff Employed | C61: No | D61: 2 | E61: 2 | F61: 2 | G61: 3 | H61: 3 | I61: 2 | J61: 2 | K61: 2 | L61: 2 | M61: 2 | N61: 2 | O61: 2 | P61: =O61 -> 2
A62: Staff/Vol.1000m3 of Volume Produced/hour (12 hour day) | C62: No/1000m3 | D62: =(D61*1000*31)/D9 -> 5.2378136 | E62: =(E61*1000*31)/E9 -> 5.2241321 | F62: =(F61*1000*31)/F9 -> 5.3922421 | G62: =(G61*1000*31)/G9 -> 8.1436077 | H62: =(H61*1000*31)/H9 -> 8.0449827 | I62: =(I61*1000*31)/I9 -> 5.5106213 | J62: =(J61*1000*31)/J9 -> 5.2815402 | K62: =(K61*1000*31)/K9 -> 5.2074584 | ... N62: =(N61*1000*31)/N9 -> 7.0727812 | O62: 7.865026 | P62: =(P61*1000*31)/P9 -> 0.47974249
A63: Temporary Staff Employed | C63: No | D63: 4 | E63: 4 | F63: 4 | G63: 4 | H63: 4 | I63: 4 | J63: 4 | K63: 4 | M63: 4 | N63: 4 | O63: 5 | P63: =SUM(D63:O63) -> 45
A65: Water Connections and Disconnections
A66: New Individual Water Connections | B66: Brought Forward | C66: No | D66: 45 | E66: =D71 -> 46 | F66: =E71 -> 52 | G66: =F71 -> 50 | H66: =G71 -> 43 | I66: =H71 -> 30 | J66: =I71 -> 24 | K66: =J71 -> 21 | L66: 22 | M66: 25 | N66: 22 | O66: 21 | P66: =D66 -> 45
B67: Applied this Month | C67: No | D67: 1 | E67: 6 | F67: 1 | G67: 1 | H67: 5 | I67: 7 | J67: 5 | K67: 7 | L67: 7 | M67: 4 | O67: 2 | P67: =SUM(D67:O67) -> 46
B68: Done this Month Postpaid | C68: No | D68: 0 | F68: 3 | G68: 8 | H68: 18 | I68: 13 | J68: 8 | K68: 6 | L68: 4 | M68: 7 | N68: 1 | O68: 6 | P68: =SUM(D68:O68) -> 74
B69: Done this Month Prepaid | C69: No | D69: 0 | P69: =SUM(D69:O69) -> 0
B70: Total Done | C70: No | D70: =D68+D69 -> 0 | E70: =E68+E69 -> 0 | F70: =F68+F69 -> 3 | G70: =G68+G69 -> 8 | H70: =H68+H69 -> 18 | I70: =I68+I69 -> 13 | J70: =J68+J69 -> 8 | K70: =K68+K69 -> 6 | L70: 4 | M70: 7 | N70: 1 | O70: 6 | P70: =P68+P69 -> 74
B71: Carried Forward | C71: No | D71: =D66+D67-D70 -> 46 | E71: =E66+E67-E70 -> 52 | F71: =F66+F67-F70 -> 50 | G71: =G66+G67-G70 -> 43 | H71: =H66+H67-H70 -> 30 | I71: =I66+I67-I70 -> 24 | J71: =J66+J67-J70 -> 21 | K71: =K66+K67-K70 -> 22 | L71: 25 | M71: =M66+M67-M70 -> 22 | N71: 21 | O71: 17 | P71: =P66+P67-P70 -> 17
A72: New Institutional Water Connections | B72: Brought Forward | C72: No | D72: 0 | E72: =D77 -> 0 | F72: =E77 -> 0 | G72: =F77 -> 0 | H72: =G77 -> 0 | P72: =D72 -> 0
B73: Applied this Month | C73: No | D73: 0 | P73: =SUM(D73:O73) -> 0
B74: Done this Month Postpaid | C74: No | D74: 0 | P74: =SUM(D74:O74) -> 0
B75: Done this Month Prepaid | C75: No | D75: 0 | P75: =SUM(D75:O75) -> 0
B76: Total Done | C76: No | D76: =D74+D75 -> 0 | E76: =E74+E75 -> 0 | F76: =F74+F75 -> 0 | G76: =G74+G75 -> 0 | H76: =H74+H75 -> 0 | I76: =I74+I75 -> 0 | J76: =J74+J75 -> 0 | K76: =K74+K75 -> 0 | ... N76: =N74+N75 -> 0 | O76: 0 | P76: =P74+P75 -> 0
B77: Carried Forward | C77: No | D77: =D72+D73-D76 -> 0 | E77: =E72+E73-E76 -> 0 | F77: =F72+F73-F76 -> 0 | G77: =G72+G73-G76 -> 0 | H77: =H72+H73-H76 -> 0 | I77: =I72+I73-I76 -> 0 | J77: =J72+J73-J76 -> 0 | K77: =K72+K73-K76 -> 0 | ... N77: =N72+N73-N76 -> 0 | O77: 0 | P77: =P72+P73-P76 -> 0
A78: New Commercial/Industrial Water Connections | B78: Brought Forward | C78: No | D78: 0 | E78: =D83 -> 0 | F78: =E83 -> 1 | G78: =F83 -> 1 | H78: =G83 -> 1 | I78: =H83 -> 1 | J78: =I83 -> 1 | K78: =J83 -> 1 | L78: 1 | M78: 1 | N78: 1 | O78: 1 | P78: =D78 -> 0
B79: Applied this Month | C79: No | D79: 0 | E79: 1 | P79: =SUM(D79:O79) -> 1
B80: Done this Month Postpaid | C80: No | D80: 0 | P80: =SUM(D80:O80) -> 0
B81: Done this Month Prepaid | C81: No | D81: 0 | P81: =SUM(D81:O81) -> 0
B82: Total Done | C82: No | D82: =D80+D81 -> 0 | E82: =E80+E81 -> 0 | F82: =F80+F81 -> 0 | G82: =G80+G81 -> 0 | H82: =H80+H81 -> 0 | I82: =I80+I81 -> 0 | J82: =J80+J81 -> 0 | K82: =K80+K81 -> 0 | L82: =L80+L81 -> 0 | M82: =M81+M80 -> 0 | N82: =N81+N80 -> 0 | O82: 0 | P82: =P81+P80 -> 0
B83: Carried Forward | C83: No | D83: =D78+D79-D82 -> 0 | E83: =E78+E79-E82 -> 1 | F83: =F78+F79-F82 -> 1 | G83: =G78+G79-G82 -> 1 | H83: =H78+H79-H82 -> 1 | I83: =I78+I79-I82 -> 1 | J83: =J78+J79-J82 -> 1 | K83: =K78+K79-K82 -> 1 | ... N83: =N78+N79-N82 -> 1 | O83: 1 | P83: =P78+P79-P82 -> 1
A84: New CWP | B84: Brought Forward | C84: No | D84: 0 | E84: =D89 -> 0 | F84: =E89 -> 0 | G84: =F89 -> 0 | P84: =D84 -> 0
B85: Applied this Month | C85: No | D85: 0 | I85: 1 | P85: =SUM(D85:O85) -> 1
B86: Done this Month Postpaid | C86: No | D86: 0 | I86: 1 | P86: =SUM(D86:O86) -> 1
B87: Done this Month Prepaid | C87: No | D87: 0 | P87: =SUM(D87:O87) -> 0
B88: Total Done | C88: No | D88: =D86+D87 -> 0 | E88: =E86+E87 -> 0 | F88: =F86+F87 -> 0 | G88: =G86+G87 -> 0 | H88: =H86+H87 -> 0 | I88: =I86+I87 -> 1 | J88: =J86+J87 -> 0 | K88: =K86+K87 -> 0 | ... M88: =M86+M87 -> 0 | N88: 0 | O88: 0 | P88: =SUM(D88:O88) -> 1
B89: Carried Forward | C89: No | D89: =D84+D85-D88 -> 0 | E89: =E84+E85-E88 -> 0 | F89: =F84+F85-F88 -> 0 | G89: =G84+G85-G88 -> 0 | H89: =H84+H85-H88 -> 0 | I89: =I84+I85-I88 -> 0 | J89: =J84+J85-J88 -> 0 | K89: =K84+K85-K88 -> 0 | ... M89: =M84+M85-M88 -> 0 | N89: =N84+N85-N86-N87 -> 0 | O89: 0 | P89: =P84+P85-P86-P87 -> 0
A90: Aggregated New Water connections | B90: Brought Forward | C90: No | D90: =D66+D72+D78+D84 -> 45 | E90: =E66+E72+E78+E84 -> 46 | F90: =F66+F72+F78+F84 -> 53 | G90: =G66+G72+G78+G84 -> 51 | H90: =H66+H72+H78+H84 -> 44 | I90: =I66+I72+I78+I84 -> 31 | J90: =J66+J72+J78+J84 -> 25 | K90: =K66+K72+K78+K84 -> 22 | ... N90: =N66+N72+N78+N84 -> 23 | O90: 22 | P90: =D90 -> 45
B91: Applied this Month | C91: No | D91: =D67+D73+D79+D85 -> 1 | E91: =E67+E73+E79+E85 -> 7 | F91: =F67+F73+F79+F85 -> 1 | G91: =G67+G73+G79+G85 -> 1 | H91: =H67+H73+H79+H85 -> 5 | I91: =I67+I73+I79+I85 -> 8 | J91: =J67+J73+J79+J85 -> 5 | K91: =K67+K73+K79+K85 -> 7 | ... N91: =N67+N73+N79+N85 -> 0 | O91: 2 | P91: =SUM(D91:O91) -> 48
B92: Done this Month Postpaid | C92: No | D92: =D68+D74+D80+D86 -> 0 | E92: =E68+E74+E80+E86 -> 0 | F92: =F68+F74+F80+F86 -> 3 | G92: =G68+G74+G80+G86 -> 8 | H92: =H68+H74+H80+H86 -> 18 | I92: =I68+I74+I80+I86 -> 14 | J92: =J68+J74+J80+J86 -> 8 | K92: =K68+K74+K80+K86 -> 6 | ... N92: =N68+N74+N80+N86 -> 1 | O92: 6 | P92: =SUM(D92:O92) -> 75
B93: Done this Month Prepaid | D93: =D69+D75+D81+D87 -> 0 | E93: =E69+E75+E81+E87 -> 0 | F93: =F69+F75+F81+F87 -> 0 | G93: =G69+G75+G81+G87 -> 0 | H93: =H69+H75+H81+H87 -> 0 | I93: =I69+I75+I81+I87 -> 0 | J93: =J69+J75+J81+J87 -> 0 | K93: =K69+K75+K81+K87 -> 0 | ... N93: =N69+N75+N81+N87 -> 0 | O93: 0 | P93: =SUM(D93:O93) -> 0
B94: Total Done | C94: No | D94: =D93+D92 -> 0 | E94: =E70+E76+E82+E88 -> 0 | F94: =F70+F76+F82+F88 -> 3 | G94: =G70+G76+G82+G88 -> 8 | H94: =H93+H92 -> 18 | I94: =I93+I92 -> 14 | J94: =J93+J92 -> 8 | K94: =K93+K92 -> 6 | L94: =L93+L92 -> 4 | M94: =M93+M92 -> 7 | N94: =N93+N92 -> 1 | O94: 6 | P94: =P93+P92 -> 75
B95: Carried Forward | C95: No | D95: =D90+D91-D94 -> 46 | E95: =E90+E91-E94 -> 53 | F95: =F90+F91-F94 -> 51 | G95: =G90+G91-G94 -> 44 | H95: =H90+H91-H94 -> 31 | I95: =I90+I91-I94 -> 25 | J95: =J90+J91-J94 -> 22 | K95: =K90+K91-K94 -> 23 | ... N95: =N90+N91-N94 -> 22 | O95: 18 | P95: =P90+P91-P94 -> 18
A97: Prepaid Metering
A98: Prepaid Meters Installed | C98: No | D98: 0 | E98: 0 | F98: 0 | P98: =SUM(D98:O98) -> 0
A100: Active and Disconnected Accounts
A101: Disconnected Individual Accounts | C101: No | D101: =194-36+10 -> 168 | E101: 190 | F101: 192 | G101: 207 | H101: 223 | I101: 219 | J101: 216 | K101: 220 | L101: 225 | M101: 254 | N101: 252 | O101: 246 | P101: =O101 -> 246
A102: Disconnected institutional Accounts | C102: No | D102: 9 | E102: 9 | F102: 9 | G102: 11 | H102: 12 | I102: 13 | J102: 13 | K102: 17 | L102: 17 | M102: 17 | N102: 17 | O102: 17 | P102: =O102 -> 17
A103: Disconnected Commercial/Industrial Accounts | C103: No | D103: 7 | E103: 7 | F103: 8 | G103: 8 | H103: 8 | I103: 8 | J103: 8 | K103: 12 | L103: 12 | M103: 12 | N103: 12 | O103: 12 | P103: =O103 -> 12
A104: Disconnected CWP | C104: No | D104: 3 | E104: 4 | F104: 4 | G104: 4 | H104: 4 | I104: 4 | J104: 4 | K104: 4 | L104: 4 | M104: 5 | N104: 5 | O104: 5 | P104: =O104 -> 5
A105: Total Disconnected Accounts | C105: No | D105: =SUM(D101:D104) -> 187 | E105: =SUM(E101:E104) -> 210 | F105: =SUM(F101:F104) -> 213 | G105: =SUM(G101:G104) -> 230 | H105: =SUM(H101:H104) -> 247 | I105: =SUM(I101:I104) -> 244 | J105: =SUM(J101:J104) -> 241 | K105: =SUM(K101:K104) -> 253 | ... N105: =SUM(N101:N104) -> 286 | O105: 280 | P105: =O105 -> 280
A106: Postpaid Consumers
...

Sheet Chikwawa
A1: SOUTHERN REGION WATER BOARD
A3: MONTHLY REPORTS - 2023/2024
A4: NGABU ZONE
A5: NGABU ZONE
A7: PARAMETERS | C7: UNITS | D7: APRIL | E7: MAY | F7: JUNE | G7: JULY | H7: AUGUST | I7: SEPTEMBER | J7: OCTOBER | K7: NOVEMBER | L7: DECEMBER | M7: JANUARY | N7: FEBRUARY | O7: MARCH | P7: TOTALS
A8: PRODUCTION
A9: Volume Produced | C9: m3 | D9: 28533 | E9: 29250 | F9: 28920 | G9: 28655 | H9: 28342 | I9: 28121 | J9: 27479 | K9: 27655 | L9: 28062 | M9: 27553 | N9: 28105 | O9: 27956 | P9: =SUM(D9:O9) -> 338631
A10: REVENUE WATER - POSTPAID
A11: Volume Billed Individuals | C11: m3 | D11: =2404+712+11700 -> 14816 | E11: =2270+680+12732 -> 15682 | F11: =2946+1017+15859 -> 19822 | G11: =2216+667+12448 -> 15331 | H11: =2254+631+12248 -> 15133 | I11: =2337+674+13201 -> 16212 | J11: =2520+806+14549 -> 17875 | K11: =2416+649+15198 -> 18263 | L11: 16641 | M11: =2214+712+13991 -> 16917 | N11: 17751 | O11: 17601 | P11: =SUM(D11:O11) -> 202044
A12: Volume Billed CWPs | C12: m3 | D12: 886 | E12: 858 | F12: 1034 | G12: 719 | H12: 864 | I12: 763 | J12: 803 | K12: 756 | L12: 692 | M12: 565 | N12: 786 | O12: 882 | P12: =SUM(D12:O12) -> 9608
A13: Volume Billed Institutions | C13: m3 | D13: 248 | E13: 282 | F13: 318 | G13: 281 | H13: 238 | I13: 217 | J13: 592 | K13: 632 | L13: 229 | M13: 206 | N13: 259 | O13: 271 | P13: =SUM(D13:O13) -> 3773
A14: Volume Billed Commercial/Industrial | C14: m3 | D14: 59 | E14: 63 | F14: 125 | G14: 78 | H14: 92 | I14: 88 | J14: 167 | K14: 210 | L14: 108 | M14: 107 | N14: 118 | O14: 84 | P14: =SUM(D14:O14) -> 1299
A15: Total Volume Billed Post Paid | C15: m3 | D15: =SUM(D11:D14) -> 16009 | E15: =SUM(E11:E14) -> 16885 | F15: =SUM(F11:F14) -> 21299 | G15: =SUM(G11:G14) -> 16409 | H15: =SUM(H11:H14) -> 16327 | I15: =SUM(I11:I14) -> 17280 | J15: =SUM(J11:J14) -> 19437 | K15: =SUM(K11:K14) -> 19861 | ... N15: =SUM(N11:N14) -> 18914 | O15: 18838 | P15: =SUM(P11:P14) -> 216724
A16: REVENUE WATER - PREPAID
A17: Individuals | C17: m3 | F17: 2252 | G17: 2215 | I17: 1757 | J17: 1692 | K17: 1493 | L17: 2119 | M17: 1560 | N17: 1142 | O17: 1001 | P17: =SUM(D17:O17) -> 15231
A18: CWPs | C18: m3 | P18: =SUM(D18:O18) -> 0
A19: Institutions | C19: m3 | D19: 6680 | E19: 7519 | F19: 2820 | G19: 2790 | H19: 6251 | I19: 2340 | J19: 2159 | K19: 220 | L19: 2321 | M19: 2401 | N19: 2466 | O19: 2285 | P19: =SUM(D19:O19) -> 40252
A20: Commercial/Industrial | C20: m3 | F20: 943 | G20: 950 | I20: 758 | J20: 697 | K20: 709 | L20: 811 | M20: 703 | N20: 755 | O20: 669 | P20: =SUM(D20:O20) -> 6995
A21: Total Volume Prepaid | C21: m3 | D21: =SUM(D17:D20) -> 6680 | E21: =SUM(E17:E20) -> 7519 | F21: =SUM(F17:F20) -> 6015 | G21: =SUM(G17:G20) -> 5955 | H21: =SUM(H17:H20) -> 6251 | I21: =SUM(I17:I20) -> 4855 | J21: =SUM(J17:J20) -> 4548 | K21: =SUM(K17:K20) -> 2422 | ... N21: =SUM(N17:N20) -> 4363 | O21: 3955 | P21: =SUM(P17:P20) -> 62478
A22: TOTAL REVENUE WATER | C22: m3 | D22: =D21+D15 -> 22689 | E22: =E21+E15 -> 24404 | F22: =F21+F15 -> 27314 | G22: =G21+G15 -> 22364 | H22: =H21+H15 -> 22578 | I22: =I21+I15 -> 22135 | J22: =J21+J15 -> 23985 | K22: =K21+K15 -> 22283 | ... N22: =N21+N15 -> 23277 | O22: 22793 | P22: =P21+P15 -> 279202
A24: Non-Revenue Water (NRW) | B24: Volume | C24: m3 | D24: =D9-D22 -> 5844 | E24: =E9-E22 -> 4846 | F24: =F9-F22 -> 1606 | G24: =G9-G22 -> 6291 | H24: =H9-H22 -> 5764 | I24: =I9-I22 -> 5986 | J24: =J9-J22 -> 3494 | K24: =K9-K22 -> 5372 | ... N24: =N9-N22 -> 4828 | O24: 5163 | P24: =P9-P22 -> 59429
B25: Percentage | C25: % | D25: =D24/D9 -> 0.20481548 | E25: =E24/E9 -> 0.16567521 | F25: =F24/F9 -> 0.055532503 | G25: =G24/G9 -> 0.21954284 | H25: =H24/H9 -> 0.20337309 | I25: =I24/I9 -> 0.21286583 | J25: =J24/J9 -> 0.12715164 | K25: =K24/K9 -> 0.19425059 | ... N25: =N24/N9 -> 0.17178438 | O25: 0.18468307 | P25: =P24/P9 -> 0.17549781
A26: OPERATING EXPENSES
A27: Chemicals
A28: Chemical | B28: Rate(MK/kg)
A29: Chlorine | B29: 3525.29 | C29: kg | D29: 30 | E29: 30 | F29: 30 | G29: 31 | H29: 31 | I29: 30 | J29: 31 | K29: 30 | L29: 31 | M29: 31 | N29: 29 | O29: 30 | P29: =SUM(D29:O29) -> 364
C30: kg/mg litre | D30: =D29/(D9/1000) -> 1.0514142 | E30: =E29/(E9/1000) -> 1.025641 | F30: =F29/(F9/1000) -> 1.0373444 | G30: =G29/(G9/1000) -> 1.0818356 | H30: =H29/(H9/1000) -> 1.0937831 | I30: =I29/(I9/1000) -> 1.0668184 | J30: =J29/(J9/1000) -> 1.1281342 | K30: =K29/(K9/1000) -> 1.0847948 | L30: 1.1046967 | M30: =M29/(M9/1000) -> 1.1251043 | N30: =N29/(N9/1000) -> 1.0318449 | O30: 1.0731149 | P30: =P29/(P9/1000) -> 1.0749164
A31: Aluminium sulphate | C31: kg | P31: =SUM(D31:O31) -> 0
B32: 1060.01 | C32: kg/mg litre | D32: =D31/(D9/1000) -> 0 | E32: =E31/(E9/1000) -> 0 | F32: =F31/(F9/1000) -> 0 | G32: =G31/(G9/1000) -> 0 | H32: =H31/(H9/1000) -> 0 | I32: =I31/(I9/1000) -> 0 | J32: =J31/(J9/1000) -> 0 | K32: =K31/(K9/1000) -> 0 | ... N32: =N31/(N9/1000) -> 0 | O32: 0 | P32: =P31/(P9/1000) -> 0
A33: Soda | C33: kg | P33: =SUM(D33:O33) -> 0
B34: 1228.29 | C34: kg/mg litre | D34: =D33/(D9/1000) -> 0 | E34: =E33/(E9/1000) -> 0 | F34: =F33/(F9/1000) -> 0 | G34: =G33/(G9/1000) -> 0 | H34: =H33/(H9/1000) -> 0 | I34: =I33/(I9/1000) -> 0 | J34: =J33/(J9/1000) -> 0 | K34: =K33/(K9/1000) -> 0 | ... N34: =N33/(N9/1000) -> 0 | O34: 0 | P34: =P33/(P9/1000) -> 0
A35: Algae floc | C35: litres
B36: 3726.73 | C36: litres/mg litre | D36: =D35/(D11/1000) -> 0 | F36: =F35/(F11/1000) -> 0
A37: Sud floc | C37: litres | H37: 0 | I37: 0 | J37: 0 | K37: 0 | L37: 0 | M37: 0 | N37: 0 | O37: 0 | P37: =SUM(D37:O37) -> 0
B38: 3951.59 | C38: litres/mg litre | D38: =D37/(D13/1000) -> 0 | E38: =E37/(E13/1000) -> 0 | F38: =F37/(F13/1000) -> 0 | G38: =G37/(G13/1000) -> 0 | H38: =H37/(H9/1000) -> 0 | I38: =I37/(I9/1000) -> 0 | J38: =J37/(J9/1000) -> 0 | K38: =K37/(K9/1000) -> 0 | L38: =L37/(L9/1000) -> 0 | M38: =M37/(M9/1000) -> 0 | N38: =N37/(N9/1000) -> 0 | O38: 0 | P38: =P37/(P9/1000) -> 0
A39: Potasium permanganate | C39: kg | H39: 0 | I39: 0 | J39: 0 | K39: 0 | L39: 0 | M39: 0 | N39: 0 | O39: 0 | P39: =SUM(D39:O39) -> 0
B40: 1950 | C40: kg/mg litre | D40: =D39/(D15/1000) -> 0 | E40: =E39/(E15/1000) -> 0 | F40: =F39/(F15/1000) -> 0 | G40: =G39/(G15/1000) -> 0 | H40: =H39/(H9/1000) -> 0 | I40: =I39/(I9/1000) -> 0 | J40: =J39/(J9/1000) -> 0 | K40: =K39/(K9/1000) -> 0 | L40: =L39/(L9/1000) -> 0 | M40: =M39/(M9/1000) -> 0 | N40: =N39/(N9/1000) -> 0 | O40: 0 | P40: =P39/(P9/1000) -> 0
A41: Cost of Chemicals | C41: Mk | D41: =(D29*$B29)+(D31*$B31)+(D33*$B33)+(D35*$B35)+(D37*$B37)+(D39*$B39) -> 105758.7 | E41: =(E29*$B29)+(E31*$B31)+(E33*$B33)+(E35*$B35)+(E37*$B37)+(E39*$B39) -> 105758.7 | F41: =(F29*$B29)+(F31*$B31)+(F33*$B33)+(F35*$B35)+(F37*$B37)+(F39*$B39) -> 105758.7 | G41: =(G29*$B29)+(G31*$B31)+(G33*$B33)+(G35*$B35)+(G37*$B37)+(G39*$B39) -> 109283.99 | H41: =(H29*$B29)+(H31*$B31)+(H33*$B33)+(H35*$B35)+(H37*$B37)+(H39*$B39) -> 109283.99 | I41: =(I29*$B29)+(I31*$B31)+(I33*$B33)+(I35*$B35)+(I37*$B37)+(I39*$B39) -> 105758.7 | J41: =(J29*$B29)+(J31*$B31)+(J33*$B33)+(J35*$B35)+(J37*$B37)+(J39*$B39) -> 109283.99 | K41: =(K29*$B29)+(K31*$B31)+(K33*$B33)+(K35*$B35)+(K37*$B37)+(K39*$B39) -> 105758.7 | ... N41: =(N29*$B29)+(N31*$B31)+(N33*$B33)+(N35*$B35)+(N37*$B37)+(N39*$B39) -> 102233.41 | O41: 105758.7 | P41: =SUM(D41:O41) -> 1283205.6
A42: Cost/vol. Produced (chemicals) | C42: Mk/m3 | D42: =D41/D9 -> 3.7065398 | E42: =E41/E9 -> 3.6156821 | F42: =F41/F9 -> 3.6569398 | G42: =G41/G9 -> 3.8137843 | H42: =H41/H9 -> 3.8559025 | I42: =I41/I9 -> 3.7608442 | J42: =J41/J9 -> 3.9770003 | K42: =K41/K9 -> 3.8242162 | ... N42: =N41/N9 -> 3.6375524 | O42: 3.7830412 | P42: =P41/P9 -> 3.7893919
A43: Power
A44: Power Usage | C44: Kw | D44: 16535 | E44: 18032 | F44: 18115 | G44: 16400 | H44: 16235 | I44: 16551 | J44: 15832 | K44: 15911 | L44: 16501 | M44: 15116 | N44: 16203 | O44: 15859 | P44: =SUM(D44:O44) -> 197290
A45: Power/ Vol. Produced | C45: Kw/m3 | D45: =D44/D9 -> 0.57950443 | E45: =E44/E9 -> 0.61647863 | F45: =F44/F9 -> 0.62638313 | G45: =G44/G9 -> 0.57232595 | H45: =H44/H9 -> 0.57282478 | I45: =I44/I9 -> 0.58856371 | J45: =J44/J9 -> 0.57614906 | K45: =K44/K9 -> 0.575339 | L45: 0.58801939 | M45: =M44/M9 -> 0.5486154 | N45: =N44/N9 -> 0.57651663 | O45: 0.5672843 | P45: =P44/P9 -> 0.58261057
A46: Cost of Power | C46: Mk | D46: =151.1*D44 -> 2498438.5 | E46: =151.1*E44 -> 2724635.2 | F46: =151.1*F44 -> 2737176.5 | G46: =151.1*G44 -> 2478040 | H46: =151.1*H44 -> 2453108.5 | I46: =151.1*I44 -> 2500856.1 | J46: =1.165*(14100+(J44*119.1)) -> 2213140.2 | K46: =1.165*(14100+(K44*119.1)) -> 2224101.6 | L46: =1.165*(14100+(L44*119.1)) -> 2305965 | M46: =1.165*(14100+(M44*119.1)) -> 2113794.2 | N46: =1.165*(14100+(N44*119.1)) -> 2264617.1 | O46: 2216886.5 | P46: =SUM(D46:O46) -> 28730759
A47: Cost/vol. Produced | C47: Mk/m3 | D47: =D46/D9 -> 87.56312 | E47: =E46/E9 -> 93.149921 | F47: =F46/F9 -> 94.64649 | G47: =G46/G9 -> 86.478451 | H47: =H46/H9 -> 86.553825 | I47: =I46/I9 -> 88.931976 | J47: =J46/J9 -> 80.53933 | K47: =K46/K9 -> 80.423128 | ... N47: =N46/N9 -> 80.577017 | O47: 79.299132 | P47: =P46/P9 -> 84.843855
A48: Plant and Vehicle Maintenance
A49: Distances covered | C49: km | D49: 336 | E49: 624 | F49: 895 | G49: 655 | H49: 517 | I49: 558 | J49: 2290 | K49: 2320 | L49: 2526 | M49: 766 | N49: 561 | O49: 745 | P49: =SUM(D49:O49) -> 12793
A50: Fuel Used (litres) | C50: litres | D50: 52 | E50: 91 | F50: 115 | G50: 155 | H50: 110 | I50: 85 | J50: 400 | K50: 420 | L50: 450 | M50: 150 | N50: 200 | O50: 155 | P50: =SUM(D50:O50) -> 2383
A51: Cost of fuel | C51: Mk | D51: =D50*1920 -> 99840 | E51: =E50*1920 -> 174720 | F51: =F50*1920 -> 220800 | G51: =G50*1920 -> 297600 | H51: =H50*1920 -> 211200 | I51: =I50*1920 -> 163200 | J51: =J50*1920 -> 768000 | K51: =K50*1920 -> 806400 | L51: 864000 | M51: =M50*1920 -> 288000 | N51: 384000 | O51: 423770 | P51: =SUM(D51:O51) -> 4701530
A52: Maintenance | C52: Mk | D52: 0 | E52: 0 | F52: 0 | G52: 0 | H52: 0 | I52: 0 | J52: 0 | K52: 0 | L52: 0 | M52: 0 | N52: 0 | O52: 0 | P52: =SUM(D52:O52) -> 0
A53: Salaries and Wages
A54: Staff Costs | C54: MK | P54: =SUM(D54:O54) -> 0
A55: Wages | C55: MK | P55: =SUM(D55:O55) -> 0
A56: Other Overhead Costs | C56: MK | P56: =SUM(D56:O56) -> 0
A57: Operating Costs
A58: Total Operating Costs | C58: MK | D58: =D41+D46+D51+D52+D54+D55+D56 -> 2704037.2 | E58: =E41+E46+E51+E52+E54+E55+E56 -> 3005113.9 | F58: =F41+F46+F51+F52+F54+F55+F56 -> 3063735.2 | G58: =G41+G46+G51+G52+G54+G55+G56 -> 2884924 | H58: =H41+H46+H51+H52+H54+H55+H56 -> 2773592.5 | I58: =I41+I46+I51+I52+I54+I55+I56 -> 2769814.8 | J58: =J41+J46+J51+J52+J54+J55+J56 -> 3090424.2 | K58: =K41+K46+K51+K52+K54+K55+K56 -> 3136260.3 | ... N58: =N41+N46+N51+N52+N54+N55+N56 -> 2750850.5 | O58: 2746415.2 | P58: =SUM(D58:O58) -> 34715495
A59: Cost/Vol. Produced | C59: Mk/m3 | D59: =D58/D9 -> 94.768766 | E59: =E58/E9 -> 102.73894 | F59: =F58/F9 -> 105.93828 | G59: =G58/G9 -> 100.67786 | H59: =H58/H9 -> 97.861566 | I59: =I58/I9 -> 98.496312 | J59: =J58/J9 -> 112.46495 | K59: =K58/K9 -> 113.40663 | ... N59: =N58/N9 -> 97.877618 | O59: 98.240637 | P59: =P58/P9 -> 102.51718
A60: Cost/Vol. Billed | C60: Mk/m3 | D60: =D58/D22 -> 119.17833 | E60: =E58/E22 -> 123.14022 | F60: =F58/F22 -> 112.16721 | G60: =G58/G22 -> 128.99857 | H60: =H58/H22 -> 122.84491 | I60: =I58/I22 -> 125.13281 | J60: =J58/J22 -> 128.84821 | K60: =K58/K22 -> 140.74677 | ... N60: =N58/N22 -> 118.17891 | O60: 120.4938 | P60: =P58/P22 -> 124.33827
A61: Permanent Staff Employed | C61: No | D61: 8 | E61: 8 | F61: 8 | G61: 8 | H61: 8 | I61: 8 | J61: 8 | K61: 8 | L61: 8 | M61: 8 | N61: 8 | O61: 8 | P61: =O61 -> 8
A62: Staff/Vol.1000m3 of Volume Produced/hour (12 hour day) | C62: No/1000m3 | D62: =(D61*1000*31)/D9 -> 8.6916903 | E62: =(E61*1000*31)/E9 -> 8.4786325 | F62: =(F61*1000*31)/F9 -> 8.5753804 | G62: =(G61*1000*31)/G9 -> 8.654685 | H62: =(H61*1000*31)/H9 -> 8.7502646 | I62: =(I61*1000*31)/I9 -> 8.819032 | J62: =(J61*1000*31)/J9 -> 9.0250737 | K62: =(K61*1000*31)/K9 -> 8.967637 | ... N62: =(N61*1000*31)/N9 -> 8.8240527 | O62: 8.8710831 | P62: =(P61*1000*31)/P9 -> 0.73236059
A63: Temporary Staff Employed | C63: No | D63: 6 | E63: 6 | F63: 6 | G63: 6 | H63: 6 | I63: 6 | J63: 6 | K63: 7 | L63: 7 | M63: 7 | N63: 7 | O63: 7 | P63: =SUM(D63:O63) -> 77
A65: Water Connections and Disconnections
A66: New Individual Water Connections | B66: Brought Forward | C66: No | D66: 376 | E66: =D71 -> 378 | F66: =E71 -> 360 | G66: =F71 -> 325 | H66: =G71 -> 289 | I66: =H71 -> 284 | J66: =I71 -> 285 | K66: =J71 -> 283 | L66: 273 | M66: =L71 -> 266 | N66: 247 | O66: 247 | P66: =D66 -> 376
B67: Applied this Month | C67: No | D67: 21 | F67: 11 | G67: 9 | H67: 17 | I67: 25 | J67: 14 | K67: 10 | L67: 7 | M67: 5 | N67: 19 | O67: 17 | P67: =SUM(D67:O67) -> 155
B68: Done this Month Postpaid | C68: No | D68: 19 | E68: 18 | F68: 46 | G68: 45 | H68: 20 | I68: 24 | J68: 16 | K68: 19 | L68: 13 | M68: 24 | N68: 19 | O68: 23 | P68: =SUM(D68:O68) -> 286
B69: Done this Month Prepaid | C69: No | H69: 2 | K69: 1 | L69: 1 | P69: =SUM(D69:O69) -> 4
B70: Total Done | C70: No | D70: =D68+D69 -> 19 | E70: =E68+E69 -> 18 | F70: =F68+F69 -> 46 | G70: =G68+G69 -> 45 | H70: =H68+H69 -> 22 | I70: =I68+I69 -> 24 | J70: =J68+J69 -> 16 | K70: =K68+K69 -> 20 | L70: 14 | M70: =M68+M69 -> 24 | N70: =N68+N69 -> 19 | O70: 23 | P70: =P68+P69 -> 290
B71: Carried Forward | C71: No | D71: =D66+D67-D70 -> 378 | E71: =E66+E67-E70 -> 360 | F71: =F66+F67-F70 -> 325 | G71: =G66+G67-G70 -> 289 | H71: =H66+H67-H70 -> 284 | I71: =I66+I67-I70 -> 285 | J71: =J66+J67-J70 -> 283 | K71: =K66+K67-K70 -> 273 | L71: 266 | M71: =M66+M67-M70 -> 247 | N71: =N66+N67-N70 -> 247 | O71: 241 | P71: =P66+P67-P70 -> 241
A72: New Institutional Water Connections | B72: Brought Forward | C72: No | E72: =D77 -> 0 | F72: =E77 -> 0 | G72: =F77 -> 0 | P72: =D72 -> 0
B73: Applied this Month | C73: No | D73: 1 | P73: =SUM(D73:O73) -> 1
B74: Done this Month Postpaid | C74: No | D74: 1 | P74: =SUM(D74:O74) -> 1
B75: Done this Month Prepaid | C75: No | P75: =SUM(D75:O75) -> 0
B76: Total Done | C76: No | D76: =D74+D75 -> 1 | E76: =E74+E75 -> 0 | F76: =F74+F75 -> 0 | G76: =G74+G75 -> 0 | H76: =H74+H75 -> 0 | I76: =I74+I75 -> 0 | J76: =J74+J75 -> 0 | K76: =K74+K75 -> 0 | ... N76: =N74+N75 -> 0 | O76: 0 | P76: =P74+P75 -> 1
B77: Carried Forward | C77: No | D77: =D72+D73-D76 -> 0 | E77: =E72+E73-E76 -> 0 | F77: =F72+F73-F76 -> 0 | G77: =G72+G73-G76 -> 0 | H77: =H72+H73-H76 -> 0 | I77: =I72+I73-I76 -> 0 | J77: =J72+J73-J76 -> 0 | K77: =K72+K73-K76 -> 0 | ... N77: =N72+N73-N76 -> 0 | O77: 0 | P77: =P72+P73-P76 -> 0
A78: New Commercial/Industrial Water Connections | B78: Brought Forward | C78: No | E78: =D83 -> 0 | F78: =E83 -> 0 | G78: =F83 -> 0 | P78: =D78 -> 0
B79: Applied this Month | C79: No | P79: =SUM(D79:O79) -> 0
B80: Done this Month Postpaid | C80: No | P80: =SUM(D80:O80) -> 0
B81: Done this Month Prepaid | C81: No | P81: =SUM(D81:O81) -> 0
B82: Total Done | C82: No | D82: =D80+D81 -> 0 | E82: =E80+E81 -> 0 | F82: =F80+F81 -> 0 | G82: =G80+G81 -> 0 | H82: =H81+H80 -> 0 | I82: =I81+I80 -> 0 | J82: =J81+J80 -> 0 | K82: =K81+K80 -> 0 | L82: =L81+L80 -> 0 | M82: =M81+M80 -> 0 | N82: =N81+N80 -> 0 | O82: 0 | P82: =P81+P80 -> 0
B83: Carried Forward | C83: No | D83: =D78+D79-D82 -> 0 | E83: =E78+E79-E82 -> 0 | F83: =F78+F79-F82 -> 0 | G83: =G78+G79-G82 -> 0 | H83: =H78+H79-H82 -> 0 | I83: =I78+I79-I82 -> 0 | J83: =J78+J79-J82 -> 0 | K83: =K78+K79-K82 -> 0 | ... N83: =N78+N79-N82 -> 0 | O83: 0 | P83: =P78+P79-P82 -> 0
A84: New CWP | B84: Brought Forward | C84: No | E84: =D89 -> 0 | F84: =E89 -> 0 | G84: =F89 -> 0 | P84: =D84 -> 0
B85: Applied this Month | C85: No | P85: =SUM(D85:O85) -> 0
B86: Done this Month Postpaid | C86: No | P86: =SUM(D86:O86) -> 0
B87: Done this Month Prepaid | C87: No | P87: =SUM(D87:O87) -> 0
B88: Total Done | C88: No | D88: =D86+D87 -> 0 | E88: =E87+E86 -> 0 | F88: =F87+F86 -> 0 | G88: =G87+G86 -> 0 | H88: =H87+H86 -> 0 | I88: =I87+I86 -> 0 | J88: =J87+J86 -> 0 | K88: =K87+K86 -> 0 | L88: =L87+L86 -> 0 | ... N88: =N87+N86 -> 0 | O88: 0 | P88: =SUM(D88:O88) -> 0
B89: Carried Forward | C89: No | D89: =D84+D85-D88 -> 0 | E89: =E84+E85-E88 -> 0 | F89: =F84+F85-F88 -> 0 | G89: =G84+G85-G88 -> 0 | H89: =H84+H85-H88 -> 0 | I89: =I84+I85-I88 -> 0 | J89: =J84+J85-J88 -> 0 | K89: =K84+K85-K88 -> 0 | ... N89: =N84+N85-N88 -> 0 | O89: 0 | P89: =P84+P85-P86-P87 -> 0
A90: Aggregated New Water connections | B90: Brought Forward | C90: No | D90: =D66+D72+D78+D84 -> 376 | E90: =E66+E72+E78+E84 -> 378 | F90: =F66+F72+F78+F84 -> 360 | G90: =G66+G72+G78+G84 -> 325 | H90: =H66+H72+H78+H84 -> 289 | I90: =I66+I72+I78+I84 -> 284 | J90: =J66+J72+J78+J84 -> 285 | K90: =K66+K72+K78+K84 -> 283 | ... N90: =N66+N72+N78+N84 -> 247 | O90: 247 | P90: =D90 -> 376
B91: Applied this Month | C91: No | D91: =D67+D73+D79+D85 -> 22 | E91: =E67+E73+E79+E85 -> 0 | F91: =F67+F73+F79+F85 -> 11 | G91: =G67+G73+G79+G85 -> 9 | H91: =H67+H73+H79+H85 -> 17 | I91: =I67+I73+I79+I85 -> 25 | J91: =J67+J73+J79+J85 -> 14 | K91: =K67+K73+K79+K85 -> 10 | ... N91: =N67+N73+N79+N85 -> 19 | O91: 17 | P91: =SUM(D91:O91) -> 156
B92: Done this Month Postpaid | C92: No | D92: =D68+D74+D80+D86 -> 20 | E92: =E68+E74+E80+E86 -> 18 | F92: =F68+F74+F80+F86 -> 46 | G92: =G68+G74+G80+G86 -> 45 | H92: =H68+H74+H80+H86 -> 20 | I92: =I68+I74+I80+I86 -> 24 | J92: =J68+J74+J80+J86 -> 16 | K92: =K68+K74+K80+K86 -> 19 | ... N92: =N68+N74+N80+N86 -> 19 | O92: 23 | P92: =SUM(D92:O92) -> 287
B93: Done this Month Prepaid | D93: =D69+D75+D81+D87 -> 0 | E93: =E69+E75+E81+E87 -> 0 | F93: =F69+F75+F81+F87 -> 0 | G93: =G69+G75+G81+G87 -> 0 | H93: =H69+H75+H81+H87 -> 2 | I93: =I69+I75+I81+I87 -> 0 | J93: =J69+J75+J81+J87 -> 0 | K93: =K69+K75+K81+K87 -> 1 | ... N93: =N69+N75+N81+N87 -> 0 | O93: 0 | P93: =SUM(D93:O93) -> 4
B94: Total Done | C94: No | D94: =D70+D76+D82+D88 -> 20 | E94: =E70+E76+E82+E88 -> 18 | F94: =F70+F76+F82+F88 -> 46 | G94: =G70+G76+G82+G88 -> 45 | H94: =H93+H92 -> 22 | I94: =I93+I92 -> 24 | J94: =J93+J92 -> 16 | K94: =K93+K92 -> 20 | L94: =L93+L92 -> 14 | M94: =M93+M92 -> 24 | N94: =N93+N92 -> 19 | O94: 23 | P94: =P93+P92 -> 291
B95: Carried Forward | C95: No | D95: =D71+D77+D83+D89 -> 378 | E95: =E71+E77+E83+E89 -> 360 | F95: =F71+F77+F83+F89 -> 325 | G95: =G71+G77+G83+G89 -> 289 | H95: =H90+H91-H94 -> 284 | I95: =I90+I91-I94 -> 285 | J95: =J90+J91-J94 -> 283 | K95: =K90+K91-K94 -> 273 | L95: =L90+L91-L94 -> 266 | M95: =M90+M91-M94 -> 247 | N95: =N90+N91-N94 -> 247 | O95: 241 | P95: =P90+P91-P94 -> 241
A97: Prepaid Metering
A98: Prepaid Meters Installed | C98: No | D98: 0 | E98: 0 | F98: 5 | P98: =SUM(D98:O98) -> 5
A100: Active and Disconnected Accounts
A101: Disconnected Individual Accounts | C101: No | D101: =287+148+103+50 -> 588 | E101: 571 | F101: 546 | G101: 580 | H101: 799 | I101: 799 | J101: 791 | K101: 780 | L101: 791 | M101: 871 | N101: 855 | O101: 835 | P101: =O101 -> 835
A102: Disconnected institutional Accounts | C102: No | D102: 11 | E102: 11 | F102: 11 | G102: 11 | H102: 11 | I102: 11 | J102: 11 | K102: 11 | L102: 11 | M102: 11 | N102: 11 | O102: 11 | P102: =O102 -> 11
A103: Disconnected Commercial/Industrial Accounts | C103: No | D103: 13 | E103: 13 | F103: 13 | G103: 16 | H103: 13 | I103: 13 | J103: 13 | K103: 13 | L103: 13 | M103: 13 | N103: 13 | O103: 13 | P103: =O103 -> 13
A104: Disconnected CWP | C104: No | D104: 14 | E104: 14 | F104: 14 | G104: 14 | H104: 16 | I104: 16 | J104: 16 | K104: 16 | L104: 16 | M104: 16 | N104: 16 | O104: 16 | P104: =O104 -> 16
A105: Total Disconnected Accounts | C105: No | D105: =SUM(D101:D104) -> 626 | E105: =SUM(E101:E104) -> 609 | F105: =SUM(F101:F104) -> 584 | G105: =SUM(G101:G104) -> 621 | H105: =SUM(H101:H104) -> 839 | I105: =SUM(I101:I104) -> 839 | J105: =SUM(J101:J104) -> 831 | K105: =SUM(K101:K104) -> 820 | ... N105: =SUM(N101:N104) -> 895 | O105: 875 | P105: =O105 -> 875
A106: Postpaid Consumers
...

Sheet Nchalo
A1: SOUTHERN REGION WATER BOARD
A3: MONTHLY REPORTS - 2023/2024
A4: NGABU ZONE
A5: NGABU ZONE
A7: PARAMETERS | C7: UNITS | D7: APRIL | E7: MAY | F7: JUNE | G7: JULY | H7: AUGUST | I7: SEPTEMBER | J7: OCTOBER | K7: NOVEMBER | L7: DECEMBER | M7: JANUARY | N7: FEBRUARY | O7: MARCH | P7: TOTALS
A8: PRODUCTION
A9: Volume Produced | C9: m3 | D9: 20645 | E9: 26000 | F9: 25006 | G9: 25832 | H9: 25158 | I9: 23447 | J9: 23417 | K9: 21185 | L9: 21185 | M9: 22587 | N9: 21686 | O9: 21393 | P9: =SUM(D9:O9) -> 277541
A10: REVENUE WATER - POSTPAID
A11: Volume Billed Individuals | C11: m3 | D11: =67+445+10456 -> 10968 | E11: =81+359+13256 -> 13696 | F11: =91+423+13471 -> 13985 | G11: =82+379+12695 -> 13156 | H11: =96+547+13603 -> 14246 | I11: =105+413+13937 -> 14455 | J11: 15986 | K11: =103+307+14615 -> 15025 | L11: 13022 | M11: 13549 | N11: =75+313+14476 -> 14864 | O11: 13763 | P11: =SUM(D11:O11) -> 166715
A12: Volume Billed CWPs | C12: m3 | D12: 655 | E12: 631 | F12: 754 | G12: 654 | H12: 762 | I12: 859 | J12: 637 | K12: 859 | L12: 750 | M12: 836 | N12: 772 | O12: 712 | P12: =SUM(D12:O12) -> 8881
A13: Volume Billed Institutions | C13: m3 | D13: 31 | E13: 24 | F13: 40 | G13: 113 | H13: 130 | I13: 124 | J13: 177 | K13: 75 | L13: 48 | M13: 38 | N13: 64 | O13: 84 | P13: =SUM(D13:O13) -> 948
A14: Volume Billed Commercial/Industrial | C14: m3 | D14: 225 | E14: 213 | F14: 212 | G14: 392 | H14: 194 | I14: 108 | J14: 602 | K14: 85 | L14: 71 | M14: 84 | N14: 108 | O14: 145 | P14: =SUM(D14:O14) -> 2439
A15: Total Volume Billed Post Paid | C15: m3 | D15: =SUM(D11:D14) -> 11879 | E15: =SUM(E11:E14) -> 14564 | F15: =SUM(F11:F14) -> 14991 | G15: =SUM(G11:G14) -> 14315 | H15: =SUM(H11:H14) -> 15332 | I15: =SUM(I11:I14) -> 15546 | J15: =SUM(J11:J14) -> 17402 | K15: =SUM(K11:K14) -> 16044 | ... N15: =SUM(N11:N14) -> 15808 | O15: 14704 | P15: =SUM(P11:P14) -> 178983
A16: REVENUE WATER - PREPAID
A17: Individuals | C17: m3 | P17: =SUM(D17:O17) -> 0
A18: CWPs | C18: m3 | P18: =SUM(D18:O18) -> 0
A19: Institutions | C19: m3 | D19: 2896 | E19: 2624.8 | F19: 2399 | G19: 2220.8 | H19: 3493.4 | I19: 2577.1 | K19: 2572.3 | L19: 2833.8 | M19: 2421.6 | N19: 3557.9 | O19: 2069.4 | P19: =SUM(D19:O19) -> 29666.1
A20: Commercial/Industrial | C20: m3 | P20: =SUM(D20:O20) -> 0
A21: Total Volume Prepaid | C21: m3 | D21: =SUM(D17:D20) -> 2896 | E21: =SUM(E17:E20) -> 2624.8 | F21: =SUM(F17:F20) -> 2399 | G21: =SUM(G17:G20) -> 2220.8 | H21: =SUM(H17:H20) -> 3493.4 | I21: =SUM(I17:I20) -> 2577.1 | J21: =SUM(J17:J20) -> 0 | K21: =SUM(K17:K20) -> 2572.3 | ... N21: =SUM(N17:N20) -> 3557.9 | O21: 2069.4 | P21: =SUM(P17:P20) -> 29666.1
A22: TOTAL REVENUE WATER | C22: m3 | D22: =D21+D15 -> 14775 | E22: =E21+E15 -> 17188.8 | F22: =F21+F15 -> 17390 | G22: =G21+G15 -> 16535.8 | H22: =H21+H15 -> 18825.4 | I22: =I21+I15 -> 18123.1 | J22: =J21+J15 -> 17402 | K22: =K21+K15 -> 18616.3 | ... N22: =N21+N15 -> 19365.9 | O22: 16773.4 | P22: =P21+P15 -> 208649.1
A24: Non-Revenue Water (NRW) | B24: Volume | C24: m3 | D24: =D9-D22 -> 5870 | E24: =E9-E22 -> 8811.2 | F24: =F9-F22 -> 7616 | G24: =G9-G22 -> 9296.2 | H24: =H9-H22 -> 6332.6 | I24: =I9-I22 -> 5323.9 | J24: =J9-J22 -> 6015 | K24: =K9-K22 -> 2568.7 | ... N24: =N9-N22 -> 2320.1 | O24: 4619.6 | P24: =P9-P22 -> 68891.9
B25: Percentage | C25: % | D25: =D24/D9 -> 0.28433035 | E25: =E24/E9 -> 0.33889231 | F25: =F24/F9 -> 0.3045669 | G25: =G24/G9 -> 0.35987148 | H25: =H24/H9 -> 0.25171317 | I25: =I24/I9 -> 0.22706103 | J25: =J24/J9 -> 0.25686467 | K25: =K24/K9 -> 0.12125089 | ... N25: =N24/N9 -> 0.10698607 | O25: 0.21593979 | P25: =P24/P9 -> 0.24822242
A26: OPERATING EXPENSES
A27: Chemicals
A28: Chemical | B28: Rate(MK/kg)
A29: Chlorine | B29: 3525.29 | C29: kg | D29: 18 | E29: 19 | F29: 16 | G29: 17 | H29: 18 | I29: 18 | J29: 20 | K29: 19 | L29: 20 | M29: 18 | N29: 18 | O29: 18 | P29: =SUM(D29:O29) -> 219
C30: kg/mg litre | D30: =D29/(D9/1000) -> 0.87188181 | E30: =E29/(E9/1000) -> 0.73076923 | F30: =F29/(F9/1000) -> 0.63984644 | G30: =G29/(G9/1000) -> 0.65809848 | H30: =H29/(H9/1000) -> 0.71547818 | I30: =I29/(I9/1000) -> 0.76768883 | J30: =J29/(J9/1000) -> 0.85408037 | K30: =K29/(K9/1000) -> 0.89686099 | L30: 0.9440642 | M30: =M29/(M9/1000) -> 0.79691858 | N30: =N29/(N9/1000) -> 0.83002859 | O30: 0.84139672 | P30: =P29/(P9/1000) -> 0.78907261
A31: Aluminium sulphate | C31: kg | P31: =SUM(D31:O31) -> 0
B32: 1060.01 | C32: kg/mg litre | D32: =D31/(D9/1000) -> 0 | E32: =E31/(E9/1000) -> 0 | F32: =F31/(F9/1000) -> 0 | G32: =G31/(G9/1000) -> 0 | H32: =H31/(H9/1000) -> 0 | I32: =I31/(I9/1000) -> 0 | J32: =J31/(J9/1000) -> 0 | K32: =K31/(K9/1000) -> 0 | ... N32: =N31/(N9/1000) -> 0 | O32: 0 | P32: =P31/(P9/1000) -> 0
A33: Soda | C33: kg | P33: =SUM(D33:O33) -> 0
B34: 1228.29 | C34: kg/mg litre | D34: =D33/(D9/1000) -> 0 | E34: =E33/(E9/1000) -> 0 | F34: =F33/(F9/1000) -> 0 | G34: =G33/(G9/1000) -> 0 | H34: =H33/(H9/1000) -> 0 | I34: =I33/(I9/1000) -> 0 | J34: =J33/(J9/1000) -> 0 | K34: =K33/(K9/1000) -> 0 | ... N34: =N33/(N9/1000) -> 0 | O34: 0 | P34: =P33/(P9/1000) -> 0
A35: Algae floc | C35: litres
B36: 3726.73 | C36: litres/mg litre | D36: =D35/(D11/1000) -> 0 | E36: =E35/(E11/1000) -> 0 | F36: =F35/(F11/1000) -> 0 | G36: =G35/(G11/1000) -> 0
A37: Sud floc | C37: litres | H37: 0 | I37: 0 | J37: 0 | K37: 0 | L37: 0 | M37: 0 | N37: 0 | O37: 0 | P37: =SUM(D37:O37) -> 0
B38: 3951.59 | C38: litres/mg litre | D38: =D37/(D13/1000) -> 0 | E38: =E37/(E13/1000) -> 0 | F38: =F37/(F13/1000) -> 0 | G38: =G37/(G13/1000) -> 0 | H38: =H37/(H9/1000) -> 0 | I38: =I37/(I9/1000) -> 0 | J38: =J37/(J9/1000) -> 0 | K38: =K37/(K9/1000) -> 0 | L38: =L37/(L9/1000) -> 0 | M38: =M37/(M9/1000) -> 0 | N38: =N37/(N9/1000) -> 0 | O38: 0 | P38: =P37/(P9/1000) -> 0
A39: Potasium permanganate | C39: kg | H39: 0 | I39: 0 | J39: 0 | K39: 0 | L39: 0 | M39: 0 | N39: 0 | O39: 0 | P39: =SUM(D39:O39) -> 0
B40: 1950 | C40: kg/mg litre | D40: =D39/(D15/1000) -> 0 | E40: =E39/(E15/1000) -> 0 | F40: =F39/(F15/1000) -> 0 | G40: =G39/(G15/1000) -> 0 | H40: =H39/(H9/1000) -> 0 | I40: =I39/(I9/1000) -> 0 | J40: =J39/(J9/1000) -> 0 | K40: =K39/(K9/1000) -> 0 | L40: =L39/(L9/1000) -> 0 | M40: =M39/(M9/1000) -> 0 | N40: =N39/(N9/1000) -> 0 | O40: 0 | P40: =P39/(P9/1000) -> 0
A41: Cost of Chemicals | C41: Mk | D41: =(D29*$B29)+(D31*$B31)+(D33*$B33)+(D35*$B35)+(D37*$B37)+(D39*$B39) -> 63455.22 | E41: =(E29*$B29)+(E31*$B31)+(E33*$B33)+(E35*$B35)+(E37*$B37)+(E39*$B39) -> 66980.51 | F41: =(F29*$B29)+(F31*$B31)+(F33*$B33)+(F35*$B35)+(F37*$B37)+(F39*$B39) -> 56404.64 | G41: =(G29*$B29)+(G31*$B31)+(G33*$B33)+(G35*$B35)+(G37*$B37)+(G39*$B39) -> 59929.93 | H41: =(H29*$B29)+(H31*$B31)+(H33*$B33)+(H35*$B35)+(H37*$B37)+(H39*$B39) -> 63455.22 | I41: =(I29*$B29)+(I31*$B31)+(I33*$B33)+(I35*$B35)+(I37*$B37)+(I39*$B39) -> 63455.22 | J41: =(J29*$B29)+(J31*$B31)+(J33*$B33)+(J35*$B35)+(J37*$B37)+(J39*$B39) -> 70505.8 | K41: =(K29*$B29)+(K31*$B31)+(K33*$B33)+(K35*$B35)+(K37*$B37)+(K39*$B39) -> 66980.51 | ... N41: =(N29*$B29)+(N31*$B31)+(N33*$B33)+(N35*$B35)+(N37*$B37)+(N39*$B39) -> 63455.22 | O41: 63455.22 | P41: =SUM(D41:O41) -> 772038.51
A42: Cost/vol. Produced (chemicals) | C42: Mk/m3 | D42: =D41/D9 -> 3.0736362 | E42: =E41/E9 -> 2.5761735 | F42: =F41/F9 -> 2.2556442 | G42: =G41/G9 -> 2.319988 | H42: =H41/H9 -> 2.5222681 | I42: =I41/I9 -> 2.7063258 | J42: =J41/J9 -> 3.010881 | K42: =K41/K9 -> 3.1616951 | ... N42: =N41/N9 -> 2.9260915 | O42: 2.9661674 | P42: =P41/P9 -> 2.7817098
A43: Power
A44: Power Usage | C44: Kw | D44: 7291 | E44: 7560 | F44: 6761 | G44: 6807 | H44: 8470 | I44: 8774 | J44: 8772 | K44: 7570 | L44: 7499 | M44: 7299 | N44: 6771 | P44: =SUM(D44:O44) -> 83574
A45: Power/ Vol. Produced | C45: Kw/m3 | D45: =D44/D9 -> 0.35316057 | E45: =E44/E9 -> 0.29076923 | F45: =F44/F9 -> 0.27037511 | G45: =G44/G9 -> 0.26351037 | H45: =H44/H9 -> 0.33667223 | I45: =I44/I9 -> 0.37420566 | J45: =J44/J9 -> 0.37459965 | K45: =K44/K9 -> 0.3573283 | L45: 0.35397687 | M45: 0.32315048 | N45: =N44/N9 -> 0.31222909 | O45: 0 | P45: =P44/P9 -> 0.30112308
A46: Cost of Power | C46: Mk | D46: =151.1*D44 -> 1101670.1 | E46: =151.1*E44 -> 1142316 | F46: =151.1*F44 -> 1021587.1 | G46: =151.1*G44 -> 1028537.7 | H46: =151.1*H44 -> 1279817 | I46: =151.1*I44 -> 1325751.4 | J46: =1.165*(14100+(J44*119.1)) -> 1233554.7 | K46: =1.165*(14100+(K44*119.1)) -> 1066775.4 | L46: =1.165*(14100+(L44*119.1)) -> 1056924 | M46: =1.165*(14100+(M44*119.1)) -> 1029173.7 | N46: =1.165*(14100+(N44*119.1)) -> 955912.91 | O46: 16426.5 | P46: =SUM(D46:O46) -> 12258446
A47: Cost/vol. Produced | C47: Mk/m3 | D47: =D46/D9 -> 53.362562 | E47: =E46/E9 -> 43.935231 | F47: =F46/F9 -> 40.853679 | G47: =G46/G9 -> 39.816418 | H47: =H46/H9 -> 50.871174 | I47: =I46/I9 -> 56.542475 | J47: =J46/J9 -> 52.677741 | K47: =K46/K9 -> 50.355221 | ... N47: =N46/N9 -> 44.079725 | O47: 0.76784462 | P47: =P46/P9 -> 44.168056
A48: Plant and Vehicle Maintenance
A49: Distances covered | C49: km | P49: =SUM(D49:O49) -> 0
A50: Fuel Used (litres) | C50: litres | P50: =SUM(D50:O50) -> 0
A51: Cost of fuel | C51: Mk | P51: =SUM(D51:O51) -> 0
A52: Maintenance | C52: Mk | D52: 0 | E52: 0 | F52: 0 | G52: 0 | H52: 0 | I52: 0 | J52: 0 | K52: 0 | L52: 0 | M52: 0 | N52: 0 | O52: 0 | P52: =SUM(D52:O52) -> 0
A53: Salaries and Wages
A54: Staff Costs | C54: MK | D54: 1522952.1 | E54: 1522952.1 | F54: 1522952.1 | G54: 1522952.1 | H54: 1522952.1 | I54: 1522952.1 | J54: 1522952.1 | K54: 1522952.1 | P54: =SUM(D54:O54) -> 12183617
A55: Wages | C55: MK | D55: 174038.8 | E55: 174038.8 | F55: 174038.8 | G55: 174038.8 | H55: 174038.8 | I55: 174038.8 | J55: 174038.8 | K55: 174038.8 | P55: =SUM(D55:O55) -> 1392310.4
A56: Other Overhead Costs | C56: MK | P56: =SUM(D56:O56) -> 0
A57: Operating Costs
A58: Total Operating Costs | C58: MK | D58: =D41+D46+D51+D52+D54+D55+D56 -> 2862116.2 | E58: =E41+E46+E51+E52+E54+E55+E56 -> 2906287.4 | F58: =F41+F46+F51+F52+F54+F55+F56 -> 2774982.6 | G58: =G41+G46+G51+G52+G54+G55+G56 -> 2785458.5 | H58: =H41+H46+H51+H52+H54+H55+H56 -> 3040263.1 | I58: =I41+I46+I51+I52+I54+I55+I56 -> 3086197.5 | J58: =J41+J46+J51+J52+J54+J55+J56 -> 3001051.3 | K58: =K41+K46+K51+K52+K54+K55+K56 -> 2830746.7 | ... N58: =N41+N46+N51+N52+N54+N55+N56 -> 1019368.1 | O58: 79881.72 | P58: =SUM(D58:O58) -> 26606412
A59: Cost/Vol. Produced | C59: Mk/m3 | D59: =D58/D9 -> 138.63484 | E59: =E58/E9 -> 111.78028 | F59: =F58/F9 -> 110.97267 | G59: =G58/G9 -> 107.82977 | H59: =H58/H9 -> 120.84677 | I59: =I58/I9 -> 131.62441 | J59: =J58/J9 -> 128.15695 | K59: =K58/K9 -> 133.62033 | ... N59: =N58/N9 -> 47.005816 | O59: 3.7340121 | P59: =P58/P9 -> 95.864798
A60: Cost/Vol. Billed | C60: Mk/m3 | D60: =D58/D22 -> 193.71345 | E60: =E58/E22 -> 169.0803 | F60: =F58/F22 -> 159.57347 | G60: =G58/G22 -> 168.45018 | H60: =H58/H22 -> 161.49793 | I60: =I58/I22 -> 170.29082 | J60: =J58/J22 -> 172.45439 | K60: =K58/K22 -> 152.05743 | ... N60: =N58/N22 -> 52.637271 | O60: 4.7624048 | P60: =P58/P22 -> 127.5175
A61: Permanent Staff Employed | C61: No | D61: 6 | E61: 6 | F61: 6 | G61: 6 | H61: 6 | I61: 6 | J61: 6 | K61: 6 | L61: 6 | M61: 6 | N61: 6 | O61: 6 | P61: =O61 -> 6
A62: Staff/Vol.1000m3 of Volume Produced/hour (12 hour day) | C62: No/1000m3 | D62: =(D61*1000*31)/D9 -> 9.0094454 | E62: =(E61*1000*31)/E9 -> 7.1538462 | F62: =(F61*1000*31)/F9 -> 7.4382148 | G62: =(G61*1000*31)/G9 -> 7.2003716 | H62: =(H61*1000*31)/H9 -> 7.3932745 | I62: =(I61*1000*31)/I9 -> 7.9327846 | J62: =(J61*1000*31)/J9 -> 7.9429474 | K62: =(K61*1000*31)/K9 -> 8.779797 | ... N62: =(N61*1000*31)/N9 -> 8.5769621 | O62: 8.6944328 | P62: =(P61*1000*31)/P9 -> 0.67017125
A63: Temporary Staff Employed | C63: No | D63: 6 | E63: 6 | F63: 6 | G63: 6 | H63: 6 | I63: 6 | J63: 6 | K63: 6 | L63: 6 | M63: 6 | N63: 6 | O63: 6 | P63: =SUM(D63:O63) -> 72
A65: Water Connections and Disconnections
A66: New Individual Water Connections | B66: Brought Forward | C66: No | D66: 54 | E66: =D71 -> 38 | F66: =E71 -> 35 | G66: =F71 -> 32 | H66: =G71 -> 32 | I66: =H71 -> 31 | J66: =I71 -> 40 | K66: =J71 -> 39 | L66: 43 | M66: 49 | N66: 32 | O66: 28 | P66: =D66 -> 54
B67: Applied this Month | C67: No | D67: 6 | E67: 15 | F67: 13 | G67: 15 | H67: 12 | I67: 16 | J67: 7 | K67: 13 | L67: 9 | O67: 10 | P67: =SUM(D67:O67) -> 116
B68: Done this Month Postpaid | C68: No | D68: 22 | E68: 18 | F68: 16 | G68: 15 | H68: 13 | J68: 8 | K68: 9 | L68: 3 | M68: 17 | N68: 4 | O68: 15 | P68: =SUM(D68:O68) -> 140
B69: Done this Month Prepaid | C69: No | I69: 7 | P69: =SUM(D69:O69) -> 7
B70: Total Done | C70: No | D70: =D68+D69 -> 22 | E70: =E68+E69 -> 18 | F70: =F68+F69 -> 16 | G70: =G68+G69 -> 15 | H70: =H68+H69 -> 13 | I70: =I68+I69 -> 7 | J70: =J68+J69 -> 8 | K70: =K68+K69 -> 9 | L70: 3 | M70: 17 | N70: 4 | O70: 15 | P70: =P68+P69 -> 147
B71: Carried Forward | C71: No | D71: =D66+D67-D70 -> 38 | E71: =E66+E67-E70 -> 35 | F71: =F66+F67-F70 -> 32 | G71: =G66+G67-G70 -> 32 | H71: =H66+H67-H70 -> 31 | I71: =I66+I67-I70 -> 40 | J71: =J66+J67-J70 -> 39 | K71: =K66+K67-K70 -> 43 | L71: 49 | M71: 32 | N71: 28 | O71: 23 | P71: =P66+P67-P70 -> 23
A72: New Institutional Water Connections | B72: Brought Forward | C72: No | E72: =D77 -> 0 | F72: =E77 -> 0 | G72: =F77 -> 0 | P72: =D72 -> 0
B73: Applied this Month | C73: No | G73: 1 | P73: =SUM(D73:O73) -> 1
B74: Done this Month Postpaid | C74: No | G74: 1 | P74: =SUM(D74:O74) -> 1
B75: Done this Month Prepaid | C75: No | P75: =SUM(D75:O75) -> 0
B76: Total Done | C76: No | D76: =D74+D75 -> 0 | E76: =E74+E75 -> 0 | F76: =F74+F75 -> 0 | G76: =G74+G75 -> 1 | H76: =H74+H75 -> 0 | I76: =I74+I75 -> 0 | J76: =J74+J75 -> 0 | K76: =K74+K75 -> 0 | ... N76: =N74+N75 -> 0 | O76: 0 | P76: =P74+P75 -> 1
B77: Carried Forward | C77: No | D77: =D72+D73-D76 -> 0 | E77: =E72+E73-E76 -> 0 | F77: =F72+F73-F76 -> 0 | G77: =G72+G73-G76 -> 0 | H77: =H73+H74-H76 -> 0 | I77: =I73+I74-I76 -> 0 | J77: =J73+J74-J76 -> 0 | K77: =K73+K74-K76 -> 0 | L77: =L73+L74-L76 -> 0 | M77: =M73+M74-M76 -> 0 | N77: =N73+N74-N76 -> 0 | O77: 0 | P77: =P73+P74-P76 -> 1
A78: New Commercial/Industrial Water Connections | B78: Brought Forward | C78: No | E78: =D83 -> 0 | F78: =E83 -> 0 | G78: =F83 -> 0 | H78: =G83 -> 0 | I78: =H83 -> 2 | J78: =I83 -> 2 | K78: =J83 -> 2 | L78: 2 | M78: 2 | N78: 2 | O78: 2 | P78: =D78 -> 0
B79: Applied this Month | C79: No | F79: 1 | H79: 3 | P79: =SUM(D79:O79) -> 4
B80: Done this Month Postpaid | C80: No | F80: 1 | P80: =SUM(D80:O80) -> 1
B81: Done this Month Prepaid | C81: No | H81: 1 | P81: =SUM(D81:O81) -> 1
B82: Total Done | C82: No | D82: =D80+D81 -> 0 | E82: =E80+E81 -> 0 | F82: =F80+F81 -> 1 | G82: =G80+G81 -> 0 | H82: =H80+H81 -> 1 | I82: =I81+I80 -> 0 | J82: =J81+J80 -> 0 | K82: =K81+K80 -> 0 | L82: =L81+L80 -> 0 | M82: =M81+M80 -> 0 | N82: =N81+N80 -> 0 | O82: 0 | P82: =P81+P80 -> 2
B83: Carried Forward | C83: No | D83: =D78+D79-D82 -> 0 | E83: =E78+E79-E82 -> 0 | F83: =F78+F79-F82 -> 0 | G83: =G78+G79-G82 -> 0 | H83: =H78+H79-H82 -> 2 | I83: =I78+I79-I82 -> 2 | J83: =J78+J79-J82 -> 2 | K83: =K78+K79-K82 -> 2 | ... N83: =N78+N79-N82 -> 2 | O83: 2 | P83: =P78+P79-P82 -> 2
A84: New CWP | B84: Brought Forward | C84: No | D84: 0 | E84: 0 | F84: 0 | P84: =D84 -> 0
B85: Applied this Month | C85: No | D85: 0 | E85: 0 | F85: 0 | P85: =SUM(D85:O85) -> 0
B86: Done this Month Postpaid | C86: No | D86: 0 | E86: 0 | F86: 0 | P86: =SUM(D86:O86) -> 0
B87: Done this Month Prepaid | C87: No | D87: 0 | E87: 0 | F87: 0 | P87: =SUM(D87:O87) -> 0
B88: Total Done | C88: No | D88: 0 | E88: 0 | F88: 0 | G88: 0 | H88: 0 | I88: 0 | J88: 0 | K88: 0 | L88: 0 | M88: 0 | N88: 0 | O88: 0
B89: Carried Forward | C89: No | D89: =D84+D85-D88 -> 0 | E89: =E84+E85-E88 -> 0 | F89: =F84+F85-F88 -> 0 | G89: =G84+G85-G88 -> 0 | H89: =H84+H85-H88 -> 0 | I89: =I84+I85-I88 -> 0 | J89: =J84+J85-J88 -> 0 | K89: =K84+K85-K88 -> 0 | ... N89: =N84+N85-N88 -> 0 | O89: 0 | P89: =P84+P85-P86-P87 -> 0
A90: Aggregated New Water connections | B90: Brought Forward | C90: No | D90: =D66+D72+D78+D84 -> 54 | E90: =E66+E72+E78+E84 -> 38 | F90: =F66+F72+F78+F84 -> 35 | G90: =G66+G72+G78+G84 -> 32 | H90: =H66+H72+H78+H84 -> 32 | I90: =I66+I72+I78+I84 -> 33 | J90: =J66+J72+J78+J84 -> 42 | K90: =K66+K72+K78+K84 -> 41 | ... N90: =N66+N72+N78+N84 -> 34 | O90: 30 | P90: =D90 -> 54
B91: Applied this Month | C91: No | D91: =D67+D73+D79+D85 -> 6 | E91: =E67+E73+E79+E85 -> 15 | F91: =F67+F73+F79+F85 -> 14 | G91: =G67+G73+G79+G85 -> 16 | H91: =H67+H73+H79+H85 -> 15 | I91: =I67+I73+I79+I85 -> 16 | J91: =J67+J73+J79+J85 -> 7 | K91: =K67+K73+K79+K85 -> 13 | ... N91: =N67+N73+N79+N85 -> 0 | O91: 10 | P91: =SUM(D91:O91) -> 121
B92: Done this Month Postpaid | C92: No | D92: =D68+D74+D80+D86 -> 22 | E92: =E68+E74+E80+E86 -> 18 | F92: =F68+F74+F80+F86 -> 17 | G92: =G68+G74+G80+G86 -> 16 | H92: =H68+H74+H80+H86 -> 13 | I92: =I68+I74+I80+I86 -> 0 | J92: =J68+J74+J80+J86 -> 8 | K92: =K68+K74+K80+K86 -> 9 | ... N92: =N68+N74+N80+N86 -> 4 | O92: 15 | P92: =SUM(D92:O92) -> 142
B93: Done this Month Prepaid | D93: =D69+D75+D81+D87 -> 0 | E93: =E69+E75+E81+E87 -> 0 | F93: =F69+F75+F81+F87 -> 0 | G93: =G69+G75+G81+G87 -> 0 | H93: =H69+H75+H81+H87 -> 1 | I93: =I69+I75+I81+I87 -> 7 | J93: =J69+J75+J81+J87 -> 0 | K93: =K69+K75+K81+K87 -> 0 | ... N93: =N69+N75+N81+N87 -> 0 | O93: 0 | P93: =SUM(D93:O93) -> 8
B94: Total Done | C94: No | D94: =D70+D76+D82+D88 -> 22 | E94: =E70+E76+E82+E88 -> 18 | F94: =F70+F76+F82+F88 -> 17 | G94: =G70+G76+G82+G88 -> 16 | H94: =H93+H92 -> 14 | I94: =I93+I92 -> 7 | J94: =J93+J92 -> 8 | K94: =K93+K92 -> 9 | L94: =L93+L92 -> 3 | M94: =M93+M92 -> 17 | N94: =N93+N92 -> 4 | O94: 15 | P94: =P93+P92 -> 150
B95: Carried Forward | C95: No | D95: =D71+D77+D83+D89 -> 38 | E95: =E71+E77+E83+E89 -> 35 | F95: =F71+F77+F83+F89 -> 32 | G95: =G71+G77+G83+G89 -> 32 | H95: =H90+H91-H94 -> 33 | I95: =I90+I91-I94 -> 42 | J95: =J90+J91-J94 -> 41 | K95: =K90+K91-K94 -> 45 | L95: =L90+L91-L94 -> 51 | M95: =M90+M91-M94 -> 34 | N95: =N90+N91-N94 -> 30 | O95: 25 | P95: =P90+P91-P94 -> 25
A97: Prepaid Metering
A98: Prepaid Meters Installed | C98: No | P98: =SUM(D98:O98) -> 0
A100: Active and Disconnected Accounts
A101: Disconnected Individual Accounts | C101: No | D101: =395+147+62 -> 604 | E101: 639 | F101: 629 | G101: 631 | H101: 625 | I101: 624 | J101: 623 | K101: 630 | L101: 623 | M101: 651 | N101: 650 | O101: 652 | P101: =O101 -> 652
A102: Disconnected institutional Accounts | C102: No | D102: 17 | E102: 17 | F102: 17 | G102: 17 | H102: 17 | I102: 17 | J102: 17 | K102: 17 | L102: 17 | M102: 17 | N102: 17 | O102: 17 | P102: =O102 -> 17
A103: Disconnected Commercial/Industrial Accounts | C103: No | D103: 27 | E103: 27 | F103: 27 | G103: 27 | H103: 27 | I103: 27 | J103: 27 | K103: 27 | L103: 27 | M103: 27 | N103: 27 | O103: 27 | P103: =O103 -> 27
A104: Disconnected CWP | C104: No | D104: 8 | E104: 11 | F104: 11 | G104: 11 | H104: 11 | I104: 11 | J104: 11 | K104: 11 | L104: 11 | M104: 11 | N104: 11 | O104: 11 | P104: =O104 -> 11
A105: Total Disconnected Accounts | C105: No | D105: =SUM(D101:D104) -> 656 | E105: =SUM(E101:E104) -> 694 | F105: =SUM(F101:F104) -> 684 | G105: =SUM(G101:G104) -> 686 | H105: =SUM(H101:H104) -> 680 | I105: =SUM(I101:I104) -> 679 | J105: =SUM(J101:J104) -> 678 | K105: =SUM(K101:K104) -> 685 | ... N105: =SUM(N101:N104) -> 705 | O105: 707 | P105: =O105 -> 707
A106: Postpaid Consumers
...

Sheet Miseu Folo
A1: SOUTHERN REGION WATER BOARD
A3: MONTHLY REPORTS - 2023/2024
A4: NGABU ZONE
A5: NGABU ZONE
A7: PARAMETERS | C7: UNITS | D7: APRIL | E7: MAY | F7: JUNE | G7: JULY | H7: AUGUST | I7: SEPTEMBER | J7: OCTOBER | K7: NOVEMBER | L7: DECEMBER | M7: JANUARY | N7: FEBRUARY | O7: MARCH | P7: TOTALS
A8: PRODUCTION
A9: Volume Produced | C9: m3 | D9: 2733 | E9: 3230 | F9: 3544 | G9: 3667 | H9: 3528 | I9: 3745 | J9: 4649 | K9: 4358 | L9: 3994 | M9: 3907 | N9: 4049 | O9: 3002 | P9: =SUM(D9:O9) -> 44406
A10: REVENUE WATER - POSTPAID
A11: Volume Billed Individuals | C11: m3 | D11: 301 | E11: 346 | F11: 526 | G11: 507 | H11: 705 | I11: 1412 | J11: 1981 | K11: 1043 | L11: 1311 | M11: 1074 | N11: 1185 | O11: 1136 | P11: =SUM(D11:O11) -> 11527
A12: Volume Billed CWPs | C12: m3 | P12: =SUM(D12:O12) -> 0
A13: Volume Billed Institutions | C13: m3 | F13: 5 | G13: 1 | H13: 7 | I13: 5 | J13: 5 | K13: 6 | M13: 5 | N13: 11 | O13: 9 | P13: =SUM(D13:O13) -> 54
A14: Volume Billed Commercial/Industrial | C14: m3 | D14: 7 | E14: 10 | F14: 19 | G14: 13 | H14: 15 | I14: 21 | J14: 11 | K14: 12 | O14: 13 | P14: =SUM(D14:O14) -> 121
A15: Total Volume Billed Post Paid | C15: m3 | D15: =SUM(D11:D14) -> 308 | E15: =SUM(E11:E14) -> 356 | F15: =SUM(F11:F14) -> 550 | G15: =SUM(G11:G14) -> 521 | H15: =SUM(H11:H14) -> 727 | I15: =SUM(I11:I14) -> 1438 | J15: =SUM(J11:J14) -> 1997 | K15: =SUM(K11:K14) -> 1061 | ... N15: =SUM(N11:N14) -> 1196 | O15: 1158 | P15: =SUM(P11:P14) -> 11702
A16: REVENUE WATER - PREPAID
A17: Individuals | C17: m3 | J17: 2037.6 | P17: =SUM(D17:O17) -> 2037.6
A18: CWPs | C18: m3 | P18: =SUM(D18:O18) -> 0
A19: Institutions | C19: m3 | D19: 1916 | E19: 2159 | F19: 2460.2 | G19: 2629 | H19: 1925 | I19: 2075.2 | K19: 2565 | L19: 1945 | M19: 1876.9 | N19: 2196 | O19: 1643.2 | P19: =SUM(D19:O19) -> 23390.5
A20: Commercial/Industrial | C20: m3 | P20: =SUM(D20:O20) -> 0
A21: Total Volume Prepaid | C21: m3 | D21: =SUM(D17:D20) -> 1916 | E21: =SUM(E17:E20) -> 2159 | F21: =SUM(F17:F20) -> 2460.2 | G21: =SUM(G17:G20) -> 2629 | H21: =SUM(H17:H20) -> 1925 | I21: =SUM(I17:I20) -> 2075.2 | J21: =SUM(J17:J20) -> 2037.6 | K21: =SUM(K17:K20) -> 2565 | ... N21: =SUM(N17:N20) -> 2196 | O21: 1643.2 | P21: =SUM(P17:P20) -> 25428.1
A22: TOTAL REVENUE WATER | C22: m3 | D22: =D21+D15 -> 2224 | E22: =E21+E15 -> 2515 | F22: =F21+F15 -> 3010.2 | G22: =G21+G15 -> 3150 | H22: =H21+H15 -> 2652 | I22: =I21+I15 -> 3513.2 | J22: =J21+J15 -> 4034.6 | K22: =K21+K15 -> 3626 | ... N22: =N21+N15 -> 3392 | O22: 2801.2 | P22: =P21+P15 -> 37130.1
A24: Non-Revenue Water (NRW) | B24: Volume | C24: m3 | D24: =D9-D22 -> 509 | E24: =E9-E22 -> 715 | F24: =F9-F22 -> 533.8 | G24: =G9-G22 -> 517 | H24: =H9-H22 -> 876 | I24: =I9-I22 -> 231.8 | J24: =J9-J22 -> 614.4 | K24: =K9-K22 -> 732 | ... N24: =N9-N22 -> 657 | O24: 200.8 | P24: =P9-P22 -> 7275.9
B25: Percentage | C25: % | D25: =D24/D9 -> 0.18624222 | E25: =E24/E9 -> 0.22136223 | F25: =F24/F9 -> 0.15062077 | G25: =G24/G9 -> 0.14098718 | H25: =H24/H9 -> 0.24829932 | I25: =I24/I9 -> 0.061895861 | J25: =J24/J9 -> 0.13215745 | K25: =K24/K9 -> 0.16796696 | ... N25: =N24/N9 -> 0.16226229 | O25: 0.066888741 | P25: =P24/P9 -> 0.16384948
A26: OPERATING EXPENSES
A27: Chemicals
A28: Chemical | B28: Rate(MK/kg)
A29: Chlorine | B29: 3525.29 | C29: kg | D29: 6 | E29: 7 | F29: 7.5 | G29: 8.1 | H29: 8 | I29: 7.2 | J29: 7 | K29: 6.8 | L29: 6.7 | M29: 6 | N29: 7 | O29: 6 | P29: =SUM(D29:O29) -> 83.3
C30: kg/mg litre | D30: =D29/(D9/1000) -> 2.1953897 | E30: =E29/(E9/1000) -> 2.1671827 | F30: =F29/(F9/1000) -> 2.1162528 | G30: =G29/(G9/1000) -> 2.2088901 | H30: =H29/(H9/1000) -> 2.2675737 | I30: =I29/(I9/1000) -> 1.9225634 | J30: =J29/(J9/1000) -> 1.5057002 | K30: =K29/(K9/1000) -> 1.5603488 | L30: 1.6775163 | M30: =M29/(M9/1000) -> 1.5357051 | N30: =N29/(N9/1000) -> 1.7288219 | O30: 1.9986676 | P30: =P29/(P9/1000) -> 1.8758726
A31: Aluminium sulphate | C31: kg | P31: =SUM(D31:O31) -> 0
B32: 1060.01 | C32: kg/mg litre | D32: =D31/(D9/1000) -> 0 | E32: =E31/(E9/1000) -> 0 | F32: =F31/(F9/1000) -> 0 | G32: =G31/(G9/1000) -> 0 | H32: =H31/(H9/1000) -> 0 | I32: =I31/(I9/1000) -> 0 | J32: =J31/(J9/1000) -> 0 | K32: =K31/(K9/1000) -> 0 | ... N32: =N31/(N9/1000) -> 0 | O32: 0 | P32: =P31/(P9/1000) -> 0
A33: Soda | C33: kg | P33: =SUM(D33:O33) -> 0
B34: 1228.29 | C34: kg/mg litre | D34: =D33/(D9/1000) -> 0 | E34: =E33/(E9/1000) -> 0 | F34: =F33/(F9/1000) -> 0 | G34: =G33/(G9/1000) -> 0 | H34: =H33/(H9/1000) -> 0 | I34: =I33/(I9/1000) -> 0 | J34: =J33/(J9/1000) -> 0 | K34: =K33/(K9/1000) -> 0 | ... N34: =N33/(N9/1000) -> 0 | O34: 0 | P34: =P33/(P9/1000) -> 0
A35: Algae floc | C35: litres
B36: 3726.73 | C36: litres/mg litre | D36: =D35/(D11/1000) -> 0 | E36: =E35/(E11/1000) -> 0 | F36: =F35/(F11/1000) -> 0 | G36: =G35/(G11/1000) -> 0
A37: Sud floc | C37: litres | H37: 0 | I37: 0 | J37: 0 | K37: 0 | L37: 0 | M37: 0 | N37: 0 | O37: 0 | P37: =SUM(D37:O37) -> 0
B38: 3951.59 | C38: litres/mg litre | D38: =D37/(D9/1000) -> 0 | E38: =E37/(E9/1000) -> 0 | F38: =F37/(F9/1000) -> 0 | G38: =G37/(G9/1000) -> 0 | H38: =H37/(H9/1000) -> 0 | I38: =I37/(I9/1000) -> 0 | J38: =J37/(J9/1000) -> 0 | K38: =K37/(K9/1000) -> 0 | ... N38: =N37/(N9/1000) -> 0 | O38: 0 | P38: =P37/(P9/1000) -> 0
A39: Potasium permanganate | C39: kg | H39: 0 | I39: 0 | J39: 0 | K39: 0 | L39: 0 | M39: 0 | N39: 0 | O39: 0 | P39: =SUM(D39:O39) -> 0
B40: 1950 | C40: kg/mg litre | D40: =D39/(D15/1000) -> 0 | E40: =E39/(E15/1000) -> 0 | F40: =F39/(F15/1000) -> 0 | G40: =G39/(G15/1000) -> 0 | H40: =H39/(H9/1000) -> 0 | I40: =I39/(I9/1000) -> 0 | J40: =J39/(J9/1000) -> 0 | K40: =K39/(K9/1000) -> 0 | L40: =L39/(L9/1000) -> 0 | M40: =M39/(M9/1000) -> 0 | N40: =N39/(N9/1000) -> 0 | O40: 0 | P40: =P39/(P9/1000) -> 0
A41: Cost of Chemicals | C41: Mk | D41: =(D29*$B29)+(D31*$B31)+(D33*$B33)+(D35*$B35)+(D37*$B37)+(D39*$B39) -> 21151.74 | E41: =(E29*$B29)+(E31*$B31)+(E33*$B33)+(E35*$B35)+(E37*$B37)+(E39*$B39) -> 24677.03 | F41: =(F29*$B29)+(F31*$B31)+(F33*$B33)+(F35*$B35)+(F37*$B37)+(F39*$B39) -> 26439.675 | G41: =(G29*$B29)+(G31*$B31)+(G33*$B33)+(G35*$B35)+(G37*$B37)+(G39*$B39) -> 28554.849 | H41: =(H29*$B29)+(H31*$B31)+(H33*$B33)+(H35*$B35)+(H37*$B37)+(H39*$B39) -> 28202.32 | I41: =(I29*$B29)+(I31*$B31)+(I33*$B33)+(I35*$B35)+(I37*$B37)+(I39*$B39) -> 25382.088 | J41: =(J29*$B29)+(J31*$B31)+(J33*$B33)+(J35*$B35)+(J37*$B37)+(J39*$B39) -> 24677.03 | K41: =(K29*$B29)+(K31*$B31)+(K33*$B33)+(K35*$B35)+(K37*$B37)+(K39*$B39) -> 23971.972 | ... N41: =(N29*$B29)+(N31*$B31)+(N33*$B33)+(N35*$B35)+(N37*$B37)+(N39*$B39) -> 24677.03 | O41: 21151.74 | P41: =SUM(D41:O41) -> 293656.66
A42: Cost/vol. Produced (chemicals) | C42: Mk/m3 | D42: =D41/D9 -> 7.7393853 | E42: =E41/E9 -> 7.6399474 | F42: =F41/F9 -> 7.4604049 | G42: =G41/G9 -> 7.7869782 | H42: =H41/H9 -> 7.9938549 | I42: =I41/I9 -> 6.7775936 | J42: =J41/J9 -> 5.3080297 | K42: =K41/K9 -> 5.500682 | ... N42: =N41/N9 -> 6.0945987 | O42: 7.0458827 | P42: =P41/P9 -> 6.612995
A43: Power
A44: Power Usage | C44: Kw | D44: 704 | E44: 759 | F44: 1032 | G44: 1052 | H44: 1070 | I44: 1034 | J44: 1394 | K44: 1245 | L44: 1299 | M44: 1200 | N44: 1055 | O44: 1131 | P44: =SUM(D44:O44) -> 12975
A45: Power/ Vol. Produced | C45: Kw/m3 | D45: =D44/D9 -> 0.25759239 | E45: =E44/E9 -> 0.23498452 | F45: =F44/F9 -> 0.29119639 | G45: =G44/G9 -> 0.28688301 | H45: =H44/H9 -> 0.30328798 | I45: =I44/I9 -> 0.27610147 | J45: =J44/J9 -> 0.29984943 | K45: =K44/K9 -> 0.28568151 | ... N45: =N44/N9 -> 0.26055816 | O45: 0.37674883 | P45: =P44/P9 -> 0.29219024
A46: Cost of Power | C46: Mk | D46: =151.1*D44 -> 106374.4 | E46: =151.1*E44 -> 114684.9 | F46: =151.1*F44 -> 155935.2 | G46: =151.1*G44 -> 158957.2 | H46: =151.1*H44 -> 161677 | I46: =151.1*I44 -> 156237.4 | J46: =1.165*(14100+(J44*119.1)) -> 209846.09 | K46: =1.165*(14100+(K44*119.1)) -> 189172.12 | L46: =1.165*(14100+(L44*119.1)) -> 196664.7 | M46: =1.165*(14100+(M44*119.1)) -> 182928.3 | N46: =1.165*(14100+(N44*119.1)) -> 162809.33 | O46: 173354.45 | P46: =SUM(D46:O46) -> 1968641.1
A47: Cost/vol. Produced | C47: Mk/m3 | D47: =D46/D9 -> 38.92221 | E47: =E46/E9 -> 35.506161 | F47: =F46/F9 -> 43.999774 | G47: =G46/G9 -> 43.348023 | H47: =H46/H9 -> 45.826814 | I47: =I46/I9 -> 41.718932 | J47: =J46/J9 -> 45.137899 | K47: =K46/K9 -> 43.408012 | ... N47: =N46/N9 -> 40.209764 | O47: 57.746318 | P47: =P46/P9 -> 44.332772
A48: Plant and Vehicle Maintenance
A49: Distances covered | C49: km | D49: 535 | E49: 120 | P49: =SUM(D49:O49) -> 655
A50: Fuel Used (litres) | C50: litres | D50: 40 | E50: 10 | P50: =SUM(D50:O50) -> 50
A51: Cost of fuel | C51: Mk | D51: =D50*1920 -> 76800 | E51: =E50*1920 -> 19200 | F51: =F50*1920 -> 0 | G51: =G50*1920 -> 0 | P51: =SUM(D51:O51) -> 96000
A52: Maintenance | C52: Mk | H52: 0 | I52: 0 | J52: 0 | K52: 0 | L52: 0 | M52: 0 | N52: 0 | O52: 0 | P52: =SUM(D52:O52) -> 0
A53: Salaries and Wages
A54: Staff Costs | C54: MK | D54: 1438152.8 | E54: 1438152.8 | F54: 1438152.8 | G54: 1438152.8 | H54: 1438152.8 | I54: 1438152.8 | J54: 1438152.8 | K54: 1438152.8 | P54: =SUM(D54:O54) -> 11505222
A55: Wages | C55: MK | P55: =SUM(D55:O55) -> 0
A56: Other Overhead Costs | C56: MK | P56: =SUM(D56:O56) -> 0
A57: Operating Costs
A58: Total Operating Costs | C58: MK | D58: =D41+D46+D51+D52+D54+D55+D56 -> 1642478.9 | E58: =E41+E46+E51+E52+E54+E55+E56 -> 1596714.7 | F58: =F41+F46+F51+F52+F54+F55+F56 -> 1620527.7 | G58: =G41+G46+G51+G52+G54+G55+G56 -> 1625664.9 | H58: =H41+H46+H51+H52+H54+H55+H56 -> 1628032.1 | I58: 181619.49 | J58: =J41+J46+J51+J52+J54+J55+J56 -> 1672675.9 | K58: =K41+K46+K51+K52+K54+K55+K56 -> 1651296.9 | L58: =L41+L46+L51+L52+L54+L55+L56 -> 220284.14 | M58: =M41+M46+M51+M52+M54+M55+M56 -> 204080.04 | N58: =N41+N46+N51+N52+N54+N55+N56 -> 187486.36 | O58: 194506.19 | P58: =SUM(D58:O58) -> 12425367
A59: Cost/Vol. Produced | C59: Mk/m3 | D59: =D58/D9 -> 600.98022 | E59: =E58/E9 -> 494.33893 | F59: =F58/F9 -> 457.2595 | G59: =G58/G9 -> 443.32284 | H59: =H58/H9 -> 461.46035 | I59: 48.496526 | J59: =J58/J9 -> 359.79263 | K59: =K58/K9 -> 378.91163 | L59: =L58/L9 -> 55.153766 | M59: =M58/M9 -> 52.234461 | N59: =N58/N9 -> 46.304362 | O59: 64.792201 | P59: =P58/P9 -> 279.8128
A60: Cost/Vol. Billed | C60: Mk/m3 | D60: =D58/D22 -> 738.52471 | E60: =E58/E22 -> 634.87663 | F60: =F58/F22 -> 538.34552 | G60: =G58/G22 -> 516.08408 | H60: =H58/H22 -> 613.88843 | I60: 51.696313 | J60: =J58/J22 -> 414.58284 | K60: =K58/K22 -> 455.40455 | L60: =L58/L22 -> 67.654835 | M60: =M58/M22 -> 69.041591 | N60: =N58/N22 -> 55.273102 | O60: 69.436737 | P60: =P58/P22 -> 334.64406
A61: Permanent Staff Employed | C61: No | D61: 8 | E61: 8 | F61: 8 | G61: 8 | H61: 8 | I61: 8 | J61: 8 | K61: 8 | L61: 8 | M61: 8 | N61: 7 | O61: 7 | P61: =O61 -> 7
A62: Staff/Vol.1000m3 of Volume Produced/hour (12 hour day) | C62: No/1000m3 | D62: =(D61*1000*31)/D9 -> 90.742774 | E62: =(E61*1000*31)/E9 -> 76.780186 | F62: =(F61*1000*31)/F9 -> 69.977427 | G62: =(G61*1000*31)/G9 -> 67.630215 | H62: =(H61*1000*31)/H9 -> 70.294785 | I62: =(I61*1000*31)/I9 -> 66.221629 | J62: =(J61*1000*31)/J9 -> 53.344805 | K62: =(K61*1000*31)/K9 -> 56.906838 | ... N62: =(N61*1000*31)/N9 -> 53.59348 | O62: 72.285143 | P62: =(P61*1000*31)/P9 -> 4.886727
A63: Temporary Staff Employed | C63: No | K63: 2 | L63: 2 | M63: 2 | N63: 2 | O63: 2 | P63: =SUM(D63:O63) -> 10
A65: Water Connections and Disconnections
A66: New Individual Water Connections | B66: Brought Forward | C66: No | D66: 4 | E66: =D71 -> 6 | F66: =E71 -> 6 | G66: =F71 -> 53 | H66: =G71 -> 214 | I66: =H71 -> 234 | J66: =I71 -> 229 | K66: =J71 -> 225 | L66: 221 | M66: 234 | N66: 230 | O66: 234 | P66: =D66 -> 4
B67: Applied this Month | C67: No | D67: 8 | E67: 4 | F67: 59 | G67: 189 | H67: 48 | I67: 15 | J67: 9 | K67: 9 | L67: 30 | M67: 6 | N67: 10 | O67: 2 | P67: =SUM(D67:O67) -> 389
B68: Done this Month Postpaid | C68: No | D68: 6 | E68: 4 | F68: 12 | G68: 28 | H68: 28 | I68: 20 | J68: 13 | K68: 13 | L68: 17 | M68: 10 | N68: 6 | O68: 3 | P68: =SUM(D68:O68) -> 160
B69: Done this Month Prepaid | C69: No | P69: =SUM(D69:O69) -> 0
B70: Total Done | C70: No | D70: =D68+D69 -> 6 | E70: =E68+E69 -> 4 | F70: =F68+F69 -> 12 | G70: =G68+G69 -> 28 | H70: 28 | I70: =I68+I69 -> 20 | J70: =J68+J69 -> 13 | K70: =K68+K69 -> 13 | L70: 17 | M70: 10 | N70: 6 | O70: 3 | P70: =P68+P69 -> 160
B71: Carried Forward | C71: No | D71: =D66+D67-D70 -> 6 | E71: =E66+E67-E70 -> 6 | F71: =F66+F67-F70 -> 53 | G71: =G66+G67-G70 -> 214 | H71: =H66+H67-H70 -> 234 | I71: =I66+I67-I70 -> 229 | J71: =J66+J67-J70 -> 225 | K71: =K66+K67-K70 -> 221 | L71: 234 | M71: 230 | N71: 234 | O71: 233 | P71: =P66+P67-P70 -> 233
A72: New Institutional Water Connections | B72: Brought Forward | C72: No | E72: =D77 -> 0 | F72: =E77 -> 0 | G72: =F77 -> 0 | P72: =D72 -> 0
B73: Applied this Month | C73: No | P73: =SUM(D73:O73) -> 0
B74: Done this Month Postpaid | C74: No | P74: =SUM(D74:O74) -> 0
B75: Done this Month Prepaid | C75: No | P75: =SUM(D75:O75) -> 0
B76: Total Done | C76: No | D76: =D74+D75 -> 0 | E76: =E74+E75 -> 0 | F76: =F74+F75 -> 0 | G76: =G74+G75 -> 0 | H76: =H74+H75 -> 0 | I76: =I74+I75 -> 0 | J76: =J74+J75 -> 0 | K76: =K74+K75 -> 0 | ... N76: =N74+N75 -> 0 | O76: 0 | P76: =P74+P75 -> 0
B77: Carried Forward | C77: No | D77: =D72+D73-D76 -> 0 | E77: =E72+E73-E76 -> 0 | F77: =F72+F73-F76 -> 0 | G77: =G72+G73-G76 -> 0 | H77: =H72+H73-H76 -> 0 | I77: =I72+I73-I76 -> 0 | J77: =J72+J73-J76 -> 0 | K77: =K72+K73-K76 -> 0 | ... N77: =N72+N73-N76 -> 0 | O77: 0 | P77: =P72+P73-P76 -> 0
A78: New Commercial/Industrial Water Connections | B78: Brought Forward | C78: No | E78: =D83 -> 0 | F78: =E83 -> 0 | G78: =F83 -> 0 | P78: =D78 -> 0
B79: Applied this Month | C79: No | P79: =SUM(D79:O79) -> 0
B80: Done this Month Postpaid | C80: No | P80: =SUM(D80:O80) -> 0
B81: Done this Month Prepaid | C81: No | P81: =SUM(D81:O81) -> 0
B82: Total Done | C82: No | D82: =D80+D81 -> 0 | E82: =E80+E81 -> 0 | F82: =F80+F81 -> 0 | G82: =G80+G81 -> 0 | H82: =H81+H80 -> 0 | I82: =I81+I80 -> 0 | J82: =J81+J80 -> 0 | K82: =K81+K80 -> 0 | L82: =L81+L80 -> 0 | M82: =M81+M80 -> 0 | N82: =N81+N80 -> 0 | O82: 0 | P82: =P81+P80 -> 0
B83: Carried Forward | C83: No | D83: =D78+D79-D82 -> 0 | E83: =E78+E79-E82 -> 0 | F83: =F78+F79-F82 -> 0 | G83: =G78+G79-G82 -> 0 | H83: =H78+H79-H82 -> 0 | I83: =I78+I79-I82 -> 0 | J83: =J78+J79-J82 -> 0 | K83: =K78+K79-K82 -> 0 | ... N83: =N78+N79-N82 -> 0 | O83: 0 | P83: =P78+P79-P82 -> 0
A84: New CWP | B84: Brought Forward | C84: No | E84: =D89 -> 0 | F84: =E89 -> 0 | G84: =F89 -> 0 | P84: =D84 -> 0
B85: Applied this Month | C85: No | P85: =SUM(D85:O85) -> 0
B86: Done this Month Postpaid | C86: No | P86: =SUM(D86:O86) -> 0
B87: Done this Month Prepaid | C87: No | P87: =SUM(D87:O87) -> 0
B88: Total Done | C88: No | D88: =D86+D87 -> 0 | E88: =E86+E87 -> 0 | F88: =F86+F87 -> 0 | G88: =G86+G87 -> 0 | H88: =H87+H86 -> 0 | I88: =I87+I86 -> 0 | J88: =J87+J86 -> 0 | K88: =K87+K86 -> 0 | L88: =L87+L86 -> 0 | M88: =M87+M86 -> 0 | N88: =N87+N86 -> 0 | O88: 0 | P88: =SUM(D88:O88) -> 0
B89: Carried Forward | C89: No | D89: =D84+D85-D88 -> 0 | E89: =E84+E85-E88 -> 0 | F89: =F84+F85-F88 -> 0 | G89: =G84+G85-G88 -> 0 | H89: =H84+H85-H88 -> 0 | I89: =I84+I85-I88 -> 0 | J89: =J84+J85-J88 -> 0 | K89: =K84+K85-K88 -> 0 | ... N89: =N84+N85-N88 -> 0 | O89: 0 | P89: =P84+P85-P88 -> 0
A90: Aggregated New Water connections | B90: Brought Forward | C90: No | D90: =D66+D72+D78+D84 -> 4 | E90: =E66+E72+E78+E84 -> 6 | F90: =F66+F72+F78+F84 -> 6 | G90: =G66+G72+G78+G84 -> 53 | H90: =H66+H72+H78+H84 -> 214 | I90: =I66+I72+I78+I84 -> 234 | J90: =J66+J72+J78+J84 -> 229 | K90: =K66+K72+K78+K84 -> 225 | ... N90: =N66+N72+N78+N84 -> 230 | O90: 234 | P90: =D90 -> 4
B91: Applied this Month | C91: No | D91: =D67+D73+D79+D85 -> 8 | E91: =E67+E73+E79+E85 -> 4 | F91: =F67+F73+F79+F85 -> 59 | G91: =G67+G73+G79+G85 -> 189 | H91: =H67+H73+H79+H85 -> 48 | I91: =I67+I73+I79+I85 -> 15 | J91: =J67+J73+J79+J85 -> 9 | K91: =K67+K73+K79+K85 -> 9 | ... N91: =N67+N73+N79+N85 -> 10 | O91: 2 | P91: =SUM(D91:O91) -> 389
B92: Done this Month Postpaid | C92: No | D92: =D68+D74+D80+D86 -> 6 | E92: =E68+E74+E80+E86 -> 4 | F92: =F68+F74+F80+F86 -> 12 | G92: =G68+G74+G80+G86 -> 28 | H92: =H68+H74+H80+H86 -> 28 | I92: =I68+I74+I80+I86 -> 20 | J92: =J68+J74+J80+J86 -> 13 | K92: =K68+K74+K80+K86 -> 13 | ... N92: =N68+N74+N80+N86 -> 6 | O92: 3 | P92: =SUM(D92:O92) -> 160
B93: Done this Month Prepaid | D93: =D69+D75+D81+D87 -> 0 | E93: =E69+E75+E81+E87 -> 0 | F93: =F69+F75+F81+F87 -> 0 | G93: =G69+G75+G81+G87 -> 0 | H93: =H69+H75+H81+H87 -> 0 | I93: =I69+I75+I81+I87 -> 0 | J93: =J69+J75+J81+J87 -> 0 | K93: =K69+K75+K81+K87 -> 0 | ... N93: =N69+N75+N81+N87 -> 0 | O93: 0 | P93: =SUM(D93:O93) -> 0
B94: Total Done | C94: No | D94: =D70+D76+D82+D88 -> 6 | E94: =E70+E76+E82+E88 -> 4 | F94: =F70+F76+F82+F88 -> 12 | G94: =G70+G76+G82+G88 -> 28 | H94: =H93+H92 -> 28 | I94: =I93+I92 -> 20 | J94: =J93+J92 -> 13 | K94: =K93+K92 -> 13 | L94: =L93+L92 -> 17 | M94: =M93+M92 -> 10 | N94: =N93+N92 -> 6 | O94: 3 | P94: =P93+P92 -> 160
B95: Carried Forward | C95: No | D95: =D71+D77+D83+D89 -> 6 | E95: =E71+E77+E83+E89 -> 6 | F95: =F71+F77+F83+F89 -> 53 | G95: =G71+G77+G83+G89 -> 214 | H95: =H90+H91-H94 -> 234 | I95: =I90+I91-I94 -> 229 | J95: =J90+J91-J94 -> 225 | K95: =K90+K91-K94 -> 221 | L95: =L90+L91-L94 -> 234 | M95: =M90+M91-M94 -> 230 | N95: =N90+N91-N94 -> 234 | O95: 233 | P95: =P90+P91-P94 -> 233
A97: Prepaid Metering
A98: Prepaid Meters Installed | C98: No | P98: =SUM(D98:O98) -> 0
A100: Active and Disconnected Accounts
A101: Disconnected Individual Accounts | C101: No | P101: =O101 -> 0
A102: Disconnected institutional Accounts | C102: No | P102: =O102 -> 0
A103: Disconnected Commercial/Industrial Accounts | C103: No | P103: =O103 -> 0
A104: Disconnected CWP | C104: No | P104: =O104 -> 0
A105: Total Disconnected Accounts | C105: No | D105: =SUM(D101:D104) -> 0 | E105: =SUM(E101:E104) -> 0 | F105: =SUM(F101:F104) -> 0 | G105: =SUM(G101:G104) -> 0 | H105: =SUM(H101:H104) -> 0 | I105: =SUM(I101:I104) -> 0 | J105: =SUM(J101:J104) -> 0 | K105: =SUM(K101:K104) -> 0 | ... N105: =SUM(N101:N104) -> 0 | O105: 0 | P105: =O105 -> 0
A106: Postpaid Consumers
...

Sheet Nsanje
A1: SOUTHERN REGION WATER BOARD
A3: MONTHLY REPORTS - 2023/2024
A4: NGABU ZONE
A5: NGABU ZONE
A7: PARAMETERS | C7: UNITS | D7: APRIL | E7: MAY | F7: JUNE | G7: JULY | H7: AUGUST | I7: SEPTEMBER | J7: OCTOBER | K7: NOVEMBER | L7: DECEMBER | M7: JANUARY | N7: FEBRUARY | O7: MARCH | P7: TOTALS
A8: PRODUCTION
A9: Volume Produced | C9: m3 | D9: 18570 | E9: 20529 | F9: 20853 | G9: 18219 | H9: 20280 | I9: 22536 | J9: 25036 | K9: 23371 | L9: 23363 | M9: 24108 | N9: 24662 | O9: 22838 | P9: =SUM(D9:O9) -> 264365
A10: REVENUE WATER - POSTPAID
A11: Volume Billed Individuals | C11: m3 | D11: =237+797+6208 -> 7242 | E11: =305+903+7326 -> 8534 | F11: =340+931+7700 -> 8971 | G11: =294+873+6753 -> 7920 | H11: =348+885+6990 -> 8223 | I11: =389+1057+8181 -> 9627 | J11: =449+1142+9131 -> 10722 | K11: =434+1101+8488 -> 10023 | L11: 10011 | M11: 10047 | N11: 10619 | O11: 9398 | P11: =SUM(D11:O11) -> 111337
A12: Volume Billed CWPs | C12: m3 | D12: 773 | E12: 806 | F12: 680 | G12: 518 | H12: 824 | I12: 733 | J12: 858 | K12: 794 | L12: 814 | M12: 757 | N12: 756 | O12: 672 | P12: =SUM(D12:O12) -> 8985
A13: Volume Billed Institutions | C13: m3 | D13: 94 | E13: 102 | F13: 133 | G13: 126 | H13: 161 | I13: 210 | J13: 68 | K13: 91 | L13: 91 | M13: 133 | N13: 133 | O13: 114 | P13: =SUM(D13:O13) -> 1456
A14: Volume Billed Commercial/Industrial | C14: m3 | D14: 6 | E14: 7 | F14: 8 | G14: 49 | H14: 162 | I14: 196 | J14: 211 | K14: 146 | L14: 5 | M14: 6 | N14: 123 | O14: 90 | P14: =SUM(D14:O14) -> 1009
A15: Total Volume Billed Post Paid | C15: m3 | D15: =SUM(D11:D14) -> 8115 | E15: =SUM(E11:E14) -> 9449 | F15: =SUM(F11:F14) -> 9792 | G15: =SUM(G11:G14) -> 8613 | H15: =SUM(H11:H14) -> 9370 | I15: =SUM(I11:I14) -> 10766 | J15: =SUM(J11:J14) -> 11859 | K15: =SUM(K11:K14) -> 11054 | ... N15: =SUM(N11:N14) -> 11631 | O15: 10274 | P15: =SUM(P11:P14) -> 122787
A16: REVENUE WATER - PREPAID
A17: Individuals | C17: m3 | F17: 4491 | G17: 3872 | I17: 4589 | J17: 5441 | K17: 4990 | L17: 4826 | M17: 5046 | N17: 4913 | O17: 4595 | P17: =SUM(D17:O17) -> 42763
A18: CWPs | C18: m3 | P18: =SUM(D18:O18) -> 0
A19: Institutions | C19: m3 | D19: 6199 | E19: 5929 | F19: 834 | G19: 723 | H19: 5688.3 | I19: 883 | J19: 889 | K19: 880 | L19: 1093 | M19: 1476 | N19: 1902 | O19: 1918 | P19: =SUM(D19:O19) -> 28414.3
A20: Commercial/Industrial | C20: m3 | F20: 529 | G20: 339 | I20: 554 | J20: 442 | K20: 331 | L20: 556 | M20: 415 | N20: 515 | O20: 270 | P20: =SUM(D20:O20) -> 3951
A21: Total Volume Prepaid | C21: m3 | D21: =SUM(D17:D20) -> 6199 | E21: =SUM(E17:E20) -> 5929 | F21: =SUM(F17:F20) -> 5854 | G21: =SUM(G17:G20) -> 4934 | H21: =SUM(H17:H20) -> 5688.3 | I21: =SUM(I17:I20) -> 6026 | J21: =SUM(J17:J20) -> 6772 | K21: =SUM(K17:K20) -> 6201 | ... N21: =SUM(N17:N20) -> 7330 | O21: 6783 | P21: =SUM(P17:P20) -> 75128.3
A22: TOTAL REVENUE WATER | C22: m3 | D22: =D21+D15 -> 14314 | E22: =E21+E15 -> 15378 | F22: =F21+F15 -> 15646 | G22: =G21+G15 -> 13547 | H22: =H21+H15 -> 15058.3 | I22: =I21+I15 -> 16792 | J22: =J21+J15 -> 18631 | K22: =K21+K15 -> 17255 | ... N22: =N21+N15 -> 18961 | O22: 17057 | P22: =P21+P15 -> 197915.3
A24: Non-Revenue Water (NRW) | B24: Volume | C24: m3 | D24: =D9-D22 -> 4256 | E24: =E9-E22 -> 5151 | F24: =F9-F22 -> 5207 | G24: =G9-G22 -> 4672 | H24: =H9-H22 -> 5221.7 | I24: =I9-I22 -> 5744 | J24: =J9-J22 -> 6405 | K24: =K9-K22 -> 6116 | ... N24: =N9-N22 -> 5701 | O24: 5781 | P24: =P9-P22 -> 66449.7
B25: Percentage | C25: % | D25: =D24/D9 -> 0.22918686 | E25: =E24/E9 -> 0.25091334 | F25: =F24/F9 -> 0.24970028 | G25: =G24/G9 -> 0.25643559 | H25: =H24/H9 -> 0.25748028 | I25: =I24/I9 -> 0.25488108 | J25: =J24/J9 -> 0.2558316 | K25: =K24/K9 -> 0.26169184 | ... N25: =N24/N9 -> 0.23116536 | O25: 0.25313075 | P25: =P24/P9 -> 0.25135589
A26: OPERATING EXPENSES
A27: Chemicals
A28: Chemical | B28: Rate(MK/kg)
A29: Chlorine | B29: 3525.29 | C29: kg | D29: 8.5 | E29: 11 | F29: 10.5 | G29: 12.25 | H29: 11.5 | I29: 13.75 | J29: 11.5 | K29: 11.25 | L29: 10 | M29: 15 | N29: 16 | O29: 18 | P29: =SUM(D29:O29) -> 149.25
C30: kg/mg litre | D30: =D29/(D9/1000) -> 0.45772752 | E30: =E29/(E9/1000) -> 0.53582737 | F30: =F29/(F9/1000) -> 0.50352467 | G30: =G29/(G9/1000) -> 0.67237499 | H30: =H29/(H9/1000) -> 0.56706114 | I30: =I29/(I9/1000) -> 0.6101349 | J30: =J29/(J9/1000) -> 0.45933855 | K30: =K29/(K9/1000) -> 0.4813658 | ... N30: =N29/(N9/1000) -> 0.64877139 | O30: 0.78816008 | P30: =P29/(P9/1000) -> 0.56456036
A31: Aluminium sulphate | C31: kg | P31: =SUM(D31:O31) -> 0
B32: 1060.01 | C32: kg/mg litre | D32: =D31/(D11/1000) -> 0 | E32: =E31/(E11/1000) -> 0 | F32: =F31/(F11/1000) -> 0 | G32: =G31/(G11/1000) -> 0 | H32: =H31/(H9/1000) -> 0 | I32: =I31/(I9/1000) -> 0 | J32: =J31/(J9/1000) -> 0 | K32: =K31/(K9/1000) -> 0 | L32: =L31/(L9/1000) -> 0 | M32: =M31/(M9/1000) -> 0 | N32: =N31/(N9/1000) -> 0 | O32: 0 | P32: =P31/(P9/1000) -> 0
A33: Soda | C33: kg | P33: =SUM(D33:O33) -> 0
B34: 1228.29 | C34: kg/mg litre | D34: =D33/(D9/1000) -> 0 | E34: =E33/(E9/1000) -> 0 | F34: =F33/(F9/1000) -> 0 | G34: =G33/(G9/1000) -> 0 | H34: =H33/(H9/1000) -> 0 | I34: =I33/(I9/1000) -> 0 | J34: =J33/(J9/1000) -> 0 | K34: =K33/(K9/1000) -> 0 | ... N34: =N33/(N9/1000) -> 0 | O34: 0 | P34: =P33/(P9/1000) -> 0
A35: Algae floc | C35: litres
B36: 3726.73 | C36: litres/mg litre
A37: Sud floc | C37: litres | H37: 0 | I37: 0 | J37: 0 | K37: 0 | L37: 0 | M37: 0 | N37: 0 | O37: 0 | P37: =SUM(D37:O37) -> 0
B38: 3951.59 | C38: litres/mg litre | D38: =D37/(D9/1000) -> 0 | E38: =E37/(E9/1000) -> 0 | F38: =F37/(F9/1000) -> 0 | G38: =G37/(G9/1000) -> 0 | H38: =H37/(H9/1000) -> 0 | I38: =I37/(I9/1000) -> 0 | J38: =J37/(J9/1000) -> 0 | K38: =K37/(K9/1000) -> 0 | ... N38: =N37/(N9/1000) -> 0 | O38: 0 | P38: =P37/(P9/1000) -> 0
A39: Potasium permanganate | C39: kg | H39: 0 | I39: 0 | J39: 0 | K39: 0 | L39: 0 | M39: 0 | N39: 0 | O39: 0 | P39: =SUM(D39:O39) -> 0
B40: 1950 | C40: kg/mg litre | D40: =D39/(D9/1000) -> 0 | E40: =E39/(E9/1000) -> 0 | F40: =F39/(F9/1000) -> 0 | G40: =G39/(G9/1000) -> 0 | H40: =H39/(H9/1000) -> 0 | I40: =I39/(I9/1000) -> 0 | J40: =J39/(J9/1000) -> 0 | K40: =K39/(K9/1000) -> 0 | ... N40: =N39/(N9/1000) -> 0 | O40: 0 | P40: =P39/(P9/1000) -> 0
A41: Cost of Chemicals | C41: Mk | D41: =(D29*$B29)+(D31*$B31)+(D33*$B33)+(D35*$B35)+(D37*$B37)+(D39*$B39) -> 29964.965 | E41: =(E29*$B29)+(E31*$B31)+(E33*$B33)+(E35*$B35)+(E37*$B37)+(E39*$B39) -> 38778.19 | F41: =(F29*$B29)+(F31*$B31)+(F33*$B33)+(F35*$B35)+(F37*$B37)+(F39*$B39) -> 37015.545 | G41: =(G29*$B29)+(G31*$B31)+(G33*$B33)+(G35*$B35)+(G37*$B37)+(G39*$B39) -> 43184.802 | H41: =(H29*$B29)+(H31*$B31)+(H33*$B33)+(H35*$B35)+(H37*$B37)+(H39*$B39) -> 40540.835 | I41: =(I29*$B29)+(I31*$B31)+(I33*$B33)+(I35*$B35)+(I37*$B37)+(I39*$B39) -> 48472.738 | J41: =(J29*$B29)+(J31*$B31)+(J33*$B33)+(J35*$B35)+(J37*$B37)+(J39*$B39) -> 40540.835 | K41: =(K29*$B29)+(K31*$B31)+(K33*$B33)+(K35*$B35)+(K37*$B37)+(K39*$B39) -> 39659.512 | ... N41: =(N29*$B29)+(N31*$B31)+(N33*$B33)+(N35*$B35)+(N37*$B37)+(N39*$B39) -> 56404.64 | O41: 63455.22 | P41: =SUM(D41:O41) -> 526149.53
A42: Cost/vol. Produced (chemicals) | C42: Mk/m3 | D42: =D41/D9 -> 1.6136222 | E42: =E41/E9 -> 1.8889469 | F42: =F41/F9 -> 1.7750705 | G42: =G41/G9 -> 2.3703168 | H42: =H41/H9 -> 1.999055 | I42: =I41/I9 -> 2.1509024 | J42: =J41/J9 -> 1.6193016 | K42: =K41/K9 -> 1.696954 | ... N42: =N41/N9 -> 2.2871073 | O42: 2.7784929 | P42: =P41/P9 -> 1.990239
A43: Power
A44: Power Usage | C44: Kw | D44: 15231 | E44: 17195 | F44: 17583 | G44: 16730 | H44: 15557 | I44: 16222 | J44: 15565 | K44: 15286 | L44: 10491 | M44: 17320 | N44: 12113 | O44: 16615 | P44: =SUM(D44:O44) -> 185908
A45: Power/ Vol. Produced | C45: Kw/m3 | D45: =D44/D9 -> 0.82019386 | E45: =E44/E9 -> 0.8375956 | F45: =F44/F9 -> 0.84318803 | G45: =G44/G9 -> 0.91827213 | H45: =H44/H9 -> 0.76711045 | I45: =I44/I9 -> 0.71982606 | J45: =J44/J9 -> 0.62170475 | K45: =K44/K9 -> 0.65405845 | ... N45: =N44/N9 -> 0.49116049 | O45: 0.72751554 | P45: =P44/P9 -> 0.70322471
A46: Cost of Power | C46: Mk | D46: =151.1*D44 -> 2301404.1 | E46: =151.1*E44 -> 2598164.5 | F46: =151.1*F44 -> 2656791.3 | G46: =151.1*G44 -> 2527903 | H46: =151.1*H44 -> 2350662.7 | I46: =151.1*I44 -> 2451144.2 | J46: =151.1*J44 -> 2351871.5 | K46: =1.165*(14100+(K44*119.1)) -> 2137381.9 | L46: =1.165*(14100+(L44*119.1)) -> 1472068.5 | M46: =1.165*(14100+(M44*119.1)) -> 2419602.5 | N46: =1.165*(14100+(N44*119.1)) -> 1697123.4 | O46: 2321782.7 | P46: =SUM(D46:O46) -> 27285900
A47: Cost/vol. Produced | C47: Mk/m3 | D47: =D46/D9 -> 123.93129 | E47: =E46/E9 -> 126.56069 | F47: =F46/F9 -> 127.40571 | G47: =G46/G9 -> 138.75092 | H47: =H46/H9 -> 115.91039 | I47: =I46/I9 -> 108.76572 | J47: =J46/J9 -> 93.939587 | K47: =K46/K9 -> 91.454449 | ... N47: =N46/N9 -> 68.81532 | O47: 101.66313 | P47: =P46/P9 -> 103.21298
A48: Plant and Vehicle Maintenance
A49: Distances covered | C49: km | D49: 439 | E49: 2469 | F49: 975 | G49: 1733 | H49: 2154 | I49: 1644 | J49: 1313 | K49: 3060 | L49: 1870 | M49: 2531 | N49: 3809 | O49: 2072 | P49: =SUM(D49:O49) -> 24069
A50: Fuel Used (litres) | C50: litres | D50: 55 | E50: 246 | F50: 144 | G50: 183 | H50: 250 | I50: 186 | J50: 169 | K50: 257 | L50: 297 | M50: 312 | N50: 395 | O50: 258 | P50: =SUM(D50:O50) -> 2752
A51: Cost of fuel | C51: Mk | D51: =D50*1920 -> 105600 | E51: =E50*1920 -> 472320 | F51: =F50*1920 -> 276480 | G51: =G50*1920 -> 351360 | H51: =H50*1920 -> 480000 | I51: =I50*1920 -> 357120 | J51: =J50*1920 -> 324480 | K51: =K50*1920 -> 493440 | L51: 570240 | M51: 599040 | N51: =N50*1920 -> 758400 | O51: 495360 | P51: =SUM(D51:O51) -> 5283840
A52: Maintenance | C52: Mk | H52: 0 | I52: 0 | J52: 0 | K52: 0 | L52: 0 | M52: 0 | N52: 0 | O52: 0 | P52: =SUM(D52:O52) -> 0
A53: Salaries and Wages
A54: Staff Costs | C54: MK | D54: 3944673.9 | E54: 3944673.9 | F54: 3944673.9 | G54: 4023431.3 | H54: 4023431.3 | I54: 4460909.2 | J54: 4460909.2 | L54: 2190683 | P54: =SUM(D54:O54) -> 30993386
A55: Wages | C55: MK | D55: 690762.09 | E55: 690762.09 | F55: 690762.09 | G55: 725327.92 | H55: 725327.92 | I55: 730263.07 | J55: 730263.07 | L55: 93.767196 | P55: =SUM(D55:O55) -> 4983562
A56: Other Overhead Costs | C56: MK | L56: 125.93027 | P56: =SUM(D56:O56) -> 125.93027
A57: Operating Costs
A58: Total Operating Costs | C58: MK | D58: =D41+D46+D51+D52+D54+D55+D56 -> 7072405.1 | E58: =E41+E46+E51+E52+E54+E55+E56 -> 7744698.7 | F58: =F41+F46+F51+F52+F54+F55+F56 -> 7605722.9 | G58: =G41+G46+G51+G52+G54+G55+G56 -> 7671207 | H58: =H41+H46+H51+H52+H54+H55+H56 -> 7619962.8 | I58: =I41+I46+I51+I52+I54+I55+I56 -> 8047909.2 | J58: =J41+J46+J51+J52+J54+J55+J56 -> 7908064.6 | K58: =K41+K46+K51+K52+K54+K55+K56 -> 2670481.4 | ... N58: =N41+N46+N51+N52+N54+N55+N56 -> 2511928.1 | O58: 2880597.9 | P58: =SUM(D58:O58) -> 69072964
A59: Cost/Vol. Produced | C59: Mk/m3 | D59: =D58/D9 -> 380.85111 | E59: =E58/E9 -> 377.2565 | F59: =F58/F9 -> 364.73039 | G59: =G58/G9 -> 421.05533 | H59: =H58/H9 -> 375.73781 | I59: =I58/I9 -> 357.11347 | J59: =J58/J9 -> 315.86773 | K59: =K58/K9 -> 114.26475 | ... N59: =N58/N9 -> 101.85419 | O59: 126.13179 | P59: =P58/P9 -> 261.27878
A60: Cost/Vol. Billed | C60: Mk/m3 | D60: =D58/D22 -> 494.09006 | E60: =E58/E22 -> 503.62197 | F60: =F58/F22 -> 486.11293 | G60: =G58/G22 -> 566.26611 | H60: =H58/H22 -> 506.03075 | I60: =I58/I22 -> 479.27044 | J60: =J58/J22 -> 424.45733 | K60: =K58/K22 -> 154.76566 | ... N60: =N58/N22 -> 132.47867 | O60: 168.88069 | P60: =P58/P22 -> 349.00265
A61: Permanent Staff Employed | C61: No | D61: 8 | E61: 8 | F61: 8 | G61: 8 | H61: 8 | I61: 7 | J61: 7 | K61: 7 | L61: 6 | M61: 6 | N61: 8 | O61: 6 | P61: =O61 -> 6
A62: Staff/Vol.1000m3 of Volume Produced/hour (12 hour day) | C62: No/1000m3 | D62: =(D61*1000*31)/D9 -> 13.354873 | E62: =(E61*1000*31)/E9 -> 12.080472 | F62: =(F61*1000*31)/F9 -> 11.892773 | G62: =(G61*1000*31)/G9 -> 13.612163 | H62: =(H61*1000*31)/H9 -> 12.228797 | I62: 6 | J62: =(J61*1000*31)/J9 -> 8.6675188 | K62: =(K61*1000*31)/K9 -> 9.2850113 | L62: =(L61*1000*31)/L9 -> 7.9613063 | M62: =(M61*1000*31)/M9 -> 7.7152812 | N62: =(N61*1000*31)/N9 -> 10.055957 | O62: 8.1443209 | P62: =(P61*1000*31)/P9 -> 0.70357271
A63: Temporary Staff Employed | C63: No | D63: 6 | E63: 6 | F63: 6 | G63: 6 | H63: 6 | I63: 6 | J63: 6 | K63: 6 | L63: 6 | M63: 6 | N63: 6 | O63: 6 | P63: =SUM(D63:O63) -> 72
A65: Water Connections and Disconnections
A66: New Individual Water Connections | B66: Brought Forward | C66: No | D66: 166 | E66: =D71 -> 162 | F66: =E71 -> 162 | G66: =F71 -> 160 | H66: =G71 -> 162 | I66: =H71 -> 162 | J66: 159 | K66: =J71 -> 149 | L66: 145 | M66: 143 | N66: 144 | O66: 134 | P66: =D66 -> 166
B67: Applied this Month | C67: No | D67: 12 | E67: 13 | F67: 15 | G67: 28 | H67: 20 | I67: 13 | J67: 11 | K67: 12 | L67: 8 | M67: 10 | N67: 5 | O67: 17 | P67: =SUM(D67:O67) -> 164
B68: Done this Month Postpaid | C68: No | D68: 16 | E68: 13 | F68: 17 | G68: 26 | H68: 20 | I68: 16 | J68: 21 | K68: 16 | L68: 10 | M68: 9 | N68: 15 | O68: 13 | P68: =SUM(D68:O68) -> 192
B69: Done this Month Prepaid | C69: No | P69: =SUM(D69:O69) -> 0
B70: Total Done | C70: No | D70: =D68+D69 -> 16 | E70: =E68+E69 -> 13 | F70: =F68+F69 -> 17 | G70: =G68+G69 -> 26 | H70: =H68+H69 -> 20 | I70: =I68+I69 -> 16 | J70: =J68+J69 -> 21 | K70: =K68+K69 -> 16 | L70: 10 | M70: 9 | N70: 15 | O70: 13 | P70: =P68+P69 -> 192
B71: Carried Forward | C71: No | D71: =D66+D67-D70 -> 162 | E71: =E66+E67-E70 -> 162 | F71: =F66+F67-F70 -> 160 | G71: =G66+G67-G70 -> 162 | H71: =H66+H67-H70 -> 162 | I71: =I66+I67-I70 -> 159 | J71: =J66+J67-J70 -> 149 | K71: =K66+K67-K70 -> 145 | L71: 143 | M71: =M66+M67-M70 -> 144 | N71: 134 | O71: 138 | P71: =P66+P67-P70 -> 138
A72: New Institutional Water Connections | B72: Brought Forward | C72: No | E72: =D77 -> 0 | F72: =E77 -> 0 | G72: =F77 -> 0 | P72: =D72 -> 0
B73: Applied this Month | C73: No | P73: =SUM(D73:O73) -> 0
B74: Done this Month Postpaid | C74: No | P74: =SUM(D74:O74) -> 0
B75: Done this Month Prepaid | C75: No | P75: =SUM(D75:O75) -> 0
B76: Total Done | C76: No | D76: =D74+D75 -> 0 | E76: =E74+E75 -> 0 | F76: =F74+F75 -> 0 | G76: =G74+G75 -> 0 | H76: =H74+H75 -> 0 | I76: =I74+I75 -> 0 | J76: =J74+J75 -> 0 | K76: =K74+K75 -> 0 | ... N76: =N74+N75 -> 0 | O76: 0 | P76: =SUM(D76:O76) -> 0
B77: Carried Forward | C77: No | D77: =D72+D73-D76 -> 0 | E77: =E72+E73-E76 -> 0 | F77: =F72+F73-F76 -> 0 | G77: =G72+G73-G76 -> 0 | H77: =H72+H73-H76 -> 0 | I77: =I72+I73-I76 -> 0 | J77: =J72+J73-J76 -> 0 | K77: =K72+K73-K76 -> 0 | ... N77: =N72+N73-N76 -> 0 | O77: 0 | P77: =P72+P73-P76 -> 0
A78: New Commercial/Industrial Water Connections | B78: Brought Forward | C78: No | E78: =D83 -> 0 | F78: =E83 -> 0 | G78: =F83 -> 0 | P78: =D78 -> 0
B79: Applied this Month | C79: No | P79: =SUM(D79:O79) -> 0
B80: Done this Month Postpaid | C80: No | P80: =SUM(D80:O80) -> 0
B81: Done this Month Prepaid | C81: No | P81: =SUM(D81:O81) -> 0
B82: Total Done | C82: No | D82: =D80+D81 -> 0 | E82: =E80+E81 -> 0 | F82: =F80+F81 -> 0 | G82: =G80+G81 -> 0 | H82: =H81+H80 -> 0 | I82: =I81+I80 -> 0 | J82: =J81+J80 -> 0 | K82: =K81+K80 -> 0 | L82: =L81+L80 -> 0 | M82: =M81+M80 -> 0 | N82: =N81+N80 -> 0 | O82: 0 | P82: =P81+P80 -> 0
B83: Carried Forward | C83: No | D83: =D78+D79-D82 -> 0 | E83: =E78+E79-E82 -> 0 | F83: =F78+F79-F82 -> 0 | G83: =G78+G79-G82 -> 0 | H83: =H78+H79-H82 -> 0 | I83: =I78+I79-I82 -> 0 | J83: =J78+J79-J82 -> 0 | K83: =K78+K79-K82 -> 0 | ... N83: =N78+N79-N82 -> 0 | O83: 0 | P83: =P78+P79-P82 -> 0
A84: New CWP | B84: Brought Forward | C84: No | E84: =D89 -> 0 | F84: =E89 -> 0 | G84: =F89 -> 0 | P84: =D84 -> 0
B85: Applied this Month | C85: No | P85: =SUM(D85:O85) -> 0
B86: Done this Month Postpaid | C86: No | P86: =SUM(D86:O86) -> 0
B87: Done this Month Prepaid | C87: No | P87: =SUM(D87:O87) -> 0
B88: Total Done | C88: No | D88: =D86+D87 -> 0 | E88: =E86+E87 -> 0 | F88: =F86+F87 -> 0 | G88: =G86+G87 -> 0 | H88: 0 | I88: 0 | J88: 0 | K88: 0 | L88: 0 | M88: 0 | N88: 0 | O88: 0 | P88: =SUM(D88:O88) -> 0
B89: Carried Forward | C89: No | D89: =D84+D85-D88 -> 0 | E89: =E84+E85-E88 -> 0 | F89: =F84+F85-F88 -> 0 | G89: =G84+G85-G88 -> 0 | H89: =H84+H85-H88 -> 0 | I89: =I84+I85-I88 -> 0 | J89: =J84+J85-J88 -> 0 | K89: =K84+K85-K88 -> 0 | ... N89: =N84+N85-N88 -> 0 | O89: 0 | P89: =P84+P85-P88 -> 0
A90: Aggregated New Water connections | B90: Brought Forward | C90: No | D90: =D66+D72+D78+D84 -> 166 | E90: =E66+E72+E78+E84 -> 162 | F90: =F66+F72+F78+F84 -> 162 | G90: =G66+G72+G78+G84 -> 160 | H90: =H66+H72+H78+H84 -> 162 | I90: =I66+I72+I78+I84 -> 162 | J90: =J66+J72+J78+J84 -> 159 | K90: =K66+K72+K78+K84 -> 149 | ... N90: =N66+N72+N78+N84 -> 144 | O90: 134 | P90: =D90 -> 166
B91: Applied this Month | C91: No | D91: =D67+D73+D79+D85 -> 12 | E91: =E67+E73+E79+E85 -> 13 | F91: =F67+F73+F79+F85 -> 15 | G91: =G67+G73+G79+G85 -> 28 | H91: =H67+H73+H79+H85 -> 20 | I91: =I67+I73+I79+I85 -> 13 | J91: =J67+J73+J79+J85 -> 11 | K91: =K67+K73+K79+K85 -> 12 | ... N91: =N67+N73+N79+N85 -> 5 | O91: 17 | P91: =SUM(D91:O91) -> 164
B92: Done this Month Postpaid | C92: No | D92: =D68+D74+D80+D86 -> 16 | E92: =E68+E74+E80+E86 -> 13 | F92: =F68+F74+F80+F86 -> 17 | G92: =G68+G74+G80+G86 -> 26 | H92: =H68+H74+H80+H86 -> 20 | I92: =I68+I74+I80+I86 -> 16 | J92: =J68+J74+J80+J86 -> 21 | K92: =K68+K74+K80+K86 -> 16 | ... N92: =N68+N74+N80+N86 -> 15 | O92: 13 | P92: =SUM(D92:O92) -> 192
B93: Done this Month Prepaid | D93: =D69+D75+D81+D87 -> 0 | E93: =E69+E75+E81+E87 -> 0 | F93: =F69+F75+F81+F87 -> 0 | G93: =G69+G75+G81+G87 -> 0 | H93: =H69+H75+H81+H87 -> 0 | I93: =I69+I75+I81+I87 -> 0 | J93: =J69+J75+J81+J87 -> 0 | K93: =K69+K75+K81+K87 -> 0 | ... N93: =N69+N75+N81+N87 -> 0 | O93: 0 | P93: =SUM(D93:O93) -> 0
B94: Total Done | C94: No | D94: =D70+D76+D82+D88 -> 16 | E94: =E70+E76+E82+E88 -> 13 | F94: =F70+F76+F82+F88 -> 17 | G94: =G70+G76+G82+G88 -> 26 | H94: =H93+H92 -> 20 | I94: =I93+I92 -> 16 | J94: =J93+J92 -> 21 | K94: =K93+K92 -> 16 | L94: =L93+L92 -> 10 | M94: =M93+M92 -> 9 | N94: =N93+N92 -> 15 | O94: 13 | P94: =P93+P92 -> 192
B95: Carried Forward | C95: No | D95: =D71+D77+D83+D89 -> 162 | E95: =E71+E77+E83+E89 -> 162 | F95: =F71+F77+F83+F89 -> 160 | G95: =G71+G77+G83+G89 -> 162 | H95: =H90+H91-H94 -> 162 | I95: =I90+I91-I94 -> 159 | J95: =J90+J91-J94 -> 149 | K95: =K90+K91-K94 -> 145 | L95: =L90+L91-L94 -> 143 | M95: =M90+M91-M94 -> 144 | N95: =N90+N91-N94 -> 134 | O95: 138 | P95: =P90+P91-P94 -> 138
A97: Prepaid Metering
A98: Prepaid Meters Installed | C98: No | P98: =SUM(D98:O98) -> 0
A100: Active and Disconnected Accounts
A101: Disconnected Individual Accounts | C101: No | D101: =435+51 -> 486 | E101: 479 | F101: 495 | G101: 482 | H101: 502 | I101: 487 | J101: 476 | K101: 482 | L101: 480 | M101: 502 | N101: 505 | O101: 515 | P101: =O101 -> 515
A102: Disconnected institutional Accounts | C102: No | D102: 20 | E102: 20 | F102: 20 | G102: 20 | H102: 20 | I102: 20 | J102: 20 | K102: 20 | L102: 20 | M102: 20 | N102: 20 | O102: 20 | P102: =O102 -> 20
A103: Disconnected Commercial/Industrial Accounts | C103: No | D103: 2 | E103: 2 | F103: 2 | G103: 2 | H103: 3 | I103: 3 | J103: 3 | K103: 3 | L103: 3 | M103: 3 | N103: 3 | O103: 3 | P103: =O103 -> 3
A104: Disconnected CWP | C104: No | D104: 24 | E104: 25 | F104: 25 | G104: 25 | H104: 25 | I104: 25 | J104: 25 | K104: 25 | L104: 25 | M104: 25 | N104: 25 | O104: 25 | P104: =O104 -> 25
A105: Total Disconnected Accounts | C105: No | D105: =SUM(D101:D104) -> 532 | E105: =SUM(E101:E104) -> 526 | F105: =SUM(F101:F104) -> 542 | G105: =SUM(G101:G104) -> 529 | H105: =SUM(H101:H104) -> 550 | I105: =SUM(I101:I104) -> 535 | J105: =SUM(J101:J104) -> 524 | K105: =SUM(K101:K104) -> 530 | ... N105: =SUM(N101:N104) -> 553 | O105: 563 | P105: =O105 -> 563
A106: Postpaid Consumers
...

Sheet Ngabu
A1: SOUTHERN REGION WATER BOARD
A3: MONTHLY REPORTS - 2023/2024
A4: NGABU ZONE
A5: NGABU ZONE
A7: PARAMETERS | C7: UNITS | D7: APRIL | E7: MAY | F7: JUNE | G7: JULY | H7: AUGUST | I7: SEPTEMBER | J7: OCTOBER | K7: NOVEMBER | L7: DECEMBER | M7: JANUARY | N7: FEBRUARY | O7: MARCH | P7: TOTALS
A8: PRODUCTION
A9: Volume Produced | C9: m3 | D9: 14129 | E9: 20254 | F9: 22284 | G9: 12150 | H9: 12141 | I9: 12988 | J9: 10612 | K9: 15053 | L9: 12734 | M9: 11668 | N9: 13056 | O9: 12109 | P9: =SUM(D9:O9) -> 169178
A10: REVENUE WATER - POSTPAID
A11: Volume Billed Individuals | C11: m3 | D11: =345+91+4282 -> 4718 | E11: =327+62+4453 -> 4842 | F11: =442+280+6466 -> 7188 | G11: =415+262+5649 -> 6326 | H11: =387+116+4874 -> 5377 | I11: =471+162+5354 -> 5987 | J11: 5422 | K11: =437+203+5921 -> 6561 | L11: 5951 | M11: =396+145+5155 -> 5696 | N11: 6285 | O11: 5843 | P11: =SUM(D11:O11) -> 70196
A12: Volume Billed CWPs | C12: m3 | D12: 902 | E12: 855 | F12: 1100 | G12: 1023 | H12: 1197 | I12: 1023 | J12: 915 | K12: 1371 | L12: 1207 | M12: 982 | N12: 1043 | O12: 895 | P12: =SUM(D12:O12) -> 12513
A13: Volume Billed Institutions | C13: m3 | D13: 93 | E13: 115 | F13: 638 | G13: 257 | H13: 88 | I13: 109 | J13: 156 | K13: 179 | L13: 202 | M13: 138 | N13: 162 | O13: 170 | P13: =SUM(D13:O13) -> 2307
A14: Volume Billed Commercial/Industrial | C14: m3 | D14: 9 | E14: 6 | F14: 60 | G14: 39 | H14: 45 | I14: 70 | J14: 103 | K14: 49 | L14: 67 | M14: 59 | N14: 90 | O14: 74 | P14: =SUM(D14:O14) -> 671
A15: Total Volume Billed Post Paid | C15: m3 | D15: =SUM(D11:D14) -> 5722 | E15: =SUM(E11:E14) -> 5818 | F15: =SUM(F11:F14) -> 8986 | G15: =SUM(G11:G14) -> 7645 | H15: =SUM(H11:H14) -> 6707 | I15: =SUM(I11:I14) -> 7189 | J15: =SUM(J11:J14) -> 6596 | K15: =SUM(K11:K14) -> 8160 | ... N15: =SUM(N11:N14) -> 7580 | O15: 6982 | P15: =SUM(P11:P14) -> 85687
A16: REVENUE WATER - PREPAID
A17: Individuals | C17: m3 | G17: 2164 | I17: 2415 | J17: 2248 | K17: 2900.2 | L17: 1506 | M17: 1375 | N17: 1684 | O17: 1494 | P17: =SUM(D17:O17) -> 15786.2 | Q17: =P17/14458% -> 109.18661
A18: CWPs | C18: m3 | P18: =SUM(D18:O18) -> 0 | Q18: =P18/14458% -> 0
A19: Institutions | C19: m3 | D19: 2868 | E19: 4163 | F19: 2634 | G19: 633 | H19: 4110 | I19: 659 | J19: 671 | K19: 855 | L19: 875 | M19: 582 | N19: 633 | O19: 754 | P19: =SUM(D19:O19) -> 19437 | Q19: =P19/14458% -> 134.43768
A20: Commercial/Industrial | C20: m3 | G20: 154 | I20: 70 | J20: 65 | K20: 103 | L20: 98 | M20: 33 | N20: 43 | O20: 51 | P20: =SUM(D20:O20) -> 617 | Q20: =P20/14458% -> 4.2675335
A21: Total Volume Prepaid | C21: m3 | D21: =SUM(D17:D20) -> 2868 | E21: =SUM(E17:E20) -> 4163 | F21: =SUM(F17:F20) -> 2634 | G21: =SUM(G17:G20) -> 2951 | H21: =SUM(H17:H20) -> 4110 | I21: =SUM(I17:I20) -> 3144 | J21: =SUM(J17:J20) -> 2984 | K21: =SUM(K17:K20) -> 3858.2 | ... N21: =SUM(N17:N20) -> 2360 | O21: 2299 | P21: =SUM(P17:P20) -> 35840.2 | Q21: =P21/14458% -> 247.89182
A22: TOTAL REVENUE WATER | C22: m3 | D22: =D21+D15 -> 8590 | E22: =E21+E15 -> 9981 | F22: =F21+F15 -> 11620 | G22: =G21+G15 -> 10596 | H22: =H21+H15 -> 10817 | I22: =I21+I15 -> 10333 | J22: =J21+J15 -> 9580 | K22: =K21+K15 -> 12018.2 | ... N22: =N21+N15 -> 9940 | O22: 9281 | P22: =P21+P15 -> 121527.2
A24: Non-Revenue Water (NRW) | B24: Volume | C24: m3 | D24: =D9-D22 -> 5539 | E24: =E9-E22 -> 10273 | F24: =F9-F22 -> 10664 | G24: =G9-G22 -> 1554 | H24: =H9-H22 -> 1324 | I24: =I9-I22 -> 2655 | J24: =J9-J22 -> 1032 | K24: =K9-K22 -> 3034.8 | ... N24: =N9-N22 -> 3116 | O24: 2828 | P24: =P9-P22 -> 47650.8
B25: Percentage | C25: % | D25: =D24/D9 -> 0.39203058 | E25: =E24/E9 -> 0.50720845 | F25: =F24/F9 -> 0.47854963 | G25: =G24/G9 -> 0.12790123 | H25: =H24/H9 -> 0.10905197 | I25: =I24/I9 -> 0.20441946 | J25: =J24/J9 -> 0.097248398 | K25: =K24/K9 -> 0.20160765 | ... N25: =N24/N9 -> 0.23866422 | O25: 0.2335453 | P25: =P24/P9 -> 0.28166074
A26: OPERATING EXPENSES
A27: Chemicals
A28: Chemical | B28: Rate(MK/kg)
A29: Chlorine | B29: 3525.29 | C29: kg | D29: 16 | E29: 21 | F29: 21 | G29: 18 | H29: 15 | I29: 18 | J29: 15 | K29: 18 | L29: 18 | M29: 15 | N29: 18 | O29: 15 | P29: =SUM(D29:O29) -> 208
C30: kg/mg litre | D30: =D29/(D9/1000) -> 1.1324227 | E30: =E29/(E9/1000) -> 1.0368322 | F30: =F29/(F9/1000) -> 0.94238018 | G30: =G29/(G9/1000) -> 1.4814815 | H30: =H29/(H9/1000) -> 1.2354831 | I30: =I29/(I9/1000) -> 1.3858947 | J30: =J29/(J9/1000) -> 1.4134942 | K30: =K29/(K9/1000) -> 1.1957749 | L30: 1.4135386 | M30: =M29/(M9/1000) -> 1.2855674 | N30: =N29/(N9/1000) -> 1.3786765 | O30: 1.238748 | P30: =P29/(P9/1000) -> 1.2294743
A31: Aluminium sulphate | C31: kg | P31: =SUM(D31:O31) -> 0
B32: 1060.01 | C32: kg/mg litre | D32: =D31/(D9/1000) -> 0 | E32: =E31/(E9/1000) -> 0 | F32: =F31/(F9/1000) -> 0 | G32: =G31/(G9/1000) -> 0 | H32: =H31/(H9/1000) -> 0 | I32: =I31/(I9/1000) -> 0 | J32: =J31/(J9/1000) -> 0 | K32: =K31/(K9/1000) -> 0 | ... N32: =N31/(N9/1000) -> 0 | O32: 0 | P32: =P31/(P9/1000) -> 0
A33: Soda | C33: kg | P33: =SUM(D33:O33) -> 0
B34: 1228.29 | C34: kg/mg litre | D34: =D33/(D9/1000) -> 0 | E34: =E33/(E9/1000) -> 0 | F34: =F33/(F9/1000) -> 0 | G34: =G33/(G9/1000) -> 0 | H34: =H33/(H9/1000) -> 0 | I34: =I33/(I9/1000) -> 0 | J34: =J33/(J9/1000) -> 0 | K34: =K33/(K9/1000) -> 0 | ... N34: =N33/(N9/1000) -> 0 | O34: 0 | P34: =P33/(P9/1000) -> 0
A35: Algae floc | C35: litres
B36: 3726.73 | C36: litres/mg litre
A37: Sud floc | C37: litres | H37: 0 | I37: 0 | J37: 0 | K37: 0 | L37: 0 | M37: 0 | N37: 0 | O37: 0 | P37: =SUM(D37:O37) -> 0
B38: 3951.59 | C38: litres/mg litre | D38: =D37/(D9/1000) -> 0 | E38: =E37/(E9/1000) -> 0 | F38: =F37/(F9/1000) -> 0 | G38: =G37/(G9/1000) -> 0 | H38: =H37/(H9/1000) -> 0 | I38: =I37/(I9/1000) -> 0 | J38: =J37/(J9/1000) -> 0 | K38: =K37/(K9/1000) -> 0 | ... N38: =N37/(N9/1000) -> 0 | O38: 0 | P38: =P37/(P9/1000) -> 0
A39: Potasium permanganate | C39: kg | H39: 0 | I39: 0 | J39: 0 | K39: 0 | L39: 0 | M39: 0 | N39: 0 | O39: 0 | P39: =SUM(D39:O39) -> 0
B40: 1950 | C40: kg/mg litre | D40: =D39/(D9/1000) -> 0 | E40: =E39/(E9/1000) -> 0 | F40: =F39/(F9/1000) -> 0 | G40: =G39/(G9/1000) -> 0 | H40: =H39/(H9/1000) -> 0 | I40: =I39/(I9/1000) -> 0 | J40: =J39/(J9/1000) -> 0 | K40: =K39/(K9/1000) -> 0 | ... N40: =N39/(N9/1000) -> 0 | O40: 0 | P40: =P39/(P9/1000) -> 0
A41: Cost of Chemicals | C41: Mk | D41: =(D29*$B29)+(D31*$B31)+(D33*$B33)+(D35*$B35)+(D37*$B37)+(D39*$B39) -> 56404.64 | E41: =(E29*$B29)+(E31*$B31)+(E33*$B33)+(E35*$B35)+(E37*$B37)+(E39*$B39) -> 74031.09 | F41: =(F29*$B29)+(F31*$B31)+(F33*$B33)+(F35*$B35)+(F37*$B37)+(F39*$B39) -> 74031.09 | G41: =(G29*$B29)+(G31*$B31)+(G33*$B33)+(G35*$B35)+(G37*$B37)+(G39*$B39) -> 63455.22 | H41: =(H29*$B29)+(H31*$B31)+(H33*$B33)+(H35*$B35)+(H37*$B37)+(H39*$B39) -> 52879.35 | I41: =(I29*$B29)+(I31*$B31)+(I33*$B33)+(I35*$B35)+(I37*$B37)+(I39*$B39) -> 63455.22 | J41: =(J29*$B29)+(J31*$B31)+(J33*$B33)+(J35*$B35)+(J37*$B37)+(J39*$B39) -> 52879.35 | K41: =(K29*$B29)+(K31*$B31)+(K33*$B33)+(K35*$B35)+(K37*$B37)+(K39*$B39) -> 63455.22 | ... N41: =(N29*$B29)+(N31*$B31)+(N33*$B33)+(N35*$B35)+(N37*$B37)+(N39*$B39) -> 63455.22 | O41: 52879.35 | P41: =SUM(D41:O41) -> 733260.32
A42: Cost/vol. Produced (chemicals) | C42: Mk/m3 | D42: =D41/D9 -> 3.9921183 | E42: =E41/E9 -> 3.6551343 | F42: =F41/F9 -> 3.3221634 | G42: =G41/G9 -> 5.2226519 | H42: =H41/H9 -> 4.3554361 | I42: =I41/I9 -> 4.8856806 | J42: =J41/J9 -> 4.9829768 | K42: =K41/K9 -> 4.2154534 | ... N42: =N41/N9 -> 4.8602344 | O42: 4.3669461 | P42: =P41/P9 -> 4.3342534
A43: Power
A44: Power Usage | C44: Kw | D44: 10967 | E44: 7501.99 | F44: 12672 | G44: 12881.19 | H44: 8218.11 | I44: 6074 | J44: 8314 | K44: 10966 | L44: 11703 | M44: 10756.94 | N44: 11143.33 | P44: =SUM(D44:O44) -> 111197.56
A45: Power/ Vol. Produced | C45: Kw/m3 | D45: =D44/D9 -> 0.77620497 | E45: =E44/E9 -> 0.37039548 | F45: =F44/F9 -> 0.56865913 | G45: =G44/G9 -> 1.0601802 | H45: =H44/H9 -> 0.67688905 | I45: =I44/I9 -> 0.46766246 | J45: =J44/J9 -> 0.7834527 | K45: =K44/K9 -> 0.72849266 | L45: 0.91903565 | M45: =M44/M9 -> 0.92191807 | N45: =N44/N9 -> 0.8535026 | O45: 0 | P45: =P44/P9 -> 0.65728144
A46: Cost of Power | C46: Mk | D46: =151.1*D44 -> 1657113.7 | E46: =151.1*E44 -> 1133550.7 | F46: =151.1*F44 -> 1914739.2 | G46: =151.1*G44 -> 1946347.8 | H46: =151.1*H44 -> 1241756.4 | I46: =151.1*I44 -> 917781.4 | J46: =1.165*(14100+(J44*119.1)) -> 1170006.5 | K46: =1.165*(14100+(K44*119.1)) -> 1537975.4 | L46: =1.165*(14100+(L44*119.1)) -> 1640235.3 | M46: =1.165*(14100+(M44*119.1)) -> 1508968.1 | N46: =1.165*(14100+(N44*119.1)) -> 1562580.3 | O46: 16426.5 | P46: =SUM(D46:O46) -> 16247481
A47: Cost/vol. Produced | C47: Mk/m3 | D47: =D46/D9 -> 117.28457 | E47: =E46/E9 -> 55.966757 | F47: =F46/F9 -> 85.924394 | G47: =G46/G9 -> 160.19324 | H47: =H46/H9 -> 102.27794 | I47: =I46/I9 -> 70.663797 | J47: =J46/J9 -> 110.25315 | K47: =K46/K9 -> 102.17069 | ... N47: =N46/N9 -> 119.68292 | O47: 1.356553 | P47: =P46/P9 -> 96.03779
A48: Plant and Vehicle Maintenance
A49: Distances covered | C49: km | D49: 1685 | E49: 1790 | F49: 2653 | G49: 2714 | H49: 386 | I49: 442 | J49: 572 | K49: 621 | P49: =SUM(D49:O49) -> 10863
A50: Fuel Used (litres) | C50: litres | D50: 200 | E50: 250 | F50: 300 | G50: 350 | H50: 76 | I50: 150 | J50: 150 | K50: 200 | P50: =SUM(D50:O50) -> 1676
A51: Cost of fuel | C51: Mk | D51: =D50*1920 -> 384000 | E51: =E50*1920 -> 480000 | F51: =F50*1920 -> 576000 | G51: =G50*1920 -> 672000 | H51: =H50*1920 -> 145920 | I51: =I50*1920 -> 288000 | J51: =J50*1920 -> 288000 | K51: =K50*1920 -> 384000 | P51: =SUM(D51:O51) -> 3217920
A52: Maintenance | C52: Mk | H52: 0 | I52: 0 | J52: 0 | K52: 0 | L52: 0 | M52: 0 | N52: 0 | O52: 0 | P52: =SUM(D52:O52) -> 0
A53: Salaries and Wages
A54: Staff Costs | C54: MK | D54: 1665809.1 | E54: 1665809.1 | F54: 1665809.1 | G54: 1665809.1 | H54: 1665809.1 | I54: 1665809.1 | J54: 1665809.1 | K54: 1665809.1 | P54: =SUM(D54:O54) -> 13326473
A55: Wages | C55: MK | D55: 241154.4 | E55: 241154.4 | F55: 241154.4 | G55: 241154.4 | H55: 241154.4 | I55: 241154.4 | J55: 241154.4 | K55: 241154.4 | P55: =SUM(D55:O55) -> 1929235.2
A56: Other Overhead Costs | C56: MK | P56: =SUM(D56:O56) -> 0
A57: Operating Costs
A58: Total Operating Costs | C58: MK | D58: =D41+D46+D51+D52+D54+D55+D56 -> 4004481.8 | E58: =E41+E46+E51+E52+E54+E55+E56 -> 3594545.2 | F58: =F41+F46+F51+F52+F54+F55+F56 -> 4471733.8 | G58: =G41+G46+G51+G52+G54+G55+G56 -> 4588766.5 | H58: =H41+H46+H51+H52+H54+H55+H56 -> 3347519.2 | I58: =I41+I46+I51+I52+I54+I55+I56 -> 3176200.1 | J58: =J41+J46+J51+J52+J54+J55+J56 -> 3417849.3 | K58: =K41+K46+K51+K52+K54+K55+K56 -> 3892394.1 | ... N58: =N41+N46+N51+N52+N54+N55+N56 -> 1626035.5 | O58: 69305.85 | P58: =SUM(D58:O58) -> 35454369
A59: Cost/Vol. Produced | C59: Mk/m3 | D59: =D58/D9 -> 283.42288 | E59: =E58/E9 -> 177.47335 | F59: =F58/F9 -> 200.67016 | G59: =G58/G9 -> 377.67625 | H59: =H58/H9 -> 275.72022 | I59: =I58/I9 -> 244.54882 | J59: =J58/J9 -> 322.074 | K59: =K58/K9 -> 258.5793 | ... N59: =N58/N9 -> 124.54316 | O59: 5.7234991 | P59: =P58/P9 -> 209.56844
A60: Cost/Vol. Billed | C60: Mk/m3 | D60: =D58/D22 -> 466.17949 | E60: =E58/E22 -> 360.13879 | F60: =F58/F22 -> 384.83079 | G60: =G58/G22 -> 433.06592 | H60: =H58/H22 -> 309.46836 | I60: =I58/I22 -> 307.38412 | J60: =J58/J22 -> 356.76924 | K60: =K58/K22 -> 323.87497 | ... N60: =N58/N22 -> 163.58506 | O60: 7.4674981 | P60: =P58/P22 -> 291.7402
A61: Permanent Staff Employed | C61: No | D61: 7 | E61: 7 | F61: 7 | G61: 7 | H61: 7 | I61: 7 | J61: 7 | K61: 7 | L61: 7 | M61: 7 | N61: 7 | O61: 7 | P61: =O61 -> 7
A62: Staff/Vol.1000m3 of Volume Produced/hour (12 hour day) | C62: No/1000m3 | D62: =(D61*1000*31)/D9 -> 15.358483 | E62: =(E61*1000*31)/E9 -> 10.713933 | F62: =(F61*1000*31)/F9 -> 9.7379286 | G62: =(G61*1000*31)/G9 -> 17.860082 | H62: =(H61*1000*31)/H9 -> 17.873322 | I62: =(I61*1000*31)/I9 -> 16.70773 | J62: =(J61*1000*31)/J9 -> 20.448549 | K62: =(K61*1000*31)/K9 -> 14.415731 | ... N62: =(N61*1000*31)/N9 -> 16.620711 | O62: 17.920555 | P62: =(P61*1000*31)/P9 -> 1.2826727
A63: Temporary Staff Employed | C63: No | D63: 6 | E63: 6 | F63: 6 | G63: 6 | H63: 6 | I63: 6 | J63: 6 | K63: 6 | L63: 6 | M63: 6 | N63: 6 | O63: 6 | P63: =SUM(D63:O63) -> 72
A65: Water Connections and Disconnections
A66: New Individual Water Connections | B66: Brought Forward | C66: No | D66: 134 | E66: =D71 -> 136 | F66: =E71 -> 135 | G66: =F71 -> 124 | H66: =G71 -> 113 | I66: =H71 -> 107 | J66: =I71 -> 86 | K66: =J71 -> 81 | L66: 71 | M66: =L71 -> 64 | N66: 58 | O66: 50 | P66: =D66 -> 134
B67: Applied this Month | C67: No | D67: 9 | E67: 8 | H67: 1 | J67: 5 | K67: 1 | P67: =SUM(D67:O67) -> 24
B68: Done this Month Postpaid | C68: No | D68: 7 | E68: 9 | F68: 11 | G68: 11 | H68: 7 | I68: 2 | J68: 10 | K68: 5 | L68: 4 | M68: 6 | N68: 8 | O68: 7 | P68: =SUM(D68:O68) -> 87
B69: Done this Month Prepaid | C69: No | I69: 19 | K69: 6 | L69: 3 | P69: =SUM(D69:O69) -> 28
B70: Total Done | C70: No | D70: =D68+D69 -> 7 | E70: =E68+E69 -> 9 | F70: =F68+F69 -> 11 | G70: =G68+G69 -> 11 | H70: =H68+H69 -> 7 | I70: =I68+I69 -> 21 | J70: =J68+J69 -> 10 | K70: =K68+K69 -> 11 | L70: 7 | M70: =M68+M69 -> 6 | N70: 8 | O70: 7 | P70: =P68+P69 -> 115
B71: Carried Forward | C71: No | D71: =D66+D67-D70 -> 136 | E71: =E66+E67-E70 -> 135 | F71: =F66+F67-F70 -> 124 | G71: =G66+G67-G70 -> 113 | H71: =H66+H67-H70 -> 107 | I71: =I66+I67-I70 -> 86 | J71: =J66+J67-J70 -> 81 | K71: =K66+K67-K70 -> 71 | L71: 64 | M71: =M66+M67-M70 -> 58 | N71: 50 | O71: 43 | P71: =P66+P67-P70 -> 43
A72: New Institutional Water Connections | B72: Brought Forward | C72: No | E72: =D77 -> 0 | F72: =E77 -> 0 | G72: =F77 -> 0 | P72: =D72 -> 0
B73: Applied this Month | C73: No | P73: =SUM(D73:O73) -> 0
B74: Done this Month Postpaid | C74: No | P74: =SUM(D74:O74) -> 0
B75: Done this Month Prepaid | C75: No | P75: =SUM(D75:O75) -> 0
B76: Total Done | C76: No | D76: =D74+D75 -> 0 | E76: =E74+E75 -> 0 | F76: =F74+F75 -> 0 | G76: =G74+G75 -> 0 | H76: =H74+H75 -> 0 | I76: =I74+I75 -> 0 | J76: =J74+J75 -> 0 | K76: =K74+K75 -> 0 | ... N76: =N74+N75 -> 0 | O76: 0 | P76: =P74+P75 -> 0
B77: Carried Forward | C77: No | D77: =D72+D73-D76 -> 0 | E77: =E72+E73-E76 -> 0 | F77: =F72+F73-F76 -> 0 | G77: =G72+G73-G76 -> 0 | H77: =H72+H73-H76 -> 0 | I77: =I72+I73-I76 -> 0 | J77: =J72+J73-J76 -> 0 | K77: =K72+K73-K76 -> 0 | ... N77: =N72+N73-N76 -> 0 | O77: 0 | P77: =P72+P73-P76 -> 0
A78: New Commercial/Industrial Water Connections | B78: Brought Forward | C78: No | E78: =D83 -> 0 | F78: =E83 -> 0 | G78: =F83 -> 0 | P78: =D78 -> 0
B79: Applied this Month | C79: No | P79: =SUM(D79:O79) -> 0
B80: Done this Month Postpaid | C80: No | P80: =SUM(D80:O80) -> 0
B81: Done this Month Prepaid | C81: No | P81: =SUM(D81:O81) -> 0
B82: Total Done | C82: No | D82: =D80+D81 -> 0 | E82: =E80+E81 -> 0 | F82: =F80+F81 -> 0 | G82: =G80+G81 -> 0 | H82: =H81+H80 -> 0 | I82: =I81+I80 -> 0 | J82: =J81+J80 -> 0 | K82: =K81+K80 -> 0 | L82: =L81+L80 -> 0 | M82: =M81+M80 -> 0 | N82: =N81+N80 -> 0 | O82: 0 | P82: =P81+P80 -> 0
B83: Carried Forward | C83: No | D83: =D78+D79-D82 -> 0 | E83: =E78+E79-E82 -> 0 | F83: =F78+F79-F82 -> 0 | G83: =G78+G79-G82 -> 0 | H83: =H78+H79-H82 -> 0 | I83: =I78+I79-I82 -> 0 | J83: =J78+J79-J82 -> 0 | K83: =K78+K79-K82 -> 0 | ... N83: =N78+N79-N82 -> 0 | O83: 0 | P83: =P78+P79-P82 -> 0
A84: New CWP | B84: Brought Forward | C84: No | E84: =D89 -> 0 | F84: =E89 -> 0 | G84: =F89 -> 0 | P84: =D84 -> 0
B85: Applied this Month | C85: No | P85: =SUM(D85:O85) -> 0
B86: Done this Month Postpaid | C86: No | P86: =SUM(D86:O86) -> 0
B87: Done this Month Prepaid | C87: No | P87: =SUM(D87:O87) -> 0
B88: Total Done | C88: No | D88: =D86+D87 -> 0 | E88: =E86+E87 -> 0 | F88: =F86+F87 -> 0 | G88: =G86+G87 -> 0 | H88: 0 | I88: 0 | J88: 0 | K88: 0 | L88: 0 | M88: 0 | N88: 0 | O88: 0 | P88: =SUM(D88:O88) -> 0
B89: Carried Forward | C89: No | D89: =D84+D85-D88 -> 0 | E89: =E84+E85-E88 -> 0 | F89: =F84+F85-F88 -> 0 | G89: =G84+G85-G88 -> 0 | H89: =H84+H85-H88 -> 0 | I89: =I84+I85-I88 -> 0 | J89: =J84+J85-J88 -> 0 | K89: =K84+K85-K88 -> 0 | ... N89: =N84+N85-N88 -> 0 | O89: 0 | P89: =P84+P85-P88 -> 0
A90: Aggregated New Water connections | B90: Brought Forward | C90: No | D90: =D66+D72+D78+D84 -> 134 | E90: =E66+E72+E78+E84 -> 136 | F90: =F66+F72+F78+F84 -> 135 | G90: =G66+G72+G78+G84 -> 124 | H90: =H66+H72+H78+H84 -> 113 | I90: =I66+I72+I78+I84 -> 107 | J90: =J66+J72+J78+J84 -> 86 | K90: =K66+K72+K78+K84 -> 81 | ... N90: =N66+N72+N78+N84 -> 58 | O90: 50 | P90: =D90 -> 134
B91: Applied this Month | C91: No | D91: =D67+D73+D79+D85 -> 9 | E91: =E67+E73+E79+E85 -> 8 | F91: =F67+F73+F79+F85 -> 0 | G91: =G67+G73+G79+G85 -> 0 | H91: =H67+H73+H79+H85 -> 1 | I91: =I67+I73+I79+I85 -> 0 | J91: =J67+J73+J79+J85 -> 5 | K91: =K67+K73+K79+K85 -> 1 | ... N91: =N67+N73+N79+N85 -> 0 | O91: 0 | P91: =SUM(D91:O91) -> 24
B92: Done this Month Postpaid | C92: No | D92: =D68+D74+D80+D86 -> 7 | E92: =E68+E74+E80+E86 -> 9 | F92: =F68+F74+F80+F86 -> 11 | G92: =G68+G74+G80+G86 -> 11 | H92: =H68+H74+H80+H86 -> 7 | I92: =I68+I74+I80+I86 -> 2 | J92: =J68+J74+J80+J86 -> 10 | K92: =K68+K74+K80+K86 -> 5 | ... N92: =N68+N74+N80+N86 -> 8 | O92: 7 | P92: =SUM(D92:O92) -> 87
B93: Done this Month Prepaid | D93: =D69+D75+D81+D87 -> 0 | E93: =E69+E75+E81+E87 -> 0 | F93: =F69+F75+F81+F87 -> 0 | G93: =G69+G75+G81+G87 -> 0 | H93: =H69+H75+H81+H87 -> 0 | I93: =I69+I75+I81+I87 -> 19 | J93: =J69+J75+J81+J87 -> 0 | K93: =K69+K75+K81+K87 -> 6 | ... N93: =N69+N75+N81+N87 -> 0 | O93: 0 | P93: =SUM(D93:O93) -> 28
B94: Total Done | C94: No | D94: =D70+D76+D82+D88 -> 7 | E94: =E70+E76+E82+E88 -> 9 | F94: =F70+F76+F82+F88 -> 11 | G94: =G70+G76+G82+G88 -> 11 | H94: =H93+H92 -> 7 | I94: =I93+I92 -> 21 | J94: =J93+J92 -> 10 | K94: =K93+K92 -> 11 | L94: =L93+L92 -> 7 | M94: =M93+M92 -> 6 | N94: =N93+N92 -> 8 | O94: 7 | P94: =P93+P92 -> 115
B95: Carried Forward | C95: No | D95: =D71+D77+D83+D89 -> 136 | E95: =E71+E77+E83+E89 -> 135 | F95: =F71+F77+F83+F89 -> 124 | G95: =G71+G77+G83+G89 -> 113 | H95: =H90+H91-H94 -> 107 | I95: =I90+I91-I94 -> 86 | J95: =J90+J91-J94 -> 81 | K95: =K90+K91-K94 -> 71 | L95: =L90+L91-L94 -> 64 | M95: =M90+M91-M94 -> 58 | N95: =N90+N91-N94 -> 50 | O95: 43 | P95: =P90+P91-P94 -> 43
A97: Prepaid Metering
A98: Prepaid Meters Installed | C98: No | D98: 0 | P98: =SUM(D98:O98) -> 0
A100: Active and Disconnected Accounts
A101: Disconnected Individual Accounts | C101: No | D101: =187+262+5 -> 454 | E101: 453 | F101: 487 | G101: 487 | H101: 498 | I101: 511 | J101: 521 | K101: 525 | L101: 598 | M101: 583 | N101: 571 | O101: 558 | P101: =O101 -> 558
A102: Disconnected institutional Accounts | C102: No | D102: 15 | E102: 10 | F102: 10 | G102: 10 | H102: 10 | I102: 10 | J102: 10 | K102: 10 | L102: 10 | M102: 10 | N102: 37 | O102: 42 | P102: =O102 -> 42
A103: Disconnected Commercial/Industrial Accounts | C103: No | D103: 13 | E103: 12 | F103: 12 | G103: 12 | H103: 12 | I103: 12 | J103: 12 | K103: 12 | L103: 12 | M103: 12 | N103: 41 | O103: 56 | P103: =O103 -> 56
A104: Disconnected CWP | C104: No | D104: 16 | E104: 20 | F104: 20 | G104: 20 | H104: 20 | I104: 20 | J104: 20 | K104: 20 | L104: 20 | M104: 19 | N104: 19 | O104: 19 | P104: =O104 -> 19
A105: Total Disconnected Accounts | C105: No | D105: =SUM(D101:D104) -> 498 | E105: =SUM(E101:E104) -> 495 | F105: =SUM(F101:F104) -> 529 | G105: =SUM(G101:G104) -> 529 | H105: =SUM(H101:H104) -> 540 | I105: =SUM(I101:I104) -> 553 | J105: =SUM(J101:J104) -> 563 | K105: =SUM(K101:K104) -> 567 | ... N105: =SUM(N101:N104) -> 668 | O105: 675 | P105: =O105 -> 675
A106: Postpaid Consumers
...

Sheet Zone Monthly
A1: SOUTHERN REGION WATER BOARD
A3: MONTHLY REPORTS - 2023/2024
A4: NGABU ZONE
A5: NGABU ZONE
A7: PARAMETERS | C7: UNITS | D7: APRIL | E7: MAY | F7: JUNE | G7: JULY | H7: AUGUST | I7: SEPTEMBER | J7: OCTOBER | K7: NOVEMBER | L7: DECEMBER | M7: JANUARY | N7: FEBRUARY | O7: MARCH | P7: TOTALS
A8: PRODUCTION
A9: Volume Produced | C9: m3 | D9: =Bangula!D9+Chikwawa!D9+Nchalo!D9+'Miseu Folo'!D9+Nsanje!D9+Ngabu!D9 -> 96447 | E9: =Bangula!E9+Chikwawa!E9+Nchalo!E9+'Miseu Folo'!E9+Nsanje!E9+Ngabu!E9 -> 111131 | F9: =Bangula!F9+Chikwawa!F9+Nchalo!F9+'Miseu Folo'!F9+Nsanje!F9+Ngabu!F9 -> 112105 | G9: =Bangula!G9+Chikwawa!G9+Nchalo!G9+'Miseu Folo'!G9+Nsanje!G9+Ngabu!G9 -> 99943 | H9: =Bangula!H9+Chikwawa!H9+Nchalo!H9+'Miseu Folo'!H9+Nsanje!H9+Ngabu!H9 -> 101009 | I9: =Bangula!I9+Chikwawa!I9+Nchalo!I9+'Miseu Folo'!I9+Nsanje!I9+Ngabu!I9 -> 102088 | J9: =Bangula!J9+Chikwawa!J9+Nchalo!J9+'Miseu Folo'!J9+Nsanje!J9+Ngabu!J9 -> 102932 | K9: =Bangula!K9+Chikwawa!K9+Nchalo!K9+'Miseu Folo'!K9+Nsanje!K9+Ngabu!K9 -> 103528 | ... O9: =Bangula!O9+Chikwawa!O9+Nchalo!O9+'Miseu Folo'!O9+Nsanje!O9+Ngabu!O9 -> 95181 | P9: =SUM(D9:O9) -> 1223357
A10: REVENUE WATER - POSTPAID
A11: Volume Billed Individuals | C11: m3 | D11: =Bangula!D11+Chikwawa!D11+'Miseu Folo'!D11+Nchalo!D11+Nsanje!D11+Ngabu!D11 -> 43319 | E11: =Bangula!E11+Chikwawa!E11+'Miseu Folo'!E11+Nchalo!E11+Nsanje!E11+Ngabu!E11 -> 47839 | F11: =Bangula!F11+Chikwawa!F11+'Miseu Folo'!F11+Nchalo!F11+Nsanje!F11+Ngabu!F11 -> 55229 | G11: =Bangula!G11+Chikwawa!G11+'Miseu Folo'!G11+Nchalo!G11+Nsanje!G11+Ngabu!G11 -> 47697 | H11: =Bangula!H11+Chikwawa!H11+'Miseu Folo'!H11+Nchalo!H11+Nsanje!H11+Ngabu!H11 -> 48503 | I11: =Bangula!I11+Chikwawa!I11+'Miseu Folo'!I11+Nchalo!I11+Nsanje!I11+Ngabu!I11 -> 52836 | J11: =Bangula!J11+Chikwawa!J11+'Miseu Folo'!J11+Nchalo!J11+Nsanje!J11+Ngabu!J11 -> 57587 | K11: =Bangula!K11+Chikwawa!K11+'Miseu Folo'!K11+Nchalo!K11+Nsanje!K11+Ngabu!K11 -> 56505 | ... O11: =Bangula!O11+Chikwawa!O11+'Miseu Folo'!O11+Nchalo!O11+Nsanje!O11+Ngabu!O11 -> 51483 | P11: =SUM(D11:O11) -> 620127
A12: Volume Billed CWPs | C12: m3 | D12: =Bangula!D12+Chikwawa!D12+'Miseu Folo'!D12+Nchalo!D12+Nsanje!D12+Ngabu!D12 -> 5469 | E12: =Bangula!E12+Chikwawa!E12+'Miseu Folo'!E12+Nchalo!E12+Nsanje!E12+Ngabu!E12 -> 4900 | F12: =Bangula!F12+Chikwawa!F12+'Miseu Folo'!F12+Nchalo!F12+Nsanje!F12+Ngabu!F12 -> 5165 | G12: =Bangula!G12+Chikwawa!G12+'Miseu Folo'!G12+Nchalo!G12+Nsanje!G12+Ngabu!G12 -> 4610 | H12: =Bangula!H12+Chikwawa!H12+'Miseu Folo'!H12+Nchalo!H12+Nsanje!H12+Ngabu!H12 -> 5429 | I12: =Bangula!I12+Chikwawa!I12+'Miseu Folo'!I12+Nchalo!I12+Nsanje!I12+Ngabu!I12 -> 4553 | J12: =Bangula!J12+Chikwawa!J12+'Miseu Folo'!J12+Nchalo!J12+Nsanje!J12+Ngabu!J12 -> 4504 | K12: =Bangula!K12+Chikwawa!K12+'Miseu Folo'!K12+Nchalo!K12+Nsanje!K12+Ngabu!K12 -> 5099 | ... O12: =Bangula!O12+Chikwawa!O12+'Miseu Folo'!O12+Nchalo!O12+Nsanje!O12+Ngabu!O12 -> 4091 | P12: =SUM(D12:O12) -> 57022
A13: Volume Billed Institutions | C13: m3 | D13: =Bangula!D13+Chikwawa!D13+'Miseu Folo'!D13+Nchalo!D13+Nsanje!D13+Ngabu!D13 -> 533 | E13: =Bangula!E13+Chikwawa!E13+'Miseu Folo'!E13+Nchalo!E13+Nsanje!E13+Ngabu!E13 -> 578 | F13: =Bangula!F13+Chikwawa!F13+'Miseu Folo'!F13+Nchalo!F13+Nsanje!F13+Ngabu!F13 -> 1192 | G13: =Bangula!G13+Chikwawa!G13+'Miseu Folo'!G13+Nchalo!G13+Nsanje!G13+Ngabu!G13 -> 845 | H13: =Bangula!H13+Chikwawa!H13+'Miseu Folo'!H13+Nchalo!H13+Nsanje!H13+Ngabu!H13 -> 677 | I13: =Bangula!I13+Chikwawa!I13+'Miseu Folo'!I13+Nchalo!I13+Nsanje!I13+Ngabu!I13 -> 720 | J13: =Bangula!J13+Chikwawa!J13+'Miseu Folo'!J13+Nchalo!J13+Nsanje!J13+Ngabu!J13 -> 1031 | K13: =Bangula!K13+Chikwawa!K13+'Miseu Folo'!K13+Nchalo!K13+Nsanje!K13+Ngabu!K13 -> 1044 | ... O13: =Bangula!O13+Chikwawa!O13+'Miseu Folo'!O13+Nchalo!O13+Nsanje!O13+Ngabu!O13 -> 681 | P13: =SUM(D13:O13) -> 9292
A14: Volume Billed Commercial/Industrial | C14: m3 | D14: =Bangula!D14+Chikwawa!D14+'Miseu Folo'!D14+Nchalo!D14+Nsanje!D14+Ngabu!D14 -> 311 | E14: =Bangula!E14+Chikwawa!E14+'Miseu Folo'!E14+Nchalo!E14+Nsanje!E14+Ngabu!E14 -> 306 | F14: =Bangula!F14+Chikwawa!F14+'Miseu Folo'!F14+Nchalo!F14+Nsanje!F14+Ngabu!F14 -> 437 | G14: =Bangula!G14+Chikwawa!G14+'Miseu Folo'!G14+Nchalo!G14+Nsanje!G14+Ngabu!G14 -> 572 | H14: =Bangula!H14+Chikwawa!H14+'Miseu Folo'!H14+Nchalo!H14+Nsanje!H14+Ngabu!H14 -> 508 | I14: =Bangula!I14+Chikwawa!I14+'Miseu Folo'!I14+Nchalo!I14+Nsanje!I14+Ngabu!I14 -> 509 | J14: =Bangula!J14+Chikwawa!J14+'Miseu Folo'!J14+Nchalo!J14+Nsanje!J14+Ngabu!J14 -> 1094 | K14: =Bangula!K14+Chikwawa!K14+'Miseu Folo'!K14+Nchalo!K14+Nsanje!K14+Ngabu!K14 -> 502 | ... O14: =Bangula!O14+Chikwawa!O14+'Miseu Folo'!O14+Nchalo!O14+Nsanje!O14+Ngabu!O14 -> 406 | P14: =SUM(D14:O14) -> 5591
A15: Total Volume Billed Post Paid | C15: m3 | D15: =SUM(D11:D14) -> 49632 | E15: =SUM(E11:E14) -> 53623 | F15: =SUM(F11:F14) -> 62023 | G15: =SUM(G11:G14) -> 53724 | H15: =SUM(H11:H14) -> 55117 | I15: =SUM(I11:I14) -> 58618 | J15: =SUM(J11:J14) -> 64216 | K15: =SUM(K11:K14) -> 63150 | ... P15: =SUM(P11:P14) -> 692032
A16: REVENUE WATER - PREPAID
A17: Individuals | C17: m3 | D17: =Bangula!D17+Chikwawa!D17+'Miseu Folo'!D17+Nchalo!D17+Nsanje!D17+Ngabu!D17 -> 0 | E17: =Bangula!E17+Chikwawa!E17+'Miseu Folo'!E17+Nchalo!E17+Nsanje!E17+Ngabu!E17 -> 0 | F17: =Bangula!F17+Chikwawa!F17+'Miseu Folo'!F17+Nchalo!F17+Nsanje!F17+Ngabu!F17 -> 8539 | G17: =Bangula!G17+Chikwawa!G17+'Miseu Folo'!G17+Nchalo!G17+Nsanje!G17+Ngabu!G17 -> 9897 | H17: =Bangula!H17+Chikwawa!H17+'Miseu Folo'!H17+Nchalo!H17+Nsanje!H17+Ngabu!H17 -> 0 | I17: =Bangula!I17+Chikwawa!I17+'Miseu Folo'!I17+Nchalo!I17+Nsanje!I17+Ngabu!I17 -> 10365 | J17: =Bangula!J17+Chikwawa!J17+'Miseu Folo'!J17+Nchalo!J17+Nsanje!J17+Ngabu!J17 -> 12452.6 | K17: =Bangula!K17+Chikwawa!K17+'Miseu Folo'!K17+Nchalo!K17+Nsanje!K17+Ngabu!K17 -> 10819.2 | ... O17: =Bangula!O17+Chikwawa!O17+'Miseu Folo'!O17+Nchalo!O17+Nsanje!O17+Ngabu!O17 -> 8134 | P17: =SUM(D17:O17) -> 89109.8
A18: CWPs | C18: m3 | D18: =Bangula!D18+Chikwawa!D18+'Miseu Folo'!D18+Nchalo!D18+Nsanje!D18+Ngabu!D18 -> 0 | E18: =Bangula!E18+Chikwawa!E18+'Miseu Folo'!E18+Nchalo!E18+Nsanje!E18+Ngabu!E18 -> 0 | F18: =Bangula!F18+Chikwawa!F18+'Miseu Folo'!F18+Nchalo!F18+Nsanje!F18+Ngabu!F18 -> 0 | G18: =Bangula!G18+Chikwawa!G18+'Miseu Folo'!G18+Nchalo!G18+Nsanje!G18+Ngabu!G18 -> 0 | H18: =Bangula!H18+Chikwawa!H18+'Miseu Folo'!H18+Nchalo!H18+Nsanje!H18+Ngabu!H18 -> 0 | I18: =Bangula!I18+Chikwawa!I18+'Miseu Folo'!I18+Nchalo!I18+Nsanje!I18+Ngabu!I18 -> 57 | J18: =Bangula!J18+Chikwawa!J18+'Miseu Folo'!J18+Nchalo!J18+Nsanje!J18+Ngabu!J18 -> 0 | K18: =Bangula!K18+Chikwawa!K18+'Miseu Folo'!K18+Nchalo!K18+Nsanje!K18+Ngabu!K18 -> 1 | ... O18: =Bangula!O18+Chikwawa!O18+'Miseu Folo'!O18+Nchalo!O18+Nsanje!O18+Ngabu!O18 -> 0 | P18: =SUM(D18:O18) -> 59
A19: Institutions | C19: m3 | D19: =Bangula!D19+Chikwawa!D19+'Miseu Folo'!D19+Nchalo!D19+Nsanje!D19+Ngabu!D19 -> 22698 | E19: =Bangula!E19+Chikwawa!E19+'Miseu Folo'!E19+Nchalo!E19+Nsanje!E19+Ngabu!E19 -> 26081.7 | F19: =Bangula!F19+Chikwawa!F19+'Miseu Folo'!F19+Nchalo!F19+Nsanje!F19+Ngabu!F19 -> 11730.2 | G19: =Bangula!G19+Chikwawa!G19+'Miseu Folo'!G19+Nchalo!G19+Nsanje!G19+Ngabu!G19 -> 9976.8 | H19: =Bangula!H19+Chikwawa!H19+'Miseu Folo'!H19+Nchalo!H19+Nsanje!H19+Ngabu!H19 -> 24486.2 | I19: =Bangula!I19+Chikwawa!I19+'Miseu Folo'!I19+Nchalo!I19+Nsanje!I19+Ngabu!I19 -> 8843.3 | J19: =Bangula!J19+Chikwawa!J19+'Miseu Folo'!J19+Nchalo!J19+Nsanje!J19+Ngabu!J19 -> 4302 | K19: =Bangula!K19+Chikwawa!K19+'Miseu Folo'!K19+Nchalo!K19+Nsanje!K19+Ngabu!K19 -> 7706.3 | ... O19: =Bangula!O19+Chikwawa!O19+'Miseu Folo'!O19+Nchalo!O19+Nsanje!O19+Ngabu!O19 -> 8849.6 | P19: =SUM(D19:O19) -> 154271.3
A20: Commercial/Industrial | C20: m3 | D20: =Bangula!D20+Chikwawa!D20+'Miseu Folo'!D20+Nchalo!D20+Nsanje!D20+Ngabu!D20 -> 0 | E20: =Bangula!E20+Chikwawa!E20+'Miseu Folo'!E20+Nchalo!E20+Nsanje!E20+Ngabu!E20 -> 0 | F20: =Bangula!F20+Chikwawa!F20+'Miseu Folo'!F20+Nchalo!F20+Nsanje!F20+Ngabu!F20 -> 1736 | G20: =Bangula!G20+Chikwawa!G20+'Miseu Folo'!G20+Nchalo!G20+Nsanje!G20+Ngabu!G20 -> 1835 | H20: =Bangula!H20+Chikwawa!H20+'Miseu Folo'!H20+Nchalo!H20+Nsanje!H20+Ngabu!H20 -> 0 | I20: =Bangula!I20+Chikwawa!I20+'Miseu Folo'!I20+Nchalo!I20+Nsanje!I20+Ngabu!I20 -> 1668 | J20: =Bangula!J20+Chikwawa!J20+'Miseu Folo'!J20+Nchalo!J20+Nsanje!J20+Ngabu!J20 -> 1620 | K20: =Bangula!K20+Chikwawa!K20+'Miseu Folo'!K20+Nchalo!K20+Nsanje!K20+Ngabu!K20 -> 1530 | ... O20: =Bangula!O20+Chikwawa!O20+'Miseu Folo'!O20+Nchalo!O20+Nsanje!O20+Ngabu!O20 -> 1207 | P20: =SUM(D20:O20) -> 14231
A21: Total Volume Prepaid | C21: m3 | D21: =SUM(D17:D20) -> 22698 | E21: =SUM(E17:E20) -> 26081.7 | F21: =SUM(F17:F20) -> 22005.2 | G21: =SUM(G17:G20) -> 21708.8 | H21: =SUM(H17:H20) -> 24486.2 | I21: =SUM(I17:I20) -> 20933.3 | J21: =SUM(J17:J20) -> 18374.6 | K21: =SUM(K17:K20) -> 20056.5 | ... P21: =SUM(P17:P20) -> 257671.1
A22: TOTAL REVENUE WATER | C22: m3 | D22: =D21+D15 -> 72330 | E22: =E21+E15 -> 79704.7 | F22: =F21+F15 -> 84028.2 | G22: =G21+G15 -> 75432.8 | H22: =H21+H15 -> 79603.2 | I22: =I21+I15 -> 79551.3 | J22: =J21+J15 -> 82590.6 | K22: =K21+K15 -> 83206.5 | ... P22: =P21+P15 -> 949703.1
A24: Non-Revenue Water (NRW) | B24: Volume | C24: m3 | D24: =D9-D22 -> 24117 | E24: =E9-E22 -> 31426.3 | F24: =F9-F22 -> 28076.8 | G24: =G9-G22 -> 24510.2 | H24: =H9-H22 -> 21405.8 | I24: =I9-I22 -> 22536.7 | J24: =J9-J22 -> 20341.4 | K24: =K9-K22 -> 20321.5 | ... P24: =P9-P22 -> 273653.9
B25: Percentage | C25: % | D25: =D24/D9 -> 0.25005443 | E25: =E24/E9 -> 0.28278608 | F25: =F24/F9 -> 0.25045092 | G25: =G24/G9 -> 0.24524179 | H25: =H24/H9 -> 0.21191973 | I25: =I24/I9 -> 0.22075758 | J25: =J24/J9 -> 0.19761979 | K25: =K24/K9 -> 0.19628989 | ... P25: =P24/P9 -> 0.22369096
A26: OPERATING EXPENSES
A27: Chemicals
A28: Chemical | B28: Rate(MK/kg)
A29: Chlorine | B29: 3525.29 | C29: kg | D29: =Bangula!D29+Chikwawa!D29+'Miseu Folo'!D29+Nchalo!D29+Nsanje!D29+Ngabu!D29 -> 92.5 | E29: =Bangula!E29+Chikwawa!E29+'Miseu Folo'!E29+Nchalo!E29+Nsanje!E29+Ngabu!E29 -> 100 | F29: =Bangula!F29+Chikwawa!F29+'Miseu Folo'!F29+Nchalo!F29+Nsanje!F29+Ngabu!F29 -> 99 | G29: =Bangula!G29+Chikwawa!G29+'Miseu Folo'!G29+Nchalo!G29+Nsanje!G29+Ngabu!G29 -> 100.35 | H29: =Bangula!H29+Chikwawa!H29+'Miseu Folo'!H29+Nchalo!H29+Nsanje!H29+Ngabu!H29 -> 99.5 | I29: =Bangula!I29+Chikwawa!I29+'Miseu Folo'!I29+Nchalo!I29+Nsanje!I29+Ngabu!I29 -> 104.95 | J29: =Bangula!J29+Chikwawa!J29+'Miseu Folo'!J29+Nchalo!J29+Nsanje!J29+Ngabu!J29 -> 102.5 | K29: =Bangula!K29+Chikwawa!K29+'Miseu Folo'!K29+Nchalo!K29+Nsanje!K29+Ngabu!K29 -> 101.05 | ... O29: =Bangula!O29+Chikwawa!O29+'Miseu Folo'!O29+Nchalo!O29+Nsanje!O29+Ngabu!O29 -> 99 | P29: =SUM(D29:O29) -> 1201.55
C30: kg/mg litre | D30: =D29/(D9/1000) -> 0.95907597 | E30: =E29/(E9/1000) -> 0.89983893 | F30: =F29/(F9/1000) -> 0.88310066 | G30: =G29/(G9/1000) -> 1.0040723 | H30: =H29/(H9/1000) -> 0.98506074 | I30: =I29/(I9/1000) -> 1.0280346 | J30: =J29/(J9/1000) -> 0.99580305 | K30: =K29/(K9/1000) -> 0.97606445 | ... P30: =P29/(P9/1000) -> 0.98217446
A31: Aluminium sulphate | C31: kg | D31: =Bangula!D31+Chikwawa!D31+'Miseu Folo'!D31+Nchalo!D31+Nsanje!D31+Ngabu!D31 -> 0 | E31: =Bangula!E31+Chikwawa!E31+'Miseu Folo'!E31+Nchalo!E31+Nsanje!E31+Ngabu!E31 -> 0 | F31: =Bangula!F31+Chikwawa!F31+'Miseu Folo'!F31+Nchalo!F31+Nsanje!F31+Ngabu!F31 -> 0 | G31: =Bangula!G31+Chikwawa!G31+'Miseu Folo'!G31+Nchalo!G31+Nsanje!G31+Ngabu!G31 -> 0 | H31: =Bangula!H31+Chikwawa!H31+'Miseu Folo'!H31+Nchalo!H31+Nsanje!H31+Ngabu!H31 -> 0 | I31: =Bangula!I31+Chikwawa!I31+'Miseu Folo'!I31+Nchalo!I31+Nsanje!I31+Ngabu!I31 -> 0 | J31: =Bangula!J31+Chikwawa!J31+'Miseu Folo'!J31+Nchalo!J31+Nsanje!J31+Ngabu!J31 -> 0 | K31: =Bangula!K31+Chikwawa!K31+'Miseu Folo'!K31+Nchalo!K31+Nsanje!K31+Ngabu!K31 -> 0 | ... O31: =Bangula!O31+Chikwawa!O31+'Miseu Folo'!O31+Nchalo!O31+Nsanje!O31+Ngabu!O31 -> 0 | P31: =SUM(D31:O31) -> 0
B32: 1060.01 | C32: kg/mg litre | D32: =D31/(D9/1000) -> 0 | E32: =E31/(E9/1000) -> 0 | F32: =F31/(F9/1000) -> 0 | G32: =G31/(G9/1000) -> 0 | H32: =H31/(H9/1000) -> 0 | I32: =I31/(I9/1000) -> 0 | J32: =J31/(J9/1000) -> 0 | K32: =K31/(K9/1000) -> 0 | ... P32: =P31/(P9/1000) -> 0
A33: Soda | C33: kg | D33: =Bangula!D33+Chikwawa!D33+'Miseu Folo'!D33+Nchalo!D33+Nsanje!D33+Ngabu!D33 -> 0 | E33: =Bangula!E33+Chikwawa!E33+'Miseu Folo'!E33+Nchalo!E33+Nsanje!E33+Ngabu!E33 -> 0 | F33: =Bangula!F33+Chikwawa!F33+'Miseu Folo'!F33+Nchalo!F33+Nsanje!F33+Ngabu!F33 -> 0 | G33: =Bangula!G33+Chikwawa!G33+'Miseu Folo'!G33+Nchalo!G33+Nsanje!G33+Ngabu!G33 -> 0 | H33: =Bangula!H33+Chikwawa!H33+'Miseu Folo'!H33+Nchalo!H33+Nsanje!H33+Ngabu!H33 -> 0 | I33: =Bangula!I33+Chikwawa!I33+'Miseu Folo'!I33+Nchalo!I33+Nsanje!I33+Ngabu!I33 -> 0 | J33: =Bangula!J33+Chikwawa!J33+'Miseu Folo'!J33+Nchalo!J33+Nsanje!J33+Ngabu!J33 -> 0 | K33: =Bangula!K33+Chikwawa!K33+'Miseu Folo'!K33+Nchalo!K33+Nsanje!K33+Ngabu!K33 -> 0 | ... O33: =Bangula!O33+Chikwawa!O33+'Miseu Folo'!O33+Nchalo!O33+Nsanje!O33+Ngabu!O33 -> 0 | P33: =SUM(D33:O33) -> 0
B34: 1228.29 | C34: kg/mg litre | D34: =D33/(D9/1000) -> 0 | E34: =E33/(E9/1000) -> 0 | F34: =F33/(F9/1000) -> 0 | G34: =G33/(G9/1000) -> 0 | H34: =H33/(H9/1000) -> 0 | I34: =I33/(I9/1000) -> 0 | J34: =J33/(J9/1000) -> 0 | K34: =K33/(K9/1000) -> 0 | ... P34: =P33/(P9/1000) -> 0
A35: Algae floc | C35: litres | D35: =Bangula!D35+Chikwawa!D35+'Miseu Folo'!D35+Nchalo!D35+Nsanje!D35+Ngabu!D35 -> 0 | E35: =Bangula!E35+Chikwawa!E35+'Miseu Folo'!E35+Nchalo!E35+Nsanje!E35+Ngabu!E35 -> 0 | F35: =Bangula!F35+Chikwawa!F35+'Miseu Folo'!F35+Nchalo!F35+Nsanje!F35+Ngabu!F35 -> 0 | G35: =Bangula!G35+Chikwawa!G35+'Miseu Folo'!G35+Nchalo!G35+Nsanje!G35+Ngabu!G35 -> 0 | H35: =Bangula!H35+Chikwawa!H35+'Miseu Folo'!H35+Nchalo!H35+Nsanje!H35+Ngabu!H35 -> 0 | I35: =Bangula!I35+Chikwawa!I35+'Miseu Folo'!I35+Nchalo!I35+Nsanje!I35+Ngabu!I35 -> 0 | J35: =Bangula!J35+Chikwawa!J35+'Miseu Folo'!J35+Nchalo!J35+Nsanje!J35+Ngabu!J35 -> 0 | K35: =Bangula!K35+Chikwawa!K35+'Miseu Folo'!K35+Nchalo!K35+Nsanje!K35+Ngabu!K35 -> 0 | ... O35: =Bangula!O35+Chikwawa!O35+'Miseu Folo'!O35+Nchalo!O35+Nsanje!O35+Ngabu!O35 -> 0
B36: 3726.73 | C36: litres/mg litre
A37: Sud floc | C37: litres | D37: =Bangula!D37+Chikwawa!D37+'Miseu Folo'!D37+Nchalo!D37+Nsanje!D37+Ngabu!D37 -> 0 | E37: =Bangula!E37+Chikwawa!E37+'Miseu Folo'!E37+Nchalo!E37+Nsanje!E37+Ngabu!E37 -> 0 | F37: =Bangula!F37+Chikwawa!F37+'Miseu Folo'!F37+Nchalo!F37+Nsanje!F37+Ngabu!F37 -> 0 | G37: =Bangula!G37+Chikwawa!G37+'Miseu Folo'!G37+Nchalo!G37+Nsanje!G37+Ngabu!G37 -> 0 | H37: =Bangula!H37+Chikwawa!H37+'Miseu Folo'!H37+Nchalo!H37+Nsanje!H37+Ngabu!H37 -> 0 | I37: =Bangula!I37+Chikwawa!I37+'Miseu Folo'!I37+Nchalo!I37+Nsanje!I37+Ngabu!I37 -> 0 | J37: =Bangula!J37+Chikwawa!J37+'Miseu Folo'!J37+Nchalo!J37+Nsanje!J37+Ngabu!J37 -> 0 | K37: =Bangula!K37+Chikwawa!K37+'Miseu Folo'!K37+Nchalo!K37+Nsanje!K37+Ngabu!K37 -> 0 | ... O37: =Bangula!O37+Chikwawa!O37+'Miseu Folo'!O37+Nchalo!O37+Nsanje!O37+Ngabu!O37 -> 0 | P37: =SUM(D37:O37) -> 0
B38: 3951.59 | C38: litres/mg litre | D38: =D37/(D9/1000) -> 0 | E38: =E37/(E9/1000) -> 0 | F38: =F37/(F9/1000) -> 0 | G38: =G37/(G9/1000) -> 0 | H38: =H37/(H9/1000) -> 0 | I38: =I37/(I9/1000) -> 0 | J38: =J37/(J9/1000) -> 0 | K38: =K37/(K9/1000) -> 0 | ... P38: =P37/(P9/1000) -> 0
A39: Potasium permanganate | C39: kg | D39: =Bangula!D39+Chikwawa!D39+'Miseu Folo'!D39+Nchalo!D39+Nsanje!D39+Ngabu!D39 -> 0 | E39: =Bangula!E39+Chikwawa!E39+'Miseu Folo'!E39+Nchalo!E39+Nsanje!E39+Ngabu!E39 -> 0 | F39: =Bangula!F39+Chikwawa!F39+'Miseu Folo'!F39+Nchalo!F39+Nsanje!F39+Ngabu!F39 -> 0 | G39: =Bangula!G39+Chikwawa!G39+'Miseu Folo'!G39+Nchalo!G39+Nsanje!G39+Ngabu!G39 -> 0 | H39: =Bangula!H39+Chikwawa!H39+'Miseu Folo'!H39+Nchalo!H39+Nsanje!H39+Ngabu!H39 -> 0 | I39: =Bangula!I39+Chikwawa!I39+'Miseu Folo'!I39+Nchalo!I39+Nsanje!I39+Ngabu!I39 -> 0 | J39: =Bangula!J39+Chikwawa!J39+'Miseu Folo'!J39+Nchalo!J39+Nsanje!J39+Ngabu!J39 -> 0 | K39: =Bangula!K39+Chikwawa!K39+'Miseu Folo'!K39+Nchalo!K39+Nsanje!K39+Ngabu!K39 -> 0 | ... O39: =Bangula!O39+Chikwawa!O39+'Miseu Folo'!O39+Nchalo!O39+Nsanje!O39+Ngabu!O39 -> 0 | P39: =SUM(D39:O39) -> 0
B40: 1950 | C40: kg/mg litre | D40: =D39/(D9/1000) -> 0 | E40: =E39/(E9/1000) -> 0 | F40: =F39/(F9/1000) -> 0 | G40: =G39/(G9/1000) -> 0 | H40: =H39/(H9/1000) -> 0 | I40: =I39/(I9/1000) -> 0 | J40: =J39/(J9/1000) -> 0 | K40: =K39/(K9/1000) -> 0 | ... P40: =P39/(P9/1000) -> 0
A41: Cost of Chemicals | C41: Mk | D41: =(D29*$B29)+(D31*$B31)+(D33*$B33)+(D35*$B35)+(D37*$B37)+(D39*$B39) -> 326089.33 | E41: =(E29*$B29)+(E31*$B31)+(E33*$B33)+(E35*$B35)+(E37*$B37)+(E39*$B39) -> 352529 | F41: =(F29*$B29)+(F31*$B31)+(F33*$B33)+(F35*$B35)+(F37*$B37)+(F39*$B39) -> 349003.71 | G41: =(G29*$B29)+(G31*$B31)+(G33*$B33)+(G35*$B35)+(G37*$B37)+(G39*$B39) -> 353762.85 | H41: =(H29*$B29)+(H31*$B31)+(H33*$B33)+(H35*$B35)+(H37*$B37)+(H39*$B39) -> 350766.35 | I41: =(I29*$B29)+(I31*$B31)+(I33*$B33)+(I35*$B35)+(I37*$B37)+(I39*$B39) -> 369979.19 | J41: =(J29*$B29)+(J31*$B31)+(J33*$B33)+(J35*$B35)+(J37*$B37)+(J39*$B39) -> 361342.22 | K41: =(K29*$B29)+(K31*$B31)+(K33*$B33)+(K35*$B35)+(K37*$B37)+(K39*$B39) -> 356230.55 | ... O41: =(O29*$B29)+(O31*$B31)+(O33*$B33)+(O35*$B35)+(O37*$B37)+(O39*$B39) -> 349003.71 | P41: =SUM(D41:O41) -> 4235812.2
A42: Cost/vol. Produced (chemicals) | C42: Mk/m3 | D42: =D41/D9 -> 3.3810209 | E42: =E41/E9 -> 3.1721932 | F42: =F41/F9 -> 3.1131859 | G42: =G41/G9 -> 3.5396461 | H42: =H41/H9 -> 3.4726248 | I42: =I41/I9 -> 3.6241202 | J42: =J41/J9 -> 3.5104945 | K42: =K41/K9 -> 3.4409102 | ... P42: =P41/P9 -> 3.4624498
A43: Power
A44: Power Usage | C44: Kw | D44: =Bangula!D44+Chikwawa!D44+'Miseu Folo'!D44+Nchalo!D44+Nsanje!D44+Ngabu!D44 -> 51170.03 | E44: =Bangula!E44+Chikwawa!E44+'Miseu Folo'!E44+Nchalo!E44+Nsanje!E44+Ngabu!E44 -> 55320.58 | F44: =Bangula!F44+Chikwawa!F44+'Miseu Folo'!F44+Nchalo!F44+Nsanje!F44+Ngabu!F44 -> 60382.15 | G44: =Bangula!G44+Chikwawa!G44+'Miseu Folo'!G44+Nchalo!G44+Nsanje!G44+Ngabu!G44 -> 59411.13 | H44: =Bangula!H44+Chikwawa!H44+'Miseu Folo'!H44+Nchalo!H44+Nsanje!H44+Ngabu!H44 -> 53976.85 | I44: =Bangula!I44+Chikwawa!I44+'Miseu Folo'!I44+Nchalo!I44+Nsanje!I44+Ngabu!I44 -> 89835.03 | J44: =Bangula!J44+Chikwawa!J44+'Miseu Folo'!J44+Nchalo!J44+Nsanje!J44+Ngabu!J44 -> 54538.69 | K44: =Bangula!K44+Chikwawa!K44+'Miseu Folo'!K44+Nchalo!K44+Nsanje!K44+Ngabu!K44 -> 55608.14 | ... O44: =Bangula!O44+Chikwawa!O44+'Miseu Folo'!O44+Nchalo!O44+Nsanje!O44+Ngabu!O44 -> 36379.95 | P44: =SUM(D44:O44) -> 673160.46
A45: Power/ Vol. Produced | C45: Kw/m3 | D45: =D44/D9 -> 0.53055077 | E45: =E44/E9 -> 0.49779611 | F45: =F44/F9 -> 0.53862138 | G45: =G44/G9 -> 0.59445014 | H45: =H44/H9 -> 0.53437664 | I45: =I44/I9 -> 0.87997639 | J45: =J44/J9 -> 0.52985165 | K45: =K44/K9 -> 0.5371314 | ... P45: =P44/P9 -> 0.55025676
A46: Cost of Power | C46: Mk | D46: =Bangula!D46+Chikwawa!D46+'Miseu Folo'!D46+Nchalo!D46+Nsanje!D46+Ngabu!D46 -> 7731791.5 | E46: =Bangula!E46+Chikwawa!E46+'Miseu Folo'!E46+Nchalo!E46+Nsanje!E46+Ngabu!E46 -> 8358939.6 | F46: =Bangula!F46+Chikwawa!F46+'Miseu Folo'!F46+Nchalo!F46+Nsanje!F46+Ngabu!F46 -> 9123742.9 | G46: =Bangula!G46+Chikwawa!G46+'Miseu Folo'!G46+Nchalo!G46+Nsanje!G46+Ngabu!G46 -> 8977021.7 | H46: =Bangula!H46+Chikwawa!H46+'Miseu Folo'!H46+Nchalo!H46+Nsanje!H46+Ngabu!H46 -> 8155902 | I46: =Bangula!I46+Chikwawa!I46+'Miseu Folo'!I46+Nchalo!I46+Nsanje!I46+Ngabu!I46 -> 13574073 | J46: =Bangula!J46+Chikwawa!J46+'Miseu Folo'!J46+Nchalo!J46+Nsanje!J46+Ngabu!J46 -> 7841661.9 | K46: =Bangula!K46+Chikwawa!K46+'Miseu Folo'!K46+Nchalo!K46+Nsanje!K46+Ngabu!K46 -> 7814271.8 | ... O46: =Bangula!O46+Chikwawa!O46+'Miseu Folo'!O46+Nchalo!O46+Nsanje!O46+Ngabu!O46 -> 5146331.6 | P46: =SUM(D46:O46) -> 98739283
A47: Cost/vol. Produced | C47: Mk/m3 | D47: =D46/D9 -> 80.166221 | E47: =E46/E9 -> 75.216993 | F47: =F46/F9 -> 81.385691 | G47: =G46/G9 -> 89.821416 | H47: =H46/H9 -> 80.74431 | I47: =I46/I9 -> 132.96443 | J47: =J46/J9 -> 76.182936 | K47: =K46/K9 -> 75.479791 | ... P47: =P46/P9 -> 80.711749
A48: Plant and Vehicle Maintenance
A49: Distances covered | C49: km | D49: =Bangula!D49+Chikwawa!D49+'Miseu Folo'!D49+Nchalo!D49+Nsanje!D49+Ngabu!D49 -> 3341 | E49: =Bangula!E49+Chikwawa!E49+'Miseu Folo'!E49+Nchalo!E49+Nsanje!E49+Ngabu!E49 -> 5304 | F49: =Bangula!F49+Chikwawa!F49+'Miseu Folo'!F49+Nchalo!F49+Nsanje!F49+Ngabu!F49 -> 4896 | G49: =Bangula!G49+Chikwawa!G49+'Miseu Folo'!G49+Nchalo!G49+Nsanje!G49+Ngabu!G49 -> 5216 | H49: =Bangula!H49+Chikwawa!H49+'Miseu Folo'!H49+Nchalo!H49+Nsanje!H49+Ngabu!H49 -> 3295 | I49: =Bangula!I49+Chikwawa!I49+'Miseu Folo'!I49+Nchalo!I49+Nsanje!I49+Ngabu!I49 -> 2942 | J49: =Bangula!J49+Chikwawa!J49+'Miseu Folo'!J49+Nchalo!J49+Nsanje!J49+Ngabu!J49 -> 4569 | K49: =Bangula!K49+Chikwawa!K49+'Miseu Folo'!K49+Nchalo!K49+Nsanje!K49+Ngabu!K49 -> 6224 | ... O49: =Bangula!O49+Chikwawa!O49+'Miseu Folo'!O49+Nchalo!O49+Nsanje!O49+Ngabu!O49 -> 2949 | P49: =SUM(D49:O49) -> 51077
A50: Fuel Used (litres) | C50: litres | D50: =Bangula!D50+Chikwawa!D50+'Miseu Folo'!D50+Nchalo!D50+Nsanje!D50+Ngabu!D50 -> 359 | E50: =Bangula!E50+Chikwawa!E50+'Miseu Folo'!E50+Nchalo!E50+Nsanje!E50+Ngabu!E50 -> 607 | F50: =Bangula!F50+Chikwawa!F50+'Miseu Folo'!F50+Nchalo!F50+Nsanje!F50+Ngabu!F50 -> 569 | G50: =Bangula!G50+Chikwawa!G50+'Miseu Folo'!G50+Nchalo!G50+Nsanje!G50+Ngabu!G50 -> 696 | H50: =Bangula!H50+Chikwawa!H50+'Miseu Folo'!H50+Nchalo!H50+Nsanje!H50+Ngabu!H50 -> 447.5 | I50: =Bangula!I50+Chikwawa!I50+'Miseu Folo'!I50+Nchalo!I50+Nsanje!I50+Ngabu!I50 -> 443 | J50: =Bangula!J50+Chikwawa!J50+'Miseu Folo'!J50+Nchalo!J50+Nsanje!J50+Ngabu!J50 -> 744.19 | K50: =Bangula!K50+Chikwawa!K50+'Miseu Folo'!K50+Nchalo!K50+Nsanje!K50+Ngabu!K50 -> 887 | ... O50: =Bangula!O50+Chikwawa!O50+'Miseu Folo'!O50+Nchalo!O50+Nsanje!O50+Ngabu!O50 -> 427.2 | P50: =SUM(D50:O50) -> 7011.79
A51: Cost of fuel | C51: Mk | D51: =Bangula!D51+Chikwawa!D51+'Miseu Folo'!D51+Nchalo!D51+Nsanje!D51+Ngabu!D51 -> 683880 | E51: =Bangula!E51+Chikwawa!E51+'Miseu Folo'!E51+Nchalo!E51+Nsanje!E51+Ngabu!E51 -> 1160940 | F51: =Bangula!F51+Chikwawa!F51+'Miseu Folo'!F51+Nchalo!F51+Nsanje!F51+Ngabu!F51 -> 1087980 | G51: =Bangula!G51+Chikwawa!G51+'Miseu Folo'!G51+Nchalo!G51+Nsanje!G51+Ngabu!G51 -> 1332720 | H51: =Bangula!H51+Chikwawa!H51+'Miseu Folo'!H51+Nchalo!H51+Nsanje!H51+Ngabu!H51 -> 854025 | I51: =Bangula!I51+Chikwawa!I51+'Miseu Folo'!I51+Nchalo!I51+Nsanje!I51+Ngabu!I51 -> 840660 | J51: =Bangula!J51+Chikwawa!J51+'Miseu Folo'!J51+Nchalo!J51+Nsanje!J51+Ngabu!J51 -> 1417509.3 | K51: =Bangula!K51+Chikwawa!K51+'Miseu Folo'!K51+Nchalo!K51+Nsanje!K51+Ngabu!K51 -> 1698540 | ... O51: =Bangula!O51+Chikwawa!O51+'Miseu Folo'!O51+Nchalo!O51+Nsanje!O51+Ngabu!O51 -> 940004 | P51: =SUM(D51:O51) -> 13520951
A52: Maintenance | C52: Mk | D52: =Bangula!D52+Chikwawa!D52+'Miseu Folo'!D52+Nchalo!D52+Nsanje!D52+Ngabu!D52 -> 50000 | E52: =Bangula!E52+Chikwawa!E52+'Miseu Folo'!E52+Nchalo!E52+Nsanje!E52+Ngabu!E52 -> 65000 | F52: =Bangula!F52+Chikwawa!F52+'Miseu Folo'!F52+Nchalo!F52+Nsanje!F52+Ngabu!F52 -> 0 | G52: =Bangula!G52+Chikwawa!G52+'Miseu Folo'!G52+Nchalo!G52+Nsanje!G52+Ngabu!G52 -> 0 | H52: =Bangula!H52+Chikwawa!H52+'Miseu Folo'!H52+Nchalo!H52+Nsanje!H52+Ngabu!H52 -> 0 | I52: =Bangula!I52+Chikwawa!I52+'Miseu Folo'!I52+Nchalo!I52+Nsanje!I52+Ngabu!I52 -> 0 | J52: =Bangula!J52+Chikwawa!J52+'Miseu Folo'!J52+Nchalo!J52+Nsanje!J52+Ngabu!J52 -> 0 | K52: =Bangula!K52+Chikwawa!K52+'Miseu Folo'!K52+Nchalo!K52+Nsanje!K52+Ngabu!K52 -> 0 | ... O52: =Bangula!O52+Chikwawa!O52+'Miseu Folo'!O52+Nchalo!O52+Nsanje!O52+Ngabu!O52 -> 0 | P52: =SUM(D52:O52) -> 115000
A53: Salaries and Wages
A54: Staff Costs | C54: MK | D54: =Bangula!D54+Chikwawa!D54+'Miseu Folo'!D54+Nchalo!D54+Nsanje!D54+Ngabu!D54 -> 9408257.6 | E54: =Bangula!E54+Chikwawa!E54+'Miseu Folo'!E54+Nchalo!E54+Nsanje!E54+Ngabu!E54 -> 9408257.6 | F54: =Bangula!F54+Chikwawa!F54+'Miseu Folo'!F54+Nchalo!F54+Nsanje!F54+Ngabu!F54 -> 9408257.6 | G54: =Bangula!G54+Chikwawa!G54+'Miseu Folo'!G54+Nchalo!G54+Nsanje!G54+Ngabu!G54 -> 9487015 | H54: =Bangula!H54+Chikwawa!H54+'Miseu Folo'!H54+Nchalo!H54+Nsanje!H54+Ngabu!H54 -> 9487015 | I54: =Bangula!I54+Chikwawa!I54+'Miseu Folo'!I54+Nchalo!I54+Nsanje!I54+Ngabu!I54 -> 9924492.9 | J54: =Bangula!J54+Chikwawa!J54+'Miseu Folo'!J54+Nchalo!J54+Nsanje!J54+Ngabu!J54 -> 9924492.9 | K54: =Bangula!K54+Chikwawa!K54+'Miseu Folo'!K54+Nchalo!K54+Nsanje!K54+Ngabu!K54 -> 5463583.7 | ... O54: =Bangula!O54+Chikwawa!O54+'Miseu Folo'!O54+Nchalo!O54+Nsanje!O54+Ngabu!O54 -> 0 | P54: =SUM(D54:O54) -> 74702055
A55: Wages | C55: MK | D55: =Bangula!D55+Chikwawa!D55+'Miseu Folo'!D55+Nchalo!D55+Nsanje!D55+Ngabu!D55 -> 1271430.4 | E55: =Bangula!E55+Chikwawa!E55+'Miseu Folo'!E55+Nchalo!E55+Nsanje!E55+Ngabu!E55 -> 1271430.4 | F55: =Bangula!F55+Chikwawa!F55+'Miseu Folo'!F55+Nchalo!F55+Nsanje!F55+Ngabu!F55 -> 1271430.4 | G55: =Bangula!G55+Chikwawa!G55+'Miseu Folo'!G55+Nchalo!G55+Nsanje!G55+Ngabu!G55 -> 1305996.2 | H55: =Bangula!H55+Chikwawa!H55+'Miseu Folo'!H55+Nchalo!H55+Nsanje!H55+Ngabu!H55 -> 1305996.2 | I55: =Bangula!I55+Chikwawa!I55+'Miseu Folo'!I55+Nchalo!I55+Nsanje!I55+Ngabu!I55 -> 1310931.4 | J55: =Bangula!J55+Chikwawa!J55+'Miseu Folo'!J55+Nchalo!J55+Nsanje!J55+Ngabu!J55 -> 1310931.4 | K55: =Bangula!K55+Chikwawa!K55+'Miseu Folo'!K55+Nchalo!K55+Nsanje!K55+Ngabu!K55 -> 580668.33 | ... O55: =Bangula!O55+Chikwawa!O55+'Miseu Folo'!O55+Nchalo!O55+Nsanje!O55+Ngabu!O55 -> 0 | P55: =SUM(D55:O55) -> 9628908.7
A56: Other Overhead Costs | C56: MK | D56: =Bangula!D56+Chikwawa!D56+'Miseu Folo'!D56+Nchalo!D56+Nsanje!D56+Ngabu!D56 -> 0 | E56: =Bangula!E56+Chikwawa!E56+'Miseu Folo'!E56+Nchalo!E56+Nsanje!E56+Ngabu!E56 -> 0 | F56: =Bangula!F56+Chikwawa!F56+'Miseu Folo'!F56+Nchalo!F56+Nsanje!F56+Ngabu!F56 -> 0 | G56: =Bangula!G56+Chikwawa!G56+'Miseu Folo'!G56+Nchalo!G56+Nsanje!G56+Ngabu!G56 -> 0 | H56: =Bangula!H56+Chikwawa!H56+'Miseu Folo'!H56+Nchalo!H56+Nsanje!H56+Ngabu!H56 -> 0 | I56: =Bangula!I56+Chikwawa!I56+'Miseu Folo'!I56+Nchalo!I56+Nsanje!I56+Ngabu!I56 -> 0 | J56: =Bangula!J56+Chikwawa!J56+'Miseu Folo'!J56+Nchalo!J56+Nsanje!J56+Ngabu!J56 -> 0 | K56: =Bangula!K56+Chikwawa!K56+'Miseu Folo'!K56+Nchalo!K56+Nsanje!K56+Ngabu!K56 -> 0 | ... O56: =Bangula!O56+Chikwawa!O56+'Miseu Folo'!O56+Nchalo!O56+Nsanje!O56+Ngabu!O56 -> 0 | P56: =SUM(D56:O56) -> 125.93027
A57: Operating Costs
A58: Total Operating Costs | C58: MK | D58: =D41+D46+D51+D52+D54+D55+D56 -> 19471449 | E58: =E41+E46+E51+E52+E54+E55+E56 -> 20617097 | F58: =F41+F46+F51+F52+F54+F55+F56 -> 21240415 | G58: =G41+G46+G51+G52+G54+G55+G56 -> 21456516 | H58: =H41+H46+H51+H52+H54+H55+H56 -> 20153705 | I58: =I41+I46+I51+I52+I54+I55+I56 -> 26020136 | J58: =J41+J46+J51+J52+J54+J55+J56 -> 20855938 | K58: =K41+K46+K51+K52+K54+K55+K56 -> 15913294 | ... O58: =O41+O46+O51+O52+O54+O55+O56 -> 6435339.3 | P58: =SUM(D58:O58) -> 2.0094214e+08
A59: Cost/Vol. Produced | C59: Mk/m3 | D59: =D58/D9 -> 201.88755 | E59: =E58/E9 -> 185.52066 | F59: =F58/F9 -> 189.46893 | G59: =G58/G9 -> 214.68753 | H59: =H58/H9 -> 199.52385 | I59: =I58/I9 -> 254.87948 | J59: =J58/J9 -> 202.6186 | K59: =K58/K9 -> 153.71005 | ... P59: =P58/P9 -> 164.2547
A60: Cost/Vol. Billed | C60: Mk/m3 | D60: =D58/D22 -> 269.20294 | E60: =E58/E22 -> 258.66852 | F60: =F58/F22 -> 252.77722 | G60: =G58/G22 -> 284.44544 | H60: =H58/H22 -> 253.17707 | I60: =I58/I22 -> 327.08625 | J60: =J58/J22 -> 252.52193 | K60: =K58/K22 -> 191.25062 | ... P60: =P58/P22 -> 211.58416
A61: Permanent Staff Employed | C61: No | D61: =Bangula!D61+Chikwawa!D61+'Miseu Folo'!D61+Nchalo!D61+Nsanje!D61+Ngabu!D61 -> 39 | E61: =Bangula!E61+Chikwawa!E61+'Miseu Folo'!E61+Nchalo!E61+Nsanje!E61+Ngabu!E61 -> 39 | F61: =Bangula!F61+Chikwawa!F61+'Miseu Folo'!F61+Nchalo!F61+Nsanje!F61+Ngabu!F61 -> 39 | G61: =Bangula!G61+Chikwawa!G61+'Miseu Folo'!G61+Nchalo!G61+Nsanje!G61+Ngabu!G61 -> 40 | H61: =Bangula!H61+Chikwawa!H61+'Miseu Folo'!H61+Nchalo!H61+Nsanje!H61+Ngabu!H61 -> 40 | I61: =Bangula!I61+Chikwawa!I61+'Miseu Folo'!I61+Nchalo!I61+Nsanje!I61+Ngabu!I61 -> 38 | J61: =Bangula!J61+Chikwawa!J61+'Miseu Folo'!J61+Nchalo!J61+Nsanje!J61+Ngabu!J61 -> 38 | K61: =Bangula!K61+Chikwawa!K61+'Miseu Folo'!K61+Nchalo!K61+Nsanje!K61+Ngabu!K61 -> 38 | ... O61: =Bangula!O61+Chikwawa!O61+'Miseu Folo'!O61+Nchalo!O61+Nsanje!O61+Ngabu!O61 -> 36 | P61: =O61 -> 36
A62: Staff/Vol.1000m3 of Volume Produced/hour (12 hour day) | C62: No/1000m3 | D62: =(D61*1000*31)/D9 -> 12.535382 | E62: =(E61*1000*31)/E9 -> 10.879053 | F62: =(F61*1000*31)/F9 -> 10.784532 | G62: =(G61*1000*31)/G9 -> 12.407072 | H62: =(H61*1000*31)/H9 -> 12.276134 | I62: =(I61*1000*31)/I9 -> 11.539064 | J62: =(J61*1000*31)/J9 -> 11.444449 | K62: =(K61*1000*31)/K9 -> 11.378564 | ... P62: =(P61*1000*31)/P9 -> 0.91224393
A63: Temporary Staff Employed | C63: No | D63: =Bangula!D63+Chikwawa!D63+'Miseu Folo'!D63+Nchalo!D63+Nsanje!D63+Ngabu!D63 -> 28 | E63: =Bangula!E63+Chikwawa!E63+'Miseu Folo'!E63+Nchalo!E63+Nsanje!E63+Ngabu!E63 -> 28 | F63: =Bangula!F63+Chikwawa!F63+'Miseu Folo'!F63+Nchalo!F63+Nsanje!F63+Ngabu!F63 -> 28 | G63: =Bangula!G63+Chikwawa!G63+'Miseu Folo'!G63+Nchalo!G63+Nsanje!G63+Ngabu!G63 -> 28 | H63: =Bangula!H63+Chikwawa!H63+'Miseu Folo'!H63+Nchalo!H63+Nsanje!H63+Ngabu!H63 -> 28 | I63: =Bangula!I63+Chikwawa!I63+'Miseu Folo'!I63+Nchalo!I63+Nsanje!I63+Ngabu!I63 -> 28 | J63: =Bangula!J63+Chikwawa!J63+'Miseu Folo'!J63+Nchalo!J63+Nsanje!J63+Ngabu!J63 -> 28 | K63: =Bangula!K63+Chikwawa!K63+'Miseu Folo'!K63+Nchalo!K63+Nsanje!K63+Ngabu!K63 -> 31 | ... O63: =Bangula!O63+Chikwawa!O63+'Miseu Folo'!O63+Nchalo!O63+Nsanje!O63+Ngabu!O63 -> 32 | P63: =SUM(D63:O63) -> 348
A65: Water Connections and Disconnections
A66: New Individual Water Connections | B66: Brought Forward | C66: No | D66: =Bangula!D66+Chikwawa!D66+'Miseu Folo'!D66+Nchalo!D66+Nsanje!D66+Ngabu!D66 -> 779 | E66: =Bangula!E66+Chikwawa!E66+'Miseu Folo'!E66+Nchalo!E66+Nsanje!E66+Ngabu!E66 -> 766 | F66: =Bangula!F66+Chikwawa!F66+'Miseu Folo'!F66+Nchalo!F66+Nsanje!F66+Ngabu!F66 -> 750 | G66: =Bangula!G66+Chikwawa!G66+'Miseu Folo'!G66+Nchalo!G66+Nsanje!G66+Ngabu!G66 -> 744 | H66: =Bangula!H66+Chikwawa!H66+'Miseu Folo'!H66+Nchalo!H66+Nsanje!H66+Ngabu!H66 -> 853 | I66: =Bangula!I66+Chikwawa!I66+'Miseu Folo'!I66+Nchalo!I66+Nsanje!I66+Ngabu!I66 -> 848 | J66: =Bangula!J66+Chikwawa!J66+'Miseu Folo'!J66+Nchalo!J66+Nsanje!J66+Ngabu!J66 -> 823 | K66: =Bangula!K66+Chikwawa!K66+'Miseu Folo'!K66+Nchalo!K66+Nsanje!K66+Ngabu!K66 -> 798 | ... O66: =Bangula!O66+Chikwawa!O66+'Miseu Folo'!O66+Nchalo!O66+Nsanje!O66+Ngabu!O66 -> 714 | P66: =D66 -> 779
B67: Applied this Month | C67: No | D67: =Bangula!D67+Chikwawa!D67+'Miseu Folo'!D67+Nchalo!D67+Nsanje!D67+Ngabu!D67 -> 57 | E67: =Bangula!E67+Chikwawa!E67+'Miseu Folo'!E67+Nchalo!E67+Nsanje!E67+Ngabu!E67 -> 46 | F67: =Bangula!F67+Chikwawa!F67+'Miseu Folo'!F67+Nchalo!F67+Nsanje!F67+Ngabu!F67 -> 99 | G67: =Bangula!G67+Chikwawa!G67+'Miseu Folo'!G67+Nchalo!G67+Nsanje!G67+Ngabu!G67 -> 242 | H67: =Bangula!H67+Chikwawa!H67+'Miseu Folo'!H67+Nchalo!H67+Nsanje!H67+Ngabu!H67 -> 103 | I67: =Bangula!I67+Chikwawa!I67+'Miseu Folo'!I67+Nchalo!I67+Nsanje!I67+Ngabu!I67 -> 76 | J67: =Bangula!J67+Chikwawa!J67+'Miseu Folo'!J67+Nchalo!J67+Nsanje!J67+Ngabu!J67 -> 51 | K67: =Bangula!K67+Chikwawa!K67+'Miseu Folo'!K67+Nchalo!K67+Nsanje!K67+Ngabu!K67 -> 52 | ... O67: =Bangula!O67+Chikwawa!O67+'Miseu Folo'!O67+Nchalo!O67+Nsanje!O67+Ngabu!O67 -> 48 | P67: =SUM(D67:O67) -> 894
B68: Done this Month Postpaid | C68: No | D68: =Bangula!D68+Chikwawa!D68+'Miseu Folo'!D68+Nchalo!D68+Nsanje!D68+Ngabu!D68 -> 70 | E68: =Bangula!E68+Chikwawa!E68+'Miseu Folo'!E68+Nchalo!E68+Nsanje!E68+Ngabu!E68 -> 62 | F68: =Bangula!F68+Chikwawa!F68+'Miseu Folo'!F68+Nchalo!F68+Nsanje!F68+Ngabu!F68 -> 105 | G68: =Bangula!G68+Chikwawa!G68+'Miseu Folo'!G68+Nchalo!G68+Nsanje!G68+Ngabu!G68 -> 133 | H68: =Bangula!H68+Chikwawa!H68+'Miseu Folo'!H68+Nchalo!H68+Nsanje!H68+Ngabu!H68 -> 106 | I68: =Bangula!I68+Chikwawa!I68+'Miseu Folo'!I68+Nchalo!I68+Nsanje!I68+Ngabu!I68 -> 75 | J68: =Bangula!J68+Chikwawa!J68+'Miseu Folo'!J68+Nchalo!J68+Nsanje!J68+Ngabu!J68 -> 76 | K68: =Bangula!K68+Chikwawa!K68+'Miseu Folo'!K68+Nchalo!K68+Nsanje!K68+Ngabu!K68 -> 68 | ... O68: =Bangula!O68+Chikwawa!O68+'Miseu Folo'!O68+Nchalo!O68+Nsanje!O68+Ngabu!O68 -> 67 | P68: =SUM(D68:O68) -> 939
B69: Done this Month Prepaid | C69: No | D69: =Bangula!D69+Chikwawa!D69+'Miseu Folo'!D69+Nchalo!D69+Nsanje!D69+Ngabu!D69 -> 0 | E69: =Bangula!E69+Chikwawa!E69+'Miseu Folo'!E69+Nchalo!E69+Nsanje!E69+Ngabu!E69 -> 0 | F69: =Bangula!F69+Chikwawa!F69+'Miseu Folo'!F69+Nchalo!F69+Nsanje!F69+Ngabu!F69 -> 0 | G69: =Bangula!G69+Chikwawa!G69+'Miseu Folo'!G69+Nchalo!G69+Nsanje!G69+Ngabu!G69 -> 0 | H69: =Bangula!H69+Chikwawa!H69+'Miseu Folo'!H69+Nchalo!H69+Nsanje!H69+Ngabu!H69 -> 2 | I69: =Bangula!I69+Chikwawa!I69+'Miseu Folo'!I69+Nchalo!I69+Nsanje!I69+Ngabu!I69 -> 26 | J69: =Bangula!J69+Chikwawa!J69+'Miseu Folo'!J69+Nchalo!J69+Nsanje!J69+Ngabu!J69 -> 0 | K69: =Bangula!K69+Chikwawa!K69+'Miseu Folo'!K69+Nchalo!K69+Nsanje!K69+Ngabu!K69 -> 7 | ... O69: =Bangula!O69+Chikwawa!O69+'Miseu Folo'!O69+Nchalo!O69+Nsanje!O69+Ngabu!O69 -> 0 | P69: =SUM(D69:O69) -> 39
B70: Total Done | C70: No | D70: =D68+D69 -> 70 | E70: =E68+E69 -> 62 | F70: =F68+F69 -> 105 | G70: =G68+G69 -> 133 | H70: =H68+H69 -> 108 | I70: =I68+I69 -> 101 | J70: =J68+J69 -> 76 | K70: =K68+K69 -> 75 | ... P70: =P68+P69 -> 978
B71: Carried Forward | C71: No | D71: =D66+D67-D70 -> 766 | E71: =E66+E67-E70 -> 750 | F71: =F66+F67-F70 -> 744 | G71: =G66+G67-G70 -> 853 | H71: =H66+H67-H70 -> 848 | I71: =I66+I67-I70 -> 823 | J71: =J66+J67-J70 -> 798 | K71: =K66+K67-K70 -> 775 | ... P71: =P66+P67-P70 -> 695
A72: New Institutional Water Connections | B72: Brought Forward | C72: No | D72: =Bangula!D72+Chikwawa!D72+'Miseu Folo'!D72+Nchalo!D72+Nsanje!D72+Ngabu!D72 -> 0 | E72: =Bangula!E72+Chikwawa!E72+'Miseu Folo'!E72+Nchalo!E72+Nsanje!E72+Ngabu!E72 -> 0 | F72: =Bangula!F72+Chikwawa!F72+'Miseu Folo'!F72+Nchalo!F72+Nsanje!F72+Ngabu!F72 -> 0 | G72: =Bangula!G72+Chikwawa!G72+'Miseu Folo'!G72+Nchalo!G72+Nsanje!G72+Ngabu!G72 -> 0 | H72: =Bangula!H72+Chikwawa!H72+'Miseu Folo'!H72+Nchalo!H72+Nsanje!H72+Ngabu!H72 -> 0 | I72: =Bangula!I72+Chikwawa!I72+'Miseu Folo'!I72+Nchalo!I72+Nsanje!I72+Ngabu!I72 -> 0 | J72: =Bangula!J72+Chikwawa!J72+'Miseu Folo'!J72+Nchalo!J72+Nsanje!J72+Ngabu!J72 -> 0 | K72: =Bangula!K72+Chikwawa!K72+'Miseu Folo'!K72+Nchalo!K72+Nsanje!K72+Ngabu!K72 -> 0 | ... O72: =Bangula!O72+Chikwawa!O72+'Miseu Folo'!O72+Nchalo!O72+Nsanje!O72+Ngabu!O72 -> 0 | P72: =D72 -> 0
B73: Applied this Month | C73: No | D73: =Bangula!D73+Chikwawa!D73+'Miseu Folo'!D73+Nchalo!D73+Nsanje!D73+Ngabu!D73 -> 1 | E73: =Bangula!E73+Chikwawa!E73+'Miseu Folo'!E73+Nchalo!E73+Nsanje!E73+Ngabu!E73 -> 0 | F73: =Bangula!F73+Chikwawa!F73+'Miseu Folo'!F73+Nchalo!F73+Nsanje!F73+Ngabu!F73 -> 0 | G73: =Bangula!G73+Chikwawa!G73+'Miseu Folo'!G73+Nchalo!G73+Nsanje!G73+Ngabu!G73 -> 1 | H73: =Bangula!H73+Chikwawa!H73+'Miseu Folo'!H73+Nchalo!H73+Nsanje!H73+Ngabu!H73 -> 0 | I73: =Bangula!I73+Chikwawa!I73+'Miseu Folo'!I73+Nchalo!I73+Nsanje!I73+Ngabu!I73 -> 0 | J73: =Bangula!J73+Chikwawa!J73+'Miseu Folo'!J73+Nchalo!J73+Nsanje!J73+Ngabu!J73 -> 0 | K73: =Bangula!K73+Chikwawa!K73+'Miseu Folo'!K73+Nchalo!K73+Nsanje!K73+Ngabu!K73 -> 0 | ... O73: =Bangula!O73+Chikwawa!O73+'Miseu Folo'!O73+Nchalo!O73+Nsanje!O73+Ngabu!O73 -> 0 | P73: =SUM(D73:O73) -> 2
B74: Done this Month Postpaid | C74: No | D74: =Bangula!D74+Chikwawa!D74+'Miseu Folo'!D74+Nchalo!D74+Nsanje!D74+Ngabu!D74 -> 1 | E74: =Bangula!E74+Chikwawa!E74+'Miseu Folo'!E74+Nchalo!E74+Nsanje!E74+Ngabu!E74 -> 0 | F74: =Bangula!F74+Chikwawa!F74+'Miseu Folo'!F74+Nchalo!F74+Nsanje!F74+Ngabu!F74 -> 0 | G74: =Bangula!G74+Chikwawa!G74+'Miseu Folo'!G74+Nchalo!G74+Nsanje!G74+Ngabu!G74 -> 1 | H74: =Bangula!H74+Chikwawa!H74+'Miseu Folo'!H74+Nchalo!H74+Nsanje!H74+Ngabu!H74 -> 0 | I74: =Bangula!I74+Chikwawa!I74+'Miseu Folo'!I74+Nchalo!I74+Nsanje!I74+Ngabu!I74 -> 0 | J74: =Bangula!J74+Chikwawa!J74+'Miseu Folo'!J74+Nchalo!J74+Nsanje!J74+Ngabu!J74 -> 0 | K74: =Bangula!K74+Chikwawa!K74+'Miseu Folo'!K74+Nchalo!K74+Nsanje!K74+Ngabu!K74 -> 0 | ... O74: =Bangula!O74+Chikwawa!O74+'Miseu Folo'!O74+Nchalo!O74+Nsanje!O74+Ngabu!O74 -> 0 | P74: =SUM(D74:O74) -> 2
B75: Done this Month Prepaid | C75: No | D75: =Bangula!D75+Chikwawa!D75+'Miseu Folo'!D75+Nchalo!D75+Nsanje!D75+Ngabu!D75 -> 0 | E75: =Bangula!E75+Chikwawa!E75+'Miseu Folo'!E75+Nchalo!E75+Nsanje!E75+Ngabu!E75 -> 0 | F75: =Bangula!F75+Chikwawa!F75+'Miseu Folo'!F75+Nchalo!F75+Nsanje!F75+Ngabu!F75 -> 0 | G75: =Bangula!G75+Chikwawa!G75+'Miseu Folo'!G75+Nchalo!G75+Nsanje!G75+Ngabu!G75 -> 0 | H75: =Bangula!H75+Chikwawa!H75+'Miseu Folo'!H75+Nchalo!H75+Nsanje!H75+Ngabu!H75 -> 0 | I75: =Bangula!I75+Chikwawa!I75+'Miseu Folo'!I75+Nchalo!I75+Nsanje!I75+Ngabu!I75 -> 0 | J75: =Bangula!J75+Chikwawa!J75+'Miseu Folo'!J75+Nchalo!J75+Nsanje!J75+Ngabu!J75 -> 0 | K75: =Bangula!K75+Chikwawa!K75+'Miseu Folo'!K75+Nchalo!K75+Nsanje!K75+Ngabu!K75 -> 0 | ... O75: =Bangula!O75+Chikwawa!O75+'Miseu Folo'!O75+Nchalo!O75+Nsanje!O75+Ngabu!O75 -> 0
B76: Total Done | C76: No | D76: =D74+D75 -> 1 | E76: =E74+E75 -> 0 | F76: =F74+F75 -> 0 | G76: =G74+G75 -> 1 | H76: =H74+H75 -> 0 | I76: =I74+I75 -> 0 | J76: =J74+J75 -> 0 | K76: =K74+K75 -> 0 | ... P76: =P74+P75 -> 2
B77: Carried Forward | C77: No | D77: =D72+D73-D76 -> 0 | E77: =E72+E73-E76 -> 0 | F77: =F72+F73-F76 -> 0 | G77: =G72+G73-G76 -> 0 | H77: =H72+H73-H76 -> 0 | I77: =I72+I73-I76 -> 0 | J77: =J72+J73-J76 -> 0 | K77: =K72+K73-K76 -> 0 | ... O77: =O72+O73-O76 -> 0 | P77: =P73+P74-P76 -> 2
A78: New Commercial/Industrial Water Connections | B78: Brought Forward | C78: No | D78: =Bangula!D78+Chikwawa!D78+'Miseu Folo'!D78+Nchalo!D78+Nsanje!D78+Ngabu!D78 -> 0 | E78: =Bangula!E78+Chikwawa!E78+'Miseu Folo'!E78+Nchalo!E78+Nsanje!E78+Ngabu!E78 -> 0 | F78: =Bangula!F78+Chikwawa!F78+'Miseu Folo'!F78+Nchalo!F78+Nsanje!F78+Ngabu!F78 -> 1 | G78: =Bangula!G78+Chikwawa!G78+'Miseu Folo'!G78+Nchalo!G78+Nsanje!G78+Ngabu!G78 -> 1 | H78: =Bangula!H78+Chikwawa!H78+'Miseu Folo'!H78+Nchalo!H78+Nsanje!H78+Ngabu!H78 -> 1 | I78: =Bangula!I78+Chikwawa!I78+'Miseu Folo'!I78+Nchalo!I78+Nsanje!I78+Ngabu!I78 -> 3 | J78: =Bangula!J78+Chikwawa!J78+'Miseu Folo'!J78+Nchalo!J78+Nsanje!J78+Ngabu!J78 -> 3 | K78: =Bangula!K78+Chikwawa!K78+'Miseu Folo'!K78+Nchalo!K78+Nsanje!K78+Ngabu!K78 -> 3 | ... O78: =Bangula!O78+Chikwawa!O78+'Miseu Folo'!O78+Nchalo!O78+Nsanje!O78+Ngabu!O78 -> 3 | P78: =D78 -> 0
B79: Applied this Month | C79: No | D79: =Bangula!D79+Chikwawa!D79+'Miseu Folo'!D79+Nchalo!D79+Nsanje!D79+Ngabu!D79 -> 0 | E79: =Bangula!E79+Chikwawa!E79+'Miseu Folo'!E79+Nchalo!E79+Nsanje!E79+Ngabu!E79 -> 1 | F79: =Bangula!F79+Chikwawa!F79+'Miseu Folo'!F79+Nchalo!F79+Nsanje!F79+Ngabu!F79 -> 1 | G79: =Bangula!G79+Chikwawa!G79+'Miseu Folo'!G79+Nchalo!G79+Nsanje!G79+Ngabu!G79 -> 0 | H79: =Bangula!H79+Chikwawa!H79+'Miseu Folo'!H79+Nchalo!H79+Nsanje!H79+Ngabu!H79 -> 3 | I79: =Bangula!I79+Chikwawa!I79+'Miseu Folo'!I79+Nchalo!I79+Nsanje!I79+Ngabu!I79 -> 0 | J79: =Bangula!J79+Chikwawa!J79+'Miseu Folo'!J79+Nchalo!J79+Nsanje!J79+Ngabu!J79 -> 0 | K79: =Bangula!K79+Chikwawa!K79+'Miseu Folo'!K79+Nchalo!K79+Nsanje!K79+Ngabu!K79 -> 0 | ... O79: =Bangula!O79+Chikwawa!O79+'Miseu Folo'!O79+Nchalo!O79+Nsanje!O79+Ngabu!O79 -> 0 | P79: =SUM(D79:O79) -> 5
B80: Done this Month Postpaid | C80: No | D80: =Bangula!D80+Chikwawa!D80+'Miseu Folo'!D80+Nchalo!D80+Nsanje!D80+Ngabu!D80 -> 0 | E80: =Bangula!E80+Chikwawa!E80+'Miseu Folo'!E80+Nchalo!E80+Nsanje!E80+Ngabu!E80 -> 0 | F80: =Bangula!F80+Chikwawa!F80+'Miseu Folo'!F80+Nchalo!F80+Nsanje!F80+Ngabu!F80 -> 1 | G80: =Bangula!G80+Chikwawa!G80+'Miseu Folo'!G80+Nchalo!G80+Nsanje!G80+Ngabu!G80 -> 0 | H80: =Bangula!H80+Chikwawa!H80+'Miseu Folo'!H80+Nchalo!H80+Nsanje!H80+Ngabu!H80 -> 0 | I80: =Bangula!I80+Chikwawa!I80+'Miseu Folo'!I80+Nchalo!I80+Nsanje!I80+Ngabu!I80 -> 0 | J80: =Bangula!J80+Chikwawa!J80+'Miseu Folo'!J80+Nchalo!J80+Nsanje!J80+Ngabu!J80 -> 0 | K80: =Bangula!K80+Chikwawa!K80+'Miseu Folo'!K80+Nchalo!K80+Nsanje!K80+Ngabu!K80 -> 0 | ... O80: =Bangula!O80+Chikwawa!O80+'Miseu Folo'!O80+Nchalo!O80+Nsanje!O80+Ngabu!O80 -> 0
B81: Done this Month Prepaid | C81: No | D81: =Bangula!D81+Chikwawa!D81+'Miseu Folo'!D81+Nchalo!D81+Nsanje!D81+Ngabu!D81 -> 0 | E81: =Bangula!E81+Chikwawa!E81+'Miseu Folo'!E81+Nchalo!E81+Nsanje!E81+Ngabu!E81 -> 0 | F81: =Bangula!F81+Chikwawa!F81+'Miseu Folo'!F81+Nchalo!F81+Nsanje!F81+Ngabu!F81 -> 0 | G81: =Bangula!G81+Chikwawa!G81+'Miseu Folo'!G81+Nchalo!G81+Nsanje!G81+Ngabu!G81 -> 0 | H81: =Bangula!H81+Chikwawa!H81+'Miseu Folo'!H81+Nchalo!H81+Nsanje!H81+Ngabu!H81 -> 1 | I81: =Bangula!I81+Chikwawa!I81+'Miseu Folo'!I81+Nchalo!I81+Nsanje!I81+Ngabu!I81 -> 0 | J81: =Bangula!J81+Chikwawa!J81+'Miseu Folo'!J81+Nchalo!J81+Nsanje!J81+Ngabu!J81 -> 0 | K81: =Bangula!K81+Chikwawa!K81+'Miseu Folo'!K81+Nchalo!K81+Nsanje!K81+Ngabu!K81 -> 0 | ... O81: =Bangula!O81+Chikwawa!O81+'Miseu Folo'!O81+Nchalo!O81+Nsanje!O81+Ngabu!O81 -> 0 | P81: =SUM(D81:O81) -> 1
B82: Total Done | C82: No | D82: =D81+D80 -> 0 | E82: =E81+E80 -> 0 | F82: =F81+F80 -> 1 | G82: =G81+G80 -> 0 | H82: =H81+H80 -> 1 | I82: =I81+I80 -> 0 | J82: =J81+J80 -> 0 | K82: =K81+K80 -> 0 | ... P82: =P81+P80 -> 1
B83: Carried Forward | C83: No | D83: =D78+D79-D82 -> 0 | E83: =E78+E79-E82 -> 1 | F83: =F78+F79-F82 -> 1 | G83: =G78+G79-G82 -> 1 | H83: =H78+H79-H82 -> 3 | I83: =I78+I79-I82 -> 3 | J83: =J78+J79-J82 -> 3 | K83: =K78+K79-K82 -> 3 | ... P83: =P78+P79-P82 -> 4
A84: New CWP | B84: Brought Forward | C84: No | D84: =Bangula!D84+Chikwawa!D84+'Miseu Folo'!D84+Nchalo!D84+Nsanje!D84+Ngabu!D84 -> 0 | E84: =Bangula!E84+Chikwawa!E84+'Miseu Folo'!E84+Nchalo!E84+Nsanje!E84+Ngabu!E84 -> 0 | F84: =Bangula!F84+Chikwawa!F84+'Miseu Folo'!F84+Nchalo!F84+Nsanje!F84+Ngabu!F84 -> 0 | G84: =Bangula!G84+Chikwawa!G84+'Miseu Folo'!G84+Nchalo!G84+Nsanje!G84+Ngabu!G84 -> 0 | H84: =Bangula!H84+Chikwawa!H84+'Miseu Folo'!H84+Nchalo!H84+Nsanje!H84+Ngabu!H84 -> 0 | I84: =Bangula!I84+Chikwawa!I84+'Miseu Folo'!I84+Nchalo!I84+Nsanje!I84+Ngabu!I84 -> 0 | J84: =Bangula!J84+Chikwawa!J84+'Miseu Folo'!J84+Nchalo!J84+Nsanje!J84+Ngabu!J84 -> 0 | K84: =Bangula!K84+Chikwawa!K84+'Miseu Folo'!K84+Nchalo!K84+Nsanje!K84+Ngabu!K84 -> 0 | ... O84: =Bangula!O84+Chikwawa!O84+'Miseu Folo'!O84+Nchalo!O84+Nsanje!O84+Ngabu!O84 -> 0 | P84: =D84 -> 0
B85: Applied this Month | C85: No | D85: =Bangula!D85+Chikwawa!D85+'Miseu Folo'!D85+Nchalo!D85+Nsanje!D85+Ngabu!D85 -> 0 | E85: =Bangula!E85+Chikwawa!E85+'Miseu Folo'!E85+Nchalo!E85+Nsanje!E85+Ngabu!E85 -> 0 | F85: =Bangula!F85+Chikwawa!F85+'Miseu Folo'!F85+Nchalo!F85+Nsanje!F85+Ngabu!F85 -> 0 | G85: =Bangula!G85+Chikwawa!G85+'Miseu Folo'!G85+Nchalo!G85+Nsanje!G85+Ngabu!G85 -> 0 | H85: =Bangula!H85+Chikwawa!H85+'Miseu Folo'!H85+Nchalo!H85+Nsanje!H85+Ngabu!H85 -> 0 | I85: =Bangula!I85+Chikwawa!I85+'Miseu Folo'!I85+Nchalo!I85+Nsanje!I85+Ngabu!I85 -> 1 | J85: =Bangula!J85+Chikwawa!J85+'Miseu Folo'!J85+Nchalo!J85+Nsanje!J85+Ngabu!J85 -> 0 | K85: =Bangula!K85+Chikwawa!K85+'Miseu Folo'!K85+Nchalo!K85+Nsanje!K85+Ngabu!K85 -> 0 | ... O85: =Bangula!O85+Chikwawa!O85+'Miseu Folo'!O85+Nchalo!O85+Nsanje!O85+Ngabu!O85 -> 0 | P85: =SUM(D85:O85) -> 1
B86: Done this Month Postpaid | C86: No | D86: =Bangula!D86+Chikwawa!D86+'Miseu Folo'!D86+Nchalo!D86+Nsanje!D86+Ngabu!D86 -> 0 | E86: =Bangula!E86+Chikwawa!E86+'Miseu Folo'!E86+Nchalo!E86+Nsanje!E86+Ngabu!E86 -> 0 | F86: =Bangula!F86+Chikwawa!F86+'Miseu Folo'!F86+Nchalo!F86+Nsanje!F86+Ngabu!F86 -> 0 | G86: =Bangula!G86+Chikwawa!G86+'Miseu Folo'!G86+Nchalo!G86+Nsanje!G86+Ngabu!G86 -> 0 | H86: =Bangula!H86+Chikwawa!H86+'Miseu Folo'!H86+Nchalo!H86+Nsanje!H86+Ngabu!H86 -> 0 | I86: =Bangula!I86+Chikwawa!I86+'Miseu Folo'!I86+Nchalo!I86+Nsanje!I86+Ngabu!I86 -> 1 | J86: =Bangula!J86+Chikwawa!J86+'Miseu Folo'!J86+Nchalo!J86+Nsanje!J86+Ngabu!J86 -> 0 | K86: =Bangula!K86+Chikwawa!K86+'Miseu Folo'!K86+Nchalo!K86+Nsanje!K86+Ngabu!K86 -> 0 | ... O86: =Bangula!O86+Chikwawa!O86+'Miseu Folo'!O86+Nchalo!O86+Nsanje!O86+Ngabu!O86 -> 0
B87: Done this Month Prepaid | C87: No | D87: =Bangula!D87+Chikwawa!D87+'Miseu Folo'!D87+Nchalo!D87+Nsanje!D87+Ngabu!D87 -> 0 | E87: =Bangula!E87+Chikwawa!E87+'Miseu Folo'!E87+Nchalo!E87+Nsanje!E87+Ngabu!E87 -> 0 | F87: =Bangula!F87+Chikwawa!F87+'Miseu Folo'!F87+Nchalo!F87+Nsanje!F87+Ngabu!F87 -> 0 | G87: =Bangula!G87+Chikwawa!G87+'Miseu Folo'!G87+Nchalo!G87+Nsanje!G87+Ngabu!G87 -> 0 | H87: =Bangula!H87+Chikwawa!H87+'Miseu Folo'!H87+Nchalo!H87+Nsanje!H87+Ngabu!H87 -> 0 | I87: =Bangula!I87+Chikwawa!I87+'Miseu Folo'!I87+Nchalo!I87+Nsanje!I87+Ngabu!I87 -> 0 | J87: =Bangula!J87+Chikwawa!J87+'Miseu Folo'!J87+Nchalo!J87+Nsanje!J87+Ngabu!J87 -> 0 | K87: =Bangula!K87+Chikwawa!K87+'Miseu Folo'!K87+Nchalo!K87+Nsanje!K87+Ngabu!K87 -> 0 | ... O87: =Bangula!O87+Chikwawa!O87+'Miseu Folo'!O87+Nchalo!O87+Nsanje!O87+Ngabu!O87 -> 0 | P87: =SUM(D87:O87) -> 0
B88: Total Done | C88: No | D88: =D87+D86 -> 0 | E88: =E87+E86 -> 0 | F88: =F87+F86 -> 0 | G88: =G87+G86 -> 0 | H88: =H87+H86 -> 0 | I88: =I87+I86 -> 1 | J88: =J87+J86 -> 0 | K88: =K87+K86 -> 0 | ... O88: =O87+O86 -> 0
B89: Carried Forward | C89: No | D89: =D84+D85-D88 -> 0 | E89: =E84+E85-E88 -> 0 | F89: =F84+F85-F88 -> 0 | G89: =G84+G85-G88 -> 0 | H89: =H84+H85-H88 -> 0 | I89: =I84+I85-I88 -> 0 | J89: =J84+J85-J88 -> 0 | K89: =K84+K85-K88 -> 0 | ... O89: =O84+O85-O88 -> 0 | P89: =P84+P85-P86-P87 -> 1
A90: Aggregated New Water connections | B90: Brought Forward | C90: No | D90: =D66+D72+D78+D84 -> 779 | E90: =E66+E72+E78+E84 -> 766 | F90: =F66+F72+F78+F84 -> 751 | G90: =G66+G72+G78+G84 -> 745 | H90: =H66+H72+H78+H84 -> 854 | I90: =I66+I72+I78+I84 -> 851 | J90: =J66+J72+J78+J84 -> 826 | K90: =K66+K72+K78+K84 -> 801 | ... O90: =O66+O72+O78+O84 -> 717 | P90: =D90 -> 779
B91: Applied this Month | C91: No | D91: =D67+D73+D79+D85 -> 58 | E91: =E67+E73+E79+E85 -> 47 | F91: =F67+F73+F79+F85 -> 100 | G91: =G67+G73+G79+G85 -> 243 | H91: =H67+H73+H79+H85 -> 106 | I91: =I67+I73+I79+I85 -> 77 | J91: =J67+J73+J79+J85 -> 51 | K91: =K67+K73+K79+K85 -> 52 | ... O91: =O67+O73+O79+O85 -> 48 | P91: =SUM(D91:O91) -> 902
B92: Done this Month Postpaid | C92: No | D92: =D68+D74+D80+D86 -> 71 | E92: =E68+E74+E80+E86 -> 62 | F92: =F68+F74+F80+F86 -> 106 | G92: =G68+G74+G80+G86 -> 134 | H92: =H68+H74+H80+H86 -> 106 | I92: =I68+I74+I80+I86 -> 76 | J92: =J68+J74+J80+J86 -> 76 | K92: =K68+K74+K80+K86 -> 68 | ... O92: =O68+O74+O80+O86 -> 67 | P92: =SUM(D92:O92) -> 943
B93: Done this Month Prepaid | D93: =D69+D75+D81+D87 -> 0 | E93: =E69+E75+E81+E87 -> 0 | F93: =F69+F75+F81+F87 -> 0 | G93: =G69+G75+G81+G87 -> 0 | H93: =H69+H75+H81+H87 -> 3 | I93: =I69+I75+I81+I87 -> 26 | J93: =J69+J75+J81+J87 -> 0 | K93: =K69+K75+K81+K87 -> 7 | ... O93: =O69+O75+O81+O87 -> 0 | P93: =SUM(D93:O93) -> 40
B94: Total Done | C94: No | D94: =D93+D92 -> 71 | E94: =E93+E92 -> 62 | F94: =F93+F92 -> 106 | G94: =G93+G92 -> 134 | H94: =H93+H92 -> 109 | I94: =I93+I92 -> 102 | J94: =J93+J92 -> 76 | K94: =K93+K92 -> 75 | ... P94: =P93+P92 -> 983
B95: Carried Forward | C95: No | D95: =D90+D91-D94 -> 766 | E95: =E90+E91-E94 -> 751 | F95: =F90+F91-F94 -> 745 | G95: =G90+G91-G94 -> 854 | H95: =H90+H91-H94 -> 851 | I95: =I90+I91-I94 -> 826 | J95: =J90+J91-J94 -> 801 | K95: =K90+K91-K94 -> 778 | ... P95: =P90+P91-P94 -> 698
A97: Prepaid Metering
A98: Prepaid Meters Installed | C98: No | D98: =Bangula!D98+Chikwawa!D98+'Miseu Folo'!D98+Nchalo!D98+Nsanje!D98+Ngabu!D98 -> 0 | E98: =Bangula!E98+Chikwawa!E98+'Miseu Folo'!E98+Nchalo!E98+Nsanje!E98+Ngabu!E98 -> 0 | F98: =Bangula!F98+Chikwawa!F98+'Miseu Folo'!F98+Nchalo!F98+Nsanje!F98+Ngabu!F98 -> 5 | G98: =Bangula!G98+Chikwawa!G98+'Miseu Folo'!G98+Nchalo!G98+Nsanje!G98+Ngabu!G98 -> 0 | H98: =Bangula!H98+Chikwawa!H98+'Miseu Folo'!H98+Nchalo!H98+Nsanje!H98+Ngabu!H98 -> 0 | I98: =Bangula!I98+Chikwawa!I98+'Miseu Folo'!I98+Nchalo!I98+Nsanje!I98+Ngabu!I98 -> 0 | J98: =Bangula!J98+Chikwawa!J98+'Miseu Folo'!J98+Nchalo!J98+Nsanje!J98+Ngabu!J98 -> 0 | K98: =Bangula!K98+Chikwawa!K98+'Miseu Folo'!K98+Nchalo!K98+Nsanje!K98+Ngabu!K98 -> 0 | ... O98: =Bangula!O98+Chikwawa!O98+'Miseu Folo'!O98+Nchalo!O98+Nsanje!O98+Ngabu!O98 -> 0 | P98: =SUM(D98:O98) -> 5
A100: Active and Disconnected Accounts
A101: Disconnected Individual Accounts | C101: No | D101: =Bangula!D101+Chikwawa!D101+'Miseu Folo'!D101+Nchalo!D101+Nsanje!D101+Ngabu!D101 -> 2300 | E101: =Bangula!E101+Chikwawa!E101+'Miseu Folo'!E101+Nchalo!E101+Nsanje!E101+Ngabu!E101 -> 2332 | F101: =Bangula!F101+Chikwawa!F101+'Miseu Folo'!F101+Nchalo!F101+Nsanje!F101+Ngabu!F101 -> 2349 | G101: =Bangula!G101+Chikwawa!G101+'Miseu Folo'!G101+Nchalo!G101+Nsanje!G101+Ngabu!G101 -> 2387 | H101: =Bangula!H101+Chikwawa!H101+'Miseu Folo'!H101+Nchalo!H101+Nsanje!H101+Ngabu!H101 -> 2647 | I101: =Bangula!I101+Chikwawa!I101+'Miseu Folo'!I101+Nchalo!I101+Nsanje!I101+Ngabu!I101 -> 2640 | J101: =Bangula!J101+Chikwawa!J101+'Miseu Folo'!J101+Nchalo!J101+Nsanje!J101+Ngabu!J101 -> 2627 | K101: =Bangula!K101+Chikwawa!K101+'Miseu Folo'!K101+Nchalo!K101+Nsanje!K101+Ngabu!K101 -> 2637 | ... O101: =Bangula!O101+Chikwawa!O101+'Miseu Folo'!O101+Nchalo!O101+Nsanje!O101+Ngabu!O101 -> 2806 | P101: =O101 -> 2806
A102: Disconnected institutional Accounts | C102: No | D102: =Bangula!D102+Chikwawa!D102+'Miseu Folo'!D102+Nchalo!D102+Nsanje!D102+Ngabu!D102 -> 72 | E102: =Bangula!E102+Chikwawa!E102+'Miseu Folo'!E102+Nchalo!E102+Nsanje!E102+Ngabu!E102 -> 67 | F102: =Bangula!F102+Chikwawa!F102+'Miseu Folo'!F102+Nchalo!F102+Nsanje!F102+Ngabu!F102 -> 67 | G102: =Bangula!G102+Chikwawa!G102+'Miseu Folo'!G102+Nchalo!G102+Nsanje!G102+Ngabu!G102 -> 69 | H102: =Bangula!H102+Chikwawa!H102+'Miseu Folo'!H102+Nchalo!H102+Nsanje!H102+Ngabu!H102 -> 70 | I102: =Bangula!I102+Chikwawa!I102+'Miseu Folo'!I102+Nchalo!I102+Nsanje!I102+Ngabu!I102 -> 71 | J102: =Bangula!J102+Chikwawa!J102+'Miseu Folo'!J102+Nchalo!J102+Nsanje!J102+Ngabu!J102 -> 71 | K102: =Bangula!K102+Chikwawa!K102+'Miseu Folo'!K102+Nchalo!K102+Nsanje!K102+Ngabu!K102 -> 75 | ... O102: =Bangula!O102+Chikwawa!O102+'Miseu Folo'!O102+Nchalo!O102+Nsanje!O102+Ngabu!O102 -> 107 | P102: =O102 -> 107
A103: Disconnected Commercial/Industrial Accounts | C103: No | D103: =Bangula!D103+Chikwawa!D103+'Miseu Folo'!D103+Nchalo!D103+Nsanje!D103+Ngabu!D103 -> 62 | E103: =Bangula!E103+Chikwawa!E103+'Miseu Folo'!E103+Nchalo!E103+Nsanje!E103+Ngabu!E103 -> 61 | F103: =Bangula!F103+Chikwawa!F103+'Miseu Folo'!F103+Nchalo!F103+Nsanje!F103+Ngabu!F103 -> 62 | G103: =Bangula!G103+Chikwawa!G103+'Miseu Folo'!G103+Nchalo!G103+Nsanje!G103+Ngabu!G103 -> 65 | H103: =Bangula!H103+Chikwawa!H103+'Miseu Folo'!H103+Nchalo!H103+Nsanje!H103+Ngabu!H103 -> 63 | I103: =Bangula!I103+Chikwawa!I103+'Miseu Folo'!I103+Nchalo!I103+Nsanje!I103+Ngabu!I103 -> 63 | J103: =Bangula!J103+Chikwawa!J103+'Miseu Folo'!J103+Nchalo!J103+Nsanje!J103+Ngabu!J103 -> 63 | K103: =Bangula!K103+Chikwawa!K103+'Miseu Folo'!K103+Nchalo!K103+Nsanje!K103+Ngabu!K103 -> 67 | ... O103: =Bangula!O103+Chikwawa!O103+'Miseu Folo'!O103+Nchalo!O103+Nsanje!O103+Ngabu!O103 -> 111 | P103: =O103 -> 111
A104: Disconnected CWP | C104: No | D104: =Bangula!D104+Chikwawa!D104+'Miseu Folo'!D104+Nchalo!D104+Nsanje!D104+Ngabu!D104 -> 65 | E104: =Bangula!E104+Chikwawa!E104+'Miseu Folo'!E104+Nchalo!E104+Nsanje!E104+Ngabu!E104 -> 74 | F104: =Bangula!F104+Chikwawa!F104+'Miseu Folo'!F104+Nchalo!F104+Nsanje!F104+Ngabu!F104 -> 74 | G104: =Bangula!G104+Chikwawa!G104+'Miseu Folo'!G104+Nchalo!G104+Nsanje!G104+Ngabu!G104 -> 74 | H104: =Bangula!H104+Chikwawa!H104+'Miseu Folo'!H104+Nchalo!H104+Nsanje!H104+Ngabu!H104 -> 76 | I104: =Bangula!I104+Chikwawa!I104+'Miseu Folo'!I104+Nchalo!I104+Nsanje!I104+Ngabu!I104 -> 76 | J104: =Bangula!J104+Chikwawa!J104+'Miseu Folo'!J104+Nchalo!J104+Nsanje!J104+Ngabu!J104 -> 76 | K104: =Bangula!K104+Chikwawa!K104+'Miseu Folo'!K104+Nchalo!K104+Nsanje!K104+Ngabu!K104 -> 76 | ... O104: =Bangula!O104+Chikwawa!O104+'Miseu Folo'!O104+Nchalo!O104+Nsanje!O104+Ngabu!O104 -> 76 | P104: =O104 -> 76
A105: Total Disconnected Accounts | C105: No | D105: =SUM(D101:D104) -> 2499 | E105: =SUM(E101:E104) -> 2534 | F105: =SUM(F101:F104) -> 2552 | G105: =SUM(G101:G104) -> 2595 | H105: =SUM(H101:H104) -> 2856 | I105: =SUM(I101:I104) -> 2850 | J105: =SUM(J101:J104) -> 2837 | K105: =SUM(K101:K104) -> 2855 | ... O105: =SUM(O101:O104) -> 3100 | P105: =O105 -> 3100
A106: Postpaid Consumers
...

Sheet 1st QTR
A1: SOUTHERN REGION WATER BOARD
A3: MONTHLY REPORTS - 2023/2024
A4: NGABU ZONE
A5: NGABU ZONE
A7: PARAMETERS | C7: UNITS | D7: Bangula | E7: Chikwawa | F7: Miseu Folo | G7: Nchalo | H7: Nsanje | I7: Ngabu | J7: TOTALS
A8: PRODUCTION
A9: Volume Produced | C9: m3 | D9: =Bangula!D9+Bangula!E9+Bangula!F9 -> 35203 | E9: =Chikwawa!D9+Chikwawa!E9+Chikwawa!F9 -> 86703 | F9: ='Miseu Folo'!D9+'Miseu Folo'!E9+'Miseu Folo'!F9 -> 9507 | G9: =Nchalo!D9+Nchalo!E9+Nchalo!F9 -> 71651 | H9: =Nsanje!D9+Nsanje!E9+Nsanje!F9 -> 59952 | I9: =Ngabu!D9+Ngabu!E9+Ngabu!F9 -> 56667 | J9: =SUM(D9:I9) -> 319683
A10: REVENUE WATER - POSTPAID
A11: Volume Billed Individuals | C11: m3 | D11: =Bangula!D11+Bangula!E11+Bangula!F11 -> 14750 | E11: =Chikwawa!D11+Chikwawa!E11+Chikwawa!F11 -> 50320 | F11: ='Miseu Folo'!D11+'Miseu Folo'!E11+'Miseu Folo'!F11 -> 1173 | G11: =Nchalo!D11+Nchalo!E11+Nchalo!F11 -> 38649 | H11: =Nsanje!D11+Nsanje!E11+Nsanje!F11 -> 24747 | I11: =Ngabu!D11+Ngabu!E11+Ngabu!F11 -> 16748 | J11: =SUM(D11:I11) -> 146387
A12: Volume Billed CWPs | C12: m3 | D12: =Bangula!D12+Bangula!E12+Bangula!F12 -> 5600 | E12: =Chikwawa!D12+Chikwawa!E12+Chikwawa!F12 -> 2778 | F12: ='Miseu Folo'!D12+'Miseu Folo'!E12+'Miseu Folo'!F12 -> 0 | G12: =Nchalo!D12+Nchalo!E12+Nchalo!F12 -> 2040 | H12: =Nsanje!D12+Nsanje!E12+Nsanje!F12 -> 2259 | I12: =Ngabu!D12+Ngabu!E12+Ngabu!F12 -> 2857 | J12: =SUM(D12:I12) -> 15534
A13: Volume Billed Institutions | C13: m3 | D13: =Bangula!D13+Bangula!E13+Bangula!F13 -> 180 | E13: =Chikwawa!D13+Chikwawa!E13+Chikwawa!F13 -> 848 | F13: ='Miseu Folo'!D13+'Miseu Folo'!E13+'Miseu Folo'!F13 -> 5 | G13: =Nchalo!D13+Nchalo!E13+Nchalo!F13 -> 95 | H13: =Nsanje!D13+Nsanje!E13+Nsanje!F13 -> 329 | I13: =Ngabu!D13+Ngabu!E13+Ngabu!F13 -> 846 | J13: =SUM(D13:I13) -> 2303
A14: Volume Billed Commercial/Industrial | C14: m3 | D14: =Bangula!D14+Bangula!E14+Bangula!F14 -> 25 | E14: =Chikwawa!D14+Chikwawa!E14+Chikwawa!F14 -> 247 | F14: ='Miseu Folo'!D14+'Miseu Folo'!E14+'Miseu Folo'!F14 -> 36 | G14: =Nchalo!D14+Nchalo!E14+Nchalo!F14 -> 650 | H14: =Nsanje!D14+Nsanje!E14+Nsanje!F14 -> 21 | I14: =Ngabu!D14+Ngabu!E14+Ngabu!F14 -> 75 | J14: =SUM(D14:I14) -> 1054
A15: Total Volume Billed Post Paid | C15: m3 | D15: =SUM(D11:D14) -> 20555 | E15: =SUM(E11:E14) -> 54193 | F15: =SUM(F11:F14) -> 1214 | G15: =SUM(G11:G14) -> 41434 | H15: =SUM(H11:H14) -> 27356 | I15: =SUM(I11:I14) -> 20526 | J15: =SUM(J11:J14) -> 165278
A16: REVENUE WATER - PREPAID
A17: Individuals | C17: m3 | D17: =Bangula!D17+Bangula!E17+Bangula!F17 -> 1796 | E17: =Chikwawa!D17+Chikwawa!E17+Chikwawa!F17 -> 2252 | F17: ='Miseu Folo'!D17+'Miseu Folo'!E17+'Miseu Folo'!F17 -> 0 | G17: =Nchalo!D17+Nchalo!E17+Nchalo!F17 -> 0 | H17: =Nsanje!D17+Nsanje!E17+Nsanje!F17 -> 4491 | I17: =Ngabu!D17+Ngabu!E17+Ngabu!F17 -> 0 | J17: =SUM(D17:I17) -> 8539
A18: CWPs | C18: m3 | D18: =Bangula!D18+Bangula!E18+Bangula!F18 -> 0 | E18: =Chikwawa!D18+Chikwawa!E18+Chikwawa!F18 -> 0 | F18: ='Miseu Folo'!D18+'Miseu Folo'!E18+'Miseu Folo'!F18 -> 0 | G18: =Nchalo!D18+Nchalo!E18+Nchalo!F18 -> 0 | H18: =Nsanje!D18+Nsanje!E18+Nsanje!F18 -> 0 | I18: =Ngabu!D18+Ngabu!E18+Ngabu!F18 -> 0 | J18: =SUM(D18:H18) -> 0
A19: Institutions | C19: m3 | D19: =Bangula!D19+Bangula!E19+Bangula!F19 -> 6408.9 | E19: =Chikwawa!D19+Chikwawa!E19+Chikwawa!F19 -> 17019 | F19: ='Miseu Folo'!D19+'Miseu Folo'!E19+'Miseu Folo'!F19 -> 6535.2 | G19: =Nchalo!D19+Nchalo!E19+Nchalo!F19 -> 7919.8 | H19: =Nsanje!D19+Nsanje!E19+Nsanje!F19 -> 12962 | I19: =Ngabu!D19+Ngabu!E19+Ngabu!F19 -> 9665 | J19: =SUM(D19:H19) -> 50844.9
A20: Commercial/Industrial | C20: m3 | D20: =Bangula!D20+Bangula!E20+Bangula!F20 -> 264 | E20: =Chikwawa!D20+Chikwawa!E20+Chikwawa!F20 -> 943 | F20: ='Miseu Folo'!D20+'Miseu Folo'!E20+'Miseu Folo'!F20 -> 0 | G20: =Nchalo!D20+Nchalo!E20+Nchalo!F20 -> 0 | H20: =Nsanje!D20+Nsanje!E20+Nsanje!F20 -> 529 | I20: =Ngabu!D20+Ngabu!E20+Ngabu!F20 -> 0 | J20: =SUM(D20:H20) -> 1736
A21: Total Volume Prepaid | C21: m3 | D21: =SUM(D17:D20) -> 8468.9 | E21: =SUM(E17:E20) -> 20214 | F21: =SUM(F17:F20) -> 6535.2 | G21: =SUM(G17:G20) -> 7919.8 | H21: =SUM(H17:H20) -> 17982 | I21: =SUM(I17:I20) -> 9665 | J21: =SUM(J17:J20) -> 61119.9
A22: TOTAL REVENUE WATER | C22: m3 | D22: =D21+D15 -> 29023.9 | E22: =E21+E15 -> 74407 | F22: =F21+F15 -> 7749.2 | G22: =G21+G15 -> 49353.8 | H22: =H21+H15 -> 45338 | I22: =I21+I15 -> 30191 | J22: =J21+J15 -> 226397.9
A23: NON-REVENUE WATER (NRW)
A24: Non-Revenue Water (NRW) | B24: Volume | C24: m3 | D24: =D9-D22 -> 6179.1 | E24: =E9-E22 -> 12296 | F24: =F9-F22 -> 1757.8 | G24: =G9-G22 -> 22297.2 | H24: =H9-H22 -> 14614 | I24: =I9-I22 -> 26476 | J24: =J9-J22 -> 93285.1
B25: Percentage | C25: % | D25: =D24/D9 -> 0.17552765 | E25: =E24/E9 -> 0.14181747 | F25: =F24/F9 -> 0.18489534 | G25: =G24/G9 -> 0.31119175 | H25: =H24/H9 -> 0.24376168 | I25: =I24/I9 -> 0.46722078 | J25: =J24/J9 -> 0.29180501
A26: OPERATING EXPENSES
A27: Chemicals
A28: Chemical | B28: Rate(MK/kg)
A29: Chlorine | B29: 3525.29 | C29: kg | D29: =Bangula!D29+Bangula!E29+Bangula!F29 -> 40 | E29: =Chikwawa!D29+Chikwawa!E29+Chikwawa!F29 -> 90 | F29: ='Miseu Folo'!D29+'Miseu Folo'!E29+'Miseu Folo'!F29 -> 20.5 | G29: =Nchalo!D29+Nchalo!E29+Nchalo!F29 -> 53 | H29: =Nsanje!D29+Nsanje!E29+Nsanje!F29 -> 30 | I29: =Ngabu!D29+Ngabu!E29+Ngabu!F29 -> 58 | J29: =SUM(D29:I29) -> 291.5
C30: kg/mg litre | D30: =D29/(D9/1000) -> 1.1362668 | E30: =E29/(E9/1000) -> 1.0380264 | F30: =F29/(F9/1000) -> 2.1563059 | G30: =G29/(G9/1000) -> 0.73969658 | H30: =H29/(H9/1000) -> 0.50040032 | I30: =I29/(I9/1000) -> 1.0235234 | J30: =J29/(J9/1000) -> 0.91184079
A31: Aluminium sulphate | C31: kg | D31: =Bangula!D31+Bangula!E31+Bangula!F31 -> 0 | E31: =Chikwawa!D31+Chikwawa!E31+Chikwawa!F31 -> 0 | F31: ='Miseu Folo'!D31+'Miseu Folo'!E31+'Miseu Folo'!F31 -> 0 | G31: =Nchalo!D31+Nchalo!E31+Nchalo!F31 -> 0 | H31: =Nsanje!D31+Nsanje!E31+Nsanje!F31 -> 0 | I31: =Ngabu!D31+Ngabu!E31+Ngabu!F31 -> 0 | J31: =SUM(D31:I31) -> 0
B32: 1060.01 | C32: kg/mg litre | D32: =D31/(D9/1000) -> 0 | E32: =E31/(E9/1000) -> 0 | F32: =F31/(F9/1000) -> 0 | G32: =G31/(G9/1000) -> 0 | H32: =H31/(H9/1000) -> 0 | I32: =Ngabu!D32+Ngabu!E32+Ngabu!F32 -> 0 | J32: =J31/(J9/1000) -> 0
A33: Soda | C33: kg | D33: =Bangula!D33+Bangula!E33+Bangula!F33 -> 0 | E33: =Chikwawa!D33+Chikwawa!E33+Chikwawa!F33 -> 0 | F33: ='Miseu Folo'!D33+'Miseu Folo'!E33+'Miseu Folo'!F33 -> 0 | G33: =Nchalo!D33+Nchalo!E33+Nchalo!F33 -> 0 | H33: =Nsanje!D33+Nsanje!E33+Nsanje!F33 -> 0 | I33: =Ngabu!D33+Ngabu!E33+Ngabu!F33 -> 0 | J33: =SUM(D33:I33) -> 0
B34: 1228.29 | C34: kg/mg litre | D34: =D33/(D9/1000) -> 0 | E34: =E33/(E9/1000) -> 0 | F34: =F33/(F9/1000) -> 0 | G34: =G33/(G9/1000) -> 0 | H34: =H33/(H9/1000) -> 0 | I34: =Ngabu!D34+Ngabu!E34+Ngabu!F34 -> 0 | J34: =J33/(J9/1000) -> 0
A35: Algae floc | C35: litres | D35: =Bangula!D35+Bangula!E35+Bangula!F35 -> 0 | E35: =Chikwawa!D35+Chikwawa!E35+Chikwawa!F35 -> 0 | F35: ='Miseu Folo'!D35+'Miseu Folo'!E35+'Miseu Folo'!F35 -> 0 | G35: =Nchalo!D35+Nchalo!E35+Nchalo!F35 -> 0 | H35: =Nsanje!D35+Nsanje!E35+Nsanje!F35 -> 0 | I35: =Ngabu!D35+Ngabu!E35+Ngabu!F35 -> 0 | J35: =SUM(D35:I35) -> 0
B36: 3726.73 | C36: litres/mg litre | D36: =D35/(D11/1000) -> 0 | E36: =E35/(E11/1000) -> 0 | F36: =F35/(F11/1000) -> 0 | G36: =G35/(G11/1000) -> 0 | H36: =H35/(H11/1000) -> 0 | I36: =Ngabu!D36+Ngabu!E36+Ngabu!F36 -> 0 | J36: =J35/(J11/1000) -> 0
A37: Sud floc | C37: litres | D37: =Bangula!D37+Bangula!E37+Bangula!F37 -> 0 | E37: =Chikwawa!D37+Chikwawa!E37+Chikwawa!F37 -> 0 | F37: ='Miseu Folo'!D37+'Miseu Folo'!E37+'Miseu Folo'!F37 -> 0 | G37: =Nchalo!D37+Nchalo!E37+Nchalo!F37 -> 0 | H37: =Nsanje!D37+Nsanje!E37+Nsanje!F37 -> 0 | I37: =Ngabu!D37+Ngabu!E37+Ngabu!F37 -> 0 | J37: =SUM(D37:I37) -> 0
B38: 3951.59 | C38: litres/mg litre | D38: =D37/(D13/1000) -> 0 | E38: =E37/(E13/1000) -> 0 | F38: =F37/(F13/1000) -> 0 | G38: =G37/(G13/1000) -> 0 | H38: =H37/(H13/1000) -> 0 | I38: =Ngabu!D38+Ngabu!E38+Ngabu!F38 -> 0 | J38: =J37/(J13/1000) -> 0
A39: Potasium permanganate | C39: kg | D39: =Bangula!D39+Bangula!E39+Bangula!F39 -> 0 | E39: =Chikwawa!D39+Chikwawa!E39+Chikwawa!F39 -> 0 | F39: ='Miseu Folo'!D39+'Miseu Folo'!E39+'Miseu Folo'!F39 -> 0 | G39: =Nchalo!D39+Nchalo!E39+Nchalo!F39 -> 0 | H39: =Nsanje!D39+Nsanje!E39+Nsanje!F39 -> 0 | I39: =Ngabu!D39+Ngabu!E39+Ngabu!F39 -> 0 | J39: =SUM(D39:I39) -> 0
B40: 1950 | C40: kg/mg litre | D40: =D39/(D9/1000) -> 0 | E40: =E39/(E9/1000) -> 0 | F40: =F39/(F9/1000) -> 0 | G40: =G39/(G9/1000) -> 0 | H40: =H39/(H9/1000) -> 0 | I40: =Ngabu!D40+Ngabu!E40+Ngabu!F40 -> 0 | J40: =J39/(J9/1000) -> 0
A41: Cost of Chemicals | C41: Mk | D41: =(D29*$B29)+(D31*$B31)+(D33*$B33)+(D35*$B35)+(D37*$B37)+(D39*$B39) -> 141011.6 | E41: =(E29*$B29)+(E31*$B31)+(E33*$B33)+(E35*$B35)+(E37*$B37)+(E39*$B39) -> 317276.1 | F41: =(F29*$B29)+(F31*$B31)+(F33*$B33)+(F35*$B35)+(F37*$B37)+(F39*$B39) -> 72268.445 | G41: =(G29*$B29)+(G31*$B31)+(G33*$B33)+(G35*$B35)+(G37*$B37)+(G39*$B39) -> 186840.37 | H41: =(H29*$B29)+(H31*$B31)+(H33*$B33)+(H35*$B35)+(H37*$B37)+(H39*$B39) -> 105758.7 | I41: =(I29*$B29)+(I31*$B31)+(I33*$B33)+(I35*$B35)+(I37*$B37)+(I39*$B39) -> 204466.82 | J41: =SUM(D41:I41) -> 1027622
A42: Cost/vol. Produced (chemicals) | C42: Mk/m3 | D42: =D41/D9 -> 4.00567 | E42: =E41/E9 -> 3.659344 | F42: =F41/F9 -> 7.6016036 | G42: =G41/G9 -> 2.607645 | H42: =H41/H9 -> 1.7640562 | I42: =I41/I9 -> 3.6082168 | J42: =J41/J9 -> 3.2145032
A43: Power
A44: Power Usage | C44: Kw | D44: =Bangula!D44+Bangula!E44+Bangula!F44 -> 8933.77 | E44: =Chikwawa!D44+Chikwawa!E44+Chikwawa!F44 -> 52682 | F44: ='Miseu Folo'!D44+'Miseu Folo'!E44+'Miseu Folo'!F44 -> 2495 | G44: =Nchalo!D44+Nchalo!E44+Nchalo!F44 -> 21612 | H44: =Nsanje!D44+Nsanje!E44+Nsanje!F44 -> 50009 | I44: =Ngabu!D44+Ngabu!E44+Ngabu!F44 -> 31140.99 | J44: =SUM(D44:I44) -> 166872.76
A45: Power/ Vol. Produced | C45: Kw/m3 | D45: =D44/D9 -> 0.25377866 | E45: =E44/E9 -> 0.6076145 | F45: =F44/F9 -> 0.2624382 | G45: =G44/G9 -> 0.30162873 | H45: =H44/H9 -> 0.83415065 | I45: =I44/I9 -> 0.54954365 | J45: =J44/J9 -> 0.52199448
A46: Cost of Power | C46: Mk | D46: =Bangula!D46+Bangula!E46+Bangula!F46 -> 1349892.6 | E46: =Chikwawa!D46+Chikwawa!E46+Chikwawa!F46 -> 7960250.2 | F46: ='Miseu Folo'!D46+'Miseu Folo'!E46+'Miseu Folo'!F46 -> 376994.5 | G46: =Nchalo!D46+Nchalo!E46+Nchalo!F46 -> 3265573.2 | H46: =Nsanje!D46+Nsanje!E46+Nsanje!F46 -> 7556359.9 | I46: =Ngabu!D46+Ngabu!E46+Ngabu!F46 -> 4705403.6 | J46: =SUM(D46:I46) -> 25214474
A47: Cost/vol. Produced | C47: Mk/m3 | D47: =D46/D9 -> 38.345955 | E47: =E46/E9 -> 91.810551 | F47: =F46/F9 -> 39.654413 | G47: =G46/G9 -> 45.576101 | H47: =H46/H9 -> 126.04016 | I47: =I46/I9 -> 83.036045 | J47: =J46/J9 -> 78.873365
A48: Plant and Vehicle Maintenance
A49: Distances covered | C49: km | D49: =Bangula!D49+Bangula!E49+Bangula!F49 -> 1020 | E49: =Chikwawa!D49+Chikwawa!E49+Chikwawa!F49 -> 1855 | F49: ='Miseu Folo'!D49+'Miseu Folo'!E49+'Miseu Folo'!F49 -> 655 | G49: =Nchalo!D49+Nchalo!E49+Nchalo!F49 -> 0 | H49: =Nsanje!D49+Nsanje!E49+Nsanje!F49 -> 3883 | I49: =Ngabu!D49+Ngabu!E49+Ngabu!F49 -> 6128 | J49: =SUM(D49:I49) -> 13541
A50: Fuel Used (litres) | C50: litres | D50: =Bangula!D50+Bangula!E50+Bangula!F50 -> 32 | E50: =Chikwawa!D50+Chikwawa!E50+Chikwawa!F50 -> 258 | F50: ='Miseu Folo'!D50+'Miseu Folo'!E50+'Miseu Folo'!F50 -> 50 | G50: =Nchalo!D50+Nchalo!E50+Nchalo!F50 -> 0 | H50: =Nsanje!D50+Nsanje!E50+Nsanje!F50 -> 445 | I50: =Ngabu!D50+Ngabu!E50+Ngabu!F50 -> 750 | J50: =SUM(D50:I50) -> 1535
A51: Cost of fuel | C51: Mk | D51: =Bangula!D51+Bangula!E51+Bangula!F51 -> 47040 | E51: =Chikwawa!D51+Chikwawa!E51+Chikwawa!F51 -> 495360 | F51: ='Miseu Folo'!D51+'Miseu Folo'!E51+'Miseu Folo'!F51 -> 96000 | G51: =Nchalo!D51+Nchalo!E51+Nchalo!F51 -> 0 | H51: =Nsanje!D51+Nsanje!E51+Nsanje!F51 -> 854400 | I51: =Ngabu!D51+Ngabu!E51+Ngabu!F51 -> 1440000 | J51: =SUM(D51:I51) -> 2932800
A52: Maintenance | C52: Mk | D52: =Bangula!D52+Bangula!E52+Bangula!F52 -> 115000 | E52: =Chikwawa!D52+Chikwawa!E52+Chikwawa!F52 -> 0 | F52: ='Miseu Folo'!D52+'Miseu Folo'!E52+'Miseu Folo'!F52 -> 0 | G52: =Nchalo!D52+Nchalo!E52+Nchalo!F52 -> 0 | H52: =Nsanje!D52+Nsanje!E52+Nsanje!F52 -> 0 | I52: =Ngabu!D52+Ngabu!E52+Ngabu!F52 -> 0 | J52: =SUM(D52:I52) -> 115000
A53: Salaries and Wages
A54: Staff Costs | C54: MK | D54: =Bangula!D54+Bangula!E54+Bangula!F54 -> 2510009.2 | E54: =Chikwawa!D54+Chikwawa!E54+Chikwawa!F54 -> 0 | F54: ='Miseu Folo'!D54+'Miseu Folo'!E54+'Miseu Folo'!F54 -> 4314458.4 | G54: =Nchalo!D54+Nchalo!E54+Nchalo!F54 -> 4568856.2 | H54: =Nsanje!D54+Nsanje!E54+Nsanje!F54 -> 11834022 | I54: =Ngabu!D54+Ngabu!E54+Ngabu!F54 -> 4997427.2 | J54: =SUM(D54:I54) -> 28224773
A55: Wages | C55: MK | D55: =Bangula!D55+Bangula!E55+Bangula!F55 -> 496425.39 | E55: =Chikwawa!D55+Chikwawa!E55+Chikwawa!F55 -> 0 | F55: ='Miseu Folo'!D55+'Miseu Folo'!E55+'Miseu Folo'!F55 -> 0 | G55: =Nchalo!D55+Nchalo!E55+Nchalo!F55 -> 522116.4 | H55: =Nsanje!D55+Nsanje!E55+Nsanje!F55 -> 2072286.3 | I55: =Ngabu!D55+Ngabu!E55+Ngabu!F55 -> 723463.2 | J55: =SUM(D55:I55) -> 3814291.3
A56: Other Overhead Costs | C56: MK | D56: =Bangula!D56+Bangula!E56+Bangula!F56 -> 0 | E56: =Chikwawa!D56+Chikwawa!E56+Chikwawa!F56 -> 0 | F56: ='Miseu Folo'!D56+'Miseu Folo'!E56+'Miseu Folo'!F56 -> 0 | G56: =Nchalo!D56+Nchalo!E56+Nchalo!F56 -> 0 | H56: =Nsanje!D56+Nsanje!E56+Nsanje!F56 -> 0 | I56: =Ngabu!D56+Ngabu!E56+Ngabu!F56 -> 0 | J56: =SUM(D56:I56) -> 0
A57: Operating Costs
A58: Total Operating Costs | C58: MK | D58: =D41+D46+D51+D52+D54+D55+D56 -> 4659378.9 | E58: =E41+E46+E51+E52+E54+E55+E56 -> 8772886.3 | F58: =F41+F46+F51+F52+F54+F55+F56 -> 4859721.4 | G58: =G41+G46+G51+G52+G54+G55+G56 -> 8543386.2 | H58: =H41+H46+H51+H52+H54+H55+H56 -> 22422827 | I58: =I41+I46+I51+I52+I54+I55+I56 -> 12070761 | J58: =SUM(D58:I58) -> 61328960
A59: Cost/Vol. Produced | C59: Mk/m3 | D59: =D58/D9 -> 132.35744 | E59: =E58/E9 -> 101.18319 | F59: =F58/F9 -> 511.17296 | G59: =G58/G9 -> 119.23611 | H59: =H58/H9 -> 374.01299 | I59: =I58/I9 -> 213.01217 | J59: =J58/J9 -> 191.84305
A60: Cost/Vol. Billed | C60: Mk/m3 | D60: =D58/D22 -> 160.53593 | E60: =E58/E22 -> 117.90405 | F60: =F58/F22 -> 627.12556 | G60: =G58/G22 -> 173.10493 | H60: =H58/H22 -> 494.57027 | I60: =I58/I22 -> 399.81322 | J60: =J58/J22 -> 270.89015
A61: Permanent Staff Employed | C61: No | D61: =Bangula!F61 -> 2 | E61: =Chikwawa!F61 -> 8 | F61: ='Miseu Folo'!F61 -> 8 | G61: =Nchalo!F61 -> 6 | H61: =Nsanje!F61 -> 8 | I61: =Ngabu!G61 -> 7 | J61: =I61 -> 7
A62: Staff/Vol.1000m3 of Volume Produced/hour (12 hour day) | C62: No/1000m3 | D62: =(D61*1000*31)/D9 -> 1.7612135 | E62: =(E61*1000*31)/E9 -> 2.8603393 | F62: =(F61*1000*31)/F9 -> 26.086042 | G62: =(G61*1000*31)/G9 -> 2.5959163 | H62: =(H61*1000*31)/H9 -> 4.1366426 | I62: =(I61*1000*31)/I9 -> 3.8293892 | J62: =(J61*1000*31)/J9 -> 0.67879743
A63: Temporary Staff Employed | C63: No | D63: =Bangula!F63 -> 4 | E63: =Chikwawa!F63 -> 6 | F63: ='Miseu Folo'!F63 -> 0 | G63: =Nchalo!F63 -> 6 | H63: =Nsanje!F63 -> 6 | I63: =Ngabu!F63 -> 6 | J63: =SUM(D63:I63) -> 28
A65: Water Connections and Disconnections
A66: New Individual Water Connections | B66: Brought Forward | C66: No | D66: =Bangula!D66 -> 45 | E66: =Chikwawa!D66 -> 376 | F66: ='Miseu Folo'!D66 -> 4 | G66: =Nchalo!D66 -> 54 | H66: =Nsanje!D66 -> 166 | I66: =Ngabu!D66 -> 134 | J66: =SUM(D66:I66) -> 779
B67: Applied this Month | C67: No | D67: =Bangula!D67+Bangula!E67+Bangula!F67 -> 8 | E67: =Chikwawa!D67+Chikwawa!E67+Chikwawa!F67 -> 32 | F67: ='Miseu Folo'!D67+'Miseu Folo'!E67+'Miseu Folo'!F67 -> 71 | G67: =Nchalo!D67+Nchalo!E67+Nchalo!F67 -> 34 | H67: =Nsanje!D67+Nsanje!E67+Nsanje!F67 -> 40 | I67: =Ngabu!D67+Ngabu!E67+Ngabu!F67 -> 17 | J67: =SUM(D67:I67) -> 202
B68: Done this Month Postpaid | C68: No | D68: =Bangula!D68+Bangula!E68+Bangula!F68 -> 3 | E68: =Chikwawa!D68+Chikwawa!E68+Chikwawa!F68 -> 83 | F68: ='Miseu Folo'!D68+'Miseu Folo'!E68+'Miseu Folo'!F68 -> 22 | G68: =Nchalo!D68+Nchalo!E68+Nchalo!F68 -> 56 | H68: =Nsanje!D68+Nsanje!E68+Nsanje!F68 -> 46 | I68: =Ngabu!D68+Ngabu!E68+Ngabu!F68 -> 27 | J68: =SUM(D68:I68) -> 237
B69: Done this Month Prepaid | C69: No | D69: =Bangula!D69+Bangula!E69+Bangula!F69 -> 0 | E69: =Chikwawa!D69+Chikwawa!E69+Chikwawa!F69 -> 0 | F69: ='Miseu Folo'!D69+'Miseu Folo'!E69+'Miseu Folo'!F69 -> 0 | G69: =Nchalo!D69+Nchalo!E69+Nchalo!F69 -> 0 | H69: =Nsanje!D69+Nsanje!E69+Nsanje!F69 -> 0 | I69: =Ngabu!D69+Ngabu!E69+Ngabu!F69 -> 0 | J69: =SUM(D69:I69) -> 0
B70: Total Done | C70: No | D70: =D68+D69 -> 3 | E70: =E68+E69 -> 83 | F70: =F68+F69 -> 22 | G70: =G68+G69 -> 56 | H70: =H68+H69 -> 46 | I70: =I68+I69 -> 27 | J70: =J68+J69 -> 237
B71: Carried Forward | C71: No | D71: =D66+D67-D70 -> 50 | E71: =E66+E67-E70 -> 325 | F71: =F66+F67-F70 -> 53 | G71: =G66+G67-G70 -> 32 | H71: =H66+H67-H70 -> 160 | I71: =I66+I67-I70 -> 124 | J71: =J66+J67-J70 -> 744
A72: New Institutional Water Connections | B72: Brought Forward | C72: No | D72: =Bangula!D72 -> 0 | E72: =Chikwawa!D72 -> 0 | F72: ='Miseu Folo'!D72 -> 0 | G72: =Nchalo!D72 -> 0 | H72: =Nsanje!D72 -> 0 | I72: =Ngabu!D72 -> 0 | J72: =SUM(D72:I72) -> 0
B73: Applied this Month | C73: No | D73: =Bangula!D73+Bangula!E73+Bangula!F73 -> 0 | E73: =Chikwawa!D73+Chikwawa!E73+Chikwawa!F73 -> 1 | F73: ='Miseu Folo'!D73+'Miseu Folo'!E73+'Miseu Folo'!F73 -> 0 | G73: =Nchalo!D73+Nchalo!E73+Nchalo!F73 -> 0 | H73: =Nsanje!D73+Nsanje!E73+Nsanje!F73 -> 0 | I73: =Ngabu!D73+Ngabu!E73+Ngabu!F73 -> 0 | J73: =SUM(D73:I73) -> 1
B74: Done this Month Postpaid | C74: No | D74: =Bangula!D74+Bangula!E74+Bangula!F74 -> 0 | E74: =Chikwawa!D74+Chikwawa!E74+Chikwawa!F74 -> 1 | F74: ='Miseu Folo'!D74+'Miseu Folo'!E74+'Miseu Folo'!F74 -> 0 | G74: =Nchalo!D74+Nchalo!E74+Nchalo!F74 -> 0 | H74: =Nsanje!D74+Nsanje!E74+Nsanje!F74 -> 0 | I74: =Ngabu!D74+Ngabu!E74+Ngabu!F74 -> 0 | J74: =SUM(D74:I74) -> 1
B75: Done this Month Prepaid | C75: No | D75: =Bangula!D75+Bangula!E75+Bangula!F75 -> 0 | E75: =Chikwawa!D75+Chikwawa!E75+Chikwawa!F75 -> 0 | F75: ='Miseu Folo'!D75+'Miseu Folo'!E75+'Miseu Folo'!F75 -> 0 | G75: =Nchalo!D75+Nchalo!E75+Nchalo!F75 -> 0 | H75: =Nsanje!D75+Nsanje!E75+Nsanje!F75 -> 0 | I75: =Ngabu!D75+Ngabu!E75+Ngabu!F75 -> 0 | J75: =SUM(D75:I75) -> 0
B76: Total Done | C76: No | D76: =D74+D75 -> 0 | E76: =E74+E75 -> 1 | F76: =F74+F75 -> 0 | G76: =G74+G75 -> 0 | H76: =H74+H75 -> 0 | I76: =I74+I75 -> 0 | J76: =J74+J75 -> 1
B77: Carried Forward | C77: No | D77: =D73+D74-D76 -> 0 | E77: =E73+E74-E76 -> 1 | F77: =F73+F74-F76 -> 0 | G77: =G73+G74-G76 -> 0 | H77: =H73+H74-H76 -> 0 | I77: =I73+I74-I76 -> 0 | J77: =J73+J74-J76 -> 1
A78: New Commercial/Industrial Water Connections | B78: Brought Forward | C78: No | D78: =Bangula!D78 -> 0 | E78: =Chikwawa!D78 -> 0 | F78: ='Miseu Folo'!D78 -> 0 | G78: =Nchalo!D78 -> 0 | H78: =Nsanje!D78 -> 0 | I78: =Ngabu!D78 -> 0 | J78: =SUM(D78:I78) -> 0
B79: Applied this Month | C79: No | D79: =Bangula!D79+Bangula!E79+Bangula!F79 -> 1 | E79: =Chikwawa!D79+Chikwawa!E79+Chikwawa!F79 -> 0 | F79: ='Miseu Folo'!D79+'Miseu Folo'!E79+'Miseu Folo'!F79 -> 0 | G79: =Nchalo!D79+Nchalo!E79+Nchalo!F79 -> 1 | H79: =Nsanje!D79+Nsanje!E79+Nsanje!F79 -> 0 | I79: =Ngabu!D79+Ngabu!E79+Ngabu!F79 -> 0 | J79: =SUM(D79:I79) -> 2
B80: Done this Month Postpaid | C80: No | D80: =Bangula!D80+Bangula!E80+Bangula!F80 -> 0 | E80: =Chikwawa!D80+Chikwawa!E80+Chikwawa!F80 -> 0 | F80: ='Miseu Folo'!D80+'Miseu Folo'!E80+'Miseu Folo'!F80 -> 0 | G80: =Nchalo!D80+Nchalo!E80+Nchalo!F80 -> 1 | H80: =Nsanje!D80+Nsanje!E80+Nsanje!F80 -> 0 | I80: =Ngabu!D80+Ngabu!E80+Ngabu!F80 -> 0 | J80: =SUM(D80:I80) -> 1
B81: Done this Month Prepaid | C81: No | D81: =Bangula!D81+Bangula!E81+Bangula!F81 -> 0 | E81: =Chikwawa!D81+Chikwawa!E81+Chikwawa!F81 -> 0 | F81: ='Miseu Folo'!D81+'Miseu Folo'!E81+'Miseu Folo'!F81 -> 0 | G81: =Nchalo!D81+Nchalo!E81+Nchalo!F81 -> 0 | H81: =Nsanje!D81+Nsanje!E81+Nsanje!F81 -> 0 | I81: =Ngabu!D81+Ngabu!E81+Ngabu!F81 -> 0 | J81: =SUM(D81:I81) -> 0
B82: Total Done | C82: No | D82: =D81+D80 -> 0 | E82: =E81+E80 -> 0 | F82: =F81+F80 -> 0 | G82: =G81+G80 -> 1 | H82: =H81+H80 -> 0 | I82: =I81+I80 -> 0 | J82: =J81+J80 -> 1
B83: Carried Forward | C83: No | D83: =D78+D79-D82 -> 1 | E83: =E78+E79-E82 -> 0 | F83: =F78+F79-F82 -> 0 | G83: =G78+G79-G82 -> 0 | H83: =H78+H79-H82 -> 0 | I83: =I78+I79-I82 -> 0 | J83: =J78+J79-J82 -> 1
A84: New CWP | B84: Brought Forward | C84: No | D84: =Bangula!D84 -> 0 | E84: =Chikwawa!D84 -> 0 | F84: ='Miseu Folo'!D84 -> 0 | G84: =Nchalo!D84 -> 0 | H84: =Ngabu!D84 -> 0 | I84: =Nsanje!E84 -> 0 | J84: =SUM(D84:I84) -> 0
B85: Applied this Month | C85: No | D85: =Bangula!D85+Bangula!E85+Bangula!F85 -> 0 | E85: =Chikwawa!D85+Chikwawa!E85+Chikwawa!F85 -> 0 | F85: ='Miseu Folo'!D85+'Miseu Folo'!E85+'Miseu Folo'!F85 -> 0 | G85: =Nchalo!D85+Nchalo!E85+Nchalo!F85 -> 0 | H85: =Nsanje!D85+Nsanje!E85+Nsanje!F85 -> 0 | I85: =Ngabu!D85+Ngabu!E85+Ngabu!F85 -> 0 | J85: =SUM(D85:I85) -> 0
B86: Done this Month Postpaid | C86: No | D86: =Bangula!D86+Bangula!E86+Bangula!F86 -> 0 | E86: =Chikwawa!D86+Chikwawa!E86+Chikwawa!F86 -> 0 | F86: ='Miseu Folo'!D86+'Miseu Folo'!E86+'Miseu Folo'!F86 -> 0 | G86: =Nchalo!D86+Nchalo!E86+Nchalo!F86 -> 0 | H86: =Nsanje!D86+Nsanje!E86+Nsanje!F86 -> 0 | I86: =Ngabu!D86+Ngabu!E86+Ngabu!F86 -> 0 | J86: =SUM(D86:I86) -> 0
B87: Done this Month Prepaid | C87: No | D87: =Bangula!D87+Bangula!E87+Bangula!F87 -> 0 | E87: =Chikwawa!D87+Chikwawa!E87+Chikwawa!F87 -> 0 | F87: ='Miseu Folo'!D87+'Miseu Folo'!E87+'Miseu Folo'!F87 -> 0 | G87: =Nchalo!D87+Nchalo!E87+Nchalo!F87 -> 0 | H87: =Nsanje!D87+Nsanje!E87+Nsanje!F87 -> 0 | I87: =Ngabu!D87+Ngabu!E87+Ngabu!F87 -> 0 | J87: =SUM(D87:I87) -> 0
B88: Total Done | C88: No | D88: =D87+D86 -> 0 | E88: =E87+E86 -> 0 | F88: =F87+F86 -> 0 | G88: =G87+G86 -> 0 | H88: =H87+H86 -> 0 | I88: =I87+I86 -> 0 | J88: =SUM(D88:I88) -> 0
B89: Carried Forward | C89: No | D89: =D84+D85-D88 -> 0 | E89: =E84+E85-E88 -> 0 | F89: =F84+F85-F88 -> 0 | G89: =G84+G85-G88 -> 0 | H89: =H84+H85-H88 -> 0 | I89: =I84+I85-I88 -> 0 | J89: =J84+J85-J86-J87 -> 0
A90: Aggregated New Water connections | B90: Brought Forward | C90: No | D90: =D66+D72+D78+D84 -> 45 | E90: =E66+E72+E78+E84 -> 376 | F90: =F66+F72+F78+F84 -> 4 | G90: =G66+G72+G78+G84 -> 54 | H90: =H66+H72+H78+H84 -> 166 | I90: =I66+I72+I78+I84 -> 134 | J90: =SUM(D90:I90) -> 779
B91: Applied this Month | C91: No | D91: =D67+D73+D79+D85 -> 9 | E91: =E67+E73+E79+E85 -> 33 | F91: =F67+F73+F79+F85 -> 71 | G91: =G67+G73+G79+G85 -> 35 | H91: =H67+H73+H79+H85 -> 40 | I91: =I67+I73+I79+I85 -> 17 | J91: =SUM(D91:I91) -> 205
B92: Done this Month Postpaid | C92: No | D92: =D68+D74+D80+D86 -> 3 | E92: =E68+E74+E80+E86 -> 84 | F92: =F68+F74+F80+F86 -> 22 | G92: =G68+G74+G80+G86 -> 57 | H92: =H68+H74+H80+H86 -> 46 | I92: =I68+I74+I80+I86 -> 27 | J92: =SUM(D92:I92) -> 239
B93: Done this Month Prepaid | D93: =D69+D75+D81+D87 -> 0 | E93: =E69+E75+E81+E87 -> 0 | F93: =F69+F75+F81+F87 -> 0 | G93: =G69+G75+G81+G87 -> 0 | H93: =H69+H75+H81+H87 -> 0 | I93: =I69+I75+I81+I87 -> 0 | J93: =SUM(D93:I93) -> 0
B94: Total Done | C94: No | D94: =D93+D92 -> 3 | E94: =E93+E92 -> 84 | F94: =F93+F92 -> 22 | G94: =G93+G92 -> 57 | H94: =H93+H92 -> 46 | I94: =I93+I92 -> 27 | J94: =J93+J92 -> 239
B95: Carried Forward | C95: No | D95: =D90+D91-D94 -> 51 | E95: =E90+E91-E94 -> 325 | F95: =F90+F91-F94 -> 53 | G95: =G90+G91-G94 -> 32 | H95: =H90+H91-H94 -> 160 | I95: =I90+I91-I94 -> 124 | J95: =J90+J91-J94 -> 745
A97: Prepaid Metering
A98: Prepaid Meters Installed | C98: No | D98: =Bangula!D98+Bangula!E98+Bangula!F98 -> 0 | E98: =Chikwawa!D98+Chikwawa!E98+Chikwawa!F98 -> 5 | F98: ='Miseu Folo'!D98+'Miseu Folo'!E98+'Miseu Folo'!F98 -> 0 | G98: =Nchalo!D98+Nchalo!E98+Nchalo!F98 -> 0 | H98: =Nsanje!D98+Nsanje!E98+Nsanje!F98 -> 0 | I98: =Ngabu!D98+Ngabu!E98+Ngabu!F98 -> 0 | J98: =SUM(D98:I98) -> 5
A100: Active and Disconnected Accounts
A101: Disconnected Individual Accounts | C101: No | D101: =Bangula!F101 -> 192 | E101: =Chikwawa!F101 -> 546 | F101: ='Miseu Folo'!F101 -> 0 | G101: =Nchalo!F101 -> 629 | H101: =Nsanje!F101 -> 495 | I101: =Ngabu!G101 -> 487 | J101: =SUM(D101:I101) -> 2349
A102: Disconnected institutional Accounts | C102: No | D102: =Bangula!F102 -> 9 | E102: =Chikwawa!F102 -> 11 | F102: ='Miseu Folo'!F102 -> 0 | G102: =Nchalo!F102 -> 17 | H102: =Nsanje!F102 -> 20 | I102: =Ngabu!G102 -> 10 | J102: =SUM(D102:I102) -> 67
A103: Disconnected Commercial/Industrial Accounts | C103: No | D103: =Bangula!F103 -> 8 | E103: =Chikwawa!F103 -> 13 | F103: ='Miseu Folo'!F103 -> 0 | G103: =Nchalo!F103 -> 27 | H103: =Nsanje!F103 -> 2 | I103: =Ngabu!G103 -> 12 | J103: =SUM(D103:I103) -> 62
A104: Disconnected CWP | C104: No | D104: =Bangula!F104 -> 4 | E104: =Chikwawa!F104 -> 14 | F104: ='Miseu Folo'!F104 -> 0 | G104: =Nchalo!F104 -> 11 | H104: =Nsanje!F104 -> 25 | I104: =Ngabu!G104 -> 20 | J104: =SUM(D104:I104) -> 74
A105: Total Disconnected Accounts | C105: No | D105: =SUM(D101:D104) -> 213 | E105: =SUM(E101:E104) -> 584 | F105: =SUM(F101:F104) -> 0 | G105: =SUM(G101:G104) -> 684 | H105: =SUM(H101:H104) -> 542 | I105: =SUM(I101:I104) -> 529 | J105: =SUM(D105:I105) -> 2552
...

Sheet 2nd QTR 
A1: SOUTHERN REGION WATER BOARD
A3: MONTHLY REPORTS - 2023/2024
A4: NAGBU ZONE
A5: NGABU ZONE
A7: PARAMETERS | C7: UNITS | D7: Bangula | E7: Chikwawa | F7: Miseu Folo | G7: Nchalo | H7: Nsanje | I7: Ngabu | J7: TOTALS
A8: PRODUCTION
A9: Volume Produced | C9: m3 | D9: =Bangula!G9+Bangula!H9+Bangula!I9 -> 34231 | E9: =Chikwawa!G9+Chikwawa!H9+Chikwawa!I9 -> 85118 | F9: ='Miseu Folo'!G9+'Miseu Folo'!H9+'Miseu Folo'!I9 -> 10940 | G9: =Nchalo!G9+Nchalo!H9+Nchalo!I9 -> 74437 | H9: =Nsanje!G9+Nsanje!H9+Nsanje!I9 -> 61035 | I9: =Ngabu!G9+Ngabu!H9+Ngabu!I9 -> 37279 | J9: =SUM(D9:I9) -> 303040
A10: REVENUE WATER - POSTPAID
A11: Volume Billed Individuals | C11: m3 | D11: =Bangula!G11+Bangula!H11+Bangula!I11 -> 14419 | E11: =Chikwawa!G11+Chikwawa!H11+Chikwawa!I11 -> 46676 | F11: ='Miseu Folo'!G11+'Miseu Folo'!H11+'Miseu Folo'!I11 -> 2624 | G11: =Nchalo!G11+Nchalo!H11+Nchalo!I11 -> 41857 | H11: =Nsanje!G11+Nsanje!H11+Nsanje!I11 -> 25770 | I11: =Ngabu!G11+Ngabu!H11+Ngabu!I11 -> 17690 | J11: =SUM(D11:I11) -> 149036
A12: Volume Billed CWPs | C12: m3 | D12: =Bangula!G12+Bangula!H12+Bangula!I12 -> 4653 | E12: =Chikwawa!G12+Chikwawa!H12+Chikwawa!I12 -> 2346 | F12: ='Miseu Folo'!G12+'Miseu Folo'!H12+'Miseu Folo'!I12 -> 0 | G12: =Nchalo!G12+Nchalo!H12+Nchalo!I12 -> 2275 | H12: =Nsanje!G12+Nsanje!H12+Nsanje!I12 -> 2075 | I12: =Ngabu!G12+Ngabu!H12+Ngabu!I12 -> 3243 | J12: =SUM(D12:I12) -> 14592
A13: Volume Billed Institutions | C13: m3 | D13: =Bangula!G13+Bangula!H13+Bangula!I13 -> 175 | E13: =Chikwawa!G13+Chikwawa!H13+Chikwawa!I13 -> 736 | F13: ='Miseu Folo'!G13+'Miseu Folo'!H13+'Miseu Folo'!I13 -> 13 | G13: =Nchalo!G13+Nchalo!H13+Nchalo!I13 -> 367 | H13: =Nsanje!G13+Nsanje!H13+Nsanje!I13 -> 497 | I13: =Ngabu!G13+Ngabu!H13+Ngabu!I13 -> 454 | J13: =SUM(D13:I13) -> 2242
A14: Volume Billed Commercial/Industrial | C14: m3 | D14: =Bangula!G14+Bangula!H14+Bangula!I14 -> 27 | E14: =Chikwawa!G14+Chikwawa!H14+Chikwawa!I14 -> 258 | F14: ='Miseu Folo'!G14+'Miseu Folo'!H14+'Miseu Folo'!I14 -> 49 | G14: =Nchalo!G14+Nchalo!H14+Nchalo!I14 -> 694 | H14: =Nsanje!G14+Nsanje!H14+Nsanje!I14 -> 407 | I14: =Ngabu!G14+Ngabu!H14+Ngabu!I14 -> 154 | J14: =SUM(D14:I14) -> 1589
A15: Total Volume Billed Post Paid | C15: m3 | D15: =SUM(D11:D14) -> 19274 | E15: =SUM(E11:E14) -> 50016 | F15: =SUM(F11:F14) -> 2686 | G15: =SUM(G11:G14) -> 45193 | H15: =SUM(H11:H14) -> 28749 | I15: =SUM(I11:I14) -> 21541 | J15: =SUM(J11:J14) -> 167459
A16: REVENUE WATER - PREPAID
A17: Individuals | C17: m3 | D17: =Bangula!G17+Bangula!H17+Bangula!I17 -> 3250 | E17: =Chikwawa!G17+Chikwawa!H17+Chikwawa!I17 -> 3972 | F17: ='Miseu Folo'!G17+'Miseu Folo'!H17+'Miseu Folo'!I17 -> 0 | G17: =Nchalo!G17+Nchalo!H17+Nchalo!I17 -> 0 | H17: =Nsanje!G17+Nsanje!H17+Nsanje!I17 -> 8461 | I17: =Ngabu!G17+Ngabu!H17+Ngabu!I17 -> 4579 | J17: =SUM(D17:I17) -> 20262
A18: CWPs | C18: m3 | D18: =Bangula!G18+Bangula!H18+Bangula!I18 -> 57 | E18: =Chikwawa!G18+Chikwawa!H18+Chikwawa!I18 -> 0 | F18: ='Miseu Folo'!G18+'Miseu Folo'!H18+'Miseu Folo'!I18 -> 0 | G18: =Nchalo!G18+Nchalo!H18+Nchalo!I18 -> 0 | H18: =Nsanje!G18+Nsanje!H18+Nsanje!I18 -> 0 | I18: =Ngabu!G18+Ngabu!H18+Ngabu!I18 -> 0 | J18: =SUM(D18:I18) -> 57
A19: Institutions | C19: m3 | D19: =Bangula!G19+Bangula!H19+Bangula!I19 -> 4308.5 | E19: =Chikwawa!G19+Chikwawa!H19+Chikwawa!I19 -> 11381 | F19: ='Miseu Folo'!G19+'Miseu Folo'!H19+'Miseu Folo'!I19 -> 6629.2 | G19: =Nchalo!G19+Nchalo!H19+Nchalo!I19 -> 8291.3 | H19: =Nsanje!G19+Nsanje!H19+Nsanje!I19 -> 7294.3 | I19: =Ngabu!G19+Ngabu!H19+Ngabu!I19 -> 5402 | J19: =SUM(D19:I19) -> 43306.3
A20: Commercial/Industrial | C20: m3 | D20: =Bangula!G20+Bangula!H20+Bangula!I20 -> 678 | E20: =Chikwawa!G20+Chikwawa!H20+Chikwawa!I20 -> 1708 | F20: ='Miseu Folo'!G20+'Miseu Folo'!H20+'Miseu Folo'!I20 -> 0 | G20: =Nchalo!G20+Nchalo!H20+Nchalo!I20 -> 0 | H20: =Nsanje!G20+Nsanje!H20+Nsanje!I20 -> 893 | I20: =Ngabu!G20+Ngabu!H20+Ngabu!I20 -> 224 | J20: =SUM(D20:I20) -> 3503
A21: Total Volume Prepaid | C21: m3 | D21: =SUM(D17:D20) -> 8293.5 | E21: =SUM(E17:E20) -> 17061 | F21: =SUM(F17:F20) -> 6629.2 | G21: =SUM(G17:G20) -> 8291.3 | H21: =SUM(H17:H20) -> 16648.3 | I21: =SUM(I17:I20) -> 10205 | J21: =SUM(J17:J20) -> 67128.3
A22: TOTAL REVENUE WATER | C22: m3 | D22: =D21+D15 -> 27567.5 | E22: =E21+E15 -> 67077 | F22: =F21+F15 -> 9315.2 | G22: =G21+G15 -> 53484.3 | H22: =H21+H15 -> 45397.3 | I22: =I21+I15 -> 31746 | J22: =J21+J15 -> 234587.3
A23: NON-REVENUE WATER (NRW)
A24: Non-Revenue Water (NRW) | B24: Volume | C24: m3 | D24: =D9-D22 -> 6663.5 | E24: =E9-E22 -> 18041 | F24: =F9-F22 -> 1624.8 | G24: =G9-G22 -> 20952.7 | H24: =H9-H22 -> 15637.7 | I24: =I9-I22 -> 5533 | J24: =J9-J22 -> 68452.7
B25: Percentage | C25: % | D25: =D24/D9 -> 0.19466273 | E25: =E24/E9 -> 0.21195282 | F25: =F24/F9 -> 0.1485192 | G25: =G24/G9 -> 0.28148233 | H25: =H24/H9 -> 0.25620873 | I25: =I24/I9 -> 0.14842136 | J25: =J24/J9 -> 0.22588668
A26: OPERATING EXPENSES
A27: Chemicals
A28: Chemical | B28: Rate(MK/kg)
A29: Chlorine | B29: 3525.29 | C29: kg | D29: =Bangula!G29+Bangula!H29+Bangula!I29 -> 48 | E29: =Chikwawa!G29+Chikwawa!H29+Chikwawa!I29 -> 92 | F29: ='Miseu Folo'!G29+'Miseu Folo'!H29+'Miseu Folo'!I29 -> 23.3 | G29: =Nchalo!G29+Nchalo!H29+Nchalo!I29 -> 53 | H29: =Nsanje!G29+Nsanje!H29+Nsanje!I29 -> 37.5 | I29: =Ngabu!G29+Ngabu!H29+Ngabu!I29 -> 51 | J29: =SUM(D29:I29) -> 304.8
C30: kg/mg litre | D30: =D29/(D9/1000) -> 1.4022377 | E30: =E29/(E9/1000) -> 1.0808525 | F30: =F29/(F9/1000) -> 2.1297989 | G30: =G29/(G9/1000) -> 0.7120115 | H30: =H29/(H9/1000) -> 0.61440157 | I30: =I29/(I9/1000) -> 1.3680624 | J30: =J29/(J9/1000) -> 1.0058078
A31: Aluminium sulphate | C31: kg | D31: =Bangula!G31+Bangula!H31+Bangula!I31 -> 0 | E31: =Chikwawa!G31+Chikwawa!H31+Chikwawa!I31 -> 0 | F31: ='Miseu Folo'!G31+'Miseu Folo'!H31+'Miseu Folo'!I31 -> 0 | G31: =Nchalo!G31+Nchalo!H31+Nchalo!I31 -> 0 | H31: =Nsanje!G31+Nsanje!H31+Nsanje!I31 -> 0 | I31: =Ngabu!G31+Ngabu!H31+Ngabu!I31 -> 0 | J31: =SUM(D31:I31) -> 0
B32: 1060.01 | C32: kg/mg litre | D32: =D31/(D9/1000) -> 0 | E32: =E31/(E9/1000) -> 0 | F32: =F31/(F9/1000) -> 0 | G32: =G31/(G9/1000) -> 0 | H32: =H31/(H9/1000) -> 0 | I32: =I31/(I9/1000) -> 0 | J32: =J31/(J9/1000) -> 0
A33: Soda | C33: kg | D33: =Bangula!G33+Bangula!H33+Bangula!I33 -> 0 | E33: =Chikwawa!G33+Chikwawa!H33+Chikwawa!I33 -> 0 | F33: ='Miseu Folo'!G33+'Miseu Folo'!H33+'Miseu Folo'!I33 -> 0 | G33: =Nchalo!G33+Nchalo!H33+Nchalo!I33 -> 0 | H33: =Nsanje!G33+Nsanje!H33+Nsanje!I33 -> 0 | I33: =Ngabu!G33+Ngabu!H33+Ngabu!I33 -> 0 | J33: =SUM(D33:I33) -> 0
